Workbook

Sheet Index
A1: GDX index
A6: Type | B6: Name | C6: Location | D6: Row | E6: Column
D7: rdim | E7: cdim
A8: dset | B8: mac | C8: sets!a7 | D8: 1
A9: dset | B9: sac | C9: sets!b7 | D9: 1
A10: dset | B10: ac | C10: sets!c7 | D10: 1
A11: dset | B11: a | C11: sets!d7 | D11: 1
A12: dset | B12: c | C12: sets!e7 | D12: 1
A13: dset | B13: f | C13: sets!f7 | D13: 1
A14: dset | B14: t | C14: sets!g7 | D14: 1
A15: set | B15: mapac | C15: sets!d7 | D15: 2 | F15: values=nodata
A16: set | B16: mapmac | C16: sets!j7 | D16: 2 | F16: values=nodata
A17: par | B17: msam | C17: mac!a7 | D17: 1 | E17: 1
A18: par | B18: sut | C18: sut!b7 | D18: 1 | E18: 1
A19: par | B19: use | C19: use!b7 | D19: 1 | E19: 1
A20: par | B20: supply | C20: sup!b7 | D20: 1 | E20: 1

Sheet Sets
A1: Sets
A4: Macro | B4: SUT | C4: Micro | D4: Activities | E4: Commodities | F4: Factors | G4: Taxes | J4: Macro-Micro
A5: accounts | B5: accounts | C5: accounts | J5: MAPMAC
A6: MAC | B6: SAC | C6: AC | D6: A | E6: C | F6: F | G6: T | J6: MAC | K6: AC
A7: mact | B7: prd | C7: asorg | D7: asorg | E7: csorg | F7: flab | G7: atax | J7: mact | K7: asorg
A8: mcom | B8: trd_imp | C8: amaiz | D8: amaiz | E8: cmaiz | F8: flnd | G8: ctax | J8: mact | K8: amaiz
A9: mtrc | B9: tax_prd | C9: awhea | D9: awhea | E9: cwhea | F9: fcap | G9: dtax | J9: mact | K9: awhea
A10: mlab | B10: tax_imp | C10: arice | D10: arice | E10: crice | G10: etax | J10: mact | K10: arice
A11: mlnd | B11: tax_exp | C11: aocer | D11: aocer | E11: cocer | G11: ftax | J11: mact | K11: aocer
A12: mcap | B12: tax_exm | C12: aipot | D12: aipot | E12: cipot | G12: mtax | J12: mact | K12: aipot
A13: ment | B13: tax_sal | C13: aspot | D13: aspot | E13: cspot | G13: stax | J13: mact | K13: aspot
A14: mhhd | B14: tax_vat | C14: acass | D14: acass | E14: ccass | G14: vtax | J14: mact | K14: acass
A15: mgov | B15: tax_exd | C15: aroot | D15: aroot | E15: croot | G15: xtax | J15: mact | K15: aroot
A16: matx | B16: trc_rec | C16: abean | D16: abean | E16: cbean | J16: mact | K16: abean
A17: mctx | B17: tot_sup | C17: apeas | D17: apeas | E17: cpeas | J17: mact | K17: apeas
A18: mdtx | B18: tot_dem | C18: avege | D18: avege | E18: cvege | J18: mact | K18: avege
A19: metx | B19: int | C19: abanb | D19: abanb | E19: cbanb | J19: mact | K19: abanb
A20: mftx | B20: trc_pay | C20: abanc | D20: abanc | E20: cbanc | J20: mact | K20: abanc
A21: mmtx | B21: con_prv | C21: abans | D21: abans | E21: cbans | J21: mact | K21: abans
A22: mstx | B22: con_pub | C22: afrui | D22: afrui | E22: cfrui | J22: mact | K22: afrui
A23: mvtx | B23: inv_dem | C23: agnut | D23: agnut | E23: cgnut | J23: mact | K23: agnut
A24: mxtx | B24: inv_gov | C24: asoya | D24: asoya | E24: csoya | J24: mact | K24: asoya
A25: ms-i | B25: inv_stk | C25: aoils | D25: aoils | E25: coils | J25: mact | K25: aoils
A26: mg-i | B26: trd_exp | C26: acoff | D26: acoff | E26: ccoff | J26: mact | K26: acoff
A27: mstk | C27: ateal | D27: ateal | E27: cteal | J27: mact | K27: ateal
A28: mrow | C28: atoba | D28: atoba | E28: ctoba | J28: mact | K28: atoba
A29: mtot | C29: asugr | D29: asugr | E29: csugr | J29: mact | K29: asugr
C30: apyre | D30: apyre | E30: cpyre | J30: mact | K30: apyre
C31: aocrp | D31: aocrp | E31: cocrp | J31: mact | K31: aocrp
C32: acatt | D32: acatt | E32: ccatt | J32: mact | K32: acatt
C33: asmlr | D33: asmlr | E33: csmlr | J33: mact | K33: asmlr
C34: apoul | D34: apoul | E34: cpoul | J34: mact | K34: apoul
C35: aoliv | D35: aoliv | E35: coliv | J35: mact | K35: aoliv
C36: amilk | D36: amilk | E36: cmilk | J36: mact | K36: amilk
C37: aeggs | D37: aeggs | E37: ceggs | J37: mact | K37: aeggs
C38: ahony | D38: ahony | E38: chony | J38: mact | K38: ahony
C39: ahunt | D39: ahunt | E39: chunt | J39: mact | K39: ahunt
C40: afuel | D40: afuel | E40: cfuel | J40: mact | K40: afuel
C41: achar | D41: achar | E41: cchar | J41: mact | K41: achar
... C110: atrdc | D110: atrdc | E110: ctrdc | J110: mact | K110: atrdc
C111: csorg | J111: mcom | K111: csorg
C112: cmaiz | J112: mcom | K112: cmaiz
C113: cwhea | J113: mcom | K113: cwhea
C114: crice | J114: mcom | K114: crice
C115: cocer | J115: mcom | K115: cocer
C116: cipot | J116: mcom | K116: cipot
C117: cspot | J117: mcom | K117: cspot
C118: ccass | J118: mcom | K118: ccass
C119: croot | J119: mcom | K119: croot
C120: cbean | J120: mcom | K120: cbean
C121: cpeas | J121: mcom | K121: cpeas
C122: cvege | J122: mcom | K122: cvege
... C235: total | J235: mtot | K235: total

Sheet Notes
A1: =CONCATENATE(B5," ",C4," SAM") -> 2024 Rwanda SAM
A2: Use with 1construct.gms and 2balance.gms
A4: Country | B4: RWA | C4: Rwanda
A5: Year | B5: 2024
A6: Units | B6: Billions of Rwanda Francs
A7: Citation
A9: Activities and commodities (N86) | E9: Other accounts
A10: ="a"&MID(B10,2,4) -> asorg | B10: csorg | C10: Sorghum (A111) | E10: trc | F10: Transaction costs
A11: ="a"&MID(B11,2,4) -> amaiz | B11: cmaiz | C11: Maize (A112) | E11: flab | F11: Labor
A12: ="a"&MID(B12,2,4) -> awhea | B12: cwhea | C12: Wheat (A113) | E12: flnd | F12: Land
A13: ="a"&MID(B13,2,4) -> arice | B13: crice | C13: Paddy & husked rice (A116) | E13: fcap | F13: Capital
A14: ="a"&MID(B14,2,4) -> aocer | B14: cocer | C14: Other cereals (A119) | E14: ent | F14: Enterprises
A15: ="a"&MID(B15,2,4) -> aipot | B15: cipot | C15: Irish potatoes (A121) | E15: hhd | F15: Households
A16: ="a"&MID(B16,2,4) -> aspot | B16: cspot | C16: Sweet potatoes (A122) | E16: gov | F16: Government
A17: ="a"&MID(B17,2,4) -> acass | B17: ccass | C17: Cassava (A123) | E17: atax | F17: Taxes - activity (production)
A18: ="a"&MID(B18,2,4) -> aroot | B18: croot | C18: Other roots & tubers (A129) | E18: ctax | F18: Taxes - customs duties (imports)
A19: ="a"&MID(B19,2,4) -> abean | B19: cbean | C19: Dried beans (A131) | E19: dtax | F19: Taxes - direct (corporate, private)
A20: ="a"&MID(B20,2,4) -> apeas | B20: cpeas | C20: Peas & other legumes (A132) | E20: etax | F20: Taxes - exports
A21: ="a"&MID(B21,2,4) -> avege | B21: cvege | C21: Other vegetables (A139) | E21: ftax | F21: Taxes - factors (royalities)
... A29: ="a"&MID(B29,2,4) -> acoff | B29: ccoff | C29: Coffee, not roasted, not decaffeinated (A210) | E29: total | F29: Total
A30: ="a"&MID(B30,2,4) -> ateal | B30: cteal | C30: Tea (unprocessed green leaf) (A220)
A31: ="a"&MID(B31,2,4) -> atoba | B31: ctoba | C31: Tobacco, raw (A291)
A32: ="a"&MID(B32,2,4) -> asugr | B32: csugr | C32: Sugar cane (A292)
A33: ="a"&MID(B33,2,4) -> apyre | B33: cpyre | C33: Pyrethrum (A293)
A34: ="a"&MID(B34,2,4) -> aocrp | B34: cocrp | C34: Agricultural products n.e.c. (A299)
A35: ="a"&MID(B35,2,4) -> acatt | B35: ccatt | C35: Bovine cattle, live (A311)
A36: ="a"&MID(B36,2,4) -> asmlr | B36: csmlr | C36: Sheep, goats, pigs,live (A312)
A37: ="a"&MID(B37,2,4) -> apoul | B37: cpoul | C37: Poultry, live (A313)
A38: ="a"&MID(B38,2,4) -> aoliv | B38: coliv | C38: Other live animals (A319)
A39: ="a"&MID(B39,2,4) -> amilk | B39: cmilk | C39: Raw milk (A321)
A40: ="a"&MID(B40,2,4) -> aeggs | B40: ceggs | C40: Eggs (A322)
A41: ="a"&MID(B41,2,4) -> ahony | B41: chony | C41: Natural honey (A323)
... A113: ="a"&MID(B113,2,4) -> atrdc | B113: ctrdc | C113: Travel debits & credits (V00)

Sheet MAC
A1: Macro SAM
A2: Final values exported to GAMS
B7: mact | C7: mcom | D7: mtrc | E7: mlab | F7: mlnd | G7: mcap | H7: ment | I7: mhhd | J7: mgov | K7: matx | L7: mctx | M7: mdtx | N7: metx | O7: mftx | P7: mmtx | Q7: mstx | R7: mvtx | S7: mxtx | T7: ms-i | U7: mg-i | V7: mstk | W7: mrow | X7: mtot
A8: mact | B8: =wMAC!C5 -> 0 | C8: =wMAC!D5 -> #DIV/0! | D8: =wMAC!E5 -> 0 | E8: =wMAC!F5 -> 0 | F8: =wMAC!G5 -> 0 | G8: =wMAC!H5 -> 0 | H8: =wMAC!I5 -> 0 | I8: =wMAC!J5 -> 0 | ... X8: =wMAC!Y5 -> #DIV/0!
A9: mcom | B9: =wMAC!C6 -> #DIV/0! | C9: =wMAC!D6 -> 0 | D9: =wMAC!E6 -> #DIV/0! | E9: =wMAC!F6 -> 0 | F9: =wMAC!G6 -> 0 | G9: =wMAC!H6 -> 0 | H9: =wMAC!I6 -> 0 | I9: =wMAC!J6 -> #DIV/0! | ... X9: =wMAC!Y6 -> #DIV/0!
A10: mtrc | B10: =wMAC!C7 -> 0 | C10: =wMAC!D7 -> #DIV/0! | D10: =wMAC!E7 -> 0 | E10: =wMAC!F7 -> 0 | F10: =wMAC!G7 -> 0 | G10: =wMAC!H7 -> 0 | H10: =wMAC!I7 -> 0 | I10: =wMAC!J7 -> 0 | ... X10: =wMAC!Y7 -> #DIV/0!
A11: mlab | B11: =wMAC!C8 -> #DIV/0! | C11: =wMAC!D8 -> 0 | D11: =wMAC!E8 -> 0 | E11: =wMAC!F8 -> 0 | F11: =wMAC!G8 -> 0 | G11: =wMAC!H8 -> 0 | H11: =wMAC!I8 -> 0 | I11: =wMAC!J8 -> 0 | ... X11: =wMAC!Y8 -> #DIV/0!
A12: mlnd | B12: =wMAC!C9 -> #DIV/0! | C12: =wMAC!D9 -> 0 | D12: =wMAC!E9 -> 0 | E12: =wMAC!F9 -> 0 | F12: =wMAC!G9 -> 0 | G12: =wMAC!H9 -> 0 | H12: =wMAC!I9 -> 0 | I12: =wMAC!J9 -> 0 | ... X12: =wMAC!Y9 -> #DIV/0!
A13: mcap | B13: =wMAC!C10 -> #DIV/0! | C13: =wMAC!D10 -> 0 | D13: =wMAC!E10 -> 0 | E13: =wMAC!F10 -> 0 | F13: =wMAC!G10 -> 0 | G13: =wMAC!H10 -> 0 | H13: =wMAC!I10 -> 0 | I13: =wMAC!J10 -> 0 | ... X13: =wMAC!Y10 -> #DIV/0!
A14: ment | B14: =wMAC!C11 -> 0 | C14: =wMAC!D11 -> 0 | D14: =wMAC!E11 -> 0 | E14: =wMAC!F11 -> 0 | F14: =wMAC!G11 -> 0 | G14: =wMAC!H11 -> #DIV/0! | H14: =wMAC!I11 -> 0 | I14: =wMAC!J11 -> 0 | ... X14: =wMAC!Y11 -> #DIV/0!
A15: mhhd | B15: =wMAC!C12 -> 0 | C15: =wMAC!D12 -> 0 | D15: =wMAC!E12 -> 0 | E15: =wMAC!F12 -> #DIV/0! | F15: =wMAC!G12 -> #DIV/0! | G15: =wMAC!H12 -> 0 | H15: =wMAC!I12 -> #DIV/0! | I15: =wMAC!J12 -> 0 | ... X15: =wMAC!Y12 -> #DIV/0!
A16: mgov | B16: =wMAC!C13 -> 0 | C16: =wMAC!D13 -> 0 | D16: =wMAC!E13 -> 0 | E16: =wMAC!F13 -> 0 | F16: =wMAC!G13 -> 0 | G16: =wMAC!H13 -> 0 | H16: =wMAC!I13 -> 18.658538 | I16: =wMAC!J13 -> 432.46991 | ... X16: =wMAC!Y13 -> #DIV/0!
A17: matx | B17: =wMAC!C14 -> #DIV/0! | C17: =wMAC!D14 -> 0 | D17: =wMAC!E14 -> 0 | E17: =wMAC!F14 -> 0 | F17: =wMAC!G14 -> 0 | G17: =wMAC!H14 -> 0 | H17: =wMAC!I14 -> 0 | I17: =wMAC!J14 -> 0 | ... X17: =wMAC!Y14 -> #DIV/0!
A18: mctx | B18: =wMAC!C15 -> 0 | C18: =wMAC!D15 -> #DIV/0! | D18: =wMAC!E15 -> 0 | E18: =wMAC!F15 -> 0 | F18: =wMAC!G15 -> 0 | G18: =wMAC!H15 -> 0 | H18: =wMAC!I15 -> 0 | I18: =wMAC!J15 -> 0 | ... X18: =wMAC!Y15 -> #DIV/0!
A19: mdtx | B19: =wMAC!C16 -> 0 | C19: =wMAC!D16 -> 0 | D19: =wMAC!E16 -> 0 | E19: =wMAC!F16 -> 0 | F19: =wMAC!G16 -> 0 | G19: =wMAC!H16 -> 0 | H19: =wMAC!I16 -> 432.89809 | I19: =wMAC!J16 -> 835.09604 | ... X19: =wMAC!Y16 -> 1267.9941
... A30: mtot | B30: =wMAC!C27 -> #DIV/0! | C30: =wMAC!D27 -> #DIV/0! | D30: =wMAC!E27 -> #DIV/0! | E30: =wMAC!F27 -> #DIV/0! | F30: =wMAC!G27 -> #DIV/0! | G30: =wMAC!H27 -> #DIV/0! | H30: =wMAC!I27 -> #DIV/0! | I30: =wMAC!J27 -> #DIV/0! | ... X30: =wMAC!Y27 -> 0

Sheet SUT
A1: Supply-Use Table
A2: Final values exported to GAMS
C4: Gross | D4: Imports | E4: Tax on | F4: Taxes on products | L4: Trans. | M4: Totals | O4: Inter- | P4: Trans. | Q4: Consumption | S4: GCF | V4: Exports | Y4: Differences
C5: output | E5: producers | F5: Customs duties | G5: Exports | H5: Import excise duties | I5: Subsidies (products) | J5: VAT | K5: Excise & Others | L5: costs | M5: Supply | N5: Demand | O5: mediates | P5: costs | Q5: Private | R5: Public | S5: Private | T5: Public | U5: Stocks | Y5: sup-dem | Z5: % sup
B6: Totals | C6: =SUM(C8:C111) -> #DIV/0! | D6: =SUM(D8:D111) -> 0 | E6: =SUM(E8:E111) -> #DIV/0! | F6: =SUM(F8:F111) -> 0 | G6: =SUM(G8:G111) -> 0 | H6: =SUM(H8:H111) -> 0 | I6: =SUM(I8:I111) -> #DIV/0! | K6: =SUM(K8:K111) -> #DIV/0! | L6: =SUM(L8:L111) -> #DIV/0! | M6: =SUM(M8:M111) -> #DIV/0! | N6: =SUM(N8:N111) -> #DIV/0! | O6: =SUM(O8:O111) -> #DIV/0! | P6: =SUM(P8:P111) -> #DIV/0! | Q6: =SUM(Q8:Q111) -> #DIV/0! | R6: =SUM(R8:R111) -> 0 | ... V6: =SUM(V8:V111) -> 0 | Y6: =M6-N6 -> #DIV/0! | Z6: =IF(M6<>0,Y6/M6*100,0) -> #DIV/0! | AC6: Totals | AE6: Differences
C7: prd | D7: trd_imp | E7: tax_prd | F7: tax_imp | G7: tax_exp | H7: tax_exm | I7: tax_sal | J7: tax_vat | K7: tax_exd | L7: trc_rec | M7: tot_sup | N7: tot_dem | O7: int | P7: trc_pay | Q7: con_prv | R7: con_pub | S7: inv_dem | T7: inv_gov | U7: inv_stk | V7: trd_exp | AC7: Supply | AD7: Demand | AE7: sup-dem | AF7: % sup
A8: Sorghum (A111) | B8: csorg | C8: {=TRANSPOSE(SUP!C4:DB4)} -> #DIV/0! | D8: =wTRD!I8 -> 0 | E8: =wTAX!G8 -> #DIV/0! | F8: =wTAX!K8 -> 0 | G8: =wTAX!O8 -> 0 | H8: =wTAX!S8 -> 0 | I8: =wTAX!W8 -> #DIV/0! | J8: =wTAX!AA8 -> #DIV/0! | K8: =wTAX!AE8 -> #DIV/0! | L8: =wTRC!G8 -> #DIV/0! | M8: =SUM(C8:L8) -> #DIV/0! | N8: =SUM(O8:V8) -> #DIV/0! | O8: =SUM(USE!C8:DB8) -> #DIV/0! | P8: =wTRC!K8 -> #DIV/0! | Q8: =wABS!G7 -> #DIV/0! | R8: =wABS!K7 -> 0 | S8: =wABS!O7 -> 0 | T8: =wABS!S7 -> 0 | U8: =wABS!W7 -> 0 | V8: =wTRD!O8 -> 0 | Y8: =M8-N8 -> #DIV/0! | Z8: =IF(M8<>0,Y8/M8*100,0) -> #DIV/0! | AB8: Agriculture | AC8: =SUM(AC9:AC20) -> #DIV/0! | AD8: =SUM(AD9:AD20) -> #DIV/0! | AE8: =AC8-AD8 -> #DIV/0! | AF8: =IF(AC8<>0,AE8/AC8*100,0) -> #DIV/0!
A9: Maize (A112) | B9: cmaiz | C9: #DIV/0! | D9: =wTRD!I9 -> 0 | E9: =wTAX!G9 -> #DIV/0! | F9: =wTAX!K9 -> 0 | G9: =wTAX!O9 -> 0 | H9: =wTAX!S9 -> 0 | I9: =wTAX!W9 -> #DIV/0! | J9: =wTAX!AA9 -> #DIV/0! | K9: =wTAX!AE9 -> #DIV/0! | L9: =wTRC!G9 -> #DIV/0! | M9: =SUM(C9:L9) -> #DIV/0! | N9: =SUM(O9:V9) -> #DIV/0! | O9: =SUM(USE!C9:DB9) -> #DIV/0! | P9: =wTRC!K9 -> #DIV/0! | Q9: =wABS!G8 -> #DIV/0! | R9: =wABS!K8 -> 0 | S9: =wABS!O8 -> 0 | T9: =wABS!S8 -> 0 | U9: =wABS!W8 -> 0 | V9: =wTRD!O9 -> 0 | Y9: =M9-N9 -> #DIV/0! | Z9: =IF(M9<>0,Y9/M9*100,0) -> #DIV/0! | AB9: Cereals | AC9: =SUM(M8:M12) -> #DIV/0! | AD9: =SUM(N8:N12) -> #DIV/0! | AE9: =AC9-AD9 -> #DIV/0! | AF9: =IF(AC9<>0,AE9/AC9*100,0) -> #DIV/0!
A10: Wheat (A113) | B10: cwhea | C10: #DIV/0! | D10: =wTRD!I10 -> 0 | E10: =wTAX!G10 -> #DIV/0! | F10: =wTAX!K10 -> 0 | G10: =wTAX!O10 -> 0 | H10: =wTAX!S10 -> 0 | I10: =wTAX!W10 -> #DIV/0! | J10: =wTAX!AA10 -> #DIV/0! | K10: =wTAX!AE10 -> #DIV/0! | L10: =wTRC!G10 -> #DIV/0! | M10: =SUM(C10:L10) -> #DIV/0! | N10: =SUM(O10:V10) -> #DIV/0! | O10: =SUM(USE!C10:DB10) -> #DIV/0! | P10: =wTRC!K10 -> #DIV/0! | Q10: =wABS!G9 -> #DIV/0! | R10: =wABS!K9 -> 0 | S10: =wABS!O9 -> 0 | T10: =wABS!S9 -> 0 | U10: =wABS!W9 -> 0 | V10: =wTRD!O10 -> 0 | Y10: =M10-N10 -> #DIV/0! | Z10: =IF(M10<>0,Y10/M10*100,0) -> #DIV/0! | AB10: Roots | AC10: =SUM(M13:M16) -> #DIV/0! | AD10: =SUM(N13:N16) -> #DIV/0! | AE10: =AC10-AD10 -> #DIV/0! | AF10: =IF(AC10<>0,AE10/AC10*100,0) -> #DIV/0!
A11: Paddy & husked rice (A116) | B11: crice | C11: #DIV/0! | D11: =wTRD!I11 -> 0 | E11: =wTAX!G11 -> #DIV/0! | F11: =wTAX!K11 -> 0 | G11: =wTAX!O11 -> 0 | H11: =wTAX!S11 -> 0 | I11: =wTAX!W11 -> #DIV/0! | J11: =wTAX!AA11 -> #DIV/0! | K11: =wTAX!AE11 -> #DIV/0! | L11: =wTRC!G11 -> #DIV/0! | M11: =SUM(C11:L11) -> #DIV/0! | N11: =SUM(O11:V11) -> #DIV/0! | O11: =SUM(USE!C11:DB11) -> #DIV/0! | P11: =wTRC!K11 -> #DIV/0! | Q11: =wABS!G10 -> #DIV/0! | R11: =wABS!K10 -> 0 | S11: =wABS!O10 -> 0 | T11: =wABS!S10 -> 0 | U11: =wABS!W10 -> 0 | V11: =wTRD!O11 -> 0 | Y11: =M11-N11 -> #DIV/0! | Z11: =IF(M11<>0,Y11/M11*100,0) -> #DIV/0! | AB11: Vegetables | AC11: =SUM(M17:M19) -> #DIV/0! | AD11: =SUM(N17:N19) -> #DIV/0! | AE11: =AC11-AD11 -> #DIV/0! | AF11: =IF(AC11<>0,AE11/AC11*100,0) -> #DIV/0!
A12: Other cereals (A119) | B12: cocer | C12: #DIV/0! | D12: =wTRD!I12 -> 0 | E12: =wTAX!G12 -> #DIV/0! | F12: =wTAX!K12 -> 0 | G12: =wTAX!O12 -> 0 | H12: =wTAX!S12 -> 0 | I12: =wTAX!W12 -> #DIV/0! | J12: =wTAX!AA12 -> #DIV/0! | K12: =wTAX!AE12 -> #DIV/0! | L12: =wTRC!G12 -> #DIV/0! | M12: =SUM(C12:L12) -> #DIV/0! | N12: =SUM(O12:V12) -> #DIV/0! | O12: =SUM(USE!C12:DB12) -> #DIV/0! | P12: =wTRC!K12 -> #DIV/0! | Q12: =wABS!G11 -> #DIV/0! | R12: =wABS!K11 -> 0 | S12: =wABS!O11 -> 0 | T12: =wABS!S11 -> 0 | U12: =wABS!W11 -> 0 | V12: =wTRD!O12 -> 0 | Y12: =M12-N12 -> #DIV/0! | Z12: =IF(M12<>0,Y12/M12*100,0) -> #DIV/0! | AB12: Bananas and fruit | AC12: =SUM(M20:M23) -> #DIV/0! | AD12: =SUM(N20:N23) -> #DIV/0! | AE12: =AC12-AD12 -> #DIV/0! | AF12: =IF(AC12<>0,AE12/AC12*100,0) -> #DIV/0!
A13: Irish potatoes (A121) | B13: cipot | C13: #DIV/0! | D13: =wTRD!I13 -> 0 | E13: =wTAX!G13 -> #DIV/0! | F13: =wTAX!K13 -> 0 | G13: =wTAX!O13 -> 0 | H13: =wTAX!S13 -> 0 | I13: =wTAX!W13 -> #DIV/0! | J13: =wTAX!AA13 -> #DIV/0! | K13: =wTAX!AE13 -> #DIV/0! | L13: =wTRC!G13 -> #DIV/0! | M13: =SUM(C13:L13) -> #DIV/0! | N13: =SUM(O13:V13) -> #DIV/0! | O13: =SUM(USE!C13:DB13) -> #DIV/0! | P13: =wTRC!K13 -> #DIV/0! | Q13: =wABS!G12 -> #DIV/0! | R13: =wABS!K12 -> 0 | S13: =wABS!O12 -> 0 | T13: =wABS!S12 -> 0 | U13: =wABS!W12 -> 0 | V13: =wTRD!O13 -> 0 | Y13: =M13-N13 -> #DIV/0! | Z13: =IF(M13<>0,Y13/M13*100,0) -> #DIV/0! | AB13: Oil seeds n.e.c. and oleaginous fruit | AC13: =SUM(M24:M26) -> #DIV/0! | AD13: =SUM(N24:N26) -> #DIV/0! | AE13: =AC13-AD13 -> #DIV/0! | AF13: =IF(AC13<>0,AE13/AC13*100,0) -> #DIV/0!
A14: Sweet potatoes (A122) | B14: cspot | C14: #DIV/0! | D14: =wTRD!I14 -> 0 | E14: =wTAX!G14 -> #DIV/0! | F14: =wTAX!K14 -> 0 | G14: =wTAX!O14 -> 0 | H14: =wTAX!S14 -> 0 | I14: =wTAX!W14 -> #DIV/0! | J14: =wTAX!AA14 -> #DIV/0! | K14: =wTAX!AE14 -> #DIV/0! | L14: =wTRC!G14 -> #DIV/0! | M14: =SUM(C14:L14) -> #DIV/0! | N14: =SUM(O14:V14) -> #DIV/0! | O14: =SUM(USE!C14:DB14) -> #DIV/0! | P14: =wTRC!K14 -> #DIV/0! | Q14: =wABS!G13 -> #DIV/0! | R14: =wABS!K13 -> 0 | S14: =wABS!O13 -> 0 | T14: =wABS!S13 -> 0 | U14: =wABS!W13 -> 0 | V14: =wTRD!O14 -> 0 | Y14: =M14-N14 -> #DIV/0! | Z14: =IF(M14<>0,Y14/M14*100,0) -> #DIV/0! | AB14: Coffee | AC14: =M27 -> #DIV/0! | AD14: =N27 -> #DIV/0! | AE14: =AC14-AD14 -> #DIV/0! | AF14: =IF(AC14<>0,AE14/AC14*100,0) -> #DIV/0!
A15: Cassava (A123) | B15: ccass | C15: #DIV/0! | D15: =wTRD!I15 -> 0 | E15: =wTAX!G15 -> #DIV/0! | F15: =wTAX!K15 -> 0 | G15: =wTAX!O15 -> 0 | H15: =wTAX!S15 -> 0 | I15: =wTAX!W15 -> #DIV/0! | J15: =wTAX!AA15 -> #DIV/0! | K15: =wTAX!AE15 -> #DIV/0! | L15: =wTRC!G15 -> #DIV/0! | M15: =SUM(C15:L15) -> #DIV/0! | N15: =SUM(O15:V15) -> #DIV/0! | O15: =SUM(USE!C15:DB15) -> #DIV/0! | P15: =wTRC!K15 -> #DIV/0! | Q15: =wABS!G14 -> #DIV/0! | R15: =wABS!K14 -> 0 | S15: =wABS!O14 -> 0 | T15: =wABS!S14 -> 0 | U15: =wABS!W14 -> 0 | V15: =wTRD!O15 -> 0 | Y15: =M15-N15 -> #DIV/0! | Z15: =IF(M15<>0,Y15/M15*100,0) -> #DIV/0! | AB15: Tea (unprocessed green leaf) | AC15: =M28 -> #DIV/0! | AD15: =N28 -> #DIV/0! | AE15: =AC15-AD15 -> #DIV/0! | AF15: =IF(AC15<>0,AE15/AC15*100,0) -> #DIV/0!
A16: Other roots & tubers (A129) | B16: croot | C16: #DIV/0! | D16: =wTRD!I16 -> 0 | E16: =wTAX!G16 -> #DIV/0! | F16: =wTAX!K16 -> 0 | G16: =wTAX!O16 -> 0 | H16: =wTAX!S16 -> 0 | I16: =wTAX!W16 -> #DIV/0! | J16: =wTAX!AA16 -> #DIV/0! | K16: =wTAX!AE16 -> #DIV/0! | L16: =wTRC!G16 -> #DIV/0! | M16: =SUM(C16:L16) -> #DIV/0! | N16: =SUM(O16:V16) -> #DIV/0! | O16: =SUM(USE!C16:DB16) -> #DIV/0! | P16: =wTRC!K16 -> #DIV/0! | Q16: =wABS!G15 -> #DIV/0! | R16: =wABS!K15 -> 0 | S16: =wABS!O15 -> 0 | T16: =wABS!S15 -> 0 | U16: =wABS!W15 -> 0 | V16: =wTRD!O16 -> 0 | Y16: =M16-N16 -> #DIV/0! | Z16: =IF(M16<>0,Y16/M16*100,0) -> #DIV/0! | AB16: Other agricultural products | AC16: =SUM(M29:M32) -> #DIV/0! | AD16: =SUM(N29:N32) -> #DIV/0! | AE16: =AC16-AD16 -> #DIV/0! | AF16: =IF(AC16<>0,AE16/AC16*100,0) -> #DIV/0!
A17: Dried beans (A131) | B17: cbean | C17: #DIV/0! | D17: =wTRD!I17 -> 0 | E17: =wTAX!G17 -> #DIV/0! | F17: =wTAX!K17 -> 0 | G17: =wTAX!O17 -> 0 | H17: =wTAX!S17 -> 0 | I17: =wTAX!W17 -> #DIV/0! | J17: =wTAX!AA17 -> #DIV/0! | K17: =wTAX!AE17 -> #DIV/0! | L17: =wTRC!G17 -> #DIV/0! | M17: =SUM(C17:L17) -> #DIV/0! | N17: =SUM(O17:V17) -> #DIV/0! | O17: =SUM(USE!C17:DB17) -> #DIV/0! | P17: =wTRC!K17 -> #DIV/0! | Q17: =wABS!G16 -> #DIV/0! | R17: =wABS!K16 -> 0 | S17: =wABS!O16 -> 0 | T17: =wABS!S16 -> 0 | U17: =wABS!W16 -> 0 | V17: =wTRD!O17 -> 0 | Y17: =M17-N17 -> #DIV/0! | Z17: =IF(M17<>0,Y17/M17*100,0) -> #DIV/0! | AB17: Livestock | AC17: =SUM(M33:M36) -> #DIV/0! | AD17: =SUM(N33:N36) -> #DIV/0! | AE17: =AC17-AD17 -> #DIV/0! | AF17: =IF(AC17<>0,AE17/AC17*100,0) -> #DIV/0!
A18: Peas & other legumes (A132) | B18: cpeas | C18: #DIV/0! | D18: =wTRD!I18 -> 0 | E18: =wTAX!G18 -> #DIV/0! | F18: =wTAX!K18 -> 0 | G18: =wTAX!O18 -> 0 | H18: =wTAX!S18 -> 0 | I18: =wTAX!W18 -> #DIV/0! | J18: =wTAX!AA18 -> #DIV/0! | K18: =wTAX!AE18 -> #DIV/0! | L18: =wTRC!G18 -> #DIV/0! | M18: =SUM(C18:L18) -> #DIV/0! | N18: =SUM(O18:V18) -> #DIV/0! | O18: =SUM(USE!C18:DB18) -> #DIV/0! | P18: =wTRC!K18 -> #DIV/0! | Q18: =wABS!G17 -> #DIV/0! | R18: =wABS!K17 -> 0 | S18: =wABS!O17 -> 0 | T18: =wABS!S17 -> 0 | U18: =wABS!W17 -> 0 | V18: =wTRD!O18 -> 0 | Y18: =M18-N18 -> #DIV/0! | Z18: =IF(M18<>0,Y18/M18*100,0) -> #DIV/0! | AB18: Livestock and hunting products | AC18: =SUM(M37:M40) -> #DIV/0! | AD18: =SUM(N37:N40) -> #DIV/0! | AE18: =AC18-AD18 -> #DIV/0! | AF18: =IF(AC18<>0,AE18/AC18*100,0) -> #DIV/0!
A19: Other vegetables (A139) | B19: cvege | C19: #DIV/0! | D19: =wTRD!I19 -> 0 | E19: =wTAX!G19 -> #DIV/0! | F19: =wTAX!K19 -> 0 | G19: =wTAX!O19 -> 0 | H19: =wTAX!S19 -> 0 | I19: =wTAX!W19 -> #DIV/0! | J19: =wTAX!AA19 -> #DIV/0! | K19: =wTAX!AE19 -> #DIV/0! | L19: =wTRC!G19 -> #DIV/0! | M19: =SUM(C19:L19) -> #DIV/0! | N19: =SUM(O19:V19) -> #DIV/0! | O19: =SUM(USE!C19:DB19) -> #DIV/0! | P19: =wTRC!K19 -> #DIV/0! | Q19: =wABS!G18 -> #DIV/0! | R19: =wABS!K18 -> 0 | S19: =wABS!O18 -> 0 | T19: =wABS!S18 -> 0 | U19: =wABS!W18 -> 0 | V19: =wTRD!O19 -> 0 | Y19: =M19-N19 -> #DIV/0! | Z19: =IF(M19<>0,Y19/M19*100,0) -> #DIV/0! | AB19: Forestry products | AC19: =SUM(M41:M43) -> #DIV/0! | AD19: =SUM(N41:N43) -> #DIV/0! | AE19: =AC19-AD19 -> #DIV/0! | AF19: =IF(AC19<>0,AE19/AC19*100,0) -> #DIV/0!
A20: Bananas for beer (A141) | B20: cbanb | C20: #DIV/0! | D20: =wTRD!I20 -> 0 | E20: =wTAX!G20 -> #DIV/0! | F20: =wTAX!K20 -> 0 | G20: =wTAX!O20 -> 0 | H20: =wTAX!S20 -> 0 | I20: =wTAX!W20 -> #DIV/0! | J20: =wTAX!AA20 -> #DIV/0! | K20: =wTAX!AE20 -> #DIV/0! | L20: =wTRC!G20 -> #DIV/0! | M20: =SUM(C20:L20) -> #DIV/0! | N20: =SUM(O20:V20) -> #DIV/0! | O20: =SUM(USE!C20:DB20) -> #DIV/0! | P20: =wTRC!K20 -> #DIV/0! | Q20: =wABS!G19 -> #DIV/0! | R20: =wABS!K19 -> 0 | S20: =wABS!O19 -> 0 | T20: =wABS!S19 -> 0 | U20: =wABS!W19 -> 0 | V20: =wTRD!O20 -> 0 | Y20: =M20-N20 -> #DIV/0! | Z20: =IF(M20<>0,Y20/M20*100,0) -> #DIV/0! | AB20: Fishery products | AC20: =SUM(M44) -> #DIV/0! | AD20: =SUM(N44) -> #DIV/0! | AE20: =AC20-AD20 -> #DIV/0! | AF20: =IF(AC20<>0,AE20/AC20*100,0) -> #DIV/0!
A21: Bananas for cooking (A142) | B21: cbanc | C21: #DIV/0! | D21: =wTRD!I21 -> 0 | E21: =wTAX!G21 -> #DIV/0! | F21: =wTAX!K21 -> 0 | G21: =wTAX!O21 -> 0 | H21: =wTAX!S21 -> 0 | I21: =wTAX!W21 -> #DIV/0! | J21: =wTAX!AA21 -> #DIV/0! | K21: =wTAX!AE21 -> #DIV/0! | L21: =wTRC!G21 -> #DIV/0! | M21: =SUM(C21:L21) -> #DIV/0! | N21: =SUM(O21:V21) -> #DIV/0! | O21: =SUM(USE!C21:DB21) -> #DIV/0! | P21: =wTRC!K21 -> #DIV/0! | Q21: =wABS!G20 -> #DIV/0! | R21: =wABS!K20 -> 0 | S21: =wABS!O20 -> 0 | T21: =wABS!S20 -> 0 | U21: =wABS!W20 -> 0 | V21: =wTRD!O21 -> 0 | Y21: =M21-N21 -> #DIV/0! | Z21: =IF(M21<>0,Y21/M21*100,0) -> #DIV/0!
A22: Bananas (sweet) (A143) | B22: cbans | C22: #DIV/0! | D22: =wTRD!I22 -> 0 | E22: =wTAX!G22 -> #DIV/0! | F22: =wTAX!K22 -> 0 | G22: =wTAX!O22 -> 0 | H22: =wTAX!S22 -> 0 | I22: =wTAX!W22 -> #DIV/0! | J22: =wTAX!AA22 -> #DIV/0! | K22: =wTAX!AE22 -> #DIV/0! | L22: =wTRC!G22 -> #DIV/0! | M22: =SUM(C22:L22) -> #DIV/0! | N22: =SUM(O22:V22) -> #DIV/0! | O22: =SUM(USE!C22:DB22) -> #DIV/0! | P22: =wTRC!K22 -> #DIV/0! | Q22: =wABS!G21 -> #DIV/0! | R22: =wABS!K21 -> 0 | S22: =wABS!O21 -> 0 | T22: =wABS!S21 -> 0 | U22: =wABS!W21 -> 0 | V22: =wTRD!O22 -> 0 | Y22: =M22-N22 -> #DIV/0! | Z22: =IF(M22<>0,Y22/M22*100,0) -> #DIV/0!
A23: Other fruit & nuts (A149) | B23: cfrui | C23: #DIV/0! | D23: =wTRD!I23 -> 0 | E23: =wTAX!G23 -> #DIV/0! | F23: =wTAX!K23 -> 0 | G23: =wTAX!O23 -> 0 | H23: =wTAX!S23 -> 0 | I23: =wTAX!W23 -> #DIV/0! | J23: =wTAX!AA23 -> #DIV/0! | K23: =wTAX!AE23 -> #DIV/0! | L23: =wTRC!G23 -> #DIV/0! | M23: =SUM(C23:L23) -> #DIV/0! | N23: =SUM(O23:V23) -> #DIV/0! | O23: =SUM(USE!C23:DB23) -> #DIV/0! | P23: =wTRC!K23 -> #DIV/0! | Q23: =wABS!G22 -> #DIV/0! | R23: =wABS!K22 -> 0 | S23: =wABS!O22 -> 0 | T23: =wABS!S22 -> 0 | U23: =wABS!W22 -> 0 | V23: =wTRD!O23 -> 0 | Y23: =M23-N23 -> #DIV/0! | Z23: =IF(M23<>0,Y23/M23*100,0) -> #DIV/0!
A24: Ground nuts (A151) | B24: cgnut | C24: #DIV/0! | D24: =wTRD!I24 -> 0 | E24: =wTAX!G24 -> #DIV/0! | F24: =wTAX!K24 -> 0 | G24: =wTAX!O24 -> 0 | H24: =wTAX!S24 -> 0 | I24: =wTAX!W24 -> #DIV/0! | J24: =wTAX!AA24 -> #DIV/0! | K24: =wTAX!AE24 -> #DIV/0! | L24: =wTRC!G24 -> #DIV/0! | M24: =SUM(C24:L24) -> #DIV/0! | N24: =SUM(O24:V24) -> #DIV/0! | O24: =SUM(USE!C24:DB24) -> #DIV/0! | P24: =wTRC!K24 -> #DIV/0! | Q24: =wABS!G23 -> #DIV/0! | R24: =wABS!K23 -> 0 | S24: =wABS!O23 -> 0 | T24: =wABS!S23 -> 0 | U24: =wABS!W23 -> 0 | V24: =wTRD!O24 -> 0 | Y24: =M24-N24 -> #DIV/0! | Z24: =IF(M24<>0,Y24/M24*100,0) -> #DIV/0!
A25: Soya (A152) | B25: csoya | C25: #DIV/0! | D25: =wTRD!I25 -> 0 | E25: =wTAX!G25 -> #DIV/0! | F25: =wTAX!K25 -> 0 | G25: =wTAX!O25 -> 0 | H25: =wTAX!S25 -> 0 | I25: =wTAX!W25 -> #DIV/0! | J25: =wTAX!AA25 -> #DIV/0! | K25: =wTAX!AE25 -> #DIV/0! | L25: =wTRC!G25 -> #DIV/0! | M25: =SUM(C25:L25) -> #DIV/0! | N25: =SUM(O25:V25) -> #DIV/0! | O25: =SUM(USE!C25:DB25) -> #DIV/0! | P25: =wTRC!K25 -> #DIV/0! | Q25: =wABS!G24 -> #DIV/0! | R25: =wABS!K24 -> 0 | S25: =wABS!O24 -> 0 | T25: =wABS!S24 -> 0 | U25: =wABS!W24 -> 0 | V25: =wTRD!O25 -> 0 | Y25: =M25-N25 -> #DIV/0! | Z25: =IF(M25<>0,Y25/M25*100,0) -> #DIV/0!
A26: Other oil seeds (A159) | B26: coils | C26: #DIV/0! | D26: =wTRD!I26 -> 0 | E26: =wTAX!G26 -> #DIV/0! | F26: =wTAX!K26 -> 0 | G26: =wTAX!O26 -> 0 | H26: =wTAX!S26 -> 0 | I26: =wTAX!W26 -> #DIV/0! | J26: =wTAX!AA26 -> #DIV/0! | K26: =wTAX!AE26 -> #DIV/0! | L26: =wTRC!G26 -> #DIV/0! | M26: =SUM(C26:L26) -> #DIV/0! | N26: =SUM(O26:V26) -> #DIV/0! | O26: =SUM(USE!C26:DB26) -> #DIV/0! | P26: =wTRC!K26 -> #DIV/0! | Q26: =wABS!G25 -> #DIV/0! | R26: =wABS!K25 -> 0 | S26: =wABS!O25 -> 0 | T26: =wABS!S25 -> 0 | U26: =wABS!W25 -> 0 | V26: =wTRD!O26 -> 0 | Y26: =M26-N26 -> #DIV/0! | Z26: =IF(M26<>0,Y26/M26*100,0) -> #DIV/0!
A27: Coffee, not roasted, not decaffeinated (A210) | B27: ccoff | C27: #DIV/0! | D27: =wTRD!I27 -> 0 | E27: =wTAX!G27 -> #DIV/0! | F27: =wTAX!K27 -> 0 | G27: =wTAX!O27 -> 0 | H27: =wTAX!S27 -> 0 | I27: =wTAX!W27 -> #DIV/0! | J27: =wTAX!AA27 -> #DIV/0! | K27: =wTAX!AE27 -> #DIV/0! | L27: =wTRC!G27 -> #DIV/0! | M27: =SUM(C27:L27) -> #DIV/0! | N27: =SUM(O27:V27) -> #DIV/0! | O27: =SUM(USE!C27:DB27) -> #DIV/0! | P27: =wTRC!K27 -> #DIV/0! | Q27: =wABS!G26 -> #DIV/0! | R27: =wABS!K26 -> 0 | S27: =wABS!O26 -> 0 | T27: =wABS!S26 -> 0 | U27: =wABS!W26 -> 0 | V27: =wTRD!O27 -> 0 | Y27: =M27-N27 -> #DIV/0! | Z27: =IF(M27<>0,Y27/M27*100,0) -> #DIV/0!
A28: Tea (unprocessed green leaf) (A220) | B28: cteal | C28: #DIV/0! | D28: =wTRD!I28 -> 0 | E28: =wTAX!G28 -> #DIV/0! | F28: =wTAX!K28 -> 0 | G28: =wTAX!O28 -> 0 | H28: =wTAX!S28 -> 0 | I28: =wTAX!W28 -> #DIV/0! | J28: =wTAX!AA28 -> #DIV/0! | K28: =wTAX!AE28 -> #DIV/0! | L28: =wTRC!G28 -> #DIV/0! | M28: =SUM(C28:L28) -> #DIV/0! | N28: =SUM(O28:V28) -> #DIV/0! | O28: =SUM(USE!C28:DB28) -> #DIV/0! | P28: =wTRC!K28 -> #DIV/0! | Q28: =wABS!G27 -> #DIV/0! | R28: =wABS!K27 -> 0 | S28: =wABS!O27 -> 0 | T28: =wABS!S27 -> 0 | U28: =wABS!W27 -> 0 | V28: =wTRD!O28 -> 0 | Y28: =M28-N28 -> #DIV/0! | Z28: =IF(M28<>0,Y28/M28*100,0) -> #DIV/0!
A29: Tobacco, raw (A291) | B29: ctoba | C29: #DIV/0! | D29: =wTRD!I29 -> 0 | E29: =wTAX!G29 -> #DIV/0! | F29: =wTAX!K29 -> 0 | G29: =wTAX!O29 -> 0 | H29: =wTAX!S29 -> 0 | I29: =wTAX!W29 -> #DIV/0! | J29: =wTAX!AA29 -> #DIV/0! | K29: =wTAX!AE29 -> #DIV/0! | L29: =wTRC!G29 -> #DIV/0! | M29: =SUM(C29:L29) -> #DIV/0! | N29: =SUM(O29:V29) -> #DIV/0! | O29: =SUM(USE!C29:DB29) -> #DIV/0! | P29: =wTRC!K29 -> #DIV/0! | Q29: =wABS!G28 -> #DIV/0! | R29: =wABS!K28 -> 0 | S29: =wABS!O28 -> 0 | T29: =wABS!S28 -> 0 | U29: =wABS!W28 -> 0 | V29: =wTRD!O29 -> 0 | Y29: =M29-N29 -> #DIV/0! | Z29: =IF(M29<>0,Y29/M29*100,0) -> #DIV/0!
A30: Sugar cane (A292) | B30: csugr | C30: #DIV/0! | D30: =wTRD!I30 -> 0 | E30: =wTAX!G30 -> #DIV/0! | F30: =wTAX!K30 -> 0 | G30: =wTAX!O30 -> 0 | H30: =wTAX!S30 -> 0 | I30: =wTAX!W30 -> #DIV/0! | J30: =wTAX!AA30 -> #DIV/0! | K30: =wTAX!AE30 -> #DIV/0! | L30: =wTRC!G30 -> #DIV/0! | M30: =SUM(C30:L30) -> #DIV/0! | N30: =SUM(O30:V30) -> #DIV/0! | O30: =SUM(USE!C30:DB30) -> #DIV/0! | P30: =wTRC!K30 -> #DIV/0! | Q30: =wABS!G29 -> #DIV/0! | R30: =wABS!K29 -> 0 | S30: =wABS!O29 -> 0 | T30: =wABS!S29 -> 0 | U30: =wABS!W29 -> 0 | V30: =wTRD!O30 -> 0 | Y30: =M30-N30 -> #DIV/0! | Z30: =IF(M30<>0,Y30/M30*100,0) -> #DIV/0!
A31: Pyrethrum (A293) | B31: cpyre | C31: #DIV/0! | D31: =wTRD!I31 -> 0 | E31: =wTAX!G31 -> #DIV/0! | F31: =wTAX!K31 -> 0 | G31: =wTAX!O31 -> 0 | H31: =wTAX!S31 -> 0 | I31: =wTAX!W31 -> #DIV/0! | J31: =wTAX!AA31 -> #DIV/0! | K31: =wTAX!AE31 -> #DIV/0! | L31: =wTRC!G31 -> #DIV/0! | M31: =SUM(C31:L31) -> #DIV/0! | N31: =SUM(O31:V31) -> #DIV/0! | O31: =SUM(USE!C31:DB31) -> #DIV/0! | P31: =wTRC!K31 -> #DIV/0! | Q31: =wABS!G30 -> #DIV/0! | R31: =wABS!K30 -> 0 | S31: =wABS!O30 -> 0 | T31: =wABS!S30 -> 0 | U31: =wABS!W30 -> 0 | V31: =wTRD!O31 -> 0 | Y31: =M31-N31 -> #DIV/0! | Z31: =IF(M31<>0,Y31/M31*100,0) -> #DIV/0!
A32: Agricultural products n.e.c. (A299) | B32: cocrp | C32: #DIV/0! | D32: =wTRD!I32 -> 0 | E32: =wTAX!G32 -> #DIV/0! | F32: =wTAX!K32 -> 0 | G32: =wTAX!O32 -> 0 | H32: =wTAX!S32 -> 0 | I32: =wTAX!W32 -> #DIV/0! | J32: =wTAX!AA32 -> #DIV/0! | K32: =wTAX!AE32 -> #DIV/0! | L32: =wTRC!G32 -> #DIV/0! | M32: =SUM(C32:L32) -> #DIV/0! | N32: =SUM(O32:V32) -> #DIV/0! | O32: =SUM(USE!C32:DB32) -> #DIV/0! | P32: =wTRC!K32 -> #DIV/0! | Q32: =wABS!G31 -> #DIV/0! | R32: =wABS!K31 -> 0 | S32: =wABS!O31 -> 0 | T32: =wABS!S31 -> 0 | U32: =wABS!W31 -> 0 | V32: =wTRD!O32 -> 0 | Y32: =M32-N32 -> #DIV/0! | Z32: =IF(M32<>0,Y32/M32*100,0) -> #DIV/0!
... A99: Architectural and engineering activities (M02) | B99: cenga | C99: #DIV/0! | D99: =wTRD!I99 -> 0 | E99: =wTAX!G99 -> #DIV/0! | F99: =wTAX!K99 -> 0 | G99: =wTAX!O99 -> 0 | H99: =wTAX!S99 -> 0 | I99: =wTAX!W99 -> #DIV/0! | J99: =wTAX!AA99 -> #DIV/0! | K99: =wTAX!AE99 -> #DIV/0! | L99: =wTRC!G99 -> #DIV/0! | M99: =SUM(C99:L99) -> #DIV/0! | N99: =SUM(O99:V99) -> #DIV/0! | O99: =SUM(USE!C99:DB99) -> #DIV/0! | P99: =wTRC!K99 -> #DIV/0! | Q99: =wABS!G98 -> #DIV/0! | R99: =wABS!K98 -> 0 | S99: =wABS!O98 -> 0 | T99: =wABS!S98 -> 0 | U99: =wABS!W98 -> 0 | V99: =wTRD!O99 -> 0 | Y99: =M99-N99 -> #DIV/0! | Z99: =IF(M99<>0,Y99/M99*100,0) -> #DIV/0!
A100: Other professional, scientific and technical activities (M03) | B100: cprod | C100: #DIV/0! | D100: =wTRD!I100 -> 0 | E100: =wTAX!G100 -> #DIV/0! | F100: =wTAX!K100 -> 0 | G100: =wTAX!O100 -> 0 | H100: =wTAX!S100 -> 0 | I100: =wTAX!W100 -> #DIV/0! | J100: =wTAX!AA100 -> #DIV/0! | K100: =wTAX!AE100 -> #DIV/0! | L100: =wTRC!G100 -> #DIV/0! | M100: =SUM(C100:L100) -> #DIV/0! | N100: =SUM(O100:V100) -> #DIV/0! | O100: =SUM(USE!C100:DB100) -> #DIV/0! | P100: =wTRC!K100 -> #DIV/0! | Q100: =wABS!G99 -> #DIV/0! | R100: =wABS!K99 -> 0 | S100: =wABS!O99 -> 0 | T100: =wABS!S99 -> 0 | U100: =wABS!W99 -> 0 | V100: =wTRD!O100 -> 0 | W100: xxx | Y100: =M100-N100 -> #DIV/0! | Z100: =IF(M100<>0,Y100/M100*100,0) -> #DIV/0!
A101: Travel agents and tour operators (N01) | B101: ctrvl | C101: #DIV/0! | D101: =wTRD!I101 -> 0 | E101: =wTAX!G101 -> #DIV/0! | F101: =wTAX!K101 -> 0 | G101: =wTAX!O101 -> 0 | H101: =wTAX!S101 -> 0 | I101: =wTAX!W101 -> #DIV/0! | J101: =wTAX!AA101 -> #DIV/0! | K101: =wTAX!AE101 -> #DIV/0! | L101: =wTRC!G101 -> #DIV/0! | M101: =SUM(C101:L101) -> #DIV/0! | N101: =SUM(O101:V101) -> #DIV/0! | O101: =SUM(USE!C101:DB101) -> #DIV/0! | P101: =wTRC!K101 -> #DIV/0! | Q101: =wABS!G100 -> #DIV/0! | R101: =wABS!K100 -> 0 | S101: =wABS!O100 -> 0 | T101: =wABS!S100 -> 0 | U101: =wABS!W100 -> 0 | V101: =wTRD!O101 -> 0 | Y101: =M101-N101 -> #DIV/0! | Z101: =IF(M101<>0,Y101/M101*100,0) -> #DIV/0!
A102: Other administrative and support service activities (N09) | B102: cobsv | C102: #DIV/0! | D102: =wTRD!I102 -> 0 | E102: =wTAX!G102 -> #DIV/0! | F102: =wTAX!K102 -> 0 | G102: =wTAX!O102 -> 0 | H102: =wTAX!S102 -> 0 | I102: =wTAX!W102 -> #DIV/0! | J102: =wTAX!AA102 -> #DIV/0! | K102: =wTAX!AE102 -> #DIV/0! | L102: =wTRC!G102 -> #DIV/0! | M102: =SUM(C102:L102) -> #DIV/0! | N102: =SUM(O102:V102) -> #DIV/0! | O102: =SUM(USE!C102:DB102) -> #DIV/0! | P102: =wTRC!K102 -> #DIV/0! | Q102: =wABS!G101 -> #DIV/0! | R102: =wABS!K101 -> 0 | S102: =wABS!O101 -> 0 | T102: =wABS!S101 -> 0 | U102: =wABS!W101 -> 0 | V102: =wTRD!O102 -> 0 | Y102: =M102-N102 -> #DIV/0! | Z102: =IF(M102<>0,Y102/M102*100,0) -> #DIV/0!
A103: Public administration and defence; compulsory social security (O00) | B103: cpadm | C103: #DIV/0! | D103: =wTRD!I103 -> 0 | E103: =wTAX!G103 -> #DIV/0! | F103: =wTAX!K103 -> 0 | G103: =wTAX!O103 -> 0 | H103: =wTAX!S103 -> 0 | I103: =wTAX!W103 -> #DIV/0! | J103: =wTAX!AA103 -> #DIV/0! | K103: =wTAX!AE103 -> #DIV/0! | L103: =wTRC!G103 -> #DIV/0! | M103: =SUM(C103:L103) -> #DIV/0! | N103: =SUM(O103:V103) -> #DIV/0! | O103: =SUM(USE!C103:DB103) -> #DIV/0! | P103: =wTRC!K103 -> #DIV/0! | Q103: =wABS!G102 -> #DIV/0! | R103: =wABS!K102 -> 0 | S103: =wABS!O102 -> 0 | T103: =wABS!S102 -> 0 | U103: =wABS!W102 -> 0 | V103: =wTRD!O103 -> 0 | Y103: =M103-N103 -> #DIV/0! | Z103: =IF(M103<>0,Y103/M103*100,0) -> #DIV/0!
A104: Education (P00) | B104: ceduc | C104: #DIV/0! | D104: =wTRD!I104 -> 0 | E104: =wTAX!G104 -> #DIV/0! | F104: =wTAX!K104 -> 0 | G104: =wTAX!O104 -> 0 | H104: =wTAX!S104 -> 0 | I104: =wTAX!W104 -> #DIV/0! | J104: =wTAX!AA104 -> #DIV/0! | K104: =wTAX!AE104 -> #DIV/0! | L104: =wTRC!G104 -> #DIV/0! | M104: =SUM(C104:L104) -> #DIV/0! | N104: =SUM(O104:V104) -> #DIV/0! | O104: =SUM(USE!C104:DB104) -> #DIV/0! | P104: =wTRC!K104 -> #DIV/0! | Q104: =wABS!G103 -> #DIV/0! | R104: =wABS!K103 -> 0 | S104: =wABS!O103 -> 0 | T104: =wABS!S103 -> 0 | U104: =wABS!W103 -> 0 | V104: =wTRD!O104 -> 0 | Y104: =M104-N104 -> #DIV/0! | Z104: =IF(M104<>0,Y104/M104*100,0) -> #DIV/0!
A105: Human health activities (Q01) | B105: cheal | C105: #DIV/0! | D105: =wTRD!I105 -> 0 | E105: =wTAX!G105 -> #DIV/0! | F105: =wTAX!K105 -> 0 | G105: =wTAX!O105 -> 0 | H105: =wTAX!S105 -> 0 | I105: =wTAX!W105 -> #DIV/0! | J105: =wTAX!AA105 -> #DIV/0! | K105: =wTAX!AE105 -> #DIV/0! | L105: =wTRC!G105 -> #DIV/0! | M105: =SUM(C105:L105) -> #DIV/0! | N105: =SUM(O105:V105) -> #DIV/0! | O105: =SUM(USE!C105:DB105) -> #DIV/0! | P105: =wTRC!K105 -> #DIV/0! | Q105: =wABS!G104 -> #DIV/0! | R105: =wABS!K104 -> 0 | S105: =wABS!O104 -> 0 | T105: =wABS!S104 -> 0 | U105: =wABS!W104 -> 0 | V105: =wTRD!O105 -> 0 | Y105: =M105-N105 -> #DIV/0! | Z105: =IF(M105<>0,Y105/M105*100,0) -> #DIV/0!
A106: Social work activities (Q02) | B106: csocw | C106: #DIV/0! | D106: =wTRD!I106 -> 0 | E106: =wTAX!G106 -> #DIV/0! | F106: =wTAX!K106 -> 0 | G106: =wTAX!O106 -> 0 | H106: =wTAX!S106 -> 0 | I106: =wTAX!W106 -> #DIV/0! | J106: =wTAX!AA106 -> #DIV/0! | K106: =wTAX!AE106 -> #DIV/0! | L106: =wTRC!G106 -> #DIV/0! | M106: =SUM(C106:L106) -> #DIV/0! | N106: =SUM(O106:V106) -> #DIV/0! | O106: =SUM(USE!C106:DB106) -> #DIV/0! | P106: =wTRC!K106 -> #DIV/0! | Q106: =wABS!G105 -> #DIV/0! | R106: =wABS!K105 -> 0 | S106: =wABS!O105 -> 0 | T106: =wABS!S105 -> 0 | U106: =wABS!W105 -> 0 | V106: =wTRD!O106 -> 0 | Y106: =M106-N106 -> #DIV/0! | Z106: =IF(M106<>0,Y106/M106*100,0) -> #DIV/0!
A107: Libraries, archives, museums and other cultural activities (R01) | B107: ccult | C107: #DIV/0! | D107: =wTRD!I107 -> 0 | E107: =wTAX!G107 -> #DIV/0! | F107: =wTAX!K107 -> 0 | G107: =wTAX!O107 -> 0 | H107: =wTAX!S107 -> 0 | I107: =wTAX!W107 -> #DIV/0! | J107: =wTAX!AA107 -> #DIV/0! | K107: =wTAX!AE107 -> #DIV/0! | L107: =wTRC!G107 -> #DIV/0! | M107: =SUM(C107:L107) -> #DIV/0! | N107: =SUM(O107:V107) -> #DIV/0! | O107: =SUM(USE!C107:DB107) -> #DIV/0! | P107: =wTRC!K107 -> #DIV/0! | Q107: =wABS!G106 -> #DIV/0! | R107: =wABS!K106 -> 0 | S107: =wABS!O106 -> 0 | T107: =wABS!S106 -> 0 | U107: =wABS!W106 -> 0 | V107: =wTRD!O107 -> 0 | Y107: =M107-N107 -> #DIV/0! | Z107: =IF(M107<>0,Y107/M107*100,0) -> #DIV/0!
A108: Other arts, entertainment and recreation (R09) | B108: carts | C108: #DIV/0! | D108: =wTRD!I108 -> 0 | E108: =wTAX!G108 -> #DIV/0! | F108: =wTAX!K108 -> 0 | G108: =wTAX!O108 -> 0 | H108: =wTAX!S108 -> 0 | I108: =wTAX!W108 -> #DIV/0! | J108: =wTAX!AA108 -> #DIV/0! | K108: =wTAX!AE108 -> #DIV/0! | L108: =wTRC!G108 -> #DIV/0! | M108: =SUM(C108:L108) -> #DIV/0! | N108: =SUM(O108:V108) -> #DIV/0! | O108: =SUM(USE!C108:DB108) -> #DIV/0! | P108: =wTRC!K108 -> #DIV/0! | Q108: =wABS!G107 -> #DIV/0! | R108: =wABS!K107 -> 0 | S108: =wABS!O107 -> 0 | T108: =wABS!S107 -> 0 | U108: =wABS!W107 -> 0 | V108: =wTRD!O108 -> 0 | Y108: =M108-N108 -> #DIV/0! | Z108: =IF(M108<>0,Y108/M108*100,0) -> #DIV/0!
A109: Other service activities (S00) | B109: cosrv | C109: #DIV/0! | D109: =wTRD!I109 -> 0 | E109: =wTAX!G109 -> #DIV/0! | F109: =wTAX!K109 -> 0 | G109: =wTAX!O109 -> 0 | H109: =wTAX!S109 -> 0 | I109: =wTAX!W109 -> #DIV/0! | J109: =wTAX!AA109 -> #DIV/0! | K109: =wTAX!AE109 -> #DIV/0! | L109: =wTRC!G109 -> #DIV/0! | M109: =SUM(C109:L109) -> #DIV/0! | N109: =SUM(O109:V109) -> #DIV/0! | O109: =SUM(USE!C109:DB109) -> #DIV/0! | P109: =wTRC!K109 -> #DIV/0! | Q109: =wABS!G108 -> #DIV/0! | R109: =wABS!K108 -> 0 | S109: =wABS!O108 -> 0 | T109: =wABS!S108 -> 0 | U109: =wABS!W108 -> 0 | V109: =wTRD!O109 -> 0 | Y109: =M109-N109 -> #DIV/0! | Z109: =IF(M109<>0,Y109/M109*100,0) -> #DIV/0!
A110: Domestic services (T00) | B110: cdsrv | C110: #DIV/0! | D110: =wTRD!I110 -> 0 | E110: =wTAX!G110 -> #DIV/0! | F110: =wTAX!K110 -> 0 | G110: =wTAX!O110 -> 0 | H110: =wTAX!S110 -> 0 | I110: =wTAX!W110 -> #DIV/0! | J110: =wTAX!AA110 -> #DIV/0! | K110: =wTAX!AE110 -> #DIV/0! | L110: =wTRC!G110 -> #DIV/0! | M110: =SUM(C110:L110) -> #DIV/0! | N110: =SUM(O110:V110) -> #DIV/0! | O110: =SUM(USE!C110:DB110) -> #DIV/0! | P110: =wTRC!K110 -> #DIV/0! | Q110: =wABS!G109 -> #DIV/0! | R110: =wABS!K109 -> 0 | S110: =wABS!O109 -> 0 | T110: =wABS!S109 -> 0 | U110: =wABS!W109 -> 0 | V110: =wTRD!O110 -> 0 | Y110: =M110-N110 -> #DIV/0! | Z110: =IF(M110<>0,Y110/M110*100,0) -> #DIV/0!
A111: Travel debits & credits (V00) | B111: ctrdc | C111: #DIV/0! | D111: =wTRD!I111 -> 0 | E111: =wTAX!G111 -> #DIV/0! | F111: =wTAX!K111 -> 0 | G111: =wTAX!O111 -> 0 | H111: =wTAX!S111 -> 0 | I111: =wTAX!W111 -> #DIV/0! | J111: =wTAX!AA111 -> #DIV/0! | K111: =wTAX!AE111 -> #DIV/0! | L111: =wTRC!G111 -> #DIV/0! | M111: =SUM(C111:L111) -> #DIV/0! | N111: =SUM(O111:V111) -> #DIV/0! | O111: =SUM(USE!C111:DB111) -> #DIV/0! | P111: =wTRC!K111 -> #DIV/0! | Q111: =wABS!G110 -> #DIV/0! | R111: =wABS!K110 -> 0 | S111: =wABS!O110 -> 0 | T111: =wABS!S110 -> 0 | U111: =wABS!W110 -> 0 | V111: =wTRD!O111 -> 0 | Y111: =M111-N111 -> #DIV/0! | Z111: =IF(M111<>0,Y111/M111*100,0) -> #DIV/0!
B112: 0

Sheet USE
A1: Use Table
A2: Final values exported to GAMS
B3: From w-GDP | C3: {=TRANSPOSE(wGDPp!D8:D111)} -> 21.594729 | D3: 46.224396 | E3: 1.9919861 | F3: 26.906478 | G3: 7.1618331e-05 | H3: 115.17255 | I3: 119.65299 | J3: 77.058038 | K3: 13.498447 | L3: 239.84649 | M3: 520.88434 | N3: 6.7888873 | O3: 7.5439806 | P3: 201.88779 | Q3: 34.792013 | R3: 160.85445 | S3: 2.4697221 | T3: 0.83264683 | U3: 0 | V3: 0 | W3: 0 | X3: 0 | Y3: 0 | Z3: 0 | AA3: 0 | AB3: 149.49015 | AC3: 54.471183 | AD3: 23.696522 | AE3: 4.226682 | AF3: 64.412811 | AG3: 27.889836 | AH3: 1.0051477 | AI3: 6.807672 | AJ3: 424.56725 | AK3: 81.840908 | AL3: 27.591839 | AM3: 36 | AN3: 0.086892472 | AO3: 85.957092 | AP3: 120.95602 | AQ3: 39.25963 | AR3: 0 | AS3: 10.909306 | AT3: 14.465852 | AU3: 8.0749184 | AV3: 187.69429 | AW3: 29.411046 | AX3: 7.0349646 | AY3: 79.149992 | AZ3: 182.6314 | BA3: 35.771021 | BB3: 8.5975797 | BC3: 112 | BD3: 36.541827 | BE3: 25.458173 | BF3: 0.6744782 | BG3: 76.148853 | BH3: 17.083977 | BI3: 11.092692 | BJ3: 4.3289072 | BK3: 39.807103 | BL3: 21.86399 | BM3: 45.561608 | BN3: 19.96855 | BO3: 10.469842 | BP3: 32.749415 | BQ3: 50.980499 | BR3: 0.27008587 | BS3: 159 | BT3: 34.228894 | BU3: 4.7711056 | BV3: 811 | BW3: 0 | BX3: 57.119505 | BY3: 6.8804952 | BZ3: 388.68805 | CA3: 897.31195 | CB3: 364.08207 | CC3: 170.03773 | CD3: 78.130054 | CE3: 17.750151 | CF3: 0 | CG3: #DIV/0! | CH3: #DIV/0! | CI3: #DIV/0! | CJ3: #DIV/0! | CK3: #DIV/0! | CL3: #DIV/0! | CM3: #DIV/0! | CN3: #DIV/0! | CO3: #DIV/0! | CP3: #DIV/0! | CQ3: #DIV/0! | CR3: #DIV/0! | CS3: #DIV/0! | CT3: 0 | CU3: 0 | CV3: #DIV/0! | CW3: #DIV/0! | CX3: #DIV/0! | CY3: #DIV/0! | CZ3: #DIV/0! | DA3: #DIV/0! | DB3: #DIV/0!
B4: To Supply | C4: =SUM(C8:C114) -> 23.143032 | D4: =SUM(D8:D114) -> 49.538603 | E4: =SUM(E8:E114) -> 2.1348079 | F4: =SUM(F8:F114) -> 28.835624 | G4: =SUM(G8:G114) -> 7.6753237e-05 | H4: =SUM(H8:H114) -> 123.14102 | I4: =SUM(I8:I114) -> 127.93145 | J4: =SUM(J8:J114) -> 82.389468 | ... DB4: =SUM(DB8:DB114) -> #DIV/0!
C7: asorg | D7: amaiz | E7: awhea | F7: arice | G7: aocer | H7: aipot | I7: aspot | J7: acass | K7: aroot | L7: abean | M7: apeas | N7: avege | O7: abanb | P7: abanc | Q7: abans | R7: afrui | S7: agnut | T7: asoya | U7: aoils | V7: acoff | W7: ateal | X7: atoba | Y7: asugr | Z7: apyre | AA7: aocrp | AB7: acatt | AC7: asmlr | AD7: apoul | AE7: aoliv | AF7: amilk | AG7: aeggs | AH7: ahony | AI7: ahunt | AJ7: afuel | AK7: achar | AL7: afore | AM7: afish | AN7: angas | AO7: amore | AP7: aomin | AQ7: ameat | AR7: afsea | AS7: afveg | AT7: afoil | AU7: adair | AV7: agmll | AW7: abake | AX7: afeed | AY7: afood | AZ7: aalco | BA7: abeve | BB7: aptob | BC7: atext | BD7: awood | BE7: aprnt | BF7: apetr | BG7: achem | BH7: aphar | BI7: aprub | BJ7: anmet | BK7: aceme | BL7: aclay | BM7: ametl | BN7: amach | BO7: avehi | BP7: afurn | BQ7: aoman | BR7: arepr | BS7: aelec | BT7: awatr | BU7: awast | BV7: acons | BW7: acont | BX7: avehr | BY7: aveht | BZ7: atrdw | CA7: atrdr | CB7: atrnl | CC7: atrna | CD7: atrns | CE7: apost | CF7: ahotl | CG7: apubl | CH7: acomm | CI7: ainfo | CJ7: abank | CK7: ainsu | CL7: aofsv | CM7: arent | CN7: areal | CO7: alegl | CP7: aenga | CQ7: aprod | CR7: atrvl | CS7: aobsv | CT7: apadm | CU7: aeduc | CV7: aheal | CW7: asocw | CX7: acult | CY7: aarts | CZ7: aosrv | DA7: adsrv | DB7: atrdc
B8: csorg | C8: =IF(SUM(wUSE!C$112:C$114),C$3*wUSE!C8/SUM(wUSE!C$112:C$114),0) -> 0.17417571 | D8: =IF(SUM(wUSE!D$112:D$114),D$3*wUSE!D8/SUM(wUSE!D$112:D$114),0) -> 0 | E8: =IF(SUM(wUSE!E$112:E$114),E$3*wUSE!E8/SUM(wUSE!E$112:E$114),0) -> 0 | F8: =IF(SUM(wUSE!F$112:F$114),F$3*wUSE!F8/SUM(wUSE!F$112:F$114),0) -> 0 | G8: =IF(SUM(wUSE!G$112:G$114),G$3*wUSE!G8/SUM(wUSE!G$112:G$114),0) -> 0 | H8: =IF(SUM(wUSE!H$112:H$114),H$3*wUSE!H8/SUM(wUSE!H$112:H$114),0) -> 0 | I8: =IF(SUM(wUSE!I$112:I$114),I$3*wUSE!I8/SUM(wUSE!I$112:I$114),0) -> 0 | J8: =IF(SUM(wUSE!J$112:J$114),J$3*wUSE!J8/SUM(wUSE!J$112:J$114),0) -> 0 | ... DB8: =IF(SUM(wUSE!DB$112:DB$114),DB$3*wUSE!DB8/SUM(wUSE!DB$112:DB$114),0) -> #DIV/0!
B9: cmaiz | C9: =IF(SUM(wUSE!C$112:C$114),C$3*wUSE!C9/SUM(wUSE!C$112:C$114),0) -> 0 | D9: =IF(SUM(wUSE!D$112:D$114),D$3*wUSE!D9/SUM(wUSE!D$112:D$114),0) -> 0.37283019 | E9: =IF(SUM(wUSE!E$112:E$114),E$3*wUSE!E9/SUM(wUSE!E$112:E$114),0) -> 0 | F9: =IF(SUM(wUSE!F$112:F$114),F$3*wUSE!F9/SUM(wUSE!F$112:F$114),0) -> 0 | G9: =IF(SUM(wUSE!G$112:G$114),G$3*wUSE!G9/SUM(wUSE!G$112:G$114),0) -> 0 | H9: =IF(SUM(wUSE!H$112:H$114),H$3*wUSE!H9/SUM(wUSE!H$112:H$114),0) -> 0 | I9: =IF(SUM(wUSE!I$112:I$114),I$3*wUSE!I9/SUM(wUSE!I$112:I$114),0) -> 0 | J9: =IF(SUM(wUSE!J$112:J$114),J$3*wUSE!J9/SUM(wUSE!J$112:J$114),0) -> 0 | ... DB9: =IF(SUM(wUSE!DB$112:DB$114),DB$3*wUSE!DB9/SUM(wUSE!DB$112:DB$114),0) -> #DIV/0!
B10: cwhea | C10: =IF(SUM(wUSE!C$112:C$114),C$3*wUSE!C10/SUM(wUSE!C$112:C$114),0) -> 0 | D10: =IF(SUM(wUSE!D$112:D$114),D$3*wUSE!D10/SUM(wUSE!D$112:D$114),0) -> 0 | E10: =IF(SUM(wUSE!E$112:E$114),E$3*wUSE!E10/SUM(wUSE!E$112:E$114),0) -> 0.016066679 | F10: =IF(SUM(wUSE!F$112:F$114),F$3*wUSE!F10/SUM(wUSE!F$112:F$114),0) -> 0 | G10: =IF(SUM(wUSE!G$112:G$114),G$3*wUSE!G10/SUM(wUSE!G$112:G$114),0) -> 0 | H10: =IF(SUM(wUSE!H$112:H$114),H$3*wUSE!H10/SUM(wUSE!H$112:H$114),0) -> 0 | I10: =IF(SUM(wUSE!I$112:I$114),I$3*wUSE!I10/SUM(wUSE!I$112:I$114),0) -> 0 | J10: =IF(SUM(wUSE!J$112:J$114),J$3*wUSE!J10/SUM(wUSE!J$112:J$114),0) -> 0 | ... DB10: =IF(SUM(wUSE!DB$112:DB$114),DB$3*wUSE!DB10/SUM(wUSE!DB$112:DB$114),0) -> #DIV/0!
B11: crice | C11: =IF(SUM(wUSE!C$112:C$114),C$3*wUSE!C11/SUM(wUSE!C$112:C$114),0) -> 0 | D11: =IF(SUM(wUSE!D$112:D$114),D$3*wUSE!D11/SUM(wUSE!D$112:D$114),0) -> 0 | E11: =IF(SUM(wUSE!E$112:E$114),E$3*wUSE!E11/SUM(wUSE!E$112:E$114),0) -> 0 | F11: =IF(SUM(wUSE!F$112:F$114),F$3*wUSE!F11/SUM(wUSE!F$112:F$114),0) -> 0.21701846 | G11: =IF(SUM(wUSE!G$112:G$114),G$3*wUSE!G11/SUM(wUSE!G$112:G$114),0) -> 0 | H11: =IF(SUM(wUSE!H$112:H$114),H$3*wUSE!H11/SUM(wUSE!H$112:H$114),0) -> 0 | I11: =IF(SUM(wUSE!I$112:I$114),I$3*wUSE!I11/SUM(wUSE!I$112:I$114),0) -> 0 | J11: =IF(SUM(wUSE!J$112:J$114),J$3*wUSE!J11/SUM(wUSE!J$112:J$114),0) -> 0 | ... DB11: =IF(SUM(wUSE!DB$112:DB$114),DB$3*wUSE!DB11/SUM(wUSE!DB$112:DB$114),0) -> #DIV/0!
B12: cocer | C12: =IF(SUM(wUSE!C$112:C$114),C$3*wUSE!C12/SUM(wUSE!C$112:C$114),0) -> 0 | D12: =IF(SUM(wUSE!D$112:D$114),D$3*wUSE!D12/SUM(wUSE!D$112:D$114),0) -> 0 | E12: =IF(SUM(wUSE!E$112:E$114),E$3*wUSE!E12/SUM(wUSE!E$112:E$114),0) -> 0 | F12: =IF(SUM(wUSE!F$112:F$114),F$3*wUSE!F12/SUM(wUSE!F$112:F$114),0) -> 0 | G12: =IF(SUM(wUSE!G$112:G$114),G$3*wUSE!G12/SUM(wUSE!G$112:G$114),0) -> 5.77649e-07 | H12: =IF(SUM(wUSE!H$112:H$114),H$3*wUSE!H12/SUM(wUSE!H$112:H$114),0) -> 0 | I12: =IF(SUM(wUSE!I$112:I$114),I$3*wUSE!I12/SUM(wUSE!I$112:I$114),0) -> 0 | J12: =IF(SUM(wUSE!J$112:J$114),J$3*wUSE!J12/SUM(wUSE!J$112:J$114),0) -> 0 | ... DB12: =IF(SUM(wUSE!DB$112:DB$114),DB$3*wUSE!DB12/SUM(wUSE!DB$112:DB$114),0) -> #DIV/0!
B13: cipot | C13: =IF(SUM(wUSE!C$112:C$114),C$3*wUSE!C13/SUM(wUSE!C$112:C$114),0) -> 0 | D13: =IF(SUM(wUSE!D$112:D$114),D$3*wUSE!D13/SUM(wUSE!D$112:D$114),0) -> 0 | E13: =IF(SUM(wUSE!E$112:E$114),E$3*wUSE!E13/SUM(wUSE!E$112:E$114),0) -> 0 | F13: =IF(SUM(wUSE!F$112:F$114),F$3*wUSE!F13/SUM(wUSE!F$112:F$114),0) -> 0 | G13: =IF(SUM(wUSE!G$112:G$114),G$3*wUSE!G13/SUM(wUSE!G$112:G$114),0) -> 0 | H13: =IF(SUM(wUSE!H$112:H$114),H$3*wUSE!H13/SUM(wUSE!H$112:H$114),0) -> 1.4084817 | I13: =IF(SUM(wUSE!I$112:I$114),I$3*wUSE!I13/SUM(wUSE!I$112:I$114),0) -> 0 | J13: =IF(SUM(wUSE!J$112:J$114),J$3*wUSE!J13/SUM(wUSE!J$112:J$114),0) -> 0 | ... DB13: =IF(SUM(wUSE!DB$112:DB$114),DB$3*wUSE!DB13/SUM(wUSE!DB$112:DB$114),0) -> #DIV/0!
B14: cspot | C14: =IF(SUM(wUSE!C$112:C$114),C$3*wUSE!C14/SUM(wUSE!C$112:C$114),0) -> 0 | D14: =IF(SUM(wUSE!D$112:D$114),D$3*wUSE!D14/SUM(wUSE!D$112:D$114),0) -> 0 | E14: =IF(SUM(wUSE!E$112:E$114),E$3*wUSE!E14/SUM(wUSE!E$112:E$114),0) -> 0 | F14: =IF(SUM(wUSE!F$112:F$114),F$3*wUSE!F14/SUM(wUSE!F$112:F$114),0) -> 0 | G14: =IF(SUM(wUSE!G$112:G$114),G$3*wUSE!G14/SUM(wUSE!G$112:G$114),0) -> 0 | H14: =IF(SUM(wUSE!H$112:H$114),H$3*wUSE!H14/SUM(wUSE!H$112:H$114),0) -> 0 | I14: =IF(SUM(wUSE!I$112:I$114),I$3*wUSE!I14/SUM(wUSE!I$112:I$114),0) -> 1.4632744 | J14: =IF(SUM(wUSE!J$112:J$114),J$3*wUSE!J14/SUM(wUSE!J$112:J$114),0) -> 0 | ... DB14: =IF(SUM(wUSE!DB$112:DB$114),DB$3*wUSE!DB14/SUM(wUSE!DB$112:DB$114),0) -> #DIV/0!
B15: ccass | C15: =IF(SUM(wUSE!C$112:C$114),C$3*wUSE!C15/SUM(wUSE!C$112:C$114),0) -> 0 | D15: =IF(SUM(wUSE!D$112:D$114),D$3*wUSE!D15/SUM(wUSE!D$112:D$114),0) -> 0 | E15: =IF(SUM(wUSE!E$112:E$114),E$3*wUSE!E15/SUM(wUSE!E$112:E$114),0) -> 0 | F15: =IF(SUM(wUSE!F$112:F$114),F$3*wUSE!F15/SUM(wUSE!F$112:F$114),0) -> 0 | G15: =IF(SUM(wUSE!G$112:G$114),G$3*wUSE!G15/SUM(wUSE!G$112:G$114),0) -> 0 | H15: =IF(SUM(wUSE!H$112:H$114),H$3*wUSE!H15/SUM(wUSE!H$112:H$114),0) -> 0 | I15: =IF(SUM(wUSE!I$112:I$114),I$3*wUSE!I15/SUM(wUSE!I$112:I$114),0) -> 0 | J15: =IF(SUM(wUSE!J$112:J$114),J$3*wUSE!J15/SUM(wUSE!J$112:J$114),0) -> 0.9423672 | ... DB15: =IF(SUM(wUSE!DB$112:DB$114),DB$3*wUSE!DB15/SUM(wUSE!DB$112:DB$114),0) -> #DIV/0!
B16: croot | C16: =IF(SUM(wUSE!C$112:C$114),C$3*wUSE!C16/SUM(wUSE!C$112:C$114),0) -> 0 | D16: =IF(SUM(wUSE!D$112:D$114),D$3*wUSE!D16/SUM(wUSE!D$112:D$114),0) -> 0 | E16: =IF(SUM(wUSE!E$112:E$114),E$3*wUSE!E16/SUM(wUSE!E$112:E$114),0) -> 0 | F16: =IF(SUM(wUSE!F$112:F$114),F$3*wUSE!F16/SUM(wUSE!F$112:F$114),0) -> 0 | G16: =IF(SUM(wUSE!G$112:G$114),G$3*wUSE!G16/SUM(wUSE!G$112:G$114),0) -> 0 | H16: =IF(SUM(wUSE!H$112:H$114),H$3*wUSE!H16/SUM(wUSE!H$112:H$114),0) -> 0 | I16: =IF(SUM(wUSE!I$112:I$114),I$3*wUSE!I16/SUM(wUSE!I$112:I$114),0) -> 0 | J16: =IF(SUM(wUSE!J$112:J$114),J$3*wUSE!J16/SUM(wUSE!J$112:J$114),0) -> 0 | ... DB16: =IF(SUM(wUSE!DB$112:DB$114),DB$3*wUSE!DB16/SUM(wUSE!DB$112:DB$114),0) -> #DIV/0!
B17: cbean | C17: =IF(SUM(wUSE!C$112:C$114),C$3*wUSE!C17/SUM(wUSE!C$112:C$114),0) -> 0 | D17: =IF(SUM(wUSE!D$112:D$114),D$3*wUSE!D17/SUM(wUSE!D$112:D$114),0) -> 0 | E17: =IF(SUM(wUSE!E$112:E$114),E$3*wUSE!E17/SUM(wUSE!E$112:E$114),0) -> 0 | F17: =IF(SUM(wUSE!F$112:F$114),F$3*wUSE!F17/SUM(wUSE!F$112:F$114),0) -> 0 | G17: =IF(SUM(wUSE!G$112:G$114),G$3*wUSE!G17/SUM(wUSE!G$112:G$114),0) -> 0 | H17: =IF(SUM(wUSE!H$112:H$114),H$3*wUSE!H17/SUM(wUSE!H$112:H$114),0) -> 0 | I17: =IF(SUM(wUSE!I$112:I$114),I$3*wUSE!I17/SUM(wUSE!I$112:I$114),0) -> 0 | J17: =IF(SUM(wUSE!J$112:J$114),J$3*wUSE!J17/SUM(wUSE!J$112:J$114),0) -> 0 | ... DB17: =IF(SUM(wUSE!DB$112:DB$114),DB$3*wUSE!DB17/SUM(wUSE!DB$112:DB$114),0) -> #DIV/0!
B18: cpeas | C18: =IF(SUM(wUSE!C$112:C$114),C$3*wUSE!C18/SUM(wUSE!C$112:C$114),0) -> 0 | D18: =IF(SUM(wUSE!D$112:D$114),D$3*wUSE!D18/SUM(wUSE!D$112:D$114),0) -> 0 | E18: =IF(SUM(wUSE!E$112:E$114),E$3*wUSE!E18/SUM(wUSE!E$112:E$114),0) -> 0 | F18: =IF(SUM(wUSE!F$112:F$114),F$3*wUSE!F18/SUM(wUSE!F$112:F$114),0) -> 0 | G18: =IF(SUM(wUSE!G$112:G$114),G$3*wUSE!G18/SUM(wUSE!G$112:G$114),0) -> 0 | H18: =IF(SUM(wUSE!H$112:H$114),H$3*wUSE!H18/SUM(wUSE!H$112:H$114),0) -> 0 | I18: =IF(SUM(wUSE!I$112:I$114),I$3*wUSE!I18/SUM(wUSE!I$112:I$114),0) -> 0 | J18: =IF(SUM(wUSE!J$112:J$114),J$3*wUSE!J18/SUM(wUSE!J$112:J$114),0) -> 0 | ... DB18: =IF(SUM(wUSE!DB$112:DB$114),DB$3*wUSE!DB18/SUM(wUSE!DB$112:DB$114),0) -> #DIV/0!
B19: cvege | C19: =IF(SUM(wUSE!C$112:C$114),C$3*wUSE!C19/SUM(wUSE!C$112:C$114),0) -> 0 | D19: =IF(SUM(wUSE!D$112:D$114),D$3*wUSE!D19/SUM(wUSE!D$112:D$114),0) -> 0 | E19: =IF(SUM(wUSE!E$112:E$114),E$3*wUSE!E19/SUM(wUSE!E$112:E$114),0) -> 0 | F19: =IF(SUM(wUSE!F$112:F$114),F$3*wUSE!F19/SUM(wUSE!F$112:F$114),0) -> 0 | G19: =IF(SUM(wUSE!G$112:G$114),G$3*wUSE!G19/SUM(wUSE!G$112:G$114),0) -> 0 | H19: =IF(SUM(wUSE!H$112:H$114),H$3*wUSE!H19/SUM(wUSE!H$112:H$114),0) -> 0 | I19: =IF(SUM(wUSE!I$112:I$114),I$3*wUSE!I19/SUM(wUSE!I$112:I$114),0) -> 0 | J19: =IF(SUM(wUSE!J$112:J$114),J$3*wUSE!J19/SUM(wUSE!J$112:J$114),0) -> 0 | ... DB19: =IF(SUM(wUSE!DB$112:DB$114),DB$3*wUSE!DB19/SUM(wUSE!DB$112:DB$114),0) -> #DIV/0!
... B114: fcap | C114: =IF(SUM(wUSE!C$112:C$114),C$3*wUSE!C114/SUM(wUSE!C$112:C$114),0) -> 1.5833994 | D114: =IF(SUM(wUSE!D$112:D$114),D$3*wUSE!D114/SUM(wUSE!D$112:D$114),0) -> 3.7016583 | E114: =IF(SUM(wUSE!E$112:E$114),E$3*wUSE!E114/SUM(wUSE!E$112:E$114),0) -> 0.18461394 | F114: =IF(SUM(wUSE!F$112:F$114),F$3*wUSE!F114/SUM(wUSE!F$112:F$114),0) -> 3.0093701 | G114: =IF(SUM(wUSE!G$112:G$114),G$3*wUSE!G114/SUM(wUSE!G$112:G$114),0) -> 5.2513011e-06 | H114: =IF(SUM(wUSE!H$112:H$114),H$3*wUSE!H114/SUM(wUSE!H$112:H$114),0) -> 12.411987 | I114: =IF(SUM(wUSE!I$112:I$114),I$3*wUSE!I114/SUM(wUSE!I$112:I$114),0) -> 8.6756779 | J114: =IF(SUM(wUSE!J$112:J$114),J$3*wUSE!J114/SUM(wUSE!J$112:J$114),0) -> 6.2152382 | ... DB114: =IF(SUM(wUSE!DB$112:DB$114),DB$3*wUSE!DB114/SUM(wUSE!DB$112:DB$114),0) -> #DIV/0!

Sheet wBOP
A1: Balance of Payments
A2: Workings | G2: =B4 -> 2024 | I2: 2010 | J2: 2011 | K2: 2012 | L2: 2013 | M2: 2014 | N2: 2015 | O2: 2016 | P2: 2017 | Q2: 2018 | R2: 2019 | S2: 2020 | T2: 2021 | U2: 2022 | V2: 2023 | W2: 2024 | X2: 2025
G3: =SUMIF($I$2:$W$2,$G$2,$I$3:$W$3) -> 1318 | H3: Exchange rate (RwF/USD) | I3: 583.13 | J3: 600.31 | K3: 614.3 | L3: 646.64 | M3: 681.86 | N3: 720.98 | O3: 787.25 | P3: 831.53 | Q3: 861.09 | R3: 899.35 | S3: 943.23 | T3: 988.62 | U3: 1030.5 | V3: 1160.1 | W3: 1318
B4: =Notes!B5 -> 2024 | C4: Year
B5: 0.001 | C5: Scaling (multiplier)
B6: =G3 -> 1318 | C6: Exchange rate | H6: Rwanda: Balance of Payments Standard Presentation
H7: Millions of U.S. Dollars
H8: https://www.bnr.rw/browse-in/statistics/external-sector-statistics/
I9: =IF(ISERR(LEFT(I10,4)/1),"",LEFT(I10,4)/1) -> 2010 | J9: =IF(ISERR(LEFT(J10,4)/1),"",LEFT(J10,4)/1) -> 2011 | K9: =IF(ISERR(LEFT(K10,4)/1),"",LEFT(K10,4)/1) -> 2012 | L9: =IF(ISERR(LEFT(L10,4)/1),"",LEFT(L10,4)/1) -> 2013 | M9: =IF(ISERR(LEFT(M10,4)/1),"",LEFT(M10,4)/1) -> 2014 | N9: =IF(ISERR(LEFT(N10,4)/1),"",LEFT(N10,4)/1) -> 2015 | O9: =IF(ISERR(LEFT(O10,4)/1),"",LEFT(O10,4)/1) -> 2016 | P9: =IF(ISERR(LEFT(P10,4)/1),"",LEFT(P10,4)/1) -> 2017 | ... AQ9: =IF(ISERR(LEFT(AQ10,4)/1),"",LEFT(AQ10,4)/1) -> 2023 | AR9: 2024 | AS9: 2024 | AT9: 2024 | AU9: 2024
B10: Receipts | D10: Payments | G10: =B4 -> 2024 | I10: 2010 | J10: 2011 | K10: 2012 | L10: 2013 | M10: 2014 | N10: 2015 | O10: 2016 | P10: 2017Q1 | Q10: 2017Q2 | R10: 2017Q3 | S10: 2017Q4 | T10: 2018Q1 | U10: 2018Q2 | V10: 2018Q3 | W10: 2018Q4 | X10: 2019Q1 | Y10: 2019Q2 | Z10: 2019Q3 | AA10: 2019Q4 | AB10: 2020Q1 | AC10: 2020Q2 | AD10: 2020Q3 | AE10: 2020Q4 | AF10: 2021Q1 | AG10: 2021Q2 | AH10: 2021Q3 | AI10: 2021Q4 | AJ10: 2022Q1 | AK10: 2022Q3 | AL10: 2022Q4 | AM10: 2022Q4 | AN10: 2023Q1 | AO10: 2023Q2 | AP10: 2023Q3 | AQ10: 2023Q4 | AR10: 2024Q1 | AS10: 2024Q2 | AT10: 2024Q3 | AU10: 2024Q4
B11: Export goods | C11: =G18 -> 4218.9202 | D11: Import goods | E11: =G19 -> 7308.8389 | G11: =SUMIF($I$9:$AU$9,G$10,$I11:$AU11)*$G$3*$B$5 -> -2382.3751 | H11: Current account | I11: -399.14244 | J11: -477.01051 | K11: -741.01596 | L11: -585.10561 | M11: -934.6195 | N11: -1083.6715 | O11: -1330.8224 | P11: -228.63633 | Q11: -186.39793 | R11: -251.98705 | S11: -194.48914 | T11: -280.72792 | U11: -225.60469 | V11: -202.27277 | W11: -270.90445 | X11: -275.24323 | Y11: -357.0171 | Z11: -342.57241 | AA11: -278.90948 | AB11: -419.57532 | AC11: -280.33188 | AD11: -330.31812 | AE11: -255.60268 | AF11: -242.38958 | AG11: -315.59641 | AH11: -354.34116 | AI11: -290.75533 | AJ11: -236.71477 | AK11: -190.80021 | AL11: -456.86498 | AM11: -362.05442 | AN11: -415.92611 | AO11: -334.87943 | AP11: -438.73794 | AQ11: -457.67931 | AR11: -517.45115 | AS11: -437.45608 | AT11: -501.16921 | AU11: -351.4919
B12: Export services | C12: =G27 -> 1424.7745 | D12: Import services | E12: =G28 -> 1305.9994 | G12: =SUMIF($I$9:$AU$9,G$10,$I12:$AU12)*$G$3*$B$5 -> 6803.2312 | H12: Credit | I12: 1356.1006 | J12: 1845.7334 | K12: 1841.6682 | L12: 2131.8792 | M12: 2006.8038 | N12: 2075.4025 | O12: 2138.3967 | P12: 558.48411 | Q12: 653.86231 | R12: 683.39402 | S12: 724.95065 | T12: 647.27323 | U12: 666.65626 | V12: 776.29843 | W12: 723.78899 | X12: 658.57486 | Y12: 649.84801 | Z12: 784.95347 | AA12: 830.20898 | AB12: 652.54253 | AC12: 514.87885 | AD12: 796.30553 | AE12: 672.50405 | AF12: 624.25364 | AG12: 731.31684 | AH12: 747.52042 | AI12: 864.868 | AJ12: 888.68048 | AK12: 1135.3487 | AL12: 1033.457 | AM12: 1039.0368 | AN12: 1009.9781 | AO12: 1262.4272 | AP12: 1140.4417 | AQ12: 1108.3894 | AR12: 1053.1167 | AS12: 1260.8225 | AT12: 1428.5321 | AU12: 1419.3126
B13: Labor | C13: =G87 -> 19.263854 | D13: Labor | E13: =G88 -> 59.218529 | G13: =SUMIF($I$9:$AU$9,G$10,$I13:$AU13)*$G$3*$B$5 -> 9185.6062 | H13: Debit | I13: 1755.243 | J13: 2322.7439 | K13: 2582.6841 | L13: 2716.9848 | M13: 2941.4233 | N13: 3159.074 | O13: 3469.219 | P13: 787.12044 | Q13: 840.26024 | R13: 935.38107 | S13: 919.43979 | T13: 928.00115 | U13: 892.26095 | V13: 978.5712 | W13: 994.69345 | X13: 933.81809 | Y13: 1006.8651 | Z13: 1127.5259 | AA13: 1109.1185 | AB13: 1072.1178 | AC13: 795.21073 | AD13: 1126.6237 | AE13: 928.10673 | AF13: 866.64322 | AG13: 1046.9132 | AH13: 1101.8616 | AI13: 1155.6233 | AJ13: 1125.3952 | AK13: 1326.1489 | AL13: 1490.3219 | AM13: 1401.0912 | AN13: 1425.9042 | AO13: 1597.3067 | AP13: 1579.1797 | AQ13: 1566.0687 | AR13: 1570.5678 | AS13: 1698.2786 | AT13: 1929.7013 | AU13: 1770.8045
B14: Land | D14: Land | G14: =SUMIF($I$9:$AU$9,G$10,$I14:$AU14)*$G$3*$B$5 -> -2971.1436 | H14: Goods and services | I14: -941.10324 | J14: -1224.7229 | K14: -1253.8153 | L14: -1154.6482 | M14: -1325.2429 | N14: -1489.7128 | O14: -1539.5993 | P14: -281.676 | Q14: -274.05727 | R14: -324.33402 | S14: -286.622 | T14: -347.59872 | U14: -276.2825 | V14: -297.68464 | W14: -377.62723 | X14: -335.35322 | Y14: -381.04758 | Z14: -396.10287 | AA14: -377.75982 | AB14: -478.51934 | AC14: -377.53732 | AD14: -437.15315 | AE14: -381.03578 | AF14: -372.19657 | AG14: -473.39611 | AH14: -485.5405 | AI14: -451.9952 | AJ14: -402.58064 | AK14: -505.31337 | AL14: -563.24827 | AM14: -513.84728 | AN14: -521.66477 | AO14: -608.88488 | AP14: -563.78236 | AQ14: -573.48829 | AR14: -594.67644 | AS14: -606.51655 | AT14: -583.57093 | AU14: -469.51806
B15: Capital | C15: =G90 -> 21.74132 | D15: Capital | E15: =G91 -> 421.17383 | G15: =SUMIF($I$9:$AU$9,G$10,$I15:$AU15)*$G$3*$B$5 -> 5643.6947 | H15: Credit | I15: 702.72842 | J15: 953.28799 | K15: 1120.3809 | L15: 1298.832 | M15: 1328.2776 | N15: 1449.0252 | O15: 1516.6459 | P15: 425.1013 | Q15: 466.64141 | R15: 491.13054 | S15: 521.02998 | T15: 468.49011 | U15: 495.3209 | V15: 574.35979 | W15: 505.08566 | X15: 481.15911 | Y15: 512.25048 | Z15: 622.77711 | AA15: 630.59644 | AB15: 498.46569 | AC15: 356.21443 | AD15: 617.73805 | AE15: 485.86369 | AF15: 422.72663 | AG15: 502.22296 | AH15: 545.80546 | AI15: 636.42268 | AJ15: 619.98772 | AK15: 746.45655 | AL15: 819.92835 | AM15: 806.71935 | AN15: 817.25225 | AO15: 900.31283 | AP15: 907.82297 | AQ15: 885.30058 | AR15: 868.51177 | AS15: 978.91883 | AT15: 1238.3711 | AU15: 1196.2125
B16: Households | C16: =G129 -> 662.20001 | D16: Households | E16: =G130 -> 72.601948 | G16: =SUMIF($I$9:$AU$9,G$10,$I16:$AU16)*$G$3*$B$5 -> 8614.8383 | H16: Debit | I16: 1643.8317 | J16: 2178.0108 | K16: 2374.1961 | L16: 2453.4802 | M16: 2653.5206 | N16: 2938.738 | O16: 3056.2452 | P16: 706.7773 | Q16: 740.69868 | R16: 815.46456 | S16: 807.65199 | T16: 816.08883 | U16: 771.60341 | V16: 872.04443 | W16: 882.71289 | X16: 816.51233 | Y16: 893.29806 | Z16: 1018.88 | AA16: 1008.3563 | AB16: 976.98503 | AC16: 733.75175 | AD16: 1054.8912 | AE16: 866.89947 | AF16: 794.92321 | AG16: 975.61907 | AH16: 1031.346 | AI16: 1088.4179 | AJ16: 1022.5684 | AK16: 1251.7699 | AL16: 1383.1766 | AM16: 1320.5666 | AN16: 1338.917 | AO16: 1509.1977 | AP16: 1471.6053 | AQ16: 1458.7889 | AR16: 1463.1882 | AS16: 1585.4354 | AT16: 1821.942 | AU16: 1665.7305
B17: Enterprises | C17: =G135 -> 98.215884 | D17: Enterprises | E17: =G136 -> 6.3768699 | G17: =SUMIF($I$9:$AU$9,G$10,$I17:$AU17)*$G$3*$B$5 -> -3089.9187 | H17: Goods | I17: -786.69823 | J17: -1104.8407 | K17: -1273.698 | L17: -1150.7782 | M17: -1268.5694 | N17: -1236.6056 | O17: -1294.1432 | P17: -243.92757 | Q17: -240.92931 | R17: -247.81955 | S17: -241.2251 | T17: -268.93842 | U17: -243.35249 | V17: -302.39128 | W17: -340.90782 | X17: -303.02834 | Y17: -378.44714 | Z17: -396.40056 | AA17: -394.94548 | AB17: -441.25589 | AC17: -366.49477 | AD17: -449.28193 | AE17: -420.49038 | AF17: -369.95261 | AG17: -444.78011 | AH17: -413.84844 | AI17: -430.11281 | AJ17: -360.23804 | AK17: -519.32108 | AL17: -619.54863 | AM17: -489.42472 | AN17: -527.36584 | AO17: -594.48766 | AP17: -644.06238 | AQ17: -602.84394 | AR17: -599.16535 | AS17: -609.54795 | AT17: -651.87229 | AU17: -483.81399
B18: Government | C18: =G123 -> 358.11541 | D18: Government | E18: =G124 -> 11.396738 | G18: =SUMIF($I$9:$AU$9,G$10,$I18:$AU18)*$G$3*$B$5 -> 4218.9202 | H18: Credit | I18: 297.27526 | J18: 464.2351 | K18: 590.75048 | L18: 703.01008 | M18: 723.0906 | N18: 682.04487 | O18: 726.6109 | P18: 223.62202 | Q18: 255.20577 | R18: 277.62813 | S18: 284.00712 | T18: 280.82884 | U18: 290.33357 | V18: 285.83251 | W18: 272.63106 | X18: 255.77903 | Y18: 287.40533 | Z18: 331.33986 | AA18: 357.28585 | AB18: 317.6034 | AC18: 279.34182 | AD18: 485.07296 | AE18: 342.1364 | AF18: 289.62498 | AG18: 370.39972 | AH18: 401.02814 | AI18: 469.77762 | AJ18: 458.71861 | AK18: 523.6826 | AL18: 562.97717 | AM18: 566.51294 | AN18: 591.79711 | AO18: 686.18421 | AP18: 590.62738 | AQ18: 597.34056 | AR18: 644.84475 | AS18: 737.81919 | AT18: 891.80587 | AU18: 926.53188
B19: Balance | C19: =-G11 -> 2382.3751 | G19: =SUMIF($I$9:$AU$9,G$10,$I19:$AU19)*$G$3*$B$5 -> 7308.8389 | H19: Debit | I19: 1083.9735 | J19: 1569.0758 | K19: 1864.4485 | L19: 1853.7883 | M19: 1991.66 | N19: 1918.6505 | O19: 2020.7541 | P19: 467.54959 | Q19: 496.13509 | R19: 525.44769 | S19: 525.23221 | T19: 549.76726 | U19: 533.68606 | V19: 588.22379 | W19: 613.53888 | X19: 558.80737 | Y19: 665.85247 | Z19: 727.74042 | AA19: 752.23132 | AB19: 758.85929 | AC19: 645.83659 | AD19: 934.35488 | AE19: 762.62678 | AF19: 659.5776 | AG19: 815.17983 | AH19: 814.87658 | AI19: 899.89043 | AJ19: 818.95665 | AK19: 1043.0037 | AL19: 1182.5258 | AM19: 1055.9377 | AN19: 1119.1629 | AO19: 1280.6719 | AP19: 1234.6898 | AQ19: 1200.1845 | AR19: 1244.0101 | AS19: 1347.3671 | AT19: 1543.6782 | AU19: 1410.3459
B20: Total | C20: =SUM(C11:C19) -> 9185.6062 | D20: Total | E20: =SUM(E11:E19) -> 9185.6062 | G20: =SUMIF($I$9:$AU$9,G$10,$I20:$AU20)*$G$3*$B$5 -> -3130.9932 | H20: General merchandise on a balance of payments basis | I20: -786.69823 | J20: -1104.8407 | K20: -1273.698 | L20: -1150.7782 | M20: -1268.5694 | N20: -1236.6056 | O20: -1294.1432 | P20: -266.55257 | Q20: -263.55432 | R20: -270.44455 | S20: -263.8501 | T20: -287.34183 | U20: -261.7559 | V20: -320.79469 | W20: -359.31123 | X20: -316.88921 | Y20: -386.24798 | Z20: -403.84434 | AA20: -402.86639 | AB20: -440.94998 | AC20: -346.36419 | AD20: -458.10855 | AE20: -424.22036 | AF20: -360.20813 | AG20: -443.3026 | AH20: -417.85139 | AI20: -432.2105 | AJ20: -358.29144 | AK20: -517.67374 | AL20: -609.70991 | AM20: -548.62399 | AN20: -510.33629 | AO20: -588.21794 | AP20: -621.21817 | AQ20: -603.20717 | AR20: -577.23427 | AS20: -633.69166 | AT20: -607.51902 | AU20: -557.11898
D21: Difference | E21: =E20-C20 -> 0 | G21: =SUMIF($I$9:$AU$9,G$10,$I21:$AU21)*$G$3*$B$5 -> 2229.9874 | H21: Credit | I21: 297.27526 | J21: 464.2351 | K21: 590.75048 | L21: 703.01008 | M21: 723.0906 | N21: 682.04487 | O21: 726.6109 | P21: 200.99702 | Q21: 232.58077 | R21: 255.00313 | S21: 261.38212 | T21: 262.42543 | U21: 271.93016 | V21: 267.4291 | W21: 254.22765 | X21: 241.91816 | Y21: 279.60449 | Z21: 212.49777 | AA21: 221.41603 | AB21: 210.41226 | AC21: 142.28026 | AD21: 190.85227 | AE21: 217.80375 | AF21: 239.16892 | AG21: 276.92775 | AH21: 298.51631 | AI21: 353.03346 | AJ21: 342.2218 | AK21: 363.49717 | AL21: 418.36788 | AM21: 432.06406 | AN21: 401.51346 | AO21: 383.49133 | AP21: 402.61359 | AQ21: 394.723 | AR21: 390.78911 | AS21: 386.93113 | AT21: 457.0785 | AU21: 457.14922
G22: =SUMIF($I$9:$AU$9,G$10,$I22:$AU22)*$G$3*$B$5 -> 5360.9806 | H22: Debit | I22: 1083.9735 | J22: 1569.0758 | K22: 1864.4485 | L22: 1853.7883 | M22: 1991.66 | N22: 1918.6505 | O22: 2020.7541 | P22: 467.54959 | Q22: 496.13509 | R22: 525.44769 | S22: 525.23221 | T22: 549.76726 | U22: 533.68606 | V22: 588.22379 | W22: 613.53888 | X22: 558.80737 | Y22: 665.85247 | Z22: 616.34211 | AA22: 624.28242 | AB22: 651.36223 | AC22: 488.64445 | AD22: 648.96081 | AE22: 642.02411 | AF22: 599.37705 | AG22: 720.23036 | AH22: 716.3677 | AI22: 785.24396 | AJ22: 700.51324 | AK22: 881.17091 | AL22: 1028.0778 | AM22: 980.68805 | AN22: 911.84974 | AO22: 971.70927 | AP22: 1023.8318 | AQ22: 997.93017 | AR22: 968.02338 | AS22: 1020.6228 | AT22: 1064.5975 | AU22: 1014.2682
G23: =SUMIF($I$9:$AU$9,G$10,$I23:$AU23)*$G$3*$B$5 -> 41.074593 | H23: Nonmonetary gold | I23: 0 | J23: 0 | K23: 0 | L23: 0 | M23: 0 | N23: 0 | O23: 0 | P23: 22.625 | Q23: 22.625004 | R23: 22.625 | S23: 22.625 | T23: 18.40341 | U23: 18.40341 | V23: 18.40341 | W23: 18.40341 | X23: 13.860868 | Y23: 7.8008382 | Z23: 7.4437794 | AA23: 7.9209139 | AB23: -0.30591755 | AC23: -20.130576 | AD23: 8.8266207 | AE23: 3.7299793 | AF23: -9.7444887 | AG23: -1.477508 | AH23: 4.0029539 | AI23: 2.0976809 | AJ23: -1.9466012 | AK23: -1.647346 | AL23: -9.838718 | AM23: 59.199273 | AN23: -17.029549 | AO23: -6.2697241 | AP23: -22.844212 | AQ23: 0.36323064 | AR23: -21.931079 | AS23: 24.143705 | AT23: -44.353278 | AU23: 73.304987
G24: =SUMIF($I$9:$AU$9,G$10,$I24:$AU24)*$G$3*$B$5 -> 1988.9328 | H24: Credit | I24: 0 | J24: 0 | K24: 0 | L24: 0 | M24: 0 | N24: 0 | O24: 0 | P24: 22.625 | Q24: 22.625004 | R24: 22.625 | S24: 22.625 | T24: 18.40341 | U24: 18.40341 | V24: 18.40341 | W24: 18.40341 | X24: 13.860868 | Y24: 7.8008382 | Z24: 118.84209 | AA24: 135.86982 | AB24: 107.19114 | AC24: 137.06156 | AD24: 294.22069 | AE24: 124.33264 | AF24: 50.456063 | AG24: 93.471964 | AH24: 102.51183 | AI24: 116.74415 | AJ24: 116.49681 | AK24: 160.18543 | AL24: 144.60929 | AM24: 134.44888 | AN24: 190.28365 | AO24: 302.69288 | AP24: 188.0138 | AQ24: 202.61757 | AR24: 254.05564 | AS24: 350.88806 | AT24: 434.72737 | AU24: 469.38266
D25: Exports | E25: Imports | G25: =SUMIF($I$9:$AU$9,G$10,$I25:$AU25)*$G$3*$B$5 -> 1947.8582 | H25: Debit | I25: 0 | J25: 0 | K25: 0 | L25: 0 | M25: 0 | N25: 0 | O25: 0 | P25: 0 | Q25: 0 | R25: 0 | S25: 0 | T25: 0 | U25: 0 | V25: 0 | W25: 0 | X25: 0 | Y25: 0 | Z25: 111.39831 | AA25: 127.94891 | AB25: 107.49706 | AC25: 157.19213 | AD25: 285.39407 | AE25: 120.60267 | AF25: 60.200551 | AG25: 94.949472 | AH25: 98.508874 | AI25: 114.64647 | AJ25: 118.44342 | AK25: 161.83278 | AL25: 154.448 | AM25: 75.249611 | AN25: 207.3132 | AO25: 308.96261 | AP25: 210.85801 | AQ25: 202.25434 | AR25: 275.98672 | AS25: 326.74436 | AT25: 479.08065 | AU25: 396.07767
B26: Services | D26: =wBOP!G27 -> 1424.7745 | E26: =wBOP!G28 -> 1305.9994 | G26: =SUMIF($I$9:$AU$9,G$10,$I26:$AU26)*$G$3*$B$5 -> 118.77502 | H26: Services | I26: -154.40501 | J26: -119.88218 | K26: 19.882714 | L26: -3.8700177 | M26: -56.673531 | N26: -253.10725 | O26: -245.45603 | P26: -37.748435 | Q26: -33.127954 | R26: -76.514467 | S26: -45.396907 | T26: -78.660303 | U26: -32.93001 | V26: 4.7066394 | W26: -36.719411 | X26: -32.324875 | Y26: -2.6004335 | Z26: 0.29769607 | AA26: 17.185654 | AB26: -37.263447 | AC26: -11.04255 | AD26: 12.128776 | AE26: 39.454602 | AF26: -2.2439592 | AG26: -28.615996 | AH26: -71.69206 | AI26: -21.882389 | AJ26: -42.342602 | AK26: 14.007708 | AL26: 56.300363 | AM26: -24.42256 | AN26: 5.7010624 | AO26: -14.397216 | AP26: 80.28002 | AQ26: 29.355652 | AR26: 4.4889172 | AS26: 3.0314043 | AT26: 68.301364 | AU26: 14.295933
B27: Manufacturing services on physical inputs owned by others | D27: =wBOP!G30 -> 0.3357411 | E27: =wBOP!G31 -> 0.017361758 | G27: =SUMIF($I$9:$AU$9,G$10,$I27:$AU27)*$G$3*$B$5 -> 1424.7745 | H27: Credit | I27: 405.45316 | J27: 489.0529 | K27: 529.63038 | L27: 595.82191 | M27: 605.18705 | N27: 766.9803 | O27: 790.03502 | P27: 201.47928 | Q27: 211.43564 | R27: 213.50241 | S27: 237.02287 | T27: 187.66126 | U27: 204.98734 | V27: 288.52728 | W27: 232.45459 | X27: 225.38008 | Y27: 224.84515 | Z27: 291.43725 | AA27: 273.31059 | AB27: 180.86229 | AC27: 76.872609 | AD27: 132.6651 | AE27: 143.7273 | AF27: 133.10165 | AG27: 131.82325 | AH27: 144.77732 | AI27: 166.64506 | AJ27: 161.26911 | AK27: 222.77394 | AL27: 256.95118 | AM27: 240.20641 | AN27: 225.45514 | AO27: 214.12862 | AP27: 317.19558 | AQ27: 287.96002 | AR27: 223.66703 | AS27: 241.09964 | AT27: 346.56523 | AU27: 269.6806
B28: Maintenance and repair services n.i.e. | D28: =wBOP!G33 -> -30.689103 | E28: =wBOP!G34 -> 0.099842926 | G28: =SUMIF($I$9:$AU$9,G$10,$I28:$AU28)*$G$3*$B$5 -> 1305.9994 | H28: Debit | I28: 559.85817 | J28: 608.93507 | K28: 509.74766 | L28: 599.69192 | M28: 661.86058 | N28: 1020.0875 | O28: 1035.4911 | P28: 239.22772 | Q28: 244.56359 | R28: 290.01688 | S28: 282.41977 | T28: 266.32157 | U28: 237.91735 | V28: 283.82064 | W28: 269.17401 | X28: 257.70495 | Y28: 227.44559 | Z28: 291.13955 | AA28: 256.12494 | AB28: 218.12574 | AC28: 87.915159 | AD28: 120.53632 | AE28: 104.27269 | AF28: 135.34561 | AG28: 160.43924 | AH28: 216.46938 | AI28: 188.52745 | AJ28: 203.61171 | AK28: 208.76623 | AL28: 200.65081 | AM28: 264.62897 | AN28: 219.75408 | AO28: 228.52583 | AP28: 236.91556 | AQ28: 258.60436 | AR28: 219.17811 | AS28: 238.06824 | AT28: 278.26386 | AU28: 255.38467
B29: Transport | D29: =wBOP!G36 -> 261.50866 | E29: =wBOP!G37 -> 612.32363 | G29: =SUMIF($I$9:$AU$9,G$10,$I29:$AU29)*$G$3*$B$5 -> 0 | H29: Manufacturing services on physical inputs owned by others | I29: 0 | J29: 0 | K29: 0 | L29: 0 | M29: 0 | N29: 0 | O29: 0 | P29: 0 | Q29: 0 | R29: 0 | S29: 0 | T29: 0 | U29: 0 | V29: 0 | W29: 0 | X29: 0 | Y29: 0 | Z29: 0 | AA29: 0 | AB29: 0 | AC29: 0 | AD29: 0 | AE29: 0 | AF29: 0 | AG29: 0 | AH29: 0 | AI29: 0 | AJ29: 0 | AK29: 0 | AL29: 0 | AM29: 0 | AN29: 0 | AO29: 0 | AP29: 0 | AQ29: 0 | AR29: 0 | AS29: 0 | AT29: 0 | AU29: 0
B30: Sea transport | D30: =wBOP!G39 -> 0 | E30: =wBOP!G40 -> 215.30193 | G30: =SUMIF($I$9:$AU$9,G$10,$I30:$AU30)*$G$3*$B$5 -> 0.3357411 | H30: Credit | I30: 0 | J30: 0 | K30: 0 | L30: 0 | M30: 0 | N30: 0 | O30: 0 | P30: 0 | Q30: 0 | R30: 0 | S30: 0 | T30: 0 | U30: 0 | V30: 0 | W30: 0 | X30: 0 | Y30: 0 | Z30: 0 | AA30: 0 | AB30: 0 | AC30: 0 | AD30: 0 | AE30: 0 | AF30: 0 | AG30: 0 | AH30: 0 | AI30: 0 | AJ30: 0 | AK30: 0 | AL30: 0 | AM30: 0 | AN30: 0.06156 | AO30: 0.06156 | AP30: 0.06156 | AQ30: 0.06156 | AR30: 0.06759288 | AS30: 0.0640224 | AT30: 0.06156 | AU30: 0.06156
B31: Air transport | D31: =wBOP!G42 -> 245.40965 | E31: =wBOP!G43 -> 102.28122 | G31: =SUMIF($I$9:$AU$9,G$10,$I31:$AU31)*$G$3*$B$5 -> 0.017361758 | H31: Debit | I31: 0 | J31: 0 | K31: 0 | L31: 0 | M31: 0 | N31: 0 | O31: 0 | P31: 0 | Q31: 0 | R31: 0 | S31: 0 | T31: 0 | U31: 0 | V31: 0 | W31: 0 | X31: 0 | Y31: 0 | Z31: 0 | AA31: 0 | AB31: 0 | AC31: 0 | AD31: 0 | AE31: 0 | AF31: 0 | AG31: 0 | AH31: 0 | AI31: 0 | AJ31: 0 | AK31: 0 | AL31: 0 | AM31: 0 | AN31: 0.003183375 | AO31: 0.003183375 | AP31: 0.003183375 | AQ31: 0.003183375 | AR31: 0.0034953458 | AS31: 0.00331071 | AT31: 0.003183375 | AU31: 0.003183375
B32: Other modes of transport | D32: =wBOP!G45 -> 14.432642 | E32: =wBOP!G46 -> 294.45798 | G32: =SUMIF($I$9:$AU$9,G$10,$I32:$AU32)*$G$3*$B$5 -> 0 | H32: Maintenance and repair services n.i.e. | I32: 0 | J32: 0 | K32: 0 | L32: 0 | M32: 0 | N32: -12.376151 | O32: -24.635076 | P32: -9.144444 | Q32: -9.2750654 | R32: -9.5080719 | S32: -8.4887632 | T32: -8.4083187 | U32: -7.5346927 | V32: -8.1860508 | W32: -8.5717558 | X32: -11.519126 | Y32: -9.7815265 | Z32: -9.7371034 | AA32: -10.192696 | AB32: -10.308657 | AC32: -0.98345506 | AD32: -3.6159952 | AE32: -4.1733709 | AF32: -3.5722069 | AG32: -3.057248 | AH32: -2.6161325 | AI32: -2.668834 | AJ32: -5.798717 | AK32: -6.0488762 | AL32: -6.3522669 | AM32: -6.6708272 | AN32: -8.1425756 | AO32: -3.7086799 | AP32: -4.3358387 | AQ32: -4.6967105 | AR32: 0 | AS32: 0 | AT32: 0 | AU32: 0
B33: Postal and courier services | D33: =wBOP!G48 -> 1.6663697 | E33: =wBOP!G49 -> 0.28249078 | G33: =SUMIF($I$9:$AU$9,G$10,$I33:$AU33)*$G$3*$B$5 -> -30.689103 | H33: Credit | I33: 0 | J33: 0 | K33: 0 | L33: 0 | M33: 0 | N33: 0.52744227 | O33: 0.082016011 | P33: 0.1118624 | Q33: 0.14260908 | R33: 0.16422982 | S33: 0.16495421 | T33: 0.024672342 | U33: 0.022420899 | V33: 0.016440196 | W33: 0.013779399 | X33: 0.023112864 | Y33: 0.018938339 | Z33: 0.018938339 | AA33: 0.018938339 | AB33: 0.018938339 | AC33: 0.018938339 | AD33: 0.018938339 | AE33: 0.018938339 | AF33: 0.018938339 | AG33: 0.018938339 | AH33: 0.018938339 | AI33: 0.018938339 | AJ33: 0.018938339 | AK33: 0.018938339 | AL33: 0.018938339 | AM33: 0.018938339 | AN33: 0.018938339 | AO33: 0.018938339 | AP33: 0.018938339 | AQ33: 0.018938339 | AR33: -5.0457491 | AS33: -4.3312014 | AT33: -6.7682543 | AU33: -7.1393952
B34: Travel | D34: =wBOP!G51 -> 763.73076 | E34: =wBOP!G52 -> 479.51598 | G34: =SUMIF($I$9:$AU$9,G$10,$I34:$AU34)*$G$3*$B$5 -> 0.099842926 | H34: Debit | I34: 0 | J34: 0 | K34: 0 | L34: 0 | M34: 0 | N34: 12.903593 | O34: 24.717092 | P34: 9.2563064 | Q34: 9.4176745 | R34: 9.6723017 | S34: 8.6537174 | T34: 8.432991 | U34: 7.5571136 | V34: 8.202491 | W34: 8.5855352 | X34: 11.542239 | Y34: 9.8004648 | Z34: 9.7560418 | AA34: 10.211634 | AB34: 10.327595 | AC34: 1.0023934 | AD34: 3.6349335 | AE34: 4.1923092 | AF34: 3.5911453 | AG34: 3.0761863 | AH34: 2.6350709 | AI34: 2.6877723 | AJ34: 5.8176553 | AK34: 6.0678145 | AL34: 6.3712052 | AM34: 6.6897655 | AN34: 8.1615139 | AO34: 3.7276183 | AP34: 4.354777 | AQ34: 4.7156488 | AR34: 0.018938339 | AS34: 0.018938339 | AT34: 0.018938339 | AU34: 0.018938339
B35: Business | D35: =wBOP!G54 -> 127.36143 | E35: =wBOP!G55 -> 168.61018 | G35: =SUMIF($I$9:$AU$9,G$10,$I35:$AU35)*$G$3*$B$5 -> -350.81497 | H35: Transport | I35: -321.36418 | J35: -355.02356 | K35: -265.03834 | L35: -309.2022 | M35: -331.49805 | N35: -336.62384 | O35: -345.26668 | P35: -75.424209 | Q35: -79.710236 | R35: -84.770834 | S35: -83.720421 | T35: -76.235262 | U35: -83.671166 | V35: -68.56116 | W35: -78.512648 | X35: -60.446567 | Y35: -69.590008 | Z35: -54.048792 | AA35: -54.362981 | AB35: -49.120674 | AC35: -48.684384 | AD35: -54.415782 | AE35: -13.815453 | AF35: -33.122414 | AG35: -57.051459 | AH35: -41.14795 | AI35: -55.793897 | AJ35: -55.553928 | AK35: -45.846707 | AL35: -38.412087 | AM35: -84.389365 | AN35: -74.411748 | AO35: -65.810595 | AP35: -43.665948 | AQ35: -54.710315 | AR35: -57.857405 | AS35: -77.78264 | AT35: -71.123501 | AU35: -59.408662
B36: Personal | D36: =wBOP!G57 -> 636.36932 | E36: =wBOP!G58 -> 310.9058 | G36: =SUMIF($I$9:$AU$9,G$10,$I36:$AU36)*$G$3*$B$5 -> 261.50866 | H36: Credit | I36: 29.435849 | J36: 50.718673 | K36: 59.896642 | L36: 75.242378 | M36: 78.078499 | N36: 103.50848 | O36: 98.420414 | P36: 29.18784 | Q36: 33.609928 | R36: 40.298309 | S36: 38.296199 | T36: 37.541296 | U36: 40.489556 | V36: 53.260694 | W36: 52.962392 | X36: 42.866769 | Y36: 46.421673 | Z36: 62.785191 | AA36: 60.770615 | AB36: 53.158299 | AC36: 5.0605103 | AD36: 18.075161 | AE36: 43.955106 | AF36: 38.215646 | AG36: 30.932799 | AH36: 33.045286 | AI36: 43.876708 | AJ36: 50.614536 | AK36: 57.413913 | AL36: 58.306948 | AM36: 68.398174 | AN36: 37.282666 | AO36: 38.580565 | AP36: 42.341057 | AQ36: 50.283982 | AR36: 38.536366 | AS36: 38.726163 | AT36: 59.454427 | AU36: 61.696291
B37: Construction | D37: =wBOP!G60 -> 4.8113449 | E37: =wBOP!G61 -> 0 | G37: =SUMIF($I$9:$AU$9,G$10,$I37:$AU37)*$G$3*$B$5 -> 612.32363 | H37: Debit | I37: 350.80003 | J37: 405.74224 | K37: 324.93498 | L37: 384.44458 | M37: 409.57655 | N37: 440.13232 | O37: 443.68709 | P37: 104.61205 | Q37: 113.32016 | R37: 125.06914 | S37: 122.01662 | T37: 113.77656 | U37: 124.16072 | V37: 121.82185 | W37: 131.47504 | X37: 103.31334 | Y37: 116.01168 | Z37: 116.83398 | AA37: 115.1336 | AB37: 102.27897 | AC37: 53.744895 | AD37: 72.490944 | AE37: 57.770559 | AF37: 71.33806 | AG37: 87.984258 | AH37: 74.193236 | AI37: 99.670606 | AJ37: 106.16846 | AK37: 103.26062 | AL37: 96.719036 | AM37: 152.78754 | AN37: 111.69441 | AO37: 104.39116 | AP37: 86.007004 | AQ37: 104.9943 | AR37: 96.393771 | AS37: 116.5088 | AT37: 130.57793 | AU37: 121.10495
B38: Insurance and pension services | D38: =wBOP!G63 -> 1.2953276 | E38: =wBOP!G64 -> 31.400042 | G38: =SUMIF($I$9:$AU$9,G$10,$I38:$AU38)*$G$3*$B$5 -> -215.30193 | H38: Sea transport | I38: -107.47086 | J38: -135.06562 | K38: -102.17333 | L38: -102.38063 | M38: -100.65246 | N38: -133.49028 | O38: -121.43013 | P38: -28.821733 | Q38: -30.597765 | R38: -34.012342 | S38: -31.529939 | T38: -31.886763 | U38: -36.964839 | V38: -36.582526 | W38: -39.852443 | X38: -26.388082 | Y38: -28.071574 | Z38: -30.640515 | AA38: -30.542636 | AB38: -28.439295 | AC38: -20.441232 | AD38: -22.616075 | AE38: -17.579552 | AF38: -17.240037 | AG38: -35.030416 | AH38: -24.478726 | AI38: -33.811995 | AJ38: -36.736709 | AK38: -34.607392 | AL38: -32.478076 | AM38: -56.459758 | AN38: -37.998325 | AO38: -34.455207 | AP38: -27.772107 | AQ38: -35.686068 | AR38: -33.539637 | AS38: -40.890951 | AT38: -46.305151 | AU38: -42.619291
B39: Financial services | D39: =wBOP!G66 -> 0.61623705 | E39: =wBOP!G67 -> 14.208739 | G39: =SUMIF($I$9:$AU$9,G$10,$I39:$AU39)*$G$3*$B$5 -> 0 | H39: Credit | I39: 0 | J39: 0 | K39: 0 | L39: 0 | M39: 0 | N39: 0 | O39: 0 | P39: 0 | Q39: 0 | R39: 0 | S39: 0 | T39: 0 | U39: 0 | V39: 0 | W39: 0 | X39: 0 | Y39: 0 | Z39: 0 | AA39: 0 | AB39: 0 | AC39: 0 | AD39: 0 | AE39: 0 | AF39: 0 | AG39: 0 | AH39: 0 | AI39: 0 | AJ39: 0 | AK39: 0 | AL39: 0 | AM39: 0 | AN39: 0 | AO39: 0 | AP39: 0 | AQ39: 0 | AR39: 0 | AS39: 0 | AT39: 0 | AU39: 0
B40: Charges for the use of intellectual property n.i.e. | D40: =wBOP!G69 -> 0.89231225 | E40: =wBOP!G70 -> 0.39173856 | G40: =SUMIF($I$9:$AU$9,G$10,$I40:$AU40)*$G$3*$B$5 -> 215.30193 | H40: Debit | I40: 107.47086 | J40: 135.06562 | K40: 102.17333 | L40: 102.38063 | M40: 100.65246 | N40: 133.49028 | O40: 121.43013 | P40: 28.821733 | Q40: 30.597765 | R40: 34.012342 | S40: 31.529939 | T40: 31.886763 | U40: 36.964839 | V40: 36.582526 | W40: 39.852443 | X40: 26.388082 | Y40: 28.071574 | Z40: 30.640515 | AA40: 30.542636 | AB40: 28.439295 | AC40: 20.441232 | AD40: 22.616075 | AE40: 17.579552 | AF40: 17.240037 | AG40: 35.030416 | AH40: 24.478726 | AI40: 33.811995 | AJ40: 36.736709 | AK40: 34.607392 | AL40: 32.478076 | AM40: 56.459758 | AN40: 37.998325 | AO40: 34.455207 | AP40: 27.772107 | AQ40: 35.686068 | AR40: 33.539637 | AS40: 40.890951 | AT40: 46.305151 | AU40: 42.619291
B41: Telecommunications, computer, and information services | D41: =wBOP!G72 -> 45.407647 | E41: =wBOP!G73 -> 32.215694 | G41: =SUMIF($I$9:$AU$9,G$10,$I41:$AU41)*$G$3*$B$5 -> 143.12842 | H41: Air transport | I41: -60.592229 | J41: -41.680058 | K41: -25.139549 | L41: -69.555734 | M41: -94.976437 | N41: -26.24975 | O41: -63.142972 | P41: -8.6399582 | Q41: -8.9476748 | R41: -5.8410515 | S41: -10.35122 | T41: -1.5586974 | U41: 1.8961618 | V41: 16.60664 | W41: 14.051583 | X41: 11.417649 | Y41: 13.255194 | Z41: 28.781475 | AA41: 28.653341 | AB41: 16.418543 | AC41: -3.406535 | AD41: -1.8007926 | AE41: 29.283409 | AF41: 17.656035 | AG41: 10.115763 | AH41: 16.38535 | AI41: 22.659742 | AJ41: 29.389063 | AK41: 34.731239 | AL41: 37.156666 | AM41: 44.691376 | AN41: 13.088639 | AO41: 14.231202 | AP41: 21.120703 | AQ41: 27.773586 | AR41: 19.803979 | AS41: 16.584266 | AT41: 34.543817 | AU41: 37.663101
B42: Other business services | D42: =wBOP!G75 -> 5.5616548 | E42: =wBOP!G76 -> 26.972858 | G42: =SUMIF($I$9:$AU$9,G$10,$I42:$AU42)*$G$3*$B$5 -> 245.40965 | H42: Credit | I42: 22.872197 | J42: 45.452271 | K42: 54.080403 | L42: 68.3796 | M42: 70.952393 | N42: 94.255962 | O42: 87.312896 | P42: 26.12997 | Q42: 30.552058 | R42: 37.503146 | S42: 35.501035 | T42: 34.325759 | U42: 37.203689 | V42: 50.138568 | W42: 49.912081 | X42: 39.38571 | Y42: 42.867651 | Z42: 58.410323 | AA42: 57.136587 | AB42: 49.450068 | AC42: 3.9933072 | AD42: 16.389829 | AE42: 42.977347 | AF42: 37.100003 | AG42: 29.795357 | AH42: 31.271897 | AI42: 42.03105 | AJ42: 48.792928 | AK42: 55.325251 | AL42: 56.041386 | AM42: 65.940488 | AN42: 35.111101 | AO42: 36.364122 | AP42: 40.154501 | AQ42: 47.956278 | AR42: 36.068439 | AS42: 35.862979 | AT42: 56.227422 | AU42: 58.039678
B43: Personal, cultural, and recreational services | D43: =wBOP!G78 -> 0 | E43: =wBOP!G79 -> 8.4713609 | G43: =SUMIF($I$9:$AU$9,G$10,$I43:$AU43)*$G$3*$B$5 -> 102.28122 | H43: Debit | I43: 83.464425 | J43: 87.132329 | K43: 79.219952 | L43: 137.93533 | M43: 165.92883 | N43: 120.50571 | O43: 150.45587 | P43: 34.769928 | Q43: 39.499733 | R43: 43.344198 | S43: 45.852255 | T43: 35.884456 | U43: 35.307527 | V43: 33.531927 | W43: 35.860498 | X43: 27.968062 | Y43: 29.612457 | Z43: 29.628849 | AA43: 28.483247 | AB43: 33.031525 | AC43: 7.3998422 | AD43: 18.190622 | AE43: 13.693938 | AF43: 19.443967 | AG43: 19.679594 | AH43: 14.886547 | AI43: 19.371307 | AJ43: 19.403866 | AK43: 20.594012 | AL43: 18.88472 | AM43: 21.249112 | AN43: 22.022462 | AO43: 22.13292 | AP43: 19.033799 | AQ43: 20.182691 | AR43: 16.26446 | AS43: 19.278713 | AT43: 21.683605 | AU43: 20.376577
B44: Government goods and services n.i.e. | D44: =wBOP!G81 -> 294.83096 | E44: =wBOP!G82 -> 33.977157 | G44: =SUMIF($I$9:$AU$9,G$10,$I44:$AU44)*$G$3*$B$5 -> -280.02534 | H44: Other modes of transport | I44: -142.35712 | J44: -178.56877 | K44: -137.69071 | L44: -137.44412 | M44: -136.04743 | N44: -177.2881 | O44: -164.82719 | P44: -39.050309 | Q44: -41.252589 | R44: -45.700304 | S44: -42.622124 | T44: -43.883845 | U44: -49.717644 | V44: -49.364233 | W44: -53.490747 | X44: -46.689099 | Y44: -56.009508 | Z44: -53.059102 | AA44: -53.343036 | AB44: -38.146807 | AC44: -24.937155 | AD44: -29.654502 | AE44: -25.292117 | AF44: -33.31122 | AG44: -31.864176 | AH44: -32.75468 | AI44: -44.296766 | AJ44: -47.940754 | AK44: -45.637002 | AL44: -42.660292 | AM44: -72.190266 | AN44: -49.17722 | AO44: -45.26426 | AP44: -36.752199 | AQ44: -46.503077 | AR44: -44.356037 | AS44: -53.722639 | AT44: -59.646737 | AU44: -54.736909
G45: =SUMIF($I$9:$AU$9,G$10,$I45:$AU45)*$G$3*$B$5 -> 14.432642 | H45: Credit | I45: 3.5736523 | J45: 4.4451998 | K45: 4.7609206 | L45: 5.8014955 | M45: 6.0648235 | N45: 6.2667587 | O45: 6.1457173 | P45: 1.7521328 | Q45: 1.7521328 | R45: 1.62 | S45: 1.62 | T45: 1.8546776 | U45: 1.9210659 | V45: 1.8938057 | W45: 1.8219896 | X45: 1.9795916 | Y45: 2.0482081 | Z45: 3.0196341 | AA45: 2.2787943 | AB45: 2.2787943 | AC45: 0.9260601 | AD45: 1.5783057 | AE45: 0.90193862 | AF45: 1.0398223 | AG45: 1.0464563 | AH45: 1.673305 | AI45: 1.730562 | AJ45: 1.7329936 | AK45: 1.9773457 | AL45: 2.1219297 | AM45: 2.3139431 | AN45: 2.4513584 | AO45: 2.49083 | AP45: 2.3930347 | AQ45: 2.5653332 | AR45: 2.1858117 | AS45: 2.566143 | AT45: 2.8843447 | AU45: 3.314112
G46: =SUMIF($I$9:$AU$9,G$10,$I46:$AU46)*$G$3*$B$5 -> 294.45798 | H46: Debit | I46: 145.93077 | J46: 183.01396 | K46: 142.45163 | L46: 143.24562 | M46: 142.11225 | N46: 183.55486 | O46: 170.97291 | P46: 40.802442 | Q46: 43.004722 | R46: 47.320304 | S46: 44.242124 | T46: 45.738523 | U46: 51.63871 | V46: 51.258038 | W46: 55.312736 | X46: 48.66869 | Y46: 58.057716 | Z46: 56.078736 | AA46: 55.62183 | AB46: 40.425602 | AC46: 25.863215 | AD46: 31.232807 | AE46: 26.194056 | AF46: 34.351043 | AG46: 32.910632 | AH46: 34.427985 | AI46: 46.027328 | AJ46: 49.673747 | AK46: 47.614347 | AL46: 44.782222 | AM46: 74.504209 | AN46: 51.628578 | AO46: 47.75509 | AP46: 39.145234 | AQ46: 49.06841 | AR46: 46.541849 | AS46: 56.288782 | AT46: 62.531082 | AU46: 58.051021
G47: =SUMIF($I$9:$AU$9,G$10,$I47:$AU47)*$G$3*$B$5 -> 1.3838789 | H47: Postal and courier services | I47: -10.943973 | J47: 0.29087723 | K47: -0.034752233 | L47: 0.1782815 | M47: 0.1782815 | N47: 0.40428626 | O47: 4.1336099 | P47: 1.0877921 | Q47: 1.0877921 | R47: 0.78286245 | S47: 0.78286245 | T47: 1.0940428 | U47: 1.115155 | V47: 0.77895829 | W47: 0.77895829 | X47: 1.2129647 | Y47: 1.2358796 | Z47: 0.86935004 | AA47: 0.86935004 | AB47: 1.0468861 | AC47: 0.10053664 | AD47: -0.34441293 | AE47: -0.22719248 | AF47: -0.22719248 | AG47: -0.27263098 | AH47: -0.29989407 | AI47: -0.34487819 | AJ47: -0.26552792 | AK47: -0.33355229 | AL47: -0.43038573 | AM47: -0.43071699 | AN47: -0.34563453 | AO47: -0.36782405 | AP47: -0.4286082 | AQ47: -0.43828971 | AR47: 0.2342898 | AS47: 0.24668499 | AT47: 0.28457125 | AU47: 0.284438
G48: =SUMIF($I$9:$AU$9,G$10,$I48:$AU48)*$G$3*$B$5 -> 1.6663697 | H48: Credit | I48: 2.99 | J48: 0.82120203 | K48: 1.0553189 | L48: 1.0612829 | M48: 1.0612829 | N48: 2.9857559 | O48: 4.9618006 | P48: 1.305737 | Q48: 1.305737 | R48: 1.1751633 | S48: 1.1751633 | T48: 1.36086 | U48: 1.3648007 | V48: 1.2283206 | W48: 1.2283206 | X48: 1.5014668 | Y48: 1.5058147 | Z48: 1.3552332 | AA48: 1.3552332 | AB48: 1.429437 | AC48: 0.14114295 | AD48: 0.10702616 | AE48: 0.075820983 | AF48: 0.075820983 | AG48: 0.09098518 | AH48: 0.1000837 | AI48: 0.11509625 | AJ48: 0.088614676 | AK48: 0.11131646 | AL48: 0.1436327 | AM48: 0.14374325 | AN48: 0.11534867 | AO48: 0.12275398 | AP48: 0.14303949 | AQ48: 0.1462705 | AR48: 0.2821153 | AS48: 0.29704072 | AT48: 0.34266069 | AU48: 0.34250024
G49: =SUMIF($I$9:$AU$9,G$10,$I49:$AU49)*$G$3*$B$5 -> 0.28249078 | H49: Debit | I49: 13.933973 | J49: 0.5303248 | K49: 1.0900712 | L49: 0.88300139 | M49: 0.88300139 | N49: 2.5814697 | O49: 0.82819068 | P49: 0.21794491 | Q49: 0.21794491 | R49: 0.39230085 | S49: 0.39230085 | T49: 0.26681714 | U49: 0.24964574 | V49: 0.44936234 | W49: 0.44936234 | X49: 0.28850207 | Y49: 0.26993511 | Z49: 0.48588319 | AA49: 0.48588319 | AB49: 0.38255089 | AC49: 0.04060631 | AD49: 0.45143909 | AE49: 0.30301346 | AF49: 0.30301346 | AG49: 0.36361616 | AH49: 0.39997777 | AI49: 0.45997444 | AJ49: 0.3541426 | AK49: 0.44486875 | AL49: 0.57401843 | AM49: 0.57446024 | AN49: 0.4609832 | AO49: 0.49057803 | AP49: 0.57164769 | AQ49: 0.5845602 | AR49: 0.047825503 | AS49: 0.050355729 | AT49: 0.05808944 | AU49: 0.05806224
G50: =SUMIF($I$9:$AU$9,G$10,$I50:$AU50)*$G$3*$B$5 -> 284.21478 | H50: Travel | I50: 124.63889 | J50: 162.61 | K50: 203.22696 | L50: 214.53653 | M50: 219.87447 | N50: 29.851772 | O50: 41.906061 | P50: 7.7839187 | Q50: 16.415857 | R50: 7.6979704 | S50: -21.605064 | T50: -10.32866 | U50: 23.087226 | V50: 13.258746 | W50: 20.816817 | X50: 8.8028568 | Y50: 51.219491 | Z50: 33.827554 | AA50: 28.036365 | AB50: 22.180856 | AC50: -3.141225 | AD50: -8.3186834 | AE50: 7.5500047 | AF50: -9.2818853 | AG50: -10.764355 | AH50: -21.135579 | AI50: 1.873875 | AJ50: -2.1063655 | AK50: 36.46639 | AL50: 63.393091 | AM50: 30.844524 | AN50: 45.695373 | AO50: 43.45776 | AP50: 78.688085 | AQ50: 40.221962 | AR50: 39.821379 | AS50: 53.687755 | AT50: 87.119183 | AU50: 35.012639
G51: =SUMIF($I$9:$AU$9,G$10,$I51:$AU51)*$G$3*$B$5 -> 763.73076 | H51: Credit | I51: 201.64867 | J51: 251.8 | K51: 281.8 | L51: 293.6 | M51: 303.7 | N51: 338.06717 | O51: 363.04845 | P51: 92.625042 | Q51: 99.727521 | R51: 109.56029 | S51: 79.160984 | T51: 88.919855 | U51: 89.950887 | V51: 112.887 | W51: 100.24226 | X51: 98.749969 | Y51: 113.55146 | Z51: 138.59504 | AA51: 107.10353 | AB51: 84.463157 | AC51: 0.96934725 | AD51: 8.4662386 | AE51: 25.923694 | AF51: 22.652731 | AG51: 30.508093 | AH51: 44.158033 | AI51: 52.577731 | AJ51: 56.460645 | AK51: 101.57328 | AL51: 134.28916 | AM51: 107.92378 | AN51: 114.69537 | AO51: 121.45776 | AP51: 178.68809 | AQ51: 149.03497 | AR51: 125.49896 | AS51: 136.78776 | AT51: 191.11356 | AU51: 126.06161
G52: =SUMIF($I$9:$AU$9,G$10,$I52:$AU52)*$G$3*$B$5 -> 479.51598 | H52: Debit | I52: 77.009785 | J52: 89.19 | K52: 78.573037 | L52: 79.06347 | M52: 83.825526 | N52: 308.21539 | O52: 321.14238 | P52: 84.841123 | Q52: 83.311663 | R52: 101.86232 | S52: 100.76605 | T52: 99.248515 | U52: 66.863661 | V52: 99.628257 | W52: 79.425438 | X52: 89.947113 | Y52: 62.331969 | Z52: 104.76748 | AA52: 79.067168 | AB52: 62.282302 | AC52: 4.1105723 | AD52: 16.784922 | AE52: 18.373689 | AF52: 31.934617 | AG52: 41.272448 | AH52: 65.293612 | AI52: 50.703856 | AJ52: 58.567011 | AK52: 65.106891 | AL52: 70.89607 | AM52: 77.079257 | AN52: 69 | AO52: 78 | AP52: 100 | AQ52: 108.81301 | AR52: 85.677577 | AS52: 83.1 | AT52: 103.99437 | AU52: 91.048972
G53: =SUMIF($I$9:$AU$9,G$10,$I53:$AU53)*$G$3*$B$5 -> -41.248746 | H53: Business | I53: 42.857265 | J53: 54.839743 | K53: 64.446452 | L53: 57.192079 | M53: 50.522139 | N53: -9.664058 | O53: -18.212682 | P53: -1.7867599 | Q53: -8.7404969 | R53: -10.556466 | S53: -1.4334277 | T53: -1.5171735 | U53: 5.7696025 | V53: 7.3726974 | W53: 5.9678881 | X53: -0.41328101 | Y53: 7.0182208 | Z53: 4.5389773 | AA53: 3.0655282 | AB53: -4.0287198 | AC53: 0 | AD53: 0.20785496 | AE53: 0.70046974 | AF53: -9.6318458 | AG53: -8.9298896 | AH53: -14.693124 | AI53: -14.436436 | AJ53: -26.288531 | AK53: 10.075225 | AL53: -5.3270231 | AM53: -10.409046 | AN53: -13.780103 | AO53: -13.557206 | AP53: -17.113994 | AQ53: -12.968825 | AR53: -10.357173 | AS53: 0.31743265 | AT53: -2.7718441 | AU53: -18.484885
G54: =SUMIF($I$9:$AU$9,G$10,$I54:$AU54)*$G$3*$B$5 -> 127.36143 | H54: Credit | I54: 82.8 | J54: 101.1 | K54: 105.2 | L54: 98.2 | M54: 94 | N54: 104.66521 | O54: 132.65168 | P54: 31.704169 | Q54: 32.29151 | R54: 27.157462 | S54: 31.640414 | T54: 31.115512 | U54: 31.727426 | V54: 34.499923 | W54: 38.027392 | X54: 36.244932 | Y54: 30.725134 | Z54: 35.127471 | AA54: 30.811979 | AB54: 18.284933 | AC54: 0 | AD54: 3.693781 | AE54: 7.0405024 | AF54: 6.6702476 | AG54: 13.011273 | AH54: 14.609024 | AI54: 14.988985 | AJ54: 14.610659 | AK54: 45.036214 | AL54: 32.745494 | AM54: 30.991009 | AN54: 29.219897 | AO54: 33.442794 | AP54: 38.886006 | AQ54: 34.379319 | AR54: 19.708345 | AS54: 28.717433 | AT54: 30.420008 | AU54: 17.78656
G55: =SUMIF($I$9:$AU$9,G$10,$I55:$AU55)*$G$3*$B$5 -> 168.61018 | H55: Debit | I55: 39.942735 | J55: 46.260257 | K55: 40.753548 | L55: 41.007921 | M55: 43.477861 | N55: 114.32927 | O55: 150.86436 | P55: 33.490929 | Q55: 41.032007 | R55: 37.713928 | S55: 33.073842 | T55: 32.632686 | U55: 25.957824 | V55: 27.127226 | W55: 32.059504 | X55: 36.658213 | Y55: 23.706913 | Z55: 30.588494 | AA55: 27.74645 | AB55: 22.313652 | AC55: 0 | AD55: 3.485926 | AE55: 6.3400327 | AF55: 16.302093 | AG55: 21.941162 | AH55: 29.302148 | AI55: 29.425421 | AJ55: 40.89919 | AK55: 34.960989 | AL55: 38.072517 | AM55: 41.400055 | AN55: 43 | AO55: 47 | AP55: 56 | AQ55: 47.348144 | AR55: 30.065518 | AS55: 28.4 | AT55: 33.191852 | AU55: 36.271445
G56: =SUMIF($I$9:$AU$9,G$10,$I56:$AU56)*$G$3*$B$5 -> 325.46353 | H56: Personal | I56: 81.781624 | J56: 107.77026 | K56: 138.78051 | L56: 157.34445 | M56: 169.35233 | N56: 39.51583 | O56: 60.118744 | P56: 9.5706786 | Q56: 25.156354 | R56: 18.254436 | S56: -20.171636 | T56: -8.8114864 | U56: 17.317624 | V56: 5.8860483 | W56: 14.848929 | X56: 9.2161378 | Y56: 44.20127 | Z56: 29.288577 | AA56: 24.970837 | AB56: 26.209575 | AC56: -3.141225 | AD56: -8.5265384 | AE56: 6.849535 | AF56: 0.3499605 | AG56: -1.8344656 | AH56: -6.4424551 | AI56: 16.310311 | AJ56: 24.182165 | AK56: 26.391165 | AL56: 68.720114 | AM56: 41.253571 | AN56: 59.475477 | AO56: 57.014966 | AP56: 95.802079 | AQ56: 53.190787 | AR56: 50.178552 | AS56: 53.370322 | AT56: 89.891027 | AU56: 53.497524
... G152: =SUMIF($I$9:$AU$9,G$10,$I152:$AU152)*$G$3*$B$5 -> -1877.5159 | H152: Net lending (+) / net borrowing (-) (balance from current and capital account) | I152: -113.50705 | J152: -280.34581 | K152: -569.79096 | L152: -350.5883 | M152: -597.56907 | N152: -783.77149 | O152: -1140.8224 | P152: -183.53633 | Q152: -141.29793 | R152: -202.2338 | S152: -144.73589 | T152: -230.97467 | U152: -175.85144 | V152: -129.77277 | W152: -198.40445 | X152: -215.54323 | Y152: -297.3171 | Z152: -272.15947 | AA152: -208.49655 | AB152: -349.16238 | AC152: -198.98649 | AD152: -258.4186 | AE152: -166.74776 | AF152: -162.63958 | AG152: -215.96371 | AH152: -244.29116 | AI152: -158.22397 | AJ152: -161.69443 | AK152: -115.77987 | AL152: -370.98337 | AM152: -276.17281 | AN152: -316.49152 | AO152: -229.61402 | AP152: -342.28794 | AQ152: -361.22931 | AR152: -412.80115 | AS152: -332.80608 | AT152: -414.29447 | AU152: -264.61716

Sheet SUP
A1: Supply Table
A2: Final values exported to GAMS
B4: To SUT | C4: =SUM(C8:C111) -> #DIV/0! | D4: =SUM(D8:D111) -> #DIV/0! | E4: =SUM(E8:E111) -> #DIV/0! | F4: =SUM(F8:F111) -> #DIV/0! | G4: =SUM(G8:G111) -> #DIV/0! | H4: =SUM(H8:H111) -> #DIV/0! | I4: =SUM(I8:I111) -> #DIV/0! | J4: =SUM(J8:J111) -> #DIV/0! | ... DB4: =SUM(DB8:DB111) -> #DIV/0!
A7: From Use | C7: csorg | D7: cmaiz | E7: cwhea | F7: crice | G7: cocer | H7: cipot | I7: cspot | J7: ccass | K7: croot | L7: cbean | M7: cpeas | N7: cvege | O7: cbanb | P7: cbanc | Q7: cbans | R7: cfrui | S7: cgnut | T7: csoya | U7: coils | V7: ccoff | W7: cteal | X7: ctoba | Y7: csugr | Z7: cpyre | AA7: cocrp | AB7: ccatt | AC7: csmlr | AD7: cpoul | AE7: coliv | AF7: cmilk | AG7: ceggs | AH7: chony | AI7: chunt | AJ7: cfuel | AK7: cchar | AL7: cfore | AM7: cfish | AN7: cngas | AO7: cmore | AP7: comin | AQ7: cmeat | AR7: cfsea | AS7: cfveg | AT7: cfoil | AU7: cdair | AV7: cgmll | AW7: cbake | AX7: cfeed | AY7: cfood | AZ7: calco | BA7: cbeve | BB7: cptob | BC7: ctext | BD7: cwood | BE7: cprnt | BF7: cpetr | BG7: cchem | BH7: cphar | BI7: cprub | BJ7: cnmet | BK7: cceme | BL7: cclay | BM7: cmetl | BN7: cmach | BO7: cvehi | BP7: cfurn | BQ7: coman | BR7: crepr | BS7: celec | BT7: cwatr | BU7: cwast | BV7: ccons | BW7: ccont | BX7: cvehr | BY7: cveht | BZ7: ctrdw | CA7: ctrdr | CB7: ctrnl | CC7: ctrna | CD7: ctrns | CE7: cpost | CF7: chotl | CG7: cpubl | CH7: ccomm | CI7: cinfo | CJ7: cbank | CK7: cinsu | CL7: cofsv | CM7: crent | CN7: creal | CO7: clegl | CP7: cenga | CQ7: cprod | CR7: ctrvl | CS7: cobsv | CT7: cpadm | CU7: ceduc | CV7: cheal | CW7: csocw | CX7: ccult | CY7: carts | CZ7: cosrv | DA7: cdsrv | DB7: ctrdc
A8: {=TRANSPOSE(USE!C4:DB4)} -> 23.143032 | B8: asorg | C8: =IF(SUM(wSUP!$C8:$DB8),$A8*wSUP!C8/SUM(wSUP!$C8:$DB8),0) -> 23.143032 | D8: =IF(SUM(wSUP!$C8:$DB8),$A8*wSUP!D8/SUM(wSUP!$C8:$DB8),0) -> 0 | E8: =IF(SUM(wSUP!$C8:$DB8),$A8*wSUP!E8/SUM(wSUP!$C8:$DB8),0) -> 0 | F8: =IF(SUM(wSUP!$C8:$DB8),$A8*wSUP!F8/SUM(wSUP!$C8:$DB8),0) -> 0 | G8: =IF(SUM(wSUP!$C8:$DB8),$A8*wSUP!G8/SUM(wSUP!$C8:$DB8),0) -> 0 | H8: =IF(SUM(wSUP!$C8:$DB8),$A8*wSUP!H8/SUM(wSUP!$C8:$DB8),0) -> 0 | I8: =IF(SUM(wSUP!$C8:$DB8),$A8*wSUP!I8/SUM(wSUP!$C8:$DB8),0) -> 0 | J8: =IF(SUM(wSUP!$C8:$DB8),$A8*wSUP!J8/SUM(wSUP!$C8:$DB8),0) -> 0 | ... DB8: =IF(SUM(wSUP!$C8:$DB8),$A8*wSUP!DB8/SUM(wSUP!$C8:$DB8),0) -> 0
A9: 49.538603 | B9: amaiz | C9: =IF(SUM(wSUP!$C9:$DB9),$A9*wSUP!C9/SUM(wSUP!$C9:$DB9),0) -> 0 | D9: =IF(SUM(wSUP!$C9:$DB9),$A9*wSUP!D9/SUM(wSUP!$C9:$DB9),0) -> 49.538603 | E9: =IF(SUM(wSUP!$C9:$DB9),$A9*wSUP!E9/SUM(wSUP!$C9:$DB9),0) -> 0 | F9: =IF(SUM(wSUP!$C9:$DB9),$A9*wSUP!F9/SUM(wSUP!$C9:$DB9),0) -> 0 | G9: =IF(SUM(wSUP!$C9:$DB9),$A9*wSUP!G9/SUM(wSUP!$C9:$DB9),0) -> 0 | H9: =IF(SUM(wSUP!$C9:$DB9),$A9*wSUP!H9/SUM(wSUP!$C9:$DB9),0) -> 0 | I9: =IF(SUM(wSUP!$C9:$DB9),$A9*wSUP!I9/SUM(wSUP!$C9:$DB9),0) -> 0 | J9: =IF(SUM(wSUP!$C9:$DB9),$A9*wSUP!J9/SUM(wSUP!$C9:$DB9),0) -> 0 | ... DB9: =IF(SUM(wSUP!$C9:$DB9),$A9*wSUP!DB9/SUM(wSUP!$C9:$DB9),0) -> 0
A10: 2.1348079 | B10: awhea | C10: =IF(SUM(wSUP!$C10:$DB10),$A10*wSUP!C10/SUM(wSUP!$C10:$DB10),0) -> 0 | D10: =IF(SUM(wSUP!$C10:$DB10),$A10*wSUP!D10/SUM(wSUP!$C10:$DB10),0) -> 0 | E10: =IF(SUM(wSUP!$C10:$DB10),$A10*wSUP!E10/SUM(wSUP!$C10:$DB10),0) -> 2.1348079 | F10: =IF(SUM(wSUP!$C10:$DB10),$A10*wSUP!F10/SUM(wSUP!$C10:$DB10),0) -> 0 | G10: =IF(SUM(wSUP!$C10:$DB10),$A10*wSUP!G10/SUM(wSUP!$C10:$DB10),0) -> 0 | H10: =IF(SUM(wSUP!$C10:$DB10),$A10*wSUP!H10/SUM(wSUP!$C10:$DB10),0) -> 0 | I10: =IF(SUM(wSUP!$C10:$DB10),$A10*wSUP!I10/SUM(wSUP!$C10:$DB10),0) -> 0 | J10: =IF(SUM(wSUP!$C10:$DB10),$A10*wSUP!J10/SUM(wSUP!$C10:$DB10),0) -> 0 | ... DB10: =IF(SUM(wSUP!$C10:$DB10),$A10*wSUP!DB10/SUM(wSUP!$C10:$DB10),0) -> 0
A11: 28.835624 | B11: arice | C11: =IF(SUM(wSUP!$C11:$DB11),$A11*wSUP!C11/SUM(wSUP!$C11:$DB11),0) -> 0 | D11: =IF(SUM(wSUP!$C11:$DB11),$A11*wSUP!D11/SUM(wSUP!$C11:$DB11),0) -> 0 | E11: =IF(SUM(wSUP!$C11:$DB11),$A11*wSUP!E11/SUM(wSUP!$C11:$DB11),0) -> 0 | F11: =IF(SUM(wSUP!$C11:$DB11),$A11*wSUP!F11/SUM(wSUP!$C11:$DB11),0) -> 28.835624 | G11: =IF(SUM(wSUP!$C11:$DB11),$A11*wSUP!G11/SUM(wSUP!$C11:$DB11),0) -> 0 | H11: =IF(SUM(wSUP!$C11:$DB11),$A11*wSUP!H11/SUM(wSUP!$C11:$DB11),0) -> 0 | I11: =IF(SUM(wSUP!$C11:$DB11),$A11*wSUP!I11/SUM(wSUP!$C11:$DB11),0) -> 0 | J11: =IF(SUM(wSUP!$C11:$DB11),$A11*wSUP!J11/SUM(wSUP!$C11:$DB11),0) -> 0 | ... DB11: =IF(SUM(wSUP!$C11:$DB11),$A11*wSUP!DB11/SUM(wSUP!$C11:$DB11),0) -> 0
A12: 7.6753237e-05 | B12: aocer | C12: =IF(SUM(wSUP!$C12:$DB12),$A12*wSUP!C12/SUM(wSUP!$C12:$DB12),0) -> 0 | D12: =IF(SUM(wSUP!$C12:$DB12),$A12*wSUP!D12/SUM(wSUP!$C12:$DB12),0) -> 0 | E12: =IF(SUM(wSUP!$C12:$DB12),$A12*wSUP!E12/SUM(wSUP!$C12:$DB12),0) -> 0 | F12: =IF(SUM(wSUP!$C12:$DB12),$A12*wSUP!F12/SUM(wSUP!$C12:$DB12),0) -> 0 | G12: =IF(SUM(wSUP!$C12:$DB12),$A12*wSUP!G12/SUM(wSUP!$C12:$DB12),0) -> 7.6753237e-05 | H12: =IF(SUM(wSUP!$C12:$DB12),$A12*wSUP!H12/SUM(wSUP!$C12:$DB12),0) -> 0 | I12: =IF(SUM(wSUP!$C12:$DB12),$A12*wSUP!I12/SUM(wSUP!$C12:$DB12),0) -> 0 | J12: =IF(SUM(wSUP!$C12:$DB12),$A12*wSUP!J12/SUM(wSUP!$C12:$DB12),0) -> 0 | ... DB12: =IF(SUM(wSUP!$C12:$DB12),$A12*wSUP!DB12/SUM(wSUP!$C12:$DB12),0) -> 0
A13: 123.14102 | B13: aipot | C13: =IF(SUM(wSUP!$C13:$DB13),$A13*wSUP!C13/SUM(wSUP!$C13:$DB13),0) -> 0 | D13: =IF(SUM(wSUP!$C13:$DB13),$A13*wSUP!D13/SUM(wSUP!$C13:$DB13),0) -> 0 | E13: =IF(SUM(wSUP!$C13:$DB13),$A13*wSUP!E13/SUM(wSUP!$C13:$DB13),0) -> 0 | F13: =IF(SUM(wSUP!$C13:$DB13),$A13*wSUP!F13/SUM(wSUP!$C13:$DB13),0) -> 0 | G13: =IF(SUM(wSUP!$C13:$DB13),$A13*wSUP!G13/SUM(wSUP!$C13:$DB13),0) -> 0 | H13: =IF(SUM(wSUP!$C13:$DB13),$A13*wSUP!H13/SUM(wSUP!$C13:$DB13),0) -> 123.14102 | I13: =IF(SUM(wSUP!$C13:$DB13),$A13*wSUP!I13/SUM(wSUP!$C13:$DB13),0) -> 0 | J13: =IF(SUM(wSUP!$C13:$DB13),$A13*wSUP!J13/SUM(wSUP!$C13:$DB13),0) -> 0 | ... DB13: =IF(SUM(wSUP!$C13:$DB13),$A13*wSUP!DB13/SUM(wSUP!$C13:$DB13),0) -> 0
A14: 127.93145 | B14: aspot | C14: =IF(SUM(wSUP!$C14:$DB14),$A14*wSUP!C14/SUM(wSUP!$C14:$DB14),0) -> 0 | D14: =IF(SUM(wSUP!$C14:$DB14),$A14*wSUP!D14/SUM(wSUP!$C14:$DB14),0) -> 0 | E14: =IF(SUM(wSUP!$C14:$DB14),$A14*wSUP!E14/SUM(wSUP!$C14:$DB14),0) -> 0 | F14: =IF(SUM(wSUP!$C14:$DB14),$A14*wSUP!F14/SUM(wSUP!$C14:$DB14),0) -> 0 | G14: =IF(SUM(wSUP!$C14:$DB14),$A14*wSUP!G14/SUM(wSUP!$C14:$DB14),0) -> 0 | H14: =IF(SUM(wSUP!$C14:$DB14),$A14*wSUP!H14/SUM(wSUP!$C14:$DB14),0) -> 0 | I14: =IF(SUM(wSUP!$C14:$DB14),$A14*wSUP!I14/SUM(wSUP!$C14:$DB14),0) -> 127.93145 | J14: =IF(SUM(wSUP!$C14:$DB14),$A14*wSUP!J14/SUM(wSUP!$C14:$DB14),0) -> 0 | ... DB14: =IF(SUM(wSUP!$C14:$DB14),$A14*wSUP!DB14/SUM(wSUP!$C14:$DB14),0) -> 0
A15: 82.389468 | B15: acass | C15: =IF(SUM(wSUP!$C15:$DB15),$A15*wSUP!C15/SUM(wSUP!$C15:$DB15),0) -> 0 | D15: =IF(SUM(wSUP!$C15:$DB15),$A15*wSUP!D15/SUM(wSUP!$C15:$DB15),0) -> 0 | E15: =IF(SUM(wSUP!$C15:$DB15),$A15*wSUP!E15/SUM(wSUP!$C15:$DB15),0) -> 0 | F15: =IF(SUM(wSUP!$C15:$DB15),$A15*wSUP!F15/SUM(wSUP!$C15:$DB15),0) -> 0 | G15: =IF(SUM(wSUP!$C15:$DB15),$A15*wSUP!G15/SUM(wSUP!$C15:$DB15),0) -> 0 | H15: =IF(SUM(wSUP!$C15:$DB15),$A15*wSUP!H15/SUM(wSUP!$C15:$DB15),0) -> 0 | I15: =IF(SUM(wSUP!$C15:$DB15),$A15*wSUP!I15/SUM(wSUP!$C15:$DB15),0) -> 0 | J15: =IF(SUM(wSUP!$C15:$DB15),$A15*wSUP!J15/SUM(wSUP!$C15:$DB15),0) -> 82.389468 | ... DB15: =IF(SUM(wSUP!$C15:$DB15),$A15*wSUP!DB15/SUM(wSUP!$C15:$DB15),0) -> 0
A16: 14.432367 | B16: aroot | C16: =IF(SUM(wSUP!$C16:$DB16),$A16*wSUP!C16/SUM(wSUP!$C16:$DB16),0) -> 0 | D16: =IF(SUM(wSUP!$C16:$DB16),$A16*wSUP!D16/SUM(wSUP!$C16:$DB16),0) -> 0 | E16: =IF(SUM(wSUP!$C16:$DB16),$A16*wSUP!E16/SUM(wSUP!$C16:$DB16),0) -> 0 | F16: =IF(SUM(wSUP!$C16:$DB16),$A16*wSUP!F16/SUM(wSUP!$C16:$DB16),0) -> 0 | G16: =IF(SUM(wSUP!$C16:$DB16),$A16*wSUP!G16/SUM(wSUP!$C16:$DB16),0) -> 0 | H16: =IF(SUM(wSUP!$C16:$DB16),$A16*wSUP!H16/SUM(wSUP!$C16:$DB16),0) -> 0 | I16: =IF(SUM(wSUP!$C16:$DB16),$A16*wSUP!I16/SUM(wSUP!$C16:$DB16),0) -> 0 | J16: =IF(SUM(wSUP!$C16:$DB16),$A16*wSUP!J16/SUM(wSUP!$C16:$DB16),0) -> 0 | ... DB16: =IF(SUM(wSUP!$C16:$DB16),$A16*wSUP!DB16/SUM(wSUP!$C16:$DB16),0) -> 0
A17: 252.28324 | B17: abean | C17: =IF(SUM(wSUP!$C17:$DB17),$A17*wSUP!C17/SUM(wSUP!$C17:$DB17),0) -> 0 | D17: =IF(SUM(wSUP!$C17:$DB17),$A17*wSUP!D17/SUM(wSUP!$C17:$DB17),0) -> 0 | E17: =IF(SUM(wSUP!$C17:$DB17),$A17*wSUP!E17/SUM(wSUP!$C17:$DB17),0) -> 0 | F17: =IF(SUM(wSUP!$C17:$DB17),$A17*wSUP!F17/SUM(wSUP!$C17:$DB17),0) -> 0 | G17: =IF(SUM(wSUP!$C17:$DB17),$A17*wSUP!G17/SUM(wSUP!$C17:$DB17),0) -> 0 | H17: =IF(SUM(wSUP!$C17:$DB17),$A17*wSUP!H17/SUM(wSUP!$C17:$DB17),0) -> 0 | I17: =IF(SUM(wSUP!$C17:$DB17),$A17*wSUP!I17/SUM(wSUP!$C17:$DB17),0) -> 0 | J17: =IF(SUM(wSUP!$C17:$DB17),$A17*wSUP!J17/SUM(wSUP!$C17:$DB17),0) -> 0 | ... DB17: =IF(SUM(wSUP!$C17:$DB17),$A17*wSUP!DB17/SUM(wSUP!$C17:$DB17),0) -> 0
A18: 547.89372 | B18: apeas | C18: =IF(SUM(wSUP!$C18:$DB18),$A18*wSUP!C18/SUM(wSUP!$C18:$DB18),0) -> 0 | D18: =IF(SUM(wSUP!$C18:$DB18),$A18*wSUP!D18/SUM(wSUP!$C18:$DB18),0) -> 0 | E18: =IF(SUM(wSUP!$C18:$DB18),$A18*wSUP!E18/SUM(wSUP!$C18:$DB18),0) -> 0 | F18: =IF(SUM(wSUP!$C18:$DB18),$A18*wSUP!F18/SUM(wSUP!$C18:$DB18),0) -> 0 | G18: =IF(SUM(wSUP!$C18:$DB18),$A18*wSUP!G18/SUM(wSUP!$C18:$DB18),0) -> 0 | H18: =IF(SUM(wSUP!$C18:$DB18),$A18*wSUP!H18/SUM(wSUP!$C18:$DB18),0) -> 0 | I18: =IF(SUM(wSUP!$C18:$DB18),$A18*wSUP!I18/SUM(wSUP!$C18:$DB18),0) -> 0 | J18: =IF(SUM(wSUP!$C18:$DB18),$A18*wSUP!J18/SUM(wSUP!$C18:$DB18),0) -> 0 | ... DB18: =IF(SUM(wSUP!$C18:$DB18),$A18*wSUP!DB18/SUM(wSUP!$C18:$DB18),0) -> 0
A19: 7.1409111 | B19: avege | C19: =IF(SUM(wSUP!$C19:$DB19),$A19*wSUP!C19/SUM(wSUP!$C19:$DB19),0) -> 0 | D19: =IF(SUM(wSUP!$C19:$DB19),$A19*wSUP!D19/SUM(wSUP!$C19:$DB19),0) -> 0 | E19: =IF(SUM(wSUP!$C19:$DB19),$A19*wSUP!E19/SUM(wSUP!$C19:$DB19),0) -> 0 | F19: =IF(SUM(wSUP!$C19:$DB19),$A19*wSUP!F19/SUM(wSUP!$C19:$DB19),0) -> 0 | G19: =IF(SUM(wSUP!$C19:$DB19),$A19*wSUP!G19/SUM(wSUP!$C19:$DB19),0) -> 0 | H19: =IF(SUM(wSUP!$C19:$DB19),$A19*wSUP!H19/SUM(wSUP!$C19:$DB19),0) -> 0 | I19: =IF(SUM(wSUP!$C19:$DB19),$A19*wSUP!I19/SUM(wSUP!$C19:$DB19),0) -> 0 | J19: =IF(SUM(wSUP!$C19:$DB19),$A19*wSUP!J19/SUM(wSUP!$C19:$DB19),0) -> 0 | ... DB19: =IF(SUM(wSUP!$C19:$DB19),$A19*wSUP!DB19/SUM(wSUP!$C19:$DB19),0) -> 0
A20: 7.7144605 | B20: abanb | C20: =IF(SUM(wSUP!$C20:$DB20),$A20*wSUP!C20/SUM(wSUP!$C20:$DB20),0) -> 0 | D20: =IF(SUM(wSUP!$C20:$DB20),$A20*wSUP!D20/SUM(wSUP!$C20:$DB20),0) -> 0 | E20: =IF(SUM(wSUP!$C20:$DB20),$A20*wSUP!E20/SUM(wSUP!$C20:$DB20),0) -> 0 | F20: =IF(SUM(wSUP!$C20:$DB20),$A20*wSUP!F20/SUM(wSUP!$C20:$DB20),0) -> 0 | G20: =IF(SUM(wSUP!$C20:$DB20),$A20*wSUP!G20/SUM(wSUP!$C20:$DB20),0) -> 0 | H20: =IF(SUM(wSUP!$C20:$DB20),$A20*wSUP!H20/SUM(wSUP!$C20:$DB20),0) -> 0 | I20: =IF(SUM(wSUP!$C20:$DB20),$A20*wSUP!I20/SUM(wSUP!$C20:$DB20),0) -> 0 | J20: =IF(SUM(wSUP!$C20:$DB20),$A20*wSUP!J20/SUM(wSUP!$C20:$DB20),0) -> 0 | ... DB20: =IF(SUM(wSUP!$C20:$DB20),$A20*wSUP!DB20/SUM(wSUP!$C20:$DB20),0) -> 0
... A89: 0 | B89: ahotl | C89: =IF(SUM(wSUP!$C89:$DB89),$A89*wSUP!C89/SUM(wSUP!$C89:$DB89),0) -> 0 | D89: =IF(SUM(wSUP!$C89:$DB89),$A89*wSUP!D89/SUM(wSUP!$C89:$DB89),0) -> 0 | E89: =IF(SUM(wSUP!$C89:$DB89),$A89*wSUP!E89/SUM(wSUP!$C89:$DB89),0) -> 0 | F89: =IF(SUM(wSUP!$C89:$DB89),$A89*wSUP!F89/SUM(wSUP!$C89:$DB89),0) -> 0 | G89: =IF(SUM(wSUP!$C89:$DB89),$A89*wSUP!G89/SUM(wSUP!$C89:$DB89),0) -> 0 | H89: =IF(SUM(wSUP!$C89:$DB89),$A89*wSUP!H89/SUM(wSUP!$C89:$DB89),0) -> 0 | I89: =IF(SUM(wSUP!$C89:$DB89),$A89*wSUP!I89/SUM(wSUP!$C89:$DB89),0) -> 0 | J89: =IF(SUM(wSUP!$C89:$DB89),$A89*wSUP!J89/SUM(wSUP!$C89:$DB89),0) -> 0 | ... DB89: =IF(SUM(wSUP!$C89:$DB89),$A89*wSUP!DB89/SUM(wSUP!$C89:$DB89),0) -> 0
A90: #DIV/0! | B90: apubl | C90: =IF(SUM(wSUP!$C90:$DB90),$A90*wSUP!C90/SUM(wSUP!$C90:$DB90),0) -> #DIV/0! | D90: =IF(SUM(wSUP!$C90:$DB90),$A90*wSUP!D90/SUM(wSUP!$C90:$DB90),0) -> #DIV/0! | E90: =IF(SUM(wSUP!$C90:$DB90),$A90*wSUP!E90/SUM(wSUP!$C90:$DB90),0) -> #DIV/0! | F90: =IF(SUM(wSUP!$C90:$DB90),$A90*wSUP!F90/SUM(wSUP!$C90:$DB90),0) -> #DIV/0! | G90: =IF(SUM(wSUP!$C90:$DB90),$A90*wSUP!G90/SUM(wSUP!$C90:$DB90),0) -> #DIV/0! | H90: =IF(SUM(wSUP!$C90:$DB90),$A90*wSUP!H90/SUM(wSUP!$C90:$DB90),0) -> #DIV/0! | I90: =IF(SUM(wSUP!$C90:$DB90),$A90*wSUP!I90/SUM(wSUP!$C90:$DB90),0) -> #DIV/0! | J90: =IF(SUM(wSUP!$C90:$DB90),$A90*wSUP!J90/SUM(wSUP!$C90:$DB90),0) -> #DIV/0! | ... DB90: =IF(SUM(wSUP!$C90:$DB90),$A90*wSUP!DB90/SUM(wSUP!$C90:$DB90),0) -> #DIV/0!
A91: #DIV/0! | B91: acomm | C91: =IF(SUM(wSUP!$C91:$DB91),$A91*wSUP!C91/SUM(wSUP!$C91:$DB91),0) -> #DIV/0! | D91: =IF(SUM(wSUP!$C91:$DB91),$A91*wSUP!D91/SUM(wSUP!$C91:$DB91),0) -> #DIV/0! | E91: =IF(SUM(wSUP!$C91:$DB91),$A91*wSUP!E91/SUM(wSUP!$C91:$DB91),0) -> #DIV/0! | F91: =IF(SUM(wSUP!$C91:$DB91),$A91*wSUP!F91/SUM(wSUP!$C91:$DB91),0) -> #DIV/0! | G91: =IF(SUM(wSUP!$C91:$DB91),$A91*wSUP!G91/SUM(wSUP!$C91:$DB91),0) -> #DIV/0! | H91: =IF(SUM(wSUP!$C91:$DB91),$A91*wSUP!H91/SUM(wSUP!$C91:$DB91),0) -> #DIV/0! | I91: =IF(SUM(wSUP!$C91:$DB91),$A91*wSUP!I91/SUM(wSUP!$C91:$DB91),0) -> #DIV/0! | J91: =IF(SUM(wSUP!$C91:$DB91),$A91*wSUP!J91/SUM(wSUP!$C91:$DB91),0) -> #DIV/0! | ... DB91: =IF(SUM(wSUP!$C91:$DB91),$A91*wSUP!DB91/SUM(wSUP!$C91:$DB91),0) -> #DIV/0!
A92: #DIV/0! | B92: ainfo | C92: =IF(SUM(wSUP!$C92:$DB92),$A92*wSUP!C92/SUM(wSUP!$C92:$DB92),0) -> #DIV/0! | D92: =IF(SUM(wSUP!$C92:$DB92),$A92*wSUP!D92/SUM(wSUP!$C92:$DB92),0) -> #DIV/0! | E92: =IF(SUM(wSUP!$C92:$DB92),$A92*wSUP!E92/SUM(wSUP!$C92:$DB92),0) -> #DIV/0! | F92: =IF(SUM(wSUP!$C92:$DB92),$A92*wSUP!F92/SUM(wSUP!$C92:$DB92),0) -> #DIV/0! | G92: =IF(SUM(wSUP!$C92:$DB92),$A92*wSUP!G92/SUM(wSUP!$C92:$DB92),0) -> #DIV/0! | H92: =IF(SUM(wSUP!$C92:$DB92),$A92*wSUP!H92/SUM(wSUP!$C92:$DB92),0) -> #DIV/0! | I92: =IF(SUM(wSUP!$C92:$DB92),$A92*wSUP!I92/SUM(wSUP!$C92:$DB92),0) -> #DIV/0! | J92: =IF(SUM(wSUP!$C92:$DB92),$A92*wSUP!J92/SUM(wSUP!$C92:$DB92),0) -> #DIV/0! | ... DB92: =IF(SUM(wSUP!$C92:$DB92),$A92*wSUP!DB92/SUM(wSUP!$C92:$DB92),0) -> #DIV/0!
A93: #DIV/0! | B93: abank | C93: =IF(SUM(wSUP!$C93:$DB93),$A93*wSUP!C93/SUM(wSUP!$C93:$DB93),0) -> #DIV/0! | D93: =IF(SUM(wSUP!$C93:$DB93),$A93*wSUP!D93/SUM(wSUP!$C93:$DB93),0) -> #DIV/0! | E93: =IF(SUM(wSUP!$C93:$DB93),$A93*wSUP!E93/SUM(wSUP!$C93:$DB93),0) -> #DIV/0! | F93: =IF(SUM(wSUP!$C93:$DB93),$A93*wSUP!F93/SUM(wSUP!$C93:$DB93),0) -> #DIV/0! | G93: =IF(SUM(wSUP!$C93:$DB93),$A93*wSUP!G93/SUM(wSUP!$C93:$DB93),0) -> #DIV/0! | H93: =IF(SUM(wSUP!$C93:$DB93),$A93*wSUP!H93/SUM(wSUP!$C93:$DB93),0) -> #DIV/0! | I93: =IF(SUM(wSUP!$C93:$DB93),$A93*wSUP!I93/SUM(wSUP!$C93:$DB93),0) -> #DIV/0! | J93: =IF(SUM(wSUP!$C93:$DB93),$A93*wSUP!J93/SUM(wSUP!$C93:$DB93),0) -> #DIV/0! | ... DB93: =IF(SUM(wSUP!$C93:$DB93),$A93*wSUP!DB93/SUM(wSUP!$C93:$DB93),0) -> #DIV/0!
A94: #DIV/0! | B94: ainsu | C94: =IF(SUM(wSUP!$C94:$DB94),$A94*wSUP!C94/SUM(wSUP!$C94:$DB94),0) -> #DIV/0! | D94: =IF(SUM(wSUP!$C94:$DB94),$A94*wSUP!D94/SUM(wSUP!$C94:$DB94),0) -> #DIV/0! | E94: =IF(SUM(wSUP!$C94:$DB94),$A94*wSUP!E94/SUM(wSUP!$C94:$DB94),0) -> #DIV/0! | F94: =IF(SUM(wSUP!$C94:$DB94),$A94*wSUP!F94/SUM(wSUP!$C94:$DB94),0) -> #DIV/0! | G94: =IF(SUM(wSUP!$C94:$DB94),$A94*wSUP!G94/SUM(wSUP!$C94:$DB94),0) -> #DIV/0! | H94: =IF(SUM(wSUP!$C94:$DB94),$A94*wSUP!H94/SUM(wSUP!$C94:$DB94),0) -> #DIV/0! | I94: =IF(SUM(wSUP!$C94:$DB94),$A94*wSUP!I94/SUM(wSUP!$C94:$DB94),0) -> #DIV/0! | J94: =IF(SUM(wSUP!$C94:$DB94),$A94*wSUP!J94/SUM(wSUP!$C94:$DB94),0) -> #DIV/0! | ... DB94: =IF(SUM(wSUP!$C94:$DB94),$A94*wSUP!DB94/SUM(wSUP!$C94:$DB94),0) -> #DIV/0!
A95: #DIV/0! | B95: aofsv | C95: =IF(SUM(wSUP!$C95:$DB95),$A95*wSUP!C95/SUM(wSUP!$C95:$DB95),0) -> #DIV/0! | D95: =IF(SUM(wSUP!$C95:$DB95),$A95*wSUP!D95/SUM(wSUP!$C95:$DB95),0) -> #DIV/0! | E95: =IF(SUM(wSUP!$C95:$DB95),$A95*wSUP!E95/SUM(wSUP!$C95:$DB95),0) -> #DIV/0! | F95: =IF(SUM(wSUP!$C95:$DB95),$A95*wSUP!F95/SUM(wSUP!$C95:$DB95),0) -> #DIV/0! | G95: =IF(SUM(wSUP!$C95:$DB95),$A95*wSUP!G95/SUM(wSUP!$C95:$DB95),0) -> #DIV/0! | H95: =IF(SUM(wSUP!$C95:$DB95),$A95*wSUP!H95/SUM(wSUP!$C95:$DB95),0) -> #DIV/0! | I95: =IF(SUM(wSUP!$C95:$DB95),$A95*wSUP!I95/SUM(wSUP!$C95:$DB95),0) -> #DIV/0! | J95: =IF(SUM(wSUP!$C95:$DB95),$A95*wSUP!J95/SUM(wSUP!$C95:$DB95),0) -> #DIV/0! | ... DB95: =IF(SUM(wSUP!$C95:$DB95),$A95*wSUP!DB95/SUM(wSUP!$C95:$DB95),0) -> #DIV/0!
A96: #DIV/0! | B96: arent | C96: =IF(SUM(wSUP!$C96:$DB96),$A96*wSUP!C96/SUM(wSUP!$C96:$DB96),0) -> #DIV/0! | D96: =IF(SUM(wSUP!$C96:$DB96),$A96*wSUP!D96/SUM(wSUP!$C96:$DB96),0) -> #DIV/0! | E96: =IF(SUM(wSUP!$C96:$DB96),$A96*wSUP!E96/SUM(wSUP!$C96:$DB96),0) -> #DIV/0! | F96: =IF(SUM(wSUP!$C96:$DB96),$A96*wSUP!F96/SUM(wSUP!$C96:$DB96),0) -> #DIV/0! | G96: =IF(SUM(wSUP!$C96:$DB96),$A96*wSUP!G96/SUM(wSUP!$C96:$DB96),0) -> #DIV/0! | H96: =IF(SUM(wSUP!$C96:$DB96),$A96*wSUP!H96/SUM(wSUP!$C96:$DB96),0) -> #DIV/0! | I96: =IF(SUM(wSUP!$C96:$DB96),$A96*wSUP!I96/SUM(wSUP!$C96:$DB96),0) -> #DIV/0! | J96: =IF(SUM(wSUP!$C96:$DB96),$A96*wSUP!J96/SUM(wSUP!$C96:$DB96),0) -> #DIV/0! | ... DB96: =IF(SUM(wSUP!$C96:$DB96),$A96*wSUP!DB96/SUM(wSUP!$C96:$DB96),0) -> #DIV/0!
A97: #DIV/0! | B97: areal | C97: =IF(SUM(wSUP!$C97:$DB97),$A97*wSUP!C97/SUM(wSUP!$C97:$DB97),0) -> #DIV/0! | D97: =IF(SUM(wSUP!$C97:$DB97),$A97*wSUP!D97/SUM(wSUP!$C97:$DB97),0) -> #DIV/0! | E97: =IF(SUM(wSUP!$C97:$DB97),$A97*wSUP!E97/SUM(wSUP!$C97:$DB97),0) -> #DIV/0! | F97: =IF(SUM(wSUP!$C97:$DB97),$A97*wSUP!F97/SUM(wSUP!$C97:$DB97),0) -> #DIV/0! | G97: =IF(SUM(wSUP!$C97:$DB97),$A97*wSUP!G97/SUM(wSUP!$C97:$DB97),0) -> #DIV/0! | H97: =IF(SUM(wSUP!$C97:$DB97),$A97*wSUP!H97/SUM(wSUP!$C97:$DB97),0) -> #DIV/0! | I97: =IF(SUM(wSUP!$C97:$DB97),$A97*wSUP!I97/SUM(wSUP!$C97:$DB97),0) -> #DIV/0! | J97: =IF(SUM(wSUP!$C97:$DB97),$A97*wSUP!J97/SUM(wSUP!$C97:$DB97),0) -> #DIV/0! | ... DB97: =IF(SUM(wSUP!$C97:$DB97),$A97*wSUP!DB97/SUM(wSUP!$C97:$DB97),0) -> #DIV/0!
A98: #DIV/0! | B98: alegl | C98: =IF(SUM(wSUP!$C98:$DB98),$A98*wSUP!C98/SUM(wSUP!$C98:$DB98),0) -> #DIV/0! | D98: =IF(SUM(wSUP!$C98:$DB98),$A98*wSUP!D98/SUM(wSUP!$C98:$DB98),0) -> #DIV/0! | E98: =IF(SUM(wSUP!$C98:$DB98),$A98*wSUP!E98/SUM(wSUP!$C98:$DB98),0) -> #DIV/0! | F98: =IF(SUM(wSUP!$C98:$DB98),$A98*wSUP!F98/SUM(wSUP!$C98:$DB98),0) -> #DIV/0! | G98: =IF(SUM(wSUP!$C98:$DB98),$A98*wSUP!G98/SUM(wSUP!$C98:$DB98),0) -> #DIV/0! | H98: =IF(SUM(wSUP!$C98:$DB98),$A98*wSUP!H98/SUM(wSUP!$C98:$DB98),0) -> #DIV/0! | I98: =IF(SUM(wSUP!$C98:$DB98),$A98*wSUP!I98/SUM(wSUP!$C98:$DB98),0) -> #DIV/0! | J98: =IF(SUM(wSUP!$C98:$DB98),$A98*wSUP!J98/SUM(wSUP!$C98:$DB98),0) -> #DIV/0! | ... DB98: =IF(SUM(wSUP!$C98:$DB98),$A98*wSUP!DB98/SUM(wSUP!$C98:$DB98),0) -> #DIV/0!
A99: #DIV/0! | B99: aenga | C99: =IF(SUM(wSUP!$C99:$DB99),$A99*wSUP!C99/SUM(wSUP!$C99:$DB99),0) -> #DIV/0! | D99: =IF(SUM(wSUP!$C99:$DB99),$A99*wSUP!D99/SUM(wSUP!$C99:$DB99),0) -> #DIV/0! | E99: =IF(SUM(wSUP!$C99:$DB99),$A99*wSUP!E99/SUM(wSUP!$C99:$DB99),0) -> #DIV/0! | F99: =IF(SUM(wSUP!$C99:$DB99),$A99*wSUP!F99/SUM(wSUP!$C99:$DB99),0) -> #DIV/0! | G99: =IF(SUM(wSUP!$C99:$DB99),$A99*wSUP!G99/SUM(wSUP!$C99:$DB99),0) -> #DIV/0! | H99: =IF(SUM(wSUP!$C99:$DB99),$A99*wSUP!H99/SUM(wSUP!$C99:$DB99),0) -> #DIV/0! | I99: =IF(SUM(wSUP!$C99:$DB99),$A99*wSUP!I99/SUM(wSUP!$C99:$DB99),0) -> #DIV/0! | J99: =IF(SUM(wSUP!$C99:$DB99),$A99*wSUP!J99/SUM(wSUP!$C99:$DB99),0) -> #DIV/0! | ... DB99: =IF(SUM(wSUP!$C99:$DB99),$A99*wSUP!DB99/SUM(wSUP!$C99:$DB99),0) -> #DIV/0!
A100: #DIV/0! | B100: aprod | C100: =IF(SUM(wSUP!$C100:$DB100),$A100*wSUP!C100/SUM(wSUP!$C100:$DB100),0) -> #DIV/0! | D100: =IF(SUM(wSUP!$C100:$DB100),$A100*wSUP!D100/SUM(wSUP!$C100:$DB100),0) -> #DIV/0! | E100: =IF(SUM(wSUP!$C100:$DB100),$A100*wSUP!E100/SUM(wSUP!$C100:$DB100),0) -> #DIV/0! | F100: =IF(SUM(wSUP!$C100:$DB100),$A100*wSUP!F100/SUM(wSUP!$C100:$DB100),0) -> #DIV/0! | G100: =IF(SUM(wSUP!$C100:$DB100),$A100*wSUP!G100/SUM(wSUP!$C100:$DB100),0) -> #DIV/0! | H100: =IF(SUM(wSUP!$C100:$DB100),$A100*wSUP!H100/SUM(wSUP!$C100:$DB100),0) -> #DIV/0! | I100: =IF(SUM(wSUP!$C100:$DB100),$A100*wSUP!I100/SUM(wSUP!$C100:$DB100),0) -> #DIV/0! | J100: =IF(SUM(wSUP!$C100:$DB100),$A100*wSUP!J100/SUM(wSUP!$C100:$DB100),0) -> #DIV/0! | ... DB100: =IF(SUM(wSUP!$C100:$DB100),$A100*wSUP!DB100/SUM(wSUP!$C100:$DB100),0) -> #DIV/0!
A101: #DIV/0! | B101: atrvl | C101: =IF(SUM(wSUP!$C101:$DB101),$A101*wSUP!C101/SUM(wSUP!$C101:$DB101),0) -> #DIV/0! | D101: =IF(SUM(wSUP!$C101:$DB101),$A101*wSUP!D101/SUM(wSUP!$C101:$DB101),0) -> #DIV/0! | E101: =IF(SUM(wSUP!$C101:$DB101),$A101*wSUP!E101/SUM(wSUP!$C101:$DB101),0) -> #DIV/0! | F101: =IF(SUM(wSUP!$C101:$DB101),$A101*wSUP!F101/SUM(wSUP!$C101:$DB101),0) -> #DIV/0! | G101: =IF(SUM(wSUP!$C101:$DB101),$A101*wSUP!G101/SUM(wSUP!$C101:$DB101),0) -> #DIV/0! | H101: =IF(SUM(wSUP!$C101:$DB101),$A101*wSUP!H101/SUM(wSUP!$C101:$DB101),0) -> #DIV/0! | I101: =IF(SUM(wSUP!$C101:$DB101),$A101*wSUP!I101/SUM(wSUP!$C101:$DB101),0) -> #DIV/0! | J101: =IF(SUM(wSUP!$C101:$DB101),$A101*wSUP!J101/SUM(wSUP!$C101:$DB101),0) -> #DIV/0! | ... DB101: =IF(SUM(wSUP!$C101:$DB101),$A101*wSUP!DB101/SUM(wSUP!$C101:$DB101),0) -> #DIV/0!
A102: #DIV/0! | B102: aobsv | C102: =IF(SUM(wSUP!$C102:$DB102),$A102*wSUP!C102/SUM(wSUP!$C102:$DB102),0) -> #DIV/0! | D102: =IF(SUM(wSUP!$C102:$DB102),$A102*wSUP!D102/SUM(wSUP!$C102:$DB102),0) -> #DIV/0! | E102: =IF(SUM(wSUP!$C102:$DB102),$A102*wSUP!E102/SUM(wSUP!$C102:$DB102),0) -> #DIV/0! | F102: =IF(SUM(wSUP!$C102:$DB102),$A102*wSUP!F102/SUM(wSUP!$C102:$DB102),0) -> #DIV/0! | G102: =IF(SUM(wSUP!$C102:$DB102),$A102*wSUP!G102/SUM(wSUP!$C102:$DB102),0) -> #DIV/0! | H102: =IF(SUM(wSUP!$C102:$DB102),$A102*wSUP!H102/SUM(wSUP!$C102:$DB102),0) -> #DIV/0! | I102: =IF(SUM(wSUP!$C102:$DB102),$A102*wSUP!I102/SUM(wSUP!$C102:$DB102),0) -> #DIV/0! | J102: =IF(SUM(wSUP!$C102:$DB102),$A102*wSUP!J102/SUM(wSUP!$C102:$DB102),0) -> #DIV/0! | ... DB102: =IF(SUM(wSUP!$C102:$DB102),$A102*wSUP!DB102/SUM(wSUP!$C102:$DB102),0) -> #DIV/0!
A103: 0 | B103: apadm | C103: =IF(SUM(wSUP!$C103:$DB103),$A103*wSUP!C103/SUM(wSUP!$C103:$DB103),0) -> 0 | D103: =IF(SUM(wSUP!$C103:$DB103),$A103*wSUP!D103/SUM(wSUP!$C103:$DB103),0) -> 0 | E103: =IF(SUM(wSUP!$C103:$DB103),$A103*wSUP!E103/SUM(wSUP!$C103:$DB103),0) -> 0 | F103: =IF(SUM(wSUP!$C103:$DB103),$A103*wSUP!F103/SUM(wSUP!$C103:$DB103),0) -> 0 | G103: =IF(SUM(wSUP!$C103:$DB103),$A103*wSUP!G103/SUM(wSUP!$C103:$DB103),0) -> 0 | H103: =IF(SUM(wSUP!$C103:$DB103),$A103*wSUP!H103/SUM(wSUP!$C103:$DB103),0) -> 0 | I103: =IF(SUM(wSUP!$C103:$DB103),$A103*wSUP!I103/SUM(wSUP!$C103:$DB103),0) -> 0 | J103: =IF(SUM(wSUP!$C103:$DB103),$A103*wSUP!J103/SUM(wSUP!$C103:$DB103),0) -> 0 | ... DB103: =IF(SUM(wSUP!$C103:$DB103),$A103*wSUP!DB103/SUM(wSUP!$C103:$DB103),0) -> 0
A104: 0 | B104: aeduc | C104: =IF(SUM(wSUP!$C104:$DB104),$A104*wSUP!C104/SUM(wSUP!$C104:$DB104),0) -> 0 | D104: =IF(SUM(wSUP!$C104:$DB104),$A104*wSUP!D104/SUM(wSUP!$C104:$DB104),0) -> 0 | E104: =IF(SUM(wSUP!$C104:$DB104),$A104*wSUP!E104/SUM(wSUP!$C104:$DB104),0) -> 0 | F104: =IF(SUM(wSUP!$C104:$DB104),$A104*wSUP!F104/SUM(wSUP!$C104:$DB104),0) -> 0 | G104: =IF(SUM(wSUP!$C104:$DB104),$A104*wSUP!G104/SUM(wSUP!$C104:$DB104),0) -> 0 | H104: =IF(SUM(wSUP!$C104:$DB104),$A104*wSUP!H104/SUM(wSUP!$C104:$DB104),0) -> 0 | I104: =IF(SUM(wSUP!$C104:$DB104),$A104*wSUP!I104/SUM(wSUP!$C104:$DB104),0) -> 0 | J104: =IF(SUM(wSUP!$C104:$DB104),$A104*wSUP!J104/SUM(wSUP!$C104:$DB104),0) -> 0 | ... DB104: =IF(SUM(wSUP!$C104:$DB104),$A104*wSUP!DB104/SUM(wSUP!$C104:$DB104),0) -> 0
A105: #DIV/0! | B105: aheal | C105: =IF(SUM(wSUP!$C105:$DB105),$A105*wSUP!C105/SUM(wSUP!$C105:$DB105),0) -> #DIV/0! | D105: =IF(SUM(wSUP!$C105:$DB105),$A105*wSUP!D105/SUM(wSUP!$C105:$DB105),0) -> #DIV/0! | E105: =IF(SUM(wSUP!$C105:$DB105),$A105*wSUP!E105/SUM(wSUP!$C105:$DB105),0) -> #DIV/0! | F105: =IF(SUM(wSUP!$C105:$DB105),$A105*wSUP!F105/SUM(wSUP!$C105:$DB105),0) -> #DIV/0! | G105: =IF(SUM(wSUP!$C105:$DB105),$A105*wSUP!G105/SUM(wSUP!$C105:$DB105),0) -> #DIV/0! | H105: =IF(SUM(wSUP!$C105:$DB105),$A105*wSUP!H105/SUM(wSUP!$C105:$DB105),0) -> #DIV/0! | I105: =IF(SUM(wSUP!$C105:$DB105),$A105*wSUP!I105/SUM(wSUP!$C105:$DB105),0) -> #DIV/0! | J105: =IF(SUM(wSUP!$C105:$DB105),$A105*wSUP!J105/SUM(wSUP!$C105:$DB105),0) -> #DIV/0! | ... DB105: =IF(SUM(wSUP!$C105:$DB105),$A105*wSUP!DB105/SUM(wSUP!$C105:$DB105),0) -> #DIV/0!
A106: #DIV/0! | B106: asocw | C106: =IF(SUM(wSUP!$C106:$DB106),$A106*wSUP!C106/SUM(wSUP!$C106:$DB106),0) -> #DIV/0! | D106: =IF(SUM(wSUP!$C106:$DB106),$A106*wSUP!D106/SUM(wSUP!$C106:$DB106),0) -> #DIV/0! | E106: =IF(SUM(wSUP!$C106:$DB106),$A106*wSUP!E106/SUM(wSUP!$C106:$DB106),0) -> #DIV/0! | F106: =IF(SUM(wSUP!$C106:$DB106),$A106*wSUP!F106/SUM(wSUP!$C106:$DB106),0) -> #DIV/0! | G106: =IF(SUM(wSUP!$C106:$DB106),$A106*wSUP!G106/SUM(wSUP!$C106:$DB106),0) -> #DIV/0! | H106: =IF(SUM(wSUP!$C106:$DB106),$A106*wSUP!H106/SUM(wSUP!$C106:$DB106),0) -> #DIV/0! | I106: =IF(SUM(wSUP!$C106:$DB106),$A106*wSUP!I106/SUM(wSUP!$C106:$DB106),0) -> #DIV/0! | J106: =IF(SUM(wSUP!$C106:$DB106),$A106*wSUP!J106/SUM(wSUP!$C106:$DB106),0) -> #DIV/0! | ... DB106: =IF(SUM(wSUP!$C106:$DB106),$A106*wSUP!DB106/SUM(wSUP!$C106:$DB106),0) -> #DIV/0!
A107: #DIV/0! | B107: acult | C107: =IF(SUM(wSUP!$C107:$DB107),$A107*wSUP!C107/SUM(wSUP!$C107:$DB107),0) -> #DIV/0! | D107: =IF(SUM(wSUP!$C107:$DB107),$A107*wSUP!D107/SUM(wSUP!$C107:$DB107),0) -> #DIV/0! | E107: =IF(SUM(wSUP!$C107:$DB107),$A107*wSUP!E107/SUM(wSUP!$C107:$DB107),0) -> #DIV/0! | F107: =IF(SUM(wSUP!$C107:$DB107),$A107*wSUP!F107/SUM(wSUP!$C107:$DB107),0) -> #DIV/0! | G107: =IF(SUM(wSUP!$C107:$DB107),$A107*wSUP!G107/SUM(wSUP!$C107:$DB107),0) -> #DIV/0! | H107: =IF(SUM(wSUP!$C107:$DB107),$A107*wSUP!H107/SUM(wSUP!$C107:$DB107),0) -> #DIV/0! | I107: =IF(SUM(wSUP!$C107:$DB107),$A107*wSUP!I107/SUM(wSUP!$C107:$DB107),0) -> #DIV/0! | J107: =IF(SUM(wSUP!$C107:$DB107),$A107*wSUP!J107/SUM(wSUP!$C107:$DB107),0) -> #DIV/0! | ... DB107: =IF(SUM(wSUP!$C107:$DB107),$A107*wSUP!DB107/SUM(wSUP!$C107:$DB107),0) -> #DIV/0!
A108: #DIV/0! | B108: aarts | C108: =IF(SUM(wSUP!$C108:$DB108),$A108*wSUP!C108/SUM(wSUP!$C108:$DB108),0) -> #DIV/0! | D108: =IF(SUM(wSUP!$C108:$DB108),$A108*wSUP!D108/SUM(wSUP!$C108:$DB108),0) -> #DIV/0! | E108: =IF(SUM(wSUP!$C108:$DB108),$A108*wSUP!E108/SUM(wSUP!$C108:$DB108),0) -> #DIV/0! | F108: =IF(SUM(wSUP!$C108:$DB108),$A108*wSUP!F108/SUM(wSUP!$C108:$DB108),0) -> #DIV/0! | G108: =IF(SUM(wSUP!$C108:$DB108),$A108*wSUP!G108/SUM(wSUP!$C108:$DB108),0) -> #DIV/0! | H108: =IF(SUM(wSUP!$C108:$DB108),$A108*wSUP!H108/SUM(wSUP!$C108:$DB108),0) -> #DIV/0! | I108: =IF(SUM(wSUP!$C108:$DB108),$A108*wSUP!I108/SUM(wSUP!$C108:$DB108),0) -> #DIV/0! | J108: =IF(SUM(wSUP!$C108:$DB108),$A108*wSUP!J108/SUM(wSUP!$C108:$DB108),0) -> #DIV/0! | ... DB108: =IF(SUM(wSUP!$C108:$DB108),$A108*wSUP!DB108/SUM(wSUP!$C108:$DB108),0) -> #DIV/0!
A109: #DIV/0! | B109: aosrv | C109: =IF(SUM(wSUP!$C109:$DB109),$A109*wSUP!C109/SUM(wSUP!$C109:$DB109),0) -> #DIV/0! | D109: =IF(SUM(wSUP!$C109:$DB109),$A109*wSUP!D109/SUM(wSUP!$C109:$DB109),0) -> #DIV/0! | E109: =IF(SUM(wSUP!$C109:$DB109),$A109*wSUP!E109/SUM(wSUP!$C109:$DB109),0) -> #DIV/0! | F109: =IF(SUM(wSUP!$C109:$DB109),$A109*wSUP!F109/SUM(wSUP!$C109:$DB109),0) -> #DIV/0! | G109: =IF(SUM(wSUP!$C109:$DB109),$A109*wSUP!G109/SUM(wSUP!$C109:$DB109),0) -> #DIV/0! | H109: =IF(SUM(wSUP!$C109:$DB109),$A109*wSUP!H109/SUM(wSUP!$C109:$DB109),0) -> #DIV/0! | I109: =IF(SUM(wSUP!$C109:$DB109),$A109*wSUP!I109/SUM(wSUP!$C109:$DB109),0) -> #DIV/0! | J109: =IF(SUM(wSUP!$C109:$DB109),$A109*wSUP!J109/SUM(wSUP!$C109:$DB109),0) -> #DIV/0! | ... DB109: =IF(SUM(wSUP!$C109:$DB109),$A109*wSUP!DB109/SUM(wSUP!$C109:$DB109),0) -> #DIV/0!
A110: #DIV/0! | B110: adsrv | C110: =IF(SUM(wSUP!$C110:$DB110),$A110*wSUP!C110/SUM(wSUP!$C110:$DB110),0) -> #DIV/0! | D110: =IF(SUM(wSUP!$C110:$DB110),$A110*wSUP!D110/SUM(wSUP!$C110:$DB110),0) -> #DIV/0! | E110: =IF(SUM(wSUP!$C110:$DB110),$A110*wSUP!E110/SUM(wSUP!$C110:$DB110),0) -> #DIV/0! | F110: =IF(SUM(wSUP!$C110:$DB110),$A110*wSUP!F110/SUM(wSUP!$C110:$DB110),0) -> #DIV/0! | G110: =IF(SUM(wSUP!$C110:$DB110),$A110*wSUP!G110/SUM(wSUP!$C110:$DB110),0) -> #DIV/0! | H110: =IF(SUM(wSUP!$C110:$DB110),$A110*wSUP!H110/SUM(wSUP!$C110:$DB110),0) -> #DIV/0! | I110: =IF(SUM(wSUP!$C110:$DB110),$A110*wSUP!I110/SUM(wSUP!$C110:$DB110),0) -> #DIV/0! | J110: =IF(SUM(wSUP!$C110:$DB110),$A110*wSUP!J110/SUM(wSUP!$C110:$DB110),0) -> #DIV/0! | ... DB110: =IF(SUM(wSUP!$C110:$DB110),$A110*wSUP!DB110/SUM(wSUP!$C110:$DB110),0) -> #DIV/0!
A111: #DIV/0! | B111: atrdc | C111: =IF(SUM(wSUP!$C111:$DB111),$A111*wSUP!C111/SUM(wSUP!$C111:$DB111),0) -> 0 | D111: =IF(SUM(wSUP!$C111:$DB111),$A111*wSUP!D111/SUM(wSUP!$C111:$DB111),0) -> 0 | E111: =IF(SUM(wSUP!$C111:$DB111),$A111*wSUP!E111/SUM(wSUP!$C111:$DB111),0) -> 0 | F111: =IF(SUM(wSUP!$C111:$DB111),$A111*wSUP!F111/SUM(wSUP!$C111:$DB111),0) -> 0 | G111: =IF(SUM(wSUP!$C111:$DB111),$A111*wSUP!G111/SUM(wSUP!$C111:$DB111),0) -> 0 | H111: =IF(SUM(wSUP!$C111:$DB111),$A111*wSUP!H111/SUM(wSUP!$C111:$DB111),0) -> 0 | I111: =IF(SUM(wSUP!$C111:$DB111),$A111*wSUP!I111/SUM(wSUP!$C111:$DB111),0) -> 0 | J111: =IF(SUM(wSUP!$C111:$DB111),$A111*wSUP!J111/SUM(wSUP!$C111:$DB111),0) -> 0 | ... DB111: =IF(SUM(wSUP!$C111:$DB111),$A111*wSUP!DB111/SUM(wSUP!$C111:$DB111),0) -> 0

Sheet wMAC
A1: Macro SAM
A2: Workings
C4: mact | D4: mcom | E4: mtrc | F4: mlab | G4: mlnd | H4: mcap | I4: ment | J4: mhhd | K4: mgov | L4: matx | M4: mctx | N4: mdtx | O4: metx | P4: mftx | Q4: mmtx | R4: mstx | S4: mvtx | T4: mxtx | U4: ms-i | V4: mg-i | W4: mstk | X4: mrow | Y4: mtot
B5: mact | D5: =C27 -> #DIV/0! | Y5: =SUM(C5:X5) -> #DIV/0! | Z5: {=Y5:Y26-TRANSPOSE(C27:X27)} -> #DIV/0!
B6: mcom | C6: =SUT!O6 -> #DIV/0! | E6: =SUT!P6 -> #DIV/0! | J6: =H34 -> #DIV/0! | K6: =H35 -> 0 | U6: =H37 -> -1998.9009 | V6: =H38 -> 1998.9009 | W6: =H39 -> 0 | X6: =H40 -> 0 | Y6: =SUM(C6:X6) -> #DIV/0! | Z6: #DIV/0!
B7: mtrc | D7: =SUT!L6 -> #DIV/0! | Y7: =SUM(C7:X7) -> #DIV/0! | Z7: #DIV/0!
B8: mlab | C8: =SUM(USE!C112:DB112) -> #DIV/0! | X8: =S36 -> 19.263854 | Y8: =SUM(C8:X8) -> #DIV/0! | Z8: #DIV/0!
B9: mlnd | C9: =SUM(USE!C113:DB113) -> #DIV/0! | X9: =S37 -> 0 | Y9: =SUM(C9:X9) -> #DIV/0! | Z9: #DIV/0!
B10: mcap | C10: =SUM(USE!C114:DB114) -> #DIV/0! | X10: =S38 -> 21.74132 | Y10: =SUM(C10:X10) -> #DIV/0! | Z10: #DIV/0!
B11: ment | H11: =Y10-SUM(H12:H26) -> #DIV/0! | K11: =O35 -> 0 | X11: =S40 -> 98.215884 | Y11: =SUM(C11:X11) -> #DIV/0! | Z11: #DIV/0!
B12: mhhd | F12: =Y8-SUM(F13:F26) -> #DIV/0! | G12: =Y9-SUM(G13:G26) -> #DIV/0! | I12: =Y11-SUM(I13:I26) -> #DIV/0! | K12: =O36 -> 248.01459 | X12: =S39 -> 662.20001 | Y12: =SUM(C12:X12) -> #DIV/0! | Z12: #DIV/0!
B13: mgov | F13: =L46 -> 0 | G13: =L47 -> 0 | H13: =L48 -> 0 | I13: =L50 -> 18.658538 | J13: =L49 -> 432.46991 | L13: {=TRANSPOSE(Y14:Y22)} -> #DIV/0! | M13: #DIV/0! | N13: 1267.9941 | O13: #DIV/0! | P13: 38.241166 | Q13: #DIV/0! | R13: #DIV/0! | S13: #DIV/0! | T13: #DIV/0! | X13: =L51 -> 686.19194 | Y13: =SUM(C13:X13) -> #DIV/0! | Z13: #DIV/0!
B14: matx | C14: =L39 -> #DIV/0! | Y14: =SUM(C14:X14) -> #DIV/0! | Z14: #DIV/0!
B15: mctx | D15: =L40 -> #DIV/0! | Y15: =SUM(C15:X15) -> #DIV/0! | Z15: #DIV/0!
B16: mdtx | I16: =L35 -> 432.89809 | J16: =L34 -> 835.09604 | Y16: =SUM(C16:X16) -> 1267.9941 | Z16: 0
B17: metx | D17: =L41 -> #DIV/0! | Y17: =SUM(C17:X17) -> #DIV/0! | Z17: #DIV/0!
B18: mftx | F18: =L36 -> 0 | G18: =L37 -> 0 | H18: =L38 -> 38.241166 | Y18: =SUM(C18:X18) -> 38.241166 | Z18: 0
B19: mmtx | D19: =L42 -> #DIV/0! | Y19: =SUM(C19:X19) -> #DIV/0! | Z19: #DIV/0!
B20: mstx | D20: =L43 -> #DIV/0! | Y20: =SUM(C20:X20) -> #DIV/0! | Z20: #DIV/0!
B21: mvtx | D21: =L44 -> #DIV/0! | Y21: =SUM(C21:X21) -> #DIV/0! | Z21: #DIV/0!
B22: mxtx | D22: =L45 -> #DIV/0! | Y22: =SUM(C22:X22) -> #DIV/0! | Z22: #DIV/0!
B23: ms-i | I23: =I29*Y11 -> #DIV/0! | J23: =Y12-SUM(J5:J22,J25:J26) -> #DIV/0! | K23: =O51 -> #DIV/0! | X23: =S42 -> -724.4617 | Y23: =SUM(C23:X23) -> #DIV/0! | Z23: #DIV/0!
B24: mg-i | U24: =V27 -> 1998.9009 | Y24: =SUM(C24:X24) -> 1998.9009 | Z24: 0
B25: mstk | U25: =W27 -> 0 | Y25: =SUM(C25:X25) -> 0 | Z25: 0
B26: mrow | D26: =H43 -> 0 | F26: =V36 -> 59.218529 | G26: =V37 -> 0 | H26: =V38 -> 421.17383 | I26: =V40 -> 6.3768699 | J26: =V39 -> 72.601948 | K26: =O37 -> 203.78013 | Y26: =SUM(C26:X26) -> 763.15131 | Z26: 0
B27: mtot | C27: =SUM(C5:C26) -> #DIV/0! | D27: =SUM(D5:D26) -> #DIV/0! | E27: =SUM(E5:E26) -> #DIV/0! | F27: =SUM(F5:F26) -> #DIV/0! | G27: =SUM(G5:G26) -> #DIV/0! | H27: =SUM(H5:H26) -> #DIV/0! | I27: =SUM(I5:I26) -> #DIV/0! | J27: =SUM(J5:J26) -> #DIV/0! | ... X27: =SUM(X5:X26) -> 763.15131
H29: Exogenous savings rate | I29: 0.0823 | J29: =J23/J27 -> #DIV/0!
C31: National accounts | J31: Government account | Q31: Current account
C32: Receipts | F32: Payments | J32: Revenues | M32: Expenditures | Q32: Receipts | T32: Payments
D33: Orig. | E33: Used | G33: Orig. | H33: Used | K33: Orig. | L33: Used | N33: Orig. | O33: Used | R33: Orig. | S33: Used | U33: Orig. | V33: Used
C34: GDPfc | D34: =wGDPp!D7 -> #DIV/0! | E34: =D34 -> #DIV/0! | F34: Private consumption | G34: =wGDPe!D7 -> 0 | H34: =E46-SUM(H35:H36,H39:H40)+H43 -> #DIV/0! | J34: Personal tax | K34: =wGFS!C13 -> 835.09604 | L34: =K34 -> 835.09604 | M34: Consumption | N34: =wGFS!E13 -> 2092.9503 | O34: =H35 -> 0 | Q34: Export goods | R34: =wBOP!C11 -> 4218.9202 | S34: =IF(H41<>0,H41,R34/SUM($R$34:$R$35)*$H$40) -> 0 | T34: Import goods | U34: =wBOP!E11 -> 7308.8389 | V34: =IF(H44<>0,H44,U34/SUM($U$34:$U$35)*$H$43) -> 0
C35: Indirect taxes | D35: =wGDPp!K4 -> 1157 | E35: =D35 -> 1157 | F35: Government consumption | G35: =wGDPe!D8 -> 0 | H35: =G35 -> 0 | J35: Corporate tax | K35: =wGFS!C14 -> 432.89809 | L35: =K35 -> 432.89809 | M35: Households | N35: =wGFS!E14 -> 0 | O35: =N35 -> 0 | Q35: Export services | R35: =wBOP!C12 -> 1424.7745 | S35: =IF(H42<>0,H42,R35/SUM($R$34:$R$35)*$H$40) -> 0 | T35: Import services | U35: =wBOP!E12 -> 1305.9994 | V35: =IF(H45<>0,H45,U35/SUM($U$34:$U$35)*$H$43) -> 0
F36: Gross fixed capital formation | G36: =wGDPe!D9 -> 0 | H36: =G36 -> 0 | J36: Labor tax | K36: =wGFS!C15 -> 0 | L36: =K36 -> 0 | M36: Enterprises | N36: =wGFS!E15 -> 248.01459 | O36: =N36 -> 248.01459 | Q36: Labor | R36: =wBOP!C13 -> 19.263854 | S36: =R36 -> 19.263854 | T36: Labor | U36: =wBOP!E13 -> 59.218529 | V36: =U36 -> 59.218529
F37: Private | H37: =H36-H38 -> -1998.9009 | J37: Land tax | K37: =wGFS!C16 -> 0 | L37: =K37 -> 0 | M37: Rest of world | N37: =wGFS!E16 -> 203.78013 | O37: =N37 -> 203.78013 | Q37: Land | R37: =wBOP!C14 -> 0 | S37: =R37 -> 0 | T37: Land | U37: =wBOP!E14 -> 0 | V37: =U37 -> 0
F38: Public | H38: =O56 -> 1998.9009 | J38: Capital tax | K38: =wGFS!C17 -> 38.241166 | L38: =K38 -> 38.241166 | N38: =wGFS!E17 -> 0 | Q38: Capital | R38: =wBOP!C15 -> 21.74132 | S38: =R38 -> 21.74132 | T38: Capital | U38: =wBOP!E15 -> 421.17383 | V38: =U38 -> 421.17383
F39: Changes in inventories | G39: =wGDPe!D10 -> 0 | H39: =G39 -> 0 | J39: Subsidies (production) | K39: =wGFS!C18 -> #DIV/0! | L39: =K39/SUM($K$39:$K$45)*$E$35 -> #DIV/0! | N39: =wGFS!E18 -> 0 | Q39: Households | R39: =wBOP!C16 -> 662.20001 | S39: =R39 -> 662.20001 | T39: Households | U39: =wBOP!E16 -> 72.601948 | V39: =U39 -> 72.601948
F40: Exports | G40: =wGDPe!D11 -> 0 | H40: =SUM(H41:H42) -> 0 | J40: Customs duties | K40: =wGFS!C19 -> #DIV/0! | L40: =K40/SUM($K$39:$K$45)*$E$35 -> #DIV/0! | N40: =wGFS!E19 -> 0 | Q40: Enterprises | R40: =wBOP!C17 -> 98.215884 | S40: =R40 -> 98.215884 | T40: Enterprises | U40: =wBOP!E17 -> 6.3768699 | V40: =U40 -> 6.3768699
F41: Goods | G41: =wGDPe!D12 -> 0 | H41: =G41 -> 0 | J41: Exports | K41: =wGFS!C20 -> #DIV/0! | L41: =K41/SUM($K$39:$K$45)*$E$35 -> #DIV/0! | N41: =wGFS!E20 -> 0 | Q41: Government | R41: =wBOP!C18 -> 358.11541 | S41: =L51 -> 686.19194 | T41: Government | U41: =wBOP!E18 -> 11.396738 | V41: =O37 -> 203.78013
F42: Services | G42: =wGDPe!D13 -> 0 | H42: =G42 -> 0 | J42: Import excise duties | K42: =wGFS!C21 -> #DIV/0! | L42: =K42/SUM($K$39:$K$45)*$E$35 -> #DIV/0! | N42: =wGFS!E21 -> 0 | Q42: Balance | R42: =wBOP!C19 -> 2382.3751 | S42: =V43-SUM(S34:S41) -> -724.4617
F43: Imports | G43: =wGDPe!D14 -> 0 | H43: =SUM(H44:H45) -> 0 | J43: Subsidies (products) | K43: =wGFS!C22 -> #DIV/0! | L43: =K43/SUM($K$39:$K$45)*$E$35 -> #DIV/0! | N43: =wGFS!E22 -> 0 | Q43: Total | R43: =SUM(R34:R42) -> 9185.6062 | S43: =SUM(S34:S42) -> 763.15131 | T43: Total | U43: =SUM(U34:U42) -> 9185.6062 | V43: =SUM(V34:V42) -> 763.15131
F44: Goods | G44: =wGDPe!D15 -> 0 | H44: =G44 -> 0 | J44: VAT | K44: =wGFS!C23 -> #DIV/0! | L44: =K44/SUM($K$39:$K$45)*$E$35 -> #DIV/0! | N44: =wGFS!E23 -> 0 | T44: Difference | U44: =U43-R43 -> 0 | V44: =V43-S43 -> 0
F45: Services | G45: =wGDPe!D16 -> 0 | H45: =G45 -> 0 | J45: Excise & Others | K45: =wGFS!C24 -> #DIV/0! | L45: =K45/SUM($K$39:$K$45)*$E$35 -> #DIV/0! | N45: =wGFS!E24 -> 0
C46: Total | D46: =SUM(D34:D45) -> #DIV/0! | E46: =SUM(E34:E45) -> #DIV/0! | F46: Total | G46: =SUM(G34:G40)-G43 -> 0 | H46: =SUM(H34:H36,H39:H40)-H43 -> #DIV/0! | J46: Labor | K46: =wGFS!C25 -> 0 | L46: =K46 -> 0 | N46: =wGFS!E25 -> 0
F47: Difference | G47: =G46-D46 -> #DIV/0! | H47: =H46-E46 -> #DIV/0! | J47: Land | K47: =wGFS!C26 -> 0 | L47: =K47 -> 0 | N47: =wGFS!E26 -> 0
J48: Capital | K48: =wGFS!C27 -> 0 | L48: =K48 -> 0 | N48: =wGFS!E27 -> 0
D49: Supply-Use Table, 2017 | J49: Households | K49: =wGFS!C28 -> 432.46991 | L49: =K49 -> 432.46991 | N49: =wGFS!E28 -> 0
D50: Receipts | F50: Payments | J50: Enterprises | K50: =wGFS!C29 -> 18.658538 | L50: =K50 -> 18.658538 | N50: =wGFS!E29 -> 0
E51: Orig. | G51: Orig. | J51: Rest of world | K51: =wGFS!C30 -> 686.19194 | L51: =K51 -> 686.19194 | M51: Savings | N51: =wGFS!E30 -> -308.06127 | O51: =L52-SUM(O34:O50) -> #DIV/0! | V51: exp | W51: exp | X51: exp | Y51: exp | Z51: inc | AA51: inc
D52: GDPfc | E52: 7040.6969 | F52: Household Final Consumption Expenditure | G52: 5438.5455 | J52: Total | K52: =SUM(K34:K51) -> #DIV/0! | L52: =SUM(L34:L51) -> #DIV/0! | M52: Total | N52: =SUM(N34:N51) -> 2236.6837 | O52: =SUM(O34:O51) -> #DIV/0! | V52: hhd | W52: gov | X52: ftax | Y52: row | Z52: gov | AA52: row
D53: Indirect taxes | E53: 653.53732 | F53: General Government and NGO Final Consumption Expenditure | G53: 1429.3238 | M53: Difference | N53: =N52-K52 -> #DIV/0! | O53: =O52-L52 -> #DIV/0! | U53: mlab | V53: =F12/$F$27 -> #DIV/0! | W53: =F13/$F$27 -> #DIV/0! | X53: =F18/$F$27 -> #DIV/0! | Y53: =F26/$F$27 -> #DIV/0! | Z53: =K8/$Y8 -> #DIV/0! | AA53: =X8/$Y8 -> #DIV/0!
F54: Gross capital formation | G54: 1797.2623 | U54: mlnd | V54: =G12/$G$27 -> #DIV/0! | W54: =G13/$G$27 -> #DIV/0! | X54: =G18/$G$27 -> #DIV/0! | Y54: =G26/$G$27 -> #DIV/0! | Z54: =K9/$Y9 -> #DIV/0! | AA54: =X9/$Y9 -> #DIV/0!
F55: Exports of Goods & Services | G55: 1579.5017 | N55: Orig. | O55: Used | U55: mcap | V55: =H12/$H$27 -> #DIV/0! | W55: =H13/$H$27 -> #DIV/0! | X55: =H18/$H$27 -> #DIV/0! | Y55: =H26/$H$27 -> #DIV/0! | Z55: =K10/$Y10 -> #DIV/0! | AA55: =X10/$Y10 -> #DIV/0!
F56: Goods | G56: =G55-G57 -> 883.21671 | M56: Public investment level | N56: =wGFS!B36 -> 1998.9009 | O56: =N56 -> 1998.9009
F57: Services | G57: 696.28499
F58: Imports of Goods & Services | G58: 2550.3991
F59: Goods | G59: =G58-G60 -> 1981.2242 | S59: inc | T59: inc | U59: inc | V59: inc | W59: exp | X59: exp | Y59: exp | Z59: exp | AA59: exp
F60: Services | G60: 569.17484 | S60: fac | T60: ent | U60: gov | V60: row | W60: con | X60: gov | Y60: dtax | Z60: s-i | AA60: row
D61: Total | E61: =SUM(E52:E60) -> 7694.2342 | F61: Total | G61: =SUM(G52:G55)-G58 -> 7694.2342 | R61: mhhd | S61: =Y12-SUM(T61:V61) -> #DIV/0! | T61: =I12 -> #DIV/0! | U61: =K12 -> 248.01459 | V61: =X12 -> 662.20001 | W61: =J6 -> #DIV/0! | X61: =J13 -> 432.46991 | Y61: =J16 -> 835.09604 | Z61: =J23 -> #DIV/0! | AA61: =J26 -> 72.601948
F62: Difference | G62: =G61-E61 -> 1.0004442e-11 | S62: =S61/SUM($S$61:$V$61) -> #DIV/0! | T62: =T61/SUM($S$61:$V$61) -> #DIV/0! | U62: =U61/SUM($S$61:$V$61) -> #DIV/0! | V62: =V61/SUM($S$61:$V$61) -> #DIV/0! | W62: =W61/SUM($W$61:$AA$61) -> #DIV/0! | X62: =X61/SUM($W$61:$AA$61) -> #DIV/0! | Y62: =Y61/SUM($W$61:$AA$61) -> #DIV/0! | Z62: =Z61/SUM($W$61:$AA$61) -> #DIV/0! | AA62: =AA61/SUM($W$61:$AA$61) -> #DIV/0!

Sheet wGDPe
A1: Gross Domestic Product by Expenditure Category, currrent prices in billion Frw
A2: Workings
F3: =Notes!B5 -> 2024 | G3: Year
F4: 1 | G4: Scaling (multiplier)
E6: Map | F6: Selected | H6: 2010 | I6: 2011 | J6: 2012 | K6: 2013 | L6: 2014 | M6: 2015 | N6: 2016 | O6: 2017 | P6: 2018 | Q6: 2019 | R6: 2020 | S6: 2021 | T6: 2022 | U6: 2023 | V6: 2024 | W6: 2022 | X6: 2022 | Y6: 2022 | Z6: 2022 | AA6: 2022 | AB6: 2022 | AC6: 2022 | AD6: 2022 | AE6: 2022 | AF6: 2022 | AG6: 2022 | AH6: 2022 | AI6: 2022 | AJ6: 2022 | AK6: 2022 | AL6: 2022 | AM6: 2022 | AN6: 2022 | AO6: 2022 | AP6: 2022 | AQ6: 2022 | AR6: 2022 | AS6: 2022 | AT6: 2022 | AU6: 2022 | AV6: 2022 | AW6: 2022 | AX6: 2022 | AY6: 2022 | AZ6: 2022 | BA6: 2022 | BB6: 2022 | BC6: 2022 | BD6: 2022 | BE6: 2022 | BF6: 2022 | BG6: 2022 | BH6: 2022 | BI6: 2022 | BJ6: 2022 | BK6: 2022 | BL6: 2022 | BM6: 2022 | BN6: 2022 | BO6: 2022 | BP6: 2022 | BQ6: 2022 | BR6: 2022 | BS6: 2022 | BT6: 2022 | BU6: 2022 | BV6: 2022 | BW6: 2022 | BX6: 2022 | BY6: 2022 | BZ6: 2022 | CA6: 2022 | CB6: 2022 | CC6: 2022 | CD6: 2022 | CE6: 2022 | CF6: 2022 | CG6: 2022 | CH6: 2022 | CI6: 2022 | CJ6: 2022 | CK6: 2022 | CL6: 2022 | CM6: 2022 | CN6: 2022 | CO6: 2022 | CP6: 2022 | CQ6: 2022 | CR6: 2022 | CS6: 2022 | CT6: 2022 | CU6: 2022 | CV6: 2022 | CW6: 2022 | CX6: 2022 | CY6: 2022 | CZ6: 2022 | DA6: 2022 | DB6: 2022 | DC6: 2022 | DD6: 2022 | DE6: 2022 | DF6: 2022 | DG6: 2022 | DH6: 2022 | DI6: 2022 | DJ6: 2022 | DK6: 2022 | DL6: 2022 | DM6: 2022 | DN6: 2022 | DO6: 2022 | DP6: 2022 | DQ6: 2022 | DR6: 2022 | DS6: 2022 | DT6: 2022 | DU6: 2022 | DV6: 2022 | DW6: 2022 | DX6: 2022 | DY6: 2022 | DZ6: 2022 | EA6: 2022 | EB6: 2022 | EC6: 2022 | ED6: 2022 | EE6: 2022 | EF6: 2022 | EG6: 2022 | EH6: 2022 | EI6: 2022 | EJ6: 2022 | EK6: 2022 | EL6: 2022 | EM6: 2022 | EN6: 2022 | EO6: 2022 | EP6: 2022 | EQ6: 2022 | ER6: 2022 | ES6: 2022 | ET6: 2022 | EU6: 2022 | EV6: 2022 | EW6: 2022 | EX6: 2022 | EY6: 2022 | EZ6: 2022 | FA6: 2022 | FB6: 2022 | FC6: 2022 | FD6: 2022 | FE6: 2022 | FF6: 2022 | FG6: 2022 | FH6: 2022 | FI6: 2022 | FJ6: 2022 | FK6: 2022 | FL6: 2022 | FM6: 2022 | FN6: 2022 | FO6: 2022 | FP6: 2022 | FQ6: 2022 | FR6: 2022 | FS6: 2022 | FT6: 2022 | FU6: 2022 | FV6: 2022 | FW6: 2022 | FX6: 2022 | FY6: 2022 | FZ6: 2022 | GA6: 2022 | GB6: 2022 | GC6: 2022 | GD6: 2022 | GE6: 2022 | GF6: 2022 | GG6: 2022 | GH6: 2022 | GI6: 2022 | GJ6: 2022 | GK6: 2022 | GL6: 2022 | GM6: 2022 | GN6: 2022 | GO6: 2022 | GP6: 2022 | GQ6: 2022 | GR6: 2022 | GS6: 2022 | GT6: 2022 | GU6: 2022 | GV6: 2022 | GW6: 2022 | GX6: 2022 | GY6: 2022 | GZ6: 2022 | HA6: 2022 | HB6: 2022 | HC6: 2022 | HD6: 2022 | HE6: 2022 | HF6: 2022 | HG6: 2022 | HH6: 2022 | HI6: 2022 | HJ6: 2022 | HK6: 2022 | HL6: 2022 | HM6: 2022 | HN6: 2022 | HO6: 2022 | HP6: 2022 | HQ6: 2022 | HR6: 2022 | HS6: 2022 | HT6: 2022 | HU6: 2022 | HV6: 2022 | HW6: 2022 | HX6: 2022 | HY6: 2022 | HZ6: 2022 | IA6: 2022 | IB6: 2022 | IC6: 2022 | ID6: 2022 | IE6: 2022 | IF6: 2022 | IG6: 2022 | IH6: 2022 | II6: 2022 | IJ6: 2022 | IK6: 2022 | IL6: 2022 | IM6: 2022 | IN6: 2022 | IO6: 2022 | IP6: 2022 | IQ6: 2022 | IR6: 2022 | IS6: 2022 | IT6: 2022 | IU6: 2022 | IV6: 2022 | IW6: 2022 | IX6: 2022 | IY6: 2022 | IZ6: 2022 | JA6: 2022 | JB6: 2022 | JC6: 2022 | JD6: 2022 | JE6: 2022 | JF6: 2022 | JG6: 2022 | JH6: 2022 | JI6: 2022 | JJ6: 2022 | JK6: 2022 | JL6: 2022 | JM6: 2022 | JN6: 2022 | JO6: 2022 | JP6: 2022 | JQ6: 2022 | JR6: 2022 | JS6: 2022 | JT6: 2022 | JU6: 2022 | JV6: 2022 | JW6: 2022 | JX6: 2022 | JY6: 2022 | JZ6: 2022 | KA6: 2022 | KB6: 2022 | KC6: 2022 | KD6: 2022 | KE6: 2022 | KF6: 2022 | KG6: 2022 | KH6: 2022 | KI6: 2022 | KJ6: 2022 | KK6: 2022 | KL6: 2022 | KM6: 2022 | KN6: 2022 | KO6: 2022 | KP6: 2022 | KQ6: 2022 | KR6: 2022 | KS6: 2022 | KT6: 2022 | KU6: 2022 | KV6: 2022 | KW6: 2022 | KX6: 2022 | KY6: 2022 | KZ6: 2022 | LA6: 2022 | LB6: 2022 | LC6: 2022 | LD6: 2022 | LE6: 2022 | LF6: 2022 | LG6: 2022 | LH6: 2022 | LI6: 2022 | LJ6: 2022 | LK6: 2022 | LL6: 2022 | LM6: 2022 | LN6: 2022 | LO6: 2022 | LP6: 2022 | LQ6: 2022 | LR6: 2022 | LS6: 2022 | LT6: 2022 | LU6: 2022 | LV6: 2022 | LW6: 2022 | LX6: 2022 | LY6: 2022 | LZ6: 2022 | MA6: 2022 | MB6: 2022 | MC6: 2022 | MD6: 2022 | ME6: 2022 | MF6: 2022 | MG6: 2022 | MH6: 2022 | MI6: 2022 | MJ6: 2022 | MK6: 2022 | ML6: 2022 | MM6: 2022 | MN6: 2022 | MO6: 2022 | MP6: 2022 | MQ6: 2022 | MR6: 2022 | MS6: 2022 | MT6: 2022 | MU6: 2022 | MV6: 2022 | MW6: 2022 | MX6: 2022 | MY6: 2022 | MZ6: 2022 | NA6: 2022 | NB6: 2022 | NC6: 2022 | ND6: 2022 | NE6: 2022 | NF6: 2022 | NG6: 2022 | NH6: 2022 | NI6: 2022 | NJ6: 2022 | NK6: 2022 | NL6: 2022 | NM6: 2022 | NN6: 2022 | NO6: 2022 | NP6: 2022 | NQ6: 2022 | NR6: 2022 | NS6: 2022 | NT6: 2022 | NU6: 2022 | NV6: 2022 | NW6: 2022 | NX6: 2022 | NY6: 2022 | NZ6: 2022 | OA6: 2022 | OB6: 2022 | OC6: 2022 | OD6: 2022 | OE6: 2022 | OF6: 2022 | OG6: 2022 | OH6: 2022 | OI6: 2022 | OJ6: 2022 | OK6: 2022 | OL6: 2022 | OM6: 2022 | ON6: 2022 | OO6: 2022 | OP6: 2022 | OQ6: 2022 | OR6: 2022 | OS6: 2022 | OT6: 2022 | OU6: 2022 | OV6: 2022 | OW6: 2022 | OX6: 2022 | OY6: 2022 | OZ6: 2022 | PA6: 2022 | PB6: 2022 | PC6: 2022 | PD6: 2022 | PE6: 2022 | PF6: 2022 | PG6: 2022 | PH6: 2022 | PI6: 2022 | PJ6: 2022 | PK6: 2022 | PL6: 2022 | PM6: 2022 | PN6: 2022 | PO6: 2022 | PP6: 2022 | PQ6: 2022 | PR6: 2022 | PS6: 2022 | PT6: 2022 | PU6: 2022 | PV6: 2022 | PW6: 2022 | PX6: 2022 | PY6: 2022 | PZ6: 2022 | QA6: 2022 | QB6: 2022 | QC6: 2022 | QD6: 2022 | QE6: 2022 | QF6: 2022 | QG6: 2022 | QH6: 2022 | QI6: 2022 | QJ6: 2022 | QK6: 2022 | QL6: 2022 | QM6: 2022 | QN6: 2022 | QO6: 2022 | QP6: 2022 | QQ6: 2022 | QR6: 2022 | QS6: 2022 | QT6: 2022 | QU6: 2022 | QV6: 2022 | QW6: 2022 | QX6: 2022 | QY6: 2022 | QZ6: 2022 | RA6: 2022 | RB6: 2022 | RC6: 2022 | RD6: 2022 | RE6: 2022 | RF6: 2022 | RG6: 2022 | RH6: 2022 | RI6: 2022 | RJ6: 2022 | RK6: 2022 | RL6: 2022 | RM6: 2022 | RN6: 2022 | RO6: 2022 | RP6: 2022 | RQ6: 2022 | RR6: 2022 | RS6: 2022 | RT6: 2022 | RU6: 2022 | RV6: 2022 | RW6: 2022 | RX6: 2022 | RY6: 2022 | RZ6: 2022 | SA6: 2022 | SB6: 2022 | SC6: 2022 | SD6: 2022 | SE6: 2022 | SF6: 2022 | SG6: 2022 | SH6: 2022 | SI6: 2022 | SJ6: 2022 | SK6: 2022 | SL6: 2022 | SM6: 2022 | SN6: 2022 | SO6: 2022 | SP6: 2022 | SQ6: 2022 | SR6: 2022 | SS6: 2022 | ST6: 2022 | SU6: 2022 | SV6: 2022 | SW6: 2022 | SX6: 2022 | SY6: 2022 | SZ6: 2022 | TA6: 2022 | TB6: 2022 | TC6: 2022 | TD6: 2022 | TE6: 2022 | TF6: 2022 | TG6: 2022 | TH6: 2022 | TI6: 2022 | TJ6: 2022 | TK6: 2022 | TL6: 2022 | TM6: 2022 | TN6: 2022 | TO6: 2022 | TP6: 2022 | TQ6: 2022 | TR6: 2022 | TS6: 2022 | TT6: 2022 | TU6: 2022 | TV6: 2022 | TW6: 2022 | TX6: 2022 | TY6: 2022 | TZ6: 2022 | UA6: 2022 | UB6: 2022 | UC6: 2022 | UD6: 2022 | UE6: 2022 | UF6: 2022 | UG6: 2022 | UH6: 2022 | UI6: 2022 | UJ6: 2022 | UK6: 2022 | UL6: 2022 | UM6: 2022 | UN6: 2022 | UO6: 2022 | UP6: 2022 | UQ6: 2022 | UR6: 2022 | US6: 2022 | UT6: 2022 | UU6: 2022 | UV6: 2022 | UW6: 2022 | UX6: 2022 | UY6: 2022 | UZ6: 2022 | VA6: 2022 | VB6: 2022 | VC6: 2022 | VD6: 2022 | VE6: 2022 | VF6: 2022 | VG6: 2022 | VH6: 2022 | VI6: 2022 | VJ6: 2022 | VK6: 2022 | VL6: 2022 | VM6: 2022 | VN6: 2022 | VO6: 2022 | VP6: 2022 | VQ6: 2022 | VR6: 2022 | VS6: 2022 | VT6: 2022 | VU6: 2022 | VV6: 2022 | VW6: 2022 | VX6: 2022 | VY6: 2022 | VZ6: 2022 | WA6: 2022 | WB6: 2022 | WC6: 2022 | WD6: 2022 | WE6: 2022 | WF6: 2022 | WG6: 2022 | WH6: 2022 | WI6: 2022 | WJ6: 2022 | WK6: 2022 | WL6: 2022 | WM6: 2022 | WN6: 2022 | WO6: 2022 | WP6: 2022 | WQ6: 2022 | WR6: 2022 | WS6: 2022 | WT6: 2022 | WU6: 2022 | WV6: 2022 | WW6: 2022 | WX6: 2022 | WY6: 2022 | WZ6: 2022 | XA6: 2022 | XB6: 2022 | XC6: 2022 | XD6: 2022 | XE6: 2022 | XF6: 2022 | XG6: 2022 | XH6: 2022 | XI6: 2022 | XJ6: 2022 | XK6: 2022 | XL6: 2022 | XM6: 2022 | XN6: 2022 | XO6: 2022 | XP6: 2022 | XQ6: 2022 | XR6: 2022 | XS6: 2022 | XT6: 2022 | XU6: 2022 | XV6: 2022 | XW6: 2022 | XX6: 2022 | XY6: 2022 | XZ6: 2022 | YA6: 2022 | YB6: 2022 | YC6: 2022 | YD6: 2022 | YE6: 2022 | YF6: 2022 | YG6: 2022 | YH6: 2022 | YI6: 2022 | YJ6: 2022 | YK6: 2022 | YL6: 2022 | YM6: 2022 | YN6: 2022 | YO6: 2022 | YP6: 2022 | YQ6: 2022 | YR6: 2022 | YS6: 2022 | YT6: 2022 | YU6: 2022 | YV6: 2022 | YW6: 2022 | YX6: 2022 | YY6: 2022 | YZ6: 2022 | ZA6: 2022 | ZB6: 2022 | ZC6: 2022 | ZD6: 2022 | ZE6: 2022 | ZF6: 2022 | ZG6: 2022 | ZH6: 2022 | ZI6: 2022 | ZJ6: 2022 | ZK6: 2022 | ZL6: 2022 | ZM6: 2022 | ZN6: 2022 | ZO6: 2022 | ZP6: 2022 | ZQ6: 2022 | ZR6: 2022 | ZS6: 2022 | ZT6: 2022 | ZU6: 2022 | ZV6: 2022 | ZW6: 2022 | ZX6: 2022 | ZY6: 2022 | ZZ6: 2022 | AAA6: 2022 | AAB6: 2022 | AAC6: 2022 | AAD6: 2022 | AAE6: 2022 | AAF6: 2022 | AAG6: 2022 | AAH6: 2022 | AAI6: 2022 | AAJ6: 2022 | AAK6: 2022 | AAL6: 2022 | AAM6: 2022 | AAN6: 2022 | AAO6: 2022 | AAP6: 2022 | AAQ6: 2022 | AAR6: 2022 | AAS6: 2022 | AAT6: 2022 | AAU6: 2022 | AAV6: 2022 | AAW6: 2022 | AAX6: 2022 | AAY6: 2022 | AAZ6: 2022 | ABA6: 2022 | ABB6: 2022 | ABC6: 2022 | ABD6: 2022 | ABE6: 2022 | ABF6: 2022 | ABG6: 2022 | ABH6: 2022 | ABI6: 2022 | ABJ6: 2022 | ABK6: 2022 | ABL6: 2022 | ABM6: 2022 | ABN6: 2022 | ABO6: 2022 | ABP6: 2022 | ABQ6: 2022 | ABR6: 2022 | ABS6: 2022 | ABT6: 2022 | ABU6: 2022 | ABV6: 2022 | ABW6: 2022 | ABX6: 2022 | ABY6: 2022 | ABZ6: 2022 | ACA6: 2022 | ACB6: 2022 | ACC6: 2022 | ACD6: 2022 | ACE6: 2022 | ACF6: 2022 | ACG6: 2022 | ACH6: 2022 | ACI6: 2022 | ACJ6: 2022 | ACK6: 2022 | ACL6: 2022 | ACM6: 2022 | ACN6: 2022 | ACO6: 2022 | ACP6: 2022 | ACQ6: 2022 | ACR6: 2022 | ACS6: 2022 | ACT6: 2022 | ACU6: 2022 | ACV6: 2022 | ACW6: 2022 | ACX6: 2022 | ACY6: 2022 | ACZ6: 2022 | ADA6: 2022 | ADB6: 2022 | ADC6: 2022 | ADD6: 2022 | ADE6: 2022 | ADF6: 2022 | ADG6: 2022 | ADH6: 2022 | ADI6: 2022 | ADJ6: 2022 | ADK6: 2022 | ADL6: 2022 | ADM6: 2022 | ADN6: 2022 | ADO6: 2022 | ADP6: 2022 | ADQ6: 2022 | ADR6: 2022 | ADS6: 2022 | ADT6: 2022 | ADU6: 2022 | ADV6: 2022 | ADW6: 2022 | ADX6: 2022 | ADY6: 2022 | ADZ6: 2022 | AEA6: 2022 | AEB6: 2022 | AEC6: 2022 | AED6: 2022 | AEE6: 2022 | AEF6: 2022 | AEG6: 2022 | AEH6: 2022 | AEI6: 2022 | AEJ6: 2022 | AEK6: 2022 | AEL6: 2022 | AEM6: 2022 | AEN6: 2022 | AEO6: 2022 | AEP6: 2022 | AEQ6: 2022 | AER6: 2022 | AES6: 2022 | AET6: 2022 | AEU6: 2022 | AEV6: 2022 | AEW6: 2022 | AEX6: 2022 | AEY6: 2022 | AEZ6: 2022 | AFA6: 2022 | AFB6: 2022 | AFC6: 2022 | AFD6: 2022 | AFE6: 2022 | AFF6: 2022 | AFG6: 2022 | AFH6: 2022 | AFI6: 2022 | AFJ6: 2022 | AFK6: 2022 | AFL6: 2022 | AFM6: 2022 | AFN6: 2022 | AFO6: 2022 | AFP6: 2022 | AFQ6: 2022 | AFR6: 2022 | AFS6: 2022 | AFT6: 2022 | AFU6: 2022 | AFV6: 2022 | AFW6: 2022 | AFX6: 2022 | AFY6: 2022 | AFZ6: 2022 | AGA6: 2022 | AGB6: 2022 | AGC6: 2022 | AGD6: 2022 | AGE6: 2022 | AGF6: 2022 | AGG6: 2022 | AGH6: 2022 | AGI6: 2022 | AGJ6: 2022 | AGK6: 2022 | AGL6: 2022 | AGM6: 2022 | AGN6: 2022 | AGO6: 2022 | AGP6: 2022 | AGQ6: 2022 | AGR6: 2022 | AGS6: 2022 | AGT6: 2022 | AGU6: 2022 | AGV6: 2022 | AGW6: 2022 | AGX6: 2022 | AGY6: 2022 | AGZ6: 2022 | AHA6: 2022 | AHB6: 2022 | AHC6: 2022 | AHD6: 2022 | AHE6: 2022 | AHF6: 2022 | AHG6: 2022 | AHH6: 2022 | AHI6: 2022 | AHJ6: 2022 | AHK6: 2022 | AHL6: 2022 | AHM6: 2022 | AHN6: 2022 | AHO6: 2022 | AHP6: 2022 | AHQ6: 2022 | AHR6: 2022 | AHS6: 2022 | AHT6: 2022 | AHU6: 2022 | AHV6: 2022 | AHW6: 2022 | AHX6: 2022 | AHY6: 2022 | AHZ6: 2022 | AIA6: 2022 | AIB6: 2022 | AIC6: 2022 | AID6: 2022 | AIE6: 2022 | AIF6: 2022 | AIG6: 2022 | AIH6: 2022 | AII6: 2022 | AIJ6: 2022 | AIK6: 2022 | AIL6: 2022 | AIM6: 2022 | AIN6: 2022 | AIO6: 2022 | AIP6: 2022 | AIQ6: 2022 | AIR6: 2022 | AIS6: 2022 | AIT6: 2022 | AIU6: 2022 | AIV6: 2022 | AIW6: 2022 | AIX6: 2022 | AIY6: 2022 | AIZ6: 2022 | AJA6: 2022 | AJB6: 2022 | AJC6: 2022 | AJD6: 2022 | AJE6: 2022 | AJF6: 2022 | AJG6: 2022 | AJH6: 2022 | AJI6: 2022 | AJJ6: 2022 | AJK6: 2022 | AJL6: 2022 | AJM6: 2022 | AJN6: 2022 | AJO6: 2022 | AJP6: 2022 | AJQ6: 2022 | AJR6: 2022 | AJS6: 2022 | AJT6: 2022 | AJU6: 2022 | AJV6: 2022 | AJW6: 2022 | AJX6: 2022 | AJY6: 2022 | AJZ6: 2022 | AKA6: 2022 | AKB6: 2022 | AKC6: 2022 | AKD6: 2022 | AKE6: 2022 | AKF6: 2022 | AKG6: 2022 | AKH6: 2022 | AKI6: 2022 | AKJ6: 2022 | AKK6: 2022 | AKL6: 2022 | AKM6: 2022 | AKN6: 2022 | AKO6: 2022 | AKP6: 2022 | AKQ6: 2022 | AKR6: 2022 | AKS6: 2022 | AKT6: 2022 | AKU6: 2022 | AKV6: 2022 | AKW6: 2022 | AKX6: 2022 | AKY6: 2022 | AKZ6: 2022 | ALA6: 2022 | ALB6: 2022 | ALC6: 2022 | ALD6: 2022 | ALE6: 2022 | ALF6: 2022 | ALG6: 2022 | ALH6: 2022 | ALI6: 2022 | ALJ6: 2022 | ALK6: 2022 | ALL6: 2022 | ALM6: 2022 | ALN6: 2022 | ALO6: 2022 | ALP6: 2022 | ALQ6: 2022 | ALR6: 2022 | ALS6: 2022 | ALT6: 2022 | ALU6: 2022 | ALV6: 2022 | ALW6: 2022 | ALX6: 2022 | ALY6: 2022 | ALZ6: 2022 | AMA6: 2022 | AMB6: 2022 | AMC6: 2022 | AMD6: 2022 | AME6: 2022 | AMF6: 2022 | AMG6: 2022 | AMH6: 2022 | AMI6: 2022 | AMJ6: 2022 | AMK6: 2022 | AML6: 2022 | AMM6: 2022 | AMN6: 2022 | AMO6: 2022 | AMP6: 2022 | AMQ6: 2022 | AMR6: 2022 | AMS6: 2022 | AMT6: 2022 | AMU6: 2022 | AMV6: 2022 | AMW6: 2022 | AMX6: 2022 | AMY6: 2022 | AMZ6: 2022 | ANA6: 2022 | ANB6: 2022 | ANC6: 2022 | AND6: 2022 | ANE6: 2022 | ANF6: 2022 | ANG6: 2022 | ANH6: 2022 | ANI6: 2022 | ANJ6: 2022 | ANK6: 2022 | ANL6: 2022 | ANM6: 2022 | ANN6: 2022 | ANO6: 2022 | ANP6: 2022 | ANQ6: 2022 | ANR6: 2022 | ANS6: 2022 | ANT6: 2022 | ANU6: 2022 | ANV6: 2022 | ANW6: 2022 | ANX6: 2022 | ANY6: 2022 | ANZ6: 2022 | AOA6: 2022 | AOB6: 2022 | AOC6: 2022 | AOD6: 2022 | AOE6: 2022 | AOF6: 2022 | AOG6: 2022 | AOH6: 2022 | AOI6: 2022 | AOJ6: 2022 | AOK6: 2022 | AOL6: 2022 | AOM6: 2022 | AON6: 2022 | AOO6: 2022 | AOP6: 2022 | AOQ6: 2022 | AOR6: 2022 | AOS6: 2022 | AOT6: 2022 | AOU6: 2022 | AOV6: 2022 | AOW6: 2022 | AOX6: 2022 | AOY6: 2022 | AOZ6: 2022 | APA6: 2022 | APB6: 2022 | APC6: 2022 | APD6: 2022 | APE6: 2022 | APF6: 2022 | APG6: 2022 | APH6: 2022 | API6: 2022 | APJ6: 2022 | APK6: 2022 | APL6: 2022 | APM6: 2022 | APN6: 2022 | APO6: 2022 | APP6: 2022 | APQ6: 2022 | APR6: 2022 | APS6: 2022 | APT6: 2022 | APU6: 2022 | APV6: 2022 | APW6: 2022 | APX6: 2022 | APY6: 2022 | APZ6: 2022 | AQA6: 2022 | AQB6: 2022 | AQC6: 2022 | AQD6: 2022 | AQE6: 2022 | AQF6: 2022 | AQG6: 2022 | AQH6: 2022 | AQI6: 2022 | AQJ6: 2022 | AQK6: 2022 | AQL6: 2022 | AQM6: 2022 | AQN6: 2022 | AQO6: 2022 | AQP6: 2022 | AQQ6: 2022 | AQR6: 2022 | AQS6: 2022 | AQT6: 2022 | AQU6: 2022 | AQV6: 2022 | AQW6: 2022 | AQX6: 2022 | AQY6: 2022 | AQZ6: 2022 | ARA6: 2022 | ARB6: 2022 | ARC6: 2022 | ARD6: 2022 | ARE6: 2022 | ARF6: 2022 | ARG6: 2022 | ARH6: 2022 | ARI6: 2022 | ARJ6: 2022 | ARK6: 2022 | ARL6: 2022 | ARM6: 2022 | ARN6: 2022 | ARO6: 2022 | ARP6: 2022 | ARQ6: 2022 | ARR6: 2022 | ARS6: 2022 | ART6: 2022 | ARU6: 2022 | ARV6: 2022 | ARW6: 2022 | ARX6: 2022 | ARY6: 2022 | ARZ6: 2022 | ASA6: 2022 | ASB6: 2022 | ASC6: 2022 | ASD6: 2022 | ASE6: 2022 | ASF6: 2022 | ASG6: 2022 | ASH6: 2022 | ASI6: 2022 | ASJ6: 2022 | ASK6: 2022 | ASL6: 2022 | ASM6: 2022 | ASN6: 2022 | ASO6: 2022 | ASP6: 2022 | ASQ6: 2022 | ASR6: 2022 | ASS6: 2022 | AST6: 2022 | ASU6: 2022 | ASV6: 2022 | ASW6: 2022 | ASX6: 2022 | ASY6: 2022 | ASZ6: 2022 | ATA6: 2022 | ATB6: 2022 | ATC6: 2022 | ATD6: 2022 | ATE6: 2022 | ATF6: 2022 | ATG6: 2022 | ATH6: 2022 | ATI6: 2022 | ATJ6: 2022 | ATK6: 2022 | ATL6: 2022 | ATM6: 2022 | ATN6: 2022 | ATO6: 2022 | ATP6: 2022 | ATQ6: 2022 | ATR6: 2022 | ATS6: 2022 | ATT6: 2022 | ATU6: 2022 | ATV6: 2022 | ATW6: 2022 | ATX6: 2022 | ATY6: 2022 | ATZ6: 2022 | AUA6: 2022 | AUB6: 2022 | AUC6: 2022 | AUD6: 2022 | AUE6: 2022 | AUF6: 2022 | AUG6: 2022 | AUH6: 2022 | AUI6: 2022 | AUJ6: 2022 | AUK6: 2022 | AUL6: 2022 | AUM6: 2022 | AUN6: 2022 | AUO6: 2022 | AUP6: 2022 | AUQ6: 2022 | AUR6: 2022 | AUS6: 2022 | AUT6: 2022 | AUU6: 2022 | AUV6: 2022 | AUW6: 2022 | AUX6: 2022 | AUY6: 2022 | AUZ6: 2022 | AVA6: 2022 | AVB6: 2022 | AVC6: 2022 | AVD6: 2022 | AVE6: 2022 | AVF6: 2022 | AVG6: 2022 | AVH6: 2022 | AVI6: 2022 | AVJ6: 2022 | AVK6: 2022 | AVL6: 2022 | AVM6: 2022 | AVN6: 2022 | AVO6: 2022 | AVP6: 2022 | AVQ6: 2022 | AVR6: 2022 | AVS6: 2022 | AVT6: 2022 | AVU6: 2022 | AVV6: 2022 | AVW6: 2022 | AVX6: 2022 | AVY6: 2022 | AVZ6: 2022 | AWA6: 2022 | AWB6: 2022 | AWC6: 2022 | AWD6: 2022 | AWE6: 2022 | AWF6: 2022 | AWG6: 2022 | AWH6: 2022 | AWI6: 2022 | AWJ6: 2022 | AWK6: 2022 | AWL6: 2022 | AWM6: 2022 | AWN6: 2022 | AWO6: 2022 | AWP6: 2022 | AWQ6: 2022 | AWR6: 2022 | AWS6: 2022 | AWT6: 2022 | AWU6: 2022 | AWV6: 2022 | AWW6: 2022 | AWX6: 2022 | AWY6: 2022 | AWZ6: 2022 | AXA6: 2022 | AXB6: 2022 | AXC6: 2022 | AXD6: 2022 | AXE6: 2022 | AXF6: 2022 | AXG6: 2022 | AXH6: 2022 | AXI6: 2022 | AXJ6: 2022 | AXK6: 2022 | AXL6: 2022 | AXM6: 2022 | AXN6: 2022 | AXO6: 2022 | AXP6: 2022 | AXQ6: 2022 | AXR6: 2022 | AXS6: 2022 | AXT6: 2022 | AXU6: 2022 | AXV6: 2022 | AXW6: 2022 | AXX6: 2022 | AXY6: 2022 | AXZ6: 2022 | AYA6: 2022 | AYB6: 2022 | AYC6: 2022 | AYD6: 2022 | AYE6: 2022 | AYF6: 2022 | AYG6: 2022 | AYH6: 2022 | AYI6: 2022 | AYJ6: 2022 | AYK6: 2022 | AYL6: 2022 | AYM6: 2022 | AYN6: 2022 | AYO6: 2022 | AYP6: 2022 | AYQ6: 2022 | AYR6: 2022 | AYS6: 2022 | AYT6: 2022 | AYU6: 2022 | AYV6: 2022 | AYW6: 2022 | AYX6: 2022 | AYY6: 2022 | AYZ6: 2022 | AZA6: 2022 | AZB6: 2022 | AZC6: 2022 | AZD6: 2022 | AZE6: 2022 | AZF6: 2022 | AZG6: 2022 | AZH6: 2022 | AZI6: 2022 | AZJ6: 2022 | AZK6: 2022 | AZL6: 2022 | AZM6: 2022 | AZN6: 2022 | AZO6: 2022 | AZP6: 2022 | AZQ6: 2022 | AZR6: 2022 | AZS6: 2022 | AZT6: 2022 | AZU6: 2022 | AZV6: 2022 | AZW6: 2022 | AZX6: 2022 | AZY6: 2022 | AZZ6: 2022 | BAA6: 2022 | BAB6: 2022 | BAC6: 2022 | BAD6: 2022 | BAE6: 2022 | BAF6: 2022 | BAG6: 2022 | BAH6: 2022 | BAI6: 2022 | BAJ6: 2022 | BAK6: 2022 | BAL6: 2022 | BAM6: 2022 | BAN6: 2022 | BAO6: 2022 | BAP6: 2022 | BAQ6: 2022 | BAR6: 2022 | BAS6: 2022 | BAT6: 2022 | BAU6: 2022 | BAV6: 2022 | BAW6: 2022 | BAX6: 2022 | BAY6: 2022 | BAZ6: 2022 | BBA6: 2022 | BBB6: 2022 | BBC6: 2022 | BBD6: 2022 | BBE6: 2022 | BBF6: 2022 | BBG6: 2022 | BBH6: 2022 | BBI6: 2022 | BBJ6: 2022 | BBK6: 2022 | BBL6: 2022 | BBM6: 2022 | BBN6: 2022 | BBO6: 2022 | BBP6: 2022 | BBQ6: 2022 | BBR6: 2022 | BBS6: 2022 | BBT6: 2022 | BBU6: 2022 | BBV6: 2022 | BBW6: 2022 | BBX6: 2022 | BBY6: 2022 | BBZ6: 2022 | BCA6: 2022 | BCB6: 2022 | BCC6: 2022 | BCD6: 2022 | BCE6: 2022 | BCF6: 2022 | BCG6: 2022 | BCH6: 2022 | BCI6: 2022 | BCJ6: 2022 | BCK6: 2022 | BCL6: 2022 | BCM6: 2022 | BCN6: 2022 | BCO6: 2022 | BCP6: 2022 | BCQ6: 2022 | BCR6: 2022 | BCS6: 2022 | BCT6: 2022 | BCU6: 2022 | BCV6: 2022 | BCW6: 2022 | BCX6: 2022 | BCY6: 2022 | BCZ6: 2022 | BDA6: 2022 | BDB6: 2022 | BDC6: 2022 | BDD6: 2022 | BDE6: 2022 | BDF6: 2022 | BDG6: 2022 | BDH6: 2022 | BDI6: 2022 | BDJ6: 2022 | BDK6: 2022 | BDL6: 2022 | BDM6: 2022 | BDN6: 2022 | BDO6: 2022 | BDP6: 2022 | BDQ6: 2022 | BDR6: 2022 | BDS6: 2022 | BDT6: 2022 | BDU6: 2022 | BDV6: 2022 | BDW6: 2022 | BDX6: 2022 | BDY6: 2022 | BDZ6: 2022 | BEA6: 2022 | BEB6: 2022 | BEC6: 2022 | BED6: 2022 | BEE6: 2022 | BEF6: 2022 | BEG6: 2022 | BEH6: 2022 | BEI6: 2022 | BEJ6: 2022 | BEK6: 2022 | BEL6: 2022 | BEM6: 2022 | BEN6: 2022 | BEO6: 2022 | BEP6: 2022 | BEQ6: 2022 | BER6: 2022 | BES6: 2022 | BET6: 2022 | BEU6: 2022 | BEV6: 2022 | BEW6: 2022 | BEX6: 2022 | BEY6: 2022 | BEZ6: 2022 | BFA6: 2022 | BFB6: 2022 | BFC6: 2022 | BFD6: 2022 | BFE6: 2022 | BFF6: 2022 | BFG6: 2022 | BFH6: 2022 | BFI6: 2022 | BFJ6: 2022 | BFK6: 2022 | BFL6: 2022 | BFM6: 2022 | BFN6: 2022 | BFO6: 2022 | BFP6: 2022 | BFQ6: 2022 | BFR6: 2022 | BFS6: 2022 | BFT6: 2022 | BFU6: 2022 | BFV6: 2022 | BFW6: 2022 | BFX6: 2022 | BFY6: 2022 | BFZ6: 2022 | BGA6: 2022 | BGB6: 2022 | BGC6: 2022 | BGD6: 2022 | BGE6: 2022 | BGF6: 2022 | BGG6: 2022 | BGH6: 2022 | BGI6: 2022 | BGJ6: 2022 | BGK6: 2022 | BGL6: 2022 | BGM6: 2022 | BGN6: 2022 | BGO6: 2022 | BGP6: 2022 | BGQ6: 2022 | BGR6: 2022 | BGS6: 2022 | BGT6: 2022 | BGU6: 2022 | BGV6: 2022 | BGW6: 2022 | BGX6: 2022 | BGY6: 2022 | BGZ6: 2022 | BHA6: 2022 | BHB6: 2022 | BHC6: 2022 | BHD6: 2022 | BHE6: 2022 | BHF6: 2022 | BHG6: 2022 | BHH6: 2022 | BHI6: 2022 | BHJ6: 2022 | BHK6: 2022 | BHL6: 2022 | BHM6: 2022 | BHN6: 2022 | BHO6: 2022 | BHP6: 2022 | BHQ6: 2022 | BHR6: 2022 | BHS6: 2022 | BHT6: 2022 | BHU6: 2022 | BHV6: 2022 | BHW6: 2022 | BHX6: 2022 | BHY6: 2022 | BHZ6: 2022 | BIA6: 2022 | BIB6: 2022 | BIC6: 2022 | BID6: 2022 | BIE6: 2022 | BIF6: 2022 | BIG6: 2022 | BIH6: 2022 | BII6: 2022 | BIJ6: 2022 | BIK6: 2022 | BIL6: 2022 | BIM6: 2022 | BIN6: 2022 | BIO6: 2022 | BIP6: 2022 | BIQ6: 2022 | BIR6: 2022 | BIS6: 2022 | BIT6: 2022 | BIU6: 2022 | BIV6: 2022 | BIW6: 2022 | BIX6: 2022 | BIY6: 2022 | BIZ6: 2022 | BJA6: 2022 | BJB6: 2022 | BJC6: 2022 | BJD6: 2022 | BJE6: 2022 | BJF6: 2022 | BJG6: 2022 | BJH6: 2022 | BJI6: 2022 | BJJ6: 2022 | BJK6: 2022 | BJL6: 2022 | BJM6: 2022 | BJN6: 2022 | BJO6: 2022 | BJP6: 2022 | BJQ6: 2022 | BJR6: 2022 | BJS6: 2022 | BJT6: 2022 | BJU6: 2022 | BJV6: 2022 | BJW6: 2022 | BJX6: 2022 | BJY6: 2022 | BJZ6: 2022 | BKA6: 2022 | BKB6: 2022 | BKC6: 2022 | BKD6: 2022 | BKE6: 2022 | BKF6: 2022 | BKG6: 2022 | BKH6: 2022 | BKI6: 2022 | BKJ6: 2022 | BKK6: 2022 | BKL6: 2022 | BKM6: 2022 | BKN6: 2022 | BKO6: 2022 | BKP6: 2022 | BKQ6: 2022 | BKR6: 2022 | BKS6: 2022 | BKT6: 2022 | BKU6: 2022 | BKV6: 2022 | BKW6: 2022 | BKX6: 2022 | BKY6: 2022 | BKZ6: 2022 | BLA6: 2022 | BLB6: 2022 | BLC6: 2022 | BLD6: 2022 | BLE6: 2022 | BLF6: 2022 | BLG6: 2022 | BLH6: 2022 | BLI6: 2022 | BLJ6: 2022 | BLK6: 2022 | BLL6: 2022 | BLM6: 2022 | BLN6: 2022 | BLO6: 2022 | BLP6: 2022 | BLQ6: 2022 | BLR6: 2022 | BLS6: 2022 | BLT6: 2022 | BLU6: 2022 | BLV6: 2022 | BLW6: 2022 | BLX6: 2022 | BLY6: 2022 | BLZ6: 2022 | BMA6: 2022 | BMB6: 2022 | BMC6: 2022 | BMD6: 2022 | BME6: 2022 | BMF6: 2022 | BMG6: 2022 | BMH6: 2022 | BMI6: 2022 | BMJ6: 2022 | BMK6: 2022 | BML6: 2022 | BMM6: 2022 | BMN6: 2022 | BMO6: 2022 | BMP6: 2022 | BMQ6: 2022 | BMR6: 2022 | BMS6: 2022 | BMT6: 2022 | BMU6: 2022 | BMV6: 2022 | BMW6: 2022 | BMX6: 2022 | BMY6: 2022 | BMZ6: 2022 | BNA6: 2022 | BNB6: 2022 | BNC6: 2022 | BND6: 2022 | BNE6: 2022 | BNF6: 2022 | BNG6: 2022 | BNH6: 2022 | BNI6: 2022 | BNJ6: 2022 | BNK6: 2022 | BNL6: 2022 | BNM6: 2022 | BNN6: 2022 | BNO6: 2022 | BNP6: 2022 | BNQ6: 2022 | BNR6: 2022 | BNS6: 2022 | BNT6: 2022 | BNU6: 2022 | BNV6: 2022 | BNW6: 2022 | BNX6: 2022 | BNY6: 2022 | BNZ6: 2022 | BOA6: 2022 | BOB6: 2022 | BOC6: 2022 | BOD6: 2022 | BOE6: 2022 | BOF6: 2022 | BOG6: 2022 | BOH6: 2022 | BOI6: 2022 | BOJ6: 2022 | BOK6: 2022 | BOL6: 2022 | BOM6: 2022 | BON6: 2022 | BOO6: 2022 | BOP6: 2022 | BOQ6: 2022 | BOR6: 2022 | BOS6: 2022 | BOT6: 2022 | BOU6: 2022 | BOV6: 2022 | BOW6: 2022 | BOX6: 2022 | BOY6: 2022 | BOZ6: 2022 | BPA6: 2022 | BPB6: 2022 | BPC6: 2022 | BPD6: 2022 | BPE6: 2022 | BPF6: 2022 | BPG6: 2022 | BPH6: 2022 | BPI6: 2022 | BPJ6: 2022 | BPK6: 2022 | BPL6: 2022 | BPM6: 2022 | BPN6: 2022 | BPO6: 2022 | BPP6: 2022 | BPQ6: 2022 | BPR6: 2022 | BPS6: 2022 | BPT6: 2022 | BPU6: 2022 | BPV6: 2022 | BPW6: 2022 | BPX6: 2022 | BPY6: 2022 | BPZ6: 2022 | BQA6: 2022 | BQB6: 2022 | BQC6: 2022 | BQD6: 2022 | BQE6: 2022 | BQF6: 2022 | BQG6: 2022 | BQH6: 2022 | BQI6: 2022 | BQJ6: 2022 | BQK6: 2022 | BQL6: 2022 | BQM6: 2022 | BQN6: 2022 | BQO6: 2022 | BQP6: 2022 | BQQ6: 2022 | BQR6: 2022 | BQS6: 2022 | BQT6: 2022 | BQU6: 2022 | BQV6: 2022 | BQW6: 2022 | BQX6: 2022 | BQY6: 2022 | BQZ6: 2022 | BRA6: 2022 | BRB6: 2022 | BRC6: 2022 | BRD6: 2022 | BRE6: 2022 | BRF6: 2022 | BRG6: 2022 | BRH6: 2022 | BRI6: 2022 | BRJ6: 2022 | BRK6: 2022 | BRL6: 2022 | BRM6: 2022 | BRN6: 2022 | BRO6: 2022 | BRP6: 2022 | BRQ6: 2022 | BRR6: 2022 | BRS6: 2022 | BRT6: 2022 | BRU6: 2022 | BRV6: 2022 | BRW6: 2022 | BRX6: 2022 | BRY6: 2022 | BRZ6: 2022 | BSA6: 2022 | BSB6: 2022 | BSC6: 2022 | BSD6: 2022 | BSE6: 2022 | BSF6: 2022 | BSG6: 2022 | BSH6: 2022 | BSI6: 2022 | BSJ6: 2022 | BSK6: 2022 | BSL6: 2022 | BSM6: 2022 | BSN6: 2022 | BSO6: 2022 | BSP6: 2022 | BSQ6: 2022 | BSR6: 2022 | BSS6: 2022 | BST6: 2022 | BSU6: 2022 | BSV6: 2022 | BSW6: 2022 | BSX6: 2022 | BSY6: 2022 | BSZ6: 2022 | BTA6: 2022 | BTB6: 2022 | BTC6: 2022 | BTD6: 2022 | BTE6: 2022 | BTF6: 2022 | BTG6: 2022 | BTH6: 2022 | BTI6: 2022 | BTJ6: 2022 | BTK6: 2022 | BTL6: 2022 | BTM6: 2022 | BTN6: 2022 | BTO6: 2022 | BTP6: 2022 | BTQ6: 2022 | BTR6: 2022 | BTS6: 2022 | BTT6: 2022 | BTU6: 2022 | BTV6: 2022 | BTW6: 2022 | BTX6: 2022 | BTY6: 2022 | BTZ6: 2022 | BUA6: 2022 | BUB6: 2022 | BUC6: 2022 | BUD6: 2022 | BUE6: 2022 | BUF6: 2022 | BUG6: 2022 | BUH6: 2022 | BUI6: 2022 | BUJ6: 2022 | BUK6: 2022 | BUL6: 2022 | BUM6: 2022 | BUN6: 2022 | BUO6: 2022 | BUP6: 2022 | BUQ6: 2022 | BUR6: 2022 | BUS6: 2022 | BUT6: 2022 | BUU6: 2022 | BUV6: 2022 | BUW6: 2022 | BUX6: 2022 | BUY6: 2022 | BUZ6: 2022 | BVA6: 2022 | BVB6: 2022 | BVC6: 2022 | BVD6: 2022 | BVE6: 2022 | BVF6: 2022 | BVG6: 2022 | BVH6: 2022 | BVI6: 2022 | BVJ6: 2022 | BVK6: 2022 | BVL6: 2022 | BVM6: 2022 | BVN6: 2022 | BVO6: 2022 | BVP6: 2022 | BVQ6: 2022 | BVR6: 2022 | BVS6: 2022 | BVT6: 2022 | BVU6: 2022 | BVV6: 2022 | BVW6: 2022 | BVX6: 2022 | BVY6: 2022 | BVZ6: 2022 | BWA6: 2022 | BWB6: 2022 | BWC6: 2022 | BWD6: 2022 | BWE6: 2022 | BWF6: 2022 | BWG6: 2022 | BWH6: 2022 | BWI6: 2022 | BWJ6: 2022 | BWK6: 2022 | BWL6: 2022 | BWM6: 2022 | BWN6: 2022 | BWO6: 2022 | BWP6: 2022 | BWQ6: 2022 | BWR6: 2022 | BWS6: 2022 | BWT6: 2022 | BWU6: 2022 | BWV6: 2022 | BWW6: 2022 | BWX6: 2022 | BWY6: 2022 | BWZ6: 2022 | BXA6: 2022 | BXB6: 2022 | BXC6: 2022 | BXD6: 2022 | BXE6: 2022 | BXF6: 2022 | BXG6: 2022 | BXH6: 2022 | BXI6: 2022 | BXJ6: 2022 | BXK6: 2022 | BXL6: 2022 | BXM6: 2022 | BXN6: 2022 | BXO6: 2022 | BXP6: 2022 | BXQ6: 2022 | BXR6: 2022 | BXS6: 2022 | BXT6: 2022 | BXU6: 2022 | BXV6: 2022 | BXW6: 2022 | BXX6: 2022 | BXY6: 2022 | BXZ6: 2022 | BYA6: 2022 | BYB6: 2022 | BYC6: 2022 | BYD6: 2022 | BYE6: 2022 | BYF6: 2022 | BYG6: 2022 | BYH6: 2022 | BYI6: 2022 | BYJ6: 2022 | BYK6: 2022 | BYL6: 2022 | BYM6: 2022 | BYN6: 2022 | BYO6: 2022 | BYP6: 2022 | BYQ6: 2022 | BYR6: 2022 | BYS6: 2022 | BYT6: 2022 | BYU6: 2022 | BYV6: 2022 | BYW6: 2022 | BYX6: 2022 | BYY6: 2022 | BYZ6: 2022 | BZA6: 2022 | BZB6: 2022 | BZC6: 2022 | BZD6: 2022 | BZE6: 2022 | BZF6: 2022 | BZG6: 2022 | BZH6: 2022 | BZI6: 2022 | BZJ6: 2022 | BZK6: 2022 | BZL6: 2022 | BZM6: 2022 | BZN6: 2022
B7: 1 | C7: Private consumption | D7: =SUMIF($E$7:$E$30,$B7,$F$7:$F$30) -> 0 | F7: =SUMIF($H$6:$T$6,F$3,H7:T7) -> 0 | G7: Gross Domestic Product | H7: 3571 | I7: 4133 | J7: 4703 | K7: 5056 | L7: 5623 | M7: 6152 | N7: 6845 | O7: 7694 | P7: 8299 | Q7: 9308 | R7: 9594 | S7: 10953 | T7: 13720 | U7: 16626 | V7: 18785
B8: 2 | C8: Government consumption | D8: =SUMIF($E$7:$E$30,$B8,$F$7:$F$30) -> 0 | F8: =SUMIF($H$6:$T$6,F$3,H8:T8) -> 0 | G8: Total final consumption expenditure | H8: 3404 | I8: 3870 | J8: 4392 | K8: 4625 | L8: 5234 | M8: 5820 | N8: 6349 | O8: 6831 | P8: 7573 | Q8: 8125 | R8: 8906 | S8: 9699 | T8: 12409 | U8: 15289 | V8: 16446
B9: 3 | C9: Gross fixed capital formation | D9: =SUMIF($E$7:$E$30,$B9,$F$7:$F$30) -> 0 | E9: 2 | F9: =SUMIF($H$6:$T$6,F$3,H9:T9) -> 0 | G9: Government | H9: 467 | I9: 497 | J9: 609 | K9: 651 | L9: 803 | M9: 852 | N9: 1031 | O9: 1155 | P9: 1224 | Q9: 1472 | R9: 1572 | S9: 1856 | T9: 2337 | U9: 2707 | V9: 3207
B10: 4 | C10: Changes in inventories | D10: =SUMIF($E$7:$E$30,$B10,$F$7:$F$30) -> 0 | E10: 1 | F10: =SUMIF($H$6:$T$6,F$3,H10:T10) -> 0 | G10: Households and NGOs | H10: 2935 | I10: 3367 | J10: 3776 | K10: 3965 | L10: 4422 | M10: 4960 | N10: 5317 | O10: 5676 | P10: 6349 | Q10: 6653 | R10: 7334 | S10: 7843 | T10: 10072 | U10: 12582 | V10: 13237
B11: 5 | C11: Exports | D11: =SUMIF($E$7:$E$30,$B11,$F$7:$F$30) -> 0 | F11: =SUMIF($H$6:$T$6,F$3,H11:T11) -> 0 | G11: Gross capital formation | H11: 733 | I11: 864 | J11: 1096 | K11: 1235 | L11: 1306 | M11: 1491 | N11: 1773 | O11: 1834 | P11: 1853 | Q11: 2516 | R11: 2275 | S11: 2928 | T11: 3532 | U11: 3810 | V11: 4515
B12: 6 | C12: Goods | D12: =SUMIF($E$7:$E$30,$B12,$F$7:$F$30) -> 0 | E12: 3 | F12: =SUMIF($H$6:$T$6,F$3,H12:T12) -> 0 | G12: Gross fixed capital formation | H12: 710 | I12: 848 | J12: 1064 | K12: 1197 | L12: 1273 | M12: 1474 | N12: 1858 | O12: 1748 | P12: 1906 | Q12: 2505 | R12: 2431 | S12: 2916 | T12: 3370 | U12: 4430 | V12: 5462
B13: 7 | C13: Services | D13: =SUMIF($E$7:$E$30,$B13,$F$7:$F$30) -> 0 | F13: =SUMIF($H$6:$T$6,F$3,H13:T13) -> 0 | G13: Construction | H13: 486 | I13: 629 | J13: 768 | K13: 886 | L13: 946 | M13: 1107 | N13: 1201 | O13: 1143 | P13: 1238 | Q13: 1651 | R13: 1574 | S13: 1878 | T13: 2229 | U13: 2867 | V13: 3636
B14: 8 | C14: Imports | D14: =SUMIF($E$7:$E$30,$B14,$F$7:$F$30) -> 0 | F14: =SUMIF($H$6:$T$6,F$3,H14:T14) -> 0 | G14: Other | H14: 223 | I14: 218 | J14: 297 | K14: 312 | L14: 327 | M14: 367 | N14: 657 | O14: 605 | P14: 668 | Q14: 853 | R14: 857 | S14: 1038 | T14: 1141 | U14: 1563 | V14: 1826
B15: 9 | C15: Goods | D15: =SUMIF($E$7:$E$30,$B15,$F$7:$F$30) -> 0 | E15: 4 | F15: =SUMIF($H$6:$T$6,F$3,H15:T15) -> 0 | G15: Change in inventories | H15: 24 | I15: 16 | J15: 31 | K15: 38 | L15: 33 | M15: 17 | N15: -85 | O15: 86 | P15: -53 | Q15: 11 | R15: -156 | S15: 12 | T15: 161 | U15: -620 | V15: -947
B16: 10 | C16: Services | D16: =SUMIF($E$7:$E$30,$B16,$F$7:$F$30) -> 0 | F16: =SUMIF($H$6:$T$6,F$3,H16:T16) -> 0 | G16: Resource balance | H16: -564 | I16: -595 | J16: -778 | K16: -794 | L16: -909 | M16: -1152 | N16: -1276 | O16: -971 | P16: -1126 | Q16: -1333 | R16: -1587 | S16: -1675 | T16: -2221 | U16: -2477 | V16: -2175
C17: GDP at market prices | D17: =SUM(D7:D11)-D14 -> 0 | E17: 5 | F17: =SUMIF($H$6:$T$6,F$3,H17:T17) -> 0 | G17: Exports of goods & services | H17: 384 | I17: 523 | J17: 564 | K17: 682 | L17: 780 | M17: 814 | N17: 1056 | O17: 1580 | P17: 1752 | Q17: 2031 | R17: 1855 | S17: 2136 | T17: 3084 | U17: 4158 | V17: 5790
C18: Indirect taxes | D18: =wGDPp!K4 -> 1157 | E18: 6 | F18: =SUMIF($H$6:$T$6,F$3,H18:T18) -> 0 | G18: Goods (fob) | H18: 168 | I18: 298 | J18: 337 | K18: 419 | L18: 429 | M18: 403 | N18: 391 | O18: 853 | P18: 956 | Q18: 1108 | R18: 1361 | S18: 1500 | T18: 2187 | U18: 2914 | V18: 4350
C19: GDP at factor cost | D19: =D17-D18 -> -1157 | E19: 7 | F19: =SUMIF($H$6:$T$6,F$3,H19:T19) -> 0 | G19: Services | H19: 215 | I19: 225 | J19: 227 | K19: 263 | L19: 351 | M19: 411 | N19: 665 | O19: 726 | P19: 796 | Q19: 924 | R19: 493 | S19: 636 | T19: 897 | U19: 1244 | V19: 1440
C20: Discrepency | D20: =D19-wGDPp!K3 -> -7961 | E20: 8 | F20: =SUMIF($H$6:$T$6,F$3,H20:T20) -> 0 | G20: Imports of goods & services | H20: 948 | I20: 1118 | J20: 1342 | K20: 1477 | L20: 1689 | M20: 1966 | N20: 2332 | O20: 2550 | P20: 2878 | Q20: 3365 | R20: 3442 | S20: 3811 | T20: 5305 | U20: 6634 | V20: 7965
E21: 9 | F21: =SUMIF($H$6:$T$6,F$3,H21:T21) -> 0 | G21: Goods (fob) | H21: 659 | I21: 790 | J21: 994 | K21: 1046 | L21: 1174 | M21: 1221 | N21: 1475 | O21: 1672 | P21: 1968 | Q21: 2436 | R21: 2928 | S21: 3221 | T21: 4351 | U21: 5462 | V21: 6655
E22: 10 | F22: =SUMIF($H$6:$T$6,F$3,H22:T22) -> 0 | G22: Services | H22: 288 | I22: 328 | J22: 348 | K22: 430 | L22: 514 | M22: 746 | N22: 857 | O22: 878 | P22: 910 | Q22: 929 | R22: 514 | S22: 590 | T22: 954 | U22: 1172 | V22: 1311
F23: =SUMIF($H$6:$T$6,F$3,H23:T23) -> 0
F24: =SUMIF($H$6:$T$6,F$3,H24:T24) -> 0
F25: =SUMIF($H$6:$T$6,F$3,H25:T25) -> 0
F26: =SUMIF($H$6:$T$6,F$3,H26:T26) -> 0
F27: =SUMIF($H$6:$T$6,F$3,H27:T27) -> 0
F28: =SUMIF($H$6:$T$6,F$3,H28:T28) -> 0
F29: =SUMIF($H$6:$T$6,F$3,H29:T29) -> 0
F30: =SUMIF($H$6:$T$6,F$3,H30:T30) -> 0

Sheet wGFS
A1: Fiscal Accounts
A2: Workings
B4: 2023/24 | C4: Year 1
B5: 2024/25 | C5: Year 2
B6: 0.001 | C6: Scaling (multiplier) | H6: Consolidated Financial Statements of the Government of Rwanda
J9: 2015/16 | K9: 2016/17 | L9: 2017/18 | M9: 2018/19 | N9: 2019/20 | O9: 2020/21 | P9: 2021/22 | Q9: 2022/23 | R9: 2023/24 | S9: 2024/25
H10: Revenues
G11: =AVERAGE(SUMIF($M$9:$T$9,$B$4,$M11:$T11),SUMIF($M$9:$T$9,$B$5,$M11:$T11)) -> 2829.194 | H11: Tax Revenues | I11: 1.6.3 | J11: 1000456.9 | K11: 1103747.1 | L11: 1252754.3 | M11: 1402.5223 | N11: 1475.6087 | O11: 1621.6893 | P11: 1876.7736 | Q11: 2287.3718 | R11: 2593.3215 | S11: 3065.0666
B12: Revenues | D12: Expenditures | G12: =AVERAGE(SUMIF($M$9:$T$9,$B$4,$M12:$T12),SUMIF($M$9:$T$9,$B$5,$M12:$T12)) -> 1267.9941 | H12: Taxes on Income, Profits or Capital Gains | J12: 381280.25 | K12: 446375.68 | L12: 511930.24 | M12: 595.37385 | N12: 641.47554 | O12: 702.55261 | P12: 853.55685 | Q12: 1022.7421 | R12: 1178.5718 | S12: 1357.4164
B13: Personal tax | C13: =D53 -> 835.09604 | D13: Consumption | E13: =G37+G41 -> 2092.9503 | G13: =AVERAGE(SUMIF($M$9:$T$9,$B$4,$M13:$T13),SUMIF($M$9:$T$9,$B$5,$M13:$T13)) -> 0 | H13: Taxes on Payroll and Workforce, (payable by individuals o/w tax on wage income) | J13: 0 | K13: 0 | L13: 0 | M13: 0 | N13: 0 | O13: 0 | P13: 0 | Q13: 0 | R13: 0 | S13: 0
B14: Corporate tax | C14: =D54 -> 432.89809 | D14: Households | E14: =G59+G60 -> 0 | G14: =AVERAGE(SUMIF($M$9:$T$9,$B$4,$M14:$T14),SUMIF($M$9:$T$9,$B$5,$M14:$T14)) -> 38.241166 | H14: Tax on Property Income | J14: 1594.102 | K14: 1235.2098 | L14: 1119.4775 | M14: 19.372401 | N14: 4.642878 | O14: 19.443675 | P14: 17.107114 | Q14: 22.576045 | R14: 30.501624 | S14: 45.980709
B15: Labor tax | C15: =G13 -> 0 | D15: Enterprises | E15: =G52+G53+G62+G65+G66+G67+G68+G69+G57 -> 248.01459 | G15: =AVERAGE(SUMIF($M$9:$T$9,$B$4,$M15:$T15),SUMIF($M$9:$T$9,$B$5,$M15:$T15)) -> 1304.5136 | H15: Taxes on goods and services | J15: 516.76898 | K15: 530.02666 | L15: 605.14217 | M15: 676.03064 | N15: 712.20881 | O15: 775.95022 | P15: 873.08969 | Q15: 1030.423 | R15: 1189.7617 | S15: 1419.2655
B16: Land tax | D16: Rest of world | E16: =G55+G56+G63 -> 203.78013 | H16: VAT on imports | Q16: 217.87647 | R16: 239.03447 | S16: 296.79587
B17: Capital tax | C17: =G14 -> 38.241166 | H17: VAT on domestic goods | Q17: 471.83337 | R17: 553.72665 | S17: 666.59784
B18: Subsidies (production) | C18: =D42 -> #DIV/0! | G18: =AVERAGE(SUMIF($M$9:$T$9,$B$4,$M18:$T18),SUMIF($M$9:$T$9,$B$5,$M18:$T18)) -> 218.44512 | H18: Taxes on international trade and transactions | J18: 170758.02 | K18: 169268.69 | L18: 182527.83 | M18: 111.74537 | N18: 117.28148 | O18: 123.74278 | P18: 133.01994 | Q18: 211.63063 | R18: 194.48632 | S18: 242.40391
B19: Customs duties | C19: =D43 -> #DIV/0! | G19: =AVERAGE(SUMIF($M$9:$T$9,$B$4,$M19:$T19),SUMIF($M$9:$T$9,$B$5,$M19:$T19)) -> 477.16374 | H19: Administrative fees, Fines, Penalties and Licenses | I19: 1.6.4 | J19: 121089.84 | K19: 200132.98 | L19: 203275.63 | M19: 267.75506 | N19: 289.92303 | O19: 385.41375 | P19: 401.22505 | Q19: 400.88814 | R19: 460.01543 | S19: 494.31205
B20: Exports | C20: =D44 -> #DIV/0! | G20: =AVERAGE(SUMIF($M$9:$T$9,$B$4,$M20:$T20),SUMIF($M$9:$T$9,$B$5,$M20:$T20)) -> 18.658538 | H20: Property Income | J20: 7993.0876 | K20: 5406.4619 | L20: 5702.8889 | M20: 4.7370362 | N20: 20.327639 | O20: 19.584411 | P20: 13.349444 | Q20: 14.63022 | R20: 24.476468 | S20: 12.840609
B21: Import excise duties | C21: =D45 -> #DIV/0! | G21: =AVERAGE(SUMIF($M$9:$T$9,$B$4,$M21:$T21),SUMIF($M$9:$T$9,$B$5,$M21:$T21)) -> 388.96787 | H21: Sales of goods and services (incl. PKO) | J21: 86958.989 | K21: 78892.601 | L21: 96343.689 | M21: 254.60815 | N21: 239.49113 | O21: 301.35411 | P21: 328.6631 | Q21: 321.33059 | R21: 395.34517 | S21: 382.59058
B22: Subsidies (products) | C22: =D46 -> #DIV/0! | G22: =AVERAGE(SUMIF($M$9:$T$9,$B$4,$M22:$T22),SUMIF($M$9:$T$9,$B$5,$M22:$T22)) -> 43.502035 | H22: Fines, penalties, and forfeits | J22: 26137.763 | K22: 115833.92 | L22: 101229.05 | M22: 8.4098653 | N22: 19.975779 | O22: 29.170398 | P22: 36.726644 | Q22: 64.92733 | R22: 40.193787 | S22: 46.810283
B23: VAT | C23: =D47 -> #DIV/0! | G23: =AVERAGE(SUMIF($M$9:$T$9,$B$4,$M23:$T23),SUMIF($M$9:$T$9,$B$5,$M23:$T23)) -> 1103.6943 | H23: Borrowings (not used in SAM-CGE) | I23: 1.6.5 | J23: 335883.79 | K23: 386526.67 | L23: 465174.92 | M23: 556.25292 | N23: 1159.9911 | O23: 753.80757 | P23: 886.59911 | Q23: 887.24472 | R23: 1182.7197 | S23: 1024.6689
B24: Excise & Others | C24: =D48 -> #DIV/0! | G24: =AVERAGE(SUMIF($M$9:$T$9,$B$4,$M24:$T24),SUMIF($M$9:$T$9,$B$5,$M24:$T24)) -> -227.50269 | H24: Domestic borrowings | I24: 1.6.5 | J24: 90301.173 | K24: 52989.25 | L24: 88820.986 | M24: 107.94095 | N24: 205.97138 | O24: 96.535129 | P24: -145.05364 | Q24: 78.736102 | R24: -124.49441 | S24: -330.51096
B25: Labor | G25: =AVERAGE(SUMIF($M$9:$T$9,$B$4,$M25:$T25),SUMIF($M$9:$T$9,$B$5,$M25:$T25)) -> 1331.197 | H25: External borrowings | I25: 1.6.5 | J25: 245582.62 | K25: 333537.42 | L25: 376353.93 | M25: 448.31197 | N25: 954.01969 | O25: 657.27244 | P25: 1031.6527 | Q25: 808.50862 | R25: 1307.2142 | S25: 1355.1799
B26: Land | G26: =AVERAGE(SUMIF($M$9:$T$9,$B$4,$M26:$T26),SUMIF($M$9:$T$9,$B$5,$M26:$T26)) -> 686.19194 | H26: Grants | I26: 1.6.6 | J26: 442748.1 | K26: 357350.9 | L26: 333536.19 | M26: 394.75006 | N26: 437.5584 | O26: 561.08817 | P26: 824.18436 | Q26: 711.30725 | R26: 757.79141 | S26: 614.59247
B27: Capital | G27: =AVERAGE(SUMIF($M$9:$T$9,$B$4,$M27:$T27),SUMIF($M$9:$T$9,$B$5,$M27:$T27)) -> 0 | H27: Capital Receipts | I27: 1.6.7 | J27: 6142.0213 | K27: 28842.124 | L27: 4459.64
B28: Households | C28: =G21+G22 -> 432.46991 | G28: =AVERAGE(SUMIF($M$9:$T$9,$B$4,$M28:$T28),SUMIF($M$9:$T$9,$B$5,$M28:$T28)) -> 0 | H28: Disposal of tangible fixed assets | J28: 1843.7337 | K28: 2728.2849 | L28: 228.9499
B29: Enterprises | C29: =G20+G27+G32 -> 18.658538 | G29: =AVERAGE(SUMIF($M$9:$T$9,$B$4,$M29:$T29),SUMIF($M$9:$T$9,$B$5,$M29:$T29)) -> 0 | H29: Sale of Inventories | J29: 42.820844 | K29: 2011.4739 | L29: 1713.6012
B30: Rest of world | C30: =G26 -> 686.19194 | D30: Savings | E30: =G73+G82-G23+G70 -> -308.06127 | G30: =AVERAGE(SUMIF($M$9:$T$9,$B$4,$M30:$T30),SUMIF($M$9:$T$9,$B$5,$M30:$T30)) -> 0 | H30: Sale of Non-Produced Assets | J30: 0 | K30: 1611.9811 | L30: 2262.0889
B31: Total | C31: =SUM(C13:C30) -> #DIV/0! | D31: Total | E31: =SUM(E13:E30) -> 2236.6837 | G31: =AVERAGE(SUMIF($M$9:$T$9,$B$4,$M31:$T31),SUMIF($M$9:$T$9,$B$5,$M31:$T31)) -> 0 | H31: Sale of Financial Assets - Domestic | J31: 4255.4668 | K31: 22490.384 | L31: 255
D32: Difference | E32: =E31-C31 -> #DIV/0! | G32: =AVERAGE(SUMIF($M$9:$T$9,$B$4,$M32:$T32),SUMIF($M$9:$T$9,$B$5,$M32:$T32)) -> 0 | H32: Other income | I32: 1.6.8 | J32: 45687.686 | K32: 41274.145 | L32: 54140.402
B33: GFS error | C33: =C31-G35 -> #DIV/0! | E33: =E31-G81-G82 -> -1618.1848 | G33: =AVERAGE(SUMIF($M$9:$T$9,$B$4,$M33:$T33),SUMIF($M$9:$T$9,$B$5,$M33:$T33)) -> 0 | H33: Voluntary transfers other than grants | J33: 18688.332 | K33: 5853.7855 | L33: 1402.5495
G34: =AVERAGE(SUMIF($M$9:$T$9,$B$4,$M34:$T34),SUMIF($M$9:$T$9,$B$5,$M34:$T34)) -> 0 | H34: Miscellaneous and unidentified Revenue | J34: 26999.354 | K34: 35420.36 | L34: 52737.853
G35: =AVERAGE(SUMIF($M$9:$T$9,$B$4,$M35:$T35),SUMIF($M$9:$T$9,$B$5,$M35:$T35)) -> 3992.5497 | H35: Total Revenue (excl. borrowing) | I35: 1.6.27 | J35: 1952008.4 | K35: 2117873.9 | L35: 2313341 | M35: 2065.0274 | N35: 2203.0901 | O35: 2568.1912 | P35: 3102.183 | Q35: 3399.5672 | R35: 3811.1284 | S35: 4173.9711
B36: =G73 -> 1998.9009 | C36: Public investment level | G36: =AVERAGE(SUMIF($M$9:$T$9,$B$4,$M36:$T36),SUMIF($M$9:$T$9,$B$5,$M36:$T36)) -> 0 | H36: Expenditure
G37: =AVERAGE(SUMIF($M$9:$T$9,$B$4,$M37:$T37),SUMIF($M$9:$T$9,$B$5,$M37:$T37)) -> 1095.5812 | H37: Compensation of Employees (incl. in EBU, LG) | I37: 1.6.9 | J37: 374376.49 | K37: 405730.88 | L37: 429673.62 | M37: 498.35881 | N37: 453.27649 | O37: 551.47122 | P37: 648.98335 | Q37: 830.28505 | R37: 1004.4009 | S37: 1186.7615
G38: =AVERAGE(SUMIF($M$9:$T$9,$B$4,$M38:$T38),SUMIF($M$9:$T$9,$B$5,$M38:$T38)) -> 0 | H38: Salaries in cash | J38: 345883.83 | K38: 373592.81 | L38: 391767.13
B39: Indirect taxes | G39: =AVERAGE(SUMIF($M$9:$T$9,$B$4,$M39:$T39),SUMIF($M$9:$T$9,$B$5,$M39:$T39)) -> 0 | H39: Social contribution | J39: 28492.655 | K39: 32138.07 | L39: 37667.663
C40: Estimate | D40: Scaled | E40: Diff. | G40: =AVERAGE(SUMIF($M$9:$T$9,$B$4,$M40:$T40),SUMIF($M$9:$T$9,$B$5,$M40:$T40)) -> 0 | H40: Salaries arrears | J40: 0 | K40: 0 | L40: 238.82692
B41: Total | C41: =SUM(C42:C48) -> #DIV/0! | D41: =SUM(D42:D48) -> #DIV/0! | E41: =D41-C41 -> #DIV/0! | G41: =AVERAGE(SUMIF($M$9:$T$9,$B$4,$M41:$T41),SUMIF($M$9:$T$9,$B$5,$M41:$T41)) -> 997.36902 | H41: Use of Goods and Services (incl. in EBU, LG) | I41: 1.6.10 | J41: 639287.25 | K41: 782912.53 | L41: 812371.27 | M41: 572.40144 | N41: 681.87331 | O41: 712.76386 | P41: 870.40128 | Q41: 1014.2229 | R41: 1007.3899 | S41: 987.34817
B42: Subsidies (production) | C42: =wTAX!F4 -> #DIV/0! | D42: =C42/SUM($C$42,$C$46:$C$48)*$G$17 -> #DIV/0! | E42: =D42-C42 -> #DIV/0! | G42: =AVERAGE(SUMIF($M$9:$T$9,$B$4,$M42:$T42),SUMIF($M$9:$T$9,$B$5,$M42:$T42)) -> 0 | H42: General Services | J42: 119957.3 | K42: 130467.85 | L42: 135158.96
B43: Customs duties | C43: =wTAX!J4 -> 0 | D43: =C43/SUM($C$43:$C$45)*$G$18 -> #DIV/0! | E43: =D43-C43 -> #DIV/0! | G43: =AVERAGE(SUMIF($M$9:$T$9,$B$4,$M43:$T43),SUMIF($M$9:$T$9,$B$5,$M43:$T43)) -> 0 | H43: Professional, Research services | J43: 140819.8 | K43: 150037.22 | L43: 170722.34
B44: Exports | C44: =wTAX!N4 -> 0 | D44: =C44/SUM($C$43:$C$45)*$G$18 -> #DIV/0! | E44: =D44-C44 -> #DIV/0! | G44: =AVERAGE(SUMIF($M$9:$T$9,$B$4,$M44:$T44),SUMIF($M$9:$T$9,$B$5,$M44:$T44)) -> 0 | H44: Transport and travel | J44: 64027.36 | K44: 70233.157 | L44: 76031.233
B45: Import excise duties | C45: =wTAX!R4 -> 0 | D45: =C45/SUM($C$43:$C$45)*$G$18 -> #DIV/0! | E45: =D45-C45 -> #DIV/0! | G45: =AVERAGE(SUMIF($M$9:$T$9,$B$4,$M45:$T45),SUMIF($M$9:$T$9,$B$5,$M45:$T45)) -> 0 | H45: Maintenance, Repairs and Spare Parts | J45: 53160.519 | K45: 64493.223 | L45: 70698.747
B46: Subsidies (products) | C46: =wTAX!V4 -> #DIV/0! | D46: =C46/SUM($C$42,$C$46:$C$48)*$G$17 -> #DIV/0! | E46: =D46-C46 -> #DIV/0! | G46: =AVERAGE(SUMIF($M$9:$T$9,$B$4,$M46:$T46),SUMIF($M$9:$T$9,$B$5,$M46:$T46)) -> 0 | H46: Tools and Small Equipment | J46: 112.257 | K46: 185.52444 | L46: 1890.1327
B47: VAT | C47: =wTAX!Z4 -> #DIV/0! | D47: =C47/SUM($C$42,$C$46:$C$48)*$G$17 -> #DIV/0! | E47: =D47-C47 -> #DIV/0! | G47: =AVERAGE(SUMIF($M$9:$T$9,$B$4,$M47:$T47),SUMIF($M$9:$T$9,$B$5,$M47:$T47)) -> 0 | H47: Training Costs | J47: 18972.55 | K47: 22005.469 | L47: 32036.116
B48: Excise & Others | C48: =wTAX!AD4 -> #DIV/0! | D48: =C48/SUM($C$42,$C$46:$C$48)*$G$17 -> #DIV/0! | E48: =D48-C48 -> #DIV/0! | G48: =AVERAGE(SUMIF($M$9:$T$9,$B$4,$M48:$T48),SUMIF($M$9:$T$9,$B$5,$M48:$T48)) -> 0 | H48: Supplies and services | J48: 211201.17 | K48: 329912.85 | L48: 307381.38
G49: =AVERAGE(SUMIF($M$9:$T$9,$B$4,$M49:$T49),SUMIF($M$9:$T$9,$B$5,$M49:$T49)) -> 0 | H49: Arrears | J49: 6617.6332 | K49: 0 | L49: 1490.0689
B50: Direct taxes | G50: =AVERAGE(SUMIF($M$9:$T$9,$B$4,$M50:$T50),SUMIF($M$9:$T$9,$B$5,$M50:$T50)) -> 0 | H50: Other Use of Goods& Services | J50: 24418.662 | K50: 15577.229 | L50: 16962.291
C51: Estimate | D51: Scaled | G51: =AVERAGE(SUMIF($M$9:$T$9,$B$4,$M51:$T51),SUMIF($M$9:$T$9,$B$5,$M51:$T51)) -> 314.53271 | H51: Subsidies | I51: 1.6.11 | J51: 84.373377 | K51: 86.226021 | L51: 99.527043 | M51: 172.02613 | N51: 251.9473 | O51: 260.16228 | P51: 382.17385 | Q51: 298.87794 | R51: 307.42048 | S51: 321.64494
B52: Total | C52: =SUM(C53:C54) -> 627.34185 | D52: =G12 -> 1267.9941 | G52: =AVERAGE(SUMIF($M$9:$T$9,$B$4,$M52:$T52),SUMIF($M$9:$T$9,$B$5,$M52:$T52)) -> 0 | H52: Indirect subsidies on commodities (negative indirect taxes) o/w electricity, water, fertilizers…. | J52: 15.373377 | K52: 5.3642821 | L52: 23.882568 | M52: 4.5158883 | N52: 21.264679
B53: Personal tax | C53: 413.16492 | D53: =C53/$C$52*$D$52 -> 835.09604 | G53: =AVERAGE(SUMIF($M$9:$T$9,$B$4,$M53:$T53),SUMIF($M$9:$T$9,$B$5,$M53:$T53)) -> 0 | H53: Public and Private Enterprises (o/w Rwa Air, Export promotion) | J53: 69 | K53: 80.861739 | L53: 75.644475 | M53: 167.51024 | N53: 230.68262
B54: Corporate tax | C54: 214.17693 | D54: =C54/$C$52*$D$52 -> 432.89809 | G54: =AVERAGE(SUMIF($M$9:$T$9,$B$4,$M54:$T54),SUMIF($M$9:$T$9,$B$5,$M54:$T54)) -> 0 | H54: Grants (excl. grants to EBU, LG, under wage, G&S, dev. spending) | I54: 1.6.12 | J54: 67241.527 | K54: 56572.689 | L54: 60162.606 | M54: 0 | N54: 0 | O54: 177.57302 | P54: 0 | Q54: 0 | R54: 0 | S54: 0
G55: =AVERAGE(SUMIF($M$9:$T$9,$B$4,$M55:$T55),SUMIF($M$9:$T$9,$B$5,$M55:$T55)) -> 0 | H55: Grants to Foreign Governments | J55: 0 | K55: 0 | L55: 0
G56: =AVERAGE(SUMIF($M$9:$T$9,$B$4,$M56:$T56),SUMIF($M$9:$T$9,$B$5,$M56:$T56)) -> 0 | H56: Grants to International Organizations - | J56: 0 | K56: 0 | L56: 0
G57: =AVERAGE(SUMIF($M$9:$T$9,$B$4,$M57:$T57),SUMIF($M$9:$T$9,$B$5,$M57:$T57)) -> 0 | H57: Grants to Subsidiary Entity (reclass. Wages, G&S, NANFA) | J57: 67241.527 | K57: 56572.689 | L57: 60162.606
G58: =AVERAGE(SUMIF($M$9:$T$9,$B$4,$M58:$T58),SUMIF($M$9:$T$9,$B$5,$M58:$T58)) -> 57.900459 | H58: Social Assistance | I58: 1.6.13 | J58: 70101.945 | K58: 70085.725 | L58: 109512.23 | M58: 25.820247 | N58: 26.669207 | O58: 41.034068 | P58: 56.665979 | Q58: 46.1 | R58: 48.931606 | S58: 66.869312
G59: =AVERAGE(SUMIF($M$9:$T$9,$B$4,$M59:$T59),SUMIF($M$9:$T$9,$B$5,$M59:$T59)) -> 0 | H59: Social Assistance Benefits | J59: 65018.162 | K59: 67367.477 | L59: 103719.8
G60: =AVERAGE(SUMIF($M$9:$T$9,$B$4,$M60:$T60),SUMIF($M$9:$T$9,$B$5,$M60:$T60)) -> 0 | H60: Employer Social Benefits | J60: 5083.7833 | K60: 2718.2472 | L60: 5792.4294
G61: =AVERAGE(SUMIF($M$9:$T$9,$B$4,$M61:$T61),SUMIF($M$9:$T$9,$B$5,$M61:$T61)) -> 451.79472 | H61: Finance cost | I61: 1.6.14 | J61: 60908.271 | K61: 82257.334 | L61: 92278.031 | M61: 102.49247 | N61: 139.1188 | O61: 180.68588 | P61: 220.33496 | Q61: 303.50286 | R61: 417.72068 | S61: 485.86876
G62: =AVERAGE(SUMIF($M$9:$T$9,$B$4,$M62:$T62),SUMIF($M$9:$T$9,$B$5,$M62:$T62)) -> 248.01459 | H62: Interest on domestic debt | J62: 31113.179 | K62: 45540.312 | L62: 42328.927 | M62: 54.603489 | N62: 78.30179 | O62: 113.50888 | P62: 150.36744 | Q62: 202.65379 | R62: 234.46881 | S62: 261.56038
G63: =AVERAGE(SUMIF($M$9:$T$9,$B$4,$M63:$T63),SUMIF($M$9:$T$9,$B$5,$M63:$T63)) -> 203.78013 | H63: Interest on foreign debt | J63: 29795.092 | K63: 36717.022 | L63: 49949.104 | M63: 47.888981 | N63: 60.817014 | O63: 67.176995 | P63: 69.967521 | Q63: 100.84906 | R63: 183.25188 | S63: 224.30839
G64: =AVERAGE(SUMIF($M$9:$T$9,$B$4,$M64:$T64),SUMIF($M$9:$T$9,$B$5,$M64:$T64)) -> 142.05727 | H64: Other Expenses (decide transfers or G&S) | I64: 1.6.15 | J64: 115089.07 | K64: 135353.02 | L64: 137726.71 | M64: 170.62253 | N64: 144.34994 | O64: 132.2615 | P64: 147.01855 | Q64: 127.7 | R64: 139.12123 | S64: 144.9933
G65: =AVERAGE(SUMIF($M$9:$T$9,$B$4,$M65:$T65),SUMIF($M$9:$T$9,$B$5,$M65:$T65)) -> 0 | H65: Miscellaneous expenses | J65: 87327.782 | K65: 76220.217 | L65: 92741.098
G66: =AVERAGE(SUMIF($M$9:$T$9,$B$4,$M66:$T66),SUMIF($M$9:$T$9,$B$5,$M66:$T66)) -> 0 | H66: Arrears on other expenditures | J66: 1.488144 | K66: 0 | L66: 0
G67: =AVERAGE(SUMIF($M$9:$T$9,$B$4,$M67:$T67),SUMIF($M$9:$T$9,$B$5,$M67:$T67)) -> 0 | H67: Property expenses other than interest | J67: 0 | K67: 0.6 | L67: 47.176125
G68: =AVERAGE(SUMIF($M$9:$T$9,$B$4,$M68:$T68),SUMIF($M$9:$T$9,$B$5,$M68:$T68)) -> 0 | H68: Transfers not elsewhere classified | J68: 24910.729 | K68: 58269.237 | L68: 42329.063
G69: =AVERAGE(SUMIF($M$9:$T$9,$B$4,$M69:$T69),SUMIF($M$9:$T$9,$B$5,$M69:$T69)) -> 0 | H69: Premiums ,Fees and Current claims | J69: 2849.0679 | K69: 862.96874 | L69: 2609.3735
G70: =AVERAGE(SUMIF($M$9:$T$9,$B$4,$M70:$T70),SUMIF($M$9:$T$9,$B$5,$M70:$T70)) -> 0 | H70: Repayment of borrowings (not used in SAM-CGE) | I70: 1.6.16 | J70: 29937.647 | K70: 39333.804 | L70: 48494.988
G71: =AVERAGE(SUMIF($M$9:$T$9,$B$4,$M71:$T71),SUMIF($M$9:$T$9,$B$5,$M71:$T71)) -> 0 | H71: Repayment of principal – Domestic debt | J71: 15039.441 | K71: 18559.684 | L71: 23786.032
G72: =AVERAGE(SUMIF($M$9:$T$9,$B$4,$M72:$T72),SUMIF($M$9:$T$9,$B$5,$M72:$T72)) -> 0 | H72: Repayment of principal – Foreign debt | J72: 14898.207 | K72: 20774.12 | L72: 24708.955
G73: =AVERAGE(SUMIF($M$9:$T$9,$B$4,$M73:$T73),SUMIF($M$9:$T$9,$B$5,$M73:$T73)) -> 1998.9009 | H73: Acquisition of Assets | I73: 1.6.17 | J73: 537525.27 | K73: 596099.43 | L73: 609695.33 | M73: 1039.8199 | N73: 1175.0382 | O73: 1434.9492 | P73: 1735.5014 | Q73: 1754.4301 | R73: 2002.9487 | S73: 1994.8531
G74: =AVERAGE(SUMIF($M$9:$T$9,$B$4,$M74:$T74),SUMIF($M$9:$T$9,$B$5,$M74:$T74)) -> 1998.9009 | H74: Acquisition of tangible fixed assets (incl. in EBU, LG) | J74: 398936.1 | K74: 219927.98 | L74: 542605.4 | M74: 1039.8199 | N74: 1175.0382 | O74: 1434.9492 | P74: 1735.5014 | Q74: 1754.4301 | R74: 2002.9487 | S74: 1994.8531
G75: =AVERAGE(SUMIF($M$9:$T$9,$B$4,$M75:$T75),SUMIF($M$9:$T$9,$B$5,$M75:$T75)) -> 0 | H75: Inventories | J75: 254.01561 | K75: 1245.6162 | L75: 892.58523
G76: =AVERAGE(SUMIF($M$9:$T$9,$B$4,$M76:$T76),SUMIF($M$9:$T$9,$B$5,$M76:$T76)) -> 0 | H76: Valuables | J76: 6120.1249 | K76: 115749.02 | L76: 23.396176
G77: =AVERAGE(SUMIF($M$9:$T$9,$B$4,$M77:$T77),SUMIF($M$9:$T$9,$B$5,$M77:$T77)) -> 0 | H77: Non Produced Assets | J77: 130840.84 | K77: 247673.94 | L77: 48930.247
G78: =AVERAGE(SUMIF($M$9:$T$9,$B$4,$M78:$T78),SUMIF($M$9:$T$9,$B$5,$M78:$T78)) -> 0 | H78: Investment in Financial Assets – Domestic | J78: 0 | K78: 2910.0212 | L78: 5949.6136
G79: =AVERAGE(SUMIF($M$9:$T$9,$B$4,$M79:$T79),SUMIF($M$9:$T$9,$B$5,$M79:$T79)) -> 0 | H79: Investment in Financial Assets – Foreign | J79: 1200.0252 | K79: 26.701033 | L79: 10494.204
G80: =AVERAGE(SUMIF($M$9:$T$9,$B$4,$M80:$T80),SUMIF($M$9:$T$9,$B$5,$M80:$T80)) -> 0 | H80: Arrears on acquisition of fixed assets | J80: 174.1549 | K80: 8566.1565 | L80: 799.87928
G81: =AVERAGE(SUMIF($M$9:$T$9,$B$4,$M81:$T81),SUMIF($M$9:$T$9,$B$5,$M81:$T81)) -> 5058.1363 | H81: Total Expenditure (excl. repayment borrowing) | I81: 1.6.28 | J81: 1923132.2 | K81: 2180807.2 | L81: 2313849.2 | M81: 2581.5416 | N81: 2872.2733 | O81: 3490.901 | P81: 4061.0794 | Q81: 4375.1188 | R81: 4927.9335 | S81: 5188.3391
G82: =AVERAGE(SUMIF($M$9:$T$9,$B$4,$M82:$T82),SUMIF($M$9:$T$9,$B$5,$M82:$T82)) -> -1203.2678 | H82: Net Surplus / (Deficit) Rev-Exp corr.for netLending, ie GFS1986 def. | J82: 28876.184 | K82: -62933.295 | L82: -508.18798 | M82: -546.48294 | N82: -772.83068 | O82: -1036.4766 | P82: -1117.8269 | Q82: -1116.9868 | R82: -1228.211 | S82: -1178.3247

Sheet wGDPp
B1: Gross Domestic Product by Production Sector / by kind of activity at current prices in billion Rwf, REBASED 2024=100
B2: Workings | K2: Summary data
K3: =F7 -> 6804 | L3: GDP factor cost
I4: =Notes!B5 -> 2024 | J4: Year | K4: =I45 -> 1157 | L4: Indirect taxes
D5: Final | E5: Sub-sectoral shares | F5: National accounts | I5: 1 | J5: Scaling (multiplier) | K5: =SUM(K3:K4) -> 7961 | L5: GDP market prices
D6: values | F6: Current
D7: =SUM(D8:D111) -> #DIV/0! | F7: =SUM(F8:F111) -> 6804 | G7: Groups | H7: Map | I7: Selected | K7: 2010 | L7: 2011 | M7: 2012 | N7: 2013 | O7: 2014 | P7: 2015 | Q7: 2016 | R7: 2017 | S7: 2018 | T7: 2019 | U7: 2020 | V7: 2021 | W7: 2022 | X7: 2023 | Y7: 2024
B8: Sorghum (A111) | C8: asorg | D8: =IF(COUNTIF($G$8:$G$111,G8)=1,F8,SUMIF($G$8:$G$111,G8,$F$8:$F$111)*E8/SUMIF($G$8:$G$111,G8,$E$8:$E$111)) -> 21.594729 | E8: =wAGR!M7 -> 0.013513598 | F8: =SUMIF($H$8:$H$46,$C8,$I$8:$I$46) -> 1598 | G8: 1 | I8: =I9+I15+I29 -> 6804 | J8: Gross Domestic Product (Gdp) | K8: 4922 | L8: 5314 | M8: 5773 | N8: 6046 | O8: 6418 | P8: 6987 | Q8: 7404 | R8: 7694 | S8: 8350 | T8: 9138 | U8: 8830 | V8: 9789 | W8: 10588 | X8: 11461 | Y8: 12480
B9: Maize (A112) | C9: amaiz | D9: =IF(COUNTIF($G$8:$G$111,G9)=1,F9,SUMIF($G$8:$G$111,G9,$F$8:$F$111)*E9/SUMIF($G$8:$G$111,G9,$E$8:$E$111)) -> 46.224396 | E9: =wAGR!M8 -> 0.028926406 | F9: =SUMIF($H$8:$H$46,$C9,$I$8:$I$46) -> 0 | G9: 1 | I9: =SUM(I10:I14) -> 2500 | J9: Agriculture, Forestry & Fishing (A) | K9: 1445 | L9: 1508 | M9: 1611 | N9: 1664 | O9: 1775 | P9: 1863 | Q9: 1935 | R9: 2027 | S9: 2151 | T9: 2259 | U9: 2278 | V9: 2423 | W9: 2461 | X9: 2502 | Y9: 2635
B10: Wheat (A113) | C10: awhea | D10: =IF(COUNTIF($G$8:$G$111,G10)=1,F10,SUMIF($G$8:$G$111,G10,$F$8:$F$111)*E10/SUMIF($G$8:$G$111,G10,$E$8:$E$111)) -> 1.9919861 | E10: =wAGR!M9 -> 0.0012465495 | F10: =SUMIF($H$8:$H$46,$C10,$I$8:$I$46) -> 0 | G10: 1 | H10: asorg | I10: =SUMIF($K$7:$Y$7,I$4,K10:Y10) -> 1598 | J10: Food Crops (AA) | K10: 912 | L10: 946 | M10: 1023 | N10: 1063 | O10: 1157 | P10: 1199 | Q10: 1235 | R10: 1297 | S10: 1373 | T10: 1428 | U10: 1433 | V10: 1529 | W10: 1516 | X10: 1516 | Y10: 1598
B11: Paddy & husked rice (A116) | C11: arice | D11: =IF(COUNTIF($G$8:$G$111,G11)=1,F11,SUMIF($G$8:$G$111,G11,$F$8:$F$111)*E11/SUMIF($G$8:$G$111,G11,$E$8:$E$111)) -> 26.906478 | E11: =wAGR!M10 -> 0.016837596 | F11: =SUMIF($H$8:$H$46,$C11,$I$8:$I$46) -> 0 | G11: 1 | H11: acoff | I11: =SUMIF($K$7:$X$7,I$4,K11:X11) -> 0 | J11: Export Crops (AB) | K11: 111 | L11: 114 | M11: 124 | N11: 118 | O11: 116 | P11: 132 | Q11: 136 | R11: 138 | S11: 147 | T11: 154 | U11: 140 | V11: 139 | W11: 144 | X11: 137 | Y11: 135
B12: Other cereals (A119) | C12: aocer | D12: =IF(COUNTIF($G$8:$G$111,G12)=1,F12,SUMIF($G$8:$G$111,G12,$F$8:$F$111)*E12/SUMIF($G$8:$G$111,G12,$E$8:$E$111)) -> 7.1618331e-05 | E12: =wAGR!M11 -> 4.4817479e-08 | F12: =SUMIF($H$8:$H$46,$C12,$I$8:$I$46) -> 0 | G12: 1 | H12: acatt | I12: =SUMIF($K$7:$Y$7,I$4,K12:Y12) -> 332 | J12: Livestock & Livestock Products (AC) | K12: 113 | L12: 116 | M12: 124 | N12: 132 | O12: 142 | P12: 155 | Q12: 170 | R12: 186 | S12: 206 | T12: 229 | U12: 247 | V12: 268 | W12: 291 | X12: 310 | Y12: 332
B13: Irish potatoes (A121) | C13: aipot | D13: =IF(COUNTIF($G$8:$G$111,G13)=1,F13,SUMIF($G$8:$G$111,G13,$F$8:$F$111)*E13/SUMIF($G$8:$G$111,G13,$E$8:$E$111)) -> 115.17255 | E13: =wAGR!M12 -> 0.072072936 | F13: =SUMIF($H$8:$H$46,$C13,$I$8:$I$46) -> 0 | G13: 1 | H13: afuel | I13: =SUMIF($K$7:$Y$7,I$4,K13:Y13) -> 534 | J13: Forestry (AD) | K13: 302 | L13: 310 | M13: 321 | N13: 330 | O13: 341 | P13: 354 | Q13: 367 | R13: 378 | S13: 395 | T13: 417 | U13: 432 | V13: 455 | W13: 477 | X13: 504 | Y13: 534
B14: Sweet potatoes (A122) | C14: aspot | D14: =IF(COUNTIF($G$8:$G$111,G14)=1,F14,SUMIF($G$8:$G$111,G14,$F$8:$F$111)*E14/SUMIF($G$8:$G$111,G14,$E$8:$E$111)) -> 119.65299 | E14: =wAGR!M13 -> 0.074876714 | F14: =SUMIF($H$8:$H$46,$C14,$I$8:$I$46) -> 0 | G14: 1 | H14: afish | I14: =SUMIF($K$7:$Y$7,I$4,K14:Y14) -> 36 | J14: Fishing (AE) | K14: 24 | L14: 24 | M14: 24 | N14: 25 | O14: 26 | P14: 26 | Q14: 27 | R14: 29 | S14: 30 | T14: 31 | U14: 26 | V14: 33 | W14: 34 | X14: 35 | Y14: 36
B15: Cassava (A123) | C15: acass | D15: =IF(COUNTIF($G$8:$G$111,G15)=1,F15,SUMIF($G$8:$G$111,G15,$F$8:$F$111)*E15/SUMIF($G$8:$G$111,G15,$E$8:$E$111)) -> 77.058038 | E15: =wAGR!M14 -> 0.04822155 | F15: =SUMIF($H$8:$H$46,$C15,$I$8:$I$46) -> 0 | G15: 1 | I15: =I16+I17+I26+I27+I28 -> 2324 | J15: Industry (B-F) | K15: 788 | L15: 928 | M15: 1005 | N15: 1099 | O15: 1127 | P15: 1228 | Q15: 1310 | R15: 1330 | S15: 1445 | T15: 1684 | U15: 1613 | V15: 1828 | W15: 1918 | X15: 2114 | Y15: 2325
B16: Other roots & tubers (A129) | C16: aroot | D16: =IF(COUNTIF($G$8:$G$111,G16)=1,F16,SUMIF($G$8:$G$111,G16,$F$8:$F$111)*E16/SUMIF($G$8:$G$111,G16,$E$8:$E$111)) -> 13.498447 | E16: =wAGR!M15 -> 0.0084470884 | F16: =SUMIF($H$8:$H$46,$C16,$I$8:$I$46) -> 0 | G16: 1 | H16: angas | I16: =SUMIF($K$7:$Y$7,I$4,K16:Y16) -> 207 | J16: Mining & Quarrying (B) | K16: 63 | L16: 94 | M16: 88 | N16: 105 | O16: 131 | P16: 125 | Q16: 138 | R16: 165 | S16: 170 | T16: 170 | U16: 117 | V16: 148 | W16: 169 | X16: 184 | Y16: 207
B17: Dried beans (A131) | C17: abean | D17: =IF(COUNTIF($G$8:$G$111,G17)=1,F17,SUMIF($G$8:$G$111,G17,$F$8:$F$111)*E17/SUMIF($G$8:$G$111,G17,$E$8:$E$111)) -> 239.84649 | E17: =wAGR!M16 -> 0.15009167 | F17: =SUMIF($H$8:$H$46,$C17,$I$8:$I$46) -> 0 | G17: 1 | I17: =SUM(I18:I25) -> 1108 | J17: Total Manufacturing (C) | K17: 458 | L17: 496 | M17: 525 | N17: 549 | O17: 480 | P17: 520 | Q17: 555 | R17: 591 | S17: 671 | T17: 746 | U17: 761 | V17: 842 | W17: 935 | X17: 1032 | Y17: 1109
B18: Peas & other legumes (A132) | C18: apeas | D18: =IF(COUNTIF($G$8:$G$111,G18)=1,F18,SUMIF($G$8:$G$111,G18,$F$8:$F$111)*E18/SUMIF($G$8:$G$111,G18,$E$8:$E$111)) -> 520.88434 | E18: =wAGR!M17 -> 0.32596016 | F18: =SUMIF($H$8:$H$46,$C18,$I$8:$I$46) -> 0 | G18: 1 | H18: ameat | I18: =SUMIF($K$7:$Y$7,I$4,K18:Y18) -> 376 | J18: Food (CA) | K18: 144 | L18: 150 | M18: 151 | N18: 163 | O18: 172 | P18: 174 | Q18: 188 | R18: 210 | S18: 237 | T18: 248 | U18: 265 | V18: 284 | W18: 322 | X18: 368 | Y18: 376
B19: Other vegetables (A139) | C19: avege | D19: =IF(COUNTIF($G$8:$G$111,G19)=1,F19,SUMIF($G$8:$G$111,G19,$F$8:$F$111)*E19/SUMIF($G$8:$G$111,G19,$E$8:$E$111)) -> 6.7888873 | E19: =wAGR!M18 -> 0.004248365 | F19: =SUMIF($H$8:$H$46,$C19,$I$8:$I$46) -> 0 | G19: 1 | H19: aalco | I19: =SUMIF($K$7:$Y$7,I$4,K19:Y19) -> 227 | J19: Beverages & Tobacco (CB) | K19: 127 | L19: 137 | M19: 143 | N19: 148 | O19: 159 | P19: 168 | Q19: 174 | R19: 159 | S19: 166 | T19: 184 | U19: 186 | V19: 197 | W19: 214 | X19: 215 | Y19: 227
B20: Bananas for beer (A141) | C20: abanb | D20: =IF(COUNTIF($G$8:$G$111,G20)=1,F20,SUMIF($G$8:$G$111,G20,$F$8:$F$111)*E20/SUMIF($G$8:$G$111,G20,$E$8:$E$111)) -> 7.5439806 | E20: =wAGR!M19 -> 0.004720889 | F20: =SUMIF($H$8:$H$46,$C20,$I$8:$I$46) -> 0 | G20: 1 | H20: atext | I20: =SUMIF($K$7:$Y$7,I$4,K20:Y20) -> 112 | J20: Textiles, Clothing & Leather Goods (CC) | K20: 85 | L20: 83 | M20: 90 | N20: 20 | O20: 21 | P20: 22 | Q20: 24 | R20: 34 | S20: 54 | T20: 64 | U20: 61 | V20: 71 | W20: 85 | X20: 102 | Y20: 112
B21: Bananas for cooking (A142) | C21: abanc | D21: =IF(COUNTIF($G$8:$G$111,G21)=1,F21,SUMIF($G$8:$G$111,G21,$F$8:$F$111)*E21/SUMIF($G$8:$G$111,G21,$E$8:$E$111)) -> 201.88779 | E21: =wAGR!M20 -> 0.12633779 | F21: =SUMIF($H$8:$H$46,$C21,$I$8:$I$46) -> 0 | G21: 1 | H21: awood | I21: =SUMIF($K$7:$Y$7,I$4,K21:Y21) -> 62 | J21: Wood & Paper; Printing (CD) | K21: 18 | L21: 16 | M21: 19 | N21: 21 | O21: 23 | P21: 26 | Q21: 28 | R21: 26 | S21: 29 | T21: 37 | U21: 34 | V21: 40 | W21: 46 | X21: 55 | Y21: 62
B22: Bananas (sweet) (A143) | C22: abans | D22: =IF(COUNTIF($G$8:$G$111,G22)=1,F22,SUMIF($G$8:$G$111,G22,$F$8:$F$111)*E22/SUMIF($G$8:$G$111,G22,$E$8:$E$111)) -> 34.792013 | E22: =wAGR!M21 -> 0.021772224 | F22: =SUMIF($H$8:$H$46,$C22,$I$8:$I$46) -> 0 | G22: 1 | H22: apetr | I22: =SUMIF($K$7:$Y$7,I$4,K22:Y22) -> 105 | J22: Chemicals, Rubber & Plastic Products (CE) | K22: 20 | L22: 22 | M22: 23 | N22: 22 | O22: 21 | P22: 24 | Q22: 26 | R22: 34 | S22: 40 | T22: 53 | U22: 54 | V22: 66 | W22: 75 | X22: 91 | Y22: 105
B23: Other fruit & nuts (A149) | C23: afrui | D23: =IF(COUNTIF($G$8:$G$111,G23)=1,F23,SUMIF($G$8:$G$111,G23,$F$8:$F$111)*E23/SUMIF($G$8:$G$111,G23,$E$8:$E$111)) -> 160.85445 | E23: =wAGR!M22 -> 0.10065986 | F23: =SUMIF($H$8:$H$46,$C23,$I$8:$I$46) -> 0 | G23: 1 | H23: anmet | I23: =SUMIF($K$7:$Y$7,I$4,K23:Y23) -> 66 | J23: Non-Metallic Mineral Products (CF) | K23: 13 | L23: 15 | M23: 17 | N23: 19 | O23: 22 | P23: 26 | Q23: 31 | R23: 34 | S23: 37 | T23: 44 | U23: 44 | V23: 49 | W23: 53 | X23: 57 | Y23: 66
B24: Ground nuts (A151) | C24: agnut | D24: =IF(COUNTIF($G$8:$G$111,G24)=1,F24,SUMIF($G$8:$G$111,G24,$F$8:$F$111)*E24/SUMIF($G$8:$G$111,G24,$E$8:$E$111)) -> 2.4697221 | E24: =wAGR!M23 -> 0.0015455082 | F24: =SUMIF($H$8:$H$46,$C24,$I$8:$I$46) -> 0 | G24: 1 | H24: ametl | I24: =SUMIF($K$7:$Y$7,I$4,K24:Y24) -> 76 | J24: Metal Products, Machinery & Equipment (CG) | K24: 10 | L24: 13 | M24: 16 | N24: 14 | O24: 18 | P24: 25 | Q24: 29 | R24: 32 | S24: 39 | T24: 47 | U24: 51 | V24: 53 | W24: 57 | X24: 63 | Y24: 76
B25: Soya (A152) | C25: asoya | D25: =IF(COUNTIF($G$8:$G$111,G25)=1,F25,SUMIF($G$8:$G$111,G25,$F$8:$F$111)*E25/SUMIF($G$8:$G$111,G25,$E$8:$E$111)) -> 0.83264683 | E25: =wAGR!M24 -> 0.00052105559 | F25: =SUMIF($H$8:$H$46,$C25,$I$8:$I$46) -> 0 | G25: 1 | H25: afurn | I25: =SUMIF($K$7:$Y$7,I$4,K25:Y25) -> 84 | J25: Furniture & Other Manufacturing (CH) | K25: 28 | L25: 38 | M25: 41 | N25: 46 | O25: 52 | P25: 61 | Q25: 55 | R25: 61 | S25: 68 | T25: 69 | U25: 67 | V25: 83 | W25: 82 | X25: 79 | Y25: 84
B26: Other oil seeds (A159) | C26: aoils | D26: =IF(COUNTIF($G$8:$G$111,G26)=1,F26,SUMIF($G$8:$G$111,G26,$F$8:$F$111)*E26/SUMIF($G$8:$G$111,G26,$E$8:$E$111)) -> 0 | E26: =wAGR!M25 -> 0 | F26: =SUMIF($H$8:$H$46,$C26,$I$8:$I$46) -> 0 | G26: 1 | H26: aelec | I26: =SUMIF($K$7:$Y$7,I$4,K26:Y26) -> 159 | J26: Electricity (D) | K26: 40 | L26: 46 | M26: 54 | N26: 58 | O26: 63 | P26: 68 | Q26: 77 | R26: 84 | S26: 92 | T26: 98 | U26: 100 | V26: 112 | W26: 128 | X26: 134 | Y26: 159
B27: Coffee, not roasted, not decaffeinated (A210) | C27: acoff | D27: =IF(COUNTIF($G$8:$G$111,G27)=1,F27,SUMIF($G$8:$G$111,G27,$F$8:$F$111)*E27/SUMIF($G$8:$G$111,G27,$E$8:$E$111)) -> 0 | E27: =wAGR!M26 -> 0.51408282 | F27: =SUMIF($H$8:$H$46,$C27,$I$8:$I$46) -> 0 | G27: 2 | H27: awatr | I27: =SUMIF($K$7:$Y$7,I$4,K27:Y27) -> 39 | J27: Water & Waste Management (E) | K27: 22 | L27: 25 | M27: 28 | N27: 29 | O27: 30 | P27: 30 | Q27: 32 | R27: 32 | S27: 33 | T27: 33 | U27: 34 | V27: 36 | W27: 37 | X27: 38 | Y27: 39
B28: Tea (unprocessed green leaf) (A220) | C28: ateal | D28: =IF(COUNTIF($G$8:$G$111,G28)=1,F28,SUMIF($G$8:$G$111,G28,$F$8:$F$111)*E28/SUMIF($G$8:$G$111,G28,$E$8:$E$111)) -> 0 | E28: =wAGR!M27 -> 0.16236215 | F28: =SUMIF($H$8:$H$46,$C28,$I$8:$I$46) -> 0 | G28: 2 | H28: acons | I28: =SUMIF($K$7:$Y$7,I$4,K28:Y28) -> 811 | J28: Construction (F) | K28: 244 | L28: 302 | M28: 345 | N28: 383 | O28: 421 | P28: 485 | Q28: 509 | R28: 458 | S28: 479 | T28: 636 | U28: 600 | V28: 690 | W28: 650 | X28: 726 | Y28: 811
B29: Tobacco, raw (A291) | C29: atoba | D29: =IF(COUNTIF($G$8:$G$111,G29)=1,F29,SUMIF($G$8:$G$111,G29,$F$8:$F$111)*E29/SUMIF($G$8:$G$111,G29,$E$8:$E$111)) -> 0 | E29: =wAGR!M28 -> 0.028145216 | F29: =SUMIF($H$8:$H$46,$C29,$I$8:$I$46) -> 0 | G29: 2 | I29: =I30+I34 -> 1980 | J29: Services (G-T) | K29: 2173 | L29: 2347 | M29: 2619 | N29: 2756 | O29: 2949 | P29: 3256 | Q29: 3489 | R29: 3684 | S29: 4041 | T29: 4376 | U29: 4133 | V29: 4624 | W29: 5187 | X29: 5767 | Y29: 6363
B30: Sugar cane (A292) | C30: asugr | D30: =IF(COUNTIF($G$8:$G$111,G30)=1,F30,SUMIF($G$8:$G$111,G30,$F$8:$F$111)*E30/SUMIF($G$8:$G$111,G30,$E$8:$E$111)) -> 0 | E30: =wAGR!M29 -> 0.064453496 | F30: =SUMIF($H$8:$H$46,$C30,$I$8:$I$46) -> 0 | G30: 2 | I30: =SUM(I31:I33) -> 1980 | J30: Trade &Transport (G-H) | K30: 563 | L30: 602 | M30: 692 | N30: 732 | O30: 782 | P30: 872 | Q30: 930 | R30: 992 | S30: 1172 | T30: 1337 | U30: 1196 | V30: 1357 | W30: 1572 | X30: 1728 | Y30: 1981
B31: Pyrethrum (A293) | C31: apyre | D31: =IF(COUNTIF($G$8:$G$111,G31)=1,F31,SUMIF($G$8:$G$111,G31,$F$8:$F$111)*E31/SUMIF($G$8:$G$111,G31,$E$8:$E$111)) -> 0 | E31: =wAGR!M30 -> 0.037485023 | F31: =SUMIF($H$8:$H$46,$C31,$I$8:$I$46) -> 0 | G31: 2 | H31: avehr | I31: =SUMIF($K$7:$Y$7,I$4,K31:Y31) -> 64 | J31: Maintenance And Repair Of Motor Vehicles (GA) | K31: 27 | L31: 29 | M31: 31 | N31: 33 | O31: 34 | P31: 36 | Q31: 38 | R31: 40 | S31: 43 | T31: 46 | U31: 45 | V31: 60 | W31: 63 | X31: 65 | Y31: 64
B32: Agricultural products n.e.c. (A299) | C32: aocrp | D32: =IF(COUNTIF($G$8:$G$111,G32)=1,F32,SUMIF($G$8:$G$111,G32,$F$8:$F$111)*E32/SUMIF($G$8:$G$111,G32,$E$8:$E$111)) -> 0 | E32: =wAGR!M31 -> 0.1934713 | F32: =SUMIF($H$8:$H$46,$C32,$I$8:$I$46) -> 0 | G32: 2 | H32: atrdw | I32: =SUMIF($K$7:$Y$7,I$4,K32:Y32) -> 1286 | J32: Wholesale & Retail Trade (GB) | K32: 346 | L32: 373 | M32: 427 | N32: 450 | O32: 488 | P32: 551 | Q32: 584 | R32: 597 | S32: 704 | T32: 815 | U32: 787 | V32: 879 | W32: 1001 | X32: 1088 | Y32: 1286
B33: Bovine cattle, live (A311) | C33: acatt | D33: =IF(COUNTIF($G$8:$G$111,G33)=1,F33,SUMIF($G$8:$G$111,G33,$F$8:$F$111)*E33/SUMIF($G$8:$G$111,G33,$E$8:$E$111)) -> 149.49015 | E33: =wAGR!M32 -> 0.45027153 | F33: =SUMIF($H$8:$H$46,$C33,$I$8:$I$46) -> 332 | G33: 3 | H33: atrnl | I33: =SUMIF($K$7:$Y$7,I$4,K33:Y33) -> 630 | J33: Transport Services (H) | K33: 189 | L33: 197 | M33: 234 | N33: 250 | O33: 260 | P33: 285 | Q33: 308 | R33: 355 | S33: 424 | T33: 477 | U33: 364 | V33: 417 | W33: 508 | X33: 575 | Y33: 630
B34: Sheep, goats, pigs,live (A312) | C34: asmlr | D34: =IF(COUNTIF($G$8:$G$111,G34)=1,F34,SUMIF($G$8:$G$111,G34,$F$8:$F$111)*E34/SUMIF($G$8:$G$111,G34,$E$8:$E$111)) -> 54.471183 | E34: =wAGR!M33 -> 0.16406983 | F34: =SUMIF($H$8:$H$46,$C34,$I$8:$I$46) -> 0 | G34: 3 | I34: =SUM(I35:I44) -> 0 | J34: Other Services (I-T) | K34: 1614 | L34: 1754 | M34: 1928 | N34: 2024 | O34: 2166 | P34: 2385 | Q34: 2559 | R34: 2692 | S34: 2869 | T34: 3038 | U34: 2937 | V34: 3267 | W34: 3614 | X34: 4038 | Y34: 4382
B35: Poultry, live (A313) | C35: apoul | D35: =IF(COUNTIF($G$8:$G$111,G35)=1,F35,SUMIF($G$8:$G$111,G35,$F$8:$F$111)*E35/SUMIF($G$8:$G$111,G35,$E$8:$E$111)) -> 23.696522 | E35: =wAGR!M34 -> 0.071375068 | F35: =SUMIF($H$8:$H$46,$C35,$I$8:$I$46) -> 0 | G35: 3 | H35: ahotl | I35: =SUMIF($K$7:$W$7,I$4,K35:Y35) -> 0 | J35: Hotels & Restaurants (I) | K35: 84 | L35: 87 | M35: 92 | N35: 95 | O35: 107 | P35: 117 | Q35: 130 | R35: 140 | S35: 150 | T35: 165 | U35: 98 | V35: 118 | W35: 221 | X35: 261 | Y35: 290
B36: Other live animals (A319) | C36: aoliv | D36: =IF(COUNTIF($G$8:$G$111,G36)=1,F36,SUMIF($G$8:$G$111,G36,$F$8:$F$111)*E36/SUMIF($G$8:$G$111,G36,$E$8:$E$111)) -> 4.226682 | E36: =wAGR!M35 -> 0.01273097 | F36: =SUMIF($H$8:$H$46,$C36,$I$8:$I$46) -> 0 | G36: 3 | H36: apubl | I36: =SUMIF($K$7:$W$7,I$4,K36:Y36) -> 0 | J36: Information & Communication (J) | K36: 65 | L36: 67 | M36: 89 | N36: 89 | O36: 95 | P36: 112 | Q36: 121 | R36: 134 | S36: 153 | T36: 167 | U36: 216 | V36: 257 | W36: 307 | X36: 414 | Y36: 517
B37: Raw milk (A321) | C37: amilk | D37: =IF(COUNTIF($G$8:$G$111,G37)=1,F37,SUMIF($G$8:$G$111,G37,$F$8:$F$111)*E37/SUMIF($G$8:$G$111,G37,$E$8:$E$111)) -> 64.412811 | E37: =wAGR!M36 -> 0.19401449 | F37: =SUMIF($H$8:$H$46,$C37,$I$8:$I$46) -> 0 | G37: 3 | H37: abank | I37: =SUMIF($K$7:$W$7,I$4,K37:Y37) -> 0 | J37: Financial Services (K) | K37: 100 | L37: 120 | M37: 135 | N37: 149 | O37: 154 | P37: 173 | Q37: 179 | R37: 191 | S37: 210 | T37: 228 | U37: 222 | V37: 262 | W37: 289 | X37: 314 | Y37: 337
B38: Eggs (A322) | C38: aeggs | D38: =IF(COUNTIF($G$8:$G$111,G38)=1,F38,SUMIF($G$8:$G$111,G38,$F$8:$F$111)*E38/SUMIF($G$8:$G$111,G38,$E$8:$E$111)) -> 27.889836 | E38: =wAGR!M37 -> 0.08400553 | F38: =SUMIF($H$8:$H$46,$C38,$I$8:$I$46) -> 0 | G38: 3 | H38: arent | I38: =SUMIF($K$7:$W$7,I$4,K38:Y38) -> 0 | J38: Real Estate Activities (L) | K38: 445 | L38: 444 | M38: 443 | N38: 446 | O38: 471 | P38: 493 | Q38: 523 | R38: 560 | S38: 586 | T38: 609 | U38: 611 | V38: 636 | W38: 646 | X38: 676 | Y38: 681
B39: Natural honey (A323) | C39: ahony | D39: =IF(COUNTIF($G$8:$G$111,G39)=1,F39,SUMIF($G$8:$G$111,G39,$F$8:$F$111)*E39/SUMIF($G$8:$G$111,G39,$E$8:$E$111)) -> 1.0051477 | E39: =wAGR!M38 -> 0.0030275534 | F39: =SUMIF($H$8:$H$46,$C39,$I$8:$I$46) -> 0 | G39: 3 | H39: alegl | I39: =SUMIF($K$7:$W$7,I$4,K39:Y39) -> 0 | J39: Professional, Scientific And Technical Activities (M) | K39: 123 | L39: 123 | M39: 130 | N39: 135 | O39: 125 | P39: 143 | Q39: 151 | R39: 163 | S39: 179 | T39: 197 | U39: 195 | V39: 221 | W39: 223 | X39: 232 | Y39: 238
B40: Other livestock & hunting products (A329) | C40: ahunt | D40: =IF(COUNTIF($G$8:$G$111,G40)=1,F40,SUMIF($G$8:$G$111,G40,$F$8:$F$111)*E40/SUMIF($G$8:$G$111,G40,$E$8:$E$111)) -> 6.807672 | E40: =wAGR!M39 -> 0.020505036 | F40: =SUMIF($H$8:$H$46,$C40,$I$8:$I$46) -> 0 | G40: 3 | H40: atrvl | I40: =SUMIF($K$7:$W$7,I$4,K40:Y40) -> 0 | J40: Administrative And Support Service Activities (N) | K40: 165 | L40: 165 | M40: 175 | N40: 181 | O40: 208 | P40: 242 | Q40: 266 | R40: 277 | S40: 288 | T40: 302 | U40: 281 | V40: 297 | W40: 301 | X40: 308 | Y40: 331
B41: Fuel wood (A401) | C41: afuel | D41: =IF(COUNTIF($G$8:$G$111,G41)=1,F41,SUMIF($G$8:$G$111,G41,$F$8:$F$111)*E41/SUMIF($G$8:$G$111,G41,$E$8:$E$111)) -> 424.56725 | E41: =wAGR!M40 -> 0.79506976 | F41: =SUMIF($H$8:$H$46,$C41,$I$8:$I$46) -> 534 | G41: 4 | H41: apadm | I41: =SUMIF($K$7:$W$7,I$4,K41:Y41) -> 0 | J41: Public Administration And Defence; Compulsory Social Security (O) | K41: 229 | L41: 262 | M41: 320 | N41: 349 | O41: 373 | P41: 393 | Q41: 437 | R41: 446 | S41: 477 | T41: 500 | U41: 514 | V41: 526 | W41: 577 | X41: 639 | Y41: 700
B42: Charcoal (A402) | C42: achar | D42: =IF(COUNTIF($G$8:$G$111,G42)=1,F42,SUMIF($G$8:$G$111,G42,$F$8:$F$111)*E42/SUMIF($G$8:$G$111,G42,$E$8:$E$111)) -> 81.840908 | E42: =wAGR!M41 -> 0.15326013 | F42: =SUMIF($H$8:$H$46,$C42,$I$8:$I$46) -> 0 | G42: 4 | H42: aeduc | I42: =SUMIF($K$7:$W$7,I$4,K42:Y42) -> 0 | J42: Education (P) | K42: 157 | L42: 185 | M42: 198 | N42: 207 | O42: 214 | P42: 218 | Q42: 226 | R42: 231 | S42: 239 | T42: 244 | U42: 153 | V42: 242 | W42: 284 | X42: 335 | Y42: 350
B43: Other forestry products (A409) | C43: afore | D43: =IF(COUNTIF($G$8:$G$111,G43)=1,F43,SUMIF($G$8:$G$111,G43,$F$8:$F$111)*E43/SUMIF($G$8:$G$111,G43,$E$8:$E$111)) -> 27.591839 | E43: =wAGR!M42 -> 0.05167011 | F43: =SUMIF($H$8:$H$46,$C43,$I$8:$I$46) -> 0 | G43: 4 | H43: aheal | I43: =SUMIF($K$7:$W$7,I$4,K43:Y43) -> 0 | J43: Human Health And Social Work Activities (Q) | K43: 91 | L43: 93 | M43: 114 | N43: 121 | O43: 131 | P43: 144 | Q43: 153 | R43: 160 | S43: 160 | T43: 165 | U43: 192 | V43: 209 | W43: 225 | X43: 223 | Y43: 257
B44: Fishery products (A500) | C44: afish | D44: =IF(COUNTIF($G$8:$G$111,G44)=1,F44,SUMIF($G$8:$G$111,G44,$F$8:$F$111)*E44/SUMIF($G$8:$G$111,G44,$E$8:$E$111)) -> 36 | F44: =SUMIF($H$8:$H$46,$C44,$I$8:$I$46) -> 36 | G44: 5 | H44: acult | I44: =SUMIF($K$7:$W$7,I$4,K44:Y44) -> 0 | J44: Cultural, Domestic & Other Services (R-T) | K44: 203 | L44: 202 | M44: 224 | N44: 252 | O44: 292 | P44: 348 | Q44: 372 | R44: 391 | S44: 427 | T44: 462 | U44: 456 | V44: 499 | W44: 540 | X44: 637 | Y44: 680
