Workbook

Sheet Notes
A1: =CONCATENATE(B4," ",B3," Standard Excel Interface Model") -> Standard Excel Interface Model
A3: Country
A4: Year
A5: Units
A7: Activities and commodities | E7: Factors | H7: Households | K7: Other accounts
A8: amaiz | B8: cmaiz | C8: Maize | E8: flab-rn | F8: Labor - rural uneducated | H8: hhd-f1 | I8: Rural - farm q1 | K8: trc | L8: Transaction costs
A9: asorg | B9: csorg | C9: Sorghum and millet | E9: flab-rp | F9: Labor - rural primary | H9: hhd-f2 | I9: Rural - farm q2 | K9: ent | L9: Enterprises
A10: arice | B10: crice | C10: Rice | E10: flab-rs | F10: Labor - rural secondary | H10: hhd-f3 | I10: Rural - farm q3 | K10: gov | L10: Government
A11: awhea | B11: cwhea | C11: Wheat and barley | E11: flab-rt | F11: Labor - rural tertiary | H11: hhd-f4 | I11: Rural - farm q4 | K11: atax | L11: Taxes - activity
A12: aocer | B12: cocer | C12: Other cereals | E12: flab-un | F12: Labor - urban uneducated | H12: hhd-f5 | I12: Rural - farm q5 | K12: dtax | L12: Taxes - direct
A13: apuls | B13: cpuls | C13: Pulses | E13: flab-up | F13: Labor - urban primary | H13: hhd-n1 | I13: Rural - nonfarm q1 | K13: etax | L13: Taxes - export
A14: agnut | B14: cgnut | C14: Groundnuts | E14: flab-us | F14: Labor - urban secondary | H14: hhd-n2 | I14: Rural - nonfarm q2 | K14: ftax | L14: Taxes - factor
A15: aoils | B15: coils | C15: Other oilseeds | E15: flab-ut | F15: Labor - urban tertiary | H15: hhd-n3 | I15: Rural - nonfarm q3 | K15: mtax | L15: Taxes - import
A16: acass | B16: ccass | C16: Cassava | E16: flnd | F16: Crop land | H16: hhd-n4 | I16: Rural - nonfarm q4 | K16: stax | L16: Taxes - sales
A17: aipot | B17: cipot | C17: Irish potatoes | E17: fcap-c | F17: Capital - crops | H17: hhd-n5 | I17: Rural - nonfarm q5 | K17: s-i | L17: Savings-investment
A18: aspot | B18: cspot | C18: Sweet potatoes | E18: fcap-l | F18: Capital - livestock | H18: hhd-u1 | I18: Urban - q1 | K18: dstk | L18: Change in stocks
A19: aroot | B19: croot | C19: Other roots | E19: fcap-m | F19: Capital - mining | H19: hhd-u2 | I19: Urban - q2 | K19: row | L19: Rest of world
A20: aleaf | B20: cleaf | C20: Leafy vegetables | E20: fcap-n | F20: Capital - non-primary | H20: hhd-u3 | I20: Urban - q3 | K20: total | L20: Total
A21: avege | B21: cvege | C21: Other vegetables | H21: hhd-u4 | I21: Urban - q4
A22: asugr | B22: csugr | C22: Sugarcane | H22: hhd-u5 | I22: Urban - q5
A23: atoba | B23: ctoba | C23: Tobacco
A24: acott | B24: ccott | C24: Cotton and fibres
A25: anuts | B25: cnuts | C25: Nuts
A26: abana | B26: cbana | C26: Bananas and plantains
A27: afrui | B27: cfrui | C27: Other fruits
A28: ateal | B28: cteal | C28: Leaf tea
A29: acoff | B29: ccoff | C29: Coffee
A30: acoco | B30: ccoco | C30: Cocoa
A31: aflwr | B31: cflwr | C31: Cut flowers
A32: arubb | B32: crubb | C32: Rubber
A33: aocrp | B33: cocrp | C33: Other crops
A34: acatt | B34: ccatt | C34: Cattle
... A93: aosrv | B93: cosrv | C93: Other services

Sheet Sets
A1: Sets and Mappings
A2: a | B2: b | C2: c | D2: d | E2: e | F2: f | G2: g | H2: h | I2: i | J2: j | K2: k | L2: l | M2: m | N2: n | O2: o | P2: p | Q2: q | R2: r | S2: s | T2: t | U2: u | V2: v | W2: w | X2: x | Y2: y | Z2: z | AA2: aa | AB2: ab | AC2: ac | AD2: ad
A4: Global | B4: Activities | G4: Commodities | L4: Factors | Q4: Institutions | U4: Households | X4: Transaction costs | AB4: Mapping: Activities-Commodities
B5: All | C5: Agric. | D5: Mining | E5: Industry | F5: Services | G5: All | H5: Agric. | I5: Mining | J5: Industry | K5: Services | L5: All | M5: Aggregate | N5: Labor | O5: Capital | P5: Land | Q5: All | R5: Domestic | S5: Non-gov. | T5: Enterprises | U5: All | V5: Rural | W5: Urban | X5: Domestic | Y5: Export | Z5: Import | AB5: MAC
A6: AC | B6: A | C6: AAGR | D6: AMIN | E6: AIND | F6: ASER | G6: C | H6: CAGR | I6: CMIN | J6: CIND | K6: CSER | L6: F | M6: FA | N6: FLAB | O6: FCAP | P6: FLND | Q6: INS | R6: INSD | S6: INSDNG | T6: EN | U6: H | V6: HRUR | W6: HURB | X6: CTD | Y6: CTE | Z6: CTM | AB6: A | AC6: C
A7: amaiz | B7: amaiz | C7: amaiz | D7: acoal | E7: ameat | F7: atrad | G7: cmaiz | H7: cmaiz | I7: ccoal | J7: cmeat | K7: ctrad | L7: flab-rn | N7: flab-rn | O7: fcap-c | P7: flnd | Q7: ent | R7: ent | S7: ent | T7: ent | U7: hhd-f1 | V7: hhd-f1 | W7: hhd-u1 | X7: trd | Y7: tre | Z7: trm | AB7: amaiz | AC7: cmaiz
A8: asorg | B8: asorg | C8: asorg | D8: acoil | E8: afsea | F8: atran | G8: csorg | H8: csorg | I8: ccoil | J8: cfsea | K8: ctran | L8: flab-rp | N8: flab-rp | O8: fcap-l | Q8: hhd-f1 | R8: hhd-f1 | S8: hhd-f1 | U8: hhd-f2 | V8: hhd-f2 | W8: hhd-u2 | AB8: asorg | AC8: csorg
A9: arice | B9: arice | C9: arice | D9: angas | E9: adair | F9: ahotl | G9: crice | H9: crice | I9: cngas | J9: cdair | K9: chotl | L9: flab-rs | N9: flab-rs | O9: fcap-m | Q9: hhd-f2 | R9: hhd-f2 | S9: hhd-f2 | U9: hhd-f3 | V9: hhd-f3 | W9: hhd-u3 | AB9: arice | AC9: crice
A10: awhea | B10: awhea | C10: awhea | D10: aomin | E10: afveg | F10: arest | G10: cwhea | H10: cwhea | I10: comin | J10: cfveg | K10: crest | L10: flab-rt | N10: flab-rt | O10: fcap-n | Q10: hhd-f3 | R10: hhd-f3 | S10: hhd-f3 | U10: hhd-f4 | V10: hhd-f4 | W10: hhd-u4 | AB10: awhea | AC10: cwhea
A11: aocer | B11: aocer | C11: aocer | E11: afoil | F11: acomm | G11: cocer | H11: cocer | J11: cfoil | K11: ccomm | L11: flab-un | N11: flab-un | Q11: hhd-f4 | R11: hhd-f4 | S11: hhd-f4 | U11: hhd-f5 | V11: hhd-f5 | W11: hhd-u5 | AB11: aocer | AC11: cocer
A12: apuls | B12: apuls | C12: apuls | E12: ammll | F12: afsrv | G12: cpuls | H12: cpuls | J12: cmmll | K12: cfsrv | L12: flab-up | N12: flab-up | Q12: hhd-f5 | R12: hhd-f5 | S12: hhd-f5 | U12: hhd-n1 | V12: hhd-n1 | AB12: apuls | AC12: cpuls
A13: agnut | B13: agnut | C13: agnut | E13: asmll | F13: areal | G13: cgnut | H13: cgnut | J13: csmll | K13: creal | L13: flab-us | N13: flab-us | Q13: hhd-n1 | R13: hhd-n1 | S13: hhd-n1 | U13: hhd-n2 | V13: hhd-n2 | AB13: agnut | AC13: cgnut
A14: aoils | B14: aoils | C14: aoils | E14: armll | F14: absrv | G14: coils | H14: coils | J14: crmll | K14: cbsrv | L14: flab-ut | N14: flab-ut | Q14: hhd-n2 | R14: hhd-n2 | S14: hhd-n2 | U14: hhd-n3 | V14: hhd-n3 | AB14: aoils | AC14: coils
A15: acass | B15: acass | C15: acass | E15: awmll | F15: apadm | G15: ccass | H15: ccass | J15: cwmll | K15: cpadm | L15: flnd | Q15: hhd-n3 | R15: hhd-n3 | S15: hhd-n3 | U15: hhd-n4 | V15: hhd-n4 | AB15: acass | AC15: ccass
A16: aipot | B16: aipot | C16: aipot | E16: agmll | F16: aeduc | G16: cipot | H16: cipot | J16: cgmll | K16: ceduc | L16: fcap-c | Q16: hhd-n4 | R16: hhd-n4 | S16: hhd-n4 | U16: hhd-n5 | V16: hhd-n5 | AB16: aipot | AC16: cipot
A17: aspot | B17: aspot | C17: aspot | E17: asref | F17: aheal | G17: cspot | H17: cspot | J17: csref | K17: cheal | L17: fcap-l | Q17: hhd-n5 | R17: hhd-n5 | S17: hhd-n5 | U17: hhd-u1 | AB17: aspot | AC17: cspot
A18: aroot | B18: aroot | C18: aroot | E18: apcof | F18: aosrv | G18: croot | H18: croot | J18: cpcof | K18: cosrv | L18: fcap-m | Q18: hhd-u1 | R18: hhd-u1 | S18: hhd-u1 | U18: hhd-u2 | AB18: aroot | AC18: croot
A19: aleaf | B19: aleaf | C19: aleaf | E19: aptea | G19: cleaf | H19: cleaf | J19: cptea | L19: fcap-n | Q19: hhd-u2 | R19: hhd-u2 | S19: hhd-u2 | U19: hhd-u3 | AB19: aleaf | AC19: cleaf
A20: avege | B20: avege | C20: avege | E20: afood | G20: cvege | H20: cvege | J20: cfood | Q20: hhd-u3 | R20: hhd-u3 | S20: hhd-u3 | U20: hhd-u4 | AB20: avege | AC20: cvege
A21: asugr | B21: asugr | C21: asugr | E21: afeed | G21: csugr | H21: csugr | J21: cfeed | Q21: hhd-u4 | R21: hhd-u4 | S21: hhd-u4 | U21: hhd-u5 | AB21: asugr | AC21: csugr
A22: atoba | B22: atoba | C22: atoba | E22: abeve | G22: ctoba | H22: ctoba | J22: cbeve | Q22: hhd-u5 | R22: hhd-u5 | S22: hhd-u5 | AB22: atoba | AC22: ctoba
A23: acott | B23: acott | C23: acott | E23: aptob | G23: ccott | H23: ccott | J23: cptob | Q23: gov | R23: gov | AB23: acott | AC23: ccott
A24: anuts | B24: anuts | C24: anuts | E24: ayarn | G24: cnuts | H24: cnuts | J24: cyarn | Q24: row | AB24: anuts | AC24: cnuts
A25: abana | B25: abana | C25: abana | E25: atext | G25: cbana | H25: cbana | J25: ctext | AB25: abana | AC25: cbana
A26: afrui | B26: afrui | C26: afrui | E26: aclth | G26: cfrui | H26: cfrui | J26: cclth | AB26: afrui | AC26: cfrui
A27: ateal | B27: ateal | C27: ateal | E27: aleat | G27: cteal | H27: cteal | J27: cleat | AB27: ateal | AC27: cteal
A28: acoff | B28: acoff | C28: acoff | E28: awood | G28: ccoff | H28: ccoff | J28: cwood | AB28: acoff | AC28: ccoff
A29: acoco | B29: acoco | C29: acoco | E29: apapr | G29: ccoco | H29: ccoco | J29: cpapr | AB29: acoco | AC29: ccoco
A30: aflwr | B30: aflwr | C30: aflwr | E30: apetr | G30: cflwr | H30: cflwr | J30: cpetr | AB30: aflwr | AC30: cflwr
A31: arubb | B31: arubb | C31: arubb | E31: afert | G31: crubb | H31: crubb | J31: cfert | AB31: arubb | AC31: crubb
A32: aocrp | B32: aocrp | C32: aocrp | E32: achem | G32: cocrp | H32: cocrp | J32: cchem | AB32: aocrp | AC32: cocrp
A33: acatt | B33: acatt | C33: acatt | E33: anmet | G33: ccatt | H33: ccatt | J33: cnmet | AB33: acatt | AC33: ccatt
A34: amilk | B34: amilk | C34: amilk | E34: ametl | G34: cmilk | H34: cmilk | J34: cmetl | AB34: amilk | AC34: cmilk
A35: apoul | B35: apoul | C35: apoul | E35: amach | G35: cpoul | H35: cpoul | J35: cmach | AB35: apoul | AC35: cpoul
A36: aeggs | B36: aeggs | C36: aeggs | E36: aequi | G36: ceggs | H36: ceggs | J36: cequi | AB36: aeggs | AC36: ceggs
... A41: afish | B41: afish | C41: afish | E41: acons | G41: cfish | H41: cfish | J41: ccons | AB41: afish | AC41: cfish
A42: acoal | B42: acoal | G42: ccoal | AB42: acoal | AC42: ccoal
A43: acoil | B43: acoil | G43: ccoil | AB43: acoil | AC43: ccoil
A44: angas | B44: angas | G44: cngas | AB44: angas | AC44: cngas
A45: aomin | B45: aomin | G45: comin | AB45: aomin | AC45: comin
A46: ameat | B46: ameat | G46: cmeat | AB46: ameat | AC46: cmeat
A47: afsea | B47: afsea | G47: cfsea | AB47: afsea | AC47: cfsea
A48: adair | B48: adair | G48: cdair | AB48: adair | AC48: cdair
A49: afveg | B49: afveg | G49: cfveg | AB49: afveg | AC49: cfveg
A50: afoil | B50: afoil | G50: cfoil | AB50: afoil | AC50: cfoil
A51: ammll | B51: ammll | G51: cmmll | AB51: ammll | AC51: cmmll
A52: asmll | B52: asmll | G52: csmll | AB52: asmll | AC52: csmll
A53: armll | B53: armll | G53: crmll | AB53: armll | AC53: crmll
... A92: aosrv | B92: aosrv | G92: cosrv | AB92: aosrv | AC92: cosrv
A93: cmaiz
A94: csorg
A95: crice
A96: cwhea
A97: cocer
A98: cpuls
A99: cgnut
A100: coils
A101: ccass
A102: cipot
A103: cspot
A104: croot
... A234: total

Sheet SAM
A1: =CONCATENATE(Notes!B4," ",Notes!B3," Social Accounting Matrix") -> Social Accounting Matrix
A6: Billions of Rwanda Francs
B7: amaiz | C7: asorg | D7: arice | E7: awhea | F7: apuls | G7: agnut | H7: aoils | I7: acass | J7: aipot | K7: aspot | L7: aroot | M7: aleaf | N7: avege | O7: asugr | P7: atoba | Q7: abana | R7: afrui | S7: ateal | T7: acoff | U7: aocrp | V7: acatt | W7: amilk | X7: apoul | Y7: aeggs | Z7: asmlr | AA7: aoliv | AB7: afore | AC7: aaqua | AD7: afish | AE7: aomin | AF7: ameat | AG7: adair | AH7: afveg | AI7: afoil | AJ7: ammll | AK7: asmll | AL7: armll | AM7: awmll | AN7: asref | AO7: apcof | AP7: aptea | AQ7: afood | AR7: afeed | AS7: abeve | AT7: aptob | AU7: atext | AV7: aclth | AW7: aleat | AX7: awood | AY7: apapr | AZ7: afert | BA7: achem | BB7: anmet | BC7: ametl | BD7: amach | BE7: aequi | BF7: avehi | BG7: aoman | BH7: aelec | BI7: awatr | BJ7: acons | BK7: atrad | BL7: atran | BM7: ahotl | BN7: arest | BO7: acomm | BP7: afsrv | BQ7: areal | BR7: absrv | BS7: apadm | BT7: aeduc | BU7: aheal | BV7: aosrv | BW7: cmaiz | BX7: csorg | BY7: crice | BZ7: cwhea | CA7: cpuls | CB7: cgnut | CC7: coils | CD7: ccass | CE7: cipot | CF7: cspot | CG7: croot | CH7: cleaf | CI7: cvege | CJ7: csugr | CK7: ctoba | CL7: cbana | CM7: cfrui | CN7: cteal | CO7: ccoff | CP7: cocrp | CQ7: ccatt | CR7: cmilk | CS7: cpoul | CT7: ceggs | CU7: csmlr | CV7: coliv | CW7: cfore | CX7: caqua | CY7: cfish | CZ7: ccoal | DA7: cngas | DB7: comin | DC7: cmeat | DD7: cfsea | DE7: cdair | DF7: cfveg | DG7: cfoil | DH7: cmmll | DI7: csmll | DJ7: crmll | DK7: cwmll | DL7: csref | DM7: cpcof | DN7: cptea | DO7: cfood | DP7: cfeed | DQ7: cbeve | DR7: cptob | DS7: cyarn | DT7: ctext | DU7: cclth | DV7: cleat | DW7: cwood | DX7: cpapr | DY7: cpetr | DZ7: cfert | EA7: cchem | EB7: cnmet | EC7: cmetl | ED7: cmach | EE7: cequi | EF7: cvehi | EG7: coman | EH7: celec | EI7: cwatr | EJ7: ccons | EK7: ctrad | EL7: ctran | EM7: chotl | EN7: crest | EO7: ccomm | EP7: cfsrv | EQ7: creal | ER7: cbsrv | ES7: cpadm | ET7: ceduc | EU7: cheal | EV7: cosrv | EW7: trc | EX7: flab-rn | EY7: flab-rp | EZ7: flab-rs | FA7: flab-rt | FB7: flab-un | FC7: flab-up | FD7: flab-us | FE7: flab-ut | FF7: flnd | FG7: fcap-c | FH7: fcap-l | FI7: fcap-m | FJ7: fcap-n | FK7: ent | FL7: hhd-f1 | FM7: hhd-f2 | FN7: hhd-f3 | FO7: hhd-f4 | FP7: hhd-f5 | FQ7: hhd-n1 | FR7: hhd-n2 | FS7: hhd-n3 | FT7: hhd-n4 | FU7: hhd-n5 | FV7: hhd-u1 | FW7: hhd-u2 | FX7: hhd-u3 | FY7: hhd-u4 | FZ7: hhd-u5 | GA7: gov | GB7: dtax | GC7: ftax | GD7: mtax | GE7: stax | GF7: s-i | GG7: dstk | GH7: row | GI7: total
A8: amaiz | BW8: 74.18564 | FL8: 2.3156935 | FM8: 3.6969663 | FN8: 5.2632086 | FO8: 6.5031495 | FP8: 3.7954764 | FV8: 0.0308592 | FW8: 0.10958441 | FX8: 0.1437226 | FY8: 0.22680586 | FZ8: 0.57867237 | GI8: 96.849778
A9: asorg | BX9: 30.796227 | FL9: 0.01191309 | FM9: 0.023352112 | FN9: 0.012480007 | FO9: 0.021472574 | FP9: 0.068811165 | GI9: 30.934256
A10: arice | BY10: 29.235197 | FL10: 0.22192994 | FM10: 0.58260707 | FN10: 0.82136818 | FO10: 1.0680663 | FP10: 0.61625157 | FW10: 0.0063398223 | FX10: 0.055957197 | FY10: 0.039771714 | FZ10: 0.014323971 | GI10: 32.661813
A11: awhea | BZ11: 10.514045 | FL11: 0.04940098 | FM11: 0.0018198163 | FN11: 0.0010600397 | FP11: 0.022509867 | FX11: 0.002030379 | GI11: 10.590866
A12: apuls | CA12: 159.97086 | FL12: 10.378059 | FM12: 17.274315 | FN12: 24.139622 | FO12: 28.828249 | FP12: 18.508412 | FV12: 0.36685072 | FW12: 0.78092207 | FX12: 1.0728396 | FY12: 1.4123506 | FZ12: 3.3845684 | GI12: 266.11705
A13: agnut | CB13: 11.601489 | FL13: 0.18871397 | FM13: 0.32156581 | FN13: 0.81962415 | FO13: 1.075562 | FP13: 0.96790179 | FV13: 0.0092650233 | FW13: 0.0037986495 | FX13: 0.026951489 | FY13: 0.012597034 | FZ13: 0.14626207 | GI13: 15.173731
A14: aoils | CC14: 3.3557016 | FL14: 0.2652908 | FM14: 0.39188717 | FN14: 0.46064989 | FO14: 0.58671867 | FP14: 0.27378579 | FV14: 0.0050206082 | FW14: 0.016867736 | FX14: 0.017289164 | FY14: 0.020499509 | FZ14: 1.0954003 | GI14: 6.4891113
A15: acass | CD15: 113.27157 | FL15: 7.0429467 | FM15: 11.959616 | FN15: 16.840759 | FO15: 18.012301 | FP15: 10.497284 | FV15: 0.16068173 | FW15: 0.36351999 | FX15: 0.29990205 | FY15: 0.80970461 | FZ15: 1.0319883 | GI15: 180.29027
A16: aipot | CE16: 64.381627 | FL16: 2.1572187 | FM16: 4.8500577 | FN16: 8.3358514 | FO16: 9.9502245 | FP16: 5.9154678 | FV16: 0.039284331 | FW16: 0.0812121 | FX16: 0.22352083 | FY16: 0.372166 | FZ16: 0.77217217 | GI16: 97.078803
A17: aspot | CF17: 57.227391 | FL17: 6.7246231 | FM17: 9.5220143 | FN17: 11.504436 | FO17: 11.218642 | FP17: 4.8603448 | FV17: 0.11461289 | FW17: 0.28072783 | FX17: 0.30337564 | FY17: 0.27090055 | FZ17: 0.3323964 | GI17: 102.35946
A18: aroot | CG18: 9.1578541 | FL18: 0.70538477 | FM18: 1.3133803 | FN18: 2.0321645 | FO18: 2.4742005 | FP18: 1.5368839 | FV18: 0.023085331 | FW18: 0.0588401 | FX18: 0.039760153 | FY18: 0.071929979 | FZ18: 0.1404431 | GI18: 17.553927
A19: aleaf | CH19: 69.501715 | FL19: 6.7009318 | FM19: 8.2045751 | FN19: 9.7040923 | FO19: 11.368299 | FP19: 7.4670232 | FV19: 0.2663671 | FW19: 0.51984891 | FX19: 0.73035381 | FY19: 0.81699125 | FZ19: 1.9463846 | GI19: 117.22658
A20: avege | CI20: 29.718428 | FL20: 0.31860507 | FM20: 0.60002285 | FN20: 0.96214467 | FO20: 1.243454 | FP20: 1.4294976 | FV20: 0.013624982 | FW20: 0.047269952 | FX20: 0.023986854 | FY20: 0.056135033 | FZ20: 0.18913076 | GI20: 34.6023
A21: asugr | CJ21: 21.177548 | GI21: 21.177548
A22: atoba | CK22: 13.612361 | GI22: 13.612361
A23: abana | CL23: 151.4767 | FL23: 6.3714546 | FM23: 11.646538 | FN23: 20.237362 | FO23: 30.293317 | FP23: 21.961186 | FV23: 0.13961585 | FW23: 0.58479347 | FX23: 0.81443421 | FY23: 1.2733783 | FZ23: 3.8745899 | GI23: 248.67337
A24: afrui | CM24: 47.713439 | FL24: 1.4232073 | FM24: 2.3357985 | FN24: 3.9028133 | FO24: 5.2461887 | FP24: 3.8163011 | FV24: 0.012149932 | FW24: 0.072482879 | FX24: 0.1643921 | FY24: 0.22293756 | FZ24: 0.92250989 | GI24: 65.832221
A25: ateal | CN25: 24.625759 | GI25: 24.625759
A26: acoff | CO26: 64.854809 | GI26: 64.854809
A27: aocrp | CP27: 2.3344349 | GI27: 2.3344349
A28: acatt | CQ28: 65.193022 | FM28: 0.033947736 | FN28: 0.043563827 | FO28: 0.012443356 | FP28: 0.028510149 | GI28: 65.311487
A29: amilk | CR29: 68.026219 | FL29: 0.30250087 | FM29: 1.7169731 | FN29: 3.3729656 | FO29: 6.2771108 | FP29: 6.8153589 | FV29: 0.01811628 | FW29: 0.055180973 | FX29: 0.094082861 | FY29: 0.27772786 | FZ29: 1.6541934 | GI29: 88.610429
A30: apoul | CS30: 53.806665 | FL30: 0.076679196 | FM30: 0.83426062 | FN30: 1.2093622 | FO30: 3.107609 | FP30: 4.6735463 | FX30: 0.38489291 | FZ30: 1.7628256 | GI30: 65.855841
A31: aeggs | CT31: 9.3678287 | FL31: 0.01092123 | FM31: 0.070562159 | FN31: 0.16602998 | FO31: 0.30405974 | FP31: 0.44204185 | FX31: 0.0045520995 | FY31: 0.017451415 | FZ31: 0.098196133 | GI31: 10.481643
A32: asmlr | CU32: 52.200559 | FL32: 0.40473757 | FN32: 1.5719198 | FO32: 0.83494311 | FP32: 0.68551109 | FY32: 0.82173989 | GI32: 56.51941
A33: aoliv | CV33: 15.453476 | FL33: 0.078316765 | FM33: 0.18301779 | FN33: 0.257502 | FO33: 0.49978413 | FP33: 0.18144125 | FX33: 0.027027247 | FZ33: 0.062252098 | GI33: 16.742818
A34: afore | CW34: 381.32137 | GI34: 381.32137
A35: aaqua | CX35: 2.3634805 | GI35: 2.3634805
A36: afish | CY36: 22.491306 | GI36: 22.491306
A37: aomin | DB37: 187.27955 | GI37: 187.27955
A38: ameat | DC38: 39.792944 | GI38: 39.792944
A39: adair | DE39: 19.720135 | GI39: 19.720135
A40: afveg | DF40: 8.5040524 | GI40: 8.5040524
A41: afoil | DG41: 1.2379079 | GI41: 1.2379079
A42: ammll | DH42: 83.695751 | GI42: 83.695751
A43: asmll | DI43: 24.902168 | GI43: 24.902168
A44: armll | DJ44: 27.039316 | GI44: 27.039316
A45: awmll | DK45: 15.866825 | GI45: 15.866825
A46: asref | DL46: 32.726484 | GI46: 32.726484
A47: apcof | DM47: 0.41106576 | GI47: 0.41106576
A48: aptea | DN48: 4.9311765 | GI48: 4.9311765
A49: afood | DO49: 147.65138 | GI49: 147.65138
A50: afeed | DP50: 0.10376829 | GI50: 0.10376829
A51: abeve | DQ51: 150.23816 | GI51: 150.23816
A52: aptob | DR52: 30.972665 | GI52: 30.972665
A53: atext | DT53: 2.6387414 | GI53: 2.6387414
A54: aclth | DU54: 44.338077 | GI54: 44.338077
A55: aleat | DV55: 0.64989954 | GI55: 0.64989954
A56: awood | DW56: 77.98448 | GI56: 77.98448
A57: apapr | DX57: 23.716593 | GI57: 23.716593
A58: afert | DZ58: 11.090585 | GI58: 11.090585
A59: achem | EA59: 152.118 | GI59: 152.118
A60: anmet | EB60: 59.50919 | GI60: 59.50919
A61: ametl | EC61: 104.29144 | GI61: 104.29144
A62: amach | ED62: 0.2756225 | GI62: 0.2756225
A63: aequi | EE63: 5.835927 | GI63: 5.835927
A64: avehi | EF64: 2.4236116 | GI64: 2.4236116
A65: aoman | EG65: 153.59251 | GI65: 153.59251
A66: aelec | EH66: 261.76448 | GI66: 261.76448
A67: awatr | EI67: 62.273416 | GI67: 62.273416
A68: acons | EJ68: 1465.6666 | GI68: 1465.6666
A69: atrad | EK69: 1241.2242 | GI69: 1241.2242
A70: atran | EL70: 599.6041 | GI70: 599.6041
A71: ahotl | EM71: 142.04402 | GI71: 142.04402
A72: arest | EN72: 243.27381 | GI72: 243.27381
A73: acomm | EO73: 334.60685 | GI73: 334.60685
A74: afsrv | EP74: 371.46627 | GI74: 371.46627
A75: areal | EQ75: 681.10044 | GI75: 681.10044
A76: absrv | ER76: 553.60296 | GI76: 553.60296
A77: apadm | ES77: 703.99317 | GI77: 703.99317
A78: aeduc | ET78: 405.37013 | GI78: 405.37013
A79: aheal | EU79: 296.65956 | GI79: 296.65956
A80: aosrv | EV80: 430.80797 | GI80: 430.80797
A81: cmaiz | B81: 3.1064289 | V81: 7.7007135 | W81: 6.6445241 | X81: 4.5251648 | Y81: 0.60525756 | Z81: 3.5629538 | AA81: 0.72562681 | AJ81: 33.850913 | AQ81: 5.6324507 | AR81: 0.020387036 | AS81: 3.1337647 | BN81: 0.077746134 | FL81: 4.2758946 | FM81: 5.5114415 | FN81: 5.2801944 | FO81: 8.4093675 | FP81: 4.8485259 | FQ81: 0.12882581 | FR81: 0.061659024 | FS81: 0.25800134 | FT81: 0.023727133 | FU81: 0.29484684 | FV81: 0.14484381 | FW81: 0.32183249 | FX81: 0.45309895 | FY81: 0.88902609 | FZ81: 2.0212068 | GH81: 0.64447817 | GI81: 103.1529
A82: csorg | C82: 0.94803564 | AK82: 10.962437 | AS82: 8.7094719 | BN82: 1.1901798 | FL82: 0.56885213 | FM82: 1.5275949 | FN82: 2.0707004 | FO82: 3.4096018 | FP82: 4.4823769 | FR82: 0.0073557348 | FS82: 0.028721224 | FT82: 0.018506314 | FU82: 0.10428625 | FW82: 0.035422599 | FX82: 0.19144239 | FY82: 0.13941082 | FZ82: 0.43961068 | GI82: 34.834007
A83: crice | D83: 3.1147231 | AL83: 13.733005 | FL83: 1.6769469 | FM83: 2.9985105 | FN83: 4.4493144 | FO83: 6.9785339 | FP83: 6.7305368 | FQ83: 0.02435592 | FR83: 0.058938981 | FS83: 0.056710906 | FT83: 0.072896042 | FU83: 0.48585939 | FV83: 0.12351675 | FW83: 0.34238686 | FX83: 0.39584065 | FY83: 1.1625166 | FZ83: 5.0173517 | GH83: 9.2892381 | GI83: 56.711183
A84: cwhea | E84: 0.61351667 | X84: 4.2259632 | AM84: 8.2088801 | AQ84: 12.434059 | BN84: 0.033265257 | FL84: 0.023023879 | FM84: 0.047029562 | FN84: 0.084933734 | FO84: 0.2025381 | FP84: 0.19495429 | FS84: 0.0085495086 | FT84: 0.0040341939 | FX84: 0.033641379 | FY84: 0.03338394 | FZ84: 0.05930115 | GI84: 26.207074
A85: cpuls | F85: 10.288411 | BN85: 0.026941176 | BT85: 0.71283998 | BU85: 0.46271087 | FL85: 21.667839 | FM85: 28.149073 | FN85: 31.005919 | FO85: 36.578849 | FP85: 23.831368 | FQ85: 0.40397762 | FR85: 0.62367068 | FS85: 0.69192627 | FT85: 0.52797445 | FU85: 2.2043538 | FV85: 0.76336547 | FW85: 2.1777084 | FX85: 2.5553779 | FY85: 5.4643993 | FZ85: 29.478122 | GH85: 1.3425019 | GI85: 198.95733
A86: cgnut | G86: 1.4313567 | AI86: 0.15708289 | FL86: 1.4088696 | FM86: 2.0300271 | FN86: 2.5746206 | FO86: 3.8498797 | FP86: 3.3035515 | FQ86: 0.020069048 | FR86: 0.053805217 | FS86: 0.059476048 | FT86: 0.06098125 | FU86: 0.33664317 | FV86: 0.057343804 | FW86: 0.18276378 | FX86: 0.24119775 | FY86: 0.63950634 | FZ86: 3.977475 | GH86: 0.08092836 | GI86: 20.465578
A87: coils | H87: 0.10099318 | AI87: 0.37757586 | AQ87: 1.0916807 | AR87: 0.030495904 | BN87: 0.23933249 | FL87: 0.78592617 | FM87: 0.86946926 | FN87: 0.86372148 | FO87: 0.95471009 | FP87: 0.84497829 | FQ87: 0.02199961 | FR87: 0.014411552 | FS87: 0.036634924 | FT87: 0.01152063 | FU87: 0.03294136 | FV87: 0.026004724 | FW87: 0.035497028 | FX87: 0.034684659 | FY87: 0.084186555 | FZ87: 0.45043045 | GI87: 6.9071949
A88: ccass | I88: 4.4838901 | AS88: 1.072447 | BT88: 15.271535 | BU88: 0.14516389 | FL88: 18.413135 | FM88: 19.96798 | FN88: 19.592638 | FO88: 20.973691 | FP88: 14.460077 | FQ88: 0.31664611 | FR88: 0.64223267 | FS88: 0.5283409 | FT88: 0.4238955 | FU88: 1.5842883 | FV88: 0.81852807 | FW88: 1.5370025 | FX88: 1.8146592 | FY88: 5.1160968 | FZ88: 19.09384 | GI88: 146.25609
A89: cipot | J89: 2.9979868 | BT89: 0.5208317 | BU89: 0.23131604 | FL89: 4.9531966 | FM89: 6.814064 | FN89: 8.9201087 | FO89: 12.429402 | FP89: 11.385706 | FQ89: 0.35260172 | FR89: 0.25753324 | FS89: 0.4671987 | FT89: 0.27536225 | FU89: 1.2340081 | FV89: 0.45209293 | FW89: 1.0972996 | FX89: 1.4927632 | FY89: 3.3562168 | FZ89: 19.999113 | GH89: 0.24066474 | GI89: 77.477467
A90: cspot | K90: 9.7563849 | BN90: 0.022450368 | BT90: 0.64847898 | BU90: 0.38545073 | FL90: 13.254527 | FM90: 10.850162 | FN90: 10.065078 | FO90: 9.4176037 | FP90: 5.5452484 | FQ90: 0.32856474 | FR90: 0.29305289 | FS90: 0.2247122 | FT90: 0.1582005 | FU90: 0.37150195 | FV90: 0.68388665 | FW90: 0.85997315 | FX90: 0.92939752 | FY90: 1.76335 | FZ90: 4.8781215 | GI90: 70.436145
A91: croot | L91: 0.48811165 | FL91: 1.4841698 | FM91: 2.3044733 | FN91: 1.9244166 | FO91: 2.0911795 | FP91: 1.4182581 | FQ91: 0.010439808 | FR91: 0.0095353761 | FS91: 0.017778345 | FT91: 0.027745871 | FU91: 0.033437421 | FV91: 0.071364919 | FW91: 0.067894354 | FX91: 0.14333293 | FY91: 0.25324889 | FZ91: 1.2790026 | GI91: 11.624389
A92: cleaf | M92: 3.8189709 | FL92: 5.0348017 | FM92: 7.6119112 | FN92: 10.376058 | FO92: 14.726536 | FP92: 14.280409 | FQ92: 0.25064676 | FR92: 0.23791832 | FS92: 0.35400531 | FT92: 0.25277484 | FU92: 1.6956793 | FV92: 0.26742632 | FW92: 0.78261004 | FX92: 1.1655758 | FY92: 3.2519663 | FZ92: 28.806489 | GH92: 0.96106894 | GI92: 93.874847
A93: cvege | N93: 1.0246777 | AH93: 1.9420859 | FL93: 1.7956494 | FM93: 3.382577 | FN93: 5.3391151 | FO93: 9.094861 | FP93: 9.8122772 | FQ93: 0.03655926 | FR93: 0.083352633 | FS93: 0.13407672 | FT93: 0.13110362 | FU93: 1.0292371 | FV93: 0.12649175 | FW93: 0.41292164 | FX93: 0.69387528 | FY93: 2.1530354 | FZ93: 17.592265 | GI93: 54.784162
A94: csugr | O94: 0.98276197 | AN94: 19.357316 | FL94: 0.25272062 | FM94: 0.41581926 | FN94: 0.56324092 | FO94: 0.75320549 | FP94: 0.5650502 | FQ94: 0.010603409 | FR94: 0.014187984 | FS94: 0.012332384 | FT94: 0.0092500249 | FU94: 0.029851318 | FV94: 0.024912669 | FW94: 0.036315348 | FX94: 0.066073687 | FY94: 0.1057365 | FZ94: 0.28341445 | GI94: 23.482792
A95: ctoba | P95: 0.54674197 | AT95: 13.849671 | FL95: 0.34813634 | FM95: 0.490071 | FN95: 0.5680989 | FO95: 0.59191942 | FP95: 0.33380265 | FQ95: 0.0065616718 | FR95: 0.0050046029 | FS95: 0.0027017268 | FT95: 0.0017910544 | FU95: 0.0062983635 | FV95: 0.011787767 | FW95: 0.030884608 | FX95: 0.022778693 | FY95: 0.015503622 | FZ95: 0.031861681 | GI95: 16.863615
A96: cbana | Q96: 0.30500914 | AS96: 1.795092 | BN96: 1.5526826 | BT96: 7.0079921 | BU96: 9.5460461 | FL96: 9.7027801 | FM96: 14.201185 | FN96: 18.909576 | FO96: 26.525048 | FP96: 29.668102 | FQ96: 0.1689761 | FR96: 0.25284082 | FS96: 0.49135773 | FT96: 0.33724189 | FU96: 3.4293586 | FV96: 0.29204696 | FW96: 1.0228175 | FX96: 1.522306 | FY96: 4.9596327 | FZ96: 49.837332 | GI96: 181.52742
A97: cfrui | R97: 2.8242774 | AS97: 0.80889139 | BN97: 1.1889811 | BT97: 1.8907537 | BU97: 2.9919144 | FL97: 1.5040098 | FM97: 2.7181135 | FN97: 4.2732849 | FO97: 6.8944232 | FP97: 9.5995061 | FQ97: 0.050911751 | FR97: 0.060934055 | FS97: 0.063046829 | FT97: 0.11248721 | FU97: 1.2246007 | FV97: 0.074971148 | FW97: 0.25991722 | FX97: 0.52897585 | FY97: 1.3407923 | FZ97: 26.449727 | GI97: 64.86052
A98: cteal | S98: 0.9247934 | AP98: 2.5151881 | GH98: 30.254457 | GI98: 33.694438
A99: ccoff | T99: 1.8265408 | AO99: 0.23598216 | AQ99: 10.634589 | GH99: 61.240052 | GI99: 73.937164
A100: cocrp | U100: 0.074311136 | AP100: 0.0052176431 | AQ100: 3.959059 | GH100: 2.2563417 | GI100: 6.2949295
A101: ccatt | V101: 5.994466 | AF101: 4.7879467 | AW101: 0.0016810286 | FL101: 0.45427257 | FM101: 1.4868009 | FN101: 3.7050985 | FO101: 8.7075459 | FP101: 12.458083 | FQ101: 0.0076994475 | FR101: 0.0041472085 | FS101: 0.07037065 | FT101: 0.09215819 | FU101: 0.96891989 | FV101: 0.028033072 | FW101: 0.21975955 | FX101: 0.34023714 | FY101: 1.6836329 | FZ101: 22.269526 | GG101: 3.5102904 | GH101: 4.3862445 | GI101: 71.176914
A102: cmilk | W102: 16.985433 | AG102: 6.0372408 | AQ102: 1.7338636 | BN102: 2.1119945 | FL102: 0.47000869 | FM102: 1.1860072 | FN102: 1.8510358 | FO102: 4.7959174 | FP102: 6.9086124 | FQ102: 0.017161235 | FR102: 0.034749179 | FS102: 0.068314604 | FT102: 0.095085829 | FU102: 1.1983054 | FV102: 0.045552782 | FW102: 0.13327763 | FX102: 0.48947446 | FY102: 1.2335281 | FZ102: 28.021915 | GI102: 73.417478
A103: cpoul | X103: 11.855325 | Y103: 1.3296805 | AF103: 5.66051 | BN103: 5.9019649 | FM103: 0.15238953 | FN103: 0.78395529 | FO103: 2.032102 | FP103: 3.4694656 | FU103: 1.203255 | FX103: 0.095850964 | FY103: 0.20667057 | FZ103: 26.18575 | GI103: 58.876919
A104: ceggs | X104: 3.0808659 | Y104: 0.49813802 | AQ104: 0.24948947 | BN104: 1.9315268 | FL104: 0.01554948 | FM104: 0.041605982 | FN104: 0.091810983 | FO104: 0.31924294 | FP104: 1.0066755 | FR104: 0.0042542621 | FS104: 0.0052583608 | FT104: 0.0039984234 | FU104: 0.16279366 | FW104: 0.0045099003 | FX104: 0.022602542 | FY104: 0.054351161 | FZ104: 3.3830198 | GH104: 0.026747333 | GI104: 10.902441
...

Sheet a
D2: Act | E2: Com | F2: Mar | G2: Fact | H2: Fact | I2: Fact | J2: Ent | K2: HH | L2: Gov | M2: S | N2: Row | O2: Tot
D3: 1 | E3: 2 | F3: 3 | G3: 4.1 | H3: 4.2 | I3: 4.3
J4: 5 | K4: 6 | L4: 7 | M4: 8 | N4: 9 | O4: 10
B5: 1 | C5: Activities | E5: =SUM(SAM!BW8:EV80) -> 10865.933 | O5: =SUM(D5:N5) -> 10865.933
B6: 2 | C6: Commodities | D6: =SUM(SAM!B81:BV158) -> 5362.1153 | O6: =SUM(D6:N6) -> 5362.1153
B7: 3 | C7: Margins | O7: =SUM(D7:N7) -> 0
B8: 4.1 | C8: Labor | O8: =SUM(D8:N8) -> 0
B9: 4.2 | C9: Land | O9: =SUM(D9:N9) -> 0
B10: 4.3 | C10: Capital | O10: =SUM(D10:N10) -> 0
B11: 5 | C11: Enterprises | O11: =SUM(D11:N11) -> 0
B12: 6 | C12: Households | O12: =SUM(D12:N12) -> 0
B13: 7 | C13: Government | O13: =SUM(D13:N13) -> 0
B14: 8 | C14: Savings | O14: =SUM(D14:N14) -> 0
B15: 9 | C15: Rest of world | O15: =SUM(D15:N15) -> 0
B16: 10 | C16: Total | D16: =SUM(D5:D15) -> 5362.1153 | E16: =SUM(E5:E15) -> 10865.933 | F16: =SUM(F5:F15) -> 0 | G16: =SUM(G5:G15) -> 0 | H16: =SUM(H5:H15) -> 0 | I16: =SUM(I5:I15) -> 0 | J16: =SUM(J5:J15) -> 0 | K16: =SUM(K5:K15) -> 0 | ... N16: =SUM(N5:N15) -> 0 | O16: =SUM(D16:N16) -> 16228.048
D18: {=TRANSPOSE(O5:O16)} -> 10865.933 | E18: 5362.1153 | F18: 0 | G18: 0 | H18: 0 | I18: 0 | J18: 0 | K18: 0 | L18: 0 | M18: 0 | N18: 0 | O18: 16228.048
D20: =D16-D18 -> -5503.8175 | E20: =E16-E18 -> 5503.8175 | F20: =F16-F18 -> 0 | G20: =G16-G18 -> 0 | H20: =H16-H18 -> 0 | I20: =I16-I18 -> 0 | J20: =J16-J18 -> 0 | K20: =K16-K18 -> 0 | ... O20: =O16-O18 -> 0

Sheet a_1
D2: Act | E2: Com | F2: Mar | G2: Fact | H2: Fact | I2: Fact | J2: Ent | K2: HH | L2: Gov | M2: S | N2: Row | O2: Tot
D3: 1 | E3: 2 | F3: 3 | G3: 4.1 | H3: 4.2 | I3: 4.3
J4: 5 | K4: 6 | L4: 7 | M4: 8 | N4: 9 | O4: 10
B5: 1 | C5: Activities | E5: =SUM(SAM!BW8:EV80) -> 10865.933 | K5: =SUM(SAM!FL8:FZ80) -> 499.79952 | O5: =SUM(D5:N5) -> 11365.732
B6: 2 | C6: Commodities | D6: =SUM(SAM!B81:BV158) -> 5362.1153 | F6: =SUM(SAM!EW81:EW158) -> 1009.9683 | K6: =SUM(SAM!FL81:FZ158) -> 4389.748 | L6: =SUM(SAM!GA81:GA158) -> 1072.2008 | M6: =SUM(SAM!GF81:GG158) -> 1715.7024 | N6: =SUM(SAM!GH81:GH158) -> 956.849 | O6: =SUM(D6:N6) -> 14506.584
B7: 3 | C7: Margins | E7: =SUM(SAM!BW159:EV159) -> 1009.9683 | O7: =SUM(D7:N7) -> 1009.9683
B8: 4.1 | C8: Labor | D8: =SUM(SAM!B160:BV167) -> 3419.5126 | N8: =SUM(SAM!GH160:GH167) -> 4.0893737 | O8: =SUM(D8:N8) -> 3423.602
B9: 4.2 | C9: Land | D9: =SUM(SAM!B168:BV168) -> 750.44467 | O9: =SUM(D9:N9) -> 750.44467
B10: 4.3 | C10: Capital | D10: =SUM(SAM!B169:BV172) -> 1833.6597 | N10: =SUM(SAM!GH169:GH172) -> 3.274695 | O10: =SUM(D10:N10) -> 1836.9344
B11: 5 | C11: Enterprises | I11: =SUM(SAM!FG173:FJ173) -> 1336.7372 | L11: =SUM(SAM!GA173) -> 144.65696 | N11: =SUM(SAM!GH173) -> 63.243465 | O11: =SUM(D11:N11) -> 1544.6376
B12: 6 | C12: Households | G12: =SUM(SAM!EX174:FE188) -> 3365.341 | H12: =SUM(SAM!FF174:FF188) -> 750.44467 | I12: =SUM(SAM!FG174:FJ188) -> 318.52876 | J12: =SUM(SAM!FK174:FK188) -> 1047.6835 | L12: =SUM(SAM!GA174:GA188) -> 120.21174 | N12: =SUM(SAM!GH174:GH188) -> 85.608471 | O12: =SUM(D12:N12) -> 5687.8181
B13: 7 | C13: Government | E13: =SUM(SAM!BW189:EV193) -> 432.66208 | I13: =SUM(SAM!FG189:FJ193) -> 0.79905242 | J13: =SUM(SAM!FK189:FK193) -> 438.51299 | K13: =SUM(SAM!FL189:FZ193) -> 379.21767 | L13: =SUM(SAM!GB189:GE189) -> 1005.3215 | N13: =SUM(SAM!GH189) -> 448.86051 | O13: =SUM(D13:N13) -> 2705.3738
B14: 8 | C14: Savings | J14: =SAM!FK194 -> 53.357948 | K14: =SUM(SAM!FL194:FZ194) -> 371.94692 | L14: =SUM(SAM!GA194) -> 331.84624 | N14: =SUM(SAM!GH194) -> 958.55127 | O14: =SUM(D14:N14) -> 1715.7024
B15: 9 | C15: Rest of world | E15: =SUM(SAM!BW196:EV196) -> 2198.0207 | G15: =SUM(SAM!EX196:FE196) -> 58.260978 | I15: =SUM(SAM!FG196:FJ196) -> 180.86936 | J15: =SAM!FK196 -> 5.0832319 | K15: =SUM(SAM!FL196:FZ196) -> 47.105972 | L15: =SUM(SAM!GA196) -> 31.136548 | O15: =SUM(D15:N15) -> 2520.4768
B16: 10 | C16: Total | D16: =SUM(D5:D15) -> 11365.732 | E16: =SUM(E5:E15) -> 14506.584 | F16: =SUM(F5:F15) -> 1009.9683 | G16: =SUM(G5:G15) -> 3423.602 | H16: =SUM(H5:H15) -> 750.44467 | I16: =SUM(I5:I15) -> 1836.9344 | J16: =SUM(J5:J15) -> 1544.6376 | K16: =SUM(K5:K15) -> 5687.8181 | ... N16: =SUM(N5:N15) -> 2520.4768 | O16: =SUM(D16:N16) -> 47067.274
D18: {=TRANSPOSE(O5:O16)} -> 11365.732 | E18: 14506.584 | F18: 1009.9683 | G18: 3423.602 | H18: 750.44467 | I18: 1836.9344 | J18: 1544.6376 | K18: 5687.8181 | L18: 2705.3738 | M18: 1715.7024 | N18: 2520.4768 | O18: 47067.274
D20: =D16-D18 -> 0 | E20: =E16-E18 -> 0 | F20: =F16-F18 -> -1.2505552e-12 | G20: =G16-G18 -> 0 | H20: =H16-H18 -> 0 | I20: =I16-I18 -> 0 | J20: =J16-J18 -> 0 | K20: =K16-K18 -> 0 | ... O20: =O16-O18 -> 0

Sheet b,c_1
C1: amaiz | D1: asorg | E1: arice | F1: awhea | G1: apuls | H1: agnut | I1: aoils | J1: acass | K1: aipot | L1: aspot | M1: aroot | N1: aleaf | O1: avege | P1: asugr | Q1: atoba | R1: abana | S1: afrui | T1: ateal | U1: acoff | V1: aocrp | W1: acatt | X1: amilk | Y1: apoul | Z1: aeggs | AA1: asmlr | AB1: aoliv | AC1: afore | AD1: aaqua | AE1: afish | AF1: aomin | AG1: ameat | AH1: adair | AI1: afveg | AJ1: afoil | AK1: ammll | AL1: asmll | AM1: armll | AN1: awmll | AO1: asref | AP1: apcof | AQ1: aptea | AR1: afood | AS1: afeed | AT1: abeve | AU1: aptob | AV1: atext | AW1: aclth | AX1: aleat | AY1: awood | AZ1: apapr | BA1: afert | BB1: achem | BC1: anmet | BD1: ametl | BE1: amach | BF1: aequi | BG1: avehi | BH1: aoman | BI1: aelec | BJ1: awatr | BK1: acons | BL1: atrad | BM1: atran | BN1: ahotl | BO1: arest | BP1: acomm | BQ1: afsrv | BR1: areal | BS1: absrv | BT1: apadm | BU1: aeduc | BV1: aheal | BW1: aosrv
A2: b) | B2: VA share | C2: =SUM(SAM!B160:B172)/SUM(SAM!B197) -> 0.85392781 | D2: =SUM(SAM!C160:C172)/SUM(SAM!C197) -> 0.9585745 | E2: =SUM(SAM!D160:D172)/SUM(SAM!D197) -> 0.79324747 | F2: =SUM(SAM!E160:E172)/SUM(SAM!E197) -> 0.81326348 | G2: =SUM(SAM!F160:F172)/SUM(SAM!F197) -> 0.924367 | H2: =SUM(SAM!G160:G172)/SUM(SAM!G197) -> 0.66757252 | I2: =SUM(SAM!H160:H172)/SUM(SAM!H197) -> 0.94490689 | J2: =SUM(SAM!I160:I172)/SUM(SAM!I197) -> 0.92521003 | ... BW2: =SUM(SAM!BV160:BV172)/SUM(SAM!BV197) -> 0.73742672
A3: c) | B3: Lab in VA | C3: =SUM(SAM!B160:B167)/SUM(SAM!B160:B172) -> 0.36896183 | D3: =SUM(SAM!C160:C167)/SUM(SAM!C160:C172) -> 0.36073796 | E3: =SUM(SAM!D160:D167)/SUM(SAM!D160:D172) -> 0.42061347 | F3: =SUM(SAM!E160:E167)/SUM(SAM!E160:E172) -> 0.37351622 | G3: =SUM(SAM!F160:F167)/SUM(SAM!F160:F172) -> 0.28741862 | H3: =SUM(SAM!G160:G167)/SUM(SAM!G160:G172) -> 0.28890383 | I3: =SUM(SAM!H160:H167)/SUM(SAM!H160:H172) -> 0.35301528 | J3: =SUM(SAM!I160:I167)/SUM(SAM!I160:I172) -> 0.3159276 | ... BW3: =SUM(SAM!BV160:BV167)/SUM(SAM!BV160:BV172) -> 0.9217928

Sheet d,e,f,h
A2: d) | B2: hhd-f1 | C2: hhd-f2 | D2: hhd-f3 | E2: hhd-f4 | F2: hhd-f5 | G2: hhd-n1 | H2: hhd-n2 | I2: hhd-n3 | J2: hhd-n4 | K2: hhd-n5 | L2: hhd-u1 | M2: hhd-u2 | N2: hhd-u3 | O2: hhd-u4 | P2: hhd-u5 | R2: Total
A3: Food | B3: =SUM(SAM!FL8:FL33,SAM!FL81:FL106,SAM!FL108:FL117,SAM!FL122:FL125,SAM!FL127) -> 157.14994 | C3: =SUM(SAM!FM8:FM33,SAM!FM81:FM106,SAM!FM108:FM117,SAM!FM122:FM125,SAM!FM127) -> 232.4392 | D3: =SUM(SAM!FN8:FN33,SAM!FN81:FN106,SAM!FN108:FN117,SAM!FN122:FN125,SAM!FN127) -> 316.8153 | E3: =SUM(SAM!FO8:FO33,SAM!FO81:FO106,SAM!FO108:FO117,SAM!FO122:FO125,SAM!FO127) -> 435.41858 | F3: =SUM(SAM!FP8:FP33,SAM!FP81:FP106,SAM!FP108:FP117,SAM!FP122:FP125,SAM!FP127) -> 401.96433 | G3: =SUM(SAM!FQ8:FQ33,SAM!FQ81:FQ106,SAM!FQ108:FQ117,SAM!FQ122:FQ125,SAM!FQ127) -> 2.554934 | H3: =SUM(SAM!FR8:FR33,SAM!FR81:FR106,SAM!FR108:FR117,SAM!FR122:FR125,SAM!FR127) -> 3.4470785 | I3: =SUM(SAM!FS8:FS33,SAM!FS81:FS106,SAM!FS108:FS117,SAM!FS122:FS125,SAM!FS127) -> 4.5315419 | ... P3: =SUM(SAM!FZ8:FZ33,SAM!FZ81:FZ106,SAM!FZ108:FZ117,SAM!FZ122:FZ125,SAM!FZ127) -> 514.05917 | R3: =SUM(B3:P3) -> 2203.8209
A4: Total | B4: =SUM(SAM!FL8:FL158) -> 233.24389 | C4: =SUM(SAM!FM8:FM158) -> 353.83939 | D4: =SUM(SAM!FN8:FN158) -> 505.78977 | E4: =SUM(SAM!FO8:FO158) -> 749.31103 | F4: =SUM(SAM!FP8:FP158) -> 926.25083 | G4: =SUM(SAM!FQ8:FQ158) -> 4.2538867 | H4: =SUM(SAM!FR8:FR158) -> 5.4096952 | I4: =SUM(SAM!FS8:FS158) -> 7.6596073 | ... P4: =SUM(SAM!FZ8:FZ158) -> 1805.261 | R4: =SUM(B4:P4) -> 4889.5476
B6: =B3/B4 -> 0.67375803 | C6: =C3/C4 -> 0.65690595 | D6: =D3/D4 -> 0.62637743 | E6: =E3/E4 -> 0.58109192 | F6: =F3/F4 -> 0.4339692 | G6: =G3/G4 -> 0.60061168 | H6: =H3/H4 -> 0.63720383 | I6: =I3/I4 -> 0.59161543 | ... P6: =P3/P4 -> 0.28475615 | R6: =R3/R4 -> 0.45072081
A9: e) | B9: eduction, health, and public adminstration
A12: f) | B12: hhd-f1 | C12: hhd-f2 | D12: hhd-f3 | E12: hhd-f4 | F12: hhd-f5 | G12: hhd-n1 | H12: hhd-n2 | I12: hhd-n3 | J12: hhd-n4 | K12: hhd-n5 | L12: hhd-u1 | M12: hhd-u2 | N12: hhd-u3 | O12: hhd-u4 | P12: hhd-u5
A13: tax | B13: =SAM!FL190/SAM!FL197 -> 0.0070172739 | C13: =SAM!FM190/SAM!FM197 -> 0.010073408 | D13: =SAM!FN190/SAM!FN197 -> 0.015845932 | E13: =SAM!FO190/SAM!FO197 -> 0.026330419 | F13: =SAM!FP190/SAM!FP197 -> 0.053980816 | G13: =SAM!FQ190/SAM!FQ197 -> 0.0049322858 | H13: =SAM!FR190/SAM!FR197 -> 0.013827818 | I13: =SAM!FS190/SAM!FS197 -> 0.025426659 | ... P13: =SAM!FZ190/SAM!FZ197 -> 0.11447308
A16: g) | B16: lab | C16: n-lab | D16: total inc | F16: labor income share
A17: hhd-f1 | B17: =SUM(SAM!EX174:FE174) -> 114.06586 | C17: =SUM(SAM!FF174:FJ174) -> 103.64441 | D17: =SAM!GI174 -> 243.88066 | F17: =B17/D17 -> 0.46771176
A18: hhd-f2 | B18: =SUM(SAM!EX175:FE175) -> 178.0485 | C18: =SUM(SAM!FF175:FJ175) -> 147.01608 | D18: =SAM!GI175 -> 373.39196 | F18: =B18/D18 -> 0.47684074
A19: hhd-f3 | B19: =SUM(SAM!EX176:FE176) -> 274.58332 | C19: =SUM(SAM!FF176:FJ176) -> 194.73655 | D19: =SAM!GI176 -> 542.31659 | F19: =B19/D19 -> 0.50631555
A20: hhd-f4 | B20: =SUM(SAM!EX177:FE177) -> 408.41058 | C20: =SUM(SAM!FF177:FJ177) -> 293.81954 | D20: =SAM!GI177 -> 822.91917 | F20: =B20/D20 -> 0.49629489
A21: hhd-f5 | B21: =SUM(SAM!EX178:FE178) -> 640.44327 | C21: =SUM(SAM!FF178:FJ178) -> 220.75327 | D21: =SAM!GI178 -> 1067.3043 | F21: =B21/D21 -> 0.60005689
A22: hhd-n1 | B22: =SUM(SAM!EX179:FE179) -> 3.4652437 | C22: =SUM(SAM!FF179:FJ179) -> 0 | D22: =SAM!GI179 -> 4.5087249 | F22: =B22/D22 -> 0.768564
A23: hhd-n2 | B23: =SUM(SAM!EX180:FE180) -> 4.677685 | C23: =SUM(SAM!FF180:FJ180) -> 0 | D23: =SAM!GI180 -> 5.7881135 | F23: =B23/D23 -> 0.80815364
A24: hhd-n3 | B24: =SUM(SAM!EX181:FE181) -> 6.3952894 | C24: =SUM(SAM!FF181:FJ181) -> 0 | D24: =SAM!GI181 -> 8.3480572 | F24: =B24/D24 -> 0.76608117
A25: hhd-n4 | B25: =SUM(SAM!EX182:FE182) -> 6.3597675 | C25: =SUM(SAM!FF182:FJ182) -> 0 | D25: =SAM!GI182 -> 8.5950975 | F25: =B25/D25 -> 0.73992965
A26: hhd-n5 | B26: =SUM(SAM!EX183:FE183) -> 73.716414 | C26: =SUM(SAM!FF183:FJ183) -> 0 | D26: =SAM!GI183 -> 92.518556 | F26: =B26/D26 -> 0.79677438
A27: hhd-u1 | B27: =SUM(SAM!EX184:FE184) -> 6.686473 | C27: =SUM(SAM!FF184:FJ184) -> 2.1697677 | D27: =SAM!GI184 -> 11.979852 | F27: =B27/D27 -> 0.55814321
A28: hhd-u2 | B28: =SUM(SAM!EX185:FE185) -> 20.16217 | C28: =SUM(SAM!FF185:FJ185) -> 5.9334856 | D28: =SAM!GI185 -> 34.039757 | F28: =B28/D28 -> 0.59231239
... A31: hhd-u5 | B31: =SUM(SAM!EX188:FE188) -> 1513.2071 | C31: =SUM(SAM!FF188:FJ188) -> 75.249912 | D31: =SAM!GI188 -> 2276.6063 | F31: =B31/D31 -> 0.66467667
A33: Total | B33: =SUM(B17:B31) -> 3365.341 | C33: =SUM(C17:C31) -> 1068.9734 | D33: =SUM(D17:D31) -> 5687.8181 | F33: =B33/D33 -> 0.59167522
A36: h) | B36: hhd-f1 | C36: hhd-f2 | D36: hhd-f3 | E36: hhd-f4 | F36: hhd-f5 | G36: hhd-n1 | H36: hhd-n2 | I36: hhd-n3 | J36: hhd-n4 | K36: hhd-n5 | L36: hhd-u1 | M36: hhd-u2 | N36: hhd-u3 | O36: hhd-u4 | P36: hhd-u5
A37: Food | B37: =B3 -> 157.14994 | C37: =C3 -> 232.4392 | D37: =D3 -> 316.8153 | E37: =E3 -> 435.41858 | F37: =F3 -> 401.96433 | G37: =G3 -> 2.554934 | H37: =H3 -> 3.4470785 | I37: =I3 -> 4.5315419 | ... P37: =P3 -> 514.05917
A38: Total | B38: =B4 -> 233.24389 | C38: =C4 -> 353.83939 | D38: =D4 -> 505.78977 | E38: =E4 -> 749.31103 | F38: =F4 -> 926.25083 | G38: =G4 -> 4.2538867 | H38: =H4 -> 5.4096952 | I38: =I4 -> 7.6596073 | ... P38: =P4 -> 1805.261
B39: =B37/B38 -> 0.67375803 | C39: =C37/C38 -> 0.65690595 | D39: =D37/D38 -> 0.62637743 | E39: =E37/E38 -> 0.58109192 | F39: =F37/F38 -> 0.4339692 | G39: =G37/G38 -> 0.60061168 | H39: =H37/H38 -> 0.63720383 | I39: =I37/I38 -> 0.59161543 | ... P39: =P37/P38 -> 0.28475615
B40: =>>> Rural hosueholds tend to spend most of their income on food.

Sheet i,j,k,l
A1: i) | B1: Export | G1: j) | H1: cmaiz | I1: csorg | J1: crice | K1: cwhea | L1: cpuls | M1: cgnut | N1: coils | O1: ccass | P1: cipot | Q1: cspot | R1: croot | S1: cleaf | T1: cvege | U1: csugr | V1: ctoba | W1: cbana | X1: cfrui | Y1: cteal | Z1: ccoff | AA1: cocrp | AB1: ccatt | AC1: cmilk | AD1: cpoul | AE1: ceggs | AF1: csmlr | AG1: coliv | AH1: cfore | AI1: caqua | AJ1: cfish | AK1: ccoal | AL1: cngas | AM1: comin | AN1: cmeat | AO1: cfsea | AP1: cdair | AQ1: cfveg | AR1: cfoil | AS1: cmmll | AT1: csmll | AU1: crmll | AV1: cwmll | AW1: csref | AX1: cpcof | AY1: cptea | AZ1: cfood | BA1: cfeed | BB1: cbeve | BC1: cptob | BD1: cyarn | BE1: ctext | BF1: cclth | BG1: cleat | BH1: cwood | BI1: cpapr | BJ1: cpetr | BK1: cfert | BL1: cchem | BM1: cnmet | BN1: cmetl | BO1: cmach | BP1: cequi | BQ1: cvehi | BR1: coman | BS1: celec | BT1: cwatr | BU1: ccons | BV1: ctrad | BW1: ctran | BX1: chotl | BY1: crest | BZ1: ccomm | CA1: cfsrv | CB1: creal | CC1: cbsrv | CD1: cpadm | CE1: ceduc | CF1: cheal | CG1: cosrv
A2: cmaiz | B2: 0.64447817 | C2: Agric export | D2: =SUM(B2:B30) -> 111.757 | E2: =D2/D3 -> 0.1167969 | G2: Import | H2: 17.458394 | I2: 1.6875419 | J2: 15.064778 | K2: 10.930979 | L2: 0.8874344 | M2: 5.4588551 | N2: 1.7529329 | O2: 11.519588 | P2: 3.3113072 | R2: 0.60596484 | S2: 1.9061701 | T2: 0.73460604 | V2: 0.14113567 | W2: 0.13027315 | X2: 5.2876102 | Y2: 0.29513886 | AA2: 1.9370176 | AB2: 0.13834595 | AD2: 0.73248501 | AE2: 0.44862945 | AG2: 0.54171833 | AH2: 0.48023568 | AJ2: 0.65396611 | AK2: 2.9498221 | AL2: 0.97514529 | AM2: 15.208631 | AN2: 0.73920891 | AO2: 20.030115 | AP2: 2.2482658 | AQ2: 2.1039899 | AR2: 49.134603 | AS2: 3.8039969 | AU2: 6.936263 | AV2: 0.76728817 | AW2: 37.991766 | AZ2: 28.699647 | BA2: 1.1255272 | BB2: 16.089158 | BC2: 2.5025113 | BD2: 0.5470089 | BE2: 36.072537 | BF2: 25.895527 | BG2: 19.092857 | BH2: 11.65688 | BI2: 27.504227 | BJ2: 18.327615 | BK2: 27.40694 | BL2: 248.65807 | BM2: 70.901856 | BN2: 114.14578 | BO2: 109.55497 | BP2: 230.60906 | BQ2: 137.36119 | BR2: 31.27879 | BU2: 71.071946 | BV2: 37.661764 | BW2: 293.48964 | BX2: 220.15193 | CA2: 18.564014 | CC2: 93.403871 | CD2: 81.253178
A3: csorg | C3: Total | D3: =SUM(B2:B79) -> 956.849
A4: crice | B4: 9.2892381 | G4: Food&Agric | H4: =SUM(H2:AJ2,AN2:AR2,AW2:BB2) -> 240.26739 | I4: =H4/H5 -> 0.10931079
A5: cwhea | G5: Total | H5: =SUM(H2:CG2) -> 2198.0207
A6: cpuls | B6: 1.3425019
A7: cgnut | B7: 0.08092836 | G7: k)
A8: coils | G8: Share | H8: =H2/$H5 -> 0.0079427796 | I8: =I2/$H5 -> 0.00076775526 | J8: =J2/$H5 -> 0.0068537928 | K8: =K2/$H5 -> 0.0049731012 | L8: =L2/$H5 -> 0.00040374252 | M8: =M2/$H5 -> 0.0024835322 | N8: =N2/$H5 -> 0.0007975052 | O8: =O2/$H5 -> 0.0052408913 | ... CG8: =CG2/$H5 -> 0
A9: ccass | H9: ==>>>Transport is the single most important import commodity with a 13% share.
A10: cipot | B10: 0.24066474
A11: cspot | G11: l) | H11: Total import of F&A | J11: =SUM(H2:AJ2,AN2:AR2,AW2:AZ2,BB2) -> 239.14186
A12: croot | H12: Total export of F&A | J12: =SUM(B2:B30,B34:B38,B43:B46,B48) -> 152.48227 | L12: =J12-J11 -> -86.65959
A13: cleaf | B13: 0.96106894 | H13: ==>>> Rwanda is net importer of food and food and agricultural commodity.
A14: cvege
A15: csugr
A16: ctoba
A17: cbana
A18: cfrui
A19: cteal | B19: 30.254457
A20: ccoff | B20: 61.240052
A21: cocrp | B21: 2.2563417
A22: ccatt | B22: 4.3862445
A23: cmilk
A24: cpoul
A25: ceggs | B25: 0.026747333
A26: csmlr
A27: coliv | B27: 1.0342763
A28: cfore
A29: caqua
A30: cfish
A31: ccoal
A32: cngas
A33: comin | B33: 114.22988
A34: cmeat | B34: 3.4732692
A35: cfsea | B35: 1.6151426
A36: cdair | B36: 1.9485309
A37: cfveg | B37: 1.5859726
A38: cfoil | B38: 17.897615
A39: cmmll | B39: 4.5192795
A40: csmll
A41: crmll | B41: 4.3467158
A42: cwmll | B42: 9.2357936
A43: csref | B43: 0.71525517
A44: cpcof
A45: cptea
A46: cfood | B46: 10.948446
A47: cfeed | B47: 0.015130345
A48: cbeve | B48: 2.5410397
A49: cptob | B49: 0.038592629
A50: cyarn | B50: 0.004942032
A51: ctext | B51: 1.3386063
A52: cclth | B52: 3.5188355
A53: cleat | B53: 5.231261
A54: cwood | B54: 0.23868583
A55: cpapr | B55: 2.6589706
A56: cpetr | B56: 29.383377
A57: cfert | B57: 0.11315132
... A65: celec | B65: 0.0066787532
A66: cwatr
A67: ccons | B67: 25.622506
A68: ctrad | B68: 4.1268174
A69: ctran | B69: 64.248594
A70: chotl | B70: 247.49713
A71: crest
A72: ccomm
A73: cfsrv | B73: 19.878108
A74: creal
A75: cbsrv | B75: 14.985045
A76: cpadm | B76: 207.34661
A77: ceduc
A78: cheal
A79: cosrv

Sheet m,n,o_1
A3: m) | C3: aagr | D3: aind | E3: asrv | F3: cagr | G3: cind | H3: csrv | I3: trc | J3: lab | K3: land | L3: cap | M3: ent | N3: hrur | O3: hurb | P3: gov | Q3: s-i | R3: row
B4: aagr | F4: =SUM(SAM!BW8:CY36) -> 1658.9367 | G4: =SUM(SAM!CZ8:EJ36) -> 0 | H4: =SUM(SAM!EK8:EV36) -> 0 | N4: =SUM(SAM!FL8:FU36) -> 466.46013 | O4: =SUM(SAM!FV8:FZ36) -> 33.339391 | T4: =SUM(C4:R4) -> 2158.7362
B5: aind | F5: =SUM(SAM!BW37:CY68) -> 0 | G5: =SUM(SAM!CZ37:EJ68) -> 3203.2425 | H5: =SUM(SAM!EK37:EV68) -> 0 | T5: =SUM(C5:R5) -> 3203.2425
B6: asrv | F6: =SUM(SAM!BW69:CY80) -> 0 | G6: =SUM(SAM!CZ69:EJ80) -> 0 | H6: =SUM(SAM!EK69:EV80) -> 6003.7535 | T6: =SUM(C6:R6) -> 6003.7535
B7: cagr | C7: =SUM(SAM!B81:AD109) -> 147.77625 | D7: =SUM(SAM!AE81:BJ109) -> 532.96276 | E7: =SUM(SAM!BK81:BV109) -> 59.889883 | N7: =SUM(SAM!FL81:FU109) -> 788.43478 | O7: =SUM(SAM!FV81:FZ109) -> 413.94353 | Q7: =SUM(SAM!GF81:GG109) -> 3.5102904 | R7: =SUM(SAM!GH81:GH109) -> 111.757 | T7: =SUM(C7:R7) -> 2058.2745
B8: cind | C8: =SUM(SAM!B110:AD146) -> 110.74379 | D8: =SUM(SAM!AE110:BJ146) -> 1077.7212 | E8: =SUM(SAM!BK110:BV146) -> 1012.2261 | N8: =SUM(SAM!FL110:FU146) -> 817.75983 | O8: =SUM(SAM!FV110:FZ146) -> 556.73449 | Q8: =SUM(SAM!GF110:GG146) -> 1712.1921 | R8: =SUM(SAM!GH110:GH146) -> 287.0097 | T8: =SUM(C8:R8) -> 5574.3872
B9: csrv | C9: =SUM(SAM!B147:AD158) -> 34.667194 | D9: =SUM(SAM!AE147:BJ158) -> 484.80689 | E9: =SUM(SAM!BK147:BV158) -> 1901.3212 | I9: =SUM(SAM!EW147:EW158) -> 1009.9683 | N9: =SUM(SAM!FL147:FU158) -> 798.87404 | O9: =SUM(SAM!FV147:FZ158) -> 1014.0014 | P9: =SUM(SAM!GA147:GA158) -> 1072.2008 | Q9: =SUM(SAM!GF147:GG159) -> 0 | R9: =SUM(SAM!GH147:GH158) -> 558.08231 | T9: =SUM(C9:R9) -> 6873.9221
B10: trc | F10: =SUM(SAM!BW159:CY159) -> 305.03852 | G10: =SUM(SAM!CZ159:EJ159) -> 704.92979 | H10: =SUM(SAM!EK159:EV159) -> 0 | T10: =SUM(C10:R10) -> 1009.9683
B11: lab | C11: =SUM(SAM!B160:AD167) -> 796.57557 | D11: =SUM(SAM!AE160:BJ167) -> 684.96944 | E11: =SUM(SAM!BK160:BV167) -> 1937.9676 | R11: =SUM(SAM!GH160:GH167) -> 4.0893737 | T11: =SUM(C11:R11) -> 3423.602
B12: land | C12: =SUM(SAM!B168:AD168) -> 750.44467 | R12: =SUM(SAM!GH168) -> 0 | T12: =SUM(C12:R12) -> 750.44467
B13: cap | C13: =SUM(SAM!B169:AD172) -> 318.52876 | D13: =SUM(SAM!AE169:BJ172) -> 422.7822 | E13: =SUM(SAM!BK169:BV172) -> 1092.3487 | R13: =SUM(SAM!GH169:GH172) -> 3.274695 | T13: =SUM(C13:R13) -> 1836.9344
B14: ent | L14: =SUM(SAM!FI173:FJ173) -> 1336.7372 | P14: =SAM!GA173 -> 144.65696 | R14: =SUM(SAM!GH173) -> 63.243465 | T14: =SUM(C14:R14) -> 1544.6376
B15: hrur | J15: =SUM(SAM!EX174:FE183) -> 1710.1659 | K15: =SUM(SAM!FF174:FF183) -> 677.93668 | L15: =SUM(SAM!FG174:FJ183) -> 282.03316 | M15: =SUM(SAM!FK174:FK183) -> 420.58043 | P15: =SUM(SAM!GA174:GA183) -> 51.13332 | R15: =SUM(SAM!GH174:GH183) -> 27.721671 | T15: =SUM(C15:R15) -> 3169.5712
B16: hurb | J16: =SUM(SAM!EX184:FE188) -> 1655.1751 | K16: =SUM(SAM!FF184:FF188) -> 72.50799 | L16: =SUM(SAM!FG184:FJ188) -> 36.4956 | M16: =SUM(SAM!FK184:FK188) -> 627.10303 | P16: =SUM(SAM!GA184:GA188) -> 69.078423 | R16: =SUM(SAM!GH184:GH188) -> 57.8868 | T16: =SUM(C16:R16) -> 2518.2469
B17: gov | F17: =SUM(SAM!BW190:CY193) -> 12.194138 | G17: =SUM(SAM!CZ190:EJ193) -> 294.82376 | H17: =SUM(SAM!EK191:EV193) -> 125.64418 | L17: =SUM(SAM!FG191:FJ191) -> 0.79905242 | M17: =SUM(SAM!FK189:FK193) -> 438.51299 | N17: =SUM(SAM!FL189:FU193) -> 102.95393 | O17: =SUM(SAM!FV189:FZ193) -> 276.26374 | P17: =SUM(SAM!GB189:GE189) -> 1005.3215 | R17: =SAM!GH189 -> 448.86051 | T17: =SUM(C17:R17) -> 2705.3738
B18: s-i | M18: =SAM!FK194 -> 53.357948 | N18: =SUM(SAM!FL194:FU195) -> 177.83095 | O18: =SUM(SAM!FV194:FZ195) -> 194.11597 | P18: =SUM(SAM!GA194:GA195) -> 331.84624 | Q18: =SUM(SAM!GF194:GF195) -> 36.89608 | R18: =SUM(SAM!GH194:GH195) -> 958.55127 | T18: =SUM(C18:R18) -> 1752.5985
B19: row | F19: =SUM(SAM!BW196:CY196) -> 82.105107 | G19: =SUM(SAM!CZ196:EJ196) -> 1371.3912 | H19: =SUM(SAM!EK196:EV196) -> 744.5244 | J19: =SUM(SAM!EX196:FE196) -> 58.260978 | L19: =SUM(SAM!FI196:FJ196) -> 180.86936 | M19: =SAM!FK196 -> 5.0832319 | N19: =SUM(SAM!FL196:FU196) -> 17.257534 | O19: =SUM(SAM!FV196:FZ196) -> 29.848438 | P19: =SAM!GA196 -> 31.136548 | T19: =SUM(C19:R19) -> 2520.4768
C22: =SUM(C4:C19) -> 2158.7362 | D22: =SUM(D4:D19) -> 3203.2425 | E22: =SUM(E4:E19) -> 6003.7535 | F22: =SUM(F4:F19) -> 2058.2745 | G22: =SUM(G4:G19) -> 5574.3872 | H22: =SUM(H4:H19) -> 6873.9221 | I22: =SUM(I4:I19) -> 1009.9683 | J22: =SUM(J4:J19) -> 3423.602 | ... R22: =SUM(R4:R19) -> 2520.4768
C24: {=TRANSPOSE(T4:T19)} -> 2158.7362 | D24: 3203.2425 | E24: 6003.7535 | F24: 2058.2745 | G24: 5574.3872 | H24: 6873.9221 | I24: 1009.9683 | J24: 3423.602 | K24: 750.44467 | L24: 1836.9344 | M24: 1544.6376 | N24: 3169.5712 | O24: 2518.2469 | P24: 2705.3738 | Q24: 1752.5985 | R24: 2520.4768
C26: =C22-C24 -> 0 | D26: =D22-D24 -> 0 | E26: =E22-E24 -> 0 | F26: =F22-F24 -> 0 | G26: =G22-G24 -> 0 | H26: =H22-H24 -> 0 | I26: =I22-I24 -> -1.0231815e-12 | J26: =J22-J24 -> 0 | ... R26: =R22-R24 -> 0
A28: n) | C28: aagr | D28: aind | E28: asrv | G28: Total
A29: Gross Q | C29: =C22 -> 2158.7362 | D29: =D22 -> 3203.2425 | E29: =E22 -> 6003.7535 | G29: =SUM(C29:E29) -> 11365.732
C30: =C29/$G29 -> 0.18993376 | D30: =D29/$G29 -> 0.28183336 | E30: =E29/$G29 -> 0.52823288
C32: aagr | D32: aind | E32: asrv | G32: Total
A33: GDP at FC | C33: =SUM(C11:C13) -> 1865.549 | D33: =SUM(D11:D13) -> 1107.7516 | E33: =SUM(E11:E13) -> 3030.3163 | G33: =SUM(C33:E33) -> 6003.617
C34: =C33/$G33 -> 0.31073751 | D34: =D33/$G33 -> 0.18451404 | E34: =E33/$G33 -> 0.50474845
C36: aagr | D36: aind | E36: asrv | G36: Total
A37: Lab in GDP at FC | C37: =C11 -> 796.57557 | D37: =D11 -> 684.96944 | E37: =E11 -> 1937.9676 | G37: =SUM(C37:E37) -> 3419.5126
A38: Share of Lab | C38: =C37/C33 -> 0.42699257 | D38: =D37/D33 -> 0.61834207 | E38: =E37/E33 -> 0.6395265
B39: ==>>Services have the largest share of labor in GDP
B43: Agric | C43: =R7 -> 111.757 | D43: =C43/C$46*100 -> 11.67969
B44: Ind | C44: =R8 -> 287.0097 | D44: =C44/C$46*100 -> 29.995297
B45: Serv | C45: =R9 -> 558.08231 | D45: =C45/C$46*100 -> 58.325013
B46: Total | C46: =SUM(C43:C45) -> 956.849

Sheet Index
A1: GDX index
A6: Type | B6: Name | C6: Location | D6: Row | E6: Column
D7: rdim | E7: cdim
A8: dset | B8: ac | C8: sets!a7 | D8: 1
A9: dset | B9: a | C9: sets!b7 | D9: 1
A10: dset | B10: aagr | C10: sets!c7 | D10: 1
A11: dset | B11: amin | C11: sets!d7 | D11: 1
A12: dset | B12: aind | C12: sets!e7 | D12: 1
A13: dset | B13: aser | C13: sets!f7 | D13: 1
A14: dset | B14: c | C14: sets!g7 | D14: 1
A15: dset | B15: cagr | C15: sets!h7 | D15: 1
A16: dset | B16: cmin | C16: sets!i7 | D16: 1
A17: dset | B17: cind | C17: sets!j7 | D17: 1
A18: dset | B18: cser | C18: sets!k7 | D18: 1
A19: dset | B19: f | C19: sets!l7 | D19: 1
... A33: dset | B33: ctm | C33: sets!z7 | D33: 1
A34: set | B34: mac | C34: sets!ab7 | D34: 2 | F34: values=nodata
A35: par | B35: sam | C35: sam!a7 | D35: 1 | E35: 1
A36: par | B36: leselas1 | C36: inc!a7 | D36: 1 | E36: 1
A37: par | B37: tradelas | C37: trd!a7 | D37: 1 | E37: 1
A38: par | B38: prodelastab | C38: trd!e7 | D38: 1 | E38: 1
A39: dset | B39: al | C39: emp!a7 | D39: 1
A40: set | B40: mala | C40: emp!c7 | D40: 2 | F40: values=nodata
A41: par | B41: qfinput | C41: emp!h6 | D41: 1 | E41: 1
A42: par | B42: wfinput | C42: emp!m6 | D42: 1 | E42: 1
A43: par | B43: facnest | C43: nst!a7 | D43: 1 | E43: 1

Sheet NST
A1: Nested Labor Market Structure
F2: [all factors (F) x aggregate factors (FAGG)]
F3: Only relate each aggregate factor to the factor beneath it in the nest.
F4: Number nested layers in order staring with 1
A5: Factor nesting
A6: Hierarchical relationship between factors at different layers of the nest
