Workbook

Sheet Index
A1: GDX index
A6: Type | B6: Name | C6: Location | D6: Row | E6: Column
D7: rdim | E7: cdim
A8: dset | B8: mac | C8: sets!a7 | D8: 1
A9: dset | B9: sac | C9: sets!b7 | D9: 1
A10: dset | B10: ac | C10: sets!c7 | D10: 1
A11: dset | B11: a | C11: sets!d7 | D11: 1
A12: dset | B12: c | C12: sets!e7 | D12: 1
A13: dset | B13: f | C13: sets!f7 | D13: 1
A14: dset | B14: t | C14: sets!g7 | D14: 1
A15: set | B15: mapac | C15: sets!d7 | D15: 2 | F15: values=nodata
A16: set | B16: mapmac | C16: sets!j7 | D16: 2 | F16: values=nodata
A17: par | B17: msam | C17: mac!a7 | D17: 1 | E17: 1
A18: par | B18: sut | C18: sut!b7 | D18: 1 | E18: 1
A19: par | B19: use | C19: use!b7 | D19: 1 | E19: 1
A20: par | B20: supply | C20: sup!b7 | D20: 1 | E20: 1

Sheet Sets
A1: Sets
A4: Macro | B4: SUT | C4: Micro | D4: Activities | E4: Commodities | F4: Factors | G4: Taxes | J4: Macro-Micro
A5: accounts | B5: accounts | C5: accounts | J5: MAPMAC
A6: MAC | B6: SAC | C6: AC | D6: A | E6: C | F6: F | G6: T | J6: MAC | K6: AC
A7: mact | B7: prd | C7: asorg | D7: asorg | E7: csorg | F7: flab | G7: atax | J7: mact | K7: asorg
A8: mcom | B8: trd_imp | C8: amaiz | D8: amaiz | E8: cmaiz | F8: flnd | G8: ctax | J8: mact | K8: amaiz
A9: mtrc | B9: tax_prd | C9: awhea | D9: awhea | E9: cwhea | F9: fcap | G9: dtax | J9: mact | K9: awhea
A10: mlab | B10: tax_imp | C10: arice | D10: arice | E10: crice | G10: etax | J10: mact | K10: arice
A11: mlnd | B11: tax_exp | C11: aocer | D11: aocer | E11: cocer | G11: ftax | J11: mact | K11: aocer
A12: mcap | B12: tax_exm | C12: aipot | D12: aipot | E12: cipot | G12: mtax | J12: mact | K12: aipot
A13: ment | B13: tax_sal | C13: aspot | D13: aspot | E13: cspot | G13: stax | J13: mact | K13: aspot
A14: mhhd | B14: tax_vat | C14: acass | D14: acass | E14: ccass | G14: vtax | J14: mact | K14: acass
A15: mgov | B15: tax_exd | C15: aroot | D15: aroot | E15: croot | G15: xtax | J15: mact | K15: aroot
A16: matx | B16: trc_rec | C16: abean | D16: abean | E16: cbean | J16: mact | K16: abean
A17: mctx | B17: tot_sup | C17: apeas | D17: apeas | E17: cpeas | J17: mact | K17: apeas
A18: mdtx | B18: tot_dem | C18: avege | D18: avege | E18: cvege | J18: mact | K18: avege
A19: metx | B19: int | C19: abanb | D19: abanb | E19: cbanb | J19: mact | K19: abanb
A20: mftx | B20: trc_pay | C20: abanc | D20: abanc | E20: cbanc | J20: mact | K20: abanc
A21: mmtx | B21: con_prv | C21: abans | D21: abans | E21: cbans | J21: mact | K21: abans
A22: mstx | B22: con_pub | C22: afrui | D22: afrui | E22: cfrui | J22: mact | K22: afrui
A23: mvtx | B23: inv_dem | C23: agnut | D23: agnut | E23: cgnut | J23: mact | K23: agnut
A24: mxtx | B24: inv_gov | C24: asoya | D24: asoya | E24: csoya | J24: mact | K24: asoya
A25: ms-i | B25: inv_stk | C25: aoils | D25: aoils | E25: coils | J25: mact | K25: aoils
A26: mg-i | B26: trd_exp | C26: acoff | D26: acoff | E26: ccoff | J26: mact | K26: acoff
A27: mstk | C27: ateal | D27: ateal | E27: cteal | J27: mact | K27: ateal
A28: mrow | C28: atoba | D28: atoba | E28: ctoba | J28: mact | K28: atoba
A29: mtot | C29: asugr | D29: asugr | E29: csugr | J29: mact | K29: asugr
C30: apyre | D30: apyre | E30: cpyre | J30: mact | K30: apyre
C31: aocrp | D31: aocrp | E31: cocrp | J31: mact | K31: aocrp
C32: acatt | D32: acatt | E32: ccatt | J32: mact | K32: acatt
C33: asmlr | D33: asmlr | E33: csmlr | J33: mact | K33: asmlr
C34: apoul | D34: apoul | E34: cpoul | J34: mact | K34: apoul
C35: aoliv | D35: aoliv | E35: coliv | J35: mact | K35: aoliv
C36: amilk | D36: amilk | E36: cmilk | J36: mact | K36: amilk
C37: aeggs | D37: aeggs | E37: ceggs | J37: mact | K37: aeggs
C38: ahony | D38: ahony | E38: chony | J38: mact | K38: ahony
C39: ahunt | D39: ahunt | E39: chunt | J39: mact | K39: ahunt
C40: afuel | D40: afuel | E40: cfuel | J40: mact | K40: afuel
C41: achar | D41: achar | E41: cchar | J41: mact | K41: achar
... C110: atrdc | D110: atrdc | E110: ctrdc | J110: mact | K110: atrdc
C111: csorg | J111: mcom | K111: csorg
C112: cmaiz | J112: mcom | K112: cmaiz
C113: cwhea | J113: mcom | K113: cwhea
C114: crice | J114: mcom | K114: crice
C115: cocer | J115: mcom | K115: cocer
C116: cipot | J116: mcom | K116: cipot
C117: cspot | J117: mcom | K117: cspot
C118: ccass | J118: mcom | K118: ccass
C119: croot | J119: mcom | K119: croot
C120: cbean | J120: mcom | K120: cbean
C121: cpeas | J121: mcom | K121: cpeas
C122: cvege | J122: mcom | K122: cvege
... C235: total | J235: mtot | K235: total

Sheet Notes
A1: =CONCATENATE(B5," ",C4," SAM") -> 2017 Rwanda SAM
A2: Use with 1construct.gms and 2balance.gms
A4: Country | B4: RWA | C4: Rwanda
A5: Year | B5: 2017
A6: Units | B6: Billions of Rwanda Francs
A9: Activities and commodities (N86) | E9: Other accounts
A10: ="a"&MID(B10,2,4) -> asorg | B10: csorg | C10: Sorghum (A111) | E10: trc | F10: Transaction costs
A11: ="a"&MID(B11,2,4) -> amaiz | B11: cmaiz | C11: Maize (A112) | E11: flab | F11: Labor
A12: ="a"&MID(B12,2,4) -> awhea | B12: cwhea | C12: Wheat (A113) | E12: flnd | F12: Land
A13: ="a"&MID(B13,2,4) -> arice | B13: crice | C13: Paddy & husked rice (A116) | E13: fcap | F13: Capital
A14: ="a"&MID(B14,2,4) -> aocer | B14: cocer | C14: Other cereals (A119) | E14: ent | F14: Enterprises
A15: ="a"&MID(B15,2,4) -> aipot | B15: cipot | C15: Irish potatoes (A121) | E15: hhd | F15: Households
A16: ="a"&MID(B16,2,4) -> aspot | B16: cspot | C16: Sweet potatoes (A122) | E16: gov | F16: Government
A17: ="a"&MID(B17,2,4) -> acass | B17: ccass | C17: Cassava (A123) | E17: atax | F17: Taxes - activity (production)
A18: ="a"&MID(B18,2,4) -> aroot | B18: croot | C18: Other roots & tubers (A129) | E18: ctax | F18: Taxes - customs duties (imports)
A19: ="a"&MID(B19,2,4) -> abean | B19: cbean | C19: Dried beans (A131) | E19: dtax | F19: Taxes - direct (corporate, private)
A20: ="a"&MID(B20,2,4) -> apeas | B20: cpeas | C20: Peas & other legumes (A132) | E20: etax | F20: Taxes - exports
A21: ="a"&MID(B21,2,4) -> avege | B21: cvege | C21: Other vegetables (A139) | E21: ftax | F21: Taxes - factors (royalities)
... A29: ="a"&MID(B29,2,4) -> acoff | B29: ccoff | C29: Coffee, not roasted, not decaffeinated (A210) | E29: total | F29: Total
A30: ="a"&MID(B30,2,4) -> ateal | B30: cteal | C30: Tea (unprocessed green leaf) (A220)
A31: ="a"&MID(B31,2,4) -> atoba | B31: ctoba | C31: Tobacco, raw (A291)
A32: ="a"&MID(B32,2,4) -> asugr | B32: csugr | C32: Sugar cane (A292)
A33: ="a"&MID(B33,2,4) -> apyre | B33: cpyre | C33: Pyrethrum (A293)
A34: ="a"&MID(B34,2,4) -> aocrp | B34: cocrp | C34: Agricultural products n.e.c. (A299)
A35: ="a"&MID(B35,2,4) -> acatt | B35: ccatt | C35: Bovine cattle, live (A311)
A36: ="a"&MID(B36,2,4) -> asmlr | B36: csmlr | C36: Sheep, goats, pigs,live (A312)
A37: ="a"&MID(B37,2,4) -> apoul | B37: cpoul | C37: Poultry, live (A313)
A38: ="a"&MID(B38,2,4) -> aoliv | B38: coliv | C38: Other live animals (A319)
A39: ="a"&MID(B39,2,4) -> amilk | B39: cmilk | C39: Raw milk (A321)
A40: ="a"&MID(B40,2,4) -> aeggs | B40: ceggs | C40: Eggs (A322)
A41: ="a"&MID(B41,2,4) -> ahony | B41: chony | C41: Natural honey (A323)
... A113: ="a"&MID(B113,2,4) -> atrdc | B113: ctrdc | C113: Travel debits & credits (V00)

Sheet MAC
A1: Macro SAM
A2: Final values exported to GAMS
B7: mact | C7: mcom | D7: mtrc | E7: mlab | F7: mlnd | G7: mcap | H7: ment | I7: mhhd | J7: mgov | K7: matx | L7: mctx | M7: mdtx | N7: metx | O7: mftx | P7: mmtx | Q7: mstx | R7: mvtx | S7: mxtx | T7: ms-i | U7: mg-i | V7: mstk | W7: mrow | X7: mtot
A8: mact | B8: =wMAC!C5 -> 0 | C8: =wMAC!D5 -> 11563.342 | D8: =wMAC!E5 -> 0 | E8: =wMAC!F5 -> 0 | F8: =wMAC!G5 -> 0 | G8: =wMAC!H5 -> 0 | H8: =wMAC!I5 -> 0 | I8: =wMAC!J5 -> 0 | ... X8: =wMAC!Y5 -> 11563.342
A9: mcom | B9: =wMAC!C6 -> 4606.6764 | C9: =wMAC!D6 -> 0 | D9: =wMAC!E6 -> 1053.7156 | E9: =wMAC!F6 -> 0 | F9: =wMAC!G6 -> 0 | G9: =wMAC!H6 -> 0 | H9: =wMAC!I6 -> 0 | I9: =wMAC!J6 -> 5676.1316 | ... X9: =wMAC!Y6 -> 15905.025
A10: mtrc | B10: =wMAC!C7 -> 0 | C10: =wMAC!D7 -> 1053.7156 | D10: =wMAC!E7 -> 0 | E10: =wMAC!F7 -> 0 | F10: =wMAC!G7 -> 0 | G10: =wMAC!H7 -> 0 | H10: =wMAC!I7 -> 0 | I10: =wMAC!J7 -> 0 | ... X10: =wMAC!Y7 -> 1053.7156
A11: mlab | B11: =wMAC!C8 -> 3889.2332 | C11: =wMAC!D8 -> 0 | D11: =wMAC!E8 -> 0 | E11: =wMAC!F8 -> 0 | F11: =wMAC!G8 -> 0 | G11: =wMAC!H8 -> 0 | H11: =wMAC!I8 -> 0 | I11: =wMAC!J8 -> 0 | ... X11: =wMAC!Y8 -> 3895.6427
A12: mlnd | B12: =wMAC!C9 -> 575.64093 | C12: =wMAC!D9 -> 0 | D12: =wMAC!E9 -> 0 | E12: =wMAC!F9 -> 0 | F12: =wMAC!G9 -> 0 | G12: =wMAC!H9 -> 0 | H12: =wMAC!I9 -> 0 | I12: =wMAC!J9 -> 0 | ... X12: =wMAC!Y9 -> 575.64093
A13: mcap | B13: =wMAC!C10 -> 2577.1259 | C13: =wMAC!D10 -> 0 | D13: =wMAC!E10 -> 0 | E13: =wMAC!F10 -> 0 | F13: =wMAC!G10 -> 0 | G13: =wMAC!H10 -> 0 | H13: =wMAC!I10 -> 0 | I13: =wMAC!J10 -> 0 | ... X13: =wMAC!Y10 -> 2588.7438
A14: ment | B14: =wMAC!C11 -> 0 | C14: =wMAC!D11 -> 0 | D14: =wMAC!E11 -> 0 | E14: =wMAC!F11 -> 0 | F14: =wMAC!G11 -> 0 | G14: =wMAC!H11 -> 2357.6183 | H14: =wMAC!I11 -> 0 | I14: =wMAC!J11 -> 0 | ... X14: =wMAC!Y11 -> 2512.2712
A15: mhhd | B15: =wMAC!C12 -> 0 | C15: =wMAC!D12 -> 0 | D15: =wMAC!E12 -> 0 | E15: =wMAC!F12 -> 3865.4278 | F15: =wMAC!G12 -> 575.64093 | G15: =wMAC!H12 -> 0 | H15: =wMAC!I12 -> 2032.1044 | I15: =wMAC!J12 -> 0 | ... X15: =wMAC!Y12 -> 6897.8259
A16: mgov | B16: =wMAC!C13 -> 0 | C16: =wMAC!D13 -> 0 | D16: =wMAC!E13 -> 0 | E16: =wMAC!F13 -> 0 | F16: =wMAC!G13 -> 0 | G16: =wMAC!H13 -> 0 | H16: =wMAC!I13 -> 69.912831 | I16: =wMAC!J13 -> 196.14963 | ... X16: =wMAC!Y13 -> 1745.3736
A17: matx | B17: =wMAC!C14 -> -85.334627 | C17: =wMAC!D14 -> 0 | D17: =wMAC!E14 -> 0 | E17: =wMAC!F14 -> 0 | F17: =wMAC!G14 -> 0 | G17: =wMAC!H14 -> 0 | H17: =wMAC!I14 -> 0 | I17: =wMAC!J14 -> 0 | ... X17: =wMAC!Y14 -> -85.334627
A18: mctx | B18: =wMAC!C15 -> 0 | C18: =wMAC!D15 -> 99.754257 | D18: =wMAC!E15 -> 0 | E18: =wMAC!F15 -> 0 | F18: =wMAC!G15 -> 0 | G18: =wMAC!H15 -> 0 | H18: =wMAC!I15 -> 0 | I18: =wMAC!J15 -> 0 | ... X18: =wMAC!Y15 -> 99.754257
A19: mdtx | B19: =wMAC!C16 -> 0 | C19: =wMAC!D16 -> 0 | D19: =wMAC!E16 -> 0 | E19: =wMAC!F16 -> 0 | F19: =wMAC!G16 -> 0 | G19: =wMAC!H16 -> 0 | H19: =wMAC!I16 -> 163.58467 | I19: =wMAC!J16 -> 315.56829 | ... X19: =wMAC!Y16 -> 479.15296
... A30: mtot | B30: =wMAC!C27 -> 11563.342 | C30: =wMAC!D27 -> 15906.328 | D30: =wMAC!E27 -> 1053.7156 | E30: =wMAC!F27 -> 3895.6427 | F30: =wMAC!G27 -> 575.64093 | G30: =wMAC!H27 -> 2588.7438 | H30: =wMAC!I27 -> 2512.2712 | I30: =wMAC!J27 -> 6897.8259 | ... X30: =wMAC!Y27 -> 0

Sheet SUT
A1: Supply-Use Table
A2: Final values exported to GAMS
C4: Gross | D4: Imports | E4: Tax on | F4: Taxes on products | L4: Trans. | M4: Totals | O4: Inter- | P4: Trans. | Q4: Consumption | S4: GCF | V4: Exports | Y4: Differences
C5: output | E5: producers | F5: Customs duties | G5: Exports | H5: Import excise duties | I5: Subsidies (products) | J5: VAT | K5: Excise & Others | L5: costs | M5: Supply | N5: Demand | O5: mediates | P5: costs | Q5: Private | R5: Public | S5: Private | T5: Public | U5: Stocks | Y5: sup-dem | Z5: % sup
B6: Totals | C6: =SUM(C8:C111) -> 11648.676 | D6: =SUM(D8:D111) -> 2550.3991 | E6: =SUM(E8:E111) -> -85.334627 | F6: =SUM(F8:F111) -> 99.754257 | G6: =SUM(G8:G111) -> 0 | H6: =SUM(H8:H111) -> 64.958051 | I6: =SUM(I8:I111) -> -30.138079 | K6: =SUM(K8:K111) -> 206.88431 | L6: =SUM(L8:L111) -> 1053.7156 | M6: =SUM(M8:M111) -> 15906.328 | N6: =SUM(N8:N111) -> 15905.025 | O6: =SUM(O8:O111) -> 4606.6764 | P6: =SUM(P8:P111) -> 1053.7156 | Q6: =SUM(Q8:Q111) -> 5676.1316 | R6: =SUM(R8:R111) -> 1155 | ... V6: =SUM(V8:V111) -> 1579.5017 | Y6: =M6-N6 -> 1.3031426 | Z6: =IF(M6<>0,Y6/M6*100,0) -> 0.0081926044 | AC6: Totals | AE6: Differences
C7: prd | D7: trd_imp | E7: tax_prd | F7: tax_imp | G7: tax_exp | H7: tax_exm | I7: tax_sal | J7: tax_vat | K7: tax_exd | L7: trc_rec | M7: tot_sup | N7: tot_dem | O7: int | P7: trc_pay | Q7: con_prv | R7: con_pub | S7: inv_dem | T7: inv_gov | U7: inv_stk | V7: trd_exp | AC7: Supply | AD7: Demand | AE7: sup-dem | AF7: % sup
A8: Sorghum (A111) | B8: csorg | C8: {=TRANSPOSE(SUP!C4:DB4)} -> 45.186128 | D8: =wTRD!I8 -> 1.0534168 | E8: =wTAX!G8 -> 0 | F8: =wTAX!K8 -> 0 | G8: =wTAX!O8 -> 0 | H8: =wTAX!S8 -> 0 | I8: =wTAX!W8 -> 0 | J8: =wTAX!AA8 -> 0.014953109 | K8: =wTAX!AE8 -> 0 | L8: =wTRC!G8 -> 0.52381858 | M8: =SUM(C8:L8) -> 46.778316 | N8: =SUM(O8:V8) -> 46.876135 | O8: =SUM(USE!C8:DB8) -> 39.453683 | P8: =wTRC!K8 -> 0 | Q8: =wABS!G7 -> 5.595082 | R8: =wABS!K7 -> 0 | S8: =wABS!O7 -> 0 | T8: =wABS!S7 -> 0 | U8: =wABS!W7 -> 0.2512223 | V8: =wTRD!O8 -> 1.5761482 | Y8: =M8-N8 -> -0.097819245 | Z8: =IF(M8<>0,Y8/M8*100,0) -> -0.20911237 | AB8: Agriculture | AC8: =SUM(AC9:AC20) -> 2380.4511 | AD8: =SUM(AD9:AD20) -> 2385.218 | AE8: =AC8-AD8 -> -4.7669471 | AF8: =IF(AC8<>0,AE8/AC8*100,0) -> -0.20025394
A9: Maize (A112) | B9: cmaiz | C9: 98.112675 | D9: =wTRD!I9 -> 25.349828 | E9: =wTAX!G9 -> 0 | F9: =wTAX!K9 -> 0.53905915 | G9: =wTAX!O9 -> 0 | H9: =wTAX!S9 -> 0 | I9: =wTAX!W9 -> 0 | J9: =wTAX!AA9 -> 0.032696955 | K9: =wTAX!AE9 -> 0.36276888 | L9: =wTRC!G9 -> 1.1543252 | M9: =SUM(C9:L9) -> 125.55135 | N9: =SUM(O9:V9) -> 129.66341 | O9: =SUM(USE!C9:DB9) -> 73.138612 | P9: =wTRC!K9 -> 0 | Q9: =wABS!G8 -> 41.735846 | R9: =wABS!K8 -> 0 | S9: =wABS!O8 -> 0 | T9: =wABS!S8 -> 0 | U9: =wABS!W8 -> 5.3465792 | V9: =wTRD!O9 -> 9.4423747 | Y9: =M9-N9 -> -4.1120586 | Z9: =IF(M9<>0,Y9/M9*100,0) -> -3.2752006 | AB9: Cereals | AC9: =SUM(M8:M12) -> 324.64064 | AD9: =SUM(N8:N12) -> 326.86549 | AE9: =AC9-AD9 -> -2.2248515 | AF9: =IF(AC9<>0,AE9/AC9*100,0) -> -0.68532746
A10: Wheat (A113) | B10: cwhea | C10: 3.2540333 | D10: =wTRD!I10 -> 54.390816 | E10: =wTAX!G10 -> 0 | F10: =wTAX!K10 -> 0 | G10: =wTAX!O10 -> 0 | H10: =wTAX!S10 -> 0 | I10: =wTAX!W10 -> 0 | J10: =wTAX!AA10 -> 0.016125022 | K10: =wTAX!AE10 -> 0.78637771 | L10: =wTRC!G10 -> 0.71507849 | M10: =SUM(C10:L10) -> 59.162431 | N10: =SUM(O10:V10) -> 62.323153 | O10: =SUM(USE!C10:DB10) -> 56.529221 | P10: =wTRC!K10 -> 0 | Q10: =wABS!G9 -> 0.72771824 | R10: =wABS!K9 -> 0 | S10: =wABS!O9 -> 0 | T10: =wABS!S9 -> 0 | U10: =wABS!W9 -> 4.786616 | V10: =wTRD!O10 -> 0.27959753 | Y10: =M10-N10 -> -3.1607221 | Z10: =IF(M10<>0,Y10/M10*100,0) -> -5.342448 | AB10: Roots | AC10: =SUM(M13:M16) -> 508.3511 | AD10: =SUM(N13:N16) -> 505.42778 | AE10: =AC10-AD10 -> 2.9233157 | AF10: =IF(AC10<>0,AE10/AC10*100,0) -> 0.5750584
A11: Paddy & husked rice (A116) | B11: crice | C11: 59.900399 | D11: =wTRD!I11 -> 17.6277 | E11: =wTAX!G11 -> 0 | F11: =wTAX!K11 -> 6.2061593 | G11: =wTAX!O11 -> 0 | H11: =wTAX!S11 -> 0 | I11: =wTAX!W11 -> 0 | J11: =wTAX!AA11 -> 2.6701794 | K11: =wTAX!AE11 -> 0.24129892 | L11: =wTRC!G11 -> 0.82326616 | M11: =SUM(C11:L11) -> 87.469003 | N11: =SUM(O11:V11) -> 83.838418 | O11: =SUM(USE!C11:DB11) -> 7.5612554 | P11: =wTRC!K11 -> 0 | Q11: =wABS!G10 -> 73.451634 | R11: =wABS!K10 -> 0 | S11: =wABS!O10 -> 0 | T11: =wABS!S10 -> 0 | U11: =wABS!W10 -> -1.9129959 | V11: =wTRD!O11 -> 4.7385243 | Y11: =M11-N11 -> 3.6305847 | Z11: =IF(M11<>0,Y11/M11*100,0) -> 4.15071 | AB11: Vegetables | AC11: =SUM(M17:M19) -> 420.76035 | AD11: =SUM(N17:N19) -> 417.95016 | AE11: =AC11-AD11 -> 2.8101816 | AF11: =IF(AC11<>0,AE11/AC11*100,0) -> 0.66788176
A12: Other cereals (A119) | B12: cocer | C12: 0.29091626 | D12: =wTRD!I12 -> 5.2367139 | E12: =wTAX!G12 -> 0 | F12: =wTAX!K12 -> 0.030887925 | G12: =wTAX!O12 -> 0 | H12: =wTAX!S12 -> 0 | I12: =wTAX!W12 -> 0 | J12: =wTAX!AA12 -> 0 | K12: =wTAX!AE12 -> 0.074708701 | L12: =wTRC!G12 -> 0.046313731 | M12: =SUM(C12:L12) -> 5.6795405 | N12: =SUM(O12:V12) -> 4.1643767 | O12: =SUM(USE!C12:DB12) -> 3.83321 | P12: =wTRC!K12 -> 0 | Q12: =wABS!G11 -> 0.10782244 | R12: =wABS!K11 -> 0 | S12: =wABS!O11 -> 0 | T12: =wABS!S11 -> 0 | U12: =wABS!W11 -> 0.0096081101 | V12: =wTRD!O12 -> 0.21373611 | Y12: =M12-N12 -> 1.5151638 | Z12: =IF(M12<>0,Y12/M12*100,0) -> 26.677577 | AB12: Bananas and fruit | AC12: =SUM(M20:M23) -> 303.02439 | AD12: =SUM(N20:N23) -> 304.48991 | AE12: =AC12-AD12 -> -1.4655183 | AF12: =IF(AC12<>0,AE12/AC12*100,0) -> -0.48363049
A13: Irish potatoes (A121) | B13: cipot | C13: 170.10332 | D13: =wTRD!I13 -> 4.7535362 | E13: =wTAX!G13 -> 0 | F13: =wTAX!K13 -> 0.011621994 | G13: =wTAX!O13 -> 0 | H13: =wTAX!S13 -> 0 | I13: =wTAX!W13 -> 0 | J13: =wTAX!AA13 -> 0.26287637 | K13: =wTAX!AE13 -> 0.053293658 | L13: =wTRC!G13 -> 9.5056657 | M13: =SUM(C13:L13) -> 184.69031 | N13: =SUM(O13:V13) -> 185.0201 | O13: =SUM(USE!C13:DB13) -> 2.2121453 | P13: =wTRC!K13 -> 0 | Q13: =wABS!G12 -> 177.67462 | R13: =wABS!K12 -> 0 | S13: =wABS!O12 -> 0 | T13: =wABS!S12 -> 0 | U13: =wABS!W12 -> -0.05596473 | V13: =wTRD!O13 -> 5.1893028 | Y13: =M13-N13 -> -0.32978913 | Z13: =IF(M13<>0,Y13/M13*100,0) -> -0.1785633 | AB13: Oil seeds n.e.c. and oleaginous fruit | AC13: =SUM(M24:M26) -> 25.246313 | AD13: =SUM(N24:N26) -> 25.072272 | AE13: =AC13-AD13 -> 0.17404028 | AF13: =IF(AC13<>0,AE13/AC13*100,0) -> 0.68936909
A14: Sweet potatoes (A122) | B14: cspot | C14: 151.42836 | D14: =wTRD!I14 -> 0.52079596 | E14: =wTAX!G14 -> 0 | F14: =wTAX!K14 -> 4.6517458e-05 | G14: =wTAX!O14 -> 0 | H14: =wTAX!S14 -> 0 | I14: =wTAX!W14 -> 0 | J14: =wTAX!AA14 -> 0.12884959 | K14: =wTAX!AE14 -> 0.0019898308 | L14: =wTRC!G14 -> 4.6469112 | M14: =SUM(C14:L14) -> 156.72695 | N14: =SUM(O14:V14) -> 156.73066 | O14: =SUM(USE!C14:DB14) -> 2.0009957 | P14: =wTRC!K14 -> 0 | Q14: =wABS!G13 -> 154.62993 | R14: =wABS!K13 -> 0 | S14: =wABS!O13 -> 0 | T14: =wABS!S13 -> 0 | U14: =wABS!W13 -> 0.0188386 | V14: =wTRD!O14 -> 0.080892994 | Y14: =M14-N14 -> -0.0037099101 | Z14: =IF(M14<>0,Y14/M14*100,0) -> -0.0023671169 | AB14: Coffee | AC14: =M27 -> 78.816824 | AD14: =N27 -> 87.891102 | AE14: =AC14-AD14 -> -9.074278 | AF14: =IF(AC14<>0,AE14/AC14*100,0) -> -11.513123
A15: Cassava (A123) | B15: ccass | C15: 125.44618 | D15: =wTRD!I15 -> 10.525037 | E15: =wTAX!G15 -> 0 | F15: =wTAX!K15 -> 0.00072855952 | G15: =wTAX!O15 -> 0 | H15: =wTAX!S15 -> 0 | I15: =wTAX!W15 -> 0 | J15: =wTAX!AA15 -> 0 | K15: =wTAX!AE15 -> 0.16768466 | L15: =wTRC!G15 -> 8.8321559 | M15: =SUM(C15:L15) -> 144.97179 | N15: =SUM(O15:V15) -> 141.1219 | O15: =SUM(USE!C15:DB15) -> 77.249343 | P15: =wTRC!K15 -> 0 | Q15: =wABS!G14 -> 63.780195 | R15: =wABS!K14 -> 0 | S15: =wABS!O14 -> 0 | T15: =wABS!S14 -> 0 | U15: =wABS!W14 -> -0.0024814996 | V15: =wTRD!O15 -> 0.094846383 | Y15: =M15-N15 -> 3.8498848 | Z15: =IF(M15<>0,Y15/M15*100,0) -> 2.6556097 | AB15: Tea (unprocessed green leaf) | AC15: =M28 -> 25.057749 | AD15: =N28 -> 25.805573 | AE15: =AC15-AD15 -> -0.74782384 | AF15: =IF(AC15<>0,AE15/AC15*100,0) -> -2.9844015
A16: Other roots & tubers (A129) | B16: croot | C16: 21.322825 | D16: =wTRD!I16 -> 0.051590165 | E16: =wTAX!G16 -> 0 | F16: =wTAX!K16 -> 0.00033623186 | G16: =wTAX!O16 -> 0 | H16: =wTAX!S16 -> 0 | I16: =wTAX!W16 -> 0 | J16: =wTAX!AA16 -> 0.015457469 | K16: =wTAX!AE16 -> 2.9327548e-05 | L16: =wTRC!G16 -> 0.57181159 | M16: =SUM(C16:L16) -> 21.96205 | N16: =SUM(O16:V16) -> 22.55512 | O16: =SUM(USE!C16:DB16) -> 0.67724229 | P16: =wTRC!K16 -> 0 | Q16: =wABS!G15 -> 21.836842 | R16: =wABS!K15 -> 0 | S16: =wABS!O15 -> 0 | T16: =wABS!S15 -> 0 | U16: =wABS!W15 -> 0 | V16: =wTRD!O16 -> 0.041035951 | Y16: =M16-N16 -> -0.59307011 | Z16: =IF(M16<>0,Y16/M16*100,0) -> -2.7004315 | AB16: Other agricultural products | AC16: =SUM(M29:M32) -> 51.205297 | AD16: =SUM(N29:N32) -> 53.016986 | AE16: =AC16-AD16 -> -1.8116881 | AF16: =IF(AC16<>0,AE16/AC16*100,0) -> -3.5380873
A17: Dried beans (A131) | B17: cbean | C17: 225.71312 | D17: =wTRD!I17 -> 1.6038528 | E17: =wTAX!G17 -> 0 | F17: =wTAX!K17 -> 0.0028139099 | G17: =wTAX!O17 -> 0 | H17: =wTAX!S17 -> 0 | I17: =wTAX!W17 -> 0 | J17: =wTAX!AA17 -> 0.25476555 | K17: =wTAX!AE17 -> 0.018300945 | L17: =wTRC!G17 -> 9.6211128 | M17: =SUM(C17:L17) -> 237.21397 | N17: =SUM(O17:V17) -> 237.70874 | O17: =SUM(USE!C17:DB17) -> 6.6503043 | P17: =wTRC!K17 -> 0 | Q17: =wABS!G16 -> 219.39461 | R17: =wABS!K16 -> 0 | S17: =wABS!O16 -> 0 | T17: =wABS!S16 -> 0 | U17: =wABS!W16 -> -0.89508085 | V17: =wTRD!O17 -> 12.558905 | Y17: =M17-N17 -> -0.49476855 | Z17: =IF(M17<>0,Y17/M17*100,0) -> -0.2085748 | AB17: Livestock | AC17: =SUM(M33:M36) -> 150.15703 | AD17: =SUM(N33:N36) -> 144.69632 | AE17: =AC17-AD17 -> 5.4607034 | AF17: =IF(AC17<>0,AE17/AC17*100,0) -> 3.6366619
A18: Peas & other legumes (A132) | B18: cpeas | C18: 22.070413 | D18: =wTRD!I18 -> 0.067616629 | E18: =wTAX!G18 -> 0 | F18: =wTAX!K18 -> 0.0035085651 | G18: =wTAX!O18 -> 0 | H18: =wTAX!S18 -> 0 | I18: =wTAX!W18 -> 0 | J18: =wTAX!AA18 -> 0 | K18: =wTAX!AE18 -> 0.00047776255 | L18: =wTRC!G18 -> 1.1435333 | M18: =SUM(C18:L18) -> 23.285549 | N18: =SUM(O18:V18) -> 20.114949 | O18: =SUM(USE!C18:DB18) -> 1.8403145 | P18: =wTRC!K18 -> 0 | Q18: =wABS!G17 -> 17.899128 | R18: =wABS!K17 -> 0 | S18: =wABS!O17 -> 0 | T18: =wABS!S17 -> 0 | U18: =wABS!W17 -> -0.0014514351 | V18: =wTRD!O18 -> 0.37695823 | Y18: =M18-N18 -> 3.1705997 | Z18: =IF(M18<>0,Y18/M18*100,0) -> 13.616169 | AB18: Livestock and hunting products | AC18: =SUM(M37:M40) -> 56.318745 | AD18: =SUM(N37:N40) -> 60.872287 | AE18: =AC18-AD18 -> -4.553542 | AF18: =IF(AC18<>0,AE18/AC18*100,0) -> -8.0853045
A19: Other vegetables (A139) | B19: cvege | C19: 149.13716 | D19: =wTRD!I19 -> 2.0750742 | E19: =wTAX!G19 -> 0 | F19: =wTAX!K19 -> 0.0016149336 | G19: =wTAX!O19 -> 0 | H19: =wTAX!S19 -> 0 | I19: =wTAX!W19 -> 0 | J19: =wTAX!AA19 -> 0.23453505 | K19: =wTAX!AE19 -> 0.026407349 | L19: =wTRC!G19 -> 8.7860369 | M19: =SUM(C19:L19) -> 160.26083 | N19: =SUM(O19:V19) -> 160.12648 | O19: =SUM(USE!C19:DB19) -> 5.1103751 | P19: =wTRC!K19 -> 0 | Q19: =wABS!G18 -> 151.97639 | R19: =wABS!K18 -> 0 | S19: =wABS!O18 -> 0 | T19: =wABS!S18 -> 0 | U19: =wABS!W18 -> -0.084160701 | V19: =wTRD!O19 -> 3.1238748 | Y19: =M19-N19 -> 0.13435042 | Z19: =IF(M19<>0,Y19/M19*100,0) -> 0.083832352 | AB19: Forestry products | AC19: =SUM(M41:M43) -> 404.20062 | AD19: =SUM(N41:N43) -> 401.15729 | AE19: =AC19-AD19 -> 3.0433346 | AF19: =IF(AC19<>0,AE19/AC19*100,0) -> 0.75292675
A20: Bananas for beer (A141) | B20: cbanb | C20: 81.996625 | D20: =wTRD!I20 -> 0 | E20: =wTAX!G20 -> 0 | F20: =wTAX!K20 -> 0 | G20: =wTAX!O20 -> 0 | H20: =wTAX!S20 -> 0 | I20: =wTAX!W20 -> 0 | J20: =wTAX!AA20 -> 0.02680285 | K20: =wTAX!AE20 -> 0 | L20: =wTRC!G20 -> 1.0858245 | M20: =SUM(C20:L20) -> 83.109253 | N20: =SUM(O20:V20) -> 79.140909 | O20: =SUM(USE!C20:DB20) -> 64.968406 | P20: =wTRC!K20 -> 0 | Q20: =wABS!G19 -> 6.2864969 | R20: =wABS!K19 -> 0 | S20: =wABS!O19 -> 0 | T20: =wABS!S19 -> 0 | U20: =wABS!W19 -> 7.8860059 | V20: =wTRD!O20 -> 0 | Y20: =M20-N20 -> 3.968344 | Z20: =IF(M20<>0,Y20/M20*100,0) -> 4.7748523 | AB20: Fishery products | AC20: =SUM(M44) -> 32.672003 | AD20: =SUM(N44) -> 31.972824 | AE20: =AC20-AD20 -> 0.69917902 | AF20: =IF(AC20<>0,AE20/AC20*100,0) -> 2.1399944
A21: Bananas for cooking (A142) | B21: cbanc | C21: 149.29912 | D21: =wTRD!I21 -> 0 | E21: =wTAX!G21 -> 0 | F21: =wTAX!K21 -> 0 | G21: =wTAX!O21 -> 0 | H21: =wTAX!S21 -> 0 | I21: =wTAX!W21 -> 0 | J21: =wTAX!AA21 -> 0 | K21: =wTAX!AE21 -> 0 | L21: =wTRC!G21 -> 7.8310607 | M21: =SUM(C21:L21) -> 157.13018 | N21: =SUM(O21:V21) -> 157.5686 | O21: =SUM(USE!C21:DB21) -> 4.3395681 | P21: =wTRC!K21 -> 0 | Q21: =wABS!G20 -> 153.22903 | R21: =wABS!K20 -> 0 | S21: =wABS!O20 -> 0 | T21: =wABS!S20 -> 0 | U21: =wABS!W20 -> 0 | V21: =wTRD!O21 -> 0 | Y21: =M21-N21 -> -0.43842263 | Z21: =IF(M21<>0,Y21/M21*100,0) -> -0.27901873
A22: Bananas (sweet) (A143) | B22: cbans | C22: 27.075522 | D22: =wTRD!I22 -> 0.41475799 | E22: =wTAX!G22 -> 0 | F22: =wTAX!K22 -> 0 | G22: =wTAX!O22 -> 0 | H22: =wTAX!S22 -> 0 | I22: =wTAX!W22 -> 0 | J22: =wTAX!AA22 -> 0.053319703 | K22: =wTAX!AE22 -> 0 | L22: =wTRC!G22 -> 1.8044565 | M22: =SUM(C22:L22) -> 29.348056 | N22: =SUM(O22:V22) -> 31.602882 | O22: =SUM(USE!C22:DB22) -> 0.52964074 | P22: =wTRC!K22 -> 0 | Q22: =wABS!G21 -> 30.448103 | R22: =wABS!K21 -> 0 | S22: =wABS!O21 -> 0 | T22: =wABS!S21 -> 0 | U22: =wABS!W21 -> -0.0037393247 | V22: =wTRD!O22 -> 0.62887799 | Y22: =M22-N22 -> -2.2548259 | Z22: =IF(M22<>0,Y22/M22*100,0) -> -7.6830504
A23: Other fruit & nuts (A149) | B23: cfrui | C23: 25.31831 | D23: =wTRD!I23 -> 5.9242395 | E23: =wTAX!G23 -> 0 | F23: =wTAX!K23 -> 0.29684318 | G23: =wTAX!O23 -> 0 | H23: =wTAX!S23 -> 0 | I23: =wTAX!W23 -> 0 | J23: =wTAX!AA23 -> 0.051246513 | K23: =wTAX!AE23 -> 0.093720851 | L23: =wTRC!G23 -> 1.7525436 | M23: =SUM(C23:L23) -> 33.436904 | N23: =SUM(O23:V23) -> 36.177517 | O23: =SUM(USE!C23:DB23) -> 0.94472221 | P23: =wTRC!K23 -> 0 | Q23: =wABS!G22 -> 33.809848 | R23: =wABS!K22 -> 0 | S23: =wABS!O22 -> 0 | T23: =wABS!S22 -> 0 | U23: =wABS!W22 -> 0.030378481 | V23: =wTRD!O23 -> 1.3925687 | Y23: =M23-N23 -> -2.7406138 | Z23: =IF(M23<>0,Y23/M23*100,0) -> -8.1963744
A24: Ground nuts (A151) | B24: cgnut | C24: 11.29778 | D24: =wTRD!I24 -> 2.6663743 | E24: =wTAX!G24 -> 0 | F24: =wTAX!K24 -> 0.022272394 | G24: =wTAX!O24 -> 0 | H24: =wTAX!S24 -> 0 | I24: =wTAX!W24 -> 0 | J24: =wTAX!AA24 -> 0.029128714 | K24: =wTAX!AE24 -> 0.042914822 | L24: =wTRC!G24 -> 0.99482031 | M24: =SUM(C24:L24) -> 15.05329 | N24: =SUM(O24:V24) -> 15.06378 | O24: =SUM(USE!C24:DB24) -> 13.816022 | P24: =wTRC!K24 -> 0 | Q24: =wABS!G23 -> 1.3784852 | R24: =wABS!K23 -> 0 | S24: =wABS!O23 -> 0 | T24: =wABS!S23 -> 0 | U24: =wABS!W23 -> -0.61086273 | V24: =wTRD!O24 -> 0.4801356 | Y24: =M24-N24 -> -0.010489798 | Z24: =IF(M24<>0,Y24/M24*100,0) -> -0.06968442
A25: Soya (A152) | B25: csoya | C25: 3.7090505 | D25: =wTRD!I25 -> 0.02941353 | E25: =wTAX!G25 -> 0 | F25: =wTAX!K25 -> 0 | G25: =wTAX!O25 -> 0 | H25: =wTAX!S25 -> 0 | I25: =wTAX!W25 -> 0 | J25: =wTAX!AA25 -> 0 | K25: =wTAX!AE25 -> 0 | L25: =wTRC!G25 -> 0.27705296 | M25: =SUM(C25:L25) -> 4.015517 | N25: =SUM(O25:V25) -> 4.1401632 | O25: =SUM(USE!C25:DB25) -> 2.9595119 | P25: =wTRC!K25 -> 0 | Q25: =wABS!G24 -> 0.9170293 | R25: =wABS!K24 -> 0 | S25: =wABS!O24 -> 0 | T25: =wABS!S24 -> 0 | U25: =wABS!W24 -> 0.17476968 | V25: =wTRD!O25 -> 0.088852277 | Y25: =M25-N25 -> -0.12464619 | Z25: =IF(M25<>0,Y25/M25*100,0) -> -3.104113
A26: Other oil seeds (A159) | B26: coils | C26: 0 | D26: =wTRD!I26 -> 5.9846523 | E26: =wTAX!G26 -> 0 | F26: =wTAX!K26 -> 0.0045607132 | G26: =wTAX!O26 -> 0 | H26: =wTAX!S26 -> 0 | I26: =wTAX!W26 -> 0 | J26: =wTAX!AA26 -> 0.02688628 | K26: =wTAX!AE26 -> 0.097818641 | L26: =wTRC!G26 -> 0.063587358 | M26: =SUM(C26:L26) -> 6.1775053 | N26: =SUM(O26:V26) -> 5.8683291 | O26: =SUM(USE!C26:DB26) -> 5.7220628 | P26: =wTRC!K26 -> 0 | Q26: =wABS!G25 -> 0 | R26: =wABS!K25 -> 0 | S26: =wABS!O25 -> 0 | T26: =wABS!S25 -> 0 | U26: =wABS!W25 -> 0.047947885 | V26: =wTRD!O26 -> 0.098318397 | Y26: =M26-N26 -> 0.30917626 | Z26: =IF(M26<>0,Y26/M26*100,0) -> 5.0048725
A27: Coffee, not roasted, not decaffeinated (A210) | B27: ccoff | C27: 77.23931 | D27: =wTRD!I27 -> 1.422821 | E27: =wTAX!G27 -> 0 | F27: =wTAX!K27 -> 0.0010978173 | G27: =wTAX!O27 -> 0 | H27: =wTAX!S27 -> 0 | I27: =wTAX!W27 -> 0 | J27: =wTAX!AA27 -> 0.0036042173 | K27: =wTAX!AE27 -> 0.00032881548 | L27: =wTRC!G27 -> 0.149662 | M27: =SUM(C27:L27) -> 78.816824 | N27: =SUM(O27:V27) -> 87.891102 | O27: =SUM(USE!C27:DB27) -> 7.4416417 | P27: =wTRC!K27 -> 0 | Q27: =wABS!G26 -> 0 | R27: =wABS!K26 -> 0 | S27: =wABS!O26 -> 0 | T27: =wABS!S26 -> 0 | U27: =wABS!W26 -> 26.939791 | V27: =wTRD!O27 -> 53.509669 | Y27: =M27-N27 -> -9.074278 | Z27: =IF(M27<>0,Y27/M27*100,0) -> -11.513123
A28: Tea (unprocessed green leaf) (A220) | B28: cteal | C28: 24.516516 | D28: =wTRD!I28 -> 0.20298914 | E28: =wTAX!G28 -> 0 | F28: =wTAX!K28 -> 0.00059266885 | G28: =wTAX!O28 -> 0 | H28: =wTAX!S28 -> 0 | I28: =wTAX!W28 -> 0 | J28: =wTAX!AA28 -> 0.037695047 | K28: =wTAX!AE28 -> 0.0033214239 | L28: =wTRC!G28 -> 0.29663475 | M28: =SUM(C28:L28) -> 25.057749 | N28: =SUM(O28:V28) -> 25.805573 | O28: =SUM(USE!C28:DB28) -> 23.399379 | P28: =wTRC!K28 -> 0 | Q28: =wABS!G27 -> 3.9758412e-14 | R28: =wABS!K27 -> 0 | S28: =wABS!O27 -> 0 | T28: =wABS!S27 -> 0 | U28: =wABS!W27 -> 2.4061937 | V28: =wTRD!O28 -> 0 | Y28: =M28-N28 -> -0.74782384 | Z28: =IF(M28<>0,Y28/M28*100,0) -> -2.9844015
A29: Tobacco, raw (A291) | B29: ctoba | C29: 4.1958653 | D29: =wTRD!I29 -> 0.41730792 | E29: =wTAX!G29 -> 0 | F29: =wTAX!K29 -> 0.00081479944 | G29: =wTAX!O29 -> 0 | H29: =wTAX!S29 -> 0 | I29: =wTAX!W29 -> 0 | J29: =wTAX!AA29 -> 0.001359976 | K29: =wTAX!AE29 -> 0.0026557946 | L29: =wTRC!G29 -> 0.049605048 | M29: =SUM(C29:L29) -> 4.6676088 | N29: =SUM(O29:V29) -> 4.6009673 | O29: =SUM(USE!C29:DB29) -> 0.039770034 | P29: =wTRC!K29 -> 0 | Q29: =wABS!G28 -> 4.6082119 | R29: =wABS!K28 -> 0 | S29: =wABS!O28 -> 0 | T29: =wABS!S28 -> 0 | U29: =wABS!W28 -> -0.049116805 | V29: =wTRD!O29 -> 0.0021022222 | Y29: =M29-N29 -> 0.066641476 | Z29: =IF(M29<>0,Y29/M29*100,0) -> 1.4277434
A30: Sugar cane (A292) | B30: csugr | C30: 9.6086734 | D30: =wTRD!I30 -> 0.082659146 | E30: =wTAX!G30 -> 0 | F30: =wTAX!K30 -> 5.8054121e-06 | G30: =wTAX!O30 -> 0 | H30: =wTAX!S30 -> 0 | I30: =wTAX!W30 -> 0 | J30: =wTAX!AA30 -> 0.0025991823 | K30: =wTAX!AE30 -> 1.0636648e-06 | L30: =wTRC!G30 -> 0.06174218 | M30: =SUM(C30:L30) -> 9.7556808 | N30: =SUM(O30:V30) -> 6.0085959 | O30: =SUM(USE!C30:DB30) -> 0.091074722 | P30: =wTRC!K30 -> 0 | Q30: =wABS!G29 -> 4.770436 | R30: =wABS!K29 -> 0 | S30: =wABS!O29 -> 0 | T30: =wABS!S29 -> 0 | U30: =wABS!W29 -> 0 | V30: =wTRD!O30 -> 1.1470852 | Y30: =M30-N30 -> 3.7470848 | Z30: =IF(M30<>0,Y30/M30*100,0) -> 38.409261
A31: Pyrethrum (A293) | B31: cpyre | C31: 5.588236 | D31: =wTRD!I31 -> 0 | E31: =wTAX!G31 -> 0 | F31: =wTAX!K31 -> 0 | G31: =wTAX!O31 -> 0 | H31: =wTAX!S31 -> 0 | I31: =wTAX!W31 -> 0 | J31: =wTAX!AA31 -> 0.0017227413 | K31: =wTAX!AE31 -> 0 | L31: =wTRC!G31 -> 0.064734908 | M31: =SUM(C31:L31) -> 5.6546937 | N31: =SUM(O31:V31) -> 5.6351931 | O31: =SUM(USE!C31:DB31) -> 0.052967462 | P31: =wTRC!K31 -> 0 | Q31: =wABS!G30 -> 0 | R31: =wABS!K30 -> 0 | S31: =wABS!O30 -> 0 | T31: =wABS!S30 -> 0 | U31: =wABS!W30 -> 0 | V31: =wTRD!O31 -> 5.5822257 | Y31: =M31-N31 -> 0.019500539 | Z31: =IF(M31<>0,Y31/M31*100,0) -> 0.3448558
A32: Agricultural products n.e.c. (A299) | B32: cocrp | C32: 28.84254 | D32: =wTRD!I32 -> 1.8305554 | E32: =wTAX!G32 -> 0 | F32: =wTAX!K32 -> 0.0022134426 | G32: =wTAX!O32 -> 0 | H32: =wTAX!S32 -> 0 | I32: =wTAX!W32 -> 0 | J32: =wTAX!AA32 -> 0.019984906 | K32: =wTAX!AE32 -> 0.012578293 | L32: =wTRC!G32 -> 0.41944261 | M32: =SUM(C32:L32) -> 31.127314 | N32: =SUM(O32:V32) -> 36.772229 | O32: =SUM(USE!C32:DB32) -> 27.108743 | P32: =wTRC!K32 -> 0 | Q32: =wABS!G31 -> 1.9419286 | R32: =wABS!K31 -> 0 | S32: =wABS!O31 -> 0 | T32: =wABS!S31 -> 0 | U32: =wABS!W31 -> 5.7045392 | V32: =wTRD!O32 -> 2.0170181 | Y32: =M32-N32 -> -5.644915 | Z32: =IF(M32<>0,Y32/M32*100,0) -> -18.134925
... A78: Waste collection and management (E02) | B78: cwast | C78: 8.6127437 | D78: =wTRD!I78 -> 0 | E78: =wTAX!G78 -> 0 | F78: =wTAX!K78 -> 0 | G78: =wTAX!O78 -> 0 | H78: =wTAX!S78 -> 0 | I78: =wTAX!W78 -> 0 | J78: =wTAX!AA78 -> 0 | K78: =wTAX!AE78 -> 0 | L78: =wTRC!G78 -> 0 | M78: =SUM(C78:L78) -> 8.6127437 | N78: =SUM(O78:V78) -> 8.6071662 | O78: =SUM(USE!C78:DB78) -> 4.865261 | P78: =wTRC!K78 -> 0 | Q78: =wABS!G77 -> 3.7419052 | R78: =wABS!K77 -> 0 | S78: =wABS!O77 -> 0 | T78: =wABS!S77 -> 0 | U78: =wABS!W77 -> 0 | V78: =wTRD!O78 -> 0 | Y78: =M78-N78 -> 0.0055775672 | Z78: =IF(M78<>0,Y78/M78*100,0) -> 0.064759471
A79: Construction (modern) (F01) | B79: ccons | C79: 1286.9555 | D79: =wTRD!I79 -> 16.625815 | E79: =wTAX!G79 -> 0 | F79: =wTAX!K79 -> 0 | G79: =wTAX!O79 -> 0 | H79: =wTAX!S79 -> 0 | I79: =wTAX!W79 -> 0 | J79: =wTAX!AA79 -> 68.877012 | K79: =wTAX!AE79 -> 0 | L79: =wTRC!G79 -> 0 | M79: =SUM(C79:L79) -> 1372.4583 | N79: =SUM(O79:V79) -> 1376.4557 | O79: =SUM(USE!C79:DB79) -> 130.41273 | P79: =wTRC!K79 -> 0 | Q79: =wABS!G78 -> 62.903839 | R79: =wABS!K78 -> 0 | S79: =wABS!O78 -> 751.64126 | T79: =wABS!S78 -> 395.73968 | U79: =wABS!W78 -> 0 | V79: =[1]SUT!AD79 -> 35.75817 | W79: =[1]SUT!U79 -> 16.625815 | Y79: =M79-N79 -> -3.9973886 | Z79: =IF(M79<>0,Y79/M79*100,0) -> -0.29125757
A80: Construction (traditional) (F02) | B80: ccont | C80: 0 | D80: =wTRD!I80 -> 0 | E80: =wTAX!G80 -> 0 | F80: =wTAX!K80 -> 0 | G80: =wTAX!O80 -> 0 | H80: =wTAX!S80 -> 0 | I80: =wTAX!W80 -> 0 | J80: =wTAX!AA80 -> 0 | K80: =wTAX!AE80 -> 0 | L80: =wTRC!G80 -> 0 | M80: =SUM(C80:L80) -> 0 | N80: =SUM(O80:V80) -> 0 | O80: =SUM(USE!C80:DB80) -> 0 | P80: =wTRC!K80 -> 0 | Q80: =wABS!G79 -> 0 | R80: =wABS!K79 -> 0 | S80: =wABS!O79 -> 0 | T80: =wABS!S79 -> 0 | U80: =wABS!W79 -> 0 | V80: =[1]SUT!AD80 -> 0 | W80: =[1]SUT!U80 -> 0 | Y80: =M80-N80 -> 0 | Z80: =IF(M80<>0,Y80/M80*100,0) -> 0
A81: Maintenance and repair of motor vehicles (G10) | B81: cvehr | C81: 45.580684 | D81: =wTRD!I81 -> 0.066082117 | E81: =wTAX!G81 -> 0 | F81: =wTAX!K81 -> 0 | G81: =wTAX!O81 -> 0 | H81: =wTAX!S81 -> 0 | I81: =wTAX!W81 -> 0 | J81: =wTAX!AA81 -> 0.30225698 | K81: =wTAX!AE81 -> 0 | L81: =wTRC!G81 -> 0 | M81: =SUM(C81:L81) -> 45.949023 | N81: =SUM(O81:V81) -> 51.173371 | O81: =SUM(USE!C81:DB81) -> 42.882659 | P81: =wTRC!K81 -> 0 | Q81: =wABS!G80 -> 8.1249167 | R81: =wABS!K80 -> 0 | S81: =wABS!O80 -> 0 | T81: =wABS!S80 -> 0 | U81: =wABS!W80 -> 0 | V81: =[1]SUT!AD81 -> 0.16579485 | W81: =[1]SUT!U81 -> 0.066082117 | Y81: =M81-N81 -> -5.2243482 | Z81: =IF(M81<>0,Y81/M81*100,0) -> -11.369879
A82: Wholesale and retail trade of motor vehicles and motorcycles (G21) | B82: cveht | C82: 8.5434633 | D82: =wTRD!I82 -> 0 | E82: =wTAX!G82 -> 0 | F82: =wTAX!K82 -> 0 | G82: =wTAX!O82 -> 0 | H82: =wTAX!S82 -> 0 | I82: =wTAX!W82 -> 0 | J82: =wTAX!AA82 -> 0 | K82: =wTAX!AE82 -> 0 | L82: =wTRC!G82 -> 0 | M82: =SUM(C82:L82) -> 8.5434633 | N82: =SUM(O82:V82) -> 9.4328712 | O82: =SUM(USE!C82:DB82) -> 0 | P82: =wTRC!K82 -> 9.4328712 | Q82: =wABS!G81 -> 5.2228096e-13 | R82: =wABS!K81 -> 0 | S82: =wABS!O81 -> 0 | T82: =wABS!S81 -> 0 | U82: =wABS!W81 -> 0 | V82: =[1]SUT!AD82 -> 0 | W82: =[1]SUT!U82 -> 0 | Y82: =M82-N82 -> -0.88940793 | Z82: =IF(M82<>0,Y82/M82*100,0) -> -10.410391
A83: Wholesale trade, except of motor vehicles and motorcycles (G22) | B83: ctrdw | C83: 369.40298 | D83: =wTRD!I83 -> 0 | E83: =wTAX!G83 -> 0 | F83: =wTAX!K83 -> 0 | G83: =wTAX!O83 -> 0 | H83: =wTAX!S83 -> 0 | I83: =wTAX!W83 -> 0 | J83: =wTAX!AA83 -> 0 | K83: =wTAX!AE83 -> 0 | L83: =wTRC!G83 -> 0 | M83: =SUM(C83:L83) -> 369.40298 | N83: =SUM(O83:V83) -> 366.8969 | O83: =SUM(USE!C83:DB83) -> 0 | P83: =wTRC!K83 -> 366.8969 | Q83: =wABS!G82 -> 0 | R83: =wABS!K82 -> 0 | S83: =wABS!O82 -> 0 | T83: =wABS!S82 -> 0 | U83: =wABS!W82 -> 0 | V83: =[1]SUT!AD83 -> 0 | W83: =[1]SUT!U83 -> 0 | Y83: =M83-N83 -> 2.5060751 | Z83: =IF(M83<>0,Y83/M83*100,0) -> 0.67841225
A84: Retail trade, except of motor vehicles and motorcycles (G23) | B84: ctrdr | C84: 682.96525 | D84: =wTRD!I84 -> 0 | E84: =wTAX!G84 -> 0 | F84: =wTAX!K84 -> 0 | G84: =wTAX!O84 -> 0 | H84: =wTAX!S84 -> 0 | I84: =wTAX!W84 -> 0 | J84: =wTAX!AA84 -> 0 | K84: =wTAX!AE84 -> 0 | L84: =wTRC!G84 -> 0 | M84: =SUM(C84:L84) -> 682.96525 | N84: =SUM(O84:V84) -> 677.38585 | O84: =SUM(USE!C84:DB84) -> 0 | P84: =wTRC!K84 -> 677.38585 | Q84: =wABS!G83 -> 0 | R84: =wABS!K83 -> 0 | S84: =wABS!O83 -> 0 | T84: =wABS!S83 -> 0 | U84: =wABS!W83 -> 0 | V84: =[1]SUT!AD84 -> 0 | W84: =[1]SUT!U84 -> 0 | Y84: =M84-N84 -> 5.5794079 | Z84: =IF(M84<>0,Y84/M84*100,0) -> 0.81693877
A85: Land transport (H10) | B85: ctrnl | C85: 443.17788 | D85: =wTRD!I85 -> -12.14762 | E85: =wTAX!G85 -> 0 | F85: =wTAX!K85 -> 0 | G85: =wTAX!O85 -> 0 | H85: =wTAX!S85 -> 0 | I85: =wTAX!W85 -> 0 | J85: =wTAX!AA85 -> 3.1801699 | K85: =wTAX!AE85 -> 35.145485 | L85: =wTRC!G85 -> 0 | M85: =SUM(C85:L85) -> 469.35592 | N85: =SUM(O85:V85) -> 466.71452 | O85: =SUM(USE!C85:DB85) -> 194.19443 | P85: =wTRC!K85 -> 0 | Q85: =wABS!G84 -> 265.42917 | R85: =wABS!K84 -> 0 | S85: =wABS!O84 -> 0 | T85: =wABS!S84 -> 0 | U85: =wABS!W84 -> 0 | V85: =[1]SUT!AD85 -> 7.0909288 | W85: =[1]SUT!U85 -> -12.14762 | Y85: =M85-N85 -> 2.6413968 | Z85: =IF(M85<>0,Y85/M85*100,0) -> 0.56277054
A86: Air transport (H20) | B86: ctrna | C86: 180.52282 | D86: =wTRD!I86 -> 63.779916 | E86: =wTAX!G86 -> -85.334627 | F86: =wTAX!K86 -> 0 | G86: =wTAX!O86 -> 0 | H86: =wTAX!S86 -> 0 | I86: =wTAX!W86 -> 0 | J86: =wTAX!AA86 -> 1.3779153 | K86: =wTAX!AE86 -> 0 | L86: =wTRC!G86 -> 0 | M86: =SUM(C86:L86) -> 160.34602 | N86: =SUM(O86:V86) -> 162.42091 | O86: =SUM(USE!C86:DB86) -> 60.119947 | P86: =wTRC!K86 -> 0 | Q86: =wABS!G85 -> 11.83282 | R86: =wABS!K85 -> 0 | S86: =wABS!O85 -> 0 | T86: =wABS!S85 -> 0 | U86: =wABS!W85 -> 0 | V86: =[1]SUT!AD86 -> 90.46814 | W86: =[1]SUT!U86 -> 63.779916 | Y86: =M86-N86 -> -2.0748867 | Z86: =IF(M86<>0,Y86/M86*100,0) -> -1.2940058
A87: Services related to transport (H31) | B87: ctrns | C87: 32.83339 | D87: =wTRD!I87 -> 0.85896521 | E87: =wTAX!G87 -> 0 | F87: =wTAX!K87 -> 0 | G87: =wTAX!O87 -> 0 | H87: =wTAX!S87 -> 0 | I87: =wTAX!W87 -> 0 | J87: =wTAX!AA87 -> 0.52308983 | K87: =wTAX!AE87 -> 0 | L87: =wTRC!G87 -> 0 | M87: =SUM(C87:L87) -> 34.215445 | N87: =SUM(O87:V87) -> 34.198767 | O87: =SUM(USE!C87:DB87) -> 31.225699 | P87: =wTRC!K87 -> 0 | Q87: =wABS!G86 -> 2.5986042 | R87: =wABS!K86 -> 0 | S87: =wABS!O86 -> 0 | T87: =wABS!S86 -> 0 | U87: =wABS!W86 -> 0 | V87: =[1]SUT!AD87 -> 0.37446455 | W87: =[1]SUT!U87 -> 0.85896521 | Y87: =M87-N87 -> 0.016677254 | Z87: =IF(M87<>0,Y87/M87*100,0) -> 0.048741889
A88: Postal and courier activities (H32) | B88: cpost | C88: 10.240254 | D88: =wTRD!I88 -> 1.0777033 | E88: =wTAX!G88 -> 0 | F88: =wTAX!K88 -> 0 | G88: =wTAX!O88 -> 0 | H88: =wTAX!S88 -> 0 | I88: =wTAX!W88 -> 0 | J88: =wTAX!AA88 -> 0 | K88: =wTAX!AE88 -> 0 | L88: =wTRC!G88 -> 0 | M88: =SUM(C88:L88) -> 11.317957 | N88: =SUM(O88:V88) -> 11.301546 | O88: =SUM(USE!C88:DB88) -> 5.9345816 | P88: =wTRC!K88 -> 0 | Q88: =wABS!G87 -> 1.0834635 | R88: =wABS!K87 -> 0 | S88: =wABS!O87 -> 0 | T88: =wABS!S87 -> 0 | U88: =wABS!W87 -> 0 | V88: =[1]SUT!AD88 -> 4.2835009 | W88: =[1]SUT!U88 -> 1.0777033 | Y88: =M88-N88 -> 0.016411098 | Z88: =IF(M88<>0,Y88/M88*100,0) -> 0.14500053
A89: Hotels & restaurants (I00) | B89: chotl | C89: 517.44763 | D89: =wTRD!I89 -> 3.5171905 | E89: =wTAX!G89 -> 0 | F89: =wTAX!K89 -> 0 | G89: =wTAX!O89 -> 0 | H89: =wTAX!S89 -> 0 | I89: =wTAX!W89 -> -7.1830529 | J89: =wTAX!AA89 -> 11.186561 | K89: =wTAX!AE89 -> 0 | L89: =wTRC!G89 -> 0 | M89: =SUM(C89:L89) -> 524.96832 | N89: =SUM(O89:V89) -> 521.78825 | O89: =SUM(USE!C89:DB89) -> 160.12924 | P89: =wTRC!K89 -> 0 | Q89: =wABS!G88 -> 352.83466 | R89: =wABS!K88 -> 0 | S89: =wABS!O88 -> 0 | T89: =wABS!S88 -> 0 | U89: =wABS!W88 -> 0 | V89: =[1]SUT!AD89 -> 8.8243551 | W89: =[1]SUT!U89 -> 3.5171905 | Y89: =M89-N89 -> 3.1800735 | Z89: =IF(M89<>0,Y89/M89*100,0) -> 0.60576483
A90: Publishing, video making, programming & broadcasting activities (J10) | B90: cpubl | C90: 29.445093 | D90: =wTRD!I90 -> 7.9451517 | E90: =wTAX!G90 -> 0 | F90: =wTAX!K90 -> 0 | G90: =wTAX!O90 -> 0 | H90: =wTAX!S90 -> 0 | I90: =wTAX!W90 -> 0 | J90: =wTAX!AA90 -> 2.6991488 | K90: =wTAX!AE90 -> 0.12169435 | L90: =wTRC!G90 -> 0 | M90: =SUM(C90:L90) -> 40.211088 | N90: =SUM(O90:V90) -> 41.183265 | O90: =SUM(USE!C90:DB90) -> 24.118474 | P90: =wTRC!K90 -> 0 | Q90: =wABS!G89 -> 15.984869 | R90: =wABS!K89 -> 0 | S90: =wABS!O89 -> 0 | T90: =wABS!S89 -> 0 | U90: =wABS!W89 -> 0 | V90: =[1]SUT!AD90 -> 1.0799223 | W90: =[1]SUT!U90 -> 7.9451517 | Y90: =M90-N90 -> -0.97217744 | Z90: =IF(M90<>0,Y90/M90*100,0) -> -2.417685
... A111: Travel debits & credits (V00) | B111: ctrdc | C111: 0 | D111: =wTRD!I111 -> 308.3126 | E111: =wTAX!G111 -> 0 | F111: =wTAX!K111 -> 0 | G111: =wTAX!O111 -> 0 | H111: =wTAX!S111 -> 0 | I111: =wTAX!W111 -> 0 | J111: =wTAX!AA111 -> 0 | K111: =wTAX!AE111 -> 0 | L111: =wTRC!G111 -> 0 | M111: =SUM(C111:L111) -> 308.3126 | N111: =SUM(O111:V111) -> 309.79001 | O111: =SUM(USE!C111:DB111) -> 215.84204 | P111: =wTRC!K111 -> 0 | Q111: =wABS!G110 -> -222.92323 | R111: =wABS!K110 -> 0 | S111: =wABS!O110 -> 0 | T111: =wABS!S110 -> 0 | U111: =wABS!W110 -> 0 | V111: =[1]SUT!AD111 -> 316.87119 | W111: =[1]SUT!U111 -> 308.3126 | Y111: =M111-N111 -> -1.4774017 | Z111: =IF(M111<>0,Y111/M111*100,0) -> -0.47918954
B112: 0

Sheet USE
A1: Use Table
A2: Final values exported to GAMS
B4: From w-GDP | C4: {=TRANSPOSE(wGDPp!D8:D111)} -> 42.163108 | D4: 91.54879 | E4: 3.0363336 | F4: 55.892973 | G4: 0.27145353 | H4: 159.09592 | I4: 141.62941 | J4: 117.32855 | K4: 19.943023 | L4: 214.58619 | M4: 20.982413 | N4: 141.78518 | O4: 80.184602 | P4: 145.99979 | Q4: 26.477187 | R4: 24.758807 | S4: 8.5193652 | T4: 2.7968996 | U4: 0 | V4: 70.943429 | W4: 22.405977 | X4: 3.8840398 | Y4: 8.8945824 | Z4: 5.1729332 | AA4: 26.699039 | AB4: 76.457883 | AC4: 44.055757 | AD4: 12.119768 | AE4: 2.1617689 | AF4: 32.944426 | AG4: 14.264471 | AH4: 0.51409051 | AI4: 3.4818361 | AJ4: 300.53637 | AK4: 57.932328 | AL4: 19.531302 | AM4: 29 | AN4: 0.069262115 | AO4: 68.516522 | AP4: 96.414216 | AQ4: 21.926921 | AR4: 0 | AS4: 6.0929636 | AT4: 8.0793322 | AU4: 4.5099278 | AV4: 104.82926 | AW4: 16.426382 | AX4: 3.9291026 | AY4: 44.206113 | AZ4: 127.92243 | BA4: 25.055473 | BB4: 6.0220933 | BC4: 34 | BD4: 15.323992 | BE4: 10.676008 | BF4: 0.21840247 | BG4: 24.657724 | BH4: 5.5319545 | BI4: 3.5919192 | BJ4: 2.2300431 | BK4: 20.506689 | BL4: 11.263268 | BM4: 19.183835 | BN4: 8.4078105 | BO4: 4.4083546 | BP4: 23.782313 | BQ4: 37.021553 | BR4: 0.19613379 | BS4: 84 | BT4: 28.085247 | BU4: 3.9147533 | BV4: 458 | BW4: 0 | BX4: 35.699691 | BY4: 4.3003095 | BZ4: 180.44072 | CA4: 416.55928 | CB4: 205.15736 | CC4: 95.814909 | CD4: 44.025665 | CE4: 10.002069 | CF4: 140 | CG4: 22.681642 | CH4: 89.229867 | CI4: 22.088491 | CJ4: 53.971869 | CK4: 39.923725 | CL4: 97.104407 | CM4: 414.40535 | CN4: 145.59465 | CO4: 46.915941 | CP4: 14.49952 | CQ4: 101.58454 | CR4: 20.526827 | CS4: 256.47317 | CT4: 446 | CU4: 231 | CV4: 101.34991 | CW4: 58.650093 | CX4: 12.292706 | CY4: 52.356976 | CZ4: 301.47796 | DA4: 24.872356 | DB4: 0
B5: To Supply | C5: =SUM(C8:C114) -> 45.186128 | D5: =SUM(D8:D114) -> 98.112675 | E5: =SUM(E8:E114) -> 3.2540333 | F5: =SUM(F8:F114) -> 59.900399 | G5: =SUM(G8:G114) -> 0.29091626 | H5: =SUM(H8:H114) -> 170.10332 | I5: =SUM(I8:I114) -> 151.42836 | J5: =SUM(J8:J114) -> 125.44618 | ... DB5: =SUM(DB8:DB114) -> 0
C7: asorg | D7: amaiz | E7: awhea | F7: arice | G7: aocer | H7: aipot | I7: aspot | J7: acass | K7: aroot | L7: abean | M7: apeas | N7: avege | O7: abanb | P7: abanc | Q7: abans | R7: afrui | S7: agnut | T7: asoya | U7: aoils | V7: acoff | W7: ateal | X7: atoba | Y7: asugr | Z7: apyre | AA7: aocrp | AB7: acatt | AC7: asmlr | AD7: apoul | AE7: aoliv | AF7: amilk | AG7: aeggs | AH7: ahony | AI7: ahunt | AJ7: afuel | AK7: achar | AL7: afore | AM7: afish | AN7: angas | AO7: amore | AP7: aomin | AQ7: ameat | AR7: afsea | AS7: afveg | AT7: afoil | AU7: adair | AV7: agmll | AW7: abake | AX7: afeed | AY7: afood | AZ7: aalco | BA7: abeve | BB7: aptob | BC7: atext | BD7: awood | BE7: aprnt | BF7: apetr | BG7: achem | BH7: aphar | BI7: aprub | BJ7: anmet | BK7: aceme | BL7: aclay | BM7: ametl | BN7: amach | BO7: avehi | BP7: afurn | BQ7: aoman | BR7: arepr | BS7: aelec | BT7: awatr | BU7: awast | BV7: acons | BW7: acont | BX7: avehr | BY7: aveht | BZ7: atrdw | CA7: atrdr | CB7: atrnl | CC7: atrna | CD7: atrns | CE7: apost | CF7: ahotl | CG7: apubl | CH7: acomm | CI7: ainfo | CJ7: abank | CK7: ainsu | CL7: aofsv | CM7: arent | CN7: areal | CO7: alegl | CP7: aenga | CQ7: aprod | CR7: atrvl | CS7: aobsv | CT7: apadm | CU7: aeduc | CV7: aheal | CW7: asocw | CX7: acult | CY7: aarts | CZ7: aosrv | DA7: adsrv | DB7: atrdc
B8: csorg | C8: =IF(SUM(wUSE!C$113:C$115),C$4*wUSE!C9/SUM(wUSE!C$113:C$115),0) -> 0.34007323 | D8: =IF(SUM(wUSE!D$113:D$115),D$4*wUSE!D9/SUM(wUSE!D$113:D$115),0) -> 0 | E8: =IF(SUM(wUSE!E$113:E$115),E$4*wUSE!E9/SUM(wUSE!E$113:E$115),0) -> 0 | F8: =IF(SUM(wUSE!F$113:F$115),F$4*wUSE!F9/SUM(wUSE!F$113:F$115),0) -> 0 | G8: =IF(SUM(wUSE!G$113:G$115),G$4*wUSE!G9/SUM(wUSE!G$113:G$115),0) -> 0 | H8: =IF(SUM(wUSE!H$113:H$115),H$4*wUSE!H9/SUM(wUSE!H$113:H$115),0) -> 0 | I8: =IF(SUM(wUSE!I$113:I$115),I$4*wUSE!I9/SUM(wUSE!I$113:I$115),0) -> 0 | J8: =IF(SUM(wUSE!J$113:J$115),J$4*wUSE!J9/SUM(wUSE!J$113:J$115),0) -> 0 | ... DB8: =IF(SUM(wUSE!DB$113:DB$115),DB$4*wUSE!DB9/SUM(wUSE!DB$113:DB$115),0) -> 0
B9: cmaiz | C9: =IF(SUM(wUSE!C$113:C$115),C$4*wUSE!C10/SUM(wUSE!C$113:C$115),0) -> 0 | D9: =IF(SUM(wUSE!D$113:D$115),D$4*wUSE!D10/SUM(wUSE!D$113:D$115),0) -> 0.73840128 | E9: =IF(SUM(wUSE!E$113:E$115),E$4*wUSE!E10/SUM(wUSE!E$113:E$115),0) -> 0 | F9: =IF(SUM(wUSE!F$113:F$115),F$4*wUSE!F10/SUM(wUSE!F$113:F$115),0) -> 0 | G9: =IF(SUM(wUSE!G$113:G$115),G$4*wUSE!G10/SUM(wUSE!G$113:G$115),0) -> 0 | H9: =IF(SUM(wUSE!H$113:H$115),H$4*wUSE!H10/SUM(wUSE!H$113:H$115),0) -> 0 | I9: =IF(SUM(wUSE!I$113:I$115),I$4*wUSE!I10/SUM(wUSE!I$113:I$115),0) -> 0 | J9: =IF(SUM(wUSE!J$113:J$115),J$4*wUSE!J10/SUM(wUSE!J$113:J$115),0) -> 0 | ... DB9: =IF(SUM(wUSE!DB$113:DB$115),DB$4*wUSE!DB10/SUM(wUSE!DB$113:DB$115),0) -> 0
B10: cwhea | C10: =IF(SUM(wUSE!C$113:C$115),C$4*wUSE!C11/SUM(wUSE!C$113:C$115),0) -> 0 | D10: =IF(SUM(wUSE!D$113:D$115),D$4*wUSE!D11/SUM(wUSE!D$113:D$115),0) -> 0 | E10: =IF(SUM(wUSE!E$113:E$115),E$4*wUSE!E11/SUM(wUSE!E$113:E$115),0) -> 0.02449003 | F10: =IF(SUM(wUSE!F$113:F$115),F$4*wUSE!F11/SUM(wUSE!F$113:F$115),0) -> 0 | G10: =IF(SUM(wUSE!G$113:G$115),G$4*wUSE!G11/SUM(wUSE!G$113:G$115),0) -> 0 | H10: =IF(SUM(wUSE!H$113:H$115),H$4*wUSE!H11/SUM(wUSE!H$113:H$115),0) -> 0 | I10: =IF(SUM(wUSE!I$113:I$115),I$4*wUSE!I11/SUM(wUSE!I$113:I$115),0) -> 0 | J10: =IF(SUM(wUSE!J$113:J$115),J$4*wUSE!J11/SUM(wUSE!J$113:J$115),0) -> 0 | ... DB10: =IF(SUM(wUSE!DB$113:DB$115),DB$4*wUSE!DB11/SUM(wUSE!DB$113:DB$115),0) -> 0
B11: crice | C11: =IF(SUM(wUSE!C$113:C$115),C$4*wUSE!C12/SUM(wUSE!C$113:C$115),0) -> 0 | D11: =IF(SUM(wUSE!D$113:D$115),D$4*wUSE!D12/SUM(wUSE!D$113:D$115),0) -> 0 | E11: =IF(SUM(wUSE!E$113:E$115),E$4*wUSE!E12/SUM(wUSE!E$113:E$115),0) -> 0 | F11: =IF(SUM(wUSE!F$113:F$115),F$4*wUSE!F12/SUM(wUSE!F$113:F$115),0) -> 0.45081363 | G11: =IF(SUM(wUSE!G$113:G$115),G$4*wUSE!G12/SUM(wUSE!G$113:G$115),0) -> 0 | H11: =IF(SUM(wUSE!H$113:H$115),H$4*wUSE!H12/SUM(wUSE!H$113:H$115),0) -> 0 | I11: =IF(SUM(wUSE!I$113:I$115),I$4*wUSE!I12/SUM(wUSE!I$113:I$115),0) -> 0 | J11: =IF(SUM(wUSE!J$113:J$115),J$4*wUSE!J12/SUM(wUSE!J$113:J$115),0) -> 0 | ... DB11: =IF(SUM(wUSE!DB$113:DB$115),DB$4*wUSE!DB12/SUM(wUSE!DB$113:DB$115),0) -> 0
B12: cocer | C12: =IF(SUM(wUSE!C$113:C$115),C$4*wUSE!C13/SUM(wUSE!C$113:C$115),0) -> 0 | D12: =IF(SUM(wUSE!D$113:D$115),D$4*wUSE!D13/SUM(wUSE!D$113:D$115),0) -> 0 | E12: =IF(SUM(wUSE!E$113:E$115),E$4*wUSE!E13/SUM(wUSE!E$113:E$115),0) -> 0 | F12: =IF(SUM(wUSE!F$113:F$115),F$4*wUSE!F13/SUM(wUSE!F$113:F$115),0) -> 0 | G12: =IF(SUM(wUSE!G$113:G$115),G$4*wUSE!G13/SUM(wUSE!G$113:G$115),0) -> 0.0021894514 | H12: =IF(SUM(wUSE!H$113:H$115),H$4*wUSE!H13/SUM(wUSE!H$113:H$115),0) -> 0 | I12: =IF(SUM(wUSE!I$113:I$115),I$4*wUSE!I13/SUM(wUSE!I$113:I$115),0) -> 0 | J12: =IF(SUM(wUSE!J$113:J$115),J$4*wUSE!J13/SUM(wUSE!J$113:J$115),0) -> 0 | ... DB12: =IF(SUM(wUSE!DB$113:DB$115),DB$4*wUSE!DB13/SUM(wUSE!DB$113:DB$115),0) -> 0
B13: cipot | C13: =IF(SUM(wUSE!C$113:C$115),C$4*wUSE!C14/SUM(wUSE!C$113:C$115),0) -> 0 | D13: =IF(SUM(wUSE!D$113:D$115),D$4*wUSE!D14/SUM(wUSE!D$113:D$115),0) -> 0 | E13: =IF(SUM(wUSE!E$113:E$115),E$4*wUSE!E14/SUM(wUSE!E$113:E$115),0) -> 0 | F13: =IF(SUM(wUSE!F$113:F$115),F$4*wUSE!F14/SUM(wUSE!F$113:F$115),0) -> 0 | G13: =IF(SUM(wUSE!G$113:G$115),G$4*wUSE!G14/SUM(wUSE!G$113:G$115),0) -> 0 | H13: =IF(SUM(wUSE!H$113:H$115),H$4*wUSE!H14/SUM(wUSE!H$113:H$115),0) -> 1.9456344 | I13: =IF(SUM(wUSE!I$113:I$115),I$4*wUSE!I14/SUM(wUSE!I$113:I$115),0) -> 0 | J13: =IF(SUM(wUSE!J$113:J$115),J$4*wUSE!J14/SUM(wUSE!J$113:J$115),0) -> 0 | ... DB13: =IF(SUM(wUSE!DB$113:DB$115),DB$4*wUSE!DB14/SUM(wUSE!DB$113:DB$115),0) -> 0
B14: cspot | C14: =IF(SUM(wUSE!C$113:C$115),C$4*wUSE!C15/SUM(wUSE!C$113:C$115),0) -> 0 | D14: =IF(SUM(wUSE!D$113:D$115),D$4*wUSE!D15/SUM(wUSE!D$113:D$115),0) -> 0 | E14: =IF(SUM(wUSE!E$113:E$115),E$4*wUSE!E15/SUM(wUSE!E$113:E$115),0) -> 0 | F14: =IF(SUM(wUSE!F$113:F$115),F$4*wUSE!F15/SUM(wUSE!F$113:F$115),0) -> 0 | G14: =IF(SUM(wUSE!G$113:G$115),G$4*wUSE!G15/SUM(wUSE!G$113:G$115),0) -> 0 | H14: =IF(SUM(wUSE!H$113:H$115),H$4*wUSE!H15/SUM(wUSE!H$113:H$115),0) -> 0 | I14: =IF(SUM(wUSE!I$113:I$115),I$4*wUSE!I15/SUM(wUSE!I$113:I$115),0) -> 1.732031 | J14: =IF(SUM(wUSE!J$113:J$115),J$4*wUSE!J15/SUM(wUSE!J$113:J$115),0) -> 0 | ... DB14: =IF(SUM(wUSE!DB$113:DB$115),DB$4*wUSE!DB15/SUM(wUSE!DB$113:DB$115),0) -> 0
B15: ccass | C15: =IF(SUM(wUSE!C$113:C$115),C$4*wUSE!C16/SUM(wUSE!C$113:C$115),0) -> 0 | D15: =IF(SUM(wUSE!D$113:D$115),D$4*wUSE!D16/SUM(wUSE!D$113:D$115),0) -> 0 | E15: =IF(SUM(wUSE!E$113:E$115),E$4*wUSE!E16/SUM(wUSE!E$113:E$115),0) -> 0 | F15: =IF(SUM(wUSE!F$113:F$115),F$4*wUSE!F16/SUM(wUSE!F$113:F$115),0) -> 0 | G15: =IF(SUM(wUSE!G$113:G$115),G$4*wUSE!G16/SUM(wUSE!G$113:G$115),0) -> 0 | H15: =IF(SUM(wUSE!H$113:H$115),H$4*wUSE!H16/SUM(wUSE!H$113:H$115),0) -> 0 | I15: =IF(SUM(wUSE!I$113:I$115),I$4*wUSE!I16/SUM(wUSE!I$113:I$115),0) -> 0 | J15: =IF(SUM(wUSE!J$113:J$115),J$4*wUSE!J16/SUM(wUSE!J$113:J$115),0) -> 1.434848 | ... DB15: =IF(SUM(wUSE!DB$113:DB$115),DB$4*wUSE!DB16/SUM(wUSE!DB$113:DB$115),0) -> 0
B16: croot | C16: =IF(SUM(wUSE!C$113:C$115),C$4*wUSE!C17/SUM(wUSE!C$113:C$115),0) -> 0 | D16: =IF(SUM(wUSE!D$113:D$115),D$4*wUSE!D17/SUM(wUSE!D$113:D$115),0) -> 0 | E16: =IF(SUM(wUSE!E$113:E$115),E$4*wUSE!E17/SUM(wUSE!E$113:E$115),0) -> 0 | F16: =IF(SUM(wUSE!F$113:F$115),F$4*wUSE!F17/SUM(wUSE!F$113:F$115),0) -> 0 | G16: =IF(SUM(wUSE!G$113:G$115),G$4*wUSE!G17/SUM(wUSE!G$113:G$115),0) -> 0 | H16: =IF(SUM(wUSE!H$113:H$115),H$4*wUSE!H17/SUM(wUSE!H$113:H$115),0) -> 0 | I16: =IF(SUM(wUSE!I$113:I$115),I$4*wUSE!I17/SUM(wUSE!I$113:I$115),0) -> 0 | J16: =IF(SUM(wUSE!J$113:J$115),J$4*wUSE!J17/SUM(wUSE!J$113:J$115),0) -> 0 | ... DB16: =IF(SUM(wUSE!DB$113:DB$115),DB$4*wUSE!DB17/SUM(wUSE!DB$113:DB$115),0) -> 0
B17: cbean | C17: =IF(SUM(wUSE!C$113:C$115),C$4*wUSE!C18/SUM(wUSE!C$113:C$115),0) -> 0 | D17: =IF(SUM(wUSE!D$113:D$115),D$4*wUSE!D18/SUM(wUSE!D$113:D$115),0) -> 0 | E17: =IF(SUM(wUSE!E$113:E$115),E$4*wUSE!E18/SUM(wUSE!E$113:E$115),0) -> 0 | F17: =IF(SUM(wUSE!F$113:F$115),F$4*wUSE!F18/SUM(wUSE!F$113:F$115),0) -> 0 | G17: =IF(SUM(wUSE!G$113:G$115),G$4*wUSE!G18/SUM(wUSE!G$113:G$115),0) -> 0 | H17: =IF(SUM(wUSE!H$113:H$115),H$4*wUSE!H18/SUM(wUSE!H$113:H$115),0) -> 0 | I17: =IF(SUM(wUSE!I$113:I$115),I$4*wUSE!I18/SUM(wUSE!I$113:I$115),0) -> 0 | J17: =IF(SUM(wUSE!J$113:J$115),J$4*wUSE!J18/SUM(wUSE!J$113:J$115),0) -> 0 | ... DB17: =IF(SUM(wUSE!DB$113:DB$115),DB$4*wUSE!DB18/SUM(wUSE!DB$113:DB$115),0) -> 0
B18: cpeas | C18: =IF(SUM(wUSE!C$113:C$115),C$4*wUSE!C19/SUM(wUSE!C$113:C$115),0) -> 0 | D18: =IF(SUM(wUSE!D$113:D$115),D$4*wUSE!D19/SUM(wUSE!D$113:D$115),0) -> 0 | E18: =IF(SUM(wUSE!E$113:E$115),E$4*wUSE!E19/SUM(wUSE!E$113:E$115),0) -> 0 | F18: =IF(SUM(wUSE!F$113:F$115),F$4*wUSE!F19/SUM(wUSE!F$113:F$115),0) -> 0 | G18: =IF(SUM(wUSE!G$113:G$115),G$4*wUSE!G19/SUM(wUSE!G$113:G$115),0) -> 0 | H18: =IF(SUM(wUSE!H$113:H$115),H$4*wUSE!H19/SUM(wUSE!H$113:H$115),0) -> 0 | I18: =IF(SUM(wUSE!I$113:I$115),I$4*wUSE!I19/SUM(wUSE!I$113:I$115),0) -> 0 | J18: =IF(SUM(wUSE!J$113:J$115),J$4*wUSE!J19/SUM(wUSE!J$113:J$115),0) -> 0 | ... DB18: =IF(SUM(wUSE!DB$113:DB$115),DB$4*wUSE!DB19/SUM(wUSE!DB$113:DB$115),0) -> 0
B19: cvege | C19: =IF(SUM(wUSE!C$113:C$115),C$4*wUSE!C20/SUM(wUSE!C$113:C$115),0) -> 0 | D19: =IF(SUM(wUSE!D$113:D$115),D$4*wUSE!D20/SUM(wUSE!D$113:D$115),0) -> 0 | E19: =IF(SUM(wUSE!E$113:E$115),E$4*wUSE!E20/SUM(wUSE!E$113:E$115),0) -> 0 | F19: =IF(SUM(wUSE!F$113:F$115),F$4*wUSE!F20/SUM(wUSE!F$113:F$115),0) -> 0 | G19: =IF(SUM(wUSE!G$113:G$115),G$4*wUSE!G20/SUM(wUSE!G$113:G$115),0) -> 0 | H19: =IF(SUM(wUSE!H$113:H$115),H$4*wUSE!H20/SUM(wUSE!H$113:H$115),0) -> 0 | I19: =IF(SUM(wUSE!I$113:I$115),I$4*wUSE!I20/SUM(wUSE!I$113:I$115),0) -> 0 | J19: =IF(SUM(wUSE!J$113:J$115),J$4*wUSE!J20/SUM(wUSE!J$113:J$115),0) -> 0 | ... DB19: =IF(SUM(wUSE!DB$113:DB$115),DB$4*wUSE!DB20/SUM(wUSE!DB$113:DB$115),0) -> 0
... B114: fcap | C114: =IF(SUM(wUSE!C$113:C$115),C$4*wUSE!C115/SUM(wUSE!C$113:C$115),0) -> 3.0915433 | D114: =IF(SUM(wUSE!D$113:D$115),D$4*wUSE!D115/SUM(wUSE!D$113:D$115),0) -> 7.3312442 | E114: =IF(SUM(wUSE!E$113:E$115),E$4*wUSE!E115/SUM(wUSE!E$113:E$115),0) -> 0.28140232 | F114: =IF(SUM(wUSE!F$113:F$115),F$4*wUSE!F115/SUM(wUSE!F$113:F$115),0) -> 6.2513809 | G114: =IF(SUM(wUSE!G$113:G$115),G$4*wUSE!G115/SUM(wUSE!G$113:G$115),0) -> 0.019903901 | H114: =IF(SUM(wUSE!H$113:H$115),H$4*wUSE!H115/SUM(wUSE!H$113:H$115),0) -> 17.145547 | I114: =IF(SUM(wUSE!I$113:I$115),I$4*wUSE!I115/SUM(wUSE!I$113:I$115),0) -> 10.269122 | J114: =IF(SUM(wUSE!J$113:J$115),J$4*wUSE!J115/SUM(wUSE!J$113:J$115),0) -> 9.46332 | ... DB114: =IF(SUM(wUSE!DB$113:DB$115),DB$4*wUSE!DB115/SUM(wUSE!DB$113:DB$115),0) -> 0

Sheet SUP
A1: Supply Table
A2: Final values exported to GAMS
B4: To SUT | C4: =SUM(C8:C111) -> 45.186128 | D4: =SUM(D8:D111) -> 98.112675 | E4: =SUM(E8:E111) -> 3.2540333 | F4: =SUM(F8:F111) -> 59.900399 | G4: =SUM(G8:G111) -> 0.29091626 | H4: =SUM(H8:H111) -> 170.10332 | I4: =SUM(I8:I111) -> 151.42836 | J4: =SUM(J8:J111) -> 125.44618 | ... DB4: =SUM(DB8:DB111) -> 0
A7: From Use | C7: csorg | D7: cmaiz | E7: cwhea | F7: crice | G7: cocer | H7: cipot | I7: cspot | J7: ccass | K7: croot | L7: cbean | M7: cpeas | N7: cvege | O7: cbanb | P7: cbanc | Q7: cbans | R7: cfrui | S7: cgnut | T7: csoya | U7: coils | V7: ccoff | W7: cteal | X7: ctoba | Y7: csugr | Z7: cpyre | AA7: cocrp | AB7: ccatt | AC7: csmlr | AD7: cpoul | AE7: coliv | AF7: cmilk | AG7: ceggs | AH7: chony | AI7: chunt | AJ7: cfuel | AK7: cchar | AL7: cfore | AM7: cfish | AN7: cngas | AO7: cmore | AP7: comin | AQ7: cmeat | AR7: cfsea | AS7: cfveg | AT7: cfoil | AU7: cdair | AV7: cgmll | AW7: cbake | AX7: cfeed | AY7: cfood | AZ7: calco | BA7: cbeve | BB7: cptob | BC7: ctext | BD7: cwood | BE7: cprnt | BF7: cpetr | BG7: cchem | BH7: cphar | BI7: cprub | BJ7: cnmet | BK7: cceme | BL7: cclay | BM7: cmetl | BN7: cmach | BO7: cvehi | BP7: cfurn | BQ7: coman | BR7: crepr | BS7: celec | BT7: cwatr | BU7: cwast | BV7: ccons | BW7: ccont | BX7: cvehr | BY7: cveht | BZ7: ctrdw | CA7: ctrdr | CB7: ctrnl | CC7: ctrna | CD7: ctrns | CE7: cpost | CF7: chotl | CG7: cpubl | CH7: ccomm | CI7: cinfo | CJ7: cbank | CK7: cinsu | CL7: cofsv | CM7: crent | CN7: creal | CO7: clegl | CP7: cenga | CQ7: cprod | CR7: ctrvl | CS7: cobsv | CT7: cpadm | CU7: ceduc | CV7: cheal | CW7: csocw | CX7: ccult | CY7: carts | CZ7: cosrv | DA7: cdsrv | DB7: ctrdc
A8: {=TRANSPOSE(USE!C5:DB5)} -> 45.186128 | B8: asorg | C8: =IF(SUM(wSUP!$C8:$DB8),$A8*wSUP!C8/SUM(wSUP!$C8:$DB8),0) -> 45.186128 | D8: =IF(SUM(wSUP!$C8:$DB8),$A8*wSUP!D8/SUM(wSUP!$C8:$DB8),0) -> 0 | E8: =IF(SUM(wSUP!$C8:$DB8),$A8*wSUP!E8/SUM(wSUP!$C8:$DB8),0) -> 0 | F8: =IF(SUM(wSUP!$C8:$DB8),$A8*wSUP!F8/SUM(wSUP!$C8:$DB8),0) -> 0 | G8: =IF(SUM(wSUP!$C8:$DB8),$A8*wSUP!G8/SUM(wSUP!$C8:$DB8),0) -> 0 | H8: =IF(SUM(wSUP!$C8:$DB8),$A8*wSUP!H8/SUM(wSUP!$C8:$DB8),0) -> 0 | I8: =IF(SUM(wSUP!$C8:$DB8),$A8*wSUP!I8/SUM(wSUP!$C8:$DB8),0) -> 0 | J8: =IF(SUM(wSUP!$C8:$DB8),$A8*wSUP!J8/SUM(wSUP!$C8:$DB8),0) -> 0 | ... DB8: =IF(SUM(wSUP!$C8:$DB8),$A8*wSUP!DB8/SUM(wSUP!$C8:$DB8),0) -> 0
A9: 98.112675 | B9: amaiz | C9: =IF(SUM(wSUP!$C9:$DB9),$A9*wSUP!C9/SUM(wSUP!$C9:$DB9),0) -> 0 | D9: =IF(SUM(wSUP!$C9:$DB9),$A9*wSUP!D9/SUM(wSUP!$C9:$DB9),0) -> 98.112675 | E9: =IF(SUM(wSUP!$C9:$DB9),$A9*wSUP!E9/SUM(wSUP!$C9:$DB9),0) -> 0 | F9: =IF(SUM(wSUP!$C9:$DB9),$A9*wSUP!F9/SUM(wSUP!$C9:$DB9),0) -> 0 | G9: =IF(SUM(wSUP!$C9:$DB9),$A9*wSUP!G9/SUM(wSUP!$C9:$DB9),0) -> 0 | H9: =IF(SUM(wSUP!$C9:$DB9),$A9*wSUP!H9/SUM(wSUP!$C9:$DB9),0) -> 0 | I9: =IF(SUM(wSUP!$C9:$DB9),$A9*wSUP!I9/SUM(wSUP!$C9:$DB9),0) -> 0 | J9: =IF(SUM(wSUP!$C9:$DB9),$A9*wSUP!J9/SUM(wSUP!$C9:$DB9),0) -> 0 | ... DB9: =IF(SUM(wSUP!$C9:$DB9),$A9*wSUP!DB9/SUM(wSUP!$C9:$DB9),0) -> 0
A10: 3.2540333 | B10: awhea | C10: =IF(SUM(wSUP!$C10:$DB10),$A10*wSUP!C10/SUM(wSUP!$C10:$DB10),0) -> 0 | D10: =IF(SUM(wSUP!$C10:$DB10),$A10*wSUP!D10/SUM(wSUP!$C10:$DB10),0) -> 0 | E10: =IF(SUM(wSUP!$C10:$DB10),$A10*wSUP!E10/SUM(wSUP!$C10:$DB10),0) -> 3.2540333 | F10: =IF(SUM(wSUP!$C10:$DB10),$A10*wSUP!F10/SUM(wSUP!$C10:$DB10),0) -> 0 | G10: =IF(SUM(wSUP!$C10:$DB10),$A10*wSUP!G10/SUM(wSUP!$C10:$DB10),0) -> 0 | H10: =IF(SUM(wSUP!$C10:$DB10),$A10*wSUP!H10/SUM(wSUP!$C10:$DB10),0) -> 0 | I10: =IF(SUM(wSUP!$C10:$DB10),$A10*wSUP!I10/SUM(wSUP!$C10:$DB10),0) -> 0 | J10: =IF(SUM(wSUP!$C10:$DB10),$A10*wSUP!J10/SUM(wSUP!$C10:$DB10),0) -> 0 | ... DB10: =IF(SUM(wSUP!$C10:$DB10),$A10*wSUP!DB10/SUM(wSUP!$C10:$DB10),0) -> 0
A11: 59.900399 | B11: arice | C11: =IF(SUM(wSUP!$C11:$DB11),$A11*wSUP!C11/SUM(wSUP!$C11:$DB11),0) -> 0 | D11: =IF(SUM(wSUP!$C11:$DB11),$A11*wSUP!D11/SUM(wSUP!$C11:$DB11),0) -> 0 | E11: =IF(SUM(wSUP!$C11:$DB11),$A11*wSUP!E11/SUM(wSUP!$C11:$DB11),0) -> 0 | F11: =IF(SUM(wSUP!$C11:$DB11),$A11*wSUP!F11/SUM(wSUP!$C11:$DB11),0) -> 59.900399 | G11: =IF(SUM(wSUP!$C11:$DB11),$A11*wSUP!G11/SUM(wSUP!$C11:$DB11),0) -> 0 | H11: =IF(SUM(wSUP!$C11:$DB11),$A11*wSUP!H11/SUM(wSUP!$C11:$DB11),0) -> 0 | I11: =IF(SUM(wSUP!$C11:$DB11),$A11*wSUP!I11/SUM(wSUP!$C11:$DB11),0) -> 0 | J11: =IF(SUM(wSUP!$C11:$DB11),$A11*wSUP!J11/SUM(wSUP!$C11:$DB11),0) -> 0 | ... DB11: =IF(SUM(wSUP!$C11:$DB11),$A11*wSUP!DB11/SUM(wSUP!$C11:$DB11),0) -> 0
A12: 0.29091626 | B12: aocer | C12: =IF(SUM(wSUP!$C12:$DB12),$A12*wSUP!C12/SUM(wSUP!$C12:$DB12),0) -> 0 | D12: =IF(SUM(wSUP!$C12:$DB12),$A12*wSUP!D12/SUM(wSUP!$C12:$DB12),0) -> 0 | E12: =IF(SUM(wSUP!$C12:$DB12),$A12*wSUP!E12/SUM(wSUP!$C12:$DB12),0) -> 0 | F12: =IF(SUM(wSUP!$C12:$DB12),$A12*wSUP!F12/SUM(wSUP!$C12:$DB12),0) -> 0 | G12: =IF(SUM(wSUP!$C12:$DB12),$A12*wSUP!G12/SUM(wSUP!$C12:$DB12),0) -> 0.29091626 | H12: =IF(SUM(wSUP!$C12:$DB12),$A12*wSUP!H12/SUM(wSUP!$C12:$DB12),0) -> 0 | I12: =IF(SUM(wSUP!$C12:$DB12),$A12*wSUP!I12/SUM(wSUP!$C12:$DB12),0) -> 0 | J12: =IF(SUM(wSUP!$C12:$DB12),$A12*wSUP!J12/SUM(wSUP!$C12:$DB12),0) -> 0 | ... DB12: =IF(SUM(wSUP!$C12:$DB12),$A12*wSUP!DB12/SUM(wSUP!$C12:$DB12),0) -> 0
A13: 170.10332 | B13: aipot | C13: =IF(SUM(wSUP!$C13:$DB13),$A13*wSUP!C13/SUM(wSUP!$C13:$DB13),0) -> 0 | D13: =IF(SUM(wSUP!$C13:$DB13),$A13*wSUP!D13/SUM(wSUP!$C13:$DB13),0) -> 0 | E13: =IF(SUM(wSUP!$C13:$DB13),$A13*wSUP!E13/SUM(wSUP!$C13:$DB13),0) -> 0 | F13: =IF(SUM(wSUP!$C13:$DB13),$A13*wSUP!F13/SUM(wSUP!$C13:$DB13),0) -> 0 | G13: =IF(SUM(wSUP!$C13:$DB13),$A13*wSUP!G13/SUM(wSUP!$C13:$DB13),0) -> 0 | H13: =IF(SUM(wSUP!$C13:$DB13),$A13*wSUP!H13/SUM(wSUP!$C13:$DB13),0) -> 170.10332 | I13: =IF(SUM(wSUP!$C13:$DB13),$A13*wSUP!I13/SUM(wSUP!$C13:$DB13),0) -> 0 | J13: =IF(SUM(wSUP!$C13:$DB13),$A13*wSUP!J13/SUM(wSUP!$C13:$DB13),0) -> 0 | ... DB13: =IF(SUM(wSUP!$C13:$DB13),$A13*wSUP!DB13/SUM(wSUP!$C13:$DB13),0) -> 0
A14: 151.42836 | B14: aspot | C14: =IF(SUM(wSUP!$C14:$DB14),$A14*wSUP!C14/SUM(wSUP!$C14:$DB14),0) -> 0 | D14: =IF(SUM(wSUP!$C14:$DB14),$A14*wSUP!D14/SUM(wSUP!$C14:$DB14),0) -> 0 | E14: =IF(SUM(wSUP!$C14:$DB14),$A14*wSUP!E14/SUM(wSUP!$C14:$DB14),0) -> 0 | F14: =IF(SUM(wSUP!$C14:$DB14),$A14*wSUP!F14/SUM(wSUP!$C14:$DB14),0) -> 0 | G14: =IF(SUM(wSUP!$C14:$DB14),$A14*wSUP!G14/SUM(wSUP!$C14:$DB14),0) -> 0 | H14: =IF(SUM(wSUP!$C14:$DB14),$A14*wSUP!H14/SUM(wSUP!$C14:$DB14),0) -> 0 | I14: =IF(SUM(wSUP!$C14:$DB14),$A14*wSUP!I14/SUM(wSUP!$C14:$DB14),0) -> 151.42836 | J14: =IF(SUM(wSUP!$C14:$DB14),$A14*wSUP!J14/SUM(wSUP!$C14:$DB14),0) -> 0 | ... DB14: =IF(SUM(wSUP!$C14:$DB14),$A14*wSUP!DB14/SUM(wSUP!$C14:$DB14),0) -> 0
A15: 125.44618 | B15: acass | C15: =IF(SUM(wSUP!$C15:$DB15),$A15*wSUP!C15/SUM(wSUP!$C15:$DB15),0) -> 0 | D15: =IF(SUM(wSUP!$C15:$DB15),$A15*wSUP!D15/SUM(wSUP!$C15:$DB15),0) -> 0 | E15: =IF(SUM(wSUP!$C15:$DB15),$A15*wSUP!E15/SUM(wSUP!$C15:$DB15),0) -> 0 | F15: =IF(SUM(wSUP!$C15:$DB15),$A15*wSUP!F15/SUM(wSUP!$C15:$DB15),0) -> 0 | G15: =IF(SUM(wSUP!$C15:$DB15),$A15*wSUP!G15/SUM(wSUP!$C15:$DB15),0) -> 0 | H15: =IF(SUM(wSUP!$C15:$DB15),$A15*wSUP!H15/SUM(wSUP!$C15:$DB15),0) -> 0 | I15: =IF(SUM(wSUP!$C15:$DB15),$A15*wSUP!I15/SUM(wSUP!$C15:$DB15),0) -> 0 | J15: =IF(SUM(wSUP!$C15:$DB15),$A15*wSUP!J15/SUM(wSUP!$C15:$DB15),0) -> 125.44618 | ... DB15: =IF(SUM(wSUP!$C15:$DB15),$A15*wSUP!DB15/SUM(wSUP!$C15:$DB15),0) -> 0
A16: 21.322825 | B16: aroot | C16: =IF(SUM(wSUP!$C16:$DB16),$A16*wSUP!C16/SUM(wSUP!$C16:$DB16),0) -> 0 | D16: =IF(SUM(wSUP!$C16:$DB16),$A16*wSUP!D16/SUM(wSUP!$C16:$DB16),0) -> 0 | E16: =IF(SUM(wSUP!$C16:$DB16),$A16*wSUP!E16/SUM(wSUP!$C16:$DB16),0) -> 0 | F16: =IF(SUM(wSUP!$C16:$DB16),$A16*wSUP!F16/SUM(wSUP!$C16:$DB16),0) -> 0 | G16: =IF(SUM(wSUP!$C16:$DB16),$A16*wSUP!G16/SUM(wSUP!$C16:$DB16),0) -> 0 | H16: =IF(SUM(wSUP!$C16:$DB16),$A16*wSUP!H16/SUM(wSUP!$C16:$DB16),0) -> 0 | I16: =IF(SUM(wSUP!$C16:$DB16),$A16*wSUP!I16/SUM(wSUP!$C16:$DB16),0) -> 0 | J16: =IF(SUM(wSUP!$C16:$DB16),$A16*wSUP!J16/SUM(wSUP!$C16:$DB16),0) -> 0 | ... DB16: =IF(SUM(wSUP!$C16:$DB16),$A16*wSUP!DB16/SUM(wSUP!$C16:$DB16),0) -> 0
A17: 225.71312 | B17: abean | C17: =IF(SUM(wSUP!$C17:$DB17),$A17*wSUP!C17/SUM(wSUP!$C17:$DB17),0) -> 0 | D17: =IF(SUM(wSUP!$C17:$DB17),$A17*wSUP!D17/SUM(wSUP!$C17:$DB17),0) -> 0 | E17: =IF(SUM(wSUP!$C17:$DB17),$A17*wSUP!E17/SUM(wSUP!$C17:$DB17),0) -> 0 | F17: =IF(SUM(wSUP!$C17:$DB17),$A17*wSUP!F17/SUM(wSUP!$C17:$DB17),0) -> 0 | G17: =IF(SUM(wSUP!$C17:$DB17),$A17*wSUP!G17/SUM(wSUP!$C17:$DB17),0) -> 0 | H17: =IF(SUM(wSUP!$C17:$DB17),$A17*wSUP!H17/SUM(wSUP!$C17:$DB17),0) -> 0 | I17: =IF(SUM(wSUP!$C17:$DB17),$A17*wSUP!I17/SUM(wSUP!$C17:$DB17),0) -> 0 | J17: =IF(SUM(wSUP!$C17:$DB17),$A17*wSUP!J17/SUM(wSUP!$C17:$DB17),0) -> 0 | ... DB17: =IF(SUM(wSUP!$C17:$DB17),$A17*wSUP!DB17/SUM(wSUP!$C17:$DB17),0) -> 0
A18: 22.070413 | B18: apeas | C18: =IF(SUM(wSUP!$C18:$DB18),$A18*wSUP!C18/SUM(wSUP!$C18:$DB18),0) -> 0 | D18: =IF(SUM(wSUP!$C18:$DB18),$A18*wSUP!D18/SUM(wSUP!$C18:$DB18),0) -> 0 | E18: =IF(SUM(wSUP!$C18:$DB18),$A18*wSUP!E18/SUM(wSUP!$C18:$DB18),0) -> 0 | F18: =IF(SUM(wSUP!$C18:$DB18),$A18*wSUP!F18/SUM(wSUP!$C18:$DB18),0) -> 0 | G18: =IF(SUM(wSUP!$C18:$DB18),$A18*wSUP!G18/SUM(wSUP!$C18:$DB18),0) -> 0 | H18: =IF(SUM(wSUP!$C18:$DB18),$A18*wSUP!H18/SUM(wSUP!$C18:$DB18),0) -> 0 | I18: =IF(SUM(wSUP!$C18:$DB18),$A18*wSUP!I18/SUM(wSUP!$C18:$DB18),0) -> 0 | J18: =IF(SUM(wSUP!$C18:$DB18),$A18*wSUP!J18/SUM(wSUP!$C18:$DB18),0) -> 0 | ... DB18: =IF(SUM(wSUP!$C18:$DB18),$A18*wSUP!DB18/SUM(wSUP!$C18:$DB18),0) -> 0
A19: 149.13716 | B19: avege | C19: =IF(SUM(wSUP!$C19:$DB19),$A19*wSUP!C19/SUM(wSUP!$C19:$DB19),0) -> 0 | D19: =IF(SUM(wSUP!$C19:$DB19),$A19*wSUP!D19/SUM(wSUP!$C19:$DB19),0) -> 0 | E19: =IF(SUM(wSUP!$C19:$DB19),$A19*wSUP!E19/SUM(wSUP!$C19:$DB19),0) -> 0 | F19: =IF(SUM(wSUP!$C19:$DB19),$A19*wSUP!F19/SUM(wSUP!$C19:$DB19),0) -> 0 | G19: =IF(SUM(wSUP!$C19:$DB19),$A19*wSUP!G19/SUM(wSUP!$C19:$DB19),0) -> 0 | H19: =IF(SUM(wSUP!$C19:$DB19),$A19*wSUP!H19/SUM(wSUP!$C19:$DB19),0) -> 0 | I19: =IF(SUM(wSUP!$C19:$DB19),$A19*wSUP!I19/SUM(wSUP!$C19:$DB19),0) -> 0 | J19: =IF(SUM(wSUP!$C19:$DB19),$A19*wSUP!J19/SUM(wSUP!$C19:$DB19),0) -> 0 | ... DB19: =IF(SUM(wSUP!$C19:$DB19),$A19*wSUP!DB19/SUM(wSUP!$C19:$DB19),0) -> 0
A20: 81.996625 | B20: abanb | C20: =IF(SUM(wSUP!$C20:$DB20),$A20*wSUP!C20/SUM(wSUP!$C20:$DB20),0) -> 0 | D20: =IF(SUM(wSUP!$C20:$DB20),$A20*wSUP!D20/SUM(wSUP!$C20:$DB20),0) -> 0 | E20: =IF(SUM(wSUP!$C20:$DB20),$A20*wSUP!E20/SUM(wSUP!$C20:$DB20),0) -> 0 | F20: =IF(SUM(wSUP!$C20:$DB20),$A20*wSUP!F20/SUM(wSUP!$C20:$DB20),0) -> 0 | G20: =IF(SUM(wSUP!$C20:$DB20),$A20*wSUP!G20/SUM(wSUP!$C20:$DB20),0) -> 0 | H20: =IF(SUM(wSUP!$C20:$DB20),$A20*wSUP!H20/SUM(wSUP!$C20:$DB20),0) -> 0 | I20: =IF(SUM(wSUP!$C20:$DB20),$A20*wSUP!I20/SUM(wSUP!$C20:$DB20),0) -> 0 | J20: =IF(SUM(wSUP!$C20:$DB20),$A20*wSUP!J20/SUM(wSUP!$C20:$DB20),0) -> 0 | ... DB20: =IF(SUM(wSUP!$C20:$DB20),$A20*wSUP!DB20/SUM(wSUP!$C20:$DB20),0) -> 0
... A111: 0 | B111: atrdc | C111: =IF(SUM(wSUP!$C111:$DB111),$A111*wSUP!C111/SUM(wSUP!$C111:$DB111),0) -> 0 | D111: =IF(SUM(wSUP!$C111:$DB111),$A111*wSUP!D111/SUM(wSUP!$C111:$DB111),0) -> 0 | E111: =IF(SUM(wSUP!$C111:$DB111),$A111*wSUP!E111/SUM(wSUP!$C111:$DB111),0) -> 0 | F111: =IF(SUM(wSUP!$C111:$DB111),$A111*wSUP!F111/SUM(wSUP!$C111:$DB111),0) -> 0 | G111: =IF(SUM(wSUP!$C111:$DB111),$A111*wSUP!G111/SUM(wSUP!$C111:$DB111),0) -> 0 | H111: =IF(SUM(wSUP!$C111:$DB111),$A111*wSUP!H111/SUM(wSUP!$C111:$DB111),0) -> 0 | I111: =IF(SUM(wSUP!$C111:$DB111),$A111*wSUP!I111/SUM(wSUP!$C111:$DB111),0) -> 0 | J111: =IF(SUM(wSUP!$C111:$DB111),$A111*wSUP!J111/SUM(wSUP!$C111:$DB111),0) -> 0 | ... DB111: =IF(SUM(wSUP!$C111:$DB111),$A111*wSUP!DB111/SUM(wSUP!$C111:$DB111),0) -> 0

Sheet wMAC
A1: Macro SAM
A2: Workings
C4: mact | D4: mcom | E4: mtrc | F4: mlab | G4: mlnd | H4: mcap | I4: ment | J4: mhhd | K4: mgov | L4: matx | M4: mctx | N4: mdtx | O4: metx | P4: mftx | Q4: mmtx | R4: mstx | S4: mvtx | T4: mxtx | U4: ms-i | V4: mg-i | W4: mstk | X4: mrow | Y4: mtot
B5: mact | D5: =C27 -> 11563.342 | Y5: =SUM(C5:X5) -> 11563.342 | Z5: {=Y5:Y26-TRANSPOSE(C27:X27)} -> 0
B6: mcom | C6: =SUT!O6 -> 4606.6764 | E6: =SUT!P6 -> 1053.7156 | J6: =H34 -> 5676.1316 | K6: =H35 -> 1155 | U6: =H37 -> 1145.1026 | V6: =H38 -> 602.89738 | W6: =H39 -> 86 | X6: =H40 -> 1579.5017 | Y6: =SUM(C6:X6) -> 15905.025 | Z6: -1.3031426
B7: mtrc | D7: =SUT!L6 -> 1053.7156 | Y7: =SUM(C7:X7) -> 1053.7156 | Z7: 0
B8: mlab | C8: =SUM(USE!C112:DB112) -> 3889.2332 | X8: =S36 -> 6.4095461 | Y8: =SUM(C8:X8) -> 3895.6427 | Z8: 0
B9: mlnd | C9: =SUM(USE!C113:DB113) -> 575.64093 | X9: =S37 -> 0 | Y9: =SUM(C9:X9) -> 575.64093 | Z9: 0
B10: mcap | C10: =SUM(USE!C114:DB114) -> 2577.1259 | X10: =S38 -> 11.617871 | Y10: =SUM(C10:X10) -> 2588.7438 | Z10: 0
B11: ment | H11: =Y10-SUM(H12:H26) -> 2357.6183 | K11: =O35 -> 89.798979 | X11: =S40 -> 64.853888 | Y11: =SUM(C11:X11) -> 2512.2712 | Z11: 0
B12: mhhd | F12: =Y8-SUM(F13:F26) -> 3865.4278 | G12: =Y9-SUM(G13:G26) -> 575.64093 | I12: =Y11-SUM(I13:I26) -> 2032.1044 | K12: =O36 -> 252.04027 | X12: =S39 -> 172.61254 | Y12: =SUM(C12:X12) -> 6897.8259 | Z12: 0
B13: mgov | F13: =L46 -> 0 | G13: =L47 -> 0 | H13: =L48 -> 0 | I13: =L50 -> 69.912831 | J13: =L49 -> 196.14963 | L13: {=TRANSPOSE(Y14:Y22)} -> -85.334627 | M13: 99.754257 | N13: 479.15296 | O13: 0 | P13: 1.1773436 | Q13: 64.958051 | R13: -30.138079 | S13: 397.41341 | T13: 206.88431 | X13: =L51 -> 345.44355 | Y13: =SUM(C13:X13) -> 1745.3736 | Z13: 0
B14: matx | C14: =L39 -> -85.334627 | Y14: =SUM(C14:X14) -> -85.334627 | Z14: 0
B15: mctx | D15: =L40 -> 99.754257 | Y15: =SUM(C15:X15) -> 99.754257 | Z15: 0
B16: mdtx | I16: =L35 -> 163.58467 | J16: =L34 -> 315.56829 | Y16: =SUM(C16:X16) -> 479.15296 | Z16: 0
B17: metx | D17: =L41 -> 0 | Y17: =SUM(C17:X17) -> 0 | Z17: 0
B18: mftx | F18: =L36 -> 0 | G18: =L37 -> 0 | H18: =L38 -> 1.1773436 | Y18: =SUM(C18:X18) -> 1.1773436 | Z18: 0
B19: mmtx | D19: =L42 -> 64.958051 | Y19: =SUM(C19:X19) -> 64.958051 | Z19: 0
B20: mstx | D20: =L43 -> -30.138079 | Y20: =SUM(C20:X20) -> -30.138079 | Z20: 0
B21: mvtx | D21: =L44 -> 397.41341 | Y21: =SUM(C21:X21) -> 397.41341 | Z21: 0
B22: mxtx | D22: =L45 -> 206.88431 | Y22: =SUM(C22:X22) -> 206.88431 | Z22: 0
B23: ms-i | I23: =I29*Y11 -> 240.9268 | J23: =Y12-SUM(J5:J22,J25:J26) -> 661.78914 | K23: =O51 -> 205.20133 | X23: =S42 -> 727.38587 | Y23: =SUM(C23:X23) -> 1835.3031 | Z23: 1.3031426
B24: mg-i | U24: =V27 -> 602.89738 | Y24: =SUM(C24:X24) -> 602.89738 | Z24: 0
B25: mstk | U25: =W27 -> 86 | Y25: =SUM(C25:X25) -> 86 | Z25: 0
B26: mrow | D26: =H43 -> 2550.3991 | F26: =V36 -> 30.214969 | G26: =V37 -> 0 | H26: =V38 -> 229.94813 | I26: =V40 -> 5.7424353 | J26: =V39 -> 48.187291 | K26: =O37 -> 43.333063 | Y26: =SUM(C26:X26) -> 2907.825 | Z26: 0
B27: mtot | C27: =SUM(C5:C26) -> 11563.342 | D27: =SUM(D5:D26) -> 15906.328 | E27: =SUM(E5:E26) -> 1053.7156 | F27: =SUM(F5:F26) -> 3895.6427 | G27: =SUM(G5:G26) -> 575.64093 | H27: =SUM(H5:H26) -> 2588.7438 | I27: =SUM(I5:I26) -> 2512.2712 | J27: =SUM(J5:J26) -> 6897.8259 | ... X27: =SUM(X5:X26) -> 2907.825
H29: Exogenous savings rate | I29: 0.0959 | J29: =J23/J27 -> 0.0959417
C31: National accounts | J31: Government account | Q31: Current account
C32: Receipts | F32: Payments | J32: Revenues | M32: Expenditures | Q32: Receipts | T32: Payments
D33: Orig. | E33: Used | G33: Orig. | H33: Used | K33: Orig. | L33: Used | N33: Orig. | O33: Used | R33: Orig. | S33: Used | U33: Orig. | V33: Used
C34: GDPfc | D34: =wGDPp!D7 -> 7042 | E34: =E52 -> 7040.6969 | F34: Private consumption | G34: =wGDPe!D7 -> 5676 | H34: =E46-SUM(H35:H36,H39:H40)+H43 -> 5676.1316 | J34: Personal tax | K34: =wGFS!C13 -> 315.56829 | L34: =K34 -> 315.56829 | M34: Consumption | N34: =wGFS!E13 -> 1215.3441 | O34: =H35 -> 1155 | Q34: Export goods | R34: =wBOP!C11 -> 865.17623 | S34: =IF(H41<>0,H41,R34/SUM($R$34:$R$35)*$H$40) -> 883.21671 | T34: Import goods | U34: =wBOP!E11 -> 1675.0046 | V34: =IF(H44<>0,H44,U34/SUM($U$34:$U$35)*$H$43) -> 1981.2242
C35: Indirect taxes | D35: =wGDPp!K4 -> 654 | E35: =E53 -> 653.53732 | F35: Government consumption | G35: =wGDPe!D8 -> 1155 | H35: =G35 -> 1155 | J35: Corporate tax | K35: =wGFS!C14 -> 163.58467 | L35: =K35 -> 163.58467 | M35: Households | N35: =wGFS!E14 -> 89.798979 | O35: =N35 -> 89.798979 | Q35: Export services | R35: =wBOP!C12 -> 717.97643 | S35: =IF(H42<>0,H42,R35/SUM($R$34:$R$35)*$H$40) -> 696.28499 | T35: Import services | U35: =wBOP!E12 -> 878.28523 | V35: =IF(H45<>0,H45,U35/SUM($U$34:$U$35)*$H$43) -> 569.17484
F36: Gross fixed capital formation | G36: =wGDPe!D9 -> 1748 | H36: =G36 -> 1748 | J36: Labor tax | K36: =wGFS!C15 -> 0 | L36: =K36 -> 0 | M36: Enterprises | N36: =wGFS!E15 -> 252.04027 | O36: =N36 -> 252.04027 | Q36: Labor | R36: =wBOP!C13 -> 6.4095461 | S36: =R36 -> 6.4095461 | T36: Labor | U36: =wBOP!E13 -> 30.214969 | V36: =U36 -> 30.214969
F37: Private | H37: =H36-H38 -> 1145.1026 | J37: Land tax | K37: =wGFS!C16 -> 0 | L37: =K37 -> 0 | M37: Rest of world | N37: =wGFS!E16 -> 43.333063 | O37: =N37 -> 43.333063 | Q37: Land | R37: =wBOP!C14 -> 0 | S37: =R37 -> 0 | T37: Land | U37: =wBOP!E14 -> 0 | V37: =U37 -> 0
F38: Public | H38: =O56 -> 602.89738 | J38: Capital tax | K38: =wGFS!C17 -> 1.1773436 | L38: =K38 -> 1.1773436 | N38: =wGFS!E17 -> 0 | Q38: Capital | R38: =wBOP!C15 -> 11.617871 | S38: =R38 -> 11.617871 | T38: Capital | U38: =wBOP!E15 -> 229.94813 | V38: =U38 -> 229.94813
F39: Changes in inventories | G39: =wGDPe!D10 -> 86 | H39: =G39 -> 86 | J39: Subsidies (production) | K39: =wGFS!C18 -> -91.129877 | L39: =K39/SUM($K$39:$K$45)*$E$35 -> -85.334627 | N39: =wGFS!E18 -> 0 | Q39: Households | R39: =wBOP!C16 -> 172.61254 | S39: =R39 -> 172.61254 | T39: Households | U39: =wBOP!E16 -> 48.187291 | V39: =U39 -> 48.187291
F40: Exports | G40: =wGDPe!D11 -> 1580 | H40: =SUM(H41:H42) -> 1579.5017 | J40: Customs duties | K40: =wGFS!C19 -> 106.52877 | L40: =K40/SUM($K$39:$K$45)*$E$35 -> 99.754257 | N40: =wGFS!E19 -> 0 | Q40: Enterprises | R40: =wBOP!C17 -> 64.853888 | S40: =R40 -> 64.853888 | T40: Enterprises | U40: =wBOP!E17 -> 5.7424353 | V40: =U40 -> 5.7424353
F41: Goods | G41: =wGDPe!D12 -> 866 | H41: =G56 -> 883.21671 | J41: Exports | K41: =wGFS!C20 -> 0 | L41: =K41/SUM($K$39:$K$45)*$E$35 -> 0 | N41: =wGFS!E20 -> 0 | Q41: Government | R41: =wBOP!C18 -> 340.53676 | S41: =L51 -> 345.44355 | T41: Government | U41: =wBOP!E18 -> 28.172423 | V41: =O37 -> 43.333063
F42: Services | G42: =wGDPe!D13 -> 714 | H42: =G57 -> 696.28499 | J42: Import excise duties | K42: =wGFS!C21 -> 69.369485 | L42: =K42/SUM($K$39:$K$45)*$E$35 -> 64.958051 | N42: =wGFS!E21 -> 0 | Q42: Balance | R42: =wBOP!C19 -> 716.37178 | S42: =V43-SUM(S34:S41) -> 727.38587
F43: Imports | G43: =wGDPe!D14 -> 2550 | H43: =SUM(H44:H45) -> 2550.3991 | J43: Subsidies (products) | K43: =wGFS!C22 -> -32.184818 | L43: =K43/SUM($K$39:$K$45)*$E$35 -> -30.138079 | N43: =wGFS!E22 -> 0 | Q43: Total | R43: =SUM(R34:R42) -> 2895.5551 | S43: =SUM(S34:S42) -> 2907.825 | T43: Total | U43: =SUM(U34:U42) -> 2895.5551 | V43: =SUM(V34:V42) -> 2907.825
F44: Goods | G44: =wGDPe!D15 -> 1672 | H44: =G59 -> 1981.2242 | J44: VAT | K44: =wGFS!C23 -> 424.40257 | L44: =K44/SUM($K$39:$K$45)*$E$35 -> 397.41341 | N44: =wGFS!E23 -> 0 | T44: Difference | U44: =U43-R43 -> 0 | V44: =V43-S43 -> 0
F45: Services | G45: =wGDPe!D16 -> 878 | H45: =G60 -> 569.17484 | J45: Excise & Others | K45: =wGFS!C24 -> 220.93425 | L45: =K45/SUM($K$39:$K$45)*$E$35 -> 206.88431 | N45: =wGFS!E24 -> 0
C46: Total | D46: =SUM(D34:D45) -> 7696 | E46: =SUM(E34:E45) -> 7694.2342 | F46: Total | G46: =SUM(G34:G40)-G43 -> 7695 | H46: =SUM(H34:H36,H39:H40)-H43 -> 7694.2342 | J46: Labor | K46: =wGFS!C25 -> 0 | L46: =K46 -> 0 | N46: =wGFS!E25 -> 0
F47: Difference | G47: =G46-D46 -> -1 | H47: =H46-E46 -> 0 | J47: Land | K47: =wGFS!C26 -> 0 | L47: =K47 -> 0 | N47: =wGFS!E26 -> 0
J48: Capital | K48: =wGFS!C27 -> 0 | L48: =K48 -> 0 | N48: =wGFS!E27 -> 0
D49: Supply-Use Table, 2017 | J49: Households | K49: =wGFS!C28 -> 196.14963 | L49: =K49 -> 196.14963 | N49: =wGFS!E28 -> 0
D50: Receipts | F50: Payments | J50: Enterprises | K50: =wGFS!C29 -> 69.912831 | L50: =K50 -> 69.912831 | N50: =wGFS!E29 -> 0
E51: Orig. | G51: Orig. | J51: Rest of world | K51: =wGFS!C30 -> 345.44355 | L51: =K51 -> 345.44355 | M51: Savings | N51: =wGFS!E30 -> 189.24024 | O51: =L52-SUM(O34:O50) -> 205.20133 | V51: exp | W51: exp | X51: exp | Y51: exp | Z51: inc | AA51: inc
D52: GDPfc | E52: 7040.6969 | F52: Household Final Consumption Expenditure | G52: 5438.5455 | J52: Total | K52: =SUM(K34:K51) -> 1789.7567 | L52: =SUM(L34:L51) -> 1745.3736 | M52: Total | N52: =SUM(N34:N51) -> 1789.7567 | O52: =SUM(O34:O51) -> 1745.3736 | V52: hhd | W52: gov | X52: ftax | Y52: row | Z52: gov | AA52: row
D53: Indirect taxes | E53: 653.53732 | F53: General Government and NGO Final Consumption Expenditure | G53: 1429.3238 | M53: Difference | N53: =N52-K52 -> -5.0044946e-10 | O53: =O52-L52 -> 0 | U53: mlab | V53: =F12/$F$27 -> 0.99224391 | W53: =F13/$F$27 -> 0 | X53: =F18/$F$27 -> 0 | Y53: =F26/$F$27 -> 0.0077560934 | Z53: =K8/$Y8 -> 0 | AA53: =X8/$Y8 -> 0.0016453116
F54: Gross capital formation | G54: 1797.2623 | U54: mlnd | V54: =G12/$G$27 -> 1 | W54: =G13/$G$27 -> 0 | X54: =G18/$G$27 -> 0 | Y54: =G26/$G$27 -> 0 | Z54: =K9/$Y9 -> 0 | AA54: =X9/$Y9 -> 0
F55: Exports of Goods & Services | G55: 1579.5017 | N55: Orig. | O55: Used | U55: mcap | V55: =H12/$H$27 -> 0 | W55: =H13/$H$27 -> 0 | X55: =H18/$H$27 -> 0.00045479342 | Y55: =H26/$H$27 -> 0.088826144 | Z55: =K10/$Y10 -> 0 | AA55: =X10/$Y10 -> 0.0044878414
F56: Goods | G56: =G55-G57 -> 883.21671 | M56: Public investment level | N56: =wGFS!B36 -> 602.89738 | O56: =N56 -> 602.89738
F57: Services | G57: 696.28499
F58: Imports of Goods & Services | G58: 2550.3991
F59: Goods | G59: =G58-G60 -> 1981.2242 | S59: inc | T59: inc | U59: inc | V59: inc | W59: exp | X59: exp | Y59: exp | Z59: exp | AA59: exp
F60: Services | G60: 569.17484 | S60: fac | T60: ent | U60: gov | V60: row | W60: con | X60: gov | Y60: dtax | Z60: s-i | AA60: row
D61: Total | E61: =SUM(E52:E60) -> 7694.2342 | F61: Total | G61: =SUM(G52:G55)-G58 -> 7694.2342 | R61: mhhd | S61: =Y12-SUM(T61:V61) -> 4441.0687 | T61: =I12 -> 2032.1044 | U61: =K12 -> 252.04027 | V61: =X12 -> 172.61254 | W61: =J6 -> 5676.1316 | X61: =J13 -> 196.14963 | Y61: =J16 -> 315.56829 | Z61: =J23 -> 661.78914 | AA61: =J26 -> 48.187291
F62: Difference | G62: =G61-E61 -> 1.0004442e-11 | S62: =S61/SUM($S$61:$V$61) -> 0.64383601 | T62: =T61/SUM($S$61:$V$61) -> 0.29460071 | U62: =U61/SUM($S$61:$V$61) -> 0.036539088 | V62: =V61/SUM($S$61:$V$61) -> 0.025024195 | W62: =W61/SUM($W$61:$AA$61) -> 0.82288704 | X62: =X61/SUM($W$61:$AA$61) -> 0.028436442 | Y62: =Y61/SUM($W$61:$AA$61) -> 0.04574895 | Z62: =Z61/SUM($W$61:$AA$61) -> 0.0959417 | AA62: =AA61/SUM($W$61:$AA$61) -> 0.0069858665

Sheet wBOP
A1: Balance of Payments
A2: Workings | F2: `
G3: =B4 -> 2017 | I3: 2010 | J3: 2011 | K3: 2012 | L3: 2013 | M3: 2014 | N3: 2015 | O3: 2016 | P3: 2017 | Q3: 2018 | R3: 2019 | S3: 2020 | T3: 2021 | U3: 2022 | V3: 2023 | W3: 2024 | X3: 2025
B4: =Notes!B5 -> 2017 | C4: Year | G4: =SUMIF($I$3:$X$3,$G$3,$I$4:$X$4) -> 831.53 | H4: Exchange rate (RwF/USD) | I4: 583.13 | J4: 600.31 | K4: 614.3 | L4: 646.64 | M4: 681.86 | N4: 720.98 | O4: 787.25 | P4: 831.53 | Q4: 861.09
B5: 0.001 | C5: Scaling (multiplier)
B6: =G4 -> 831.53 | C6: Exchange rate | H6: Rwanda: Balance of Payments Standard Presentation
H7: Millions of U.S. Dollars
H8: https://www.bnr.rw/browse-in/statistics/external-sector-statistics/
I9: =IF(ISERR(LEFT(I10,4)/1),"",LEFT(I10,4)/1) -> 2010 | J9: =IF(ISERR(LEFT(J10,4)/1),"",LEFT(J10,4)/1) -> 2011 | K9: =IF(ISERR(LEFT(K10,4)/1),"",LEFT(K10,4)/1) -> 2012 | L9: =IF(ISERR(LEFT(L10,4)/1),"",LEFT(L10,4)/1) -> 2013 | M9: =IF(ISERR(LEFT(M10,4)/1),"",LEFT(M10,4)/1) -> 2014 | N9: =IF(ISERR(LEFT(N10,4)/1),"",LEFT(N10,4)/1) -> 2015 | O9: =IF(ISERR(LEFT(O10,4)/1),"",LEFT(O10,4)/1) -> 2016 | P9: =IF(ISERR(LEFT(P10,4)/1),"",LEFT(P10,4)/1) -> 2017 | ... AU9: =IF(ISERR(LEFT(AU10,4)/1),"",LEFT(AU10,4)/1)
B10: Receipts | D10: Payments | G10: =B4 -> 2017 | I10: 2010 | J10: 2011 | K10: 2012 | L10: 2013 | M10: 2014 | N10: 2015 | O10: 2016 | P10: 2017Q1 | Q10: 2017Q2 | R10: 2017Q3 | S10: 2017Q4 | T10: 2018Q1 | U10: 2018Q2 | V10: 2018Q3 | W10: 2018Q4 | X10: 2019Q1 | Y10: 2019Q2 | Z10: 2019Q3 | AA10: 2019Q4 | AB10: 2020Q1 | AC10: 2020Q2
B11: Export goods | C11: =G18 -> 865.17623 | D11: Import goods | E11: =G19 -> 1675.0046 | G11: =SUMIF($I$9:$AU$9,G$10,$I11:$AU11)*$G$4*$B$5 -> -716.37178 | H11: Current account | I11: -399.14244 | J11: -477.01051 | K11: -741.01596 | L11: -585.10561 | M11: -934.6195 | N11: -1083.6715 | O11: -1330.8224 | P11: -228.63633 | Q11: -186.39793 | R11: -251.98705 | S11: -194.48914 | T11: -280.72792 | U11: -225.60469 | V11: -202.27277 | W11: -270.90445 | X11: -275.24323 | Y11: -357.0171 | Z11: -342.57241 | AA11: -278.90948 | AB11: -419.57532 | AC11: -280.33188
B12: Export services | C12: =G27 -> 717.97643 | D12: Import services | E12: =G28 -> 878.28523 | G12: =SUMIF($I$9:$AU$9,G$10,$I12:$AU12)*$G$4*$B$5 -> 2179.1833 | H12: Credit | I12: 1356.1006 | J12: 1845.7334 | K12: 1841.6682 | L12: 2131.8792 | M12: 2006.8038 | N12: 2075.4025 | O12: 2138.3967 | P12: 558.48411 | Q12: 653.86231 | R12: 683.39402 | S12: 724.95065 | T12: 647.27323 | U12: 666.65626 | V12: 776.29843 | W12: 723.78899 | X12: 658.57486 | Y12: 649.84801 | Z12: 784.95347 | AA12: 830.20898 | AB12: 652.54253 | AC12: 514.87885
B13: Labor | C13: =G87 -> 6.4095461 | D13: Labor | E13: =G88 -> 30.214969 | G13: =SUMIF($I$9:$AU$9,G$10,$I13:$AU13)*$G$4*$B$5 -> 2895.5551 | H13: Debit | I13: 1755.243 | J13: 2322.7439 | K13: 2582.6841 | L13: 2716.9848 | M13: 2941.4233 | N13: 3159.074 | O13: 3469.219 | P13: 787.12044 | Q13: 840.26024 | R13: 935.38107 | S13: 919.43979 | T13: 928.00115 | U13: 892.26095 | V13: 978.5712 | W13: 994.69345 | X13: 933.81809 | Y13: 1006.8651 | Z13: 1127.5259 | AA13: 1109.1185 | AB13: 1072.1178 | AC13: 795.21073
B14: Land | D14: Land | G14: =SUMIF($I$9:$AU$9,G$10,$I14:$AU14)*$G$4*$B$5 -> -970.13715 | H14: Goods and services | I14: -941.10324 | J14: -1224.7229 | K14: -1253.8153 | L14: -1154.6482 | M14: -1325.2429 | N14: -1489.7128 | O14: -1539.5993 | P14: -281.676 | Q14: -274.05727 | R14: -324.33402 | S14: -286.622 | T14: -347.59872 | U14: -276.2825 | V14: -297.68464 | W14: -377.62723 | X14: -335.35322 | Y14: -381.04758 | Z14: -396.10287 | AA14: -377.75982 | AB14: -478.51934 | AC14: -377.53732
B15: Capital | C15: =G90 -> 11.617871 | D15: Capital | E15: =G91 -> 229.94813 | G15: =SUMIF($I$9:$AU$9,G$10,$I15:$AU15)*$G$4*$B$5 -> 1583.1527 | H15: Credit | I15: 702.72842 | J15: 953.28799 | K15: 1120.3809 | L15: 1298.832 | M15: 1328.2776 | N15: 1449.0252 | O15: 1516.6459 | P15: 425.1013 | Q15: 466.64141 | R15: 491.13054 | S15: 521.02998 | T15: 468.49011 | U15: 495.3209 | V15: 574.35979 | W15: 505.08566 | X15: 481.15911 | Y15: 512.25048 | Z15: 622.77711 | AA15: 630.59644 | AB15: 498.46569 | AC15: 356.21443
B16: Households | C16: =G129 -> 172.61254 | D16: Households | E16: =G130 -> 48.187291 | G16: =SUMIF($I$9:$AU$9,G$10,$I16:$AU16)*$G$4*$B$5 -> 2553.2898 | H16: Debit | I16: 1643.8317 | J16: 2178.0108 | K16: 2374.1961 | L16: 2453.4802 | M16: 2653.5206 | N16: 2938.738 | O16: 3056.2452 | P16: 706.7773 | Q16: 740.69868 | R16: 815.46456 | S16: 807.65199 | T16: 816.08883 | U16: 771.60341 | V16: 872.04443 | W16: 882.71289 | X16: 816.51233 | Y16: 893.29806 | Z16: 1018.88 | AA16: 1008.3563 | AB16: 976.98503 | AC16: 733.75175
B17: Enterprises | C17: =G135 -> 64.853888 | D17: Enterprises | E17: =G136 -> 5.7424353 | G17: =SUMIF($I$9:$AU$9,G$10,$I17:$AU17)*$G$4*$B$5 -> -809.82834 | H17: Goods | I17: -786.69823 | J17: -1104.8407 | K17: -1273.698 | L17: -1150.7782 | M17: -1268.5694 | N17: -1236.6056 | O17: -1294.1432 | P17: -243.92757 | Q17: -240.92931 | R17: -247.81955 | S17: -241.2251 | T17: -268.93842 | U17: -243.35249 | V17: -302.39128 | W17: -340.90782 | X17: -303.02834 | Y17: -378.44714 | Z17: -396.40056 | AA17: -394.94548 | AB17: -441.25589 | AC17: -366.49477
B18: Government | C18: =G123 -> 340.53676 | D18: Government | E18: =G124 -> 28.172423 | G18: =SUMIF($I$9:$AU$9,G$10,$I18:$AU18)*$G$4*$B$5 -> 865.17623 | H18: Credit | I18: 297.27526 | J18: 464.2351 | K18: 590.75048 | L18: 703.01008 | M18: 723.0906 | N18: 682.04487 | O18: 726.6109 | P18: 223.62202 | Q18: 255.20577 | R18: 277.62813 | S18: 284.00712 | T18: 280.82884 | U18: 290.33357 | V18: 285.83251 | W18: 272.63106 | X18: 255.77903 | Y18: 287.40533 | Z18: 331.33986 | AA18: 357.28585 | AB18: 317.6034 | AC18: 279.34182
B19: Balance | C19: =-G11 -> 716.37178 | G19: =SUMIF($I$9:$AU$9,G$10,$I19:$AU19)*$G$4*$B$5 -> 1675.0046 | H19: Debit | I19: 1083.9735 | J19: 1569.0758 | K19: 1864.4485 | L19: 1853.7883 | M19: 1991.66 | N19: 1918.6505 | O19: 2020.7541 | P19: 467.54959 | Q19: 496.13509 | R19: 525.44769 | S19: 525.23221 | T19: 549.76726 | U19: 533.68606 | V19: 588.22379 | W19: 613.53888 | X19: 558.80737 | Y19: 665.85247 | Z19: 727.74042 | AA19: 752.23132 | AB19: 758.85929 | AC19: 645.83659
B20: Total | C20: =SUM(C11:C19) -> 2895.5551 | D20: Total | E20: =SUM(E11:E19) -> 2895.5551 | G20: =SUMIF($I$9:$AU$9,G$10,$I20:$AU20)*$G$4*$B$5 -> -885.08181 | H20: General merchandise on a balance of payments basis | I20: -786.69823 | J20: -1104.8407 | K20: -1273.698 | L20: -1150.7782 | M20: -1268.5694 | N20: -1236.6056 | O20: -1294.1432 | P20: -266.55257 | Q20: -263.55432 | R20: -270.44455 | S20: -263.8501 | T20: -287.34183 | U20: -261.7559 | V20: -320.79469 | W20: -359.31123 | X20: -316.88921 | Y20: -386.24798 | Z20: -403.84434 | AA20: -402.86639 | AB20: -440.94998 | AC20: -346.36419
D21: Difference | E21: =E20-C20 -> 0 | G21: =SUMIF($I$9:$AU$9,G$10,$I21:$AU21)*$G$4*$B$5 -> 789.92276 | H21: Credit | I21: 297.27526 | J21: 464.2351 | K21: 590.75048 | L21: 703.01008 | M21: 723.0906 | N21: 682.04487 | O21: 726.6109 | P21: 200.99702 | Q21: 232.58077 | R21: 255.00313 | S21: 261.38212 | T21: 262.42543 | U21: 271.93016 | V21: 267.4291 | W21: 254.22765 | X21: 241.91816 | Y21: 279.60449 | Z21: 212.49777 | AA21: 221.41603 | AB21: 210.41226 | AC21: 142.28026
G22: =SUMIF($I$9:$AU$9,G$10,$I22:$AU22)*$G$4*$B$5 -> 1675.0046 | H22: Debit | I22: 1083.9735 | J22: 1569.0758 | K22: 1864.4485 | L22: 1853.7883 | M22: 1991.66 | N22: 1918.6505 | O22: 2020.7541 | P22: 467.54959 | Q22: 496.13509 | R22: 525.44769 | S22: 525.23221 | T22: 549.76726 | U22: 533.68606 | V22: 588.22379 | W22: 613.53888 | X22: 558.80737 | Y22: 665.85247 | Z22: 616.34211 | AA22: 624.28242 | AB22: 651.36223 | AC22: 488.64445
G23: =SUMIF($I$9:$AU$9,G$10,$I23:$AU23)*$G$4*$B$5 -> 75.253468 | H23: Nonmonetary gold | I23: 0 | J23: 0 | K23: 0 | L23: 0 | M23: 0 | N23: 0 | O23: 0 | P23: 22.625 | Q23: 22.625004 | R23: 22.625 | S23: 22.625 | T23: 18.40341 | U23: 18.40341 | V23: 18.40341 | W23: 18.40341 | X23: 13.860868 | Y23: 7.8008382 | Z23: 7.4437794 | AA23: 7.9209139 | AB23: -0.30591755 | AC23: -20.130576
G24: =SUMIF($I$9:$AU$9,G$10,$I24:$AU24)*$G$4*$B$5 -> 75.253468 | H24: Credit | I24: 0 | J24: 0 | K24: 0 | L24: 0 | M24: 0 | N24: 0 | O24: 0 | P24: 22.625 | Q24: 22.625004 | R24: 22.625 | S24: 22.625 | T24: 18.40341 | U24: 18.40341 | V24: 18.40341 | W24: 18.40341 | X24: 13.860868 | Y24: 7.8008382 | Z24: 118.84209 | AA24: 135.86982 | AB24: 107.19114 | AC24: 137.06156
D25: Exports | E25: Imports | G25: =SUMIF($I$9:$AU$9,G$10,$I25:$AU25)*$G$4*$B$5 -> 0 | H25: Debit | I25: 0 | J25: 0 | K25: 0 | L25: 0 | M25: 0 | N25: 0 | O25: 0 | P25: 0 | Q25: 0 | R25: 0 | S25: 0 | T25: 0 | U25: 0 | V25: 0 | W25: 0 | X25: 0 | Y25: 0 | Z25: 111.39831 | AA25: 127.94891 | AB25: 107.49706 | AC25: 157.19213
B26: Services | D26: =wBOP!G27 -> 717.97643 | E26: =wBOP!G28 -> 878.28523 | G26: =SUMIF($I$9:$AU$9,G$10,$I26:$AU26)*$G$4*$B$5 -> -160.30881 | H26: Services | I26: -154.40501 | J26: -119.88218 | K26: 19.882714 | L26: -3.8700177 | M26: -56.673531 | N26: -253.10725 | O26: -245.45603 | P26: -37.748435 | Q26: -33.127954 | R26: -76.514467 | S26: -45.396907 | T26: -78.660303 | U26: -32.93001 | V26: 4.7066394 | W26: -36.719411 | X26: -32.324875 | Y26: -2.6004335 | Z26: 0.29769607 | AA26: 17.185654 | AB26: -37.263447 | AC26: -11.04255
B27: Manufacturing services on physical inputs owned by others | D27: =wBOP!G30 -> 0 | E27: =wBOP!G31 -> 0 | G27: =SUMIF($I$9:$AU$9,G$10,$I27:$AU27)*$G$4*$B$5 -> 717.97643 | H27: Credit | I27: 405.45316 | J27: 489.0529 | K27: 529.63038 | L27: 595.82191 | M27: 605.18705 | N27: 766.9803 | O27: 790.03502 | P27: 201.47928 | Q27: 211.43564 | R27: 213.50241 | S27: 237.02287 | T27: 187.66126 | U27: 204.98734 | V27: 288.52728 | W27: 232.45459 | X27: 225.38008 | Y27: 224.84515 | Z27: 291.43725 | AA27: 273.31059 | AB27: 180.86229 | AC27: 76.872609
B28: Maintenance and repair services n.i.e. | D28: =wBOP!G33 -> 0.48532707 | E28: =wBOP!G34 -> 30.76661 | G28: =SUMIF($I$9:$AU$9,G$10,$I28:$AU28)*$G$4*$B$5 -> 878.28523 | H28: Debit | I28: 559.85817 | J28: 608.93507 | K28: 509.74766 | L28: 599.69192 | M28: 661.86058 | N28: 1020.0875 | O28: 1035.4911 | P28: 239.22772 | Q28: 244.56359 | R28: 290.01688 | S28: 282.41977 | T28: 266.32157 | U28: 237.91735 | V28: 283.82064 | W28: 269.17401 | X28: 257.70495 | Y28: 227.44559 | Z28: 291.13955 | AA28: 256.12494 | AB28: 218.12574 | AC28: 87.915159
B29: Transport | D29: =wBOP!G36 -> 117.57192 | E29: =wBOP!G37 -> 386.6764 | G29: =SUMIF($I$9:$AU$9,G$10,$I29:$AU29)*$G$4*$B$5 -> 0 | H29: Manufacturing services on physical inputs owned by others | I29: 0 | J29: 0 | K29: 0 | L29: 0 | M29: 0 | N29: 0 | O29: 0 | P29: 0 | Q29: 0 | R29: 0 | S29: 0 | T29: 0 | U29: 0 | V29: 0 | W29: 0 | X29: 0 | Y29: 0 | Z29: 0 | AA29: 0 | AB29: 0 | AC29: 0
B30: Sea transport | D30: =wBOP!G39 -> 0 | E30: =wBOP!G40 -> 103.90947 | G30: =SUMIF($I$9:$AU$9,G$10,$I30:$AU30)*$G$4*$B$5 -> 0 | H30: Credit | I30: 0 | J30: 0 | K30: 0 | L30: 0 | M30: 0 | N30: 0 | O30: 0 | P30: 0 | Q30: 0 | R30: 0 | S30: 0 | T30: 0 | U30: 0 | V30: 0 | W30: 0 | X30: 0 | Y30: 0 | Z30: 0 | AA30: 0 | AB30: 0 | AC30: 0
B31: Air transport | D31: =wBOP!G42 -> 107.83797 | E31: =wBOP!G43 -> 135.92698 | G31: =SUMIF($I$9:$AU$9,G$10,$I31:$AU31)*$G$4*$B$5 -> 0 | H31: Debit | I31: 0 | J31: 0 | K31: 0 | L31: 0 | M31: 0 | N31: 0 | O31: 0 | P31: 0 | Q31: 0 | R31: 0 | S31: 0 | T31: 0 | U31: 0 | V31: 0 | W31: 0 | X31: 0 | Y31: 0 | Z31: 0 | AA31: 0 | AB31: 0 | AC31: 0
B32: Other modes of transport | D32: =wBOP!G45 -> 5.6080592 | E32: =wBOP!G46 -> 145.82508 | G32: =SUMIF($I$9:$AU$9,G$10,$I32:$AU32)*$G$4*$B$5 -> -30.281283 | H32: Maintenance and repair services n.i.e. | I32: 0 | J32: 0 | K32: 0 | L32: 0 | M32: 0 | N32: -12.376151 | O32: -24.635076 | P32: -9.144444 | Q32: -9.2750654 | R32: -9.5080719 | S32: -8.4887632 | T32: -8.4083187 | U32: -7.5346927 | V32: -8.1860508 | W32: -8.5717558 | X32: -11.519126 | Y32: -9.7815265 | Z32: -9.7371034 | AA32: -10.192696 | AB32: -10.308657 | AC32: -0.98345506
B33: Postal and courier services | D33: =wBOP!G48 -> 4.125886 | E33: =wBOP!G49 -> 1.0148753 | G33: =SUMIF($I$9:$AU$9,G$10,$I33:$AU33)*$G$4*$B$5 -> 0.48532707 | H33: Credit | I33: 0 | J33: 0 | K33: 0 | L33: 0 | M33: 0 | N33: 0.52744227 | O33: 0.082016011 | P33: 0.1118624 | Q33: 0.14260908 | R33: 0.16422982 | S33: 0.16495421 | T33: 0.024672342 | U33: 0.022420899 | V33: 0.016440196 | W33: 0.013779399 | X33: 0.023112864 | Y33: 0.018938339 | Z33: 0.018938339 | AA33: 0.018938339 | AB33: 0.018938339 | AC33: 0.018938339
B34: Travel | D34: =wBOP!G51 -> 316.87432 | E34: =wBOP!G52 -> 308.31565 | G34: =SUMIF($I$9:$AU$9,G$10,$I34:$AU34)*$G$4*$B$5 -> 30.76661 | H34: Debit | I34: 0 | J34: 0 | K34: 0 | L34: 0 | M34: 0 | N34: 12.903593 | O34: 24.717092 | P34: 9.2563064 | Q34: 9.4176745 | R34: 9.6723017 | S34: 8.6537174 | T34: 8.432991 | U34: 7.5571136 | V34: 8.202491 | W34: 8.5855352 | X34: 11.542239 | Y34: 9.8004648 | Z34: 9.7560418 | AA34: 10.211634 | AB34: 10.327595 | AC34: 1.0023934
B35: Business | D35: =wBOP!G54 -> 102.10652 | E35: =wBOP!G55 -> 120.83021 | G35: =SUMIF($I$9:$AU$9,G$10,$I35:$AU35)*$G$4*$B$5 -> -269.10448 | H35: Transport | I35: -321.36418 | J35: -355.02356 | K35: -265.03834 | L35: -309.2022 | M35: -331.49805 | N35: -336.62384 | O35: -345.26668 | P35: -75.424209 | Q35: -79.710236 | R35: -84.770834 | S35: -83.720421 | T35: -76.235262 | U35: -83.671166 | V35: -68.56116 | W35: -78.512648 | X35: -60.446567 | Y35: -69.590008 | Z35: -54.048792 | AA35: -54.362981 | AB35: -49.120674 | AC35: -48.684384
B36: Personal | D36: =wBOP!G57 -> 214.7678 | E36: =wBOP!G58 -> 187.48544 | G36: =SUMIF($I$9:$AU$9,G$10,$I36:$AU36)*$G$4*$B$5 -> 117.57192 | H36: Credit | I36: 29.435849 | J36: 50.718673 | K36: 59.896642 | L36: 75.242378 | M36: 78.078499 | N36: 103.50848 | O36: 98.420414 | P36: 29.18784 | Q36: 33.609928 | R36: 40.298309 | S36: 38.296199 | T36: 37.541296 | U36: 40.489556 | V36: 53.260694 | W36: 52.962392 | X36: 42.866769 | Y36: 46.421673 | Z36: 62.785191 | AA36: 60.770615 | AB36: 53.158299 | AC36: 5.0605103
B37: Construction | D37: =wBOP!G60 -> 28.502981 | E37: =wBOP!G61 -> 13.546988 | G37: =SUMIF($I$9:$AU$9,G$10,$I37:$AU37)*$G$4*$B$5 -> 386.6764 | H37: Debit | I37: 350.80003 | J37: 405.74224 | K37: 324.93498 | L37: 384.44458 | M37: 409.57655 | N37: 440.13232 | O37: 443.68709 | P37: 104.61205 | Q37: 113.32016 | R37: 125.06914 | S37: 122.01662 | T37: 113.77656 | U37: 124.16072 | V37: 121.82185 | W37: 131.47504 | X37: 103.31334 | Y37: 116.01168 | Z37: 116.83398 | AA37: 115.1336 | AB37: 102.27897 | AC37: 53.744895
B38: Insurance and pension services | D38: =wBOP!G63 -> 0.48607194 | E38: =wBOP!G64 -> 7.2448759 | G38: =SUMIF($I$9:$AU$9,G$10,$I38:$AU38)*$G$4*$B$5 -> -103.90947 | H38: Sea transport | I38: -107.47086 | J38: -135.06562 | K38: -102.17333 | L38: -102.38063 | M38: -100.65246 | N38: -133.49028 | O38: -121.43013 | P38: -28.821733 | Q38: -30.597765 | R38: -34.012342 | S38: -31.529939 | T38: -31.886763 | U38: -36.964839 | V38: -36.582526 | W38: -39.852443 | X38: -26.388082 | Y38: -28.071574 | Z38: -30.640515 | AA38: -30.542636 | AB38: -28.439295 | AC38: -20.441232
B39: Financial services | D39: =wBOP!G66 -> 9.8573422 | E39: =wBOP!G67 -> 4.6490926 | G39: =SUMIF($I$9:$AU$9,G$10,$I39:$AU39)*$G$4*$B$5 -> 0 | H39: Credit | I39: 0 | J39: 0 | K39: 0 | L39: 0 | M39: 0 | N39: 0 | O39: 0 | P39: 0 | Q39: 0 | R39: 0 | S39: 0 | T39: 0 | U39: 0 | V39: 0 | W39: 0 | X39: 0 | Y39: 0 | Z39: 0 | AA39: 0 | AB39: 0 | AC39: 0
B40: Charges for the use of intellectual property n.i.e. | D40: =wBOP!G69 -> 0 | E40: =wBOP!G70 -> 0 | G40: =SUMIF($I$9:$AU$9,G$10,$I40:$AU40)*$G$4*$B$5 -> 103.90947 | H40: Debit | I40: 107.47086 | J40: 135.06562 | K40: 102.17333 | L40: 102.38063 | M40: 100.65246 | N40: 133.49028 | O40: 121.43013 | P40: 28.821733 | Q40: 30.597765 | R40: 34.012342 | S40: 31.529939 | T40: 31.886763 | U40: 36.964839 | V40: 36.582526 | W40: 39.852443 | X40: 26.388082 | Y40: 28.071574 | Z40: 30.640515 | AA40: 30.542636 | AB40: 28.439295 | AC40: 20.441232
B41: Telecommunications, computer, and information services | D41: =wBOP!G72 -> 15.462427 | E41: =wBOP!G73 -> 12.066627 | G41: =SUMIF($I$9:$AU$9,G$10,$I41:$AU41)*$G$4*$B$5 -> -28.089004 | H41: Air transport | I41: -60.592229 | J41: -41.680058 | K41: -25.139549 | L41: -69.555734 | M41: -94.976437 | N41: -26.24975 | O41: -63.142972 | P41: -8.6399582 | Q41: -8.9476748 | R41: -5.8410515 | S41: -10.35122 | T41: -1.5586974 | U41: 1.8961618 | V41: 16.60664 | W41: 14.051583 | X41: 11.417649 | Y41: 13.255194 | Z41: 28.781475 | AA41: 28.653341 | AB41: 16.418543 | AC41: -3.406535
B42: Other business services | D42: =wBOP!G75 -> 4.6092284 | E42: =wBOP!G76 -> 25.768485 | G42: =SUMIF($I$9:$AU$9,G$10,$I42:$AU42)*$G$4*$B$5 -> 107.83797 | H42: Credit | I42: 22.872197 | J42: 45.452271 | K42: 54.080403 | L42: 68.3796 | M42: 70.952393 | N42: 94.255962 | O42: 87.312896 | P42: 26.12997 | Q42: 30.552058 | R42: 37.503146 | S42: 35.501035 | T42: 34.325759 | U42: 37.203689 | V42: 50.138568 | W42: 49.912081 | X42: 39.38571 | Y42: 42.867651 | Z42: 58.410323 | AA42: 57.136587 | AB42: 49.450068 | AC42: 3.9933072
B43: Personal, cultural, and recreational services | D43: =wBOP!G78 -> 0 | E43: =wBOP!G79 -> 0 | G43: =SUMIF($I$9:$AU$9,G$10,$I43:$AU43)*$G$4*$B$5 -> 135.92698 | H43: Debit | I43: 83.464425 | J43: 87.132329 | K43: 79.219952 | L43: 137.93533 | M43: 165.92883 | N43: 120.50571 | O43: 150.45587 | P43: 34.769928 | Q43: 39.499733 | R43: 43.344198 | S43: 45.852255 | T43: 35.884456 | U43: 35.307527 | V43: 33.531927 | W43: 35.860498 | X43: 27.968062 | Y43: 29.612457 | Z43: 29.628849 | AA43: 28.483247 | AB43: 33.031525 | AC43: 7.3998422
B44: Government goods and services n.i.e. | D44: =wBOP!G81 -> 224.1268 | E44: =wBOP!G82 -> 89.250507 | G44: =SUMIF($I$9:$AU$9,G$10,$I44:$AU44)*$G$4*$B$5 -> -140.21702 | H44: Other modes of transport | I44: -142.35712 | J44: -178.56877 | K44: -137.69071 | L44: -137.44412 | M44: -136.04743 | N44: -177.2881 | O44: -164.82719 | P44: -39.050309 | Q44: -41.252589 | R44: -45.700304 | S44: -42.622124 | T44: -43.883845 | U44: -49.717644 | V44: -49.364233 | W44: -53.490747 | X44: -46.689099 | Y44: -56.009508 | Z44: -53.059102 | AA44: -53.343036 | AB44: -38.146807 | AC44: -24.937155
G45: =SUMIF($I$9:$AU$9,G$10,$I45:$AU45)*$G$4*$B$5 -> 5.6080592 | H45: Credit | I45: 3.5736523 | J45: 4.4451998 | K45: 4.7609206 | L45: 5.8014955 | M45: 6.0648235 | N45: 6.2667587 | O45: 6.1457173 | P45: 1.7521328 | Q45: 1.7521328 | R45: 1.62 | S45: 1.62 | T45: 1.8546776 | U45: 1.9210659 | V45: 1.8938057 | W45: 1.8219896 | X45: 1.9795916 | Y45: 2.0482081 | Z45: 3.0196341 | AA45: 2.2787943 | AB45: 2.2787943 | AC45: 0.9260601
G46: =SUMIF($I$9:$AU$9,G$10,$I46:$AU46)*$G$4*$B$5 -> 145.82508 | H46: Debit | I46: 145.93077 | J46: 183.01396 | K46: 142.45163 | L46: 143.24562 | M46: 142.11225 | N46: 183.55486 | O46: 170.97291 | P46: 40.802442 | Q46: 43.004722 | R46: 47.320304 | S46: 44.242124 | T46: 45.738523 | U46: 51.63871 | V46: 51.258038 | W46: 55.312736 | X46: 48.66869 | Y46: 58.057716 | Z46: 56.078736 | AA46: 55.62183 | AB46: 40.425602 | AC46: 25.863215
G47: =SUMIF($I$9:$AU$9,G$10,$I47:$AU47)*$G$4*$B$5 -> 3.1110107 | H47: Postal and courier services | I47: -10.943973 | J47: 0.29087723 | K47: -0.034752233 | L47: 0.1782815 | M47: 0.1782815 | N47: 0.40428626 | O47: 4.1336099 | P47: 1.0877921 | Q47: 1.0877921 | R47: 0.78286245 | S47: 0.78286245 | T47: 1.0940428 | U47: 1.115155 | V47: 0.77895829 | W47: 0.77895829 | X47: 1.2129647 | Y47: 1.2358796 | Z47: 0.86935004 | AA47: 0.86935004 | AB47: 1.0468861 | AC47: 0.10053664
G48: =SUMIF($I$9:$AU$9,G$10,$I48:$AU48)*$G$4*$B$5 -> 4.125886 | H48: Credit | I48: 2.99 | J48: 0.82120203 | K48: 1.0553189 | L48: 1.0612829 | M48: 1.0612829 | N48: 2.9857559 | O48: 4.9618006 | P48: 1.305737 | Q48: 1.305737 | R48: 1.1751633 | S48: 1.1751633 | T48: 1.36086 | U48: 1.3648007 | V48: 1.2283206 | W48: 1.2283206 | X48: 1.5014668 | Y48: 1.5058147 | Z48: 1.3552332 | AA48: 1.3552332 | AB48: 1.429437 | AC48: 0.14114295
G49: =SUMIF($I$9:$AU$9,G$10,$I49:$AU49)*$G$4*$B$5 -> 1.0148753 | H49: Debit | I49: 13.933973 | J49: 0.5303248 | K49: 1.0900712 | L49: 0.88300139 | M49: 0.88300139 | N49: 2.5814697 | O49: 0.82819068 | P49: 0.21794491 | Q49: 0.21794491 | R49: 0.39230085 | S49: 0.39230085 | T49: 0.26681714 | U49: 0.24964574 | V49: 0.44936234 | W49: 0.44936234 | X49: 0.28850207 | Y49: 0.26993511 | Z49: 0.48588319 | AA49: 0.48588319 | AB49: 0.38255089 | AC49: 0.04060631
G50: =SUMIF($I$9:$AU$9,G$10,$I50:$AU50)*$G$4*$B$5 -> 8.5586744 | H50: Travel | I50: 124.63889 | J50: 162.61 | K50: 203.22696 | L50: 214.53653 | M50: 219.87447 | N50: 29.851772 | O50: 41.906061 | P50: 7.7839187 | Q50: 16.415857 | R50: 7.6979704 | S50: -21.605064 | T50: -10.32866 | U50: 23.087226 | V50: 13.258746 | W50: 20.816817 | X50: 8.8028568 | Y50: 51.219491 | Z50: 33.827554 | AA50: 28.036365 | AB50: 22.180856 | AC50: -3.141225
G51: =SUMIF($I$9:$AU$9,G$10,$I51:$AU51)*$G$4*$B$5 -> 316.87432 | H51: Credit | I51: 201.64867 | J51: 251.8 | K51: 281.8 | L51: 293.6 | M51: 303.7 | N51: 338.06717 | O51: 363.04845 | P51: 92.625042 | Q51: 99.727521 | R51: 109.56029 | S51: 79.160984 | T51: 88.919855 | U51: 89.950887 | V51: 112.887 | W51: 100.24226 | X51: 98.749969 | Y51: 113.55146 | Z51: 138.59504 | AA51: 107.10353 | AB51: 84.463157 | AC51: 0.96934725
G52: =SUMIF($I$9:$AU$9,G$10,$I52:$AU52)*$G$4*$B$5 -> 308.31565 | H52: Debit | I52: 77.009785 | J52: 89.19 | K52: 78.573037 | L52: 79.06347 | M52: 83.825526 | N52: 308.21539 | O52: 321.14238 | P52: 84.841123 | Q52: 83.311663 | R52: 101.86232 | S52: 100.76605 | T52: 99.248515 | U52: 66.863661 | V52: 99.628257 | W52: 79.425438 | X52: 89.947113 | Y52: 62.331969 | Z52: 104.76748 | AA52: 79.067168 | AB52: 62.282302 | AC52: 4.1105723
G53: =SUMIF($I$9:$AU$9,G$10,$I53:$AU53)*$G$4*$B$5 -> -18.723686 | H53: Business | I53: 42.857265 | J53: 54.839743 | K53: 64.446452 | L53: 57.192079 | M53: 50.522139 | N53: -9.664058 | O53: -18.212682 | P53: -1.7867599 | Q53: -8.7404969 | R53: -10.556466 | S53: -1.4334277 | T53: -1.5171735 | U53: 5.7696025 | V53: 7.3726974 | W53: 5.9678881 | X53: -0.41328101 | Y53: 7.0182208 | Z53: 4.5389773 | AA53: 3.0655282 | AB53: -4.0287198 | AC53: 0
G54: =SUMIF($I$9:$AU$9,G$10,$I54:$AU54)*$G$4*$B$5 -> 102.10652 | H54: Credit | I54: 82.8 | J54: 101.1 | K54: 105.2 | L54: 98.2 | M54: 94 | N54: 104.66521 | O54: 132.65168 | P54: 31.704169 | Q54: 32.29151 | R54: 27.157462 | S54: 31.640414 | T54: 31.115512 | U54: 31.727426 | V54: 34.499923 | W54: 38.027392 | X54: 36.244932 | Y54: 30.725134 | Z54: 35.127471 | AA54: 30.811979 | AB54: 18.284933 | AC54: 0
G55: =SUMIF($I$9:$AU$9,G$10,$I55:$AU55)*$G$4*$B$5 -> 120.83021 | H55: Debit | I55: 39.942735 | J55: 46.260257 | K55: 40.753548 | L55: 41.007921 | M55: 43.477861 | N55: 114.32927 | O55: 150.86436 | P55: 33.490929 | Q55: 41.032007 | R55: 37.713928 | S55: 33.073842 | T55: 32.632686 | U55: 25.957824 | V55: 27.127226 | W55: 32.059504 | X55: 36.658213 | Y55: 23.706913 | Z55: 30.588494 | AA55: 27.74645 | AB55: 22.313652 | AC55: 0
G56: =SUMIF($I$9:$AU$9,G$10,$I56:$AU56)*$G$4*$B$5 -> 27.28236 | H56: Personal | I56: 81.781624 | J56: 107.77026 | K56: 138.78051 | L56: 157.34445 | M56: 169.35233 | N56: 39.51583 | O56: 60.118744 | P56: 9.5706786 | Q56: 25.156354 | R56: 18.254436 | S56: -20.171636 | T56: -8.8114864 | U56: 17.317624 | V56: 5.8860483 | W56: 14.848929 | X56: 9.2161378 | Y56: 44.20127 | Z56: 29.288577 | AA56: 24.970837 | AB56: 26.209575 | AC56: -3.141225
... G152: =SUMIF($I$9:$AU$9,G$10,$I152:$AU152)*$G$4*$B$5 -> -558.62514 | H152: Net lending (+) / net borrowing (-) (balance from current and capital account) | I152: -113.50705 | J152: -280.34581 | K152: -569.79096 | L152: -350.5883 | M152: -597.56907 | N152: -783.77149 | O152: -1140.8224 | P152: -183.53633 | Q152: -141.29793 | R152: -202.2338 | S152: -144.73589 | T152: -230.97467 | U152: -175.85144 | V152: -129.77277 | W152: -198.40445 | X152: -215.54323 | Y152: -297.3171 | Z152: -272.15947 | AA152: -208.49655 | AB152: -349.16238 | AC152: -198.98649

Sheet wGFS
A1: Fiscal Accounts
A2: Workings
B4: 2016/17 | C4: Year 1
B5: 2017/18 | C5: Year 2
B6: 0.001 | C6: Scaling (multiplier) | H6: Consolidated Financial Statements of the Government of Rwanda
H7: http://www.minecofin.gov.rw/fileadmin/templates/documents/PAU_Files/Consolidated_Financial_Statements/Consolidated_Financial_Statements/GoR_Consolidated_Financial_Statements_FY_2016-2017.pdf
H8: http://www.minecofin.gov.rw/fileadmin/templates/documents/PAU_Files/Consolidated_Financial_Statements/Consolidated_Financial_Statements/GoR_Consolidated_Financial_Statements_FY_2017-2018.pdf
J9: 2015/16 | K9: 2016/17 | L9: 2017/18
H10: Revenues
G11: =AVERAGE(SUMIF($J$9:$T$9,$B$4,$J11:$T11),SUMIF($J$9:$T$9,$B$5,$J11:$T11))*$B$6 -> 1178.2507 | H11: Tax Revenues | I11: 1.6.3 | J11: 1000456.9 | K11: 1103747.1 | L11: 1252754.3
B12: Revenues | D12: Expenditures | G12: =AVERAGE(SUMIF($J$9:$T$9,$B$4,$J12:$T12),SUMIF($J$9:$T$9,$B$5,$J12:$T12))*$B$6 -> 479.15296 | H12: Taxes on Income, Profits or Capital Gains | J12: 381280.25 | K12: 446375.68 | L12: 511930.24
B13: Personal tax | C13: =D53 -> 315.56829 | D13: Consumption | E13: =G35+G39 -> 1215.3441 | G13: =AVERAGE(SUMIF($J$9:$T$9,$B$4,$J13:$T13),SUMIF($J$9:$T$9,$B$5,$J13:$T13))*$B$6 -> 0 | H13: Taxes on Payroll and Workforce | J13: 0 | K13: 0 | L13: 0
B14: Corporate tax | C14: =D54 -> 163.58467 | D14: Households | E14: =G57+G58 -> 89.798979 | G14: =AVERAGE(SUMIF($J$9:$T$9,$B$4,$J14:$T14),SUMIF($J$9:$T$9,$B$5,$J14:$T14))*$B$6 -> 1.1773436 | H14: Tax on Property Income | J14: 1594.102 | K14: 1235.2098 | L14: 1119.4775
B15: Labor tax | C15: =G13 -> 0 | D15: Enterprises | E15: =G50+G51+G60+G63+G64+G65+G66+G67+G55 -> 252.04027 | G15: =AVERAGE(SUMIF($J$9:$T$9,$B$4,$J15:$T15),SUMIF($J$9:$T$9,$B$5,$J15:$T15))*$B$6 -> 522.02212 | H15: Taxes on goods and services | J15: 446824.55 | K15: 486867.53 | L15: 557176.72
B16: Land tax | D16: Rest of world | E16: =G53+G54+G61 -> 43.333063 | G16: =AVERAGE(SUMIF($J$9:$T$9,$B$4,$J16:$T16),SUMIF($J$9:$T$9,$B$5,$J16:$T16))*$B$6 -> 175.89826 | H16: Taxes on international trade and transactions | J16: 170758.02 | K16: 169268.69 | L16: 182527.83
B17: Capital tax | C17: =G14 -> 1.1773436 | G17: =AVERAGE(SUMIF($J$9:$T$9,$B$4,$J17:$T17),SUMIF($J$9:$T$9,$B$5,$J17:$T17))*$B$6 -> 201.7043 | H17: Administrative fees, Fines, Penalties and Licenses | I17: 1.6.4 | J17: 121089.84 | K17: 200132.98 | L17: 203275.63
B18: Subsidies (production) | C18: =D42 -> -91.129877 | G18: =AVERAGE(SUMIF($J$9:$T$9,$B$4,$J18:$T18),SUMIF($J$9:$T$9,$B$5,$J18:$T18))*$B$6 -> 5.5546754 | H18: Property Income | J18: 7993.0876 | K18: 5406.4619 | L18: 5702.8889
B19: Customs duties | C19: =D43 -> 106.52877 | G19: =AVERAGE(SUMIF($J$9:$T$9,$B$4,$J19:$T19),SUMIF($J$9:$T$9,$B$5,$J19:$T19))*$B$6 -> 87.618145 | H19: Sales of goods and services | J19: 86958.989 | K19: 78892.601 | L19: 96343.689
B20: Exports | C20: =D44 -> 0 | G20: =AVERAGE(SUMIF($J$9:$T$9,$B$4,$J20:$T20),SUMIF($J$9:$T$9,$B$5,$J20:$T20))*$B$6 -> 108.53148 | H20: Fines, penalties, and forfeits | J20: 26137.763 | K20: 115833.92 | L20: 101229.05
B21: Import excise duties | C21: =D45 -> 69.369485 | G21: =AVERAGE(SUMIF($J$9:$T$9,$B$4,$J21:$T21),SUMIF($J$9:$T$9,$B$5,$J21:$T21))*$B$6 -> 425.85079 | H21: Borrowings | I21: 1.6.5 | J21: 335883.79 | K21: 386526.67 | L21: 465174.92
B22: Subsidies (products) | C22: =D46 -> -32.184818 | G22: =AVERAGE(SUMIF($J$9:$T$9,$B$4,$J22:$T22),SUMIF($J$9:$T$9,$B$5,$J22:$T22))*$B$6 -> 70.905118 | H22: Domestic borrowings | I22: 1.6.5 | J22: 90301.173 | K22: 52989.25 | L22: 88820.986
B23: VAT | C23: =D47 -> 424.40257 | G23: =AVERAGE(SUMIF($J$9:$T$9,$B$4,$J23:$T23),SUMIF($J$9:$T$9,$B$5,$J23:$T23))*$B$6 -> 354.94568 | H23: External borrowings | I23: 1.6.5 | J23: 245582.62 | K23: 333537.42 | L23: 376353.93
B24: Excise & Others | C24: =D48 -> 220.93425 | G24: =AVERAGE(SUMIF($J$9:$T$9,$B$4,$J24:$T24),SUMIF($J$9:$T$9,$B$5,$J24:$T24))*$B$6 -> 345.44355 | H24: Grants | I24: 1.6.6 | J24: 442748.1 | K24: 357350.9 | L24: 333536.19
B25: Labor | G25: =AVERAGE(SUMIF($J$9:$T$9,$B$4,$J25:$T25),SUMIF($J$9:$T$9,$B$5,$J25:$T25))*$B$6 -> 16.650882 | H25: Capital Receipts | I25: 1.6.7 | J25: 6142.0213 | K25: 28842.124 | L25: 4459.64
B26: Land | G26: =AVERAGE(SUMIF($J$9:$T$9,$B$4,$J26:$T26),SUMIF($J$9:$T$9,$B$5,$J26:$T26))*$B$6 -> 1.4786174 | H26: Disposal of tangible fixed assets | J26: 1843.7337 | K26: 2728.2849 | L26: 228.9499
B27: Capital | G27: =AVERAGE(SUMIF($J$9:$T$9,$B$4,$J27:$T27),SUMIF($J$9:$T$9,$B$5,$J27:$T27))*$B$6 -> 1.8625375 | H27: Sale of Inventories | J27: 42.820844 | K27: 2011.4739 | L27: 1713.6012
B28: Households | C28: =G19+G20 -> 196.14963 | G28: =AVERAGE(SUMIF($J$9:$T$9,$B$4,$J28:$T28),SUMIF($J$9:$T$9,$B$5,$J28:$T28))*$B$6 -> 1.937035 | H28: Sale of Non-Produced Assets | J28: 0 | K28: 1611.9811 | L28: 2262.0889
B29: Enterprises | C29: =G18+G25+G30 -> 69.912831 | G29: =AVERAGE(SUMIF($J$9:$T$9,$B$4,$J29:$T29),SUMIF($J$9:$T$9,$B$5,$J29:$T29))*$B$6 -> 11.372692 | H29: Sale of Financial Assets - Domestic | J29: 4255.4668 | K29: 22490.384 | L29: 255
B30: Rest of world | C30: =G24 -> 345.44355 | D30: Savings | E30: =G71+G80-G21+G68 -> 189.24024 | G30: =AVERAGE(SUMIF($J$9:$T$9,$B$4,$J30:$T30),SUMIF($J$9:$T$9,$B$5,$J30:$T30))*$B$6 -> 47.707274 | H30: Other income | I30: 1.6.8 | J30: 45687.686 | K30: 41274.145 | L30: 54140.402
B31: Total | C31: =SUM(C13:C30) -> 1789.7567 | D31: Total | E31: =SUM(E13:E30) -> 1789.7567 | G31: =AVERAGE(SUMIF($J$9:$T$9,$B$4,$J31:$T31),SUMIF($J$9:$T$9,$B$5,$J31:$T31))*$B$6 -> 3.6281675 | H31: Voluntary transfers other than grants | J31: 18688.332 | K31: 5853.7855 | L31: 1402.5495
D32: Difference | E32: =E31-C31 -> -5.0044946e-10 | G32: =AVERAGE(SUMIF($J$9:$T$9,$B$4,$J32:$T32),SUMIF($J$9:$T$9,$B$5,$J32:$T32))*$B$6 -> 44.079106 | H32: Miscellaneous and unidentified Revenue | J32: 26999.354 | K32: 35420.36 | L32: 52737.853
B33: GFS error | C33: =C31-G33 -> -425.85079 | E33: =E31-G79-G80 -> -425.85079 | G33: =AVERAGE(SUMIF($J$9:$T$9,$B$4,$J33:$T33),SUMIF($J$9:$T$9,$B$5,$J33:$T33))*$B$6 -> 2215.6075 | H33: Total Revenue | I33: 1.6.27 | J33: 1952008.4 | K33: 2117873.9 | L33: 2313341
G34: =AVERAGE(SUMIF($J$9:$T$9,$B$4,$J34:$T34),SUMIF($J$9:$T$9,$B$5,$J34:$T34))*$B$6 -> 0 | H34: Expenditure
G35: =AVERAGE(SUMIF($J$9:$T$9,$B$4,$J35:$T35),SUMIF($J$9:$T$9,$B$5,$J35:$T35))*$B$6 -> 417.70225 | H35: Compensation of Employees | I35: 1.6.9 | J35: 374376.49 | K35: 405730.88 | L35: 429673.62
B36: =G71 -> 602.89738 | C36: Public investment level | G36: =AVERAGE(SUMIF($J$9:$T$9,$B$4,$J36:$T36),SUMIF($J$9:$T$9,$B$5,$J36:$T36))*$B$6 -> 382.67997 | H36: Salaries in cash | J36: 345883.83 | K36: 373592.81 | L36: 391767.13
G37: =AVERAGE(SUMIF($J$9:$T$9,$B$4,$J37:$T37),SUMIF($J$9:$T$9,$B$5,$J37:$T37))*$B$6 -> 34.902866 | H37: Social contribution | J37: 28492.655 | K37: 32138.07 | L37: 37667.663
G38: =AVERAGE(SUMIF($J$9:$T$9,$B$4,$J38:$T38),SUMIF($J$9:$T$9,$B$5,$J38:$T38))*$B$6 -> 0.11941346 | H38: Salaries arrears | J38: 0 | K38: 0 | L38: 238.82692
B39: Indirect taxes | G39: =AVERAGE(SUMIF($J$9:$T$9,$B$4,$J39:$T39),SUMIF($J$9:$T$9,$B$5,$J39:$T39))*$B$6 -> 797.6419 | H39: Use of Goods and Services | I39: 1.6.10 | J39: 639287.25 | K39: 782912.53 | L39: 812371.27
B40: see wTAX | C40: Estimate | D40: Scaled | E40: Diff. | G40: =AVERAGE(SUMIF($J$9:$T$9,$B$4,$J40:$T40),SUMIF($J$9:$T$9,$B$5,$J40:$T40))*$B$6 -> 132.8134 | H40: General Services | J40: 119957.3 | K40: 130467.85 | L40: 135158.96
B41: Total | C41: =SUM(C42:C48) -> 653.08542 | D41: =SUM(D42:D48) -> 697.92038 | E41: =D41-C41 -> 44.834966 | G41: =AVERAGE(SUMIF($J$9:$T$9,$B$4,$J41:$T41),SUMIF($J$9:$T$9,$B$5,$J41:$T41))*$B$6 -> 160.37978 | H41: Professional, Research services | J41: 140819.8 | K41: 150037.22 | L41: 170722.34
B42: Subsidies (production) | C42: =wTAX!F4 -> -83.113857 | D42: =C42/SUM($C$42,$C$46:$C$48)*$G$15 -> -91.129877 | E42: =D42-C42 -> -8.0160202 | G42: =AVERAGE(SUMIF($J$9:$T$9,$B$4,$J42:$T42),SUMIF($J$9:$T$9,$B$5,$J42:$T42))*$B$6 -> 73.132195 | H42: Transport and travel | J42: 64027.36 | K42: 70233.157 | L42: 76031.233
B43: Customs duties | C43: =wTAX!J4 -> 107.18494 | D43: =C43/SUM($C$43:$C$45)*$G$16 -> 106.52877 | E43: =D43-C43 -> -0.65616881 | G43: =AVERAGE(SUMIF($J$9:$T$9,$B$4,$J43:$T43),SUMIF($J$9:$T$9,$B$5,$J43:$T43))*$B$6 -> 67.595985 | H43: Maintenance, Repairs and Spare Parts | J43: 53160.519 | K43: 64493.223 | L43: 70698.747
B44: Exports | C44: =wTAX!N4 -> 0 | D44: =C44/SUM($C$43:$C$45)*$G$16 -> 0 | E44: =D44-C44 -> 0 | G44: =AVERAGE(SUMIF($J$9:$T$9,$B$4,$J44:$T44),SUMIF($J$9:$T$9,$B$5,$J44:$T44))*$B$6 -> 1.0378286 | H44: Tools and Small Equipment | J44: 112.257 | K44: 185.52444 | L44: 1890.1327
B45: Import excise duties | C45: =wTAX!R4 -> 69.79677 | D45: =C45/SUM($C$43:$C$45)*$G$16 -> 69.369485 | E45: =D45-C45 -> -0.42728449 | G45: =AVERAGE(SUMIF($J$9:$T$9,$B$4,$J45:$T45),SUMIF($J$9:$T$9,$B$5,$J45:$T45))*$B$6 -> 27.020793 | H45: Training Costs | J45: 18972.55 | K45: 22005.469 | L45: 32036.116
B46: Subsidies (products) | C46: =wTAX!V4 -> -29.353758 | D46: =C46/SUM($C$42,$C$46:$C$48)*$G$15 -> -32.184818 | E46: =D46-C46 -> -2.83106 | G46: =AVERAGE(SUMIF($J$9:$T$9,$B$4,$J46:$T46),SUMIF($J$9:$T$9,$B$5,$J46:$T46))*$B$6 -> 318.64711 | H46: Supplies and services | J46: 211201.17 | K46: 329912.85 | L46: 307381.38
B47: VAT | C47: =wTAX!Z4 -> 387.07102 | D47: =C47/SUM($C$42,$C$46:$C$48)*$G$15 -> 424.40257 | E47: =D47-C47 -> 37.33155 | G47: =AVERAGE(SUMIF($J$9:$T$9,$B$4,$J47:$T47),SUMIF($J$9:$T$9,$B$5,$J47:$T47))*$B$6 -> 0.74503447 | H47: Arrears | J47: 6617.6332 | K47: 0 | L47: 1490.0689
B48: Excise & Others | C48: =wTAX!AD4 -> 201.5003 | D48: =C48/SUM($C$42,$C$46:$C$48)*$G$15 -> 220.93425 | E48: =D48-C48 -> 19.433949 | G48: =AVERAGE(SUMIF($J$9:$T$9,$B$4,$J48:$T48),SUMIF($J$9:$T$9,$B$5,$J48:$T48))*$B$6 -> 16.26976 | H48: Other Use of Goods& Services | J48: 24418.662 | K48: 15577.229 | L48: 16962.291
G49: =AVERAGE(SUMIF($J$9:$T$9,$B$4,$J49:$T49),SUMIF($J$9:$T$9,$B$5,$J49:$T49))*$B$6 -> 13.198132 | H49: Subsidies | I49: 1.6.11 | J49: 28664.717 | K49: 12461.817 | L49: 13934.447
B50: Direct taxes | G50: =AVERAGE(SUMIF($J$9:$T$9,$B$4,$J50:$T50),SUMIF($J$9:$T$9,$B$5,$J50:$T50))*$B$6 -> 9.5322553 | H50: Subsidies to Public Corporations | J50: 26347.803 | K50: 6300.1025 | L50: 12764.408
C51: Estimate | D51: Scaled | G51: =AVERAGE(SUMIF($J$9:$T$9,$B$4,$J51:$T51),SUMIF($J$9:$T$9,$B$5,$J51:$T51))*$B$6 -> 3.6658763 | H51: Subsidies to Private Enterprises | J51: 2316.9132 | K51: 6161.7141 | L51: 1170.0384
B52: Total | C52: =SUM(C53:C54) -> 627.34185 | D52: =G12 -> 479.15296 | G52: =AVERAGE(SUMIF($J$9:$T$9,$B$4,$J52:$T52),SUMIF($J$9:$T$9,$B$5,$J52:$T52))*$B$6 -> 58.367648 | H52: Grants | I52: 1.6.12 | J52: 67241.527 | K52: 56572.689 | L52: 60162.606
B53: Personal tax | C53: 413.16492 | D53: =C53/$C$52*$D$52 -> 315.56829 | G53: =AVERAGE(SUMIF($J$9:$T$9,$B$4,$J53:$T53),SUMIF($J$9:$T$9,$B$5,$J53:$T53))*$B$6 -> 0 | H53: Grants to Foreign Governments | J53: 0 | K53: 0 | L53: 0
B54: Corporate tax | C54: 214.17693 | D54: =C54/$C$52*$D$52 -> 163.58467 | G54: =AVERAGE(SUMIF($J$9:$T$9,$B$4,$J54:$T54),SUMIF($J$9:$T$9,$B$5,$J54:$T54))*$B$6 -> 0 | H54: Grants to International Organizations - | J54: 0 | K54: 0 | L54: 0
G55: =AVERAGE(SUMIF($J$9:$T$9,$B$4,$J55:$T55),SUMIF($J$9:$T$9,$B$5,$J55:$T55))*$B$6 -> 58.367648 | H55: Grants to Subsidiary Entity | J55: 67241.527 | K55: 56572.689 | L55: 60162.606
G56: =AVERAGE(SUMIF($J$9:$T$9,$B$4,$J56:$T56),SUMIF($J$9:$T$9,$B$5,$J56:$T56))*$B$6 -> 89.798979 | H56: Social Assistance | I56: 1.6.13 | J56: 70101.945 | K56: 70085.725 | L56: 109512.23
G57: =AVERAGE(SUMIF($J$9:$T$9,$B$4,$J57:$T57),SUMIF($J$9:$T$9,$B$5,$J57:$T57))*$B$6 -> 85.54364 | H57: Social Assistance Benefits | J57: 65018.162 | K57: 67367.477 | L57: 103719.8
G58: =AVERAGE(SUMIF($J$9:$T$9,$B$4,$J58:$T58),SUMIF($J$9:$T$9,$B$5,$J58:$T58))*$B$6 -> 4.2553383 | H58: Employer Social Benefits | J58: 5083.7833 | K58: 2718.2472 | L58: 5792.4294
G59: =AVERAGE(SUMIF($J$9:$T$9,$B$4,$J59:$T59),SUMIF($J$9:$T$9,$B$5,$J59:$T59))*$B$6 -> 87.267682 | H59: Finance cost | I59: 1.6.14 | J59: 60908.271 | K59: 82257.334 | L59: 92278.031
G60: =AVERAGE(SUMIF($J$9:$T$9,$B$4,$J60:$T60),SUMIF($J$9:$T$9,$B$5,$J60:$T60))*$B$6 -> 43.934619 | H60: Interest on domestic debt | J60: 31113.179 | K60: 45540.312 | L60: 42328.927
G61: =AVERAGE(SUMIF($J$9:$T$9,$B$4,$J61:$T61),SUMIF($J$9:$T$9,$B$5,$J61:$T61))*$B$6 -> 43.333063 | H61: Interest on foreign debt | J61: 29795.092 | K61: 36717.022 | L61: 49949.104
G62: =AVERAGE(SUMIF($J$9:$T$9,$B$4,$J62:$T62),SUMIF($J$9:$T$9,$B$5,$J62:$T62))*$B$6 -> 136.53987 | H62: Other Expenses | I62: 1.6.15 | J62: 115089.07 | K62: 135353.02 | L62: 137726.71
G63: =AVERAGE(SUMIF($J$9:$T$9,$B$4,$J63:$T63),SUMIF($J$9:$T$9,$B$5,$J63:$T63))*$B$6 -> 84.480658 | H63: Miscellaneous expenses | J63: 87327.782 | K63: 76220.217 | L63: 92741.098
G64: =AVERAGE(SUMIF($J$9:$T$9,$B$4,$J64:$T64),SUMIF($J$9:$T$9,$B$5,$J64:$T64))*$B$6 -> 0 | H64: Arrears on other expenditures | J64: 1.488144 | K64: 0 | L64: 0
G65: =AVERAGE(SUMIF($J$9:$T$9,$B$4,$J65:$T65),SUMIF($J$9:$T$9,$B$5,$J65:$T65))*$B$6 -> 0.023888063 | H65: Property expenses other than interest | J65: 0 | K65: 0.6 | L65: 47.176125
G66: =AVERAGE(SUMIF($J$9:$T$9,$B$4,$J66:$T66),SUMIF($J$9:$T$9,$B$5,$J66:$T66))*$B$6 -> 50.29915 | H66: Transfers not elsewhere classified | J66: 24910.729 | K66: 58269.237 | L66: 42329.063
G67: =AVERAGE(SUMIF($J$9:$T$9,$B$4,$J67:$T67),SUMIF($J$9:$T$9,$B$5,$J67:$T67))*$B$6 -> 1.7361711 | H67: Premiums ,Fees and Current claims | J67: 2849.0679 | K67: 862.96874 | L67: 2609.3735
G68: =AVERAGE(SUMIF($J$9:$T$9,$B$4,$J68:$T68),SUMIF($J$9:$T$9,$B$5,$J68:$T68))*$B$6 -> 43.914396 | H68: Repayment of borrowings | I68: 1.6.16 | J68: 29937.647 | K68: 39333.804 | L68: 48494.988
G69: =AVERAGE(SUMIF($J$9:$T$9,$B$4,$J69:$T69),SUMIF($J$9:$T$9,$B$5,$J69:$T69))*$B$6 -> 21.172858 | H69: Repayment of principal – Domestic debt | J69: 15039.441 | K69: 18559.684 | L69: 23786.032
G70: =AVERAGE(SUMIF($J$9:$T$9,$B$4,$J70:$T70),SUMIF($J$9:$T$9,$B$5,$J70:$T70))*$B$6 -> 22.741538 | H70: Repayment of principal – Foreign debt | J70: 14898.207 | K70: 20774.12 | L70: 24708.955
G71: =AVERAGE(SUMIF($J$9:$T$9,$B$4,$J71:$T71),SUMIF($J$9:$T$9,$B$5,$J71:$T71))*$B$6 -> 602.89738 | H71: Acquisition of Assets | I71: 1.6.17 | J71: 537525.27 | K71: 596099.43 | L71: 609695.33
G72: =AVERAGE(SUMIF($J$9:$T$9,$B$4,$J72:$T72),SUMIF($J$9:$T$9,$B$5,$J72:$T72))*$B$6 -> 381.26669 | H72: Acquisition of tangible fixed assets | J72: 398936.1 | K72: 219927.98 | L72: 542605.4
G73: =AVERAGE(SUMIF($J$9:$T$9,$B$4,$J73:$T73),SUMIF($J$9:$T$9,$B$5,$J73:$T73))*$B$6 -> 1.0691007 | H73: Inventories | J73: 254.01561 | K73: 1245.6162 | L73: 892.58523
G74: =AVERAGE(SUMIF($J$9:$T$9,$B$4,$J74:$T74),SUMIF($J$9:$T$9,$B$5,$J74:$T74))*$B$6 -> 57.886206 | H74: Valuables | J74: 6120.1249 | K74: 115749.02 | L74: 23.396176
G75: =AVERAGE(SUMIF($J$9:$T$9,$B$4,$J75:$T75),SUMIF($J$9:$T$9,$B$5,$J75:$T75))*$B$6 -> 148.30209 | H75: Non Produced Assets | J75: 130840.84 | K75: 247673.94 | L75: 48930.247
G76: =AVERAGE(SUMIF($J$9:$T$9,$B$4,$J76:$T76),SUMIF($J$9:$T$9,$B$5,$J76:$T76))*$B$6 -> 4.4298174 | H76: Investment in Financial Assets – Domestic | J76: 0 | K76: 2910.0212 | L76: 5949.6136
G77: =AVERAGE(SUMIF($J$9:$T$9,$B$4,$J77:$T77),SUMIF($J$9:$T$9,$B$5,$J77:$T77))*$B$6 -> 5.2604524 | H77: Investment in Financial Assets – Foreign | J77: 1200.0252 | K77: 26.701033 | L77: 10494.204
G78: =AVERAGE(SUMIF($J$9:$T$9,$B$4,$J78:$T78),SUMIF($J$9:$T$9,$B$5,$J78:$T78))*$B$6 -> 4.6830179 | H78: Arrears on acquisition of fixed assets | J78: 174.1549 | K78: 8566.1565 | L78: 799.87928
G79: =AVERAGE(SUMIF($J$9:$T$9,$B$4,$J79:$T79),SUMIF($J$9:$T$9,$B$5,$J79:$T79))*$B$6 -> 2247.3282 | H79: Total Expenditure | I79: 1.6.28 | J79: 1923132.2 | K79: 2180807.2 | L79: 2313849.2
G80: =AVERAGE(SUMIF($J$9:$T$9,$B$4,$J80:$T80),SUMIF($J$9:$T$9,$B$5,$J80:$T80))*$B$6 -> -31.720742 | H80: Net Surplus / (Deficit) | J80: 28876.184 | K80: -62933.295 | L80: -508.18798

Sheet wGDPe
A1: Gross Domestic Product by Expenditure Category
A2: Workings
F3: =Notes!B5 -> 2017 | G3: Year
F4: 1 | G4: Scaling (multiplier)
E6: Map | F6: Selected | H6: 2010 | I6: 2011 | J6: 2012 | K6: 2013 | L6: 2014 | M6: 2015 | N6: 2016 | O6: 2017 | P6: 2018 | Q6: 2019 | R6: 2020 | S6: 2021 | T6: 2022
B7: 1 | C7: Private consumption | D7: =SUMIF($E$7:$E$30,$B7,$F$7:$F$30) -> 5676 | F7: =SUMIF($H$6:$T$6,F$3,H7:T7) -> 7694 | G7: Gross Domestic Product | H7: 3571 | I7: 4133 | J7: 4703 | K7: 5056 | L7: 5623 | M7: 6152 | N7: 6847 | O7: 7694 | P7: 8298 | Q7: 9313
B8: 2 | C8: Government consumption | D8: =SUMIF($E$7:$E$30,$B8,$F$7:$F$30) -> 1155 | F8: =SUMIF($H$6:$T$6,F$3,H8:T8) -> 6831 | G8: Total final consumption expenditure | H8: 3404 | I8: 3870 | J8: 4392 | K8: 4625 | L8: 5234 | M8: 5820 | N8: 6363 | O8: 6831 | P8: 7545 | Q8: 8126
B9: 3 | C9: Gross fixed capital formation | D9: =SUMIF($E$7:$E$30,$B9,$F$7:$F$30) -> 1748 | E9: 2 | F9: =SUMIF($H$6:$T$6,F$3,H9:T9) -> 1155 | G9: Government | H9: 467 | I9: 497 | J9: 609 | K9: 650 | L9: 803 | M9: 851 | N9: 1032 | O9: 1155 | P9: 1223 | Q9: 1472
B10: 4 | C10: Changes in inventories | D10: =SUMIF($E$7:$E$30,$B10,$F$7:$F$30) -> 86 | E10: 1 | F10: =SUMIF($H$6:$T$6,F$3,H10:T10) -> 5676 | G10: Households and NGOs | H10: 2937 | I10: 3374 | J10: 3784 | K10: 3975 | L10: 4431 | M10: 4968 | N10: 5331 | O10: 5676 | P10: 6322 | Q10: 6655
B11: 5 | C11: Exports | D11: =SUMIF($E$7:$E$30,$B11,$F$7:$F$30) -> 1580 | F11: =SUMIF($H$6:$T$6,F$3,H11:T11) -> 1834 | G11: Gross capital formation | H11: 733 | I11: 864 | J11: 1096 | K11: 1235 | L11: 1306 | M11: 1491 | N11: 1758 | O11: 1834 | P11: 1877 | Q11: 2520
B12: 6 | C12: Goods | D12: =SUMIF($E$7:$E$30,$B12,$F$7:$F$30) -> 866 | E12: 3 | F12: =SUMIF($H$6:$T$6,F$3,H12:T12) -> 1748 | G12: Gross fixed capital formation | H12: 710 | I12: 847 | J12: 1064 | K12: 1197 | L12: 1273 | M12: 1474 | N12: 1858 | O12: 1748 | P12: 1906 | Q12: 2504
B13: 7 | C13: Services | D13: =SUMIF($E$7:$E$30,$B13,$F$7:$F$30) -> 714 | F13: =SUMIF($H$6:$T$6,F$3,H13:T13) -> 1143 | G13: Construction | H13: 486 | I13: 629 | J13: 768 | K13: 886 | L13: 945 | M13: 1107 | N13: 1201 | O13: 1143 | P13: 1238 | Q13: 1651
B14: 8 | C14: Imports | D14: =SUMIF($E$7:$E$30,$B14,$F$7:$F$30) -> 2550 | F14: =SUMIF($H$6:$T$6,F$3,H14:T14) -> 605 | G14: Other | H14: 223 | I14: 218 | J14: 297 | K14: 312 | L14: 327 | M14: 367 | N14: 657 | O14: 605 | P14: 668 | Q14: 853
B15: 9 | C15: Goods | D15: =SUMIF($E$7:$E$30,$B15,$F$7:$F$30) -> 1672 | E15: 4 | F15: =SUMIF($H$6:$T$6,F$3,H15:T15) -> 86 | G15: Change in inventories | H15: 24 | I15: 16 | J15: 31 | K15: 38 | L15: 33 | M15: 17 | N15: -100 | O15: 86 | P15: -28 | Q15: 16
B16: 10 | C16: Services | D16: =SUMIF($E$7:$E$30,$B16,$F$7:$F$30) -> 878 | F16: =SUMIF($H$6:$T$6,F$3,H16:T16) -> -971 | G16: Resource balance | H16: -566 | I16: -601 | J16: -786 | K16: -804 | L16: -917 | M16: -1159 | N16: -1274 | O16: -971 | P16: -1123 | Q16: -1333
C17: GDP at market prices | D17: =SUM(D7:D11)-D14 -> 7695 | E17: 5 | F17: =SUMIF($H$6:$T$6,F$3,H17:T17) -> 1580 | G17: Exports of goods & services | H17: 382 | I17: 517 | J17: 557 | K17: 673 | L17: 771 | M17: 807 | N17: 1058 | O17: 1580 | P17: 1754 | Q17: 2032
C18: Indirect taxes | D18: =wGDPp!K4 -> 654 | E18: 6 | F18: =SUMIF($H$6:$T$6,F$3,H18:T18) -> 866 | G18: Goods (fob) | H18: 163 | I18: 288 | J18: 326 | K18: 405 | L18: 415 | M18: 389 | N18: 404 | O18: 866 | P18: 972 | Q18: 1124
C19: GDP at factor cost | D19: =D17-D18 -> 7041 | E19: 7 | F19: =SUMIF($H$6:$T$6,F$3,H19:T19) -> 714 | G19: Services | H19: 219 | I19: 229 | J19: 231 | K19: 267 | L19: 357 | M19: 418 | N19: 654 | O19: 714 | P19: 783 | Q19: 908
C20: Discrepency | D20: =D19-wGDPp!K3 -> -1 | E20: 8 | F20: =SUMIF($H$6:$T$6,F$3,H20:T20) -> 2550 | G20: Imports of goods & services | H20: 948 | I20: 1118 | J20: 1342 | K20: 1477 | L20: 1689 | M20: 1966 | N20: 2332 | O20: 2550 | P20: 2878 | Q20: 3365
E21: 9 | F21: =SUMIF($H$6:$T$6,F$3,H21:T21) -> 1672 | G21: Goods (fob) | H21: 659 | I21: 790 | J21: 994 | K21: 1046 | L21: 1174 | M21: 1221 | N21: 1475 | O21: 1672 | P21: 1968 | Q21: 2436
E22: 10 | F22: =SUMIF($H$6:$T$6,F$3,H22:T22) -> 878 | G22: Services | H22: 288 | I22: 328 | J22: 348 | K22: 430 | L22: 514 | M22: 746 | N22: 857 | O22: 878 | P22: 910 | Q22: 929
F23: =SUMIF($H$6:$T$6,F$3,H23:T23) -> 0
F24: =SUMIF($H$6:$T$6,F$3,H24:T24) -> 0
F25: =SUMIF($H$6:$T$6,F$3,H25:T25) -> 0
F26: =SUMIF($H$6:$T$6,F$3,H26:T26) -> 0
F27: =SUMIF($H$6:$T$6,F$3,H27:T27) -> 0
F28: =SUMIF($H$6:$T$6,F$3,H28:T28) -> 0
F29: =SUMIF($H$6:$T$6,F$3,H29:T29) -> 0
F30: =SUMIF($H$6:$T$6,F$3,H30:T30) -> 0

Sheet wGDPp
A1: Gross Domestic Product by Production Sector
B2: Workings | K2: Summary data
K3: =F7 -> 7042 | L3: GDP factor cost
I4: =Notes!B5 -> 2017 | J4: Year | K4: =I45 -> 654 | L4: Indirect taxes
D5: Final | E5: Sub-sectoral shares | F5: National accounts | I5: 1 | J5: Scaling (multiplier) | K5: =SUM(K3:K4) -> 7696 | L5: GDP market prices
D6: values | F6: Current
D7: =SUM(D8:D111) -> 7042 | F7: =SUM(F8:F111) -> 7042 | G7: Groups | H7: Map | I7: Selected | K7: 2010 | L7: 2011 | M7: 2012 | N7: 2013 | O7: 2014 | P7: 2015 | Q7: 2016 | R7: 2017 | S7: 2018 | T7: 2019 | U7: 2020 | V7: 2021 | W7: 2022
B8: Sorghum (A111) | C8: asorg | D8: =IF(COUNTIF($G$8:$G$111,G8)=1,F8,SUMIF($G$8:$G$111,G8,$F$8:$F$111)*E8/SUMIF($G$8:$G$111,G8,$E$8:$E$111)) -> 42.163108 | E8: =wAGR!M7 -> 0.032508179 | F8: =SUMIF($H$8:$H$46,$C8,$I$8:$I$46) -> 1297 | G8: 1 | I8: =I9+I15+I29 -> 7042 | J8: Gross Domestic Product (Gdp) () | K8: 3571 | L8: 4133 | M8: 4703 | N8: 5056 | O8: 5623 | P8: 6152 | Q8: 6847 | R8: 7694 | S8: 8298 | T8: 9313
B9: Maize (A112) | C9: amaiz | D9: =IF(COUNTIF($G$8:$G$111,G9)=1,F9,SUMIF($G$8:$G$111,G9,$F$8:$F$111)*E9/SUMIF($G$8:$G$111,G9,$E$8:$E$111)) -> 91.54879 | E9: =wAGR!M8 -> 0.070585035 | F9: =SUMIF($H$8:$H$46,$C9,$I$8:$I$46) -> 0 | G9: 1 | I9: =SUM(I10:I14) -> 2028 | J9: Agriculture, Forestry & Fishing (A) | K9: 868 | L9: 985 | M9: 1165 | N9: 1260 | O9: 1388 | P9: 1475 | Q9: 1722 | R9: 2027 | S9: 2044 | T9: 2193
B10: Wheat (A113) | C10: awhea | D10: =IF(COUNTIF($G$8:$G$111,G10)=1,F10,SUMIF($G$8:$G$111,G10,$F$8:$F$111)*E10/SUMIF($G$8:$G$111,G10,$E$8:$E$111)) -> 3.0363336 | E10: =wAGR!M9 -> 0.0023410437 | F10: =SUMIF($H$8:$H$46,$C10,$I$8:$I$46) -> 0 | G10: 1 | H10: asorg | I10: =SUMIF($K$7:$W$7,I$4,K10:W10) -> 1297 | J10: Food Crops (AA) | K10: 457 | L10: 534 | M10: 652 | N10: 739 | O10: 823 | P10: 874 | Q10: 1065 | R10: 1297 | S10: 1156 | T10: 1245
B11: Paddy & husked rice (A116) | C11: arice | D11: =IF(COUNTIF($G$8:$G$111,G11)=1,F11,SUMIF($G$8:$G$111,G11,$F$8:$F$111)*E11/SUMIF($G$8:$G$111,G11,$E$8:$E$111)) -> 55.892973 | E11: =wAGR!M10 -> 0.043094043 | F11: =SUMIF($H$8:$H$46,$C11,$I$8:$I$46) -> 0 | G11: 1 | H11: acoff | I11: =SUMIF($K$7:$W$7,I$4,K11:W11) -> 138 | J11: Export Crops (AB) | K11: 64 | L11: 67 | M11: 86 | N11: 68 | O11: 87 | P11: 89 | Q11: 105 | R11: 138 | S11: 138 | T11: 115
B12: Other cereals (A119) | C12: aocer | D12: =IF(COUNTIF($G$8:$G$111,G12)=1,F12,SUMIF($G$8:$G$111,G12,$F$8:$F$111)*E12/SUMIF($G$8:$G$111,G12,$E$8:$E$111)) -> 0.27145353 | E12: =wAGR!M11 -> 0.00020929339 | F12: =SUMIF($H$8:$H$46,$C12,$I$8:$I$46) -> 0 | G12: 1 | H12: acatt | I12: =SUMIF($K$7:$W$7,I$4,K12:W12) -> 186 | J12: Livestock & Livestock Products (AC) | K12: 84 | L12: 94 | M12: 106 | N12: 117 | O12: 129 | P12: 144 | Q12: 166 | R12: 186 | S12: 212 | T12: 254
B13: Irish potatoes (A121) | C13: aipot | D13: =IF(COUNTIF($G$8:$G$111,G13)=1,F13,SUMIF($G$8:$G$111,G13,$F$8:$F$111)*E13/SUMIF($G$8:$G$111,G13,$E$8:$E$111)) -> 159.09592 | E13: =wAGR!M12 -> 0.12266455 | F13: =SUMIF($H$8:$H$46,$C13,$I$8:$I$46) -> 0 | G13: 1 | H13: afuel | I13: =SUMIF($K$7:$W$7,I$4,K13:W13) -> 378 | J13: Forestry (AD) | K13: 250 | L13: 274 | M13: 303 | N13: 315 | O13: 327 | P13: 343 | Q13: 360 | R13: 378 | S13: 504 | T13: 545
B14: Sweet potatoes (A122) | C14: aspot | D14: =IF(COUNTIF($G$8:$G$111,G14)=1,F14,SUMIF($G$8:$G$111,G14,$F$8:$F$111)*E14/SUMIF($G$8:$G$111,G14,$E$8:$E$111)) -> 141.62941 | E14: =wAGR!M13 -> 0.1091977 | F14: =SUMIF($H$8:$H$46,$C14,$I$8:$I$46) -> 0 | G14: 1 | H14: afish | I14: =SUMIF($K$7:$W$7,I$4,K14:W14) -> 29 | J14: Fishing (AE) | K14: 13 | L14: 16 | M14: 18 | N14: 21 | O14: 22 | P14: 25 | Q14: 26 | R14: 29 | S14: 33 | T14: 34
B15: Cassava (A123) | C15: acass | D15: =IF(COUNTIF($G$8:$G$111,G15)=1,F15,SUMIF($G$8:$G$111,G15,$F$8:$F$111)*E15/SUMIF($G$8:$G$111,G15,$E$8:$E$111)) -> 117.32855 | E15: =wAGR!M14 -> 0.090461486 | F15: =SUMIF($H$8:$H$46,$C15,$I$8:$I$46) -> 0 | G15: 1 | I15: =I16+I17+I26+I27+I28 -> 1329 | J15: Industry (B-F) | K15: 584 | L15: 752 | M15: 859 | N15: 892 | O15: 989 | P15: 1076 | Q15: 1156 | R15: 1330 | S15: 1436 | T15: 1759
B16: Other roots & tubers (A129) | C16: aroot | D16: =IF(COUNTIF($G$8:$G$111,G16)=1,F16,SUMIF($G$8:$G$111,G16,$F$8:$F$111)*E16/SUMIF($G$8:$G$111,G16,$E$8:$E$111)) -> 19.943023 | E16: =wAGR!M15 -> 0.01537627 | F16: =SUMIF($H$8:$H$46,$C16,$I$8:$I$46) -> 0 | G16: 1 | H16: angas | I16: =SUMIF($K$7:$W$7,I$4,K16:W16) -> 165 | J16: Mining & Quarrying (B) | K16: 37 | L16: 82 | M16: 78 | N16: 100 | O16: 119 | P16: 106 | Q16: 110 | R16: 165 | S16: 185 | T16: 135
B17: Dried beans (A131) | C17: abean | D17: =IF(COUNTIF($G$8:$G$111,G17)=1,F17,SUMIF($G$8:$G$111,G17,$F$8:$F$111)*E17/SUMIF($G$8:$G$111,G17,$E$8:$E$111)) -> 214.58619 | E17: =wAGR!M16 -> 0.16544811 | F17: =SUMIF($H$8:$H$46,$C17,$I$8:$I$46) -> 0 | G17: 1 | I17: =SUM(I18:I25) -> 590 | J17: Total Manufacturing (C) | K17: 296 | L17: 347 | M17: 392 | N17: 347 | O17: 386 | P17: 424 | Q17: 463 | R17: 591 | S17: 629 | T17: 782
B18: Peas & other legumes (A132) | C18: apeas | D18: =IF(COUNTIF($G$8:$G$111,G18)=1,F18,SUMIF($G$8:$G$111,G18,$F$8:$F$111)*E18/SUMIF($G$8:$G$111,G18,$E$8:$E$111)) -> 20.982413 | E18: =wAGR!M17 -> 0.01617765 | F18: =SUMIF($H$8:$H$46,$C18,$I$8:$I$46) -> 0 | G18: 1 | H18: ameat | I18: =SUMIF($K$7:$W$7,I$4,K18:W18) -> 210 | J18: Food (CA) | K18: 69 | L18: 81 | M18: 90 | N18: 96 | O18: 105 | P18: 108 | Q18: 123 | R18: 210 | S18: 185 | T18: 257
B19: Other vegetables (A139) | C19: avege | D19: =IF(COUNTIF($G$8:$G$111,G19)=1,F19,SUMIF($G$8:$G$111,G19,$F$8:$F$111)*E19/SUMIF($G$8:$G$111,G19,$E$8:$E$111)) -> 141.78518 | E19: =wAGR!M18 -> 0.1093178 | F19: =SUMIF($H$8:$H$46,$C19,$I$8:$I$46) -> 0 | G19: 1 | H19: aalco | I19: =SUMIF($K$7:$W$7,I$4,K19:W19) -> 159 | J19: Beverages & Tobacco (CB) | K19: 78 | L19: 84 | M19: 98 | N19: 108 | O19: 122 | P19: 130 | Q19: 140 | R19: 159 | S19: 176 | T19: 190
B20: Bananas for beer (A141) | C20: abanb | D20: =IF(COUNTIF($G$8:$G$111,G20)=1,F20,SUMIF($G$8:$G$111,G20,$F$8:$F$111)*E20/SUMIF($G$8:$G$111,G20,$E$8:$E$111)) -> 80.184602 | E20: =wAGR!M19 -> 0.061823132 | F20: =SUMIF($H$8:$H$46,$C20,$I$8:$I$46) -> 0 | G20: 1 | H20: atext | I20: =SUMIF($K$7:$W$7,I$4,K20:W20) -> 34 | J20: Textiles, Clothing & Leather Goods (CC) | K20: 68 | L20: 81 | M20: 87 | N20: 20 | O20: 22 | P20: 22 | Q20: 25 | R20: 34 | S20: 60 | T20: 72
B21: Bananas for cooking (A142) | C21: abanc | D21: =IF(COUNTIF($G$8:$G$111,G21)=1,F21,SUMIF($G$8:$G$111,G21,$F$8:$F$111)*E21/SUMIF($G$8:$G$111,G21,$E$8:$E$111)) -> 145.99979 | E21: =wAGR!M20 -> 0.1125673 | F21: =SUMIF($H$8:$H$46,$C21,$I$8:$I$46) -> 0 | G21: 1 | H21: awood | I21: =SUMIF($K$7:$W$7,I$4,K21:W21) -> 26 | J21: Wood & Paper; Printing (CD) | K21: 16 | L21: 15 | M21: 18 | N21: 20 | O21: 21 | P21: 25 | Q21: 29 | R21: 26 | S21: 27 | T21: 34
B22: Bananas (sweet) (A143) | C22: abans | D22: =IF(COUNTIF($G$8:$G$111,G22)=1,F22,SUMIF($G$8:$G$111,G22,$F$8:$F$111)*E22/SUMIF($G$8:$G$111,G22,$E$8:$E$111)) -> 26.477187 | E22: =wAGR!M21 -> 0.020414176 | F22: =SUMIF($H$8:$H$46,$C22,$I$8:$I$46) -> 0 | G22: 1 | H22: apetr | I22: =SUMIF($K$7:$W$7,I$4,K22:W22) -> 34 | J22: Chemicals, Rubber & Plastic Products (CE) | K22: 19 | L22: 23 | M22: 26 | N22: 27 | O22: 26 | P22: 29 | Q22: 31 | R22: 34 | S22: 38 | T22: 55
B23: Other fruit & nuts (A149) | C23: afrui | D23: =IF(COUNTIF($G$8:$G$111,G23)=1,F23,SUMIF($G$8:$G$111,G23,$F$8:$F$111)*E23/SUMIF($G$8:$G$111,G23,$E$8:$E$111)) -> 24.758807 | E23: =wAGR!M22 -> 0.019089288 | F23: =SUMIF($H$8:$H$46,$C23,$I$8:$I$46) -> 0 | G23: 1 | H23: anmet | I23: =SUMIF($K$7:$W$7,I$4,K23:W23) -> 34 | J23: Non-Metallic Mineral Products (CF) | K23: 12 | L23: 14 | M23: 17 | N23: 18 | O23: 21 | P23: 25 | Q23: 30 | R23: 34 | S23: 34 | T23: 44
B24: Ground nuts (A151) | C24: agnut | D24: =IF(COUNTIF($G$8:$G$111,G24)=1,F24,SUMIF($G$8:$G$111,G24,$F$8:$F$111)*E24/SUMIF($G$8:$G$111,G24,$E$8:$E$111)) -> 8.5193652 | E24: =wAGR!M23 -> 0.0065685159 | F24: =SUMIF($H$8:$H$46,$C24,$I$8:$I$46) -> 0 | G24: 1 | H24: ametl | I24: =SUMIF($K$7:$W$7,I$4,K24:W24) -> 32 | J24: Metal Products, Machinery & Equipment (CG) | K24: 11 | L24: 15 | M24: 19 | N24: 16 | O24: 21 | P24: 30 | Q24: 34 | R24: 32 | S24: 36 | T24: 49
B25: Soya (A152) | C25: asoya | D25: =IF(COUNTIF($G$8:$G$111,G25)=1,F25,SUMIF($G$8:$G$111,G25,$F$8:$F$111)*E25/SUMIF($G$8:$G$111,G25,$E$8:$E$111)) -> 2.7968996 | E25: =wAGR!M24 -> 0.0021564376 | F25: =SUMIF($H$8:$H$46,$C25,$I$8:$I$46) -> 0 | G25: 1 | H25: afurn | I25: =SUMIF($K$7:$W$7,I$4,K25:W25) -> 61 | J25: Furniture & Other Manufacturing (CH) | K25: 24 | L25: 33 | M25: 37 | N25: 41 | O25: 47 | P25: 55 | Q25: 52 | R25: 61 | S25: 72 | T25: 80
B26: Other oil seeds (A159) | C26: aoils | D26: =IF(COUNTIF($G$8:$G$111,G26)=1,F26,SUMIF($G$8:$G$111,G26,$F$8:$F$111)*E26/SUMIF($G$8:$G$111,G26,$E$8:$E$111)) -> 0 | E26: =wAGR!M25 -> 0 | F26: =SUMIF($H$8:$H$46,$C26,$I$8:$I$46) -> 0 | G26: 1 | H26: aelec | I26: =SUMIF($K$7:$W$7,I$4,K26:W26) -> 84 | J26: Electricity (D) | K26: 23 | L26: 27 | M26: 35 | N26: 41 | O26: 45 | P26: 55 | Q26: 77 | R26: 84 | S26: 87 | T26: 90
B27: Coffee, not roasted, not decaffeinated (A210) | C27: acoff | D27: =IF(COUNTIF($G$8:$G$111,G27)=1,F27,SUMIF($G$8:$G$111,G27,$F$8:$F$111)*E27/SUMIF($G$8:$G$111,G27,$E$8:$E$111)) -> 70.943429 | E27: =wAGR!M26 -> 0.51408282 | F27: =SUMIF($H$8:$H$46,$C27,$I$8:$I$46) -> 138 | G27: 2 | H27: awatr | I27: =SUMIF($K$7:$W$7,I$4,K27:W27) -> 32 | J27: Water & Waste Management (E) | K27: 19 | L27: 22 | M27: 24 | N27: 25 | O27: 26 | P27: 28 | Q27: 32 | R27: 32 | S27: 33 | T27: 55
B28: Tea (unprocessed green leaf) (A220) | C28: ateal | D28: =IF(COUNTIF($G$8:$G$111,G28)=1,F28,SUMIF($G$8:$G$111,G28,$F$8:$F$111)*E28/SUMIF($G$8:$G$111,G28,$E$8:$E$111)) -> 22.405977 | E28: =wAGR!M27 -> 0.16236215 | F28: =SUMIF($H$8:$H$46,$C28,$I$8:$I$46) -> 0 | G28: 2 | H28: acons | I28: =SUMIF($K$7:$W$7,I$4,K28:W28) -> 458 | J28: Construction (F) | K28: 209 | L28: 273 | M28: 330 | N28: 379 | O28: 414 | P28: 464 | Q28: 474 | R28: 458 | S28: 502 | T28: 698
B29: Tobacco, raw (A291) | C29: atoba | D29: =IF(COUNTIF($G$8:$G$111,G29)=1,F29,SUMIF($G$8:$G$111,G29,$F$8:$F$111)*E29/SUMIF($G$8:$G$111,G29,$E$8:$E$111)) -> 3.8840398 | E29: =wAGR!M28 -> 0.028145216 | F29: =SUMIF($H$8:$H$46,$C29,$I$8:$I$46) -> 0 | G29: 2 | I29: =I30+I34 -> 3685 | J29: Services (G-T) | K29: 1780 | L29: 1979 | M29: 2296 | N29: 2517 | O29: 2766 | P29: 3058 | Q29: 3372 | R29: 3684 | S29: 4127 | T29: 4572
B30: Sugar cane (A292) | C30: asugr | D30: =IF(COUNTIF($G$8:$G$111,G30)=1,F30,SUMIF($G$8:$G$111,G30,$F$8:$F$111)*E30/SUMIF($G$8:$G$111,G30,$E$8:$E$111)) -> 8.8945824 | E30: =wAGR!M29 -> 0.064453496 | F30: =SUMIF($H$8:$H$46,$C30,$I$8:$I$46) -> 0 | G30: 2 | I30: =SUM(I31:I33) -> 992 | J30: Trade &Transport (G-H) | K30: 475 | L30: 539 | M30: 649 | N30: 699 | O30: 754 | P30: 824 | Q30: 897 | R30: 992 | S30: 1219 | T30: 1411
B31: Pyrethrum (A293) | C31: apyre | D31: =IF(COUNTIF($G$8:$G$111,G31)=1,F31,SUMIF($G$8:$G$111,G31,$F$8:$F$111)*E31/SUMIF($G$8:$G$111,G31,$E$8:$E$111)) -> 5.1729332 | E31: =wAGR!M30 -> 0.037485023 | F31: =SUMIF($H$8:$H$46,$C31,$I$8:$I$46) -> 0 | G31: 2 | H31: avehr | I31: =SUMIF($K$7:$W$7,I$4,K31:W31) -> 40 | J31: Maintenance And Repair Of Motor Vehicles (GA) | K31: 21 | L31: 24 | M31: 27 | N31: 29 | O31: 31 | P31: 33 | Q31: 37 | R31: 40 | S31: 45 | T31: 50
B32: Agricultural products n.e.c. (A299) | C32: aocrp | D32: =IF(COUNTIF($G$8:$G$111,G32)=1,F32,SUMIF($G$8:$G$111,G32,$F$8:$F$111)*E32/SUMIF($G$8:$G$111,G32,$E$8:$E$111)) -> 26.699039 | E32: =wAGR!M31 -> 0.1934713 | F32: =SUMIF($H$8:$H$46,$C32,$I$8:$I$46) -> 0 | G32: 2 | H32: atrdw | I32: =SUMIF($K$7:$W$7,I$4,K32:W32) -> 597 | J32: Wholesale & Retail Trade (GB) | K32: 302 | L32: 344 | M32: 409 | N32: 435 | O32: 482 | P32: 528 | Q32: 559 | R32: 597 | S32: 706 | T32: 789
B33: Bovine cattle, live (A311) | C33: acatt | D33: =IF(COUNTIF($G$8:$G$111,G33)=1,F33,SUMIF($G$8:$G$111,G33,$F$8:$F$111)*E33/SUMIF($G$8:$G$111,G33,$E$8:$E$111)) -> 76.457883 | E33: =wAGR!M32 -> 0.41106388 | F33: =SUMIF($H$8:$H$46,$C33,$I$8:$I$46) -> 186 | G33: 3 | H33: atrnl | I33: =SUMIF($K$7:$W$7,I$4,K33:W33) -> 355 | J33: Transport Services (H) | K33: 152 | L33: 171 | M33: 213 | N33: 235 | O33: 241 | P33: 262 | Q33: 300 | R33: 355 | S33: 468 | T33: 572
B34: Sheep, goats, pigs,live (A312) | C34: asmlr | D34: =IF(COUNTIF($G$8:$G$111,G34)=1,F34,SUMIF($G$8:$G$111,G34,$F$8:$F$111)*E34/SUMIF($G$8:$G$111,G34,$E$8:$E$111)) -> 44.055757 | E34: =wAGR!M33 -> 0.23685891 | F34: =SUMIF($H$8:$H$46,$C34,$I$8:$I$46) -> 0 | G34: 3 | I34: =SUM(I35:I44) -> 2693 | J34: Other Services (I-T) | K34: 1306 | L34: 1439 | M34: 1647 | N34: 1818 | O34: 2012 | P34: 2234 | Q34: 2475 | R34: 2692 | S34: 2908 | T34: 3162
B35: Poultry, live (A313) | C35: apoul | D35: =IF(COUNTIF($G$8:$G$111,G35)=1,F35,SUMIF($G$8:$G$111,G35,$F$8:$F$111)*E35/SUMIF($G$8:$G$111,G35,$E$8:$E$111)) -> 12.119768 | E35: =wAGR!M34 -> 0.065160044 | F35: =SUMIF($H$8:$H$46,$C35,$I$8:$I$46) -> 0 | G35: 3 | H35: ahotl | I35: =SUMIF($K$7:$W$7,I$4,K35:W35) -> 140 | J35: Hotels & Restaurants (I) | K35: 84 | L35: 90 | M35: 96 | N35: 100 | O35: 119 | P35: 134 | Q35: 154 | R35: 140 | S35: 158 | T35: 172
B36: Other live animals (A319) | C36: aoliv | D36: =IF(COUNTIF($G$8:$G$111,G36)=1,F36,SUMIF($G$8:$G$111,G36,$F$8:$F$111)*E36/SUMIF($G$8:$G$111,G36,$E$8:$E$111)) -> 2.1617689 | E36: =wAGR!M35 -> 0.011622414 | F36: =SUMIF($H$8:$H$46,$C36,$I$8:$I$46) -> 0 | G36: 3 | H36: apubl | I36: =SUMIF($K$7:$W$7,I$4,K36:W36) -> 134 | J36: Information & Communication (J) | K36: 77 | L36: 86 | M36: 108 | N36: 106 | O36: 118 | P36: 135 | Q36: 138 | R36: 134 | S36: 144 | T36: 186
B37: Raw milk (A321) | C37: amilk | D37: =IF(COUNTIF($G$8:$G$111,G37)=1,F37,SUMIF($G$8:$G$111,G37,$F$8:$F$111)*E37/SUMIF($G$8:$G$111,G37,$E$8:$E$111)) -> 32.944426 | E37: =wAGR!M36 -> 0.17712057 | F37: =SUMIF($H$8:$H$46,$C37,$I$8:$I$46) -> 0 | G37: 3 | H37: abank | I37: =SUMIF($K$7:$W$7,I$4,K37:W37) -> 191 | J37: Financial Services (K) | K37: 75 | L37: 94 | M37: 121 | N37: 144 | O37: 145 | P37: 159 | Q37: 164 | R37: 191 | S37: 206 | T37: 225
B38: Eggs (A322) | C38: aeggs | D38: =IF(COUNTIF($G$8:$G$111,G38)=1,F38,SUMIF($G$8:$G$111,G38,$F$8:$F$111)*E38/SUMIF($G$8:$G$111,G38,$E$8:$E$111)) -> 14.264471 | E38: =wAGR!M37 -> 0.076690702 | F38: =SUMIF($H$8:$H$46,$C38,$I$8:$I$46) -> 0 | G38: 3 | H38: arent | I38: =SUMIF($K$7:$W$7,I$4,K38:W38) -> 560 | J38: Real Estate Activities (L) | K38: 355 | L38: 374 | M38: 371 | N38: 367 | O38: 401 | P38: 430 | Q38: 488 | R38: 560 | S38: 607 | T38: 648
B39: Natural honey (A323) | C39: ahony | D39: =IF(COUNTIF($G$8:$G$111,G39)=1,F39,SUMIF($G$8:$G$111,G39,$F$8:$F$111)*E39/SUMIF($G$8:$G$111,G39,$E$8:$E$111)) -> 0.51409051 | E39: =wAGR!M38 -> 0.0027639275 | F39: =SUMIF($H$8:$H$46,$C39,$I$8:$I$46) -> 0 | G39: 3 | H39: alegl | I39: =SUMIF($K$7:$W$7,I$4,K39:W39) -> 163 | J39: Professional, Scientific And Technical Activities (M) | K39: 90 | L39: 95 | M39: 107 | N39: 116 | O39: 109 | P39: 128 | Q39: 144 | R39: 163 | S39: 181 | T39: 204
B40: Other livestock & hunting products (A329) | C40: ahunt | D40: =IF(COUNTIF($G$8:$G$111,G40)=1,F40,SUMIF($G$8:$G$111,G40,$F$8:$F$111)*E40/SUMIF($G$8:$G$111,G40,$E$8:$E$111)) -> 3.4818361 | E40: =wAGR!M39 -> 0.018719549 | F40: =SUMIF($H$8:$H$46,$C40,$I$8:$I$46) -> 0 | G40: 3 | H40: atrvl | I40: =SUMIF($K$7:$W$7,I$4,K40:W40) -> 277 | J40: Administrative And Support Service Activities (N) | K40: 121 | L40: 128 | M40: 145 | N40: 156 | O40: 183 | P40: 218 | Q40: 253 | R40: 277 | S40: 291 | T40: 313
B41: Fuel wood (A401) | C41: afuel | D41: =IF(COUNTIF($G$8:$G$111,G41)=1,F41,SUMIF($G$8:$G$111,G41,$F$8:$F$111)*E41/SUMIF($G$8:$G$111,G41,$E$8:$E$111)) -> 300.53637 | E41: =wAGR!M40 -> 0.79506976 | F41: =SUMIF($H$8:$H$46,$C41,$I$8:$I$46) -> 378 | G41: 4 | H41: apadm | I41: =SUMIF($K$7:$W$7,I$4,K41:W41) -> 446 | J41: Public Administration And Defence; Compulsory Social Security (O) | K41: 174 | L41: 211 | M41: 268 | N41: 303 | O41: 332 | P41: 359 | Q41: 418 | R41: 446 | S41: 488 | T41: 523
B42: Charcoal (A402) | C42: achar | D42: =IF(COUNTIF($G$8:$G$111,G42)=1,F42,SUMIF($G$8:$G$111,G42,$F$8:$F$111)*E42/SUMIF($G$8:$G$111,G42,$E$8:$E$111)) -> 57.932328 | E42: =wAGR!M41 -> 0.15326013 | F42: =SUMIF($H$8:$H$46,$C42,$I$8:$I$46) -> 0 | G42: 4 | H42: aeduc | I42: =SUMIF($K$7:$W$7,I$4,K42:W42) -> 231 | J42: Education (P) | K42: 90 | L42: 112 | M42: 138 | N42: 185 | O42: 204 | P42: 207 | Q42: 220 | R42: 231 | S42: 240 | T42: 255
B43: Other forestry products (A409) | C43: afore | D43: =IF(COUNTIF($G$8:$G$111,G43)=1,F43,SUMIF($G$8:$G$111,G43,$F$8:$F$111)*E43/SUMIF($G$8:$G$111,G43,$E$8:$E$111)) -> 19.531302 | E43: =wAGR!M42 -> 0.05167011 | F43: =SUMIF($H$8:$H$46,$C43,$I$8:$I$46) -> 0 | G43: 4 | H43: aheal | I43: =SUMIF($K$7:$W$7,I$4,K43:W43) -> 160 | J43: Human Health And Social Work Activities (Q) | K43: 76 | L43: 78 | M43: 99 | N43: 114 | O43: 130 | P43: 133 | Q43: 136 | R43: 160 | S43: 155 | T43: 157
B44: Fishery products (A500) | C44: afish | D44: =IF(COUNTIF($G$8:$G$111,G44)=1,F44,SUMIF($G$8:$G$111,G44,$F$8:$F$111)*E44/SUMIF($G$8:$G$111,G44,$E$8:$E$111)) -> 29 | F44: =SUMIF($H$8:$H$46,$C44,$I$8:$I$46) -> 29 | G44: 5 | H44: acult | I44: =SUMIF($K$7:$W$7,I$4,K44:W44) -> 391 | J44: Cultural, Domestic & Other Services (R-T) | K44: 162 | L44: 170 | M44: 195 | N44: 226 | O44: 271 | P44: 330 | Q44: 361 | R44: 391 | S44: 437 | T44: 478
B45: Natural gas (B01) | C45: angas | D45: =IF(COUNTIF($G$8:$G$111,G45)=1,F45,SUMIF($G$8:$G$111,G45,$F$8:$F$111)*E45/SUMIF($G$8:$G$111,G45,$E$8:$E$111)) -> 0.069262115 | E45: =wIND!K7 -> 0.0004197704 | F45: =SUMIF($H$8:$H$46,$C45,$I$8:$I$46) -> 165 | G45: 6 | I45: =SUMIF($K$7:$W$7,I$4,K45:W45) -> 654 | J45: Taxes Less Subsidies On Products () | K45: 338 | L45: 417 | M45: 384 | N45: 387 | O45: 480 | P45: 543 | Q45: 597 | R45: 654 | S45: 692 | T45: 789
B46: Metal ores (B03) | C46: amore | D46: =IF(COUNTIF($G$8:$G$111,G46)=1,F46,SUMIF($G$8:$G$111,G46,$F$8:$F$111)*E46/SUMIF($G$8:$G$111,G46,$E$8:$E$111)) -> 68.516522 | E46: =wIND!K8 -> 0.41525165 | F46: =SUMIF($H$8:$H$46,$C46,$I$8:$I$46) -> 0 | G46: 6 | I46: =SUMIF($K$7:$W$7,I$4,K46:W46) -> 0
B47: Quarry & other mining products (B09) | C47: aomin | D47: =IF(COUNTIF($G$8:$G$111,G47)=1,F47,SUMIF($G$8:$G$111,G47,$F$8:$F$111)*E47/SUMIF($G$8:$G$111,G47,$E$8:$E$111)) -> 96.414216 | E47: =wIND!K9 -> 0.58432858 | F47: =SUMIF($H$8:$H$46,$C47,$I$8:$I$46) -> 0 | G47: 6
B48: Meat and meat products (C11) | C48: ameat | D48: =IF(COUNTIF($G$8:$G$111,G48)=1,F48,SUMIF($G$8:$G$111,G48,$F$8:$F$111)*E48/SUMIF($G$8:$G$111,G48,$E$8:$E$111)) -> 21.926921 | E48: =wIND!K10 -> 0.10441391 | F48: =SUMIF($H$8:$H$46,$C48,$I$8:$I$46) -> 210 | G48: 7
B49: Prepared and preserved fish (C12) | C49: afsea | D49: =IF(COUNTIF($G$8:$G$111,G49)=1,F49,SUMIF($G$8:$G$111,G49,$F$8:$F$111)*E49/SUMIF($G$8:$G$111,G49,$E$8:$E$111)) -> 0 | E49: =wIND!K11 -> 0 | F49: =SUMIF($H$8:$H$46,$C49,$I$8:$I$46) -> 0 | G49: 7
B50: Prepared and preserved vegetables (C13) | C50: afveg | D50: =IF(COUNTIF($G$8:$G$111,G50)=1,F50,SUMIF($G$8:$G$111,G50,$F$8:$F$111)*E50/SUMIF($G$8:$G$111,G50,$E$8:$E$111)) -> 6.0929636 | E50: =wIND!K12 -> 0.029014112 | F50: =SUMIF($H$8:$H$46,$C50,$I$8:$I$46) -> 0 | G50: 7
B51: Animal and vegetable oils and fats (C14) | C51: afoil | D51: =IF(COUNTIF($G$8:$G$111,G51)=1,F51,SUMIF($G$8:$G$111,G51,$F$8:$F$111)*E51/SUMIF($G$8:$G$111,G51,$E$8:$E$111)) -> 8.0793322 | E51: =wIND!K13 -> 0.038473011 | F51: =SUMIF($H$8:$H$46,$C51,$I$8:$I$46) -> 0 | G51: 7
B52: Dairy products (C15) | C52: adair | D52: =IF(COUNTIF($G$8:$G$111,G52)=1,F52,SUMIF($G$8:$G$111,G52,$F$8:$F$111)*E52/SUMIF($G$8:$G$111,G52,$E$8:$E$111)) -> 4.5099278 | E52: =wIND!K14 -> 0.021475847 | F52: =SUMIF($H$8:$H$46,$C52,$I$8:$I$46) -> 0 | G52: 7
B53: Grain mill products (C16) | C53: agmll | D53: =IF(COUNTIF($G$8:$G$111,G53)=1,F53,SUMIF($G$8:$G$111,G53,$F$8:$F$111)*E53/SUMIF($G$8:$G$111,G53,$E$8:$E$111)) -> 104.82926 | E53: =wIND!K15 -> 0.49918694 | F53: =SUMIF($H$8:$H$46,$C53,$I$8:$I$46) -> 0 | G53: 7
B54: Bakery products (C17) | C54: abake | D54: =IF(COUNTIF($G$8:$G$111,G54)=1,F54,SUMIF($G$8:$G$111,G54,$F$8:$F$111)*E54/SUMIF($G$8:$G$111,G54,$E$8:$E$111)) -> 16.426382 | E54: =wIND!K16 -> 0.078220867 | F54: =SUMIF($H$8:$H$46,$C54,$I$8:$I$46) -> 0 | G54: 7
B55: Animal feed & other by-products (C18) | C55: afeed | D55: =IF(COUNTIF($G$8:$G$111,G55)=1,F55,SUMIF($G$8:$G$111,G55,$F$8:$F$111)*E55/SUMIF($G$8:$G$111,G55,$E$8:$E$111)) -> 3.9291026 | E55: =wIND!K17 -> 0.018710012 | F55: =SUMIF($H$8:$H$46,$C55,$I$8:$I$46) -> 0 | G55: 7
B56: Other manufactured food products (C19) | C56: afood | D56: =IF(COUNTIF($G$8:$G$111,G56)=1,F56,SUMIF($G$8:$G$111,G56,$F$8:$F$111)*E56/SUMIF($G$8:$G$111,G56,$E$8:$E$111)) -> 44.206113 | E56: =wIND!K18 -> 0.2105053 | F56: =SUMIF($H$8:$H$46,$C56,$I$8:$I$46) -> 0 | G56: 7
B57: Alcoholic drinks (C21) | C57: aalco | D57: =IF(COUNTIF($G$8:$G$111,G57)=1,F57,SUMIF($G$8:$G$111,G57,$F$8:$F$111)*E57/SUMIF($G$8:$G$111,G57,$E$8:$E$111)) -> 127.92243 | E57: =wIND!K19 -> 0.80454361 | F57: =SUMIF($H$8:$H$46,$C57,$I$8:$I$46) -> 159 | G57: 8
B58: Soft drinks (C22) | C58: abeve | D58: =IF(COUNTIF($G$8:$G$111,G58)=1,F58,SUMIF($G$8:$G$111,G58,$F$8:$F$111)*E58/SUMIF($G$8:$G$111,G58,$E$8:$E$111)) -> 25.055473 | E58: =wIND!K20 -> 0.15758159 | F58: =SUMIF($H$8:$H$46,$C58,$I$8:$I$46) -> 0 | G58: 8
... B80: Construction (traditional) (F02) | C80: acont | D80: =IF(COUNTIF($G$8:$G$111,G80)=1,F80,SUMIF($G$8:$G$111,G80,$F$8:$F$111)*E80/SUMIF($G$8:$G$111,G80,$E$8:$E$111)) -> 0 | E80: =wIND!K42 -> 0 | F80: =SUMIF($H$8:$H$46,$C80,$I$8:$I$46) -> 0 | G80: 17
B81: Maintenance and repair of motor vehicles (G10) | C81: avehr | D81: =IF(COUNTIF($G$8:$G$111,G81)=1,F81,SUMIF($G$8:$G$111,G81,$F$8:$F$111)*E81/SUMIF($G$8:$G$111,G81,$E$8:$E$111)) -> 35.699691 | E81: =wSRV!K7 -> 0.89249226 | F81: =SUMIF($H$8:$H$46,$C81,$I$8:$I$46) -> 40 | G81: 18
B82: Wholesale and retail trade of motor vehicles and motorcycles (G21) | C82: aveht | D82: =IF(COUNTIF($G$8:$G$111,G82)=1,F82,SUMIF($G$8:$G$111,G82,$F$8:$F$111)*E82/SUMIF($G$8:$G$111,G82,$E$8:$E$111)) -> 4.3003095 | E82: =wSRV!K8 -> 0.10750774 | F82: =SUMIF($H$8:$H$46,$C82,$I$8:$I$46) -> 0 | G82: 18
B83: Wholesale trade, except of motor vehicles and motorcycles (G22) | C83: atrdw | D83: =IF(COUNTIF($G$8:$G$111,G83)=1,F83,SUMIF($G$8:$G$111,G83,$F$8:$F$111)*E83/SUMIF($G$8:$G$111,G83,$E$8:$E$111)) -> 180.44072 | E83: =wSRV!K9 -> 0.30224576 | F83: =SUMIF($H$8:$H$46,$C83,$I$8:$I$46) -> 597 | G83: 19
B84: Retail trade, except of motor vehicles and motorcycles (G23) | C84: atrdr | D84: =IF(COUNTIF($G$8:$G$111,G84)=1,F84,SUMIF($G$8:$G$111,G84,$F$8:$F$111)*E84/SUMIF($G$8:$G$111,G84,$E$8:$E$111)) -> 416.55928 | E84: =wSRV!K10 -> 0.69775424 | F84: =SUMIF($H$8:$H$46,$C84,$I$8:$I$46) -> 0 | G84: 19
B85: Land transport (H10) | C85: atrnl | D85: =IF(COUNTIF($G$8:$G$111,G85)=1,F85,SUMIF($G$8:$G$111,G85,$F$8:$F$111)*E85/SUMIF($G$8:$G$111,G85,$E$8:$E$111)) -> 205.15736 | E85: =wSRV!K11 -> 0.57790805 | F85: =SUMIF($H$8:$H$46,$C85,$I$8:$I$46) -> 355 | G85: 20
B86: Air transport (H20) | C86: atrna | D86: =IF(COUNTIF($G$8:$G$111,G86)=1,F86,SUMIF($G$8:$G$111,G86,$F$8:$F$111)*E86/SUMIF($G$8:$G$111,G86,$E$8:$E$111)) -> 95.814909 | E86: =wSRV!K12 -> 0.26990115 | F86: =SUMIF($H$8:$H$46,$C86,$I$8:$I$46) -> 0 | G86: 20
B87: Services related to transport (H31) | C87: atrns | D87: =IF(COUNTIF($G$8:$G$111,G87)=1,F87,SUMIF($G$8:$G$111,G87,$F$8:$F$111)*E87/SUMIF($G$8:$G$111,G87,$E$8:$E$111)) -> 44.025665 | E87: =wSRV!K13 -> 0.12401596 | F87: =SUMIF($H$8:$H$46,$C87,$I$8:$I$46) -> 0 | G87: 20
B88: Postal and courier activities (H32) | C88: apost | D88: =IF(COUNTIF($G$8:$G$111,G88)=1,F88,SUMIF($G$8:$G$111,G88,$F$8:$F$111)*E88/SUMIF($G$8:$G$111,G88,$E$8:$E$111)) -> 10.002069 | E88: =wSRV!K14 -> 0.028174843 | F88: =SUMIF($H$8:$H$46,$C88,$I$8:$I$46) -> 0 | G88: 20
B89: Hotels & restaurants (I00) | C89: ahotl | D89: =IF(COUNTIF($G$8:$G$111,G89)=1,F89,SUMIF($G$8:$G$111,G89,$F$8:$F$111)*E89/SUMIF($G$8:$G$111,G89,$E$8:$E$111)) -> 140 | E89: =wSRV!K15 -> 1 | F89: =SUMIF($H$8:$H$46,$C89,$I$8:$I$46) -> 140 | G89: 21
B90: Publishing, video making, programming & broadcasting activities (J10) | C90: apubl | D90: =IF(COUNTIF($G$8:$G$111,G90)=1,F90,SUMIF($G$8:$G$111,G90,$F$8:$F$111)*E90/SUMIF($G$8:$G$111,G90,$E$8:$E$111)) -> 22.681642 | E90: =wSRV!K16 -> 0.16926599 | F90: =SUMIF($H$8:$H$46,$C90,$I$8:$I$46) -> 134 | G90: 22
B91: Telecommunication (J20) | C91: acomm | D91: =IF(COUNTIF($G$8:$G$111,G91)=1,F91,SUMIF($G$8:$G$111,G91,$F$8:$F$111)*E91/SUMIF($G$8:$G$111,G91,$E$8:$E$111)) -> 89.229867 | E91: =wSRV!K17 -> 0.66589453 | F91: =SUMIF($H$8:$H$46,$C91,$I$8:$I$46) -> 0 | G91: 22
B92: Information technology services (J30) | C92: ainfo | D92: =IF(COUNTIF($G$8:$G$111,G92)=1,F92,SUMIF($G$8:$G$111,G92,$F$8:$F$111)*E92/SUMIF($G$8:$G$111,G92,$E$8:$E$111)) -> 22.088491 | E92: =wSRV!K18 -> 0.16483949 | F92: =SUMIF($H$8:$H$46,$C92,$I$8:$I$46) -> 0 | G92: 22
... B111: Travel debits & credits (V00) | C111: atrdc | D111: =IF(COUNTIF($G$8:$G$111,G111)=1,F111,SUMIF($G$8:$G$111,G111,$F$8:$F$111)*E111/SUMIF($G$8:$G$111,G111,$E$8:$E$111)) -> 0 | E111: =wSRV!K37 -> 0 | F111: =SUMIF($H$8:$H$46,$C111,$I$8:$I$46) -> 0 | G111: 30

Sheet wAGR
A1: Agriculture
A2: Workings
B3: =Notes!B5 -> 2017 | C3: Year | BD3: Summary of Seasonal Agricultural Survey main indicators
BD4: http://statistics.gov.rw/publication/seasonal-agricultural-survey-2019-annual-report
C5: New production value | F5: SUT17 | H5: Final production value | K5: GDP calculations | T5: Price scaling, 2017 | AA5: Production quantity (1000mt) | AK5: Producer Price (RwF/mt) | BF5: SAS 2017 | BI5: SAS 2018 | BL5: SAS 2019
C6: Quantity | D6: Price | E6: Value | F6: Value | G6: Price | H6: Value | I6: Adjust | J6: Final | K6: GDP/GO | L6: GDP | M6: Share | N6: Groups | Q6: Quantity | R6: Value | S6: Price | T6: Price | U6: Ratio | X6: Quantity | Y6: Price | AA6: Source | AB6: 2017 | AC6: 2018 | AD6: 2019 | AE6: 2020 | AF6: 2021 | AG6: 2022 | AH6: 2023 | AI6: 2024 | AJ6: 2025 | AK6: Source | AL6: 2017 | AM6: 2018 | AN6: 2019 | AO6: 2020 | AP6: 2021 | AQ6: 2022 | AR6: 2023 | AS6: 2024 | AT6: 2025 | AY6: 2017 | AZ6: 2018 | BA6: 2019 | BF6: Season A | BG6: Season B | BH6: Season C | BI6: Season A | BJ6: Season B | BK6: Season C | BL6: Season A | BM6: Season B | BN6: Season C
A7: Sorghum (A111) | B7: asorg | C7: =SUMIF($W$7:$W$64,$B7,$X$7:$X$64) -> 159.972 | D7: =SUMIF($W$7:$W$64,$B7,$Y$7:$Y$64)*U7 -> 282.36963 | E7: =D7*C7/1000 -> 45.171235 | F7: =xGDP!D7 -> 45.171235 | G7: =S7 -> 282.36963 | H7: =IF(E7=0,IF(C7*G7=0,F7,C7*G7),C7*D7)/1000 -> 45.171235 | I7: 1 | J7: =I7*H7 -> 45.171235 | K7: {=TRANSPOSE(wUSE!C3:AL3)} -> 0.93309851 | L7: =K7*J7 -> 42.149212 | M7: =L7/SUMIF($N$7:$N$42,$N7,$L$7:$L$42) -> 0.032508179 | N7: 1 | P7: asorg | Q7: =_xlfn.XLOOKUP(P7,$W$7:$W$64,X$7:X$64,0) -> 159.972 | R7: =xGDP!E7 -> 45.171235 | S7: =IF(Q7,R7/Q7*1000,0) -> 282.36963 | T7: =_xlfn.XLOOKUP(P7,$W$7:$W$64,Y$7:Y$64,0) -> 444.1889 | U7: =IF(T7,S7/T7,1) -> 0.63569718 | W7: amaiz | X7: =SUMIF($AB$6:$AJ$6,B$3,$AB7:$AJ7)/1000 -> 410.28 | Y7: =SUMIF($AL$6:$AT$6,B$3,$AL7:$AT7)/1000 -> 347.8772 | Z7: Maize | AA7: SAS | AB7: 410280 | AC7: 424204 | AD7: 421218 | AK7: FAO | AL7: 347877.2 | AM7: 227884.1 | AW7: Production for major crops (MT) | AX7: Maize | AY7: =SUM(BF7:BH7) -> 410280 | AZ7: =SUM(BI7:BK7) -> 424204 | BA7: =SUM(BL7:BN7) -> 421218 | BD7: Production for major crops (MT) | BE7: Maize | BF7: 324368 | BG7: 85912 | BI7: 332670 | BJ7: 91534 | BL7: 331090 | BM7: 90128
A8: Maize (A112) | B8: amaiz | C8: =SUMIF($W$7:$W$64,$B8,$X$7:$X$64) -> 410.28 | D8: =SUMIF($W$7:$W$64,$B8,$Y$7:$Y$64)*U8 -> 239.05708 | E8: =D8*C8/1000 -> 98.080338 | F8: =xGDP!D8 -> 98.080338 | G8: =S8 -> 239.05708 | H8: =IF(E8=0,IF(C8*G8=0,F8,C8*G8),C8*D8)/1000 -> 98.080338 | I8: 1 | J8: =I8*H8 -> 98.080338 | K8: 0.93309851 | L8: =K8*J8 -> 91.518617 | M8: =L8/SUMIF($N$7:$N$42,$N8,$L$7:$L$42) -> 0.070585035 | N8: 1 | P8: amaiz | Q8: =_xlfn.XLOOKUP(P8,$W$7:$W$64,X$7:X$64,0) -> 410.28 | R8: =xGDP!E8 -> 98.080338 | S8: =IF(Q8,R8/Q8*1000,0) -> 239.05708 | T8: 347.8772 | U8: =IF(T8,S8/T8,1) -> 0.68718812 | W8: asorg | X8: =SUMIF($AB$6:$AJ$6,B$3,$AB8:$AJ8)/1000 -> 159.972 | Y8: =SUMIF($AL$6:$AT$6,B$3,$AL8:$AT8)/1000 -> 444.1889 | Z8: Sorghum | AA8: SAS | AB8: 159972 | AC8: 154692 | AD8: 159626 | AK8: FAO | AL8: 444188.9 | AM8: 360359.4 | AX8: Sorghum | AY8: =SUM(BF8:BH8) -> 159972 | AZ8: =SUM(BI8:BK8) -> 154692 | BA8: =SUM(BL8:BN8) -> 159626 | BE8: Sorghum | BF8: 41662 | BG8: 118310 | BI8: 36581 | BJ8: 118111 | BL8: 37584 | BM8: 122042
A9: Wheat (A113) | B9: awhea | C9: =SUMIF($W$7:$W$64,$B9,$X$7:$X$64) -> 10.875 | D9: =SUMIF($W$7:$W$64,$B9,$Y$7:$Y$64)*U9 -> 299.12284 | E9: =D9*C9/1000 -> 3.2529609 | F9: =xGDP!D9 -> 3.2529609 | G9: =S9 -> 299.12284 | H9: =IF(E9=0,IF(C9*G9=0,F9,C9*G9),C9*D9)/1000 -> 3.2529609 | I9: 1 | J9: =I9*H9 -> 3.2529609 | K9: 0.93309851 | L9: =K9*J9 -> 3.0353329 | M9: =L9/SUMIF($N$7:$N$42,$N9,$L$7:$L$42) -> 0.0023410437 | N9: 1 | P9: awhea | Q9: =_xlfn.XLOOKUP(P9,$W$7:$W$64,X$7:X$64,0) -> 10.875 | R9: =xGDP!E9 -> 3.2529609 | S9: =IF(Q9,R9/Q9*1000,0) -> 299.12284 | T9: 525.2677 | U9: =IF(T9,S9/T9,1) -> 0.56946741 | W9: arice | X9: =SUMIF($AB$6:$AJ$6,B$3,$AB9:$AJ9)/1000 -> 119.932 | Y9: =SUMIF($AL$6:$AT$6,B$3,$AL9:$AT9)/1000 -> 729.2727 | Z9: Paddy Rice | AA9: SAS | AB9: 119932 | AC9: 113880 | AD9: 131577 | AK9: FAO | AL9: 729272.7 | AM9: 747136.7 | AX9: Paddy Rice | AY9: =SUM(BF9:BH9) -> 119932 | AZ9: =SUM(BI9:BK9) -> 113880 | BA9: =SUM(BL9:BN9) -> 131577 | BE9: Paddy Rice | BF9: 55217 | BG9: 64715 | BI9: 57934 | BJ9: 55946 | BL9: 59286 | BM9: 72291
A10: Paddy & husked rice (A116) | B10: arice | C10: =SUMIF($W$7:$W$64,$B10,$X$7:$X$64) -> 119.932 | D10: =SUMIF($W$7:$W$64,$B10,$Y$7:$Y$64)*U10 -> 499.2884 | E10: =D10*C10/1000 -> 59.880657 | F10: =xGDP!D10 -> 59.880657 | G10: =S10 -> 499.2884 | H10: =IF(E10=0,IF(C10*G10=0,F10,C10*G10),C10*D10)/1000 -> 59.880657 | I10: 1 | J10: =I10*H10 -> 59.880657 | K10: 0.93309851 | L10: =K10*J10 -> 55.874552 | M10: =L10/SUMIF($N$7:$N$42,$N10,$L$7:$L$42) -> 0.043094043 | N10: 1 | P10: arice | Q10: =_xlfn.XLOOKUP(P10,$W$7:$W$64,X$7:X$64,0) -> 119.932 | R10: =xGDP!E10 -> 59.880657 | S10: =IF(Q10,R10/Q10*1000,0) -> 499.2884 | T10: 729.2727 | U10: =IF(T10,S10/T10,1) -> 0.68463883 | W10: awhea | X10: =SUMIF($AB$6:$AJ$6,B$3,$AB10:$AJ10)/1000 -> 10.875 | Y10: =SUMIF($AL$6:$AT$6,B$3,$AL10:$AT10)/1000 -> 525.2677 | Z10: Wheat | AA10: SAS | AB10: 10875 | AC10: 13475 | AD10: 15687 | AK10: FAO | AL10: 525267.7 | AM10: 434369.2 | AX10: Wheat | AY10: =SUM(BF10:BH10) -> 10875 | AZ10: =SUM(BI10:BK10) -> 13475 | BA10: =SUM(BL10:BN10) -> 15687 | BE10: Wheat | BF10: 3651 | BG10: 7224 | BI10: 5950 | BJ10: 7525 | BL10: 7082 | BM10: 8605
A11: Other cereals (A119) | B11: aocer | C11: =SUMIF($W$7:$W$64,$B11,$X$7:$X$64) -> 5.065 | D11: =SUMIF($W$7:$W$64,$B11,$Y$7:$Y$64)*U11 -> 0 | E11: =D11*C11/1000 -> 0 | F11: =xGDP!D11 -> 0.29082038 | G11: =S11 -> 57.417646 | H11: =IF(E11=0,IF(C11*G11=0,F11,C11*G11),C11*D11)/1000 -> 0.29082038 | I11: 1 | J11: =I11*H11 -> 0.29082038 | K11: 0.93309851 | L11: =K11*J11 -> 0.27136406 | M11: =L11/SUMIF($N$7:$N$42,$N11,$L$7:$L$42) -> 0.00020929339 | N11: 1 | P11: aocer | Q11: =_xlfn.XLOOKUP(P11,$W$7:$W$64,X$7:X$64,0) -> 5.065 | R11: =xGDP!E11 -> 0.29082038 | S11: =IF(Q11,R11/Q11*1000,0) -> 57.417646 | U11: =IF(T11,S11/T11,1) -> 1 | W11: acass | X11: =SUMIF($AB$6:$AJ$6,B$3,$AB11:$AJ11)/1000 -> 1041.843 | Y11: =SUMIF($AL$6:$AT$6,B$3,$AL11:$AT11)/1000 -> 279.9302 | Z11: Cassava | AA11: SAS | AB11: 1041843 | AC11: 1127199 | AD11: 1181825 | AK11: FAO | AL11: 279930.2 | AM11: 240307.9 | AX11: Cassava | AY11: =SUM(BF11:BH11) -> 1041843 | AZ11: =SUM(BI11:BK11) -> 1127199 | BA11: =SUM(BL11:BN11) -> 1181825 | BE11: Cassava | BF11: 451362 | BG11: 590481 | BI11: 486440 | BJ11: 640759 | BL11: 523117 | BM11: 658708
A12: Irish potatoes (A121) | B12: aipot | C12: =SUMIF($W$7:$W$64,$B12,$X$7:$X$64) -> 847.302 | D12: =SUMIF($W$7:$W$64,$B12,$Y$7:$Y$64)*U12 -> 200.69262 | E12: =D12*C12/1000 -> 170.04725 | F12: =xGDP!D12 -> 170.04725 | G12: =S12 -> 200.69262 | H12: =IF(E12=0,IF(C12*G12=0,F12,C12*G12),C12*D12)/1000 -> 170.04725 | I12: 1 | J12: =I12*H12 -> 170.04725 | K12: 0.9352899 | L12: =K12*J12 -> 159.04348 | M12: =L12/SUMIF($N$7:$N$42,$N12,$L$7:$L$42) -> 0.12266455 | N12: 1 | P12: aipot | Q12: =_xlfn.XLOOKUP(P12,$W$7:$W$64,X$7:X$64,0) -> 847.302 | R12: =xGDP!E12 -> 170.04725 | S12: =IF(Q12,R12/Q12*1000,0) -> 200.69262 | T12: 224.9563 | U12: =IF(T12,S12/T12,1) -> 0.89214046 | W12: aspot | X12: =SUMIF($AB$6:$AJ$6,B$3,$AB12:$AJ12)/1000 -> 1082.364 | Y12: =SUMIF($AL$6:$AT$6,B$3,$AL12:$AT12)/1000 -> 221.5486 | Z12: Sweet potato | AA12: SAS | AB12: 1082364 | AC12: 1186731 | AD12: 1247584 | AK12: FAO | AL12: 221548.6 | AM12: 162407 | AX12: Sweet potato | AY12: =SUM(BF12:BH12) -> 1082364 | AZ12: =SUM(BI12:BK12) -> 1186731 | BA12: =SUM(BL12:BN12) -> 1247584 | BE12: Sweet potato | BF12: 574500 | BG12: 483898 | BH12: 23966 | BI12: 661583 | BJ12: 498790 | BK12: 26358 | BL12: 674257 | BM12: 546788 | BN12: 26539
A13: Sweet potatoes (A122) | B13: aspot | C13: =SUMIF($W$7:$W$64,$B13,$X$7:$X$64) -> 1082.364 | D13: =SUMIF($W$7:$W$64,$B13,$Y$7:$Y$64)*U13 -> 139.85909 | E13: =D13*C13/1000 -> 151.37845 | F13: =xGDP!D13 -> 151.37845 | G13: =S13 -> 139.85909 | H13: =IF(E13=0,IF(C13*G13=0,F13,C13*G13),C13*D13)/1000 -> 151.37845 | I13: 1 | J13: =I13*H13 -> 151.37845 | K13: 0.9352899 | L13: =K13*J13 -> 141.58273 | M13: =L13/SUMIF($N$7:$N$42,$N13,$L$7:$L$42) -> 0.1091977 | N13: 1 | P13: aspot | Q13: =_xlfn.XLOOKUP(P13,$W$7:$W$64,X$7:X$64,0) -> 1082.364 | R13: =xGDP!E13 -> 151.37845 | S13: =IF(Q13,R13/Q13*1000,0) -> 139.85909 | T13: 221.5486 | U13: =IF(T13,S13/T13,1) -> 0.63127952 | W13: aipot | X13: =SUMIF($AB$6:$AJ$6,B$3,$AB13:$AJ13)/1000 -> 847.302 | Y13: =SUMIF($AL$6:$AT$6,B$3,$AL13:$AT13)/1000 -> 224.9563 | Z13: Irish potato | AA13: SAS | AB13: 847302 | AC13: 916063 | AD13: 973408 | AK13: FAO | AL13: 224956.3 | AM13: 223102.5 | AX13: Irish potato | AY13: =SUM(BF13:BH13) -> 847302 | AZ13: =SUM(BI13:BK13) -> 916063 | BA13: =SUM(BL13:BN13) -> 973408 | BE13: Irish potato | BF13: 378906 | BG13: 398934 | BH13: 69462 | BI13: 439512 | BJ13: 396064 | BK13: 80487 | BL13: 468931 | BM13: 422266 | BN13: 82211
A14: Cassava (A123) | B14: acass | C14: =SUMIF($W$7:$W$64,$B14,$X$7:$X$64) -> 1041.843 | D14: =SUMIF($W$7:$W$64,$B14,$Y$7:$Y$64)*U14 -> 120.36827 | E14: =D14*C14/1000 -> 125.40484 | F14: =xGDP!D14 -> 125.40484 | G14: =S14 -> 120.36827 | H14: =IF(E14=0,IF(C14*G14=0,F14,C14*G14),C14*D14)/1000 -> 125.40484 | I14: 1 | J14: =I14*H14 -> 125.40484 | K14: 0.9352899 | L14: =K14*J14 -> 117.28988 | M14: =L14/SUMIF($N$7:$N$42,$N14,$L$7:$L$42) -> 0.090461486 | N14: 1 | P14: acass | Q14: =_xlfn.XLOOKUP(P14,$W$7:$W$64,X$7:X$64,0) -> 1041.843 | R14: =xGDP!E14 -> 125.40484 | S14: =IF(Q14,R14/Q14*1000,0) -> 120.36827 | T14: 279.9302 | U14: =IF(T14,S14/T14,1) -> 0.42999386 | W14: aroot | X14: =SUMIF($AB$6:$AJ$6,B$3,$AB14:$AJ14)/1000 -> 222.761 | Y14: =SUMIF($AL$6:$AT$6,B$3,$AL14:$AT14)/1000 -> 264.6721 | Z14: Yams & Taro | AA14: SAS | AB14: 222761 | AC14: 167984 | AD14: 171804 | AK14: FAO | AL14: 264672.1 | AM14: 176627 | AX14: Yams & Taro | AY14: =SUM(BF14:BH14) -> 222761 | AZ14: =SUM(BI14:BK14) -> 167984 | BA14: =SUM(BL14:BN14) -> 171804 | BE14: Yams & Taro | BF14: 129630 | BG14: 93131 | BI14: 70653 | BJ14: 97331 | BL14: 71104 | BM14: 100700
A15: Other roots & tubers (A129) | B15: aroot | C15: =SUMIF($W$7:$W$64,$B15,$X$7:$X$64) -> 222.761 | D15: =SUMIF($W$7:$W$64,$B15,$Y$7:$Y$64)*U15 -> 95.689089 | E15: =D15*C15/1000 -> 21.315797 | F15: =xGDP!D15 -> 21.315797 | G15: =S15 -> 95.689089 | H15: =IF(E15=0,IF(C15*G15=0,F15,C15*G15),C15*D15)/1000 -> 21.315797 | I15: 1 | J15: =I15*H15 -> 21.315797 | K15: 0.9352899 | L15: =K15*J15 -> 19.93645 | M15: =L15/SUMIF($N$7:$N$42,$N15,$L$7:$L$42) -> 0.01537627 | N15: 1 | P15: aroot | Q15: =_xlfn.XLOOKUP(P15,$W$7:$W$64,X$7:X$64,0) -> 222.761 | R15: =xGDP!E15 -> 21.315797 | S15: =IF(Q15,R15/Q15*1000,0) -> 95.689089 | T15: 264.6721 | U15: =IF(T15,S15/T15,1) -> 0.36153826 | W15: abanc | X15: =SUMIF($AB$6:$AJ$6,B$3,$AB15:$AJ15)/1000 -> 731.349 | Y15: =SUMIF($AL$6:$AT$6,B$3,$AL15:$AT15)/1000 -> 247.018 | Z15: Cooking banana | AA15: SAS | AB15: 731349 | AC15: 759696 | AD15: 820917 | AK15: FAO | AL15: 247018 | AM15: 204961 | AX15: Banana | AY15: =SUM(BF15:BH15) -> 1739007 | AZ15: =SUM(BI15:BK15) -> 1769697 | BA15: =SUM(BL15:BN15) -> 1850632 | BE15: Banana | BF15: 985485 | BG15: 753522 | BI15: 952684 | BJ15: 817013 | BL15: 1020141 | BM15: 830491
A16: Dried beans (A131) | B16: abean | C16: =SUMIF($W$7:$W$64,$B16,$X$7:$X$64) -> 454.174 | D16: =SUMIF($W$7:$W$64,$B16,$Y$7:$Y$64)*U16 -> 496.8112 | E16: =D16*C16/1000 -> 225.63873 | F16: =xGDP!D16 -> 225.63873 | G16: =S16 -> 496.8112 | H16: =IF(E16=0,IF(C16*G16=0,F16,C16*G16),C16*D16)/1000 -> 225.63873 | I16: 1 | J16: =I16*H16 -> 225.63873 | K16: 0.95070324 | L16: =K16*J16 -> 214.51547 | M16: =L16/SUMIF($N$7:$N$42,$N16,$L$7:$L$42) -> 0.16544811 | N16: 1 | P16: abean | Q16: =_xlfn.XLOOKUP(P16,$W$7:$W$64,X$7:X$64,0) -> 454.174 | R16: =xGDP!E16 -> 225.63873 | S16: =IF(Q16,R16/Q16*1000,0) -> 496.8112 | T16: 456.469 | U16: =IF(T16,S16/T16,1) -> 1.0883788 | W16: abans | X16: =SUMIF($AB$6:$AJ$6,B$3,$AB16:$AJ16)/1000 -> 224.344 | Y16: =SUMIF($AL$6:$AT$6,B$3,$AL16:$AT16)/1000 -> 247.018 | Z16: Dessert banana | AA16: SAS | AB16: 224344 | AC16: 229340 | AD16: 241210 | AK16: FAO | AL16: 247018 | AM16: 204961 | AX16: Cooking banana | AY16: =SUM(BF16:BH16) -> 731349 | AZ16: =SUM(BI16:BK16) -> 759696 | BA16: =SUM(BL16:BN16) -> 820917 | BE16: Cooking banana | BF16: 415868 | BG16: 315481 | BI16: 406044 | BJ16: 353652 | BL16: 456351 | BM16: 364566
A17: Peas & other legumes (A132) | B17: apeas | C17: =SUMIF($W$7:$W$64,$B17,$X$7:$X$64) -> 12.423 | D17: =SUMIF($W$7:$W$64,$B17,$Y$7:$Y$64)*U17 -> 1775.9912 | E17: =D17*C17/1000 -> 22.063138 | F17: =xGDP!D17 -> 22.063138 | G17: =S17 -> 1775.9912 | H17: =IF(E17=0,IF(C17*G17=0,F17,C17*G17),C17*D17)/1000 -> 22.063138 | I17: 1 | J17: =I17*H17 -> 22.063138 | K17: 0.95070324 | L17: =K17*J17 -> 20.975497 | M17: =L17/SUMIF($N$7:$N$42,$N17,$L$7:$L$42) -> 0.01617765 | N17: 1 | P17: apeas | Q17: =_xlfn.XLOOKUP(P17,$W$7:$W$64,X$7:X$64,0) -> 12.423 | R17: =xGDP!E17 -> 22.063138 | S17: =IF(Q17,R17/Q17*1000,0) -> 1775.9912 | T17: 1024.0141 | U17: =IF(T17,S17/T17,1) -> 1.7343425 | W17: abanb | X17: =SUMIF($AB$6:$AJ$6,B$3,$AB17:$AJ17)/1000 -> 783.314 | Y17: =SUMIF($AL$6:$AT$6,B$3,$AL17:$AT17)/1000 -> 247.018 | Z17: Banana for beer | AA17: SAS | AB17: 783314 | AC17: 780660 | AD17: 805783 | AK17: FAO | AL17: 247018 | AM17: 204961 | AX17: Dessert banana | AY17: =SUM(BF17:BH17) -> 224344 | AZ17: =SUM(BI17:BK17) -> 229340 | BA17: =SUM(BL17:BN17) -> 241210 | BE17: Dessert banana | BF17: 113032 | BG17: 111312 | BI17: 112283 | BJ17: 117057 | BL17: 112937 | BM17: 128273
A18: Other vegetables (A139) | B18: avege | C18: =SUMIF($W$7:$W$64,$B18,$X$7:$X$64) -> 318.899 | D18: =SUMIF($W$7:$W$64,$B18,$Y$7:$Y$64)*U18 -> 0 | E18: =D18*C18/1000 -> 0 | F18: =xGDP!D18 -> 149.08801 | G18: =S18 -> 467.50855 | H18: =IF(E18=0,IF(C18*G18=0,F18,C18*G18),C18*D18)/1000 -> 149.08801 | I18: 1 | J18: =I18*H18 -> 149.08801 | K18: 0.95070324 | L18: =K18*J18 -> 141.73845 | M18: =L18/SUMIF($N$7:$N$42,$N18,$L$7:$L$42) -> 0.1093178 | N18: 1 | P18: avege | Q18: =_xlfn.XLOOKUP(P18,$W$7:$W$64,X$7:X$64,0) -> 318.899 | R18: =xGDP!E18 -> 149.08801 | S18: =IF(Q18,R18/Q18*1000,0) -> 467.50855 | U18: =IF(T18,S18/T18,1) -> 1 | W18: abean | X18: =SUMIF($AB$6:$AJ$6,B$3,$AB18:$AJ18)/1000 -> 454.174 | Y18: =SUMIF($AL$6:$AT$6,B$3,$AL18:$AT18)/1000 -> 456.469 | Z18: Beans | AA18: SAS | AB18: 454174 | AC18: 485756 | AD18: 484251 | AK18: FAO | AL18: 456469 | AM18: 387629.5 | AX18: Banana for beer | AY18: =SUM(BF18:BH18) -> 783314 | AZ18: =SUM(BI18:BK18) -> 780660 | BA18: =SUM(BL18:BN18) -> 805783 | BE18: Banana for beer | BF18: 456585 | BG18: 326729 | BI18: 434356 | BJ18: 346304 | BL18: 450853 | BM18: 354930
A19: Bananas for beer (A141) | B19: abanb | C19: =SUMIF($W$7:$W$64,$B19,$X$7:$X$64) -> 783.314 | D19: =SUMIF($W$7:$W$64,$B19,$Y$7:$Y$64)*U19 -> 104.64463 | E19: =D19*C19/1000 -> 81.9696 | F19: =xGDP!D19 -> 81.9696 | G19: =S19 -> 104.64463 | H19: =IF(E19=0,IF(C19*G19=0,F19,C19*G19),C19*D19)/1000 -> 81.9696 | I19: 1 | J19: =I19*H19 -> 81.9696 | K19: 0.97790125 | L19: =K19*J19 -> 80.158174 | M19: =L19/SUMIF($N$7:$N$42,$N19,$L$7:$L$42) -> 0.061823132 | N19: 1 | P19: abanb | Q19: =_xlfn.XLOOKUP(P19,$W$7:$W$64,X$7:X$64,0) -> 783.314 | R19: =xGDP!E19 -> 81.9696 | S19: =IF(Q19,R19/Q19*1000,0) -> 104.64463 | T19: 247.018 | U19: =IF(T19,S19/T19,1) -> 0.42363158 | W19: apeas | X19: =SUMIF($AB$6:$AJ$6,B$3,$AB19:$AJ19)/1000 -> 12.423 | Y19: =SUMIF($AL$6:$AT$6,B$3,$AL19:$AT19)/1000 -> 1024.0141 | Z19: Peas | AA19: SAS | AB19: 12423 | AC19: 14827 | AD19: 15400 | AK19: FAO | AL19: 1024014.1 | AM19: 797632.3 | AX19: Beans | AY19: =SUM(BF19:BH19) -> 454174 | AZ19: =SUM(BI19:BK19) -> 485756 | BA19: =SUM(BL19:BN19) -> 484251 | BE19: Beans | BF19: 224233 | BG19: 226131 | BH19: 3810 | BI19: 251189 | BJ19: 233540 | BK19: 1027 | BL19: 252569 | BM19: 230744 | BN19: 938
A20: Bananas for cooking (A142) | B20: abanc | C20: =SUMIF($W$7:$W$64,$B20,$X$7:$X$64) -> 731.349 | D20: =SUMIF($W$7:$W$64,$B20,$Y$7:$Y$64)*U20 -> 204.07481 | E20: =D20*C20/1000 -> 149.24991 | F20: =xGDP!D20 -> 149.24991 | G20: =S20 -> 204.07481 | H20: =IF(E20=0,IF(C20*G20=0,F20,C20*G20),C20*D20)/1000 -> 149.24991 | I20: 1 | J20: =I20*H20 -> 149.24991 | K20: 0.97790125 | L20: =K20*J20 -> 145.95167 | M20: =L20/SUMIF($N$7:$N$42,$N20,$L$7:$L$42) -> 0.1125673 | N20: 1 | P20: abanc | Q20: =_xlfn.XLOOKUP(P20,$W$7:$W$64,X$7:X$64,0) -> 731.349 | R20: =xGDP!E20 -> 149.24991 | S20: =IF(Q20,R20/Q20*1000,0) -> 204.07481 | T20: 247.018 | U20: =IF(T20,S20/T20,1) -> 0.82615362 | W20: agnut | X20: =SUMIF($AB$6:$AJ$6,B$3,$AB20:$AJ20)/1000 -> 20.678 | Y20: =SUMIF($AL$6:$AT$6,B$3,$AL20:$AT20)/1000 -> 1061.6885 | Z20: Groundnut | AA20: SAS | AB20: 20678 | AC20: 22280 | AD20: 19562 | AK20: FAO | AL20: 1061688.5 | AM20: 991562.4 | AX20: Peas | AY20: =SUM(BF20:BH20) -> 12423 | AZ20: =SUM(BI20:BK20) -> 14827 | BA20: =SUM(BL20:BN20) -> 15400 | BE20: Peas | BF20: 6768 | BG20: 5600 | BH20: 55 | BI20: 9001 | BJ20: 5689 | BK20: 137 | BL20: 9115 | BM20: 6136 | BN20: 149
A21: Bananas (sweet) (A143) | B21: abans | C21: =SUMIF($W$7:$W$64,$B21,$X$7:$X$64) -> 224.344 | D21: =SUMIF($W$7:$W$64,$B21,$Y$7:$Y$64)*U21 -> 120.64775 | E21: =D21*C21/1000 -> 27.066598 | F21: =xGDP!D21 -> 27.066598 | G21: =S21 -> 120.64775 | H21: =IF(E21=0,IF(C21*G21=0,F21,C21*G21),C21*D21)/1000 -> 27.066598 | I21: 1 | J21: =I21*H21 -> 27.066598 | K21: 0.97790125 | L21: =K21*J21 -> 26.46846 | M21: =L21/SUMIF($N$7:$N$42,$N21,$L$7:$L$42) -> 0.020414176 | N21: 1 | P21: abans | Q21: =_xlfn.XLOOKUP(P21,$W$7:$W$64,X$7:X$64,0) -> 224.344 | R21: =xGDP!E21 -> 27.066598 | S21: =IF(Q21,R21/Q21*1000,0) -> 120.64775 | T21: 247.018 | U21: =IF(T21,S21/T21,1) -> 0.48841683 | W21: asoya | X21: =SUMIF($AB$6:$AJ$6,B$3,$AB21:$AJ21)/1000 -> 23.803 | Y21: =SUMIF($AL$6:$AT$6,B$3,$AL21:$AT21)/1000 -> 478.8119 | Z21: Soybean | AA21: SAS | AB21: 23803 | AC21: 22810 | AD21: 24525 | AK21: FAO | AL21: 478811.9 | AM21: 453807.8 | AX21: Groundnut | AY21: =SUM(BF21:BH21) -> 20678 | AZ21: =SUM(BI21:BK21) -> 22280 | BA21: =SUM(BL21:BN21) -> 19562 | BE21: Groundnut | BF21: 11873 | BG21: 8805 | BI21: 12546 | BJ21: 9734 | BL21: 9362 | BM21: 10200
A22: Other fruit & nuts (A149) | B22: afrui | C22: =SUMIF($W$7:$W$64,$B22,$X$7:$X$64) -> 71.732 | D22: =SUMIF($W$7:$W$64,$B22,$Y$7:$Y$64)*U22 -> 0 | E22: =D22*C22/1000 -> 0 | F22: =xGDP!D22 -> 25.309965 | G22: =S22 -> 352.84065 | H22: =IF(E22=0,IF(C22*G22=0,F22,C22*G22),C22*D22)/1000 -> 25.309965 | I22: 1 | J22: =I22*H22 -> 25.309965 | K22: 0.97790125 | L22: =K22*J22 -> 24.750647 | M22: =L22/SUMIF($N$7:$N$42,$N22,$L$7:$L$42) -> 0.019089288 | N22: 1 | P22: afrui | Q22: =_xlfn.XLOOKUP(P22,$W$7:$W$64,X$7:X$64,0) -> 71.732 | R22: =xGDP!E22 -> 25.309965 | S22: =IF(Q22,R22/Q22*1000,0) -> 352.84065 | U22: =IF(T22,S22/T22,1) -> 1 | W22: avege | X22: =SUMIF($AB$6:$AJ$6,B$3,$AB22:$AJ22)/1000 -> 318.899 | Y22: =SUMIF($AL$6:$AT$6,B$3,$AL22:$AT22)/1000 -> 0 | Z22: Vegetables | AA22: SAS | AB22: 318899 | AC22: 348627 | AD22: 350505 | AK22: FAO | AX22: Soybean | AY22: =SUM(BF22:BH22) -> 23803 | AZ22: =SUM(BI22:BK22) -> 22810 | BA22: =SUM(BL22:BN22) -> 24525 | BE22: Soybean | BF22: 10686 | BG22: 12925 | BH22: 192 | BI22: 12156 | BJ22: 10427 | BK22: 227 | BL22: 13638 | BM22: 10588 | BN22: 299
A23: Ground nuts (A151) | B23: agnut | C23: =SUMIF($W$7:$W$64,$B23,$X$7:$X$64) -> 20.678 | D23: =SUMIF($W$7:$W$64,$B23,$Y$7:$Y$64)*U23 -> 546.18707 | E23: =D23*C23/1000 -> 11.294056 | F23: =xGDP!D23 -> 11.294056 | G23: =S23 -> 546.18707 | H23: =IF(E23=0,IF(C23*G23=0,F23,C23*G23),C23*D23)/1000 -> 11.294056 | I23: 1 | J23: =I23*H23 -> 11.294056 | K23: 0.75407428 | L23: =K23*J23 -> 8.5165573 | M23: =L23/SUMIF($N$7:$N$42,$N23,$L$7:$L$42) -> 0.0065685159 | N23: 1 | P23: agnut | Q23: =_xlfn.XLOOKUP(P23,$W$7:$W$64,X$7:X$64,0) -> 20.678 | R23: =xGDP!E23 -> 11.294056 | S23: =IF(Q23,R23/Q23*1000,0) -> 546.18707 | T23: 1061.6885 | U23: =IF(T23,S23/T23,1) -> 0.51445134 | W23: afrui | X23: =SUMIF($AB$6:$AJ$6,B$3,$AB23:$AJ23)/1000 -> 71.732 | Y23: =SUMIF($AL$6:$AT$6,B$3,$AL23:$AT23)/1000 -> 0 | Z23: Fruits | AA23: SAS | AB23: 71732 | AC23: 53594 | AD23: 77793 | AK23: FAO | AX23: Vegetables | AY23: =SUM(BF23:BH23) -> 318899 | AZ23: =SUM(BI23:BK23) -> 348627 | BA23: =SUM(BL23:BN23) -> 350505 | BE23: Vegetables | BF23: 133118 | BG23: 155476 | BH23: 30305 | BI23: 162938 | BJ23: 145272 | BK23: 40417 | BL23: 158927 | BM23: 155506 | BN23: 36072
A24: Soya (A152) | B24: asoya | C24: =SUMIF($W$7:$W$64,$B24,$X$7:$X$64) -> 23.803 | D24: =SUMIF($W$7:$W$64,$B24,$Y$7:$Y$64)*U24 -> 155.77146 | E24: =D24*C24/1000 -> 3.7078281 | F24: =xGDP!D24 -> 3.7078281 | G24: =S24 -> 155.77146 | H24: =IF(E24=0,IF(C24*G24=0,F24,C24*G24),C24*D24)/1000 -> 3.7078281 | I24: 1 | J24: =I24*H24 -> 3.7078281 | K24: 0.75407428 | L24: =K24*J24 -> 2.7959778 | M24: =L24/SUMIF($N$7:$N$42,$N24,$L$7:$L$42) -> 0.0021564376 | N24: 1 | P24: asoya | Q24: =_xlfn.XLOOKUP(P24,$W$7:$W$64,X$7:X$64,0) -> 23.803 | R24: =xGDP!E24 -> 3.7078281 | S24: =IF(Q24,R24/Q24*1000,0) -> 155.77146 | T24: 478.8119 | U24: =IF(T24,S24/T24,1) -> 0.32532913 | W24: acoff | X24: =SUMIF($AB$6:$AJ$6,B$3,$AB24:$AJ24)/1000 -> 22.009 | Y24: =SUMIF($AL$6:$AT$6,B$3,$AL24:$AT24)/1000 -> 0 | Z24: Coffee | AA24: NAEB | AB24: 22009 | AC24: 22390 | AD24: 19231 | AK24: FAO | AX24: Fruits | AY24: =SUM(BF24:BH24) -> 71732 | AZ24: =SUM(BI24:BK24) -> 53594 | BA24: =SUM(BL24:BN24) -> 77793 | BE24: Fruits | BF24: 54940 | BG24: 16378 | BH24: 414 | BI24: 35883 | BJ24: 17711 | BL24: 48791 | BM24: 29002
A25: Other oil seeds (A159) | B25: aoils | C25: =SUMIF($W$7:$W$64,$B25,$X$7:$X$64) -> 0 | D25: =SUMIF($W$7:$W$64,$B25,$Y$7:$Y$64)*U25 -> 0 | E25: =D25*C25/1000 -> 0 | F25: =xGDP!D25 -> 0 | G25: =S25 -> 0 | H25: =IF(E25=0,IF(C25*G25=0,F25,C25*G25),C25*D25)/1000 -> 0 | I25: 1 | J25: =I25*H25 -> 0 | K25: 0.75407428 | L25: =K25*J25 -> 0 | M25: =L25/SUMIF($N$7:$N$42,$N25,$L$7:$L$42) -> 0 | N25: 1 | P25: aoils | Q25: =_xlfn.XLOOKUP(P25,$W$7:$W$64,X$7:X$64,0) -> 0 | R25: =xGDP!E25 -> 0 | S25: =IF(Q25,R25/Q25*1000,0) -> 0 | U25: =IF(T25,S25/T25,1) -> 1 | W25: ateal | X25: =SUMIF($AB$6:$AJ$6,B$3,$AB25:$AJ25)/1000 -> 25.628 | Y25: =SUMIF($AL$6:$AT$6,B$3,$AL25:$AT25)/1000 -> 0 | Z25: Tea | AA25: NAEB | AB25: 25628 | AC25: 27887 | AD25: 31068 | AK25: FAO | AW25: Cultivated area for major crops (Ha) | AX25: Maize | AY25: =SUM(BF25:BH25) -> 295739 | AZ25: =SUM(BI25:BK25) -> 296330 | BA25: =SUM(BL25:BN25) -> 288298 | BD25: Cultivated area for major crops (Ha) | BE25: Maize | BF25: 210609 | BG25: 85130 | BI25: 218179 | BJ25: 78151 | BL25: 215159 | BM25: 73139
A26: Coffee, not roasted, not decaffeinated (A210) | B26: acoff | C26: =SUMIF($W$7:$W$64,$B26,$X$7:$X$64) -> 22.009 | D26: =SUMIF($W$7:$W$64,$B26,$Y$7:$Y$64)*U26 -> 0 | E26: =D26*C26/1000 -> 0 | F26: =xGDP!D26 -> 77.156236 | G26: =S26 -> 3505.6675 | H26: =IF(E26=0,IF(C26*G26=0,F26,C26*G26),C26*D26)/1000 -> 77.156236 | I26: 1 | J26: =I26*H26 -> 77.156236 | K26: 0.91848864 | L26: =K26*J26 -> 70.867127 | M26: =L26/SUMIF($N$7:$N$42,$N26,$L$7:$L$42) -> 0.51408282 | N26: 2 | P26: acoff | Q26: =_xlfn.XLOOKUP(P26,$W$7:$W$64,X$7:X$64,0) -> 22.009 | R26: =xGDP!E26 -> 77.156236 | S26: =IF(Q26,R26/Q26*1000,0) -> 3505.6675 | U26: =IF(T26,S26/T26,1) -> 1 | W26: asugr | X26: =SUMIF($AB$6:$AJ$6,B$3,$AB26:$AJ26)/1000 -> 105.939 | Y26: =SUMIF($AL$6:$AT$6,B$3,$AL26:$AT26)/1000 -> 0 | Z26: Sugar cane | AA26: FAO | AB26: 105939 | AC26: 116473 | AK26: FAO | AX26: Sorghum | AY26: =SUM(BF26:BH26) -> 142396 | AZ26: =SUM(BI26:BK26) -> 144137 | BA26: =SUM(BL26:BN26) -> 161850 | BE26: Sorghum | BF26: 29702 | BG26: 112694 | BI26: 27151 | BJ26: 116986 | BL26: 30467 | BM26: 131383
A27: Tea (unprocessed green leaf) (A220) | B27: ateal | C27: =SUMIF($W$7:$W$64,$B27,$X$7:$X$64) -> 25.628 | D27: =SUMIF($W$7:$W$64,$B27,$Y$7:$Y$64)*U27 -> 0 | E27: =D27*C27/1000 -> 0 | F27: =xGDP!D27 -> 24.490147 | G27: =S27 -> 955.60119 | H27: =IF(E27=0,IF(C27*G27=0,F27,C27*G27),C27*D27)/1000 -> 24.490147 | I27: 1 | J27: =I27*H27 -> 24.490147 | K27: 0.91391359 | L27: =K27*J27 -> 22.381878 | M27: =L27/SUMIF($N$7:$N$42,$N27,$L$7:$L$42) -> 0.16236215 | N27: 2 | P27: ateal | Q27: =_xlfn.XLOOKUP(P27,$W$7:$W$64,X$7:X$64,0) -> 25.628 | R27: =xGDP!E27 -> 24.490147 | S27: =IF(Q27,R27/Q27*1000,0) -> 955.60119 | U27: =IF(T27,S27/T27,1) -> 1 | W27: atoba | X27: =SUMIF($AB$6:$AJ$6,B$3,$AB27:$AJ27)/1000 -> 5.002 | Y27: =SUMIF($AL$6:$AT$6,B$3,$AL27:$AT27)/1000 -> 0 | Z27: Tobacco, unmanufactured | AA27: FAO | AB27: 5002 | AC27: 5029 | AK27: FAO | AX27: Paddy rice | AY27: =SUM(BF27:BH27) -> 34205 | AZ27: =SUM(BI27:BK27) -> 33677 | BA27: =SUM(BL27:BN27) -> 32896 | BE27: Paddy rice | BF27: 16922 | BG27: 17283 | BI27: 16938 | BJ27: 16739 | BL27: 14671 | BM27: 18225
A28: Tobacco, raw (A291) | B28: atoba | C28: =SUMIF($W$7:$W$64,$B28,$X$7:$X$64) -> 5.002 | D28: =SUMIF($W$7:$W$64,$B28,$Y$7:$Y$64)*U28 -> 0 | E28: =D28*C28/1000 -> 0 | F28: =xGDP!D28 -> 4.1913525 | G28: =S28 -> 837.93532 | H28: =IF(E28=0,IF(C28*G28=0,F28,C28*G28),C28*D28)/1000 -> 4.1913525 | I28: 1 | J28: =I28*H28 -> 4.1913525 | K28: 0.92568267 | L28: =K28*J28 -> 3.8798623 | M28: =L28/SUMIF($N$7:$N$42,$N28,$L$7:$L$42) -> 0.028145216 | N28: 2 | P28: atoba | Q28: =_xlfn.XLOOKUP(P28,$W$7:$W$64,X$7:X$64,0) -> 5.002 | R28: =xGDP!E28 -> 4.1913525 | S28: =IF(Q28,R28/Q28*1000,0) -> 837.93532 | U28: =IF(T28,S28/T28,1) -> 1 | W28: apyre | X28: =SUMIF($AB$6:$AJ$6,B$3,$AB28:$AJ28)/1000 -> 5.082 | Y28: =SUMIF($AL$6:$AT$6,B$3,$AL28:$AT28)/1000 -> 0 | Z28: Pyrethrum, dried | AA28: FAO | AB28: 5082 | AC28: 2081 | AK28: FAO | AX28: Wheat | AY28: =SUM(BF28:BH28) -> 10761 | AZ28: =SUM(BI28:BK28) -> 12225 | BA28: =SUM(BL28:BN28) -> 13234 | BE28: Wheat | BF28: 3313 | BG28: 7448 | BI28: 4490 | BJ28: 7735 | BL28: 5487 | BM28: 7747
A29: Sugar cane (A292) | B29: asugr | C29: =SUMIF($W$7:$W$64,$B29,$X$7:$X$64) -> 105.939 | D29: =SUMIF($W$7:$W$64,$B29,$Y$7:$Y$64)*U29 -> 0 | E29: =D29*C29/1000 -> 0 | F29: =xGDP!D29 -> 9.5983389 | G29: =S29 -> 90.602506 | H29: =IF(E29=0,IF(C29*G29=0,F29,C29*G29),C29*D29)/1000 -> 9.5983389 | I29: 1 | J29: =I29*H29 -> 9.5983389 | K29: 0.92568267 | L29: =K29*J29 -> 8.885016 | M29: =L29/SUMIF($N$7:$N$42,$N29,$L$7:$L$42) -> 0.064453496 | N29: 2 | P29: asugr | Q29: =_xlfn.XLOOKUP(P29,$W$7:$W$64,X$7:X$64,0) -> 105.939 | R29: =xGDP!E29 -> 9.5983389 | S29: =IF(Q29,R29/Q29*1000,0) -> 90.602506 | U29: =IF(T29,S29/T29,1) -> 1 | W29: aocer | X29: =SUMIF($AB$6:$AJ$6,B$3,$AB29:$AJ29)/1000 -> 5.065 | Y29: =SUMIF($AL$6:$AT$6,B$3,$AL29:$AT29)/1000 -> 0 | Z29: Millet | AA29: FAO | AB29: 5065 | AC29: 5116 | AK29: FAO | AX29: Cassava | AY29: =SUM(BF29:BH29) -> 384374 | AZ29: =SUM(BI29:BK29) -> 383202 | BA29: =SUM(BL29:BN29) -> 382646 | BE29: Cassava | BF29: 219845 | BG29: 164529 | BI29: 194717 | BJ29: 188485 | BL29: 195135 | BM29: 187511
A30: Pyrethrum (A293) | B30: apyre | C30: =SUMIF($W$7:$W$64,$B30,$X$7:$X$64) -> 5.082 | D30: =SUMIF($W$7:$W$64,$B30,$Y$7:$Y$64)*U30 -> 0 | E30: =D30*C30/1000 -> 0 | F30: =xGDP!D30 -> 5.5822257 | G30: =S30 -> 1098.4309 | H30: =IF(E30=0,IF(C30*G30=0,F30,C30*G30),C30*D30)/1000 -> 5.5822257 | I30: 1 | J30: =I30*H30 -> 5.5822257 | K30: 0.92568267 | L30: =K30*J30 -> 5.1673696 | M30: =L30/SUMIF($N$7:$N$42,$N30,$L$7:$L$42) -> 0.037485023 | N30: 2 | P30: apyre | Q30: =_xlfn.XLOOKUP(P30,$W$7:$W$64,X$7:X$64,0) -> 5.082 | R30: =xGDP!E30 -> 5.5822257 | S30: =IF(Q30,R30/Q30*1000,0) -> 1098.4309 | U30: =IF(T30,S30/T30,1) -> 1 | W30: aocrp | X30: =SUMIF($AB$6:$AJ$6,B$3,$AB30:$AJ30)/1000 -> 4.75 | Y30: =SUMIF($AL$6:$AT$6,B$3,$AL30:$AT30)/1000 -> 0 | Z30: Chillies and peppers, green | AA30: FAO | AB30: 4750 | AC30: 5009 | AK30: FAO | AX30: Sweet potato | AY30: =SUM(BF30:BH30) -> 180534 | AZ30: =SUM(BI30:BK30) -> 173122 | BA30: =SUM(BL30:BN30) -> 183889 | BE30: Sweet potato | BF30: 87725 | BG30: 85200 | BH30: 7609 | BI30: 87456 | BJ30: 79983 | BK30: 5683 | BL30: 97639 | BM30: 80919 | BN30: 5331
A31: Agricultural products n.e.c. (A299) | B31: aocrp | C31: =SUMIF($W$7:$W$64,$B31,$X$7:$X$64) -> 4.75 | D31: =SUMIF($W$7:$W$64,$B31,$Y$7:$Y$64)*U31 -> 0 | E31: =D31*C31/1000 -> 0 | F31: =xGDP!D31 -> 28.811518 | G31: =S31 -> 6065.5828 | H31: =IF(E31=0,IF(C31*G31=0,F31,C31*G31),C31*D31)/1000 -> 28.811518 | I31: 1 | J31: =I31*H31 -> 28.811518 | K31: 0.92568267 | L31: =K31*J31 -> 26.670323 | M31: =L31/SUMIF($N$7:$N$42,$N31,$L$7:$L$42) -> 0.1934713 | N31: 2 | P31: aocrp | Q31: =_xlfn.XLOOKUP(P31,$W$7:$W$64,X$7:X$64,0) -> 4.75 | R31: =xGDP!E31 -> 28.811518 | S31: =IF(Q31,R31/Q31*1000,0) -> 6065.5828 | T31: 527.7084 | U31: =IF(T31,S31/T31,1) -> 11.494194 | W31: aeggs | X31: =SUMIF($AB$6:$AJ$6,B$3,$AB31:$AJ31)/1000 -> 7.5 | Y31: =SUMIF($AL$6:$AT$6,B$3,$AL31:$AT31)/1000 -> 2187.4587 | Z31: Eggs, hen, in shell | AA31: FAO | AB31: 7500 | AC31: 7800 | AK31: FAO | AL31: 2187458.7 | AM31: 2202165.1 | AX31: Irish potato | AY31: =SUM(BF31:BH31) -> 92800 | AZ31: =SUM(BI31:BK31) -> 119220 | BA31: =SUM(BL31:BN31) -> 107590 | BE31: Irish potato | BF31: 38351 | BG31: 45923 | BH31: 8526 | BI31: 50836 | BJ31: 60644 | BK31: 7740 | BL31: 49728 | BM31: 49244 | BN31: 8618
A32: Bovine cattle, live (A311) | B32: acatt | C32: =SUMIF($W$7:$W$64,$B32,$X$7:$X$64) -> 29.833 | D32: =SUMIF($W$7:$W$64,$B32,$Y$7:$Y$64)*U32 -> 3057.0048 | E32: =D32*C32/1000 -> 91.199625 | F32: =xGDP!D32 -> 91.199625 | G32: =S32 -> 3057.0048 | H32: =IF(E32=0,IF(C32*G32=0,F32,C32*G32),C32*D32)/1000 -> 91.199625 | I32: 1 | J32: =I32*H32 -> 91.199625 | K32: 0.91678309 | L32: =K32*J32 -> 83.610275 | M32: =L32/SUMIF($N$7:$N$42,$N32,$L$7:$L$42) -> 0.41106388 | N32: 3 | P32: acatt | Q32: 29.833 | R32: =xGDP!E32 -> 91.199625 | S32: =IF(Q32,R32/Q32*1000,0) -> 3057.0048 | T32: 2156.9806 | U32: =IF(T32,S32/T32,1) -> 1.4172612 | W32: ahunt | X32: =SUMIF($AB$6:$AJ$6,B$3,$AB32:$AJ32)/1000 -> 4.309 | Y32: =SUMIF($AL$6:$AT$6,B$3,$AL32:$AT32)/1000 -> 0 | Z32: Hides, cattle, fresh | AA32: FAO | AB32: 4309 | AC32: 4724 | AK32: FAO | AX32: Yams & Taro | AY32: =SUM(BF32:BH32) -> 57349 | AZ32: =SUM(BI32:BK32) -> 30693 | BA32: =SUM(BL32:BN32) -> 28164 | BE32: Yams & Taro | BF32: 35321 | BG32: 22028 | BI32: 11406 | BJ32: 19287 | BL32: 12695 | BM32: 15469
A33: Sheep, goats, pigs,live (A312) | B33: asmlr | C33: =SUMIF($W$7:$W$64,$B33,$X$7:$X$64) -> 27.718 | D33: =SUMIF($W$7:$W$64,$B33,$Y$7:$Y$64)*U33 -> 1895.8831 | E33: =D33*C33/1000 -> 52.550089 | F33: =xGDP!D33 -> 33.231297 | G33: =S33 -> 1198.9067 | H33: =IF(E33=0,IF(C33*G33=0,F33,C33*G33),C33*D33)/1000 -> 52.550089 | I33: 1 | J33: =I33*H33 -> 52.550089 | K33: 0.91678309 | L33: =K33*J33 -> 48.177033 | M33: =L33/SUMIF($N$7:$N$42,$N33,$L$7:$L$42) -> 0.23685891 | N33: 3 | P33: asmlr | Q33: 27.718 | R33: =xGDP!E33 -> 33.231297 | S33: =IF(Q33,R33/Q33*1000,0) -> 1198.9067 | T33: 2304.1667 | U33: =IF(T33,S33/T33,1) -> 0.52032118 | W33: ahony | X33: =SUMIF($AB$6:$AJ$6,B$3,$AB33:$AJ33)/1000 -> 5 | Y33: =SUMIF($AL$6:$AT$6,B$3,$AL33:$AT33)/1000 -> 3518.633 | Z33: Honey, natural | AA33: FAO | AB33: 5000 | AC33: 5000 | AK33: FAO | AL33: 3518633 | AM33: 3740020 | AX33: Banana | AY33: =SUM(BF33:BH33) -> 464321 | AZ33: =SUM(BI33:BK33) -> 456473 | BA33: =SUM(BL33:BN33) -> 490413 | BE33: Banana | BF33: 237849 | BG33: 226472 | BI33: 224053 | BJ33: 232420 | BL33: 253996 | BM33: 236417
A34: Poultry, live (A313) | B34: apoul | C34: =SUMIF($W$7:$W$64,$B34,$X$7:$X$64) -> 15.87 | D34: =SUMIF($W$7:$W$64,$B34,$Y$7:$Y$64)*U34 -> 0 | E34: =D34*C34/1000 -> 0 | F34: =xGDP!D34 -> 14.456565 | G34: =S34 -> 910.93665 | H34: =IF(E34=0,IF(C34*G34=0,F34,C34*G34),C34*D34)/1000 -> 14.456565 | I34: 1 | J34: =I34*H34 -> 14.456565 | K34: 0.91678309 | L34: =K34*J34 -> 13.253534 | M34: =L34/SUMIF($N$7:$N$42,$N34,$L$7:$L$42) -> 0.065160044 | N34: 3 | P34: apoul | Q34: 15.87 | R34: =xGDP!E34 -> 14.456565 | S34: =IF(Q34,R34/Q34*1000,0) -> 910.93665 | U34: =IF(T34,S34/T34,1) -> 1 | W34: acatt | X34: =SUMIF($AB$6:$AJ$6,B$3,$AB34:$AJ34)/1000 -> 29.833 | Y34: =SUMIF($AL$6:$AT$6,B$3,$AL34:$AT34)/1000 -> 2156.9806 | Z34: Meat, cattle | AA34: FAO | AB34: 29833 | AC34: 32707 | AK34: FAO | AL34: 2156980.6 | AM34: 2227651.3 | AX34: Cooking banana | AY34: =SUM(BF34:BH34) -> 190120 | AZ34: =SUM(BI34:BK34) -> 175699 | BA34: =SUM(BL34:BN34) -> 167717 | BE34: Cooking banana | BF34: 96571 | BG34: 93549 | BI34: 85524 | BJ34: 90175 | BL34: 86707 | BM34: 81010
A35: Other live animals (A319) | B35: aoliv | C35: =SUMIF($W$7:$W$64,$B35,$X$7:$X$64) -> 3.909 | D35: =SUMIF($W$7:$W$64,$B35,$Y$7:$Y$64)*U35 -> 0 | E35: =D35*C35/1000 -> 0 | F35: =xGDP!D35 -> 2.5785767 | G35: =S35 -> 659.65125 | H35: =IF(E35=0,IF(C35*G35=0,F35,C35*G35),C35*D35)/1000 -> 2.5785767 | I35: 1 | J35: =I35*H35 -> 2.5785767 | K35: 0.91678309 | L35: =K35*J35 -> 2.3639956 | M35: =L35/SUMIF($N$7:$N$42,$N35,$L$7:$L$42) -> 0.011622414 | N35: 3 | P35: aoliv | Q35: 3.909 | R35: =xGDP!E35 -> 2.5785767 | S35: =IF(Q35,R35/Q35*1000,0) -> 659.65125 | U35: =IF(T35,S35/T35,1) -> 1 | W35: apoul | X35: =SUMIF($AB$6:$AJ$6,B$3,$AB35:$AJ35)/1000 -> 15.87 | Y35: =SUMIF($AL$6:$AT$6,B$3,$AL35:$AT35)/1000 -> 0 | Z35: Meat, chicken | AA35: FAO | AB35: 15870 | AC35: 15725 | AK35: FAO | AM35: 2165109.6 | AX35: Dessert banana | AY35: =SUM(BF35:BH35) -> 68005 | AZ35: =SUM(BI35:BK35) -> 64263 | BA35: =SUM(BL35:BN35) -> 69434 | BE35: Dessert banana | BF35: 35430 | BG35: 32575 | BI35: 30110 | BJ35: 34153 | BL35: 32036 | BM35: 37398
A36: Raw milk (A321) | B36: amilk | C36: =SUMIF($W$7:$W$64,$B36,$X$7:$X$64) -> 242.592 | D36: =SUMIF($W$7:$W$64,$B36,$Y$7:$Y$64)*U36 -> 152.51386 | E36: =D36*C36/1000 -> 36.998643 | F36: =xGDP!D36 -> 36.998643 | G36: =S36 -> 152.51386 | H36: =IF(E36=0,IF(C36*G36=0,F36,C36*G36),C36*D36)/1000 -> 36.998643 | I36: 1 | J36: =I36*H36 -> 36.998643 | K36: 0.97371875 | L36: =K36*J36 -> 36.026273 | M36: =L36/SUMIF($N$7:$N$42,$N36,$L$7:$L$42) -> 0.17712057 | N36: 3 | P36: amilk | Q36: 242.592 | R36: =xGDP!E36 -> 36.998643 | S36: =IF(Q36,R36/Q36*1000,0) -> 152.51386 | T36: 528.9154 | U36: =IF(T36,S36/T36,1) -> 0.28835209 | W36: ahunt | X36: =SUMIF($AB$6:$AJ$6,B$3,$AB36:$AJ36)/1000 -> 15.914 | Y36: =SUMIF($AL$6:$AT$6,B$3,$AL36:$AT36)/1000 -> 0 | Z36: Meat, game | AA36: FAO | AB36: 15914 | AC36: 16218 | AK36: FAO | AX36: Banana for beer | AY36: =SUM(BF36:BH36) -> 206195 | AZ36: =SUM(BI36:BK36) -> 219304 | BA36: =SUM(BL36:BN36) -> 253261 | BE36: Banana for beer | BF36: 105847 | BG36: 100348 | BI36: 111213 | BJ36: 108091 | BL36: 135252 | BM36: 118009
A37: Eggs (A322) | B37: aeggs | C37: =SUMIF($W$7:$W$64,$B37,$X$7:$X$64) -> 7.5 | D37: =SUMIF($W$7:$W$64,$B37,$Y$7:$Y$64)*U37 -> 2135.9852 | E37: =D37*C37/1000 -> 16.019889 | F37: =xGDP!D37 -> 16.019889 | G37: =S37 -> 2135.9852 | H37: =IF(E37=0,IF(C37*G37=0,F37,C37*G37),C37*D37)/1000 -> 16.019889 | I37: 1 | J37: =I37*H37 -> 16.019889 | K37: 0.97371875 | L37: =K37*J37 -> 15.598866 | M37: =L37/SUMIF($N$7:$N$42,$N37,$L$7:$L$42) -> 0.076690702 | N37: 3 | P37: aeggs | Q37: 7.5 | R37: =xGDP!E37 -> 16.019889 | S37: =IF(Q37,R37/Q37*1000,0) -> 2135.9852 | T37: 2187.4587 | U37: =IF(T37,S37/T37,1) -> 0.97646882 | W37: asmlr | X37: =SUMIF($AB$6:$AJ$6,B$3,$AB37:$AJ37)/1000 -> 13.958 | Y37: =SUMIF($AL$6:$AT$6,B$3,$AL37:$AT37)/1000 -> 1339.5119 | Z37: Meat, goat | AA37: FAO | AB37: 13958 | AC37: 13449 | AK37: FAO | AL37: 1339511.9 | AM37: 1357285.4 | AX37: Bean | AY37: =SUM(BF37:BH37) -> 547786 | AZ37: =SUM(BI37:BK37) -> 557208 | BA37: =SUM(BL37:BN37) -> 582670 | BE37: Bean | BF37: 268095 | BG37: 276435 | BH37: 3256 | BI37: 287218 | BJ37: 269105 | BK37: 885 | BL37: 299443 | BM37: 282099 | BN37: 1128
A38: Natural honey (A323) | B38: ahony | C38: =SUMIF($W$7:$W$64,$B38,$X$7:$X$64) -> 5 | D38: =SUMIF($W$7:$W$64,$B38,$Y$7:$Y$64)*U38 -> 115.47114 | E38: =D38*C38/1000 -> 0.57735568 | F38: =xGDP!D38 -> 0.57735568 | G38: =S38 -> 115.47114 | H38: =IF(E38=0,IF(C38*G38=0,F38,C38*G38),C38*D38)/1000 -> 0.57735568 | I38: 1 | J38: =I38*H38 -> 0.57735568 | K38: 0.97371875 | L38: =K38*J38 -> 0.56218205 | M38: =L38/SUMIF($N$7:$N$42,$N38,$L$7:$L$42) -> 0.0027639275 | N38: 3 | P38: ahony | Q38: 5 | R38: =xGDP!E38 -> 0.57735568 | S38: =IF(Q38,R38/Q38*1000,0) -> 115.47114 | T38: 3518.633 | U38: =IF(T38,S38/T38,1) -> 0.032817044 | W38: asmlr | X38: =SUMIF($AB$6:$AJ$6,B$3,$AB38:$AJ38)/1000 -> 9.535 | Y38: =SUMIF($AL$6:$AT$6,B$3,$AL38:$AT38)/1000 -> 2304.1667 | Z38: Meat, pig | AA38: FAO | AB38: 9535 | AC38: 9310 | AK38: FAO | AL38: 2304166.7 | AM38: 2848958.3 | AX38: Pea | AY38: =SUM(BF38:BH38) -> 19774 | AZ38: =SUM(BI38:BK38) -> 25961 | BA38: =SUM(BL38:BN38) -> 24772 | BE38: Pea | BF38: 9373 | BG38: 10298 | BH38: 103 | BI38: 15121 | BJ38: 10612 | BK38: 228 | BL38: 17658 | BM38: 6859 | BN38: 255
A39: Other livestock & hunting products (A329) | B39: ahunt | C39: =SUMIF($W$7:$W$64,$B39,$X$7:$X$64) -> 20.223 | D39: =SUMIF($W$7:$W$64,$B39,$Y$7:$Y$64)*U39 -> 0 | E39: =D39*C39/1000 -> 0 | F39: =xGDP!D39 -> 3.9103188 | G39: =S39 -> 193.35998 | H39: =IF(E39=0,IF(C39*G39=0,F39,C39*G39),C39*D39)/1000 -> 3.9103188 | I39: 1 | J39: =I39*H39 -> 3.9103188 | K39: 0.97371875 | L39: =K39*J39 -> 3.8075508 | M39: =L39/SUMIF($N$7:$N$42,$N39,$L$7:$L$42) -> 0.018719549 | N39: 3 | P39: ahunt | Q39: 20.223 | R39: =xGDP!E39 -> 3.9103188 | S39: =IF(Q39,R39/Q39*1000,0) -> 193.35998 | U39: =IF(T39,S39/T39,1) -> 1 | W39: aoliv | X39: =SUMIF($AB$6:$AJ$6,B$3,$AB39:$AJ39)/1000 -> 3.909 | Y39: =SUMIF($AL$6:$AT$6,B$3,$AL39:$AT39)/1000 -> 0 | Z39: Meat, rabbit | AA39: FAO | AB39: 3909 | AC39: 3844 | AK39: FAO | AX39: Groundnut | AY39: =SUM(BF39:BH39) -> 45455 | AZ39: =SUM(BI39:BK39) -> 41457 | BA39: =SUM(BL39:BN39) -> 43919 | BE39: Groundnut | BF39: 25004 | BG39: 20451 | BI39: 20474 | BJ39: 20983 | BL39: 23929 | BM39: 19990
A40: Fuel wood (A401) | B40: afuel | C40: =SUMIF($W$7:$W$64,$B40,$X$7:$X$64) -> 0 | D40: =SUMIF($W$7:$W$64,$B40,$Y$7:$Y$64)*U40 -> 0 | E40: =D40*C40/1000 -> 0 | F40: =xGDP!D40 -> 301.43662 | G40: =S40 -> 0 | H40: =IF(E40=0,IF(C40*G40=0,F40,C40*G40),C40*D40)/1000 -> 0.30143662 | I40: 1 | J40: =I40*H40 -> 0.30143662 | K40: 0.99816602 | L40: =K40*J40 -> 0.30088379 | M40: =L40/SUMIF($N$7:$N$42,$N40,$L$7:$L$42) -> 0.79506976 | N40: 4 | P40: afuel | Q40: 0 | R40: =xGDP!E40 -> 301.43662 | S40: =IF(Q40,R40/Q40*1000,0) -> 0 | U40: =IF(T40,S40/T40,1) -> 1 | W40: asmlr | X40: =SUMIF($AB$6:$AJ$6,B$3,$AB40:$AJ40)/1000 -> 4.225 | Y40: =SUMIF($AL$6:$AT$6,B$3,$AL40:$AT40)/1000 -> 0 | Z40: Meat, sheep | AA40: FAO | AB40: 4225 | AC40: 4025 | AK40: FAO | AX40: Soybean | AY40: =SUM(BF40:BH40) -> 53061 | AZ40: =SUM(BI40:BK40) -> 54793 | BA40: =SUM(BL40:BN40) -> 46695 | BE40: Soybean | BF40: 22268 | BG40: 30486 | BH40: 307 | BI40: 24011 | BJ40: 30431 | BK40: 351 | BL40: 24593 | BM40: 21543 | BN40: 559
A41: Charcoal (A402) | B41: achar | C41: =SUMIF($W$7:$W$64,$B41,$X$7:$X$64) -> 0 | D41: =SUMIF($W$7:$W$64,$B41,$Y$7:$Y$64)*U41 -> 0 | E41: =D41*C41/1000 -> 0 | F41: =xGDP!D41 -> 58.105862 | G41: =S41 -> 0 | H41: =IF(E41=0,IF(C41*G41=0,F41,C41*G41),C41*D41)/1000 -> 0.058105862 | I41: 1 | J41: =I41*H41 -> 0.058105862 | K41: 0.99816602 | L41: =K41*J41 -> 0.057999297 | M41: =L41/SUMIF($N$7:$N$42,$N41,$L$7:$L$42) -> 0.15326013 | N41: 4 | P41: achar | Q41: 0 | R41: =xGDP!E41 -> 58.105862 | S41: =IF(Q41,R41/Q41*1000,0) -> 0 | U41: =IF(T41,S41/T41,1) -> 1 | W41: amilk | X41: =SUMIF($AB$6:$AJ$6,B$3,$AB41:$AJ41)/1000 -> 156.812 | Y41: =SUMIF($AL$6:$AT$6,B$3,$AL41:$AT41)/1000 -> 528.9154 | Z41: Milk, whole fresh cow | AA41: FAO | AB41: 156812 | AC41: 170309 | AK41: FAO | AL41: 528915.4 | AM41: 553684.1 | AX41: Vegetables | AY41: =SUM(BF41:BH41) -> 42504 | AZ41: =SUM(BI41:BK41) -> 29291 | BA41: =SUM(BL41:BN41) -> 33732 | BE41: Vegetables | BF41: 19969 | BG41: 19010 | BH41: 3525 | BI41: 13794 | BJ41: 12480 | BK41: 3017 | BL41: 15012 | BM41: 14976 | BN41: 3744
A42: Other forestry products (A409) | B42: afore | C42: =SUMIF($W$7:$W$64,$B42,$X$7:$X$64) -> 0 | D42: =SUMIF($W$7:$W$64,$B42,$Y$7:$Y$64)*U42 -> 0 | E42: =D42*C42/1000 -> 0 | F42: =xGDP!D42 -> 19.589807 | G42: =S42 -> 0 | H42: =IF(E42=0,IF(C42*G42=0,F42,C42*G42),C42*D42)/1000 -> 0.019589807 | I42: 1 | J42: =I42*H42 -> 0.019589807 | K42: 0.99816602 | L42: =K42*J42 -> 0.01955388 | M42: =L42/SUMIF($N$7:$N$42,$N42,$L$7:$L$42) -> 0.05167011 | N42: 4 | P42: afore | Q42: 0 | R42: =xGDP!E42 -> 19.589807 | S42: =IF(Q42,R42/Q42*1000,0) -> 0 | U42: =IF(T42,S42/T42,1) -> 1 | W42: amilk | X42: =SUMIF($AB$6:$AJ$6,B$3,$AB42:$AJ42)/1000 -> 76.919 | Y42: =SUMIF($AL$6:$AT$6,B$3,$AL42:$AT42)/1000 -> 0 | Z42: Milk, whole fresh goat | AA42: FAO | AB42: 76919 | AC42: 73370 | AK42: FAO | AX42: Fruits | AY42: =SUM(BF42:BH42) -> 13395 | AZ42: =SUM(BI42:BK42) -> 12652 | BA42: =SUM(BL42:BN42) -> 15837 | BE42: Fruits | BF42: 6551 | BG42: 6844 | BI42: 5975 | BJ42: 6677 | BL42: 8383 | BM42: 7454
W43: amilk | X43: =SUMIF($AB$6:$AJ$6,B$3,$AB43:$AJ43)/1000 -> 8.861 | Y43: =SUMIF($AL$6:$AT$6,B$3,$AL43:$AT43)/1000 -> 0 | Z43: Milk, whole fresh sheep | AA43: FAO | AB43: 8861 | AC43: 8334 | AK43: FAO
X51: =SUMIF($AB$6:$AJ$6,B$3,$AB51:$AJ51)/1000 -> 0
X52: =SUMIF($AB$6:$AJ$6,B$3,$AB52:$AJ52)/1000 -> 0
X53: =SUMIF($AB$6:$AJ$6,B$3,$AB53:$AJ53)/1000 -> 0
X54: =SUMIF($AB$6:$AJ$6,B$3,$AB54:$AJ54)/1000 -> 0
X55: =SUMIF($AB$6:$AJ$6,B$3,$AB55:$AJ55)/1000 -> 0
X56: =SUMIF($AB$6:$AJ$6,B$3,$AB56:$AJ56)/1000 -> 0
X57: =SUMIF($AB$6:$AJ$6,B$3,$AB57:$AJ57)/1000 -> 0
X58: =SUMIF($AB$6:$AJ$6,B$3,$AB58:$AJ58)/1000 -> 0
X59: =SUMIF($AB$6:$AJ$6,B$3,$AB59:$AJ59)/1000 -> 0
X60: =SUMIF($AB$6:$AJ$6,B$3,$AB60:$AJ60)/1000 -> 0
X61: =SUMIF($AB$6:$AJ$6,B$3,$AB61:$AJ61)/1000 -> 0
X62: =SUMIF($AB$6:$AJ$6,B$3,$AB62:$AJ62)/1000 -> 0
... X64: =SUMIF($AB$6:$AJ$6,B$3,$AB64:$AJ64)/1000 -> 0

Sheet wIND
A1: Industry
A2: Workings
C5: Output value | I5: GDP calc.
C6: Nat. Acc. | D6: SUT17 | E6: Groups | F6: Initial | G6: Adjust | H6: Final | I6: GDP/GO | J6: GDP | K6: Share | L6: Groups
A7: Natural gas (B01) | B7: angas | C7: =wGDPp!F45 -> 165 | D7: =xGDP!G44 -> 0.069273647 | E7: 1 | F7: =IF(SUMIF($E$7:$E$42,$E7,$D$7:$D$42),D7/SUMIF($E$7:$E$42,$E7,$D$7:$D$42)*SUMIF($E$7:$E$42,$E7,$C$7:$C$42),0) -> 0.069262115 | G7: 1 | H7: =G7*F7 -> 0.069262115 | I7: {=TRANSPOSE(wUSE!AN3:BW3)} -> 1 | J7: =H7*I7 -> 0.069262115 | K7: =IF(SUMIF($L$7:$L$42,$L7,$H$7:$H$42),H7/SUMIF($L$7:$L$42,$L7,$H$7:$H$42),0) -> 0.0004197704 | L7: =E7 -> 1
A8: Metal ores (B03) | B8: amore | C8: =wGDPp!F46 -> 0 | D8: =xGDP!G45 -> 68.52793 | E8: 1 | F8: =IF(SUMIF($E$7:$E$42,$E8,$D$7:$D$42),D8/SUMIF($E$7:$E$42,$E8,$D$7:$D$42)*SUMIF($E$7:$E$42,$E8,$C$7:$C$42),0) -> 68.516522 | G8: 1 | H8: =G8*F8 -> 68.516522 | I8: 0.6416892 | J8: =H8*I8 -> 43.966313 | K8: =IF(SUMIF($L$7:$L$42,$L8,$H$7:$H$42),H8/SUMIF($L$7:$L$42,$L8,$H$7:$H$42),0) -> 0.41525165 | L8: =E8 -> 1
A9: Quarry & other mining products (B09) | B9: aomin | C9: =wGDPp!F47 -> 0 | D9: =xGDP!G46 -> 96.430268 | E9: 1 | F9: =IF(SUMIF($E$7:$E$42,$E9,$D$7:$D$42),D9/SUMIF($E$7:$E$42,$E9,$D$7:$D$42)*SUMIF($E$7:$E$42,$E9,$C$7:$C$42),0) -> 96.414216 | G9: 1 | H9: =G9*F9 -> 96.414216 | I9: 0.7314137 | J9: =H9*I9 -> 70.518678 | K9: =IF(SUMIF($L$7:$L$42,$L9,$H$7:$H$42),H9/SUMIF($L$7:$L$42,$L9,$H$7:$H$42),0) -> 0.58432858 | L9: =E9 -> 1
A10: Meat and meat products (C11) | B10: ameat | C10: =wGDPp!F48 -> 210 | D10: =xGDP!G47 -> 21.961141 | E10: 2 | F10: =IF(SUMIF($E$7:$E$42,$E10,$D$7:$D$42),D10/SUMIF($E$7:$E$42,$E10,$D$7:$D$42)*SUMIF($E$7:$E$42,$E10,$C$7:$C$42),0) -> 21.926921 | G10: 1 | H10: =G10*F10 -> 21.926921 | I10: 0.2266543 | J10: =H10*I10 -> 4.9698309 | K10: =IF(SUMIF($L$7:$L$42,$L10,$H$7:$H$42),H10/SUMIF($L$7:$L$42,$L10,$H$7:$H$42),0) -> 0.10441391 | L10: =E10 -> 2
A11: Prepared and preserved fish (C12) | B11: afsea | C11: =wGDPp!F49 -> 0 | D11: =xGDP!G48 -> 0 | E11: 2 | F11: =IF(SUMIF($E$7:$E$42,$E11,$D$7:$D$42),D11/SUMIF($E$7:$E$42,$E11,$D$7:$D$42)*SUMIF($E$7:$E$42,$E11,$C$7:$C$42),0) -> 0 | G11: 1 | H11: =G11*F11 -> 0 | I11: 0.2266543 | J11: =H11*I11 -> 0 | K11: =IF(SUMIF($L$7:$L$42,$L11,$H$7:$H$42),H11/SUMIF($L$7:$L$42,$L11,$H$7:$H$42),0) -> 0 | L11: =E11 -> 2
A12: Prepared and preserved vegetables (C13) | B12: afveg | C12: =wGDPp!F50 -> 0 | D12: =xGDP!G49 -> 6.1024723 | E12: 2 | F12: =IF(SUMIF($E$7:$E$42,$E12,$D$7:$D$42),D12/SUMIF($E$7:$E$42,$E12,$D$7:$D$42)*SUMIF($E$7:$E$42,$E12,$C$7:$C$42),0) -> 6.0929636 | G12: 1 | H12: =G12*F12 -> 6.0929636 | I12: 0.32565389 | J12: =H12*I12 -> 1.9841973 | K12: =IF(SUMIF($L$7:$L$42,$L12,$H$7:$H$42),H12/SUMIF($L$7:$L$42,$L12,$H$7:$H$42),0) -> 0.029014112 | L12: =E12 -> 2
A13: Animal and vegetable oils and fats (C14) | B13: afoil | C13: =wGDPp!F51 -> 0 | D13: =xGDP!G50 -> 8.0919409 | E13: 2 | F13: =IF(SUMIF($E$7:$E$42,$E13,$D$7:$D$42),D13/SUMIF($E$7:$E$42,$E13,$D$7:$D$42)*SUMIF($E$7:$E$42,$E13,$C$7:$C$42),0) -> 8.0793322 | G13: 1 | H13: =G13*F13 -> 8.0793322 | I13: 0.49112069 | J13: =H13*I13 -> 3.9679272 | K13: =IF(SUMIF($L$7:$L$42,$L13,$H$7:$H$42),H13/SUMIF($L$7:$L$42,$L13,$H$7:$H$42),0) -> 0.038473011 | L13: =E13 -> 2
A14: Dairy products (C15) | B14: adair | C14: =wGDPp!F52 -> 0 | D14: =xGDP!G51 -> 4.5169661 | E14: 2 | F14: =IF(SUMIF($E$7:$E$42,$E14,$D$7:$D$42),D14/SUMIF($E$7:$E$42,$E14,$D$7:$D$42)*SUMIF($E$7:$E$42,$E14,$C$7:$C$42),0) -> 4.5099278 | G14: 1 | H14: =G14*F14 -> 4.5099278 | I14: 0.57009698 | J14: =H14*I14 -> 2.5710962 | K14: =IF(SUMIF($L$7:$L$42,$L14,$H$7:$H$42),H14/SUMIF($L$7:$L$42,$L14,$H$7:$H$42),0) -> 0.021475847 | L14: =E14 -> 2
A15: Grain mill products (C16) | B15: agmll | C15: =wGDPp!F53 -> 0 | D15: =xGDP!G52 -> 104.99285 | E15: 2 | F15: =IF(SUMIF($E$7:$E$42,$E15,$D$7:$D$42),D15/SUMIF($E$7:$E$42,$E15,$D$7:$D$42)*SUMIF($E$7:$E$42,$E15,$C$7:$C$42),0) -> 104.82926 | G15: 1 | H15: =G15*F15 -> 104.82926 | I15: 0.27681751 | J15: =H15*I15 -> 29.018574 | K15: =IF(SUMIF($L$7:$L$42,$L15,$H$7:$H$42),H15/SUMIF($L$7:$L$42,$L15,$H$7:$H$42),0) -> 0.49918694 | L15: =E15 -> 2
A16: Bakery products (C17) | B16: abake | C16: =wGDPp!F54 -> 0 | D16: =xGDP!G53 -> 16.452017 | E16: 2 | F16: =IF(SUMIF($E$7:$E$42,$E16,$D$7:$D$42),D16/SUMIF($E$7:$E$42,$E16,$D$7:$D$42)*SUMIF($E$7:$E$42,$E16,$C$7:$C$42),0) -> 16.426382 | G16: 1 | H16: =G16*F16 -> 16.426382 | I16: 0.24094973 | J16: =H16*I16 -> 3.9579323 | K16: =IF(SUMIF($L$7:$L$42,$L16,$H$7:$H$42),H16/SUMIF($L$7:$L$42,$L16,$H$7:$H$42),0) -> 0.078220867 | L16: =E16 -> 2
A17: Animal feed & other by-products (C18) | B17: afeed | C17: =wGDPp!F55 -> 0 | D17: =xGDP!G54 -> 3.9352344 | E17: 2 | F17: =IF(SUMIF($E$7:$E$42,$E17,$D$7:$D$42),D17/SUMIF($E$7:$E$42,$E17,$D$7:$D$42)*SUMIF($E$7:$E$42,$E17,$C$7:$C$42),0) -> 3.9291026 | G17: 1 | H17: =G17*F17 -> 3.9291026 | I17: 0.94501676 | J17: =H17*I17 -> 3.7130678 | K17: =IF(SUMIF($L$7:$L$42,$L17,$H$7:$H$42),H17/SUMIF($L$7:$L$42,$L17,$H$7:$H$42),0) -> 0.018710012 | L17: =E17 -> 2
A18: Other manufactured food products (C19) | B18: afood | C18: =wGDPp!F56 -> 0 | D18: =xGDP!G55 -> 44.275101 | E18: 2 | F18: =IF(SUMIF($E$7:$E$42,$E18,$D$7:$D$42),D18/SUMIF($E$7:$E$42,$E18,$D$7:$D$42)*SUMIF($E$7:$E$42,$E18,$C$7:$C$42),0) -> 44.206113 | G18: 1 | H18: =G18*F18 -> 44.206113 | I18: 0.40607617 | J18: =H18*I18 -> 17.951049 | K18: =IF(SUMIF($L$7:$L$42,$L18,$H$7:$H$42),H18/SUMIF($L$7:$L$42,$L18,$H$7:$H$42),0) -> 0.2105053 | L18: =E18 -> 2
A19: Alcoholic drinks (C21) | B19: aalco | C19: =wGDPp!F57 -> 159 | D19: =xGDP!G56 -> 128.19497 | E19: 3 | F19: =IF(SUMIF($E$7:$E$42,$E19,$D$7:$D$42),D19/SUMIF($E$7:$E$42,$E19,$D$7:$D$42)*SUMIF($E$7:$E$42,$E19,$C$7:$C$42),0) -> 127.92243 | G19: 1 | H19: =G19*F19 -> 127.92243 | I19: 0.4883556 | J19: =H19*I19 -> 62.471637 | K19: =IF(SUMIF($L$7:$L$42,$L19,$H$7:$H$42),H19/SUMIF($L$7:$L$42,$L19,$H$7:$H$42),0) -> 0.80454361 | L19: =E19 -> 3
... A42: Construction (traditional) (F02) | B42: acont | C42: =wGDPp!F80 -> 0 | D42: =xGDP!G79 -> 0 | E42: 12 | F42: =IF(SUMIF($E$7:$E$42,$E42,$D$7:$D$42),D42/SUMIF($E$7:$E$42,$E42,$D$7:$D$42)*SUMIF($E$7:$E$42,$E42,$C$7:$C$42),0) -> 0 | G42: 1 | H42: =G42*F42 -> 0 | I42: 0 | J42: =H42*I42 -> 0 | K42: =IF(SUMIF($L$7:$L$42,$L42,$H$7:$H$42),H42/SUMIF($L$7:$L$42,$L42,$H$7:$H$42),0) -> 0 | L42: =E42 -> 12

Sheet wSRV
A1: Services
A2: Workings
C5: Output value | I5: GDP calc.
C6: Nat. Acc. | D6: Detailed | E6: Groups | F6: Initial | G6: Adjust | H6: Final | I6: GDP/GO | J6: GDP | K6: Share | L6: Groups
A7: Maintenance and repair of motor vehicles (G10) | B7: avehr | C7: =wGDPp!F81 -> 40 | D7: =xGDP!G80 -> 40.309849 | E7: 1 | F7: =IF(SUMIF($E$7:$E$42,$E7,$D$7:$D$42),D7/SUMIF($E$7:$E$42,$E7,$D$7:$D$42)*SUMIF($E$7:$E$42,$E7,$C$7:$C$42),0) -> 35.699691 | G7: 1 | H7: =G7*F7 -> 35.699691 | I7: {=TRANSPOSE(wUSE!BX3:DB3)} -> 0.71823903 | J7: =H7*I7 -> 25.640911 | K7: =IF(SUMIF($L$7:$L$37,$L7,$H$7:$H$37),H7/SUMIF($L$7:$L$37,$L7,$H$7:$H$37),0) -> 0.89249226 | L7: 1
A8: Wholesale and retail trade of motor vehicles and motorcycles (G21) | B8: aveht | C8: =wGDPp!F82 -> 0 | D8: =xGDP!G81 -> 4.8556395 | E8: 1 | F8: =IF(SUMIF($E$7:$E$42,$E8,$D$7:$D$42),D8/SUMIF($E$7:$E$42,$E8,$D$7:$D$42)*SUMIF($E$7:$E$42,$E8,$C$7:$C$42),0) -> 4.3003095 | G8: 1 | H8: =G8*F8 -> 4.3003095 | I8: 0.41214028 | J8: =H8*I8 -> 1.7723307 | K8: =IF(SUMIF($L$7:$L$37,$L8,$H$7:$H$37),H8/SUMIF($L$7:$L$37,$L8,$H$7:$H$37),0) -> 0.10750774 | L8: 1
A9: Wholesale trade, except of motor vehicles and motorcycles (G22) | B9: atrdw | C9: =wGDPp!F83 -> 597 | D9: =xGDP!G82 -> 178.86777 | E9: 2 | F9: =IF(SUMIF($E$7:$E$42,$E9,$D$7:$D$42),D9/SUMIF($E$7:$E$42,$E9,$D$7:$D$42)*SUMIF($E$7:$E$42,$E9,$C$7:$C$42),0) -> 180.44072 | G9: 1 | H9: =G9*F9 -> 180.44072 | I9: 0.50163381 | J9: =H9*I9 -> 90.515166 | K9: =IF(SUMIF($L$7:$L$37,$L9,$H$7:$H$37),H9/SUMIF($L$7:$L$37,$L9,$H$7:$H$37),0) -> 0.30224576 | L9: 2
A10: Retail trade, except of motor vehicles and motorcycles (G23) | B10: atrdr | C10: =wGDPp!F84 -> 0 | D10: =xGDP!G83 -> 412.92801 | E10: 2 | F10: =IF(SUMIF($E$7:$E$42,$E10,$D$7:$D$42),D10/SUMIF($E$7:$E$42,$E10,$D$7:$D$42)*SUMIF($E$7:$E$42,$E10,$C$7:$C$42),0) -> 416.55928 | G10: 1 | H10: =G10*F10 -> 416.55928 | I10: 0.6134132 | J10: =H10*I10 -> 255.52296 | K10: =IF(SUMIF($L$7:$L$37,$L10,$H$7:$H$37),H10/SUMIF($L$7:$L$37,$L10,$H$7:$H$37),0) -> 0.69775424 | L10: 2
A11: Land transport (H10) | B11: atrnl | C11: =wGDPp!F85 -> 355 | D11: =xGDP!G84 -> 204.95827 | E11: 3 | F11: =IF(SUMIF($E$7:$E$42,$E11,$D$7:$D$42),D11/SUMIF($E$7:$E$42,$E11,$D$7:$D$42)*SUMIF($E$7:$E$42,$E11,$C$7:$C$42),0) -> 205.15736 | G11: 1 | H11: =G11*F11 -> 205.15736 | I11: 0.50004408 | J11: =H11*I11 -> 102.58772 | K11: =IF(SUMIF($L$7:$L$37,$L11,$H$7:$H$37),H11/SUMIF($L$7:$L$37,$L11,$H$7:$H$37),0) -> 0.57790805 | L11: 3
A12: Air transport (H20) | B12: atrna | C12: =wGDPp!F86 -> 0 | D12: =xGDP!G85 -> 95.721929 | E12: 3 | F12: =IF(SUMIF($E$7:$E$42,$E12,$D$7:$D$42),D12/SUMIF($E$7:$E$42,$E12,$D$7:$D$42)*SUMIF($E$7:$E$42,$E12,$C$7:$C$42),0) -> 95.814909 | G12: 1 | H12: =G12*F12 -> 95.814909 | I12: 0.53332365 | J12: =H12*I12 -> 51.100357 | K12: =IF(SUMIF($L$7:$L$37,$L12,$H$7:$H$37),H12/SUMIF($L$7:$L$37,$L12,$H$7:$H$37),0) -> 0.26990115 | L12: 3
A13: Services related to transport (H31) | B13: atrns | C13: =wGDPp!F87 -> 0 | D13: =xGDP!G86 -> 43.982942 | E13: 3 | F13: =IF(SUMIF($E$7:$E$42,$E13,$D$7:$D$42),D13/SUMIF($E$7:$E$42,$E13,$D$7:$D$42)*SUMIF($E$7:$E$42,$E13,$C$7:$C$42),0) -> 44.025665 | G13: 1 | H13: =G13*F13 -> 44.025665 | I13: 0.63866813 | J13: =H13*I13 -> 28.117789 | K13: =IF(SUMIF($L$7:$L$37,$L13,$H$7:$H$37),H13/SUMIF($L$7:$L$37,$L13,$H$7:$H$37),0) -> 0.12401596 | L13: 3
A14: Postal and courier activities (H32) | B14: apost | C14: =wGDPp!F88 -> 0 | D14: =xGDP!G87 -> 9.992363 | E14: 3 | F14: =IF(SUMIF($E$7:$E$42,$E14,$D$7:$D$42),D14/SUMIF($E$7:$E$42,$E14,$D$7:$D$42)*SUMIF($E$7:$E$42,$E14,$C$7:$C$42),0) -> 10.002069 | G14: 1 | H14: =G14*F14 -> 10.002069 | I14: 0.62636219 | J14: =H14*I14 -> 6.264918 | K14: =IF(SUMIF($L$7:$L$37,$L14,$H$7:$H$37),H14/SUMIF($L$7:$L$37,$L14,$H$7:$H$37),0) -> 0.028174843 | L14: 3
A15: Hotels & restaurants (I00) | B15: ahotl | C15: =wGDPp!F89 -> 140 | D15: =xGDP!G88 -> 139.76863 | E15: 4 | F15: =IF(SUMIF($E$7:$E$42,$E15,$D$7:$D$42),D15/SUMIF($E$7:$E$42,$E15,$D$7:$D$42)*SUMIF($E$7:$E$42,$E15,$C$7:$C$42),0) -> 140 | G15: 1 | H15: =G15*F15 -> 140 | I15: 0.27276413 | J15: =H15*I15 -> 38.186979 | K15: =IF(SUMIF($L$7:$L$37,$L15,$H$7:$H$37),H15/SUMIF($L$7:$L$37,$L15,$H$7:$H$37),0) -> 1 | L15: 4
A16: Publishing, video making, programming & broadcasting activities (J10) | B16: apubl | C16: =wGDPp!F90 -> 134 | D16: =xGDP!G89 -> 22.696705 | E16: 5 | F16: =IF(SUMIF($E$7:$E$42,$E16,$D$7:$D$42),D16/SUMIF($E$7:$E$42,$E16,$D$7:$D$42)*SUMIF($E$7:$E$42,$E16,$C$7:$C$42),0) -> 22.681642 | G16: 1 | H16: =G16*F16 -> 22.681642 | I16: 0.71682835 | J16: =H16*I16 -> 16.258844 | K16: =IF(SUMIF($L$7:$L$37,$L16,$H$7:$H$37),H16/SUMIF($L$7:$L$37,$L16,$H$7:$H$37),0) -> 0.16926599 | L16: 5
A17: Telecommunication (J20) | B17: acomm | C17: =wGDPp!F91 -> 0 | D17: =xGDP!G90 -> 89.289125 | E17: 5 | F17: =IF(SUMIF($E$7:$E$42,$E17,$D$7:$D$42),D17/SUMIF($E$7:$E$42,$E17,$D$7:$D$42)*SUMIF($E$7:$E$42,$E17,$C$7:$C$42),0) -> 89.229867 | G17: 1 | H17: =G17*F17 -> 89.229867 | I17: 0.47015673 | J17: =H17*I17 -> 41.952023 | K17: =IF(SUMIF($L$7:$L$37,$L17,$H$7:$H$37),H17/SUMIF($L$7:$L$37,$L17,$H$7:$H$37),0) -> 0.66589453 | L17: 5
A18: Information technology services (J30) | B18: ainfo | C18: =wGDPp!F92 -> 0 | D18: =xGDP!G91 -> 22.10316 | E18: 5 | F18: =IF(SUMIF($E$7:$E$42,$E18,$D$7:$D$42),D18/SUMIF($E$7:$E$42,$E18,$D$7:$D$42)*SUMIF($E$7:$E$42,$E18,$C$7:$C$42),0) -> 22.088491 | G18: 1 | H18: =G18*F18 -> 22.088491 | I18: 0.59216837 | J18: =H18*I18 -> 13.080106 | K18: =IF(SUMIF($L$7:$L$37,$L18,$H$7:$H$37),H18/SUMIF($L$7:$L$37,$L18,$H$7:$H$37),0) -> 0.16483949 | L18: 5
A19: Monetary institutions (K01) | B19: abank | C19: =wGDPp!F93 -> 191 | D19: =xGDP!G92 -> 53.933271 | E19: 6 | F19: =IF(SUMIF($E$7:$E$42,$E19,$D$7:$D$42),D19/SUMIF($E$7:$E$42,$E19,$D$7:$D$42)*SUMIF($E$7:$E$42,$E19,$C$7:$C$42),0) -> 53.971869 | G19: 1 | H19: =G19*F19 -> 53.971869 | I19: 0.46601904 | J19: =H19*I19 -> 25.151919 | K19: =IF(SUMIF($L$7:$L$37,$L19,$H$7:$H$37),H19/SUMIF($L$7:$L$37,$L19,$H$7:$H$37),0) -> 0.28257523 | L19: 6
... A37: Travel debits & credits (V00) | B37: atrdc | C37: =wGDPp!F111 -> 0 | D37: =xGDP!G110 -> 0 | E37: 13 | F37: =IF(SUMIF($E$7:$E$42,$E37,$D$7:$D$42),D37/SUMIF($E$7:$E$42,$E37,$D$7:$D$42)*SUMIF($E$7:$E$42,$E37,$C$7:$C$42),0) -> 0 | G37: 1 | H37: =G37*F37 -> 0 | I37: 1 | J37: =H37*I37 -> 0 | K37: =IF(SUMIF($L$7:$L$37,$L37,$H$7:$H$37),H37/SUMIF($L$7:$L$37,$L37,$H$7:$H$37),0) -> 0 | L37: 13

Sheet wTRD
A1: Trade flows
A2: Workings
D3: Imported goods and services | J3: Exported goods and services
D4: Bil. LCU | E4: Bil. LCU | G4: =wMAC!V34 -> 1981.2242 | H4: =wMAC!V35 -> 569.17484 | I4: =SUM(G4:H4) -> 2550.3991 | J4: Mil. LCU | K4: Mil. LCU | M4: =wMAC!S34 -> 883.21671 | N4: =wMAC!S35 -> 696.28499 | O4: =SUM(M4:N4) -> 1579.5017
C5: Total | D5: =SUM(D8:D111) -> 1981.2242 | E5: =SUM(E8:E111) -> 569.17484 | G5: =SUM(G8:G111) -> 1981.2242 | H5: =SUM(H8:H111) -> 569.17484 | I5: =SUM(I8:I111) -> 2550.3991 | J5: =SUM(J8:J111) -> 883.21671 | K5: =SUM(K8:K111) -> 677.15263 | M5: =SUM(M8:M111) -> 883.21671 | N5: =SUM(N8:N111) -> 677.15263 | O5: =SUM(O8:O111) -> 1579.5017
