Workbook

Sheet FinUSE
A1: Final Coefficients
A3: GDP/GO | C3: =C$20 -> amaiz | D3: =D$20 -> asorg | E3: =E$20 -> arice | F3: =F$20 -> awhea | G3: =G$20 -> aocer | H3: =H$20 -> apuls | I3: =I$20 -> agnut | J3: =J$20 -> aoils | ... DO3: =DO$20 -> aosrv
B4: Orig. | C4: =#REF! -> #REF! | D4: =#REF! -> #REF! | E4: =#REF! -> #REF! | F4: =#REF! -> #REF! | G4: =#REF! -> #REF! | H4: =#REF! -> #REF! | I4: =#REF! -> #REF! | J4: =#REF! -> #REF! | ... DO4: =#REF! -> #REF!
B5: Alt 1
B6: Alt 2
B7: Final | C7: =C4 -> #REF! | D7: =D4 -> #REF! | E7: =E4 -> #REF! | F7: =F4 -> #REF! | G7: =G4 -> #REF! | H7: =H4 -> #REF! | I7: =I4 -> #REF! | J7: =J4 -> #REF! | ... DO7: =DO4 -> #REF!
A10: FAC SHR | C10: =C$20 -> amaiz | D10: =D$20 -> asorg | E10: =E$20 -> arice | F10: =F$20 -> awhea | G10: =G$20 -> aocer | H10: =H$20 -> apuls | I10: =I$20 -> agnut | J10: =J$20 -> aoils | ... DO10: =DO$20 -> aosrv
B11: flab | C11: =#REF! -> #REF! | D11: =#REF! -> #REF! | E11: =#REF! -> #REF! | F11: =#REF! -> #REF! | G11: =#REF! -> #REF! | H11: =#REF! -> #REF! | I11: =#REF! -> #REF! | J11: =#REF! -> #REF! | ... DO11: =#REF! -> #REF!
B12: flnd | C12: =#REF! -> #REF! | D12: =#REF! -> #REF! | E12: =#REF! -> #REF! | F12: =#REF! -> #REF! | G12: =#REF! -> #REF! | H12: =#REF! -> #REF! | I12: =#REF! -> #REF! | J12: =#REF! -> #REF! | ... DO12: =#REF! -> #REF!
B13: fcap | C13: =#REF! -> #REF! | D13: =#REF! -> #REF! | E13: =#REF! -> #REF! | F13: =#REF! -> #REF! | G13: =#REF! -> #REF! | H13: =#REF! -> #REF! | I13: =#REF! -> #REF! | J13: =#REF! -> #REF! | ... DO13: =#REF! -> #REF!
B14: flab | C14: =C11 -> #REF! | D14: =D11 -> #REF! | E14: =E11 -> #REF! | F14: =F11 -> #REF! | G14: =G11 -> #REF! | H14: =H11 -> #REF! | I14: =I11 -> #REF! | J14: =J11 -> #REF! | ... DO14: =DO11 -> #REF!
B15: flnd | C15: =C12 -> #REF! | D15: =D12 -> #REF! | E15: =E12 -> #REF! | F15: =F12 -> #REF! | G15: =G12 -> #REF! | H15: =H12 -> #REF! | I15: =I12 -> #REF! | J15: =J12 -> #REF! | ... DO15: =DO12 -> #REF!
B16: fcap | C16: =1-SUM(C14:C15) -> #REF! | D16: =1-SUM(D14:D15) -> #REF! | E16: =1-SUM(E14:E15) -> #REF! | F16: =1-SUM(F14:F15) -> #REF! | G16: =1-SUM(G14:G15) -> #REF! | H16: =1-SUM(H14:H15) -> #REF! | I16: =1-SUM(I14:I15) -> #REF! | J16: =1-SUM(J14:J15) -> #REF! | ... DO16: =1-SUM(DO14:DO15) -> #REF!
C19: =SUM(C21:C109) -> 0 | D19: =SUM(D21:D109) -> 0 | E19: =SUM(E21:E109) -> 0 | F19: =SUM(F21:F109) -> 0 | G19: =SUM(G21:G109) -> 0 | H19: =SUM(H21:H109) -> 0 | I19: =SUM(I21:I109) -> 0 | J19: =SUM(J21:J109) -> 0 | ... CJ19: =SUM(CJ21:CJ109) -> 0
C20: amaiz | D20: asorg | E20: arice | F20: awhea | G20: aocer | H20: apuls | I20: agnut | J20: aoils | K20: acass | L20: aipot | M20: aspot | N20: aroot | O20: aleaf | P20: avege | Q20: asugr | R20: atoba | S20: acott | T20: anuts | U20: abana | V20: afrui | W20: ateal | X20: acoff | Y20: acoco | Z20: aflwr | AA20: arubb | AB20: aocrp | AC20: acatt | AD20: amilk | AE20: apoul | AF20: aeggs | AG20: asmlr | AH20: aoliv | AI20: afore | AJ20: aaqua | AK20: afish | AL20: acoal | AM20: acoil | AN20: angas | AO20: amore | AP20: aomin | AQ20: ameat | AR20: afsea | AS20: adair | AT20: afveg | AU20: afoil | AV20: ammill | AW20: asmll | AX20: armll | AY20: awmll | AZ20: agmll | BA20: asref | BB20: apcof | BC20: aptea | BD20: abake | BE20: afood | BF20: afeed | BG20: aalco | BH20: abeve | BI20: aptob | BJ20: ayarn | BK20: atext | BL20: aclth | BM20: aleat | BN20: awood | BO20: apapr | BP20: aprnt | BQ20: apetr | BR20: afert | BS20: aphar | BT20: aprub | BU20: achem | BV20: anmet | BW20: aceme | BX20: aclay | BY20: ametl | BZ20: amach | CA20: aequi | CB20: avehi | CC20: afurn | CD20: aoman | CE20: arepr | CF20: aelec | CG20: awatr | CH20: awast | CI20: acons | CJ20: acont | CK20: avehr | CL20: aveht | CM20: atrdw | CN20: atrdr | CO20: atrnl | CP20: atrna | CQ20: atrns | CR20: apost | CS20: ahotl | CT20: arest | CU20: apubl | CV20: acomm | CW20: ainfo | CX20: abank | CY20: ainsu | CZ20: aofsv | DA20: arent | DB20: areal | DC20: alegl | DD20: aenga | DE20: aprod | DF20: atrvl | DG20: aobsv | DH20: apadm | DI20: aeduc | DJ20: aheal | DK20: asocw | DL20: acult | DM20: aarts | DN20: adsrv | DO20: aosrv
B21: cmaiz
B22: csorg
B23: crice
B24: cwhea
B25: cocer
B26: cpuls
B27: cgnut
B28: coils
B29: ccass
B30: cipot
B31: cspot
B32: croot
... B141: atax

Sheet oSUP
A1: SUT Part D: Make matrix
A2: Billions of FRW
E4: Activities
E5: Cereals | F5: Roots and Tubers | G5: Vegetables | H5: Bananas and fruit | I5: Oil seeds n.e.c. and oleaginous fruit | J5: Coffee | K5: Tea (unprocessed green leaf) | L5: Other agricultural products | M5: Livestock | N5: Livestock and hunting products | O5: Forestry products | P5: Fishery products | Q5: Natural gas | R5: Metal ores | S5: Quarry & other mining products | T5: Meat and meat products | U5: Prepared and preserved fish | V5: Prepared and preserved vegetables | W5: Animal and vegetable oils and fats | X5: Dairy products | Y5: Grain mill products | Z5: Bakery products | AA5: Animal feed & other by-products | AB5: Other manufactured food products | AC5: Alcoholic drinks | AD5: Soft drinks | AE5: Tobacco products | AF5: Textiles, clothing & leather products | AG5: Wood, paper and related products | AH5: Printing and reproduction of recorded media | AI5: Coke and refined petroleum products | AJ5: Chemicals and chemical products | AK5: Pharmaceutical products | AL5: Rubber and plastics products | AM5: Non-metallic mineral products n.e.c. | AN5: Manufacture of cement, lime and plaster | AO5: Manufacture of clay building materials | AP5: Metals & metal products, except machinery and equipment | AQ5: Machinery and equipment (except transport) | AR5: Transport equipment | AS5: Furniture | AT5: Other manufacturing | AU5: Repair and installation of machinery and equipment | AV5: Electricity, gas, steam and air conditioning supply | AW5: Water collection, treatment and supply: sewrage | AX5: Waste collection and management | AY5: Construction (modern) | AZ5: Construction (traditional) | BA5: Maintenance and repair of motor vehicles | BB5: Wholesale and retail trade of motor vehicles and motorcycles | BC5: Wholesale trade, except of motor vehicles and motorcycles | BD5: Retail trade, except of motor vehicles and motorcycles | BE5: Land transport | BF5: Air transport | BG5: Services related to transport | BH5: Postal and courier activities | BI5: Hotels & restaurants | BJ5: Publishing, video making, programming & broadcasting activities | BK5: Telecommunication | BL5: Information technology services | BM5: Monetary institutions | BN5: Insurance, reinsurance and pension funding, except compulsory social security | BO5: Other financial services | BP5: Rental value of dwellings | BQ5: Other real estate activities | BR5: Legal, accounting management & head office activities | BS5: Architectural and engineering activities | BT5: Other professional, scientific and technical activities | BU5: Travel agents and tour operators | BV5: Other administrative and support service activities | BW5: Public administration and defence; compulsory social security | BX5: Education | BY5: Human health activities | BZ5: Social work activities | CA5: Libraries, archives, museums and other cultural activities | CB5: Other arts, entertainment and recreation | CC5: Other service activities | CD5: Domestic services
E6: A11 | F6: A12 | G6: A13 | H6: A14 | I6: A15 | J6: A21 | K6: A22 | L6: A29 | M6: A31 | N6: A32 | O6: A40 | P6: A50 | Q6: B01 | R6: B03 | S6: B09 | T6: C11 | U6: C12 | V6: C13 | W6: C14 | X6: C15 | Y6: C16 | Z6: C17 | AA6: C18 | AB6: C19 | AC6: C21 | AD6: C22 | AE6: C23 | AF6: C30 | AG6: C41 | AH6: C42 | AI6: C51 | AJ6: C52 | AK6: C53 | AL6: C54 | AM6: C61 | AN6: C62 | AO6: C63 | AP6: C72 | AQ6: C74 | AR6: C76 | AS6: C81 | AT6: C82 | AU6: C83 | AV6: D00 | AW6: E01 | AX6: E02 | AY6: F01 | AZ6: F02 | BA6: G10 | BB6: G21 | BC6: G22 | BD6: G23 | BE6: H10 | BF6: H20 | BG6: H31 | BH6: H32 | BI6: I00 | BJ6: J10 | BK6: J20 | BL6: J30 | BM6: K01 | BN6: K02 | BO6: K03 | BP6: L01 | BQ6: L09 | BR6: M01 | BS6: M02 | BT6: M03 | BU6: N01 | BV6: N09 | BW6: O00 | BX6: P00 | BY6: Q01 | BZ6: Q02 | CA6: R01 | CB6: R09 | CC6: S00 | CD6: T00
D7: =SUM(E7:CD7) -> 11646.996 | E7: =SUM(E8:E86) -> 206.67601 | F7: =SUM(F8:F86) -> 468.14634 | G7: =SUM(G8:G86) -> 396.78988 | H7: =SUM(H8:H86) -> 283.59608 | I7: =SUM(I8:I86) -> 15.001884 | J7: =SUM(J8:J86) -> 77.156236 | K7: =SUM(K8:K86) -> 24.490147 | L7: =SUM(L8:L86) -> 48.183435 | ... CD7: =SUM(CD8:CD86) -> 25.436762
B8: Cereals | C8: A11 | D8: =SUM(E8:CD8) -> 206.67601 | E8: 206.67601 | F8: 0 | G8: 0 | H8: 0 | I8: 0 | J8: 0 | K8: 0 | L8: 0 | M8: 0 | N8: 0 | O8: 0 | P8: 0 | Q8: 0 | R8: 0 | S8: 0 | T8: 0 | U8: 0 | V8: 0 | W8: 0 | X8: 0 | Y8: 0 | Z8: 0 | AA8: 0 | AB8: 0 | AC8: 0 | AD8: 0 | AE8: 0 | AF8: 0 | AG8: 0 | AH8: 0 | AI8: 0 | AJ8: 0 | AK8: 0 | AL8: 0 | AM8: 0 | AN8: 0 | AO8: 0 | AP8: 0 | AQ8: 0 | AR8: 0 | AS8: 0 | AT8: 0 | AU8: 0 | AV8: 0 | AW8: 0 | AX8: 0 | AY8: 0 | AZ8: 0 | BA8: 0 | BB8: 0 | BC8: 0 | BD8: 0 | BE8: 0 | BF8: 0 | BG8: 0 | BH8: 0 | BI8: 0 | BJ8: 0 | BK8: 0 | BL8: 0 | BM8: 0 | BN8: 0 | BO8: 0 | BP8: 0 | BQ8: 0 | BR8: 0 | BS8: 0 | BT8: 0 | BU8: 0 | BV8: 0 | BW8: 0 | BX8: 0 | BY8: 0 | BZ8: 0 | CA8: 0 | CB8: 0 | CC8: 0 | CD8: 0
B9: Roots and Tubers | C9: A12 | D9: =SUM(E9:CD9) -> 468.14634 | E9: 0 | F9: 468.14634 | G9: 0 | H9: 0 | I9: 0 | J9: 0 | K9: 0 | L9: 0 | M9: 0 | N9: 0 | O9: 0 | P9: 0 | Q9: 0 | R9: 0 | S9: 0 | T9: 0 | U9: 0 | V9: 0 | W9: 0 | X9: 0 | Y9: 0 | Z9: 0 | AA9: 0 | AB9: 0 | AC9: 0 | AD9: 0 | AE9: 0 | AF9: 0 | AG9: 0 | AH9: 0 | AI9: 0 | AJ9: 0 | AK9: 0 | AL9: 0 | AM9: 0 | AN9: 0 | AO9: 0 | AP9: 0 | AQ9: 0 | AR9: 0 | AS9: 0 | AT9: 0 | AU9: 0 | AV9: 0 | AW9: 0 | AX9: 0 | AY9: 0 | AZ9: 0 | BA9: 0 | BB9: 0 | BC9: 0 | BD9: 0 | BE9: 0 | BF9: 0 | BG9: 0 | BH9: 0 | BI9: 0 | BJ9: 0 | BK9: 0 | BL9: 0 | BM9: 0 | BN9: 0 | BO9: 0 | BP9: 0 | BQ9: 0 | BR9: 0 | BS9: 0 | BT9: 0 | BU9: 0 | BV9: 0 | BW9: 0 | BX9: 0 | BY9: 0 | BZ9: 0 | CA9: 0 | CB9: 0 | CC9: 0 | CD9: 0
B10: Vegetables | C10: A13 | D10: =SUM(E10:CD10) -> 396.78988 | E10: 0 | F10: 0 | G10: 396.78988 | H10: 0 | I10: 0 | J10: 0 | K10: 0 | L10: 0 | M10: 0 | N10: 0 | O10: 0 | P10: 0 | Q10: 0 | R10: 0 | S10: 0 | T10: 0 | U10: 0 | V10: 0 | W10: 0 | X10: 0 | Y10: 0 | Z10: 0 | AA10: 0 | AB10: 0 | AC10: 0 | AD10: 0 | AE10: 0 | AF10: 0 | AG10: 0 | AH10: 0 | AI10: 0 | AJ10: 0 | AK10: 0 | AL10: 0 | AM10: 0 | AN10: 0 | AO10: 0 | AP10: 0 | AQ10: 0 | AR10: 0 | AS10: 0 | AT10: 0 | AU10: 0 | AV10: 0 | AW10: 0 | AX10: 0 | AY10: 0 | AZ10: 0 | BA10: 0 | BB10: 0 | BC10: 0 | BD10: 0 | BE10: 0 | BF10: 0 | BG10: 0 | BH10: 0 | BI10: 0 | BJ10: 0 | BK10: 0 | BL10: 0 | BM10: 0 | BN10: 0 | BO10: 0 | BP10: 0 | BQ10: 0 | BR10: 0 | BS10: 0 | BT10: 0 | BU10: 0 | BV10: 0 | BW10: 0 | BX10: 0 | BY10: 0 | BZ10: 0 | CA10: 0 | CB10: 0 | CC10: 0 | CD10: 0
B11: Bananas and fruit | C11: A14 | D11: =SUM(E11:CD11) -> 283.59608 | E11: 0 | F11: 0 | G11: 0 | H11: 283.59608 | I11: 0 | J11: 0 | K11: 0 | L11: 0 | M11: 0 | N11: 0 | O11: 0 | P11: 0 | Q11: 0 | R11: 0 | S11: 0 | T11: 0 | U11: 0 | V11: 0 | W11: 0 | X11: 0 | Y11: 0 | Z11: 0 | AA11: 0 | AB11: 0 | AC11: 0 | AD11: 0 | AE11: 0 | AF11: 0 | AG11: 0 | AH11: 0 | AI11: 0 | AJ11: 0 | AK11: 0 | AL11: 0 | AM11: 0 | AN11: 0 | AO11: 0 | AP11: 0 | AQ11: 0 | AR11: 0 | AS11: 0 | AT11: 0 | AU11: 0 | AV11: 0 | AW11: 0 | AX11: 0 | AY11: 0 | AZ11: 0 | BA11: 0 | BB11: 0 | BC11: 0 | BD11: 0 | BE11: 0 | BF11: 0 | BG11: 0 | BH11: 0 | BI11: 0 | BJ11: 0 | BK11: 0 | BL11: 0 | BM11: 0 | BN11: 0 | BO11: 0 | BP11: 0 | BQ11: 0 | BR11: 0 | BS11: 0 | BT11: 0 | BU11: 0 | BV11: 0 | BW11: 0 | BX11: 0 | BY11: 0 | BZ11: 0 | CA11: 0 | CB11: 0 | CC11: 0 | CD11: 0
B12: Oil seeds n.e.c. and oleaginous fruit | C12: A15 | D12: =SUM(E12:CD12) -> 15.001884 | E12: 0 | F12: 0 | G12: 0 | H12: 0 | I12: 15.001884 | J12: 0 | K12: 0 | L12: 0 | M12: 0 | N12: 0 | O12: 0 | P12: 0 | Q12: 0 | R12: 0 | S12: 0 | T12: 0 | U12: 0 | V12: 0 | W12: 0 | X12: 0 | Y12: 0 | Z12: 0 | AA12: 0 | AB12: 0 | AC12: 0 | AD12: 0 | AE12: 0 | AF12: 0 | AG12: 0 | AH12: 0 | AI12: 0 | AJ12: 0 | AK12: 0 | AL12: 0 | AM12: 0 | AN12: 0 | AO12: 0 | AP12: 0 | AQ12: 0 | AR12: 0 | AS12: 0 | AT12: 0 | AU12: 0 | AV12: 0 | AW12: 0 | AX12: 0 | AY12: 0 | AZ12: 0 | BA12: 0 | BB12: 0 | BC12: 0 | BD12: 0 | BE12: 0 | BF12: 0 | BG12: 0 | BH12: 0 | BI12: 0 | BJ12: 0 | BK12: 0 | BL12: 0 | BM12: 0 | BN12: 0 | BO12: 0 | BP12: 0 | BQ12: 0 | BR12: 0 | BS12: 0 | BT12: 0 | BU12: 0 | BV12: 0 | BW12: 0 | BX12: 0 | BY12: 0 | BZ12: 0 | CA12: 0 | CB12: 0 | CC12: 0 | CD12: 0
B13: Coffee | C13: A21 | D13: =SUM(E13:CD13) -> 77.156236 | E13: 0 | F13: 0 | G13: 0 | H13: 0 | I13: 0 | J13: 77.156236 | K13: 0 | L13: 0 | M13: 0 | N13: 0 | O13: 0 | P13: 0 | Q13: 0 | R13: 0 | S13: 0 | T13: 0 | U13: 0 | V13: 0 | W13: 0 | X13: 0 | Y13: 0 | Z13: 0 | AA13: 0 | AB13: 0 | AC13: 0 | AD13: 0 | AE13: 0 | AF13: 0 | AG13: 0 | AH13: 0 | AI13: 0 | AJ13: 0 | AK13: 0 | AL13: 0 | AM13: 0 | AN13: 0 | AO13: 0 | AP13: 0 | AQ13: 0 | AR13: 0 | AS13: 0 | AT13: 0 | AU13: 0 | AV13: 0 | AW13: 0 | AX13: 0 | AY13: 0 | AZ13: 0 | BA13: 0 | BB13: 0 | BC13: 0 | BD13: 0 | BE13: 0 | BF13: 0 | BG13: 0 | BH13: 0 | BI13: 0 | BJ13: 0 | BK13: 0 | BL13: 0 | BM13: 0 | BN13: 0 | BO13: 0 | BP13: 0 | BQ13: 0 | BR13: 0 | BS13: 0 | BT13: 0 | BU13: 0 | BV13: 0 | BW13: 0 | BX13: 0 | BY13: 0 | BZ13: 0 | CA13: 0 | CB13: 0 | CC13: 0 | CD13: 0
B14: Tea (unprocessed green leaf) | C14: A22 | D14: =SUM(E14:CD14) -> 24.490147 | E14: 0 | F14: 0 | G14: 0 | H14: 0 | I14: 0 | J14: 0 | K14: 24.490147 | L14: 0 | M14: 0 | N14: 0 | O14: 0 | P14: 0 | Q14: 0 | R14: 0 | S14: 0 | T14: 0 | U14: 0 | V14: 0 | W14: 0 | X14: 0 | Y14: 0 | Z14: 0 | AA14: 0 | AB14: 0 | AC14: 0 | AD14: 0 | AE14: 0 | AF14: 0 | AG14: 0 | AH14: 0 | AI14: 0 | AJ14: 0 | AK14: 0 | AL14: 0 | AM14: 0 | AN14: 0 | AO14: 0 | AP14: 0 | AQ14: 0 | AR14: 0 | AS14: 0 | AT14: 0 | AU14: 0 | AV14: 0 | AW14: 0 | AX14: 0 | AY14: 0 | AZ14: 0 | BA14: 0 | BB14: 0 | BC14: 0 | BD14: 0 | BE14: 0 | BF14: 0 | BG14: 0 | BH14: 0 | BI14: 0 | BJ14: 0 | BK14: 0 | BL14: 0 | BM14: 0 | BN14: 0 | BO14: 0 | BP14: 0 | BQ14: 0 | BR14: 0 | BS14: 0 | BT14: 0 | BU14: 0 | BV14: 0 | BW14: 0 | BX14: 0 | BY14: 0 | BZ14: 0 | CA14: 0 | CB14: 0 | CC14: 0 | CD14: 0
B15: Other agricultural products | C15: A29 | D15: =SUM(E15:CD15) -> 48.183435 | E15: 0 | F15: 0 | G15: 0 | H15: 0 | I15: 0 | J15: 0 | K15: 0 | L15: 48.183435 | M15: 0 | N15: 0 | O15: 0 | P15: 0 | Q15: 0 | R15: 0 | S15: 0 | T15: 0 | U15: 0 | V15: 0 | W15: 0 | X15: 0 | Y15: 0 | Z15: 0 | AA15: 0 | AB15: 0 | AC15: 0 | AD15: 0 | AE15: 0 | AF15: 0 | AG15: 0 | AH15: 0 | AI15: 0 | AJ15: 0 | AK15: 0 | AL15: 0 | AM15: 0 | AN15: 0 | AO15: 0 | AP15: 0 | AQ15: 0 | AR15: 0 | AS15: 0 | AT15: 0 | AU15: 0 | AV15: 0 | AW15: 0 | AX15: 0 | AY15: 0 | AZ15: 0 | BA15: 0 | BB15: 0 | BC15: 0 | BD15: 0 | BE15: 0 | BF15: 0 | BG15: 0 | BH15: 0 | BI15: 0 | BJ15: 0 | BK15: 0 | BL15: 0 | BM15: 0 | BN15: 0 | BO15: 0 | BP15: 0 | BQ15: 0 | BR15: 0 | BS15: 0 | BT15: 0 | BU15: 0 | BV15: 0 | BW15: 0 | BX15: 0 | BY15: 0 | BZ15: 0 | CA15: 0 | CB15: 0 | CC15: 0 | CD15: 0
B16: Livestock | C16: A31 | D16: =SUM(E16:CD16) -> 141.46606 | E16: 0 | F16: 0 | G16: 0 | H16: 0 | I16: 0 | J16: 0 | K16: 0 | L16: 0 | M16: 141.46606 | N16: 0 | O16: 0 | P16: 0 | Q16: 0 | R16: 0 | S16: 0 | T16: 0 | U16: 0 | V16: 0 | W16: 0 | X16: 0 | Y16: 0 | Z16: 0 | AA16: 0 | AB16: 0 | AC16: 0 | AD16: 0 | AE16: 0 | AF16: 0 | AG16: 0 | AH16: 0 | AI16: 0 | AJ16: 0 | AK16: 0 | AL16: 0 | AM16: 0 | AN16: 0 | AO16: 0 | AP16: 0 | AQ16: 0 | AR16: 0 | AS16: 0 | AT16: 0 | AU16: 0 | AV16: 0 | AW16: 0 | AX16: 0 | AY16: 0 | AZ16: 0 | BA16: 0 | BB16: 0 | BC16: 0 | BD16: 0 | BE16: 0 | BF16: 0 | BG16: 0 | BH16: 0 | BI16: 0 | BJ16: 0 | BK16: 0 | BL16: 0 | BM16: 0 | BN16: 0 | BO16: 0 | BP16: 0 | BQ16: 0 | BR16: 0 | BS16: 0 | BT16: 0 | BU16: 0 | BV16: 0 | BW16: 0 | BX16: 0 | BY16: 0 | BZ16: 0 | CA16: 0 | CB16: 0 | CC16: 0 | CD16: 0
B17: Livestock and hunting products | C17: A32 | D17: =SUM(E17:CD17) -> 57.506207 | E17: 0 | F17: 0 | G17: 0 | H17: 0 | I17: 0 | J17: 0 | K17: 0 | L17: 0 | M17: 0 | N17: 57.506207 | O17: 0 | P17: 0 | Q17: 0 | R17: 0 | S17: 0 | T17: 0 | U17: 0 | V17: 0 | W17: 0 | X17: 0 | Y17: 0 | Z17: 0 | AA17: 0 | AB17: 0 | AC17: 0 | AD17: 0 | AE17: 0 | AF17: 0 | AG17: 0 | AH17: 0 | AI17: 0 | AJ17: 0 | AK17: 0 | AL17: 0 | AM17: 0 | AN17: 0 | AO17: 0 | AP17: 0 | AQ17: 0 | AR17: 0 | AS17: 0 | AT17: 0 | AU17: 0 | AV17: 0 | AW17: 0 | AX17: 0 | AY17: 0 | AZ17: 0 | BA17: 0 | BB17: 0 | BC17: 0 | BD17: 0 | BE17: 0 | BF17: 0 | BG17: 0 | BH17: 0 | BI17: 0 | BJ17: 0 | BK17: 0 | BL17: 0 | BM17: 0 | BN17: 0 | BO17: 0 | BP17: 0 | BQ17: 0 | BR17: 0 | BS17: 0 | BT17: 0 | BU17: 0 | BV17: 0 | BW17: 0 | BX17: 0 | BY17: 0 | BZ17: 0 | CA17: 0 | CB17: 0 | CC17: 0 | CD17: 0
B18: Forestry products | C18: A40 | D18: =SUM(E18:CD18) -> 379.13228 | E18: 0 | F18: 0 | G18: 0 | H18: 0 | I18: 0 | J18: 0 | K18: 0 | L18: 0 | M18: 0 | N18: 0 | O18: 379.13228 | P18: 0 | Q18: 0 | R18: 0 | S18: 0 | T18: 0 | U18: 0 | V18: 0 | W18: 0 | X18: 0 | Y18: 0 | Z18: 0 | AA18: 0 | AB18: 0 | AC18: 0 | AD18: 0 | AE18: 0 | AF18: 0 | AG18: 0 | AH18: 0 | AI18: 0 | AJ18: 0 | AK18: 0 | AL18: 0 | AM18: 0 | AN18: 0 | AO18: 0 | AP18: 0 | AQ18: 0 | AR18: 0 | AS18: 0 | AT18: 0 | AU18: 0 | AV18: 0 | AW18: 0 | AX18: 0 | AY18: 0 | AZ18: 0 | BA18: 0 | BB18: 0 | BC18: 0 | BD18: 0 | BE18: 0 | BF18: 0 | BG18: 0 | BH18: 0 | BI18: 0 | BJ18: 0 | BK18: 0 | BL18: 0 | BM18: 0 | BN18: 0 | BO18: 0 | BP18: 0 | BQ18: 0 | BR18: 0 | BS18: 0 | BT18: 0 | BU18: 0 | BV18: 0 | BW18: 0 | BX18: 0 | BY18: 0 | BZ18: 0 | CA18: 0 | CB18: 0 | CC18: 0 | CD18: 0
B19: Fishery products | C19: A50 | D19: =SUM(E19:CD19) -> 29.763623 | E19: 0 | F19: 0 | G19: 0 | H19: 0 | I19: 0 | J19: 0 | K19: 0 | L19: 0 | M19: 0 | N19: 0 | O19: 0 | P19: 29.763623 | Q19: 0 | R19: 0 | S19: 0 | T19: 0 | U19: 0 | V19: 0 | W19: 0 | X19: 0 | Y19: 0 | Z19: 0 | AA19: 0 | AB19: 0 | AC19: 0 | AD19: 0 | AE19: 0 | AF19: 0 | AG19: 0 | AH19: 0 | AI19: 0 | AJ19: 0 | AK19: 0 | AL19: 0 | AM19: 0 | AN19: 0 | AO19: 0 | AP19: 0 | AQ19: 0 | AR19: 0 | AS19: 0 | AT19: 0 | AU19: 0 | AV19: 0 | AW19: 0 | AX19: 0 | AY19: 0 | AZ19: 0 | BA19: 0 | BB19: 0 | BC19: 0 | BD19: 0 | BE19: 0 | BF19: 0 | BG19: 0 | BH19: 0 | BI19: 0 | BJ19: 0 | BK19: 0 | BL19: 0 | BM19: 0 | BN19: 0 | BO19: 0 | BP19: 0 | BQ19: 0 | BR19: 0 | BS19: 0 | BT19: 0 | BU19: 0 | BV19: 0 | BW19: 0 | BX19: 0 | BY19: 0 | BZ19: 0 | CA19: 0 | CB19: 0 | CC19: 0 | CD19: 0
... B86: Travel debits & credits | C86: V00 | D86: =SUM(E86:CD86) -> 0 | E86: 0 | F86: 0 | G86: 0 | H86: 0 | I86: 0 | J86: 0 | K86: 0 | L86: 0 | M86: 0 | N86: 0 | O86: 0 | P86: 0 | Q86: 0 | R86: 0 | S86: 0 | T86: 0 | U86: 0 | V86: 0 | W86: 0 | X86: 0 | Y86: 0 | Z86: 0 | AA86: 0 | AB86: 0 | AC86: 0 | AD86: 0 | AE86: 0 | AF86: 0 | AG86: 0 | AH86: 0 | AI86: 0 | AJ86: 0 | AK86: 0 | AL86: 0 | AM86: 0 | AN86: 0 | AO86: 0 | AP86: 0 | AQ86: 0 | AR86: 0 | AS86: 0 | AT86: 0 | AU86: 0 | AV86: 0 | AW86: 0 | AX86: 0 | AY86: 0 | AZ86: 0 | BA86: 0 | BB86: 0 | BC86: 0 | BD86: 0 | BE86: 0 | BF86: 0 | BG86: 0 | BH86: 0 | BI86: 0 | BJ86: 0 | BK86: 0 | BL86: 0 | BM86: 0 | BN86: 0 | BO86: 0 | BP86: 0 | BQ86: 0 | BR86: 0 | BS86: 0 | BT86: 0 | BU86: 0 | BV86: 0 | BW86: 0 | BX86: 0 | BY86: 0 | BZ86: 0 | CA86: 0 | CB86: 0 | CC86: 0 | CD86: 0

Sheet Notes
A1: SAM Accounts
A6: RCPA2 | B6: RCPA3 | C6: Abbrev. | D6: Activity | E6: Commodity | F6: Description | M6: RCPA2 | N6: Description
A7: A11 | B7: A111 | C7: sorg | D7: asorg | E7: csorg | F7: Sorghum (A111) | M7: A11 | N7: Cereals | S7: apota | T7: Sorghum (A111) | U7: A111 | X7: asorg | Y7: Sorghum (A111)
A8: A11 | B8: A112 | C8: maiz | D8: amaiz | E8: cmaiz | F8: Maize (A112) | M8: A12 | N8: Roots and Tubers | S8: aspot | T8: Maize (A112) | U8: A112 | X8: amaiz | Y8: Maize (A112)
A9: A11 | B9: A113 | C9: whea | D9: awhea | E9: cwhea | F9: Wheat (A113) | M9: A13 | N9: Vegetables | S9: acass | T9: Wheat (A113) | U9: A113 | X9: awhea | Y9: Wheat (A113)
A10: A11 | B10: A116 | C10: rice | D10: arice | E10: crice | F10: Paddy & husked rice (A116) | M10: A14 | N10: Bananas and fruit | S10: aroot | T10: Paddy & husked rice (A116) | U10: A116 | X10: arice | Y10: Paddy & husked rice (A116)
A11: A11 | B11: A119 | C11: ocer | D11: aocer | E11: cocer | F11: Other cereals (A119) | M11: A15 | N11: Oil seeds n.e.c. and oleaginous fruit | S11: apuls | T11: Other cereals (A119) | U11: A119 | Y11: Other cereals (A119)
A12: A12 | B12: A121 | C12: ipot | D12: aipot | E12: cipot | F12: Irish potatoes (A121) | M12: A21 | N12: Coffee | S12: apuls | T12: Irish potatoes (A121) | U12: A121 | X12: apota | Y12: Irish potatoes (A121)
A13: A12 | B13: A122 | C13: spot | D13: aspot | E13: cspot | F13: Sweet potatoes (A122) | M13: A22 | N13: Tea (unprocessed green leaf) | S13: avege | T13: Sweet potatoes (A122) | U13: A122 | X13: aspot | Y13: Sweet potatoes (A122)
A14: A12 | B14: A123 | C14: cass | D14: acass | E14: ccass | F14: Cassava (A123) | M14: A29 | N14: Other agricultural products | S14: abana | T14: Cassava (A123) | U14: A123 | X14: acass | Y14: Cassava (A123)
A15: A12 | B15: A129 | C15: root | D15: aroot | E15: croot | F15: Other roots & tubers (A129) | M15: A31 | N15: Livestock | S15: abana | T15: Other roots & tubers (A129) | U15: A129 | X15: aroot | Y15: Other roots & tubers (A129)
A16: A13 | B16: A131 | C16: bean | D16: abean | E16: cbean | F16: Dried beans (A131) | M16: A32 | N16: Livestock and hunting products | S16: abana | T16: Dried beans (A131) | U16: A131 | X16: apuls | Y16: Dried beans (A131)
A17: A13 | B17: A132 | C17: peas | D17: apeas | E17: cpeas | F17: Peas & other legumes (A132) | M17: A40 | N17: Forestry products | S17: afrui | T17: Peas & other legumes (A132) | U17: A132 | X17: apuls | Y17: Peas & other legumes (A132)
A18: A13 | B18: A139 | C18: vege | D18: avege | E18: cvege | F18: Other vegetables (A139) | M18: A50 | N18: Fishery products | S18: aoils | T18: Other vegetables (A139) | U18: A139 | X18: avege | Y18: Other vegetables (A139)
A19: A14 | B19: A141 | C19: banb | D19: abanb | E19: cbanb | F19: Bananas for beer (A141) | M19: B01 | N19: Natural gas | S19: aoils | T19: Bananas for beer (A141) | U19: A141 | X19: abana | Y19: Bananas for beer (A141)
A20: A14 | B20: A142 | C20: banc | D20: abanc | E20: cbanc | F20: Bananas for cooking (A142) | M20: B03 | N20: Metal ores | S20: aoils | T20: Bananas for cooking (A142) | U20: A142 | X20: abana | Y20: Bananas for cooking (A142)
A21: A14 | B21: A143 | C21: bans | D21: abans | E21: cbans | F21: Bananas (sweet) (A143) | M21: B09 | N21: Quarry & other mining products | S21: acoff | T21: Bananas (sweet) (A143) | U21: A143 | X21: abana | Y21: Bananas (sweet) (A143)
A22: A14 | B22: A149 | C22: frui | D22: afrui | E22: cfrui | F22: Other fruit & nuts (A149) | M22: C11 | N22: Meat and meat products | S22: agtea | T22: Other fruit & nuts (A149) | U22: A149 | X22: afrui | Y22: Other fruit & nuts (A149)
A23: A15 | B23: A151 | C23: gnut | D23: agnut | E23: cgnut | F23: Ground nuts (A151) | M23: C12 | N23: Prepared and preserved fish | S23: aotex | T23: Ground nuts (A151) | U23: A151 | X23: aoils | Y23: Ground nuts (A151)
... A86: H31 | B86: H31 | C86: trns | D86: atrns | E86: ctrns | F86: Services related to transport (H31) | M86: X00 | N86: Unallocated products | S86: acomm | T86: Services related to transport (H31) | U86: H31 | X86: atran | Y86: Services related to transport (H31)
A87: H32 | B87: H32 | C87: post | D87: apost | E87: cpost | F87: Postal and courier activities (H32) | S87: afina | T87: Postal and courier activities (H32) | U87: H32 | X87: atran | Y87: Postal and courier activities (H32)
A88: I00 | B88: I00 | C88: hotl | D88: ahotl | E88: chotl | F88: Hotels & restaurants (I00) | S88: afina | T88: Hotels & restaurants (I00) | U88: I00 | X88: ahote | Y88: Hotels & restaurants (I00)
A89: J10 | B89: J10 | C89: publ | D89: apubl | E89: cpubl | F89: Publishing, video making, programming & broadcasting activities (J10) | S89: afina | T89: Publishing, video making, programming & broadcasting activities (J10) | U89: J10 | X89: acomm | Y89: Publishing, video making, programming & broadcasting activities (J10)
A90: J20 | B90: J20 | C90: comm | D90: acomm | E90: ccomm | F90: Telecommunication (J20) | S90: arsta | T90: Telecommunication (J20) | U90: J20 | X90: acomm | Y90: Telecommunication (J20)
A91: J30 | B91: J30 | C91: info | D91: ainfo | E91: cinfo | F91: Information technology services (J30) | S91: arsta | T91: Information technology services (J30) | U91: J30 | X91: acomm | Y91: Information technology services (J30)
A92: K01 | B92: K01 | C92: bank | D92: abank | E92: cbank | F92: Monetary institutions (K01) | S92: aserv | T92: Monetary institutions (K01) | U92: K01 | X92: afina | Y92: Monetary institutions (K01)
A93: K02 | B93: K02 | C93: insu | D93: ainsu | E93: cinsu | F93: Insurance, reinsurance and pension funding, except compulsory social security (K02) | S93: aserv | T93: Insurance, reinsurance and pension funding, except compulsory social security (K02) | U93: K02 | X93: afina | Y93: Insurance, reinsurance and pension funding, except compulsory social security (K02)
A94: K03 | B94: K03 | C94: ofsv | D94: aofsv | E94: cofsv | F94: Other financial services (K03) | S94: aserv | T94: Other financial services (K03) | U94: K03 | X94: afina | Y94: Other financial services (K03)
A95: L01 | B95: L01 | C95: rent | D95: arent | E95: crent | F95: Rental value of dwellings (L01) | S95: aserv | T95: Rental value of dwellings (L01) | U95: L01 | X95: arsta | Y95: Rental value of dwellings (L01)
A96: L09 | B96: L09 | C96: real | D96: areal | E96: creal | F96: Other real estate activities (L09) | S96: aserv | T96: Other real estate activities (L09) | U96: L09 | X96: arsta | Y96: Other real estate activities (L09)
A97: M01 | B97: M01 | C97: legl | D97: alegl | E97: clegl | F97: Legal, accounting management & head office activities (M01) | S97: agov | T97: Legal, accounting management & head office activities (M01) | U97: M01 | X97: aserv | Y97: Legal, accounting management & head office activities (M01)
A98: M02 | B98: M02 | C98: enga | D98: aenga | E98: cenga | F98: Architectural and engineering activities (M02) | S98: aeduc | T98: Architectural and engineering activities (M02) | U98: M02 | X98: aserv | Y98: Architectural and engineering activities (M02)
... A109: T00 | B109: T00 | C109: dsrv | D109: adsrv | E109: cdsrv | F109: Domestic services (T00) | S109: arsta | T109: Domestic services (T00) | U109: T00 | X109: aoser | Y109: Domestic services (T00)
A110: V00 | B110: V00 | D110: atrdc | E110: ctrdc | F110: Travel debits & credits (V00) | S110: arsta | T110: Travel debits & credits (V00) | U110: V00 | X110: aoser | Y110: Travel debits & credits (V00)
A111: X00 | B111: X00 | F111: Unallocated products (X00) | S111: aserv | T111: Unallocated products (X00) | U111: X00 | X111: aoser | Y111: Unallocated products (X00)

Sheet Final
A1: Final Supply and Use Tables
D2: INT = 1 - GDP/GO | F2: GO = GDP + INT
A3: Use table coefficients | D3: Sorghum (A111) | E3: Maize (A112) | F3: Wheat (A113) | G3: Paddy & husked rice (A116) | H3: Other cereals (A119) | I3: Irish potatoes (A121) | J3: Sweet potatoes (A122) | K3: Cassava (A123) | L3: Other roots & tubers (A129) | M3: Dried beans (A131) | N3: Peas & other legumes (A132) | O3: Other vegetables (A139) | P3: Bananas for beer (A141) | Q3: Bananas for cooking (A142) | R3: Bananas (sweet) (A143) | S3: Other fruit & nuts (A149) | T3: Ground nuts (A151) | U3: Soya (A152) | V3: Other oil seeds (A159) | W3: Coffee, not roasted, not decaffeinated (A210) | X3: Tea (unprocessed green leaf) (A220) | Y3: Tobacco, raw (A291) | Z3: Sugar cane (A292) | AA3: Pyrethrum (A293) | AB3: Agricultural products n.e.c. (A299) | AC3: Bovine cattle, live (A311) | AD3: Sheep, goats, pigs,live (A312) | AE3: Poultry, live (A313) | AF3: Other live animals (A319) | AG3: Raw milk (A321) | AH3: Eggs (A322) | AI3: Natural honey (A323) | AJ3: Other livestock & hunting products (A329) | AK3: Fuel wood (A401) | AL3: Charcoal (A402) | AM3: Other forestry products (A409) | AN3: Fishery products (A500) | AO3: Natural gas (B01) | AP3: Metal ores (B03) | AQ3: Quarry & other mining products (B09) | AR3: Meat and meat products (C11) | AS3: Prepared and preserved fish (C12) | AT3: Prepared and preserved vegetables (C13) | AU3: Animal and vegetable oils and fats (C14) | AV3: Dairy products (C15) | AW3: Grain mill products (C16) | AX3: Bakery products (C17) | AY3: Animal feed & other by-products (C18) | AZ3: Other manufactured food products (C19) | BA3: Alcoholic drinks (C21) | BB3: Soft drinks (C22) | BC3: Tobacco products (C23) | BD3: Textiles, clothing & leather products (C30) | BE3: Wood, paper and related products (C41) | BF3: Printing and reproduction of recorded media (C42) | BG3: Coke and refined petroleum products (C51) | BH3: Chemicals and chemical products (C52) | BI3: Pharmaceutical products (C53) | BJ3: Rubber and plastics products (C54) | BK3: Non-metallic mineral products n.e.c. (C61) | BL3: Manufacture of cement, lime and plaster (C62) | BM3: Manufacture of clay building materials (C63) | BN3: Metals & metal products, except machinery and equipment (C72) | BO3: Machinery and equipment (except transport) (C74) | BP3: Transport equipment (C76) | BQ3: Furniture (C81) | BR3: Other manufacturing (C82) | BS3: Repair and installation of machinery and equipment (C83) | BT3: Electricity, gas, steam and air conditioning supply (D00) | BU3: Water collection, treatment and supply: sewrage (E01) | BV3: Waste collection and management (E02) | BW3: Construction (modern) (F01) | BX3: Construction (traditional) (F02) | BY3: Maintenance and repair of motor vehicles (G10) | BZ3: Wholesale and retail trade of motor vehicles and motorcycles (G21) | CA3: Wholesale trade, except of motor vehicles and motorcycles (G22) | CB3: Retail trade, except of motor vehicles and motorcycles (G23) | CC3: Land transport (H10) | CD3: Air transport (H20) | CE3: Services related to transport (H31) | CF3: Postal and courier activities (H32) | CG3: Hotels & restaurants (I00) | CH3: Publishing, video making, programming & broadcasting activities (J10) | CI3: Telecommunication (J20) | CJ3: Information technology services (J30) | CK3: Monetary institutions (K01) | CL3: Insurance, reinsurance and pension funding, except compulsory social security (K02) | CM3: Other financial services (K03) | CN3: Rental value of dwellings (L01) | CO3: Other real estate activities (L09) | CP3: Legal, accounting management & head office activities (M01) | CQ3: Architectural and engineering activities (M02) | CR3: Other professional, scientific and technical activities (M03) | CS3: Travel agents and tour operators (N01) | CT3: Other administrative and support service activities (N09) | CU3: Public administration and defence; compulsory social security (O00) | CV3: Education (P00) | CW3: Human health activities (Q01) | CX3: Social work activities (Q02) | CY3: Libraries, archives, museums and other cultural activities (R01) | CZ3: Other arts, entertainment and recreation (R09) | DA3: Other service activities (S00) | DB3: Domestic services (T00) | DC3: Travel debits & credits (V00)
B4: GDP/GO | C4: Orig. | D4: {=TRANSPOSE(GDP!W7:W111)} -> 0.93309851 | E4: 0.93309851 | F4: 0.93309851 | G4: 0.93309851 | H4: 0.93309851 | I4: 0.9352899 | J4: 0.9352899 | K4: 0.9352899 | L4: 0.9352899 | M4: 0.95070324 | N4: 0.95070324 | O4: 0.95070324 | P4: 0.97790125 | Q4: 0.97790125 | R4: 0.97790125 | S4: 0.97790125 | T4: 0.75407428 | U4: 0.75407428 | V4: 0.75407428 | W4: 0.91848864 | X4: 0.91391359 | Y4: 0.92568267 | Z4: 0.92568267 | AA4: 0.92568267 | AB4: 0.92568267 | AC4: 0.91678309 | AD4: 0.91678309 | AE4: 0.91678309 | AF4: 0.91678309 | AG4: 0.97371875 | AH4: 0.97371875 | AI4: 0.97371875 | AJ4: 0.97371875 | AK4: 0.99816602 | AL4: 0.99816602 | AM4: 0.99816602 | AN4: 0.95855384 | AO4: 1 | AP4: 0.6416892 | AQ4: 0.7314137 | AR4: 0.2266543 | AS4: 0.2266543 | AT4: 0.32565389 | AU4: 0.49112069 | AV4: 0.57009698 | AW4: 0.27681751 | AX4: 0.24094973 | AY4: 0.94501676 | AZ4: 0.40607617 | BA4: 0.4883556 | BB4: 0.57494378 | BC4: 0.76946244 | BD4: 0.48790814 | BE4: 0.48876047 | BF4: 0.41458021 | BG4: 0.86046312 | BH4: 0.36286877 | BI4: 0.78781152 | BJ4: 0.26019123 | BK4: 0.28141842 | BL4: 0.38147134 | BM4: 0.55609693 | BN4: 0.1559116 | BO4: 0.64203789 | BP4: 0.50321092 | BQ4: 0.61979088 | BR4: 0.79911143 | BS4: 0.25122961 | BT4: 0.5155325 | BU4: 0.63688917 | BV4: 0.42852161 | BW4: 0.35223586 | BX4: 0.35223586 | BY4: 0.71823903 | BZ4: 0.41214028 | CA4: 0.50163381 | CB4: 0.6134132 | CC4: 0.50004408 | CD4: 0.53332365 | CE4: 0.63866813 | CF4: 0.62636219 | CG4: 0.27276413 | CH4: 0.71682835 | CI4: 0.47015673 | CJ4: 0.59216837 | CK4: 0.46601904 | CL4: 0.81756387 | CM4: 0.68170899 | CN4: 1 | CO4: 0.88758421 | CP4: 0.84616728 | CQ4: 0.77425173 | CR4: 0.90286586 | CS4: 0.55541203 | CT4: 0.92930972 | CU4: 0.40177469 | CV4: 0.62857876 | CW4: 0.48138281 | CX4: 0.59039791 | CY4: 0.8148947 | CZ4: 0.95194844 | DA4: 0.73665734 | DB4: 0.97663132 | DC4: 1
C5: Used | D5: =D4 -> 0.93309851 | E5: =E4 -> 0.93309851 | F5: =F4 -> 0.93309851 | G5: =G4 -> 0.93309851 | H5: =H4 -> 0.93309851 | I5: =I4 -> 0.9352899 | J5: =J4 -> 0.9352899 | K5: =K4 -> 0.9352899 | ... DC5: =DC4 -> 1
B7: Orig. | C7: flab | D7: {=TRANSPOSE(GDP!L7:N111)} -> 0.42220218 | E7: 0.44086658 | F7: 0.45348046 | G7: 0.4532881 | H7: 0.42220218 | I7: 0.47058963 | J7: 0.43368245 | K7: 0.42490888 | L7: 0.46228215 | M7: 0.51205744 | N7: 0.51205744 | O7: 0.56833808 | P7: 0.46534412 | Q7: 0.46534412 | R7: 0.46534412 | S7: 0.56228195 | T7: 0.46263043 | U7: 0.46263043 | V7: 0.46263043 | W7: 0.67904408 | X7: 0.66358066 | Y7: 0.5372261 | Z7: 0.5372261 | AA7: 0.5243602 | AB7: 0.5372261 | AC7: 0.45338998 | AD7: 0.45408331 | AE7: 0.45077431 | AF7: 0.45548988 | AG7: 0.45593561 | AH7: 0.45558062 | AI7: 0.4739655 | AJ7: 0.4739655 | AK7: 0.59955647 | AL7: 0.59955647 | AM7: 0.59955647 | AN7: 0.64999756 | AO7: 0.48154359 | AP7: 0.48154359 | AQ7: 0.48154359 | AR7: 0.47345894 | AS7: 0.47345894 | AT7: 0.47345894 | AU7: 0.4982256 | AV7: 0.47345894 | AW7: 0.53745677 | AX7: 0.4982256 | AY7: 0.4982256 | AZ7: 0.4982256 | BA7: 0.38282644 | BB7: 0.38282644 | BC7: 0.27416796 | BD7: 0.62064856 | BE7: 0.37779779 | BF7: 0.37779779 | BG7: 0.19346372 | BH7: 0.19346372 | BI7: 0.19346372 | BJ7: 0.19346372 | BK7: 0.19928649 | BL7: 0.19928649 | BM7: 0.19928649 | BN7: 0.29785743 | BO7: 0.29785743 | BP7: 0.29785743 | BQ7: 0.29785743 | BR7: 0.29785743 | BS7: 0.38173186 | BT7: 0.5638309 | BU7: 0.5638309 | BV7: 0.5638309 | BW7: 0.5638309 | BX7: 0.5638309 | BY7: 0.51658773 | BZ7: 0.51658773 | CA7: 0.51658773 | CB7: 0.51658773 | CC7: 0.59792235 | CD7: 0.59792235 | CE7: 0.59792235 | CF7: 0.59792235 | CG7: 0.50245285 | CH7: 0.4104047 | CI7: 0.4104047 | CJ7: 0.4104047 | CK7: 0.60717415 | CL7: 0.60717415 | CM7: 0.60717415 | CN7: 0.18842179 | CO7: 0.18842179 | CP7: 0.54906236 | CQ7: 0.54906236 | CR7: 0.54906236 | CS7: 0.54906236 | CT7: 0.54906236 | CU7: 1 | CV7: 0.77181106 | CW7: 0.71198926 | CX7: 0.71198926 | CY7: 0.87667501 | CZ7: 0.87667501 | DA7: 0.87667501 | DB7: 0.87667501 | DC7: 0.87667501
C8: flnd | D8: 0.5044744 | E8: 0.47905324 | F8: 0.45384121 | G8: 0.43486634 | H8: 0.5044744 | I8: 0.42164176 | J8: 0.49381057 | K8: 0.49443453 | L8: 0.45213772 | M8: 0.34841381 | N8: 0.34841381 | O8: 0.31138237 | P8: 0.4258277 | Q8: 0.4258277 | R8: 0.4258277 | S8: 0.33387151 | T8: 0.4433428 | U8: 0.4433428 | V8: 0.4433428 | W8: 0.18801515 | X8: 0.21246482 | Y8: 0.34917301 | Z8: 0.34917301 | AA8: 0.32156415 | AB8: 0.34917301 | AC8: 0 | AD8: 0 | AE8: 0 | AF8: 0 | AG8: 0 | AH8: 0 | AI8: 0 | AJ8: 0 | AK8: 0 | AL8: 0 | AM8: 0 | AN8: 0 | AO8: 0 | AP8: 0 | AQ8: 0 | AR8: 0 | AS8: 0 | AT8: 0 | AU8: 0 | AV8: 0 | AW8: 0 | AX8: 0 | AY8: 0 | AZ8: 0 | BA8: 0 | BB8: 0 | BC8: 0 | BD8: 0 | BE8: 0 | BF8: 0 | BG8: 0 | BH8: 0 | BI8: 0 | BJ8: 0 | BK8: 0 | BL8: 0 | BM8: 0 | BN8: 0 | BO8: 0 | BP8: 0 | BQ8: 0 | BR8: 0 | BS8: 0 | BT8: 0 | BU8: 0 | BV8: 0 | BW8: 0 | BX8: 0 | BY8: 0 | BZ8: 0 | CA8: 0 | CB8: 0 | CC8: 0 | CD8: 0 | CE8: 0 | CF8: 0 | CG8: 0 | CH8: 0 | CI8: 0 | CJ8: 0 | CK8: 0 | CL8: 0 | CM8: 0 | CN8: 0 | CO8: 0 | CP8: 0 | CQ8: 0 | CR8: 0 | CS8: 0 | CT8: 0 | CU8: 0 | CV8: 0 | CW8: 0 | CX8: 0 | CY8: 0 | CZ8: 0 | DA8: 0 | DB8: 0 | DC8: 0
C9: fcap | D9: 0.073323421 | E9: 0.080080187 | F9: 0.092678327 | G9: 0.11184556 | H9: 0.073323421 | I9: 0.10776862 | J9: 0.072506988 | K9: 0.080656585 | L9: 0.085580135 | M9: 0.13952875 | N9: 0.13952875 | O9: 0.12027955 | P9: 0.10882819 | Q9: 0.10882819 | R9: 0.10882819 | S9: 0.10384653 | T9: 0.094026777 | U9: 0.094026777 | V9: 0.094026777 | W9: 0.13294077 | X9: 0.12395452 | Y9: 0.11360088 | Z9: 0.11360088 | AA9: 0.15407565 | AB9: 0.11360088 | AC9: 0.54661002 | AD9: 0.54591669 | AE9: 0.54922569 | AF9: 0.54451012 | AG9: 0.54406439 | AH9: 0.54441938 | AI9: 0.5260345 | AJ9: 0.5260345 | AK9: 0.40044353 | AL9: 0.40044353 | AM9: 0.40044353 | AN9: 0.35000244 | AO9: 0.51845641 | AP9: 0.51845641 | AQ9: 0.51845641 | AR9: 0.52654106 | AS9: 0.52654106 | AT9: 0.52654106 | AU9: 0.5017744 | AV9: 0.52654106 | AW9: 0.46254323 | AX9: 0.5017744 | AY9: 0.5017744 | AZ9: 0.5017744 | BA9: 0.61717356 | BB9: 0.61717356 | BC9: 0.72583204 | BD9: 0.37935144 | BE9: 0.62220221 | BF9: 0.62220221 | BG9: 0.80653628 | BH9: 0.80653628 | BI9: 0.80653628 | BJ9: 0.80653628 | BK9: 0.80071351 | BL9: 0.80071351 | BM9: 0.80071351 | BN9: 0.70214257 | BO9: 0.70214257 | BP9: 0.70214257 | BQ9: 0.70214257 | BR9: 0.70214257 | BS9: 0.61826814 | BT9: 0.4361691 | BU9: 0.4361691 | BV9: 0.4361691 | BW9: 0.4361691 | BX9: 0.4361691 | BY9: 0.48341227 | BZ9: 0.48341227 | CA9: 0.48341227 | CB9: 0.48341227 | CC9: 0.40207765 | CD9: 0.40207765 | CE9: 0.40207765 | CF9: 0.40207765 | CG9: 0.49754715 | CH9: 0.5895953 | CI9: 0.5895953 | CJ9: 0.5895953 | CK9: 0.39282585 | CL9: 0.39282585 | CM9: 0.39282585 | CN9: 0.81157821 | CO9: 0.81157821 | CP9: 0.45093764 | CQ9: 0.45093764 | CR9: 0.45093764 | CS9: 0.45093764 | CT9: 0.45093764 | CU9: 0 | CV9: 0.22818894 | CW9: 0.28801074 | CX9: 0.28801074 | CY9: 0.12332499 | CZ9: 0.12332499 | DA9: 0.12332499 | DB9: 0.12332499 | DC9: 0.12332499
B10: Used | C10: flab | D10: =D7 -> 0.42220218 | E10: =E7 -> 0.44086658 | F10: =F7 -> 0.45348046 | G10: =G7 -> 0.4532881 | H10: =H7 -> 0.42220218 | I10: =I7 -> 0.47058963 | J10: =J7 -> 0.43368245 | K10: =K7 -> 0.42490888 | ... DC10: =DC7 -> 0.87667501
C11: flnd | D11: =D8 -> 0.5044744 | E11: =E8 -> 0.47905324 | F11: =F8 -> 0.45384121 | G11: =G8 -> 0.43486634 | H11: =H8 -> 0.5044744 | I11: =I8 -> 0.42164176 | J11: =J8 -> 0.49381057 | K11: =K8 -> 0.49443453 | ... DC11: =DC8 -> 0
C12: fcap | D12: =1-SUM(D10:D11) -> 0.073323421 | E12: =1-SUM(E10:E11) -> 0.080080187 | F12: =1-SUM(F10:F11) -> 0.092678327 | G12: =1-SUM(G10:G11) -> 0.11184556 | H12: =1-SUM(H10:H11) -> 0.073323421 | I12: =1-SUM(I10:I11) -> 0.10776862 | J12: =1-SUM(J10:J11) -> 0.072506988 | K12: =1-SUM(K10:K11) -> 0.080656585 | ... DC12: =1-SUM(DC10:DC11) -> 0.12332499
D14: =SUM(D17:D123) -> 1 | E14: =SUM(E17:E123) -> 1 | F14: =SUM(F17:F123) -> 1 | G14: =SUM(G17:G123) -> 1 | H14: =SUM(H17:H123) -> 1 | I14: =SUM(I17:I123) -> 1 | J14: =SUM(J17:J123) -> 1 | K14: =SUM(K17:K123) -> 1 | ... DC14: =SUM(DC17:DC123) -> 1
D15: Sorghum (A111) | E15: Maize (A112) | F15: Wheat (A113) | G15: Paddy & husked rice (A116) | H15: Other cereals (A119) | I15: Irish potatoes (A121) | J15: Sweet potatoes (A122) | K15: Cassava (A123) | L15: Other roots & tubers (A129) | M15: Dried beans (A131) | N15: Peas & other legumes (A132) | O15: Other vegetables (A139) | P15: Bananas for beer (A141) | Q15: Bananas for cooking (A142) | R15: Bananas (sweet) (A143) | S15: Other fruit & nuts (A149) | T15: Ground nuts (A151) | U15: Soya (A152) | V15: Other oil seeds (A159) | W15: Coffee, not roasted, not decaffeinated (A210) | X15: Tea (unprocessed green leaf) (A220) | Y15: Tobacco, raw (A291) | Z15: Sugar cane (A292) | AA15: Pyrethrum (A293) | AB15: Agricultural products n.e.c. (A299) | AC15: Bovine cattle, live (A311) | AD15: Sheep, goats, pigs,live (A312) | AE15: Poultry, live (A313) | AF15: Other live animals (A319) | AG15: Raw milk (A321) | AH15: Eggs (A322) | AI15: Natural honey (A323) | AJ15: Other livestock & hunting products (A329) | AK15: Fuel wood (A401) | AL15: Charcoal (A402) | AM15: Other forestry products (A409) | AN15: Fishery products (A500) | AO15: Natural gas (B01) | AP15: Metal ores (B03) | AQ15: Quarry & other mining products (B09) | AR15: Meat and meat products (C11) | AS15: Prepared and preserved fish (C12) | AT15: Prepared and preserved vegetables (C13) | AU15: Animal and vegetable oils and fats (C14) | AV15: Dairy products (C15) | AW15: Grain mill products (C16) | AX15: Bakery products (C17) | AY15: Animal feed & other by-products (C18) | AZ15: Other manufactured food products (C19) | BA15: Alcoholic drinks (C21) | BB15: Soft drinks (C22) | BC15: Tobacco products (C23) | BD15: Textiles, clothing & leather products (C30) | BE15: Wood, paper and related products (C41) | BF15: Printing and reproduction of recorded media (C42) | BG15: Coke and refined petroleum products (C51) | BH15: Chemicals and chemical products (C52) | BI15: Pharmaceutical products (C53) | BJ15: Rubber and plastics products (C54) | BK15: Non-metallic mineral products n.e.c. (C61) | BL15: Manufacture of cement, lime and plaster (C62) | BM15: Manufacture of clay building materials (C63) | BN15: Metals & metal products, except machinery and equipment (C72) | BO15: Machinery and equipment (except transport) (C74) | BP15: Transport equipment (C76) | BQ15: Furniture (C81) | BR15: Other manufacturing (C82) | BS15: Repair and installation of machinery and equipment (C83) | BT15: Electricity, gas, steam and air conditioning supply (D00) | BU15: Water collection, treatment and supply: sewrage (E01) | BV15: Waste collection and management (E02) | BW15: Construction (modern) (F01) | BX15: Construction (traditional) (F02) | BY15: Maintenance and repair of motor vehicles (G10) | BZ15: Wholesale and retail trade of motor vehicles and motorcycles (G21) | CA15: Wholesale trade, except of motor vehicles and motorcycles (G22) | CB15: Retail trade, except of motor vehicles and motorcycles (G23) | CC15: Land transport (H10) | CD15: Air transport (H20) | CE15: Services related to transport (H31) | CF15: Postal and courier activities (H32) | CG15: Hotels & restaurants (I00) | CH15: Publishing, video making, programming & broadcasting activities (J10) | CI15: Telecommunication (J20) | CJ15: Information technology services (J30) | CK15: Monetary institutions (K01) | CL15: Insurance, reinsurance and pension funding, except compulsory social security (K02) | CM15: Other financial services (K03) | CN15: Rental value of dwellings (L01) | CO15: Other real estate activities (L09) | CP15: Legal, accounting management & head office activities (M01) | CQ15: Architectural and engineering activities (M02) | CR15: Other professional, scientific and technical activities (M03) | CS15: Travel agents and tour operators (N01) | CT15: Other administrative and support service activities (N09) | CU15: Public administration and defence; compulsory social security (O00) | CV15: Education (P00) | CW15: Human health activities (Q01) | CX15: Social work activities (Q02) | CY15: Libraries, archives, museums and other cultural activities (R01) | CZ15: Other arts, entertainment and recreation (R09) | DA15: Other service activities (S00) | DB15: Domestic services (T00) | DC15: Travel debits & credits (V00)
D16: asorg | E16: amaiz | F16: awhea | G16: arice | H16: aocer | I16: aipot | J16: aspot | K16: acass | L16: aroot | M16: abean | N16: apeas | O16: avege | P16: abanb | Q16: abanc | R16: abans | S16: afrui | T16: agnut | U16: asoya | V16: aoils | W16: acoff | X16: ateal | Y16: atoba | Z16: asugr | AA16: apyre | AB16: aocrp | AC16: acatt | AD16: asmlr | AE16: apoul | AF16: aoliv | AG16: amilk | AH16: aeggs | AI16: ahony | AJ16: ahunt | AK16: afuel | AL16: achar | AM16: afore | AN16: afish | AO16: angas | AP16: amore | AQ16: aomin | AR16: ameat | AS16: afsea | AT16: afveg | AU16: afoil | AV16: adair | AW16: agmll | AX16: abake | AY16: afeed | AZ16: afood | BA16: aalco | BB16: abeve | BC16: aptob | BD16: atext | BE16: awood | BF16: aprnt | BG16: apetr | BH16: achem | BI16: aphar | BJ16: aprub | BK16: anmet | BL16: aceme | BM16: aclay | BN16: ametl | BO16: amach | BP16: avehi | BQ16: afurn | BR16: aoman | BS16: arepr | BT16: aelec | BU16: awatr | BV16: awast | BW16: acons | BX16: acont | BY16: avehr | BZ16: aveht | CA16: atrdw | CB16: atrdr | CC16: atrnl | CD16: atrna | CE16: atrns | CF16: apost | CG16: ahotl | CH16: apubl | CI16: acomm | CJ16: ainfo | CK16: abank | CL16: ainsu | CM16: aofsv | CN16: arent | CO16: areal | CP16: alegl | CQ16: aenga | CR16: aprod | CS16: atrvl | CT16: aobsv | CU16: apadm | CV16: aeduc | CW16: aheal | CX16: asocw | CY16: acult | CZ16: aarts | DA16: aosrv | DB16: adsrv | DC16: atrdc
B17: Sorghum (A111) | C17: csorg | D17: =IF(USE!E$538<>0,(1-D$5)*USE!E542/USE!E$538,(1-D$5)*USE!E318) -> 0.0075260539 | E17: =IF(USE!F$538<>0,(1-E$5)*USE!F542/USE!F$538,(1-E$5)*USE!F318) -> 0 | F17: =IF(USE!G$538<>0,(1-F$5)*USE!G542/USE!G$538,(1-F$5)*USE!G318) -> 0 | G17: =IF(USE!H$538<>0,(1-G$5)*USE!H542/USE!H$538,(1-G$5)*USE!H318) -> 0 | H17: =IF(USE!I$538<>0,(1-H$5)*USE!I542/USE!I$538,(1-H$5)*USE!I318) -> 0 | I17: =IF(USE!J$538<>0,(1-I$5)*USE!J542/USE!J$538,(1-I$5)*USE!J318) -> 0 | J17: =IF(USE!K$538<>0,(1-J$5)*USE!K542/USE!K$538,(1-J$5)*USE!K318) -> 0 | K17: =IF(USE!L$538<>0,(1-K$5)*USE!L542/USE!L$538,(1-K$5)*USE!L318) -> 0 | ... DC17: =IF(USE!DD$538<>0,(1-DC$5)*USE!DD542/USE!DD$538,(1-DC$5)*USE!DD318) -> 0
B18: Maize (A112) | C18: cmaiz | D18: =IF(USE!E$538<>0,(1-D$5)*USE!E543/USE!E$538,(1-D$5)*USE!E319) -> 0 | E18: =IF(USE!F$538<>0,(1-E$5)*USE!F543/USE!F$538,(1-E$5)*USE!F319) -> 0.0075260539 | F18: =IF(USE!G$538<>0,(1-F$5)*USE!G543/USE!G$538,(1-F$5)*USE!G319) -> 0 | G18: =IF(USE!H$538<>0,(1-G$5)*USE!H543/USE!H$538,(1-G$5)*USE!H319) -> 0 | H18: =IF(USE!I$538<>0,(1-H$5)*USE!I543/USE!I$538,(1-H$5)*USE!I319) -> 0 | I18: =IF(USE!J$538<>0,(1-I$5)*USE!J543/USE!J$538,(1-I$5)*USE!J319) -> 0 | J18: =IF(USE!K$538<>0,(1-J$5)*USE!K543/USE!K$538,(1-J$5)*USE!K319) -> 0 | K18: =IF(USE!L$538<>0,(1-K$5)*USE!L543/USE!L$538,(1-K$5)*USE!L319) -> 0 | ... DC18: =IF(USE!DD$538<>0,(1-DC$5)*USE!DD543/USE!DD$538,(1-DC$5)*USE!DD319) -> 0
B19: Wheat (A113) | C19: cwhea | D19: =IF(USE!E$538<>0,(1-D$5)*USE!E544/USE!E$538,(1-D$5)*USE!E320) -> 0 | E19: =IF(USE!F$538<>0,(1-E$5)*USE!F544/USE!F$538,(1-E$5)*USE!F320) -> 0 | F19: =IF(USE!G$538<>0,(1-F$5)*USE!G544/USE!G$538,(1-F$5)*USE!G320) -> 0.0075260539 | G19: =IF(USE!H$538<>0,(1-G$5)*USE!H544/USE!H$538,(1-G$5)*USE!H320) -> 0 | H19: =IF(USE!I$538<>0,(1-H$5)*USE!I544/USE!I$538,(1-H$5)*USE!I320) -> 0 | I19: =IF(USE!J$538<>0,(1-I$5)*USE!J544/USE!J$538,(1-I$5)*USE!J320) -> 0 | J19: =IF(USE!K$538<>0,(1-J$5)*USE!K544/USE!K$538,(1-J$5)*USE!K320) -> 0 | K19: =IF(USE!L$538<>0,(1-K$5)*USE!L544/USE!L$538,(1-K$5)*USE!L320) -> 0 | ... DC19: =IF(USE!DD$538<>0,(1-DC$5)*USE!DD544/USE!DD$538,(1-DC$5)*USE!DD320) -> 0
B20: Paddy & husked rice (A116) | C20: crice | D20: =IF(USE!E$538<>0,(1-D$5)*USE!E545/USE!E$538,(1-D$5)*USE!E321) -> 0 | E20: =IF(USE!F$538<>0,(1-E$5)*USE!F545/USE!F$538,(1-E$5)*USE!F321) -> 0 | F20: =IF(USE!G$538<>0,(1-F$5)*USE!G545/USE!G$538,(1-F$5)*USE!G321) -> 0 | G20: =IF(USE!H$538<>0,(1-G$5)*USE!H545/USE!H$538,(1-G$5)*USE!H321) -> 0.0075260539 | H20: =IF(USE!I$538<>0,(1-H$5)*USE!I545/USE!I$538,(1-H$5)*USE!I321) -> 0 | I20: =IF(USE!J$538<>0,(1-I$5)*USE!J545/USE!J$538,(1-I$5)*USE!J321) -> 0 | J20: =IF(USE!K$538<>0,(1-J$5)*USE!K545/USE!K$538,(1-J$5)*USE!K321) -> 0 | K20: =IF(USE!L$538<>0,(1-K$5)*USE!L545/USE!L$538,(1-K$5)*USE!L321) -> 0 | ... DC20: =IF(USE!DD$538<>0,(1-DC$5)*USE!DD545/USE!DD$538,(1-DC$5)*USE!DD321) -> 0
B21: Other cereals (A119) | C21: cocer | D21: =IF(USE!E$538<>0,(1-D$5)*USE!E546/USE!E$538,(1-D$5)*USE!E322) -> 0 | E21: =IF(USE!F$538<>0,(1-E$5)*USE!F546/USE!F$538,(1-E$5)*USE!F322) -> 0 | F21: =IF(USE!G$538<>0,(1-F$5)*USE!G546/USE!G$538,(1-F$5)*USE!G322) -> 0 | G21: =IF(USE!H$538<>0,(1-G$5)*USE!H546/USE!H$538,(1-G$5)*USE!H322) -> 0 | H21: =IF(USE!I$538<>0,(1-H$5)*USE!I546/USE!I$538,(1-H$5)*USE!I322) -> 0.0075260539 | I21: =IF(USE!J$538<>0,(1-I$5)*USE!J546/USE!J$538,(1-I$5)*USE!J322) -> 0 | J21: =IF(USE!K$538<>0,(1-J$5)*USE!K546/USE!K$538,(1-J$5)*USE!K322) -> 0 | K21: =IF(USE!L$538<>0,(1-K$5)*USE!L546/USE!L$538,(1-K$5)*USE!L322) -> 0 | ... DC21: =IF(USE!DD$538<>0,(1-DC$5)*USE!DD546/USE!DD$538,(1-DC$5)*USE!DD322) -> 0
B22: Irish potatoes (A121) | C22: cipot | D22: =IF(USE!E$538<>0,(1-D$5)*USE!E547/USE!E$538,(1-D$5)*USE!E323) -> 0 | E22: =IF(USE!F$538<>0,(1-E$5)*USE!F547/USE!F$538,(1-E$5)*USE!F323) -> 0 | F22: =IF(USE!G$538<>0,(1-F$5)*USE!G547/USE!G$538,(1-F$5)*USE!G323) -> 0 | G22: =IF(USE!H$538<>0,(1-G$5)*USE!H547/USE!H$538,(1-G$5)*USE!H323) -> 0 | H22: =IF(USE!I$538<>0,(1-H$5)*USE!I547/USE!I$538,(1-H$5)*USE!I323) -> 0 | I22: =IF(USE!J$538<>0,(1-I$5)*USE!J547/USE!J$538,(1-I$5)*USE!J323) -> 0.011437957 | J22: =IF(USE!K$538<>0,(1-J$5)*USE!K547/USE!K$538,(1-J$5)*USE!K323) -> 0 | K22: =IF(USE!L$538<>0,(1-K$5)*USE!L547/USE!L$538,(1-K$5)*USE!L323) -> 0 | ... DC22: =IF(USE!DD$538<>0,(1-DC$5)*USE!DD547/USE!DD$538,(1-DC$5)*USE!DD323) -> 0
B23: Sweet potatoes (A122) | C23: cspot | D23: =IF(USE!E$538<>0,(1-D$5)*USE!E548/USE!E$538,(1-D$5)*USE!E324) -> 0 | E23: =IF(USE!F$538<>0,(1-E$5)*USE!F548/USE!F$538,(1-E$5)*USE!F324) -> 0 | F23: =IF(USE!G$538<>0,(1-F$5)*USE!G548/USE!G$538,(1-F$5)*USE!G324) -> 0 | G23: =IF(USE!H$538<>0,(1-G$5)*USE!H548/USE!H$538,(1-G$5)*USE!H324) -> 0 | H23: =IF(USE!I$538<>0,(1-H$5)*USE!I548/USE!I$538,(1-H$5)*USE!I324) -> 0 | I23: =IF(USE!J$538<>0,(1-I$5)*USE!J548/USE!J$538,(1-I$5)*USE!J324) -> 0 | J23: =IF(USE!K$538<>0,(1-J$5)*USE!K548/USE!K$538,(1-J$5)*USE!K324) -> 0.011437957 | K23: =IF(USE!L$538<>0,(1-K$5)*USE!L548/USE!L$538,(1-K$5)*USE!L324) -> 0 | ... DC23: =IF(USE!DD$538<>0,(1-DC$5)*USE!DD548/USE!DD$538,(1-DC$5)*USE!DD324) -> 0
B24: Cassava (A123) | C24: ccass | D24: =IF(USE!E$538<>0,(1-D$5)*USE!E549/USE!E$538,(1-D$5)*USE!E325) -> 0 | E24: =IF(USE!F$538<>0,(1-E$5)*USE!F549/USE!F$538,(1-E$5)*USE!F325) -> 0 | F24: =IF(USE!G$538<>0,(1-F$5)*USE!G549/USE!G$538,(1-F$5)*USE!G325) -> 0 | G24: =IF(USE!H$538<>0,(1-G$5)*USE!H549/USE!H$538,(1-G$5)*USE!H325) -> 0 | H24: =IF(USE!I$538<>0,(1-H$5)*USE!I549/USE!I$538,(1-H$5)*USE!I325) -> 0 | I24: =IF(USE!J$538<>0,(1-I$5)*USE!J549/USE!J$538,(1-I$5)*USE!J325) -> 0 | J24: =IF(USE!K$538<>0,(1-J$5)*USE!K549/USE!K$538,(1-J$5)*USE!K325) -> 0 | K24: =IF(USE!L$538<>0,(1-K$5)*USE!L549/USE!L$538,(1-K$5)*USE!L325) -> 0.011437957 | ... DC24: =IF(USE!DD$538<>0,(1-DC$5)*USE!DD549/USE!DD$538,(1-DC$5)*USE!DD325) -> 0
B25: Other roots & tubers (A129) | C25: croot | D25: =IF(USE!E$538<>0,(1-D$5)*USE!E550/USE!E$538,(1-D$5)*USE!E326) -> 0 | E25: =IF(USE!F$538<>0,(1-E$5)*USE!F550/USE!F$538,(1-E$5)*USE!F326) -> 0 | F25: =IF(USE!G$538<>0,(1-F$5)*USE!G550/USE!G$538,(1-F$5)*USE!G326) -> 0 | G25: =IF(USE!H$538<>0,(1-G$5)*USE!H550/USE!H$538,(1-G$5)*USE!H326) -> 0 | H25: =IF(USE!I$538<>0,(1-H$5)*USE!I550/USE!I$538,(1-H$5)*USE!I326) -> 0 | I25: =IF(USE!J$538<>0,(1-I$5)*USE!J550/USE!J$538,(1-I$5)*USE!J326) -> 0 | J25: =IF(USE!K$538<>0,(1-J$5)*USE!K550/USE!K$538,(1-J$5)*USE!K326) -> 0 | K25: =IF(USE!L$538<>0,(1-K$5)*USE!L550/USE!L$538,(1-K$5)*USE!L326) -> 0 | ... DC25: =IF(USE!DD$538<>0,(1-DC$5)*USE!DD550/USE!DD$538,(1-DC$5)*USE!DD326) -> 0
B26: Dried beans (A131) | C26: cbean | D26: =IF(USE!E$538<>0,(1-D$5)*USE!E551/USE!E$538,(1-D$5)*USE!E327) -> 0 | E26: =IF(USE!F$538<>0,(1-E$5)*USE!F551/USE!F$538,(1-E$5)*USE!F327) -> 0 | F26: =IF(USE!G$538<>0,(1-F$5)*USE!G551/USE!G$538,(1-F$5)*USE!G327) -> 0 | G26: =IF(USE!H$538<>0,(1-G$5)*USE!H551/USE!H$538,(1-G$5)*USE!H327) -> 0 | H26: =IF(USE!I$538<>0,(1-H$5)*USE!I551/USE!I$538,(1-H$5)*USE!I327) -> 0 | I26: =IF(USE!J$538<>0,(1-I$5)*USE!J551/USE!J$538,(1-I$5)*USE!J327) -> 0 | J26: =IF(USE!K$538<>0,(1-J$5)*USE!K551/USE!K$538,(1-J$5)*USE!K327) -> 0 | K26: =IF(USE!L$538<>0,(1-K$5)*USE!L551/USE!L$538,(1-K$5)*USE!L327) -> 0 | ... DC26: =IF(USE!DD$538<>0,(1-DC$5)*USE!DD551/USE!DD$538,(1-DC$5)*USE!DD327) -> 0
B27: Peas & other legumes (A132) | C27: cpeas | D27: =IF(USE!E$538<>0,(1-D$5)*USE!E552/USE!E$538,(1-D$5)*USE!E328) -> 0 | E27: =IF(USE!F$538<>0,(1-E$5)*USE!F552/USE!F$538,(1-E$5)*USE!F328) -> 0 | F27: =IF(USE!G$538<>0,(1-F$5)*USE!G552/USE!G$538,(1-F$5)*USE!G328) -> 0 | G27: =IF(USE!H$538<>0,(1-G$5)*USE!H552/USE!H$538,(1-G$5)*USE!H328) -> 0 | H27: =IF(USE!I$538<>0,(1-H$5)*USE!I552/USE!I$538,(1-H$5)*USE!I328) -> 0 | I27: =IF(USE!J$538<>0,(1-I$5)*USE!J552/USE!J$538,(1-I$5)*USE!J328) -> 0 | J27: =IF(USE!K$538<>0,(1-J$5)*USE!K552/USE!K$538,(1-J$5)*USE!K328) -> 0 | K27: =IF(USE!L$538<>0,(1-K$5)*USE!L552/USE!L$538,(1-K$5)*USE!L328) -> 0 | ... DC27: =IF(USE!DD$538<>0,(1-DC$5)*USE!DD552/USE!DD$538,(1-DC$5)*USE!DD328) -> 0
B28: Other vegetables (A139) | C28: cvege | D28: =IF(USE!E$538<>0,(1-D$5)*USE!E553/USE!E$538,(1-D$5)*USE!E329) -> 0 | E28: =IF(USE!F$538<>0,(1-E$5)*USE!F553/USE!F$538,(1-E$5)*USE!F329) -> 0 | F28: =IF(USE!G$538<>0,(1-F$5)*USE!G553/USE!G$538,(1-F$5)*USE!G329) -> 0 | G28: =IF(USE!H$538<>0,(1-G$5)*USE!H553/USE!H$538,(1-G$5)*USE!H329) -> 0 | H28: =IF(USE!I$538<>0,(1-H$5)*USE!I553/USE!I$538,(1-H$5)*USE!I329) -> 0 | I28: =IF(USE!J$538<>0,(1-I$5)*USE!J553/USE!J$538,(1-I$5)*USE!J329) -> 0 | J28: =IF(USE!K$538<>0,(1-J$5)*USE!K553/USE!K$538,(1-J$5)*USE!K329) -> 0 | K28: =IF(USE!L$538<>0,(1-K$5)*USE!L553/USE!L$538,(1-K$5)*USE!L329) -> 0 | ... DC28: =IF(USE!DD$538<>0,(1-DC$5)*USE!DD553/USE!DD$538,(1-DC$5)*USE!DD329) -> 0
... B120: Travel debits & credits (V00) | C120: ctrdc | D120: =IF(USE!E$538<>0,(1-D$5)*USE!E645/USE!E$538,(1-D$5)*USE!E421) -> 0 | E120: =IF(USE!F$538<>0,(1-E$5)*USE!F645/USE!F$538,(1-E$5)*USE!F421) -> 0 | F120: =IF(USE!G$538<>0,(1-F$5)*USE!G645/USE!G$538,(1-F$5)*USE!G421) -> 0 | G120: =IF(USE!H$538<>0,(1-G$5)*USE!H645/USE!H$538,(1-G$5)*USE!H421) -> 0 | H120: =IF(USE!I$538<>0,(1-H$5)*USE!I645/USE!I$538,(1-H$5)*USE!I421) -> 0 | I120: =IF(USE!J$538<>0,(1-I$5)*USE!J645/USE!J$538,(1-I$5)*USE!J421) -> 0 | J120: =IF(USE!K$538<>0,(1-J$5)*USE!K645/USE!K$538,(1-J$5)*USE!K421) -> 0 | K120: =IF(USE!L$538<>0,(1-K$5)*USE!L645/USE!L$538,(1-K$5)*USE!L421) -> 0 | ... DC120: =IF(USE!DD$538<>0,(1-DC$5)*USE!DD645/USE!DD$538,(1-DC$5)*USE!DD421) -> 0
B121: Labor | C121: flab | D121: =D$5*D10 -> 0.39395623 | E121: =E$5*E10 -> 0.41137194 | F121: =F$5*F10 -> 0.42314194 | G121: =G$5*G10 -> 0.42296245 | H121: =H$5*H10 -> 0.39395623 | I121: =I$5*I10 -> 0.44013773 | J121: =J$5*J10 -> 0.40561881 | K121: =K$5*K10 -> 0.39741299 | ... DC121: =DC$5*DC10 -> 0.87667501
B122: Land transport (H10) | C122: flnd | D122: =D$5*D11 -> 0.47072431 | E122: =E$5*E11 -> 0.44700386 | F122: =F$5*F11 -> 0.42347856 | G122: =G$5*G11 -> 0.40577314 | H122: =H$5*H11 -> 0.47072431 | I122: =I$5*I11 -> 0.39435728 | J122: =J$5*J11 -> 0.46185604 | K122: =K$5*K11 -> 0.46243963 | ... DC122: =DC$5*DC11 -> 0
B123: Capital | C123: fcap | D123: =D$5*D12 -> 0.068417975 | E123: =E$5*E12 -> 0.074722703 | F123: =F$5*F12 -> 0.086478008 | G123: =G$5*G12 -> 0.10436292 | H123: =H$5*H12 -> 0.068417975 | I123: =I$5*I12 -> 0.1007949 | J123: =J$5*J12 -> 0.067815054 | K123: =K$5*K12 -> 0.07543729 | ... DC123: =DC$5*DC12 -> 0.12332499
A126: Supply table coefficients
D127: Sorghum (A111) | E127: Maize (A112) | F127: Wheat (A113) | G127: Paddy & husked rice (A116) | H127: Other cereals (A119) | I127: Irish potatoes (A121) | J127: Sweet potatoes (A122) | K127: Cassava (A123) | L127: Other roots & tubers (A129) | M127: Dried beans (A131) | N127: Peas & other legumes (A132) | O127: Other vegetables (A139) | P127: Bananas for beer (A141) | Q127: Bananas for cooking (A142) | R127: Bananas (sweet) (A143) | S127: Other fruit & nuts (A149) | T127: Ground nuts (A151) | U127: Soya (A152) | V127: Other oil seeds (A159) | W127: Coffee, not roasted, not decaffeinated (A210) | X127: Tea (unprocessed green leaf) (A220) | Y127: Tobacco, raw (A291) | Z127: Sugar cane (A292) | AA127: Pyrethrum (A293) | AB127: Agricultural products n.e.c. (A299) | AC127: Bovine cattle, live (A311) | AD127: Sheep, goats, pigs,live (A312) | AE127: Poultry, live (A313) | AF127: Other live animals (A319) | AG127: Raw milk (A321) | AH127: Eggs (A322) | AI127: Natural honey (A323) | AJ127: Other livestock & hunting products (A329) | AK127: Fuel wood (A401) | AL127: Charcoal (A402) | AM127: Other forestry products (A409) | AN127: Fishery products (A500) | AO127: Natural gas (B01) | AP127: Metal ores (B03) | AQ127: Quarry & other mining products (B09) | AR127: Meat and meat products (C11) | AS127: Prepared and preserved fish (C12) | AT127: Prepared and preserved vegetables (C13) | AU127: Animal and vegetable oils and fats (C14) | AV127: Dairy products (C15) | AW127: Grain mill products (C16) | AX127: Bakery products (C17) | AY127: Animal feed & other by-products (C18) | AZ127: Other manufactured food products (C19) | BA127: Alcoholic drinks (C21) | BB127: Soft drinks (C22) | BC127: Tobacco products (C23) | BD127: Textiles, clothing & leather products (C30) | BE127: Wood, paper and related products (C41) | BF127: Printing and reproduction of recorded media (C42) | BG127: Coke and refined petroleum products (C51) | BH127: Chemicals and chemical products (C52) | BI127: Pharmaceutical products (C53) | BJ127: Rubber and plastics products (C54) | BK127: Non-metallic mineral products n.e.c. (C61) | BL127: Manufacture of cement, lime and plaster (C62) | BM127: Manufacture of clay building materials (C63) | BN127: Metals & metal products, except machinery and equipment (C72) | BO127: Machinery and equipment (except transport) (C74) | BP127: Transport equipment (C76) | BQ127: Furniture (C81) | BR127: Other manufacturing (C82) | BS127: Repair and installation of machinery and equipment (C83) | BT127: Electricity, gas, steam and air conditioning supply (D00) | BU127: Water collection, treatment and supply: sewrage (E01) | BV127: Waste collection and management (E02) | BW127: Construction (modern) (F01) | BX127: Construction (traditional) (F02) | BY127: Maintenance and repair of motor vehicles (G10) | BZ127: Wholesale and retail trade of motor vehicles and motorcycles (G21) | CA127: Wholesale trade, except of motor vehicles and motorcycles (G22) | CB127: Retail trade, except of motor vehicles and motorcycles (G23) | CC127: Land transport (H10) | CD127: Air transport (H20) | CE127: Services related to transport (H31) | CF127: Postal and courier activities (H32) | CG127: Hotels & restaurants (I00) | CH127: Publishing, video making, programming & broadcasting activities (J10) | CI127: Telecommunication (J20) | CJ127: Information technology services (J30) | CK127: Monetary institutions (K01) | CL127: Insurance, reinsurance and pension funding, except compulsory social security (K02) | CM127: Other financial services (K03) | CN127: Rental value of dwellings (L01) | CO127: Other real estate activities (L09) | CP127: Legal, accounting management & head office activities (M01) | CQ127: Architectural and engineering activities (M02) | CR127: Other professional, scientific and technical activities (M03) | CS127: Travel agents and tour operators (N01) | CT127: Other administrative and support service activities (N09) | CU127: Public administration and defence; compulsory social security (O00) | CV127: Education (P00) | CW127: Human health activities (Q01) | CX127: Social work activities (Q02) | CY127: Libraries, archives, museums and other cultural activities (R01) | CZ127: Other arts, entertainment and recreation (R09) | DA127: Other service activities (S00) | DB127: Domestic services (T00) | DC127: Travel debits & credits (V00)
D128: csorg | E128: cmaiz | F128: cwhea | G128: crice | H128: cocer | I128: cipot | J128: cspot | K128: ccass | L128: croot | M128: cbean | N128: cpeas | O128: cvege | P128: cbanb | Q128: cbanc | R128: cbans | S128: cfrui | T128: cgnut | U128: csoya | V128: coils | W128: ccoff | X128: cteal | Y128: ctoba | Z128: csugr | AA128: cpyre | AB128: cocrp | AC128: ccatt | AD128: csmlr | AE128: cpoul | AF128: coliv | AG128: cmilk | AH128: ceggs | AI128: chony | AJ128: chunt | AK128: cfuel | AL128: cchar | AM128: cfore | AN128: cfish | AO128: cngas | AP128: cmore | AQ128: comin | AR128: cmeat | AS128: cfsea | AT128: cfveg | AU128: cfoil | AV128: cdair | AW128: cgmll | AX128: cbake | AY128: cfeed | AZ128: cfood | BA128: calco | BB128: cbeve | BC128: cptob | BD128: ctext | BE128: cwood | BF128: cprnt | BG128: cpetr | BH128: cchem | BI128: cphar | BJ128: cprub | BK128: cnmet | BL128: cceme | BM128: cclay | BN128: cmetl | BO128: cmach | BP128: cvehi | BQ128: cfurn | BR128: coman | BS128: crepr | BT128: celec | BU128: cwatr | BV128: cwast | BW128: ccons | BX128: ccont | BY128: cvehr | BZ128: cveht | CA128: ctrdw | CB128: ctrdr | CC128: ctrnl | CD128: ctrna | CE128: ctrns | CF128: cpost | CG128: chotl | CH128: cpubl | CI128: ccomm | CJ128: cinfo | CK128: cbank | CL128: cinsu | CM128: cofsv | CN128: crent | CO128: creal | CP128: clegl | CQ128: cenga | CR128: cprod | CS128: ctrvl | CT128: cobsv | CU128: cpadm | CV128: ceduc | CW128: cheal | CX128: csocw | CY128: ccult | CZ128: carts | DA128: cosrv | DB128: cdsrv | DC128: ctrdc
B129: Sorghum (A111) | C129: asorg | D129: =SUP!E318 -> 1 | E129: =SUP!F318 -> 0 | F129: =SUP!G318 -> 0 | G129: =SUP!H318 -> 0 | H129: =SUP!I318 -> 0 | I129: =SUP!J318 -> 0 | J129: =SUP!K318 -> 0 | K129: =SUP!L318 -> 0 | ... DC129: =SUP!DD318 -> 0
B130: Maize (A112) | C130: amaiz | D130: =SUP!E319 -> 0 | E130: =SUP!F319 -> 1 | F130: =SUP!G319 -> 0 | G130: =SUP!H319 -> 0 | H130: =SUP!I319 -> 0 | I130: =SUP!J319 -> 0 | J130: =SUP!K319 -> 0 | K130: =SUP!L319 -> 0 | ... DC130: =SUP!DD319 -> 0
B131: Wheat (A113) | C131: awhea | D131: =SUP!E320 -> 0 | E131: =SUP!F320 -> 0 | F131: =SUP!G320 -> 1 | G131: =SUP!H320 -> 0 | H131: =SUP!I320 -> 0 | I131: =SUP!J320 -> 0 | J131: =SUP!K320 -> 0 | K131: =SUP!L320 -> 0 | ... DC131: =SUP!DD320 -> 0
B132: Paddy & husked rice (A116) | C132: arice | D132: =SUP!E321 -> 0 | E132: =SUP!F321 -> 0 | F132: =SUP!G321 -> 0 | G132: =SUP!H321 -> 1 | H132: =SUP!I321 -> 0 | I132: =SUP!J321 -> 0 | J132: =SUP!K321 -> 0 | K132: =SUP!L321 -> 0 | ... DC132: =SUP!DD321 -> 0
B133: Other cereals (A119) | C133: aocer | D133: =SUP!E322 -> 0 | E133: =SUP!F322 -> 0 | F133: =SUP!G322 -> 0 | G133: =SUP!H322 -> 0 | H133: =SUP!I322 -> 1 | I133: =SUP!J322 -> 0 | J133: =SUP!K322 -> 0 | K133: =SUP!L322 -> 0 | ... DC133: =SUP!DD322 -> 0
B134: Irish potatoes (A121) | C134: aipot | D134: =SUP!E323 -> 0 | E134: =SUP!F323 -> 0 | F134: =SUP!G323 -> 0 | G134: =SUP!H323 -> 0 | H134: =SUP!I323 -> 0 | I134: =SUP!J323 -> 1 | J134: =SUP!K323 -> 0 | K134: =SUP!L323 -> 0 | ... DC134: =SUP!DD323 -> 0
B135: Sweet potatoes (A122) | C135: aspot | D135: =SUP!E324 -> 0 | E135: =SUP!F324 -> 0 | F135: =SUP!G324 -> 0 | G135: =SUP!H324 -> 0 | H135: =SUP!I324 -> 0 | I135: =SUP!J324 -> 0 | J135: =SUP!K324 -> 1 | K135: =SUP!L324 -> 0 | ... DC135: =SUP!DD324 -> 0
B136: Cassava (A123) | C136: acass | D136: =SUP!E325 -> 0 | E136: =SUP!F325 -> 0 | F136: =SUP!G325 -> 0 | G136: =SUP!H325 -> 0 | H136: =SUP!I325 -> 0 | I136: =SUP!J325 -> 0 | J136: =SUP!K325 -> 0 | K136: =SUP!L325 -> 1 | ... DC136: =SUP!DD325 -> 0
B137: Other roots & tubers (A129) | C137: aroot | D137: =SUP!E326 -> 0 | E137: =SUP!F326 -> 0 | F137: =SUP!G326 -> 0 | G137: =SUP!H326 -> 0 | H137: =SUP!I326 -> 0 | I137: =SUP!J326 -> 0 | J137: =SUP!K326 -> 0 | K137: =SUP!L326 -> 0 | ... DC137: =SUP!DD326 -> 0
B138: Dried beans (A131) | C138: abean | D138: =SUP!E327 -> 0 | E138: =SUP!F327 -> 0 | F138: =SUP!G327 -> 0 | G138: =SUP!H327 -> 0 | H138: =SUP!I327 -> 0 | I138: =SUP!J327 -> 0 | J138: =SUP!K327 -> 0 | K138: =SUP!L327 -> 0 | ... DC138: =SUP!DD327 -> 0
B139: Peas & other legumes (A132) | C139: apeas | D139: =SUP!E328 -> 0 | E139: =SUP!F328 -> 0 | F139: =SUP!G328 -> 0 | G139: =SUP!H328 -> 0 | H139: =SUP!I328 -> 0 | I139: =SUP!J328 -> 0 | J139: =SUP!K328 -> 0 | K139: =SUP!L328 -> 0 | ... DC139: =SUP!DD328 -> 0
B140: Other vegetables (A139) | C140: avege | D140: =SUP!E329 -> 0 | E140: =SUP!F329 -> 0 | F140: =SUP!G329 -> 0 | G140: =SUP!H329 -> 0 | H140: =SUP!I329 -> 0 | I140: =SUP!J329 -> 0 | J140: =SUP!K329 -> 0 | K140: =SUP!L329 -> 0 | ... DC140: =SUP!DD329 -> 0
... B232: Travel debits & credits (V00) | C232: atrdc | D232: =SUP!E421 -> 0 | E232: =SUP!F421 -> 0 | F232: =SUP!G421 -> 0 | G232: =SUP!H421 -> 0 | H232: =SUP!I421 -> 0 | I232: =SUP!J421 -> 0 | J232: =SUP!K421 -> 0 | K232: =SUP!L421 -> 0 | ... DC232: =SUP!DD421 -> 0

Sheet GDP
A1: Gross Domestic Product | D1: Domestic production
F2: Intermediate demand
G3: Value-added
B4: Original data | D4: SUP | E4: GO | F4: INT | G4: GDP | H4: GDP/GO | K4: Factors shares from 2011 SAM | R4: Mapped to SAM activity accounts
D5: Commodity | E5: Activity | F5: Activity | G5: Activity | H5: Activity | L5: Labor | M5: Land | N5: Capital | O5: Total | V5: GDP/GO | W5: Used | X5: SUP | Y5: GO | Z5: INT | AA5: GDP | AB5: FLAB | AC5: FLND | AD5: FCAP
D6: =SUM(D7:D84) -> 11646.996 | E6: =SUM(E7:E84) -> 11646.996 | F6: =SUM(F7:F84) -> 4606.299 | G6: =E6-F6 -> 7040.6969 | H6: =IF(E6,G6/E6,0) -> 0.60450754 | L6: FLAB | M6: FLND | N6: FCAP | X6: =SUM(X7:X111) -> 11646.996 | Y6: =SUM(Y7:Y111) -> 11646.996 | Z6: =SUM(Z7:Z111) -> 4606.299 | AA6: =SUM(AA7:AA111) -> 7040.6969 | AB6: =SUM(AB7:AB111) -> 3888.4208 | AC6: =SUM(AC7:AC111) -> 575.42618 | AD6: =SUM(AD7:AD111) -> 2576.8498
B7: A11 | C7: Cereals | D7: =SUMIF(SUT!$B$8:$B$124,$B7,SUT!$D$8:$D$124) -> 206.67601 | E7: =IF(ISNA(VLOOKUP(B7,SUP!$C$8:$D$86,2,0)),0,VLOOKUP(B7,SUP!$C$8:$D$86,2,0)) -> 206.67601 | F7: =IF(ISNA(HLOOKUP(B7,USE!$E$6:$CE$7,2,0)),0,HLOOKUP(B7,USE!$E$6:$CE$7,2,0)) -> 13.826933 | G7: =E7-F7 -> 192.84908 | H7: =IF(E7,G7/E7,0) -> 0.93309851 | K7: A111 | L7: =HLOOKUP($K7,SAM!$B$7:$DB$10,2,0) -> 0.42220218 | M7: =HLOOKUP($K7,SAM!$B$7:$DB$10,3,0) -> 0.5044744 | N7: =HLOOKUP($K7,SAM!$B$7:$DB$10,4,0) -> 0.073323421 | O7: =SUM(L7:N7) -> 1 | R7: A11 | S7: A111 | T7: =VLOOKUP(S7,Notes!$B$7:$F$111,5,0) -> Sorghum (A111) | U7: =VLOOKUP(S7,Notes!$B$7:$F$111,3,0) -> asorg | V7: =IF(ISNA(VLOOKUP(R7,$B$7:$H$84,7,0)),0,VLOOKUP(R7,$B$7:$H$84,7,0)) -> 0.93309851 | W7: =V7 -> 0.93309851 | X7: =SUT!T8 -> 45.171235 | Y7: =X7 -> 45.171235 | Z7: =Y7-AA7 -> 3.022023 | AA7: =W7*Y7 -> 42.149212 | AB7: =$AA7*L7 -> 17.795489 | AC7: =$AA7*M7 -> 21.263198 | AD7: =$AA7*N7 -> 3.0905244
B8: A12 | C8: Roots and Tubers | D8: =SUMIF(SUT!$B$8:$B$124,$B8,SUT!$D$8:$D$124) -> 468.14634 | E8: =IF(ISNA(VLOOKUP(B8,SUP!$C$8:$D$86,2,0)),0,VLOOKUP(B8,SUP!$C$8:$D$86,2,0)) -> 468.14634 | F8: =IF(ISNA(HLOOKUP(B8,USE!$E$6:$CE$7,2,0)),0,HLOOKUP(B8,USE!$E$6:$CE$7,2,0)) -> 30.293796 | G8: =E8-F8 -> 437.85254 | H8: =IF(E8,G8/E8,0) -> 0.9352899 | K8: A112 | L8: =HLOOKUP($K8,SAM!$B$7:$DB$10,2,0) -> 0.44086658 | M8: =HLOOKUP($K8,SAM!$B$7:$DB$10,3,0) -> 0.47905324 | N8: =HLOOKUP($K8,SAM!$B$7:$DB$10,4,0) -> 0.080080187 | O8: =SUM(L8:N8) -> 1 | R8: A11 | S8: A112 | T8: =VLOOKUP(S8,Notes!$B$7:$F$111,5,0) -> Maize (A112) | U8: =VLOOKUP(S8,Notes!$B$7:$F$111,3,0) -> amaiz | V8: =IF(ISNA(VLOOKUP(R8,$B$7:$H$84,7,0)),0,VLOOKUP(R8,$B$7:$H$84,7,0)) -> 0.93309851 | W8: =V8 -> 0.93309851 | X8: =SUT!T9 -> 98.080338 | Y8: =X8 -> 98.080338 | Z8: =Y8-AA8 -> 6.5617209 | AA8: =W8*Y8 -> 91.518617 | AB8: =$AA8*L8 -> 40.347499 | AC8: =$AA8*M8 -> 43.84229 | AD8: =$AA8*N8 -> 7.328828
B9: A13 | C9: Vegetables | D9: =SUMIF(SUT!$B$8:$B$124,$B9,SUT!$D$8:$D$124) -> 396.78988 | E9: =IF(ISNA(VLOOKUP(B9,SUP!$C$8:$D$86,2,0)),0,VLOOKUP(B9,SUP!$C$8:$D$86,2,0)) -> 396.78988 | F9: =IF(ISNA(HLOOKUP(B9,USE!$E$6:$CE$7,2,0)),0,HLOOKUP(B9,USE!$E$6:$CE$7,2,0)) -> 19.560457 | G9: =E9-F9 -> 377.22942 | H9: =IF(E9,G9/E9,0) -> 0.95070324 | K9: A113 | L9: =HLOOKUP($K9,SAM!$B$7:$DB$10,2,0) -> 0.45348046 | M9: =HLOOKUP($K9,SAM!$B$7:$DB$10,3,0) -> 0.45384121 | N9: =HLOOKUP($K9,SAM!$B$7:$DB$10,4,0) -> 0.092678327 | O9: =SUM(L9:N9) -> 1 | R9: A11 | S9: A113 | T9: =VLOOKUP(S9,Notes!$B$7:$F$111,5,0) -> Wheat (A113) | U9: =VLOOKUP(S9,Notes!$B$7:$F$111,3,0) -> awhea | V9: =IF(ISNA(VLOOKUP(R9,$B$7:$H$84,7,0)),0,VLOOKUP(R9,$B$7:$H$84,7,0)) -> 0.93309851 | W9: =V9 -> 0.93309851 | X9: =SUT!T10 -> 3.2529609 | Y9: =X9 -> 3.2529609 | Z9: =Y9-AA9 -> 0.21762793 | AA9: =W9*Y9 -> 3.0353329 | AB9: =$AA9*L9 -> 1.3764642 | AC9: =$AA9*M9 -> 1.3775592 | AD9: =$AA9*N9 -> 0.28130958
B10: A14 | C10: Bananas and fruit | D10: =SUMIF(SUT!$B$8:$B$124,$B10,SUT!$D$8:$D$124) -> 283.59608 | E10: =IF(ISNA(VLOOKUP(B10,SUP!$C$8:$D$86,2,0)),0,VLOOKUP(B10,SUP!$C$8:$D$86,2,0)) -> 283.59608 | F10: =IF(ISNA(HLOOKUP(B10,USE!$E$6:$CE$7,2,0)),0,HLOOKUP(B10,USE!$E$6:$CE$7,2,0)) -> 6.26712 | G10: =E10-F10 -> 277.32896 | H10: =IF(E10,G10/E10,0) -> 0.97790125 | K10: A116 | L10: =HLOOKUP($K10,SAM!$B$7:$DB$10,2,0) -> 0.4532881 | M10: =HLOOKUP($K10,SAM!$B$7:$DB$10,3,0) -> 0.43486634 | N10: =HLOOKUP($K10,SAM!$B$7:$DB$10,4,0) -> 0.11184556 | O10: =SUM(L10:N10) -> 1 | R10: A11 | S10: A116 | T10: =VLOOKUP(S10,Notes!$B$7:$F$111,5,0) -> Paddy & husked rice (A116) | U10: =VLOOKUP(S10,Notes!$B$7:$F$111,3,0) -> arice | V10: =IF(ISNA(VLOOKUP(R10,$B$7:$H$84,7,0)),0,VLOOKUP(R10,$B$7:$H$84,7,0)) -> 0.93309851 | W10: =V10 -> 0.93309851 | X10: =SUT!T11 -> 59.880657 | Y10: =X10 -> 59.880657 | Z10: =Y10-AA10 -> 4.0061053 | AA10: =W10*Y10 -> 55.874552 | AB10: =$AA10*L10 -> 25.327269 | AC10: =$AA10*M10 -> 24.297962 | AD10: =$AA10*N10 -> 6.2493205
B11: A15 | C11: Oil seeds n.e.c. and oleaginous fruit | D11: =SUMIF(SUT!$B$8:$B$124,$B11,SUT!$D$8:$D$124) -> 15.001884 | E11: =IF(ISNA(VLOOKUP(B11,SUP!$C$8:$D$86,2,0)),0,VLOOKUP(B11,SUP!$C$8:$D$86,2,0)) -> 15.001884 | F11: =IF(ISNA(HLOOKUP(B11,USE!$E$6:$CE$7,2,0)),0,HLOOKUP(B11,USE!$E$6:$CE$7,2,0)) -> 3.6893492 | G11: =E11-F11 -> 11.312535 | H11: =IF(E11,G11/E11,0) -> 0.75407428 | K11: A119 | L11: =HLOOKUP($K11,SAM!$B$7:$DB$10,2,0) -> 0.42220218 | M11: =HLOOKUP($K11,SAM!$B$7:$DB$10,3,0) -> 0.5044744 | N11: =HLOOKUP($K11,SAM!$B$7:$DB$10,4,0) -> 0.073323421 | O11: =SUM(L11:N11) -> 1 | R11: A11 | S11: A119 | T11: =VLOOKUP(S11,Notes!$B$7:$F$111,5,0) -> Other cereals (A119) | U11: =VLOOKUP(S11,Notes!$B$7:$F$111,3,0) -> aocer | V11: =IF(ISNA(VLOOKUP(R11,$B$7:$H$84,7,0)),0,VLOOKUP(R11,$B$7:$H$84,7,0)) -> 0.93309851 | W11: =V11 -> 0.93309851 | X11: =SUT!T12 -> 0.29082038 | Y11: =X11 -> 0.29082038 | Z11: =Y11-AA11 -> 0.019456317 | AA11: =W11*Y11 -> 0.27136406 | AB11: =$AA11*L11 -> 0.1145705 | AC11: =$AA11*M11 -> 0.13689622 | AD11: =$AA11*N11 -> 0.019897341
B12: A21 | C12: Coffee | D12: =SUMIF(SUT!$B$8:$B$124,$B12,SUT!$D$8:$D$124) -> 77.156236 | E12: =IF(ISNA(VLOOKUP(B12,SUP!$C$8:$D$86,2,0)),0,VLOOKUP(B12,SUP!$C$8:$D$86,2,0)) -> 77.156236 | F12: =IF(ISNA(HLOOKUP(B12,USE!$E$6:$CE$7,2,0)),0,HLOOKUP(B12,USE!$E$6:$CE$7,2,0)) -> 6.2891096 | G12: =E12-F12 -> 70.867127 | H12: =IF(E12,G12/E12,0) -> 0.91848864 | K12: A121 | L12: =HLOOKUP($K12,SAM!$B$7:$DB$10,2,0) -> 0.47058963 | M12: =HLOOKUP($K12,SAM!$B$7:$DB$10,3,0) -> 0.42164176 | N12: =HLOOKUP($K12,SAM!$B$7:$DB$10,4,0) -> 0.10776862 | O12: =SUM(L12:N12) -> 1 | R12: A12 | S12: A121 | T12: =VLOOKUP(S12,Notes!$B$7:$F$111,5,0) -> Irish potatoes (A121) | U12: =VLOOKUP(S12,Notes!$B$7:$F$111,3,0) -> aipot | V12: =IF(ISNA(VLOOKUP(R12,$B$7:$H$84,7,0)),0,VLOOKUP(R12,$B$7:$H$84,7,0)) -> 0.9352899 | W12: =V12 -> 0.9352899 | X12: =SUT!T13 -> 170.04725 | Y12: =X12 -> 170.04725 | Z12: =Y12-AA12 -> 11.003775 | AA12: =W12*Y12 -> 159.04348 | AB12: =$AA12*L12 -> 74.844212 | AC12: =$AA12*M12 -> 67.059372 | AD12: =$AA12*N12 -> 17.139896
B13: A22 | C13: Tea (unprocessed green leaf) | D13: =SUMIF(SUT!$B$8:$B$124,$B13,SUT!$D$8:$D$124) -> 24.490147 | E13: =IF(ISNA(VLOOKUP(B13,SUP!$C$8:$D$86,2,0)),0,VLOOKUP(B13,SUP!$C$8:$D$86,2,0)) -> 24.490147 | F13: =IF(ISNA(HLOOKUP(B13,USE!$E$6:$CE$7,2,0)),0,HLOOKUP(B13,USE!$E$6:$CE$7,2,0)) -> 2.108269 | G13: =E13-F13 -> 22.381878 | H13: =IF(E13,G13/E13,0) -> 0.91391359 | K13: A122 | L13: =HLOOKUP($K13,SAM!$B$7:$DB$10,2,0) -> 0.43368245 | M13: =HLOOKUP($K13,SAM!$B$7:$DB$10,3,0) -> 0.49381057 | N13: =HLOOKUP($K13,SAM!$B$7:$DB$10,4,0) -> 0.072506988 | O13: =SUM(L13:N13) -> 1 | R13: A12 | S13: A122 | T13: =VLOOKUP(S13,Notes!$B$7:$F$111,5,0) -> Sweet potatoes (A122) | U13: =VLOOKUP(S13,Notes!$B$7:$F$111,3,0) -> aspot | V13: =IF(ISNA(VLOOKUP(R13,$B$7:$H$84,7,0)),0,VLOOKUP(R13,$B$7:$H$84,7,0)) -> 0.9352899 | W13: =V13 -> 0.9352899 | X13: =SUT!T14 -> 151.37845 | Y13: =X13 -> 151.37845 | Z13: =Y13-AA13 -> 9.7957145 | AA13: =W13*Y13 -> 141.58273 | AB13: =$AA13*L13 -> 61.401946 | AC13: =$AA13*M13 -> 69.91505 | AD13: =$AA13*N13 -> 10.265738
B14: A29 | C14: Other agricultural products | D14: =SUMIF(SUT!$B$8:$B$124,$B14,SUT!$D$8:$D$124) -> 48.183435 | E14: =IF(ISNA(VLOOKUP(B14,SUP!$C$8:$D$86,2,0)),0,VLOOKUP(B14,SUP!$C$8:$D$86,2,0)) -> 48.183435 | F14: =IF(ISNA(HLOOKUP(B14,USE!$E$6:$CE$7,2,0)),0,HLOOKUP(B14,USE!$E$6:$CE$7,2,0)) -> 3.5808644 | G14: =E14-F14 -> 44.602571 | H14: =IF(E14,G14/E14,0) -> 0.92568267 | K14: A123 | L14: =HLOOKUP($K14,SAM!$B$7:$DB$10,2,0) -> 0.42490888 | M14: =HLOOKUP($K14,SAM!$B$7:$DB$10,3,0) -> 0.49443453 | N14: =HLOOKUP($K14,SAM!$B$7:$DB$10,4,0) -> 0.080656585 | O14: =SUM(L14:N14) -> 1 | R14: A12 | S14: A123 | T14: =VLOOKUP(S14,Notes!$B$7:$F$111,5,0) -> Cassava (A123) | U14: =VLOOKUP(S14,Notes!$B$7:$F$111,3,0) -> acass | V14: =IF(ISNA(VLOOKUP(R14,$B$7:$H$84,7,0)),0,VLOOKUP(R14,$B$7:$H$84,7,0)) -> 0.9352899 | W14: =V14 -> 0.9352899 | X14: =SUT!T15 -> 125.40484 | Y14: =X14 -> 125.40484 | Z14: =Y14-AA14 -> 8.1149595 | AA14: =W14*Y14 -> 117.28988 | AB14: =$AA14*L14 -> 49.837511 | AC14: =$AA14*M14 -> 57.992166 | AD14: =$AA14*N14 -> 9.460201
B15: A31 | C15: Livestock | D15: =SUMIF(SUT!$B$8:$B$124,$B15,SUT!$D$8:$D$124) -> 141.46606 | E15: =IF(ISNA(VLOOKUP(B15,SUP!$C$8:$D$86,2,0)),0,VLOOKUP(B15,SUP!$C$8:$D$86,2,0)) -> 141.46606 | F15: =IF(ISNA(HLOOKUP(B15,USE!$E$6:$CE$7,2,0)),0,HLOOKUP(B15,USE!$E$6:$CE$7,2,0)) -> 11.772368 | G15: =E15-F15 -> 129.6937 | H15: =IF(E15,G15/E15,0) -> 0.91678309 | K15: A129 | L15: =HLOOKUP($K15,SAM!$B$7:$DB$10,2,0) -> 0.46228215 | M15: =HLOOKUP($K15,SAM!$B$7:$DB$10,3,0) -> 0.45213772 | N15: =HLOOKUP($K15,SAM!$B$7:$DB$10,4,0) -> 0.085580135 | O15: =SUM(L15:N15) -> 1 | R15: A12 | S15: A129 | T15: =VLOOKUP(S15,Notes!$B$7:$F$111,5,0) -> Other roots & tubers (A129) | U15: =VLOOKUP(S15,Notes!$B$7:$F$111,3,0) -> aroot | V15: =IF(ISNA(VLOOKUP(R15,$B$7:$H$84,7,0)),0,VLOOKUP(R15,$B$7:$H$84,7,0)) -> 0.9352899 | W15: =V15 -> 0.9352899 | X15: =SUT!T16 -> 21.315797 | Y15: =X15 -> 21.315797 | Z15: =Y15-AA15 -> 1.3793474 | AA15: =W15*Y15 -> 19.93645 | AB15: =$AA15*L15 -> 9.2162649 | AC15: =$AA15*M15 -> 9.0140209 | AD15: =$AA15*N15 -> 1.7061641
B16: A32 | C16: Livestock and hunting products | D16: =SUMIF(SUT!$B$8:$B$124,$B16,SUT!$D$8:$D$124) -> 57.506207 | E16: =IF(ISNA(VLOOKUP(B16,SUP!$C$8:$D$86,2,0)),0,VLOOKUP(B16,SUP!$C$8:$D$86,2,0)) -> 57.506207 | F16: =IF(ISNA(HLOOKUP(B16,USE!$E$6:$CE$7,2,0)),0,HLOOKUP(B16,USE!$E$6:$CE$7,2,0)) -> 1.5113351 | G16: =E16-F16 -> 55.994872 | H16: =IF(E16,G16/E16,0) -> 0.97371875 | K16: A131 | L16: =HLOOKUP($K16,SAM!$B$7:$DB$10,2,0) -> 0.51205744 | M16: =HLOOKUP($K16,SAM!$B$7:$DB$10,3,0) -> 0.34841381 | N16: =HLOOKUP($K16,SAM!$B$7:$DB$10,4,0) -> 0.13952875 | O16: =SUM(L16:N16) -> 1 | R16: A13 | S16: A131 | T16: =VLOOKUP(S16,Notes!$B$7:$F$111,5,0) -> Dried beans (A131) | U16: =VLOOKUP(S16,Notes!$B$7:$F$111,3,0) -> abean | V16: =IF(ISNA(VLOOKUP(R16,$B$7:$H$84,7,0)),0,VLOOKUP(R16,$B$7:$H$84,7,0)) -> 0.95070324 | W16: =V16 -> 0.95070324 | X16: =SUT!T17 -> 225.63873 | Y16: =X16 -> 225.63873 | Z16: =Y16-AA16 -> 11.123259 | AA16: =W16*Y16 -> 214.51547 | AB16: =$AA16*L16 -> 109.84424 | AC16: =$AA16*M16 -> 74.740151 | AD16: =$AA16*N16 -> 29.931076
B17: A40 | C17: Forestry products | D17: =SUMIF(SUT!$B$8:$B$124,$B17,SUT!$D$8:$D$124) -> 379.13228 | E17: =IF(ISNA(VLOOKUP(B17,SUP!$C$8:$D$86,2,0)),0,VLOOKUP(B17,SUP!$C$8:$D$86,2,0)) -> 379.13228 | F17: =IF(ISNA(HLOOKUP(B17,USE!$E$6:$CE$7,2,0)),0,HLOOKUP(B17,USE!$E$6:$CE$7,2,0)) -> 0.69532137 | G17: =E17-F17 -> 378.43696 | H17: =IF(E17,G17/E17,0) -> 0.99816602 | K17: A132 | L17: =HLOOKUP($K17,SAM!$B$7:$DB$10,2,0) -> 0.51205744 | M17: =HLOOKUP($K17,SAM!$B$7:$DB$10,3,0) -> 0.34841381 | N17: =HLOOKUP($K17,SAM!$B$7:$DB$10,4,0) -> 0.13952875 | O17: =SUM(L17:N17) -> 1 | R17: A13 | S17: A132 | T17: =VLOOKUP(S17,Notes!$B$7:$F$111,5,0) -> Peas & other legumes (A132) | U17: =VLOOKUP(S17,Notes!$B$7:$F$111,3,0) -> apeas | V17: =IF(ISNA(VLOOKUP(R17,$B$7:$H$84,7,0)),0,VLOOKUP(R17,$B$7:$H$84,7,0)) -> 0.95070324 | W17: =V17 -> 0.95070324 | X17: =SUT!T18 -> 22.063138 | Y17: =X17 -> 22.063138 | Z17: =Y17-AA17 -> 1.0876413 | AA17: =W17*Y17 -> 20.975497 | AB17: =$AA17*L17 -> 10.740659 | AC17: =$AA17*M17 -> 7.3081528 | AD17: =$AA17*N17 -> 2.9266849
B18: A50 | C18: Fishery products | D18: =SUMIF(SUT!$B$8:$B$124,$B18,SUT!$D$8:$D$124) -> 29.763623 | E18: =IF(ISNA(VLOOKUP(B18,SUP!$C$8:$D$86,2,0)),0,VLOOKUP(B18,SUP!$C$8:$D$86,2,0)) -> 29.763623 | F18: =IF(ISNA(HLOOKUP(B18,USE!$E$6:$CE$7,2,0)),0,HLOOKUP(B18,USE!$E$6:$CE$7,2,0)) -> 1.233588 | G18: =E18-F18 -> 28.530035 | H18: =IF(E18,G18/E18,0) -> 0.95855384 | K18: A139 | L18: =HLOOKUP($K18,SAM!$B$7:$DB$10,2,0) -> 0.56833808 | M18: =HLOOKUP($K18,SAM!$B$7:$DB$10,3,0) -> 0.31138237 | N18: =HLOOKUP($K18,SAM!$B$7:$DB$10,4,0) -> 0.12027955 | O18: =SUM(L18:N18) -> 1 | R18: A13 | S18: A139 | T18: =VLOOKUP(S18,Notes!$B$7:$F$111,5,0) -> Other vegetables (A139) | U18: =VLOOKUP(S18,Notes!$B$7:$F$111,3,0) -> avege | V18: =IF(ISNA(VLOOKUP(R18,$B$7:$H$84,7,0)),0,VLOOKUP(R18,$B$7:$H$84,7,0)) -> 0.95070324 | W18: =V18 -> 0.95070324 | X18: =SUT!T19 -> 149.08801 | Y18: =X18 -> 149.08801 | Z18: =Y18-AA18 -> 7.3495563 | AA18: =W18*Y18 -> 141.73845 | AB18: =$AA18*L18 -> 80.555359 | AC18: =$AA18*M18 -> 44.134856 | AD18: =$AA18*N18 -> 17.048237
... B43: C63 | C43: Manufacture of clay building materials | D43: =SUMIF(SUT!$B$8:$B$124,$B43,SUT!$D$8:$D$124) -> 21.15271 | E43: =IF(ISNA(VLOOKUP(B43,SUP!$C$8:$D$86,2,0)),0,VLOOKUP(B43,SUP!$C$8:$D$86,2,0)) -> 20.256688 | F43: =IF(ISNA(HLOOKUP(B43,USE!$E$6:$CE$7,2,0)),0,HLOOKUP(B43,USE!$E$6:$CE$7,2,0)) -> 8.9920058 | G43: =E43-F43 -> 11.264682 | H43: =IF(E43,G43/E43,0) -> 0.55609693 | K43: A500 | L43: =HLOOKUP($K43,SAM!$B$7:$DB$10,2,0) -> 0.64999756 | M43: =HLOOKUP($K43,SAM!$B$7:$DB$10,3,0) -> 0 | N43: =HLOOKUP($K43,SAM!$B$7:$DB$10,4,0) -> 0.35000244 | O43: =SUM(L43:N43) -> 1 | R43: A50 | S43: A500 | T43: =VLOOKUP(S43,Notes!$B$7:$F$111,5,0) -> Fishery products (A500) | U43: =VLOOKUP(S43,Notes!$B$7:$F$111,3,0) -> afish | V43: =IF(ISNA(VLOOKUP(R43,$B$7:$H$84,7,0)),0,VLOOKUP(R43,$B$7:$H$84,7,0)) -> 0.95855384 | W43: =V43 -> 0.95855384 | X43: =SUT!T44 -> 29.763623 | Y43: =X43 -> 29.763623 | Z43: =Y43-AA43 -> 1.233588 | AA43: =W43*Y43 -> 28.530035 | AB43: =$AA43*L43 -> 18.544453 | AC43: =$AA43*M43 -> 0 | AD43: =$AA43*N43 -> 9.9855817
B44: C72 | C44: Metals & metal products, except machinery and equipment | D44: =SUMIF(SUT!$B$8:$B$124,$B44,SUT!$D$8:$D$124) -> 117.16854 | E44: =IF(ISNA(VLOOKUP(B44,SUP!$C$8:$D$86,2,0)),0,VLOOKUP(B44,SUP!$C$8:$D$86,2,0)) -> 123.85248 | F44: =IF(ISNA(HLOOKUP(B44,USE!$E$6:$CE$7,2,0)),0,HLOOKUP(B44,USE!$E$6:$CE$7,2,0)) -> 104.54244 | G44: =E44-F44 -> 19.310039 | H44: =IF(E44,G44/E44,0) -> 0.1559116 | K44: B01 | L44: =HLOOKUP($K44,SAM!$B$7:$DB$10,2,0) -> 0.48154359 | M44: =HLOOKUP($K44,SAM!$B$7:$DB$10,3,0) -> 0 | N44: =HLOOKUP($K44,SAM!$B$7:$DB$10,4,0) -> 0.51845641 | O44: =SUM(L44:N44) -> 1 | R44: B01 | S44: B01 | T44: =VLOOKUP(S44,Notes!$B$7:$F$111,5,0) -> Natural gas (B01) | U44: =VLOOKUP(S44,Notes!$B$7:$F$111,3,0) -> angas | V44: =IF(ISNA(VLOOKUP(R44,$B$7:$H$84,7,0)),0,VLOOKUP(R44,$B$7:$H$84,7,0)) -> 1 | W44: =V44 -> 1 | X44: =SUT!T45 -> 0.069273647 | Y44: =E19 -> 0.069273647 | Z44: =Y44-AA44 -> 0 | AA44: =W44*Y44 -> 0.069273647 | AB44: =$AA44*L44 -> 0.03335828 | AC44: =$AA44*M44 -> 0 | AD44: =$AA44*N44 -> 0.035915367
B45: C74 | C45: Machinery and equipment (except transport) | D45: =SUMIF(SUT!$B$8:$B$124,$B45,SUT!$D$8:$D$124) -> 12.122323 | E45: =IF(ISNA(VLOOKUP(B45,SUP!$C$8:$D$86,2,0)),0,VLOOKUP(B45,SUP!$C$8:$D$86,2,0)) -> 13.181656 | F45: =IF(ISNA(HLOOKUP(B45,USE!$E$6:$CE$7,2,0)),0,HLOOKUP(B45,USE!$E$6:$CE$7,2,0)) -> 4.7185336 | G45: =E45-F45 -> 8.4631229 | H45: =IF(E45,G45/E45,0) -> 0.64203789 | K45: B03 | L45: =HLOOKUP($K45,SAM!$B$7:$DB$10,2,0) -> 0.48154359 | M45: =HLOOKUP($K45,SAM!$B$7:$DB$10,3,0) -> 0 | N45: =HLOOKUP($K45,SAM!$B$7:$DB$10,4,0) -> 0.51845641 | O45: =SUM(L45:N45) -> 1 | R45: B03 | S45: B03 | T45: =VLOOKUP(S45,Notes!$B$7:$F$111,5,0) -> Metal ores (B03) | U45: =VLOOKUP(S45,Notes!$B$7:$F$111,3,0) -> amore | V45: =IF(ISNA(VLOOKUP(R45,$B$7:$H$84,7,0)),0,VLOOKUP(R45,$B$7:$H$84,7,0)) -> 0.6416892 | W45: =V45 -> 0.6416892 | X45: =SUT!T46 -> 90.760661 | Y45: =E20 -> 106.79302 | Z45: =Y45-AA45 -> 38.265093 | AA45: =W45*Y45 -> 68.52793 | AB45: =$AA45*L45 -> 32.999185 | AC45: =$AA45*M45 -> 0 | AD45: =$AA45*N45 -> 35.528745
B46: C76 | C46: Transport equipment | D46: =SUMIF(SUT!$B$8:$B$124,$B46,SUT!$D$8:$D$124) -> 8.8180832 | E46: =IF(ISNA(VLOOKUP(B46,SUP!$C$8:$D$86,2,0)),0,VLOOKUP(B46,SUP!$C$8:$D$86,2,0)) -> 8.8180832 | F46: =IF(ISNA(HLOOKUP(B46,USE!$E$6:$CE$7,2,0)),0,HLOOKUP(B46,USE!$E$6:$CE$7,2,0)) -> 4.3807275 | G46: =E46-F46 -> 4.4373558 | H46: =IF(E46,G46/E46,0) -> 0.50321092 | K46: B09 | L46: =HLOOKUP($K46,SAM!$B$7:$DB$10,2,0) -> 0.48154359 | M46: =HLOOKUP($K46,SAM!$B$7:$DB$10,3,0) -> 0 | N46: =HLOOKUP($K46,SAM!$B$7:$DB$10,4,0) -> 0.51845641 | O46: =SUM(L46:N46) -> 1 | R46: B09 | S46: B09 | T46: =VLOOKUP(S46,Notes!$B$7:$F$111,5,0) -> Quarry & other mining products (B09) | U46: =VLOOKUP(S46,Notes!$B$7:$F$111,3,0) -> aomin | V46: =IF(ISNA(VLOOKUP(R46,$B$7:$H$84,7,0)),0,VLOOKUP(R46,$B$7:$H$84,7,0)) -> 0.7314137 | W46: =V46 -> 0.7314137 | X46: =SUT!T47 -> 152.29613 | Y46: =E21 -> 131.84094 | Z46: =Y46-AA46 -> 35.41067 | AA46: =W46*Y46 -> 96.430268 | AB46: =$AA46*L46 -> 46.435377 | AC46: =$AA46*M46 -> 0 | AD46: =$AA46*N46 -> 49.994891
B47: C81 | C47: Furniture | D47: =SUMIF(SUT!$B$8:$B$124,$B47,SUT!$D$8:$D$124) -> 27.59031 | E47: =IF(ISNA(VLOOKUP(B47,SUP!$C$8:$D$86,2,0)),0,VLOOKUP(B47,SUP!$C$8:$D$86,2,0)) -> 38.49072 | F47: =IF(ISNA(HLOOKUP(B47,USE!$E$6:$CE$7,2,0)),0,HLOOKUP(B47,USE!$E$6:$CE$7,2,0)) -> 14.634522 | G47: =E47-F47 -> 23.856197 | H47: =IF(E47,G47/E47,0) -> 0.61979088 | K47: C11 | L47: =HLOOKUP($K47,SAM!$B$7:$DB$10,2,0) -> 0.47345894 | M47: =HLOOKUP($K47,SAM!$B$7:$DB$10,3,0) -> 0 | N47: =HLOOKUP($K47,SAM!$B$7:$DB$10,4,0) -> 0.52654106 | O47: =SUM(L47:N47) -> 1 | R47: C11 | S47: C11 | T47: =VLOOKUP(S47,Notes!$B$7:$F$111,5,0) -> Meat and meat products (C11) | U47: =VLOOKUP(S47,Notes!$B$7:$F$111,3,0) -> ameat | V47: =IF(ISNA(VLOOKUP(R47,$B$7:$H$84,7,0)),0,VLOOKUP(R47,$B$7:$H$84,7,0)) -> 0.2266543 | W47: =V47 -> 0.2266543 | X47: =SUT!T48 -> 93.719543 | Y47: =E22 -> 96.892672 | Z47: =Y47-AA47 -> 74.931532 | AA47: =W47*Y47 -> 21.961141 | AB47: =$AA47*L47 -> 10.397698 | AC47: =$AA47*M47 -> 0 | AD47: =$AA47*N47 -> 11.563442
B48: C82 | C48: Other manufacturing | D48: =SUMIF(SUT!$B$8:$B$124,$B48,SUT!$D$8:$D$124) -> 45.091143 | E48: =IF(ISNA(VLOOKUP(B48,SUP!$C$8:$D$86,2,0)),0,VLOOKUP(B48,SUP!$C$8:$D$86,2,0)) -> 46.472325 | F48: =IF(ISNA(HLOOKUP(B48,USE!$E$6:$CE$7,2,0)),0,HLOOKUP(B48,USE!$E$6:$CE$7,2,0)) -> 9.3357588 | G48: =E48-F48 -> 37.136566 | H48: =IF(E48,G48/E48,0) -> 0.79911143 | K48: C12 | L48: =HLOOKUP($K48,SAM!$B$7:$DB$10,2,0) -> 0.47345894 | M48: =HLOOKUP($K48,SAM!$B$7:$DB$10,3,0) -> 0 | N48: =HLOOKUP($K48,SAM!$B$7:$DB$10,4,0) -> 0.52654106 | O48: =SUM(L48:N48) -> 1 | R48: C12 | S48: C12 | T48: =VLOOKUP(S48,Notes!$B$7:$F$111,5,0) -> Prepared and preserved fish (C12) | U48: =VLOOKUP(S48,Notes!$B$7:$F$111,3,0) -> afsea | V48: =IF(ISNA(VLOOKUP(R48,$B$7:$H$84,7,0)),0,VLOOKUP(R48,$B$7:$H$84,7,0)) -> 0 | W48: =W47 -> 0.2266543 | X48: =SUT!T49 -> 0.70970427 | Y48: =E23 -> 0 | Z48: =Y48-AA48 -> 0 | AA48: =W48*Y48 -> 0 | AB48: =$AA48*L48 -> 0 | AC48: =$AA48*M48 -> 0 | AD48: =$AA48*N48 -> 0
B49: C83 | C49: Repair and installation of machinery and equipment | D49: =SUMIF(SUT!$B$8:$B$124,$B49,SUT!$D$8:$D$124) -> 0.26006752 | E49: =IF(ISNA(VLOOKUP(B49,SUP!$C$8:$D$86,2,0)),0,VLOOKUP(B49,SUP!$C$8:$D$86,2,0)) -> 0.78312071 | F49: =IF(ISNA(HLOOKUP(B49,USE!$E$6:$CE$7,2,0)),0,HLOOKUP(B49,USE!$E$6:$CE$7,2,0)) -> 0.5863776 | G49: =E49-F49 -> 0.19674311 | H49: =IF(E49,G49/E49,0) -> 0.25122961 | K49: C13 | L49: =HLOOKUP($K49,SAM!$B$7:$DB$10,2,0) -> 0.47345894 | M49: =HLOOKUP($K49,SAM!$B$7:$DB$10,3,0) -> 0 | N49: =HLOOKUP($K49,SAM!$B$7:$DB$10,4,0) -> 0.52654106 | O49: =SUM(L49:N49) -> 1 | R49: C13 | S49: C13 | T49: =VLOOKUP(S49,Notes!$B$7:$F$111,5,0) -> Prepared and preserved vegetables (C13) | U49: =VLOOKUP(S49,Notes!$B$7:$F$111,3,0) -> afveg | V49: =IF(ISNA(VLOOKUP(R49,$B$7:$H$84,7,0)),0,VLOOKUP(R49,$B$7:$H$84,7,0)) -> 0.32565389 | W49: =V49 -> 0.32565389 | X49: =SUT!T50 -> 20.9065 | Y49: =E24 -> 18.739136 | Z49: =Y49-AA49 -> 12.636663 | AA49: =W49*Y49 -> 6.1024723 | AB49: =$AA49*L49 -> 2.88927 | AC49: =$AA49*M49 -> 0 | AD49: =$AA49*N49 -> 3.2132023
B50: D00 | C50: Electricity, gas, steam and air conditioning supply | D50: =SUMIF(SUT!$B$8:$B$124,$B50,SUT!$D$8:$D$124) -> 163.60557 | E50: =IF(ISNA(VLOOKUP(B50,SUP!$C$8:$D$86,2,0)),0,VLOOKUP(B50,SUP!$C$8:$D$86,2,0)) -> 162.11641 | F50: =IF(ISNA(HLOOKUP(B50,USE!$E$6:$CE$7,2,0)),0,HLOOKUP(B50,USE!$E$6:$CE$7,2,0)) -> 78.540129 | G50: =E50-F50 -> 83.576277 | H50: =IF(E50,G50/E50,0) -> 0.5155325 | K50: C14 | L50: =HLOOKUP($K50,SAM!$B$7:$DB$10,2,0) -> 0.4982256 | M50: =HLOOKUP($K50,SAM!$B$7:$DB$10,3,0) -> 0 | N50: =HLOOKUP($K50,SAM!$B$7:$DB$10,4,0) -> 0.5017744 | O50: =SUM(L50:N50) -> 1 | R50: C14 | S50: C14 | T50: =VLOOKUP(S50,Notes!$B$7:$F$111,5,0) -> Animal and vegetable oils and fats (C14) | U50: =VLOOKUP(S50,Notes!$B$7:$F$111,3,0) -> afoil | V50: =IF(ISNA(VLOOKUP(R50,$B$7:$H$84,7,0)),0,VLOOKUP(R50,$B$7:$H$84,7,0)) -> 0.49112069 | W50: =V50 -> 0.49112069 | X50: =SUT!T51 -> 14.876357 | Y50: =E25 -> 16.476481 | Z50: =Y50-AA50 -> 8.3845406 | AA50: =W50*Y50 -> 8.0919409 | AB50: =$AA50*L50 -> 4.0316121 | AC50: =$AA50*M50 -> 0 | AD50: =$AA50*N50 -> 4.0603288
B51: E01 | C51: Water collection, treatment and supply: sewrage | D51: =SUMIF(SUT!$B$8:$B$124,$B51,SUT!$D$8:$D$124) -> 48.901118 | E51: =IF(ISNA(VLOOKUP(B51,SUP!$C$8:$D$86,2,0)),0,VLOOKUP(B51,SUP!$C$8:$D$86,2,0)) -> 44.182947 | F51: =IF(ISNA(HLOOKUP(B51,USE!$E$6:$CE$7,2,0)),0,HLOOKUP(B51,USE!$E$6:$CE$7,2,0)) -> 16.043307 | G51: =E51-F51 -> 28.13964 | H51: =IF(E51,G51/E51,0) -> 0.63688917 | K51: C15 | L51: =HLOOKUP($K51,SAM!$B$7:$DB$10,2,0) -> 0.47345894 | M51: =HLOOKUP($K51,SAM!$B$7:$DB$10,3,0) -> 0 | N51: =HLOOKUP($K51,SAM!$B$7:$DB$10,4,0) -> 0.52654106 | O51: =SUM(L51:N51) -> 1 | R51: C15 | S51: C15 | T51: =VLOOKUP(S51,Notes!$B$7:$F$111,5,0) -> Dairy products (C15) | U51: =VLOOKUP(S51,Notes!$B$7:$F$111,3,0) -> adair | V51: =IF(ISNA(VLOOKUP(R51,$B$7:$H$84,7,0)),0,VLOOKUP(R51,$B$7:$H$84,7,0)) -> 0.57009698 | W51: =V51 -> 0.57009698 | X51: =SUT!T52 -> 12.578488 | Y51: =E26 -> 7.9231538 | Z51: =Y51-AA51 -> 3.4061878 | AA51: =W51*Y51 -> 4.5169661 | AB51: =$AA51*L51 -> 2.1385979 | AC51: =$AA51*M51 -> 0 | AD51: =$AA51*N51 -> 2.3783681
B52: E02 | C52: Waste collection and management | D52: =SUMIF(SUT!$B$8:$B$124,$B52,SUT!$D$8:$D$124) -> 8.6291668 | E52: =IF(ISNA(VLOOKUP(B52,SUP!$C$8:$D$86,2,0)),0,VLOOKUP(B52,SUP!$C$8:$D$86,2,0)) -> 9.1531792 | F52: =IF(ISNA(HLOOKUP(B52,USE!$E$6:$CE$7,2,0)),0,HLOOKUP(B52,USE!$E$6:$CE$7,2,0)) -> 5.2308441 | G52: =E52-F52 -> 3.9223351 | H52: =IF(E52,G52/E52,0) -> 0.42852161 | K52: C16 | L52: =HLOOKUP($K52,SAM!$B$7:$DB$10,2,0) -> 0.53745677 | M52: =HLOOKUP($K52,SAM!$B$7:$DB$10,3,0) -> 0 | N52: =HLOOKUP($K52,SAM!$B$7:$DB$10,4,0) -> 0.46254323 | O52: =SUM(L52:N52) -> 1 | R52: C16 | S52: C16 | T52: =VLOOKUP(S52,Notes!$B$7:$F$111,5,0) -> Grain mill products (C16) | U52: =VLOOKUP(S52,Notes!$B$7:$F$111,3,0) -> agmll | V52: =IF(ISNA(VLOOKUP(R52,$B$7:$H$84,7,0)),0,VLOOKUP(R52,$B$7:$H$84,7,0)) -> 0.27681751 | W52: =V52 -> 0.27681751 | X52: =SUT!T53 -> 369.54145 | Y52: =E27 -> 379.28546 | Z52: =Y52-AA52 -> 274.2926 | AA52: =W52*Y52 -> 104.99285 | AB52: =$AA52*L52 -> 56.42912 | AC52: =$AA52*M52 -> 0 | AD52: =$AA52*N52 -> 48.563735
B53: F01 | C53: Construction (modern) | D53: =SUMIF(SUT!$B$8:$B$124,$B53,SUT!$D$8:$D$124) -> 1288.1823 | E53: =IF(ISNA(VLOOKUP(B53,SUP!$C$8:$D$86,2,0)),0,VLOOKUP(B53,SUP!$C$8:$D$86,2,0)) -> 1301.5981 | F53: =IF(ISNA(HLOOKUP(B53,USE!$E$6:$CE$7,2,0)),0,HLOOKUP(B53,USE!$E$6:$CE$7,2,0)) -> 843.12858 | G53: =E53-F53 -> 458.46952 | H53: =IF(E53,G53/E53,0) -> 0.35223586 | K53: C17 | L53: =HLOOKUP($K53,SAM!$B$7:$DB$10,2,0) -> 0.4982256 | M53: =HLOOKUP($K53,SAM!$B$7:$DB$10,3,0) -> 0 | N53: =HLOOKUP($K53,SAM!$B$7:$DB$10,4,0) -> 0.5017744 | O53: =SUM(L53:N53) -> 1 | R53: C17 | S53: C17 | T53: =VLOOKUP(S53,Notes!$B$7:$F$111,5,0) -> Bakery products (C17) | U53: =VLOOKUP(S53,Notes!$B$7:$F$111,3,0) -> abake | V53: =IF(ISNA(VLOOKUP(R53,$B$7:$H$84,7,0)),0,VLOOKUP(R53,$B$7:$H$84,7,0)) -> 0.24094973 | W53: =V53 -> 0.24094973 | X53: =SUT!T54 -> 67.521618 | Y53: =E28 -> 68.279875 | Z53: =Y53-AA53 -> 51.827857 | AA53: =W53*Y53 -> 16.452017 | AB53: =$AA53*L53 -> 8.1968161 | AC53: =$AA53*M53 -> 0 | AD53: =$AA53*N53 -> 8.255201
B54: F02 | C54: Construction (traditional) | D54: =SUMIF(SUT!$B$8:$B$124,$B54,SUT!$D$8:$D$124) -> 0 | E54: =IF(ISNA(VLOOKUP(B54,SUP!$C$8:$D$86,2,0)),0,VLOOKUP(B54,SUP!$C$8:$D$86,2,0)) -> 0 | F54: =IF(ISNA(HLOOKUP(B54,USE!$E$6:$CE$7,2,0)),0,HLOOKUP(B54,USE!$E$6:$CE$7,2,0)) -> 0 | G54: =E54-F54 -> 0 | H54: =IF(E54,G54/E54,0) -> 0 | K54: C18 | L54: =HLOOKUP($K54,SAM!$B$7:$DB$10,2,0) -> 0.4982256 | M54: =HLOOKUP($K54,SAM!$B$7:$DB$10,3,0) -> 0 | N54: =HLOOKUP($K54,SAM!$B$7:$DB$10,4,0) -> 0.5017744 | O54: =SUM(L54:N54) -> 1 | R54: C18 | S54: C18 | T54: =VLOOKUP(S54,Notes!$B$7:$F$111,5,0) -> Animal feed & other by-products (C18) | U54: =VLOOKUP(S54,Notes!$B$7:$F$111,3,0) -> afeed | V54: =IF(ISNA(VLOOKUP(R54,$B$7:$H$84,7,0)),0,VLOOKUP(R54,$B$7:$H$84,7,0)) -> 0.94501676 | W54: =V54 -> 0.94501676 | X54: =SUT!T55 -> 8.5304007 | Y54: =E29 -> 4.1641953 | Z54: =Y54-AA54 -> 0.22896095 | AA54: =W54*Y54 -> 3.9352344 | AB54: =$AA54*L54 -> 1.9606345 | AC54: =$AA54*M54 -> 0 | AD54: =$AA54*N54 -> 1.9745999
B55: G10 | C55: Maintenance and repair of motor vehicles | D55: =SUMIF(SUT!$B$8:$B$124,$B55,SUT!$D$8:$D$124) -> 50.837891 | E55: =IF(ISNA(VLOOKUP(B55,SUP!$C$8:$D$86,2,0)),0,VLOOKUP(B55,SUP!$C$8:$D$86,2,0)) -> 56.123168 | F55: =IF(ISNA(HLOOKUP(B55,USE!$E$6:$CE$7,2,0)),0,HLOOKUP(B55,USE!$E$6:$CE$7,2,0)) -> 15.813318 | G55: =E55-F55 -> 40.309849 | H55: =IF(E55,G55/E55,0) -> 0.71823903 | K55: C19 | L55: =HLOOKUP($K55,SAM!$B$7:$DB$10,2,0) -> 0.4982256 | M55: =HLOOKUP($K55,SAM!$B$7:$DB$10,3,0) -> 0 | N55: =HLOOKUP($K55,SAM!$B$7:$DB$10,4,0) -> 0.5017744 | O55: =SUM(L55:N55) -> 1 | R55: C19 | S55: C19 | T55: =VLOOKUP(S55,Notes!$B$7:$F$111,5,0) -> Other manufactured food products (C19) | U55: =VLOOKUP(S55,Notes!$B$7:$F$111,3,0) -> afood | V55: =IF(ISNA(VLOOKUP(R55,$B$7:$H$84,7,0)),0,VLOOKUP(R55,$B$7:$H$84,7,0)) -> 0.40607617 | W55: =V55 -> 0.40607617 | X55: =SUT!T56 -> 101.95145 | Y55: =E30 -> 109.03152 | Z55: =Y55-AA55 -> 64.756417 | AA55: =W55*Y55 -> 44.275101 | AB55: =$AA55*L55 -> 22.058989 | AC55: =$AA55*M55 -> 0 | AD55: =$AA55*N55 -> 22.216112
B56: G21 | C56: Wholesale and retail trade of motor vehicles and motorcycles | D56: =SUMIF(SUT!$B$8:$B$124,$B56,SUT!$D$8:$D$124) -> 9.4425563 | E56: =IF(ISNA(VLOOKUP(B56,SUP!$C$8:$D$86,2,0)),0,VLOOKUP(B56,SUP!$C$8:$D$86,2,0)) -> 11.781521 | F56: =IF(ISNA(HLOOKUP(B56,USE!$E$6:$CE$7,2,0)),0,HLOOKUP(B56,USE!$E$6:$CE$7,2,0)) -> 6.9258819 | G56: =E56-F56 -> 4.8556395 | H56: =IF(E56,G56/E56,0) -> 0.41214028 | K56: C21 | L56: =HLOOKUP($K56,SAM!$B$7:$DB$10,2,0) -> 0.38282644 | M56: =HLOOKUP($K56,SAM!$B$7:$DB$10,3,0) -> 0 | N56: =HLOOKUP($K56,SAM!$B$7:$DB$10,4,0) -> 0.61717356 | O56: =SUM(L56:N56) -> 1 | R56: C21 | S56: C21 | T56: =VLOOKUP(S56,Notes!$B$7:$F$111,5,0) -> Alcoholic drinks (C21) | U56: =VLOOKUP(S56,Notes!$B$7:$F$111,3,0) -> aalco | V56: =IF(ISNA(VLOOKUP(R56,$B$7:$H$84,7,0)),0,VLOOKUP(R56,$B$7:$H$84,7,0)) -> 0.4883556 | W56: =V56 -> 0.4883556 | X56: =SUT!T57 -> 229.99839 | Y56: =E31 -> 262.50333 | Z56: =Y56-AA56 -> 134.30836 | AA56: =W56*Y56 -> 128.19497 | AB56: =$AA56*L56 -> 49.076425 | AC56: =$AA56*M56 -> 0 | AD56: =$AA56*N56 -> 79.118549
B57: G22 | C57: Wholesale trade, except of motor vehicles and motorcycles | D57: =SUMIF(SUT!$B$8:$B$124,$B57,SUT!$D$8:$D$124) -> 367.27361 | E57: =IF(ISNA(VLOOKUP(B57,SUP!$C$8:$D$86,2,0)),0,VLOOKUP(B57,SUP!$C$8:$D$86,2,0)) -> 356.5704 | F57: =IF(ISNA(HLOOKUP(B57,USE!$E$6:$CE$7,2,0)),0,HLOOKUP(B57,USE!$E$6:$CE$7,2,0)) -> 177.70263 | G57: =E57-F57 -> 178.86777 | H57: =IF(E57,G57/E57,0) -> 0.50163381 | K57: C22 | L57: =HLOOKUP($K57,SAM!$B$7:$DB$10,2,0) -> 0.38282644 | M57: =HLOOKUP($K57,SAM!$B$7:$DB$10,3,0) -> 0 | N57: =HLOOKUP($K57,SAM!$B$7:$DB$10,4,0) -> 0.61717356 | O57: =SUM(L57:N57) -> 1 | R57: C22 | S57: C22 | T57: =VLOOKUP(S57,Notes!$B$7:$F$111,5,0) -> Soft drinks (C22) | U57: =VLOOKUP(S57,Notes!$B$7:$F$111,3,0) -> abeve | V57: =IF(ISNA(VLOOKUP(R57,$B$7:$H$84,7,0)),0,VLOOKUP(R57,$B$7:$H$84,7,0)) -> 0.57494378 | W57: =V57 -> 0.57494378 | X57: =SUT!T58 -> 67.765458 | Y57: =E32 -> 43.671842 | Z57: =Y57-AA57 -> 18.562988 | AA57: =W57*Y57 -> 25.108854 | AB57: =$AA57*L57 -> 9.6123331 | AC57: =$AA57*M57 -> 0 | AD57: =$AA57*N57 -> 15.496521
B58: G23 | C58: Retail trade, except of motor vehicles and motorcycles | D58: =SUMIF(SUT!$B$8:$B$124,$B58,SUT!$D$8:$D$124) -> 678.08134 | E58: =IF(ISNA(VLOOKUP(B58,SUP!$C$8:$D$86,2,0)),0,VLOOKUP(B58,SUP!$C$8:$D$86,2,0)) -> 673.16454 | F58: =IF(ISNA(HLOOKUP(B58,USE!$E$6:$CE$7,2,0)),0,HLOOKUP(B58,USE!$E$6:$CE$7,2,0)) -> 260.23653 | G58: =E58-F58 -> 412.92801 | H58: =IF(E58,G58/E58,0) -> 0.6134132 | K58: C23 | L58: =HLOOKUP($K58,SAM!$B$7:$DB$10,2,0) -> 0.27416796 | M58: =HLOOKUP($K58,SAM!$B$7:$DB$10,3,0) -> 0 | N58: =HLOOKUP($K58,SAM!$B$7:$DB$10,4,0) -> 0.72583204 | O58: =SUM(L58:N58) -> 1 | R58: C23 | S58: C23 | T58: =VLOOKUP(S58,Notes!$B$7:$F$111,5,0) -> Tobacco products (C23) | U58: =VLOOKUP(S58,Notes!$B$7:$F$111,3,0) -> aptob | V58: =IF(ISNA(VLOOKUP(R58,$B$7:$H$84,7,0)),0,VLOOKUP(R58,$B$7:$H$84,7,0)) -> 0.76946244 | W58: =V58 -> 0.76946244 | X58: =SUT!T59 -> 7.8430383 | Y58: =E33 -> 7.8430383 | Z58: =Y58-AA58 -> 1.8081149 | AA58: =W58*Y58 -> 6.0349234 | AB58: =$AA58*L58 -> 1.6545826 | AC58: =$AA58*M58 -> 0 | AD58: =$AA58*N58 -> 4.3803408
B59: H10 | C59: Land transport | D59: =SUMIF(SUT!$B$8:$B$124,$B59,SUT!$D$8:$D$124) -> 442.63902 | E59: =IF(ISNA(VLOOKUP(B59,SUP!$C$8:$D$86,2,0)),0,VLOOKUP(B59,SUP!$C$8:$D$86,2,0)) -> 409.88041 | F59: =IF(ISNA(HLOOKUP(B59,USE!$E$6:$CE$7,2,0)),0,HLOOKUP(B59,USE!$E$6:$CE$7,2,0)) -> 204.92214 | G59: =E59-F59 -> 204.95827 | H59: =IF(E59,G59/E59,0) -> 0.50004408 | K59: C30 | L59: =HLOOKUP($K59,SAM!$B$7:$DB$10,2,0) -> 0.62064856 | M59: =HLOOKUP($K59,SAM!$B$7:$DB$10,3,0) -> 0 | N59: =HLOOKUP($K59,SAM!$B$7:$DB$10,4,0) -> 0.37935144 | O59: =SUM(L59:N59) -> 1 | R59: C30 | S59: C30 | T59: =VLOOKUP(S59,Notes!$B$7:$F$111,5,0) -> Textiles, clothing & leather products (C30) | U59: =VLOOKUP(S59,Notes!$B$7:$F$111,3,0) -> atext | V59: =IF(ISNA(VLOOKUP(R59,$B$7:$H$84,7,0)),0,VLOOKUP(R59,$B$7:$H$84,7,0)) -> 0.48790814 | W59: =V59 -> 0.48790814 | X59: =SUT!T60 -> 59.78059 | Y59: =E34 -> 69.155827 | Z59: =Y59-AA59 -> 35.414136 | AA59: =W59*Y59 -> 33.741691 | AB59: =$AA59*L59 -> 20.941732 | AC59: =$AA59*M59 -> 0 | AD59: =$AA59*N59 -> 12.799959
B60: H20 | C60: Air transport | D60: =SUMIF(SUT!$B$8:$B$124,$B60,SUT!$D$8:$D$124) -> 180.34401 | E60: =IF(ISNA(VLOOKUP(B60,SUP!$C$8:$D$86,2,0)),0,VLOOKUP(B60,SUP!$C$8:$D$86,2,0)) -> 179.48188 | F60: =IF(ISNA(HLOOKUP(B60,USE!$E$6:$CE$7,2,0)),0,HLOOKUP(B60,USE!$E$6:$CE$7,2,0)) -> 83.759946 | G60: =E60-F60 -> 95.721929 | H60: =IF(E60,G60/E60,0) -> 0.53332365 | K60: C41 | L60: =HLOOKUP($K60,SAM!$B$7:$DB$10,2,0) -> 0.37779779 | M60: =HLOOKUP($K60,SAM!$B$7:$DB$10,3,0) -> 0 | N60: =HLOOKUP($K60,SAM!$B$7:$DB$10,4,0) -> 0.62220221 | O60: =SUM(L60:N60) -> 1 | R60: C41 | S60: C41 | T60: =VLOOKUP(S60,Notes!$B$7:$F$111,5,0) -> Wood, paper and related products (C41) | U60: =VLOOKUP(S60,Notes!$B$7:$F$111,3,0) -> awood | V60: =IF(ISNA(VLOOKUP(R60,$B$7:$H$84,7,0)),0,VLOOKUP(R60,$B$7:$H$84,7,0)) -> 0.48876047 | W60: =V60 -> 0.48876047 | X60: =SUT!T61 -> 40.542143 | Y60: =E35 -> 31.358362 | Z60: =Y60-AA60 -> 16.031634 | AA60: =W60*Y60 -> 15.326728 | AB60: =$AA60*L60 -> 5.7904038 | AC60: =$AA60*M60 -> 0 | AD60: =$AA60*N60 -> 9.5363237
... B78: P00 | C78: Education | D78: =SUMIF(SUT!$B$8:$B$124,$B78,SUT!$D$8:$D$124) -> 360.18246 | E78: =IF(ISNA(VLOOKUP(B78,SUP!$C$8:$D$86,2,0)),0,VLOOKUP(B78,SUP!$C$8:$D$86,2,0)) -> 367.45636 | F78: =IF(ISNA(HLOOKUP(B78,USE!$E$6:$CE$7,2,0)),0,HLOOKUP(B78,USE!$E$6:$CE$7,2,0)) -> 136.4811 | G78: =E78-F78 -> 230.97527 | H78: =IF(E78,G78/E78,0) -> 0.62857876 | K78: F01 | L78: =HLOOKUP($K78,SAM!$B$7:$DB$10,2,0) -> 0.5638309 | M78: =HLOOKUP($K78,SAM!$B$7:$DB$10,3,0) -> 0 | N78: =HLOOKUP($K78,SAM!$B$7:$DB$10,4,0) -> 0.4361691 | O78: =SUM(L78:N78) -> 1 | R78: F01 | S78: F01 | T78: =VLOOKUP(S78,Notes!$B$7:$F$111,5,0) -> Construction (modern) (F01) | U78: =VLOOKUP(S78,Notes!$B$7:$F$111,3,0) -> acons | V78: =IF(ISNA(VLOOKUP(R78,$B$7:$H$84,7,0)),0,VLOOKUP(R78,$B$7:$H$84,7,0)) -> 0.35223586 | W78: =V78 -> 0.35223586 | X78: =SUT!T79 -> 1288.1823 | Y78: =E53 -> 1301.5981 | Z78: =Y78-AA78 -> 843.12858 | AA78: =W78*Y78 -> 458.46952 | AB78: =$AA78*L78 -> 258.49929 | AC78: =$AA78*M78 -> 0 | AD78: =$AA78*N78 -> 199.97024
B79: Q01 | C79: Human health activities | D79: =SUMIF(SUT!$B$8:$B$124,$B79,SUT!$D$8:$D$124) -> 212.79473 | E79: =IF(ISNA(VLOOKUP(B79,SUP!$C$8:$D$86,2,0)),0,VLOOKUP(B79,SUP!$C$8:$D$86,2,0)) -> 210.85838 | F79: =IF(ISNA(HLOOKUP(B79,USE!$E$6:$CE$7,2,0)),0,HLOOKUP(B79,USE!$E$6:$CE$7,2,0)) -> 109.35478 | G79: =E79-F79 -> 101.5036 | H79: =IF(E79,G79/E79,0) -> 0.48138281 | K79: F02 | L79: =HLOOKUP($K79,SAM!$B$7:$DB$10,2,0) -> 0.5638309 | M79: =HLOOKUP($K79,SAM!$B$7:$DB$10,3,0) -> 0 | N79: =HLOOKUP($K79,SAM!$B$7:$DB$10,4,0) -> 0.4361691 | O79: =SUM(L79:N79) -> 1 | R79: F02 | S79: F02 | T79: =VLOOKUP(S79,Notes!$B$7:$F$111,5,0) -> Construction (traditional) (F02) | U79: =VLOOKUP(S79,Notes!$B$7:$F$111,3,0) -> acont | V79: =IF(ISNA(VLOOKUP(R79,$B$7:$H$84,7,0)),0,VLOOKUP(R79,$B$7:$H$84,7,0)) -> 0 | W79: =W78 -> 0.35223586 | X79: =SUT!T80 -> 0 | Y79: =E54 -> 0 | Z79: =Y79-AA79 -> 0 | AA79: =W79*Y79 -> 0 | AB79: =$AA79*L79 -> 0 | AC79: =$AA79*M79 -> 0 | AD79: =$AA79*N79 -> 0
B80: Q02 | C80: Social work activities | D80: =SUMIF(SUT!$B$8:$B$124,$B80,SUT!$D$8:$D$124) -> 97.651638 | E80: =IF(ISNA(VLOOKUP(B80,SUP!$C$8:$D$86,2,0)),0,VLOOKUP(B80,SUP!$C$8:$D$86,2,0)) -> 99.490586 | F80: =IF(ISNA(HLOOKUP(B80,USE!$E$6:$CE$7,2,0)),0,HLOOKUP(B80,USE!$E$6:$CE$7,2,0)) -> 40.751552 | G80: =E80-F80 -> 58.739034 | H80: =IF(E80,G80/E80,0) -> 0.59039791 | K80: G10 | L80: =HLOOKUP($K80,SAM!$B$7:$DB$10,2,0) -> 0.51658773 | M80: =HLOOKUP($K80,SAM!$B$7:$DB$10,3,0) -> 0 | N80: =HLOOKUP($K80,SAM!$B$7:$DB$10,4,0) -> 0.48341227 | O80: =SUM(L80:N80) -> 1 | R80: G10 | S80: G10 | T80: =VLOOKUP(S80,Notes!$B$7:$F$111,5,0) -> Maintenance and repair of motor vehicles (G10) | U80: =VLOOKUP(S80,Notes!$B$7:$F$111,3,0) -> avehr | V80: =IF(ISNA(VLOOKUP(R80,$B$7:$H$84,7,0)),0,VLOOKUP(R80,$B$7:$H$84,7,0)) -> 0.71823903 | W80: =V80 -> 0.71823903 | X80: =SUT!T81 -> 50.837891 | Y80: =E55 -> 56.123168 | Z80: =Y80-AA80 -> 15.813318 | AA80: =W80*Y80 -> 40.309849 | AB80: =$AA80*L80 -> 20.823574 | AC80: =$AA80*M80 -> 0 | AD80: =$AA80*N80 -> 19.486276
B81: R01 | C81: Libraries, archives, museums and other cultural activities | D81: =SUMIF(SUT!$B$8:$B$124,$B81,SUT!$D$8:$D$124) -> 15.058193 | E81: =IF(ISNA(VLOOKUP(B81,SUP!$C$8:$D$86,2,0)),0,VLOOKUP(B81,SUP!$C$8:$D$86,2,0)) -> 15.066818 | F81: =IF(ISNA(HLOOKUP(B81,USE!$E$6:$CE$7,2,0)),0,HLOOKUP(B81,USE!$E$6:$CE$7,2,0)) -> 2.7889478 | G81: =E81-F81 -> 12.27787 | H81: =IF(E81,G81/E81,0) -> 0.8148947 | K81: G21 | L81: =HLOOKUP($K81,SAM!$B$7:$DB$10,2,0) -> 0.51658773 | M81: =HLOOKUP($K81,SAM!$B$7:$DB$10,3,0) -> 0 | N81: =HLOOKUP($K81,SAM!$B$7:$DB$10,4,0) -> 0.48341227 | O81: =SUM(L81:N81) -> 1 | R81: G21 | S81: G21 | T81: =VLOOKUP(S81,Notes!$B$7:$F$111,5,0) -> Wholesale and retail trade of motor vehicles and motorcycles (G21) | U81: =VLOOKUP(S81,Notes!$B$7:$F$111,3,0) -> aveht | V81: =IF(ISNA(VLOOKUP(R81,$B$7:$H$84,7,0)),0,VLOOKUP(R81,$B$7:$H$84,7,0)) -> 0.41214028 | W81: =V81 -> 0.41214028 | X81: =SUT!T82 -> 9.4425563 | Y81: =E56 -> 11.781521 | Z81: =Y81-AA81 -> 6.9258819 | AA81: =W81*Y81 -> 4.8556395 | AB81: =$AA81*L81 -> 2.5083638 | AC81: =$AA81*M81 -> 0 | AD81: =$AA81*N81 -> 2.3472757
B82: R09 | C82: Other arts, entertainment and recreation | D82: =SUMIF(SUT!$B$8:$B$124,$B82,SUT!$D$8:$D$124) -> 63.374693 | E82: =IF(ISNA(VLOOKUP(B82,SUP!$C$8:$D$86,2,0)),0,VLOOKUP(B82,SUP!$C$8:$D$86,2,0)) -> 54.933425 | F82: =IF(ISNA(HLOOKUP(B82,USE!$E$6:$CE$7,2,0)),0,HLOOKUP(B82,USE!$E$6:$CE$7,2,0)) -> 2.6396367 | G82: =E82-F82 -> 52.293788 | H82: =IF(E82,G82/E82,0) -> 0.95194844 | K82: G22 | L82: =HLOOKUP($K82,SAM!$B$7:$DB$10,2,0) -> 0.51658773 | M82: =HLOOKUP($K82,SAM!$B$7:$DB$10,3,0) -> 0 | N82: =HLOOKUP($K82,SAM!$B$7:$DB$10,4,0) -> 0.48341227 | O82: =SUM(L82:N82) -> 1 | R82: G22 | S82: G22 | T82: =VLOOKUP(S82,Notes!$B$7:$F$111,5,0) -> Wholesale trade, except of motor vehicles and motorcycles (G22) | U82: =VLOOKUP(S82,Notes!$B$7:$F$111,3,0) -> atrdw | V82: =IF(ISNA(VLOOKUP(R82,$B$7:$H$84,7,0)),0,VLOOKUP(R82,$B$7:$H$84,7,0)) -> 0.50163381 | W82: =V82 -> 0.50163381 | X82: =SUT!T83 -> 367.27361 | Y82: =E57 -> 356.5704 | Z82: =Y82-AA82 -> 177.70263 | AA82: =W82*Y82 -> 178.86777 | AB82: =$AA82*L82 -> 92.400895 | AC82: =$AA82*M82 -> 0 | AD82: =$AA82*N82 -> 86.466874
B83: S00 | C83: Other service activities | D83: =SUMIF(SUT!$B$8:$B$124,$B83,SUT!$D$8:$D$124) -> 407.53025 | E83: =IF(ISNA(VLOOKUP(B83,SUP!$C$8:$D$86,2,0)),0,VLOOKUP(B83,SUP!$C$8:$D$86,2,0)) -> 408.75737 | F83: =IF(ISNA(HLOOKUP(B83,USE!$E$6:$CE$7,2,0)),0,HLOOKUP(B83,USE!$E$6:$CE$7,2,0)) -> 107.64325 | G83: =E83-F83 -> 301.11412 | H83: =IF(E83,G83/E83,0) -> 0.73665734 | K83: G23 | L83: =HLOOKUP($K83,SAM!$B$7:$DB$10,2,0) -> 0.51658773 | M83: =HLOOKUP($K83,SAM!$B$7:$DB$10,3,0) -> 0 | N83: =HLOOKUP($K83,SAM!$B$7:$DB$10,4,0) -> 0.48341227 | O83: =SUM(L83:N83) -> 1 | R83: G23 | S83: G23 | T83: =VLOOKUP(S83,Notes!$B$7:$F$111,5,0) -> Retail trade, except of motor vehicles and motorcycles (G23) | U83: =VLOOKUP(S83,Notes!$B$7:$F$111,3,0) -> atrdr | V83: =IF(ISNA(VLOOKUP(R83,$B$7:$H$84,7,0)),0,VLOOKUP(R83,$B$7:$H$84,7,0)) -> 0.6134132 | W83: =V83 -> 0.6134132 | X83: =SUT!T84 -> 678.08134 | Y83: =E58 -> 673.16454 | Z83: =Y83-AA83 -> 260.23653 | AA83: =W83*Y83 -> 412.92801 | AB83: =$AA83*L83 -> 213.31355 | AC83: =$AA83*M83 -> 0 | AD83: =$AA83*N83 -> 199.61447
B84: T00 | C84: Domestic services | D84: =SUMIF(SUT!$B$8:$B$124,$B84,SUT!$D$8:$D$124) -> 25.436762 | E84: =IF(ISNA(VLOOKUP(B84,SUP!$C$8:$D$86,2,0)),0,VLOOKUP(B84,SUP!$C$8:$D$86,2,0)) -> 25.436762 | F84: =IF(ISNA(HLOOKUP(B84,USE!$E$6:$CE$7,2,0)),0,HLOOKUP(B84,USE!$E$6:$CE$7,2,0)) -> 0.59442349 | G84: =E84-F84 -> 24.842339 | H84: =IF(E84,G84/E84,0) -> 0.97663132 | K84: H10 | L84: =HLOOKUP($K84,SAM!$B$7:$DB$10,2,0) -> 0.59792235 | M84: =HLOOKUP($K84,SAM!$B$7:$DB$10,3,0) -> 0 | N84: =HLOOKUP($K84,SAM!$B$7:$DB$10,4,0) -> 0.40207765 | O84: =SUM(L84:N84) -> 1 | R84: H10 | S84: H10 | T84: =VLOOKUP(S84,Notes!$B$7:$F$111,5,0) -> Land transport (H10) | U84: =VLOOKUP(S84,Notes!$B$7:$F$111,3,0) -> atrnl | V84: =IF(ISNA(VLOOKUP(R84,$B$7:$H$84,7,0)),0,VLOOKUP(R84,$B$7:$H$84,7,0)) -> 0.50004408 | W84: =V84 -> 0.50004408 | X84: =SUT!T85 -> 442.63902 | Y84: =E59 -> 409.88041 | Z84: =Y84-AA84 -> 204.92214 | AA84: =W84*Y84 -> 204.95827 | AB84: =$AA84*L84 -> 122.54913 | AC84: =$AA84*M84 -> 0 | AD84: =$AA84*N84 -> 82.40914
B85: V00 | C85: =VLOOKUP(B85,Notes!$B$7:$F$111,5,0) -> Travel debits & credits (V00) | D85: =SUMIF(SUT!$B$8:$B$124,$B85,SUT!$D$8:$D$124) -> 0 | E85: =IF(ISNA(VLOOKUP(B85,SUP!$C$8:$D$86,2,0)),0,VLOOKUP(B85,SUP!$C$8:$D$86,2,0)) -> 0 | F85: =IF(ISNA(HLOOKUP(B85,USE!$E$6:$CE$7,2,0)),0,HLOOKUP(B85,USE!$E$6:$CE$7,2,0)) -> 0 | G85: =E85-F85 -> 0 | H85: =IF(E85,G85/E85,0) -> 0 | K85: H20 | L85: =HLOOKUP($K85,SAM!$B$7:$DB$10,2,0) -> 0.59792235 | M85: =HLOOKUP($K85,SAM!$B$7:$DB$10,3,0) -> 0 | N85: =HLOOKUP($K85,SAM!$B$7:$DB$10,4,0) -> 0.40207765 | O85: =SUM(L85:N85) -> 1 | R85: H20 | S85: H20 | T85: =VLOOKUP(S85,Notes!$B$7:$F$111,5,0) -> Air transport (H20) | U85: =VLOOKUP(S85,Notes!$B$7:$F$111,3,0) -> atrna | V85: =IF(ISNA(VLOOKUP(R85,$B$7:$H$84,7,0)),0,VLOOKUP(R85,$B$7:$H$84,7,0)) -> 0.53332365 | W85: =V85 -> 0.53332365 | X85: =SUT!T86 -> 180.34401 | Y85: =E60 -> 179.48188 | Z85: =Y85-AA85 -> 83.759946 | AA85: =W85*Y85 -> 95.721929 | AB85: =$AA85*L85 -> 57.234281 | AC85: =$AA85*M85 -> 0 | AD85: =$AA85*N85 -> 38.487649
B86: X00 | C86: =VLOOKUP(B86,Notes!$B$7:$F$111,5,0) -> Unallocated products (X00) | D86: =SUMIF(SUT!$B$8:$B$124,$B86,SUT!$D$8:$D$124) -> 0 | E86: =IF(ISNA(VLOOKUP(B86,SUP!$C$8:$D$86,2,0)),0,VLOOKUP(B86,SUP!$C$8:$D$86,2,0)) -> 0 | F86: =IF(ISNA(HLOOKUP(B86,USE!$E$6:$CE$7,2,0)),0,HLOOKUP(B86,USE!$E$6:$CE$7,2,0)) -> 0 | G86: =E86-F86 -> 0 | H86: =IF(E86,G86/E86,0) -> 0 | K86: H31 | L86: =HLOOKUP($K86,SAM!$B$7:$DB$10,2,0) -> 0.59792235 | M86: =HLOOKUP($K86,SAM!$B$7:$DB$10,3,0) -> 0 | N86: =HLOOKUP($K86,SAM!$B$7:$DB$10,4,0) -> 0.40207765 | O86: =SUM(L86:N86) -> 1 | R86: H31 | S86: H31 | T86: =VLOOKUP(S86,Notes!$B$7:$F$111,5,0) -> Services related to transport (H31) | U86: =VLOOKUP(S86,Notes!$B$7:$F$111,3,0) -> atrns | V86: =IF(ISNA(VLOOKUP(R86,$B$7:$H$84,7,0)),0,VLOOKUP(R86,$B$7:$H$84,7,0)) -> 0.63866813 | W86: =V86 -> 0.63866813 | X86: =SUT!T87 -> 32.801446 | Y86: =E61 -> 68.866662 | Z86: =Y86-AA86 -> 24.88372 | AA86: =W86*Y86 -> 43.982942 | AB86: =$AA86*L86 -> 26.298384 | AC86: =$AA86*M86 -> 0 | AD86: =$AA86*N86 -> 17.684558
K87: H32 | L87: =HLOOKUP($K87,SAM!$B$7:$DB$10,2,0) -> 0.59792235 | M87: =HLOOKUP($K87,SAM!$B$7:$DB$10,3,0) -> 0 | N87: =HLOOKUP($K87,SAM!$B$7:$DB$10,4,0) -> 0.40207765 | O87: =SUM(L87:N87) -> 1 | R87: H32 | S87: H32 | T87: =VLOOKUP(S87,Notes!$B$7:$F$111,5,0) -> Postal and courier activities (H32) | U87: =VLOOKUP(S87,Notes!$B$7:$F$111,3,0) -> apost | V87: =IF(ISNA(VLOOKUP(R87,$B$7:$H$84,7,0)),0,VLOOKUP(R87,$B$7:$H$84,7,0)) -> 0.62636219 | W87: =V87 -> 0.62636219 | X87: =SUT!T88 -> 10.230317 | Y87: =E62 -> 15.953011 | Z87: =Y87-AA87 -> 5.9606481 | AA87: =W87*Y87 -> 9.992363 | AB87: =$AA87*L87 -> 5.9746572 | AC87: =$AA87*M87 -> 0 | AD87: =$AA87*N87 -> 4.0177059
K88: I00 | L88: =HLOOKUP($K88,SAM!$B$7:$DB$10,2,0) -> 0.50245285 | M88: =HLOOKUP($K88,SAM!$B$7:$DB$10,3,0) -> 0 | N88: =HLOOKUP($K88,SAM!$B$7:$DB$10,4,0) -> 0.49754715 | O88: =SUM(L88:N88) -> 1 | R88: I00 | S88: I00 | T88: =VLOOKUP(S88,Notes!$B$7:$F$111,5,0) -> Hotels & restaurants (I00) | U88: =VLOOKUP(S88,Notes!$B$7:$F$111,3,0) -> ahotl | V88: =IF(ISNA(VLOOKUP(R88,$B$7:$H$84,7,0)),0,VLOOKUP(R88,$B$7:$H$84,7,0)) -> 0.27276413 | W88: =V88 -> 0.27276413 | X88: =SUT!T89 -> 516.57322 | Y88: =E63 -> 512.41574 | Z88: =Y88-AA88 -> 372.6471 | AA88: =W88*Y88 -> 139.76863 | AB88: =$AA88*L88 -> 70.227149 | AC88: =$AA88*M88 -> 0 | AD88: =$AA88*N88 -> 69.541486
K89: J10 | L89: =HLOOKUP($K89,SAM!$B$7:$DB$10,2,0) -> 0.4104047 | M89: =HLOOKUP($K89,SAM!$B$7:$DB$10,3,0) -> 0 | N89: =HLOOKUP($K89,SAM!$B$7:$DB$10,4,0) -> 0.5895953 | O89: =SUM(L89:N89) -> 1 | R89: J10 | S89: J10 | T89: =VLOOKUP(S89,Notes!$B$7:$F$111,5,0) -> Publishing, video making, programming & broadcasting activities (J10) | U89: =VLOOKUP(S89,Notes!$B$7:$F$111,3,0) -> apubl | V89: =IF(ISNA(VLOOKUP(R89,$B$7:$H$84,7,0)),0,VLOOKUP(R89,$B$7:$H$84,7,0)) -> 0.71682835 | W89: =V89 -> 0.71682835 | X89: =SUT!T90 -> 29.464901 | Y89: =E64 -> 31.662678 | Z89: =Y89-AA89 -> 8.9659725 | AA89: =W89*Y89 -> 22.696705 | AB89: =$AA89*L89 -> 9.3148343 | AC89: =$AA89*M89 -> 0 | AD89: =$AA89*N89 -> 13.381871
K90: J20 | L90: =HLOOKUP($K90,SAM!$B$7:$DB$10,2,0) -> 0.4104047 | M90: =HLOOKUP($K90,SAM!$B$7:$DB$10,3,0) -> 0 | N90: =HLOOKUP($K90,SAM!$B$7:$DB$10,4,0) -> 0.5895953 | O90: =SUM(L90:N90) -> 1 | R90: J20 | S90: J20 | T90: =VLOOKUP(S90,Notes!$B$7:$F$111,5,0) -> Telecommunication (J20) | U90: =VLOOKUP(S90,Notes!$B$7:$F$111,3,0) -> acomm | V90: =IF(ISNA(VLOOKUP(R90,$B$7:$H$84,7,0)),0,VLOOKUP(R90,$B$7:$H$84,7,0)) -> 0.47015673 | W90: =V90 -> 0.47015673 | X90: =SUT!T91 -> 128.09289 | Y90: =E65 -> 189.91353 | Z90: =Y90-AA90 -> 100.62441 | AA90: =W90*Y90 -> 89.289125 | AB90: =$AA90*L90 -> 36.644676 | AC90: =$AA90*M90 -> 0 | AD90: =$AA90*N90 -> 52.644449
K91: J30 | L91: =HLOOKUP($K91,SAM!$B$7:$DB$10,2,0) -> 0.4104047 | M91: =HLOOKUP($K91,SAM!$B$7:$DB$10,3,0) -> 0 | N91: =HLOOKUP($K91,SAM!$B$7:$DB$10,4,0) -> 0.5895953 | O91: =SUM(L91:N91) -> 1 | R91: J30 | S91: J30 | T91: =VLOOKUP(S91,Notes!$B$7:$F$111,5,0) -> Information technology services (J30) | U91: =VLOOKUP(S91,Notes!$B$7:$F$111,3,0) -> ainfo | V91: =IF(ISNA(VLOOKUP(R91,$B$7:$H$84,7,0)),0,VLOOKUP(R91,$B$7:$H$84,7,0)) -> 0.59216837 | W91: =V91 -> 0.59216837 | X91: =SUT!T92 -> 44.222812 | Y91: =E66 -> 37.325804 | Z91: =Y91-AA91 -> 15.222644 | AA91: =W91*Y91 -> 22.10316 | AB91: =$AA91*L91 -> 9.0712407 | AC91: =$AA91*M91 -> 0 | AD91: =$AA91*N91 -> 13.031919
K92: K01 | L92: =HLOOKUP($K92,SAM!$B$7:$DB$10,2,0) -> 0.60717415 | M92: =HLOOKUP($K92,SAM!$B$7:$DB$10,3,0) -> 0 | N92: =HLOOKUP($K92,SAM!$B$7:$DB$10,4,0) -> 0.39282585 | O92: =SUM(L92:N92) -> 1 | R92: K01 | S92: K01 | T92: =VLOOKUP(S92,Notes!$B$7:$F$111,5,0) -> Monetary institutions (K01) | U92: =VLOOKUP(S92,Notes!$B$7:$F$111,3,0) -> abank | V92: =IF(ISNA(VLOOKUP(R92,$B$7:$H$84,7,0)),0,VLOOKUP(R92,$B$7:$H$84,7,0)) -> 0.46601904 | W92: =V92 -> 0.46601904 | X92: =SUT!T93 -> 115.7319 | Y92: =E67 -> 115.7319 | Z92: =Y92-AA92 -> 61.798633 | AA92: =W92*Y92 -> 53.933271 | AB92: =$AA92*L92 -> 32.746888 | AC92: =$AA92*M92 -> 0 | AD92: =$AA92*N92 -> 21.186383
K93: K02 | L93: =HLOOKUP($K93,SAM!$B$7:$DB$10,2,0) -> 0.60717415 | M93: =HLOOKUP($K93,SAM!$B$7:$DB$10,3,0) -> 0 | N93: =HLOOKUP($K93,SAM!$B$7:$DB$10,4,0) -> 0.39282585 | O93: =SUM(L93:N93) -> 1 | R93: K02 | S93: K02 | T93: =VLOOKUP(S93,Notes!$B$7:$F$111,5,0) -> Insurance, reinsurance and pension funding, except compulsory social security (K02) | U93: =VLOOKUP(S93,Notes!$B$7:$F$111,3,0) -> ainsu | V93: =IF(ISNA(VLOOKUP(R93,$B$7:$H$84,7,0)),0,VLOOKUP(R93,$B$7:$H$84,7,0)) -> 0.81756387 | W93: =V93 -> 0.81756387 | X93: =SUT!T94 -> 48.797623 | Y93: =E68 -> 48.797623 | Z93: =Y93-AA93 -> 8.9024496 | AA93: =W93*Y93 -> 39.895174 | AB93: =$AA93*L93 -> 24.223318 | AC93: =$AA93*M93 -> 0 | AD93: =$AA93*N93 -> 15.671855
K94: K03 | L94: =HLOOKUP($K94,SAM!$B$7:$DB$10,2,0) -> 0.60717415 | M94: =HLOOKUP($K94,SAM!$B$7:$DB$10,3,0) -> 0 | N94: =HLOOKUP($K94,SAM!$B$7:$DB$10,4,0) -> 0.39282585 | O94: =SUM(L94:N94) -> 1 | R94: K03 | S94: K03 | T94: =VLOOKUP(S94,Notes!$B$7:$F$111,5,0) -> Other financial services (K03) | U94: =VLOOKUP(S94,Notes!$B$7:$F$111,3,0) -> aofsv | V94: =IF(ISNA(VLOOKUP(R94,$B$7:$H$84,7,0)),0,VLOOKUP(R94,$B$7:$H$84,7,0)) -> 0.68170899 | W94: =V94 -> 0.68170899 | X94: =SUT!T95 -> 155.51155 | Y94: =E69 -> 142.34074 | Z94: =Y94-AA94 -> 45.305779 | AA94: =W94*Y94 -> 97.034963 | AB94: =$AA94*L94 -> 58.917122 | AC94: =$AA94*M94 -> 0 | AD94: =$AA94*N94 -> 38.117842
K95: L01 | L95: =HLOOKUP($K95,SAM!$B$7:$DB$10,2,0) -> 0.18842179 | M95: =HLOOKUP($K95,SAM!$B$7:$DB$10,3,0) -> 0 | N95: =HLOOKUP($K95,SAM!$B$7:$DB$10,4,0) -> 0.81157821 | O95: =SUM(L95:N95) -> 1 | R95: L01 | S95: L01 | T95: =VLOOKUP(S95,Notes!$B$7:$F$111,5,0) -> Rental value of dwellings (L01) | U95: =VLOOKUP(S95,Notes!$B$7:$F$111,3,0) -> arent | V95: =IF(ISNA(VLOOKUP(R95,$B$7:$H$84,7,0)),0,VLOOKUP(R95,$B$7:$H$84,7,0)) -> 1 | W95: =V95 -> 1 | X95: =SUT!T96 -> 414.34402 | Y95: =E70 -> 414.04969 | Z95: =Y95-AA95 -> 0 | AA95: =W95*Y95 -> 414.04969 | AB95: =$AA95*L95 -> 78.015986 | AC95: =$AA95*M95 -> 0 | AD95: =$AA95*N95 -> 336.0337
K96: L09 | L96: =HLOOKUP($K96,SAM!$B$7:$DB$10,2,0) -> 0.18842179 | M96: =HLOOKUP($K96,SAM!$B$7:$DB$10,3,0) -> 0 | N96: =HLOOKUP($K96,SAM!$B$7:$DB$10,4,0) -> 0.81157821 | O96: =SUM(L96:N96) -> 1 | R96: L09 | S96: L09 | T96: =VLOOKUP(S96,Notes!$B$7:$F$111,5,0) -> Other real estate activities (L09) | U96: =VLOOKUP(S96,Notes!$B$7:$F$111,3,0) -> areal | V96: =IF(ISNA(VLOOKUP(R96,$B$7:$H$84,7,0)),0,VLOOKUP(R96,$B$7:$H$84,7,0)) -> 0.88758421 | W96: =V96 -> 0.88758421 | X96: =SUT!T97 -> 188.02978 | Y96: =E71 -> 163.89397 | Z96: =Y96-AA96 -> 18.42427 | AA96: =W96*Y96 -> 145.4697 | AB96: =$AA96*L96 -> 27.409661 | AC96: =$AA96*M96 -> 0 | AD96: =$AA96*N96 -> 118.06004
K97: M01 | L97: =HLOOKUP($K97,SAM!$B$7:$DB$10,2,0) -> 0.54906236 | M97: =HLOOKUP($K97,SAM!$B$7:$DB$10,3,0) -> 0 | N97: =HLOOKUP($K97,SAM!$B$7:$DB$10,4,0) -> 0.45093764 | O97: =SUM(L97:N97) -> 1 | R97: M01 | S97: M01 | T97: =VLOOKUP(S97,Notes!$B$7:$F$111,5,0) -> Legal, accounting management & head office activities (M01) | U97: =VLOOKUP(S97,Notes!$B$7:$F$111,3,0) -> alegl | V97: =IF(ISNA(VLOOKUP(R97,$B$7:$H$84,7,0)),0,VLOOKUP(R97,$B$7:$H$84,7,0)) -> 0.84616728 | W97: =V97 -> 0.84616728 | X97: =SUT!T98 -> 60.681638 | Y97: =E72 -> 55.581231 | Z97: =Y97-AA97 -> 8.5502122 | AA97: =W97*Y97 -> 47.031019 | AB97: =$AA97*L97 -> 25.822962 | AC97: =$AA97*M97 -> 0 | AD97: =$AA97*N97 -> 21.208057
K98: M02 | L98: =HLOOKUP($K98,SAM!$B$7:$DB$10,2,0) -> 0.54906236 | M98: =HLOOKUP($K98,SAM!$B$7:$DB$10,3,0) -> 0 | N98: =HLOOKUP($K98,SAM!$B$7:$DB$10,4,0) -> 0.45093764 | O98: =SUM(L98:N98) -> 1 | R98: M02 | S98: M02 | T98: =VLOOKUP(S98,Notes!$B$7:$F$111,5,0) -> Architectural and engineering activities (M02) | U98: =VLOOKUP(S98,Notes!$B$7:$F$111,3,0) -> aenga | V98: =IF(ISNA(VLOOKUP(R98,$B$7:$H$84,7,0)),0,VLOOKUP(R98,$B$7:$H$84,7,0)) -> 0.77425173 | W98: =V98 -> 0.77425173 | X98: =SUT!T99 -> 19.735374 | Y98: =E73 -> 18.773075 | Z98: =Y98-AA98 -> 4.2379892 | AA98: =W98*Y98 -> 14.535086 | AB98: =$AA98*L98 -> 7.9806685 | AC98: =$AA98*M98 -> 0 | AD98: =$AA98*N98 -> 6.5544172
... K109: T00 | L109: =HLOOKUP($K109,SAM!$B$7:$DB$10,2,0) -> 0.87667501 | M109: =HLOOKUP($K109,SAM!$B$7:$DB$10,3,0) -> 0 | N109: =HLOOKUP($K109,SAM!$B$7:$DB$10,4,0) -> 0.12332499 | O109: =SUM(L109:N109) -> 1 | R109: T00 | S109: T00 | T109: =VLOOKUP(S109,Notes!$B$7:$F$111,5,0) -> Domestic services (T00) | U109: =VLOOKUP(S109,Notes!$B$7:$F$111,3,0) -> adsrv | V109: =IF(ISNA(VLOOKUP(R109,$B$7:$H$84,7,0)),0,VLOOKUP(R109,$B$7:$H$84,7,0)) -> 0.97663132 | W109: =V109 -> 0.97663132 | X109: =SUT!T110 -> 25.436762 | Y109: =E84 -> 25.436762 | Z109: =Y109-AA109 -> 0.59442349 | AA109: =W109*Y109 -> 24.842339 | AB109: =$AA109*L109 -> 21.778657 | AC109: =$AA109*M109 -> 0 | AD109: =$AA109*N109 -> 3.0636812
K110: V00 | L110: =HLOOKUP($K110,SAM!$B$7:$DB$10,2,0) -> 0.87667501 | M110: =HLOOKUP($K110,SAM!$B$7:$DB$10,3,0) -> 0 | N110: =HLOOKUP($K110,SAM!$B$7:$DB$10,4,0) -> 0.12332499 | O110: =SUM(L110:N110) -> 1 | R110: V00 | S110: V00 | T110: =VLOOKUP(S110,Notes!$B$7:$F$111,5,0) -> Travel debits & credits (V00) | U110: =VLOOKUP(S110,Notes!$B$7:$F$111,3,0) -> atrdc | V110: =IF(ISNA(VLOOKUP(R110,$B$7:$H$84,7,0)),0,VLOOKUP(R110,$B$7:$H$84,7,0)) -> 0 | W110: 1 | X110: =SUT!T111 -> 0 | Y110: =E85 -> 0 | Z110: =Y110-AA110 -> 0 | AA110: =W110*Y110 -> 0 | AB110: =$AA110*L110 -> 0 | AC110: =$AA110*M110 -> 0 | AD110: =$AA110*N110 -> 0
K111: X00 | L111: =HLOOKUP($K111,SAM!$B$7:$DB$10,2,0) -> 0.87667501 | M111: =HLOOKUP($K111,SAM!$B$7:$DB$10,3,0) -> 0 | N111: =HLOOKUP($K111,SAM!$B$7:$DB$10,4,0) -> 0.12332499 | O111: =SUM(L111:N111) -> 1 | R111: X00 | S111: X00 | T111: =VLOOKUP(S111,Notes!$B$7:$F$111,5,0) -> Unallocated products (X00) | U111: =VLOOKUP(S111,Notes!$B$7:$F$111,3,0) -> 0 | V111: =IF(ISNA(VLOOKUP(R111,$B$7:$H$84,7,0)),0,VLOOKUP(R111,$B$7:$H$84,7,0)) -> 0 | W111: =V111 -> 0 | X111: =SUT!T112 -> 0 | Y111: =E86 -> 0 | Z111: =Y111-AA111 -> 0 | AA111: =W111*Y111 -> 0 | AB111: =$AA111*L111 -> 0 | AC111: =$AA111*M111 -> 0 | AD111: =$AA111*N111 -> 0

Sheet SUT
A1: Table 1: Summary Supply and Use Table: Rwanda 2017, RWF billions
A2: Billions of FRW
B5: Original SUT data | Q5: Mapped to SAM commodity accounts | AH5: GDP components | AP5: Margins
D6: Domestic Production | E6: Imports of Goods & Services | F6: Margins | G6: Taxes on products less Subsidies on products | H6: Total Supply | I6: Total Demand | J6: Intermediate Demand | K6: Household Final Consumption Expenditure | L6: General Government and NGO Final Consumption Expenditure | M6: Gross Capital Formation | N6: Exports of Goods & Services | T6: Domestic Production | U6: Imports of Goods & Services | V6: Margins | W6: Taxes on products less Subsidies on products | X6: Total Supply | Y6: Total Demand | Z6: Intermediate Demand | AA6: Household Final Consumption Expenditure | AB6: General Government and NGO Final Consumption Expenditure | AC6: Gross Capital Formation | AD6: Exports of Goods & Services | AE6: Diff. | AH6: SUT | AI6: =SUM(AI8:AI112) -> 5438.5455 | AJ6: =SUM(AJ8:AJ112) -> 1429.3238 | AK6: =SUM(AK8:AK112) -> 1797.2623 | AQ6: Collections | AT6: Disbursement
D7: 11646.996 | E7: 2550.3991 | F7: 5.7065463e-14 | G7: 653.53732 | H7: 14850.932 | I7: 14850.932 | J7: 4606.299 | K7: 5438.5455 | L7: 1429.3238 | M7: 1797.2623 | N7: 1579.5017 | T7: =SUM(T8:T112) -> 11646.996 | U7: =SUM(U8:U112) -> 2550.3991 | V7: =SUM(V8:V112) -> 3.9812598e-13 | W7: =SUM(W8:W112) -> 653.53732 | X7: =SUM(X8:X112) -> 14850.932 | Y7: =SUM(Y8:Y112) -> 14850.932 | Z7: =SUM(Z8:Z112) -> 4606.299 | AA7: =SUM(AA8:AA112) -> 5438.5455 | ... AE7: =SUM(AE8:AE112) -> -9.8178106e-12 | AI7: HHD | AJ7: GOV | AK7: S-I | AL7: EXP | AM7: IMP | AQ7: Values | AR7: Base | AS7: Rate | AT7: Values | AU7: Share
B8: A11 | C8: Cereals | D8: 206.67601 | E8: 103.65847 | F8: 3.2250672 | G8: 11.379997 | H8: 324.93955 | I8: 324.93955 | J8: 180.68808 | K8: 122.41145 | L8: 0 | M8: 5.5896385 | N8: 16.250381 | Q8: A111 | R8: =VLOOKUP(Q8,Notes!$B$7:$F$111,5,0) -> Sorghum (A111) | S8: =VLOOKUP(Q8,Notes!$B$7:$F$111,4,0) -> csorg | T8: =SUMIF($B$8:$B$124,$Q8,D$8:D$124) -> 45.171235 | U8: =SUMIF($B$8:$B$124,$Q8,E$8:E$124) -> 1.0534168 | V8: =SUMIF($B$8:$B$124,$Q8,F$8:F$124) -> 0.53481019 | W8: =SUMIF($B$8:$B$124,$Q8,G$8:G$124) -> 0.015335133 | X8: =SUM(T8:W8) -> 46.774797 | Y8: =SUM(Z8:AD8) -> 47.859766 | Z8: =SUMIF($B$8:$B$124,$Q8,J$8:J$124) -> 40.486464 | AA8: =SUMIF($B$8:$B$124,$Q8,K$8:K$124) -> 5.6315802 | AB8: =SUMIF($B$8:$B$124,$Q8,L$8:L$124) -> 0 | AC8: =SUMIF($B$8:$B$124,$Q8,M$8:M$124) -> 0.16557445 | AD8: =SUMIF($B$8:$B$124,$Q8,N$8:N$124) -> 1.5761482 | AE8: =X8-Y8 -> -1.0849695 | AH8: =S8 -> csorg | AI8: =AA8 -> 5.6315802 | AJ8: =AB8 -> 0 | AK8: =AC8 -> 0.16557445 | AL8: =AD8 -> 1.5761482 | AM8: =U8 -> 1.0534168 | AP8: csorg | AQ8: =IF(V8>=0,V8,0) -> 0.53481019 | AR8: =Z8+AA8+AB8+AC8+AD8 -> 47.859766 | AS8: =IF(AR8,AQ8/AR8,0) -> 0.011174526 | AT8: =IF(V8<0,-V8,0) -> 0 | AU8: =AT8/SUM($AT$8:$AT$112) -> 0
B9: A111 | C9: Sorghum | D9: 45.171235 | E9: 1.0534168 | F9: 0.53481019 | G9: 0.015335133 | H9: 49.271476 | I9: 49.271476 | J9: 40.486464 | K9: 5.6315802 | L9: 0 | M9: 0.16557445 | N9: 1.5761482 | Q9: A112 | R9: =VLOOKUP(Q9,Notes!$B$7:$F$111,5,0) -> Maize (A112) | S9: =VLOOKUP(Q9,Notes!$B$7:$F$111,4,0) -> cmaiz | T9: =SUMIF($B$8:$B$124,$Q9,D$8:D$124) -> 98.080338 | U9: =SUMIF($B$8:$B$124,$Q9,E$8:E$124) -> 25.349828 | V9: =SUMIF($B$8:$B$124,$Q9,F$8:F$124) -> 1.1639048 | W9: =SUMIF($B$8:$B$124,$Q9,G$8:G$124) -> 0.96642458 | X9: =SUM(T9:W9) -> 125.5605 | Y9: =SUM(Z9:AD9) -> 130.73947 | Z9: =SUMIF($B$8:$B$124,$Q9,J$8:J$124) -> 75.765192 | AA9: =SUMIF($B$8:$B$124,$Q9,K$8:K$124) -> 42.0081 | AB9: =SUMIF($B$8:$B$124,$Q9,L$8:L$124) -> 0 | AC9: =SUMIF($B$8:$B$124,$Q9,M$8:M$124) -> 3.5237991 | AD9: =SUMIF($B$8:$B$124,$Q9,N$8:N$124) -> 9.4423747 | AE9: =X9-Y9 -> -5.1789696 | AH9: =S9 -> cmaiz | AI9: =AA9 -> 42.0081 | AJ9: =AB9 -> 0 | AK9: =AC9 -> 3.5237991 | AL9: =AD9 -> 9.4423747 | AM9: =U9 -> 25.349828 | AP9: cmaiz | AQ9: =IF(V9>=0,V9,0) -> 1.1639048 | AR9: =Z9+AA9+AB9+AC9+AD9 -> 130.73947 | AS9: =IF(AR9,AQ9/AR9,0) -> 0.0089024745 | AT9: =IF(V9<0,-V9,0) -> 0 | AU9: =AT9/SUM($AT$8:$AT$112) -> 0
B10: A112 | C10: Maize | D10: 98.080338 | E10: 25.349828 | F10: 1.1639048 | G10: 0.96642458 | H10: 128.32741 | I10: 128.32741 | J10: 75.765192 | K10: 42.0081 | L10: 0 | M10: 3.5237991 | N10: 9.4423747 | Q10: A113 | R10: =VLOOKUP(Q10,Notes!$B$7:$F$111,5,0) -> Wheat (A113) | S10: =VLOOKUP(Q10,Notes!$B$7:$F$111,4,0) -> cwhea | T10: =SUMIF($B$8:$B$124,$Q10,D$8:D$124) -> 3.2529609 | U10: =SUMIF($B$8:$B$124,$Q10,E$8:E$124) -> 54.390816 | V10: =SUMIF($B$8:$B$124,$Q10,F$8:F$124) -> 0.57478968 | W10: =SUMIF($B$8:$B$124,$Q10,G$8:G$124) -> 0.78274881 | X10: =SUM(T10:W10) -> 59.001316 | Y10: =SUM(Z10:AD10) -> 50.096186 | Z10: =SUMIF($B$8:$B$124,$Q10,J$8:J$124) -> 45.929382 | AA10: =SUMIF($B$8:$B$124,$Q10,K$8:K$124) -> 0.73246533 | AB10: =SUMIF($B$8:$B$124,$Q10,L$8:L$124) -> 0 | AC10: =SUMIF($B$8:$B$124,$Q10,M$8:M$124) -> 3.1547411 | AD10: =SUMIF($B$8:$B$124,$Q10,N$8:N$124) -> 0.27959753 | AE10: =X10-Y10 -> 8.9051294 | AH10: =S10 -> cwhea | AI10: =AA10 -> 0.73246533 | AJ10: =AB10 -> 0 | AK10: =AC10 -> 3.1547411 | AL10: =AD10 -> 0.27959753 | AM10: =U10 -> 54.390816 | AP10: cwhea | AQ10: =IF(V10>=0,V10,0) -> 0.57478968 | AR10: =Z10+AA10+AB10+AC10+AD10 -> 50.096186 | AS10: =IF(AR10,AQ10/AR10,0) -> 0.011473721 | AT10: =IF(V10<0,-V10,0) -> 0 | AU10: =AT10/SUM($AT$8:$AT$112) -> 0
B11: A113 | C11: Wheat | D11: 3.2529609 | E11: 54.390816 | F11: 0.57478968 | G11: 0.78274881 | H11: 52.899516 | I11: 52.899516 | J11: 45.929382 | K11: 0.73246533 | L11: 0 | M11: 3.1547411 | N11: 0.27959753 | Q11: A116 | R11: =VLOOKUP(Q11,Notes!$B$7:$F$111,5,0) -> Paddy & husked rice (A116) | S11: =VLOOKUP(Q11,Notes!$B$7:$F$111,4,0) -> crice | T11: =SUMIF($B$8:$B$124,$Q11,D$8:D$124) -> 59.880657 | U11: =SUMIF($B$8:$B$124,$Q11,E$8:E$124) -> 17.6277 | V11: =SUMIF($B$8:$B$124,$Q11,F$8:F$124) -> 0.89623158 | W11: =SUMIF($B$8:$B$124,$Q11,G$8:G$124) -> 9.5094852 | X11: =SUM(T11:W11) -> 87.914073 | Y11: =SUM(Z11:AD11) -> 91.26895 | Z11: =SUMIF($B$8:$B$124,$Q11,J$8:J$124) -> 13.860456 | AA11: =SUMIF($B$8:$B$124,$Q11,K$8:K$124) -> 73.930779 | AB11: =SUMIF($B$8:$B$124,$Q11,L$8:L$124) -> 0 | AC11: =SUMIF($B$8:$B$124,$Q11,M$8:M$124) -> -1.2608086 | AD11: =SUMIF($B$8:$B$124,$Q11,N$8:N$124) -> 4.7385243 | AE11: =X11-Y11 -> -3.3548766 | AH11: =S11 -> crice | AI11: =AA11 -> 73.930779 | AJ11: =AB11 -> 0 | AK11: =AC11 -> -1.2608086 | AL11: =AD11 -> 4.7385243 | AM11: =U11 -> 17.6277 | AP11: crice | AQ11: =IF(V11>=0,V11,0) -> 0.89623158 | AR11: =Z11+AA11+AB11+AC11+AD11 -> 91.26895 | AS11: =IF(AR11,AQ11/AR11,0) -> 0.0098196767 | AT11: =IF(V11<0,-V11,0) -> 0 | AU11: =AT11/SUM($AT$8:$AT$112) -> 0
B12: A116 | C12: Paddy & husked rice | D12: 59.880657 | E12: 17.6277 | F12: 0.89623158 | G12: 9.5094852 | H12: 89.341082 | I12: 89.341082 | J12: 13.860456 | K12: 73.930779 | L12: 0 | M12: -1.2608086 | N12: 4.7385243 | Q12: A119 | R12: =VLOOKUP(Q12,Notes!$B$7:$F$111,5,0) -> Other cereals (A119) | S12: =VLOOKUP(Q12,Notes!$B$7:$F$111,4,0) -> cocer | T12: =SUMIF($B$8:$B$124,$Q12,D$8:D$124) -> 0.29082038 | U12: =SUMIF($B$8:$B$124,$Q12,E$8:E$124) -> 5.2367139 | V12: =SUMIF($B$8:$B$124,$Q12,F$8:F$124) -> 0.055331028 | W12: =SUMIF($B$8:$B$124,$Q12,G$8:G$124) -> 0.10600297 | X12: =SUM(T12:W12) -> 5.6888683 | Y12: =SUM(Z12:AD12) -> 4.975182 | Z12: =SUMIF($B$8:$B$124,$Q12,J$8:J$124) -> 4.6465876 | AA12: =SUMIF($B$8:$B$124,$Q12,K$8:K$124) -> 0.1085258 | AB12: =SUMIF($B$8:$B$124,$Q12,L$8:L$124) -> 0 | AC12: =SUMIF($B$8:$B$124,$Q12,M$8:M$124) -> 0.0063324694 | AD12: =SUMIF($B$8:$B$124,$Q12,N$8:N$124) -> 0.21373611 | AE12: =X12-Y12 -> 0.7136863 | AH12: =S12 -> cocer | AI12: =AA12 -> 0.1085258 | AJ12: =AB12 -> 0 | AK12: =AC12 -> 0.0063324694 | AL12: =AD12 -> 0.21373611 | AM12: =U12 -> 5.2367139 | AP12: cocer | AQ12: =IF(V12>=0,V12,0) -> 0.055331028 | AR12: =Z12+AA12+AB12+AC12+AD12 -> 4.975182 | AS12: =IF(AR12,AQ12/AR12,0) -> 0.011121408 | AT12: =IF(V12<0,-V12,0) -> 0 | AU12: =AT12/SUM($AT$8:$AT$112) -> 0
B13: A119 | C13: Other cereals | D13: 0.29082038 | E13: 5.2367139 | F13: 0.055331028 | G13: 0.10600297 | H13: 5.1000661 | I13: 5.1000661 | J13: 4.6465876 | K13: 0.1085258 | L13: 0 | M13: 0.0063324694 | N13: 0.21373611 | Q13: A121 | R13: =VLOOKUP(Q13,Notes!$B$7:$F$111,5,0) -> Irish potatoes (A121) | S13: =VLOOKUP(Q13,Notes!$B$7:$F$111,4,0) -> cipot | T13: =SUMIF($B$8:$B$124,$Q13,D$8:D$124) -> 170.04725 | U13: =SUMIF($B$8:$B$124,$Q13,E$8:E$124) -> 4.7535362 | V13: =SUMIF($B$8:$B$124,$Q13,F$8:F$124) -> 9.7338638 | W13: =SUMIF($B$8:$B$124,$Q13,G$8:G$124) -> 0.33687037 | X13: =SUM(T13:W13) -> 184.87153 | Y13: =SUM(Z13:AD13) -> 189.46179 | Z13: =SUMIF($B$8:$B$124,$Q13,J$8:J$124) -> 5.4757388 | AA13: =SUMIF($B$8:$B$124,$Q13,K$8:K$124) -> 178.83364 | AB13: =SUMIF($B$8:$B$124,$Q13,L$8:L$124) -> 0 | AC13: =SUMIF($B$8:$B$124,$Q13,M$8:M$124) -> -0.036884979 | AD13: =SUMIF($B$8:$B$124,$Q13,N$8:N$124) -> 5.1893028 | AE13: =X13-Y13 -> -4.5902676 | AH13: =S13 -> cipot | AI13: =AA13 -> 178.83364 | AJ13: =AB13 -> 0 | AK13: =AC13 -> -0.036884979 | AL13: =AD13 -> 5.1893028 | AM13: =U13 -> 4.7535362 | AP13: cipot | AQ13: =IF(V13>=0,V13,0) -> 9.7338638 | AR13: =Z13+AA13+AB13+AC13+AD13 -> 189.46179 | AS13: =IF(AR13,AQ13/AR13,0) -> 0.051376394 | AT13: =IF(V13<0,-V13,0) -> 0 | AU13: =AT13/SUM($AT$8:$AT$112) -> 0
B14: A12 | C14: Roots and Tubers | D14: 468.14634 | E14: 15.850959 | F14: 23.540987 | G14: 0.65257767 | H14: 508.19086 | I14: 508.19086 | J14: 82.163087 | K14: 420.6478 | L14: 0 | M14: -0.026104416 | N14: 5.4060781 | Q14: A122 | R14: =VLOOKUP(Q14,Notes!$B$7:$F$111,5,0) -> Sweet potatoes (A122) | S14: =VLOOKUP(Q14,Notes!$B$7:$F$111,4,0) -> cspot | T14: =SUMIF($B$8:$B$124,$Q14,D$8:D$124) -> 151.37845 | U14: =SUMIF($B$8:$B$124,$Q14,E$8:E$124) -> 0.52079596 | V14: =SUMIF($B$8:$B$124,$Q14,F$8:F$124) -> 4.7710435 | W14: =SUMIF($B$8:$B$124,$Q14,G$8:G$124) -> 0.13561896 | X14: =SUM(T14:W14) -> 156.80591 | Y14: =SUM(Z14:AD14) -> 160.91738 | Z14: =SUMIF($B$8:$B$124,$Q14,J$8:J$124) -> 5.1854497 | AA14: =SUMIF($B$8:$B$124,$Q14,K$8:K$124) -> 155.63862 | AB14: =SUMIF($B$8:$B$124,$Q14,L$8:L$124) -> 0 | AC14: =SUMIF($B$8:$B$124,$Q14,M$8:M$124) -> 0.012416058 | AD14: =SUMIF($B$8:$B$124,$Q14,N$8:N$124) -> 0.080892994 | AE14: =X14-Y14 -> -4.1114764 | AH14: =S14 -> cspot | AI14: =AA14 -> 155.63862 | AJ14: =AB14 -> 0 | AK14: =AC14 -> 0.012416058 | AL14: =AD14 -> 0.080892994 | AM14: =U14 -> 0.52079596 | AP14: cspot | AQ14: =IF(V14>=0,V14,0) -> 4.7710435 | AR14: =Z14+AA14+AB14+AC14+AD14 -> 160.91738 | AS14: =IF(AR14,AQ14/AR14,0) -> 0.029649025 | AT14: =IF(V14<0,-V14,0) -> 0 | AU14: =AT14/SUM($AT$8:$AT$112) -> 0
B15: A121 | C15: Irish potatoes | D15: 170.04725 | E15: 4.7535362 | F15: 9.7338638 | G15: 0.33687037 | H15: 184.77345 | I15: 184.77345 | J15: 5.4757388 | K15: 178.83364 | L15: 0 | M15: -0.036884979 | N15: 5.1893028 | Q15: A123 | R15: =VLOOKUP(Q15,Notes!$B$7:$F$111,5,0) -> Cassava (A123) | S15: =VLOOKUP(Q15,Notes!$B$7:$F$111,4,0) -> ccass | T15: =SUMIF($B$8:$B$124,$Q15,D$8:D$124) -> 125.40484 | U15: =SUMIF($B$8:$B$124,$Q15,E$8:E$124) -> 10.525037 | V15: =SUMIF($B$8:$B$124,$Q15,F$8:F$124) -> 8.4637205 | W15: =SUMIF($B$8:$B$124,$Q15,G$8:G$124) -> 0.16366774 | X15: =SUM(T15:W15) -> 144.55726 | Y15: =SUM(Z15:AD15) -> 135.23497 | Z15: =SUMIF($B$8:$B$124,$Q15,J$8:J$124) -> 70.94551 | AA15: =SUMIF($B$8:$B$124,$Q15,K$8:K$124) -> 64.19625 | AB15: =SUMIF($B$8:$B$124,$Q15,L$8:L$124) -> 0 | AC15: =SUMIF($B$8:$B$124,$Q15,M$8:M$124) -> -0.0016354954 | AD15: =SUMIF($B$8:$B$124,$Q15,N$8:N$124) -> 0.094846383 | AE15: =X15-Y15 -> 9.322291 | AH15: =S15 -> ccass | AI15: =AA15 -> 64.19625 | AJ15: =AB15 -> 0 | AK15: =AC15 -> -0.0016354954 | AL15: =AD15 -> 0.094846383 | AM15: =U15 -> 10.525037 | AP15: ccass | AQ15: =IF(V15>=0,V15,0) -> 8.4637205 | AR15: =Z15+AA15+AB15+AC15+AD15 -> 135.23497 | AS15: =IF(AR15,AQ15/AR15,0) -> 0.062585295 | AT15: =IF(V15<0,-V15,0) -> 0 | AU15: =AT15/SUM($AT$8:$AT$112) -> 0
B16: A122 | C16: Sweet potatoes | D16: 151.37845 | E16: 0.52079596 | F16: 4.7710435 | G16: 0.13561896 | H16: 157.24224 | I16: 157.24224 | J16: 5.1854497 | K16: 155.63862 | L16: 0 | M16: 0.012416058 | N16: 0.080892994 | Q16: A129 | R16: =VLOOKUP(Q16,Notes!$B$7:$F$111,5,0) -> Other roots & tubers (A129) | S16: =VLOOKUP(Q16,Notes!$B$7:$F$111,4,0) -> croot | T16: =SUMIF($B$8:$B$124,$Q16,D$8:D$124) -> 21.315797 | U16: =SUMIF($B$8:$B$124,$Q16,E$8:E$124) -> 0.051590165 | V16: =SUMIF($B$8:$B$124,$Q16,F$8:F$124) -> 0.57235904 | W16: =SUMIF($B$8:$B$124,$Q16,G$8:G$124) -> 0.016420609 | X16: =SUM(T16:W16) -> 21.956167 | Y16: =SUM(Z16:AD16) -> 22.576714 | Z16: =SUMIF($B$8:$B$124,$Q16,J$8:J$124) -> 0.55638908 | AA16: =SUMIF($B$8:$B$124,$Q16,K$8:K$124) -> 21.979289 | AB16: =SUMIF($B$8:$B$124,$Q16,L$8:L$124) -> 0 | AC16: =SUMIF($B$8:$B$124,$Q16,M$8:M$124) -> 0 | AD16: =SUMIF($B$8:$B$124,$Q16,N$8:N$124) -> 0.041035951 | AE16: =X16-Y16 -> -0.620547 | AH16: =S16 -> croot | AI16: =AA16 -> 21.979289 | AJ16: =AB16 -> 0 | AK16: =AC16 -> 0 | AL16: =AD16 -> 0.041035951 | AM16: =U16 -> 0.051590165 | AP16: croot | AQ16: =IF(V16>=0,V16,0) -> 0.57235904 | AR16: =Z16+AA16+AB16+AC16+AD16 -> 22.576714 | AS16: =IF(AR16,AQ16/AR16,0) -> 0.025351743 | AT16: =IF(V16<0,-V16,0) -> 0 | AU16: =AT16/SUM($AT$8:$AT$112) -> 0
B17: A123 | C17: Cassava | D17: 125.40484 | E17: 10.525037 | F17: 8.4637205 | G17: 0.16366774 | H17: 144.14637 | I17: 144.14637 | J17: 70.94551 | K17: 64.19625 | L17: 0 | M17: -0.0016354954 | N17: 0.094846383 | Q17: A131 | R17: =VLOOKUP(Q17,Notes!$B$7:$F$111,5,0) -> Dried beans (A131) | S17: =VLOOKUP(Q17,Notes!$B$7:$F$111,4,0) -> cbean | T17: =SUMIF($B$8:$B$124,$Q17,D$8:D$124) -> 225.63873 | U17: =SUMIF($B$8:$B$124,$Q17,E$8:E$124) -> 1.6038528 | V17: =SUMIF($B$8:$B$124,$Q17,F$8:F$124) -> 9.6342064 | W17: =SUMIF($B$8:$B$124,$Q17,G$8:G$124) -> 0.28498487 | X17: =SUM(T17:W17) -> 237.16177 | Y17: =SUM(Z17:AD17) -> 238.03224 | Z17: =SUMIF($B$8:$B$124,$Q17,J$8:J$124) -> 5.2374845 | AA17: =SUMIF($B$8:$B$124,$Q17,K$8:K$124) -> 220.82578 | AB17: =SUMIF($B$8:$B$124,$Q17,L$8:L$124) -> 0 | AC17: =SUMIF($B$8:$B$124,$Q17,M$8:M$124) -> -0.58992581 | AD17: =SUMIF($B$8:$B$124,$Q17,N$8:N$124) -> 12.558905 | AE17: =X17-Y17 -> -0.87046606 | AH17: =S17 -> cbean | AI17: =AA17 -> 220.82578 | AJ17: =AB17 -> 0 | AK17: =AC17 -> -0.58992581 | AL17: =AD17 -> 12.558905 | AM17: =U17 -> 1.6038528 | AP17: cbean | AQ17: =IF(V17>=0,V17,0) -> 9.6342064 | AR17: =Z17+AA17+AB17+AC17+AD17 -> 238.03224 | AS17: =IF(AR17,AQ17/AR17,0) -> 0.040474376 | AT17: =IF(V17<0,-V17,0) -> 0 | AU17: =AT17/SUM($AT$8:$AT$112) -> 0
B18: A129 | C18: Other roots & tubers | D18: 21.315797 | E18: 0.051590165 | F18: 0.57235904 | G18: 0.016420609 | H18: 22.028805 | I18: 22.028805 | J18: 0.55638908 | K18: 21.979289 | L18: 0 | M18: 0 | N18: 0.041035951 | Q18: A132 | R18: =VLOOKUP(Q18,Notes!$B$7:$F$111,5,0) -> Peas & other legumes (A132) | S18: =VLOOKUP(Q18,Notes!$B$7:$F$111,4,0) -> cpeas | T18: =SUMIF($B$8:$B$124,$Q18,D$8:D$124) -> 22.063138 | U18: =SUMIF($B$8:$B$124,$Q18,E$8:E$124) -> 0.067616629 | V18: =SUMIF($B$8:$B$124,$Q18,F$8:F$124) -> 1.2847744 | W18: =SUMIF($B$8:$B$124,$Q18,G$8:G$124) -> 0.0042245513 | X18: =SUM(T18:W18) -> 23.419754 | Y18: =SUM(Z18:AD18) -> 22.599405 | Z18: =SUMIF($B$8:$B$124,$Q18,J$8:J$124) -> 4.2075146 | AA18: =SUMIF($B$8:$B$124,$Q18,K$8:K$124) -> 18.015888 | AB18: =SUMIF($B$8:$B$124,$Q18,L$8:L$124) -> 0 | AC18: =SUMIF($B$8:$B$124,$Q18,M$8:M$124) -> -0.00095660525 | AD18: =SUMIF($B$8:$B$124,$Q18,N$8:N$124) -> 0.37695823 | AE18: =X18-Y18 -> 0.82034936 | AH18: =S18 -> cpeas | AI18: =AA18 -> 18.015888 | AJ18: =AB18 -> 0 | AK18: =AC18 -> -0.00095660525 | AL18: =AD18 -> 0.37695823 | AM18: =U18 -> 0.067616629 | AP18: cpeas | AQ18: =IF(V18>=0,V18,0) -> 1.2847744 | AR18: =Z18+AA18+AB18+AC18+AD18 -> 22.599405 | AS18: =IF(AR18,AQ18/AR18,0) -> 0.056849922 | AT18: =IF(V18<0,-V18,0) -> 0 | AU18: =AT18/SUM($AT$8:$AT$112) -> 0
B19: A13 | C19: Vegetables | D19: 396.78988 | E19: 3.7465437 | F19: 19.707512 | G19: 0.55965767 | H19: 420.80359 | I19: 420.80359 | J19: 13.580766 | K19: 391.80944 | L19: 0 | M19: -0.64635066 | N19: 16.059738 | Q19: A139 | R19: =VLOOKUP(Q19,Notes!$B$7:$F$111,5,0) -> Other vegetables (A139) | S19: =VLOOKUP(Q19,Notes!$B$7:$F$111,4,0) -> cvege | T19: =SUMIF($B$8:$B$124,$Q19,D$8:D$124) -> 149.08801 | U19: =SUMIF($B$8:$B$124,$Q19,E$8:E$124) -> 2.0750742 | V19: =SUMIF($B$8:$B$124,$Q19,F$8:F$124) -> 8.7885316 | W19: =SUMIF($B$8:$B$124,$Q19,G$8:G$124) -> 0.27044824 | X19: =SUM(T19:W19) -> 160.22206 | Y19: =SUM(Z19:AD19) -> 160.17195 | Z19: =SUMIF($B$8:$B$124,$Q19,J$8:J$124) -> 4.1357666 | AA19: =SUMIF($B$8:$B$124,$Q19,K$8:K$124) -> 152.96777 | AB19: =SUMIF($B$8:$B$124,$Q19,L$8:L$124) -> 0 | AC19: =SUMIF($B$8:$B$124,$Q19,M$8:M$124) -> -0.055468251 | AD19: =SUMIF($B$8:$B$124,$Q19,N$8:N$124) -> 3.1238748 | AE19: =X19-Y19 -> 0.050116701 | AH19: =S19 -> cvege | AI19: =AA19 -> 152.96777 | AJ19: =AB19 -> 0 | AK19: =AC19 -> -0.055468251 | AL19: =AD19 -> 3.1238748 | AM19: =U19 -> 2.0750742 | AP19: cvege | AQ19: =IF(V19>=0,V19,0) -> 8.7885316 | AR19: =Z19+AA19+AB19+AC19+AD19 -> 160.17195 | AS19: =IF(AR19,AQ19/AR19,0) -> 0.054869356 | AT19: =IF(V19<0,-V19,0) -> 0 | AU19: =AT19/SUM($AT$8:$AT$112) -> 0
... B74: C42 | C74: Printing and reproduction of recorded media | D74: 26.268771 | E74: 7.2274988 | F74: 3.5542838 | G74: 1.2639624 | H74: 38.314516 | I74: 38.314516 | J74: 31.648694 | K74: 3.7195352 | L74: 0 | M74: 0.21511004 | N74: 2.731176 | Q74: C82 | R74: =VLOOKUP(Q74,Notes!$B$7:$F$111,5,0) -> Other manufacturing (C82) | S74: =VLOOKUP(Q74,Notes!$B$7:$F$111,4,0) -> coman | T74: =SUMIF($B$8:$B$124,$Q74,D$8:D$124) -> 45.091143 | U74: =SUMIF($B$8:$B$124,$Q74,E$8:E$124) -> 50.977158 | V74: =SUMIF($B$8:$B$124,$Q74,F$8:F$124) -> 16.399929 | W74: =SUMIF($B$8:$B$124,$Q74,G$8:G$124) -> 5.7700858 | X74: =SUM(T74:W74) -> 118.23832 | Y74: =SUM(Z74:AD74) -> 118.23832 | Z74: =SUMIF($B$8:$B$124,$Q74,J$8:J$124) -> 16.931339 | AA74: =SUMIF($B$8:$B$124,$Q74,K$8:K$124) -> 47.927441 | AB74: =SUMIF($B$8:$B$124,$Q74,L$8:L$124) -> 0 | AC74: =SUMIF($B$8:$B$124,$Q74,M$8:M$124) -> 31.562144 | AD74: =SUMIF($B$8:$B$124,$Q74,N$8:N$124) -> 21.81739 | AE74: =X74-Y74 -> 0 | AH74: =S74 -> coman | AI74: =AA74 -> 47.927441 | AJ74: =AB74 -> 0 | AK74: =AC74 -> 31.562144 | AL74: =AD74 -> 21.81739 | AM74: =U74 -> 50.977158 | AP74: coman | AQ74: =IF(V74>=0,V74,0) -> 16.399929 | AR74: =Z74+AA74+AB74+AC74+AD74 -> 118.23832 | AS74: =IF(AR74,AQ74/AR74,0) -> 0.13870232 | AT74: =IF(V74<0,-V74,0) -> 0 | AU74: =AT74/SUM($AT$8:$AT$112) -> 0
B75: C51 | C75: Coke and refined petroleum products | D75: 0.25334385 | E75: 399.8844 | F75: 79.991927 | G75: 55.640101 | H75: 535.76977 | I75: 535.76977 | J75: 338.11955 | K75: 70.647756 | L75: 0 | M75: 10.402332 | N75: 116.60013 | Q75: C83 | R75: =VLOOKUP(Q75,Notes!$B$7:$F$111,5,0) -> Repair and installation of machinery and equipment (C83) | S75: =VLOOKUP(Q75,Notes!$B$7:$F$111,4,0) -> crepr | T75: =SUMIF($B$8:$B$124,$Q75,D$8:D$124) -> 0.26006752 | U75: =SUMIF($B$8:$B$124,$Q75,E$8:E$124) -> 30.876565 | V75: =SUMIF($B$8:$B$124,$Q75,F$8:F$124) -> 0 | W75: =SUMIF($B$8:$B$124,$Q75,G$8:G$124) -> 0 | X75: =SUM(T75:W75) -> 31.136632 | Y75: =SUM(Z75:AD75) -> 31.136632 | Z75: =SUMIF($B$8:$B$124,$Q75,J$8:J$124) -> 20.138001 | AA75: =SUMIF($B$8:$B$124,$Q75,K$8:K$124) -> 0 | AB75: =SUMIF($B$8:$B$124,$Q75,L$8:L$124) -> 0 | AC75: =SUMIF($B$8:$B$124,$Q75,M$8:M$124) -> 10.236678 | AD75: =SUMIF($B$8:$B$124,$Q75,N$8:N$124) -> 0.76195313 | AE75: =X75-Y75 -> -7.9580786e-13 | AH75: =S75 -> crepr | AI75: =AA75 -> 0 | AJ75: =AB75 -> 0 | AK75: =AC75 -> 10.236678 | AL75: =AD75 -> 0.76195313 | AM75: =U75 -> 30.876565 | AP75: crepr | AQ75: =IF(V75>=0,V75,0) -> 0 | AT75: =IF(V75<0,-V75,0) -> 0 | AU75: =AT75/SUM($AT$8:$AT$112) -> 0
B76: C52 | C76: Chemicals and chemical products | D76: 62.16707 | E76: 140.41205 | F76: 56.494269 | G76: 16.575455 | H76: 275.64885 | I76: 275.64885 | J76: 127.74955 | K76: 131.58166 | L76: 0 | M76: 6.1768111 | N76: 10.140827 | Q76: D00 | R76: =VLOOKUP(Q76,Notes!$B$7:$F$111,5,0) -> Electricity, gas, steam and air conditioning supply (D00) | S76: =VLOOKUP(Q76,Notes!$B$7:$F$111,4,0) -> celec | T76: =SUMIF($B$8:$B$124,$Q76,D$8:D$124) -> 163.60557 | U76: =SUMIF($B$8:$B$124,$Q76,E$8:E$124) -> 3.2941674 | V76: =SUMIF($B$8:$B$124,$Q76,F$8:F$124) -> 0 | W76: =SUMIF($B$8:$B$124,$Q76,G$8:G$124) -> -4.5045575 | X76: =SUM(T76:W76) -> 162.39518 | Y76: =SUM(Z76:AD76) -> 162.39518 | Z76: =SUMIF($B$8:$B$124,$Q76,J$8:J$124) -> 138.89965 | AA76: =SUMIF($B$8:$B$124,$Q76,K$8:K$124) -> 22.169753 | AB76: =SUMIF($B$8:$B$124,$Q76,L$8:L$124) -> 0 | AC76: =SUMIF($B$8:$B$124,$Q76,M$8:M$124) -> 0 | AD76: =SUMIF($B$8:$B$124,$Q76,N$8:N$124) -> 1.3257822 | AE76: =X76-Y76 -> 0 | AH76: =S76 -> celec | AI76: =AA76 -> 22.169753 | AJ76: =AB76 -> 0 | AK76: =AC76 -> 0 | AL76: =AD76 -> 1.3257822 | AM76: =U76 -> 3.2941674 | AP76: celec | AQ76: =IF(V76>=0,V76,0) -> 0 | AT76: =IF(V76<0,-V76,0) -> 0 | AU76: =AT76/SUM($AT$8:$AT$112) -> 0
B77: C53 | C77: Pharmaceutical products | D77: 4.8273898 | E77: 75.21319 | F77: 29.455778 | G77: 2.6284105 | H77: 112.12477 | I77: 112.12477 | J77: 52.375187 | K77: 56.957083 | L77: 0 | M77: 2.211465 | N77: 0.58103243 | Q77: E01 | R77: =VLOOKUP(Q77,Notes!$B$7:$F$111,5,0) -> Water collection, treatment and supply: sewrage (E01) | S77: =VLOOKUP(Q77,Notes!$B$7:$F$111,4,0) -> cwatr | T77: =SUMIF($B$8:$B$124,$Q77,D$8:D$124) -> 48.901118 | U77: =SUMIF($B$8:$B$124,$Q77,E$8:E$124) -> 0 | V77: =SUMIF($B$8:$B$124,$Q77,F$8:F$124) -> 0 | W77: =SUMIF($B$8:$B$124,$Q77,G$8:G$124) -> -2.1626607 | X77: =SUM(T77:W77) -> 46.738457 | Y77: =SUM(Z77:AD77) -> 46.738457 | Z77: =SUMIF($B$8:$B$124,$Q77,J$8:J$124) -> 25.606295 | AA77: =SUMIF($B$8:$B$124,$Q77,K$8:K$124) -> 21.132162 | AB77: =SUMIF($B$8:$B$124,$Q77,L$8:L$124) -> 0 | AC77: =SUMIF($B$8:$B$124,$Q77,M$8:M$124) -> 0 | AD77: =SUMIF($B$8:$B$124,$Q77,N$8:N$124) -> 0 | AE77: =X77-Y77 -> 0 | AH77: =S77 -> cwatr | AI77: =AA77 -> 21.132162 | AJ77: =AB77 -> 0 | AK77: =AC77 -> 0 | AL77: =AD77 -> 0 | AM77: =U77 -> 0 | AP77: cwatr | AQ77: =IF(V77>=0,V77,0) -> 0 | AT77: =IF(V77<0,-V77,0) -> 0 | AU77: =AT77/SUM($AT$8:$AT$112) -> 0
B78: C54 | C78: Rubber and plastics products | D78: 30.963808 | E78: 43.472499 | F78: 23.622884 | G78: 12.739293 | H78: 110.79848 | I78: 110.79848 | J78: 107.62459 | K78: 0 | L78: 0 | M78: -1.410781 | N78: 4.5846779 | Q78: E02 | R78: =VLOOKUP(Q78,Notes!$B$7:$F$111,5,0) -> Waste collection and management (E02) | S78: =VLOOKUP(Q78,Notes!$B$7:$F$111,4,0) -> cwast | T78: =SUMIF($B$8:$B$124,$Q78,D$8:D$124) -> 8.6291668 | U78: =SUMIF($B$8:$B$124,$Q78,E$8:E$124) -> 0 | V78: =SUMIF($B$8:$B$124,$Q78,F$8:F$124) -> 0 | W78: =SUMIF($B$8:$B$124,$Q78,G$8:G$124) -> 0 | X78: =SUM(T78:W78) -> 8.6291668 | Y78: =SUM(Z78:AD78) -> 8.6291668 | Z78: =SUMIF($B$8:$B$124,$Q78,J$8:J$124) -> 4.8628521 | AA78: =SUMIF($B$8:$B$124,$Q78,K$8:K$124) -> 3.7663146 | AB78: =SUMIF($B$8:$B$124,$Q78,L$8:L$124) -> 0 | AC78: =SUMIF($B$8:$B$124,$Q78,M$8:M$124) -> 0 | AD78: =SUMIF($B$8:$B$124,$Q78,N$8:N$124) -> 0 | AE78: =X78-Y78 -> 0 | AH78: =S78 -> cwast | AI78: =AA78 -> 3.7663146 | AJ78: =AB78 -> 0 | AK78: =AC78 -> 0 | AL78: =AD78 -> 0 | AM78: =U78 -> 0 | AP78: cwast | AQ78: =IF(V78>=0,V78,0) -> 0 | AT78: =IF(V78<0,-V78,0) -> 0 | AU78: =AT78/SUM($AT$8:$AT$112) -> 0
B79: C61 | C79: Non-metallic mineral products n.e.c. | D79: 6.7716982 | E79: 20.375431 | F79: 6.4978807 | G79: 4.261296 | H79: 37.906306 | I79: 37.906306 | J79: 29.171532 | K79: 3.231526 | L79: 0 | M79: 4.4956221 | N79: 1.0076253 | Q79: F01 | R79: =VLOOKUP(Q79,Notes!$B$7:$F$111,5,0) -> Construction (modern) (F01) | S79: =VLOOKUP(Q79,Notes!$B$7:$F$111,4,0) -> ccons | T79: =SUMIF($B$8:$B$124,$Q79,D$8:D$124) -> 1288.1823 | U79: =SUMIF($B$8:$B$124,$Q79,E$8:E$124) -> 16.625815 | V79: =SUMIF($B$8:$B$124,$Q79,F$8:F$124) -> 0 | W79: =SUMIF($B$8:$B$124,$Q79,G$8:G$124) -> 67.176326 | X79: =SUM(T79:W79) -> 1371.9845 | Y79: =SUM(Z79:AD79) -> 1371.9845 | Z79: =SUMIF($B$8:$B$124,$Q79,J$8:J$124) -> 130.40044 | AA79: =SUMIF($B$8:$B$124,$Q79,K$8:K$124) -> 63.314177 | AB79: =SUMIF($B$8:$B$124,$Q79,L$8:L$124) -> 0 | AC79: =SUMIF($B$8:$B$124,$Q79,M$8:M$124) -> 1142.5117 | AD79: =SUMIF($B$8:$B$124,$Q79,N$8:N$124) -> 35.75817 | AE79: =X79-Y79 -> 0 | AH79: =S79 -> ccons | AI79: =AA79 -> 63.314177 | AJ79: =AB79 -> 0 | AK79: =AC79 -> 1142.5117 | AL79: =AD79 -> 35.75817 | AM79: =U79 -> 16.625815 | AP79: ccons | AQ79: =IF(V79>=0,V79,0) -> 0 | AT79: =IF(V79<0,-V79,0) -> 0 | AU79: =AT79/SUM($AT$8:$AT$112) -> 0
B80: C62 | C80: Manufacture of cement, lime and plaster | D80: 58.697107 | E80: 37.136855 | F80: 25.596556 | G80: 11.889674 | H80: 133.32019 | I80: 133.32019 | J80: 126.50303 | K80: 0 | L80: 0 | M80: -4.3562137 | N80: 11.173379 | Q80: F02 | R80: =VLOOKUP(Q80,Notes!$B$7:$F$111,5,0) -> Construction (traditional) (F02) | S80: =VLOOKUP(Q80,Notes!$B$7:$F$111,4,0) -> ccont | T80: =SUMIF($B$8:$B$124,$Q80,D$8:D$124) -> 0 | U80: =SUMIF($B$8:$B$124,$Q80,E$8:E$124) -> 0 | V80: =SUMIF($B$8:$B$124,$Q80,F$8:F$124) -> 0 | W80: =SUMIF($B$8:$B$124,$Q80,G$8:G$124) -> 0 | X80: =SUM(T80:W80) -> 0 | Y80: =SUM(Z80:AD80) -> 0 | Z80: =SUMIF($B$8:$B$124,$Q80,J$8:J$124) -> 0 | AA80: =SUMIF($B$8:$B$124,$Q80,K$8:K$124) -> 0 | AB80: =SUMIF($B$8:$B$124,$Q80,L$8:L$124) -> 0 | AC80: =SUMIF($B$8:$B$124,$Q80,M$8:M$124) -> 0 | AD80: =SUMIF($B$8:$B$124,$Q80,N$8:N$124) -> 0 | AE80: =X80-Y80 -> 0 | AH80: =S80 -> ccont | AI80: =AA80 -> 0 | AJ80: =AB80 -> 0 | AK80: =AC80 -> 0 | AL80: =AD80 -> 0 | AM80: =U80 -> 0 | AP80: ccont | AQ80: =IF(V80>=0,V80,0) -> 0 | AT80: =IF(V80<0,-V80,0) -> 0 | AU80: =AT80/SUM($AT$8:$AT$112) -> 0
B81: C63 | C81: Manufacture of clay building materials | D81: 21.15271 | E81: 11.206126 | F81: 8.2868472 | G81: 3.5403078 | H81: 44.185991 | I81: 44.185991 | J81: 46.576147 | K81: 0 | L81: 0 | M81: -2.5578338 | N81: 0.16767796 | Q81: G10 | R81: =VLOOKUP(Q81,Notes!$B$7:$F$111,5,0) -> Maintenance and repair of motor vehicles (G10) | S81: =VLOOKUP(Q81,Notes!$B$7:$F$111,4,0) -> cvehr | T81: =SUMIF($B$8:$B$124,$Q81,D$8:D$124) -> 50.837891 | U81: =SUMIF($B$8:$B$124,$Q81,E$8:E$124) -> 0.066082117 | V81: =SUMIF($B$8:$B$124,$Q81,F$8:F$124) -> 0 | W81: =SUMIF($B$8:$B$124,$Q81,G$8:G$124) -> 0.32896804 | X81: =SUM(T81:W81) -> 51.232941 | Y81: =SUM(Z81:AD81) -> 51.232941 | Z81: =SUMIF($B$8:$B$124,$Q81,J$8:J$124) -> 42.889229 | AA81: =SUMIF($B$8:$B$124,$Q81,K$8:K$124) -> 8.1779177 | AB81: =SUMIF($B$8:$B$124,$Q81,L$8:L$124) -> 0 | AC81: =SUMIF($B$8:$B$124,$Q81,M$8:M$124) -> 0 | AD81: =SUMIF($B$8:$B$124,$Q81,N$8:N$124) -> 0.16579485 | AE81: =X81-Y81 -> 0 | AH81: =S81 -> cvehr | AI81: =AA81 -> 8.1779177 | AJ81: =AB81 -> 0 | AK81: =AC81 -> 0 | AL81: =AD81 -> 0.16579485 | AM81: =U81 -> 0.066082117 | AP81: cvehr | AQ81: =IF(V81>=0,V81,0) -> 0 | AT81: =IF(V81<0,-V81,0) -> 0 | AU81: =AT81/SUM($AT$8:$AT$112) -> 0
B82: C72 | C82: Metals & metal products, except machinery and equipment | D82: 117.16854 | E82: 138.67646 | F82: 49.406637 | G82: 27.926374 | H82: 333.17801 | I82: 333.17801 | J82: 244.4839 | K82: 4.3543789 | L82: 0 | M82: -1.0452621 | N82: 85.384994 | Q82: G21 | R82: =VLOOKUP(Q82,Notes!$B$7:$F$111,5,0) -> Wholesale and retail trade of motor vehicles and motorcycles (G21) | S82: =VLOOKUP(Q82,Notes!$B$7:$F$111,4,0) -> cveht | T82: =SUMIF($B$8:$B$124,$Q82,D$8:D$124) -> 9.4425563 | U82: =SUMIF($B$8:$B$124,$Q82,E$8:E$124) -> 0 | V82: =SUMIF($B$8:$B$124,$Q82,F$8:F$124) -> -9.4425563 | W82: =SUMIF($B$8:$B$124,$Q82,G$8:G$124) -> 0 | X82: =SUM(T82:W82) -> 5.2580162e-13 | Y82: =SUM(Z82:AD82) -> 5.2568794e-13 | Z82: =SUMIF($B$8:$B$124,$Q82,J$8:J$124) -> 0 | AA82: =SUMIF($B$8:$B$124,$Q82,K$8:K$124) -> 5.2568794e-13 | AB82: =SUMIF($B$8:$B$124,$Q82,L$8:L$124) -> 0 | AC82: =SUMIF($B$8:$B$124,$Q82,M$8:M$124) -> 0 | AD82: =SUMIF($B$8:$B$124,$Q82,N$8:N$124) -> 0 | AE82: =X82-Y82 -> 1.1368684e-16 | AH82: =S82 -> cveht | AI82: =AA82 -> 5.2568794e-13 | AJ82: =AB82 -> 0 | AK82: =AC82 -> 0 | AL82: =AD82 -> 0 | AM82: =U82 -> 0 | AP82: cveht | AQ82: =IF(V82>=0,V82,0) -> 0 | AT82: =IF(V82<0,-V82,0) -> 9.4425563 | AU82: =AT82/SUM($AT$8:$AT$112) -> 0.0089520085
B83: C74 | C83: Machinery and equipment (except transport) | D83: 12.122323 | E83: 311.83334 | F83: 127.30739 | G83: 42.470894 | H83: 493.73395 | I83: 493.73395 | J83: 36.079736 | K83: 57.045934 | L83: 0 | M83: 390.10762 | N83: 10.500661 | Q83: G22 | R83: =VLOOKUP(Q83,Notes!$B$7:$F$111,5,0) -> Wholesale trade, except of motor vehicles and motorcycles (G22) | S83: =VLOOKUP(Q83,Notes!$B$7:$F$111,4,0) -> ctrdw | T83: =SUMIF($B$8:$B$124,$Q83,D$8:D$124) -> 367.27361 | U83: =SUMIF($B$8:$B$124,$Q83,E$8:E$124) -> 0 | V83: =SUMIF($B$8:$B$124,$Q83,F$8:F$124) -> -367.27361 | W83: =SUMIF($B$8:$B$124,$Q83,G$8:G$124) -> 0 | X83: =SUM(T83:W83) -> -3.0127012e-12 | Y83: =SUM(Z83:AD83) -> 0 | Z83: =SUMIF($B$8:$B$124,$Q83,J$8:J$124) -> 0 | AA83: =SUMIF($B$8:$B$124,$Q83,K$8:K$124) -> 0 | AB83: =SUMIF($B$8:$B$124,$Q83,L$8:L$124) -> 0 | AC83: =SUMIF($B$8:$B$124,$Q83,M$8:M$124) -> 0 | AD83: =SUMIF($B$8:$B$124,$Q83,N$8:N$124) -> 0 | AE83: =X83-Y83 -> -3.0127012e-12 | AH83: =S83 -> ctrdw | AI83: =AA83 -> 0 | AJ83: =AB83 -> 0 | AK83: =AC83 -> 0 | AL83: =AD83 -> 0 | AM83: =U83 -> 0 | AP83: ctrdw | AQ83: =IF(V83>=0,V83,0) -> 0 | AT83: =IF(V83<0,-V83,0) -> 367.27361 | AU83: =AT83/SUM($AT$8:$AT$112) -> 0.34819347
B84: C76 | C84: Transport equipment | D84: 8.8180832 | E84: 109.95767 | F84: 71.691211 | G84: 36.729638 | H84: 227.1966 | I84: 227.1966 | J84: 16.448467 | K84: 107.89675 | L84: 0 | M84: 88.215031 | N84: 14.636351 | Q84: G23 | R84: =VLOOKUP(Q84,Notes!$B$7:$F$111,5,0) -> Retail trade, except of motor vehicles and motorcycles (G23) | S84: =VLOOKUP(Q84,Notes!$B$7:$F$111,4,0) -> ctrdr | T84: =SUMIF($B$8:$B$124,$Q84,D$8:D$124) -> 678.08134 | U84: =SUMIF($B$8:$B$124,$Q84,E$8:E$124) -> 0 | V84: =SUMIF($B$8:$B$124,$Q84,F$8:F$124) -> -678.08134 | W84: =SUMIF($B$8:$B$124,$Q84,G$8:G$124) -> 0 | X84: =SUM(T84:W84) -> -4.0927262e-12 | Y84: =SUM(Z84:AD84) -> 0 | Z84: =SUMIF($B$8:$B$124,$Q84,J$8:J$124) -> 0 | AA84: =SUMIF($B$8:$B$124,$Q84,K$8:K$124) -> 0 | AB84: =SUMIF($B$8:$B$124,$Q84,L$8:L$124) -> 0 | AC84: =SUMIF($B$8:$B$124,$Q84,M$8:M$124) -> 0 | AD84: =SUMIF($B$8:$B$124,$Q84,N$8:N$124) -> 0 | AE84: =X84-Y84 -> -4.0927262e-12 | AH84: =S84 -> ctrdr | AI84: =AA84 -> 0 | AJ84: =AB84 -> 0 | AK84: =AC84 -> 0 | AL84: =AD84 -> 0 | AM84: =U84 -> 0 | AP84: ctrdr | AQ84: =IF(V84>=0,V84,0) -> 0 | AT84: =IF(V84<0,-V84,0) -> 678.08134 | AU84: =AT84/SUM($AT$8:$AT$112) -> 0.64285452
B85: C81 | C85: Furniture | D85: 27.59031 | E85: 10.087123 | F85: 5.8015881 | G85: 4.1905168 | H85: 47.669538 | I85: 47.669538 | J85: 0 | K85: 17.89798 | L85: 0 | M85: 26.883875 | N85: 2.8876837 | Q85: H10 | R85: =VLOOKUP(Q85,Notes!$B$7:$F$111,5,0) -> Land transport (H10) | S85: =VLOOKUP(Q85,Notes!$B$7:$F$111,4,0) -> ctrnl | T85: =SUMIF($B$8:$B$124,$Q85,D$8:D$124) -> 442.63902 | U85: =SUMIF($B$8:$B$124,$Q85,E$8:E$124) -> -12.14762 | V85: =SUMIF($B$8:$B$124,$Q85,F$8:F$124) -> 0 | W85: =SUMIF($B$8:$B$124,$Q85,G$8:G$124) -> 37.291143 | X85: =SUM(T85:W85) -> 467.78254 | Y85: =SUM(Z85:AD85) -> 467.78254 | Z85: =SUMIF($B$8:$B$124,$Q85,J$8:J$124) -> 193.53098 | AA85: =SUMIF($B$8:$B$124,$Q85,K$8:K$124) -> 267.16063 | AB85: =SUMIF($B$8:$B$124,$Q85,L$8:L$124) -> 0 | AC85: =SUMIF($B$8:$B$124,$Q85,M$8:M$124) -> 0 | AD85: =SUMIF($B$8:$B$124,$Q85,N$8:N$124) -> 7.0909288 | AE85: =X85-Y85 -> 0 | AH85: =S85 -> ctrnl | AI85: =AA85 -> 267.16063 | AJ85: =AB85 -> 0 | AK85: =AC85 -> 0 | AL85: =AD85 -> 7.0909288 | AM85: =U85 -> -12.14762 | AP85: ctrnl | AQ85: =IF(V85>=0,V85,0) -> 0 | AT85: =IF(V85<0,-V85,0) -> 0 | AU85: =AT85/SUM($AT$8:$AT$112) -> 0
B86: C82 | C86: Other manufacturing | D86: 45.091143 | E86: 50.977158 | F86: 16.399929 | G86: 5.7700858 | H86: 118.23832 | I86: 118.23832 | J86: 16.931339 | K86: 47.927441 | L86: 0 | M86: 31.562144 | N86: 21.81739 | Q86: H20 | R86: =VLOOKUP(Q86,Notes!$B$7:$F$111,5,0) -> Air transport (H20) | S86: =VLOOKUP(Q86,Notes!$B$7:$F$111,4,0) -> ctrna | T86: =SUMIF($B$8:$B$124,$Q86,D$8:D$124) -> 180.34401 | U86: =SUMIF($B$8:$B$124,$Q86,E$8:E$124) -> 63.779916 | V86: =SUMIF($B$8:$B$124,$Q86,F$8:F$124) -> 0 | W86: =SUMIF($B$8:$B$124,$Q86,G$8:G$124) -> -81.690678 | X86: =SUM(T86:W86) -> 162.43325 | Y86: =SUM(Z86:AD86) -> 162.43325 | Z86: =SUMIF($B$8:$B$124,$Q86,J$8:J$124) -> 60.055103 | AA86: =SUMIF($B$8:$B$124,$Q86,K$8:K$124) -> 11.910009 | AB86: =SUMIF($B$8:$B$124,$Q86,L$8:L$124) -> 0 | AC86: =SUMIF($B$8:$B$124,$Q86,M$8:M$124) -> 0 | AD86: =SUMIF($B$8:$B$124,$Q86,N$8:N$124) -> 90.46814 | AE86: =X86-Y86 -> 0 | AH86: =S86 -> ctrna | AI86: =AA86 -> 11.910009 | AJ86: =AB86 -> 0 | AK86: =AC86 -> 0 | AL86: =AD86 -> 90.46814 | AM86: =U86 -> 63.779916 | AP86: ctrna | AQ86: =IF(V86>=0,V86,0) -> 0 | AT86: =IF(V86<0,-V86,0) -> 0 | AU86: =AT86/SUM($AT$8:$AT$112) -> 0
... B111: M02 | C111: Architectural and engineering activities | D111: 19.735374 | E111: 40.000134 | F111: 0 | G111: 3.9948517 | H111: 63.73036 | I111: 63.73036 | J111: 63.73036 | K111: 3.1141099e-12 | L111: 0 | M111: 0 | N111: 0 | Q111: V00 | R111: =VLOOKUP(Q111,Notes!$B$7:$F$111,5,0) -> Travel debits & credits (V00) | S111: =VLOOKUP(Q111,Notes!$B$7:$F$111,4,0) -> ctrdc | T111: =SUMIF($B$8:$B$124,$Q111,D$8:D$124) -> 0 | U111: =SUMIF($B$8:$B$124,$Q111,E$8:E$124) -> 308.3126 | V111: =SUMIF($B$8:$B$124,$Q111,F$8:F$124) -> 0 | W111: =SUMIF($B$8:$B$124,$Q111,G$8:G$124) -> 0 | X111: =SUM(T111:W111) -> 308.3126 | Y111: =SUM(Z111:AD111) -> 308.3126 | Z111: =SUMIF($B$8:$B$124,$Q111,J$8:J$124) -> 215.81882 | AA111: =SUMIF($B$8:$B$124,$Q111,K$8:K$124) -> -224.37741 | AB111: =SUMIF($B$8:$B$124,$Q111,L$8:L$124) -> 0 | AC111: =SUMIF($B$8:$B$124,$Q111,M$8:M$124) -> 0 | AD111: =SUMIF($B$8:$B$124,$Q111,N$8:N$124) -> 316.87119 | AE111: =X111-Y111 -> 0 | AH111: =S111 -> ctrdc | AI111: =AA111 -> -224.37741 | AJ111: =AB111 -> 0 | AK111: =AC111 -> 0 | AL111: =AD111 -> 316.87119 | AM111: =U111 -> 308.3126 | AP111: ctrdc | AQ111: =IF(V111>=0,V111,0) -> 0 | AT111: =IF(V111<0,-V111,0) -> 0 | AU111: =AT111/SUM($AT$8:$AT$112) -> 0
B112: M03 | C112: Other professional, scientific and technical activities | D112: 114.37986 | E112: 64.401767 | F112: 0 | G112: 73.48159 | H112: 252.26322 | I112: 252.26322 | J112: 235.23665 | K112: 1.7108915 | L112: 0 | M112: 0 | N112: 15.315674 | Q112: X00 | R112: =VLOOKUP(Q112,Notes!$B$7:$F$111,5,0) -> Unallocated products (X00) | S112: =VLOOKUP(Q112,Notes!$B$7:$F$111,4,0) -> 0 | T112: =SUMIF($B$8:$B$124,$Q112,D$8:D$124) -> 0 | U112: =SUMIF($B$8:$B$124,$Q112,E$8:E$124) -> 0 | V112: =SUMIF($B$8:$B$124,$Q112,F$8:F$124) -> 0 | W112: =SUMIF($B$8:$B$124,$Q112,G$8:G$124) -> 0 | X112: =SUM(T112:W112) -> 0 | Y112: =SUM(Z112:AD112) -> 0 | Z112: =SUMIF($B$8:$B$124,$Q112,J$8:J$124) -> 0 | AA112: =SUMIF($B$8:$B$124,$Q112,K$8:K$124) -> 0 | AB112: =SUMIF($B$8:$B$124,$Q112,L$8:L$124) -> 0 | AC112: =SUMIF($B$8:$B$124,$Q112,M$8:M$124) -> 0 | AD112: =SUMIF($B$8:$B$124,$Q112,N$8:N$124) -> 0 | AE112: =X112-Y112 -> 0 | AH112: =S112 -> 0 | AI112: =AA112 -> 0 | AJ112: =AB112 -> 0 | AK112: =AC112 -> 0 | AL112: =AD112 -> 0 | AM112: =U112 -> 0 | AP112: 0 | AQ112: =IF(V112>=0,V112,0) -> 0 | AT112: =IF(V112<0,-V112,0) -> 0 | AU112: =AT112/SUM($AT$8:$AT$112) -> 0
B113: N01 | C113: Travel agents and tour operators | D113: 33.921278 | E113: 0 | F113: 0 | G113: 0.72826534 | H113: 34.649543 | I113: 34.649543 | J113: 3.1972182 | K113: 31.452325 | L113: 0 | M113: 0 | N113: 0
B114: N09 | C114: Other administrative and support service activities | D114: 314.90971 | E114: 10.487201 | F114: 0 | G114: 7.4008287 | H114: 332.79774 | I114: 332.79774 | J114: 300.12067 | K114: 6.3655078 | L114: 0 | M114: 0 | N114: 26.311565
B115: O00 | C115: Public administration and defence; compulsory social security | D115: 1110.1505 | E115: 0 | F115: 0 | G115: 0 | H115: 1110.1505 | I115: 1110.1505 | J115: 33.714261 | K115: 42.96487 | L115: 887.87191 | M115: 0 | N115: 145.59946
B116: P00 | C116: Education | D116: 360.18246 | E116: 0 | F116: 0 | G116: 0.3240267 | H116: 360.50649 | I116: 360.50649 | J116: 17.692778 | K116: 141.68044 | L116: 201.13328 | M116: 0 | N116: 0
B117: Q01 | C117: Human health activities | D117: 212.79473 | E117: 0.0084424662 | F117: 0 | G117: 0.51942828 | H117: 213.3226 | I117: 213.3226 | J117: 0.18602226 | K117: 72.666104 | L117: 140.44929 | M117: 0 | N117: 0.021181486
B118: Q02 | C118: Social work activities | D118: 97.651638 | E118: 0 | F118: 0 | G118: 0.26755316 | H118: 97.919191 | I118: 97.919191 | J118: 0 | K118: 7.1361702 | L118: 90.78302 | M118: 0 | N118: 0
B119: R01 | C119: Libraries, archives, museums and other cultural activities | D119: 15.058193 | E119: 2.9214775e-05 | F119: 0 | G119: 0.19114247 | H119: 15.249365 | I119: 15.249365 | J119: 0.00064372168 | K119: 15.248648 | L119: 0 | M119: 0 | N119: 7.3297578e-05
B120: R09 | C120: Other arts, entertainment and recreation | D120: 63.374693 | E120: 0.16300897 | F120: 0 | G120: 3.9816929 | H120: 67.519395 | I120: 67.519395 | J120: 13.904982 | K120: 53.179232 | L120: 0 | M120: 0 | N120: 0.43518115
B121: S00 | C121: Other service activities | D121: 407.53025 | E121: 0.30154209 | F121: 0 | G121: 13.749193 | H121: 421.58098 | I121: 421.58098 | J121: 8.1652549 | K121: 326.66324 | L121: 86 | M121: 0 | N121: 0.75249436
B122: T00 | C122: Domestic services | D122: 25.436762 | E122: 0 | F122: 0 | G122: 0 | H122: 25.436762 | I122: 25.436762 | J122: 0 | K122: 25.436762 | L122: 0 | M122: 0 | N122: 0
B123: V00 | C123: Travel debits & credits | D123: 0 | E123: 308.3126 | F123: 0 | G123: 0 | H123: 308.3126 | I123: 308.3126 | J123: 215.81882 | K123: -224.37741 | L123: 0 | M123: 0 | N123: 316.87119
B124: X00 | C124: Unallocated products | D124: 0 | E124: 0 | F124: 0 | G124: 0 | H124: 0 | I124: 0 | J124: 0 | K124: 0 | L124: 0 | M124: 0 | N124: 0

Sheet USE
A1: SUT Part C: Intermediate consumption matrix
A2: Billions of FRW
E4: Activities
A5: Original data | E5: Cereals | F5: Roots and Tubers | G5: Vegetables | H5: Bananas and fruit | I5: Oil seeds n.e.c. and oleaginous fruit | J5: Coffee | K5: Tea (unprocessed green leaf) | L5: Other agricultural products | M5: Livestock | N5: Livestock and hunting products | O5: Forestry products | P5: Fishery products | Q5: Natural gas | R5: Metal ores | S5: Quarry & other mining products | T5: Meat and meat products | U5: Prepared and preserved fish | V5: Prepared and preserved vegetables | W5: Animal and vegetable oils and fats | X5: Dairy products | Y5: Grain mill products | Z5: Bakery products | AA5: Animal feed & other by-products | AB5: Other manufactured food products | AC5: Alcoholic drinks | AD5: Soft drinks | AE5: Tobacco products | AF5: Textiles, clothing & leather products | AG5: Wood, paper and related products | AH5: Printing and reproduction of recorded media | AI5: Coke and refined petroleum products | AJ5: Chemicals and chemical products | AK5: Pharmaceutical products | AL5: Rubber and plastics products | AM5: Non-metallic mineral products n.e.c. | AN5: Manufacture of cement, lime and plaster | AO5: Manufacture of clay building materials | AP5: Metals & metal products, except machinery and equipment | AQ5: Machinery and equipment (except transport) | AR5: Transport equipment | AS5: Furniture | AT5: Other manufacturing | AU5: Repair and installation of machinery and equipment | AV5: Electricity, gas, steam and air conditioning supply | AW5: Water collection, treatment and supply: sewrage | AX5: Waste collection and management | AY5: Construction (modern) | AZ5: Construction (traditional) | BA5: Maintenance and repair of motor vehicles | BB5: Wholesale and retail trade of motor vehicles and motorcycles | BC5: Wholesale trade, except of motor vehicles and motorcycles | BD5: Retail trade, except of motor vehicles and motorcycles | BE5: Land transport | BF5: Air transport | BG5: Services related to transport | BH5: Postal and courier activities | BI5: Hotels & restaurants | BJ5: Publishing, video making, programming & broadcasting activities | BK5: Telecommunication | BL5: Information technology services | BM5: Monetary institutions | BN5: Insurance, reinsurance and pension funding, except compulsory social security | BO5: Other financial services | BP5: Rental value of dwellings | BQ5: Other real estate activities | BR5: Legal, accounting management & head office activities | BS5: Architectural and engineering activities | BT5: Other professional, scientific and technical activities | BU5: Travel agents and tour operators | BV5: Other administrative and support service activities | BW5: Public administration and defence; compulsory social security | BX5: Education | BY5: Human health activities | BZ5: Social work activities | CA5: Libraries, archives, museums and other cultural activities | CB5: Other arts, entertainment and recreation | CC5: Other service activities | CD5: Domestic services | CE5: Travel debits & credits
E6: A11 | F6: A12 | G6: A13 | H6: A14 | I6: A15 | J6: A21 | K6: A22 | L6: A29 | M6: A31 | N6: A32 | O6: A40 | P6: A50 | Q6: B01 | R6: B03 | S6: B09 | T6: C11 | U6: C12 | V6: C13 | W6: C14 | X6: C15 | Y6: C16 | Z6: C17 | AA6: C18 | AB6: C19 | AC6: C21 | AD6: C22 | AE6: C23 | AF6: C30 | AG6: C41 | AH6: C42 | AI6: C51 | AJ6: C52 | AK6: C53 | AL6: C54 | AM6: C61 | AN6: C62 | AO6: C63 | AP6: C72 | AQ6: C74 | AR6: C76 | AS6: C81 | AT6: C82 | AU6: C83 | AV6: D00 | AW6: E01 | AX6: E02 | AY6: F01 | AZ6: F02 | BA6: G10 | BB6: G21 | BC6: G22 | BD6: G23 | BE6: H10 | BF6: H20 | BG6: H31 | BH6: H32 | BI6: I00 | BJ6: J10 | BK6: J20 | BL6: J30 | BM6: K01 | BN6: K02 | BO6: K03 | BP6: L01 | BQ6: L09 | BR6: M01 | BS6: M02 | BT6: M03 | BU6: N01 | BV6: N09 | BW6: O00 | BX6: P00 | BY6: Q01 | BZ6: Q02 | CA6: R01 | CB6: R09 | CC6: S00 | CD6: T00 | CE6: V00
B7: Commodities | D7: =SUM(E8:CE86) -> 4606.299 | E7: 13.826933 | F7: 30.293796 | G7: 19.560457 | H7: 6.26712 | I7: 3.6893492 | J7: 6.2891096 | K7: 2.108269 | L7: 3.5808644 | M7: 11.772368 | N7: 1.5113351 | O7: 0.69532137 | P7: 1.233588 | Q7: 0 | R7: 38.265093 | S7: 35.41067 | T7: 74.931532 | U7: 0 | V7: 12.636663 | W7: 8.3845406 | X7: 3.4061878 | Y7: 274.2926 | Z7: 51.827857 | AA7: 0.22896095 | AB7: 64.756417 | AC7: 134.30836 | AD7: 18.562988 | AE7: 1.8081149 | AF7: 35.414136 | AG7: 16.031634 | AH7: 15.078052 | AI7: 0.03535081 | AJ7: 43.213294 | AK7: 1.4871787 | AL7: 10.193855 | AM7: 5.6949687 | AN7: 33.254314 | AO7: 8.9920058 | AP7: 104.54244 | AQ7: 4.7185336 | AR7: 4.3807275 | AS7: 14.634522 | AT7: 9.3357588 | AU7: 0.5863776 | AV7: 78.540129 | AW7: 16.043307 | AX7: 5.2308441 | AY7: 843.12858 | AZ7: 0 | BA7: 15.813318 | BB7: 6.9258819 | BC7: 177.70263 | BD7: 260.23653 | BE7: 204.92214 | BF7: 83.759946 | BG7: 24.88372 | BH7: 5.9606481 | BI7: 372.6471 | BJ7: 8.9659725 | BK7: 100.62441 | BL7: 15.222644 | BM7: 61.798633 | BN7: 8.9024496 | BO7: 45.305779 | BP7: 0 | BQ7: 18.42427 | BR7: 8.5502122 | BS7: 4.2379892 | BT7: 10.955703 | BU7: 16.412928 | BV7: 19.487806 | BW7: 664.12013 | BX7: 136.4811 | BY7: 109.35478 | BZ7: 40.751552 | CA7: 2.7889478 | CB7: 2.6396367 | CC7: 107.64325 | CD7: 0.59442349 | CE7: 0
B8: Cereals | C8: A11 | D8: =SUM(E8:CE8) -> 180.68808 | E8: 1.5554548 | F8: 0 | G8: 0 | H8: 0 | I8: 0 | J8: 0 | K8: 0 | L8: 0 | M8: 2.9406326 | N8: 0 | O8: 0 | P8: 0 | Q8: 0 | R8: 0 | S8: 0 | T8: 0 | U8: 0 | V8: 0.048908252 | W8: 0.82647492 | X8: 0 | Y8: 142.50053 | Z8: 1.5643533 | AA8: 0 | AB8: 3.2775829 | AC8: 27.40828 | AD8: 0 | AE8: 0 | AF8: 0 | AG8: 0 | AH8: 0 | AI8: 0 | AJ8: 0 | AK8: 0 | AL8: 0 | AM8: 0 | AN8: 0 | AO8: 0 | AP8: 0 | AQ8: 0 | AR8: 0 | AS8: 0 | AT8: 0 | AU8: 0 | AV8: 0 | AW8: 0 | AX8: 0 | AY8: 0 | AZ8: 0 | BA8: 0 | BB8: 0 | BC8: 0 | BD8: 0 | BE8: 0 | BF8: 0 | BG8: 0 | BH8: 0 | BI8: 0.56586226 | BJ8: 0 | BK8: 0 | BL8: 0 | BM8: 0 | BN8: 0 | BO8: 0 | BP8: 0 | BQ8: 0 | BR8: 0 | BS8: 0 | BT8: 0 | BU8: 0 | BV8: 0 | BW8: 0 | BX8: 0 | BY8: 0 | BZ8: 0 | CA8: 0 | CB8: 0 | CC8: 0 | CD8: 0 | CE8: 0
B9: Roots and Tubers | C9: A12 | D9: =SUM(E9:CE9) -> 82.163087 | E9: 0 | F9: 5.3546377 | G9: 0 | H9: 0 | I9: 0 | J9: 0 | K9: 0 | L9: 0 | M9: 0 | N9: 0 | O9: 0 | P9: 0 | Q9: 0 | R9: 0 | S9: 0 | T9: 0 | U9: 0 | V9: 0 | W9: 0 | X9: 0 | Y9: 55.181234 | Z9: 0 | AA9: 0 | AB9: 1.4619619 | AC9: 0 | AD9: 0 | AE9: 0 | AF9: 0 | AG9: 0.032479534 | AH9: 0 | AI9: 0 | AJ9: 0 | AK9: 0 | AL9: 0 | AM9: 0.059485861 | AN9: 0 | AO9: 0 | AP9: 0 | AQ9: 0 | AR9: 0 | AS9: 0 | AT9: 0 | AU9: 0 | AV9: 0 | AW9: 0 | AX9: 0 | AY9: 0 | AZ9: 0 | BA9: 0 | BB9: 0 | BC9: 0 | BD9: 4.1910952 | BE9: 0 | BF9: 0 | BG9: 0 | BH9: 0 | BI9: 15.882193 | BJ9: 0 | BK9: 0 | BL9: 0 | BM9: 0 | BN9: 0 | BO9: 0 | BP9: 0 | BQ9: 0 | BR9: 0 | BS9: 0 | BT9: 0 | BU9: 0 | BV9: 0 | BW9: 0 | BX9: 0 | BY9: 0 | BZ9: 0 | CA9: 0 | CB9: 0 | CC9: 0 | CD9: 0 | CE9: 0
B10: Vegetables | C10: A13 | D10: =SUM(E10:CE10) -> 13.580766 | E10: 0 | F10: 0 | G10: 2.7596475 | H10: 0 | I10: 0 | J10: 0 | K10: 0 | L10: 0 | M10: 0 | N10: 0 | O10: 0 | P10: 0 | Q10: 0 | R10: 0 | S10: 0 | T10: 0 | U10: 0 | V10: 1.0970896 | W10: 0 | X10: 0 | Y10: 0 | Z10: 0 | AA10: 0 | AB10: 1.3160124 | AC10: 0 | AD10: 0 | AE10: 0 | AF10: 0 | AG10: 0.031251132 | AH10: 0 | AI10: 0 | AJ10: 0 | AK10: 0 | AL10: 0 | AM10: 0.055987014 | AN10: 0 | AO10: 0 | AP10: 0 | AQ10: 0 | AR10: 0 | AS10: 0 | AT10: 0 | AU10: 0 | AV10: 0 | AW10: 0 | AX10: 0 | AY10: 0 | AZ10: 0 | BA10: 0 | BB10: 0 | BC10: 0 | BD10: 1.3051836 | BE10: 0 | BF10: 0 | BG10: 0 | BH10: 0 | BI10: 7.0155945 | BJ10: 0 | BK10: 0 | BL10: 0 | BM10: 0 | BN10: 0 | BO10: 0 | BP10: 0 | BQ10: 0 | BR10: 0 | BS10: 0 | BT10: 0 | BU10: 0 | BV10: 0 | BW10: 0 | BX10: 0 | BY10: 0 | BZ10: 0 | CA10: 0 | CB10: 0 | CC10: 0 | CD10: 0 | CE10: 0
B11: Bananas and fruit | C11: A14 | D11: =SUM(E11:CE11) -> 70.89097 | E11: 0 | F11: 0 | G11: 0 | H11: 0.76781479 | I11: 0 | J11: 0 | K11: 0 | L11: 0 | M11: 0 | N11: 0 | O11: 0 | P11: 0 | Q11: 0 | R11: 0 | S11: 0 | T11: 0 | U11: 0 | V11: 6.7288012 | W11: 0 | X11: 0 | Y11: 0 | Z11: 0 | AA11: 0 | AB11: 0 | AC11: 47.790972 | AD11: 5.9330963 | AE11: 0 | AF11: 0 | AG11: 0.03645277 | AH11: 0 | AI11: 0 | AJ11: 0 | AK11: 0 | AL11: 0 | AM11: 0.070802792 | AN11: 0 | AO11: 0 | AP11: 0 | AQ11: 0 | AR11: 0 | AS11: 0 | AT11: 0 | AU11: 0 | AV11: 0 | AW11: 0 | AX11: 0 | AY11: 0 | AZ11: 0 | BA11: 0 | BB11: 0 | BC11: 0 | BD11: 0 | BE11: 0 | BF11: 0 | BG11: 0 | BH11: 0 | BI11: 9.5630299 | BJ11: 0 | BK11: 0 | BL11: 0 | BM11: 0 | BN11: 0 | BO11: 0 | BP11: 0 | BQ11: 0 | BR11: 0 | BS11: 0 | BT11: 0 | BU11: 0 | BV11: 0 | BW11: 0 | BX11: 0 | BY11: 0 | BZ11: 0 | CA11: 0 | CB11: 0 | CC11: 0 | CD11: 0 | CE11: 0
B12: Oil seeds n.e.c. and oleaginous fruit | C12: A15 | D12: =SUM(E12:CE12) -> 22.529324 | E12: 0 | F12: 0 | G12: 0 | H12: 0 | I12: 1.6895388 | J12: 0 | K12: 0 | L12: 0 | M12: 0 | N12: 0 | O12: 0 | P12: 0 | Q12: 0 | R12: 0 | S12: 0 | T12: 0 | U12: 0 | V12: 1.2182858 | W12: 6.2595638 | X12: 0 | Y12: 11.781048 | Z12: 0 | AA12: 0 | AB12: 1.4627108 | AC12: 0 | AD12: 0 | AE12: 0 | AF12: 0 | AG12: 0.036361298 | AH12: 0 | AI12: 0 | AJ12: 0 | AK12: 0 | AL12: 0 | AM12: 0.070542255 | AN12: 0 | AO12: 0 | AP12: 0 | AQ12: 0 | AR12: 0 | AS12: 0 | AT12: 0 | AU12: 0 | AV12: 0 | AW12: 0 | AX12: 0 | AY12: 0 | AZ12: 0 | BA12: 0 | BB12: 0 | BC12: 0 | BD12: 0 | BE12: 0 | BF12: 0 | BG12: 0 | BH12: 0 | BI12: 0.011273537 | BJ12: 0 | BK12: 0 | BL12: 0 | BM12: 0 | BN12: 0 | BO12: 0 | BP12: 0 | BQ12: 0 | BR12: 0 | BS12: 0 | BT12: 0 | BU12: 0 | BV12: 0 | BW12: 0 | BX12: 0 | BY12: 0 | BZ12: 0 | CA12: 0 | CB12: 0 | CC12: 0 | CD12: 0 | CE12: 0
B13: Coffee | C13: A21 | D13: =SUM(E13:CE13) -> 7.4532552 | E13: 0 | F13: 0 | G13: 0 | H13: 0 | I13: 0 | J13: 0 | K13: 0 | L13: 0 | M13: 0 | N13: 0 | O13: 0 | P13: 0 | Q13: 0 | R13: 0 | S13: 0 | T13: 0 | U13: 0 | V13: 0 | W13: 0 | X13: 0 | Y13: 0 | Z13: 0 | AA13: 0 | AB13: 7.4532552 | AC13: 0 | AD13: 0 | AE13: 0 | AF13: 0 | AG13: 0 | AH13: 0 | AI13: 0 | AJ13: 0 | AK13: 0 | AL13: 0 | AM13: 0 | AN13: 0 | AO13: 0 | AP13: 0 | AQ13: 0 | AR13: 0 | AS13: 0 | AT13: 0 | AU13: 0 | AV13: 0 | AW13: 0 | AX13: 0 | AY13: 0 | AZ13: 0 | BA13: 0 | BB13: 0 | BC13: 0 | BD13: 0 | BE13: 0 | BF13: 0 | BG13: 0 | BH13: 0 | BI13: 0 | BJ13: 0 | BK13: 0 | BL13: 0 | BM13: 0 | BN13: 0 | BO13: 0 | BP13: 0 | BQ13: 0 | BR13: 0 | BS13: 0 | BT13: 0 | BU13: 0 | BV13: 0 | BW13: 0 | BX13: 0 | BY13: 0 | BZ13: 0 | CA13: 0 | CB13: 0 | CC13: 0 | CD13: 0 | CE13: 0
B14: Tea (unprocessed green leaf) | C14: A22 | D14: =SUM(E14:CE14) -> 23.435896 | E14: 0 | F14: 0 | G14: 0 | H14: 0 | I14: 0 | J14: 0 | K14: 0 | L14: 0 | M14: 0 | N14: 0 | O14: 0 | P14: 0 | Q14: 0 | R14: 0 | S14: 0 | T14: 0 | U14: 0 | V14: 0 | W14: 0 | X14: 0 | Y14: 0 | Z14: 0 | AA14: 0 | AB14: 23.435896 | AC14: 0 | AD14: 0 | AE14: 0 | AF14: 0 | AG14: 0 | AH14: 0 | AI14: 0 | AJ14: 0 | AK14: 0 | AL14: 0 | AM14: 0 | AN14: 0 | AO14: 0 | AP14: 0 | AQ14: 0 | AR14: 0 | AS14: 0 | AT14: 0 | AU14: 0 | AV14: 0 | AW14: 0 | AX14: 0 | AY14: 0 | AZ14: 0 | BA14: 0 | BB14: 0 | BC14: 0 | BD14: 0 | BE14: 0 | BF14: 0 | BG14: 0 | BH14: 0 | BI14: 0 | BJ14: 0 | BK14: 0 | BL14: 0 | BM14: 0 | BN14: 0 | BO14: 0 | BP14: 0 | BQ14: 0 | BR14: 0 | BS14: 0 | BT14: 0 | BU14: 0 | BV14: 0 | BW14: 0 | BX14: 0 | BY14: 0 | BZ14: 0 | CA14: 0 | CB14: 0 | CC14: 0 | CD14: 0 | CE14: 0
B15: Other agricultural products | C15: A29 | D15: =SUM(E15:CE15) -> 27.257544 | E15: 0 | F15: 0 | G15: 0 | H15: 0 | I15: 0 | J15: 1.7223674 | K15: 0.78895952 | L15: 0.45670123 | M15: 0.84744927 | N15: 0 | O15: 0 | P15: 0 | Q15: 0 | R15: 0 | S15: 0 | T15: 0 | U15: 0 | V15: 0 | W15: 0 | X15: 0 | Y15: 0 | Z15: 0 | AA15: 0 | AB15: 0 | AC15: 0 | AD15: 0 | AE15: 0 | AF15: 0 | AG15: 0 | AH15: 0 | AI15: 0 | AJ15: 0 | AK15: 0 | AL15: 0 | AM15: 0 | AN15: 0 | AO15: 0 | AP15: 0 | AQ15: 0 | AR15: 0 | AS15: 0 | AT15: 0 | AU15: 0 | AV15: 0 | AW15: 0 | AX15: 0 | AY15: 0 | AZ15: 0 | BA15: 0 | BB15: 0 | BC15: 0 | BD15: 0 | BE15: 0 | BF15: 0 | BG15: 0 | BH15: 0 | BI15: 0.049821138 | BJ15: 0 | BK15: 0 | BL15: 0 | BM15: 0 | BN15: 0 | BO15: 0 | BP15: 0 | BQ15: 0 | BR15: 0 | BS15: 0 | BT15: 0 | BU15: 0 | BV15: 0 | BW15: 23.386658 | BX15: 0 | BY15: 0.0055880943 | BZ15: 0 | CA15: 0 | CB15: 0 | CC15: 0 | CD15: 0 | CE15: 0
B16: Livestock | C16: A31 | D16: =SUM(E16:CE16) -> 74.110589 | E16: 0 | F16: 0 | G16: 0 | H16: 0 | I16: 0 | J16: 0 | K16: 0 | L16: 0 | M16: 0 | N16: 0 | O16: 0 | P16: 0 | Q16: 0 | R16: 0 | S16: 0 | T16: 62.914631 | U16: 0 | V16: 0 | W16: 0 | X16: 0 | Y16: 0 | Z16: 0 | AA16: 0 | AB16: 0.29884435 | AC16: 0 | AD16: 0 | AE16: 0 | AF16: 0 | AG16: 0 | AH16: 0 | AI16: 0 | AJ16: 0 | AK16: 0 | AL16: 0 | AM16: 0 | AN16: 0 | AO16: 0 | AP16: 0 | AQ16: 0 | AR16: 0 | AS16: 0 | AT16: 0 | AU16: 0 | AV16: 0 | AW16: 0 | AX16: 0 | AY16: 0 | AZ16: 0 | BA16: 0 | BB16: 0 | BC16: 0 | BD16: 0 | BE16: 0 | BF16: 0 | BG16: 0 | BH16: 0 | BI16: 10.897113 | BJ16: 0 | BK16: 0 | BL16: 0 | BM16: 0 | BN16: 0 | BO16: 0 | BP16: 0 | BQ16: 0 | BR16: 0 | BS16: 0 | BT16: 0 | BU16: 0 | BV16: 0 | BW16: 0 | BX16: 0 | BY16: 0 | BZ16: 0 | CA16: 0 | CB16: 0 | CC16: 0 | CD16: 0 | CE16: 0
B17: Livestock and hunting products | C17: A32 | D17: =SUM(E17:CE17) -> 15.480699 | E17: 1.8038625 | F17: 2.2061683 | G17: 2.0373297 | H17: 0.89485862 | I17: 1.3157772 | J17: 0 | K17: 0 | L17: 0 | M17: 0 | N17: 0 | O17: 0 | P17: 0 | Q17: 0 | R17: 0 | S17: 0 | T17: 0 | U17: 0 | V17: 0.26824038 | W17: 0 | X17: 1.9186795 | Y17: 0 | Z17: 4.8474251 | AA17: 0 | AB17: 0 | AC17: 0 | AD17: 0 | AE17: 0 | AF17: 0 | AG17: 0 | AH17: 0 | AI17: 0 | AJ17: 0 | AK17: 0 | AL17: 0 | AM17: 0 | AN17: 0 | AO17: 0 | AP17: 0 | AQ17: 0 | AR17: 0 | AS17: 0 | AT17: 0 | AU17: 0 | AV17: 0 | AW17: 0 | AX17: 0 | AY17: 0 | AZ17: 0 | BA17: 0 | BB17: 0 | BC17: 0 | BD17: 0 | BE17: 0 | BF17: 0 | BG17: 0 | BH17: 0 | BI17: 0.1883572 | BJ17: 0 | BK17: 0 | BL17: 0 | BM17: 0 | BN17: 0 | BO17: 0 | BP17: 0 | BQ17: 0 | BR17: 0 | BS17: 0 | BT17: 0 | BU17: 0 | BV17: 0 | BW17: 0 | BX17: 0 | BY17: 0 | BZ17: 0 | CA17: 0 | CB17: 0 | CC17: 0 | CD17: 0 | CE17: 0
B18: Forestry products | C18: A40 | D18: =SUM(E18:CE18) -> 41.990833 | E18: 0 | F18: 0 | G18: 0 | H18: 0 | I18: 0 | J18: 0 | K18: 0 | L18: 0 | M18: 0 | N18: 0 | O18: 0 | P18: 0 | Q18: 0 | R18: 0.50226816 | S18: 0 | T18: 0 | U18: 0 | V18: 0.05381285 | W18: 0 | X18: 0 | Y18: 0 | Z18: 0.47406369 | AA18: 0 | AB18: 0.31611955 | AC18: 0.11706379 | AD18: 0 | AE18: 0 | AF18: 0 | AG18: 7.5525129 | AH18: 0 | AI18: 0 | AJ18: 0 | AK18: 0 | AL18: 0 | AM18: 3.0461097e-05 | AN18: 0.011429148 | AO18: 1.6515926 | AP18: 0 | AQ18: 0 | AR18: 0 | AS18: 0 | AT18: 0 | AU18: 0 | AV18: 0.88784911 | AW18: 0 | AX18: 0 | AY18: 17.452246 | AZ18: 0 | BA18: 0 | BB18: 0 | BC18: 0 | BD18: 0 | BE18: 0 | BF18: 0 | BG18: 0 | BH18: 0 | BI18: 12.971844 | BJ18: 0 | BK18: 0 | BL18: 0 | BM18: 0 | BN18: 0 | BO18: 0 | BP18: 0 | BQ18: 0 | BR18: 0 | BS18: 0 | BT18: 0 | BU18: 0 | BV18: 0 | BW18: 0 | BX18: 0 | BY18: 0 | BZ18: 0 | CA18: 0 | CB18: 0 | CC18: 0 | CD18: 0 | CE18: 0
B19: Fishery products | C19: A50 | D19: =SUM(E19:CE19) -> 0.87082182 | E19: 0 | F19: 0 | G19: 0 | H19: 0 | I19: 0 | J19: 0 | K19: 0 | L19: 0 | M19: 0 | N19: 0 | O19: 0 | P19: 0 | Q19: 0 | R19: 0 | S19: 0 | T19: 0 | U19: 0 | V19: 0 | W19: 0 | X19: 0 | Y19: 0 | Z19: 0 | AA19: 0 | AB19: 0 | AC19: 0 | AD19: 0 | AE19: 0 | AF19: 0 | AG19: 0 | AH19: 0 | AI19: 0 | AJ19: 0 | AK19: 0 | AL19: 0 | AM19: 0 | AN19: 0 | AO19: 0 | AP19: 0 | AQ19: 0 | AR19: 0 | AS19: 0 | AT19: 0 | AU19: 0 | AV19: 0 | AW19: 0 | AX19: 0 | AY19: 0 | AZ19: 0 | BA19: 0 | BB19: 0 | BC19: 0 | BD19: 0 | BE19: 0 | BF19: 0 | BG19: 0 | BH19: 0 | BI19: 0.87082182 | BJ19: 0 | BK19: 0 | BL19: 0 | BM19: 0 | BN19: 0 | BO19: 0 | BP19: 0 | BQ19: 0 | BR19: 0 | BS19: 0 | BT19: 0 | BU19: 0 | BV19: 0 | BW19: 0 | BX19: 0 | BY19: 0 | BZ19: 0 | CA19: 0 | CB19: 0 | CC19: 0 | CD19: 0 | CE19: 0
... B86: Travel debits & credits | C86: V00 | D86: =SUM(E86:CE86) -> 215.81882 | E86: 0 | F86: 0 | G86: 0 | H86: 0 | I86: 0 | J86: 0 | K86: 0 | L86: 0 | M86: 0 | N86: 0 | O86: 0 | P86: 0 | Q86: 0 | R86: 2.4701775 | S86: 2.0791637 | T86: 4.7763964 | U86: 0 | V86: 0.76209705 | W86: 0.51766462 | X86: 0.2242675 | Y86: 17.271405 | Z86: 3.1714237 | AA86: 0.016124605 | AB86: 4.0294623 | AC86: 8.5244514 | AD86: 1.1224235 | AE86: 0.11575722 | AF86: 2.1248764 | AG86: 1.0340633 | AH86: 0.82897379 | AI86: 0.002289378 | AJ86: 2.5450685 | AK86: 0.092656511 | AL86: 0.60044348 | AM86: 0.30081562 | AN86: 1.9138042 | AO86: 0.53812702 | AP86: 5.4032259 | AQ86: 0.28306313 | AR86: 0.25861025 | AS86: 0.80590414 | AT86: 0.57056374 | AU86: 0.034762007 | AV86: 4.6616187 | AW86: 0.97387842 | AX86: 0.30804431 | AY86: 47.502736 | AZ86: 0 | BA86: 0.95339173 | BB86: 0.4227965 | BC86: 11.023114 | BD86: 16.063932 | BE86: 11.974793 | BF86: 5.061235 | BG86: 1.5823429 | BH86: 0.36917149 | BI86: 22.573511 | BJ86: 0.56442285 | BK86: 6.1186427 | BL86: 0.97706019 | BM86: 3.5140543 | BN86: 0.57658845 | BO86: 2.930843 | BP86: 0 | BQ86: 1.1506122 | BR86: 0.54064472 | BS86: 0.26701067 | BT86: 0.68126765 | BU86: 0.99539815 | BV86: 1.2096206 | BW86: 0 | BX86: 3.4482798 | BY86: 1.1984008 | BZ86: 0.049623692 | CA86: 0.17832991 | CB86: 0.16582235 | CC86: 5.3635722 | CD86: 0 | CE86: 0
A90: Mapped to SAM accounts | E90: =SUM(E94:E198) -> 13.826933 | F90: =SUM(F94:F198) -> 0 | G90: =SUM(G94:G198) -> 0 | H90: =SUM(H94:H198) -> 0 | I90: =SUM(I94:I198) -> 0 | J90: =SUM(J94:J198) -> 30.293796 | K90: =SUM(K94:K198) -> 0 | L90: =SUM(L94:L198) -> 0 | ... DD90: =SUM(DD94:DD198) -> 0
E91: Sorghum (A111) | F91: Maize (A112) | G91: Wheat (A113) | H91: Paddy & husked rice (A116) | I91: Other cereals (A119) | J91: Irish potatoes (A121) | K91: Sweet potatoes (A122) | L91: Cassava (A123) | M91: Other roots & tubers (A129) | N91: Dried beans (A131) | O91: Peas & other legumes (A132) | P91: Other vegetables (A139) | Q91: Bananas for beer (A141) | R91: Bananas for cooking (A142) | S91: Bananas (sweet) (A143) | T91: Other fruit & nuts (A149) | U91: Ground nuts (A151) | V91: Soya (A152) | W91: Other oil seeds (A159) | X91: Coffee, not roasted, not decaffeinated (A210) | Y91: Tea (unprocessed green leaf) (A220) | Z91: Tobacco, raw (A291) | AA91: Sugar cane (A292) | AB91: Pyrethrum (A293) | AC91: Agricultural products n.e.c. (A299) | AD91: Bovine cattle, live (A311) | AE91: Sheep, goats, pigs,live (A312) | AF91: Poultry, live (A313) | AG91: Other live animals (A319) | AH91: Raw milk (A321) | AI91: Eggs (A322) | AJ91: Natural honey (A323) | AK91: Other livestock & hunting products (A329) | AL91: Fuel wood (A401) | AM91: Charcoal (A402) | AN91: Other forestry products (A409) | AO91: Fishery products (A500) | AP91: Natural gas (B01) | AQ91: Metal ores (B03) | AR91: Quarry & other mining products (B09) | AS91: Meat and meat products (C11) | AT91: Prepared and preserved fish (C12) | AU91: Prepared and preserved vegetables (C13) | AV91: Animal and vegetable oils and fats (C14) | AW91: Dairy products (C15) | AX91: Grain mill products (C16) | AY91: Bakery products (C17) | AZ91: Animal feed & other by-products (C18) | BA91: Other manufactured food products (C19) | BB91: Alcoholic drinks (C21) | BC91: Soft drinks (C22) | BD91: Tobacco products (C23) | BE91: Textiles, clothing & leather products (C30) | BF91: Wood, paper and related products (C41) | BG91: Printing and reproduction of recorded media (C42) | BH91: Coke and refined petroleum products (C51) | BI91: Chemicals and chemical products (C52) | BJ91: Pharmaceutical products (C53) | BK91: Rubber and plastics products (C54) | BL91: Non-metallic mineral products n.e.c. (C61) | BM91: Manufacture of cement, lime and plaster (C62) | BN91: Manufacture of clay building materials (C63) | BO91: Metals & metal products, except machinery and equipment (C72) | BP91: Machinery and equipment (except transport) (C74) | BQ91: Transport equipment (C76) | BR91: Furniture (C81) | BS91: Other manufacturing (C82) | BT91: Repair and installation of machinery and equipment (C83) | BU91: Electricity, gas, steam and air conditioning supply (D00) | BV91: Water collection, treatment and supply: sewrage (E01) | BW91: Waste collection and management (E02) | BX91: Construction (modern) (F01) | BY91: Construction (traditional) (F02) | BZ91: Maintenance and repair of motor vehicles (G10) | CA91: Wholesale and retail trade of motor vehicles and motorcycles (G21) | CB91: Wholesale trade, except of motor vehicles and motorcycles (G22) | CC91: Retail trade, except of motor vehicles and motorcycles (G23) | CD91: Land transport (H10) | CE91: Air transport (H20) | CF91: Services related to transport (H31) | CG91: Postal and courier activities (H32) | CH91: Hotels & restaurants (I00) | CI91: Publishing, video making, programming & broadcasting activities (J10) | CJ91: Telecommunication (J20) | CK91: Information technology services (J30) | CL91: Monetary institutions (K01) | CM91: Insurance, reinsurance and pension funding, except compulsory social security (K02) | CN91: Other financial services (K03) | CO91: Rental value of dwellings (L01) | CP91: Other real estate activities (L09) | CQ91: Legal, accounting management & head office activities (M01) | CR91: Architectural and engineering activities (M02) | CS91: Other professional, scientific and technical activities (M03) | CT91: Travel agents and tour operators (N01) | CU91: Other administrative and support service activities (N09) | CV91: Public administration and defence; compulsory social security (O00) | CW91: Education (P00) | CX91: Human health activities (Q01) | CY91: Social work activities (Q02) | CZ91: Libraries, archives, museums and other cultural activities (R01) | DA91: Other arts, entertainment and recreation (R09) | DB91: Other service activities (S00) | DC91: Domestic services (T00) | DD91: Travel debits & credits
E92: A11 | J92: A12 | N92: A13 | Q92: A14 | U92: A15 | X92: A21 | Y92: A22 | Z92: A29 | AD92: A31 | AH92: A32 | AL92: A40 | AO92: A50 | AP92: B01 | AQ92: B03 | AR92: B09 | AS92: C11 | AT92: C12 | AU92: C13 | AV92: C14 | AW92: C15 | AX92: C16 | AY92: C17 | AZ92: C18 | BA92: C19 | BB92: C21 | BC92: C22 | BD92: C23 | BE92: C30 | BF92: C41 | BG92: C42 | BH92: C51 | BI92: C52 | BJ92: C53 | BK92: C54 | BL92: C61 | BM92: C62 | BN92: C63 | BO92: C72 | BP92: C74 | BQ92: C76 | BR92: C81 | BS92: C82 | BT92: C83 | BU92: D00 | BV92: E01 | BW92: E02 | BX92: F01 | BY92: F02 | BZ92: G10 | CA92: G21 | CB92: G22 | CC92: G23 | CD92: H10 | CE92: H20 | CF92: H31 | CG92: H32 | CH92: I00 | CI92: J10 | CJ92: J20 | CK92: J30 | CL92: K01 | CM92: K02 | CN92: K03 | CO92: L01 | CP92: L09 | CQ92: M01 | CR92: M02 | CS92: M03 | CT92: N01 | CU92: N09 | CV92: O00 | CW92: P00 | CX92: Q01 | CY92: Q02 | CZ92: R01 | DA92: R09 | DB92: S00 | DC92: T00 | DD92: V00
D93: =SUM(E94:DD198) -> 4606.299 | E93: A111 | F93: A112 | G93: A113 | H93: A116 | I93: A119 | J93: A121 | K93: A122 | L93: A123 | M93: A129 | N93: A131 | O93: A132 | P93: A139 | Q93: A141 | R93: A142 | S93: A143 | T93: A149 | U93: A151 | V93: A152 | W93: A159 | X93: A210 | Y93: A220 | Z93: A291 | AA93: A292 | AB93: A293 | AC93: A299 | AD93: A311 | AE93: A312 | AF93: A313 | AG93: A319 | AH93: A321 | AI93: A322 | AJ93: A323 | AK93: A329 | AL93: A401 | AM93: A402 | AN93: A409 | AO93: A500 | AP93: B01 | AQ93: B03 | AR93: B09 | AS93: C11 | AT93: C12 | AU93: C13 | AV93: C14 | AW93: C15 | AX93: C16 | AY93: C17 | AZ93: C18 | BA93: C19 | BB93: C21 | BC93: C22 | BD93: C23 | BE93: C30 | BF93: C41 | BG93: C42 | BH93: C51 | BI93: C52 | BJ93: C53 | BK93: C54 | BL93: C61 | BM93: C62 | BN93: C63 | BO93: C72 | BP93: C74 | BQ93: C76 | BR93: C81 | BS93: C82 | BT93: C83 | BU93: D00 | BV93: E01 | BW93: E02 | BX93: F01 | BY93: F02 | BZ93: G10 | CA93: G21 | CB93: G22 | CC93: G23 | CD93: H10 | CE93: H20 | CF93: H31 | CG93: H32 | CH93: I00 | CI93: J10 | CJ93: J20 | CK93: J30 | CL93: K01 | CM93: K02 | CN93: K03 | CO93: L01 | CP93: L09 | CQ93: M01 | CR93: M02 | CS93: M03 | CT93: N01 | CU93: N09 | CV93: O00 | CW93: P00 | CX93: Q01 | CY93: Q02 | CZ93: R01 | DA93: R09 | DB93: S00 | DC93: T00 | DD93: V00
B94: Sorghum (A111) | C94: A11 | D94: A111 | E94: =IF(ISNA(INDEX($E$8:$CE$86,MATCH($C94,$C$8:$C$86,0),MATCH(E$92,$E$6:$CE$6,0))),0,INDEX($E$8:$CE$86,MATCH($C94,$C$8:$C$86,0),MATCH(E$92,$E$6:$CE$6,0))) -> 1.5554548 | F94: =IF(ISNA(INDEX($E$8:$CE$86,MATCH($C94,$C$8:$C$86,0),MATCH(F$92,$E$6:$CE$6,0))),0,INDEX($E$8:$CE$86,MATCH($C94,$C$8:$C$86,0),MATCH(F$92,$E$6:$CE$6,0))) -> 0 | G94: =IF(ISNA(INDEX($E$8:$CE$86,MATCH($C94,$C$8:$C$86,0),MATCH(G$92,$E$6:$CE$6,0))),0,INDEX($E$8:$CE$86,MATCH($C94,$C$8:$C$86,0),MATCH(G$92,$E$6:$CE$6,0))) -> 0 | H94: =IF(ISNA(INDEX($E$8:$CE$86,MATCH($C94,$C$8:$C$86,0),MATCH(H$92,$E$6:$CE$6,0))),0,INDEX($E$8:$CE$86,MATCH($C94,$C$8:$C$86,0),MATCH(H$92,$E$6:$CE$6,0))) -> 0 | I94: =IF(ISNA(INDEX($E$8:$CE$86,MATCH($C94,$C$8:$C$86,0),MATCH(I$92,$E$6:$CE$6,0))),0,INDEX($E$8:$CE$86,MATCH($C94,$C$8:$C$86,0),MATCH(I$92,$E$6:$CE$6,0))) -> 0 | J94: =IF(ISNA(INDEX($E$8:$CE$86,MATCH($C94,$C$8:$C$86,0),MATCH(J$92,$E$6:$CE$6,0))),0,INDEX($E$8:$CE$86,MATCH($C94,$C$8:$C$86,0),MATCH(J$92,$E$6:$CE$6,0))) -> 0 | K94: =IF(ISNA(INDEX($E$8:$CE$86,MATCH($C94,$C$8:$C$86,0),MATCH(K$92,$E$6:$CE$6,0))),0,INDEX($E$8:$CE$86,MATCH($C94,$C$8:$C$86,0),MATCH(K$92,$E$6:$CE$6,0))) -> 0 | L94: =IF(ISNA(INDEX($E$8:$CE$86,MATCH($C94,$C$8:$C$86,0),MATCH(L$92,$E$6:$CE$6,0))),0,INDEX($E$8:$CE$86,MATCH($C94,$C$8:$C$86,0),MATCH(L$92,$E$6:$CE$6,0))) -> 0 | ... DD94: =IF(ISNA(INDEX($E$8:$CE$86,MATCH($C94,$C$8:$C$86,0),MATCH(DD$92,$E$6:$CE$6,0))),0,INDEX($E$8:$CE$86,MATCH($C94,$C$8:$C$86,0),MATCH(DD$92,$E$6:$CE$6,0))) -> 0
B95: Maize (A112) | D95: A112 | E95: =IF(ISNA(INDEX($E$8:$CE$86,MATCH($C95,$C$8:$C$86,0),MATCH(E$92,$E$6:$CE$6,0))),0,INDEX($E$8:$CE$86,MATCH($C95,$C$8:$C$86,0),MATCH(E$92,$E$6:$CE$6,0))) -> 0 | F95: =IF(ISNA(INDEX($E$8:$CE$86,MATCH($C95,$C$8:$C$86,0),MATCH(F$92,$E$6:$CE$6,0))),0,INDEX($E$8:$CE$86,MATCH($C95,$C$8:$C$86,0),MATCH(F$92,$E$6:$CE$6,0))) -> 0 | G95: =IF(ISNA(INDEX($E$8:$CE$86,MATCH($C95,$C$8:$C$86,0),MATCH(G$92,$E$6:$CE$6,0))),0,INDEX($E$8:$CE$86,MATCH($C95,$C$8:$C$86,0),MATCH(G$92,$E$6:$CE$6,0))) -> 0 | H95: =IF(ISNA(INDEX($E$8:$CE$86,MATCH($C95,$C$8:$C$86,0),MATCH(H$92,$E$6:$CE$6,0))),0,INDEX($E$8:$CE$86,MATCH($C95,$C$8:$C$86,0),MATCH(H$92,$E$6:$CE$6,0))) -> 0 | I95: =IF(ISNA(INDEX($E$8:$CE$86,MATCH($C95,$C$8:$C$86,0),MATCH(I$92,$E$6:$CE$6,0))),0,INDEX($E$8:$CE$86,MATCH($C95,$C$8:$C$86,0),MATCH(I$92,$E$6:$CE$6,0))) -> 0 | J95: =IF(ISNA(INDEX($E$8:$CE$86,MATCH($C95,$C$8:$C$86,0),MATCH(J$92,$E$6:$CE$6,0))),0,INDEX($E$8:$CE$86,MATCH($C95,$C$8:$C$86,0),MATCH(J$92,$E$6:$CE$6,0))) -> 0 | K95: =IF(ISNA(INDEX($E$8:$CE$86,MATCH($C95,$C$8:$C$86,0),MATCH(K$92,$E$6:$CE$6,0))),0,INDEX($E$8:$CE$86,MATCH($C95,$C$8:$C$86,0),MATCH(K$92,$E$6:$CE$6,0))) -> 0 | L95: =IF(ISNA(INDEX($E$8:$CE$86,MATCH($C95,$C$8:$C$86,0),MATCH(L$92,$E$6:$CE$6,0))),0,INDEX($E$8:$CE$86,MATCH($C95,$C$8:$C$86,0),MATCH(L$92,$E$6:$CE$6,0))) -> 0 | ... DD95: =IF(ISNA(INDEX($E$8:$CE$86,MATCH($C95,$C$8:$C$86,0),MATCH(DD$92,$E$6:$CE$6,0))),0,INDEX($E$8:$CE$86,MATCH($C95,$C$8:$C$86,0),MATCH(DD$92,$E$6:$CE$6,0))) -> 0
B96: Wheat (A113) | D96: A113 | E96: =IF(ISNA(INDEX($E$8:$CE$86,MATCH($C96,$C$8:$C$86,0),MATCH(E$92,$E$6:$CE$6,0))),0,INDEX($E$8:$CE$86,MATCH($C96,$C$8:$C$86,0),MATCH(E$92,$E$6:$CE$6,0))) -> 0 | F96: =IF(ISNA(INDEX($E$8:$CE$86,MATCH($C96,$C$8:$C$86,0),MATCH(F$92,$E$6:$CE$6,0))),0,INDEX($E$8:$CE$86,MATCH($C96,$C$8:$C$86,0),MATCH(F$92,$E$6:$CE$6,0))) -> 0 | G96: =IF(ISNA(INDEX($E$8:$CE$86,MATCH($C96,$C$8:$C$86,0),MATCH(G$92,$E$6:$CE$6,0))),0,INDEX($E$8:$CE$86,MATCH($C96,$C$8:$C$86,0),MATCH(G$92,$E$6:$CE$6,0))) -> 0 | H96: =IF(ISNA(INDEX($E$8:$CE$86,MATCH($C96,$C$8:$C$86,0),MATCH(H$92,$E$6:$CE$6,0))),0,INDEX($E$8:$CE$86,MATCH($C96,$C$8:$C$86,0),MATCH(H$92,$E$6:$CE$6,0))) -> 0 | I96: =IF(ISNA(INDEX($E$8:$CE$86,MATCH($C96,$C$8:$C$86,0),MATCH(I$92,$E$6:$CE$6,0))),0,INDEX($E$8:$CE$86,MATCH($C96,$C$8:$C$86,0),MATCH(I$92,$E$6:$CE$6,0))) -> 0 | J96: =IF(ISNA(INDEX($E$8:$CE$86,MATCH($C96,$C$8:$C$86,0),MATCH(J$92,$E$6:$CE$6,0))),0,INDEX($E$8:$CE$86,MATCH($C96,$C$8:$C$86,0),MATCH(J$92,$E$6:$CE$6,0))) -> 0 | K96: =IF(ISNA(INDEX($E$8:$CE$86,MATCH($C96,$C$8:$C$86,0),MATCH(K$92,$E$6:$CE$6,0))),0,INDEX($E$8:$CE$86,MATCH($C96,$C$8:$C$86,0),MATCH(K$92,$E$6:$CE$6,0))) -> 0 | L96: =IF(ISNA(INDEX($E$8:$CE$86,MATCH($C96,$C$8:$C$86,0),MATCH(L$92,$E$6:$CE$6,0))),0,INDEX($E$8:$CE$86,MATCH($C96,$C$8:$C$86,0),MATCH(L$92,$E$6:$CE$6,0))) -> 0 | ... DD96: =IF(ISNA(INDEX($E$8:$CE$86,MATCH($C96,$C$8:$C$86,0),MATCH(DD$92,$E$6:$CE$6,0))),0,INDEX($E$8:$CE$86,MATCH($C96,$C$8:$C$86,0),MATCH(DD$92,$E$6:$CE$6,0))) -> 0
B97: Paddy & husked rice (A116) | D97: A116 | E97: =IF(ISNA(INDEX($E$8:$CE$86,MATCH($C97,$C$8:$C$86,0),MATCH(E$92,$E$6:$CE$6,0))),0,INDEX($E$8:$CE$86,MATCH($C97,$C$8:$C$86,0),MATCH(E$92,$E$6:$CE$6,0))) -> 0 | F97: =IF(ISNA(INDEX($E$8:$CE$86,MATCH($C97,$C$8:$C$86,0),MATCH(F$92,$E$6:$CE$6,0))),0,INDEX($E$8:$CE$86,MATCH($C97,$C$8:$C$86,0),MATCH(F$92,$E$6:$CE$6,0))) -> 0 | G97: =IF(ISNA(INDEX($E$8:$CE$86,MATCH($C97,$C$8:$C$86,0),MATCH(G$92,$E$6:$CE$6,0))),0,INDEX($E$8:$CE$86,MATCH($C97,$C$8:$C$86,0),MATCH(G$92,$E$6:$CE$6,0))) -> 0 | H97: =IF(ISNA(INDEX($E$8:$CE$86,MATCH($C97,$C$8:$C$86,0),MATCH(H$92,$E$6:$CE$6,0))),0,INDEX($E$8:$CE$86,MATCH($C97,$C$8:$C$86,0),MATCH(H$92,$E$6:$CE$6,0))) -> 0 | I97: =IF(ISNA(INDEX($E$8:$CE$86,MATCH($C97,$C$8:$C$86,0),MATCH(I$92,$E$6:$CE$6,0))),0,INDEX($E$8:$CE$86,MATCH($C97,$C$8:$C$86,0),MATCH(I$92,$E$6:$CE$6,0))) -> 0 | J97: =IF(ISNA(INDEX($E$8:$CE$86,MATCH($C97,$C$8:$C$86,0),MATCH(J$92,$E$6:$CE$6,0))),0,INDEX($E$8:$CE$86,MATCH($C97,$C$8:$C$86,0),MATCH(J$92,$E$6:$CE$6,0))) -> 0 | K97: =IF(ISNA(INDEX($E$8:$CE$86,MATCH($C97,$C$8:$C$86,0),MATCH(K$92,$E$6:$CE$6,0))),0,INDEX($E$8:$CE$86,MATCH($C97,$C$8:$C$86,0),MATCH(K$92,$E$6:$CE$6,0))) -> 0 | L97: =IF(ISNA(INDEX($E$8:$CE$86,MATCH($C97,$C$8:$C$86,0),MATCH(L$92,$E$6:$CE$6,0))),0,INDEX($E$8:$CE$86,MATCH($C97,$C$8:$C$86,0),MATCH(L$92,$E$6:$CE$6,0))) -> 0 | ... DD97: =IF(ISNA(INDEX($E$8:$CE$86,MATCH($C97,$C$8:$C$86,0),MATCH(DD$92,$E$6:$CE$6,0))),0,INDEX($E$8:$CE$86,MATCH($C97,$C$8:$C$86,0),MATCH(DD$92,$E$6:$CE$6,0))) -> 0
B98: Other cereals (A119) | D98: A119 | E98: =IF(ISNA(INDEX($E$8:$CE$86,MATCH($C98,$C$8:$C$86,0),MATCH(E$92,$E$6:$CE$6,0))),0,INDEX($E$8:$CE$86,MATCH($C98,$C$8:$C$86,0),MATCH(E$92,$E$6:$CE$6,0))) -> 0 | F98: =IF(ISNA(INDEX($E$8:$CE$86,MATCH($C98,$C$8:$C$86,0),MATCH(F$92,$E$6:$CE$6,0))),0,INDEX($E$8:$CE$86,MATCH($C98,$C$8:$C$86,0),MATCH(F$92,$E$6:$CE$6,0))) -> 0 | G98: =IF(ISNA(INDEX($E$8:$CE$86,MATCH($C98,$C$8:$C$86,0),MATCH(G$92,$E$6:$CE$6,0))),0,INDEX($E$8:$CE$86,MATCH($C98,$C$8:$C$86,0),MATCH(G$92,$E$6:$CE$6,0))) -> 0 | H98: =IF(ISNA(INDEX($E$8:$CE$86,MATCH($C98,$C$8:$C$86,0),MATCH(H$92,$E$6:$CE$6,0))),0,INDEX($E$8:$CE$86,MATCH($C98,$C$8:$C$86,0),MATCH(H$92,$E$6:$CE$6,0))) -> 0 | I98: =IF(ISNA(INDEX($E$8:$CE$86,MATCH($C98,$C$8:$C$86,0),MATCH(I$92,$E$6:$CE$6,0))),0,INDEX($E$8:$CE$86,MATCH($C98,$C$8:$C$86,0),MATCH(I$92,$E$6:$CE$6,0))) -> 0 | J98: =IF(ISNA(INDEX($E$8:$CE$86,MATCH($C98,$C$8:$C$86,0),MATCH(J$92,$E$6:$CE$6,0))),0,INDEX($E$8:$CE$86,MATCH($C98,$C$8:$C$86,0),MATCH(J$92,$E$6:$CE$6,0))) -> 0 | K98: =IF(ISNA(INDEX($E$8:$CE$86,MATCH($C98,$C$8:$C$86,0),MATCH(K$92,$E$6:$CE$6,0))),0,INDEX($E$8:$CE$86,MATCH($C98,$C$8:$C$86,0),MATCH(K$92,$E$6:$CE$6,0))) -> 0 | L98: =IF(ISNA(INDEX($E$8:$CE$86,MATCH($C98,$C$8:$C$86,0),MATCH(L$92,$E$6:$CE$6,0))),0,INDEX($E$8:$CE$86,MATCH($C98,$C$8:$C$86,0),MATCH(L$92,$E$6:$CE$6,0))) -> 0 | ... DD98: =IF(ISNA(INDEX($E$8:$CE$86,MATCH($C98,$C$8:$C$86,0),MATCH(DD$92,$E$6:$CE$6,0))),0,INDEX($E$8:$CE$86,MATCH($C98,$C$8:$C$86,0),MATCH(DD$92,$E$6:$CE$6,0))) -> 0
B99: Irish potatoes (A121) | C99: A12 | D99: A121 | E99: =IF(ISNA(INDEX($E$8:$CE$86,MATCH($C99,$C$8:$C$86,0),MATCH(E$92,$E$6:$CE$6,0))),0,INDEX($E$8:$CE$86,MATCH($C99,$C$8:$C$86,0),MATCH(E$92,$E$6:$CE$6,0))) -> 0 | F99: =IF(ISNA(INDEX($E$8:$CE$86,MATCH($C99,$C$8:$C$86,0),MATCH(F$92,$E$6:$CE$6,0))),0,INDEX($E$8:$CE$86,MATCH($C99,$C$8:$C$86,0),MATCH(F$92,$E$6:$CE$6,0))) -> 0 | G99: =IF(ISNA(INDEX($E$8:$CE$86,MATCH($C99,$C$8:$C$86,0),MATCH(G$92,$E$6:$CE$6,0))),0,INDEX($E$8:$CE$86,MATCH($C99,$C$8:$C$86,0),MATCH(G$92,$E$6:$CE$6,0))) -> 0 | H99: =IF(ISNA(INDEX($E$8:$CE$86,MATCH($C99,$C$8:$C$86,0),MATCH(H$92,$E$6:$CE$6,0))),0,INDEX($E$8:$CE$86,MATCH($C99,$C$8:$C$86,0),MATCH(H$92,$E$6:$CE$6,0))) -> 0 | I99: =IF(ISNA(INDEX($E$8:$CE$86,MATCH($C99,$C$8:$C$86,0),MATCH(I$92,$E$6:$CE$6,0))),0,INDEX($E$8:$CE$86,MATCH($C99,$C$8:$C$86,0),MATCH(I$92,$E$6:$CE$6,0))) -> 0 | J99: =IF(ISNA(INDEX($E$8:$CE$86,MATCH($C99,$C$8:$C$86,0),MATCH(J$92,$E$6:$CE$6,0))),0,INDEX($E$8:$CE$86,MATCH($C99,$C$8:$C$86,0),MATCH(J$92,$E$6:$CE$6,0))) -> 5.3546377 | K99: =IF(ISNA(INDEX($E$8:$CE$86,MATCH($C99,$C$8:$C$86,0),MATCH(K$92,$E$6:$CE$6,0))),0,INDEX($E$8:$CE$86,MATCH($C99,$C$8:$C$86,0),MATCH(K$92,$E$6:$CE$6,0))) -> 0 | L99: =IF(ISNA(INDEX($E$8:$CE$86,MATCH($C99,$C$8:$C$86,0),MATCH(L$92,$E$6:$CE$6,0))),0,INDEX($E$8:$CE$86,MATCH($C99,$C$8:$C$86,0),MATCH(L$92,$E$6:$CE$6,0))) -> 0 | ... DD99: =IF(ISNA(INDEX($E$8:$CE$86,MATCH($C99,$C$8:$C$86,0),MATCH(DD$92,$E$6:$CE$6,0))),0,INDEX($E$8:$CE$86,MATCH($C99,$C$8:$C$86,0),MATCH(DD$92,$E$6:$CE$6,0))) -> 0
B100: Sweet potatoes (A122) | D100: A122 | E100: =IF(ISNA(INDEX($E$8:$CE$86,MATCH($C100,$C$8:$C$86,0),MATCH(E$92,$E$6:$CE$6,0))),0,INDEX($E$8:$CE$86,MATCH($C100,$C$8:$C$86,0),MATCH(E$92,$E$6:$CE$6,0))) -> 0 | F100: =IF(ISNA(INDEX($E$8:$CE$86,MATCH($C100,$C$8:$C$86,0),MATCH(F$92,$E$6:$CE$6,0))),0,INDEX($E$8:$CE$86,MATCH($C100,$C$8:$C$86,0),MATCH(F$92,$E$6:$CE$6,0))) -> 0 | G100: =IF(ISNA(INDEX($E$8:$CE$86,MATCH($C100,$C$8:$C$86,0),MATCH(G$92,$E$6:$CE$6,0))),0,INDEX($E$8:$CE$86,MATCH($C100,$C$8:$C$86,0),MATCH(G$92,$E$6:$CE$6,0))) -> 0 | H100: =IF(ISNA(INDEX($E$8:$CE$86,MATCH($C100,$C$8:$C$86,0),MATCH(H$92,$E$6:$CE$6,0))),0,INDEX($E$8:$CE$86,MATCH($C100,$C$8:$C$86,0),MATCH(H$92,$E$6:$CE$6,0))) -> 0 | I100: =IF(ISNA(INDEX($E$8:$CE$86,MATCH($C100,$C$8:$C$86,0),MATCH(I$92,$E$6:$CE$6,0))),0,INDEX($E$8:$CE$86,MATCH($C100,$C$8:$C$86,0),MATCH(I$92,$E$6:$CE$6,0))) -> 0 | J100: =IF(ISNA(INDEX($E$8:$CE$86,MATCH($C100,$C$8:$C$86,0),MATCH(J$92,$E$6:$CE$6,0))),0,INDEX($E$8:$CE$86,MATCH($C100,$C$8:$C$86,0),MATCH(J$92,$E$6:$CE$6,0))) -> 0 | K100: =IF(ISNA(INDEX($E$8:$CE$86,MATCH($C100,$C$8:$C$86,0),MATCH(K$92,$E$6:$CE$6,0))),0,INDEX($E$8:$CE$86,MATCH($C100,$C$8:$C$86,0),MATCH(K$92,$E$6:$CE$6,0))) -> 0 | L100: =IF(ISNA(INDEX($E$8:$CE$86,MATCH($C100,$C$8:$C$86,0),MATCH(L$92,$E$6:$CE$6,0))),0,INDEX($E$8:$CE$86,MATCH($C100,$C$8:$C$86,0),MATCH(L$92,$E$6:$CE$6,0))) -> 0 | ... DD100: =IF(ISNA(INDEX($E$8:$CE$86,MATCH($C100,$C$8:$C$86,0),MATCH(DD$92,$E$6:$CE$6,0))),0,INDEX($E$8:$CE$86,MATCH($C100,$C$8:$C$86,0),MATCH(DD$92,$E$6:$CE$6,0))) -> 0
B101: Cassava (A123) | D101: A123 | E101: =IF(ISNA(INDEX($E$8:$CE$86,MATCH($C101,$C$8:$C$86,0),MATCH(E$92,$E$6:$CE$6,0))),0,INDEX($E$8:$CE$86,MATCH($C101,$C$8:$C$86,0),MATCH(E$92,$E$6:$CE$6,0))) -> 0 | F101: =IF(ISNA(INDEX($E$8:$CE$86,MATCH($C101,$C$8:$C$86,0),MATCH(F$92,$E$6:$CE$6,0))),0,INDEX($E$8:$CE$86,MATCH($C101,$C$8:$C$86,0),MATCH(F$92,$E$6:$CE$6,0))) -> 0 | G101: =IF(ISNA(INDEX($E$8:$CE$86,MATCH($C101,$C$8:$C$86,0),MATCH(G$92,$E$6:$CE$6,0))),0,INDEX($E$8:$CE$86,MATCH($C101,$C$8:$C$86,0),MATCH(G$92,$E$6:$CE$6,0))) -> 0 | H101: =IF(ISNA(INDEX($E$8:$CE$86,MATCH($C101,$C$8:$C$86,0),MATCH(H$92,$E$6:$CE$6,0))),0,INDEX($E$8:$CE$86,MATCH($C101,$C$8:$C$86,0),MATCH(H$92,$E$6:$CE$6,0))) -> 0 | I101: =IF(ISNA(INDEX($E$8:$CE$86,MATCH($C101,$C$8:$C$86,0),MATCH(I$92,$E$6:$CE$6,0))),0,INDEX($E$8:$CE$86,MATCH($C101,$C$8:$C$86,0),MATCH(I$92,$E$6:$CE$6,0))) -> 0 | J101: =IF(ISNA(INDEX($E$8:$CE$86,MATCH($C101,$C$8:$C$86,0),MATCH(J$92,$E$6:$CE$6,0))),0,INDEX($E$8:$CE$86,MATCH($C101,$C$8:$C$86,0),MATCH(J$92,$E$6:$CE$6,0))) -> 0 | K101: =IF(ISNA(INDEX($E$8:$CE$86,MATCH($C101,$C$8:$C$86,0),MATCH(K$92,$E$6:$CE$6,0))),0,INDEX($E$8:$CE$86,MATCH($C101,$C$8:$C$86,0),MATCH(K$92,$E$6:$CE$6,0))) -> 0 | L101: =IF(ISNA(INDEX($E$8:$CE$86,MATCH($C101,$C$8:$C$86,0),MATCH(L$92,$E$6:$CE$6,0))),0,INDEX($E$8:$CE$86,MATCH($C101,$C$8:$C$86,0),MATCH(L$92,$E$6:$CE$6,0))) -> 0 | ... DD101: =IF(ISNA(INDEX($E$8:$CE$86,MATCH($C101,$C$8:$C$86,0),MATCH(DD$92,$E$6:$CE$6,0))),0,INDEX($E$8:$CE$86,MATCH($C101,$C$8:$C$86,0),MATCH(DD$92,$E$6:$CE$6,0))) -> 0
B102: Other roots & tubers (A129) | D102: A129 | E102: =IF(ISNA(INDEX($E$8:$CE$86,MATCH($C102,$C$8:$C$86,0),MATCH(E$92,$E$6:$CE$6,0))),0,INDEX($E$8:$CE$86,MATCH($C102,$C$8:$C$86,0),MATCH(E$92,$E$6:$CE$6,0))) -> 0 | F102: =IF(ISNA(INDEX($E$8:$CE$86,MATCH($C102,$C$8:$C$86,0),MATCH(F$92,$E$6:$CE$6,0))),0,INDEX($E$8:$CE$86,MATCH($C102,$C$8:$C$86,0),MATCH(F$92,$E$6:$CE$6,0))) -> 0 | G102: =IF(ISNA(INDEX($E$8:$CE$86,MATCH($C102,$C$8:$C$86,0),MATCH(G$92,$E$6:$CE$6,0))),0,INDEX($E$8:$CE$86,MATCH($C102,$C$8:$C$86,0),MATCH(G$92,$E$6:$CE$6,0))) -> 0 | H102: =IF(ISNA(INDEX($E$8:$CE$86,MATCH($C102,$C$8:$C$86,0),MATCH(H$92,$E$6:$CE$6,0))),0,INDEX($E$8:$CE$86,MATCH($C102,$C$8:$C$86,0),MATCH(H$92,$E$6:$CE$6,0))) -> 0 | I102: =IF(ISNA(INDEX($E$8:$CE$86,MATCH($C102,$C$8:$C$86,0),MATCH(I$92,$E$6:$CE$6,0))),0,INDEX($E$8:$CE$86,MATCH($C102,$C$8:$C$86,0),MATCH(I$92,$E$6:$CE$6,0))) -> 0 | J102: =IF(ISNA(INDEX($E$8:$CE$86,MATCH($C102,$C$8:$C$86,0),MATCH(J$92,$E$6:$CE$6,0))),0,INDEX($E$8:$CE$86,MATCH($C102,$C$8:$C$86,0),MATCH(J$92,$E$6:$CE$6,0))) -> 0 | K102: =IF(ISNA(INDEX($E$8:$CE$86,MATCH($C102,$C$8:$C$86,0),MATCH(K$92,$E$6:$CE$6,0))),0,INDEX($E$8:$CE$86,MATCH($C102,$C$8:$C$86,0),MATCH(K$92,$E$6:$CE$6,0))) -> 0 | L102: =IF(ISNA(INDEX($E$8:$CE$86,MATCH($C102,$C$8:$C$86,0),MATCH(L$92,$E$6:$CE$6,0))),0,INDEX($E$8:$CE$86,MATCH($C102,$C$8:$C$86,0),MATCH(L$92,$E$6:$CE$6,0))) -> 0 | ... DD102: =IF(ISNA(INDEX($E$8:$CE$86,MATCH($C102,$C$8:$C$86,0),MATCH(DD$92,$E$6:$CE$6,0))),0,INDEX($E$8:$CE$86,MATCH($C102,$C$8:$C$86,0),MATCH(DD$92,$E$6:$CE$6,0))) -> 0
B103: Dried beans (A131) | C103: A13 | D103: A131 | E103: =IF(ISNA(INDEX($E$8:$CE$86,MATCH($C103,$C$8:$C$86,0),MATCH(E$92,$E$6:$CE$6,0))),0,INDEX($E$8:$CE$86,MATCH($C103,$C$8:$C$86,0),MATCH(E$92,$E$6:$CE$6,0))) -> 0 | F103: =IF(ISNA(INDEX($E$8:$CE$86,MATCH($C103,$C$8:$C$86,0),MATCH(F$92,$E$6:$CE$6,0))),0,INDEX($E$8:$CE$86,MATCH($C103,$C$8:$C$86,0),MATCH(F$92,$E$6:$CE$6,0))) -> 0 | G103: =IF(ISNA(INDEX($E$8:$CE$86,MATCH($C103,$C$8:$C$86,0),MATCH(G$92,$E$6:$CE$6,0))),0,INDEX($E$8:$CE$86,MATCH($C103,$C$8:$C$86,0),MATCH(G$92,$E$6:$CE$6,0))) -> 0 | H103: =IF(ISNA(INDEX($E$8:$CE$86,MATCH($C103,$C$8:$C$86,0),MATCH(H$92,$E$6:$CE$6,0))),0,INDEX($E$8:$CE$86,MATCH($C103,$C$8:$C$86,0),MATCH(H$92,$E$6:$CE$6,0))) -> 0 | I103: =IF(ISNA(INDEX($E$8:$CE$86,MATCH($C103,$C$8:$C$86,0),MATCH(I$92,$E$6:$CE$6,0))),0,INDEX($E$8:$CE$86,MATCH($C103,$C$8:$C$86,0),MATCH(I$92,$E$6:$CE$6,0))) -> 0 | J103: =IF(ISNA(INDEX($E$8:$CE$86,MATCH($C103,$C$8:$C$86,0),MATCH(J$92,$E$6:$CE$6,0))),0,INDEX($E$8:$CE$86,MATCH($C103,$C$8:$C$86,0),MATCH(J$92,$E$6:$CE$6,0))) -> 0 | K103: =IF(ISNA(INDEX($E$8:$CE$86,MATCH($C103,$C$8:$C$86,0),MATCH(K$92,$E$6:$CE$6,0))),0,INDEX($E$8:$CE$86,MATCH($C103,$C$8:$C$86,0),MATCH(K$92,$E$6:$CE$6,0))) -> 0 | L103: =IF(ISNA(INDEX($E$8:$CE$86,MATCH($C103,$C$8:$C$86,0),MATCH(L$92,$E$6:$CE$6,0))),0,INDEX($E$8:$CE$86,MATCH($C103,$C$8:$C$86,0),MATCH(L$92,$E$6:$CE$6,0))) -> 0 | ... DD103: =IF(ISNA(INDEX($E$8:$CE$86,MATCH($C103,$C$8:$C$86,0),MATCH(DD$92,$E$6:$CE$6,0))),0,INDEX($E$8:$CE$86,MATCH($C103,$C$8:$C$86,0),MATCH(DD$92,$E$6:$CE$6,0))) -> 0
B104: Peas & other legumes (A132) | D104: A132 | E104: =IF(ISNA(INDEX($E$8:$CE$86,MATCH($C104,$C$8:$C$86,0),MATCH(E$92,$E$6:$CE$6,0))),0,INDEX($E$8:$CE$86,MATCH($C104,$C$8:$C$86,0),MATCH(E$92,$E$6:$CE$6,0))) -> 0 | F104: =IF(ISNA(INDEX($E$8:$CE$86,MATCH($C104,$C$8:$C$86,0),MATCH(F$92,$E$6:$CE$6,0))),0,INDEX($E$8:$CE$86,MATCH($C104,$C$8:$C$86,0),MATCH(F$92,$E$6:$CE$6,0))) -> 0 | G104: =IF(ISNA(INDEX($E$8:$CE$86,MATCH($C104,$C$8:$C$86,0),MATCH(G$92,$E$6:$CE$6,0))),0,INDEX($E$8:$CE$86,MATCH($C104,$C$8:$C$86,0),MATCH(G$92,$E$6:$CE$6,0))) -> 0 | H104: =IF(ISNA(INDEX($E$8:$CE$86,MATCH($C104,$C$8:$C$86,0),MATCH(H$92,$E$6:$CE$6,0))),0,INDEX($E$8:$CE$86,MATCH($C104,$C$8:$C$86,0),MATCH(H$92,$E$6:$CE$6,0))) -> 0 | I104: =IF(ISNA(INDEX($E$8:$CE$86,MATCH($C104,$C$8:$C$86,0),MATCH(I$92,$E$6:$CE$6,0))),0,INDEX($E$8:$CE$86,MATCH($C104,$C$8:$C$86,0),MATCH(I$92,$E$6:$CE$6,0))) -> 0 | J104: =IF(ISNA(INDEX($E$8:$CE$86,MATCH($C104,$C$8:$C$86,0),MATCH(J$92,$E$6:$CE$6,0))),0,INDEX($E$8:$CE$86,MATCH($C104,$C$8:$C$86,0),MATCH(J$92,$E$6:$CE$6,0))) -> 0 | K104: =IF(ISNA(INDEX($E$8:$CE$86,MATCH($C104,$C$8:$C$86,0),MATCH(K$92,$E$6:$CE$6,0))),0,INDEX($E$8:$CE$86,MATCH($C104,$C$8:$C$86,0),MATCH(K$92,$E$6:$CE$6,0))) -> 0 | L104: =IF(ISNA(INDEX($E$8:$CE$86,MATCH($C104,$C$8:$C$86,0),MATCH(L$92,$E$6:$CE$6,0))),0,INDEX($E$8:$CE$86,MATCH($C104,$C$8:$C$86,0),MATCH(L$92,$E$6:$CE$6,0))) -> 0 | ... DD104: =IF(ISNA(INDEX($E$8:$CE$86,MATCH($C104,$C$8:$C$86,0),MATCH(DD$92,$E$6:$CE$6,0))),0,INDEX($E$8:$CE$86,MATCH($C104,$C$8:$C$86,0),MATCH(DD$92,$E$6:$CE$6,0))) -> 0
B105: Other vegetables (A139) | D105: A139 | E105: =IF(ISNA(INDEX($E$8:$CE$86,MATCH($C105,$C$8:$C$86,0),MATCH(E$92,$E$6:$CE$6,0))),0,INDEX($E$8:$CE$86,MATCH($C105,$C$8:$C$86,0),MATCH(E$92,$E$6:$CE$6,0))) -> 0 | F105: =IF(ISNA(INDEX($E$8:$CE$86,MATCH($C105,$C$8:$C$86,0),MATCH(F$92,$E$6:$CE$6,0))),0,INDEX($E$8:$CE$86,MATCH($C105,$C$8:$C$86,0),MATCH(F$92,$E$6:$CE$6,0))) -> 0 | G105: =IF(ISNA(INDEX($E$8:$CE$86,MATCH($C105,$C$8:$C$86,0),MATCH(G$92,$E$6:$CE$6,0))),0,INDEX($E$8:$CE$86,MATCH($C105,$C$8:$C$86,0),MATCH(G$92,$E$6:$CE$6,0))) -> 0 | H105: =IF(ISNA(INDEX($E$8:$CE$86,MATCH($C105,$C$8:$C$86,0),MATCH(H$92,$E$6:$CE$6,0))),0,INDEX($E$8:$CE$86,MATCH($C105,$C$8:$C$86,0),MATCH(H$92,$E$6:$CE$6,0))) -> 0 | I105: =IF(ISNA(INDEX($E$8:$CE$86,MATCH($C105,$C$8:$C$86,0),MATCH(I$92,$E$6:$CE$6,0))),0,INDEX($E$8:$CE$86,MATCH($C105,$C$8:$C$86,0),MATCH(I$92,$E$6:$CE$6,0))) -> 0 | J105: =IF(ISNA(INDEX($E$8:$CE$86,MATCH($C105,$C$8:$C$86,0),MATCH(J$92,$E$6:$CE$6,0))),0,INDEX($E$8:$CE$86,MATCH($C105,$C$8:$C$86,0),MATCH(J$92,$E$6:$CE$6,0))) -> 0 | K105: =IF(ISNA(INDEX($E$8:$CE$86,MATCH($C105,$C$8:$C$86,0),MATCH(K$92,$E$6:$CE$6,0))),0,INDEX($E$8:$CE$86,MATCH($C105,$C$8:$C$86,0),MATCH(K$92,$E$6:$CE$6,0))) -> 0 | L105: =IF(ISNA(INDEX($E$8:$CE$86,MATCH($C105,$C$8:$C$86,0),MATCH(L$92,$E$6:$CE$6,0))),0,INDEX($E$8:$CE$86,MATCH($C105,$C$8:$C$86,0),MATCH(L$92,$E$6:$CE$6,0))) -> 0 | ... DD105: =IF(ISNA(INDEX($E$8:$CE$86,MATCH($C105,$C$8:$C$86,0),MATCH(DD$92,$E$6:$CE$6,0))),0,INDEX($E$8:$CE$86,MATCH($C105,$C$8:$C$86,0),MATCH(DD$92,$E$6:$CE$6,0))) -> 0
B106: Bananas for beer (A141) | C106: A14 | D106: A141 | E106: =IF(ISNA(INDEX($E$8:$CE$86,MATCH($C106,$C$8:$C$86,0),MATCH(E$92,$E$6:$CE$6,0))),0,INDEX($E$8:$CE$86,MATCH($C106,$C$8:$C$86,0),MATCH(E$92,$E$6:$CE$6,0))) -> 0 | F106: =IF(ISNA(INDEX($E$8:$CE$86,MATCH($C106,$C$8:$C$86,0),MATCH(F$92,$E$6:$CE$6,0))),0,INDEX($E$8:$CE$86,MATCH($C106,$C$8:$C$86,0),MATCH(F$92,$E$6:$CE$6,0))) -> 0 | G106: =IF(ISNA(INDEX($E$8:$CE$86,MATCH($C106,$C$8:$C$86,0),MATCH(G$92,$E$6:$CE$6,0))),0,INDEX($E$8:$CE$86,MATCH($C106,$C$8:$C$86,0),MATCH(G$92,$E$6:$CE$6,0))) -> 0 | H106: =IF(ISNA(INDEX($E$8:$CE$86,MATCH($C106,$C$8:$C$86,0),MATCH(H$92,$E$6:$CE$6,0))),0,INDEX($E$8:$CE$86,MATCH($C106,$C$8:$C$86,0),MATCH(H$92,$E$6:$CE$6,0))) -> 0 | I106: =IF(ISNA(INDEX($E$8:$CE$86,MATCH($C106,$C$8:$C$86,0),MATCH(I$92,$E$6:$CE$6,0))),0,INDEX($E$8:$CE$86,MATCH($C106,$C$8:$C$86,0),MATCH(I$92,$E$6:$CE$6,0))) -> 0 | J106: =IF(ISNA(INDEX($E$8:$CE$86,MATCH($C106,$C$8:$C$86,0),MATCH(J$92,$E$6:$CE$6,0))),0,INDEX($E$8:$CE$86,MATCH($C106,$C$8:$C$86,0),MATCH(J$92,$E$6:$CE$6,0))) -> 0 | K106: =IF(ISNA(INDEX($E$8:$CE$86,MATCH($C106,$C$8:$C$86,0),MATCH(K$92,$E$6:$CE$6,0))),0,INDEX($E$8:$CE$86,MATCH($C106,$C$8:$C$86,0),MATCH(K$92,$E$6:$CE$6,0))) -> 0 | L106: =IF(ISNA(INDEX($E$8:$CE$86,MATCH($C106,$C$8:$C$86,0),MATCH(L$92,$E$6:$CE$6,0))),0,INDEX($E$8:$CE$86,MATCH($C106,$C$8:$C$86,0),MATCH(L$92,$E$6:$CE$6,0))) -> 0 | ... DD106: =IF(ISNA(INDEX($E$8:$CE$86,MATCH($C106,$C$8:$C$86,0),MATCH(DD$92,$E$6:$CE$6,0))),0,INDEX($E$8:$CE$86,MATCH($C106,$C$8:$C$86,0),MATCH(DD$92,$E$6:$CE$6,0))) -> 0
B107: Bananas for cooking (A142) | D107: A142 | E107: =IF(ISNA(INDEX($E$8:$CE$86,MATCH($C107,$C$8:$C$86,0),MATCH(E$92,$E$6:$CE$6,0))),0,INDEX($E$8:$CE$86,MATCH($C107,$C$8:$C$86,0),MATCH(E$92,$E$6:$CE$6,0))) -> 0 | F107: =IF(ISNA(INDEX($E$8:$CE$86,MATCH($C107,$C$8:$C$86,0),MATCH(F$92,$E$6:$CE$6,0))),0,INDEX($E$8:$CE$86,MATCH($C107,$C$8:$C$86,0),MATCH(F$92,$E$6:$CE$6,0))) -> 0 | G107: =IF(ISNA(INDEX($E$8:$CE$86,MATCH($C107,$C$8:$C$86,0),MATCH(G$92,$E$6:$CE$6,0))),0,INDEX($E$8:$CE$86,MATCH($C107,$C$8:$C$86,0),MATCH(G$92,$E$6:$CE$6,0))) -> 0 | H107: =IF(ISNA(INDEX($E$8:$CE$86,MATCH($C107,$C$8:$C$86,0),MATCH(H$92,$E$6:$CE$6,0))),0,INDEX($E$8:$CE$86,MATCH($C107,$C$8:$C$86,0),MATCH(H$92,$E$6:$CE$6,0))) -> 0 | I107: =IF(ISNA(INDEX($E$8:$CE$86,MATCH($C107,$C$8:$C$86,0),MATCH(I$92,$E$6:$CE$6,0))),0,INDEX($E$8:$CE$86,MATCH($C107,$C$8:$C$86,0),MATCH(I$92,$E$6:$CE$6,0))) -> 0 | J107: =IF(ISNA(INDEX($E$8:$CE$86,MATCH($C107,$C$8:$C$86,0),MATCH(J$92,$E$6:$CE$6,0))),0,INDEX($E$8:$CE$86,MATCH($C107,$C$8:$C$86,0),MATCH(J$92,$E$6:$CE$6,0))) -> 0 | K107: =IF(ISNA(INDEX($E$8:$CE$86,MATCH($C107,$C$8:$C$86,0),MATCH(K$92,$E$6:$CE$6,0))),0,INDEX($E$8:$CE$86,MATCH($C107,$C$8:$C$86,0),MATCH(K$92,$E$6:$CE$6,0))) -> 0 | L107: =IF(ISNA(INDEX($E$8:$CE$86,MATCH($C107,$C$8:$C$86,0),MATCH(L$92,$E$6:$CE$6,0))),0,INDEX($E$8:$CE$86,MATCH($C107,$C$8:$C$86,0),MATCH(L$92,$E$6:$CE$6,0))) -> 0 | ... DD107: =IF(ISNA(INDEX($E$8:$CE$86,MATCH($C107,$C$8:$C$86,0),MATCH(DD$92,$E$6:$CE$6,0))),0,INDEX($E$8:$CE$86,MATCH($C107,$C$8:$C$86,0),MATCH(DD$92,$E$6:$CE$6,0))) -> 0
