Workbook

Sheet Notes
A1: =CONCATENATE(B5," ",C4," SAM") -> 2017 Rwanda SAM
A2: Use with 1construct.gms and 2balance.gms
A4: Country | B4: RWA | C4: =IF(ISNA(INDEX([1]wEXR!$A$8:$A$196,MATCH([1]Notes!B4,[1]wEXR!$B$8:$B$196,0))),"Check name",INDEX([1]wEXR!$A$8:$A$196,MATCH([1]Notes!B4,[1]wEXR!$B$8:$B$196,0))) -> Rwanda
A5: Year | B5: 2017
A6: Units | B6: Billions of Rwanda Francs
A7: Citation
A9: Activities and commodities (X104) | E9: Factors | H9: Households | K9: Other accounts
A10: ="a"&MID(B10,2,4) -> asorg | B10: csorg | C10: Sorghum (A111) | E10: flab-rn | F10: Labor - rural uneducated | H10: hhd-f1 | I10: Rural - farm q1 | K10: trc | L10: Transaction costs
A11: ="a"&MID(B11,2,4) -> amaiz | B11: cmaiz | C11: Maize (A112) | E11: flab-rp | F11: Labor - rural primary | H11: hhd-f2 | I11: Rural - farm q2 | K11: flab | L11: Labor
A12: ="a"&MID(B12,2,4) -> awhea | B12: cwhea | C12: Wheat (A113) | E12: flab-rs | F12: Labor - rural secondary | H12: hhd-f3 | I12: Rural - farm q3 | K12: flnd | L12: Land
A13: ="a"&MID(B13,2,4) -> arice | B13: crice | C13: Paddy & husked rice (A116) | E13: flab-rt | F13: Labor - rural tertiary | H13: hhd-f4 | I13: Rural - farm q4 | K13: fcap | L13: Capital
A14: ="a"&MID(B14,2,4) -> aocer | B14: cocer | C14: Other cereals (A119) | E14: flab-un | F14: Labor - urban uneducated | H14: hhd-f5 | I14: Rural - farm q5 | K14: ent | L14: Enterprises
A15: ="a"&MID(B15,2,4) -> aipot | B15: cipot | C15: Irish potatoes (A121) | E15: flab-up | F15: Labor - urban primary | H15: hhd-n1 | I15: Rural - nonfarm q1 | K15: hhd | L15: Households
A16: ="a"&MID(B16,2,4) -> aspot | B16: cspot | C16: Sweet potatoes (A122) | E16: flab-us | F16: Labor - urban secondary | H16: hhd-n2 | I16: Rural - nonfarm q2 | K16: gov | L16: Government
A17: ="a"&MID(B17,2,4) -> acass | B17: ccass | C17: Cassava (A123) | E17: flab-ut | F17: Labor - urban tertiary | H17: hhd-n3 | I17: Rural - nonfarm q3 | K17: atax | L17: Taxes - activity (production)
A18: ="a"&MID(B18,2,4) -> aroot | B18: croot | C18: Other roots & tubers (A129) | E18: flab-kn | F18: Labor - Kigali uneducated | H18: hhd-n4 | I18: Rural - nonfarm q4 | K18: ctax | L18: Taxes - customs duties (imports)
A19: ="a"&MID(B19,2,4) -> abean | B19: cbean | C19: Dried beans (A131) | E19: flab-kp | F19: Labor - Kigali primary | H19: hhd-n5 | I19: Rural - nonfarm q5 | K19: dtax | L19: Taxes - direct (corporate, private)
A20: ="a"&MID(B20,2,4) -> apeas | B20: cpeas | C20: Peas & other legumes (A132) | E20: flab-ks | F20: Labor - Kigali secondary | H20: hhd-u1 | I20: Urban - q1 | K20: etax | L20: Taxes - exports
A21: ="a"&MID(B21,2,4) -> avege | B21: cvege | C21: Other vegetables (A139) | E21: flab-kt | F21: Labor - Kigali tertiary | H21: hhd-u2 | I21: Urban - q2 | K21: ftax | L21: Taxes - factors (royalities)
... A26: ="a"&MID(B26,2,4) -> agnut | B26: cgnut | C26: Ground nuts (A151) | E26: fcap-n | F26: Capital - non-primary | H26: hhd-k2 | I26: Kigali - q2 | K26: s-i | L26: Savings-investment
A27: ="a"&MID(B27,2,4) -> asoya | B27: csoya | C27: Soya (A152) | H27: hhd-k3 | I27: Kigali - q3 | K27: dstk | L27: Change in stocks
A28: ="a"&MID(B28,2,4) -> aoils | B28: coils | C28: Other oil seeds (A159) | H28: hhd-k4 | I28: Kigali - q4 | K28: row | L28: Rest of world
A29: ="a"&MID(B29,2,4) -> acoff | B29: ccoff | C29: Coffee, not roasted, not decaffeinated (A210) | H29: hhd-k5 | I29: Kigali - q5 | K29: total | L29: Total
A30: ="a"&MID(B30,2,4) -> ateal | B30: cteal | C30: Tea (unprocessed green leaf) (A220)
A31: ="a"&MID(B31,2,4) -> atoba | B31: ctoba | C31: Tobacco, raw (A291)
A32: ="a"&MID(B32,2,4) -> asugr | B32: csugr | C32: Sugar cane (A292)
A33: ="a"&MID(B33,2,4) -> apyre | B33: cpyre | C33: Pyrethrum (A293)
A34: ="a"&MID(B34,2,4) -> aocrp | B34: cocrp | C34: Agricultural products n.e.c. (A299)
A35: ="a"&MID(B35,2,4) -> acatt | B35: ccatt | C35: Bovine cattle, live (A311)
A36: ="a"&MID(B36,2,4) -> asmlr | B36: csmlr | C36: Sheep, goats, pigs,live (A312)
A37: ="a"&MID(B37,2,4) -> apoul | B37: cpoul | C37: Poultry, live (A313)
A38: ="a"&MID(B38,2,4) -> aoliv | B38: coliv | C38: Other live animals (A319)
A39: ="a"&MID(B39,2,4) -> amilk | B39: cmilk | C39: Raw milk (A321)
A40: ="a"&MID(B40,2,4) -> aeggs | B40: ceggs | C40: Eggs (A322)
A41: ="a"&MID(B41,2,4) -> ahony | B41: chony | C41: Natural honey (A323)
... A113: ="a"&MID(B113,2,4) -> atrdc | B113: ctrdc | C113: Travel debits & credits (V00)

Sheet Index
A1: GDX index
A6: Type | B6: Name | C6: Location | D6: Row | E6: Column
D7: rdim | E7: cdim
A8: dset | B8: mac | C8: sets!a7 | D8: 1
A9: dset | B9: ac | C9: sets!b7 | D9: 1
A10: dset | B10: aac | C10: sets!c7 | D10: 1
A11: dset | B11: a | C11: sets!d7 | D11: 1
A12: dset | B12: aliv | C12: sets!e7 | D12: 1
A13: dset | B13: amin | C13: sets!f7 | D13: 1
A14: dset | B14: c | C14: sets!g7 | D14: 1
A15: dset | B15: f | C15: sets!h7 | D15: 1
A16: dset | B16: flab | C16: sets!i7 | D16: 1
A17: dset | B17: flnd | C17: sets!j7 | D17: 1
A18: dset | B18: fcap | C18: sets!k7 | D18: 1
A19: dset | B19: h | C19: sets!l7 | D19: 1
... A21: dset | B21: food | C21: sets!n7 | D21: 1
A22: set | B22: mapmac | C22: sets!q7 | D22: 2 | F22: values=nodata
A23: set | B23: mapac | C23: sets!t7 | D23: 2 | F23: values=nodata
A24: set | B24: mapaacac | C24: sets!w7 | D24: 2 | F24: values=nodata
A25: par | B25: facact | C25: fa!b7 | D25: 1 | E25: 1
A26: par | B26: miscfac | C26: mf!b6 | D26: 1 | E26: 2
A27: par | B27: hhdfac | C27: hf!b7 | D27: 1 | E27: 1
A28: par | B28: ownshr | C28: ah!b8 | D28: 1
A29: par | B29: acthhd | C29: ah!f7 | D29: 1 | E29: 1
A30: par | B30: comhhd | C30: ch!b7 | D30: 1 | E30: 1
A31: par | B31: mischhd | C31: mh!b6 | D31: 1 | E31: 2
A32: par | B32: hhddata | C32: mh!t7 | D32: 1 | E32: 1

Sheet Sets
A1: Sets | Q1: Mappings
A2: a | B2: b | C2: c | D2: d | E2: e | F2: f | G2: g | H2: h | I2: i | J2: j | K2: k | L2: l | M2: m | N2: n | O2: o | P2: p | Q2: q | R2: r | S2: s | T2: t | U2: u | V2: v | W2: w | X2: x | Y2: y | Z2: z
A4: Macro | B4: Micro accounts | D4: Activities | G4: Commodities | H4: Factors | L4: Households | M4: Taxes | N4: Food | Q4: Macro-micro accounts | T4: Activities-commodities | W4: National-all
A5: accounts | B5: All | C5: National | D5: All | E5: Livestock | F5: Mining | G5: All | H5: All | I5: Labor | J5: Land | K5: Capital | L5: All | N5: items | Q5: MMAC | T5: MAC | W5: MAACAC
A6: MAC | B6: AC | C6: AAC | D6: A | E6: ALIV | F6: AMIN | G6: C | H6: F | I6: FLAB | J6: FLND | K6: FCAP | L6: H | M6: T | N6: FOOD | Q6: MAC | R6: AC | T6: A | U6: C | W6: AAC | X6: AC
A7: mact | B7: asorg | C7: asorg | D7: asorg | E7: acatt | F7: angas | G7: csorg | H7: flab | I7: flab | J7: flnd | K7: fcap | L7: hhd | M7: atax | N7: asorg | Q7: mact | R7: asorg | T7: asorg | U7: csorg | W7: asorg | X7: asorg
A8: mcom | B8: amaiz | C8: amaiz | D8: amaiz | E8: asmlr | F8: amore | G8: cmaiz | H8: flab-rn | I8: flab-rn | K8: fcap-c | L8: hhd-f1 | M8: ctax | N8: amaiz | Q8: mact | R8: amaiz | T8: amaiz | U8: cmaiz | W8: amaiz | X8: amaiz
A9: mtrc | B9: awhea | C9: awhea | D9: awhea | E9: apoul | F9: aomin | G9: cwhea | H9: flab-rp | I9: flab-rp | K9: fcap-l | L9: hhd-f2 | M9: dtax | N9: awhea | Q9: mact | R9: awhea | T9: awhea | U9: cwhea | W9: awhea | X9: awhea
A10: mlab | B10: arice | C10: arice | D10: arice | E10: aoliv | G10: crice | H10: flab-rs | I10: flab-rs | K10: fcap-m | L10: hhd-f3 | M10: etax | N10: arice | Q10: mact | R10: arice | T10: arice | U10: crice | W10: arice | X10: arice
A11: mlnd | B11: aocer | C11: aocer | D11: aocer | E11: amilk | G11: cocer | H11: flab-rt | I11: flab-rt | K11: fcap-n | L11: hhd-f4 | M11: ftax | N11: aocer | Q11: mact | R11: aocer | T11: aocer | U11: cocer | W11: aocer | X11: aocer
A12: mcap | B12: aipot | C12: aipot | D12: aipot | E12: aeggs | G12: cipot | H12: flab-un | I12: flab-un | L12: hhd-f5 | M12: mtax | N12: aipot | Q12: mact | R12: aipot | T12: aipot | U12: cipot | W12: aipot | X12: aipot
A13: ment | B13: aspot | C13: aspot | D13: aspot | E13: ahony | G13: cspot | H13: flab-up | I13: flab-up | L13: hhd-n1 | M13: stax | N13: aspot | Q13: mact | R13: aspot | T13: aspot | U13: cspot | W13: aspot | X13: aspot
A14: mhhd | B14: acass | C14: acass | D14: acass | E14: ahunt | G14: ccass | H14: flab-us | I14: flab-us | L14: hhd-n2 | M14: vtax | N14: acass | Q14: mact | R14: acass | T14: acass | U14: ccass | W14: acass | X14: acass
A15: mgov | B15: aroot | C15: aroot | D15: aroot | G15: croot | H15: flab-ut | I15: flab-ut | L15: hhd-n3 | M15: xtax | N15: aroot | Q15: mact | R15: aroot | T15: aroot | U15: croot | W15: aroot | X15: aroot
A16: matx | B16: abean | C16: abean | D16: abean | G16: cbean | H16: flab-kn | I16: flab-kn | L16: hhd-n4 | N16: abean | Q16: mact | R16: abean | T16: abean | U16: cbean | W16: abean | X16: abean
A17: mctx | B17: apeas | C17: apeas | D17: apeas | G17: cpeas | H17: flab-kp | I17: flab-kp | L17: hhd-n5 | N17: apeas | Q17: mact | R17: apeas | T17: apeas | U17: cpeas | W17: apeas | X17: apeas
A18: mdtx | B18: avege | C18: avege | D18: avege | G18: cvege | H18: flab-ks | I18: flab-ks | L18: hhd-u1 | N18: avege | Q18: mact | R18: avege | T18: avege | U18: cvege | W18: avege | X18: avege
A19: metx | B19: abanb | C19: abanb | D19: abanb | G19: cbanb | H19: flab-kt | I19: flab-kt | L19: hhd-u2 | N19: abanb | Q19: mact | R19: abanb | T19: abanb | U19: cbanb | W19: abanb | X19: abanb
A20: mftx | B20: abanc | C20: abanc | D20: abanc | G20: cbanc | H20: flnd | L20: hhd-u3 | N20: abanc | Q20: mact | R20: abanc | T20: abanc | U20: cbanc | W20: abanc | X20: abanc
A21: mmtx | B21: abans | C21: abans | D21: abans | G21: cbans | H21: fcap | L21: hhd-u4 | N21: abans | Q21: mact | R21: abans | T21: abans | U21: cbans | W21: abans | X21: abans
A22: mstx | B22: afrui | C22: afrui | D22: afrui | G22: cfrui | H22: fcap-c | L22: hhd-u5 | N22: afrui | Q22: mact | R22: afrui | T22: afrui | U22: cfrui | W22: afrui | X22: afrui
A23: mvtx | B23: agnut | C23: agnut | D23: agnut | G23: cgnut | H23: fcap-l | L23: hhd-k1 | N23: agnut | Q23: mact | R23: agnut | T23: agnut | U23: cgnut | W23: agnut | X23: agnut
A24: mxtx | B24: asoya | C24: asoya | D24: asoya | G24: csoya | H24: fcap-m | L24: hhd-k2 | N24: asoya | Q24: mact | R24: asoya | T24: asoya | U24: csoya | W24: asoya | X24: asoya
A25: ms-i | B25: aoils | C25: aoils | D25: aoils | G25: coils | H25: fcap-n | L25: hhd-k3 | N25: aoils | Q25: mact | R25: aoils | T25: aoils | U25: coils | W25: aoils | X25: aoils
A26: mg-i | B26: acoff | C26: acoff | D26: acoff | G26: ccoff | L26: hhd-k4 | N26: asugr | Q26: mact | R26: acoff | T26: acoff | U26: ccoff | W26: acoff | X26: acoff
A27: mstk | B27: ateal | C27: ateal | D27: ateal | G27: cteal | L27: hhd-k5 | N27: acatt | Q27: mact | R27: ateal | T27: ateal | U27: cteal | W27: ateal | X27: ateal
A28: mrow | B28: atoba | C28: atoba | D28: atoba | G28: ctoba | N28: asmlr | Q28: mact | R28: atoba | T28: atoba | U28: ctoba | W28: atoba | X28: atoba
A29: mtot | B29: asugr | C29: asugr | D29: asugr | G29: csugr | N29: apoul | Q29: mact | R29: asugr | T29: asugr | U29: csugr | W29: asugr | X29: asugr
B30: apyre | C30: apyre | D30: apyre | G30: cpyre | N30: aoliv | Q30: mact | R30: apyre | T30: apyre | U30: cpyre | W30: apyre | X30: apyre
B31: aocrp | C31: aocrp | D31: aocrp | G31: cocrp | N31: amilk | Q31: mact | R31: aocrp | T31: aocrp | U31: cocrp | W31: aocrp | X31: aocrp
B32: acatt | C32: acatt | D32: acatt | G32: ccatt | N32: aeggs | Q32: mact | R32: acatt | T32: acatt | U32: ccatt | W32: acatt | X32: acatt
B33: asmlr | C33: asmlr | D33: asmlr | G33: csmlr | N33: ahony | Q33: mact | R33: asmlr | T33: asmlr | U33: csmlr | W33: asmlr | X33: asmlr
B34: apoul | C34: apoul | D34: apoul | G34: cpoul | N34: ahunt | Q34: mact | R34: apoul | T34: apoul | U34: cpoul | W34: apoul | X34: apoul
B35: aoliv | C35: aoliv | D35: aoliv | G35: coliv | N35: afish | Q35: mact | R35: aoliv | T35: aoliv | U35: coliv | W35: aoliv | X35: aoliv
B36: amilk | C36: amilk | D36: amilk | G36: cmilk | N36: ameat | Q36: mact | R36: amilk | T36: amilk | U36: cmilk | W36: amilk | X36: amilk
B37: aeggs | C37: aeggs | D37: aeggs | G37: ceggs | N37: afsea | Q37: mact | R37: aeggs | T37: aeggs | U37: ceggs | W37: aeggs | X37: aeggs
B38: ahony | C38: ahony | D38: ahony | G38: chony | N38: afveg | Q38: mact | R38: ahony | T38: ahony | U38: chony | W38: ahony | X38: ahony
B39: ahunt | C39: ahunt | D39: ahunt | G39: chunt | N39: afoil | Q39: mact | R39: ahunt | T39: ahunt | U39: chunt | W39: ahunt | X39: ahunt
B40: afuel | C40: afuel | D40: afuel | G40: cfuel | N40: adair | Q40: mact | R40: afuel | T40: afuel | U40: cfuel | W40: afuel | X40: afuel
B41: achar | C41: achar | D41: achar | G41: cchar | N41: agmll | Q41: mact | R41: achar | T41: achar | U41: cchar | W41: achar | X41: achar
... B45: amore | C45: amore | D45: amore | G45: cmore | N45: ahotl | Q45: mact | R45: amore | T45: amore | U45: cmore | W45: amore | X45: amore
B46: aomin | C46: aomin | D46: aomin | G46: comin | Q46: mact | R46: aomin | T46: aomin | U46: comin | W46: aomin | X46: aomin
B47: ameat | C47: ameat | D47: ameat | G47: cmeat | Q47: mact | R47: ameat | T47: ameat | U47: cmeat | W47: ameat | X47: ameat
B48: afsea | C48: afsea | D48: afsea | G48: cfsea | Q48: mact | R48: afsea | T48: afsea | U48: cfsea | W48: afsea | X48: afsea
B49: afveg | C49: afveg | D49: afveg | G49: cfveg | Q49: mact | R49: afveg | T49: afveg | U49: cfveg | W49: afveg | X49: afveg
B50: afoil | C50: afoil | D50: afoil | G50: cfoil | Q50: mact | R50: afoil | T50: afoil | U50: cfoil | W50: afoil | X50: afoil
B51: adair | C51: adair | D51: adair | G51: cdair | Q51: mact | R51: adair | T51: adair | U51: cdair | W51: adair | X51: adair
B52: agmll | C52: agmll | D52: agmll | G52: cgmll | Q52: mact | R52: agmll | T52: agmll | U52: cgmll | W52: agmll | X52: agmll
B53: abake | C53: abake | D53: abake | G53: cbake | Q53: mact | R53: abake | T53: abake | U53: cbake | W53: abake | X53: abake
B54: afeed | C54: afeed | D54: afeed | G54: cfeed | Q54: mact | R54: afeed | T54: afeed | U54: cfeed | W54: afeed | X54: afeed
B55: afood | C55: afood | D55: afood | G55: cfood | Q55: mact | R55: afood | T55: afood | U55: cfood | W55: afood | X55: afood
B56: aalco | C56: aalco | D56: aalco | G56: calco | Q56: mact | R56: aalco | T56: aalco | U56: calco | W56: aalco | X56: aalco
B57: abeve | C57: abeve | D57: abeve | G57: cbeve | Q57: mact | R57: abeve | T57: abeve | U57: cbeve | W57: abeve | X57: abeve
... B110: atrdc | C110: atrdc | D110: atrdc | G110: ctrdc | Q110: mact | R110: atrdc | T110: atrdc | U110: ctrdc | W110: atrdc | X110: atrdc
B111: csorg | C111: csorg | Q111: mcom | R111: csorg | W111: csorg | X111: csorg
B112: cmaiz | C112: cmaiz | Q112: mcom | R112: cmaiz | W112: cmaiz | X112: cmaiz
B113: cwhea | C113: cwhea | Q113: mcom | R113: cwhea | W113: cwhea | X113: cwhea
B114: crice | C114: crice | Q114: mcom | R114: crice | W114: crice | X114: crice
B115: cocer | C115: cocer | Q115: mcom | R115: cocer | W115: cocer | X115: cocer
B116: cipot | C116: cipot | Q116: mcom | R116: cipot | W116: cipot | X116: cipot
B117: cspot | C117: cspot | Q117: mcom | R117: cspot | W117: cspot | X117: cspot
B118: ccass | C118: ccass | Q118: mcom | R118: ccass | W118: ccass | X118: ccass
B119: croot | C119: croot | Q119: mcom | R119: croot | W119: croot | X119: croot
B120: cbean | C120: cbean | Q120: mcom | R120: cbean | W120: cbean | X120: cbean
B121: cpeas | C121: cpeas | Q121: mcom | R121: cpeas | W121: cpeas | X121: cpeas
B122: cvege | C122: cvege | Q122: mcom | R122: cvege | W122: cvege | X122: cvege
... B235: ent | C235: total | Q235: ment | R235: ent | W235: ent | X235: ent
B236: hhd | Q236: mhhd | R236: hhd | W236: hhd | X236: hhd
B237: hhd-f1 | Q237: mhhd | R237: hhd-f1 | W237: hhd | X237: hhd-f1
B238: hhd-f2 | Q238: mhhd | R238: hhd-f2 | W238: hhd | X238: hhd-f2
B239: hhd-f3 | Q239: mhhd | R239: hhd-f3 | W239: hhd | X239: hhd-f3
B240: hhd-f4 | Q240: mhhd | R240: hhd-f4 | W240: hhd | X240: hhd-f4
B241: hhd-f5 | Q241: mhhd | R241: hhd-f5 | W241: hhd | X241: hhd-f5
B242: hhd-n1 | Q242: mhhd | R242: hhd-n1 | W242: hhd | X242: hhd-n1
B243: hhd-n2 | Q243: mhhd | R243: hhd-n2 | W243: hhd | X243: hhd-n2
B244: hhd-n3 | Q244: mhhd | R244: hhd-n3 | W244: hhd | X244: hhd-n3
B245: hhd-n4 | Q245: mhhd | R245: hhd-n4 | W245: hhd | X245: hhd-n4
B246: hhd-n5 | Q246: mhhd | R246: hhd-n5 | W246: hhd | X246: hhd-n5
B247: hhd-u1 | Q247: mhhd | R247: hhd-u1 | W247: hhd | X247: hhd-u1
... B271: total | Q271: mtot | R271: total | W271: total | X271: total

Sheet FA
A1: Factor income generation
A4: Disaggregated factors' share of national aggregate factor value-added
A5: FACACT | C5: Labor | O5: Land | P5: Capital
C6: Rural uneducated | D6: Rural primary | E6: Rural secondary | F6: Rural tertiary | G6: Urban uneducated | H6: Urban primary | I6: Urban secondary | J6: Urban tertiary | K6: Kigali uneducated | L6: Kigali primary | M6: Kigali secondary | N6: Kigali tertiary | O6: Crops | P6: Crops | Q6: Livestock | R6: Mining | S6: Other
C7: flab-rn | D7: flab-rp | E7: flab-rs | F7: flab-rt | G7: flab-un | H7: flab-up | I7: flab-us | J7: flab-ut | K7: flab-kn | L7: flab-kp | M7: flab-ks | N7: flab-kt | O7: flnd | P7: fcap-c | Q7: fcap-l | R7: fcap-m | S7: fcap-n
A8: Sorghum (A111) | B8: asorg | C8: =SVY!D7 -> 0.49259772 | D8: =SVY!E7 -> 0.3616742 | E8: =SVY!F7 -> 0.039480441 | F8: =SVY!G7 -> 0.010552685 | G8: =SVY!H7 -> 0.010225128 | H8: =SVY!I7 -> 0.018300974 | I8: =SVY!J7 -> 0.0045167072 | J8: =SVY!K7 -> 0.0054580675 | ... N8: =SVY!O7 -> 0.0087581275 | O8: 1 | P8: 1
A9: Maize (A112) | B9: amaiz | C9: =SVY!D8 -> 0.49922869 | D9: =SVY!E8 -> 0.36654278 | E9: =SVY!F8 -> 0.040011896 | F9: =SVY!G8 -> 0.010694737 | G9: =SVY!H8 -> 0.010577163 | H9: =SVY!I8 -> 0.018931048 | I9: =SVY!J8 -> 0.0046722106 | J9: =SVY!K8 -> 0.0056459805 | ... N9: =SVY!O8 -> 0.006691091 | O9: 1 | P9: 1
A10: Wheat (A113) | B10: awhea | C10: =SVY!D9 -> 0.52564511 | D10: =SVY!E9 -> 0.38593819 | E10: =SVY!F9 -> 0.042129104 | F10: =SVY!G9 -> 0.011260643 | G10: =SVY!H9 -> 0.006800444 | H10: =SVY!I9 -> 0.012171461 | I10: =SVY!J9 -> 0.0030039345 | J10: =SVY!K9 -> 0.0036300068 | ... N10: =SVY!O9 -> 0.0014426538 | O10: 1 | P10: 1
A11: Paddy & husked rice (A116) | B11: arice | C11: =SVY!D10 -> 0.50532883 | D11: =SVY!E10 -> 0.37102161 | E11: =SVY!F10 -> 0.040500806 | F11: =SVY!G10 -> 0.010825417 | G11: =SVY!H10 -> 0.015833767 | H11: =SVY!I10 -> 0.028339338 | I11: =SVY!J10 -> 0.0069941903 | J11: =SVY!K10 -> 0.0084519012 | ... N11: =SVY!O10 -> 0.0019453855 | O11: 1 | P11: 1
A12: Other cereals (A119) | B12: aocer | C12: =SVY!D11 -> 0.53530655 | D12: =SVY!E11 -> 0.39303179 | E12: =SVY!F11 -> 0.042903443 | F12: =SVY!G11 -> 0.011467615 | G12: =SVY!H11 -> 0.0026795475 | H12: =SVY!I11 -> 0.0047958646 | I12: =SVY!J11 -> 0.0011836264 | J12: =SVY!K11 -> 0.0014303148 | ... N12: =SVY!O11 -> 0.001102727 | O12: 1 | P12: 1
A13: Irish potatoes (A121) | B13: aipot | C13: =SVY!D12 -> 0.46720129 | D13: =SVY!E12 -> 0.37726805 | E13: =SVY!F12 -> 0.026879792 | F13: =SVY!G12 -> 0.011946 | G13: =SVY!H12 -> 0.025108999 | H13: =SVY!I12 -> 0.026689454 | I13: =SVY!J12 -> 0.037589338 | J13: =SVY!K12 -> 0.0074107533 | ... N13: =SVY!O12 -> 0.0035005913 | O13: 1 | P13: 1
A14: Sweet potatoes (A122) | B14: aspot | C14: =SVY!D13 -> 0.50527702 | D14: =SVY!E13 -> 0.40801445 | E14: =SVY!F13 -> 0.029070428 | F14: =SVY!G13 -> 0.012919569 | G14: =SVY!H13 -> 0.005590998 | H14: =SVY!I13 -> 0.0059429163 | I14: =SVY!J13 -> 0.0083699836 | J14: =SVY!K13 -> 0.0016501457 | ... N14: =SVY!O13 -> 0.0040735494 | O14: 1 | P14: 1
A15: Cassava (A123) | B15: acass | C15: =SVY!D14 -> 0.49036261 | D15: =SVY!E14 -> 0.39597097 | E15: =SVY!F14 -> 0.028212347 | F15: =SVY!G14 -> 0.012538219 | G15: =SVY!H14 -> 0.0082632319 | H15: =SVY!I14 -> 0.0087833506 | I15: =SVY!J14 -> 0.012370442 | J15: =SVY!K14 -> 0.0024388376 | ... N15: =SVY!O14 -> 0.0072205318 | O15: 1 | P15: 1
A16: Other roots & tubers (A129) | B16: aroot | C16: =SVY!D15 -> 0.49775754 | D16: =SVY!E15 -> 0.40194242 | E16: =SVY!F15 -> 0.028637804 | F16: =SVY!G15 -> 0.012727302 | G16: =SVY!H15 -> 0.0070264783 | H16: =SVY!I15 -> 0.0074687511 | I16: =SVY!J15 -> 0.010518964 | J16: =SVY!K15 -> 0.0020738181 | ... N16: =SVY!O15 -> 0.005600384 | O16: 1 | P16: 1
A17: Dried beans (A131) | B17: abean | C17: =SVY!D16 -> 0.47919011 | D17: =SVY!E16 -> 0.3588048 | E17: =SVY!F16 -> 0.029643078 | F17: =SVY!G16 -> 0.011400722 | G17: =SVY!H16 -> 0.010822825 | H17: =SVY!I16 -> 0.016164162 | I17: =SVY!J16 -> 0.0054678963 | J17: =SVY!K16 -> 0.0036284212 | ... N17: =SVY!O16 -> 0.028753901 | O17: 1 | P17: 1
A18: Peas & other legumes (A132) | B18: apeas | C18: =SVY!D17 -> 0.47919011 | D18: =SVY!E17 -> 0.3588048 | E18: =SVY!F17 -> 0.029643078 | F18: =SVY!G17 -> 0.011400722 | G18: =SVY!H17 -> 0.010822825 | H18: =SVY!I17 -> 0.016164162 | I18: =SVY!J17 -> 0.0054678963 | J18: =SVY!K17 -> 0.0036284212 | ... N18: =SVY!O17 -> 0.028753901 | O18: 1 | P18: 1
A19: Other vegetables (A139) | B19: avege | C19: =SVY!D18 -> 0.47666172 | D19: =SVY!E18 -> 0.35691162 | E19: =SVY!F18 -> 0.02948667 | F19: =SVY!G18 -> 0.011340567 | G19: =SVY!H18 -> 0.019748059 | H19: =SVY!I18 -> 0.029494225 | I19: =SVY!J18 -> 0.0099770938 | J19: =SVY!K18 -> 0.006620663 | ... N19: =SVY!O18 -> 0.020244537 | O19: 1 | P19: 1
... A32: Agricultural products n.e.c. (A299) | B32: aocrp | C32: =SVY!D31 -> 0.47617212 | D32: =SVY!E31 -> 0.41450317 | E32: =SVY!F31 -> 0.015059169 | F32: =SVY!G31 -> 0.013068783 | G32: =SVY!H31 -> 0.032551894 | H32: =SVY!I31 -> 0.012207592 | I32: =SVY!J31 -> 0.0054582272 | J32: =SVY!K31 -> 0.016426124 | ... N32: =SVY!O31 -> 0.00041980755 | O32: 1 | P32: 1
A33: Bovine cattle, live (A311) | B33: acatt | C33: =SVY!D32 -> 0.44064905 | D33: =SVY!E32 -> 0.29085561 | E33: =SVY!F32 -> 0.027823024 | F33: =SVY!G32 -> 0.015604799 | G33: =SVY!H32 -> 0.017860947 | H33: =SVY!I32 -> 0.025417589 | I33: =SVY!J32 -> 0.022653569 | J33: =SVY!K32 -> 0.015675612 | ... N33: =SVY!O32 -> 0.029486613 | Q33: 1
A34: Sheep, goats, pigs,live (A312) | B34: asmlr | C34: =SVY!D33 -> 0.47916601 | D34: =SVY!E33 -> 0.34824836 | E34: =SVY!F33 -> 0.02921921 | F34: =SVY!G33 -> 0.013476399 | G34: =SVY!H33 -> 0.018838165 | H34: =SVY!I33 -> 0.025188021 | I34: =SVY!J33 -> 0.004754479 | J34: =SVY!K33 -> 0.0038552281 | ... N34: =SVY!O33 -> 0.021664515 | Q34: 1
A35: Poultry, live (A313) | B35: apoul | C35: =SVY!D34 -> 0.46923066 | D35: =SVY!E34 -> 0.2519272 | E35: =SVY!F34 -> 0.025170528 | F35: =SVY!G34 -> 0.036820588 | G35: =SVY!H34 -> 0.016914831 | H35: =SVY!I34 -> 0.041870871 | I35: =SVY!J34 -> 0.012848248 | J35: =SVY!K34 -> 0.051554101 | ... N35: =SVY!O34 -> 0.016602008 | Q35: 1
A36: Other live animals (A319) | B36: aoliv | C36: =SVY!D35 -> 0.46424309 | D36: =SVY!E35 -> 0.33740268 | E36: =SVY!F35 -> 0.028309221 | F36: =SVY!G35 -> 0.013056697 | G36: =SVY!H35 -> 0.019186691 | H36: =SVY!I35 -> 0.025654027 | I36: =SVY!J35 -> 0.0048424421 | J36: =SVY!K35 -> 0.003926554 | ... N36: =SVY!O35 -> 0.028990647 | Q36: 1
A37: Raw milk (A321) | B37: amilk | C37: =SVY!D36 -> 0.24418869 | D37: =SVY!E36 -> 0.16647005 | E37: =SVY!F36 -> 0.022646827 | F37: =SVY!G36 -> 0.0086551802 | G37: =SVY!H36 -> 0.018401586 | H37: =SVY!I36 -> 0.03540589 | I37: =SVY!J36 -> 0.026246361 | J37: =SVY!K36 -> 0.01877357 | ... N37: =SVY!O36 -> 0.1119317 | Q37: 1
A38: Eggs (A322) | B38: aeggs | C38: =SVY!D37 -> 0.29290897 | D38: =SVY!E37 -> 0.30232267 | E38: =SVY!F37 -> 0.013736516 | F38: =SVY!G37 -> 0.005926831 | G38: =SVY!H37 -> 0.018325613 | H38: =SVY!I37 -> 0.0091038585 | I38: =SVY!J37 -> 0.0047548965 | J38: =SVY!K37 -> 0.16574323 | ... N38: =SVY!O37 -> 0.0019851997 | Q38: 1
A39: Natural honey (A323) | B39: ahony | C39: =SVY!D38 -> 0.46424309 | D39: =SVY!E38 -> 0.33740268 | E39: =SVY!F38 -> 0.028309221 | F39: =SVY!G38 -> 0.013056697 | G39: =SVY!H38 -> 0.019186691 | H39: =SVY!I38 -> 0.025654027 | I39: =SVY!J38 -> 0.0048424421 | J39: =SVY!K38 -> 0.003926554 | ... N39: =SVY!O38 -> 0.028990647 | Q39: 1
A40: Other livestock & hunting products (A329) | B40: ahunt | C40: =SVY!D39 -> 0.4547593 | D40: =SVY!E39 -> 0.33051004 | E40: =SVY!F39 -> 0.027730906 | F40: =SVY!G39 -> 0.012789968 | G40: =SVY!H39 -> 0.042360641 | H40: =SVY!I39 -> 0.056639314 | I40: =SVY!J39 -> 0.01069121 | J40: =SVY!K39 -> 0.0086690999 | ... N40: =SVY!O39 -> 0.015661983 | Q40: 1
A41: Fuel wood (A401) | B41: afuel | C41: =SVY!D40 -> 0.394288 | D41: =SVY!E40 -> 0.49627498 | E41: =SVY!F40 -> 0.025290128 | F41: =SVY!G40 -> 0 | G41: =SVY!H40 -> 0.035301789 | H41: =SVY!I40 -> 0.012803404 | I41: =SVY!J40 -> 0 | J41: =SVY!K40 -> 0 | ... N41: =SVY!O40 -> 0 | P41: 1
A42: Charcoal (A402) | B42: achar | C42: =SVY!D41 -> 0.394288 | D42: =SVY!E41 -> 0.49627498 | E42: =SVY!F41 -> 0.025290128 | F42: =SVY!G41 -> 0 | G42: =SVY!H41 -> 0.035301789 | H42: =SVY!I41 -> 0.012803404 | I42: =SVY!J41 -> 0 | J42: =SVY!K41 -> 0 | ... N42: =SVY!O41 -> 0 | P42: 1
A43: Other forestry products (A409) | B43: afore | C43: =SVY!D42 -> 0.394288 | D43: =SVY!E42 -> 0.49627498 | E43: =SVY!F42 -> 0.025290128 | F43: =SVY!G42 -> 0 | G43: =SVY!H42 -> 0.035301789 | H43: =SVY!I42 -> 0.012803404 | I43: =SVY!J42 -> 0 | J43: =SVY!K42 -> 0 | ... N43: =SVY!O42 -> 0 | P43: 1
A44: Fishery products (A500) | B44: afish | C44: =SVY!D43 -> 0.52569482 | D44: =SVY!E43 -> 0.43704433 | E44: =SVY!F43 -> 0.037260841 | F44: =SVY!G43 -> 0 | G44: =SVY!H43 -> 0 | H44: =SVY!I43 -> 0 | I44: =SVY!J43 -> 0 | J44: =SVY!K43 -> 0 | ... N44: =SVY!O43 -> 0 | P44: 1
A45: Natural gas (B01) | B45: angas | C45: =SVY!D44 -> 0.35876341 | D45: =SVY!E44 -> 0.56076169 | E45: =SVY!F44 -> 0.01558566 | F45: =SVY!G44 -> 0 | G45: =SVY!H44 -> 0 | H45: =SVY!I44 -> 0.0060375086 | I45: =SVY!J44 -> 0 | J45: =SVY!K44 -> 0 | ... N45: =SVY!O44 -> 0.038798807 | R45: 1
A46: Metal ores (B03) | B46: amore | C46: =SVY!D45 -> 0.34721191 | D46: =SVY!E45 -> 0.54270623 | E46: =SVY!F45 -> 0.015083831 | F46: =SVY!G45 -> 0 | G46: =SVY!H45 -> 0 | H46: =SVY!I45 -> 0.012075017 | I46: =SVY!J45 -> 0 | J46: =SVY!K45 -> 0 | ... N46: =SVY!O45 -> 0.054668128 | R46: 1
A47: Quarry & other mining products (B09) | B47: aomin | C47: =SVY!D46 -> 0.37031491 | D47: =SVY!E46 -> 0.57881715 | E47: =SVY!F46 -> 0.016087488 | F47: =SVY!G46 -> 0 | G47: =SVY!H46 -> 0 | H47: =SVY!I46 -> 0 | I47: =SVY!J46 -> 0 | J47: =SVY!K46 -> 0 | ... N47: =SVY!O46 -> 0.022929486 | R47: 1
A48: Meat and meat products (C11) | B48: ameat | C48: =SVY!D47 -> 0.23432434 | D48: =SVY!E47 -> 0.42270003 | E48: =SVY!F47 -> 0.0889595 | F48: =SVY!G47 -> 0.050460745 | G48: =SVY!H47 -> 0.023204384 | H48: =SVY!I47 -> 0.032578796 | I48: =SVY!J47 -> 0.022611435 | J48: =SVY!K47 -> 0 | ... N48: =SVY!O47 -> 0.030962795 | S48: 1
A49: Prepared and preserved fish (C12) | B49: afsea | C49: =SVY!D48 -> 0.25170213 | D49: =SVY!E48 -> 0.45404801 | E49: =SVY!F48 -> 0.095556851 | F49: =SVY!G48 -> 0.054202979 | G49: =SVY!H48 -> 0.011977674 | H49: =SVY!I48 -> 0.016816572 | I49: =SVY!J48 -> 0.011671605 | J49: =SVY!K48 -> 0 | ... N49: =SVY!O48 -> 0.025733937 | S49: 1
A50: Prepared and preserved vegetables (C13) | B50: afveg | C50: =SVY!D49 -> 0.25158408 | D50: =SVY!E49 -> 0.45383506 | E50: =SVY!F49 -> 0.095512034 | F50: =SVY!G49 -> 0.054177557 | G50: =SVY!H49 -> 0.014966548 | H50: =SVY!I49 -> 0.02101293 | I50: =SVY!J49 -> 0.014584103 | J50: =SVY!K49 -> 0 | ... N50: =SVY!O49 -> 0.023335179 | S50: 1
A51: Animal and vegetable oils and fats (C14) | B51: afoil | C51: =SVY!D50 -> 0.26092101 | D51: =SVY!E50 -> 0.47067803 | E51: =SVY!F50 -> 0.09905673 | F51: =SVY!G50 -> 0.056188225 | G51: =SVY!H50 -> 0.010444608 | H51: =SVY!I50 -> 0.014664158 | I51: =SVY!J50 -> 0.010177713 | J51: =SVY!K50 -> 0 | ... N51: =SVY!O50 -> 0.019263689 | S51: 1
A52: Dairy products (C15) | B52: adair | C52: =SVY!D51 -> 0.16961094 | D52: =SVY!E51 -> 0.30596288 | E52: =SVY!F51 -> 0.064391537 | F52: =SVY!G51 -> 0.036524991 | G52: =SVY!H51 -> 0.026603865 | H52: =SVY!I51 -> 0.037351643 | I52: =SVY!J51 -> 0.025924047 | J52: =SVY!K51 -> 0 | ... N52: =SVY!O51 -> 0.082534812 | S52: 1
A53: Grain mill products (C16) | B53: agmll | C53: =SVY!D52 -> 0.26514288 | D53: =SVY!E52 -> 0.4782939 | E53: =SVY!F52 -> 0.10065953 | F53: =SVY!G52 -> 0.057097386 | G53: =SVY!H52 -> 0.012558725 | H53: =SVY!I52 -> 0.017632363 | I53: =SVY!J52 -> 0.012237808 | J53: =SVY!K52 -> 0 | ... N53: =SVY!O52 -> 0.013946879 | S53: 1
A54: Bakery products (C17) | B54: abake | C54: =SVY!D53 -> 0.20919129 | D54: =SVY!E53 -> 0.37736227 | E54: =SVY!F53 -> 0.079417925 | F54: =SVY!G53 -> 0.045048451 | G54: =SVY!H53 -> 0.023955349 | H54: =SVY!I53 -> 0.033633144 | I54: =SVY!J53 -> 0.02334321 | J54: =SVY!K53 -> 0 | ... N54: =SVY!O53 -> 0.051467874 | S54: 1
A55: Animal feed & other by-products (C18) | B55: afeed | C55: =SVY!D54 -> 0.24847014 | D55: =SVY!E54 -> 0.44821778 | E55: =SVY!F54 -> 0.094329847 | F55: =SVY!G54 -> 0.053506982 | G55: =SVY!H54 -> 0.014779933 | H55: =SVY!I54 -> 0.020750923 | I55: =SVY!J54 -> 0.014402256 | J55: =SVY!K54 -> 0 | ... N55: =SVY!O54 -> 0.026109459 | S55: 1
A56: Other manufactured food products (C19) | B56: afood | C56: =SVY!D55 -> 0.26600993 | D56: =SVY!E55 -> 0.47985798 | E56: =SVY!F55 -> 0.1009887 | F56: =SVY!G55 -> 0.057284101 | G56: =SVY!H55 -> 0.013789069 | H56: =SVY!I55 -> 0.019359757 | I56: =SVY!J55 -> 0.013436712 | J56: =SVY!K55 -> 0 | ... N56: =SVY!O55 -> 0.012189549 | S56: 1
A57: Alcoholic drinks (C21) | B57: aalco | C57: =SVY!D56 -> 0.066087107 | D57: =SVY!E56 -> 0.20042123 | E57: =SVY!F56 -> 0.0017292858 | F57: =SVY!G56 -> 0 | G57: =SVY!H56 -> 0.010752762 | H57: =SVY!I56 -> 0.01221904 | I57: =SVY!J56 -> 0.073289258 | J57: =SVY!K56 -> 0 | ... N57: =SVY!O56 -> 0.45094956 | S57: 1
A58: Soft drinks (C22) | B58: abeve | C58: =SVY!D57 -> 0.066087107 | D58: =SVY!E57 -> 0.20042123 | E58: =SVY!F57 -> 0.0017292858 | F58: =SVY!G57 -> 0 | G58: =SVY!H57 -> 0.010752762 | H58: =SVY!I57 -> 0.01221904 | I58: =SVY!J57 -> 0.073289258 | J58: =SVY!K57 -> 0 | ... N58: =SVY!O57 -> 0.45094956 | S58: 1
A59: Tobacco products (C23) | B59: aptob | C59: =SVY!D58 -> 0.22550643 | D59: =SVY!E58 -> 0.68388947 | E59: =SVY!F58 -> 0.0059007736 | F59: =SVY!G58 -> 0 | G59: =SVY!H58 -> 0.002647764 | H59: =SVY!I58 -> 0.0030088208 | I59: =SVY!J58 -> 0.018046773 | J59: =SVY!K58 -> 0 | ... N59: =SVY!O58 -> 0.043285367 | S59: 1
... A111: Travel debits & credits (V00) | B111: atrdc | C111: =SVY!D110 -> 0 | D111: =SVY!E110 -> 0 | E111: =SVY!F110 -> 0 | F111: =SVY!G110 -> 0 | G111: =SVY!H110 -> 0 | H111: =SVY!I110 -> 0 | I111: =SVY!J110 -> 0 | J111: =SVY!K110 -> 0 | ... N111: =SVY!O110 -> 0 | S111: 1

Sheet MF
A1: Miscellaneous factor accounts
A3: Disaggregated factors' income and expenditure shares
A4: MISCFAC | C4: Expenditure shares (sums to 1) | G4: Income shares (need not sum to 1)
C5: Households | D5: Government | E5: Factor taxes | F5: Rest of world | G5: Government | H5: Rest of world
C6: exp | D6: exp | E6: exp | F6: exp | G6: inc | H6: inc
C7: hhd | D7: gov | E7: ftax | F7: row | G7: gov | H7: row
A8: Labor - rural uneducated | B8: flab-rn | C8: =SVY!D505 -> 0.98354243 | D8: =SVY!E505 -> 0 | E8: =SVY!F505 -> 0 | F8: =SVY!G505 -> 0.016457574 | G8: =SVY!H505 -> 0 | H8: =SVY!I505 -> 0.0016453087
A9: Labor - rural primary | B9: flab-rp | C9: =SVY!D506 -> 0.98354243 | D9: =SVY!E506 -> 0 | E9: =SVY!F506 -> 0 | F9: =SVY!G506 -> 0.016457574 | G9: =SVY!H506 -> 0 | H9: =SVY!I506 -> 0.0016453087
A10: Labor - rural secondary | B10: flab-rs | C10: =SVY!D507 -> 0.98354243 | D10: =SVY!E507 -> 0 | E10: =SVY!F507 -> 0 | F10: =SVY!G507 -> 0.016457574 | G10: =SVY!H507 -> 0 | H10: =SVY!I507 -> 0.0016453087
A11: Labor - rural tertiary | B11: flab-rt | C11: =SVY!D508 -> 0.98354243 | D11: =SVY!E508 -> 0 | E11: =SVY!F508 -> 0 | F11: =SVY!G508 -> 0.016457574 | G11: =SVY!H508 -> 0 | H11: =SVY!I508 -> 0.0016453087
A12: Labor - urban uneducated | B12: flab-un | C12: =SVY!D509 -> 0.98354243 | D12: =SVY!E509 -> 0 | E12: =SVY!F509 -> 0 | F12: =SVY!G509 -> 0.016457574 | G12: =SVY!H509 -> 0 | H12: =SVY!I509 -> 0.0016453087
A13: Labor - urban primary | B13: flab-up | C13: =SVY!D510 -> 0.98354243 | D13: =SVY!E510 -> 0 | E13: =SVY!F510 -> 0 | F13: =SVY!G510 -> 0.016457574 | G13: =SVY!H510 -> 0 | H13: =SVY!I510 -> 0.0016453087
A14: Labor - urban secondary | B14: flab-us | C14: =SVY!D511 -> 0.98354243 | D14: =SVY!E511 -> 0 | E14: =SVY!F511 -> 0 | F14: =SVY!G511 -> 0.016457574 | G14: =SVY!H511 -> 0 | H14: =SVY!I511 -> 0.0016453087
A15: Labor - urban tertiary | B15: flab-ut | C15: =SVY!D512 -> 0.98354243 | D15: =SVY!E512 -> 0 | E15: =SVY!F512 -> 0 | F15: =SVY!G512 -> 0.016457574 | G15: =SVY!H512 -> 0 | H15: =SVY!I512 -> 0.0016453087
A16: Labor - Kigali uneducated | B16: flab-kn | C16: =SVY!D513 -> 0.98354243 | D16: =SVY!E513 -> 0 | E16: =SVY!F513 -> 0 | F16: =SVY!G513 -> 0.016457574 | G16: =SVY!H513 -> 0 | H16: =SVY!I513 -> 0.0016453087
A17: Labor - Kigali primary | B17: flab-kp | C17: =SVY!D514 -> 0.98354243 | D17: =SVY!E514 -> 0 | E17: =SVY!F514 -> 0 | F17: =SVY!G514 -> 0.016457574 | G17: =SVY!H514 -> 0 | H17: =SVY!I514 -> 0.0016453087
A18: Labor - Kigali secondary | B18: flab-ks | C18: =SVY!D515 -> 0.98354243 | D18: =SVY!E515 -> 0 | E18: =SVY!F515 -> 0 | F18: =SVY!G515 -> 0.016457574 | G18: =SVY!H515 -> 0 | H18: =SVY!I515 -> 0.0016453087
A19: Labor - Kigali tertiary | B19: flab-kt | C19: =SVY!D516 -> 0.98354243 | D19: =SVY!E516 -> 0 | E19: =SVY!F516 -> 0 | F19: =SVY!G516 -> 0.016457574 | G19: =SVY!H516 -> 0 | H19: =SVY!I516 -> 0.0016453087
... A24: Capital - non-primary | B24: fcap-n | C24: =SVY!D521 -> 0.92203986 | D24: =SVY!E521 -> 0.00045503844 | E24: =SVY!F521 -> 0 | F24: =SVY!G521 -> 0.077505104 | G24: =SVY!H521 -> 0 | H24: =SVY!I521 -> 0.0039541628

Sheet HF
A1: Factor payments to households
A4: Share of factor incomes distributed to different households
A5: HHDFAC | C5: Labor | O5: Land | P5: Capital
C6: Labor - rural uneducated | D6: Labor - rural primary | E6: Labor - rural secondary | F6: Labor - rural tertiary | G6: Labor - urban uneducated | H6: Labor - urban primary | I6: Labor - urban secondary | J6: Labor - urban tertiary | K6: Labor - Kigali uneducated | L6: Labor - Kigali primary | M6: Labor - Kigali secondary | N6: Labor - Kigali tertiary | O6: Crop land | P6: Crops | Q6: Livestock
C7: flab-rn | D7: flab-rp | E7: flab-rs | F7: flab-rt | G7: flab-un | H7: flab-up | I7: flab-us | J7: flab-ut | K7: flab-kn | L7: flab-kp | M7: flab-ks | N7: flab-kt | O7: flnd | P7: fcap-c | Q7: fcap-l
A8: Rural - farm q1 | B8: hhd-f1 | C8: =SVY!D452 -> 0.19998698 | D8: =SVY!E452 -> 0.12327347 | E8: =SVY!F452 -> 0.022663474 | F8: =SVY!G452 -> 0.00090909863 | G8: =SVY!H452 -> 0 | H8: =SVY!I452 -> 0 | I8: =SVY!J452 -> 0 | J8: =SVY!K452 -> 0 | ... Q8: =SVY!R452 -> 0.10079254
A9: Rural - farm q2 | B9: hhd-f2 | C9: =SVY!D453 -> 0.16962729 | D9: =SVY!E453 -> 0.1465441 | E9: =SVY!F453 -> 0.062567709 | F9: =SVY!G453 -> 0.0063945346 | G9: =SVY!H453 -> 0 | H9: =SVY!I453 -> 0 | I9: =SVY!J453 -> 0 | J9: =SVY!K453 -> 0 | ... Q9: =SVY!R453 -> 0.11383123
A10: Rural - farm q3 | B10: hhd-f3 | C10: =SVY!D454 -> 0.22046459 | D10: =SVY!E454 -> 0.20923347 | E10: =SVY!F454 -> 0.099784582 | F10: =SVY!G454 -> 0.0054874271 | G10: =SVY!H454 -> 0 | H10: =SVY!I454 -> 0 | I10: =SVY!J454 -> 0 | J10: =SVY!K454 -> 0 | ... Q10: =SVY!R454 -> 0.15986297
A11: Rural - farm q4 | B11: hhd-f4 | C11: =SVY!D455 -> 0.20649287 | D11: =SVY!E455 -> 0.22545432 | E11: =SVY!F455 -> 0.18535615 | F11: =SVY!G455 -> 0.12605772 | G11: =SVY!H455 -> 0 | H11: =SVY!I455 -> 0 | I11: =SVY!J455 -> 0 | J11: =SVY!K455 -> 0 | ... Q11: =SVY!R455 -> 0.19494254
A12: Rural - farm q5 | B12: hhd-f5 | C12: =SVY!D456 -> 0.103778 | D12: =SVY!E456 -> 0.17284774 | E12: =SVY!F456 -> 0.32959945 | F12: =SVY!G456 -> 0.38031867 | G12: =SVY!H456 -> 0 | H12: =SVY!I456 -> 0 | I12: =SVY!J456 -> 0 | J12: =SVY!K456 -> 0 | ... Q12: =SVY!R456 -> 0.12893035
A13: Rural - nonfarm q1 | B13: hhd-n1 | C13: =SVY!D457 -> 0.0092585833 | D13: =SVY!E457 -> 0.0033831982 | E13: =SVY!F457 -> 0 | F13: =SVY!G457 -> 0 | G13: =SVY!H457 -> 0 | H13: =SVY!I457 -> 0 | I13: =SVY!J457 -> 0 | J13: =SVY!K457 -> 0 | ... Q13: =SVY!R457 -> 0
A14: Rural - nonfarm q2 | B14: hhd-n2 | C14: =SVY!D458 -> 0.0031128255 | D14: =SVY!E458 -> 0.0037687682 | E14: =SVY!F458 -> 0.0019443243 | F14: =SVY!G458 -> 0 | G14: =SVY!H458 -> 0 | H14: =SVY!I458 -> 0 | I14: =SVY!J458 -> 0 | J14: =SVY!K458 -> 0 | ... Q14: =SVY!R458 -> 0
A15: Rural - nonfarm q3 | B15: hhd-n3 | C15: =SVY!D459 -> 0.010525274 | D15: =SVY!E459 -> 0.0099784499 | E15: =SVY!F459 -> 0.012743831 | F15: =SVY!G459 -> 0 | G15: =SVY!H459 -> 0 | H15: =SVY!I459 -> 0 | I15: =SVY!J459 -> 0 | J15: =SVY!K459 -> 0 | ... Q15: =SVY!R459 -> 0
A16: Rural - nonfarm q4 | B16: hhd-n4 | C16: =SVY!D460 -> 0.060890531 | D16: =SVY!E460 -> 0.062007005 | E16: =SVY!F460 -> 0.10484692 | F16: =SVY!G460 -> 0.068621996 | G16: =SVY!H460 -> 0 | H16: =SVY!I460 -> 0 | I16: =SVY!J460 -> 0 | J16: =SVY!K460 -> 0 | ... Q16: =SVY!R460 -> 0
A17: Rural - nonfarm q5 | B17: hhd-n5 | C17: =SVY!D461 -> 0.015863055 | D17: =SVY!E461 -> 0.043509482 | E17: =SVY!F461 -> 0.18049355 | F17: =SVY!G461 -> 0.41221056 | G17: =SVY!H461 -> 0 | H17: =SVY!I461 -> 0 | I17: =SVY!J461 -> 0 | J17: =SVY!K461 -> 0 | ... Q17: =SVY!R461 -> 0
A18: Urban - q1 | B18: hhd-u1 | C18: =SVY!D462 -> 0 | D18: =SVY!E462 -> 0 | E18: =SVY!F462 -> 0 | F18: =SVY!G462 -> 0 | G18: =SVY!H462 -> 0.15180034 | H18: =SVY!I462 -> 0.058134351 | I18: =SVY!J462 -> 0.0061220309 | J18: =SVY!K462 -> 0.0017944513 | ... Q18: =SVY!R462 -> 0.0056056852
A19: Urban - q2 | B19: hhd-u2 | C19: =SVY!D463 -> 0 | D19: =SVY!E463 -> 0 | E19: =SVY!F463 -> 0 | F19: =SVY!G463 -> 0 | G19: =SVY!H463 -> 0.15009388 | H19: =SVY!I463 -> 0.079049772 | I19: =SVY!J463 -> 0.012260127 | J19: =SVY!K463 -> 0.0035936116 | ... Q19: =SVY!R463 -> 0.0062917267
... A27: Kigali - q5 | B27: hhd-k5 | C27: =SVY!D471 -> 0 | D27: =SVY!E471 -> 0 | E27: =SVY!F471 -> 0 | F27: =SVY!G471 -> 0 | G27: =SVY!H471 -> 0 | H27: =SVY!I471 -> 0 | I27: =SVY!J471 -> 0 | J27: =SVY!K471 -> 0 | ... Q27: =SVY!R471 -> 0.10748496

Sheet AH
A1: Household own consumption
F4: Households' share of own consumption
B5: Own consumption share of | F5: ACTHHD | G5: Households
B6: total household consumption | G6: Rural - farm q1 | H6: Rural - farm q2 | I6: Rural - farm q3 | J6: Rural - farm q4 | K6: Rural - farm q5 | L6: Rural - nonfarm q1 | M6: Rural - nonfarm q2 | N6: Rural - nonfarm q3 | O6: Rural - nonfarm q4 | P6: Rural - nonfarm q5 | Q6: Urban - q1 | R6: Urban - q2 | S6: Urban - q3 | T6: Urban - q4 | U6: Urban - q5 | V6: Kigali - q1 | W6: Kigali - q2 | X6: Kigali - q3 | Y6: Kigali - q4 | Z6: Kigali - q5
B7: OWNSHR | G7: hhd-f1 | H7: hhd-f2 | I7: hhd-f3 | J7: hhd-f4 | K7: hhd-f5 | L7: hhd-n1 | M7: hhd-n2 | N7: hhd-n3 | O7: hhd-n4 | P7: hhd-n5 | Q7: hhd-u1 | R7: hhd-u2 | S7: hhd-u3 | T7: hhd-u4 | U7: hhd-u5 | V7: hhd-k1 | W7: hhd-k2 | X7: hhd-k3 | Y7: hhd-k4 | Z7: hhd-k5
A8: Sorghum (A111) | B8: asorg | C8: =SVY!D117 -> 0.0090826841 | F8: asorg | G8: =SVY!D229 -> 0.10115023 | H8: =SVY!E229 -> 0.28651565 | I8: =SVY!F229 -> 0.13900145 | J8: =SVY!G229 -> 0.047965076 | K8: =SVY!H229 -> 0.11535926 | L8: =SVY!I229 -> 0 | M8: =SVY!J229 -> 0 | N8: =SVY!K229 -> 0 | ... Z8: =SVY!W229 -> 0.0077483372
A9: Maize (A112) | B9: amaiz | C9: =SVY!D118 -> 0.37819606 | F9: amaiz | G9: =SVY!D230 -> 0.1136522 | H9: =SVY!E230 -> 0.21170351 | I9: =SVY!F230 -> 0.22793792 | J9: =SVY!G230 -> 0.28953884 | K9: =SVY!H230 -> 0.13328287 | L9: =SVY!I230 -> 0 | M9: =SVY!J230 -> 0 | N9: =SVY!K230 -> 0 | ... Z9: =SVY!W230 -> 0.0046313071
A10: Wheat (A113) | B10: awhea | C10: =SVY!D119 -> 0.054519829 | F10: awhea | G10: =SVY!D231 -> 0.42169484 | H10: =SVY!E231 -> 0.43043722 | I10: =SVY!F231 -> 0.037551381 | J10: =SVY!G231 -> 0.067828857 | K10: =SVY!H231 -> 0.042487705 | L10: =SVY!I231 -> 0 | M10: =SVY!J231 -> 0 | N10: =SVY!K231 -> 0 | ... Z10: =SVY!W231 -> 0
A11: Paddy & husked rice (A116) | B11: arice | C11: =SVY!D120 -> 0.048623734 | F11: arice | G11: =SVY!D232 -> 0.042879806 | H11: =SVY!E232 -> 0.11070648 | I11: =SVY!F232 -> 0.17345243 | J11: =SVY!G232 -> 0.3518898 | K11: =SVY!H232 -> 0.26399988 | L11: =SVY!I232 -> 0 | M11: =SVY!J232 -> 0 | N11: =SVY!K232 -> 0 | ... Z11: =SVY!W232 -> 0
A12: Other cereals (A119) | B12: aocer | C12: =SVY!D121 -> 0 | F12: aocer | G12: =SVY!D233 -> 0 | H12: =SVY!E233 -> 0 | I12: =SVY!F233 -> 0 | J12: =SVY!G233 -> 0 | K12: =SVY!H233 -> 0 | L12: =SVY!I233 -> 0 | M12: =SVY!J233 -> 0 | N12: =SVY!K233 -> 0 | ... Z12: =SVY!W233 -> 0
A13: Irish potatoes (A121) | B13: aipot | C13: =SVY!D122 -> 0.74961992 | F13: aipot | G13: =SVY!D234 -> 0.068822373 | H13: =SVY!E234 -> 0.15511119 | I13: =SVY!F234 -> 0.21288179 | J13: =SVY!G234 -> 0.31738814 | K13: =SVY!H234 -> 0.22016748 | L13: =SVY!I234 -> 0 | M13: =SVY!J234 -> 0 | N13: =SVY!K234 -> 0 | ... Z13: =SVY!W234 -> 0.0022190598
A14: Sweet potatoes (A122) | B14: aspot | C14: =SVY!D123 -> 0.91713353 | F14: aspot | G14: =SVY!D235 -> 0.10126147 | H14: =SVY!E235 -> 0.20386101 | I14: =SVY!F235 -> 0.26130222 | J14: =SVY!G235 -> 0.27309641 | K14: =SVY!H235 -> 0.11945566 | L14: =SVY!I235 -> 0 | M14: =SVY!J235 -> 0 | N14: =SVY!K235 -> 0 | ... Z14: =SVY!W235 -> 0.010096242
A15: Cassava (A123) | B15: acass | C15: =SVY!D124 -> 0.23666939 | F15: acass | G15: =SVY!D236 -> 0.10113466 | H15: =SVY!E236 -> 0.15450757 | I15: =SVY!F236 -> 0.25943373 | J15: =SVY!G236 -> 0.30141685 | K15: =SVY!H236 -> 0.13318656 | L15: =SVY!I236 -> 0 | M15: =SVY!J236 -> 0 | N15: =SVY!K236 -> 0 | ... Z15: =SVY!W236 -> 0.015612611
A16: Other roots & tubers (A129) | B16: aroot | C16: =SVY!D125 -> 0.63020242 | F16: aroot | G16: =SVY!D237 -> 0.076354836 | H16: =SVY!E237 -> 0.15917166 | I16: =SVY!F237 -> 0.25811781 | J16: =SVY!G237 -> 0.3085671 | K16: =SVY!H237 -> 0.15161946 | L16: =SVY!I237 -> 0 | M16: =SVY!J237 -> 0 | N16: =SVY!K237 -> 0 | ... Z16: =SVY!W237 -> 0.013955795
A17: Dried beans (A131) | B17: abean | C17: =SVY!D126 -> 0.40271014 | F17: abean | G17: =SVY!D238 -> 0.1036524 | H17: =SVY!E238 -> 0.17727513 | I17: =SVY!F238 -> 0.22625055 | J17: =SVY!G238 -> 0.2772591 | K17: =SVY!H238 -> 0.15391815 | L17: =SVY!I238 -> 0 | M17: =SVY!J238 -> 0 | N17: =SVY!K238 -> 0 | ... Z17: =SVY!W238 -> 0.020588644
A18: Peas & other legumes (A132) | B18: apeas | C18: =SVY!D127 -> 0.066835422 | F18: apeas | G18: =SVY!D239 -> 0.056417716 | H18: =SVY!E239 -> 0.099033795 | I18: =SVY!F239 -> 0.21664893 | J18: =SVY!G239 -> 0.32256826 | K18: =SVY!H239 -> 0.2942151 | L18: =SVY!I239 -> 0 | M18: =SVY!J239 -> 0 | N18: =SVY!K239 -> 0 | ... Z18: =SVY!W239 -> 0.0031703605
A19: Other vegetables (A139) | B19: avege | C19: =SVY!D128 -> 0.10262336 | F19: avege | G19: =SVY!D240 -> 0.16266407 | H19: =SVY!E240 -> 0.18662736 | I19: =SVY!F240 -> 0.21966372 | J19: =SVY!G240 -> 0.21845125 | K19: =SVY!H240 -> 0.12270148 | L19: =SVY!I240 -> 0 | M19: =SVY!J240 -> 0 | N19: =SVY!K240 -> 0 | ... Z19: =SVY!W240 -> 0.014586378
... A111: Travel debits & credits (V00) | B111: atrdc | C111: =SVY!D220 -> 0 | F111: atrdc | G111: =SVY!D332 -> 0 | H111: =SVY!E332 -> 0 | I111: =SVY!F332 -> 0 | J111: =SVY!G332 -> 0 | K111: =SVY!H332 -> 0 | L111: =SVY!I332 -> 0 | M111: =SVY!J332 -> 0 | N111: =SVY!K332 -> 0 | ... Z111: =SVY!W332 -> 0

Sheet CH
A1: Household market consumption
A4: Households' share of marketed consumption
A5: COMHHD | C5: Households
C6: Rural - farm q1 | D6: Rural - farm q2 | E6: Rural - farm q3 | F6: Rural - farm q4 | G6: Rural - farm q5 | H6: Rural - nonfarm q1 | I6: Rural - nonfarm q2 | J6: Rural - nonfarm q3 | K6: Rural - nonfarm q4 | L6: Rural - nonfarm q5 | M6: Urban - q1 | N6: Urban - q2 | O6: Urban - q3 | P6: Urban - q4 | Q6: Urban - q5 | R6: Kigali - q1 | S6: Kigali - q2 | T6: Kigali - q3 | U6: Kigali - q4 | V6: Kigali - q5
C7: hhd-f1 | D7: hhd-f2 | E7: hhd-f3 | F7: hhd-f4 | G7: hhd-f5 | H7: hhd-n1 | I7: hhd-n2 | J7: hhd-n3 | K7: hhd-n4 | L7: hhd-n5 | M7: hhd-u1 | N7: hhd-u2 | O7: hhd-u3 | P7: hhd-u4 | Q7: hhd-u5 | R7: hhd-k1 | S7: hhd-k2 | T7: hhd-k3 | U7: hhd-k4 | V7: hhd-k5
A8: Sorghum (A111) | B8: csorg | C8: =SVY!D339 -> 0.077741863 | D8: =SVY!E339 -> 0.12811141 | E8: =SVY!F339 -> 0.21020468 | F8: =SVY!G339 -> 0.22813236 | G8: =SVY!H339 -> 0.20098426 | H8: =SVY!I339 -> 0.0021867699 | I8: =SVY!J339 -> 0 | J8: =SVY!K339 -> 0.00067208422 | ... V8: =SVY!W339 -> 0.023773125
A9: Maize (A112) | B9: cmaiz | C9: =SVY!D340 -> 0.17060048 | D9: =SVY!E340 -> 0.21754572 | E9: =SVY!F340 -> 0.2275114 | F9: =SVY!G340 -> 0.20681815 | G9: =SVY!H340 -> 0.091803822 | H9: =SVY!I340 -> 0.00049287001 | I9: =SVY!J340 -> 0.00015037411 | J9: =SVY!K340 -> 0.0011701526 | ... V9: =SVY!W340 -> 0.01557963
A10: Wheat (A113) | B10: cwhea | C10: =SVY!D341 -> 0.068464788 | D10: =SVY!E341 -> 0.098109475 | E10: =SVY!F341 -> 0.19578451 | F10: =SVY!G341 -> 0.19386283 | G10: =SVY!H341 -> 0.20407486 | H10: =SVY!I341 -> 0 | I10: =SVY!J341 -> 0 | J10: =SVY!K341 -> 0 | ... V10: =SVY!W341 -> 0.054709886
A11: Paddy & husked rice (A116) | B11: crice | C11: =SVY!D342 -> 0.056059242 | D11: =SVY!E342 -> 0.10462678 | E11: =SVY!F342 -> 0.15515738 | F11: =SVY!G342 -> 0.23357403 | G11: =SVY!H342 -> 0.18380854 | H11: =SVY!I342 -> 0.00046554919 | I11: =SVY!J342 -> 0.00045526679 | J11: =SVY!K342 -> 0.0019178109 | ... V11: =SVY!W342 -> 0.070517857
A12: Other cereals (A119) | B12: cocer | C12: =SVY!D343 -> 0.0050302063 | D12: =SVY!E343 -> 0.027685586 | E12: =SVY!F343 -> 0.13193012 | F12: =SVY!G343 -> 0.23138419 | G12: =SVY!H343 -> 0.24998625 | H12: =SVY!I343 -> 0 | I12: =SVY!J343 -> 0 | J12: =SVY!K343 -> 0 | ... V12: =SVY!W343 -> 0.13615702
A13: Irish potatoes (A121) | B13: cipot | C13: =SVY!D344 -> 0.17219315 | D13: =SVY!E344 -> 0.17695376 | E13: =SVY!F344 -> 0.18602358 | F13: =SVY!G344 -> 0.18228436 | G13: =SVY!H344 -> 0.094836318 | H13: =SVY!I344 -> 0.00024600233 | I13: =SVY!J344 -> 0 | J13: =SVY!K344 -> 0.00054400047 | ... V13: =SVY!W344 -> 0.058759348
A14: Sweet potatoes (A122) | B14: cspot | C14: =SVY!D345 -> 0.14163004 | D14: =SVY!E345 -> 0.17597503 | E14: =SVY!F345 -> 0.20096087 | F14: =SVY!G345 -> 0.20865496 | G14: =SVY!H345 -> 0.10287793 | H14: =SVY!I345 -> 0.00029258777 | I14: =SVY!J345 -> 0.0017971324 | J14: =SVY!K345 -> 0.0015210908 | ... V14: =SVY!W345 -> 0.065155861
A15: Cassava (A123) | B15: ccass | C15: =SVY!D346 -> 0.11846543 | D15: =SVY!E346 -> 0.15521952 | E15: =SVY!F346 -> 0.15617267 | F15: =SVY!G346 -> 0.17627424 | G15: =SVY!H346 -> 0.1114607 | H15: =SVY!I346 -> 0.0003820972 | I15: =SVY!J346 -> 0.00015627299 | J15: =SVY!K346 -> 0.0011793543 | ... V15: =SVY!W346 -> 0.092414932
A16: Other roots & tubers (A129) | B16: croot | C16: =SVY!D347 -> 0.13982378 | D16: =SVY!E347 -> 0.13131621 | E16: =SVY!F347 -> 0.18823388 | F16: =SVY!G347 -> 0.22084367 | G16: =SVY!H347 -> 0.12941565 | H16: =SVY!I347 -> 0 | I16: =SVY!J347 -> 0 | J16: =SVY!K347 -> 0 | ... V16: =SVY!W347 -> 0.027422214
A17: Dried beans (A131) | B17: cbean | C17: =SVY!D348 -> 0.13270662 | D17: =SVY!E348 -> 0.16695994 | E17: =SVY!F348 -> 0.19413236 | F17: =SVY!G348 -> 0.16528468 | G17: =SVY!H348 -> 0.10126751 | H17: =SVY!I348 -> 0.00034794324 | I17: =SVY!J348 -> 0.00045396527 | J17: =SVY!K348 -> 0.0016795315 | ... V17: =SVY!W348 -> 0.076607752
A18: Peas & other legumes (A132) | B18: cpeas | C18: =SVY!D349 -> 0.040115535 | D18: =SVY!E349 -> 0.076599112 | E18: =SVY!F349 -> 0.11137276 | F18: =SVY!G349 -> 0.17619194 | G18: =SVY!H349 -> 0.17325637 | H18: =SVY!I349 -> 0.00020371018 | I18: =SVY!J349 -> 0.0003008408 | J18: =SVY!K349 -> 0.0014509771 | ... V18: =SVY!W349 -> 0.20785116
A19: Other vegetables (A139) | B19: cvege | C19: =SVY!D350 -> 0.10924466 | D19: =SVY!E350 -> 0.1327151 | E19: =SVY!F350 -> 0.14412991 | F19: =SVY!G350 -> 0.1490009 | G19: =SVY!H350 -> 0.11880746 | H19: =SVY!I350 -> 0.00063747654 | I19: =SVY!J350 -> 0.00049546066 | J19: =SVY!K350 -> 0.001560689 | ... V19: =SVY!W350 -> 0.15726347
... A111: Travel debits & credits (V00) | B111: ctrdc | C111: =SVY!D442 -> 0.052673169 | D111: =SVY!E442 -> 0.076797628 | E111: =SVY!F442 -> 0.10082863 | F111: =SVY!G442 -> 0.13875894 | G111: =SVY!H442 -> 0.14489328 | H111: =SVY!I442 -> 0.00022639625 | I111: =SVY!J442 -> 0.00026641325 | J111: =SVY!K442 -> 0.001044192 | ... V111: =SVY!W442 -> 0.30123323

Sheet MH
A1: Miscellaneous household accounts
A3: Disaggregated households' income and expenditure shares
A4: MISCHHD | C4: Income shares (sums to 1) | G4: Expenditure shares (sums to 1)
C5: Factors | D5: Enterprises | E5: Government | F5: Rest of world | G5: Consumption | H5: Government | I5: Direct taxes | J5: Savings | K5: Rest of world
C6: inc | D6: inc | E6: inc | F6: inc | G6: exp | H6: exp | I6: exp | J6: exp | K6: exp | T6: Survey data
C7: fac | D7: ent | E7: gov | F7: row | G7: con | H7: gov | I7: dtax | J7: s-i | K7: row | U7: tcons | V7: pop
A8: Rural - farm q1 | B8: hhd-f1 | C8: =SVY!D530 -> 0.90609066 | D8: =SVY!E530 -> 0.021969066 | E8: =SVY!F530 -> 0.060957768 | F8: =SVY!G530 -> 0.01098251 | G8: =SVY!H530 -> 0.96084668 | H8: =SVY!I530 -> 0.0008419057 | I8: =SVY!J530 -> 0.0050205176 | J8: =SVY!K530 -> 0.03015304 | K8: =SVY!L530 -> 0.0031378599 | S8: Rural - farm q1 | T8: hhd-f1 | U8: =SVY!Y530 -> 294247.57 | V8: =SVY!D566 -> 2151.384
A9: Rural - farm q2 | B9: hhd-f2 | C9: =SVY!D531 -> 0.92236556 | D9: =SVY!E531 -> 0.030149855 | E9: =SVY!F531 -> 0.038403151 | F9: =SVY!G531 -> 0.0090814314 | G9: =SVY!H531 -> 0.96242339 | H9: =SVY!I531 -> 0.0021495348 | I9: =SVY!J531 -> 0.0050108697 | J9: =SVY!K531 -> 0.027821513 | K9: =SVY!L531 -> 0.0025946947 | S9: Rural - farm q2 | T9: hhd-f2 | U9: =SVY!Y531 -> 429883.16 | V9: =SVY!D567 -> 2082.696
A10: Rural - farm q3 | B10: hhd-f3 | C10: =SVY!D532 -> 0.93474497 | D10: =SVY!E532 -> 0.020093062 | E10: =SVY!F532 -> 0.031897306 | F10: =SVY!G532 -> 0.013264662 | G10: =SVY!H532 -> 0.95806307 | H10: =SVY!I532 -> 0.0028349943 | I10: =SVY!J532 -> 0.0059643142 | J10: =SVY!K532 -> 0.029347719 | K10: =SVY!L532 -> 0.0037899035 | S10: Rural - farm q3 | T10: hhd-f3 | U10: =SVY!Y532 -> 552628.93 | V10: =SVY!D568 -> 2026.14
A11: Rural - farm q4 | B11: hhd-f4 | C11: =SVY!D533 -> 0.89390197 | D11: =SVY!E533 -> 0.060272903 | E11: =SVY!F533 -> 0.032504148 | F11: =SVY!G533 -> 0.013320982 | G11: =SVY!H533 -> 0.93762172 | H11: =SVY!I533 -> 0.0045680542 | I11: =SVY!J533 -> 0.013214437 | J11: =SVY!K533 -> 0.040789791 | K11: =SVY!L533 -> 0.0038059949 | S11: Rural - farm q4 | T11: hhd-f4 | U11: =SVY!Y533 -> 722684.96 | V11: =SVY!D569 -> 1890.207
A12: Rural - farm q5 | B12: hhd-f5 | C12: =SVY!D534 -> 0.8682289 | D12: =SVY!E534 -> 0.075416484 | E12: =SVY!F534 -> 0.026995192 | F12: =SVY!G534 -> 0.029359422 | G12: =SVY!H534 -> 0.89055292 | H12: =SVY!I534 -> 0.020362578 | I12: =SVY!J534 -> 0.032912972 | J12: =SVY!K534 -> 0.047783121 | K12: =SVY!L534 -> 0.0083884063 | S12: Rural - farm q5 | T12: hhd-f5 | U12: =SVY!Y534 -> 656301.28 | V12: =SVY!D570 -> 970.2514
A13: Rural - nonfarm q1 | B13: hhd-n1 | C13: =SVY!D535 -> 0.90892374 | D13: =SVY!E535 -> 0 | E13: =SVY!F535 -> 0.075094827 | F13: =SVY!G535 -> 0.015981434 | G13: =SVY!H535 -> 0.99217669 | H13: =SVY!I535 -> 0 | I13: =SVY!J535 -> 0 | J13: =SVY!K535 -> 0.003257181 | K13: =SVY!L535 -> 0.0045661241 | S13: Rural - nonfarm q1 | T13: hhd-n1 | U13: =SVY!Y535 -> 988.06606 | V13: =SVY!D571 -> 8.869401
A14: Rural - nonfarm q2 | B14: hhd-n2 | C14: =SVY!D536 -> 0.92648872 | D14: =SVY!E536 -> 0 | E14: =SVY!F536 -> 0.073511284 | F14: =SVY!G536 -> 0 | G14: =SVY!H536 -> 0.95106898 | H14: =SVY!I536 -> 0.0070773368 | I14: =SVY!J536 -> 0.028309347 | J14: =SVY!K536 -> 0.013544333 | K14: =SVY!L536 -> 0 | S14: Rural - nonfarm q2 | T14: hhd-n2 | U14: =SVY!Y536 -> 1078.4692 | V14: =SVY!D572 -> 9.170509
A15: Rural - nonfarm q3 | B15: hhd-n3 | C15: =SVY!D537 -> 0.88447385 | D15: =SVY!E537 -> 0.055682486 | E15: =SVY!F537 -> 0.026404509 | F15: =SVY!G537 -> 0.033439157 | G15: =SVY!H537 -> 0.89630657 | H15: =SVY!I537 -> 0.0039281072 | I15: =SVY!J537 -> 0.050215348 | J15: =SVY!K537 -> 0.039995935 | K15: =SVY!L537 -> 0.0095540448 | S15: Rural - nonfarm q3 | T15: hhd-n3 | U15: =SVY!Y537 -> 3985.0376 | V15: =SVY!D573 -> 18.082
A16: Rural - nonfarm q4 | B16: hhd-n4 | C16: =SVY!D538 -> 0.88697175 | D16: =SVY!E538 -> 0.081994121 | E16: =SVY!F538 -> 0.0202944 | F16: =SVY!G538 -> 0.010739728 | G16: =SVY!H538 -> 0.83091202 | H16: =SVY!I538 -> 0.032673172 | I16: =SVY!J538 -> 0.054590341 | J16: =SVY!K538 -> 0.078755969 | K16: =SVY!L538 -> 0.0030684938 | S16: Rural - nonfarm q4 | T16: hhd-n4 | U16: =SVY!Y538 -> 9749.9734 | V16: =SVY!D574 -> 30.3314
A17: Rural - nonfarm q5 | B17: hhd-n5 | C17: =SVY!D539 -> 0.83629267 | D17: =SVY!E539 -> 0.12222508 | E17: =SVY!F539 -> 0.029152479 | F17: =SVY!G539 -> 0.012329766 | G17: =SVY!H539 -> 0.81322401 | H17: =SVY!I539 -> 0.042530336 | I17: =SVY!J539 -> 0.076779839 | J17: =SVY!K539 -> 0.063943026 | K17: =SVY!L539 -> 0.0035227903 | S17: Rural - nonfarm q5 | T17: hhd-n5 | U17: =SVY!Y539 -> 58158.204 | V17: =SVY!D575 -> 63.09233
A18: Urban - q1 | B18: hhd-u1 | C18: =SVY!D540 -> 0.91466938 | D18: =SVY!E540 -> 0.025621419 | E18: =SVY!F540 -> 0.051911684 | F18: =SVY!G540 -> 0.0077975124 | G18: =SVY!H540 -> 0.94097383 | H18: =SVY!I540 -> 0.0043648121 | I18: =SVY!J540 -> 0.01747804 | J18: =SVY!K540 -> 0.034955454 | K18: =SVY!L540 -> 0.0022278607 | S18: Urban - q1 | T18: hhd-u1 | U18: =SVY!Y540 -> 16732.514 | V18: =SVY!D576 -> 128.8187
A19: Urban - q2 | B19: hhd-u2 | C19: =SVY!D541 -> 0.89252967 | D19: =SVY!E541 -> 0.062500561 | E19: =SVY!F541 -> 0.03318368 | F19: =SVY!G541 -> 0.01178609 | G19: =SVY!H541 -> 0.94265348 | H19: =SVY!I541 -> 0.0032247044 | I19: =SVY!J541 -> 0.019744999 | J19: =SVY!K541 -> 0.031009361 | K19: =SVY!L541 -> 0.0033674544 | S19: Urban - q2 | T19: hhd-u2 | U19: =SVY!Y541 -> 29661.714 | V19: =SVY!D577 -> 142.283
... A27: Kigali - q5 | B27: hhd-k5 | C27: =SVY!D549 -> 0.81610025 | D27: =SVY!E549 -> 0.0999817 | E27: =SVY!F549 -> 0.02975909 | F27: =SVY!G549 -> 0.054158962 | G27: =SVY!H549 -> 0.57144256 | H27: =SVY!I549 -> 0.068843307 | I27: =SVY!J549 -> 0.11684938 | J27: =SVY!K549 -> 0.22739077 | K27: =SVY!L549 -> 0.015473989 | S27: Kigali - q5 | T27: hhd-k5 | U27: =SVY!Y549 -> 1093372.5 | V27: =SVY!D585 -> 959.8911

Sheet SVY
A1: Data tables extracted from household and labor force surveys
A4: Factor income generation | EG4: Survey data table - Labor wages | EQ4: Scaling | ER4: Scaled | ES4: Original | EU4: Survey data table - Nonfarm enterprises earnings | FE4: Scaling | FF4: Scaled | FG4: Original | FI4: Survey data table - Crop earnings | FS4: Scaling | FT4: Scaled | FU4: Original | FW4: Survey data table - Livestock earnings | GG4: Scaling | GH4: Scaled | GI4: Original | GK4: Survey data table - Labor wages | GU4: Scaling | GV4: Scaled | GW4: Original
A5: FACACT | R5: Shares | AE5: Education levels | AI5: Original | AK5: Selected | AN5: Scaled | AQ5: Shares | BE5: Adjustment factors | BS5: Adjusted values | CH5: Assigned to sectors | CV5: Adjusted values | DK5: Combined data | DY5: Selected sector data sources | EG5: Household survey (act_wage) | EQ5: 1 | ER5: =EQ5*ES5 -> 1895875.9 | ES5: =SUM(EH7:ES110) -> 1895875.9 | EU5: Household survey (act_entr) | FE5: 1 | FF5: =FE5*FG5 -> 11272241 | FG5: =SUM(EV7:FG110) -> 11272241 | FI5: Household survey (act_crop) | FS5: 1 | FT5: =FS5*FU5 -> 524967.34 | FU5: =SUM(FJ7:FU110) -> 524967.34 | FW5: Household survey (act_live) | GG5: 1 | GH5: =GG5*GI5 -> 345167.15 | GI5: =SUM(FX7:GI110) -> 345167.15 | GK5: Labor force survey (act_wage) | GU5: 1 | GV5: =GU5*GW5 -> 2970969.4 | GW5: =SUM(GL7:GW110) -> 2970969.4
D6: flab-rn | E6: flab-rp | F6: flab-rs | G6: flab-rt | H6: flab-un | I6: flab-up | J6: flab-us | K6: flab-ut | L6: flab-kn | M6: flab-kp | N6: flab-ks | O6: flab-kt | S6: flab-rn | T6: flab-rp | U6: flab-rs | V6: flab-rt | W6: flab-un | X6: flab-up | Y6: flab-us | Z6: flab-ut | AA6: flab-kn | AB6: flab-kp | AC6: flab-ks | AD6: flab-kt | AE6: None | AF6: Primary | AG6: Secondary | AH6: Tertiary | AI6: Rural | AJ6: Urban | AK6: Rural | AL6: Urban | AM6: Kigali | AN6: Rural | AO6: Urban | AR6: flab-rn | AS6: flab-rp | AT6: flab-rs | AU6: flab-rt | AV6: flab-un | AW6: flab-up | AX6: flab-us | AY6: flab-ut | AZ6: flab-kn | BA6: flab-kp | BB6: flab-ks | BC6: flab-kt | BF6: flab-rn | BG6: flab-rp | BH6: flab-rs | BI6: flab-rt | BJ6: flab-un | BK6: flab-up | BL6: flab-us | BM6: flab-ut | BN6: flab-kn | BO6: flab-kp | BP6: flab-ks | BQ6: flab-kt | BT6: flab-rn | BU6: flab-rp | BV6: flab-rs | BW6: flab-rt | BX6: flab-un | BY6: flab-up | BZ6: flab-us | CA6: flab-ut | CB6: flab-kn | CC6: flab-kp | CD6: flab-ks | CE6: flab-kt | CG6: Use which sector? | CI6: flab-rn | CJ6: flab-rp | CK6: flab-rs | CL6: flab-rt | CM6: flab-un | CN6: flab-up | CO6: flab-us | CP6: flab-ut | CQ6: flab-kn | CR6: flab-kp | CS6: flab-ks | CT6: flab-kt | CW6: flab-rn | CX6: flab-rp | CY6: flab-rs | CZ6: flab-rt | DA6: flab-un | DB6: flab-up | DC6: flab-us | DD6: flab-ut | DE6: flab-kn | DF6: flab-kp | DG6: flab-ks | DH6: flab-kt | DJ6: Aggregate to which sectors? | DL6: flab-rn | DM6: flab-rp | DN6: flab-rs | DO6: flab-rt | DP6: flab-un | DQ6: flab-up | DR6: flab-us | DS6: flab-ut | DT6: flab-kn | DU6: flab-kp | DV6: flab-ks | DW6: flab-kt | DZ6: Wages | EA6: Enterprises | EB6: Crops | EC6: Livestock | ED6: Other | EG6: samdesc | EH6: flab11 | EI6: flab12 | EJ6: flab13 | EK6: flab14 | EL6: flab21 | EM6: flab22 | EN6: flab23 | EO6: flab24 | EP6: flab31 | EQ6: flab32 | ER6: flab33 | ES6: flab34 | EU6: samdesc | EV6: flab11 | EW6: flab12 | EX6: flab13 | EY6: flab14 | EZ6: flab21 | FA6: flab22 | FB6: flab23 | FC6: flab24 | FD6: flab31 | FE6: flab32 | FF6: flab33 | FG6: flab34 | FI6: samdesc | FJ6: flab11 | FK6: flab12 | FL6: flab13 | FM6: flab14 | FN6: flab21 | FO6: flab22 | FP6: flab23 | FQ6: flab24 | FR6: flab31 | FS6: flab32 | FT6: flab33 | FU6: flab34 | FW6: samdesc | FX6: flab11 | FY6: flab12 | FZ6: flab13 | GA6: flab14 | GB6: flab21 | GC6: flab22 | GD6: flab23 | GE6: flab24 | GF6: flab31 | GG6: flab32 | GH6: flab33 | GI6: flab34 | GK6: samdesc | GL6: flab11 | GM6: flab12 | GN6: flab13 | GO6: flab14 | GP6: flab21 | GQ6: flab22 | GR6: flab23 | GS6: flab24 | GT6: flab31 | GU6: flab32 | GV6: flab33 | GW6: flab34
C7: asorg | D7: =IF(SUM($S7:$AD7),S7/SUM($S7:$AD7),0) -> 0.49259772 | E7: =IF(SUM($S7:$AD7),T7/SUM($S7:$AD7),0) -> 0.3616742 | F7: =IF(SUM($S7:$AD7),U7/SUM($S7:$AD7),0) -> 0.039480441 | G7: =IF(SUM($S7:$AD7),V7/SUM($S7:$AD7),0) -> 0.010552685 | H7: =IF(SUM($S7:$AD7),W7/SUM($S7:$AD7),0) -> 0.010225128 | I7: =IF(SUM($S7:$AD7),X7/SUM($S7:$AD7),0) -> 0.018300974 | J7: =IF(SUM($S7:$AD7),Y7/SUM($S7:$AD7),0) -> 0.0045167072 | K7: =IF(SUM($S7:$AD7),Z7/SUM($S7:$AD7),0) -> 0.0054580675 | ... O7: =IF(SUM($S7:$AD7),AD7/SUM($S7:$AD7),0) -> 0.0087581275 | P7: =SUM(D7:O7) -> 1 | R7: asorg | S7: =IF(SUM($AR7:$AU7),$AK7*AR7/SUM($AR7:$AU7),0) -> 0.49259772 | T7: =IF(SUM($AR7:$AU7),$AK7*AS7/SUM($AR7:$AU7),0) -> 0.3616742 | U7: =IF(SUM($AR7:$AU7),$AK7*AT7/SUM($AR7:$AU7),0) -> 0.039480441 | V7: =IF(SUM($AR7:$AU7),$AK7*AU7/SUM($AR7:$AU7),0) -> 0.010552685 | W7: =IF(SUM($AV7:$AY7),$AL7*AV7/SUM($AV7:$AY7),0) -> 0.010225128 | X7: =IF(SUM($AV7:$AY7),$AL7*AW7/SUM($AV7:$AY7),0) -> 0.018300974 | Y7: =IF(SUM($AV7:$AY7),$AL7*AX7/SUM($AV7:$AY7),0) -> 0.0045167072 | Z7: =IF(SUM($AV7:$AY7),$AL7*AY7/SUM($AV7:$AY7),0) -> 0.0054580675 | AA7: =IF(SUM($AZ7:$BC7),(1-$AL7-$AK7)*AZ7/SUM($AZ7:$BC7),0) -> 0.020208753 | AB7: =IF(SUM($AZ7:$BC7),(1-$AL7-$AK7)*BA7/SUM($AZ7:$BC7),0) -> 0.022175616 | AC7: =IF(SUM($AZ7:$BC7),(1-$AL7-$AK7)*BB7/SUM($AZ7:$BC7),0) -> 0.006051581 | AD7: =IF(SUM($AZ7:$BC7),(1-$AL7-$AK7)*BC7/SUM($AZ7:$BC7),0) -> 0.0087581275 | AE7: =S7+W7+AA7 -> 0.5230316 | AF7: =T7+X7+AB7 -> 0.40215079 | AG7: =U7+Y7+AC7 -> 0.050048729 | AH7: =V7+Z7+AD7 -> 0.02476888 | AI7: =IF(SUM($DL7:$DW7),SUM(DL7:DO7)/SUM($DL7:$DW7),0) -> 0.90430505 | AJ7: =IF(SUM($DL7:$DW7),SUM(DP7:DS7)/SUM($DL7:$DW7),0) -> 0.038500876 | AK7: =AI7 -> 0.90430505 | AL7: =AJ7 -> 0.038500876 | AM7: =1-SUM(AK7:AL7) -> 0.057194077 | AN7: 1 | AO7: 1 | AQ7: asorg | AR7: =IF(SUM($BT7:$CE7),BT7/SUM($BT7:$CE7),0) -> 0.49922991 | AS7: =IF(SUM($BT7:$CE7),BU7/SUM($BT7:$CE7),0) -> 0.36654367 | AT7: =IF(SUM($BT7:$CE7),BV7/SUM($BT7:$CE7),0) -> 0.040011994 | AU7: =IF(SUM($BT7:$CE7),BW7/SUM($BT7:$CE7),0) -> 0.010694763 | AV7: =IF(SUM($BT7:$CE7),BX7/SUM($BT7:$CE7),0) -> 0.011165037 | AW7: =IF(SUM($BT7:$CE7),BY7/SUM($BT7:$CE7),0) -> 0.019983226 | AX7: =IF(SUM($BT7:$CE7),BZ7/SUM($BT7:$CE7),0) -> 0.0049318896 | AY7: =IF(SUM($BT7:$CE7),CA7/SUM($BT7:$CE7),0) -> 0.0059597812 | ... BC7: =IF(SUM($BT7:$CE7),CE7/SUM($BT7:$CE7),0) -> 0.0063517897 | BE7: asorg | BF7: 1 | BG7: 1 | BH7: 1 | BI7: 1 | BJ7: 1 | BK7: 1 | BL7: 1 | BM7: 1 | BN7: 1 | BO7: 1 | BP7: 1 | BQ7: 1 | BS7: asorg | BT7: =BF7*CI7 -> 42948.13 | BU7: =BG7*CJ7 -> 31533.298 | BV7: =BH7*CK7 -> 3442.1822 | BW7: =BI7*CL7 -> 920.0572 | BX7: =BJ7*CM7 -> 960.51426 | BY7: =BK7*CN7 -> 1719.1322 | BZ7: =BL7*CO7 -> 424.28435 | CA7: =BM7*CP7 -> 512.71259 | ... CE7: =BQ7*CT7 -> 546.43659 | CG7: =DJ7 -> asorg | CH7: asorg | CI7: =SUMIF($CV$7:$CV$110,$CG7,CW$7:CW$110) -> 42948.13 | CJ7: =SUMIF($CV$7:$CV$110,$CG7,CX$7:CX$110) -> 31533.298 | CK7: =SUMIF($CV$7:$CV$110,$CG7,CY$7:CY$110) -> 3442.1822 | CL7: =SUMIF($CV$7:$CV$110,$CG7,CZ$7:CZ$110) -> 920.0572 | CM7: =SUMIF($CV$7:$CV$110,$CG7,DA$7:DA$110) -> 960.51426 | CN7: =SUMIF($CV$7:$CV$110,$CG7,DB$7:DB$110) -> 1719.1322 | CO7: =SUMIF($CV$7:$CV$110,$CG7,DC$7:DC$110) -> 424.28435 | CP7: =SUMIF($CV$7:$CV$110,$CG7,DD$7:DD$110) -> 512.71259 | ... CT7: =SUMIF($CV$7:$CV$110,$CG7,DH$7:DH$110) -> 546.43659 | CV7: asorg | CW7: =SUMIF($DJ$7:$DJ$110,$CV7,DL$7:DL$110) -> 42948.13 | CX7: =SUMIF($DJ$7:$DJ$110,$CV7,DM$7:DM$110) -> 31533.298 | CY7: =SUMIF($DJ$7:$DJ$110,$CV7,DN$7:DN$110) -> 3442.1822 | CZ7: =SUMIF($DJ$7:$DJ$110,$CV7,DO$7:DO$110) -> 920.0572 | DA7: =SUMIF($DJ$7:$DJ$110,$CV7,DP$7:DP$110) -> 960.51426 | DB7: =SUMIF($DJ$7:$DJ$110,$CV7,DQ$7:DQ$110) -> 1719.1322 | DC7: =SUMIF($DJ$7:$DJ$110,$CV7,DR$7:DR$110) -> 424.28435 | DD7: =SUMIF($DJ$7:$DJ$110,$CV7,DS$7:DS$110) -> 512.71259 | ... DH7: =SUMIF($DJ$7:$DJ$110,$CV7,DW$7:DW$110) -> 546.43659 | DJ7: asorg | DK7: asorg | DL7: =SUMIF($EF$7:$EF$110,$DK7,EH$7:EH$110)*$DZ7*$EQ$5+SUMIF($ET$7:$ET$110,$DK7,EV$7:EV$110)*$EA7*$FE$5+SUMIF($FH$7:$FH$110,$DK7,FJ$7:FJ$110)*$EB7*$FS$5+SUMIF($FV$7:$FV$110,$DK7,FX$7:FX$110)*$EC7*$GG$5+SUMIF($GJ$7:$GJ$110,$DK7,GL$7:GL$110)*$ED7*$GU$5 -> 10925.36 | DM7: =SUMIF($EF$7:$EF$110,$DK7,EI$7:EI$110)*$DZ7*$EQ$5+SUMIF($ET$7:$ET$110,$DK7,EW$7:EW$110)*$EA7*$FE$5+SUMIF($FH$7:$FH$110,$DK7,FK$7:FK$110)*$EB7*$FS$5+SUMIF($FV$7:$FV$110,$DK7,FY$7:FY$110)*$EC7*$GG$5+SUMIF($GJ$7:$GJ$110,$DK7,GM$7:GM$110)*$ED7*$GU$5 -> 8040.616 | DN7: =SUMIF($EF$7:$EF$110,$DK7,EJ$7:EJ$110)*$DZ7*$EQ$5+SUMIF($ET$7:$ET$110,$DK7,EX$7:EX$110)*$EA7*$FE$5+SUMIF($FH$7:$FH$110,$DK7,FL$7:FL$110)*$EB7*$FS$5+SUMIF($FV$7:$FV$110,$DK7,FZ$7:FZ$110)*$EC7*$GG$5+SUMIF($GJ$7:$GJ$110,$DK7,GN$7:GN$110)*$ED7*$GU$5 -> 669.4517 | DO7: =SUMIF($EF$7:$EF$110,$DK7,EK$7:EK$110)*$DZ7*$EQ$5+SUMIF($ET$7:$ET$110,$DK7,EY$7:EY$110)*$EA7*$FE$5+SUMIF($FH$7:$FH$110,$DK7,FM$7:FM$110)*$EB7*$FS$5+SUMIF($FV$7:$FV$110,$DK7,GA$7:GA$110)*$EC7*$GG$5+SUMIF($GJ$7:$GJ$110,$DK7,GO$7:GO$110)*$ED7*$GU$5 -> 271.1942 | DP7: =SUMIF($EF$7:$EF$110,$DK7,EL$7:EL$110)*$DZ7*$EQ$5+SUMIF($ET$7:$ET$110,$DK7,EZ$7:EZ$110)*$EA7*$FE$5+SUMIF($FH$7:$FH$110,$DK7,FN$7:FN$110)*$EB7*$FS$5+SUMIF($FV$7:$FV$110,$DK7,GB$7:GB$110)*$EC7*$GG$5+SUMIF($GJ$7:$GJ$110,$DK7,GP$7:GP$110)*$ED7*$GU$5 -> 266.2394 | DQ7: =SUMIF($EF$7:$EF$110,$DK7,EM$7:EM$110)*$DZ7*$EQ$5+SUMIF($ET$7:$ET$110,$DK7,FA$7:FA$110)*$EA7*$FE$5+SUMIF($FH$7:$FH$110,$DK7,FO$7:FO$110)*$EB7*$FS$5+SUMIF($FV$7:$FV$110,$DK7,GC$7:GC$110)*$EC7*$GG$5+SUMIF($GJ$7:$GJ$110,$DK7,GQ$7:GQ$110)*$ED7*$GU$5 -> 382.885 | DR7: =SUMIF($EF$7:$EF$110,$DK7,EN$7:EN$110)*$DZ7*$EQ$5+SUMIF($ET$7:$ET$110,$DK7,FB$7:FB$110)*$EA7*$FE$5+SUMIF($FH$7:$FH$110,$DK7,FP$7:FP$110)*$EB7*$FS$5+SUMIF($FV$7:$FV$110,$DK7,GD$7:GD$110)*$EC7*$GG$5+SUMIF($GJ$7:$GJ$110,$DK7,GR$7:GR$110)*$ED7*$GU$5 -> 70.75178 | DS7: =SUMIF($EF$7:$EF$110,$DK7,EO$7:EO$110)*$DZ7*$EQ$5+SUMIF($ET$7:$ET$110,$DK7,FC$7:FC$110)*$EA7*$FE$5+SUMIF($FH$7:$FH$110,$DK7,FQ$7:FQ$110)*$EB7*$FS$5+SUMIF($FV$7:$FV$110,$DK7,GE$7:GE$110)*$EC7*$GG$5+SUMIF($GJ$7:$GJ$110,$DK7,GS$7:GS$110)*$ED7*$GU$5 -> 127.6502 | ... DW7: =SUMIF($EF$7:$EF$110,$DK7,ES$7:ES$110)*$DZ7*$EQ$5+SUMIF($ET$7:$ET$110,$DK7,FG$7:FG$110)*$EA7*$FE$5+SUMIF($FH$7:$FH$110,$DK7,FU$7:FU$110)*$EB7*$FS$5+SUMIF($FV$7:$FV$110,$DK7,GI$7:GI$110)*$EC7*$GG$5+SUMIF($GJ$7:$GJ$110,$DK7,GW$7:GW$110)*$ED7*$GU$5 -> 27.28041 | DY7: asorg | EB7: 1 | EF7: asorg | EG7: asorg | EH7: 203840.1 | EI7: 110616 | EJ7: 5835.801 | EK7: 3262.225 | EL7: 10266.58 | EM7: 5551.206 | EN7: 2781.239 | EO7: 2664.473 | EP7: 11009.96 | EQ7: 10010.09 | ER7: 534.5046 | ES7: 11988.09 | ET7: asorg | EU7: asorg | EV7: 116761.2 | EW7: 56703.02 | EX7: 1276.127 | EY7: 1920.307 | EZ7: 820.746 | FA7: 1620.492 | FB7: 1031.184 | FC7: 2424.438 | FH7: asorg | FI7: asorg | FJ7: 10925.36 | FK7: 8040.616 | FL7: 669.4517 | FM7: 271.1942 | FN7: 266.2394 | FO7: 382.885 | FP7: 70.75178 | FQ7: 127.6502 | FR7: 606.6286 | FS7: 601.7004 | FT7: 23.4136 | FU7: 27.28041 | FV7: asorg | FW7: asorg | GJ7: asorg | GK7: asorg | GL7: 239409.9 | GM7: 182258.8 | GN7: 8501.997 | GO7: 11772.6 | GP7: 11413.77 | GQ7: 7730.901 | GR7: 2652.024 | GS7: 1477.278 | GT7: 2303.398 | GU7: 1577.814 | GV7: 1268.048 | GW7: 11178.09
C8: amaiz | D8: =IF(SUM($S8:$AD8),S8/SUM($S8:$AD8),0) -> 0.49922869 | E8: =IF(SUM($S8:$AD8),T8/SUM($S8:$AD8),0) -> 0.36654278 | F8: =IF(SUM($S8:$AD8),U8/SUM($S8:$AD8),0) -> 0.040011896 | G8: =IF(SUM($S8:$AD8),V8/SUM($S8:$AD8),0) -> 0.010694737 | H8: =IF(SUM($S8:$AD8),W8/SUM($S8:$AD8),0) -> 0.010577163 | I8: =IF(SUM($S8:$AD8),X8/SUM($S8:$AD8),0) -> 0.018931048 | J8: =IF(SUM($S8:$AD8),Y8/SUM($S8:$AD8),0) -> 0.0046722106 | K8: =IF(SUM($S8:$AD8),Z8/SUM($S8:$AD8),0) -> 0.0056459805 | ... O8: =IF(SUM($S8:$AD8),AD8/SUM($S8:$AD8),0) -> 0.006691091 | P8: =SUM(D8:O8) -> 1 | R8: amaiz | S8: =IF(SUM($AR8:$AU8),$AK8*AR8/SUM($AR8:$AU8),0) -> 0.49922869 | T8: =IF(SUM($AR8:$AU8),$AK8*AS8/SUM($AR8:$AU8),0) -> 0.36654278 | U8: =IF(SUM($AR8:$AU8),$AK8*AT8/SUM($AR8:$AU8),0) -> 0.040011896 | V8: =IF(SUM($AR8:$AU8),$AK8*AU8/SUM($AR8:$AU8),0) -> 0.010694737 | W8: =IF(SUM($AV8:$AY8),$AL8*AV8/SUM($AV8:$AY8),0) -> 0.010577163 | X8: =IF(SUM($AV8:$AY8),$AL8*AW8/SUM($AV8:$AY8),0) -> 0.018931048 | Y8: =IF(SUM($AV8:$AY8),$AL8*AX8/SUM($AV8:$AY8),0) -> 0.0046722106 | Z8: =IF(SUM($AV8:$AY8),$AL8*AY8/SUM($AV8:$AY8),0) -> 0.0056459805 | AA8: =IF(SUM($AZ8:$BC8),(1-$AL8-$AK8)*AZ8/SUM($AZ8:$BC8),0) -> 0.015439214 | AB8: =IF(SUM($AZ8:$BC8),(1-$AL8-$AK8)*BA8/SUM($AZ8:$BC8),0) -> 0.016941871 | AC8: =IF(SUM($AZ8:$BC8),(1-$AL8-$AK8)*BB8/SUM($AZ8:$BC8),0) -> 0.0046233261 | AD8: =IF(SUM($AZ8:$BC8),(1-$AL8-$AK8)*BC8/SUM($AZ8:$BC8),0) -> 0.006691091 | AE8: =S8+W8+AA8 -> 0.52524506 | AF8: =T8+X8+AB8 -> 0.40241569 | AG8: =U8+Y8+AC8 -> 0.049307433 | AH8: =V8+Z8+AD8 -> 0.023031808 | AI8: =IF(SUM($DL8:$DW8),SUM(DL8:DO8)/SUM($DL8:$DW8),0) -> 0.9164781 | AJ8: =IF(SUM($DL8:$DW8),SUM(DP8:DS8)/SUM($DL8:$DW8),0) -> 0.039826403 | AK8: =AI8 -> 0.9164781 | AL8: =AJ8 -> 0.039826403 | AM8: =1-SUM(AK8:AL8) -> 0.043695501 | AN8: 1 | AO8: 1 | AQ8: amaiz | AR8: =IF(SUM($BT8:$CE8),BT8/SUM($BT8:$CE8),0) -> 0.49922991 | AS8: =IF(SUM($BT8:$CE8),BU8/SUM($BT8:$CE8),0) -> 0.36654367 | AT8: =IF(SUM($BT8:$CE8),BV8/SUM($BT8:$CE8),0) -> 0.040011994 | AU8: =IF(SUM($BT8:$CE8),BW8/SUM($BT8:$CE8),0) -> 0.010694763 | AV8: =IF(SUM($BT8:$CE8),BX8/SUM($BT8:$CE8),0) -> 0.011165037 | AW8: =IF(SUM($BT8:$CE8),BY8/SUM($BT8:$CE8),0) -> 0.019983226 | AX8: =IF(SUM($BT8:$CE8),BZ8/SUM($BT8:$CE8),0) -> 0.0049318896 | AY8: =IF(SUM($BT8:$CE8),CA8/SUM($BT8:$CE8),0) -> 0.0059597812 | ... BC8: =IF(SUM($BT8:$CE8),CE8/SUM($BT8:$CE8),0) -> 0.0063517897 | BE8: amaiz | BF8: 1 | BG8: 1 | BH8: 1 | BI8: 1 | BJ8: 1 | BK8: 1 | BL8: 1 | BM8: 1 | BN8: 1 | BO8: 1 | BP8: 1 | BQ8: 1 | BS8: amaiz | BT8: =BF8*CI8 -> 42948.13 | BU8: =BG8*CJ8 -> 31533.298 | BV8: =BH8*CK8 -> 3442.1822 | BW8: =BI8*CL8 -> 920.0572 | BX8: =BJ8*CM8 -> 960.51426 | BY8: =BK8*CN8 -> 1719.1322 | BZ8: =BL8*CO8 -> 424.28435 | CA8: =BM8*CP8 -> 512.71259 | ... CE8: =BQ8*CT8 -> 546.43659 | CG8: =DJ8 -> asorg | CH8: amaiz | CI8: =SUMIF($CV$7:$CV$110,$CG8,CW$7:CW$110) -> 42948.13 | CJ8: =SUMIF($CV$7:$CV$110,$CG8,CX$7:CX$110) -> 31533.298 | CK8: =SUMIF($CV$7:$CV$110,$CG8,CY$7:CY$110) -> 3442.1822 | CL8: =SUMIF($CV$7:$CV$110,$CG8,CZ$7:CZ$110) -> 920.0572 | CM8: =SUMIF($CV$7:$CV$110,$CG8,DA$7:DA$110) -> 960.51426 | CN8: =SUMIF($CV$7:$CV$110,$CG8,DB$7:DB$110) -> 1719.1322 | CO8: =SUMIF($CV$7:$CV$110,$CG8,DC$7:DC$110) -> 424.28435 | CP8: =SUMIF($CV$7:$CV$110,$CG8,DD$7:DD$110) -> 512.71259 | ... CT8: =SUMIF($CV$7:$CV$110,$CG8,DH$7:DH$110) -> 546.43659 | CV8: amaiz | CW8: =SUMIF($DJ$7:$DJ$110,$CV8,DL$7:DL$110) -> 0 | CX8: =SUMIF($DJ$7:$DJ$110,$CV8,DM$7:DM$110) -> 0 | CY8: =SUMIF($DJ$7:$DJ$110,$CV8,DN$7:DN$110) -> 0 | CZ8: =SUMIF($DJ$7:$DJ$110,$CV8,DO$7:DO$110) -> 0 | DA8: =SUMIF($DJ$7:$DJ$110,$CV8,DP$7:DP$110) -> 0 | DB8: =SUMIF($DJ$7:$DJ$110,$CV8,DQ$7:DQ$110) -> 0 | DC8: =SUMIF($DJ$7:$DJ$110,$CV8,DR$7:DR$110) -> 0 | DD8: =SUMIF($DJ$7:$DJ$110,$CV8,DS$7:DS$110) -> 0 | ... DH8: =SUMIF($DJ$7:$DJ$110,$CV8,DW$7:DW$110) -> 0 | DJ8: asorg | DK8: amaiz | DL8: =SUMIF($EF$7:$EF$110,$DK8,EH$7:EH$110)*$DZ8*$EQ$5+SUMIF($ET$7:$ET$110,$DK8,EV$7:EV$110)*$EA8*$FE$5+SUMIF($FH$7:$FH$110,$DK8,FJ$7:FJ$110)*$EB8*$FS$5+SUMIF($FV$7:$FV$110,$DK8,FX$7:FX$110)*$EC8*$GG$5+SUMIF($GJ$7:$GJ$110,$DK8,GL$7:GL$110)*$ED8*$GU$5 -> 23848.1 | DM8: =SUMIF($EF$7:$EF$110,$DK8,EI$7:EI$110)*$DZ8*$EQ$5+SUMIF($ET$7:$ET$110,$DK8,EW$7:EW$110)*$EA8*$FE$5+SUMIF($FH$7:$FH$110,$DK8,FK$7:FK$110)*$EB8*$FS$5+SUMIF($FV$7:$FV$110,$DK8,FY$7:FY$110)*$EC8*$GG$5+SUMIF($GJ$7:$GJ$110,$DK8,GM$7:GM$110)*$ED8*$GU$5 -> 18047.67 | DN8: =SUMIF($EF$7:$EF$110,$DK8,EJ$7:EJ$110)*$DZ8*$EQ$5+SUMIF($ET$7:$ET$110,$DK8,EX$7:EX$110)*$EA8*$FE$5+SUMIF($FH$7:$FH$110,$DK8,FL$7:FL$110)*$EB8*$FS$5+SUMIF($FV$7:$FV$110,$DK8,FZ$7:FZ$110)*$EC8*$GG$5+SUMIF($GJ$7:$GJ$110,$DK8,GN$7:GN$110)*$ED8*$GU$5 -> 2034.078 | DO8: =SUMIF($EF$7:$EF$110,$DK8,EK$7:EK$110)*$DZ8*$EQ$5+SUMIF($ET$7:$ET$110,$DK8,EY$7:EY$110)*$EA8*$FE$5+SUMIF($FH$7:$FH$110,$DK8,FM$7:FM$110)*$EB8*$FS$5+SUMIF($FV$7:$FV$110,$DK8,GA$7:GA$110)*$EC8*$GG$5+SUMIF($GJ$7:$GJ$110,$DK8,GO$7:GO$110)*$ED8*$GU$5 -> 572.4752 | DP8: =SUMIF($EF$7:$EF$110,$DK8,EL$7:EL$110)*$DZ8*$EQ$5+SUMIF($ET$7:$ET$110,$DK8,EZ$7:EZ$110)*$EA8*$FE$5+SUMIF($FH$7:$FH$110,$DK8,FN$7:FN$110)*$EB8*$FS$5+SUMIF($FV$7:$FV$110,$DK8,GB$7:GB$110)*$EC8*$GG$5+SUMIF($GJ$7:$GJ$110,$DK8,GP$7:GP$110)*$ED8*$GU$5 -> 665.4911 | DQ8: =SUMIF($EF$7:$EF$110,$DK8,EM$7:EM$110)*$DZ8*$EQ$5+SUMIF($ET$7:$ET$110,$DK8,FA$7:FA$110)*$EA8*$FE$5+SUMIF($FH$7:$FH$110,$DK8,FO$7:FO$110)*$EB8*$FS$5+SUMIF($FV$7:$FV$110,$DK8,GC$7:GC$110)*$EC8*$GG$5+SUMIF($GJ$7:$GJ$110,$DK8,GQ$7:GQ$110)*$ED8*$GU$5 -> 992.3242 | DR8: =SUMIF($EF$7:$EF$110,$DK8,EN$7:EN$110)*$DZ8*$EQ$5+SUMIF($ET$7:$ET$110,$DK8,FB$7:FB$110)*$EA8*$FE$5+SUMIF($FH$7:$FH$110,$DK8,FP$7:FP$110)*$EB8*$FS$5+SUMIF($FV$7:$FV$110,$DK8,GD$7:GD$110)*$EC8*$GG$5+SUMIF($GJ$7:$GJ$110,$DK8,GR$7:GR$110)*$ED8*$GU$5 -> 121.9954 | DS8: =SUMIF($EF$7:$EF$110,$DK8,EO$7:EO$110)*$DZ8*$EQ$5+SUMIF($ET$7:$ET$110,$DK8,FC$7:FC$110)*$EA8*$FE$5+SUMIF($FH$7:$FH$110,$DK8,FQ$7:FQ$110)*$EB8*$FS$5+SUMIF($FV$7:$FV$110,$DK8,GE$7:GE$110)*$EC8*$GG$5+SUMIF($GJ$7:$GJ$110,$DK8,GS$7:GS$110)*$ED8*$GU$5 -> 154.0789 | ... DW8: =SUMIF($EF$7:$EF$110,$DK8,ES$7:ES$110)*$DZ8*$EQ$5+SUMIF($ET$7:$ET$110,$DK8,FG$7:FG$110)*$EA8*$FE$5+SUMIF($FH$7:$FH$110,$DK8,FU$7:FU$110)*$EB8*$FS$5+SUMIF($FV$7:$FV$110,$DK8,GI$7:GI$110)*$EC8*$GG$5+SUMIF($GJ$7:$GJ$110,$DK8,GW$7:GW$110)*$ED8*$GU$5 -> 504.8643 | DY8: amaiz | EB8: 1 | EF8: amaiz | EG8: amaiz | ET8: amaiz | EU8: amaiz | FH8: amaiz | FI8: amaiz | FJ8: 23848.1 | FK8: 18047.67 | FL8: 2034.078 | FM8: 572.4752 | FN8: 665.4911 | FO8: 992.3242 | FP8: 121.9954 | FQ8: 154.0789 | FR8: 624.4499 | FS8: 638.2947 | FT8: 354.1563 | FU8: 504.8643 | FV8: amaiz | FW8: amaiz | GJ8: amaiz | GK8: amaiz
C9: awhea | D9: =IF(SUM($S9:$AD9),S9/SUM($S9:$AD9),0) -> 0.52564511 | E9: =IF(SUM($S9:$AD9),T9/SUM($S9:$AD9),0) -> 0.38593819 | F9: =IF(SUM($S9:$AD9),U9/SUM($S9:$AD9),0) -> 0.042129104 | G9: =IF(SUM($S9:$AD9),V9/SUM($S9:$AD9),0) -> 0.011260643 | H9: =IF(SUM($S9:$AD9),W9/SUM($S9:$AD9),0) -> 0.006800444 | I9: =IF(SUM($S9:$AD9),X9/SUM($S9:$AD9),0) -> 0.012171461 | J9: =IF(SUM($S9:$AD9),Y9/SUM($S9:$AD9),0) -> 0.0030039345 | K9: =IF(SUM($S9:$AD9),Z9/SUM($S9:$AD9),0) -> 0.0036300068 | ... O9: =IF(SUM($S9:$AD9),AD9/SUM($S9:$AD9),0) -> 0.0014426538 | P9: =SUM(D9:O9) -> 1 | R9: awhea | S9: =IF(SUM($AR9:$AU9),$AK9*AR9/SUM($AR9:$AU9),0) -> 0.52564511 | T9: =IF(SUM($AR9:$AU9),$AK9*AS9/SUM($AR9:$AU9),0) -> 0.38593819 | U9: =IF(SUM($AR9:$AU9),$AK9*AT9/SUM($AR9:$AU9),0) -> 0.042129104 | V9: =IF(SUM($AR9:$AU9),$AK9*AU9/SUM($AR9:$AU9),0) -> 0.011260643 | W9: =IF(SUM($AV9:$AY9),$AL9*AV9/SUM($AV9:$AY9),0) -> 0.006800444 | X9: =IF(SUM($AV9:$AY9),$AL9*AW9/SUM($AV9:$AY9),0) -> 0.012171461 | Y9: =IF(SUM($AV9:$AY9),$AL9*AX9/SUM($AV9:$AY9),0) -> 0.0030039345 | Z9: =IF(SUM($AV9:$AY9),$AL9*AY9/SUM($AV9:$AY9),0) -> 0.0036300068 | AA9: =IF(SUM($AZ9:$BC9),(1-$AL9-$AK9)*AZ9/SUM($AZ9:$BC9),0) -> 0.0033288205 | AB9: =IF(SUM($AZ9:$BC9),(1-$AL9-$AK9)*BA9/SUM($AZ9:$BC9),0) -> 0.0036528056 | AC9: =IF(SUM($AZ9:$BC9),(1-$AL9-$AK9)*BB9/SUM($AZ9:$BC9),0) -> 0.00099682685 | AD9: =IF(SUM($AZ9:$BC9),(1-$AL9-$AK9)*BC9/SUM($AZ9:$BC9),0) -> 0.0014426538 | AE9: =S9+W9+AA9 -> 0.53577437 | AF9: =T9+X9+AB9 -> 0.40176246 | AG9: =U9+Y9+AC9 -> 0.046129865 | AH9: =V9+Z9+AD9 -> 0.016333304 | AI9: =IF(SUM($DL9:$DW9),SUM(DL9:DO9)/SUM($DL9:$DW9),0) -> 0.96497305 | AJ9: =IF(SUM($DL9:$DW9),SUM(DP9:DS9)/SUM($DL9:$DW9),0) -> 0.025605847 | AK9: =AI9 -> 0.96497305 | AL9: =AJ9 -> 0.025605847 | AM9: =1-SUM(AK9:AL9) -> 0.0094211068 | AN9: 1 | AO9: 1 | AQ9: awhea | AR9: =IF(SUM($BT9:$CE9),BT9/SUM($BT9:$CE9),0) -> 0.49922991 | AS9: =IF(SUM($BT9:$CE9),BU9/SUM($BT9:$CE9),0) -> 0.36654367 | AT9: =IF(SUM($BT9:$CE9),BV9/SUM($BT9:$CE9),0) -> 0.040011994 | AU9: =IF(SUM($BT9:$CE9),BW9/SUM($BT9:$CE9),0) -> 0.010694763 | AV9: =IF(SUM($BT9:$CE9),BX9/SUM($BT9:$CE9),0) -> 0.011165037 | AW9: =IF(SUM($BT9:$CE9),BY9/SUM($BT9:$CE9),0) -> 0.019983226 | AX9: =IF(SUM($BT9:$CE9),BZ9/SUM($BT9:$CE9),0) -> 0.0049318896 | AY9: =IF(SUM($BT9:$CE9),CA9/SUM($BT9:$CE9),0) -> 0.0059597812 | ... BC9: =IF(SUM($BT9:$CE9),CE9/SUM($BT9:$CE9),0) -> 0.0063517897 | BE9: awhea | BF9: 1 | BG9: 1 | BH9: 1 | BI9: 1 | BJ9: 1 | BK9: 1 | BL9: 1 | BM9: 1 | BN9: 1 | BO9: 1 | BP9: 1 | BQ9: 1 | BS9: awhea | BT9: =BF9*CI9 -> 42948.13 | BU9: =BG9*CJ9 -> 31533.298 | BV9: =BH9*CK9 -> 3442.1822 | BW9: =BI9*CL9 -> 920.0572 | BX9: =BJ9*CM9 -> 960.51426 | BY9: =BK9*CN9 -> 1719.1322 | BZ9: =BL9*CO9 -> 424.28435 | CA9: =BM9*CP9 -> 512.71259 | ... CE9: =BQ9*CT9 -> 546.43659 | CG9: =DJ9 -> asorg | CH9: awhea | CI9: =SUMIF($CV$7:$CV$110,$CG9,CW$7:CW$110) -> 42948.13 | CJ9: =SUMIF($CV$7:$CV$110,$CG9,CX$7:CX$110) -> 31533.298 | CK9: =SUMIF($CV$7:$CV$110,$CG9,CY$7:CY$110) -> 3442.1822 | CL9: =SUMIF($CV$7:$CV$110,$CG9,CZ$7:CZ$110) -> 920.0572 | CM9: =SUMIF($CV$7:$CV$110,$CG9,DA$7:DA$110) -> 960.51426 | CN9: =SUMIF($CV$7:$CV$110,$CG9,DB$7:DB$110) -> 1719.1322 | CO9: =SUMIF($CV$7:$CV$110,$CG9,DC$7:DC$110) -> 424.28435 | CP9: =SUMIF($CV$7:$CV$110,$CG9,DD$7:DD$110) -> 512.71259 | ... CT9: =SUMIF($CV$7:$CV$110,$CG9,DH$7:DH$110) -> 546.43659 | CV9: awhea | CW9: =SUMIF($DJ$7:$DJ$110,$CV9,DL$7:DL$110) -> 0 | CX9: =SUMIF($DJ$7:$DJ$110,$CV9,DM$7:DM$110) -> 0 | CY9: =SUMIF($DJ$7:$DJ$110,$CV9,DN$7:DN$110) -> 0 | CZ9: =SUMIF($DJ$7:$DJ$110,$CV9,DO$7:DO$110) -> 0 | DA9: =SUMIF($DJ$7:$DJ$110,$CV9,DP$7:DP$110) -> 0 | DB9: =SUMIF($DJ$7:$DJ$110,$CV9,DQ$7:DQ$110) -> 0 | DC9: =SUMIF($DJ$7:$DJ$110,$CV9,DR$7:DR$110) -> 0 | DD9: =SUMIF($DJ$7:$DJ$110,$CV9,DS$7:DS$110) -> 0 | ... DH9: =SUMIF($DJ$7:$DJ$110,$CV9,DW$7:DW$110) -> 0 | DJ9: asorg | DK9: awhea | DL9: =SUMIF($EF$7:$EF$110,$DK9,EH$7:EH$110)*$DZ9*$EQ$5+SUMIF($ET$7:$ET$110,$DK9,EV$7:EV$110)*$EA9*$FE$5+SUMIF($FH$7:$FH$110,$DK9,FJ$7:FJ$110)*$EB9*$FS$5+SUMIF($FV$7:$FV$110,$DK9,FX$7:FX$110)*$EC9*$GG$5+SUMIF($GJ$7:$GJ$110,$DK9,GL$7:GL$110)*$ED9*$GU$5 -> 786.2206 | DM9: =SUMIF($EF$7:$EF$110,$DK9,EI$7:EI$110)*$DZ9*$EQ$5+SUMIF($ET$7:$ET$110,$DK9,EW$7:EW$110)*$EA9*$FE$5+SUMIF($FH$7:$FH$110,$DK9,FK$7:FK$110)*$EB9*$FS$5+SUMIF($FV$7:$FV$110,$DK9,FY$7:FY$110)*$EC9*$GG$5+SUMIF($GJ$7:$GJ$110,$DK9,GM$7:GM$110)*$ED9*$GU$5 -> 845.6878 | DN9: =SUMIF($EF$7:$EF$110,$DK9,EJ$7:EJ$110)*$DZ9*$EQ$5+SUMIF($ET$7:$ET$110,$DK9,EX$7:EX$110)*$EA9*$FE$5+SUMIF($FH$7:$FH$110,$DK9,FL$7:FL$110)*$EB9*$FS$5+SUMIF($FV$7:$FV$110,$DK9,FZ$7:FZ$110)*$EC9*$GG$5+SUMIF($GJ$7:$GJ$110,$DK9,GN$7:GN$110)*$ED9*$GU$5 -> 54.15379 | DO9: =SUMIF($EF$7:$EF$110,$DK9,EK$7:EK$110)*$DZ9*$EQ$5+SUMIF($ET$7:$ET$110,$DK9,EY$7:EY$110)*$EA9*$FE$5+SUMIF($FH$7:$FH$110,$DK9,FM$7:FM$110)*$EB9*$FS$5+SUMIF($FV$7:$FV$110,$DK9,GA$7:GA$110)*$EC9*$GG$5+SUMIF($GJ$7:$GJ$110,$DK9,GO$7:GO$110)*$ED9*$GU$5 -> 23.42109 | DP9: =SUMIF($EF$7:$EF$110,$DK9,EL$7:EL$110)*$DZ9*$EQ$5+SUMIF($ET$7:$ET$110,$DK9,EZ$7:EZ$110)*$EA9*$FE$5+SUMIF($FH$7:$FH$110,$DK9,FN$7:FN$110)*$EB9*$FS$5+SUMIF($FV$7:$FV$110,$DK9,GB$7:GB$110)*$EC9*$GG$5+SUMIF($GJ$7:$GJ$110,$DK9,GP$7:GP$110)*$ED9*$GU$5 -> 4.849576 | DQ9: =SUMIF($EF$7:$EF$110,$DK9,EM$7:EM$110)*$DZ9*$EQ$5+SUMIF($ET$7:$ET$110,$DK9,FA$7:FA$110)*$EA9*$FE$5+SUMIF($FH$7:$FH$110,$DK9,FO$7:FO$110)*$EB9*$FS$5+SUMIF($FV$7:$FV$110,$DK9,GC$7:GC$110)*$EC9*$GG$5+SUMIF($GJ$7:$GJ$110,$DK9,GQ$7:GQ$110)*$ED9*$GU$5 -> 3.312711 | DR9: =SUMIF($EF$7:$EF$110,$DK9,EN$7:EN$110)*$DZ9*$EQ$5+SUMIF($ET$7:$ET$110,$DK9,FB$7:FB$110)*$EA9*$FE$5+SUMIF($FH$7:$FH$110,$DK9,FP$7:FP$110)*$EB9*$FS$5+SUMIF($FV$7:$FV$110,$DK9,GD$7:GD$110)*$EC9*$GG$5+SUMIF($GJ$7:$GJ$110,$DK9,GR$7:GR$110)*$ED9*$GU$5 -> 13.88127 | DS9: =SUMIF($EF$7:$EF$110,$DK9,EO$7:EO$110)*$DZ9*$EQ$5+SUMIF($ET$7:$ET$110,$DK9,FC$7:FC$110)*$EA9*$FE$5+SUMIF($FH$7:$FH$110,$DK9,FQ$7:FQ$110)*$EB9*$FS$5+SUMIF($FV$7:$FV$110,$DK9,GE$7:GE$110)*$EC9*$GG$5+SUMIF($GJ$7:$GJ$110,$DK9,GS$7:GS$110)*$ED9*$GU$5 -> 23.31809 | ... DW9: =SUMIF($EF$7:$EF$110,$DK9,ES$7:ES$110)*$DZ9*$EQ$5+SUMIF($ET$7:$ET$110,$DK9,FG$7:FG$110)*$EA9*$FE$5+SUMIF($FH$7:$FH$110,$DK9,FU$7:FU$110)*$EB9*$FS$5+SUMIF($FV$7:$FV$110,$DK9,GI$7:GI$110)*$EC9*$GG$5+SUMIF($GJ$7:$GJ$110,$DK9,GW$7:GW$110)*$ED9*$GU$5 -> 14.29188 | DY9: awhea | EB9: 1 | EF9: awhea | EG9: awhea | ET9: awhea | EU9: awhea | FH9: awhea | FI9: awhea | FJ9: 786.2206 | FK9: 845.6878 | FL9: 54.15379 | FM9: 23.42109 | FN9: 4.849576 | FO9: 3.312711 | FP9: 13.88127 | FQ9: 23.31809 | FR9: 2.397938 | FU9: 14.29188 | FV9: awhea | FW9: awhea | GJ9: awhea | GK9: awhea
C10: arice | D10: =IF(SUM($S10:$AD10),S10/SUM($S10:$AD10),0) -> 0.50532883 | E10: =IF(SUM($S10:$AD10),T10/SUM($S10:$AD10),0) -> 0.37102161 | F10: =IF(SUM($S10:$AD10),U10/SUM($S10:$AD10),0) -> 0.040500806 | G10: =IF(SUM($S10:$AD10),V10/SUM($S10:$AD10),0) -> 0.010825417 | H10: =IF(SUM($S10:$AD10),W10/SUM($S10:$AD10),0) -> 0.015833767 | I10: =IF(SUM($S10:$AD10),X10/SUM($S10:$AD10),0) -> 0.028339338 | J10: =IF(SUM($S10:$AD10),Y10/SUM($S10:$AD10),0) -> 0.0069941903 | K10: =IF(SUM($S10:$AD10),Z10/SUM($S10:$AD10),0) -> 0.0084519012 | ... O10: =IF(SUM($S10:$AD10),AD10/SUM($S10:$AD10),0) -> 0.0019453855 | P10: =SUM(D10:O10) -> 1 | R10: arice | S10: =IF(SUM($AR10:$AU10),$AK10*AR10/SUM($AR10:$AU10),0) -> 0.50532883 | T10: =IF(SUM($AR10:$AU10),$AK10*AS10/SUM($AR10:$AU10),0) -> 0.37102161 | U10: =IF(SUM($AR10:$AU10),$AK10*AT10/SUM($AR10:$AU10),0) -> 0.040500806 | V10: =IF(SUM($AR10:$AU10),$AK10*AU10/SUM($AR10:$AU10),0) -> 0.010825417 | W10: =IF(SUM($AV10:$AY10),$AL10*AV10/SUM($AV10:$AY10),0) -> 0.015833767 | X10: =IF(SUM($AV10:$AY10),$AL10*AW10/SUM($AV10:$AY10),0) -> 0.028339338 | Y10: =IF(SUM($AV10:$AY10),$AL10*AX10/SUM($AV10:$AY10),0) -> 0.0069941903 | Z10: =IF(SUM($AV10:$AY10),$AL10*AY10/SUM($AV10:$AY10),0) -> 0.0084519012 | AA10: =IF(SUM($AZ10:$BC10),(1-$AL10-$AK10)*AZ10/SUM($AZ10:$BC10),0) -> 0.0044888378 | AB10: =IF(SUM($AZ10:$BC10),(1-$AL10-$AK10)*BA10/SUM($AZ10:$BC10),0) -> 0.0049257242 | AC10: =IF(SUM($AZ10:$BC10),(1-$AL10-$AK10)*BB10/SUM($AZ10:$BC10),0) -> 0.001344198 | AD10: =IF(SUM($AZ10:$BC10),(1-$AL10-$AK10)*BC10/SUM($AZ10:$BC10),0) -> 0.0019453855 | AE10: =S10+W10+AA10 -> 0.52565143 | AF10: =T10+X10+AB10 -> 0.40428667 | AG10: =U10+Y10+AC10 -> 0.048839195 | AH10: =V10+Z10+AD10 -> 0.021222704 | AI10: =IF(SUM($DL10:$DW10),SUM(DL10:DO10)/SUM($DL10:$DW10),0) -> 0.92767666 | AJ10: =IF(SUM($DL10:$DW10),SUM(DP10:DS10)/SUM($DL10:$DW10),0) -> 0.059619196 | AK10: =AI10 -> 0.92767666 | AL10: =AJ10 -> 0.059619196 | AM10: =1-SUM(AK10:AL10) -> 0.012704146 | AN10: 1 | AO10: 1 | AQ10: arice | AR10: =IF(SUM($BT10:$CE10),BT10/SUM($BT10:$CE10),0) -> 0.49922991 | AS10: =IF(SUM($BT10:$CE10),BU10/SUM($BT10:$CE10),0) -> 0.36654367 | AT10: =IF(SUM($BT10:$CE10),BV10/SUM($BT10:$CE10),0) -> 0.040011994 | AU10: =IF(SUM($BT10:$CE10),BW10/SUM($BT10:$CE10),0) -> 0.010694763 | AV10: =IF(SUM($BT10:$CE10),BX10/SUM($BT10:$CE10),0) -> 0.011165037 | AW10: =IF(SUM($BT10:$CE10),BY10/SUM($BT10:$CE10),0) -> 0.019983226 | AX10: =IF(SUM($BT10:$CE10),BZ10/SUM($BT10:$CE10),0) -> 0.0049318896 | AY10: =IF(SUM($BT10:$CE10),CA10/SUM($BT10:$CE10),0) -> 0.0059597812 | ... BC10: =IF(SUM($BT10:$CE10),CE10/SUM($BT10:$CE10),0) -> 0.0063517897 | BE10: arice | BF10: 1 | BG10: 1 | BH10: 1 | BI10: 1 | BJ10: 1 | BK10: 1 | BL10: 1 | BM10: 1 | BN10: 1 | BO10: 1 | BP10: 1 | BQ10: 1 | BS10: arice | BT10: =BF10*CI10 -> 42948.13 | BU10: =BG10*CJ10 -> 31533.298 | BV10: =BH10*CK10 -> 3442.1822 | BW10: =BI10*CL10 -> 920.0572 | BX10: =BJ10*CM10 -> 960.51426 | BY10: =BK10*CN10 -> 1719.1322 | BZ10: =BL10*CO10 -> 424.28435 | CA10: =BM10*CP10 -> 512.71259 | ... CE10: =BQ10*CT10 -> 546.43659 | CG10: =DJ10 -> asorg | CH10: arice | CI10: =SUMIF($CV$7:$CV$110,$CG10,CW$7:CW$110) -> 42948.13 | CJ10: =SUMIF($CV$7:$CV$110,$CG10,CX$7:CX$110) -> 31533.298 | CK10: =SUMIF($CV$7:$CV$110,$CG10,CY$7:CY$110) -> 3442.1822 | CL10: =SUMIF($CV$7:$CV$110,$CG10,CZ$7:CZ$110) -> 920.0572 | CM10: =SUMIF($CV$7:$CV$110,$CG10,DA$7:DA$110) -> 960.51426 | CN10: =SUMIF($CV$7:$CV$110,$CG10,DB$7:DB$110) -> 1719.1322 | CO10: =SUMIF($CV$7:$CV$110,$CG10,DC$7:DC$110) -> 424.28435 | CP10: =SUMIF($CV$7:$CV$110,$CG10,DD$7:DD$110) -> 512.71259 | ... CT10: =SUMIF($CV$7:$CV$110,$CG10,DH$7:DH$110) -> 546.43659 | CV10: arice | CW10: =SUMIF($DJ$7:$DJ$110,$CV10,DL$7:DL$110) -> 0 | CX10: =SUMIF($DJ$7:$DJ$110,$CV10,DM$7:DM$110) -> 0 | CY10: =SUMIF($DJ$7:$DJ$110,$CV10,DN$7:DN$110) -> 0 | CZ10: =SUMIF($DJ$7:$DJ$110,$CV10,DO$7:DO$110) -> 0 | DA10: =SUMIF($DJ$7:$DJ$110,$CV10,DP$7:DP$110) -> 0 | DB10: =SUMIF($DJ$7:$DJ$110,$CV10,DQ$7:DQ$110) -> 0 | DC10: =SUMIF($DJ$7:$DJ$110,$CV10,DR$7:DR$110) -> 0 | DD10: =SUMIF($DJ$7:$DJ$110,$CV10,DS$7:DS$110) -> 0 | ... DH10: =SUMIF($DJ$7:$DJ$110,$CV10,DW$7:DW$110) -> 0 | DJ10: asorg | DK10: arice | DL10: =SUMIF($EF$7:$EF$110,$DK10,EH$7:EH$110)*$DZ10*$EQ$5+SUMIF($ET$7:$ET$110,$DK10,EV$7:EV$110)*$EA10*$FE$5+SUMIF($FH$7:$FH$110,$DK10,FJ$7:FJ$110)*$EB10*$FS$5+SUMIF($FV$7:$FV$110,$DK10,FX$7:FX$110)*$EC10*$GG$5+SUMIF($GJ$7:$GJ$110,$DK10,GL$7:GL$110)*$ED10*$GU$5 -> 7153.132 | DM10: =SUMIF($EF$7:$EF$110,$DK10,EI$7:EI$110)*$DZ10*$EQ$5+SUMIF($ET$7:$ET$110,$DK10,EW$7:EW$110)*$EA10*$FE$5+SUMIF($FH$7:$FH$110,$DK10,FK$7:FK$110)*$EB10*$FS$5+SUMIF($FV$7:$FV$110,$DK10,FY$7:FY$110)*$EC10*$GG$5+SUMIF($GJ$7:$GJ$110,$DK10,GM$7:GM$110)*$ED10*$GU$5 -> 4388.14 | DN10: =SUMIF($EF$7:$EF$110,$DK10,EJ$7:EJ$110)*$DZ10*$EQ$5+SUMIF($ET$7:$ET$110,$DK10,EX$7:EX$110)*$EA10*$FE$5+SUMIF($FH$7:$FH$110,$DK10,FL$7:FL$110)*$EB10*$FS$5+SUMIF($FV$7:$FV$110,$DK10,FZ$7:FZ$110)*$EC10*$GG$5+SUMIF($GJ$7:$GJ$110,$DK10,GN$7:GN$110)*$ED10*$GU$5 -> 644.3606 | DO10: =SUMIF($EF$7:$EF$110,$DK10,EK$7:EK$110)*$DZ10*$EQ$5+SUMIF($ET$7:$ET$110,$DK10,EY$7:EY$110)*$EA10*$FE$5+SUMIF($FH$7:$FH$110,$DK10,FM$7:FM$110)*$EB10*$FS$5+SUMIF($FV$7:$FV$110,$DK10,GA$7:GA$110)*$EC10*$GG$5+SUMIF($GJ$7:$GJ$110,$DK10,GO$7:GO$110)*$ED10*$GU$5 -> 22.01859 | DP10: =SUMIF($EF$7:$EF$110,$DK10,EL$7:EL$110)*$DZ10*$EQ$5+SUMIF($ET$7:$ET$110,$DK10,EZ$7:EZ$110)*$EA10*$FE$5+SUMIF($FH$7:$FH$110,$DK10,FN$7:FN$110)*$EB10*$FS$5+SUMIF($FV$7:$FV$110,$DK10,GB$7:GB$110)*$EC10*$GG$5+SUMIF($GJ$7:$GJ$110,$DK10,GP$7:GP$110)*$ED10*$GU$5 -> 19.99696 | DQ10: =SUMIF($EF$7:$EF$110,$DK10,EM$7:EM$110)*$DZ10*$EQ$5+SUMIF($ET$7:$ET$110,$DK10,FA$7:FA$110)*$EA10*$FE$5+SUMIF($FH$7:$FH$110,$DK10,FO$7:FO$110)*$EB10*$FS$5+SUMIF($FV$7:$FV$110,$DK10,GC$7:GC$110)*$EC10*$GG$5+SUMIF($GJ$7:$GJ$110,$DK10,GQ$7:GQ$110)*$ED10*$GU$5 -> 339.2335 | DR10: =SUMIF($EF$7:$EF$110,$DK10,EN$7:EN$110)*$DZ10*$EQ$5+SUMIF($ET$7:$ET$110,$DK10,FB$7:FB$110)*$EA10*$FE$5+SUMIF($FH$7:$FH$110,$DK10,FP$7:FP$110)*$EB10*$FS$5+SUMIF($FV$7:$FV$110,$DK10,GD$7:GD$110)*$EC10*$GG$5+SUMIF($GJ$7:$GJ$110,$DK10,GR$7:GR$110)*$ED10*$GU$5 -> 217.6559 | DS10: =SUMIF($EF$7:$EF$110,$DK10,EO$7:EO$110)*$DZ10*$EQ$5+SUMIF($ET$7:$ET$110,$DK10,FC$7:FC$110)*$EA10*$FE$5+SUMIF($FH$7:$FH$110,$DK10,FQ$7:FQ$110)*$EB10*$FS$5+SUMIF($FV$7:$FV$110,$DK10,GE$7:GE$110)*$EC10*$GG$5+SUMIF($GJ$7:$GJ$110,$DK10,GS$7:GS$110)*$ED10*$GU$5 -> 207.6654 | ... DW10: =SUMIF($EF$7:$EF$110,$DK10,ES$7:ES$110)*$DZ10*$EQ$5+SUMIF($ET$7:$ET$110,$DK10,FG$7:FG$110)*$EA10*$FE$5+SUMIF($FH$7:$FH$110,$DK10,FU$7:FU$110)*$EB10*$FS$5+SUMIF($FV$7:$FV$110,$DK10,GI$7:GI$110)*$EC10*$GG$5+SUMIF($GJ$7:$GJ$110,$DK10,GW$7:GW$110)*$ED10*$GU$5 -> 0 | DY10: arice | EB10: 1 | EF10: arice | EG10: arice | ET10: arice | EU10: arice | FH10: arice | FI10: arice | FJ10: 7153.132 | FK10: 4388.14 | FL10: 644.3606 | FM10: 22.01859 | FN10: 19.99696 | FO10: 339.2335 | FP10: 217.6559 | FQ10: 207.6654 | FR10: 25.0869 | FS10: 142.0918 | FV10: arice | FW10: arice | GJ10: arice | GK10: arice
C11: aocer | D11: =IF(SUM($S11:$AD11),S11/SUM($S11:$AD11),0) -> 0.53530655 | E11: =IF(SUM($S11:$AD11),T11/SUM($S11:$AD11),0) -> 0.39303179 | F11: =IF(SUM($S11:$AD11),U11/SUM($S11:$AD11),0) -> 0.042903443 | G11: =IF(SUM($S11:$AD11),V11/SUM($S11:$AD11),0) -> 0.011467615 | H11: =IF(SUM($S11:$AD11),W11/SUM($S11:$AD11),0) -> 0.0026795475 | I11: =IF(SUM($S11:$AD11),X11/SUM($S11:$AD11),0) -> 0.0047958646 | J11: =IF(SUM($S11:$AD11),Y11/SUM($S11:$AD11),0) -> 0.0011836264 | K11: =IF(SUM($S11:$AD11),Z11/SUM($S11:$AD11),0) -> 0.0014303148 | ... O11: =IF(SUM($S11:$AD11),AD11/SUM($S11:$AD11),0) -> 0.001102727 | P11: =SUM(D11:O11) -> 1 | R11: aocer | S11: =IF(SUM($AR11:$AU11),$AK11*AR11/SUM($AR11:$AU11),0) -> 0.53530655 | T11: =IF(SUM($AR11:$AU11),$AK11*AS11/SUM($AR11:$AU11),0) -> 0.39303179 | U11: =IF(SUM($AR11:$AU11),$AK11*AT11/SUM($AR11:$AU11),0) -> 0.042903443 | V11: =IF(SUM($AR11:$AU11),$AK11*AU11/SUM($AR11:$AU11),0) -> 0.011467615 | W11: =IF(SUM($AV11:$AY11),$AL11*AV11/SUM($AV11:$AY11),0) -> 0.0026795475 | X11: =IF(SUM($AV11:$AY11),$AL11*AW11/SUM($AV11:$AY11),0) -> 0.0047958646 | Y11: =IF(SUM($AV11:$AY11),$AL11*AX11/SUM($AV11:$AY11),0) -> 0.0011836264 | Z11: =IF(SUM($AV11:$AY11),$AL11*AY11/SUM($AV11:$AY11),0) -> 0.0014303148 | AA11: =IF(SUM($AZ11:$BC11),(1-$AL11-$AK11)*AZ11/SUM($AZ11:$BC11),0) -> 0.0025444636 | AB11: =IF(SUM($AZ11:$BC11),(1-$AL11-$AK11)*BA11/SUM($AZ11:$BC11),0) -> 0.0027921093 | AC11: =IF(SUM($AZ11:$BC11),(1-$AL11-$AK11)*BB11/SUM($AZ11:$BC11),0) -> 0.00076194845 | AD11: =IF(SUM($AZ11:$BC11),(1-$AL11-$AK11)*BC11/SUM($AZ11:$BC11),0) -> 0.001102727 | AE11: =S11+W11+AA11 -> 0.54053056 | AF11: =T11+X11+AB11 -> 0.40061977 | AG11: =U11+Y11+AC11 -> 0.044849018 | AH11: =V11+Z11+AD11 -> 0.014000657 | AI11: =IF(SUM($DL11:$DW11),SUM(DL11:DO11)/SUM($DL11:$DW11),0) -> 0.9827094 | AJ11: =IF(SUM($DL11:$DW11),SUM(DP11:DS11)/SUM($DL11:$DW11),0) -> 0.010089353 | AK11: =AI11 -> 0.9827094 | AL11: =AJ11 -> 0.010089353 | AM11: =1-SUM(AK11:AL11) -> 0.0072012483 | AN11: 1 | AO11: 1 | AQ11: aocer | AR11: =IF(SUM($BT11:$CE11),BT11/SUM($BT11:$CE11),0) -> 0.49922991 | AS11: =IF(SUM($BT11:$CE11),BU11/SUM($BT11:$CE11),0) -> 0.36654367 | AT11: =IF(SUM($BT11:$CE11),BV11/SUM($BT11:$CE11),0) -> 0.040011994 | AU11: =IF(SUM($BT11:$CE11),BW11/SUM($BT11:$CE11),0) -> 0.010694763 | AV11: =IF(SUM($BT11:$CE11),BX11/SUM($BT11:$CE11),0) -> 0.011165037 | AW11: =IF(SUM($BT11:$CE11),BY11/SUM($BT11:$CE11),0) -> 0.019983226 | AX11: =IF(SUM($BT11:$CE11),BZ11/SUM($BT11:$CE11),0) -> 0.0049318896 | AY11: =IF(SUM($BT11:$CE11),CA11/SUM($BT11:$CE11),0) -> 0.0059597812 | ... BC11: =IF(SUM($BT11:$CE11),CE11/SUM($BT11:$CE11),0) -> 0.0063517897 | BE11: aocer | BF11: 1 | BG11: 1 | BH11: 1 | BI11: 1 | BJ11: 1 | BK11: 1 | BL11: 1 | BM11: 1 | BN11: 1 | BO11: 1 | BP11: 1 | BQ11: 1 | BS11: aocer | BT11: =BF11*CI11 -> 42948.13 | BU11: =BG11*CJ11 -> 31533.298 | BV11: =BH11*CK11 -> 3442.1822 | BW11: =BI11*CL11 -> 920.0572 | BX11: =BJ11*CM11 -> 960.51426 | BY11: =BK11*CN11 -> 1719.1322 | BZ11: =BL11*CO11 -> 424.28435 | CA11: =BM11*CP11 -> 512.71259 | ... CE11: =BQ11*CT11 -> 546.43659 | CG11: =DJ11 -> asorg | CH11: aocer | CI11: =SUMIF($CV$7:$CV$110,$CG11,CW$7:CW$110) -> 42948.13 | CJ11: =SUMIF($CV$7:$CV$110,$CG11,CX$7:CX$110) -> 31533.298 | CK11: =SUMIF($CV$7:$CV$110,$CG11,CY$7:CY$110) -> 3442.1822 | CL11: =SUMIF($CV$7:$CV$110,$CG11,CZ$7:CZ$110) -> 920.0572 | CM11: =SUMIF($CV$7:$CV$110,$CG11,DA$7:DA$110) -> 960.51426 | CN11: =SUMIF($CV$7:$CV$110,$CG11,DB$7:DB$110) -> 1719.1322 | CO11: =SUMIF($CV$7:$CV$110,$CG11,DC$7:DC$110) -> 424.28435 | CP11: =SUMIF($CV$7:$CV$110,$CG11,DD$7:DD$110) -> 512.71259 | ... CT11: =SUMIF($CV$7:$CV$110,$CG11,DH$7:DH$110) -> 546.43659 | CV11: aocer | CW11: =SUMIF($DJ$7:$DJ$110,$CV11,DL$7:DL$110) -> 0 | CX11: =SUMIF($DJ$7:$DJ$110,$CV11,DM$7:DM$110) -> 0 | CY11: =SUMIF($DJ$7:$DJ$110,$CV11,DN$7:DN$110) -> 0 | CZ11: =SUMIF($DJ$7:$DJ$110,$CV11,DO$7:DO$110) -> 0 | DA11: =SUMIF($DJ$7:$DJ$110,$CV11,DP$7:DP$110) -> 0 | DB11: =SUMIF($DJ$7:$DJ$110,$CV11,DQ$7:DQ$110) -> 0 | DC11: =SUMIF($DJ$7:$DJ$110,$CV11,DR$7:DR$110) -> 0 | DD11: =SUMIF($DJ$7:$DJ$110,$CV11,DS$7:DS$110) -> 0 | ... DH11: =SUMIF($DJ$7:$DJ$110,$CV11,DW$7:DW$110) -> 0 | DJ11: asorg | DK11: aocer | DL11: =SUMIF($EF$7:$EF$110,$DK11,EH$7:EH$110)*$DZ11*$EQ$5+SUMIF($ET$7:$ET$110,$DK11,EV$7:EV$110)*$EA11*$FE$5+SUMIF($FH$7:$FH$110,$DK11,FJ$7:FJ$110)*$EB11*$FS$5+SUMIF($FV$7:$FV$110,$DK11,FX$7:FX$110)*$EC11*$GG$5+SUMIF($GJ$7:$GJ$110,$DK11,GL$7:GL$110)*$ED11*$GU$5 -> 235.3175 | DM11: =SUMIF($EF$7:$EF$110,$DK11,EI$7:EI$110)*$DZ11*$EQ$5+SUMIF($ET$7:$ET$110,$DK11,EW$7:EW$110)*$EA11*$FE$5+SUMIF($FH$7:$FH$110,$DK11,FK$7:FK$110)*$EB11*$FS$5+SUMIF($FV$7:$FV$110,$DK11,FY$7:FY$110)*$EC11*$GG$5+SUMIF($GJ$7:$GJ$110,$DK11,GM$7:GM$110)*$ED11*$GU$5 -> 211.1839 | DN11: =SUMIF($EF$7:$EF$110,$DK11,EJ$7:EJ$110)*$DZ11*$EQ$5+SUMIF($ET$7:$ET$110,$DK11,EX$7:EX$110)*$EA11*$FE$5+SUMIF($FH$7:$FH$110,$DK11,FL$7:FL$110)*$EB11*$FS$5+SUMIF($FV$7:$FV$110,$DK11,FZ$7:FZ$110)*$EC11*$GG$5+SUMIF($GJ$7:$GJ$110,$DK11,GN$7:GN$110)*$ED11*$GU$5 -> 40.13813 | DO11: =SUMIF($EF$7:$EF$110,$DK11,EK$7:EK$110)*$DZ11*$EQ$5+SUMIF($ET$7:$ET$110,$DK11,EY$7:EY$110)*$EA11*$FE$5+SUMIF($FH$7:$FH$110,$DK11,FM$7:FM$110)*$EB11*$FS$5+SUMIF($FV$7:$FV$110,$DK11,GA$7:GA$110)*$EC11*$GG$5+SUMIF($GJ$7:$GJ$110,$DK11,GO$7:GO$110)*$ED11*$GU$5 -> 30.94812 | DP11: =SUMIF($EF$7:$EF$110,$DK11,EL$7:EL$110)*$DZ11*$EQ$5+SUMIF($ET$7:$ET$110,$DK11,EZ$7:EZ$110)*$EA11*$FE$5+SUMIF($FH$7:$FH$110,$DK11,FN$7:FN$110)*$EB11*$FS$5+SUMIF($FV$7:$FV$110,$DK11,GB$7:GB$110)*$EC11*$GG$5+SUMIF($GJ$7:$GJ$110,$DK11,GP$7:GP$110)*$ED11*$GU$5 -> 3.937228 | DQ11: =SUMIF($EF$7:$EF$110,$DK11,EM$7:EM$110)*$DZ11*$EQ$5+SUMIF($ET$7:$ET$110,$DK11,FA$7:FA$110)*$EA11*$FE$5+SUMIF($FH$7:$FH$110,$DK11,FO$7:FO$110)*$EB11*$FS$5+SUMIF($FV$7:$FV$110,$DK11,GC$7:GC$110)*$EC11*$GG$5+SUMIF($GJ$7:$GJ$110,$DK11,GQ$7:GQ$110)*$ED11*$GU$5 -> 1.376779 | DR11: =SUMIF($EF$7:$EF$110,$DK11,EN$7:EN$110)*$DZ11*$EQ$5+SUMIF($ET$7:$ET$110,$DK11,FB$7:FB$110)*$EA11*$FE$5+SUMIF($FH$7:$FH$110,$DK11,FP$7:FP$110)*$EB11*$FS$5+SUMIF($FV$7:$FV$110,$DK11,GD$7:GD$110)*$EC11*$GG$5+SUMIF($GJ$7:$GJ$110,$DK11,GR$7:GR$110)*$ED11*$GU$5 -> 0 | DS11: =SUMIF($EF$7:$EF$110,$DK11,EO$7:EO$110)*$DZ11*$EQ$5+SUMIF($ET$7:$ET$110,$DK11,FC$7:FC$110)*$EA11*$FE$5+SUMIF($FH$7:$FH$110,$DK11,FQ$7:FQ$110)*$EB11*$FS$5+SUMIF($FV$7:$FV$110,$DK11,GE$7:GE$110)*$EC11*$GG$5+SUMIF($GJ$7:$GJ$110,$DK11,GS$7:GS$110)*$ED11*$GU$5 -> 0 | ... DW11: =SUMIF($EF$7:$EF$110,$DK11,ES$7:ES$110)*$DZ11*$EQ$5+SUMIF($ET$7:$ET$110,$DK11,FG$7:FG$110)*$EA11*$FE$5+SUMIF($FH$7:$FH$110,$DK11,FU$7:FU$110)*$EB11*$FS$5+SUMIF($FV$7:$FV$110,$DK11,GI$7:GI$110)*$EC11*$GG$5+SUMIF($GJ$7:$GJ$110,$DK11,GW$7:GW$110)*$ED11*$GU$5 -> 0 | DY11: aocer | EB11: 1 | EF11: aocer | EG11: aocer | ET11: aocer | EU11: aocer | FH11: aocer | FI11: aocer | FJ11: 235.3175 | FK11: 211.1839 | FL11: 40.13813 | FM11: 30.94812 | FN11: 3.937228 | FO11: 1.376779 | FR11: 2.300008 | FS11: 1.49285 | FV11: aocer | FW11: aocer | GJ11: aocer | GK11: aocer
C12: aipot | D12: =IF(SUM($S12:$AD12),S12/SUM($S12:$AD12),0) -> 0.46720129 | E12: =IF(SUM($S12:$AD12),T12/SUM($S12:$AD12),0) -> 0.37726805 | F12: =IF(SUM($S12:$AD12),U12/SUM($S12:$AD12),0) -> 0.026879792 | G12: =IF(SUM($S12:$AD12),V12/SUM($S12:$AD12),0) -> 0.011946 | H12: =IF(SUM($S12:$AD12),W12/SUM($S12:$AD12),0) -> 0.025108999 | I12: =IF(SUM($S12:$AD12),X12/SUM($S12:$AD12),0) -> 0.026689454 | J12: =IF(SUM($S12:$AD12),Y12/SUM($S12:$AD12),0) -> 0.037589338 | K12: =IF(SUM($S12:$AD12),Z12/SUM($S12:$AD12),0) -> 0.0074107533 | ... O12: =IF(SUM($S12:$AD12),AD12/SUM($S12:$AD12),0) -> 0.0035005913 | P12: =SUM(D12:O12) -> 1 | R12: aipot | S12: =IF(SUM($AR12:$AU12),$AK12*AR12/SUM($AR12:$AU12),0) -> 0.46720129 | T12: =IF(SUM($AR12:$AU12),$AK12*AS12/SUM($AR12:$AU12),0) -> 0.37726805 | U12: =IF(SUM($AR12:$AU12),$AK12*AT12/SUM($AR12:$AU12),0) -> 0.026879792 | V12: =IF(SUM($AR12:$AU12),$AK12*AU12/SUM($AR12:$AU12),0) -> 0.011946 | W12: =IF(SUM($AV12:$AY12),$AL12*AV12/SUM($AV12:$AY12),0) -> 0.025108999 | X12: =IF(SUM($AV12:$AY12),$AL12*AW12/SUM($AV12:$AY12),0) -> 0.026689454 | Y12: =IF(SUM($AV12:$AY12),$AL12*AX12/SUM($AV12:$AY12),0) -> 0.037589338 | Z12: =IF(SUM($AV12:$AY12),$AL12*AY12/SUM($AV12:$AY12),0) -> 0.0074107533 | AA12: =IF(SUM($AZ12:$BC12),(1-$AL12-$AK12)*AZ12/SUM($AZ12:$BC12),0) -> 0.0071856047 | AB12: =IF(SUM($AZ12:$BC12),(1-$AL12-$AK12)*BA12/SUM($AZ12:$BC12),0) -> 0.0080696645 | AC12: =IF(SUM($AZ12:$BC12),(1-$AL12-$AK12)*BB12/SUM($AZ12:$BC12),0) -> 0.0011504669 | AD12: =IF(SUM($AZ12:$BC12),(1-$AL12-$AK12)*BC12/SUM($AZ12:$BC12),0) -> 0.0035005913 | AE12: =S12+W12+AA12 -> 0.49949589 | AF12: =T12+X12+AB12 -> 0.41202717 | AG12: =U12+Y12+AC12 -> 0.065619596 | AH12: =V12+Z12+AD12 -> 0.022857345 | AI12: =IF(SUM($DL12:$DW12),SUM(DL12:DO12)/SUM($DL12:$DW12),0) -> 0.88329513 | AJ12: =IF(SUM($DL12:$DW12),SUM(DP12:DS12)/SUM($DL12:$DW12),0) -> 0.096798544 | AK12: =AI12 -> 0.88329513 | AL12: =AJ12 -> 0.096798544 | AM12: =1-SUM(AK12:AL12) -> 0.019906327 | AN12: 1 | AO12: 1 | AQ12: aipot | AR12: =IF(SUM($BT12:$CE12),BT12/SUM($BT12:$CE12),0) -> 0.49024134 | AS12: =IF(SUM($BT12:$CE12),BU12/SUM($BT12:$CE12),0) -> 0.39587304 | AT12: =IF(SUM($BT12:$CE12),BV12/SUM($BT12:$CE12),0) -> 0.02820537 | AU12: =IF(SUM($BT12:$CE12),BW12/SUM($BT12:$CE12),0) -> 0.012535118 | AV12: =IF(SUM($BT12:$CE12),BX12/SUM($BT12:$CE12),0) -> 0.01207462 | AW12: =IF(SUM($BT12:$CE12),BY12/SUM($BT12:$CE12),0) -> 0.012834642 | AX12: =IF(SUM($BT12:$CE12),BZ12/SUM($BT12:$CE12),0) -> 0.018076266 | AY12: =IF(SUM($BT12:$CE12),CA12/SUM($BT12:$CE12),0) -> 0.0035637433 | ... BC12: =IF(SUM($BT12:$CE12),CE12/SUM($BT12:$CE12),0) -> 0.0046769681 | BE12: aipot | BF12: 1 | BG12: 1 | BH12: 1 | BI12: 1 | BJ12: 1 | BK12: 1 | BL12: 1 | BM12: 1 | BN12: 1 | BO12: 1 | BP12: 1 | BQ12: 1 | BS12: aipot | BT12: =BF12*CI12 -> 75514.377 | BU12: =BG12*CJ12 -> 60978.346 | BV12: =BH12*CK12 -> 4344.6172 | BW12: =BI12*CL12 -> 1930.8482 | BX12: =BJ12*CM12 -> 1859.9154 | BY12: =BK12*CN12 -> 1976.9854 | BZ12: =BL12*CO12 -> 2784.3796 | CA12: =BM12*CP12 -> 548.94159 | ... CE12: =BQ12*CT12 -> 720.41728 | CG12: =DJ12 -> aipot | CH12: aipot | CI12: =SUMIF($CV$7:$CV$110,$CG12,CW$7:CW$110) -> 75514.377 | CJ12: =SUMIF($CV$7:$CV$110,$CG12,CX$7:CX$110) -> 60978.346 | CK12: =SUMIF($CV$7:$CV$110,$CG12,CY$7:CY$110) -> 4344.6172 | CL12: =SUMIF($CV$7:$CV$110,$CG12,CZ$7:CZ$110) -> 1930.8482 | CM12: =SUMIF($CV$7:$CV$110,$CG12,DA$7:DA$110) -> 1859.9154 | CN12: =SUMIF($CV$7:$CV$110,$CG12,DB$7:DB$110) -> 1976.9854 | CO12: =SUMIF($CV$7:$CV$110,$CG12,DC$7:DC$110) -> 2784.3796 | CP12: =SUMIF($CV$7:$CV$110,$CG12,DD$7:DD$110) -> 548.94159 | ... CT12: =SUMIF($CV$7:$CV$110,$CG12,DH$7:DH$110) -> 720.41728 | CV12: aipot | CW12: =SUMIF($DJ$7:$DJ$110,$CV12,DL$7:DL$110) -> 75514.377 | CX12: =SUMIF($DJ$7:$DJ$110,$CV12,DM$7:DM$110) -> 60978.346 | CY12: =SUMIF($DJ$7:$DJ$110,$CV12,DN$7:DN$110) -> 4344.6172 | CZ12: =SUMIF($DJ$7:$DJ$110,$CV12,DO$7:DO$110) -> 1930.8482 | DA12: =SUMIF($DJ$7:$DJ$110,$CV12,DP$7:DP$110) -> 1859.9154 | DB12: =SUMIF($DJ$7:$DJ$110,$CV12,DQ$7:DQ$110) -> 1976.9854 | DC12: =SUMIF($DJ$7:$DJ$110,$CV12,DR$7:DR$110) -> 2784.3796 | DD12: =SUMIF($DJ$7:$DJ$110,$CV12,DS$7:DS$110) -> 548.94159 | ... DH12: =SUMIF($DJ$7:$DJ$110,$CV12,DW$7:DW$110) -> 720.41728 | DJ12: aipot | DK12: aipot | DL12: =SUMIF($EF$7:$EF$110,$DK12,EH$7:EH$110)*$DZ12*$EQ$5+SUMIF($ET$7:$ET$110,$DK12,EV$7:EV$110)*$EA12*$FE$5+SUMIF($FH$7:$FH$110,$DK12,FJ$7:FJ$110)*$EB12*$FS$5+SUMIF($FV$7:$FV$110,$DK12,FX$7:FX$110)*$EC12*$GG$5+SUMIF($GJ$7:$GJ$110,$DK12,GL$7:GL$110)*$ED12*$GU$5 -> 19162.94 | DM12: =SUMIF($EF$7:$EF$110,$DK12,EI$7:EI$110)*$DZ12*$EQ$5+SUMIF($ET$7:$ET$110,$DK12,EW$7:EW$110)*$EA12*$FE$5+SUMIF($FH$7:$FH$110,$DK12,FK$7:FK$110)*$EB12*$FS$5+SUMIF($FV$7:$FV$110,$DK12,FY$7:FY$110)*$EC12*$GG$5+SUMIF($GJ$7:$GJ$110,$DK12,GM$7:GM$110)*$ED12*$GU$5 -> 18293.23 | DN12: =SUMIF($EF$7:$EF$110,$DK12,EJ$7:EJ$110)*$DZ12*$EQ$5+SUMIF($ET$7:$ET$110,$DK12,EX$7:EX$110)*$EA12*$FE$5+SUMIF($FH$7:$FH$110,$DK12,FL$7:FL$110)*$EB12*$FS$5+SUMIF($FV$7:$FV$110,$DK12,FZ$7:FZ$110)*$EC12*$GG$5+SUMIF($GJ$7:$GJ$110,$DK12,GN$7:GN$110)*$ED12*$GU$5 -> 2099.748 | DO12: =SUMIF($EF$7:$EF$110,$DK12,EK$7:EK$110)*$DZ12*$EQ$5+SUMIF($ET$7:$ET$110,$DK12,EY$7:EY$110)*$EA12*$FE$5+SUMIF($FH$7:$FH$110,$DK12,FM$7:FM$110)*$EB12*$FS$5+SUMIF($FV$7:$FV$110,$DK12,GA$7:GA$110)*$EC12*$GG$5+SUMIF($GJ$7:$GJ$110,$DK12,GO$7:GO$110)*$ED12*$GU$5 -> 991.9524 | DP12: =SUMIF($EF$7:$EF$110,$DK12,EL$7:EL$110)*$DZ12*$EQ$5+SUMIF($ET$7:$ET$110,$DK12,EZ$7:EZ$110)*$EA12*$FE$5+SUMIF($FH$7:$FH$110,$DK12,FN$7:FN$110)*$EB12*$FS$5+SUMIF($FV$7:$FV$110,$DK12,GB$7:GB$110)*$EC12*$GG$5+SUMIF($GJ$7:$GJ$110,$DK12,GP$7:GP$110)*$ED12*$GU$5 -> 686.3594 | DQ12: =SUMIF($EF$7:$EF$110,$DK12,EM$7:EM$110)*$DZ12*$EQ$5+SUMIF($ET$7:$ET$110,$DK12,FA$7:FA$110)*$EA12*$FE$5+SUMIF($FH$7:$FH$110,$DK12,FO$7:FO$110)*$EB12*$FS$5+SUMIF($FV$7:$FV$110,$DK12,GC$7:GC$110)*$EC12*$GG$5+SUMIF($GJ$7:$GJ$110,$DK12,GQ$7:GQ$110)*$ED12*$GU$5 -> 690.5525 | DR12: =SUMIF($EF$7:$EF$110,$DK12,EN$7:EN$110)*$DZ12*$EQ$5+SUMIF($ET$7:$ET$110,$DK12,FB$7:FB$110)*$EA12*$FE$5+SUMIF($FH$7:$FH$110,$DK12,FP$7:FP$110)*$EB12*$FS$5+SUMIF($FV$7:$FV$110,$DK12,GD$7:GD$110)*$EC12*$GG$5+SUMIF($GJ$7:$GJ$110,$DK12,GR$7:GR$110)*$ED12*$GU$5 -> 2621.628 | DS12: =SUMIF($EF$7:$EF$110,$DK12,EO$7:EO$110)*$DZ12*$EQ$5+SUMIF($ET$7:$ET$110,$DK12,FC$7:FC$110)*$EA12*$FE$5+SUMIF($FH$7:$FH$110,$DK12,FQ$7:FQ$110)*$EB12*$FS$5+SUMIF($FV$7:$FV$110,$DK12,GE$7:GE$110)*$EC12*$GG$5+SUMIF($GJ$7:$GJ$110,$DK12,GS$7:GS$110)*$ED12*$GU$5 -> 445.02 | ... DW12: =SUMIF($EF$7:$EF$110,$DK12,ES$7:ES$110)*$DZ12*$EQ$5+SUMIF($ET$7:$ET$110,$DK12,FG$7:FG$110)*$EA12*$FE$5+SUMIF($FH$7:$FH$110,$DK12,FU$7:FU$110)*$EB12*$FS$5+SUMIF($FV$7:$FV$110,$DK12,GI$7:GI$110)*$EC12*$GG$5+SUMIF($GJ$7:$GJ$110,$DK12,GW$7:GW$110)*$ED12*$GU$5 -> 619.6169 | DY12: aipot | EB12: 1 | EF12: aipot | EG12: aipot | ET12: aipot | EU12: aipot | FH12: aipot | FI12: aipot | FJ12: 19162.94 | FK12: 18293.23 | FL12: 2099.748 | FM12: 991.9524 | FN12: 686.3594 | FO12: 690.5525 | FP12: 2621.628 | FQ12: 445.02 | FR12: 147.1015 | FS12: 145.17 | FT12: 1.916236 | FU12: 619.6169 | FV12: aipot | FW12: aipot | GJ12: aipot | GK12: aipot
C13: aspot | D13: =IF(SUM($S13:$AD13),S13/SUM($S13:$AD13),0) -> 0.50527702 | E13: =IF(SUM($S13:$AD13),T13/SUM($S13:$AD13),0) -> 0.40801445 | F13: =IF(SUM($S13:$AD13),U13/SUM($S13:$AD13),0) -> 0.029070428 | G13: =IF(SUM($S13:$AD13),V13/SUM($S13:$AD13),0) -> 0.012919569 | H13: =IF(SUM($S13:$AD13),W13/SUM($S13:$AD13),0) -> 0.005590998 | I13: =IF(SUM($S13:$AD13),X13/SUM($S13:$AD13),0) -> 0.0059429163 | J13: =IF(SUM($S13:$AD13),Y13/SUM($S13:$AD13),0) -> 0.0083699836 | K13: =IF(SUM($S13:$AD13),Z13/SUM($S13:$AD13),0) -> 0.0016501457 | ... O13: =IF(SUM($S13:$AD13),AD13/SUM($S13:$AD13),0) -> 0.0040735494 | P13: =SUM(D13:O13) -> 1 | R13: aspot | S13: =IF(SUM($AR13:$AU13),$AK13*AR13/SUM($AR13:$AU13),0) -> 0.50527702 | T13: =IF(SUM($AR13:$AU13),$AK13*AS13/SUM($AR13:$AU13),0) -> 0.40801445 | U13: =IF(SUM($AR13:$AU13),$AK13*AT13/SUM($AR13:$AU13),0) -> 0.029070428 | V13: =IF(SUM($AR13:$AU13),$AK13*AU13/SUM($AR13:$AU13),0) -> 0.012919569 | W13: =IF(SUM($AV13:$AY13),$AL13*AV13/SUM($AV13:$AY13),0) -> 0.005590998 | X13: =IF(SUM($AV13:$AY13),$AL13*AW13/SUM($AV13:$AY13),0) -> 0.0059429163 | Y13: =IF(SUM($AV13:$AY13),$AL13*AX13/SUM($AV13:$AY13),0) -> 0.0083699836 | Z13: =IF(SUM($AV13:$AY13),$AL13*AY13/SUM($AV13:$AY13),0) -> 0.0016501457 | AA13: =IF(SUM($AZ13:$BC13),(1-$AL13-$AK13)*AZ13/SUM($AZ13:$BC13),0) -> 0.0083617061 | AB13: =IF(SUM($AZ13:$BC13),(1-$AL13-$AK13)*BA13/SUM($AZ13:$BC13),0) -> 0.0093904641 | AC13: =IF(SUM($AZ13:$BC13),(1-$AL13-$AK13)*BB13/SUM($AZ13:$BC13),0) -> 0.0013387692 | AD13: =IF(SUM($AZ13:$BC13),(1-$AL13-$AK13)*BC13/SUM($AZ13:$BC13),0) -> 0.0040735494 | AE13: =S13+W13+AA13 -> 0.51922972 | AF13: =T13+X13+AB13 -> 0.42334783 | AG13: =U13+Y13+AC13 -> 0.03877918 | AH13: =V13+Z13+AD13 -> 0.018643264 | AI13: =IF(SUM($DL13:$DW13),SUM(DL13:DO13)/SUM($DL13:$DW13),0) -> 0.95528147 | AJ13: =IF(SUM($DL13:$DW13),SUM(DP13:DS13)/SUM($DL13:$DW13),0) -> 0.021554044 | AK13: =AI13 -> 0.95528147 | AL13: =AJ13 -> 0.021554044 | AM13: =1-SUM(AK13:AL13) -> 0.023164489 | AN13: 1 | AO13: 1 | AQ13: aspot | AR13: =IF(SUM($BT13:$CE13),BT13/SUM($BT13:$CE13),0) -> 0.49024134 | AS13: =IF(SUM($BT13:$CE13),BU13/SUM($BT13:$CE13),0) -> 0.39587304 | AT13: =IF(SUM($BT13:$CE13),BV13/SUM($BT13:$CE13),0) -> 0.02820537 | AU13: =IF(SUM($BT13:$CE13),BW13/SUM($BT13:$CE13),0) -> 0.012535118 | AV13: =IF(SUM($BT13:$CE13),BX13/SUM($BT13:$CE13),0) -> 0.01207462 | AW13: =IF(SUM($BT13:$CE13),BY13/SUM($BT13:$CE13),0) -> 0.012834642 | AX13: =IF(SUM($BT13:$CE13),BZ13/SUM($BT13:$CE13),0) -> 0.018076266 | AY13: =IF(SUM($BT13:$CE13),CA13/SUM($BT13:$CE13),0) -> 0.0035637433 | ... BC13: =IF(SUM($BT13:$CE13),CE13/SUM($BT13:$CE13),0) -> 0.0046769681 | BE13: aspot | BF13: 1 | BG13: 1 | BH13: 1 | BI13: 1 | BJ13: 1 | BK13: 1 | BL13: 1 | BM13: 1 | BN13: 1 | BO13: 1 | BP13: 1 | BQ13: 1 | BS13: aspot | BT13: =BF13*CI13 -> 75514.377 | BU13: =BG13*CJ13 -> 60978.346 | BV13: =BH13*CK13 -> 4344.6172 | BW13: =BI13*CL13 -> 1930.8482 | BX13: =BJ13*CM13 -> 1859.9154 | BY13: =BK13*CN13 -> 1976.9854 | BZ13: =BL13*CO13 -> 2784.3796 | CA13: =BM13*CP13 -> 548.94159 | ... CE13: =BQ13*CT13 -> 720.41728 | CG13: =DJ13 -> aipot | CH13: aspot | CI13: =SUMIF($CV$7:$CV$110,$CG13,CW$7:CW$110) -> 75514.377 | CJ13: =SUMIF($CV$7:$CV$110,$CG13,CX$7:CX$110) -> 60978.346 | CK13: =SUMIF($CV$7:$CV$110,$CG13,CY$7:CY$110) -> 4344.6172 | CL13: =SUMIF($CV$7:$CV$110,$CG13,CZ$7:CZ$110) -> 1930.8482 | CM13: =SUMIF($CV$7:$CV$110,$CG13,DA$7:DA$110) -> 1859.9154 | CN13: =SUMIF($CV$7:$CV$110,$CG13,DB$7:DB$110) -> 1976.9854 | CO13: =SUMIF($CV$7:$CV$110,$CG13,DC$7:DC$110) -> 2784.3796 | CP13: =SUMIF($CV$7:$CV$110,$CG13,DD$7:DD$110) -> 548.94159 | ... CT13: =SUMIF($CV$7:$CV$110,$CG13,DH$7:DH$110) -> 720.41728 | CV13: aspot | CW13: =SUMIF($DJ$7:$DJ$110,$CV13,DL$7:DL$110) -> 0 | CX13: =SUMIF($DJ$7:$DJ$110,$CV13,DM$7:DM$110) -> 0 | CY13: =SUMIF($DJ$7:$DJ$110,$CV13,DN$7:DN$110) -> 0 | CZ13: =SUMIF($DJ$7:$DJ$110,$CV13,DO$7:DO$110) -> 0 | DA13: =SUMIF($DJ$7:$DJ$110,$CV13,DP$7:DP$110) -> 0 | DB13: =SUMIF($DJ$7:$DJ$110,$CV13,DQ$7:DQ$110) -> 0 | DC13: =SUMIF($DJ$7:$DJ$110,$CV13,DR$7:DR$110) -> 0 | DD13: =SUMIF($DJ$7:$DJ$110,$CV13,DS$7:DS$110) -> 0 | ... DH13: =SUMIF($DJ$7:$DJ$110,$CV13,DW$7:DW$110) -> 0 | DJ13: aipot | DK13: aspot | DL13: =SUMIF($EF$7:$EF$110,$DK13,EH$7:EH$110)*$DZ13*$EQ$5+SUMIF($ET$7:$ET$110,$DK13,EV$7:EV$110)*$EA13*$FE$5+SUMIF($FH$7:$FH$110,$DK13,FJ$7:FJ$110)*$EB13*$FS$5+SUMIF($FV$7:$FV$110,$DK13,FX$7:FX$110)*$EC13*$GG$5+SUMIF($GJ$7:$GJ$110,$DK13,GL$7:GL$110)*$ED13*$GU$5 -> 34484.47 | DM13: =SUMIF($EF$7:$EF$110,$DK13,EI$7:EI$110)*$DZ13*$EQ$5+SUMIF($ET$7:$ET$110,$DK13,EW$7:EW$110)*$EA13*$FE$5+SUMIF($FH$7:$FH$110,$DK13,FK$7:FK$110)*$EB13*$FS$5+SUMIF($FV$7:$FV$110,$DK13,FY$7:FY$110)*$EC13*$GG$5+SUMIF($GJ$7:$GJ$110,$DK13,GM$7:GM$110)*$ED13*$GU$5 -> 25627.56 | DN13: =SUMIF($EF$7:$EF$110,$DK13,EJ$7:EJ$110)*$DZ13*$EQ$5+SUMIF($ET$7:$ET$110,$DK13,EX$7:EX$110)*$EA13*$FE$5+SUMIF($FH$7:$FH$110,$DK13,FL$7:FL$110)*$EB13*$FS$5+SUMIF($FV$7:$FV$110,$DK13,FZ$7:FZ$110)*$EC13*$GG$5+SUMIF($GJ$7:$GJ$110,$DK13,GN$7:GN$110)*$ED13*$GU$5 -> 1289.606 | DO13: =SUMIF($EF$7:$EF$110,$DK13,EK$7:EK$110)*$DZ13*$EQ$5+SUMIF($ET$7:$ET$110,$DK13,EY$7:EY$110)*$EA13*$FE$5+SUMIF($FH$7:$FH$110,$DK13,FM$7:FM$110)*$EB13*$FS$5+SUMIF($FV$7:$FV$110,$DK13,GA$7:GA$110)*$EC13*$GG$5+SUMIF($GJ$7:$GJ$110,$DK13,GO$7:GO$110)*$ED13*$GU$5 -> 501.9046 | DP13: =SUMIF($EF$7:$EF$110,$DK13,EL$7:EL$110)*$DZ13*$EQ$5+SUMIF($ET$7:$ET$110,$DK13,EZ$7:EZ$110)*$EA13*$FE$5+SUMIF($FH$7:$FH$110,$DK13,FN$7:FN$110)*$EB13*$FS$5+SUMIF($FV$7:$FV$110,$DK13,GB$7:GB$110)*$EC13*$GG$5+SUMIF($GJ$7:$GJ$110,$DK13,GP$7:GP$110)*$ED13*$GU$5 -> 649.9757 | DQ13: =SUMIF($EF$7:$EF$110,$DK13,EM$7:EM$110)*$DZ13*$EQ$5+SUMIF($ET$7:$ET$110,$DK13,FA$7:FA$110)*$EA13*$FE$5+SUMIF($FH$7:$FH$110,$DK13,FO$7:FO$110)*$EB13*$FS$5+SUMIF($FV$7:$FV$110,$DK13,GC$7:GC$110)*$EC13*$GG$5+SUMIF($GJ$7:$GJ$110,$DK13,GQ$7:GQ$110)*$ED13*$GU$5 -> 673.1437 | DR13: =SUMIF($EF$7:$EF$110,$DK13,EN$7:EN$110)*$DZ13*$EQ$5+SUMIF($ET$7:$ET$110,$DK13,FB$7:FB$110)*$EA13*$FE$5+SUMIF($FH$7:$FH$110,$DK13,FP$7:FP$110)*$EB13*$FS$5+SUMIF($FV$7:$FV$110,$DK13,GD$7:GD$110)*$EC13*$GG$5+SUMIF($GJ$7:$GJ$110,$DK13,GR$7:GR$110)*$ED13*$GU$5 -> 38.14664 | DS13: =SUMIF($EF$7:$EF$110,$DK13,EO$7:EO$110)*$DZ13*$EQ$5+SUMIF($ET$7:$ET$110,$DK13,FC$7:FC$110)*$EA13*$FE$5+SUMIF($FH$7:$FH$110,$DK13,FQ$7:FQ$110)*$EB13*$FS$5+SUMIF($FV$7:$FV$110,$DK13,GE$7:GE$110)*$EC13*$GG$5+SUMIF($GJ$7:$GJ$110,$DK13,GS$7:GS$110)*$ED13*$GU$5 -> 35.46535 | ... DW13: =SUMIF($EF$7:$EF$110,$DK13,ES$7:ES$110)*$DZ13*$EQ$5+SUMIF($ET$7:$ET$110,$DK13,FG$7:FG$110)*$EA13*$FE$5+SUMIF($FH$7:$FH$110,$DK13,FU$7:FU$110)*$EB13*$FS$5+SUMIF($FV$7:$FV$110,$DK13,GI$7:GI$110)*$EC13*$GG$5+SUMIF($GJ$7:$GJ$110,$DK13,GW$7:GW$110)*$ED13*$GU$5 -> 65.45613 | DY13: aspot | EB13: 1 | EF13: aspot | EG13: aspot | ET13: aspot | EU13: aspot | FH13: aspot | FI13: aspot | FJ13: 34484.47 | FK13: 25627.56 | FL13: 1289.606 | FM13: 501.9046 | FN13: 649.9757 | FO13: 673.1437 | FP13: 38.14664 | FQ13: 35.46535 | FR13: 658.3847 | FS13: 639.1322 | FT13: 138.1174 | FU13: 65.45613 | FV13: aspot | FW13: aspot | GJ13: aspot | GK13: aspot
C14: acass | D14: =IF(SUM($S14:$AD14),S14/SUM($S14:$AD14),0) -> 0.49036261 | E14: =IF(SUM($S14:$AD14),T14/SUM($S14:$AD14),0) -> 0.39597097 | F14: =IF(SUM($S14:$AD14),U14/SUM($S14:$AD14),0) -> 0.028212347 | G14: =IF(SUM($S14:$AD14),V14/SUM($S14:$AD14),0) -> 0.012538219 | H14: =IF(SUM($S14:$AD14),W14/SUM($S14:$AD14),0) -> 0.0082632319 | I14: =IF(SUM($S14:$AD14),X14/SUM($S14:$AD14),0) -> 0.0087833506 | J14: =IF(SUM($S14:$AD14),Y14/SUM($S14:$AD14),0) -> 0.012370442 | K14: =IF(SUM($S14:$AD14),Z14/SUM($S14:$AD14),0) -> 0.0024388376 | ... O14: =IF(SUM($S14:$AD14),AD14/SUM($S14:$AD14),0) -> 0.0072205318 | P14: =SUM(D14:O14) -> 1 | R14: acass | S14: =IF(SUM($AR14:$AU14),$AK14*AR14/SUM($AR14:$AU14),0) -> 0.49036261 | T14: =IF(SUM($AR14:$AU14),$AK14*AS14/SUM($AR14:$AU14),0) -> 0.39597097 | U14: =IF(SUM($AR14:$AU14),$AK14*AT14/SUM($AR14:$AU14),0) -> 0.028212347 | V14: =IF(SUM($AR14:$AU14),$AK14*AU14/SUM($AR14:$AU14),0) -> 0.012538219 | W14: =IF(SUM($AV14:$AY14),$AL14*AV14/SUM($AV14:$AY14),0) -> 0.0082632319 | X14: =IF(SUM($AV14:$AY14),$AL14*AW14/SUM($AV14:$AY14),0) -> 0.0087833506 | Y14: =IF(SUM($AV14:$AY14),$AL14*AX14/SUM($AV14:$AY14),0) -> 0.012370442 | Z14: =IF(SUM($AV14:$AY14),$AL14*AY14/SUM($AV14:$AY14),0) -> 0.0024388376 | AA14: =IF(SUM($AZ14:$BC14),(1-$AL14-$AK14)*AZ14/SUM($AZ14:$BC14),0) -> 0.014821464 | AB14: =IF(SUM($AZ14:$BC14),(1-$AL14-$AK14)*BA14/SUM($AZ14:$BC14),0) -> 0.016644979 | AC14: =IF(SUM($AZ14:$BC14),(1-$AL14-$AK14)*BB14/SUM($AZ14:$BC14),0) -> 0.0023730227 | AD14: =IF(SUM($AZ14:$BC14),(1-$AL14-$AK14)*BC14/SUM($AZ14:$BC14),0) -> 0.0072205318 | AE14: =S14+W14+AA14 -> 0.5134473 | AF14: =T14+X14+AB14 -> 0.4213993 | AG14: =U14+Y14+AC14 -> 0.042955812 | AH14: =V14+Z14+AD14 -> 0.022197588 | AI14: =IF(SUM($DL14:$DW14),SUM(DL14:DO14)/SUM($DL14:$DW14),0) -> 0.92708414 | AJ14: =IF(SUM($DL14:$DW14),SUM(DP14:DS14)/SUM($DL14:$DW14),0) -> 0.031855862 | AK14: =AI14 -> 0.92708414 | AL14: =AJ14 -> 0.031855862 | AM14: =1-SUM(AK14:AL14) -> 0.041059997 | AN14: 1 | AO14: 1 | AQ14: acass | AR14: =IF(SUM($BT14:$CE14),BT14/SUM($BT14:$CE14),0) -> 0.49024134 | AS14: =IF(SUM($BT14:$CE14),BU14/SUM($BT14:$CE14),0) -> 0.39587304 | AT14: =IF(SUM($BT14:$CE14),BV14/SUM($BT14:$CE14),0) -> 0.02820537 | AU14: =IF(SUM($BT14:$CE14),BW14/SUM($BT14:$CE14),0) -> 0.012535118 | AV14: =IF(SUM($BT14:$CE14),BX14/SUM($BT14:$CE14),0) -> 0.01207462 | AW14: =IF(SUM($BT14:$CE14),BY14/SUM($BT14:$CE14),0) -> 0.012834642 | AX14: =IF(SUM($BT14:$CE14),BZ14/SUM($BT14:$CE14),0) -> 0.018076266 | AY14: =IF(SUM($BT14:$CE14),CA14/SUM($BT14:$CE14),0) -> 0.0035637433 | ... BC14: =IF(SUM($BT14:$CE14),CE14/SUM($BT14:$CE14),0) -> 0.0046769681 | BE14: acass | BF14: 1 | BG14: 1 | BH14: 1 | BI14: 1 | BJ14: 1 | BK14: 1 | BL14: 1 | BM14: 1 | BN14: 1 | BO14: 1 | BP14: 1 | BQ14: 1 | BS14: acass | BT14: =BF14*CI14 -> 75514.377 | BU14: =BG14*CJ14 -> 60978.346 | BV14: =BH14*CK14 -> 4344.6172 | BW14: =BI14*CL14 -> 1930.8482 | BX14: =BJ14*CM14 -> 1859.9154 | BY14: =BK14*CN14 -> 1976.9854 | BZ14: =BL14*CO14 -> 2784.3796 | CA14: =BM14*CP14 -> 548.94159 | ... CE14: =BQ14*CT14 -> 720.41728 | CG14: =DJ14 -> aipot | CH14: acass | CI14: =SUMIF($CV$7:$CV$110,$CG14,CW$7:CW$110) -> 75514.377 | CJ14: =SUMIF($CV$7:$CV$110,$CG14,CX$7:CX$110) -> 60978.346 | CK14: =SUMIF($CV$7:$CV$110,$CG14,CY$7:CY$110) -> 4344.6172 | CL14: =SUMIF($CV$7:$CV$110,$CG14,CZ$7:CZ$110) -> 1930.8482 | CM14: =SUMIF($CV$7:$CV$110,$CG14,DA$7:DA$110) -> 1859.9154 | CN14: =SUMIF($CV$7:$CV$110,$CG14,DB$7:DB$110) -> 1976.9854 | CO14: =SUMIF($CV$7:$CV$110,$CG14,DC$7:DC$110) -> 2784.3796 | CP14: =SUMIF($CV$7:$CV$110,$CG14,DD$7:DD$110) -> 548.94159 | ... CT14: =SUMIF($CV$7:$CV$110,$CG14,DH$7:DH$110) -> 720.41728 | CV14: acass | CW14: =SUMIF($DJ$7:$DJ$110,$CV14,DL$7:DL$110) -> 0 | CX14: =SUMIF($DJ$7:$DJ$110,$CV14,DM$7:DM$110) -> 0 | CY14: =SUMIF($DJ$7:$DJ$110,$CV14,DN$7:DN$110) -> 0 | CZ14: =SUMIF($DJ$7:$DJ$110,$CV14,DO$7:DO$110) -> 0 | DA14: =SUMIF($DJ$7:$DJ$110,$CV14,DP$7:DP$110) -> 0 | DB14: =SUMIF($DJ$7:$DJ$110,$CV14,DQ$7:DQ$110) -> 0 | DC14: =SUMIF($DJ$7:$DJ$110,$CV14,DR$7:DR$110) -> 0 | DD14: =SUMIF($DJ$7:$DJ$110,$CV14,DS$7:DS$110) -> 0 | ... DH14: =SUMIF($DJ$7:$DJ$110,$CV14,DW$7:DW$110) -> 0 | DJ14: aipot | DK14: acass | DL14: =SUMIF($EF$7:$EF$110,$DK14,EH$7:EH$110)*$DZ14*$EQ$5+SUMIF($ET$7:$ET$110,$DK14,EV$7:EV$110)*$EA14*$FE$5+SUMIF($FH$7:$FH$110,$DK14,FJ$7:FJ$110)*$EB14*$FS$5+SUMIF($FV$7:$FV$110,$DK14,FX$7:FX$110)*$EC14*$GG$5+SUMIF($GJ$7:$GJ$110,$DK14,GL$7:GL$110)*$ED14*$GU$5 -> 16470.56 | DM14: =SUMIF($EF$7:$EF$110,$DK14,EI$7:EI$110)*$DZ14*$EQ$5+SUMIF($ET$7:$ET$110,$DK14,EW$7:EW$110)*$EA14*$FE$5+SUMIF($FH$7:$FH$110,$DK14,FK$7:FK$110)*$EB14*$FS$5+SUMIF($FV$7:$FV$110,$DK14,FY$7:FY$110)*$EC14*$GG$5+SUMIF($GJ$7:$GJ$110,$DK14,GM$7:GM$110)*$ED14*$GU$5 -> 12888.57 | DN14: =SUMIF($EF$7:$EF$110,$DK14,EJ$7:EJ$110)*$DZ14*$EQ$5+SUMIF($ET$7:$ET$110,$DK14,EX$7:EX$110)*$EA14*$FE$5+SUMIF($FH$7:$FH$110,$DK14,FL$7:FL$110)*$EB14*$FS$5+SUMIF($FV$7:$FV$110,$DK14,FZ$7:FZ$110)*$EC14*$GG$5+SUMIF($GJ$7:$GJ$110,$DK14,GN$7:GN$110)*$ED14*$GU$5 -> 706.8925 | DO14: =SUMIF($EF$7:$EF$110,$DK14,EK$7:EK$110)*$DZ14*$EQ$5+SUMIF($ET$7:$ET$110,$DK14,EY$7:EY$110)*$EA14*$FE$5+SUMIF($FH$7:$FH$110,$DK14,FM$7:FM$110)*$EB14*$FS$5+SUMIF($FV$7:$FV$110,$DK14,GA$7:GA$110)*$EC14*$GG$5+SUMIF($GJ$7:$GJ$110,$DK14,GO$7:GO$110)*$ED14*$GU$5 -> 315.5139 | DP14: =SUMIF($EF$7:$EF$110,$DK14,EL$7:EL$110)*$DZ14*$EQ$5+SUMIF($ET$7:$ET$110,$DK14,EZ$7:EZ$110)*$EA14*$FE$5+SUMIF($FH$7:$FH$110,$DK14,FN$7:FN$110)*$EB14*$FS$5+SUMIF($FV$7:$FV$110,$DK14,GB$7:GB$110)*$EC14*$GG$5+SUMIF($GJ$7:$GJ$110,$DK14,GP$7:GP$110)*$ED14*$GU$5 -> 427.6997 | DQ14: =SUMIF($EF$7:$EF$110,$DK14,EM$7:EM$110)*$DZ14*$EQ$5+SUMIF($ET$7:$ET$110,$DK14,FA$7:FA$110)*$EA14*$FE$5+SUMIF($FH$7:$FH$110,$DK14,FO$7:FO$110)*$EB14*$FS$5+SUMIF($FV$7:$FV$110,$DK14,GC$7:GC$110)*$EC14*$GG$5+SUMIF($GJ$7:$GJ$110,$DK14,GQ$7:GQ$110)*$ED14*$GU$5 -> 455.4421 | DR14: =SUMIF($EF$7:$EF$110,$DK14,EN$7:EN$110)*$DZ14*$EQ$5+SUMIF($ET$7:$ET$110,$DK14,FB$7:FB$110)*$EA14*$FE$5+SUMIF($FH$7:$FH$110,$DK14,FP$7:FP$110)*$EB14*$FS$5+SUMIF($FV$7:$FV$110,$DK14,GD$7:GD$110)*$EC14*$GG$5+SUMIF($GJ$7:$GJ$110,$DK14,GR$7:GR$110)*$ED14*$GU$5 -> 101.5649 | DS14: =SUMIF($EF$7:$EF$110,$DK14,EO$7:EO$110)*$DZ14*$EQ$5+SUMIF($ET$7:$ET$110,$DK14,FC$7:FC$110)*$EA14*$FE$5+SUMIF($FH$7:$FH$110,$DK14,FQ$7:FQ$110)*$EB14*$FS$5+SUMIF($FV$7:$FV$110,$DK14,GE$7:GE$110)*$EC14*$GG$5+SUMIF($GJ$7:$GJ$110,$DK14,GS$7:GS$110)*$ED14*$GU$5 -> 59.24388 | ... DW14: =SUMIF($EF$7:$EF$110,$DK14,ES$7:ES$110)*$DZ14*$EQ$5+SUMIF($ET$7:$ET$110,$DK14,FG$7:FG$110)*$EA14*$FE$5+SUMIF($FH$7:$FH$110,$DK14,FU$7:FU$110)*$EB14*$FS$5+SUMIF($FV$7:$FV$110,$DK14,GI$7:GI$110)*$EC14*$GG$5+SUMIF($GJ$7:$GJ$110,$DK14,GW$7:GW$110)*$ED14*$GU$5 -> 25.25554 | DY14: acass | EB14: 1 | EF14: acass | EG14: acass | ET14: acass | EU14: acass | FH14: acass | FI14: acass | FJ14: 16470.56 | FK14: 12888.57 | FL14: 706.8925 | FM14: 315.5139 | FN14: 427.6997 | FO14: 455.4421 | FP14: 101.5649 | FQ14: 59.24388 | FR14: 524.4992 | FS14: 756.7698 | FT14: 39.05538 | FU14: 25.25554 | FV14: acass | FW14: acass | GJ14: acass | GK14: acass
C15: aroot | D15: =IF(SUM($S15:$AD15),S15/SUM($S15:$AD15),0) -> 0.49775754 | E15: =IF(SUM($S15:$AD15),T15/SUM($S15:$AD15),0) -> 0.40194242 | F15: =IF(SUM($S15:$AD15),U15/SUM($S15:$AD15),0) -> 0.028637804 | G15: =IF(SUM($S15:$AD15),V15/SUM($S15:$AD15),0) -> 0.012727302 | H15: =IF(SUM($S15:$AD15),W15/SUM($S15:$AD15),0) -> 0.0070264783 | I15: =IF(SUM($S15:$AD15),X15/SUM($S15:$AD15),0) -> 0.0074687511 | J15: =IF(SUM($S15:$AD15),Y15/SUM($S15:$AD15),0) -> 0.010518964 | K15: =IF(SUM($S15:$AD15),Z15/SUM($S15:$AD15),0) -> 0.0020738181 | ... O15: =IF(SUM($S15:$AD15),AD15/SUM($S15:$AD15),0) -> 0.005600384 | P15: =SUM(D15:O15) -> 1 | R15: aroot | S15: =IF(SUM($AR15:$AU15),$AK15*AR15/SUM($AR15:$AU15),0) -> 0.49775754 | T15: =IF(SUM($AR15:$AU15),$AK15*AS15/SUM($AR15:$AU15),0) -> 0.40194242 | U15: =IF(SUM($AR15:$AU15),$AK15*AT15/SUM($AR15:$AU15),0) -> 0.028637804 | V15: =IF(SUM($AR15:$AU15),$AK15*AU15/SUM($AR15:$AU15),0) -> 0.012727302 | W15: =IF(SUM($AV15:$AY15),$AL15*AV15/SUM($AV15:$AY15),0) -> 0.0070264783 | X15: =IF(SUM($AV15:$AY15),$AL15*AW15/SUM($AV15:$AY15),0) -> 0.0074687511 | Y15: =IF(SUM($AV15:$AY15),$AL15*AX15/SUM($AV15:$AY15),0) -> 0.010518964 | Z15: =IF(SUM($AV15:$AY15),$AL15*AY15/SUM($AV15:$AY15),0) -> 0.0020738181 | AA15: =IF(SUM($AZ15:$BC15),(1-$AL15-$AK15)*AZ15/SUM($AZ15:$BC15),0) -> 0.011495814 | AB15: =IF(SUM($AZ15:$BC15),(1-$AL15-$AK15)*BA15/SUM($AZ15:$BC15),0) -> 0.012910167 | AC15: =IF(SUM($AZ15:$BC15),(1-$AL15-$AK15)*BB15/SUM($AZ15:$BC15),0) -> 0.0018405623 | AD15: =IF(SUM($AZ15:$BC15),(1-$AL15-$AK15)*BC15/SUM($AZ15:$BC15),0) -> 0.005600384 | AE15: =S15+W15+AA15 -> 0.51627983 | AF15: =T15+X15+AB15 -> 0.42232134 | AG15: =U15+Y15+AC15 -> 0.040997331 | AH15: =V15+Z15+AD15 -> 0.020401504 | AI15: =IF(SUM($DL15:$DW15),SUM(DL15:DO15)/SUM($DL15:$DW15),0) -> 0.94106506 | AJ15: =IF(SUM($DL15:$DW15),SUM(DP15:DS15)/SUM($DL15:$DW15),0) -> 0.027088012 | AK15: =AI15 -> 0.94106506 | AL15: =AJ15 -> 0.027088012 | AM15: =1-SUM(AK15:AL15) -> 0.031846927 | AN15: 1 | AO15: 1 | AQ15: aroot | AR15: =IF(SUM($BT15:$CE15),BT15/SUM($BT15:$CE15),0) -> 0.49024134 | AS15: =IF(SUM($BT15:$CE15),BU15/SUM($BT15:$CE15),0) -> 0.39587304 | AT15: =IF(SUM($BT15:$CE15),BV15/SUM($BT15:$CE15),0) -> 0.02820537 | AU15: =IF(SUM($BT15:$CE15),BW15/SUM($BT15:$CE15),0) -> 0.012535118 | AV15: =IF(SUM($BT15:$CE15),BX15/SUM($BT15:$CE15),0) -> 0.01207462 | AW15: =IF(SUM($BT15:$CE15),BY15/SUM($BT15:$CE15),0) -> 0.012834642 | AX15: =IF(SUM($BT15:$CE15),BZ15/SUM($BT15:$CE15),0) -> 0.018076266 | AY15: =IF(SUM($BT15:$CE15),CA15/SUM($BT15:$CE15),0) -> 0.0035637433 | ... BC15: =IF(SUM($BT15:$CE15),CE15/SUM($BT15:$CE15),0) -> 0.0046769681 | BE15: aroot | BF15: 1 | BG15: 1 | BH15: 1 | BI15: 1 | BJ15: 1 | BK15: 1 | BL15: 1 | BM15: 1 | BN15: 1 | BO15: 1 | BP15: 1 | BQ15: 1 | BS15: aroot | BT15: =BF15*CI15 -> 75514.377 | BU15: =BG15*CJ15 -> 60978.346 | BV15: =BH15*CK15 -> 4344.6172 | BW15: =BI15*CL15 -> 1930.8482 | BX15: =BJ15*CM15 -> 1859.9154 | BY15: =BK15*CN15 -> 1976.9854 | BZ15: =BL15*CO15 -> 2784.3796 | CA15: =BM15*CP15 -> 548.94159 | ... CE15: =BQ15*CT15 -> 720.41728 | CG15: =DJ15 -> aipot | CH15: aroot | CI15: =SUMIF($CV$7:$CV$110,$CG15,CW$7:CW$110) -> 75514.377 | CJ15: =SUMIF($CV$7:$CV$110,$CG15,CX$7:CX$110) -> 60978.346 | CK15: =SUMIF($CV$7:$CV$110,$CG15,CY$7:CY$110) -> 4344.6172 | CL15: =SUMIF($CV$7:$CV$110,$CG15,CZ$7:CZ$110) -> 1930.8482 | CM15: =SUMIF($CV$7:$CV$110,$CG15,DA$7:DA$110) -> 1859.9154 | CN15: =SUMIF($CV$7:$CV$110,$CG15,DB$7:DB$110) -> 1976.9854 | CO15: =SUMIF($CV$7:$CV$110,$CG15,DC$7:DC$110) -> 2784.3796 | CP15: =SUMIF($CV$7:$CV$110,$CG15,DD$7:DD$110) -> 548.94159 | ... CT15: =SUMIF($CV$7:$CV$110,$CG15,DH$7:DH$110) -> 720.41728 | CV15: aroot | CW15: =SUMIF($DJ$7:$DJ$110,$CV15,DL$7:DL$110) -> 0 | CX15: =SUMIF($DJ$7:$DJ$110,$CV15,DM$7:DM$110) -> 0 | CY15: =SUMIF($DJ$7:$DJ$110,$CV15,DN$7:DN$110) -> 0 | CZ15: =SUMIF($DJ$7:$DJ$110,$CV15,DO$7:DO$110) -> 0 | DA15: =SUMIF($DJ$7:$DJ$110,$CV15,DP$7:DP$110) -> 0 | DB15: =SUMIF($DJ$7:$DJ$110,$CV15,DQ$7:DQ$110) -> 0 | DC15: =SUMIF($DJ$7:$DJ$110,$CV15,DR$7:DR$110) -> 0 | DD15: =SUMIF($DJ$7:$DJ$110,$CV15,DS$7:DS$110) -> 0 | ... DH15: =SUMIF($DJ$7:$DJ$110,$CV15,DW$7:DW$110) -> 0 | DJ15: aipot | DK15: aroot | DL15: =SUMIF($EF$7:$EF$110,$DK15,EH$7:EH$110)*$DZ15*$EQ$5+SUMIF($ET$7:$ET$110,$DK15,EV$7:EV$110)*$EA15*$FE$5+SUMIF($FH$7:$FH$110,$DK15,FJ$7:FJ$110)*$EB15*$FS$5+SUMIF($FV$7:$FV$110,$DK15,FX$7:FX$110)*$EC15*$GG$5+SUMIF($GJ$7:$GJ$110,$DK15,GL$7:GL$110)*$ED15*$GU$5 -> 5396.407 | DM15: =SUMIF($EF$7:$EF$110,$DK15,EI$7:EI$110)*$DZ15*$EQ$5+SUMIF($ET$7:$ET$110,$DK15,EW$7:EW$110)*$EA15*$FE$5+SUMIF($FH$7:$FH$110,$DK15,FK$7:FK$110)*$EB15*$FS$5+SUMIF($FV$7:$FV$110,$DK15,FY$7:FY$110)*$EC15*$GG$5+SUMIF($GJ$7:$GJ$110,$DK15,GM$7:GM$110)*$ED15*$GU$5 -> 4168.986 | DN15: =SUMIF($EF$7:$EF$110,$DK15,EJ$7:EJ$110)*$DZ15*$EQ$5+SUMIF($ET$7:$ET$110,$DK15,EX$7:EX$110)*$EA15*$FE$5+SUMIF($FH$7:$FH$110,$DK15,FL$7:FL$110)*$EB15*$FS$5+SUMIF($FV$7:$FV$110,$DK15,FZ$7:FZ$110)*$EC15*$GG$5+SUMIF($GJ$7:$GJ$110,$DK15,GN$7:GN$110)*$ED15*$GU$5 -> 248.3707 | DO15: =SUMIF($EF$7:$EF$110,$DK15,EK$7:EK$110)*$DZ15*$EQ$5+SUMIF($ET$7:$ET$110,$DK15,EY$7:EY$110)*$EA15*$FE$5+SUMIF($FH$7:$FH$110,$DK15,FM$7:FM$110)*$EB15*$FS$5+SUMIF($FV$7:$FV$110,$DK15,GA$7:GA$110)*$EC15*$GG$5+SUMIF($GJ$7:$GJ$110,$DK15,GO$7:GO$110)*$ED15*$GU$5 -> 121.4773 | DP15: =SUMIF($EF$7:$EF$110,$DK15,EL$7:EL$110)*$DZ15*$EQ$5+SUMIF($ET$7:$ET$110,$DK15,EZ$7:EZ$110)*$EA15*$FE$5+SUMIF($FH$7:$FH$110,$DK15,FN$7:FN$110)*$EB15*$FS$5+SUMIF($FV$7:$FV$110,$DK15,GB$7:GB$110)*$EC15*$GG$5+SUMIF($GJ$7:$GJ$110,$DK15,GP$7:GP$110)*$ED15*$GU$5 -> 95.88058 | DQ15: =SUMIF($EF$7:$EF$110,$DK15,EM$7:EM$110)*$DZ15*$EQ$5+SUMIF($ET$7:$ET$110,$DK15,FA$7:FA$110)*$EA15*$FE$5+SUMIF($FH$7:$FH$110,$DK15,FO$7:FO$110)*$EB15*$FS$5+SUMIF($FV$7:$FV$110,$DK15,GC$7:GC$110)*$EC15*$GG$5+SUMIF($GJ$7:$GJ$110,$DK15,GQ$7:GQ$110)*$ED15*$GU$5 -> 157.8471 | DR15: =SUMIF($EF$7:$EF$110,$DK15,EN$7:EN$110)*$DZ15*$EQ$5+SUMIF($ET$7:$ET$110,$DK15,FB$7:FB$110)*$EA15*$FE$5+SUMIF($FH$7:$FH$110,$DK15,FP$7:FP$110)*$EB15*$FS$5+SUMIF($FV$7:$FV$110,$DK15,GD$7:GD$110)*$EC15*$GG$5+SUMIF($GJ$7:$GJ$110,$DK15,GR$7:GR$110)*$ED15*$GU$5 -> 23.04011 | DS15: =SUMIF($EF$7:$EF$110,$DK15,EO$7:EO$110)*$DZ15*$EQ$5+SUMIF($ET$7:$ET$110,$DK15,FC$7:FC$110)*$EA15*$FE$5+SUMIF($FH$7:$FH$110,$DK15,FQ$7:FQ$110)*$EB15*$FS$5+SUMIF($FV$7:$FV$110,$DK15,GE$7:GE$110)*$EC15*$GG$5+SUMIF($GJ$7:$GJ$110,$DK15,GS$7:GS$110)*$ED15*$GU$5 -> 9.212357 | ... DW15: =SUMIF($EF$7:$EF$110,$DK15,ES$7:ES$110)*$DZ15*$EQ$5+SUMIF($ET$7:$ET$110,$DK15,FG$7:FG$110)*$EA15*$FE$5+SUMIF($FH$7:$FH$110,$DK15,FU$7:FU$110)*$EB15*$FS$5+SUMIF($FV$7:$FV$110,$DK15,GI$7:GI$110)*$EC15*$GG$5+SUMIF($GJ$7:$GJ$110,$DK15,GW$7:GW$110)*$ED15*$GU$5 -> 10.08871 | DY15: aroot | EB15: 1 | EF15: aroot | EG15: aroot | ET15: aroot | EU15: aroot | FH15: aroot | FI15: aroot | FJ15: 5396.407 | FK15: 4168.986 | FL15: 248.3707 | FM15: 121.4773 | FN15: 95.88058 | FO15: 157.8471 | FP15: 23.04011 | FQ15: 9.212357 | FR15: 148.803 | FS15: 119.6548 | FT15: 57.67562 | FU15: 10.08871 | FV15: aroot | FW15: aroot | GJ15: aroot | GK15: aroot
C16: abean | D16: =IF(SUM($S16:$AD16),S16/SUM($S16:$AD16),0) -> 0.47919011 | E16: =IF(SUM($S16:$AD16),T16/SUM($S16:$AD16),0) -> 0.3588048 | F16: =IF(SUM($S16:$AD16),U16/SUM($S16:$AD16),0) -> 0.029643078 | G16: =IF(SUM($S16:$AD16),V16/SUM($S16:$AD16),0) -> 0.011400722 | H16: =IF(SUM($S16:$AD16),W16/SUM($S16:$AD16),0) -> 0.010822825 | I16: =IF(SUM($S16:$AD16),X16/SUM($S16:$AD16),0) -> 0.016164162 | J16: =IF(SUM($S16:$AD16),Y16/SUM($S16:$AD16),0) -> 0.0054678963 | K16: =IF(SUM($S16:$AD16),Z16/SUM($S16:$AD16),0) -> 0.0036284212 | ... O16: =IF(SUM($S16:$AD16),AD16/SUM($S16:$AD16),0) -> 0.028753901 | P16: =SUM(D16:O16) -> 1 | R16: abean | S16: =IF(SUM($AR16:$AU16),$AK16*AR16/SUM($AR16:$AU16),0) -> 0.47919011 | T16: =IF(SUM($AR16:$AU16),$AK16*AS16/SUM($AR16:$AU16),0) -> 0.3588048 | U16: =IF(SUM($AR16:$AU16),$AK16*AT16/SUM($AR16:$AU16),0) -> 0.029643078 | V16: =IF(SUM($AR16:$AU16),$AK16*AU16/SUM($AR16:$AU16),0) -> 0.011400722 | W16: =IF(SUM($AV16:$AY16),$AL16*AV16/SUM($AV16:$AY16),0) -> 0.010822825 | X16: =IF(SUM($AV16:$AY16),$AL16*AW16/SUM($AV16:$AY16),0) -> 0.016164162 | Y16: =IF(SUM($AV16:$AY16),$AL16*AX16/SUM($AV16:$AY16),0) -> 0.0054678963 | Z16: =IF(SUM($AV16:$AY16),$AL16*AY16/SUM($AV16:$AY16),0) -> 0.0036284212 | AA16: =IF(SUM($AZ16:$BC16),(1-$AL16-$AK16)*AZ16/SUM($AZ16:$BC16),0) -> 0.025906442 | AB16: =IF(SUM($AZ16:$BC16),(1-$AL16-$AK16)*BA16/SUM($AZ16:$BC16),0) -> 0.023818811 | AC16: =IF(SUM($AZ16:$BC16),(1-$AL16-$AK16)*BB16/SUM($AZ16:$BC16),0) -> 0.0063988321 | AD16: =IF(SUM($AZ16:$BC16),(1-$AL16-$AK16)*BC16/SUM($AZ16:$BC16),0) -> 0.028753901 | AE16: =S16+W16+AA16 -> 0.51591937 | AF16: =T16+X16+AB16 -> 0.39878778 | AG16: =U16+Y16+AC16 -> 0.041509806 | AH16: =V16+Z16+AD16 -> 0.043783044 | AI16: =IF(SUM($DL16:$DW16),SUM(DL16:DO16)/SUM($DL16:$DW16),0) -> 0.87903871 | AJ16: =IF(SUM($DL16:$DW16),SUM(DP16:DS16)/SUM($DL16:$DW16),0) -> 0.036083305 | AK16: =AI16 -> 0.87903871 | AL16: =AJ16 -> 0.036083305 | AM16: =1-SUM(AK16:AL16) -> 0.084877986 | AN16: 1 | AO16: 1 | AQ16: abean | AR16: =IF(SUM($BT16:$CE16),BT16/SUM($BT16:$CE16),0) -> 0.47836062 | AS16: =IF(SUM($BT16:$CE16),BU16/SUM($BT16:$CE16),0) -> 0.3581837 | AT16: =IF(SUM($BT16:$CE16),BV16/SUM($BT16:$CE16),0) -> 0.029591765 | AU16: =IF(SUM($BT16:$CE16),BW16/SUM($BT16:$CE16),0) -> 0.011380987 | AV16: =IF(SUM($BT16:$CE16),BX16/SUM($BT16:$CE16),0) -> 0.01375094 | AW16: =IF(SUM($BT16:$CE16),BY16/SUM($BT16:$CE16),0) -> 0.020537377 | AX16: =IF(SUM($BT16:$CE16),BZ16/SUM($BT16:$CE16),0) -> 0.0069472358 | AY16: =IF(SUM($BT16:$CE16),CA16/SUM($BT16:$CE16),0) -> 0.0046100907 | ... BC16: =IF(SUM($BT16:$CE16),CE16/SUM($BT16:$CE16),0) -> 0.025962221 | BE16: abean | BF16: 1 | BG16: 1 | BH16: 1 | BI16: 1 | BJ16: 1 | BK16: 1 | BL16: 1 | BM16: 1 | BN16: 1 | BO16: 1 | BP16: 1 | BQ16: 1 | BS16: abean | BT16: =BF16*CI16 -> 71004.98 | BU16: =BG16*CJ16 -> 53166.64 | BV16: =BH16*CK16 -> 4392.424 | BW16: =BI16*CL16 -> 1689.3254 | BX16: =BJ16*CM16 -> 2041.1071 | BY16: =BK16*CN16 -> 3048.445 | BZ16: =BL16*CO16 -> 1031.206 | CA16: =BM16*CP16 -> 684.2942 | ... CE16: =BQ16*CT16 -> 3853.6763 | CG16: =DJ16 -> abean | CH16: abean | CI16: =SUMIF($CV$7:$CV$110,$CG16,CW$7:CW$110) -> 71004.98 | CJ16: =SUMIF($CV$7:$CV$110,$CG16,CX$7:CX$110) -> 53166.64 | CK16: =SUMIF($CV$7:$CV$110,$CG16,CY$7:CY$110) -> 4392.424 | CL16: =SUMIF($CV$7:$CV$110,$CG16,CZ$7:CZ$110) -> 1689.3254 | CM16: =SUMIF($CV$7:$CV$110,$CG16,DA$7:DA$110) -> 2041.1071 | CN16: =SUMIF($CV$7:$CV$110,$CG16,DB$7:DB$110) -> 3048.445 | CO16: =SUMIF($CV$7:$CV$110,$CG16,DC$7:DC$110) -> 1031.206 | CP16: =SUMIF($CV$7:$CV$110,$CG16,DD$7:DD$110) -> 684.2942 | ... CT16: =SUMIF($CV$7:$CV$110,$CG16,DH$7:DH$110) -> 3853.6763 | CV16: abean | CW16: =SUMIF($DJ$7:$DJ$110,$CV16,DL$7:DL$110) -> 71004.98 | CX16: =SUMIF($DJ$7:$DJ$110,$CV16,DM$7:DM$110) -> 53166.64 | CY16: =SUMIF($DJ$7:$DJ$110,$CV16,DN$7:DN$110) -> 4392.424 | CZ16: =SUMIF($DJ$7:$DJ$110,$CV16,DO$7:DO$110) -> 1689.3254 | DA16: =SUMIF($DJ$7:$DJ$110,$CV16,DP$7:DP$110) -> 2041.1071 | DB16: =SUMIF($DJ$7:$DJ$110,$CV16,DQ$7:DQ$110) -> 3048.445 | DC16: =SUMIF($DJ$7:$DJ$110,$CV16,DR$7:DR$110) -> 1031.206 | DD16: =SUMIF($DJ$7:$DJ$110,$CV16,DS$7:DS$110) -> 684.2942 | ... DH16: =SUMIF($DJ$7:$DJ$110,$CV16,DW$7:DW$110) -> 3853.6763 | DJ16: abean | DK16: abean | DL16: =SUMIF($EF$7:$EF$110,$DK16,EH$7:EH$110)*$DZ16*$EQ$5+SUMIF($ET$7:$ET$110,$DK16,EV$7:EV$110)*$EA16*$FE$5+SUMIF($FH$7:$FH$110,$DK16,FJ$7:FJ$110)*$EB16*$FS$5+SUMIF($FV$7:$FV$110,$DK16,FX$7:FX$110)*$EC16*$GG$5+SUMIF($GJ$7:$GJ$110,$DK16,GL$7:GL$110)*$ED16*$GU$5 -> 47333.9 | DM16: =SUMIF($EF$7:$EF$110,$DK16,EI$7:EI$110)*$DZ16*$EQ$5+SUMIF($ET$7:$ET$110,$DK16,EW$7:EW$110)*$EA16*$FE$5+SUMIF($FH$7:$FH$110,$DK16,FK$7:FK$110)*$EB16*$FS$5+SUMIF($FV$7:$FV$110,$DK16,FY$7:FY$110)*$EC16*$GG$5+SUMIF($GJ$7:$GJ$110,$DK16,GM$7:GM$110)*$ED16*$GU$5 -> 35928.07 | DN16: =SUMIF($EF$7:$EF$110,$DK16,EJ$7:EJ$110)*$DZ16*$EQ$5+SUMIF($ET$7:$ET$110,$DK16,EX$7:EX$110)*$EA16*$FE$5+SUMIF($FH$7:$FH$110,$DK16,FL$7:FL$110)*$EB16*$FS$5+SUMIF($FV$7:$FV$110,$DK16,FZ$7:FZ$110)*$EC16*$GG$5+SUMIF($GJ$7:$GJ$110,$DK16,GN$7:GN$110)*$ED16*$GU$5 -> 3218.175 | DO16: =SUMIF($EF$7:$EF$110,$DK16,EK$7:EK$110)*$DZ16*$EQ$5+SUMIF($ET$7:$ET$110,$DK16,EY$7:EY$110)*$EA16*$FE$5+SUMIF($FH$7:$FH$110,$DK16,FM$7:FM$110)*$EB16*$FS$5+SUMIF($FV$7:$FV$110,$DK16,GA$7:GA$110)*$EC16*$GG$5+SUMIF($GJ$7:$GJ$110,$DK16,GO$7:GO$110)*$ED16*$GU$5 -> 1192.562 | DP16: =SUMIF($EF$7:$EF$110,$DK16,EL$7:EL$110)*$DZ16*$EQ$5+SUMIF($ET$7:$ET$110,$DK16,EZ$7:EZ$110)*$EA16*$FE$5+SUMIF($FH$7:$FH$110,$DK16,FN$7:FN$110)*$EB16*$FS$5+SUMIF($FV$7:$FV$110,$DK16,GB$7:GB$110)*$EC16*$GG$5+SUMIF($GJ$7:$GJ$110,$DK16,GP$7:GP$110)*$ED16*$GU$5 -> 1162.295 | DQ16: =SUMIF($EF$7:$EF$110,$DK16,EM$7:EM$110)*$DZ16*$EQ$5+SUMIF($ET$7:$ET$110,$DK16,FA$7:FA$110)*$EA16*$FE$5+SUMIF($FH$7:$FH$110,$DK16,FO$7:FO$110)*$EB16*$FS$5+SUMIF($FV$7:$FV$110,$DK16,GC$7:GC$110)*$EC16*$GG$5+SUMIF($GJ$7:$GJ$110,$DK16,GQ$7:GQ$110)*$ED16*$GU$5 -> 1864.439 | DR16: =SUMIF($EF$7:$EF$110,$DK16,EN$7:EN$110)*$DZ16*$EQ$5+SUMIF($ET$7:$ET$110,$DK16,FB$7:FB$110)*$EA16*$FE$5+SUMIF($FH$7:$FH$110,$DK16,FP$7:FP$110)*$EB16*$FS$5+SUMIF($FV$7:$FV$110,$DK16,GD$7:GD$110)*$EC16*$GG$5+SUMIF($GJ$7:$GJ$110,$DK16,GR$7:GR$110)*$ED16*$GU$5 -> 320.1979 | DS16: =SUMIF($EF$7:$EF$110,$DK16,EO$7:EO$110)*$DZ16*$EQ$5+SUMIF($ET$7:$ET$110,$DK16,FC$7:FC$110)*$EA16*$FE$5+SUMIF($FH$7:$FH$110,$DK16,FQ$7:FQ$110)*$EB16*$FS$5+SUMIF($FV$7:$FV$110,$DK16,GE$7:GE$110)*$EC16*$GG$5+SUMIF($GJ$7:$GJ$110,$DK16,GS$7:GS$110)*$ED16*$GU$5 -> 251.9096 | ... DW16: =SUMIF($EF$7:$EF$110,$DK16,ES$7:ES$110)*$DZ16*$EQ$5+SUMIF($ET$7:$ET$110,$DK16,FG$7:FG$110)*$EA16*$FE$5+SUMIF($FH$7:$FH$110,$DK16,FU$7:FU$110)*$EB16*$FS$5+SUMIF($FV$7:$FV$110,$DK16,GI$7:GI$110)*$EC16*$GG$5+SUMIF($GJ$7:$GJ$110,$DK16,GW$7:GW$110)*$ED16*$GU$5 -> 3307.505 | DY16: abean | EB16: 1 | EF16: abean | EG16: abean | ET16: abean | EU16: abean | FH16: abean | FI16: abean | FJ16: 47333.9 | FK16: 35928.07 | FL16: 3218.175 | FM16: 1192.562 | FN16: 1162.295 | FO16: 1864.439 | FP16: 320.1979 | FQ16: 251.9096 | FR16: 2297.663 | FS16: 2070.586 | FT16: 789.7239 | FU16: 3307.505 | FV16: abean | FW16: abean | GJ16: abean | GK16: abean
C17: apeas | D17: =IF(SUM($S17:$AD17),S17/SUM($S17:$AD17),0) -> 0.47919011 | E17: =IF(SUM($S17:$AD17),T17/SUM($S17:$AD17),0) -> 0.3588048 | F17: =IF(SUM($S17:$AD17),U17/SUM($S17:$AD17),0) -> 0.029643078 | G17: =IF(SUM($S17:$AD17),V17/SUM($S17:$AD17),0) -> 0.011400722 | H17: =IF(SUM($S17:$AD17),W17/SUM($S17:$AD17),0) -> 0.010822825 | I17: =IF(SUM($S17:$AD17),X17/SUM($S17:$AD17),0) -> 0.016164162 | J17: =IF(SUM($S17:$AD17),Y17/SUM($S17:$AD17),0) -> 0.0054678963 | K17: =IF(SUM($S17:$AD17),Z17/SUM($S17:$AD17),0) -> 0.0036284212 | ... O17: =IF(SUM($S17:$AD17),AD17/SUM($S17:$AD17),0) -> 0.028753901 | P17: =SUM(D17:O17) -> 1 | R17: apeas | S17: =IF(SUM($AR17:$AU17),$AK17*AR17/SUM($AR17:$AU17),0) -> 0.47919011 | T17: =IF(SUM($AR17:$AU17),$AK17*AS17/SUM($AR17:$AU17),0) -> 0.3588048 | U17: =IF(SUM($AR17:$AU17),$AK17*AT17/SUM($AR17:$AU17),0) -> 0.029643078 | V17: =IF(SUM($AR17:$AU17),$AK17*AU17/SUM($AR17:$AU17),0) -> 0.011400722 | W17: =IF(SUM($AV17:$AY17),$AL17*AV17/SUM($AV17:$AY17),0) -> 0.010822825 | X17: =IF(SUM($AV17:$AY17),$AL17*AW17/SUM($AV17:$AY17),0) -> 0.016164162 | Y17: =IF(SUM($AV17:$AY17),$AL17*AX17/SUM($AV17:$AY17),0) -> 0.0054678963 | Z17: =IF(SUM($AV17:$AY17),$AL17*AY17/SUM($AV17:$AY17),0) -> 0.0036284212 | AA17: =IF(SUM($AZ17:$BC17),(1-$AL17-$AK17)*AZ17/SUM($AZ17:$BC17),0) -> 0.025906442 | AB17: =IF(SUM($AZ17:$BC17),(1-$AL17-$AK17)*BA17/SUM($AZ17:$BC17),0) -> 0.023818811 | AC17: =IF(SUM($AZ17:$BC17),(1-$AL17-$AK17)*BB17/SUM($AZ17:$BC17),0) -> 0.0063988321 | AD17: =IF(SUM($AZ17:$BC17),(1-$AL17-$AK17)*BC17/SUM($AZ17:$BC17),0) -> 0.028753901 | AE17: =S17+W17+AA17 -> 0.51591937 | AF17: =T17+X17+AB17 -> 0.39878778 | AG17: =U17+Y17+AC17 -> 0.041509806 | AH17: =V17+Z17+AD17 -> 0.043783044 | AI17: =IF(SUM($DL17:$DW17),SUM(DL17:DO17)/SUM($DL17:$DW17),0) -> 0 | AJ17: =IF(SUM($DL17:$DW17),SUM(DP17:DS17)/SUM($DL17:$DW17),0) -> 0 | AK17: =AK16 -> 0.87903871 | AL17: =AL16 -> 0.036083305 | AM17: =1-SUM(AK17:AL17) -> 0.084877986 | AN17: 1 | AO17: 1 | AQ17: apeas | AR17: =IF(SUM($BT17:$CE17),BT17/SUM($BT17:$CE17),0) -> 0.47836062 | AS17: =IF(SUM($BT17:$CE17),BU17/SUM($BT17:$CE17),0) -> 0.3581837 | AT17: =IF(SUM($BT17:$CE17),BV17/SUM($BT17:$CE17),0) -> 0.029591765 | AU17: =IF(SUM($BT17:$CE17),BW17/SUM($BT17:$CE17),0) -> 0.011380987 | AV17: =IF(SUM($BT17:$CE17),BX17/SUM($BT17:$CE17),0) -> 0.01375094 | AW17: =IF(SUM($BT17:$CE17),BY17/SUM($BT17:$CE17),0) -> 0.020537377 | AX17: =IF(SUM($BT17:$CE17),BZ17/SUM($BT17:$CE17),0) -> 0.0069472358 | AY17: =IF(SUM($BT17:$CE17),CA17/SUM($BT17:$CE17),0) -> 0.0046100907 | ... BC17: =IF(SUM($BT17:$CE17),CE17/SUM($BT17:$CE17),0) -> 0.025962221 | BE17: apeas | BF17: 1 | BG17: 1 | BH17: 1 | BI17: 1 | BJ17: 1 | BK17: 1 | BL17: 1 | BM17: 1 | BN17: 1 | BO17: 1 | BP17: 1 | BQ17: 1 | BS17: apeas | BT17: =BF17*CI17 -> 71004.98 | BU17: =BG17*CJ17 -> 53166.64 | BV17: =BH17*CK17 -> 4392.424 | BW17: =BI17*CL17 -> 1689.3254 | BX17: =BJ17*CM17 -> 2041.1071 | BY17: =BK17*CN17 -> 3048.445 | BZ17: =BL17*CO17 -> 1031.206 | CA17: =BM17*CP17 -> 684.2942 | ... CE17: =BQ17*CT17 -> 3853.6763 | CG17: =DJ17 -> abean | CH17: apeas | CI17: =SUMIF($CV$7:$CV$110,$CG17,CW$7:CW$110) -> 71004.98 | CJ17: =SUMIF($CV$7:$CV$110,$CG17,CX$7:CX$110) -> 53166.64 | CK17: =SUMIF($CV$7:$CV$110,$CG17,CY$7:CY$110) -> 4392.424 | CL17: =SUMIF($CV$7:$CV$110,$CG17,CZ$7:CZ$110) -> 1689.3254 | CM17: =SUMIF($CV$7:$CV$110,$CG17,DA$7:DA$110) -> 2041.1071 | CN17: =SUMIF($CV$7:$CV$110,$CG17,DB$7:DB$110) -> 3048.445 | CO17: =SUMIF($CV$7:$CV$110,$CG17,DC$7:DC$110) -> 1031.206 | CP17: =SUMIF($CV$7:$CV$110,$CG17,DD$7:DD$110) -> 684.2942 | ... CT17: =SUMIF($CV$7:$CV$110,$CG17,DH$7:DH$110) -> 3853.6763 | CV17: apeas | CW17: =SUMIF($DJ$7:$DJ$110,$CV17,DL$7:DL$110) -> 0 | CX17: =SUMIF($DJ$7:$DJ$110,$CV17,DM$7:DM$110) -> 0 | CY17: =SUMIF($DJ$7:$DJ$110,$CV17,DN$7:DN$110) -> 0 | CZ17: =SUMIF($DJ$7:$DJ$110,$CV17,DO$7:DO$110) -> 0 | DA17: =SUMIF($DJ$7:$DJ$110,$CV17,DP$7:DP$110) -> 0 | DB17: =SUMIF($DJ$7:$DJ$110,$CV17,DQ$7:DQ$110) -> 0 | DC17: =SUMIF($DJ$7:$DJ$110,$CV17,DR$7:DR$110) -> 0 | DD17: =SUMIF($DJ$7:$DJ$110,$CV17,DS$7:DS$110) -> 0 | ... DH17: =SUMIF($DJ$7:$DJ$110,$CV17,DW$7:DW$110) -> 0 | DJ17: abean | DK17: apeas | DL17: =SUMIF($EF$7:$EF$110,$DK17,EH$7:EH$110)*$DZ17*$EQ$5+SUMIF($ET$7:$ET$110,$DK17,EV$7:EV$110)*$EA17*$FE$5+SUMIF($FH$7:$FH$110,$DK17,FJ$7:FJ$110)*$EB17*$FS$5+SUMIF($FV$7:$FV$110,$DK17,FX$7:FX$110)*$EC17*$GG$5+SUMIF($GJ$7:$GJ$110,$DK17,GL$7:GL$110)*$ED17*$GU$5 -> 0 | DM17: =SUMIF($EF$7:$EF$110,$DK17,EI$7:EI$110)*$DZ17*$EQ$5+SUMIF($ET$7:$ET$110,$DK17,EW$7:EW$110)*$EA17*$FE$5+SUMIF($FH$7:$FH$110,$DK17,FK$7:FK$110)*$EB17*$FS$5+SUMIF($FV$7:$FV$110,$DK17,FY$7:FY$110)*$EC17*$GG$5+SUMIF($GJ$7:$GJ$110,$DK17,GM$7:GM$110)*$ED17*$GU$5 -> 0 | DN17: =SUMIF($EF$7:$EF$110,$DK17,EJ$7:EJ$110)*$DZ17*$EQ$5+SUMIF($ET$7:$ET$110,$DK17,EX$7:EX$110)*$EA17*$FE$5+SUMIF($FH$7:$FH$110,$DK17,FL$7:FL$110)*$EB17*$FS$5+SUMIF($FV$7:$FV$110,$DK17,FZ$7:FZ$110)*$EC17*$GG$5+SUMIF($GJ$7:$GJ$110,$DK17,GN$7:GN$110)*$ED17*$GU$5 -> 0 | DO17: =SUMIF($EF$7:$EF$110,$DK17,EK$7:EK$110)*$DZ17*$EQ$5+SUMIF($ET$7:$ET$110,$DK17,EY$7:EY$110)*$EA17*$FE$5+SUMIF($FH$7:$FH$110,$DK17,FM$7:FM$110)*$EB17*$FS$5+SUMIF($FV$7:$FV$110,$DK17,GA$7:GA$110)*$EC17*$GG$5+SUMIF($GJ$7:$GJ$110,$DK17,GO$7:GO$110)*$ED17*$GU$5 -> 0 | DP17: =SUMIF($EF$7:$EF$110,$DK17,EL$7:EL$110)*$DZ17*$EQ$5+SUMIF($ET$7:$ET$110,$DK17,EZ$7:EZ$110)*$EA17*$FE$5+SUMIF($FH$7:$FH$110,$DK17,FN$7:FN$110)*$EB17*$FS$5+SUMIF($FV$7:$FV$110,$DK17,GB$7:GB$110)*$EC17*$GG$5+SUMIF($GJ$7:$GJ$110,$DK17,GP$7:GP$110)*$ED17*$GU$5 -> 0 | DQ17: =SUMIF($EF$7:$EF$110,$DK17,EM$7:EM$110)*$DZ17*$EQ$5+SUMIF($ET$7:$ET$110,$DK17,FA$7:FA$110)*$EA17*$FE$5+SUMIF($FH$7:$FH$110,$DK17,FO$7:FO$110)*$EB17*$FS$5+SUMIF($FV$7:$FV$110,$DK17,GC$7:GC$110)*$EC17*$GG$5+SUMIF($GJ$7:$GJ$110,$DK17,GQ$7:GQ$110)*$ED17*$GU$5 -> 0 | DR17: =SUMIF($EF$7:$EF$110,$DK17,EN$7:EN$110)*$DZ17*$EQ$5+SUMIF($ET$7:$ET$110,$DK17,FB$7:FB$110)*$EA17*$FE$5+SUMIF($FH$7:$FH$110,$DK17,FP$7:FP$110)*$EB17*$FS$5+SUMIF($FV$7:$FV$110,$DK17,GD$7:GD$110)*$EC17*$GG$5+SUMIF($GJ$7:$GJ$110,$DK17,GR$7:GR$110)*$ED17*$GU$5 -> 0 | DS17: =SUMIF($EF$7:$EF$110,$DK17,EO$7:EO$110)*$DZ17*$EQ$5+SUMIF($ET$7:$ET$110,$DK17,FC$7:FC$110)*$EA17*$FE$5+SUMIF($FH$7:$FH$110,$DK17,FQ$7:FQ$110)*$EB17*$FS$5+SUMIF($FV$7:$FV$110,$DK17,GE$7:GE$110)*$EC17*$GG$5+SUMIF($GJ$7:$GJ$110,$DK17,GS$7:GS$110)*$ED17*$GU$5 -> 0 | ... DW17: =SUMIF($EF$7:$EF$110,$DK17,ES$7:ES$110)*$DZ17*$EQ$5+SUMIF($ET$7:$ET$110,$DK17,FG$7:FG$110)*$EA17*$FE$5+SUMIF($FH$7:$FH$110,$DK17,FU$7:FU$110)*$EB17*$FS$5+SUMIF($FV$7:$FV$110,$DK17,GI$7:GI$110)*$EC17*$GG$5+SUMIF($GJ$7:$GJ$110,$DK17,GW$7:GW$110)*$ED17*$GU$5 -> 0 | DY17: apeas | EB17: 1 | EF17: apeas | EG17: apeas | ET17: apeas | EU17: apeas | FH17: apeas | FI17: apeas | FV17: apeas | FW17: apeas | GJ17: apeas | GK17: apeas
C18: avege | D18: =IF(SUM($S18:$AD18),S18/SUM($S18:$AD18),0) -> 0.47666172 | E18: =IF(SUM($S18:$AD18),T18/SUM($S18:$AD18),0) -> 0.35691162 | F18: =IF(SUM($S18:$AD18),U18/SUM($S18:$AD18),0) -> 0.02948667 | G18: =IF(SUM($S18:$AD18),V18/SUM($S18:$AD18),0) -> 0.011340567 | H18: =IF(SUM($S18:$AD18),W18/SUM($S18:$AD18),0) -> 0.019748059 | I18: =IF(SUM($S18:$AD18),X18/SUM($S18:$AD18),0) -> 0.029494225 | J18: =IF(SUM($S18:$AD18),Y18/SUM($S18:$AD18),0) -> 0.0099770938 | K18: =IF(SUM($S18:$AD18),Z18/SUM($S18:$AD18),0) -> 0.006620663 | ... O18: =IF(SUM($S18:$AD18),AD18/SUM($S18:$AD18),0) -> 0.020244537 | P18: =SUM(D18:O18) -> 1 | R18: avege | S18: =IF(SUM($AR18:$AU18),$AK18*AR18/SUM($AR18:$AU18),0) -> 0.47666172 | T18: =IF(SUM($AR18:$AU18),$AK18*AS18/SUM($AR18:$AU18),0) -> 0.35691162 | U18: =IF(SUM($AR18:$AU18),$AK18*AT18/SUM($AR18:$AU18),0) -> 0.02948667 | V18: =IF(SUM($AR18:$AU18),$AK18*AU18/SUM($AR18:$AU18),0) -> 0.011340567 | W18: =IF(SUM($AV18:$AY18),$AL18*AV18/SUM($AV18:$AY18),0) -> 0.019748059 | X18: =IF(SUM($AV18:$AY18),$AL18*AW18/SUM($AV18:$AY18),0) -> 0.029494225 | Y18: =IF(SUM($AV18:$AY18),$AL18*AX18/SUM($AV18:$AY18),0) -> 0.0099770938 | Z18: =IF(SUM($AV18:$AY18),$AL18*AY18/SUM($AV18:$AY18),0) -> 0.006620663 | AA18: =IF(SUM($AZ18:$BC18),(1-$AL18-$AK18)*AZ18/SUM($AZ18:$BC18),0) -> 0.018239748 | AB18: =IF(SUM($AZ18:$BC18),(1-$AL18-$AK18)*BA18/SUM($AZ18:$BC18),0) -> 0.016769926 | AC18: =IF(SUM($AZ18:$BC18),(1-$AL18-$AK18)*BB18/SUM($AZ18:$BC18),0) -> 0.0045051762 | AD18: =IF(SUM($AZ18:$BC18),(1-$AL18-$AK18)*BC18/SUM($AZ18:$BC18),0) -> 0.020244537 | AE18: =S18+W18+AA18 -> 0.51464953 | AF18: =T18+X18+AB18 -> 0.40317577 | AG18: =U18+Y18+AC18 -> 0.04396894 | AH18: =V18+Z18+AD18 -> 0.038205767 | AI18: =IF(SUM($DL18:$DW18),SUM(DL18:DO18)/SUM($DL18:$DW18),0) -> 0.87440057 | AJ18: =IF(SUM($DL18:$DW18),SUM(DP18:DS18)/SUM($DL18:$DW18),0) -> 0.065840041 | AK18: =AI18 -> 0.87440057 | AL18: =AJ18 -> 0.065840041 | AM18: =1-SUM(AK18:AL18) -> 0.059759387 | AN18: 1 | AO18: 1 | AQ18: avege | AR18: =IF(SUM($BT18:$CE18),BT18/SUM($BT18:$CE18),0) -> 0.47836062 | AS18: =IF(SUM($BT18:$CE18),BU18/SUM($BT18:$CE18),0) -> 0.3581837 | AT18: =IF(SUM($BT18:$CE18),BV18/SUM($BT18:$CE18),0) -> 0.029591765 | AU18: =IF(SUM($BT18:$CE18),BW18/SUM($BT18:$CE18),0) -> 0.011380987 | AV18: =IF(SUM($BT18:$CE18),BX18/SUM($BT18:$CE18),0) -> 0.01375094 | AW18: =IF(SUM($BT18:$CE18),BY18/SUM($BT18:$CE18),0) -> 0.020537377 | AX18: =IF(SUM($BT18:$CE18),BZ18/SUM($BT18:$CE18),0) -> 0.0069472358 | AY18: =IF(SUM($BT18:$CE18),CA18/SUM($BT18:$CE18),0) -> 0.0046100907 | ... BC18: =IF(SUM($BT18:$CE18),CE18/SUM($BT18:$CE18),0) -> 0.025962221 | BE18: avege | BF18: 1 | BG18: 1 | BH18: 1 | BI18: 1 | BJ18: 1 | BK18: 1 | BL18: 1 | BM18: 1 | BN18: 1 | BO18: 1 | BP18: 1 | BQ18: 1 | BS18: avege | BT18: =BF18*CI18 -> 71004.98 | BU18: =BG18*CJ18 -> 53166.64 | BV18: =BH18*CK18 -> 4392.424 | BW18: =BI18*CL18 -> 1689.3254 | BX18: =BJ18*CM18 -> 2041.1071 | BY18: =BK18*CN18 -> 3048.445 | BZ18: =BL18*CO18 -> 1031.206 | CA18: =BM18*CP18 -> 684.2942 | ... CE18: =BQ18*CT18 -> 3853.6763 | CG18: =DJ18 -> abean | CH18: avege | CI18: =SUMIF($CV$7:$CV$110,$CG18,CW$7:CW$110) -> 71004.98 | CJ18: =SUMIF($CV$7:$CV$110,$CG18,CX$7:CX$110) -> 53166.64 | CK18: =SUMIF($CV$7:$CV$110,$CG18,CY$7:CY$110) -> 4392.424 | CL18: =SUMIF($CV$7:$CV$110,$CG18,CZ$7:CZ$110) -> 1689.3254 | CM18: =SUMIF($CV$7:$CV$110,$CG18,DA$7:DA$110) -> 2041.1071 | CN18: =SUMIF($CV$7:$CV$110,$CG18,DB$7:DB$110) -> 3048.445 | CO18: =SUMIF($CV$7:$CV$110,$CG18,DC$7:DC$110) -> 1031.206 | CP18: =SUMIF($CV$7:$CV$110,$CG18,DD$7:DD$110) -> 684.2942 | ... CT18: =SUMIF($CV$7:$CV$110,$CG18,DH$7:DH$110) -> 3853.6763 | CV18: avege | CW18: =SUMIF($DJ$7:$DJ$110,$CV18,DL$7:DL$110) -> 0 | CX18: =SUMIF($DJ$7:$DJ$110,$CV18,DM$7:DM$110) -> 0 | CY18: =SUMIF($DJ$7:$DJ$110,$CV18,DN$7:DN$110) -> 0 | CZ18: =SUMIF($DJ$7:$DJ$110,$CV18,DO$7:DO$110) -> 0 | DA18: =SUMIF($DJ$7:$DJ$110,$CV18,DP$7:DP$110) -> 0 | DB18: =SUMIF($DJ$7:$DJ$110,$CV18,DQ$7:DQ$110) -> 0 | DC18: =SUMIF($DJ$7:$DJ$110,$CV18,DR$7:DR$110) -> 0 | DD18: =SUMIF($DJ$7:$DJ$110,$CV18,DS$7:DS$110) -> 0 | ... DH18: =SUMIF($DJ$7:$DJ$110,$CV18,DW$7:DW$110) -> 0 | DJ18: abean | DK18: avege | DL18: =SUMIF($EF$7:$EF$110,$DK18,EH$7:EH$110)*$DZ18*$EQ$5+SUMIF($ET$7:$ET$110,$DK18,EV$7:EV$110)*$EA18*$FE$5+SUMIF($FH$7:$FH$110,$DK18,FJ$7:FJ$110)*$EB18*$FS$5+SUMIF($FV$7:$FV$110,$DK18,FX$7:FX$110)*$EC18*$GG$5+SUMIF($GJ$7:$GJ$110,$DK18,GL$7:GL$110)*$ED18*$GU$5 -> 23671.08 | DM18: =SUMIF($EF$7:$EF$110,$DK18,EI$7:EI$110)*$DZ18*$EQ$5+SUMIF($ET$7:$ET$110,$DK18,EW$7:EW$110)*$EA18*$FE$5+SUMIF($FH$7:$FH$110,$DK18,FK$7:FK$110)*$EB18*$FS$5+SUMIF($FV$7:$FV$110,$DK18,FY$7:FY$110)*$EC18*$GG$5+SUMIF($GJ$7:$GJ$110,$DK18,GM$7:GM$110)*$ED18*$GU$5 -> 17238.57 | DN18: =SUMIF($EF$7:$EF$110,$DK18,EJ$7:EJ$110)*$DZ18*$EQ$5+SUMIF($ET$7:$ET$110,$DK18,EX$7:EX$110)*$EA18*$FE$5+SUMIF($FH$7:$FH$110,$DK18,FL$7:FL$110)*$EB18*$FS$5+SUMIF($FV$7:$FV$110,$DK18,FZ$7:FZ$110)*$EC18*$GG$5+SUMIF($GJ$7:$GJ$110,$DK18,GN$7:GN$110)*$ED18*$GU$5 -> 1174.249 | DO18: =SUMIF($EF$7:$EF$110,$DK18,EK$7:EK$110)*$DZ18*$EQ$5+SUMIF($ET$7:$ET$110,$DK18,EY$7:EY$110)*$EA18*$FE$5+SUMIF($FH$7:$FH$110,$DK18,FM$7:FM$110)*$EB18*$FS$5+SUMIF($FV$7:$FV$110,$DK18,GA$7:GA$110)*$EC18*$GG$5+SUMIF($GJ$7:$GJ$110,$DK18,GO$7:GO$110)*$ED18*$GU$5 -> 496.7634 | DP18: =SUMIF($EF$7:$EF$110,$DK18,EL$7:EL$110)*$DZ18*$EQ$5+SUMIF($ET$7:$ET$110,$DK18,EZ$7:EZ$110)*$EA18*$FE$5+SUMIF($FH$7:$FH$110,$DK18,FN$7:FN$110)*$EB18*$FS$5+SUMIF($FV$7:$FV$110,$DK18,GB$7:GB$110)*$EC18*$GG$5+SUMIF($GJ$7:$GJ$110,$DK18,GP$7:GP$110)*$ED18*$GU$5 -> 878.8121 | DQ18: =SUMIF($EF$7:$EF$110,$DK18,EM$7:EM$110)*$DZ18*$EQ$5+SUMIF($ET$7:$ET$110,$DK18,FA$7:FA$110)*$EA18*$FE$5+SUMIF($FH$7:$FH$110,$DK18,FO$7:FO$110)*$EB18*$FS$5+SUMIF($FV$7:$FV$110,$DK18,GC$7:GC$110)*$EC18*$GG$5+SUMIF($GJ$7:$GJ$110,$DK18,GQ$7:GQ$110)*$ED18*$GU$5 -> 1184.006 | DR18: =SUMIF($EF$7:$EF$110,$DK18,EN$7:EN$110)*$DZ18*$EQ$5+SUMIF($ET$7:$ET$110,$DK18,FB$7:FB$110)*$EA18*$FE$5+SUMIF($FH$7:$FH$110,$DK18,FP$7:FP$110)*$EB18*$FS$5+SUMIF($FV$7:$FV$110,$DK18,GD$7:GD$110)*$EC18*$GG$5+SUMIF($GJ$7:$GJ$110,$DK18,GR$7:GR$110)*$ED18*$GU$5 -> 711.0081 | DS18: =SUMIF($EF$7:$EF$110,$DK18,EO$7:EO$110)*$DZ18*$EQ$5+SUMIF($ET$7:$ET$110,$DK18,FC$7:FC$110)*$EA18*$FE$5+SUMIF($FH$7:$FH$110,$DK18,FQ$7:FQ$110)*$EB18*$FS$5+SUMIF($FV$7:$FV$110,$DK18,GE$7:GE$110)*$EC18*$GG$5+SUMIF($GJ$7:$GJ$110,$DK18,GS$7:GS$110)*$ED18*$GU$5 -> 432.3846 | ... DW18: =SUMIF($EF$7:$EF$110,$DK18,ES$7:ES$110)*$DZ18*$EQ$5+SUMIF($ET$7:$ET$110,$DK18,FG$7:FG$110)*$EA18*$FE$5+SUMIF($FH$7:$FH$110,$DK18,FU$7:FU$110)*$EB18*$FS$5+SUMIF($FV$7:$FV$110,$DK18,GI$7:GI$110)*$EC18*$GG$5+SUMIF($GJ$7:$GJ$110,$DK18,GW$7:GW$110)*$ED18*$GU$5 -> 546.1713 | DY18: avege | EB18: 1 | EF18: avege | EG18: avege | ET18: avege | EU18: avege | FH18: avege | FI18: avege | FJ18: 23671.08 | FK18: 17238.57 | FL18: 1174.249 | FM18: 496.7634 | FN18: 878.8121 | FO18: 1184.006 | FP18: 711.0081 | FQ18: 432.3846 | FR18: 1174.389 | FS18: 1121.676 | FT18: 67.86504 | FU18: 546.1713 | FV18: avege | FW18: avege | GJ18: avege | GK18: avege
C19: abanb | D19: =IF(SUM($S19:$AD19),S19/SUM($S19:$AD19),0) -> 0.48729293 | E19: =IF(SUM($S19:$AD19),T19/SUM($S19:$AD19),0) -> 0.42211105 | F19: =IF(SUM($S19:$AD19),U19/SUM($S19:$AD19),0) -> 0.030421315 | G19: =IF(SUM($S19:$AD19),V19/SUM($S19:$AD19),0) -> 0.013642183 | H19: =IF(SUM($S19:$AD19),W19/SUM($S19:$AD19),0) -> 0.0061847913 | I19: =IF(SUM($S19:$AD19),X19/SUM($S19:$AD19),0) -> 0.013732954 | J19: =IF(SUM($S19:$AD19),Y19/SUM($S19:$AD19),0) -> 0.0017763009 | K19: =IF(SUM($S19:$AD19),Z19/SUM($S19:$AD19),0) -> 0.0013790654 | ... O19: =IF(SUM($S19:$AD19),AD19/SUM($S19:$AD19),0) -> 0.003925093 | P19: =SUM(D19:O19) -> 1 | R19: abanb | S19: =IF(SUM($AR19:$AU19),$AK19*AR19/SUM($AR19:$AU19),0) -> 0.48729293 | T19: =IF(SUM($AR19:$AU19),$AK19*AS19/SUM($AR19:$AU19),0) -> 0.42211105 | U19: =IF(SUM($AR19:$AU19),$AK19*AT19/SUM($AR19:$AU19),0) -> 0.030421315 | V19: =IF(SUM($AR19:$AU19),$AK19*AU19/SUM($AR19:$AU19),0) -> 0.013642183 | W19: =IF(SUM($AV19:$AY19),$AL19*AV19/SUM($AV19:$AY19),0) -> 0.0061847913 | X19: =IF(SUM($AV19:$AY19),$AL19*AW19/SUM($AV19:$AY19),0) -> 0.013732954 | Y19: =IF(SUM($AV19:$AY19),$AL19*AX19/SUM($AV19:$AY19),0) -> 0.0017763009 | Z19: =IF(SUM($AV19:$AY19),$AL19*AY19/SUM($AV19:$AY19),0) -> 0.0013790654 | AA19: =IF(SUM($AZ19:$BC19),(1-$AL19-$AK19)*AZ19/SUM($AZ19:$BC19),0) -> 0.0082535001 | AB19: =IF(SUM($AZ19:$BC19),(1-$AL19-$AK19)*BA19/SUM($AZ19:$BC19),0) -> 0.010362928 | AC19: =IF(SUM($AZ19:$BC19),(1-$AL19-$AK19)*BB19/SUM($AZ19:$BC19),0) -> 0.00091788714 | AD19: =IF(SUM($AZ19:$BC19),(1-$AL19-$AK19)*BC19/SUM($AZ19:$BC19),0) -> 0.003925093 | AE19: =S19+W19+AA19 -> 0.50173122 | AF19: =T19+X19+AB19 -> 0.44620693 | AG19: =U19+Y19+AC19 -> 0.033115503 | AH19: =V19+Z19+AD19 -> 0.018946341 | AI19: =IF(SUM($DL19:$DW19),SUM(DL19:DO19)/SUM($DL19:$DW19),0) -> 0.95346748 | AJ19: =IF(SUM($DL19:$DW19),SUM(DP19:DS19)/SUM($DL19:$DW19),0) -> 0.023073111 | AK19: =AI19 -> 0.95346748 | AL19: =AJ19 -> 0.023073111 | AM19: =1-SUM(AK19:AL19) -> 0.023459409 | AN19: 1 | AO19: 1 | AQ19: abanb | AR19: =IF(SUM($BT19:$CE19),BT19/SUM($BT19:$CE19),0) -> 0.45500847 | AS19: =IF(SUM($BT19:$CE19),BU19/SUM($BT19:$CE19),0) -> 0.39414506 | AT19: =IF(SUM($BT19:$CE19),BV19/SUM($BT19:$CE19),0) -> 0.028405822 | AU19: =IF(SUM($BT19:$CE19),BW19/SUM($BT19:$CE19),0) -> 0.012738351 | AV19: =IF(SUM($BT19:$CE19),BX19/SUM($BT19:$CE19),0) -> 0.011007889 | AW19: =IF(SUM($BT19:$CE19),BY19/SUM($BT19:$CE19),0) -> 0.024442349 | AX19: =IF(SUM($BT19:$CE19),BZ19/SUM($BT19:$CE19),0) -> 0.003161517 | AY19: =IF(SUM($BT19:$CE19),CA19/SUM($BT19:$CE19),0) -> 0.0024545046 | ... BC19: =IF(SUM($BT19:$CE19),CE19/SUM($BT19:$CE19),0) -> 0.011483785 | BE19: abanb | BF19: 1 | BG19: 1 | BH19: 1 | BI19: 1 | BJ19: 1 | BK19: 1 | BL19: 1 | BM19: 1 | BN19: 1 | BO19: 1 | BP19: 1 | BQ19: 1 | BS19: abanb | BT19: =BF19*CI19 -> 44801.074 | BU19: =BG19*CJ19 -> 38808.337 | BV19: =BH19*CK19 -> 2796.8959 | BW19: =BI19*CL19 -> 1254.2444 | BX19: =BJ19*CM19 -> 1083.8595 | BY19: =BK19*CN19 -> 2406.6442 | BZ19: =BL19*CO19 -> 311.28949 | CA19: =BM19*CP19 -> 241.67559 | ... CE19: =BQ19*CT19 -> 1130.7172 | CG19: =DJ19 -> abanb | CH19: abanb | CI19: =SUMIF($CV$7:$CV$110,$CG19,CW$7:CW$110) -> 44801.074 | CJ19: =SUMIF($CV$7:$CV$110,$CG19,CX$7:CX$110) -> 38808.337 | CK19: =SUMIF($CV$7:$CV$110,$CG19,CY$7:CY$110) -> 2796.8959 | CL19: =SUMIF($CV$7:$CV$110,$CG19,CZ$7:CZ$110) -> 1254.2444 | CM19: =SUMIF($CV$7:$CV$110,$CG19,DA$7:DA$110) -> 1083.8595 | CN19: =SUMIF($CV$7:$CV$110,$CG19,DB$7:DB$110) -> 2406.6442 | CO19: =SUMIF($CV$7:$CV$110,$CG19,DC$7:DC$110) -> 311.28949 | CP19: =SUMIF($CV$7:$CV$110,$CG19,DD$7:DD$110) -> 241.67559 | ... CT19: =SUMIF($CV$7:$CV$110,$CG19,DH$7:DH$110) -> 1130.7172 | CV19: abanb | CW19: =SUMIF($DJ$7:$DJ$110,$CV19,DL$7:DL$110) -> 44801.074 | CX19: =SUMIF($DJ$7:$DJ$110,$CV19,DM$7:DM$110) -> 38808.337 | CY19: =SUMIF($DJ$7:$DJ$110,$CV19,DN$7:DN$110) -> 2796.8959 | CZ19: =SUMIF($DJ$7:$DJ$110,$CV19,DO$7:DO$110) -> 1254.2444 | DA19: =SUMIF($DJ$7:$DJ$110,$CV19,DP$7:DP$110) -> 1083.8595 | DB19: =SUMIF($DJ$7:$DJ$110,$CV19,DQ$7:DQ$110) -> 2406.6442 | DC19: =SUMIF($DJ$7:$DJ$110,$CV19,DR$7:DR$110) -> 311.28949 | DD19: =SUMIF($DJ$7:$DJ$110,$CV19,DS$7:DS$110) -> 241.67559 | ... DH19: =SUMIF($DJ$7:$DJ$110,$CV19,DW$7:DW$110) -> 1130.7172 | DJ19: abanb | DK19: abanb | DL19: =SUMIF($EF$7:$EF$110,$DK19,EH$7:EH$110)*$DZ19*$EQ$5+SUMIF($ET$7:$ET$110,$DK19,EV$7:EV$110)*$EA19*$FE$5+SUMIF($FH$7:$FH$110,$DK19,FJ$7:FJ$110)*$EB19*$FS$5+SUMIF($FV$7:$FV$110,$DK19,FX$7:FX$110)*$EC19*$GG$5+SUMIF($GJ$7:$GJ$110,$DK19,GL$7:GL$110)*$ED19*$GU$5 -> 12947.17 | DM19: =SUMIF($EF$7:$EF$110,$DK19,EI$7:EI$110)*$DZ19*$EQ$5+SUMIF($ET$7:$ET$110,$DK19,EW$7:EW$110)*$EA19*$FE$5+SUMIF($FH$7:$FH$110,$DK19,FK$7:FK$110)*$EB19*$FS$5+SUMIF($FV$7:$FV$110,$DK19,FY$7:FY$110)*$EC19*$GG$5+SUMIF($GJ$7:$GJ$110,$DK19,GM$7:GM$110)*$ED19*$GU$5 -> 11119.2 | DN19: =SUMIF($EF$7:$EF$110,$DK19,EJ$7:EJ$110)*$DZ19*$EQ$5+SUMIF($ET$7:$ET$110,$DK19,EX$7:EX$110)*$EA19*$FE$5+SUMIF($FH$7:$FH$110,$DK19,FL$7:FL$110)*$EB19*$FS$5+SUMIF($FV$7:$FV$110,$DK19,FZ$7:FZ$110)*$EC19*$GG$5+SUMIF($GJ$7:$GJ$110,$DK19,GN$7:GN$110)*$ED19*$GU$5 -> 426.6727 | DO19: =SUMIF($EF$7:$EF$110,$DK19,EK$7:EK$110)*$DZ19*$EQ$5+SUMIF($ET$7:$ET$110,$DK19,EY$7:EY$110)*$EA19*$FE$5+SUMIF($FH$7:$FH$110,$DK19,FM$7:FM$110)*$EB19*$FS$5+SUMIF($FV$7:$FV$110,$DK19,GA$7:GA$110)*$EC19*$GG$5+SUMIF($GJ$7:$GJ$110,$DK19,GO$7:GO$110)*$ED19*$GU$5 -> 342.9378 | DP19: =SUMIF($EF$7:$EF$110,$DK19,EL$7:EL$110)*$DZ19*$EQ$5+SUMIF($ET$7:$ET$110,$DK19,EZ$7:EZ$110)*$EA19*$FE$5+SUMIF($FH$7:$FH$110,$DK19,FN$7:FN$110)*$EB19*$FS$5+SUMIF($FV$7:$FV$110,$DK19,GB$7:GB$110)*$EC19*$GG$5+SUMIF($GJ$7:$GJ$110,$DK19,GP$7:GP$110)*$ED19*$GU$5 -> 217.4891 | DQ19: =SUMIF($EF$7:$EF$110,$DK19,EM$7:EM$110)*$DZ19*$EQ$5+SUMIF($ET$7:$ET$110,$DK19,FA$7:FA$110)*$EA19*$FE$5+SUMIF($FH$7:$FH$110,$DK19,FO$7:FO$110)*$EB19*$FS$5+SUMIF($FV$7:$FV$110,$DK19,GC$7:GC$110)*$EC19*$GG$5+SUMIF($GJ$7:$GJ$110,$DK19,GQ$7:GQ$110)*$ED19*$GU$5 -> 314.7396 | DR19: =SUMIF($EF$7:$EF$110,$DK19,EN$7:EN$110)*$DZ19*$EQ$5+SUMIF($ET$7:$ET$110,$DK19,FB$7:FB$110)*$EA19*$FE$5+SUMIF($FH$7:$FH$110,$DK19,FP$7:FP$110)*$EB19*$FS$5+SUMIF($FV$7:$FV$110,$DK19,GD$7:GD$110)*$EC19*$GG$5+SUMIF($GJ$7:$GJ$110,$DK19,GR$7:GR$110)*$ED19*$GU$5 -> 25.99095 | DS19: =SUMIF($EF$7:$EF$110,$DK19,EO$7:EO$110)*$DZ19*$EQ$5+SUMIF($ET$7:$ET$110,$DK19,FC$7:FC$110)*$EA19*$FE$5+SUMIF($FH$7:$FH$110,$DK19,FQ$7:FQ$110)*$EB19*$FS$5+SUMIF($FV$7:$FV$110,$DK19,GE$7:GE$110)*$EC19*$GG$5+SUMIF($GJ$7:$GJ$110,$DK19,GS$7:GS$110)*$ED19*$GU$5 -> 42.7902 | ... DW19: =SUMIF($EF$7:$EF$110,$DK19,ES$7:ES$110)*$DZ19*$EQ$5+SUMIF($ET$7:$ET$110,$DK19,FG$7:FG$110)*$EA19*$FE$5+SUMIF($FH$7:$FH$110,$DK19,FU$7:FU$110)*$EB19*$FS$5+SUMIF($FV$7:$FV$110,$DK19,GI$7:GI$110)*$EC19*$GG$5+SUMIF($GJ$7:$GJ$110,$DK19,GW$7:GW$110)*$ED19*$GU$5 -> 18.35264 | DY19: abanb | EB19: 1 | EF19: abanb | EG19: abanb | ET19: abanb | EU19: abanb | FH19: abanb | FI19: abanb | FJ19: 12947.17 | FK19: 11119.2 | FL19: 426.6727 | FM19: 342.9378 | FN19: 217.4891 | FO19: 314.7396 | FP19: 25.99095 | FQ19: 42.7902 | FR19: 333.7164 | FS19: 259.0031 | FU19: 18.35264 | FV19: abanb | FW19: abanb | GJ19: abanb | GK19: abanb
C20: abanc | D20: =IF(SUM($S20:$AD20),S20/SUM($S20:$AD20),0) -> 0.44033075 | E20: =IF(SUM($S20:$AD20),T20/SUM($S20:$AD20),0) -> 0.38143068 | F20: =IF(SUM($S20:$AD20),U20/SUM($S20:$AD20),0) -> 0.027489503 | G20: =IF(SUM($S20:$AD20),V20/SUM($S20:$AD20),0) -> 0.012327436 | H20: =IF(SUM($S20:$AD20),W20/SUM($S20:$AD20),0) -> 0.015111945 | I20: =IF(SUM($S20:$AD20),X20/SUM($S20:$AD20),0) -> 0.033555158 | J20: =IF(SUM($S20:$AD20),Y20/SUM($S20:$AD20),0) -> 0.0043402211 | K20: =IF(SUM($S20:$AD20),Z20/SUM($S20:$AD20),0) -> 0.0033696142 | ... O20: =IF(SUM($S20:$AD20),AD20/SUM($S20:$AD20),0) -> 0.013727246 | P20: =SUM(D20:O20) -> 1 | R20: abanc | S20: =IF(SUM($AR20:$AU20),$AK20*AR20/SUM($AR20:$AU20),0) -> 0.44033075 | T20: =IF(SUM($AR20:$AU20),$AK20*AS20/SUM($AR20:$AU20),0) -> 0.38143068 | U20: =IF(SUM($AR20:$AU20),$AK20*AT20/SUM($AR20:$AU20),0) -> 0.027489503 | V20: =IF(SUM($AR20:$AU20),$AK20*AU20/SUM($AR20:$AU20),0) -> 0.012327436 | W20: =IF(SUM($AV20:$AY20),$AL20*AV20/SUM($AV20:$AY20),0) -> 0.015111945 | X20: =IF(SUM($AV20:$AY20),$AL20*AW20/SUM($AV20:$AY20),0) -> 0.033555158 | Y20: =IF(SUM($AV20:$AY20),$AL20*AX20/SUM($AV20:$AY20),0) -> 0.0043402211 | Z20: =IF(SUM($AV20:$AY20),$AL20*AY20/SUM($AV20:$AY20),0) -> 0.0033696142 | AA20: =IF(SUM($AZ20:$BC20),(1-$AL20-$AK20)*AZ20/SUM($AZ20:$BC20),0) -> 0.028865004 | AB20: =IF(SUM($AZ20:$BC20),(1-$AL20-$AK20)*BA20/SUM($AZ20:$BC20),0) -> 0.036242317 | AC20: =IF(SUM($AZ20:$BC20),(1-$AL20-$AK20)*BB20/SUM($AZ20:$BC20),0) -> 0.003210131 | AD20: =IF(SUM($AZ20:$BC20),(1-$AL20-$AK20)*BC20/SUM($AZ20:$BC20),0) -> 0.013727246 | AE20: =S20+W20+AA20 -> 0.4843077 | AF20: =T20+X20+AB20 -> 0.45122815 | AG20: =U20+Y20+AC20 -> 0.035039855 | AH20: =V20+Z20+AD20 -> 0.029424296 | AI20: =IF(SUM($DL20:$DW20),SUM(DL20:DO20)/SUM($DL20:$DW20),0) -> 0.86157836 | AJ20: =IF(SUM($DL20:$DW20),SUM(DP20:DS20)/SUM($DL20:$DW20),0) -> 0.056376938 | AK20: =AI20 -> 0.86157836 | AL20: =AJ20 -> 0.056376938 | AM20: =1-SUM(AK20:AL20) -> 0.082044699 | AN20: 1 | AO20: 1 | AQ20: abanc | AR20: =IF(SUM($BT20:$CE20),BT20/SUM($BT20:$CE20),0) -> 0.45500847 | AS20: =IF(SUM($BT20:$CE20),BU20/SUM($BT20:$CE20),0) -> 0.39414506 | AT20: =IF(SUM($BT20:$CE20),BV20/SUM($BT20:$CE20),0) -> 0.028405822 | AU20: =IF(SUM($BT20:$CE20),BW20/SUM($BT20:$CE20),0) -> 0.012738351 | AV20: =IF(SUM($BT20:$CE20),BX20/SUM($BT20:$CE20),0) -> 0.011007889 | AW20: =IF(SUM($BT20:$CE20),BY20/SUM($BT20:$CE20),0) -> 0.024442349 | AX20: =IF(SUM($BT20:$CE20),BZ20/SUM($BT20:$CE20),0) -> 0.003161517 | AY20: =IF(SUM($BT20:$CE20),CA20/SUM($BT20:$CE20),0) -> 0.0024545046 | ... BC20: =IF(SUM($BT20:$CE20),CE20/SUM($BT20:$CE20),0) -> 0.011483785 | BE20: abanc | BF20: 1 | BG20: 1 | BH20: 1 | BI20: 1 | BJ20: 1 | BK20: 1 | BL20: 1 | BM20: 1 | BN20: 1 | BO20: 1 | BP20: 1 | BQ20: 1 | BS20: abanc | BT20: =BF20*CI20 -> 44801.074 | BU20: =BG20*CJ20 -> 38808.337 | BV20: =BH20*CK20 -> 2796.8959 | BW20: =BI20*CL20 -> 1254.2444 | BX20: =BJ20*CM20 -> 1083.8595 | BY20: =BK20*CN20 -> 2406.6442 | BZ20: =BL20*CO20 -> 311.28949 | CA20: =BM20*CP20 -> 241.67559 | ... CE20: =BQ20*CT20 -> 1130.7172 | CG20: =DJ20 -> abanb | CH20: abanc | CI20: =SUMIF($CV$7:$CV$110,$CG20,CW$7:CW$110) -> 44801.074 | CJ20: =SUMIF($CV$7:$CV$110,$CG20,CX$7:CX$110) -> 38808.337 | CK20: =SUMIF($CV$7:$CV$110,$CG20,CY$7:CY$110) -> 2796.8959 | CL20: =SUMIF($CV$7:$CV$110,$CG20,CZ$7:CZ$110) -> 1254.2444 | CM20: =SUMIF($CV$7:$CV$110,$CG20,DA$7:DA$110) -> 1083.8595 | CN20: =SUMIF($CV$7:$CV$110,$CG20,DB$7:DB$110) -> 2406.6442 | CO20: =SUMIF($CV$7:$CV$110,$CG20,DC$7:DC$110) -> 311.28949 | CP20: =SUMIF($CV$7:$CV$110,$CG20,DD$7:DD$110) -> 241.67559 | ... CT20: =SUMIF($CV$7:$CV$110,$CG20,DH$7:DH$110) -> 1130.7172 | CV20: abanc | CW20: =SUMIF($DJ$7:$DJ$110,$CV20,DL$7:DL$110) -> 0 | CX20: =SUMIF($DJ$7:$DJ$110,$CV20,DM$7:DM$110) -> 0 | CY20: =SUMIF($DJ$7:$DJ$110,$CV20,DN$7:DN$110) -> 0 | CZ20: =SUMIF($DJ$7:$DJ$110,$CV20,DO$7:DO$110) -> 0 | DA20: =SUMIF($DJ$7:$DJ$110,$CV20,DP$7:DP$110) -> 0 | DB20: =SUMIF($DJ$7:$DJ$110,$CV20,DQ$7:DQ$110) -> 0 | DC20: =SUMIF($DJ$7:$DJ$110,$CV20,DR$7:DR$110) -> 0 | DD20: =SUMIF($DJ$7:$DJ$110,$CV20,DS$7:DS$110) -> 0 | ... DH20: =SUMIF($DJ$7:$DJ$110,$CV20,DW$7:DW$110) -> 0 | DJ20: abanb | DK20: abanc | DL20: =SUMIF($EF$7:$EF$110,$DK20,EH$7:EH$110)*$DZ20*$EQ$5+SUMIF($ET$7:$ET$110,$DK20,EV$7:EV$110)*$EA20*$FE$5+SUMIF($FH$7:$FH$110,$DK20,FJ$7:FJ$110)*$EB20*$FS$5+SUMIF($FV$7:$FV$110,$DK20,FX$7:FX$110)*$EC20*$GG$5+SUMIF($GJ$7:$GJ$110,$DK20,GL$7:GL$110)*$ED20*$GU$5 -> 15978.58 | DM20: =SUMIF($EF$7:$EF$110,$DK20,EI$7:EI$110)*$DZ20*$EQ$5+SUMIF($ET$7:$ET$110,$DK20,EW$7:EW$110)*$EA20*$FE$5+SUMIF($FH$7:$FH$110,$DK20,FK$7:FK$110)*$EB20*$FS$5+SUMIF($FV$7:$FV$110,$DK20,FY$7:FY$110)*$EC20*$GG$5+SUMIF($GJ$7:$GJ$110,$DK20,GM$7:GM$110)*$ED20*$GU$5 -> 14227.8 | DN20: =SUMIF($EF$7:$EF$110,$DK20,EJ$7:EJ$110)*$DZ20*$EQ$5+SUMIF($ET$7:$ET$110,$DK20,EX$7:EX$110)*$EA20*$FE$5+SUMIF($FH$7:$FH$110,$DK20,FL$7:FL$110)*$EB20*$FS$5+SUMIF($FV$7:$FV$110,$DK20,FZ$7:FZ$110)*$EC20*$GG$5+SUMIF($GJ$7:$GJ$110,$DK20,GN$7:GN$110)*$ED20*$GU$5 -> 1437.157 | DO20: =SUMIF($EF$7:$EF$110,$DK20,EK$7:EK$110)*$DZ20*$EQ$5+SUMIF($ET$7:$ET$110,$DK20,EY$7:EY$110)*$EA20*$FE$5+SUMIF($FH$7:$FH$110,$DK20,FM$7:FM$110)*$EB20*$FS$5+SUMIF($FV$7:$FV$110,$DK20,GA$7:GA$110)*$EC20*$GG$5+SUMIF($GJ$7:$GJ$110,$DK20,GO$7:GO$110)*$ED20*$GU$5 -> 511.4375 | DP20: =SUMIF($EF$7:$EF$110,$DK20,EL$7:EL$110)*$DZ20*$EQ$5+SUMIF($ET$7:$ET$110,$DK20,EZ$7:EZ$110)*$EA20*$FE$5+SUMIF($FH$7:$FH$110,$DK20,FN$7:FN$110)*$EB20*$FS$5+SUMIF($FV$7:$FV$110,$DK20,GB$7:GB$110)*$EC20*$GG$5+SUMIF($GJ$7:$GJ$110,$DK20,GP$7:GP$110)*$ED20*$GU$5 -> 396.0234 | DQ20: =SUMIF($EF$7:$EF$110,$DK20,EM$7:EM$110)*$DZ20*$EQ$5+SUMIF($ET$7:$ET$110,$DK20,FA$7:FA$110)*$EA20*$FE$5+SUMIF($FH$7:$FH$110,$DK20,FO$7:FO$110)*$EB20*$FS$5+SUMIF($FV$7:$FV$110,$DK20,GC$7:GC$110)*$EC20*$GG$5+SUMIF($GJ$7:$GJ$110,$DK20,GQ$7:GQ$110)*$ED20*$GU$5 -> 1485.369 | DR20: =SUMIF($EF$7:$EF$110,$DK20,EN$7:EN$110)*$DZ20*$EQ$5+SUMIF($ET$7:$ET$110,$DK20,FB$7:FB$110)*$EA20*$FE$5+SUMIF($FH$7:$FH$110,$DK20,FP$7:FP$110)*$EB20*$FS$5+SUMIF($FV$7:$FV$110,$DK20,GD$7:GD$110)*$EC20*$GG$5+SUMIF($GJ$7:$GJ$110,$DK20,GR$7:GR$110)*$ED20*$GU$5 -> 129.5771 | DS20: =SUMIF($EF$7:$EF$110,$DK20,EO$7:EO$110)*$DZ20*$EQ$5+SUMIF($ET$7:$ET$110,$DK20,FC$7:FC$110)*$EA20*$FE$5+SUMIF($FH$7:$FH$110,$DK20,FQ$7:FQ$110)*$EB20*$FS$5+SUMIF($FV$7:$FV$110,$DK20,GE$7:GE$110)*$EC20*$GG$5+SUMIF($GJ$7:$GJ$110,$DK20,GS$7:GS$110)*$ED20*$GU$5 -> 93.07476 | ... DW20: =SUMIF($EF$7:$EF$110,$DK20,ES$7:ES$110)*$DZ20*$EQ$5+SUMIF($ET$7:$ET$110,$DK20,FG$7:FG$110)*$EA20*$FE$5+SUMIF($FH$7:$FH$110,$DK20,FU$7:FU$110)*$EB20*$FS$5+SUMIF($FV$7:$FV$110,$DK20,GI$7:GI$110)*$EC20*$GG$5+SUMIF($GJ$7:$GJ$110,$DK20,GW$7:GW$110)*$ED20*$GU$5 -> 528.1392 | DY20: abanc | EB20: 1 | EF20: abanc | EG20: abanc | ET20: abanc | EU20: abanc | FH20: abanc | FI20: abanc | FJ20: 15978.58 | FK20: 14227.8 | FL20: 1437.157 | FM20: 511.4375 | FN20: 396.0234 | FO20: 1485.369 | FP20: 129.5771 | FQ20: 93.07476 | FR20: 718.6446 | FS20: 1700.704 | FT20: 114.5032 | FU20: 528.1392 | FV20: abanc | FW20: abanc | GJ20: abanc | GK20: abanc
C21: abans | D21: =IF(SUM($S21:$AD21),S21/SUM($S21:$AD21),0) -> 0.42768851 | E21: =IF(SUM($S21:$AD21),T21/SUM($S21:$AD21),0) -> 0.37047951 | F21: =IF(SUM($S21:$AD21),U21/SUM($S21:$AD21),0) -> 0.026700258 | G21: =IF(SUM($S21:$AD21),V21/SUM($S21:$AD21),0) -> 0.011973506 | H21: =IF(SUM($S21:$AD21),W21/SUM($S21:$AD21),0) -> 0.010718163 | I21: =IF(SUM($S21:$AD21),X21/SUM($S21:$AD21),0) -> 0.023799031 | J21: =IF(SUM($S21:$AD21),Y21/SUM($S21:$AD21),0) -> 0.0030783064 | K21: =IF(SUM($S21:$AD21),Z21/SUM($S21:$AD21),0) -> 0.0023899024 | ... O21: =IF(SUM($S21:$AD21),AD21/SUM($S21:$AD21),0) -> 0.020608564 | P21: =SUM(D21:O21) -> 1 | R21: abans | S21: =IF(SUM($AR21:$AU21),$AK21*AR21/SUM($AR21:$AU21),0) -> 0.42768851 | T21: =IF(SUM($AR21:$AU21),$AK21*AS21/SUM($AR21:$AU21),0) -> 0.37047951 | U21: =IF(SUM($AR21:$AU21),$AK21*AT21/SUM($AR21:$AU21),0) -> 0.026700258 | V21: =IF(SUM($AR21:$AU21),$AK21*AU21/SUM($AR21:$AU21),0) -> 0.011973506 | W21: =IF(SUM($AV21:$AY21),$AL21*AV21/SUM($AV21:$AY21),0) -> 0.010718163 | X21: =IF(SUM($AV21:$AY21),$AL21*AW21/SUM($AV21:$AY21),0) -> 0.023799031 | Y21: =IF(SUM($AV21:$AY21),$AL21*AX21/SUM($AV21:$AY21),0) -> 0.0030783064 | Z21: =IF(SUM($AV21:$AY21),$AL21*AY21/SUM($AV21:$AY21),0) -> 0.0023899024 | AA21: =IF(SUM($AZ21:$BC21),(1-$AL21-$AK21)*AZ21/SUM($AZ21:$BC21),0) -> 0.043334715 | AB21: =IF(SUM($AZ21:$BC21),(1-$AL21-$AK21)*BA21/SUM($AZ21:$BC21),0) -> 0.054410194 | AC21: =IF(SUM($AZ21:$BC21),(1-$AL21-$AK21)*BB21/SUM($AZ21:$BC21),0) -> 0.0048193345 | AD21: =IF(SUM($AZ21:$BC21),(1-$AL21-$AK21)*BC21/SUM($AZ21:$BC21),0) -> 0.020608564 | AE21: =S21+W21+AA21 -> 0.48174139 | AF21: =T21+X21+AB21 -> 0.44868874 | AG21: =U21+Y21+AC21 -> 0.034597899 | AH21: =V21+Z21+AD21 -> 0.034971972 | AI21: =IF(SUM($DL21:$DW21),SUM(DL21:DO21)/SUM($DL21:$DW21),0) -> 0.83684179 | AJ21: =IF(SUM($DL21:$DW21),SUM(DP21:DS21)/SUM($DL21:$DW21),0) -> 0.039985403 | AK21: =AI21 -> 0.83684179 | AL21: =AJ21 -> 0.039985403 | AM21: =1-SUM(AK21:AL21) -> 0.12317281 | AN21: 1 | AO21: 1 | AQ21: abans | AR21: =IF(SUM($BT21:$CE21),BT21/SUM($BT21:$CE21),0) -> 0.45500847 | AS21: =IF(SUM($BT21:$CE21),BU21/SUM($BT21:$CE21),0) -> 0.39414506 | AT21: =IF(SUM($BT21:$CE21),BV21/SUM($BT21:$CE21),0) -> 0.028405822 | AU21: =IF(SUM($BT21:$CE21),BW21/SUM($BT21:$CE21),0) -> 0.012738351 | AV21: =IF(SUM($BT21:$CE21),BX21/SUM($BT21:$CE21),0) -> 0.011007889 | AW21: =IF(SUM($BT21:$CE21),BY21/SUM($BT21:$CE21),0) -> 0.024442349 | AX21: =IF(SUM($BT21:$CE21),BZ21/SUM($BT21:$CE21),0) -> 0.003161517 | AY21: =IF(SUM($BT21:$CE21),CA21/SUM($BT21:$CE21),0) -> 0.0024545046 | ... BC21: =IF(SUM($BT21:$CE21),CE21/SUM($BT21:$CE21),0) -> 0.011483785 | BE21: abans | BF21: 1 | BG21: 1 | BH21: 1 | BI21: 1 | BJ21: 1 | BK21: 1 | BL21: 1 | BM21: 1 | BN21: 1 | BO21: 1 | BP21: 1 | BQ21: 1 | BS21: abans | BT21: =BF21*CI21 -> 44801.074 | BU21: =BG21*CJ21 -> 38808.337 | BV21: =BH21*CK21 -> 2796.8959 | BW21: =BI21*CL21 -> 1254.2444 | BX21: =BJ21*CM21 -> 1083.8595 | BY21: =BK21*CN21 -> 2406.6442 | BZ21: =BL21*CO21 -> 311.28949 | CA21: =BM21*CP21 -> 241.67559 | ... CE21: =BQ21*CT21 -> 1130.7172 | CG21: =DJ21 -> abanb | CH21: abans | CI21: =SUMIF($CV$7:$CV$110,$CG21,CW$7:CW$110) -> 44801.074 | CJ21: =SUMIF($CV$7:$CV$110,$CG21,CX$7:CX$110) -> 38808.337 | CK21: =SUMIF($CV$7:$CV$110,$CG21,CY$7:CY$110) -> 2796.8959 | CL21: =SUMIF($CV$7:$CV$110,$CG21,CZ$7:CZ$110) -> 1254.2444 | CM21: =SUMIF($CV$7:$CV$110,$CG21,DA$7:DA$110) -> 1083.8595 | CN21: =SUMIF($CV$7:$CV$110,$CG21,DB$7:DB$110) -> 2406.6442 | CO21: =SUMIF($CV$7:$CV$110,$CG21,DC$7:DC$110) -> 311.28949 | CP21: =SUMIF($CV$7:$CV$110,$CG21,DD$7:DD$110) -> 241.67559 | ... CT21: =SUMIF($CV$7:$CV$110,$CG21,DH$7:DH$110) -> 1130.7172 | CV21: abans | CW21: =SUMIF($DJ$7:$DJ$110,$CV21,DL$7:DL$110) -> 0 | CX21: =SUMIF($DJ$7:$DJ$110,$CV21,DM$7:DM$110) -> 0 | CY21: =SUMIF($DJ$7:$DJ$110,$CV21,DN$7:DN$110) -> 0 | CZ21: =SUMIF($DJ$7:$DJ$110,$CV21,DO$7:DO$110) -> 0 | DA21: =SUMIF($DJ$7:$DJ$110,$CV21,DP$7:DP$110) -> 0 | DB21: =SUMIF($DJ$7:$DJ$110,$CV21,DQ$7:DQ$110) -> 0 | DC21: =SUMIF($DJ$7:$DJ$110,$CV21,DR$7:DR$110) -> 0 | DD21: =SUMIF($DJ$7:$DJ$110,$CV21,DS$7:DS$110) -> 0 | ... DH21: =SUMIF($DJ$7:$DJ$110,$CV21,DW$7:DW$110) -> 0 | DJ21: abanb | DK21: abans | DL21: =SUMIF($EF$7:$EF$110,$DK21,EH$7:EH$110)*$DZ21*$EQ$5+SUMIF($ET$7:$ET$110,$DK21,EV$7:EV$110)*$EA21*$FE$5+SUMIF($FH$7:$FH$110,$DK21,FJ$7:FJ$110)*$EB21*$FS$5+SUMIF($FV$7:$FV$110,$DK21,FX$7:FX$110)*$EC21*$GG$5+SUMIF($GJ$7:$GJ$110,$DK21,GL$7:GL$110)*$ED21*$GU$5 -> 4455.424 | DM21: =SUMIF($EF$7:$EF$110,$DK21,EI$7:EI$110)*$DZ21*$EQ$5+SUMIF($ET$7:$ET$110,$DK21,EW$7:EW$110)*$EA21*$FE$5+SUMIF($FH$7:$FH$110,$DK21,FK$7:FK$110)*$EB21*$FS$5+SUMIF($FV$7:$FV$110,$DK21,FY$7:FY$110)*$EC21*$GG$5+SUMIF($GJ$7:$GJ$110,$DK21,GM$7:GM$110)*$ED21*$GU$5 -> 4983.487 | DN21: =SUMIF($EF$7:$EF$110,$DK21,EJ$7:EJ$110)*$DZ21*$EQ$5+SUMIF($ET$7:$ET$110,$DK21,EX$7:EX$110)*$EA21*$FE$5+SUMIF($FH$7:$FH$110,$DK21,FL$7:FL$110)*$EB21*$FS$5+SUMIF($FV$7:$FV$110,$DK21,FZ$7:FZ$110)*$EC21*$GG$5+SUMIF($GJ$7:$GJ$110,$DK21,GN$7:GN$110)*$ED21*$GU$5 -> 394.6572 | DO21: =SUMIF($EF$7:$EF$110,$DK21,EK$7:EK$110)*$DZ21*$EQ$5+SUMIF($ET$7:$ET$110,$DK21,EY$7:EY$110)*$EA21*$FE$5+SUMIF($FH$7:$FH$110,$DK21,FM$7:FM$110)*$EB21*$FS$5+SUMIF($FV$7:$FV$110,$DK21,GA$7:GA$110)*$EC21*$GG$5+SUMIF($GJ$7:$GJ$110,$DK21,GO$7:GO$110)*$ED21*$GU$5 -> 245.5264 | DP21: =SUMIF($EF$7:$EF$110,$DK21,EL$7:EL$110)*$DZ21*$EQ$5+SUMIF($ET$7:$ET$110,$DK21,EZ$7:EZ$110)*$EA21*$FE$5+SUMIF($FH$7:$FH$110,$DK21,FN$7:FN$110)*$EB21*$FS$5+SUMIF($FV$7:$FV$110,$DK21,GB$7:GB$110)*$EC21*$GG$5+SUMIF($GJ$7:$GJ$110,$DK21,GP$7:GP$110)*$ED21*$GU$5 -> 92.17737 | DQ21: =SUMIF($EF$7:$EF$110,$DK21,EM$7:EM$110)*$DZ21*$EQ$5+SUMIF($ET$7:$ET$110,$DK21,FA$7:FA$110)*$EA21*$FE$5+SUMIF($FH$7:$FH$110,$DK21,FO$7:FO$110)*$EB21*$FS$5+SUMIF($FV$7:$FV$110,$DK21,GC$7:GC$110)*$EC21*$GG$5+SUMIF($GJ$7:$GJ$110,$DK21,GQ$7:GQ$110)*$ED21*$GU$5 -> 234.2089 | DR21: =SUMIF($EF$7:$EF$110,$DK21,EN$7:EN$110)*$DZ21*$EQ$5+SUMIF($ET$7:$ET$110,$DK21,FB$7:FB$110)*$EA21*$FE$5+SUMIF($FH$7:$FH$110,$DK21,FP$7:FP$110)*$EB21*$FS$5+SUMIF($FV$7:$FV$110,$DK21,GD$7:GD$110)*$EC21*$GG$5+SUMIF($GJ$7:$GJ$110,$DK21,GR$7:GR$110)*$ED21*$GU$5 -> 93.96724 | DS21: =SUMIF($EF$7:$EF$110,$DK21,EO$7:EO$110)*$DZ21*$EQ$5+SUMIF($ET$7:$ET$110,$DK21,FC$7:FC$110)*$EA21*$FE$5+SUMIF($FH$7:$FH$110,$DK21,FQ$7:FQ$110)*$EB21*$FS$5+SUMIF($FV$7:$FV$110,$DK21,GE$7:GE$110)*$EC21*$GG$5+SUMIF($GJ$7:$GJ$110,$DK21,GS$7:GS$110)*$ED21*$GU$5 -> 61.2389 | ... DW21: =SUMIF($EF$7:$EF$110,$DK21,ES$7:ES$110)*$DZ21*$EQ$5+SUMIF($ET$7:$ET$110,$DK21,FG$7:FG$110)*$EA21*$FE$5+SUMIF($FH$7:$FH$110,$DK21,FU$7:FU$110)*$EB21*$FS$5+SUMIF($FV$7:$FV$110,$DK21,GI$7:GI$110)*$EC21*$GG$5+SUMIF($GJ$7:$GJ$110,$DK21,GW$7:GW$110)*$ED21*$GU$5 -> 192.0036 | DY21: abans | EB21: 1 | EF21: abans | EG21: abans | ET21: abans | EU21: abans | FH21: abans | FI21: abans | FJ21: 4455.424 | FK21: 4983.487 | FL21: 394.6572 | FM21: 245.5264 | FN21: 92.17737 | FO21: 234.2089 | FP21: 93.96724 | FQ21: 61.2389 | FR21: 680.6524 | FS21: 586.8489 | FT21: 24.01372 | FU21: 192.0036 | FV21: abans | FW21: abans | GJ21: abans | GK21: abans
C22: afrui | D22: =IF(SUM($S22:$AD22),S22/SUM($S22:$AD22),0) -> 0.45656547 | E22: =IF(SUM($S22:$AD22),T22/SUM($S22:$AD22),0) -> 0.39549379 | F22: =IF(SUM($S22:$AD22),U22/SUM($S22:$AD22),0) -> 0.028503024 | G22: =IF(SUM($S22:$AD22),V22/SUM($S22:$AD22),0) -> 0.012781941 | H22: =IF(SUM($S22:$AD22),W22/SUM($S22:$AD22),0) -> 0.0099646379 | I22: =IF(SUM($S22:$AD22),X22/SUM($S22:$AD22),0) -> 0.022125874 | J22: =IF(SUM($S22:$AD22),Y22/SUM($S22:$AD22),0) -> 0.0028618904 | K22: =IF(SUM($S22:$AD22),Z22/SUM($S22:$AD22),0) -> 0.0022218837 | ... O22: =IF(SUM($S22:$AD22),AD22/SUM($S22:$AD22),0) -> 0.011625241 | P22: =SUM(D22:O22) -> 1 | R22: afrui | S22: =IF(SUM($AR22:$AU22),$AK22*AR22/SUM($AR22:$AU22),0) -> 0.45656547 | T22: =IF(SUM($AR22:$AU22),$AK22*AS22/SUM($AR22:$AU22),0) -> 0.39549379 | U22: =IF(SUM($AR22:$AU22),$AK22*AT22/SUM($AR22:$AU22),0) -> 0.028503024 | V22: =IF(SUM($AR22:$AU22),$AK22*AU22/SUM($AR22:$AU22),0) -> 0.012781941 | W22: =IF(SUM($AV22:$AY22),$AL22*AV22/SUM($AV22:$AY22),0) -> 0.0099646379 | X22: =IF(SUM($AV22:$AY22),$AL22*AW22/SUM($AV22:$AY22),0) -> 0.022125874 | Y22: =IF(SUM($AV22:$AY22),$AL22*AX22/SUM($AV22:$AY22),0) -> 0.0028618904 | Z22: =IF(SUM($AV22:$AY22),$AL22*AY22/SUM($AV22:$AY22),0) -> 0.0022218837 | AA22: =IF(SUM($AZ22:$BC22),(1-$AL22-$AK22)*AZ22/SUM($AZ22:$BC22),0) -> 0.024445007 | AB22: =IF(SUM($AZ22:$BC22),(1-$AL22-$AK22)*BA22/SUM($AZ22:$BC22),0) -> 0.030692658 | AC22: =IF(SUM($AZ22:$BC22),(1-$AL22-$AK22)*BB22/SUM($AZ22:$BC22),0) -> 0.0027185748 | AD22: =IF(SUM($AZ22:$BC22),(1-$AL22-$AK22)*BC22/SUM($AZ22:$BC22),0) -> 0.011625241 | AE22: =S22+W22+AA22 -> 0.49097512 | AF22: =T22+X22+AB22 -> 0.44831233 | AG22: =U22+Y22+AC22 -> 0.03408349 | AH22: =V22+Z22+AD22 -> 0.026629066 | AI22: =IF(SUM($DL22:$DW22),SUM(DL22:DO22)/SUM($DL22:$DW22),0) -> 0.89334423 | AJ22: =IF(SUM($DL22:$DW22),SUM(DP22:DS22)/SUM($DL22:$DW22),0) -> 0.037174286 | AK22: =AI22 -> 0.89334423 | AL22: =AJ22 -> 0.037174286 | AM22: =1-SUM(AK22:AL22) -> 0.06948148 | AN22: 1 | AO22: 1 | AQ22: afrui | AR22: =IF(SUM($BT22:$CE22),BT22/SUM($BT22:$CE22),0) -> 0.45500847 | AS22: =IF(SUM($BT22:$CE22),BU22/SUM($BT22:$CE22),0) -> 0.39414506 | AT22: =IF(SUM($BT22:$CE22),BV22/SUM($BT22:$CE22),0) -> 0.028405822 | AU22: =IF(SUM($BT22:$CE22),BW22/SUM($BT22:$CE22),0) -> 0.012738351 | AV22: =IF(SUM($BT22:$CE22),BX22/SUM($BT22:$CE22),0) -> 0.011007889 | AW22: =IF(SUM($BT22:$CE22),BY22/SUM($BT22:$CE22),0) -> 0.024442349 | AX22: =IF(SUM($BT22:$CE22),BZ22/SUM($BT22:$CE22),0) -> 0.003161517 | AY22: =IF(SUM($BT22:$CE22),CA22/SUM($BT22:$CE22),0) -> 0.0024545046 | ... BC22: =IF(SUM($BT22:$CE22),CE22/SUM($BT22:$CE22),0) -> 0.011483785 | BE22: afrui | BF22: 1 | BG22: 1 | BH22: 1 | BI22: 1 | BJ22: 1 | BK22: 1 | BL22: 1 | BM22: 1 | BN22: 1 | BO22: 1 | BP22: 1 | BQ22: 1 | BS22: afrui | BT22: =BF22*CI22 -> 44801.074 | BU22: =BG22*CJ22 -> 38808.337 | BV22: =BH22*CK22 -> 2796.8959 | BW22: =BI22*CL22 -> 1254.2444 | BX22: =BJ22*CM22 -> 1083.8595 | BY22: =BK22*CN22 -> 2406.6442 | BZ22: =BL22*CO22 -> 311.28949 | CA22: =BM22*CP22 -> 241.67559 | ... CE22: =BQ22*CT22 -> 1130.7172 | CG22: =DJ22 -> abanb | CH22: afrui | CI22: =SUMIF($CV$7:$CV$110,$CG22,CW$7:CW$110) -> 44801.074 | CJ22: =SUMIF($CV$7:$CV$110,$CG22,CX$7:CX$110) -> 38808.337 | CK22: =SUMIF($CV$7:$CV$110,$CG22,CY$7:CY$110) -> 2796.8959 | CL22: =SUMIF($CV$7:$CV$110,$CG22,CZ$7:CZ$110) -> 1254.2444 | CM22: =SUMIF($CV$7:$CV$110,$CG22,DA$7:DA$110) -> 1083.8595 | CN22: =SUMIF($CV$7:$CV$110,$CG22,DB$7:DB$110) -> 2406.6442 | CO22: =SUMIF($CV$7:$CV$110,$CG22,DC$7:DC$110) -> 311.28949 | CP22: =SUMIF($CV$7:$CV$110,$CG22,DD$7:DD$110) -> 241.67559 | ... CT22: =SUMIF($CV$7:$CV$110,$CG22,DH$7:DH$110) -> 1130.7172 | CV22: afrui | CW22: =SUMIF($DJ$7:$DJ$110,$CV22,DL$7:DL$110) -> 0 | CX22: =SUMIF($DJ$7:$DJ$110,$CV22,DM$7:DM$110) -> 0 | CY22: =SUMIF($DJ$7:$DJ$110,$CV22,DN$7:DN$110) -> 0 | CZ22: =SUMIF($DJ$7:$DJ$110,$CV22,DO$7:DO$110) -> 0 | DA22: =SUMIF($DJ$7:$DJ$110,$CV22,DP$7:DP$110) -> 0 | DB22: =SUMIF($DJ$7:$DJ$110,$CV22,DQ$7:DQ$110) -> 0 | DC22: =SUMIF($DJ$7:$DJ$110,$CV22,DR$7:DR$110) -> 0 | DD22: =SUMIF($DJ$7:$DJ$110,$CV22,DS$7:DS$110) -> 0 | ... DH22: =SUMIF($DJ$7:$DJ$110,$CV22,DW$7:DW$110) -> 0 | DJ22: abanb | DK22: afrui | DL22: =SUMIF($EF$7:$EF$110,$DK22,EH$7:EH$110)*$DZ22*$EQ$5+SUMIF($ET$7:$ET$110,$DK22,EV$7:EV$110)*$EA22*$FE$5+SUMIF($FH$7:$FH$110,$DK22,FJ$7:FJ$110)*$EB22*$FS$5+SUMIF($FV$7:$FV$110,$DK22,FX$7:FX$110)*$EC22*$GG$5+SUMIF($GJ$7:$GJ$110,$DK22,GL$7:GL$110)*$ED22*$GU$5 -> 11419.9 | DM22: =SUMIF($EF$7:$EF$110,$DK22,EI$7:EI$110)*$DZ22*$EQ$5+SUMIF($ET$7:$ET$110,$DK22,EW$7:EW$110)*$EA22*$FE$5+SUMIF($FH$7:$FH$110,$DK22,FK$7:FK$110)*$EB22*$FS$5+SUMIF($FV$7:$FV$110,$DK22,FY$7:FY$110)*$EC22*$GG$5+SUMIF($GJ$7:$GJ$110,$DK22,GM$7:GM$110)*$ED22*$GU$5 -> 8477.85 | DN22: =SUMIF($EF$7:$EF$110,$DK22,EJ$7:EJ$110)*$DZ22*$EQ$5+SUMIF($ET$7:$ET$110,$DK22,EX$7:EX$110)*$EA22*$FE$5+SUMIF($FH$7:$FH$110,$DK22,FL$7:FL$110)*$EB22*$FS$5+SUMIF($FV$7:$FV$110,$DK22,FZ$7:FZ$110)*$EC22*$GG$5+SUMIF($GJ$7:$GJ$110,$DK22,GN$7:GN$110)*$ED22*$GU$5 -> 538.409 | DO22: =SUMIF($EF$7:$EF$110,$DK22,EK$7:EK$110)*$DZ22*$EQ$5+SUMIF($ET$7:$ET$110,$DK22,EY$7:EY$110)*$EA22*$FE$5+SUMIF($FH$7:$FH$110,$DK22,FM$7:FM$110)*$EB22*$FS$5+SUMIF($FV$7:$FV$110,$DK22,GA$7:GA$110)*$EC22*$GG$5+SUMIF($GJ$7:$GJ$110,$DK22,GO$7:GO$110)*$ED22*$GU$5 -> 154.3427 | DP22: =SUMIF($EF$7:$EF$110,$DK22,EL$7:EL$110)*$DZ22*$EQ$5+SUMIF($ET$7:$ET$110,$DK22,EZ$7:EZ$110)*$EA22*$FE$5+SUMIF($FH$7:$FH$110,$DK22,FN$7:FN$110)*$EB22*$FS$5+SUMIF($FV$7:$FV$110,$DK22,GB$7:GB$110)*$EC22*$GG$5+SUMIF($GJ$7:$GJ$110,$DK22,GP$7:GP$110)*$ED22*$GU$5 -> 378.1696 | DQ22: =SUMIF($EF$7:$EF$110,$DK22,EM$7:EM$110)*$DZ22*$EQ$5+SUMIF($ET$7:$ET$110,$DK22,FA$7:FA$110)*$EA22*$FE$5+SUMIF($FH$7:$FH$110,$DK22,FO$7:FO$110)*$EB22*$FS$5+SUMIF($FV$7:$FV$110,$DK22,GC$7:GC$110)*$EC22*$GG$5+SUMIF($GJ$7:$GJ$110,$DK22,GQ$7:GQ$110)*$ED22*$GU$5 -> 372.3267 | DR22: =SUMIF($EF$7:$EF$110,$DK22,EN$7:EN$110)*$DZ22*$EQ$5+SUMIF($ET$7:$ET$110,$DK22,FB$7:FB$110)*$EA22*$FE$5+SUMIF($FH$7:$FH$110,$DK22,FP$7:FP$110)*$EB22*$FS$5+SUMIF($FV$7:$FV$110,$DK22,GD$7:GD$110)*$EC22*$GG$5+SUMIF($GJ$7:$GJ$110,$DK22,GR$7:GR$110)*$ED22*$GU$5 -> 61.7542 | DS22: =SUMIF($EF$7:$EF$110,$DK22,EO$7:EO$110)*$DZ22*$EQ$5+SUMIF($ET$7:$ET$110,$DK22,FC$7:FC$110)*$EA22*$FE$5+SUMIF($FH$7:$FH$110,$DK22,FQ$7:FQ$110)*$EB22*$FS$5+SUMIF($FV$7:$FV$110,$DK22,GE$7:GE$110)*$EC22*$GG$5+SUMIF($GJ$7:$GJ$110,$DK22,GS$7:GS$110)*$ED22*$GU$5 -> 44.57173 | ... DW22: =SUMIF($EF$7:$EF$110,$DK22,ES$7:ES$110)*$DZ22*$EQ$5+SUMIF($ET$7:$ET$110,$DK22,FG$7:FG$110)*$EA22*$FE$5+SUMIF($FH$7:$FH$110,$DK22,FU$7:FU$110)*$EB22*$FS$5+SUMIF($FV$7:$FV$110,$DK22,GI$7:GI$110)*$EC22*$GG$5+SUMIF($GJ$7:$GJ$110,$DK22,GW$7:GW$110)*$ED22*$GU$5 -> 392.2218 | DY22: afrui | EB22: 1 | EF22: afrui | EG22: afrui | ET22: afrui | EU22: afrui | FH22: afrui | FI22: afrui | FJ22: 11419.9 | FK22: 8477.85 | FL22: 538.409 | FM22: 154.3427 | FN22: 378.1696 | FO22: 372.3267 | FP22: 61.7542 | FQ22: 44.57173 | FR22: 644.6054 | FS22: 438.7342 | FT22: 125.9025 | FU22: 392.2218 | FV22: afrui | FW22: afrui | GJ22: afrui | GK22: afrui
C23: agnut | D23: =IF(SUM($S23:$AD23),S23/SUM($S23:$AD23),0) -> 0.50876285 | E23: =IF(SUM($S23:$AD23),T23/SUM($S23:$AD23),0) -> 0.38630888 | F23: =IF(SUM($S23:$AD23),U23/SUM($S23:$AD23),0) -> 0.031382561 | G23: =IF(SUM($S23:$AD23),V23/SUM($S23:$AD23),0) -> 0.013944389 | H23: =IF(SUM($S23:$AD23),W23/SUM($S23:$AD23),0) -> 0.01079371 | I23: =IF(SUM($S23:$AD23),X23/SUM($S23:$AD23),0) -> 0.013101394 | J23: =IF(SUM($S23:$AD23),Y23/SUM($S23:$AD23),0) -> 0.0017378197 | K23: =IF(SUM($S23:$AD23),Z23/SUM($S23:$AD23),0) -> 0.00099966362 | ... O23: =IF(SUM($S23:$AD23),AD23/SUM($S23:$AD23),0) -> 0.0055421632 | P23: =SUM(D23:O23) -> 1 | R23: agnut | S23: =IF(SUM($AR23:$AU23),$AK23*AR23/SUM($AR23:$AU23),0) -> 0.50876285 | T23: =IF(SUM($AR23:$AU23),$AK23*AS23/SUM($AR23:$AU23),0) -> 0.38630888 | U23: =IF(SUM($AR23:$AU23),$AK23*AT23/SUM($AR23:$AU23),0) -> 0.031382561 | V23: =IF(SUM($AR23:$AU23),$AK23*AU23/SUM($AR23:$AU23),0) -> 0.013944389 | W23: =IF(SUM($AV23:$AY23),$AL23*AV23/SUM($AV23:$AY23),0) -> 0.01079371 | X23: =IF(SUM($AV23:$AY23),$AL23*AW23/SUM($AV23:$AY23),0) -> 0.013101394 | Y23: =IF(SUM($AV23:$AY23),$AL23*AX23/SUM($AV23:$AY23),0) -> 0.0017378197 | Z23: =IF(SUM($AV23:$AY23),$AL23*AY23/SUM($AV23:$AY23),0) -> 0.00099966362 | AA23: =IF(SUM($AZ23:$BC23),(1-$AL23-$AK23)*AZ23/SUM($AZ23:$BC23),0) -> 0.013628967 | AB23: =IF(SUM($AZ23:$BC23),(1-$AL23-$AK23)*BA23/SUM($AZ23:$BC23),0) -> 0.012434032 | AC23: =IF(SUM($AZ23:$BC23),(1-$AL23-$AK23)*BB23/SUM($AZ23:$BC23),0) -> 0.0013635677 | AD23: =IF(SUM($AZ23:$BC23),(1-$AL23-$AK23)*BC23/SUM($AZ23:$BC23),0) -> 0.0055421632 | AE23: =S23+W23+AA23 -> 0.53318553 | AF23: =T23+X23+AB23 -> 0.41184431 | AG23: =U23+Y23+AC23 -> 0.034483949 | AH23: =V23+Z23+AD23 -> 0.020486215 | AI23: =IF(SUM($DL23:$DW23),SUM(DL23:DO23)/SUM($DL23:$DW23),0) -> 0.94039868 | AJ23: =IF(SUM($DL23:$DW23),SUM(DP23:DS23)/SUM($DL23:$DW23),0) -> 0.026632587 | AK23: =AI23 -> 0.94039868 | AL23: =AJ23 -> 0.026632587 | AM23: =1-SUM(AK23:AL23) -> 0.03296873 | AN23: 1 | AO23: 1 | AQ23: agnut | AR23: =IF(SUM($BT23:$CE23),BT23/SUM($BT23:$CE23),0) -> 0.50426186 | AS23: =IF(SUM($BT23:$CE23),BU23/SUM($BT23:$CE23),0) -> 0.38289124 | AT23: =IF(SUM($BT23:$CE23),BV23/SUM($BT23:$CE23),0) -> 0.031104922 | AU23: =IF(SUM($BT23:$CE23),BW23/SUM($BT23:$CE23),0) -> 0.013821024 | AV23: =IF(SUM($BT23:$CE23),BX23/SUM($BT23:$CE23),0) -> 0.010659007 | AW23: =IF(SUM($BT23:$CE23),BY23/SUM($BT23:$CE23),0) -> 0.012937891 | AX23: =IF(SUM($BT23:$CE23),BZ23/SUM($BT23:$CE23),0) -> 0.0017161321 | AY23: =IF(SUM($BT23:$CE23),CA23/SUM($BT23:$CE23),0) -> 0.00098718804 | ... BC23: =IF(SUM($BT23:$CE23),CE23/SUM($BT23:$CE23),0) -> 0.0069965967 | BE23: agnut | BF23: 1 | BG23: 1 | BH23: 1 | BI23: 1 | BJ23: 1 | BK23: 1 | BL23: 1 | BM23: 1 | BN23: 1 | BO23: 1 | BP23: 1 | BQ23: 1 | BS23: agnut | BT23: =BF23*CI23 -> 7520.9259 | BU23: =BG23*CJ23 -> 5710.7167 | BV23: =BH23*CK23 -> 463.92129 | BW23: =BI23*CL23 -> 206.13674 | BX23: =BJ23*CM23 -> 158.97614 | BY23: =BK23*CN23 -> 192.96506 | BZ23: =BL23*CO23 -> 25.595634 | CA23: =BM23*CP23 -> 14.723636 | ... CE23: =BQ23*CT23 -> 104.3523 | CG23: =DJ23 -> agnut | CH23: agnut | CI23: =SUMIF($CV$7:$CV$110,$CG23,CW$7:CW$110) -> 7520.9259 | CJ23: =SUMIF($CV$7:$CV$110,$CG23,CX$7:CX$110) -> 5710.7167 | CK23: =SUMIF($CV$7:$CV$110,$CG23,CY$7:CY$110) -> 463.92129 | CL23: =SUMIF($CV$7:$CV$110,$CG23,CZ$7:CZ$110) -> 206.13674 | CM23: =SUMIF($CV$7:$CV$110,$CG23,DA$7:DA$110) -> 158.97614 | CN23: =SUMIF($CV$7:$CV$110,$CG23,DB$7:DB$110) -> 192.96506 | CO23: =SUMIF($CV$7:$CV$110,$CG23,DC$7:DC$110) -> 25.595634 | CP23: =SUMIF($CV$7:$CV$110,$CG23,DD$7:DD$110) -> 14.723636 | ... CT23: =SUMIF($CV$7:$CV$110,$CG23,DH$7:DH$110) -> 104.3523 | CV23: agnut | CW23: =SUMIF($DJ$7:$DJ$110,$CV23,DL$7:DL$110) -> 7520.9259 | CX23: =SUMIF($DJ$7:$DJ$110,$CV23,DM$7:DM$110) -> 5710.7167 | CY23: =SUMIF($DJ$7:$DJ$110,$CV23,DN$7:DN$110) -> 463.92129 | CZ23: =SUMIF($DJ$7:$DJ$110,$CV23,DO$7:DO$110) -> 206.13674 | DA23: =SUMIF($DJ$7:$DJ$110,$CV23,DP$7:DP$110) -> 158.97614 | DB23: =SUMIF($DJ$7:$DJ$110,$CV23,DQ$7:DQ$110) -> 192.96506 | DC23: =SUMIF($DJ$7:$DJ$110,$CV23,DR$7:DR$110) -> 25.595634 | DD23: =SUMIF($DJ$7:$DJ$110,$CV23,DS$7:DS$110) -> 14.723636 | ... DH23: =SUMIF($DJ$7:$DJ$110,$CV23,DW$7:DW$110) -> 104.3523 | DJ23: agnut | DK23: agnut | DL23: =SUMIF($EF$7:$EF$110,$DK23,EH$7:EH$110)*$DZ23*$EQ$5+SUMIF($ET$7:$ET$110,$DK23,EV$7:EV$110)*$EA23*$FE$5+SUMIF($FH$7:$FH$110,$DK23,FJ$7:FJ$110)*$EB23*$FS$5+SUMIF($FV$7:$FV$110,$DK23,FX$7:FX$110)*$EC23*$GG$5+SUMIF($GJ$7:$GJ$110,$DK23,GL$7:GL$110)*$ED23*$GU$5 -> 4834.118 | DM23: =SUMIF($EF$7:$EF$110,$DK23,EI$7:EI$110)*$DZ23*$EQ$5+SUMIF($ET$7:$ET$110,$DK23,EW$7:EW$110)*$EA23*$FE$5+SUMIF($FH$7:$FH$110,$DK23,FK$7:FK$110)*$EB23*$FS$5+SUMIF($FV$7:$FV$110,$DK23,FY$7:FY$110)*$EC23*$GG$5+SUMIF($GJ$7:$GJ$110,$DK23,GM$7:GM$110)*$ED23*$GU$5 -> 3688.727 | DN23: =SUMIF($EF$7:$EF$110,$DK23,EJ$7:EJ$110)*$DZ23*$EQ$5+SUMIF($ET$7:$ET$110,$DK23,EX$7:EX$110)*$EA23*$FE$5+SUMIF($FH$7:$FH$110,$DK23,FL$7:FL$110)*$EB23*$FS$5+SUMIF($FV$7:$FV$110,$DK23,FZ$7:FZ$110)*$EC23*$GG$5+SUMIF($GJ$7:$GJ$110,$DK23,GN$7:GN$110)*$ED23*$GU$5 -> 294.5618 | DO23: =SUMIF($EF$7:$EF$110,$DK23,EK$7:EK$110)*$DZ23*$EQ$5+SUMIF($ET$7:$ET$110,$DK23,EY$7:EY$110)*$EA23*$FE$5+SUMIF($FH$7:$FH$110,$DK23,FM$7:FM$110)*$EB23*$FS$5+SUMIF($FV$7:$FV$110,$DK23,GA$7:GA$110)*$EC23*$GG$5+SUMIF($GJ$7:$GJ$110,$DK23,GO$7:GO$110)*$ED23*$GU$5 -> 123.4164 | DP23: =SUMIF($EF$7:$EF$110,$DK23,EL$7:EL$110)*$DZ23*$EQ$5+SUMIF($ET$7:$ET$110,$DK23,EZ$7:EZ$110)*$EA23*$FE$5+SUMIF($FH$7:$FH$110,$DK23,FN$7:FN$110)*$EB23*$FS$5+SUMIF($FV$7:$FV$110,$DK23,GB$7:GB$110)*$EC23*$GG$5+SUMIF($GJ$7:$GJ$110,$DK23,GP$7:GP$110)*$ED23*$GU$5 -> 107.8758 | DQ23: =SUMIF($EF$7:$EF$110,$DK23,EM$7:EM$110)*$DZ23*$EQ$5+SUMIF($ET$7:$ET$110,$DK23,FA$7:FA$110)*$EA23*$FE$5+SUMIF($FH$7:$FH$110,$DK23,FO$7:FO$110)*$EB23*$FS$5+SUMIF($FV$7:$FV$110,$DK23,GC$7:GC$110)*$EC23*$GG$5+SUMIF($GJ$7:$GJ$110,$DK23,GQ$7:GQ$110)*$ED23*$GU$5 -> 133.2177 | DR23: =SUMIF($EF$7:$EF$110,$DK23,EN$7:EN$110)*$DZ23*$EQ$5+SUMIF($ET$7:$ET$110,$DK23,FB$7:FB$110)*$EA23*$FE$5+SUMIF($FH$7:$FH$110,$DK23,FP$7:FP$110)*$EB23*$FS$5+SUMIF($FV$7:$FV$110,$DK23,GD$7:GD$110)*$EC23*$GG$5+SUMIF($GJ$7:$GJ$110,$DK23,GR$7:GR$110)*$ED23*$GU$5 -> 6.837573 | DS23: =SUMIF($EF$7:$EF$110,$DK23,EO$7:EO$110)*$DZ23*$EQ$5+SUMIF($ET$7:$ET$110,$DK23,FC$7:FC$110)*$EA23*$FE$5+SUMIF($FH$7:$FH$110,$DK23,FQ$7:FQ$110)*$EB23*$FS$5+SUMIF($FV$7:$FV$110,$DK23,GE$7:GE$110)*$EC23*$GG$5+SUMIF($GJ$7:$GJ$110,$DK23,GS$7:GS$110)*$ED23*$GU$5 -> 5.277761 | ... DW23: =SUMIF($EF$7:$EF$110,$DK23,ES$7:ES$110)*$DZ23*$EQ$5+SUMIF($ET$7:$ET$110,$DK23,FG$7:FG$110)*$EA23*$FE$5+SUMIF($FH$7:$FH$110,$DK23,FU$7:FU$110)*$EB23*$FS$5+SUMIF($FV$7:$FV$110,$DK23,GI$7:GI$110)*$EC23*$GG$5+SUMIF($GJ$7:$GJ$110,$DK23,GW$7:GW$110)*$ED23*$GU$5 -> 19.78442 | DY23: agnut | EB23: 1 | EF23: agnut | EG23: agnut | ET23: agnut | EU23: agnut | FH23: agnut | FI23: agnut | FJ23: 4834.118 | FK23: 3688.727 | FL23: 294.5618 | FM23: 123.4164 | FN23: 107.8758 | FO23: 133.2177 | FP23: 6.837573 | FQ23: 5.277761 | FR23: 171.843 | FS23: 97.44954 | FT23: 24.37263 | FU23: 19.78442 | FV23: agnut | FW23: agnut | GJ23: agnut | GK23: agnut
C24: asoya | D24: =IF(SUM($S24:$AD24),S24/SUM($S24:$AD24),0) -> 0.49019412 | E24: =IF(SUM($S24:$AD24),T24/SUM($S24:$AD24),0) -> 0.37220945 | F24: =IF(SUM($S24:$AD24),U24/SUM($S24:$AD24),0) -> 0.030237166 | G24: =IF(SUM($S24:$AD24),V24/SUM($S24:$AD24),0) -> 0.013435449 | H24: =IF(SUM($S24:$AD24),W24/SUM($S24:$AD24),0) -> 0.01176989 | I24: =IF(SUM($S24:$AD24),X24/SUM($S24:$AD24),0) -> 0.01428628 | J24: =IF(SUM($S24:$AD24),Y24/SUM($S24:$AD24),0) -> 0.0018949876 | K24: =IF(SUM($S24:$AD24),Z24/SUM($S24:$AD24),0) -> 0.0010900729 | ... O24: =IF(SUM($S24:$AD24),AD24/SUM($S24:$AD24),0) -> 0.010906998 | P24: =SUM(D24:O24) -> 1 | R24: asoya | S24: =IF(SUM($AR24:$AU24),$AK24*AR24/SUM($AR24:$AU24),0) -> 0.49019412 | T24: =IF(SUM($AR24:$AU24),$AK24*AS24/SUM($AR24:$AU24),0) -> 0.37220945 | U24: =IF(SUM($AR24:$AU24),$AK24*AT24/SUM($AR24:$AU24),0) -> 0.030237166 | V24: =IF(SUM($AR24:$AU24),$AK24*AU24/SUM($AR24:$AU24),0) -> 0.013435449 | W24: =IF(SUM($AV24:$AY24),$AL24*AV24/SUM($AV24:$AY24),0) -> 0.01176989 | X24: =IF(SUM($AV24:$AY24),$AL24*AW24/SUM($AV24:$AY24),0) -> 0.01428628 | Y24: =IF(SUM($AV24:$AY24),$AL24*AX24/SUM($AV24:$AY24),0) -> 0.0018949876 | Z24: =IF(SUM($AV24:$AY24),$AL24*AY24/SUM($AV24:$AY24),0) -> 0.0010900729 | AA24: =IF(SUM($AZ24:$BC24),(1-$AL24-$AK24)*AZ24/SUM($AZ24:$BC24),0) -> 0.026821858 | AB24: =IF(SUM($AZ24:$BC24),(1-$AL24-$AK24)*BA24/SUM($AZ24:$BC24),0) -> 0.024470222 | AC24: =IF(SUM($AZ24:$BC24),(1-$AL24-$AK24)*BB24/SUM($AZ24:$BC24),0) -> 0.0026835064 | AD24: =IF(SUM($AZ24:$BC24),(1-$AL24-$AK24)*BC24/SUM($AZ24:$BC24),0) -> 0.010906998 | AE24: =S24+W24+AA24 -> 0.52878586 | AF24: =T24+X24+AB24 -> 0.41096596 | AG24: =U24+Y24+AC24 -> 0.03481566 | AH24: =V24+Z24+AD24 -> 0.02543252 | AI24: =IF(SUM($DL24:$DW24),SUM(DL24:DO24)/SUM($DL24:$DW24),0) -> 0.90607618 | AJ24: =IF(SUM($DL24:$DW24),SUM(DP24:DS24)/SUM($DL24:$DW24),0) -> 0.029041231 | AK24: =AI24 -> 0.90607618 | AL24: =AJ24 -> 0.029041231 | AM24: =1-SUM(AK24:AL24) -> 0.064882585 | AN24: 1 | AO24: 1 | AQ24: asoya | AR24: =IF(SUM($BT24:$CE24),BT24/SUM($BT24:$CE24),0) -> 0.50426186 | AS24: =IF(SUM($BT24:$CE24),BU24/SUM($BT24:$CE24),0) -> 0.38289124 | AT24: =IF(SUM($BT24:$CE24),BV24/SUM($BT24:$CE24),0) -> 0.031104922 | AU24: =IF(SUM($BT24:$CE24),BW24/SUM($BT24:$CE24),0) -> 0.013821024 | AV24: =IF(SUM($BT24:$CE24),BX24/SUM($BT24:$CE24),0) -> 0.010659007 | AW24: =IF(SUM($BT24:$CE24),BY24/SUM($BT24:$CE24),0) -> 0.012937891 | AX24: =IF(SUM($BT24:$CE24),BZ24/SUM($BT24:$CE24),0) -> 0.0017161321 | AY24: =IF(SUM($BT24:$CE24),CA24/SUM($BT24:$CE24),0) -> 0.00098718804 | ... BC24: =IF(SUM($BT24:$CE24),CE24/SUM($BT24:$CE24),0) -> 0.0069965967 | BE24: asoya | BF24: 1 | BG24: 1 | BH24: 1 | BI24: 1 | BJ24: 1 | BK24: 1 | BL24: 1 | BM24: 1 | BN24: 1 | BO24: 1 | BP24: 1 | BQ24: 1 | BS24: asoya | BT24: =BF24*CI24 -> 7520.9259 | BU24: =BG24*CJ24 -> 5710.7167 | BV24: =BH24*CK24 -> 463.92129 | BW24: =BI24*CL24 -> 206.13674 | BX24: =BJ24*CM24 -> 158.97614 | BY24: =BK24*CN24 -> 192.96506 | BZ24: =BL24*CO24 -> 25.595634 | CA24: =BM24*CP24 -> 14.723636 | ... CE24: =BQ24*CT24 -> 104.3523 | CG24: =DJ24 -> agnut | CH24: asoya | CI24: =SUMIF($CV$7:$CV$110,$CG24,CW$7:CW$110) -> 7520.9259 | CJ24: =SUMIF($CV$7:$CV$110,$CG24,CX$7:CX$110) -> 5710.7167 | CK24: =SUMIF($CV$7:$CV$110,$CG24,CY$7:CY$110) -> 463.92129 | CL24: =SUMIF($CV$7:$CV$110,$CG24,CZ$7:CZ$110) -> 206.13674 | CM24: =SUMIF($CV$7:$CV$110,$CG24,DA$7:DA$110) -> 158.97614 | CN24: =SUMIF($CV$7:$CV$110,$CG24,DB$7:DB$110) -> 192.96506 | CO24: =SUMIF($CV$7:$CV$110,$CG24,DC$7:DC$110) -> 25.595634 | CP24: =SUMIF($CV$7:$CV$110,$CG24,DD$7:DD$110) -> 14.723636 | ... CT24: =SUMIF($CV$7:$CV$110,$CG24,DH$7:DH$110) -> 104.3523 | CV24: asoya | CW24: =SUMIF($DJ$7:$DJ$110,$CV24,DL$7:DL$110) -> 0 | CX24: =SUMIF($DJ$7:$DJ$110,$CV24,DM$7:DM$110) -> 0 | CY24: =SUMIF($DJ$7:$DJ$110,$CV24,DN$7:DN$110) -> 0 | CZ24: =SUMIF($DJ$7:$DJ$110,$CV24,DO$7:DO$110) -> 0 | DA24: =SUMIF($DJ$7:$DJ$110,$CV24,DP$7:DP$110) -> 0 | DB24: =SUMIF($DJ$7:$DJ$110,$CV24,DQ$7:DQ$110) -> 0 | DC24: =SUMIF($DJ$7:$DJ$110,$CV24,DR$7:DR$110) -> 0 | DD24: =SUMIF($DJ$7:$DJ$110,$CV24,DS$7:DS$110) -> 0 | ... DH24: =SUMIF($DJ$7:$DJ$110,$CV24,DW$7:DW$110) -> 0 | DJ24: agnut | DK24: asoya | DL24: =SUMIF($EF$7:$EF$110,$DK24,EH$7:EH$110)*$DZ24*$EQ$5+SUMIF($ET$7:$ET$110,$DK24,EV$7:EV$110)*$EA24*$FE$5+SUMIF($FH$7:$FH$110,$DK24,FJ$7:FJ$110)*$EB24*$FS$5+SUMIF($FV$7:$FV$110,$DK24,FX$7:FX$110)*$EC24*$GG$5+SUMIF($GJ$7:$GJ$110,$DK24,GL$7:GL$110)*$ED24*$GU$5 -> 2210.502 | DM24: =SUMIF($EF$7:$EF$110,$DK24,EI$7:EI$110)*$DZ24*$EQ$5+SUMIF($ET$7:$ET$110,$DK24,EW$7:EW$110)*$EA24*$FE$5+SUMIF($FH$7:$FH$110,$DK24,FK$7:FK$110)*$EB24*$FS$5+SUMIF($FV$7:$FV$110,$DK24,FY$7:FY$110)*$EC24*$GG$5+SUMIF($GJ$7:$GJ$110,$DK24,GM$7:GM$110)*$ED24*$GU$5 -> 1788.362 | DN24: =SUMIF($EF$7:$EF$110,$DK24,EJ$7:EJ$110)*$DZ24*$EQ$5+SUMIF($ET$7:$ET$110,$DK24,EX$7:EX$110)*$EA24*$FE$5+SUMIF($FH$7:$FH$110,$DK24,FL$7:FL$110)*$EB24*$FS$5+SUMIF($FV$7:$FV$110,$DK24,FZ$7:FZ$110)*$EC24*$GG$5+SUMIF($GJ$7:$GJ$110,$DK24,GN$7:GN$110)*$ED24*$GU$5 -> 153.3423 | DO24: =SUMIF($EF$7:$EF$110,$DK24,EK$7:EK$110)*$DZ24*$EQ$5+SUMIF($ET$7:$ET$110,$DK24,EY$7:EY$110)*$EA24*$FE$5+SUMIF($FH$7:$FH$110,$DK24,FM$7:FM$110)*$EB24*$FS$5+SUMIF($FV$7:$FV$110,$DK24,GA$7:GA$110)*$EC24*$GG$5+SUMIF($GJ$7:$GJ$110,$DK24,GO$7:GO$110)*$ED24*$GU$5 -> 82.19173 | DP24: =SUMIF($EF$7:$EF$110,$DK24,EL$7:EL$110)*$DZ24*$EQ$5+SUMIF($ET$7:$ET$110,$DK24,EZ$7:EZ$110)*$EA24*$FE$5+SUMIF($FH$7:$FH$110,$DK24,FN$7:FN$110)*$EB24*$FS$5+SUMIF($FV$7:$FV$110,$DK24,GB$7:GB$110)*$EC24*$GG$5+SUMIF($GJ$7:$GJ$110,$DK24,GP$7:GP$110)*$ED24*$GU$5 -> 48.88851 | DQ24: =SUMIF($EF$7:$EF$110,$DK24,EM$7:EM$110)*$DZ24*$EQ$5+SUMIF($ET$7:$ET$110,$DK24,FA$7:FA$110)*$EA24*$FE$5+SUMIF($FH$7:$FH$110,$DK24,FO$7:FO$110)*$EB24*$FS$5+SUMIF($FV$7:$FV$110,$DK24,GC$7:GC$110)*$EC24*$GG$5+SUMIF($GJ$7:$GJ$110,$DK24,GQ$7:GQ$110)*$ED24*$GU$5 -> 58.94504 | DR24: =SUMIF($EF$7:$EF$110,$DK24,EN$7:EN$110)*$DZ24*$EQ$5+SUMIF($ET$7:$ET$110,$DK24,FB$7:FB$110)*$EA24*$FE$5+SUMIF($FH$7:$FH$110,$DK24,FP$7:FP$110)*$EB24*$FS$5+SUMIF($FV$7:$FV$110,$DK24,GD$7:GD$110)*$EC24*$GG$5+SUMIF($GJ$7:$GJ$110,$DK24,GR$7:GR$110)*$ED24*$GU$5 -> 18.43999 | DS24: =SUMIF($EF$7:$EF$110,$DK24,EO$7:EO$110)*$DZ24*$EQ$5+SUMIF($ET$7:$ET$110,$DK24,FC$7:FC$110)*$EA24*$FE$5+SUMIF($FH$7:$FH$110,$DK24,FQ$7:FQ$110)*$EB24*$FS$5+SUMIF($FV$7:$FV$110,$DK24,GE$7:GE$110)*$EC24*$GG$5+SUMIF($GJ$7:$GJ$110,$DK24,GS$7:GS$110)*$ED24*$GU$5 -> 9.445875 | ... DW24: =SUMIF($EF$7:$EF$110,$DK24,ES$7:ES$110)*$DZ24*$EQ$5+SUMIF($ET$7:$ET$110,$DK24,FG$7:FG$110)*$EA24*$FE$5+SUMIF($FH$7:$FH$110,$DK24,FU$7:FU$110)*$EB24*$FS$5+SUMIF($FV$7:$FV$110,$DK24,GI$7:GI$110)*$EC24*$GG$5+SUMIF($GJ$7:$GJ$110,$DK24,GW$7:GW$110)*$ED24*$GU$5 -> 84.56788 | DY24: asoya | EB24: 1 | EF24: asoya | EG24: asoya | ET24: asoya | EU24: asoya | FH24: asoya | FI24: asoya | FJ24: 2210.502 | FK24: 1788.362 | FL24: 153.3423 | FM24: 82.19173 | FN24: 48.88851 | FO24: 58.94504 | FP24: 18.43999 | FQ24: 9.445875 | FR24: 82.27109 | FS24: 135.0774 | FT24: 1.301718 | FU24: 84.56788 | FV24: asoya | FW24: asoya | GJ24: asoya | GK24: asoya
C25: aoils | D25: =IF(SUM($S25:$AD25),S25/SUM($S25:$AD25),0) -> 0.53553326 | E25: =IF(SUM($S25:$AD25),T25/SUM($S25:$AD25),0) -> 0.40663593 | F25: =IF(SUM($S25:$AD25),U25/SUM($S25:$AD25),0) -> 0.033033869 | G25: =IF(SUM($S25:$AD25),V25/SUM($S25:$AD25),0) -> 0.014678123 | H25: =IF(SUM($S25:$AD25),W25/SUM($S25:$AD25),0) -> 0.0018401406 | I25: =IF(SUM($S25:$AD25),X25/SUM($S25:$AD25),0) -> 0.0022335606 | J25: =IF(SUM($S25:$AD25),Y25/SUM($S25:$AD25),0) -> 0.00029626815 | K25: =IF(SUM($S25:$AD25),Z25/SUM($S25:$AD25),0) -> 0.00017042533 | ... O25: =IF(SUM($S25:$AD25),AD25/SUM($S25:$AD25),0) -> 0.00093775291 | P25: =SUM(D25:O25) -> 1 | R25: aoils | S25: =IF(SUM($AR25:$AU25),$AK25*AR25/SUM($AR25:$AU25),0) -> 0.53553326 | T25: =IF(SUM($AR25:$AU25),$AK25*AS25/SUM($AR25:$AU25),0) -> 0.40663593 | U25: =IF(SUM($AR25:$AU25),$AK25*AT25/SUM($AR25:$AU25),0) -> 0.033033869 | V25: =IF(SUM($AR25:$AU25),$AK25*AU25/SUM($AR25:$AU25),0) -> 0.014678123 | W25: =IF(SUM($AV25:$AY25),$AL25*AV25/SUM($AV25:$AY25),0) -> 0.0018401406 | X25: =IF(SUM($AV25:$AY25),$AL25*AW25/SUM($AV25:$AY25),0) -> 0.0022335606 | Y25: =IF(SUM($AV25:$AY25),$AL25*AX25/SUM($AV25:$AY25),0) -> 0.00029626815 | Z25: =IF(SUM($AV25:$AY25),$AL25*AY25/SUM($AV25:$AY25),0) -> 0.00017042533 | AA25: =IF(SUM($AZ25:$BC25),(1-$AL25-$AK25)*AZ25/SUM($AZ25:$BC25),0) -> 0.0023060676 | AB25: =IF(SUM($AZ25:$BC25),(1-$AL25-$AK25)*BA25/SUM($AZ25:$BC25),0) -> 0.0021038806 | AC25: =IF(SUM($AZ25:$BC25),(1-$AL25-$AK25)*BB25/SUM($AZ25:$BC25),0) -> 0.00023072031 | AD25: =IF(SUM($AZ25:$BC25),(1-$AL25-$AK25)*BC25/SUM($AZ25:$BC25),0) -> 0.00093775291 | AE25: =S25+W25+AA25 -> 0.53967947 | AF25: =T25+X25+AB25 -> 0.41097337 | AG25: =U25+Y25+AC25 -> 0.033560857 | AH25: =V25+Z25+AD25 -> 0.015786302 | AI25: =IF(SUM($DL25:$DW25),SUM(DL25:DO25)/SUM($DL25:$DW25),0) -> 0.98988118 | AJ25: =IF(SUM($DL25:$DW25),SUM(DP25:DS25)/SUM($DL25:$DW25),0) -> 0.0045403947 | AK25: =AI25 -> 0.98988118 | AL25: =AJ25 -> 0.0045403947 | AM25: =1-SUM(AK25:AL25) -> 0.0055784214 | AN25: 1 | AO25: 1 | AQ25: aoils | AR25: =IF(SUM($BT25:$CE25),BT25/SUM($BT25:$CE25),0) -> 0.50426186 | AS25: =IF(SUM($BT25:$CE25),BU25/SUM($BT25:$CE25),0) -> 0.38289124 | AT25: =IF(SUM($BT25:$CE25),BV25/SUM($BT25:$CE25),0) -> 0.031104922 | AU25: =IF(SUM($BT25:$CE25),BW25/SUM($BT25:$CE25),0) -> 0.013821024 | AV25: =IF(SUM($BT25:$CE25),BX25/SUM($BT25:$CE25),0) -> 0.010659007 | AW25: =IF(SUM($BT25:$CE25),BY25/SUM($BT25:$CE25),0) -> 0.012937891 | AX25: =IF(SUM($BT25:$CE25),BZ25/SUM($BT25:$CE25),0) -> 0.0017161321 | AY25: =IF(SUM($BT25:$CE25),CA25/SUM($BT25:$CE25),0) -> 0.00098718804 | ... BC25: =IF(SUM($BT25:$CE25),CE25/SUM($BT25:$CE25),0) -> 0.0069965967 | BE25: aoils | BF25: 1 | BG25: 1 | BH25: 1 | BI25: 1 | BJ25: 1 | BK25: 1 | BL25: 1 | BM25: 1 | BN25: 1 | BO25: 1 | BP25: 1 | BQ25: 1 | BS25: aoils | BT25: =BF25*CI25 -> 7520.9259 | BU25: =BG25*CJ25 -> 5710.7167 | BV25: =BH25*CK25 -> 463.92129 | BW25: =BI25*CL25 -> 206.13674 | BX25: =BJ25*CM25 -> 158.97614 | BY25: =BK25*CN25 -> 192.96506 | BZ25: =BL25*CO25 -> 25.595634 | CA25: =BM25*CP25 -> 14.723636 | ... CE25: =BQ25*CT25 -> 104.3523 | CG25: =DJ25 -> agnut | CH25: aoils | CI25: =SUMIF($CV$7:$CV$110,$CG25,CW$7:CW$110) -> 7520.9259 | CJ25: =SUMIF($CV$7:$CV$110,$CG25,CX$7:CX$110) -> 5710.7167 | CK25: =SUMIF($CV$7:$CV$110,$CG25,CY$7:CY$110) -> 463.92129 | CL25: =SUMIF($CV$7:$CV$110,$CG25,CZ$7:CZ$110) -> 206.13674 | CM25: =SUMIF($CV$7:$CV$110,$CG25,DA$7:DA$110) -> 158.97614 | CN25: =SUMIF($CV$7:$CV$110,$CG25,DB$7:DB$110) -> 192.96506 | CO25: =SUMIF($CV$7:$CV$110,$CG25,DC$7:DC$110) -> 25.595634 | CP25: =SUMIF($CV$7:$CV$110,$CG25,DD$7:DD$110) -> 14.723636 | ... CT25: =SUMIF($CV$7:$CV$110,$CG25,DH$7:DH$110) -> 104.3523 | CV25: aoils | CW25: =SUMIF($DJ$7:$DJ$110,$CV25,DL$7:DL$110) -> 0 | CX25: =SUMIF($DJ$7:$DJ$110,$CV25,DM$7:DM$110) -> 0 | CY25: =SUMIF($DJ$7:$DJ$110,$CV25,DN$7:DN$110) -> 0 | CZ25: =SUMIF($DJ$7:$DJ$110,$CV25,DO$7:DO$110) -> 0 | DA25: =SUMIF($DJ$7:$DJ$110,$CV25,DP$7:DP$110) -> 0 | DB25: =SUMIF($DJ$7:$DJ$110,$CV25,DQ$7:DQ$110) -> 0 | DC25: =SUMIF($DJ$7:$DJ$110,$CV25,DR$7:DR$110) -> 0 | DD25: =SUMIF($DJ$7:$DJ$110,$CV25,DS$7:DS$110) -> 0 | ... DH25: =SUMIF($DJ$7:$DJ$110,$CV25,DW$7:DW$110) -> 0 | DJ25: agnut | DK25: aoils | DL25: =SUMIF($EF$7:$EF$110,$DK25,EH$7:EH$110)*$DZ25*$EQ$5+SUMIF($ET$7:$ET$110,$DK25,EV$7:EV$110)*$EA25*$FE$5+SUMIF($FH$7:$FH$110,$DK25,FJ$7:FJ$110)*$EB25*$FS$5+SUMIF($FV$7:$FV$110,$DK25,FX$7:FX$110)*$EC25*$GG$5+SUMIF($GJ$7:$GJ$110,$DK25,GL$7:GL$110)*$ED25*$GU$5 -> 476.3059 | DM25: =SUMIF($EF$7:$EF$110,$DK25,EI$7:EI$110)*$DZ25*$EQ$5+SUMIF($ET$7:$ET$110,$DK25,EW$7:EW$110)*$EA25*$FE$5+SUMIF($FH$7:$FH$110,$DK25,FK$7:FK$110)*$EB25*$FS$5+SUMIF($FV$7:$FV$110,$DK25,FY$7:FY$110)*$EC25*$GG$5+SUMIF($GJ$7:$GJ$110,$DK25,GM$7:GM$110)*$ED25*$GU$5 -> 233.6277 | DN25: =SUMIF($EF$7:$EF$110,$DK25,EJ$7:EJ$110)*$DZ25*$EQ$5+SUMIF($ET$7:$ET$110,$DK25,EX$7:EX$110)*$EA25*$FE$5+SUMIF($FH$7:$FH$110,$DK25,FL$7:FL$110)*$EB25*$FS$5+SUMIF($FV$7:$FV$110,$DK25,FZ$7:FZ$110)*$EC25*$GG$5+SUMIF($GJ$7:$GJ$110,$DK25,GN$7:GN$110)*$ED25*$GU$5 -> 16.01719 | DO25: =SUMIF($EF$7:$EF$110,$DK25,EK$7:EK$110)*$DZ25*$EQ$5+SUMIF($ET$7:$ET$110,$DK25,EY$7:EY$110)*$EA25*$FE$5+SUMIF($FH$7:$FH$110,$DK25,FM$7:FM$110)*$EB25*$FS$5+SUMIF($FV$7:$FV$110,$DK25,GA$7:GA$110)*$EC25*$GG$5+SUMIF($GJ$7:$GJ$110,$DK25,GO$7:GO$110)*$ED25*$GU$5 -> 0.5286064 | DP25: =SUMIF($EF$7:$EF$110,$DK25,EL$7:EL$110)*$DZ25*$EQ$5+SUMIF($ET$7:$ET$110,$DK25,EZ$7:EZ$110)*$EA25*$FE$5+SUMIF($FH$7:$FH$110,$DK25,FN$7:FN$110)*$EB25*$FS$5+SUMIF($FV$7:$FV$110,$DK25,GB$7:GB$110)*$EC25*$GG$5+SUMIF($GJ$7:$GJ$110,$DK25,GP$7:GP$110)*$ED25*$GU$5 -> 2.21183 | DQ25: =SUMIF($EF$7:$EF$110,$DK25,EM$7:EM$110)*$DZ25*$EQ$5+SUMIF($ET$7:$ET$110,$DK25,FA$7:FA$110)*$EA25*$FE$5+SUMIF($FH$7:$FH$110,$DK25,FO$7:FO$110)*$EB25*$FS$5+SUMIF($FV$7:$FV$110,$DK25,GC$7:GC$110)*$EC25*$GG$5+SUMIF($GJ$7:$GJ$110,$DK25,GQ$7:GQ$110)*$ED25*$GU$5 -> 0.8023198 | DR25: =SUMIF($EF$7:$EF$110,$DK25,EN$7:EN$110)*$DZ25*$EQ$5+SUMIF($ET$7:$ET$110,$DK25,FB$7:FB$110)*$EA25*$FE$5+SUMIF($FH$7:$FH$110,$DK25,FP$7:FP$110)*$EB25*$FS$5+SUMIF($FV$7:$FV$110,$DK25,GD$7:GD$110)*$EC25*$GG$5+SUMIF($GJ$7:$GJ$110,$DK25,GR$7:GR$110)*$ED25*$GU$5 -> 0.3180715 | DS25: =SUMIF($EF$7:$EF$110,$DK25,EO$7:EO$110)*$DZ25*$EQ$5+SUMIF($ET$7:$ET$110,$DK25,FC$7:FC$110)*$EA25*$FE$5+SUMIF($FH$7:$FH$110,$DK25,FQ$7:FQ$110)*$EB25*$FS$5+SUMIF($FV$7:$FV$110,$DK25,GE$7:GE$110)*$EC25*$GG$5+SUMIF($GJ$7:$GJ$110,$DK25,GS$7:GS$110)*$ED25*$GU$5 -> 0 | ... DW25: =SUMIF($EF$7:$EF$110,$DK25,ES$7:ES$110)*$DZ25*$EQ$5+SUMIF($ET$7:$ET$110,$DK25,FG$7:FG$110)*$EA25*$FE$5+SUMIF($FH$7:$FH$110,$DK25,FU$7:FU$110)*$EB25*$FS$5+SUMIF($FV$7:$FV$110,$DK25,GI$7:GI$110)*$EC25*$GG$5+SUMIF($GJ$7:$GJ$110,$DK25,GW$7:GW$110)*$ED25*$GU$5 -> 0 | DY25: aoils | EB25: 1 | EF25: aoils | EG25: aoils | ET25: aoils | EU25: aoils | FH25: aoils | FI25: aoils | FJ25: 476.3059 | FK25: 233.6277 | FL25: 16.01719 | FM25: 0.5286064 | FN25: 2.21183 | FO25: 0.8023198 | FP25: 0.3180715 | FR25: 2.503039 | FS25: 1.590996 | FV25: aoils | FW25: aoils | GJ25: aoils | GK25: aoils
C26: acoff | D26: =IF(SUM($S26:$AD26),S26/SUM($S26:$AD26),0) -> 0.50144513 | E26: =IF(SUM($S26:$AD26),T26/SUM($S26:$AD26),0) -> 0.45886274 | F26: =IF(SUM($S26:$AD26),U26/SUM($S26:$AD26),0) -> 0.022078291 | G26: =IF(SUM($S26:$AD26),V26/SUM($S26:$AD26),0) -> 0.003700532 | H26: =IF(SUM($S26:$AD26),W26/SUM($S26:$AD26),0) -> 0.0025406412 | I26: =IF(SUM($S26:$AD26),X26/SUM($S26:$AD26),0) -> 0.0053065678 | J26: =IF(SUM($S26:$AD26),Y26/SUM($S26:$AD26),0) -> 0.00010540727 | K26: =IF(SUM($S26:$AD26),Z26/SUM($S26:$AD26),0) -> 0.00039235304 | ... O26: =IF(SUM($S26:$AD26),AD26/SUM($S26:$AD26),0) -> 0 | P26: =SUM(D26:O26) -> 1 | R26: acoff | S26: =IF(SUM($AR26:$AU26),$AK26*AR26/SUM($AR26:$AU26),0) -> 0.50144513 | T26: =IF(SUM($AR26:$AU26),$AK26*AS26/SUM($AR26:$AU26),0) -> 0.45886274 | U26: =IF(SUM($AR26:$AU26),$AK26*AT26/SUM($AR26:$AU26),0) -> 0.022078291 | V26: =IF(SUM($AR26:$AU26),$AK26*AU26/SUM($AR26:$AU26),0) -> 0.003700532 | W26: =IF(SUM($AV26:$AY26),$AL26*AV26/SUM($AV26:$AY26),0) -> 0.0025406412 | X26: =IF(SUM($AV26:$AY26),$AL26*AW26/SUM($AV26:$AY26),0) -> 0.0053065678 | Y26: =IF(SUM($AV26:$AY26),$AL26*AX26/SUM($AV26:$AY26),0) -> 0.00010540727 | Z26: =IF(SUM($AV26:$AY26),$AL26*AY26/SUM($AV26:$AY26),0) -> 0.00039235304 | AA26: =IF(SUM($AZ26:$BC26),(1-$AL26-$AK26)*AZ26/SUM($AZ26:$BC26),0) -> 0.0054567393 | AB26: =IF(SUM($AZ26:$BC26),(1-$AL26-$AK26)*BA26/SUM($AZ26:$BC26),0) -> 0.00011159706 | AC26: =IF(SUM($AZ26:$BC26),(1-$AL26-$AK26)*BB26/SUM($AZ26:$BC26),0) -> 0 | AD26: =IF(SUM($AZ26:$BC26),(1-$AL26-$AK26)*BC26/SUM($AZ26:$BC26),0) -> 0 | AE26: =S26+W26+AA26 -> 0.50944251 | AF26: =T26+X26+AB26 -> 0.46428091 | AG26: =U26+Y26+AC26 -> 0.022183698 | AH26: =V26+Z26+AD26 -> 0.004092885 | AI26: =IF(SUM($DL26:$DW26),SUM(DL26:DO26)/SUM($DL26:$DW26),0) -> 0.98608669 | AJ26: =IF(SUM($DL26:$DW26),SUM(DP26:DS26)/SUM($DL26:$DW26),0) -> 0.0083449693 | AK26: =AI26 -> 0.98608669 | AL26: =AJ26 -> 0.0083449693 | AM26: =1-SUM(AK26:AL26) -> 0.0055683364 | AN26: 1 | AO26: 1 | AQ26: acoff | AR26: =IF(SUM($BT26:$CE26),BT26/SUM($BT26:$CE26),0) -> 0.50252996 | AS26: =IF(SUM($BT26:$CE26),BU26/SUM($BT26:$CE26),0) -> 0.45985545 | AT26: =IF(SUM($BT26:$CE26),BV26/SUM($BT26:$CE26),0) -> 0.022126055 | AU26: =IF(SUM($BT26:$CE26),BW26/SUM($BT26:$CE26),0) -> 0.0037085378 | AV26: =IF(SUM($BT26:$CE26),BX26/SUM($BT26:$CE26),0) -> 0.0022652552 | AW26: =IF(SUM($BT26:$CE26),BY26/SUM($BT26:$CE26),0) -> 0.0047313765 | AX26: =IF(SUM($BT26:$CE26),BZ26/SUM($BT26:$CE26),0) -> 9.3981929e-05 | AY26: =IF(SUM($BT26:$CE26),CA26/SUM($BT26:$CE26),0) -> 0.00034982498 | ... BC26: =IF(SUM($BT26:$CE26),CE26/SUM($BT26:$CE26),0) -> 0 | BE26: acoff | BF26: 1 | BG26: 1 | BH26: 1 | BI26: 1 | BJ26: 1 | BK26: 1 | BL26: 1 | BM26: 1 | BN26: 1 | BO26: 1 | BP26: 1 | BQ26: 1 | BS26: acoff | BT26: =BF26*CI26 -> 6608.636 | BU26: =BG26*CJ26 -> 6047.435 | BV26: =BH26*CK26 -> 290.97378 | BW26: =BI26*CL26 -> 48.76998 | BX26: =BJ26*CM26 -> 29.78976 | BY26: =BK26*CN26 -> 62.221057 | BZ26: =BL26*CO26 -> 1.235931 | CA26: =BM26*CP26 -> 4.600454 | ... CE26: =BQ26*CT26 -> 0 | CG26: =DJ26 -> acoff | CH26: acoff | CI26: =SUMIF($CV$7:$CV$110,$CG26,CW$7:CW$110) -> 6608.636 | CJ26: =SUMIF($CV$7:$CV$110,$CG26,CX$7:CX$110) -> 6047.435 | CK26: =SUMIF($CV$7:$CV$110,$CG26,CY$7:CY$110) -> 290.97378 | CL26: =SUMIF($CV$7:$CV$110,$CG26,CZ$7:CZ$110) -> 48.76998 | CM26: =SUMIF($CV$7:$CV$110,$CG26,DA$7:DA$110) -> 29.78976 | CN26: =SUMIF($CV$7:$CV$110,$CG26,DB$7:DB$110) -> 62.221057 | CO26: =SUMIF($CV$7:$CV$110,$CG26,DC$7:DC$110) -> 1.235931 | CP26: =SUMIF($CV$7:$CV$110,$CG26,DD$7:DD$110) -> 4.600454 | ... CT26: =SUMIF($CV$7:$CV$110,$CG26,DH$7:DH$110) -> 0 | CV26: acoff | CW26: =SUMIF($DJ$7:$DJ$110,$CV26,DL$7:DL$110) -> 6608.636 | CX26: =SUMIF($DJ$7:$DJ$110,$CV26,DM$7:DM$110) -> 6047.435 | CY26: =SUMIF($DJ$7:$DJ$110,$CV26,DN$7:DN$110) -> 290.97378 | CZ26: =SUMIF($DJ$7:$DJ$110,$CV26,DO$7:DO$110) -> 48.76998 | DA26: =SUMIF($DJ$7:$DJ$110,$CV26,DP$7:DP$110) -> 29.78976 | DB26: =SUMIF($DJ$7:$DJ$110,$CV26,DQ$7:DQ$110) -> 62.221057 | DC26: =SUMIF($DJ$7:$DJ$110,$CV26,DR$7:DR$110) -> 1.235931 | DD26: =SUMIF($DJ$7:$DJ$110,$CV26,DS$7:DS$110) -> 4.600454 | ... DH26: =SUMIF($DJ$7:$DJ$110,$CV26,DW$7:DW$110) -> 0 | DJ26: acoff | DK26: acoff | DL26: =SUMIF($EF$7:$EF$110,$DK26,EH$7:EH$110)*$DZ26*$EQ$5+SUMIF($ET$7:$ET$110,$DK26,EV$7:EV$110)*$EA26*$FE$5+SUMIF($FH$7:$FH$110,$DK26,FJ$7:FJ$110)*$EB26*$FS$5+SUMIF($FV$7:$FV$110,$DK26,FX$7:FX$110)*$EC26*$GG$5+SUMIF($GJ$7:$GJ$110,$DK26,GL$7:GL$110)*$ED26*$GU$5 -> 5524.926 | DM26: =SUMIF($EF$7:$EF$110,$DK26,EI$7:EI$110)*$DZ26*$EQ$5+SUMIF($ET$7:$ET$110,$DK26,EW$7:EW$110)*$EA26*$FE$5+SUMIF($FH$7:$FH$110,$DK26,FK$7:FK$110)*$EB26*$FS$5+SUMIF($FV$7:$FV$110,$DK26,FY$7:FY$110)*$EC26*$GG$5+SUMIF($GJ$7:$GJ$110,$DK26,GM$7:GM$110)*$ED26*$GU$5 -> 4243.023 | DN26: =SUMIF($EF$7:$EF$110,$DK26,EJ$7:EJ$110)*$DZ26*$EQ$5+SUMIF($ET$7:$ET$110,$DK26,EX$7:EX$110)*$EA26*$FE$5+SUMIF($FH$7:$FH$110,$DK26,FL$7:FL$110)*$EB26*$FS$5+SUMIF($FV$7:$FV$110,$DK26,FZ$7:FZ$110)*$EC26*$GG$5+SUMIF($GJ$7:$GJ$110,$DK26,GN$7:GN$110)*$ED26*$GU$5 -> 289.4159 | DO26: =SUMIF($EF$7:$EF$110,$DK26,EK$7:EK$110)*$DZ26*$EQ$5+SUMIF($ET$7:$ET$110,$DK26,EY$7:EY$110)*$EA26*$FE$5+SUMIF($FH$7:$FH$110,$DK26,FM$7:FM$110)*$EB26*$FS$5+SUMIF($FV$7:$FV$110,$DK26,GA$7:GA$110)*$EC26*$GG$5+SUMIF($GJ$7:$GJ$110,$DK26,GO$7:GO$110)*$ED26*$GU$5 -> 48.76998 | DP26: =SUMIF($EF$7:$EF$110,$DK26,EL$7:EL$110)*$DZ26*$EQ$5+SUMIF($ET$7:$ET$110,$DK26,EZ$7:EZ$110)*$EA26*$FE$5+SUMIF($FH$7:$FH$110,$DK26,FN$7:FN$110)*$EB26*$FS$5+SUMIF($FV$7:$FV$110,$DK26,GB$7:GB$110)*$EC26*$GG$5+SUMIF($GJ$7:$GJ$110,$DK26,GP$7:GP$110)*$ED26*$GU$5 -> 19.72655 | DQ26: =SUMIF($EF$7:$EF$110,$DK26,EM$7:EM$110)*$DZ26*$EQ$5+SUMIF($ET$7:$ET$110,$DK26,FA$7:FA$110)*$EA26*$FE$5+SUMIF($FH$7:$FH$110,$DK26,FO$7:FO$110)*$EB26*$FS$5+SUMIF($FV$7:$FV$110,$DK26,GC$7:GC$110)*$EC26*$GG$5+SUMIF($GJ$7:$GJ$110,$DK26,GQ$7:GQ$110)*$ED26*$GU$5 -> 59.96239 | DR26: =SUMIF($EF$7:$EF$110,$DK26,EN$7:EN$110)*$DZ26*$EQ$5+SUMIF($ET$7:$ET$110,$DK26,FB$7:FB$110)*$EA26*$FE$5+SUMIF($FH$7:$FH$110,$DK26,FP$7:FP$110)*$EB26*$FS$5+SUMIF($FV$7:$FV$110,$DK26,GD$7:GD$110)*$EC26*$GG$5+SUMIF($GJ$7:$GJ$110,$DK26,GR$7:GR$110)*$ED26*$GU$5 -> 1.235931 | DS26: =SUMIF($EF$7:$EF$110,$DK26,EO$7:EO$110)*$DZ26*$EQ$5+SUMIF($ET$7:$ET$110,$DK26,FC$7:FC$110)*$EA26*$FE$5+SUMIF($FH$7:$FH$110,$DK26,FQ$7:FQ$110)*$EB26*$FS$5+SUMIF($FV$7:$FV$110,$DK26,GE$7:GE$110)*$EC26*$GG$5+SUMIF($GJ$7:$GJ$110,$DK26,GS$7:GS$110)*$ED26*$GU$5 -> 4.600454 | ... DW26: =SUMIF($EF$7:$EF$110,$DK26,ES$7:ES$110)*$DZ26*$EQ$5+SUMIF($ET$7:$ET$110,$DK26,FG$7:FG$110)*$EA26*$FE$5+SUMIF($FH$7:$FH$110,$DK26,FU$7:FU$110)*$EB26*$FS$5+SUMIF($FV$7:$FV$110,$DK26,GI$7:GI$110)*$EC26*$GG$5+SUMIF($GJ$7:$GJ$110,$DK26,GW$7:GW$110)*$ED26*$GU$5 -> 0 | DY26: acoff | EB26: 1 | EF26: acoff | EG26: acoff | ET26: acoff | EU26: acoff | FH26: acoff | FI26: acoff | FJ26: 5524.926 | FK26: 4243.023 | FL26: 289.4159 | FM26: 48.76998 | FN26: 19.72655 | FO26: 59.96239 | FP26: 1.235931 | FQ26: 4.600454 | FR26: 55.92464 | FS26: 1.143728 | FV26: acoff | FW26: acoff | GJ26: acoff | GK26: acoff
