Workbook

Sheet Notes
A1: Exercise 2x - Detailed SAM Analysis
A7: Activities and commodities | F7: Factors | I7: Households | M7: Other accounts
A8: acere | B8: ccere | C8: Cereals | F8: flab-n | G8: Labor - uneducated | I8: hhd-1 | J8: Household - quintile 1 | M8: trc | N8: Transaction costs
A9: apoil | B9: cpoil | C9: Pulses and oilseeds | F9: flab-p | G9: Labor - primary | I9: hhd-2 | J9: Household - quintile 2 | M9: ent | N9: Enterprises
A10: aroot | B10: croot | C10: Root crops | F10: flab-s | G10: Labor - secondary | I10: hhd-3 | J10: Household - quintile 3 | M10: gov | N10: Government
A11: ahort | B11: chort | C11: Vegetables & fruits | F11: flab-t | G11: Labor - tertiary | I11: hhd-4 | J11: Household - quintile 4 | M11: atax | N11: Taxes - activity
A12: axcrp | B12: cxcrp | C12: Export-oriented crops | F12: flnd | G12: Land - crops | I12: hhd-5 | J12: Household - quintile 5 | M12: dtax | N12: Taxes - direct
A13: acatt | B13: ccatt | C13: Cattle and milk | F13: fcap | G13: Capital | M13: etax | N13: Taxes - export
A14: apoul | B14: cpoul | C14: Poultry and eggs | M14: ftax | N14: Taxes - factor
A15: aoliv | B15: coliv | C15: Other livestock | M15: mtax | N15: Taxes - import
A16: afore | B16: cfore | C16: Forestry | M16: stax | N16: Taxes - sales
A17: afish | B17: cfish | C17: Fisheries | M17: s-i | N17: Savings-investment
A18: amine | B18: cmine | C18: Mining | M18: dstk | N18: Change in stocks
A19: ameat | B19: cmeat | C19: Meat, fish and dairy | M19: row | N19: Rest of world
A20: afveg | B20: cfveg | C20: Fruits and vegetables | M20: total | N20: Total
A21: afoil | B21: cfoil | C21: Fats and oils
A22: agmll | B22: cgmll | C22: Grain milling
A23: afood | B23: cfood | C23: Other food processing
A24: abeve | B24: cbeve | C24: Beverages and tobacco
A25: atext | B25: ctext | C25: Textiles, clothing and footwear
A26: awood | B26: cwood | C26: Wood and paper products
A27: achem | B27: cchem | C27: Chemicals
A28: anmet | B28: cnmet | C28: Nonmetal minerals
A29: amach | B29: cmach | C29: Metals and machinery
A30: aoman | B30: coman | C30: Other manufacturing
A31: autil | B31: cutil | C31: Electricity and water
A32: acons | B32: ccons | C32: Construction
... A37: aosrv | B37: cosrv | C37: Other services

Sheet Structure
A1: Structure of the Micro SAM
B3: Activities | C3: Commodities | D3: Transaction costs | E3: Labor | F3: Land | G3: Capital | H3: Enterprises | I3: Households | J3: Government | K3: Direct taxes | L3: Factor taxes | M3: Import tariffs | N3: Sales taxes | O3: Investment | P3: Stock changes | Q3: Rest of world | R3: Total
A4: Activities | C4: 30 x 30 | I4: 30 x 5
A5: Commodities | B5: 30 x 30 | D5: 30 x 1 | I5: 30 x 5 | J5: 30 x 1 | O5: 30 x 1 | P5: 30 x 1 | Q5: 30 x 1
A6: Transaction costs | C6: 1 x 30
A7: Labor | B7: 4 x 30
A8: Land | B8: 1 x 30
A9: Capital | B9: 1 x 30
A10: Enterprises | G10: 1 x 1 | J10: 1 x 1
A11: Households | E11: 5 x 4 | F11: 5 x 1 | G11: 5 x 1 | H11: 5 x 1 | J11: 5 x 1 | Q11: 5 x 1
A12: Government | H12: 1 x 1 | I12: 1 x 5 | K12: 1 x 1 | L12: 1 x 1 | M12: 1 x 1 | N12: 1 x 1
A13: Direct taxes | H13: 1 x 1 | I13: 1 x 5
A14: Factor taxes | G14: 1 x 1
A15: Import tariffs | C15: 1 x 30
A16: Sales taxes | C16: 1 x 30
A17: Savings | H17: 1 x 1 | I17: 1 x 5 | J17: 1 x 1 | Q17: 1 x 1
A18: Stock changes | O18: 1 x 1
A19: Rest of world | C19: 1 x 30 | E19: 1 x 4 | G19: 1 x 1 | H19: 1 x 1 | I19: 1 x 5 | J19: 1 x 1
A20: Total

Sheet SAM
A1: 30-Sector Social Accounting Matrix
C4: Cereals | D4: Pulses and oilseeds | E4: Root crops | F4: Vegetables & fruits | G4: Export-oriented crops | H4: Cattle and milk | I4: Poultry and eggs | J4: Other livestock | K4: Forestry | L4: Fisheries | M4: Mining | N4: Meat, fish and dairy | O4: Fruits and vegetables | P4: Fats and oils | Q4: Grain milling | R4: Other food processing | S4: Beverages and tobacco | T4: Textiles, clothing and footwear | U4: Wood and paper products | V4: Chemicals | W4: Nonmetal minerals | X4: Metals and machinery | Y4: Other manufacturing | Z4: Electricity and water | AA4: Construction | AB4: Trade, hotels and food services | AC4: Transport and communication | AD4: Finance, business and real estate | AE4: Government, health and education | AF4: Other services | AG4: Cereals | AH4: Pulses and oilseeds | AI4: Root crops | AJ4: Vegetables & fruits | AK4: Export-oriented crops | AL4: Cattle and milk | AM4: Poultry and eggs | AN4: Other livestock | AO4: Forestry | AP4: Fisheries | AQ4: Mining | AR4: Meat, fish and dairy | AS4: Fruits and vegetables | AT4: Fats and oils | AU4: Grain milling | AV4: Other food processing | AW4: Beverages and tobacco | AX4: Textiles, clothing and footwear | AY4: Wood and paper products | AZ4: Chemicals | BA4: Nonmetal minerals | BB4: Metals and machinery | BC4: Other manufacturing | BD4: Electricity and water | BE4: Construction | BF4: Trade, hotels and food services | BG4: Transport and communication | BH4: Finance, business and real estate | BI4: Government, health and education | BJ4: Other services | BK4: Transaction costs | BL4: Labor - uneducated | BM4: Labor - primary | BN4: Labor - secondary | BO4: Labor - tertiary | BP4: Land - crops | BQ4: Capital | BR4: Enterprise | BS4: Household - quintile 1 | BT4: Household - quintile 2 | BU4: Household - quintile 3 | BV4: Household - quintile 4 | BW4: Household - quintile 5 | BX4: Government | BY4: Taxes - direct | BZ4: Taxes - factor | CA4: Taxes - import | CB4: Taxes - sales | CC4: Savings-investment | CD4: Change in stocks | CE4: Rest of world | CF4: Total
C5: acere | D5: apoil | E5: aroot | F5: ahort | G5: axcrp | H5: acatt | I5: apoul | J5: aoliv | K5: afore | L5: afish | M5: amine | N5: ameat | O5: afveg | P5: afoil | Q5: agmll | R5: afood | S5: abeve | T5: atext | U5: awood | V5: achem | W5: anmet | X5: amach | Y5: aoman | Z5: autil | AA5: acons | AB5: atrad | AC5: atran | AD5: afbsv | AE5: agsrv | AF5: aosrv | AG5: ccere | AH5: cpoil | AI5: croot | AJ5: chort | AK5: cxcrp | AL5: ccatt | AM5: cpoul | AN5: coliv | AO5: cfore | AP5: cfish | AQ5: cmine | AR5: cmeat | AS5: cfveg | AT5: cfoil | AU5: cgmll | AV5: cfood | AW5: cbeve | AX5: ctext | AY5: cwood | AZ5: cchem | BA5: cnmet | BB5: cmach | BC5: coman | BD5: cutil | BE5: ccons | BF5: ctrad | BG5: ctran | BH5: cfbsv | BI5: cgsrv | BJ5: cosrv | BK5: trc | BL5: flab-n | BM5: flab-p | BN5: flab-s | BO5: flab-t | BP5: flnd | BQ5: fcap | BR5: ent | BS5: hhd-1 | BT5: hhd-2 | BU5: hhd-3 | BV5: hhd-4 | BW5: hhd-5 | BX5: gov | BY5: dtax | BZ5: ftax | CA5: mtax | CB5: stax | CC5: s-i | CD5: dstk | CE5: row | CF5: total
A6: =VLOOKUP(B6,Notes!$A$8:$C$37,3,0) -> Cereals | B6: acere | AG6: 969.53395 | CF6: 969.53395
A7: =VLOOKUP(B7,Notes!$A$8:$C$37,3,0) -> Pulses and oilseeds | B7: apoil | AH7: 74.351835 | BS7: 14.77499 | BT7: 13.761288 | BU7: 12.052192 | BV7: 9.8723053 | BW7: 7.6293315 | CF7: 132.44194
A8: =VLOOKUP(B8,Notes!$A$8:$C$37,3,0) -> Root crops | B8: aroot | AI8: 242.53103 | BS8: 0.21788978 | BT8: 0.29512099 | BU8: 0.31696875 | BV8: 0.29258783 | BW8: 0.28924826 | CF8: 243.94285
A9: =VLOOKUP(B9,Notes!$A$8:$C$37,3,0) -> Vegetables & fruits | B9: ahort | AJ9: 246.45957 | BS9: 2.1688955 | BT9: 2.877557 | BU9: 3.4852292 | BV9: 4.1966037 | BW9: 4.241083 | CF9: 263.42893
A10: =VLOOKUP(B10,Notes!$A$8:$C$37,3,0) -> Export-oriented crops | B10: axcrp | AK10: 281.47193 | BS10: 0.2431864 | BT10: 0.40081479 | BU10: 0.42775311 | BV10: 0.51922648 | BW10: 0.4949684 | CF10: 283.55788
A11: =VLOOKUP(B11,Notes!$A$8:$C$37,3,0) -> Cattle and milk | B11: acatt | AL11: 296.85477 | BS11: 4.0473873 | BT11: 5.6346297 | BU11: 6.4581882 | BV11: 7.8957979 | BW11: 7.7989888 | CF11: 328.68976
A12: =VLOOKUP(B12,Notes!$A$8:$C$37,3,0) -> Poultry and eggs | B12: apoul | AM12: 291.72804 | BS12: 1.6348228 | BT12: 2.255715 | BU12: 2.7789321 | BV12: 2.7799192 | BW12: 2.9881319 | CF12: 304.16557
A13: =VLOOKUP(B13,Notes!$A$8:$C$37,3,0) -> Other livestock | B13: aoliv | AN13: 214.76319 | BS13: 0.56908462 | BT13: 1.134716 | BU13: 3.7144439 | BV13: 5.7918237 | BW13: 12.560758 | CF13: 238.53401
A14: =VLOOKUP(B14,Notes!$A$8:$C$37,3,0) -> Forestry | B14: afore | AO14: 377.39082 | BS14: 12.286033 | BT14: 15.181252 | BU14: 17.581972 | BV14: 18.149081 | BW14: 18.219826 | CF14: 458.80898
A15: =VLOOKUP(B15,Notes!$A$8:$C$37,3,0) -> Fisheries | B15: afish | AP15: 1199.0117 | BS15: 4.4799055 | BT15: 6.4840277 | BU15: 6.3349985 | BV15: 6.3085901 | BW15: 5.9300739 | CF15: 1228.5493
A16: =VLOOKUP(B16,Notes!$A$8:$C$37,3,0) -> Mining | B16: amine | AQ16: 517.75716 | CF16: 517.75716
A17: =VLOOKUP(B17,Notes!$A$8:$C$37,3,0) -> Meat, fish and dairy | B17: ameat | AR17: 135.36841 | BS17: 0.011182487 | BT17: 0.025454126 | BU17: 0.026304269 | BV17: 0.032435584 | BW17: 0.088365274 | CF17: 135.55216
A18: =VLOOKUP(B18,Notes!$A$8:$C$37,3,0) -> Fruits and vegetables | B18: afveg | AS18: 14.570814 | CF18: 14.570814
A19: =VLOOKUP(B19,Notes!$A$8:$C$37,3,0) -> Fats and oils | B19: afoil | AT19: 129.34793 | BS19: 0.13118549 | BT19: 0.14309611 | BU19: 0.18376864 | BV19: 0.27325234 | BW19: 0.18900089 | CF19: 130.26823
A20: =VLOOKUP(B20,Notes!$A$8:$C$37,3,0) -> Grain milling | B20: agmll | AU20: 832.39335 | BS20: 26.054551 | BT20: 34.194055 | BU20: 33.448208 | BV20: 32.306775 | BW20: 26.443203 | CF20: 984.84014
A21: =VLOOKUP(B21,Notes!$A$8:$C$37,3,0) -> Other food processing | B21: afood | AV21: 405.26453 | BS21: 0.13282444 | BT21: 0.19685539 | BU21: 0.2915151 | BV21: 0.35458652 | BW21: 0.7404851 | CF21: 406.98079
A22: =VLOOKUP(B22,Notes!$A$8:$C$37,3,0) -> Beverages and tobacco | B22: abeve | AW22: 289.16367 | CF22: 289.16367
A23: =VLOOKUP(B23,Notes!$A$8:$C$37,3,0) -> Textiles, clothing and footwear | B23: atext | AX23: 3548.1146 | CF23: 3548.1146
A24: =VLOOKUP(B24,Notes!$A$8:$C$37,3,0) -> Wood and paper products | B24: awood | AY24: 451.88793 | CF24: 451.88793
A25: =VLOOKUP(B25,Notes!$A$8:$C$37,3,0) -> Chemicals | B25: achem | AZ25: 401.13925 | CF25: 401.13925
A26: =VLOOKUP(B26,Notes!$A$8:$C$37,3,0) -> Nonmetal minerals | B26: anmet | BA26: 793.09756 | CF26: 793.09756
A27: =VLOOKUP(B27,Notes!$A$8:$C$37,3,0) -> Metals and machinery | B27: amach | BB27: 1767.9933 | CF27: 1767.9933
A28: =VLOOKUP(B28,Notes!$A$8:$C$37,3,0) -> Other manufacturing | B28: aoman | BC28: 546.81909 | CF28: 546.81909
A29: =VLOOKUP(B29,Notes!$A$8:$C$37,3,0) -> Electricity and water | B29: autil | BD29: 1038.6952 | CF29: 1038.6952
A30: =VLOOKUP(B30,Notes!$A$8:$C$37,3,0) -> Construction | B30: acons | BE30: 3926.0191 | CF30: 3926.0191
A31: =VLOOKUP(B31,Notes!$A$8:$C$37,3,0) -> Trade, hotels and food services | B31: atrad | BF31: 3220.384 | CF31: 3220.384
A32: =VLOOKUP(B32,Notes!$A$8:$C$37,3,0) -> Transport and communication | B32: atran | BG32: 2859.1981 | CF32: 2859.1981
A33: =VLOOKUP(B33,Notes!$A$8:$C$37,3,0) -> Finance, business and real estate | B33: afbsv | BH33: 2508.2331 | CF33: 2508.2331
A34: =VLOOKUP(B34,Notes!$A$8:$C$37,3,0) -> Government, health and education | B34: agsrv | BI34: 2262.4773 | CF34: 2262.4773
A35: =VLOOKUP(B35,Notes!$A$8:$C$37,3,0) -> Other services | B35: aosrv | BJ35: 1998.7722 | CF35: 1998.7722
A36: =VLOOKUP(B36,Notes!$B$8:$C$37,2,0) -> Cereals | B36: ccere | C36: 76.166746 | H36: 46.53707 | I36: 11.91275 | J36: 22.035207 | O36: 0.021601231 | Q36: 842.25167 | R36: 69.31527 | AB36: 1.7216086 | CE36: 3.2781518e-05 | CF36: 1069.962
A37: =VLOOKUP(B37,Notes!$B$8:$C$37,2,0) -> Pulses and oilseeds | B37: cpoil | D37: 12.285982 | H37: 4.256976 | I37: 15.425749 | J37: 2.0543881 | O37: 0.022248977 | P37: 38.560376 | R37: 14.989752 | AB37: 2.491125 | BS37: 8.7673975 | BT37: 13.519074 | BU37: 18.321062 | BV37: 28.467058 | BW37: 74.211649 | CE37: 1.4929173 | CF37: 234.86576
A38: =VLOOKUP(B38,Notes!$B$8:$C$37,2,0) -> Root crops | B38: croot | E38: 16.041846 | O38: 0.02208082 | R38: 12.426866 | AB38: 11.716584 | BS38: 14.972512 | BT38: 20.067856 | BU38: 26.251144 | BV38: 39.649146 | BW38: 99.844176 | CE38: 1.5388236 | CF38: 242.53103
A39: =VLOOKUP(B39,Notes!$B$8:$C$37,2,0) -> Vegetables & fruits | B39: chort | F39: 12.045377 | N39: 1.1247402 | O39: 7.625098 | P39: 3.9833823 | R39: 2.6797187 | AB39: 13.832118 | BS39: 44.110106 | BT39: 67.041442 | BU39: 93.294094 | BV39: 138.85002 | BW39: 337.12326 | CE39: 2.7266931 | CF39: 724.43605
A40: =VLOOKUP(B40,Notes!$B$8:$C$37,2,0) -> Export-oriented crops | B40: cxcrp | G40: 39.217189 | H40: 4.3148955 | J40: 2.0807402 | N40: 0.17076597 | O40: 0.086731209 | P40: 0.63190806 | R40: 33.123757 | S40: 25.208417 | T40: 140.11263 | U40: 2.6039802 | V40: 10.616452 | Y40: 31.664381 | AB40: 18.053364 | AE40: 1.786524 | AF40: 3.608282 | BS40: 34.675371 | BT40: 52.200432 | BU40: 67.523348 | BV40: 93.772653 | BW40: 186.1576 | CE40: 19.558832 | CF40: 767.16825
A41: =VLOOKUP(B41,Notes!$B$8:$C$37,2,0) -> Cattle and milk | B41: ccatt | C41: 7.4343915 | D41: 3.486659 | E41: 3.3496726 | F41: 3.5428494 | G41: 2.1263618 | H41: 6.3608092 | I41: 0.70564461 | J41: 3.0727469 | N41: 17.7265 | R41: 2.660695 | T41: 23.525761 | Y41: 8.7364229 | AB41: 60.967344 | AE41: 6.702686 | BS41: 8.8757688 | BT41: 17.793366 | BU41: 31.016927 | BV41: 53.571237 | BW41: 132.48333 | CE41: 0.0029315303 | CF41: 394.1421
A42: =VLOOKUP(B42,Notes!$B$8:$C$37,2,0) -> Poultry and eggs | B42: cpoul | I42: 100.35734 | N42: 2.5922074 | R42: 4.6210309 | BS42: 13.596365 | BT42: 22.467029 | BU42: 32.067258 | BV42: 46.26297 | BW42: 107.39434 | CE42: 0.028450019 | CF42: 329.38699
A43: =VLOOKUP(B43,Notes!$B$8:$C$37,2,0) -> Other livestock | B43: coliv | N43: 33.244918 | BS43: 9.2498738 | BT43: 16.887152 | BU43: 27.41402 | BV43: 47.773365 | BW43: 80.483361 | CE43: 0.29034971 | CF43: 215.34304
A44: =VLOOKUP(B44,Notes!$B$8:$C$37,2,0) -> Forestry | B44: cfore | F44: 3.2837619 | G44: 0.55080035 | K44: 150.83674 | L44: 3.9941074 | N44: 6.3300242e-06 | R44: 0.53892872 | T44: 0.36971159 | U44: 132.38415 | AA44: 218.84705 | AB44: 2.0753247 | AD44: 9.5719605 | AE44: 0.048894587 | BS44: 14.876139 | BT44: 24.811462 | BU44: 32.497829 | BV44: 39.728321 | BW44: 53.791192 | CE44: 0.0023411786 | CF44: 688.20871
A45: =VLOOKUP(B45,Notes!$B$8:$C$37,2,0) -> Fisheries | B45: cfish | I45: 2.0692301 | L45: 378.81124 | N45: 17.46592 | R45: 7.3379092 | Y45: 3.704572 | AB45: 77.045563 | AE45: 5.8217642 | BS45: 77.099306 | BT45: 130.19471 | BU45: 173.86854 | BV45: 230.08472 | BW45: 399.77178 | CE45: 1.6948614 | CF45: 1504.9701
A46: =VLOOKUP(B46,Notes!$B$8:$C$37,2,0) -> Mining | B46: cmine | L46: 13.318282 | M46: 9.9289247 | N46: 0.18845165 | O46: 0.031767037 | R46: 10.014087 | S46: 2.570864 | T46: 0.23835983 | V46: 33.176492 | W46: 98.853985 | X46: 41.024603 | Y46: 5.1064653 | Z46: 159.18452 | AA46: 155.09524 | AB46: 12.107815 | AC46: 88.758564 | AD46: 3.5118364 | AE46: 0.17299333 | AF46: 0.027013938 | CE46: 1.5284415 | CF46: 634.8387
A47: =VLOOKUP(B47,Notes!$B$8:$C$37,2,0) -> Meat, fish and dairy | B47: cmeat | L47: 0.47954927 | N47: 15.686946 | R47: 5.9614606 | V47: 15.537992 | AB47: 30.946888 | AF47: 5.3012349 | BS47: 3.5425505 | BT47: 7.4232141 | BU47: 12.466932 | BV47: 17.633566 | BW47: 48.631431 | CE47: 15.746724 | CF47: 179.35849
A48: =VLOOKUP(B48,Notes!$B$8:$C$37,2,0) -> Fruits and vegetables | B48: cfveg | N48: 0.0034146126 | O48: 0.17264127 | R48: 0.87324432 | AB48: 2.1621409 | BS48: 0.61814294 | BT48: 0.92885924 | BU48: 1.2791249 | BV48: 1.8873836 | BW48: 4.5424491 | CE48: 3.9834505 | CF48: 16.450851
A49: =VLOOKUP(B49,Notes!$B$8:$C$37,2,0) -> Fats and oils | B49: cfoil | H49: 11.633743 | I49: 2.0458729 | J49: 5.5775346 | L49: 23.289207 | N49: 0.088896814 | O49: 0.012922013 | P49: 41.788545 | R49: 11.68765 | U49: 1.0597974 | BS49: 44.957152 | BT49: 66.096233 | BU49: 91.226218 | BV49: 138.5233 | BW49: 318.59433 | CE49: 1.5043425 | CF49: 758.08575
A50: =VLOOKUP(B50,Notes!$B$8:$C$37,2,0) -> Grain milling | B50: cgmll | H50: 2.5949321 | I50: 4.2118522 | N50: 0.98860243 | O50: 0.012407823 | Q50: 0.068304383 | R50: 17.402598 | T50: 0.019125172 | AB50: 6.2462095 | BS50: 110.38183 | BT50: 133.1062 | BU50: 154.8752 | BV50: 198.72791 | BW50: 388.02508 | CE50: 0.44563616 | CF50: 1017.1059
A51: =VLOOKUP(B51,Notes!$B$8:$C$37,2,0) -> Other food processing | B51: cfood | H51: 90.353371 | I51: 36.291526 | J51: 40.468782 | L51: 11.328473 | N51: 0.2809481 | O51: 0.065735068 | R51: 15.095841 | S51: 22.323916 | T51: 0.39420725 | U51: 0.35694512 | V51: 2.1341046 | AA51: 0.95248637 | AB51: 22.911414 | AC51: 6.7048569 | AD51: 9.184695 | AE51: 1.7920431 | AF51: 16.999961 | BS51: 20.583247 | BT51: 32.27624 | BU51: 45.299489 | BV51: 68.151025 | BW51: 170.30824 | CE51: 8.1196434 | CF51: 622.37719
A52: =VLOOKUP(B52,Notes!$B$8:$C$37,2,0) -> Beverages and tobacco | B52: cbeve | N52: 2.6586101e-05 | S52: 32.177355 | AB52: 8.2545343 | BS52: 19.251018 | BT52: 34.087249 | BU52: 47.095033 | BV52: 70.27426 | BW52: 179.15912 | CE52: 2.5256185 | CF52: 392.82422
A53: =VLOOKUP(B53,Notes!$B$8:$C$37,2,0) -> Textiles, clothing and footwear | B53: ctext | H53: 0.055781057 | I53: 0.0083072631 | J53: 0.026961082 | K53: 0.0083955008 | L53: 1.4740267 | N53: 1.2660048e-06 | S53: 5.4817888 | T53: 1225.1316 | U53: 0.51492513 | V53: 28.544115 | W53: 48.067485 | X53: 75.843675 | Y53: 69.674946 | Z53: 11.434774 | AA53: 40.982488 | AB53: 40.649085 | AC53: 62.749684 | AD53: 11.387698 | AE53: 13.956174 | AF53: 32.793142 | BS53: 5.4036494 | BT53: 8.8960469 | BU53: 12.072811 | BV53: 16.250724 | BW53: 30.477151 | CE53: 2853.3012 | CF53: 4595.1866
A54: =VLOOKUP(B54,Notes!$B$8:$C$37,2,0) -> Wood and paper products | B54: cwood | C54: 4.1120412 | G54: 0.019488197 | I54: 0.056078743 | L54: 9.3796207 | M54: 1.1971236 | N54: 0.83608005 | O54: 0.11689016 | P54: 0.15516696 | Q54: 5.3021503 | R54: 0.86884039 | S54: 17.440604 | T54: 8.6635906 | U54: 136.36298 | V54: 11.273803 | W54: 12.737179 | X54: 30.33137 | Y54: 27.202708 | Z54: 41.923355 | AA54: 35.163651 | AB54: 23.13813 | AC54: 48.786074 | AD54: 70.608153 | AE54: 27.561432 | AF54: 20.485448 | BS54: 5.47544 | BT54: 7.4411647 | BU54: 9.6192123 | BV54: 13.227466 | BW54: 17.512503 | CE54: 4.1227388 | CF54: 591.12049
A55: =VLOOKUP(B55,Notes!$B$8:$C$37,2,0) -> Chemicals | B55: cchem | C55: 76.514339 | D55: 9.6487069 | E55: 39.743309 | F55: 10.496154 | G55: 24.686491 | H55: 2.3637136 | I55: 4.0503676 | J55: 1.1399206 | K55: 2.9135065 | L55: 15.038785 | M55: 14.902631 | N55: 0.99985762 | O55: 0.15489197 | P55: 0.86638508 | Q55: 3.5350426 | R55: 11.407348 | S55: 8.7221308 | T55: 62.073421 | U55: 5.3699245 | V55: 65.242269 | W55: 36.508057 | X55: 95.731353 | Y55: 7.8628622 | Z55: 69.397309 | AA55: 91.846996 | AB55: 20.079675 | AC55: 227.49451 | AD55: 28.82522 | AE55: 340.18846 | AF55: 5.5325085 | BS55: 28.384114 | BT55: 43.840748 | BU55: 62.067118 | BV55: 93.530782 | BW55: 212.01622 | CE55: 30.439696 | CF55: 1753.6148
A56: =VLOOKUP(B56,Notes!$B$8:$C$37,2,0) -> Nonmetal minerals | B56: cnmet | H56: 0.079033721 | J56: 0.038197763 | M56: 0.71381978 | R56: 0.41079405 | S56: 6.3351386 | T56: 0.062572172 | V56: 16.573089 | W56: 22.463233 | X56: 9.6739016 | Y56: 32.514299 | Z56: 50.101297 | AA56: 854.6196 | AB56: 24.98047 | AC56: 16.095782 | AD56: 29.707636 | AE56: 31.355298 | AF56: 26.243042 | BS56: 0.67703287 | BT56: 1.1285424 | BU56: 1.5686992 | BV56: 2.3837133 | BW56: 3.7101157 | CE56: 3.3648214 | CF56: 1134.8001
A57: =VLOOKUP(B57,Notes!$B$8:$C$37,2,0) -> Metals and machinery | B57: cmach | C57: 18.370356 | D57: 1.1962541 | E57: 11.663445 | F57: 0.84051269 | G57: 2.0579387 | H57: 0.70728396 | I57: 0.72630627 | J57: 0.34161786 | K57: 11.074965 | L57: 5.9825565 | M57: 74.636949 | N57: 0.22399456 | O57: 0.19329287 | P57: 0.92437494 | Q57: 4.1962907 | R57: 2.5103019 | S57: 11.142728 | T57: 64.915585 | U57: 6.0596492 | V57: 15.650883 | W57: 9.567143 | X57: 504.6069 | Y57: 41.58935 | Z57: 107.86965 | AA57: 451.05358 | AB57: 31.382124 | AC57: 116.05038 | AD57: 31.393001 | AE57: 30.357957 | AF57: 16.265919 | BS57: 6.3208197 | BT57: 11.058853 | BU57: 18.404994 | BV57: 31.198084 | BW57: 66.173974 | CC57: 1563.4579 | CE57: 44.68928 | CF57: 3314.8552
A58: =VLOOKUP(B58,Notes!$B$8:$C$37,2,0) -> Other manufacturing | B58: coman | F58: 0.010629165 | G58: 0.034820439 | H58: 0.037190808 | I58: 0.0083074225 | J58: 0.01797534 | K58: 0.72917368 | L58: 0.25753961 | M58: 1.2963167 | N58: 0.15526812 | O58: 0.020181288 | P58: 0.079808531 | Q58: 0.20253885 | R58: 1.055222 | T58: 10.419848 | U58: 3.2819012 | V58: 0.023627187 | X58: 9.7284654 | Y58: 58.806087 | AA58: 49.878702 | AB58: 34.069476 | AC58: 33.615636 | AD58: 39.187525 | AE58: 33.92288 | AF58: 20.038986 | BS58: 13.009429 | BT58: 22.941447 | BU58: 41.114975 | BV58: 69.462346 | BW58: 169.11151 | CE58: 6.3634921 | CF58: 618.8813
A59: =VLOOKUP(B59,Notes!$B$8:$C$37,2,0) -> Electricity and water | B59: cutil | C59: 1.7292626 | E59: 0.62574731 | F59: 0.03517875 | G59: 0.078578274 | I59: 0.1235946 | L59: 0.16623417 | M59: 4.6753347 | N59: 0.40027559 | O59: 0.04917416 | P59: 0.15208814 | Q59: 0.47883112 | R59: 2.2431642 | S59: 10.777147 | T59: 115.58695 | U59: 4.0309046 | V59: 20.794088 | W59: 79.383645 | X59: 78.560099 | Y59: 6.3258121 | Z59: 26.459174 | AA59: 328.59295 | AB59: 3.1452162 | AC59: 52.108063 | AD59: 23.715856 | AE59: 6.9057221 | AF59: 2.0531584 | BS59: 14.311375 | BT59: 24.315552 | BU59: 40.871865 | BV59: 62.20928 | BW59: 127.79093 | CF59: 1038.6952
A60: =VLOOKUP(B60,Notes!$B$8:$C$37,2,0) -> Construction | B60: ccons | N60: 0.0092619753 | O60: 0.014389265 | P60: 0.10841261 | Q60: 0.22999938 | R60: 0.11265965 | S60: 0.80016661 | T60: 1.9849437 | U60: 0.32202191 | V60: 0.25734108 | W60: 1.110259 | X60: 1.3588933 | Y60: 0.3930006 | Z60: 0.54384427 | AA60: 19.254694 | AB60: 1.9162945 | AC60: 6.225595 | AD60: 3.7255908 | AE60: 0.42023247 | AF60: 0.5905166 | BS60: 2.877212 | BT60: 6.740197 | BU60: 13.859799 | BV60: 30.665063 | BW60: 186.76685 | CC60: 3654.544 | CE60: 8.2793569 | CF60: 3943.1106
A61: =VLOOKUP(B61,Notes!$B$8:$C$37,2,0) -> Trade, hotels and food services | B61: ctrad | C61: 23.374347 | D61: 4.1048667 | E61: 21.159533 | F61: 14.543567 | G61: 6.2483742 | H61: 12.199796 | I61: 3.5708165 | J61: 5.8256253 | K61: 39.423036 | L61: 26.572649 | M61: 3.3028481 | N61: 0.37784785 | P61: 4.4153079 | Q61: 34.870882 | R61: 11.320749 | S61: 5.8441177 | T61: 103.21654 | U61: 19.589942 | V61: 6.1103457 | W61: 34.886249 | X61: 29.078121 | Y61: 11.452453 | Z61: 18.413041 | AA61: 28.943039 | AB61: 37.618953 | AC61: 61.052896 | AD61: 54.371288 | AE61: 12.397975 | AF61: 19.733399 | BK61: 2265.4604 | BS61: 14.637419 | BT61: 26.420591 | BU61: 39.963818 | BV61: 66.288683 | BW61: 173.86001 | CE61: 16.910688 | CF61: 3257.5603
A62: =VLOOKUP(B62,Notes!$B$8:$C$37,2,0) -> Transport and communication | B62: ctran | C62: 10.424411 | D62: 1.574686 | E62: 9.1116773 | F62: 6.2921567 | G62: 3.8012231 | H62: 5.3869889 | I62: 2.9331858 | J62: 2.5897059 | K62: 17.509502 | L62: 16.281846 | M62: 19.629748 | N62: 0.28728181 | O62: 0.048156999 | P62: 2.3100589 | Q62: 15.712369 | R62: 18.541836 | S62: 45.826121 | T62: 158.66353 | U62: 25.61057 | V62: 29.735614 | W62: 31.858324 | X62: 180.40802 | Y62: 12.5573 | Z62: 83.956013 | AA62: 39.276408 | AB62: 68.273984 | AC62: 93.573576 | AD62: 99.719479 | AE62: 56.929125 | AF62: 20.652445 | BK62: 1502.0643 | BS62: 47.513724 | BT62: 75.677917 | BU62: 105.85387 | BV62: 146.31704 | BW62: 298.96366 | CE62: 31.916776 | CF62: 3287.7826
A63: =VLOOKUP(B63,Notes!$B$8:$C$37,2,0) -> Finance, business and real estate | B63: cfbsv | C63: 2.0892592 | D63: 1.0027729 | E63: 0.36094624 | F63: 2.2856943 | G63: 3.3321332 | H63: 5.2858273 | I63: 3.9689407 | J63: 2.5441092 | K63: 0.41138562 | L63: 10.006524 | M63: 50.889339 | N63: 0.76103271 | O63: 0.10411118 | P63: 0.26804734 | Q63: 3.0293881 | R63: 3.2530846 | S63: 26.36555 | T63: 179.57561 | U63: 2.256502 | V63: 33.777041 | W63: 114.8821 | X63: 127.96656 | Y63: 31.803917 | Z63: 124.54081 | AA63: 206.19647 | AB63: 100.99367 | AC63: 191.15146 | AD63: 154.58651 | AE63: 54.105132 | AF63: 57.688667 | BS63: 58.4047 | BT63: 102.21502 | BU63: 159.38814 | BV63: 231.98875 | BW63: 476.86023 | CE63: 88.352599 | CF63: 2612.692
A64: =VLOOKUP(B64,Notes!$B$8:$C$37,2,0) -> Government, health and education | B64: cgsrv | C64: 0.10698531 | D64: 0.01726161 | E64: 0.18204118 | F64: 2.6703163 | G64: 1.238345 | H64: 24.949598 | I64: 5.6438617 | J64: 11.782669 | K64: 10.201568 | L64: 4.7747854 | M64: 12.886468 | N64: 0.051783045 | P64: 0.13251169 | Q64: 1.7614578 | R64: 0.74038099 | S64: 3.5454254 | T64: 29.024264 | U64: 0.13761487 | V64: 3.5561604 | W64: 5.8346763 | X64: 19.000594 | Y64: 2.1887417 | Z64: 7.6913092 | AA64: 28.670562 | AB64: 15.829376 | AC64: 21.198722 | AD64: 19.183688 | AE64: 136.53844 | AF64: 13.91264 | BS64: 42.202462 | BT64: 76.839803 | BU64: 118.9263 | BV64: 172.02485 | BW64: 342.31958 | BX64: 1028.2672 | CE64: 113.87969 | CF64: 2277.9122
A65: =VLOOKUP(B65,Notes!$B$8:$C$37,2,0) -> Other services | B65: cosrv | C65: 8.2829712 | D65: 1.6323548 | E65: 6.8339725 | F65: 6.945628 | G65: 5.5688954 | H65: 0.17204632 | I65: 2.5124871 | J65: 0.083142242 | K65: 9.6068342 | L65: 2.3055937 | M65: 38.03222 | N65: 0.015224614 | P65: 0.12498888 | Q65: 2.4753838 | R65: 0.8055749 | S65: 8.3789891 | T65: 120.72902 | U65: 13.801823 | V65: 11.678092 | W65: 44.728247 | X65: 65.647788 | Y65: 12.775069 | Z65: 99.124735 | AA65: 121.46865 | AB65: 186.70016 | AC65: 128.81516 | AD65: 132.26292 | AE65: 25.403392 | AF65: 25.583461 | BS65: 30.335613 | BT65: 57.938874 | BU65: 93.34661 | BV65: 162.85289 | BW65: 572.07263 | CE65: 0.55547716 | CF65: 1999.5969
A66: Transaction costs | B66: trc | AG66: 23.515639 | AH66: 86.939044 | AJ66: 433.20312 | AK66: 348.85597 | AL66: 97.273093 | AM66: 33.02359 | AO66: 305.02154 | AP66: 304.46295 | AQ66: 13.240773 | AR66: 7.9816724 | AT66: 35.450014 | AU66: 158.08174 | AV66: 65.10706 | AW66: 102.55226 | AX66: 558.71577 | AY66: 72.66559 | AZ66: 326.3253 | BA66: 254.26803 | BB66: 492.7256 | BC66: 48.115938 | CF66: 3767.5247
A67: Labor - uneducated | B67: flab-n | C67: 253.06585 | D67: 31.335264 | E67: 33.111534 | F67: 35.857197 | G67: 58.190466 | H67: 26.851769 | I67: 19.983084 | J67: 34.764707 | K67: 18.639614 | L67: 179.32328 | M67: 22.692447 | N67: 15.668464 | O67: 2.9948565 | P67: 8.7455259 | Q67: 20.616147 | R67: 51.715013 | S67: 8.1003304 | T67: 380.42853 | U67: 16.939859 | V67: 2.5398979 | W67: 30.299533 | X67: 33.729395 | Y67: 25.505596 | Z67: 7.6321949 | AA67: 716.98742 | AB67: 212.64763 | AC67: 160.97303 | AD67: 63.671539 | AE67: 108.60943 | AF67: 52.182106 | CF67: 2633.8017
A68: Labor - primary | B68: flab-p | C68: 91.093868 | D68: 8.1207166 | E68: 9.9106708 | F68: 6.7002911 | G68: 12.766427 | H68: 5.8375581 | I68: 6.7737852 | J68: 7.09196 | K68: 6.3936705 | L68: 53.273231 | M68: 5.3204366 | N68: 6.2752667 | O68: 1.199449 | P68: 3.5026094 | Q68: 8.2568289 | R68: 20.712018 | S68: 1.7370063 | T68: 186.76159 | U68: 4.6053386 | V68: 10.83904 | W68: 5.5540732 | X68: 31.136714 | Y68: 5.7689655 | Z68: 8.5805369 | AA68: 138.16786 | AB68: 154.23321 | AC68: 50.543723 | AD68: 30.613681 | AE68: 92.703422 | AF68: 23.993462 | CF68: 998.46741
A69: Labor - secondary | B69: flab-s | C69: 45.1545 | D69: 4.1656224 | E69: 7.4408616 | F69: 3.1016722 | G69: 9.2752248 | H69: 2.5135062 | I69: 3.748948 | J69: 2.5688282 | K69: 4.2997017 | L69: 28.901511 | M69: 18.10571 | N69: 3.6497666 | O69: 0.69761322 | P69: 2.0371575 | Q69: 4.8022658 | R69: 12.046346 | S69: 3.3238725 | T69: 153.24938 | U69: 16.274186 | V69: 3.3814819 | W69: 3.735599 | X69: 30.155966 | Y69: 4.6027037 | Z69: 11.515227 | AA69: 143.79215 | AB69: 110.96242 | AC69: 24.82546 | AD69: 61.666956 | AE69: 346.90089 | AF69: 8.3987315 | CE69: 1.1794083 | CF69: 1076.4737
A70: Labor - tertiary | B70: flab-t | C70: 11.968807 | D70: 0.87722305 | E70: 2.1948293 | F70: 1.6242014 | G70: 1.3435815 | H70: 0.71700839 | I70: 0.49774475 | J70: 1.0289632 | K70: 3.0062426 | L70: 2.0200515 | M70: 7.0475093 | N70: 0.43426116 | O70: 0.083004301 | P70: 0.24238766 | Q70: 0.57138928 | R70: 1.4333136 | S70: 1.8442998 | T70: 35.518419 | U70: 2.5561427 | V70: 2.4461737 | W70: 1.1055978 | X70: 14.914618 | Y70: 0.69637005 | Z70: 3.6253497 | AA70: 24.293208 | AB70: 29.914137 | AC70: 8.184354 | AD70: 68.173456 | AE70: 426.77232 | AF70: 10.574353 | CE70: 0.80518761 | CF70: 666.5145
A71: Land - crops | B71: flnd | C71: 321.32354 | D71: 50.448344 | E71: 78.613767 | F71: 145.94398 | G71: 107.83477 | CF71: 704.1644
A72: Capital | B72: fcap | C72: 18.322282 | D72: 2.5452273 | E72: 3.598996 | F72: 7.2097639 | G72: 5.1867693 | H72: 75.480868 | I72: 76.539782 | J72: 93.400233 | K72: 183.75465 | L72: 441.57019 | M72: 232.49933 | N72: 15.844144 | O72: 0.82157001 | P72: 21.23919 | Q72: 36.479201 | R72: 59.075339 | S72: 41.2177 | T72: 547.44943 | U72: 57.768775 | V72: 77.251149 | W72: 211.52218 | X72: 389.09629 | Y72: 145.88707 | Z72: 206.70211 | AA72: 231.93592 | AB72: 1853.3179 | AC72: 1460.2906 | AD72: 1563.1644 | AE72: 501.1241 | AF72: 1616.1137 | CE72: 5.3979776 | CF72: 10181.807
A73: Enterprise | B73: ent | BQ73: 9681.3545 | BX73: 459.8008 | CE73: 48.729248 | CF73: 10189.885
A74: Household - quintile 1 | B74: hhd-1 | BL74: 378.52434 | BM74: 62.926139 | BN74: 36.040268 | BO74: 10.00951 | BP74: 81.088336 | BQ74: 37.761333 | BR74: 244.59221 | BX74: 32.234884 | CE74: 18.708354 | CF74: 901.88537
A75: Household - quintile 2 | B75: hhd-2 | BL75: 514.14414 | BM75: 131.51684 | BN75: 85.387259 | BO75: 23.424652 | BP75: 148.42303 | BQ75: 53.918505 | BR75: 428.91726 | BX75: 42.675429 | CE75: 48.045435 | CF75: 1476.4525
A76: Household - quintile 3 | B76: hhd-3 | BL76: 562.9149 | BM76: 203.08238 | BN76: 192.66879 | BO76: 54.832534 | BP76: 160.08788 | BQ76: 59.029136 | BR76: 764.8425 | BX76: 36.119786 | CE76: 108.46065 | CF76: 2142.0386
A77: Household - quintile 4 | B77: hhd-4 | BL77: 587.01701 | BM77: 213.10816 | BN77: 257.9717 | BO77: 119.32506 | BP77: 168.59714 | BQ77: 59.343608 | BR77: 1444.7663 | BX77: 31.156131 | CE77: 171.17098 | CF77: 3052.4561
A78: Household - quintile 5 | B78: hhd-5 | BL78: 591.11165 | BM78: 387.79989 | BN78: 504.369 | BO78: 458.90006 | BP78: 145.96802 | BQ78: 72.231339 | BR78: 4243.5472 | BX78: 21.987028 | CE78: 393.33357 | CF78: 6819.2478
A79: Government | B79: gov | BR79: 246.79959 | BS79: 0.096306857 | BT79: 0.15502199 | BU79: 0.37281595 | BV79: 0.55181442 | BW79: 2.3140746 | BY79: 501.63124 | CA79: 369.20103 | CB79: 491.32599 | CE79: 21.632158 | CF79: 1634.08
A80: Taxes - direct | B80: dtax | BR80: 353.97184 | BS80: 3.2696438 | BT80: 5.2283594 | BU80: 12.777832 | BV80: 24.598108 | BW80: 101.78545 | CF80: 501.63124
A81: Taxes - factor | B81: ftax
A82: Taxes - import | B82: mtax | AH82: 0.95298845 | AJ82: 8.1368569 | AK82: 4.9711061 | AL82: 0.00012739727 | AM82: 1.0731994 | AQ82: 10.070963 | AR82: 1.4594737 | AT82: 23.772009 | AU82: 0.0018305732 | AV82: 2.8960141 | AW82: 0.017845239 | AX82: 64.455879 | AY82: 11.530818 | AZ82: 84.717509 | BA82: 19.67956 | BB82: 132.9993 | BC82: 2.4655489 | CF82: 369.20103
A83: Taxes - sales | B83: stax | AH83: 1.6825112e-05 | AK83: 0.67532758 | AQ83: 0.01416581 | AR83: 12.034386 | AT83: 258.28412 | AV83: 37.839398 | AX83: 22.756608 | AY83: 4.5560381 | AZ83: 155.16593 | CF83: 491.32599
A84: Savings-investment | B84: s-i | BR84: 2456.4244 | BS84: 136.36018 | BT84: 283.80987 | BU84: 469.74814 | BV84: 626.14743 | BW84: 1368.0581 | BX84: -34.25657 | CE84: -88.289671 | CF84: 5218.0019
A85: Change in stocks | B85: dstk
A86: Rest of world | B86: row | AG86: 76.912372 | AH86: 72.621871 | AJ86: 36.636512 | AK86: 131.19392 | AL86: 0.014106393 | AM86: 3.5621604 | AN86: 0.57985224 | AO86: 5.7963516 | AP86: 1.4954665 | AQ86: 93.755641 | AR86: 22.514545 | AS86: 1.8800369 | AT86: 311.23167 | AU86: 26.628965 | AV86: 111.27019 | AW86: 1.0904457 | AX86: 401.14376 | AY86: 50.480108 | AZ86: 786.26684 | BA86: 67.754973 | BB86: 921.13696 | BC86: 21.480727 | BE86: 17.091489 | BF86: 37.176306 | BG86: 428.58446 | BH86: 104.45891 | BI86: 15.434896 | BJ86: 0.82472438 | BL86: 0.08967179 | BM86: 0.033994343 | BN86: 0.036650185 | BO86: 0.022692501 | BQ86: 218.16844 | BR86: 6.0232095 | BS86: 0.29753865 | BT86: 0.31942544 | BU86: 0.4848774 | BV86: 0.62911981 | BW86: 1.3200212 | BX86: 16.095307 | CF86: 3992.5392
A87: Total | B87: total | C87: 969.53395 | D87: 132.44194 | E87: 243.94285 | F87: 263.42893 | G87: 283.55788 | H87: 328.68976 | I87: 304.16557 | J87: 238.53401 | K87: 458.80898 | L87: 1228.5493 | M87: 517.75716 | N87: 135.55216 | O87: 14.570814 | P87: 130.26823 | Q87: 984.84014 | R87: 406.98079 | S87: 289.16367 | T87: 3548.1146 | U87: 451.88793 | V87: 401.13925 | W87: 793.09756 | X87: 1767.9933 | Y87: 546.81909 | Z87: 1038.6952 | AA87: 3926.0191 | AB87: 3220.384 | AC87: 2859.1981 | AD87: 2508.2331 | AE87: 2262.4773 | AF87: 1998.7722 | AG87: 1069.962 | AH87: 234.86576 | AI87: 242.53103 | AJ87: 724.43605 | AK87: 767.16825 | AL87: 394.1421 | AM87: 329.38699 | AN87: 215.34304 | AO87: 688.20871 | AP87: 1504.9701 | AQ87: 634.8387 | AR87: 179.35849 | AS87: 16.450851 | AT87: 758.08575 | AU87: 1017.1059 | AV87: 622.37719 | AW87: 392.82422 | AX87: 4595.1866 | AY87: 591.12049 | AZ87: 1753.6148 | BA87: 1134.8001 | BB87: 3314.8552 | BC87: 618.8813 | BD87: 1038.6952 | BE87: 3943.1106 | BF87: 3257.5603 | BG87: 3287.7826 | BH87: 2612.692 | BI87: 2277.9122 | BJ87: 1999.5969 | BK87: 3767.5247 | BL87: 2633.8017 | BM87: 998.46741 | BN87: 1076.4737 | BO87: 666.5145 | BP87: 704.1644 | BQ87: 10181.807 | BR87: 10189.885 | BS87: 901.88537 | BT87: 1476.4525 | BU87: 2142.0386 | BV87: 3052.4561 | BW87: 6819.2478 | BX87: 1634.08 | BY87: 501.63124 | CA87: 369.20103 | CB87: 491.32599 | CC87: 5218.0019 | CE87: 3992.5392
C89: =SUM(AF67:AF72) -> 1711.2624
C90: =SUM(C67:AF72) -> 16253.846
C91: =C89/C90 -> 0.10528353

Sheet Ex2x_Question
A1: Questions | C1: Answers | D1: Hints and suggestions
A2: Use the information contained in the SAM to answer the following questions.
A4: GDP
A5: 1 | B5: What is the value of total GDP measured at factor cost? | D5: GDP at factor is the sum of all factor incomes earned during the production process (payments from producers/activities to land, labor and capital)
A6: 2 | B6: What are the shares of agriculture, industry and services in total GDP? | D6: Agriculture = cereals to fisheries; Industry = mining to construction; Services = Trade to other services. First calculate total agricultural GDP, and then divide by national GDP.
A7: 3 | B7: Which is the largest agricultural subsector in terms of GDP? | D7: First calculate GDP for each (by summing across factors), and then calculate shares across totals
A8: 4 | B8: What is the share of food and agriculture-related processing within manufacturing GDP? | D8: Food and Ag-processing includes Meat, fish and dairy; fruit and vegetables; Fats and oils; Grain milling; Other food processing; and beverage and tobaco sectors
A9: 5 | B9: What is the share of the government (incl. health and education) in total GDP? | D9: Divide Government, health and education sector with total GDP
A10: 6 | B10: What is the value of GDP measured at market prices? | D10: GDP mp = C + I + G + X - M
A12: Production technologies
A13: =MAX(A1:A12)+1 -> 7 | B13: What share of labor value-added is generated by uneducated workers? | D13: divide uneducated labor value-added with total labor value added
A14: =MAX(A2:A13)+1 -> 8 | B14: Which is the most capital-intensive sector in the economy? | D14: Treat capital separate from land
A15: =MAX(A4:A14)+1 -> 9 | B15: Which is the most skill-intensive sector of the economy? | D15: Share of labor value added earned by high skill worker to total labor value added
A16: =MAX(A5:A15)+1 -> 10 | B16: Which sector has the highest of production costs associated with petroleum products (chemicals)? | D16: Divide intermediate demand spending on chemical inputs by value of gross output
A17: =MAX(A6:A16)+1 -> 11 | B17: Which sector has the lowest GDP to gross output ratio? | D17: Divide GDP to value of gross output
A19: Transaction costs
A20: =MAX(A8:A19)+1 -> 12 | B20: Which product has the highest transaction costs? (calculate transaction costs as a share of total supply) | D20: Transaction costs are in the account TRC
A21: =MAX(A9:A20)+1 -> 13 | B21: What share of total transaction costs generates demand for transport services? | D21: Divide transaction costs demand on transport services with total demand of transport services
A23: Trade
A24: =MAX(A12:A23)+1 -> 14 | B24: What share of domestic production is exported? | D24: Divide total exports by total gross output
A25: =MAX(A13:A24)+1 -> 15 | B25: What share of domestic demand is supplied by imports? | D25: First subtract exports from total demand
A27: Government finance
A28: =MAX(A16:A27)+1 -> 16 | B28: What is the share of tax collections in total government revenue? | D28: Divide total taxes revenue by total government revenue
A29: =MAX(A17:A28)+1 -> 17 | B29: What share of tax revenues come from indirect and direct taxes? | D29: Divide direct and indirect taxes revenue by total government revenue
A30: =MAX(A18:A29)+1 -> 18 | B30: What is the average direct tax rate on household and enterprise incomes? | D30: Divide tax expenditure spent by enterprise and households by its total income
A31: =MAX(A19:A30)+1 -> 19 | B31: Which imported product faces the highest tariff rate? | D31: Take tariff collection (MTAX) and divide by import value (ROW)
A32: =MAX(A20:A31)+1 -> 20 | B32: What product has the highest sales tax rate? (as a share of intermediate and final demand for goods and services) | D32: First calculate total demand less exports for each product. Then take sales taxes (STAX) and divide by demand less exports
A33: =MAX(A21:A32)+1 -> 21 | B33: What share of government revenues comes from foreign grants? | D33: Divide government revenue from rest of the world by total government revenue
A34: =MAX(A22:A33)+1 -> 22 | B34: What share of government spending are transfers to domestic enterprises? What could this transfer include? | D34: Divied government spending on enterprise with total government spending
A35: =MAX(A23:A34)+1 -> 23 | B35: Does the government run a recurrent deficit or surplus, and what is it as a share of total recurrent expenditures? | D35: Look at value of government spending on savings-investment account
A37: Household incomes and expenditures | K37: Population (millions)
A38: =MAX(A26:A37)+1 -> 24 | B38: What is the total value of consumption spending for each household group? | D38: Consumption spending only includes commodities | K38: 32.105198 | L38: Household - quintile 1
A39: =MAX(A27:A38)+1 -> 25 | B39: What is the average level of per capita consumption for each household quintile? (see population data) | D39: Divide consumption spending by total household population | K39: 32.018407 | L39: Household - quintile 2
A40: =MAX(A28:A39)+1 -> 26 | B40: What share of consumption spending for each quintile is spent on agricultural and food products? | D40: For foods, include from Meat-Beverages | K40: 32.056355 | L40: Household - quintile 3
A41: =MAX(A29:A40)+1 -> 27 | B41: What share of incomes for each household group comes from factors, enterprises, government and rest of world? | D41: First collect on income source values in a single table, and then calculate shares | K41: 32.086998 | L41: Household - quintile 4
A42: =MAX(A30:A41)+1 -> 28 | B42: What is the average marginal propensity to save for households? (average for all groups) | D42: Divide total household savings with total expenditure | K42: 32.010027 | L42: Household - quintile 5
K43: =SUM(K38:K42) -> 160.27698 | L43: All households
A44: Other accounts
A45: =MAX(A35:A44)+1 -> 29 | B45: What share of gross fixed capital formation is demand for construction? | D45: Divide investment demand on construction by total construction demand
A46: =MAX(A36:A45)+1 -> 30 | B46: What share of gross capital formation is changes in stocks? | D46: GCF includes GFCF plus stock changes
A47: =MAX(A37:A46)+1 -> 31 | B47: What is the current account deficit as a share of total GDP at market prices? | D47: Use your GDP mp estimate from Q6

Sheet Workings

Sheet Ex2x_Answers
A1: Questions | C1: Answers | D1: Hints and suggestions
A2: Use the information contained in the SAM to answer the following questions.
A4: GDP
A5: 1 | B5: What is the value of total GDP measured at factor cost? | C5: =SUM(SAM!C67:AF72) -> 16253.846 | D5: GDP at factor is the sum of all factor incomes earned during the production process (payments from producers/activities to land, labor and capital)
A6: 2 | B6: What are the shares of agriculture, industry and services in total GDP? | C6: 16.287266 | D6: Agriculture = cereals to fisheries; Industry = mining to construction; Services = Trade to other services. First calculate total agricultural GDP, and then divide by national GDP.
A7: 3 | B7: Which is the largest agricultural subsector in terms of GDP? | C7: Cereal | D7: First calculate GDP for each (by summing across factors), and then calculate shares across totals
A8: 4 | B8: What is the share of food and agriculture-related processing within manufacturing GDP? | C8: 11.565084 | D8: Food and Ag-processing includes Meat, fish and dairy; fruit and vegetables; Fats and oils; Grain milling; Other food processing; and beverage and tobaco sectors
A9: 5 | B9: What is the share of the government (incl. health and education) in total GDP? | C9: 9.0816054 | D9: Divide Government, health and education sector with total GDP
A10: 6 | B10: What is the value of GDP measured at market prices? | C10: 13147.974 | D10: GDP mp = C + I + G + X - M
A12: Production technologies
A13: =MAX(A1:A12)+1 -> 7 | B13: What share of labor value-added is generated by uneducated workers? | C13: 49.016714 | D13: divide uneducated labor value-added with total labor value added
A14: =MAX(A2:A13)+1 -> 8 | B14: Which is the most capital-intensive sector in the economy? | C14: Other services | D14: Treat capital separate from land
A15: =MAX(A4:A14)+1 -> 9 | B15: Which is the most skill-intensive sector of the economy? | C15: Gov. services | D15: Share of labor value added earned by high skill worker to total labor value added
A16: =MAX(A5:A15)+1 -> 10 | B16: Which sector has the highest of production costs associated with petroleum products (chemicals)? | C16: chemical | D16: Divide intermediate demand spending on chemical inputs by value of gross output
A17: =MAX(A6:A16)+1 -> 11 | B17: Which sector has the lowest GDP to gross output ratio? | C17: grain milling | D17: Divide GDP to value of gross output
A19: Transaction costs
A20: =MAX(A8:A19)+1 -> 12 | B20: Which product has the highest transaction costs? (calculate transaction costs as a share of total supply) | C20: Horticulture | D20: Transaction costs are in the account TRC
A21: =MAX(A9:A20)+1 -> 13 | B21: What share of total transaction costs generates demand for transport services? | C21: =SAM!BK62/SAM!CF62*100 -> 45.68624 | D21: Divide transaction costs demand on transport services with total demand of transport services
A23: Trade
A24: =MAX(A12:A23)+1 -> 14 | B24: What share of domestic production is exported? | C24: =SUM(SAM!CE36:CE65)/SUM(SAM!CF6:CF29)*100 -> 21.083173 | D24: Divide total exports by total gross output
A25: =MAX(A13:A24)+1 -> 15 | B25: What share of domestic demand is supplied by imports? | C25: 10.144958 | D25: First subtract exports from total demand
A27: Government finance
A28: =MAX(A16:A27)+1 -> 16 | B28: What is the share of tax collections in total government revenue? | C28: 83.359335 | D28: Divide total taxes revenue by total government revenue
A29: =MAX(A17:A28)+1 -> 17 | B29: What share of tax revenues come from indirect and direct taxes? | C29: 30.7 and 52.7 | D29: Divide direct and indirect taxes revenue by total government revenue
A30: =MAX(A18:A29)+1 -> 18 | B30: What is the average direct tax rate on household and enterprise incomes? | C30: 3.5 and 1 | D30: Divide tax expenditure spent by enterprise and households by its total income
A31: =MAX(A19:A30)+1 -> 19 | B31: Which imported product faces the highest tariff rate? | C31: Poultry | D31: Take tariff collection (MTAX) and divide by import value (ROW)
A32: =MAX(A20:A31)+1 -> 20 | B32: What product has the highest sales tax rate? (as a share of intermediate and final demand for goods and services) | C32: fats and oil | D32: First calculate total demand less exports for each product. Then take sales taxes (STAX) and divide by demand less exports
A33: =MAX(A21:A32)+1 -> 21 | B33: What share of government revenues comes from foreign grants? | C33: =SAM!CE79/SAM!CF79*100 -> 1.3238126 | D33: Divide government revenue from rest of the world by total government revenue
A34: =MAX(A22:A33)+1 -> 22 | B34: What share of government spending are transfers to domestic enterprises? What could this transfer include? | C34: =SAM!BX73/SAM!BX87 -> 0.28138206 | D34: Divied government spending on enterprise with total government spending
A35: =MAX(A23:A34)+1 -> 23 | B35: Does the government run a recurrent deficit or surplus, and what is it as a share of total recurrent expenditures? | C35: deficit | D35: Look at value of government spending on savings-investment account
C36: =SAM!BX84/SAM!BX87 -> -0.020963826
A37: Household incomes and expenditures | L37: Population (millions)
A38: =MAX(A26:A37)+1 -> 24 | B38: What is the total value of consumption spending for each household group? | C38: look at answer_workings sheet | D38: Consumption spending only includes commodities | L38: 32.105198 | M38: Household - quintile 1
A39: =MAX(A27:A38)+1 -> 25 | B39: What is the average level of per capita consumption for each household quintile? (see population data) | C39: look at answer_workings sheet | D39: Divide consumption spending by total household population | L39: 32.018407 | M39: Household - quintile 2
A40: =MAX(A28:A39)+1 -> 26 | B40: What share of consumption spending for each quintile is spent on agricultural and food products? | C40: look at answer_workings sheet | D40: For foods, include from Meat-Beverages | L40: 32.056355 | M40: Household - quintile 3
A41: =MAX(A29:A40)+1 -> 27 | B41: What share of incomes for each household group comes from factors, enterprises, government and rest of world? | C41: look at answer_workings sheet | D41: First collect on income source values in a single table, and then calculate shares | L41: 32.086998 | M41: Household - quintile 4
A42: =MAX(A30:A41)+1 -> 28 | B42: What is the average marginal propensity to save for households? (average for all groups) | C42: 20.039658 | D42: Divide total household savings with total expenditure | L42: 32.010027 | M42: Household - quintile 5
L43: =SUM(L38:L42) -> 160.27698 | M43: All households
A44: Other accounts
A45: =MAX(A35:A44)+1 -> 29 | B45: What share of gross fixed capital formation is demand for construction? | C45: =SAM!CC60/SAM!CF60*100 -> 92.681752 | D45: Divide investment demand on construction by total construction demand
A46: =MAX(A36:A45)+1 -> 30 | B46: What share of gross capital formation is changes in stocks? | C46: =SAM!CD87/SAM!CC87 -> 0 | D46: GCF includes GFCF plus stock changes
A47: =MAX(A37:A46)+1 -> 31 | B47: What is the current account deficit as a share of total GDP at market prices? | C47: =SAM!CE83/Ex2x_Answers!C10*100 -> 0 | D47: Use your GDP mp estimate from Q6

Sheet Answer_Workings
B2: Answer calculations
C4: GDP | D4: GDP Share (%)
A5: No.1-2 | B5: Agr | C5: =SUM(SAM!C67:L72) -> 2647.3071 | D5: =C5/$C$8*100 -> 16.287266
B6: Ind | C6: =SUM(SAM!M67:AA72) -> 4565.9838 | D6: =C6/$C$8*100 -> 28.091713
B7: Srv | C7: =SUM(SAM!AB67:AF72) -> 9040.555 | D7: =C7/$C$8*100 -> 55.621021
C8: =SUM(C5:C7) -> 16253.846
A12: 3 | C12: acere | D12: apoil | E12: aroot | F12: ahort | G12: axcrp | H12: acatt | I12: apoul | J12: aoliv | K12: afore | L12: afish | M12: tot_AgGDP
B13: AgGDP | C13: =SUM(SAM!C67:C72) -> 740.92884 | D13: =SUM(SAM!D67:D72) -> 97.492398 | E13: =SUM(SAM!E67:E72) -> 134.87066 | F13: =SUM(SAM!F67:F72) -> 200.43711 | G13: =SUM(SAM!G67:G72) -> 194.59724 | H13: =SUM(SAM!H67:H72) -> 111.40071 | I13: =SUM(SAM!I67:I72) -> 107.54334 | J13: =SUM(SAM!J67:J72) -> 138.85469 | ... L13: =SUM(SAM!L67:L72) -> 705.08827 | M13: =SUM(C13:L13) -> 2647.3071
B14: Share | C14: =C13/$M$13 -> 0.2798802 | D14: =D13/$M$13 -> 0.036827007 | E14: =E13/$M$13 -> 0.050946359 | F14: =F13/$M$13 -> 0.075713583 | G14: =G13/$M$13 -> 0.073507617 | H14: =H13/$M$13 -> 0.042080765 | I14: =I13/$M$13 -> 0.040623675 | J14: =J13/$M$13 -> 0.052451297 | ... L14: =L13/$M$13 -> 0.26634169
C19: amine | D19: ameat | E19: afveg | F19: afoil | G19: agmll | H19: afood | I19: abeve | J19: atext | K19: awood | L19: achem | M19: anmet | N19: amach | O19: aoman | P19: tot_MnfGDP
B20: MnfGDP | C20: =SUM(SAM!M67:M72) -> 285.66544 | D20: =SUM(SAM!N67:N72) -> 41.871902 | E20: =SUM(SAM!O67:O72) -> 5.7964931 | F20: =SUM(SAM!P67:P72) -> 35.76687 | G20: =SUM(SAM!Q67:Q72) -> 70.725832 | H20: =SUM(SAM!R67:R72) -> 144.98203 | I20: =SUM(SAM!S67:S72) -> 56.223209 | J20: =SUM(SAM!T67:T72) -> 1303.4073 | ... O20: =SUM(SAM!Y67:Y72) -> 182.4607 | P20: =SUM(C20:O20) -> 3072.7518
B21: Share | C21: =C20/$P$20 -> 0.092967298 | D21: =D20/$P$20 -> 0.013626841 | E21: =E20/$P$20 -> 0.0018864176 | F21: =F20/$P$20 -> 0.011640013 | G21: =G20/$P$20 -> 0.023017099 | H21: =H20/$P$20 -> 0.047183124 | I21: =I20/$P$20 -> 0.018297348 | J21: =J20/$P$20 -> 0.42418243 | ... O21: =O20/$P$20 -> 0.059380227
A23: 4 | B23: Food_Shr | C23: =SUM(D21:I21) -> 0.11565084
C27: autil | D27: acons | E27: atrad | F27: atran | G27: afbsv | H27: agsrv | I27: aosrv | J27: Tot_srvGDP | K27: Tot_GDP
B28: Srv_GDP | C28: =SUM(SAM!Z67:Z72) -> 238.05542 | D28: =SUM(SAM!AA67:AA72) -> 1255.1766 | E28: =SUM(SAM!AB67:AB72) -> 2361.0753 | F28: =SUM(SAM!AC67:AC72) -> 1704.8172 | G28: =SUM(SAM!AD67:AD72) -> 1787.2901 | H28: =SUM(SAM!AE67:AE72) -> 1476.1101 | I28: =SUM(SAM!AF67:AF72) -> 1711.2624 | J28: =SUM(C28:I28) -> 10533.787 | K28: =M13+P20+J28 -> 16253.846
C29: =C28/$J$28 -> 0.022599225 | D29: =D28/$J$28 -> 0.1191572 | E29: =E28/$J$28 -> 0.22414306 | F29: =F28/$J$28 -> 0.16184276 | G29: =G28/$J$28 -> 0.16967213 | H29: =H28/$J$28 -> 0.140131 | I29: =I28/$J$28 -> 0.16245462
A31: 5 | B31: Gov/GDP | C31: =H28/K28 -> 0.090816054
A35: 6 | C35: hhd-1 | D35: hhd-2 | E35: hhd-3 | F35: hhd-4 | G35: hhd-5 | H35: gov | I35: s-i | J35: dstk | K35: X | L35: M | M35: GDP at market price
B36: Demand | C36: =SAM!BS87 -> 901.88537 | D36: =SAM!BT87 -> 1476.4525 | E36: =SAM!BU87 -> 2142.0386 | F36: =SAM!BV87 -> 3052.4561 | G36: =SAM!BW87 -> 6819.2478 | H36: =SAM!BX87 -> 1634.08 | I36: =SAM!BY87 -> 501.63124 | J36: =SAM!BZ87 -> 0 | K36: =SAM!CA87 -> 369.20103 | L36: =-SUM(SAM!AG86:BJ86) -> -3749.0183 | M36: =SUM(C36:L36) -> 13147.974
C38: Labor VA | D38: Share
A39: 7 | B39: flab-n | C39: =SUM(SAM!C67:AF67) -> 2633.8017 | D39: =C39/SUM($C$39:$C$42) -> 0.49016714
B40: flab-p | C40: =SUM(SAM!C68:AF68) -> 998.46741 | D40: =C40/SUM($C$39:$C$42) -> 0.18582109
B41: flab-s | C41: =SUM(SAM!C69:AF69) -> 1075.2943 | D41: =C41/SUM($C$39:$C$42) -> 0.20011906
B42: flab-t | C42: =SUM(SAM!C70:AF70) -> 665.70931 | D42: =C42/SUM($C$39:$C$42) -> 0.12389271
C44: acere | D44: apoil | E44: aroot | F44: ahort | G44: axcrp | H44: acatt | I44: apoul | J44: aoliv | K44: afore | L44: afish | M44: amine | N44: ameat | O44: afveg | P44: afoil | Q44: agmll | R44: afood | S44: abeve | T44: atext | U44: awood | V44: achem | W44: anmet | X44: amach | Y44: aoman | Z44: autil | AA44: acons | AB44: atrad | AC44: atran | AD44: afbsv | AE44: agsrv | AF44: aosrv
A45: 8 | B45: Lab | C45: =SUM(SAM!C67:C70) -> 401.28302 | D45: =SUM(SAM!D67:D70) -> 44.498826 | E45: =SUM(SAM!E67:E70) -> 52.657895 | F45: =SUM(SAM!F67:F70) -> 47.283362 | G45: =SUM(SAM!G67:G70) -> 81.575699 | H45: =SUM(SAM!H67:H70) -> 35.919842 | I45: =SUM(SAM!I67:I70) -> 31.003562 | J45: =SUM(SAM!J67:J70) -> 45.454459 | ... AF45: =SUM(SAM!AF67:AF70) -> 95.148653
B46: Land | C46: =SAM!C71 -> 321.32354 | D46: =SAM!D71 -> 50.448344 | E46: =SAM!E71 -> 78.613767 | F46: =SAM!F71 -> 145.94398 | G46: =SAM!G71 -> 107.83477 | H46: =SAM!H71 -> 0 | I46: =SAM!I71 -> 0 | J46: =SAM!J71 -> 0 | ... AF46: =SAM!AF71 -> 0
B47: Cap | C47: =SAM!C72 -> 18.322282 | D47: =SAM!D72 -> 2.5452273 | E47: =SAM!E72 -> 3.598996 | F47: =SAM!F72 -> 7.2097639 | G47: =SAM!G72 -> 5.1867693 | H47: =SAM!H72 -> 75.480868 | I47: =SAM!I72 -> 76.539782 | J47: =SAM!J72 -> 93.400233 | ... AF47: =SAM!AF72 -> 1616.1137
C48: =SUM(C45:C47) -> 740.92884 | D48: =SUM(D45:D47) -> 97.492398 | E48: =SUM(E45:E47) -> 134.87066 | F48: =SUM(F45:F47) -> 200.43711 | G48: =SUM(G45:G47) -> 194.59724 | H48: =SUM(H45:H47) -> 111.40071 | I48: =SUM(I45:I47) -> 107.54334 | J48: =SUM(J45:J47) -> 138.85469 | ... AF48: =SUM(AF45:AF47) -> 1711.2624
A50: 8 | B50: Cap_shr | C50: =C47/C48 -> 0.024728801 | D50: =D47/D48 -> 0.026106931 | E50: =E47/E48 -> 0.026684796 | F50: =F47/F48 -> 0.035970205 | G50: =G47/G48 -> 0.026653869 | H50: =H47/H48 -> 0.67756182 | I50: =I47/I48 -> 0.71171101 | J50: =J47/J48 -> 0.6726473 | ... AF50: =AF47/AF48 -> 0.94439856
A52: 9 | B52: Labor Value Added (VA)
C53: acere | D53: apoil | E53: aroot | F53: ahort | G53: axcrp | H53: acatt | I53: apoul | J53: aoliv | K53: afore | L53: afish | M53: amine | N53: ameat | O53: afveg | P53: afoil | Q53: agmll | R53: afood | S53: abeve | T53: atext | U53: awood | V53: achem | W53: anmet | X53: amach | Y53: aoman | Z53: autil | AA53: acons | AB53: atrad | AC53: atran | AD53: afbsv | AE53: agsrv | AF53: aosrv
B54: flab-n | C54: =SAM!C67 -> 253.06585 | D54: =SAM!D67 -> 31.335264 | E54: =SAM!E67 -> 33.111534 | F54: =SAM!F67 -> 35.857197 | G54: =SAM!G67 -> 58.190466 | H54: =SAM!H67 -> 26.851769 | I54: =SAM!I67 -> 19.983084 | J54: =SAM!J67 -> 34.764707 | ... AF54: =SAM!AF67 -> 52.182106
B55: flab-p | C55: =SAM!C68 -> 91.093868 | D55: =SAM!D68 -> 8.1207166 | E55: =SAM!E68 -> 9.9106708 | F55: =SAM!F68 -> 6.7002911 | G55: =SAM!G68 -> 12.766427 | H55: =SAM!H68 -> 5.8375581 | I55: =SAM!I68 -> 6.7737852 | J55: =SAM!J68 -> 7.09196 | ... AF55: =SAM!AF68 -> 23.993462
B56: flab-s | C56: =SAM!C69 -> 45.1545 | D56: =SAM!D69 -> 4.1656224 | E56: =SAM!E69 -> 7.4408616 | F56: =SAM!F69 -> 3.1016722 | G56: =SAM!G69 -> 9.2752248 | H56: =SAM!H69 -> 2.5135062 | I56: =SAM!I69 -> 3.748948 | J56: =SAM!J69 -> 2.5688282 | ... AF56: =SAM!AF69 -> 8.3987315
B57: flab-t | C57: =SAM!C70 -> 11.968807 | D57: =SAM!D70 -> 0.87722305 | E57: =SAM!E70 -> 2.1948293 | F57: =SAM!F70 -> 1.6242014 | G57: =SAM!G70 -> 1.3435815 | H57: =SAM!H70 -> 0.71700839 | I57: =SAM!I70 -> 0.49774475 | J57: =SAM!J70 -> 1.0289632 | ... AF57: =SAM!AF70 -> 10.574353
B59: Labor VA share
A60: 9 | B60: flab-n | C60: =C54/C$48 -> 0.34155216 | D60: =D54/D$48 -> 0.32141239 | E60: =E54/E$48 -> 0.24550583 | F60: =F54/F$48 -> 0.178895 | G60: =G54/G$48 -> 0.29903027 | H60: =H54/H$48 -> 0.24103768 | I60: =I54/I$48 -> 0.18581424 | J60: =J54/J$48 -> 0.25036754 | ... AF60: =AF54/AF$48 -> 0.030493341
B61: flab-p | C61: =C55/C$48 -> 0.1229455 | D61: =D55/D$48 -> 0.083295895 | E61: =E55/E$48 -> 0.073482779 | F61: =F55/F$48 -> 0.033428396 | G61: =G55/G$48 -> 0.065604357 | H61: =H55/H$48 -> 0.052401444 | I61: =I55/I$48 -> 0.062986559 | J61: =J55/J$48 -> 0.051074687 | ... AF61: =AF55/AF$48 -> 0.014020914
B62: flab-s | C62: =C56/C$48 -> 0.060943099 | D62: =D56/D$48 -> 0.042727664 | E62: =E56/E$48 -> 0.055170352 | F62: =F56/F$48 -> 0.015474541 | G62: =G56/G$48 -> 0.047663702 | H62: =H56/H$48 -> 0.022562748 | I62: =I56/I$48 -> 0.03485988 | J62: =J56/J$48 -> 0.018500118 | ... AF62: =AF56/AF$48 -> 0.0049079158
B63: flab-t | C63: =C57/C$48 -> 0.016153787 | D63: =D57/D$48 -> 0.008997861 | E63: =E57/E$48 -> 0.016273586 | F63: =F57/F$48 -> 0.0081032971 | G63: =G57/G$48 -> 0.0069044223 | H63: =H57/H$48 -> 0.0064363001 | I63: =I57/I$48 -> 0.0046283176 | J63: =J57/J$48 -> 0.0074103599 | ... AF63: =AF57/AF$48 -> 0.0061792705
A66: 10 | C66: acere | D66: apoil | E66: aroot | F66: ahort | G66: axcrp | H66: acatt | I66: apoul | J66: aoliv | K66: afore | L66: afish | M66: amine | N66: ameat | O66: afveg | P66: afoil | Q66: agmll | R66: afood | S66: abeve | T66: atext | U66: awood | V66: achem | W66: anmet | X66: amach | Y66: aoman | Z66: autil | AA66: acons | AB66: atrad | AC66: atran | AD66: afbsv | AE66: agsrv | AF66: aosrv
B67: Chemicals | C67: =SAM!C55 -> 76.514339 | D67: =SAM!D55 -> 9.6487069 | E67: =SAM!E55 -> 39.743309 | F67: =SAM!F55 -> 10.496154 | G67: =SAM!G55 -> 24.686491 | H67: =SAM!H55 -> 2.3637136 | I67: =SAM!I55 -> 4.0503676 | J67: =SAM!J55 -> 1.1399206 | ... AF67: =SAM!AF55 -> 5.5325085
C68: =C67/SAM!C87 -> 0.078918679 | D68: =D67/SAM!D87 -> 0.072852351 | E68: =E67/SAM!E87 -> 0.16292058 | F68: =F67/SAM!F87 -> 0.039844346 | G68: =G67/SAM!G87 -> 0.087059796 | H68: =H67/SAM!H87 -> 0.0071913211 | I68: =I67/SAM!I87 -> 0.013316325 | J68: =J67/SAM!J87 -> 0.0047788597 | ... AF68: =AF67/SAM!AF87 -> 0.0027679535
A70: 11 | B70: GDP/Out | C70: =C48/SAM!C87 -> 0.76421134 | D70: =D48/SAM!D87 -> 0.73611423 | E70: =E48/SAM!E87 -> 0.5528781 | F70: =F48/SAM!F87 -> 0.76087735 | G70: =G48/SAM!G87 -> 0.68626991 | H70: =H48/SAM!H87 -> 0.33892357 | I70: =I48/SAM!I87 -> 0.35356844 | J70: =J48/SAM!J87 -> 0.58211695 | ... AF70: =AF48/SAM!AF87 -> 0.85615678
A72: 12 | B72: trc/out | C72: =SAM!AG66/SAM!C87 -> 0.02425458 | D72: =SAM!AH66/SAM!D87 -> 0.65643136 | E72: =SAM!AI66/SAM!E87 -> 0 | F72: =SAM!AJ66/SAM!F87 -> 1.6444781 | G72: =SAM!AK66/SAM!G87 -> 1.2302814 | H72: =SAM!AL66/SAM!H87 -> 0.29594196 | I72: =SAM!AM66/SAM!I87 -> 0.1085711 | J72: =SAM!AN66/SAM!J87 -> 0 | ... AF72: =SAM!BJ66/SAM!AF87 -> 0
C74: Total Demand | D74: Export | E74: Dom.Dem | F74: Import | G74: Import/Dom. Demand
A75: 15 | B75: Demand | C75: =SUM(SAM!CF36:CF65) -> 40217.863 | D75: =SUM(SAM!CE36:CE65) -> 3263.3659 | E75: =C75-D75 -> 36954.498 | F75: =SUM(SAM!AG86:BJ86) -> 3749.0183 | G75: =F75/E75 -> 0.10144958
A77: 16 | C77: Tot. tax | D77: Tot. Rev | E77: Tax/Grev
B78: Gov. Rev | C78: =SUM(SAM!BY87:CB87) -> 1362.1583 | D78: =SUM(SAM!CF79) -> 1634.08 | E78: =C78/D78 -> 0.83359335
A80: 17 | C80: Dir. Tax | D80: Ind. Tax
B81: Gov. Rev | C81: =SUM(SAM!BY87) -> 501.63124 | D81: =SUM(SAM!BZ87:CB87) -> 860.52702
B82: share | C82: =C81/$D$78 -> 0.30698082 | D82: =D81/$D$78 -> 0.52661253
A85: 18 | C85: ent | D85: hhd-1 | E85: hhd-2 | F85: hhd-3 | G85: hhd-4 | H85: hhd-5 | I85: HH
C86: =SAM!BR80 -> 353.97184 | D86: =SAM!BS80 -> 3.2696438 | E86: =SAM!BT80 -> 5.2283594 | F86: =SAM!BU80 -> 12.777832 | G86: =SAM!BV80 -> 24.598108 | H86: =SAM!BW80 -> 101.78545 | I86: =SUM(D86:H86) -> 147.65939
C88: ent | D88: hh
B89: inc | C89: =SAM!BR87 -> 10189.885 | D89: =SUM(SAM!BS87:BW87) -> 14392.08
C91: =C86/C89 -> 0.034737572 | D91: =I86/D89 -> 0.010259767
C94: acere | D94: apoil | E94: aroot | F94: ahort | G94: axcrp | H94: acatt | I94: apoul | J94: aoliv | K94: afore | L94: afish | M94: amine | N94: ameat | O94: afveg | P94: afoil | Q94: agmll | R94: afood | S94: abeve | T94: atext | U94: awood | V94: achem | W94: anmet | X94: amach | Y94: aoman | Z94: autil | AA94: acons | AB94: atrad | AC94: atran | AD94: afbsv | AE94: agsrv | AF94: aosrv
B95: import value | C95: =SAM!AG86 -> 76.912372 | D95: =SAM!AH86 -> 72.621871 | E95: =SAM!AI86 -> 0 | F95: =SAM!AJ86 -> 36.636512 | G95: =SAM!AK86 -> 131.19392 | H95: =SAM!AL86 -> 0.014106393 | I95: =SAM!AM86 -> 3.5621604 | J95: =SAM!AN86 -> 0.57985224 | ... AF95: =SAM!BJ86 -> 0.82472438
B96: import tariff | C96: =SAM!AG82 -> 0 | D96: =SAM!AH82 -> 0.95298845 | E96: =SAM!AI82 -> 0 | F96: =SAM!AJ82 -> 8.1368569 | G96: =SAM!AK82 -> 4.9711061 | H96: =SAM!AL82 -> 0.00012739727 | I96: =SAM!AM82 -> 1.0731994 | J96: =SAM!AN82 -> 0 | ... AF96: =SAM!BJ82 -> 0
B97: Tariff rate | C97: =IF(C95,C96/C95,0) -> 0 | D97: =IF(D95,D96/D95,0) -> 0.013122609 | E97: =IF(E95,E96/E95,0) -> 0 | F97: =IF(F95,F96/F95,0) -> 0.22209693 | G97: =IF(G95,G96/G95,0) -> 0.037891283 | H97: =IF(H95,H96/H95,0) -> 0.0090311728 | I97: =IF(I95,I96/I95,0) -> 0.30127768 | J97: =IF(J95,J96/J95,0) -> 0 | ... AF97: =IF(AF95,AF96/AF95,0) -> 0
A100: 20 | C100: acere | D100: apoil | E100: aroot | F100: ahort | G100: axcrp | H100: acatt | I100: apoul | J100: aoliv | K100: afore | L100: afish | M100: amine | N100: ameat | O100: afveg | P100: afoil | Q100: agmll | R100: afood | S100: abeve | T100: atext | U100: awood | V100: achem | W100: anmet | X100: amach | Y100: aoman | Z100: autil | AA100: acons | AB100: atrad | AC100: atran | AD100: afbsv | AE100: agsrv | AF100: aosrv
B101: stax | C101: =SAM!AG83 -> 0 | D101: =SAM!AH83 -> 1.6825112e-05 | E101: =SAM!AI83 -> 0 | F101: =SAM!AJ83 -> 0 | G101: =SAM!AK83 -> 0.67532758 | H101: =SAM!AL83 -> 0 | I101: =SAM!AM83 -> 0 | J101: =SAM!AN83 -> 0 | ... AF101: =SAM!BJ83 -> 0
B102: Export | C102: 3.2781518e-05 | D102: 1.4929173 | E102: 1.5388236 | F102: 2.7266931 | G102: 19.558832 | H102: 0.0029315303 | I102: 0.028450019 | J102: 0.29034971 | K102: 0.0023411786 | L102: 1.6948614 | M102: 1.5284415 | N102: 15.746724 | O102: 3.9834505 | P102: 1.5043425 | Q102: 0.44563616 | R102: 8.1196434 | S102: 2.5256185 | T102: 2853.3012 | U102: 4.1227388 | V102: 30.439696 | W102: 3.3648214 | X102: 44.68928 | Y102: 6.3634921 | AA102: 8.2793569 | AB102: 16.910688 | AC102: 31.916776 | AD102: 88.352599 | AE102: 113.87969 | AF102: 0.55547716
B103: Demand | C103: 1069.962 | D103: 234.86576 | E103: 242.53103 | F103: 724.43605 | G103: 767.16825 | H103: 394.1421 | I103: 329.38699 | J103: 215.34304 | K103: 688.20871 | L103: 1504.9701 | M103: 634.8387 | N103: 179.35849 | O103: 16.450851 | P103: 758.08575 | Q103: 1017.1059 | R103: 622.37719 | S103: 392.82422 | T103: 4595.1866 | U103: 591.12049 | V103: 1753.6148 | W103: 1134.8001 | X103: 3314.8552 | Y103: 618.8813 | Z103: 1038.6952 | AA103: 3943.1106 | AB103: 3257.5603 | AC103: 3287.7826 | AD103: 2612.692 | AE103: 2277.9122 | AF103: 1999.5969
B104: Dem.-Exp | C104: =C103-C102 -> 1069.9619 | D104: =D103-D102 -> 233.37284 | E104: =E103-E102 -> 240.99221 | F104: =F103-F102 -> 721.70936 | G104: =G103-G102 -> 747.60942 | H104: =H103-H102 -> 394.13917 | I104: =I103-I102 -> 329.35854 | J104: =J103-J102 -> 215.05269 | ... AF104: =AF103-AF102 -> 1999.0414
C105: =C101/C104 -> 0 | D105: =D101/D104 -> 7.2095414e-08 | E105: =E101/E104 -> 0 | F105: =F101/F104 -> 0 | G105: =G101/G104 -> 0.00090331604 | H105: =H101/H104 -> 0 | I105: =I101/I104 -> 0 | J105: =J101/J104 -> 0 | ... AF105: =AF101/AF104 -> 0
A107: 24 | C107: hhd-1 | D107: hhd-2 | E107: hhd-3 | F107: hhd-4 | G107: hhd-5
B108: cons | C108: =SUM(SAM!BS37:BS65) -> 695.10977 | D108: =SUM(SAM!BT37:BT65) -> 1104.3553 | E108: =SUM(SAM!BU37:BU65) -> 1571.5544 | F108: =SUM(SAM!BV37:BV65) -> 2311.7566 | G108: =SUM(SAM!BW37:BW65) -> 5258.1567
C110: hhd-1 | D110: hhd-2 | E110: hhd-3 | F110: hhd-4 | G110: hhd-5
A111: 25 | B111: pop | C111: 32.105198 | D111: 32.018407 | E111: 32.056355 | F111: 32.086998 | G111: 32.010027
B112: con/cap | C112: =C108/C111*1000 -> 21651.004 | D112: =D108/D111*1000 -> 34491.262 | E112: =E108/E111*1000 -> 49024.739 | F112: =F108/F111*1000 -> 72046.521 | G112: =G108/G111*1000 -> 164265.93
C115: hhd-1 | D115: hhd-2 | E115: hhd-3 | F115: hhd-4 | G115: hhd-5
A116: 26 | B116: ag_food | C116: =SUM(SAM!BS36:BS43,SAM!BS45,SAM!BS47:BS52) -> 410.68064 | D116: =SUM(SAM!BT36:BT43,SAM!BT45,SAM!BT47:BT52) -> 614.08905 | E116: =SUM(SAM!BU36:BU43,SAM!BU45,SAM!BU47:BU52) -> 821.99839 | F116: =SUM(SAM!BV36:BV43,SAM!BV45,SAM!BV47:BV52) -> 1173.6286 | G116: =SUM(SAM!BW36:BW43,SAM!BW45,SAM!BW47:BW52) -> 2526.7301
C117: =C116/C108 -> 0.59081408 | D117: =D116/D108 -> 0.55606114 | E117: =E116/E108 -> 0.523048 | F117: =F116/F108 -> 0.50767828 | G117: =G116/G108 -> 0.48053535
C120: fac | D120: ent | E120: gov | F120: row
B121: hhd-1 | C121: =SUM(SAM!BL74:BQ74) -> 606.34993 | D121: =SAM!BR74 -> 244.59221 | E121: =SAM!BX74 -> 32.234884 | F121: =SAM!CE74 -> 18.708354 | G121: =SAM!CF74 -> 901.88537
B122: hhd-2 | C122: =SUM(SAM!BL75:BQ75) -> 956.81442 | D122: =SAM!BR75 -> 428.91726 | E122: =SAM!BX75 -> 42.675429 | F122: =SAM!CE75 -> 48.045435 | G122: =SAM!CF75 -> 1476.4525
B123: hhd-3 | C123: =SUM(SAM!BL76:BQ76) -> 1232.6156 | D123: =SAM!BR76 -> 764.8425 | E123: =SAM!BX76 -> 36.119786 | F123: =SAM!CE76 -> 108.46065 | G123: =SAM!CF76 -> 2142.0386
B124: hhd-4 | C124: =SUM(SAM!BL77:BQ77) -> 1405.3627 | D124: =SAM!BR77 -> 1444.7663 | E124: =SAM!BX77 -> 31.156131 | F124: =SAM!CE77 -> 171.17098 | G124: =SAM!CF77 -> 3052.4561
B125: hhd-5 | C125: =SUM(SAM!BL78:BQ78) -> 2160.38 | D125: =SAM!BR78 -> 4243.5472 | E125: =SAM!BX78 -> 21.987028 | F125: =SAM!CE78 -> 393.33357 | G125: =SAM!CF78 -> 6819.2478
A127: 27 | B127: hhd-1 | C127: =C121/$G121 -> 0.67231374 | D127: =D121/$G121 -> 0.27120099 | E127: =E121/$G121 -> 0.035741664 | F127: =F121/$G121 -> 0.020743605
B128: hhd-2 | C128: =C122/$G122 -> 0.64804956 | D128: =D122/$G122 -> 0.29050528 | E128: =E122/$G122 -> 0.02890403 | F128: =F122/$G122 -> 0.03254113
B129: hhd-3 | C129: =C123/$G123 -> 0.57544044 | D129: =D123/$G123 -> 0.3570629 | E129: =E123/$G123 -> 0.016862342 | F129: =F123/$G123 -> 0.050634314
B130: hhd-4 | C130: =C124/$G124 -> 0.4604039 | D130: =D124/$G124 -> 0.47331272 | E130: =E124/$G124 -> 0.010206906 | F130: =F124/$G124 -> 0.056076477
B131: hhd-5 | C131: =C125/$G125 -> 0.3168062 | D131: =D125/$G125 -> 0.62228964 | E131: =E125/$G125 -> 0.00322426 | F131: =F125/$G125 -> 0.057679906
A134: 28 | B134: sav | C134: =SUM(SAM!BS84:BW84) -> 2884.1237
B135: exp | C135: =SUM(SAM!BS87:BW87) -> 14392.08
C136: =C134/C135 -> 0.20039658
