Workbook

Sheet Notes
A1: ="Static Standard Reporting | "&E3&" ("&E4&")" -> Static Standard Reporting | Nepal (2022)
D3: Country | E3: Nepal
D4: Year | E4: 2022
D5: Units | E5: Billions of Nepalese Rupee
C7: Activities and commodities | I7: Factors | N7: Households | T7: Appearance in reporting tables
C8: Level | D8: Account | E8: Description (activities) | F8: Description (commodities) | I8: Level | J8: Account | K8: Description | N8: Level | O8: Account | P8: Description | T8: Activities | U8: Commodities | V8: Factors | W8: Households
C9: 1 | D9: aa_GDP | E9: All sectors | F9: All products | I9: 1 | J9: ff_LAB | K9: Labor | N9: 1 | O9: hh_ALL | P9: All households | T9: =IF(C9=1,E9,IF(C9=2," "&E9,IF(C9=3," "&E9,IF(C9=4," "&E9," "&E9)))) -> All sectors | U9: =IF(C9=1,F9,IF(C9=2," "&F9,IF(C9=3," "&F9,IF(C9=4," "&F9," "&F9)))) -> All products | V9: =IF(I9=1,K9,IF(I9=2," "&K9,IF(I9=3," "&K9,IF(I9=4," "&K9," "&K9)))) -> Labor | W9: =IF(N9=1,P9,IF(N9=2," "&P9,IF(N9=3," "&P9,IF(N9=4," "&P9," "&P9)))) -> All households
C10: 1 | D10: aa_AGRI | E10: Agriculture | F10: Agriculture | I10: 3 | J10: ff_LAB_N | K10: Labor - uneducated | N10: 3 | O10: hh_D1 | P10: Decile 1 (low) | T10: =IF(C10=1,E10,IF(C10=2," "&E10,IF(C10=3," "&E10,IF(C10=4," "&E10," "&E10)))) -> Agriculture | U10: =IF(C10=1,F10,IF(C10=2," "&F10,IF(C10=3," "&F10,IF(C10=4," "&F10," "&F10)))) -> Agriculture | V10: =IF(I10=1,K10,IF(I10=2," "&K10,IF(I10=3," "&K10,IF(I10=4," "&K10," "&K10)))) -> Labor - uneducated | W10: =IF(N10=1,P10,IF(N10=2," "&P10,IF(N10=3," "&P10,IF(N10=4," "&P10," "&P10)))) -> Decile 1 (low)
C11: 2 | D11: aa_CROP | E11: Crops | F11: Crops | I11: 3 | J11: ff_LAB_P | K11: Labor - primary | N11: 3 | O11: hh_D2 | P11: Decile 2 | T11: =IF(C11=1,E11,IF(C11=2," "&E11,IF(C11=3," "&E11,IF(C11=4," "&E11," "&E11)))) -> Crops | U11: =IF(C11=1,F11,IF(C11=2," "&F11,IF(C11=3," "&F11,IF(C11=4," "&F11," "&F11)))) -> Crops | V11: =IF(I11=1,K11,IF(I11=2," "&K11,IF(I11=3," "&K11,IF(I11=4," "&K11," "&K11)))) -> Labor - primary | W11: =IF(N11=1,P11,IF(N11=2," "&P11,IF(N11=3," "&P11,IF(N11=4," "&P11," "&P11)))) -> Decile 2
C12: 3 | D12: a_maiz | E12: Maize | F12: Maize | I12: 3 | J12: ff_LAB_S | K12: Labor - secondary | N12: 3 | O12: hh_D3 | P12: Decile 3 | T12: =IF(C12=1,E12,IF(C12=2," "&E12,IF(C12=3," "&E12,IF(C12=4," "&E12," "&E12)))) -> Maize | U12: =IF(C12=1,F12,IF(C12=2," "&F12,IF(C12=3," "&F12,IF(C12=4," "&F12," "&F12)))) -> Maize | V12: =IF(I12=1,K12,IF(I12=2," "&K12,IF(I12=3," "&K12,IF(I12=4," "&K12," "&K12)))) -> Labor - secondary | W12: =IF(N12=1,P12,IF(N12=2," "&P12,IF(N12=3," "&P12,IF(N12=4," "&P12," "&P12)))) -> Decile 3
C13: 3 | D13: a_sorg | E13: Sorghum and millet | F13: Sorghum and millet | I13: 3 | J13: ff_LAB_T | K13: Labor - tertiary | N13: 3 | O13: hh_D4 | P13: Decile 4 | T13: =IF(C13=1,E13,IF(C13=2," "&E13,IF(C13=3," "&E13,IF(C13=4," "&E13," "&E13)))) -> Sorghum and millet | U13: =IF(C13=1,F13,IF(C13=2," "&F13,IF(C13=3," "&F13,IF(C13=4," "&F13," "&F13)))) -> Sorghum and millet | V13: =IF(I13=1,K13,IF(I13=2," "&K13,IF(I13=3," "&K13,IF(I13=4," "&K13," "&K13)))) -> Labor - tertiary | W13: =IF(N13=1,P13,IF(N13=2," "&P13,IF(N13=3," "&P13,IF(N13=4," "&P13," "&P13)))) -> Decile 4
C14: 3 | D14: a_aman | E14: Rice paddy (Aman) | F14: Rice paddy (Aman) | I14: 2 | J14: ff_RUR | K14: Labor - rural | N14: 3 | O14: hh_D5 | P14: Decile 5 | T14: =IF(C14=1,E14,IF(C14=2," "&E14,IF(C14=3," "&E14,IF(C14=4," "&E14," "&E14)))) -> Rice paddy (Aman) | U14: =IF(C14=1,F14,IF(C14=2," "&F14,IF(C14=3," "&F14,IF(C14=4," "&F14," "&F14)))) -> Rice paddy (Aman) | V14: =IF(I14=1,K14,IF(I14=2," "&K14,IF(I14=3," "&K14,IF(I14=4," "&K14," "&K14)))) -> Labor - rural | W14: =IF(N14=1,P14,IF(N14=2," "&P14,IF(N14=3," "&P14,IF(N14=4," "&P14," "&P14)))) -> Decile 5
C15: 3 | D15: a_boro | E15: Rice paddy (Boro) | F15: Rice paddy (Boro) | I15: 3 | J15: f_lab-rn | K15: Labor - rural uneducated | N15: 3 | O15: hh_D6 | P15: Decile 6 | T15: =IF(C15=1,E15,IF(C15=2," "&E15,IF(C15=3," "&E15,IF(C15=4," "&E15," "&E15)))) -> Rice paddy (Boro) | U15: =IF(C15=1,F15,IF(C15=2," "&F15,IF(C15=3," "&F15,IF(C15=4," "&F15," "&F15)))) -> Rice paddy (Boro) | V15: =IF(I15=1,K15,IF(I15=2," "&K15,IF(I15=3," "&K15,IF(I15=4," "&K15," "&K15)))) -> Labor - rural uneducated | W15: =IF(N15=1,P15,IF(N15=2," "&P15,IF(N15=3," "&P15,IF(N15=4," "&P15," "&P15)))) -> Decile 6
C16: 3 | D16: a_whea | E16: Wheat and barley | F16: Wheat and barley | I16: 3 | J16: f_lab-rp | K16: Labor - rural primary | N16: 3 | O16: hh_D7 | P16: Decile 7 | T16: =IF(C16=1,E16,IF(C16=2," "&E16,IF(C16=3," "&E16,IF(C16=4," "&E16," "&E16)))) -> Wheat and barley | U16: =IF(C16=1,F16,IF(C16=2," "&F16,IF(C16=3," "&F16,IF(C16=4," "&F16," "&F16)))) -> Wheat and barley | V16: =IF(I16=1,K16,IF(I16=2," "&K16,IF(I16=3," "&K16,IF(I16=4," "&K16," "&K16)))) -> Labor - rural primary | W16: =IF(N16=1,P16,IF(N16=2," "&P16,IF(N16=3," "&P16,IF(N16=4," "&P16," "&P16)))) -> Decile 7
C17: 3 | D17: a_ocer | E17: Other cereals | F17: Other cereals | I17: 3 | J17: f_lab-rs | K17: Labor - rural secondary | N17: 3 | O17: hh_D8 | P17: Decile 8 | T17: =IF(C17=1,E17,IF(C17=2," "&E17,IF(C17=3," "&E17,IF(C17=4," "&E17," "&E17)))) -> Other cereals | U17: =IF(C17=1,F17,IF(C17=2," "&F17,IF(C17=3," "&F17,IF(C17=4," "&F17," "&F17)))) -> Other cereals | V17: =IF(I17=1,K17,IF(I17=2," "&K17,IF(I17=3," "&K17,IF(I17=4," "&K17," "&K17)))) -> Labor - rural secondary | W17: =IF(N17=1,P17,IF(N17=2," "&P17,IF(N17=3," "&P17,IF(N17=4," "&P17," "&P17)))) -> Decile 8
C18: 3 | D18: a_puls | E18: Pulses | F18: Pulses | I18: 3 | J18: f_lab-rt | K18: Labor - rural tertiary | N18: 3 | O18: hh_D9 | P18: Decile 9 | T18: =IF(C18=1,E18,IF(C18=2," "&E18,IF(C18=3," "&E18,IF(C18=4," "&E18," "&E18)))) -> Pulses | U18: =IF(C18=1,F18,IF(C18=2," "&F18,IF(C18=3," "&F18,IF(C18=4," "&F18," "&F18)))) -> Pulses | V18: =IF(I18=1,K18,IF(I18=2," "&K18,IF(I18=3," "&K18,IF(I18=4," "&K18," "&K18)))) -> Labor - rural tertiary | W18: =IF(N18=1,P18,IF(N18=2," "&P18,IF(N18=3," "&P18,IF(N18=4," "&P18," "&P18)))) -> Decile 9
C19: 3 | D19: a_gnut | E19: Groundnuts | F19: Groundnuts | I19: 2 | J19: ff_URB | K19: Labor - urban | N19: 3 | O19: hh_D10 | P19: Decile 10 (high) | T19: =IF(C19=1,E19,IF(C19=2," "&E19,IF(C19=3," "&E19,IF(C19=4," "&E19," "&E19)))) -> Groundnuts | U19: =IF(C19=1,F19,IF(C19=2," "&F19,IF(C19=3," "&F19,IF(C19=4," "&F19," "&F19)))) -> Groundnuts | V19: =IF(I19=1,K19,IF(I19=2," "&K19,IF(I19=3," "&K19,IF(I19=4," "&K19," "&K19)))) -> Labor - urban | W19: =IF(N19=1,P19,IF(N19=2," "&P19,IF(N19=3," "&P19,IF(N19=4," "&P19," "&P19)))) -> Decile 10 (high)
C20: 3 | D20: a_oils | E20: Other oilseeds | F20: Other oilseeds | I20: 3 | J20: f_lab-un | K20: Labor - urban uneducated | N20: 2 | O20: hh_RUR | P20: Rural households | T20: =IF(C20=1,E20,IF(C20=2," "&E20,IF(C20=3," "&E20,IF(C20=4," "&E20," "&E20)))) -> Other oilseeds | U20: =IF(C20=1,F20,IF(C20=2," "&F20,IF(C20=3," "&F20,IF(C20=4," "&F20," "&F20)))) -> Other oilseeds | V20: =IF(I20=1,K20,IF(I20=2," "&K20,IF(I20=3," "&K20,IF(I20=4," "&K20," "&K20)))) -> Labor - urban uneducated | W20: =IF(N20=1,P20,IF(N20=2," "&P20,IF(N20=3," "&P20,IF(N20=4," "&P20," "&P20)))) -> Rural households
... C29: 3 | D29: a_cott | E29: Cotton and fibres | F29: Cotton and fibres | I29: 2 | J29: f_cap-n | K29: Capital - non-primary | N29: 3 | O29: h_hhd-r8 | P29: Rural - decile 9 | T29: =IF(C29=1,E29,IF(C29=2," "&E29,IF(C29=3," "&E29,IF(C29=4," "&E29," "&E29)))) -> Cotton and fibres | U29: =IF(C29=1,F29,IF(C29=2," "&F29,IF(C29=3," "&F29,IF(C29=4," "&F29," "&F29)))) -> Cotton and fibres | V29: =IF(I29=1,K29,IF(I29=2," "&K29,IF(I29=3," "&K29,IF(I29=4," "&K29," "&K29)))) -> Capital - non-primary | W29: =IF(N29=1,P29,IF(N29=2," "&P29,IF(N29=3," "&P29,IF(N29=4," "&P29," "&P29)))) -> Rural - decile 9
C30: 3 | D30: a_jute | E30: Jute | F30: Jute | N30: 3 | O30: h_hhd-r9 | P30: Rural - decile 10 (high) | T30: =IF(C30=1,E30,IF(C30=2," "&E30,IF(C30=3," "&E30,IF(C30=4," "&E30," "&E30)))) -> Jute | U30: =IF(C30=1,F30,IF(C30=2," "&F30,IF(C30=3," "&F30,IF(C30=4," "&F30," "&F30)))) -> Jute | V30: =IF(I30=1,K30,IF(I30=2," "&K30,IF(I30=3," "&K30,IF(I30=4," "&K30," "&K30)))) | W30: =IF(N30=1,P30,IF(N30=2," "&P30,IF(N30=3," "&P30,IF(N30=4," "&P30," "&P30)))) -> Rural - decile 10 (high)
C31: 3 | D31: a_nuts | E31: Nuts | F31: Nuts | N31: 2 | O31: hh_URB | P31: Urban households | T31: =IF(C31=1,E31,IF(C31=2," "&E31,IF(C31=3," "&E31,IF(C31=4," "&E31," "&E31)))) -> Nuts | U31: =IF(C31=1,F31,IF(C31=2," "&F31,IF(C31=3," "&F31,IF(C31=4," "&F31," "&F31)))) -> Nuts | V31: =IF(I31=1,K31,IF(I31=2," "&K31,IF(I31=3," "&K31,IF(I31=4," "&K31," "&K31)))) | W31: =IF(N31=1,P31,IF(N31=2," "&P31,IF(N31=3," "&P31,IF(N31=4," "&P31," "&P31)))) -> Urban households
C32: 3 | D32: a_bana | E32: Bananas and plantains | F32: Bananas and plantains | N32: 3 | O32: h_hhd-u0 | P32: Urban - decile 1 (low) | T32: =IF(C32=1,E32,IF(C32=2," "&E32,IF(C32=3," "&E32,IF(C32=4," "&E32," "&E32)))) -> Bananas and plantains | U32: =IF(C32=1,F32,IF(C32=2," "&F32,IF(C32=3," "&F32,IF(C32=4," "&F32," "&F32)))) -> Bananas and plantains | V32: =IF(I32=1,K32,IF(I32=2," "&K32,IF(I32=3," "&K32,IF(I32=4," "&K32," "&K32)))) | W32: =IF(N32=1,P32,IF(N32=2," "&P32,IF(N32=3," "&P32,IF(N32=4," "&P32," "&P32)))) -> Urban - decile 1 (low)
C33: 3 | D33: a_frui | E33: Other fruits | F33: Other fruits | N33: 3 | O33: h_hhd-u1 | P33: Urban - decile 2 | T33: =IF(C33=1,E33,IF(C33=2," "&E33,IF(C33=3," "&E33,IF(C33=4," "&E33," "&E33)))) -> Other fruits | U33: =IF(C33=1,F33,IF(C33=2," "&F33,IF(C33=3," "&F33,IF(C33=4," "&F33," "&F33)))) -> Other fruits | V33: =IF(I33=1,K33,IF(I33=2," "&K33,IF(I33=3," "&K33,IF(I33=4," "&K33," "&K33)))) | W33: =IF(N33=1,P33,IF(N33=2," "&P33,IF(N33=3," "&P33,IF(N33=4," "&P33," "&P33)))) -> Urban - decile 2
C34: 3 | D34: a_teal | E34: Leaf tea | F34: Leaf tea | N34: 3 | O34: h_hhd-u2 | P34: Urban - decile 3 | T34: =IF(C34=1,E34,IF(C34=2," "&E34,IF(C34=3," "&E34,IF(C34=4," "&E34," "&E34)))) -> Leaf tea | U34: =IF(C34=1,F34,IF(C34=2," "&F34,IF(C34=3," "&F34,IF(C34=4," "&F34," "&F34)))) -> Leaf tea | V34: =IF(I34=1,K34,IF(I34=2," "&K34,IF(I34=3," "&K34,IF(I34=4," "&K34," "&K34)))) | W34: =IF(N34=1,P34,IF(N34=2," "&P34,IF(N34=3," "&P34,IF(N34=4," "&P34," "&P34)))) -> Urban - decile 3
C35: 3 | D35: a_coff | E35: Coffee | F35: Coffee | N35: 3 | O35: h_hhd-u3 | P35: Urban - decile 4 | T35: =IF(C35=1,E35,IF(C35=2," "&E35,IF(C35=3," "&E35,IF(C35=4," "&E35," "&E35)))) -> Coffee | U35: =IF(C35=1,F35,IF(C35=2," "&F35,IF(C35=3," "&F35,IF(C35=4," "&F35," "&F35)))) -> Coffee | V35: =IF(I35=1,K35,IF(I35=2," "&K35,IF(I35=3," "&K35,IF(I35=4," "&K35," "&K35)))) | W35: =IF(N35=1,P35,IF(N35=2," "&P35,IF(N35=3," "&P35,IF(N35=4," "&P35," "&P35)))) -> Urban - decile 4
C36: 3 | D36: a_coco | E36: Cocoa | F36: Cocoa | N36: 3 | O36: h_hhd-u4 | P36: Urban - decile 5 | T36: =IF(C36=1,E36,IF(C36=2," "&E36,IF(C36=3," "&E36,IF(C36=4," "&E36," "&E36)))) -> Cocoa | U36: =IF(C36=1,F36,IF(C36=2," "&F36,IF(C36=3," "&F36,IF(C36=4," "&F36," "&F36)))) -> Cocoa | V36: =IF(I36=1,K36,IF(I36=2," "&K36,IF(I36=3," "&K36,IF(I36=4," "&K36," "&K36)))) | W36: =IF(N36=1,P36,IF(N36=2," "&P36,IF(N36=3," "&P36,IF(N36=4," "&P36," "&P36)))) -> Urban - decile 5
C37: 3 | D37: a_flwr | E37: Cut flowers | F37: Cut flowers | N37: 3 | O37: h_hhd-u5 | P37: Urban - decile 6 | T37: =IF(C37=1,E37,IF(C37=2," "&E37,IF(C37=3," "&E37,IF(C37=4," "&E37," "&E37)))) -> Cut flowers | U37: =IF(C37=1,F37,IF(C37=2," "&F37,IF(C37=3," "&F37,IF(C37=4," "&F37," "&F37)))) -> Cut flowers | V37: =IF(I37=1,K37,IF(I37=2," "&K37,IF(I37=3," "&K37,IF(I37=4," "&K37," "&K37)))) | W37: =IF(N37=1,P37,IF(N37=2," "&P37,IF(N37=3," "&P37,IF(N37=4," "&P37," "&P37)))) -> Urban - decile 6
C38: 3 | D38: a_rubb | E38: Rubber | F38: Rubber | N38: 3 | O38: h_hhd-u6 | P38: Urban - decile 7 | T38: =IF(C38=1,E38,IF(C38=2," "&E38,IF(C38=3," "&E38,IF(C38=4," "&E38," "&E38)))) -> Rubber | U38: =IF(C38=1,F38,IF(C38=2," "&F38,IF(C38=3," "&F38,IF(C38=4," "&F38," "&F38)))) -> Rubber | V38: =IF(I38=1,K38,IF(I38=2," "&K38,IF(I38=3," "&K38,IF(I38=4," "&K38," "&K38)))) | W38: =IF(N38=1,P38,IF(N38=2," "&P38,IF(N38=3," "&P38,IF(N38=4," "&P38," "&P38)))) -> Urban - decile 7
C39: 3 | D39: a_ocrp | E39: Other crops | F39: Other crops | N39: 3 | O39: h_hhd-u7 | P39: Urban - decile 8 | T39: =IF(C39=1,E39,IF(C39=2," "&E39,IF(C39=3," "&E39,IF(C39=4," "&E39," "&E39)))) -> Other crops | U39: =IF(C39=1,F39,IF(C39=2," "&F39,IF(C39=3," "&F39,IF(C39=4," "&F39," "&F39)))) -> Other crops | V39: =IF(I39=1,K39,IF(I39=2," "&K39,IF(I39=3," "&K39,IF(I39=4," "&K39," "&K39)))) | W39: =IF(N39=1,P39,IF(N39=2," "&P39,IF(N39=3," "&P39,IF(N39=4," "&P39," "&P39)))) -> Urban - decile 8
C40: 2 | D40: aa_LIVE | E40: Livestock | F40: Livestock | N40: 3 | O40: h_hhd-u8 | P40: Urban - decile 9 | T40: =IF(C40=1,E40,IF(C40=2," "&E40,IF(C40=3," "&E40,IF(C40=4," "&E40," "&E40)))) -> Livestock | U40: =IF(C40=1,F40,IF(C40=2," "&F40,IF(C40=3," "&F40,IF(C40=4," "&F40," "&F40)))) -> Livestock | V40: =IF(I40=1,K40,IF(I40=2," "&K40,IF(I40=3," "&K40,IF(I40=4," "&K40," "&K40)))) | W40: =IF(N40=1,P40,IF(N40=2," "&P40,IF(N40=3," "&P40,IF(N40=4," "&P40," "&P40)))) -> Urban - decile 9
C41: 3 | D41: a_catt | E41: Cattle | F41: Cattle | N41: 3 | O41: h_hhd-u9 | P41: Urban - decile 10 (high) | T41: =IF(C41=1,E41,IF(C41=2," "&E41,IF(C41=3," "&E41,IF(C41=4," "&E41," "&E41)))) -> Cattle | U41: =IF(C41=1,F41,IF(C41=2," "&F41,IF(C41=3," "&F41,IF(C41=4," "&F41," "&F41)))) -> Cattle | V41: =IF(I41=1,K41,IF(I41=2," "&K41,IF(I41=3," "&K41,IF(I41=4," "&K41," "&K41)))) | W41: =IF(N41=1,P41,IF(N41=2," "&P41,IF(N41=3," "&P41,IF(N41=4," "&P41," "&P41)))) -> Urban - decile 10 (high)
C42: 3 | D42: a_milk | E42: Raw milk | F42: Raw milk | T42: =IF(C42=1,E42,IF(C42=2," "&E42,IF(C42=3," "&E42,IF(C42=4," "&E42," "&E42)))) -> Raw milk | U42: =IF(C42=1,F42,IF(C42=2," "&F42,IF(C42=3," "&F42,IF(C42=4," "&F42," "&F42)))) -> Raw milk | V42: =IF(I42=1,K42,IF(I42=2," "&K42,IF(I42=3," "&K42,IF(I42=4," "&K42," "&K42)))) | W42: =IF(N42=1,P42,IF(N42=2," "&P42,IF(N42=3," "&P42,IF(N42=4," "&P42," "&P42))))
C43: 3 | D43: a_poul | E43: Poultry | F43: Poultry | T43: =IF(C43=1,E43,IF(C43=2," "&E43,IF(C43=3," "&E43,IF(C43=4," "&E43," "&E43)))) -> Poultry | U43: =IF(C43=1,F43,IF(C43=2," "&F43,IF(C43=3," "&F43,IF(C43=4," "&F43," "&F43)))) -> Poultry | V43: =IF(I43=1,K43,IF(I43=2," "&K43,IF(I43=3," "&K43,IF(I43=4," "&K43," "&K43)))) | W43: =IF(N43=1,P43,IF(N43=2," "&P43,IF(N43=3," "&P43,IF(N43=4," "&P43," "&P43))))
C44: 3 | D44: a_eggs | E44: Eggs | F44: Eggs | T44: =IF(C44=1,E44,IF(C44=2," "&E44,IF(C44=3," "&E44,IF(C44=4," "&E44," "&E44)))) -> Eggs | U44: =IF(C44=1,F44,IF(C44=2," "&F44,IF(C44=3," "&F44,IF(C44=4," "&F44," "&F44)))) -> Eggs | V44: =IF(I44=1,K44,IF(I44=2," "&K44,IF(I44=3," "&K44,IF(I44=4," "&K44," "&K44)))) | W44: =IF(N44=1,P44,IF(N44=2," "&P44,IF(N44=3," "&P44,IF(N44=4," "&P44," "&P44))))
C45: 3 | D45: a_smlr | E45: Small ruminants | F45: Small ruminants | T45: =IF(C45=1,E45,IF(C45=2," "&E45,IF(C45=3," "&E45,IF(C45=4," "&E45," "&E45)))) -> Small ruminants | U45: =IF(C45=1,F45,IF(C45=2," "&F45,IF(C45=3," "&F45,IF(C45=4," "&F45," "&F45)))) -> Small ruminants | V45: =IF(I45=1,K45,IF(I45=2," "&K45,IF(I45=3," "&K45,IF(I45=4," "&K45," "&K45)))) | W45: =IF(N45=1,P45,IF(N45=2," "&P45,IF(N45=3," "&P45,IF(N45=4," "&P45," "&P45))))
C46: 3 | D46: a_oliv | E46: Other livestock | F46: Other livestock | T46: =IF(C46=1,E46,IF(C46=2," "&E46,IF(C46=3," "&E46,IF(C46=4," "&E46," "&E46)))) -> Other livestock | U46: =IF(C46=1,F46,IF(C46=2," "&F46,IF(C46=3," "&F46,IF(C46=4," "&F46," "&F46)))) -> Other livestock | V46: =IF(I46=1,K46,IF(I46=2," "&K46,IF(I46=3," "&K46,IF(I46=4," "&K46," "&K46)))) | W46: =IF(N46=1,P46,IF(N46=2," "&P46,IF(N46=3," "&P46,IF(N46=4," "&P46," "&P46))))
C47: 2 | D47: aa_OAGR | E47: Other agriculture | F47: Other agriculture | T47: =IF(C47=1,E47,IF(C47=2," "&E47,IF(C47=3," "&E47,IF(C47=4," "&E47," "&E47)))) -> Other agriculture | U47: =IF(C47=1,F47,IF(C47=2," "&F47,IF(C47=3," "&F47,IF(C47=4," "&F47," "&F47)))) -> Other agriculture | V47: =IF(I47=1,K47,IF(I47=2," "&K47,IF(I47=3," "&K47,IF(I47=4," "&K47," "&K47)))) | W47: =IF(N47=1,P47,IF(N47=2," "&P47,IF(N47=3," "&P47,IF(N47=4," "&P47," "&P47))))
C48: 3 | D48: a_fore | E48: Forestry | F48: Forestry | T48: =IF(C48=1,E48,IF(C48=2," "&E48,IF(C48=3," "&E48,IF(C48=4," "&E48," "&E48)))) -> Forestry | U48: =IF(C48=1,F48,IF(C48=2," "&F48,IF(C48=3," "&F48,IF(C48=4," "&F48," "&F48)))) -> Forestry | V48: =IF(I48=1,K48,IF(I48=2," "&K48,IF(I48=3," "&K48,IF(I48=4," "&K48," "&K48)))) | W48: =IF(N48=1,P48,IF(N48=2," "&P48,IF(N48=3," "&P48,IF(N48=4," "&P48," "&P48))))
C49: 3 | D49: a_aqua | E49: Aquaculture | F49: Aquaculture | T49: =IF(C49=1,E49,IF(C49=2," "&E49,IF(C49=3," "&E49,IF(C49=4," "&E49," "&E49)))) -> Aquaculture | U49: =IF(C49=1,F49,IF(C49=2," "&F49,IF(C49=3," "&F49,IF(C49=4," "&F49," "&F49)))) -> Aquaculture | V49: =IF(I49=1,K49,IF(I49=2," "&K49,IF(I49=3," "&K49,IF(I49=4," "&K49," "&K49)))) | W49: =IF(N49=1,P49,IF(N49=2," "&P49,IF(N49=3," "&P49,IF(N49=4," "&P49," "&P49))))
C50: 3 | D50: a_fish | E50: Capture fisheries | F50: Capture fisheries | T50: =IF(C50=1,E50,IF(C50=2," "&E50,IF(C50=3," "&E50,IF(C50=4," "&E50," "&E50)))) -> Capture fisheries | U50: =IF(C50=1,F50,IF(C50=2," "&F50,IF(C50=3," "&F50,IF(C50=4," "&F50," "&F50)))) -> Capture fisheries | V50: =IF(I50=1,K50,IF(I50=2," "&K50,IF(I50=3," "&K50,IF(I50=4," "&K50," "&K50)))) | W50: =IF(N50=1,P50,IF(N50=2," "&P50,IF(N50=3," "&P50,IF(N50=4," "&P50," "&P50))))
C51: 1 | D51: aa_INDU | E51: Industry | F51: Industry | T51: =IF(C51=1,E51,IF(C51=2," "&E51,IF(C51=3," "&E51,IF(C51=4," "&E51," "&E51)))) -> Industry | U51: =IF(C51=1,F51,IF(C51=2," "&F51,IF(C51=3," "&F51,IF(C51=4," "&F51," "&F51)))) -> Industry | V51: =IF(I51=1,K51,IF(I51=2," "&K51,IF(I51=3," "&K51,IF(I51=4," "&K51," "&K51)))) | W51: =IF(N51=1,P51,IF(N51=2," "&P51,IF(N51=3," "&P51,IF(N51=4," "&P51," "&P51))))
C52: 2 | D52: aa_MINE | E52: Mining | F52: Mining | T52: =IF(C52=1,E52,IF(C52=2," "&E52,IF(C52=3," "&E52,IF(C52=4," "&E52," "&E52)))) -> Mining | U52: =IF(C52=1,F52,IF(C52=2," "&F52,IF(C52=3," "&F52,IF(C52=4," "&F52," "&F52)))) -> Mining | V52: =IF(I52=1,K52,IF(I52=2," "&K52,IF(I52=3," "&K52,IF(I52=4," "&K52," "&K52)))) | W52: =IF(N52=1,P52,IF(N52=2," "&P52,IF(N52=3," "&P52,IF(N52=4," "&P52," "&P52))))
C53: 3 | D53: a_coal | E53: Coal and lignite | F53: Coal and lignite | T53: =IF(C53=1,E53,IF(C53=2," "&E53,IF(C53=3," "&E53,IF(C53=4," "&E53," "&E53)))) -> Coal and lignite | U53: =IF(C53=1,F53,IF(C53=2," "&F53,IF(C53=3," "&F53,IF(C53=4," "&F53," "&F53)))) -> Coal and lignite | V53: =IF(I53=1,K53,IF(I53=2," "&K53,IF(I53=3," "&K53,IF(I53=4," "&K53," "&K53)))) | W53: =IF(N53=1,P53,IF(N53=2," "&P53,IF(N53=3," "&P53,IF(N53=4," "&P53," "&P53))))
... C120: 2 | D120: a_osrv | E120: Other services | F120: Other services | T120: =IF(C120=1,E120,IF(C120=2," "&E120,IF(C120=3," "&E120,IF(C120=4," "&E120," "&E120)))) -> Other services | U120: =IF(C120=1,F120,IF(C120=2," "&F120,IF(C120=3," "&F120,IF(C120=4," "&F120," "&F120)))) -> Other services | V120: =IF(I120=1,K120,IF(I120=2," "&K120,IF(I120=3," "&K120,IF(I120=4," "&K120," "&K120)))) | W120: =IF(N120=1,P120,IF(N120=2," "&P120,IF(N120=3," "&P120,IF(N120=4," "&P120," "&P120))))
T121: =IF(C121=1,E121,IF(C121=2," "&E121,IF(C121=3," "&E121,IF(C121=4," "&E121," "&E121)))) | U121: =IF(C121=1,F121,IF(C121=2," "&F121,IF(C121=3," "&F121,IF(C121=4," "&F121," "&F121)))) | V121: =IF(I121=1,K121,IF(I121=2," "&K121,IF(I121=3," "&K121,IF(I121=4," "&K121," "&K121)))) | W121: =IF(N121=1,P121,IF(N121=2," "&P121,IF(N121=3," "&P121,IF(N121=4," "&P121," "&P121))))
T122: =IF(C122=1,E122,IF(C122=2," "&E122,IF(C122=3," "&E122,IF(C122=4," "&E122," "&E122)))) | U122: =IF(C122=1,F122,IF(C122=2," "&F122,IF(C122=3," "&F122,IF(C122=4," "&F122," "&F122)))) | V122: =IF(I122=1,K122,IF(I122=2," "&K122,IF(I122=3," "&K122,IF(I122=4," "&K122," "&K122)))) | W122: =IF(N122=1,P122,IF(N122=2," "&P122,IF(N122=3," "&P122,IF(N122=4," "&P122," "&P122))))
T123: =IF(C123=1,E123,IF(C123=2," "&E123,IF(C123=3," "&E123,IF(C123=4," "&E123," "&E123)))) | U123: =IF(C123=1,F123,IF(C123=2," "&F123,IF(C123=3," "&F123,IF(C123=4," "&F123," "&F123)))) | V123: =IF(I123=1,K123,IF(I123=2," "&K123,IF(I123=3," "&K123,IF(I123=4," "&K123," "&K123)))) | W123: =IF(N123=1,P123,IF(N123=2," "&P123,IF(N123=3," "&P123,IF(N123=4," "&P123," "&P123))))
T124: =IF(C124=1,E124,IF(C124=2," "&E124,IF(C124=3," "&E124,IF(C124=4," "&E124," "&E124)))) | U124: =IF(C124=1,F124,IF(C124=2," "&F124,IF(C124=3," "&F124,IF(C124=4," "&F124," "&F124)))) | V124: =IF(I124=1,K124,IF(I124=2," "&K124,IF(I124=3," "&K124,IF(I124=4," "&K124," "&K124)))) | W124: =IF(N124=1,P124,IF(N124=2," "&P124,IF(N124=3," "&P124,IF(N124=4," "&P124," "&P124))))
T125: =IF(C125=1,E125,IF(C125=2," "&E125,IF(C125=3," "&E125,IF(C125=4," "&E125," "&E125)))) | U125: =IF(C125=1,F125,IF(C125=2," "&F125,IF(C125=3," "&F125,IF(C125=4," "&F125," "&F125)))) | V125: =IF(I125=1,K125,IF(I125=2," "&K125,IF(I125=3," "&K125,IF(I125=4," "&K125," "&K125)))) | W125: =IF(N125=1,P125,IF(N125=2," "&P125,IF(N125=3," "&P125,IF(N125=4," "&P125," "&P125))))
T126: =IF(C126=1,E126,IF(C126=2," "&E126,IF(C126=3," "&E126,IF(C126=4," "&E126," "&E126)))) | U126: =IF(C126=1,F126,IF(C126=2," "&F126,IF(C126=3," "&F126,IF(C126=4," "&F126," "&F126)))) | V126: =IF(I126=1,K126,IF(I126=2," "&K126,IF(I126=3," "&K126,IF(I126=4," "&K126," "&K126)))) | W126: =IF(N126=1,P126,IF(N126=2," "&P126,IF(N126=3," "&P126,IF(N126=4," "&P126," "&P126))))
T127: =IF(C127=1,E127,IF(C127=2," "&E127,IF(C127=3," "&E127,IF(C127=4," "&E127," "&E127)))) | U127: =IF(C127=1,F127,IF(C127=2," "&F127,IF(C127=3," "&F127,IF(C127=4," "&F127," "&F127)))) | V127: =IF(I127=1,K127,IF(I127=2," "&K127,IF(I127=3," "&K127,IF(I127=4," "&K127," "&K127)))) | W127: =IF(N127=1,P127,IF(N127=2," "&P127,IF(N127=3," "&P127,IF(N127=4," "&P127," "&P127))))
T128: =IF(C128=1,E128,IF(C128=2," "&E128,IF(C128=3," "&E128,IF(C128=4," "&E128," "&E128)))) | U128: =IF(C128=1,F128,IF(C128=2," "&F128,IF(C128=3," "&F128,IF(C128=4," "&F128," "&F128)))) | V128: =IF(I128=1,K128,IF(I128=2," "&K128,IF(I128=3," "&K128,IF(I128=4," "&K128," "&K128)))) | W128: =IF(N128=1,P128,IF(N128=2," "&P128,IF(N128=3," "&P128,IF(N128=4," "&P128," "&P128))))
T129: =IF(C129=1,E129,IF(C129=2," "&E129,IF(C129=3," "&E129,IF(C129=4," "&E129," "&E129)))) | U129: =IF(C129=1,F129,IF(C129=2," "&F129,IF(C129=3," "&F129,IF(C129=4," "&F129," "&F129)))) | V129: =IF(I129=1,K129,IF(I129=2," "&K129,IF(I129=3," "&K129,IF(I129=4," "&K129," "&K129)))) | W129: =IF(N129=1,P129,IF(N129=2," "&P129,IF(N129=3," "&P129,IF(N129=4," "&P129," "&P129))))
T130: =IF(C130=1,E130,IF(C130=2," "&E130,IF(C130=3," "&E130,IF(C130=4," "&E130," "&E130)))) | U130: =IF(C130=1,F130,IF(C130=2," "&F130,IF(C130=3," "&F130,IF(C130=4," "&F130," "&F130)))) | V130: =IF(I130=1,K130,IF(I130=2," "&K130,IF(I130=3," "&K130,IF(I130=4," "&K130," "&K130)))) | W130: =IF(N130=1,P130,IF(N130=2," "&P130,IF(N130=3," "&P130,IF(N130=4," "&P130," "&P130))))
T131: =IF(C131=1,E131,IF(C131=2," "&E131,IF(C131=3," "&E131,IF(C131=4," "&E131," "&E131)))) | U131: =IF(C131=1,F131,IF(C131=2," "&F131,IF(C131=3," "&F131,IF(C131=4," "&F131," "&F131)))) | V131: =IF(I131=1,K131,IF(I131=2," "&K131,IF(I131=3," "&K131,IF(I131=4," "&K131," "&K131)))) | W131: =IF(N131=1,P131,IF(N131=2," "&P131,IF(N131=3," "&P131,IF(N131=4," "&P131," "&P131))))
T132: =IF(C132=1,E132,IF(C132=2," "&E132,IF(C132=3," "&E132,IF(C132=4," "&E132," "&E132)))) | U132: =IF(C132=1,F132,IF(C132=2," "&F132,IF(C132=3," "&F132,IF(C132=4," "&F132," "&F132)))) | V132: =IF(I132=1,K132,IF(I132=2," "&K132,IF(I132=3," "&K132,IF(I132=4," "&K132," "&K132)))) | W132: =IF(N132=1,P132,IF(N132=2," "&P132,IF(N132=3," "&P132,IF(N132=4," "&P132," "&P132))))
... T158: =IF(C158=1,E158,IF(C158=2," "&E158,IF(C158=3," "&E158,IF(C158=4," "&E158," "&E158)))) | U158: =IF(C158=1,F158,IF(C158=2," "&F158,IF(C158=3," "&F158,IF(C158=4," "&F158," "&F158)))) | V158: =IF(I158=1,K158,IF(I158=2," "&K158,IF(I158=3," "&K158,IF(I158=4," "&K158," "&K158)))) | W158: =IF(N158=1,P158,IF(N158=2," "&P158,IF(N158=3," "&P158,IF(N158=4," "&P158," "&P158))))

Sheet Base
A1: Base Year Economic Structure and Tax Revenues | L1: Tables: | M1: =C5 -> Economic structure
M2: =X5 -> Indirect taxes
C5: Economic structure | X5: Indirect taxes
E6: Share of total (%) | P6: Intensity ratios | S6: Transaction cost rates (%) | Z6: Import tariffs | AC6: Export taxes | AF6: Sales taxes | AI6: Activity taxes | AL6: Value-added taxes
E7: Value- | F7: Output | G7: Employ- | H7: Comp. | I7: Private consumption | L7: Gov. | M7: Invest. | N7: Export | O7: Import | P7: Own con. | Q7: Exports | R7: Imports | S7: Exports | T7: Imports | U7: Domestic | Z7: Tax base | AA7: Tax | AB7: Revenue | AC7: Tax base | AD7: Tax | AE7: Revenue | AF7: Tax base | AG7: Tax | AH7: Revenue | AI7: Tax base | AJ7: Tax | AK7: Revenue | AL7: Tax base | AM7: Tax | AN7: Revenue
E8: added | F8: value | G8: ment | H8: supply | I8: Total | J8: Own | K8: Market | L8: cons. | M8: demand | N8: value | O8: value | P8: / output | Q8: / output | R8: / demand | Z8: shares | AA8: rate | AB8: share | AC8: shares | AD8: rate | AE8: share | AF8: shares | AG8: rate | AH8: share | AI8: shares | AJ8: rate | AK8: share | AL8: shares | AM8: rate | AN8: share
E9: VAshr | F9: PRDshr | G9: EMPshr | H9: QQshr | I9: HHDshr | J9: OWNshr | K9: MKTshr | L9: GOVshr | M9: INVshr | N9: EXPshr | O9: IMPshr | P9: OWN-OUTshr | Q9: EXP-OUTshr | R9: IMP-DEMshr | S9: TRErate | T9: TRMrate | U9: TRDrate | Z9: tIMPshr | AA9: tIMPtax | AB9: tIMPrev | AC9: tEXPshr | AD9: tEXPtax | AE9: tEXPrev | AF9: tSALshr | AG9: tSALtax | AH9: tSALrev | AI9: tACTshr | AJ9: tACTtax | AK9: tACTrev | AL9: tVADshr | AM9: tVADtax | AN9: tVADrev
A10: 1 | C10: =Notes!U9 -> All products | D10: aa_GDP | E10: 100 | F10: 100 | G10: 100 | H10: 100 | I10: 100 | J10: 100 | K10: 100 | L10: 100 | M10: 100 | N10: 100 | O10: 100 | P10: 0.60475287 | Q10: 4.7997568 | R10: 8.6630262 | S10: 10.899257 | T10: 12.088755 | U10: 7.9429173 | X10: =Notes!U9 -> All products | Y10: aa_GDP | Z10: 100 | AA10: 3.6487805 | AB10: 100 | AC10: 100 | AD10: 0.00010507789 | AE10: 100 | AF10: 100 | AG10: 1.2247334 | AH10: 100 | AI10: 100 | AJ10: Eps | AK10: Eps | AL10: 100 | AM10: Eps | AN10: Eps
A11: 2 | C11: =Notes!U10 -> Agriculture | D11: aa_AGRI | E11: 11.553747 | F11: 10.238637 | G11: 13.109828 | H11: 11.359471 | I11: 12.187737 | J11: 100 | K11: 10.634928 | L11: Eps | M11: Eps | N11: 1.2441389 | O11: 12.301297 | P11: 5.9065757 | Q11: 0.59052269 | R11: 9.2389667 | S11: 14.598563 | T11: 10.892793 | U11: 18.461649 | X11: =Notes!U10 -> Agriculture | Y11: aa_AGRI | Z11: 12.301297 | AA11: 4.737806 | AB11: 15.972778 | AC11: 1.2441389 | AD11: Eps | AE11: Eps | AF11: 11.359471 | AG11: 0.0096402411 | AH11: 0.089413778 | AI11: 10.238637 | AJ11: Eps | AK11: Eps | AL11: 11.553747 | AM11: Eps | AN11: Eps
A12: 3 | C12: =Notes!U11 -> Crops | D12: aa_CROP | E12: 5.8017781 | F12: 3.9325564 | G12: 7.8527519 | H12: 5.1209736 | I12: 3.5585992 | J12: 11.866097 | K12: 3.4116954 | L12: Eps | M12: Eps | N12: 0.77696186 | O12: 12.276392 | P12: 1.8247816 | Q12: 0.97093689 | R12: 20.450527 | S12: 9.8918325 | T12: 10.895827 | U12: 17.606889 | X12: =Notes!U11 -> Crops | Y12: aa_CROP | Z12: 12.276392 | AA12: 4.7112615 | AB12: 15.85113 | AC12: 0.77696186 | AD12: Eps | AE12: Eps | AF12: 5.1209736 | AG12: 0.021384222 | AH12: 0.089413778 | AI12: 3.9325564 | AJ12: Eps | AK12: Eps | AL12: 5.8017781 | AM12: Eps | AN12: Eps
A13: 4 | C13: =Notes!U12 -> Maize | D13: a_maiz | E13: 0.057176284 | F13: 0.035421683 | G13: 0.065273844 | H13: 0.11106867 | I13: 0.00095890009 | J13: 0.055185278 | K13: Eps | L13: Eps | M13: Eps | N13: Eps | O13: 0.91911364 | P13: 0.94217587 | Q13: Eps | R13: 68.414527 | S13: Eps | T13: 12.213567 | U13: 12.213567 | X13: =Notes!U12 -> Maize | Y13: a_maiz | Z13: 0.91911364 | AA13: Eps | AB13: Eps | AC13: Eps | AD13: Eps | AE13: Eps | AF13: 0.11106867 | AG13: Eps | AH13: Eps | AI13: 0.035421683 | AJ13: Eps | AK13: Eps | AL13: 0.057176284 | AM13: Eps | AN13: Eps
A14: 5 | C14: =Notes!U13 -> Sorghum and millet | D14: a_sorg | E14: Eps | F14: Eps | G14: Eps | H14: Eps | I14: Eps | J14: Eps | K14: Eps | L14: Eps | M14: Eps | N14: Eps | O14: Eps | P14: Eps | Q14: Eps | R14: Eps | S14: Eps | T14: Eps | U14: Eps | X14: =Notes!U13 -> Sorghum and millet | Y14: a_sorg | Z14: Eps | AA14: Eps | AB14: Eps | AC14: Eps | AD14: Eps | AE14: Eps | AF14: Eps | AG14: Eps | AH14: Eps | AI14: Eps | AJ14: Eps | AK14: Eps | AL14: Eps | AM14: Eps | AN14: Eps
A15: 6 | C15: =Notes!U14 -> Rice paddy (Aman) | D15: a_aman | E15: 1.7790835 | F15: 1.0235941 | G15: 2.7223872 | H15: 1.1263284 | I15: Eps | J15: Eps | K15: Eps | L15: Eps | M15: Eps | N15: Eps | O15: Eps | P15: Eps | Q15: Eps | R15: Eps | S15: Eps | T15: Eps | U15: 20.235236 | X15: =Notes!U14 -> Rice paddy (Aman) | Y15: a_aman | Z15: Eps | AA15: Eps | AB15: Eps | AC15: Eps | AD15: Eps | AE15: Eps | AF15: 1.1263284 | AG15: Eps | AH15: Eps | AI15: 1.0235941 | AJ15: Eps | AK15: Eps | AL15: 1.7790835 | AM15: Eps | AN15: Eps
A16: 7 | C16: =Notes!U15 -> Rice paddy (Boro) | D16: a_boro | E16: 1.7183562 | F16: 1.1733921 | G16: 2.6294443 | H16: 1.2816833 | I16: Eps | J16: Eps | K16: Eps | L16: Eps | M16: Eps | N16: Eps | O16: Eps | P16: Eps | Q16: Eps | R16: Eps | S16: Eps | T16: Eps | U16: 19.645386 | X16: =Notes!U15 -> Rice paddy (Boro) | Y16: a_boro | Z16: Eps | AA16: Eps | AB16: Eps | AC16: Eps | AD16: Eps | AE16: Eps | AF16: 1.2816833 | AG16: Eps | AH16: Eps | AI16: 1.1733921 | AJ16: Eps | AK16: Eps | AL16: 1.7183562 | AM16: Eps | AN16: Eps
A17: 8 | C17: =Notes!U16 -> Wheat and barley | D17: a_whea | E17: 0.019864455 | F17: 0.013934424 | G17: 0.025794146 | H17: 0.33105043 | I17: 0.024401669 | J17: 1.4043308 | K17: Eps | L17: Eps | M17: Eps | N17: Eps | O17: 4.078035 | P17: 60.947838 | Q17: Eps | R17: 98.411888 | S17: Eps | T17: 9.1536886 | U17: 9.1536886 | X17: =Notes!U16 -> Wheat and barley | Y17: a_whea | Z17: 4.078035 | AA17: Eps | AB17: Eps | AC17: Eps | AD17: Eps | AE17: Eps | AF17: 0.33105043 | AG17: Eps | AH17: Eps | AI17: 0.013934424 | AJ17: Eps | AK17: Eps | AL17: 0.019864455 | AM17: Eps | AN17: Eps
A18: 9 | C18: =Notes!U17 -> Other cereals | D18: a_ocer | E18: Eps | F18: Eps | G18: Eps | H18: Eps | I18: Eps | J18: Eps | K18: Eps | L18: Eps | M18: Eps | N18: Eps | O18: Eps | P18: Eps | Q18: Eps | R18: Eps | S18: Eps | T18: Eps | U18: Eps | X18: =Notes!U17 -> Other cereals | Y18: a_ocer | Z18: Eps | AA18: Eps | AB18: Eps | AC18: Eps | AD18: Eps | AE18: Eps | AF18: Eps | AG18: Eps | AH18: Eps | AI18: Eps | AJ18: Eps | AK18: Eps | AL18: Eps | AM18: Eps | AN18: Eps
A19: 10 | C19: =Notes!U18 -> Pulses | D19: a_puls | E19: 0.097083773 | F19: 0.071768206 | G19: 0.10132265 | H19: 0.18482441 | I19: 0.44607328 | J19: 0.29640181 | K19: 0.44871997 | L19: Eps | M19: Eps | N19: Eps | O19: 1.4135578 | P19: 2.4976219 | Q19: Eps | R19: 62.552183 | S19: Eps | T19: 11.261959 | U19: 11.261959 | X19: =Notes!U18 -> Pulses | Y19: a_puls | Z19: 1.4135578 | AA19: Eps | AB19: Eps | AC19: Eps | AD19: Eps | AE19: Eps | AF19: 0.18482441 | AG19: Eps | AH19: Eps | AI19: 0.071768206 | AJ19: Eps | AK19: Eps | AL19: 0.097083773 | AM19: Eps | AN19: Eps
A20: 11 | C20: =Notes!U19 -> Groundnuts | D20: a_gnut | E20: Eps | F20: Eps | G20: Eps | H20: Eps | I20: Eps | J20: Eps | K20: Eps | L20: Eps | M20: Eps | N20: Eps | O20: Eps | P20: Eps | Q20: Eps | R20: Eps | S20: Eps | T20: Eps | U20: Eps | X20: =Notes!U19 -> Groundnuts | Y20: a_gnut | Z20: Eps | AA20: Eps | AB20: Eps | AC20: Eps | AD20: Eps | AE20: Eps | AF20: Eps | AG20: Eps | AH20: Eps | AI20: Eps | AJ20: Eps | AK20: Eps | AL20: Eps | AM20: Eps | AN20: Eps
A21: 12 | C21: =Notes!U20 -> Other oilseeds | D21: a_oils | E21: 0.17907292 | F21: 0.11760405 | G21: 0.25315463 | H21: 0.25840135 | I21: 0.60133246 | J21: 0.052687335 | K21: 0.61103431 | L21: Eps | M21: Eps | N21: Eps | O21: 1.6621684 | P21: 0.270933 | Q21: Eps | R21: 54.300435 | S21: Eps | T21: 12.826277 | U21: 12.826277 | X21: =Notes!U20 -> Other oilseeds | Y21: a_oils | Z21: 1.6621684 | AA21: 1.3935964 | AB21: 0.63484001 | AC21: Eps | AD21: Eps | AE21: Eps | AF21: 0.25840135 | AG21: 1.2899384e-05 | AH21: 2.7215869e-06 | AI21: 0.11760405 | AJ21: Eps | AK21: Eps | AL21: 0.17907292 | AM21: Eps | AN21: Eps
A22: 13 | C22: =Notes!U21 -> Cassava | D22: a_cass | E22: Eps | F22: Eps | G22: Eps | H22: Eps | I22: Eps | J22: Eps | K22: Eps | L22: Eps | M22: Eps | N22: Eps | O22: Eps | P22: Eps | Q22: Eps | R22: Eps | S22: Eps | T22: Eps | U22: Eps | X22: =Notes!U21 -> Cassava | Y22: a_cass | Z22: Eps | AA22: Eps | AB22: Eps | AC22: Eps | AD22: Eps | AE22: Eps | AF22: Eps | AG22: Eps | AH22: Eps | AI22: Eps | AJ22: Eps | AK22: Eps | AL22: Eps | AM22: Eps | AN22: Eps
A23: 14 | C23: =Notes!U22 -> Irish potatoes | D23: a_ipot | E23: 0.15284804 | F23: 0.179351 | G23: 0.19812525 | H23: 0.17228927 | I23: 0.22602178 | J23: 0.37148202 | K23: 0.22344957 | L23: Eps | M23: Eps | N23: Eps | O23: Eps | P23: 1.2525987 | Q23: Eps | R23: Eps | S23: Eps | T23: Eps | U23: 9.7765135 | X23: =Notes!U22 -> Irish potatoes | Y23: a_ipot | Z23: Eps | AA23: Eps | AB23: Eps | AC23: Eps | AD23: Eps | AE23: Eps | AF23: 0.17228927 | AG23: Eps | AH23: Eps | AI23: 0.179351 | AJ23: Eps | AK23: Eps | AL23: 0.15284804 | AM23: Eps | AN23: Eps
A24: 15 | C24: =Notes!U23 -> Sweet potatoes | D24: a_spot | E24: Eps | F24: Eps | G24: Eps | H24: Eps | I24: Eps | J24: Eps | K24: Eps | L24: Eps | M24: Eps | N24: Eps | O24: Eps | P24: Eps | Q24: Eps | R24: Eps | S24: Eps | T24: Eps | U24: Eps | X24: =Notes!U23 -> Sweet potatoes | Y24: a_spot | Z24: Eps | AA24: Eps | AB24: Eps | AC24: Eps | AD24: Eps | AE24: Eps | AF24: Eps | AG24: Eps | AH24: Eps | AI24: Eps | AJ24: Eps | AK24: Eps | AL24: Eps | AM24: Eps | AN24: Eps
A25: 16 | C25: =Notes!U24 -> Other roots | D25: a_root | E25: Eps | F25: Eps | G25: Eps | H25: Eps | I25: Eps | J25: Eps | K25: Eps | L25: Eps | M25: Eps | N25: Eps | O25: Eps | P25: Eps | Q25: Eps | R25: Eps | S25: Eps | T25: Eps | U25: Eps | X25: =Notes!U24 -> Other roots | Y25: a_root | Z25: Eps | AA25: Eps | AB25: Eps | AC25: Eps | AD25: Eps | AE25: Eps | AF25: Eps | AG25: Eps | AH25: Eps | AI25: Eps | AJ25: Eps | AK25: Eps | AL25: Eps | AM25: Eps | AN25: Eps
A26: 17 | C26: =Notes!U25 -> Leafy vegetables | D26: a_leaf | E26: 0.13963036 | F26: 0.099928008 | G26: 0.16669182 | H26: 0.10870114 | I26: 0.37103589 | J26: 1.6291178 | K26: 0.34878888 | L26: Eps | M26: Eps | N26: Eps | O26: Eps | P26: 9.8592346 | Q26: Eps | R26: Eps | S26: Eps | T26: Eps | U26: 27.26847 | X26: =Notes!U25 -> Leafy vegetables | Y26: a_leaf | Z26: Eps | AA26: Eps | AB26: Eps | AC26: Eps | AD26: Eps | AE26: Eps | AF26: 0.10870114 | AG26: Eps | AH26: Eps | AI26: 0.099928008 | AJ26: Eps | AK26: Eps | AL26: 0.13963036 | AM26: Eps | AN26: Eps
A27: 18 | C27: =Notes!U26 -> Other vegetables | D27: a_vege | E27: 0.3074146 | F27: 0.22028886 | G27: 0.3668882 | H27: 0.28779819 | I27: 0.81368072 | J27: 3.5726511 | K27: 0.76489308 | L27: Eps | M27: Eps | N27: Eps | O27: 0.5461967 | P27: 9.8078993 | Q27: Eps | R27: 18.592568 | S27: Eps | T27: 25.568411 | U27: 25.568411 | X27: =Notes!U26 -> Other vegetables | Y27: a_vege | Z27: 0.5461967 | AA27: 0.47027658 | AB27: 0.070397086 | AC27: Eps | AD27: Eps | AE27: Eps | AF27: 0.28779819 | AG27: Eps | AH27: Eps | AI27: 0.22028886 | AJ27: Eps | AK27: Eps | AL27: 0.3074146 | AM27: Eps | AN27: Eps
A28: 19 | C28: =Notes!U27 -> Sugarcane | D28: a_sugr | E28: 0.082417407 | F28: 0.078609442 | G28: 0.099107279 | H28: 0.081424427 | I28: 0.0019455905 | J28: 0.1119699 | K28: Eps | L28: Eps | M28: Eps | N28: Eps | O28: Eps | P28: 0.86139931 | Q28: Eps | R28: Eps | S28: Eps | T28: Eps | U28: 15.993837 | X28: =Notes!U27 -> Sugarcane | Y28: a_sugr | Z28: Eps | AA28: Eps | AB28: Eps | AC28: Eps | AD28: Eps | AE28: Eps | AF28: 0.081424427 | AG28: Eps | AH28: Eps | AI28: 0.078609442 | AJ28: Eps | AK28: Eps | AL28: 0.082417407 | AM28: Eps | AN28: Eps
A29: 20 | C29: =Notes!U28 -> Tobacco | D29: a_toba | E29: 0.21507085 | F29: 0.22170607 | G29: 0.28371126 | H29: 0.21299529 | I29: 0.00064422136 | J29: 0.037075327 | K29: Eps | L29: Eps | M29: Eps | N29: Eps | O29: Eps | P29: 0.10113124 | Q29: Eps | R29: Eps | S29: Eps | T29: Eps | U29: 8.7324243 | X29: =Notes!U28 -> Tobacco | Y29: a_toba | Z29: Eps | AA29: Eps | AB29: Eps | AC29: Eps | AD29: Eps | AE29: Eps | AF29: 0.21299529 | AG29: Eps | AH29: Eps | AI29: 0.22170607 | AJ29: Eps | AK29: Eps | AL29: 0.21507085 | AM29: Eps | AN29: Eps
A30: 21 | C30: =Notes!U29 -> Cotton and fibres | D30: a_cott | E30: 0.0012261848 | F30: 0.00069174165 | G30: 0.0010244216 | H30: 0.11663325 | I30: Eps | J30: Eps | K30: Eps | L30: Eps | M30: Eps | N30: Eps | O30: 1.5760217 | P30: Eps | Q30: Eps | R30: 99.47202 | S30: Eps | T30: 1.4055052 | U30: 1.4055052 | X30: =Notes!U29 -> Cotton and fibres | Y30: a_cott | Z30: 1.5760217 | AA30: 0.0036142005 | AB30: 0.0015610856 | AC30: Eps | AD30: Eps | AE30: Eps | AF30: 0.11663325 | AG30: Eps | AH30: Eps | AI30: 0.00069174165 | AJ30: Eps | AK30: Eps | AL30: 0.0012261848 | AM30: Eps | AN30: Eps
A31: 22 | C31: =Notes!U30 -> Jute | D31: a_jute | E31: 0.25549077 | F31: 0.1722585 | G31: 0.41817349 | H31: 0.13423423 | I31: Eps | J31: Eps | K31: Eps | L31: Eps | M31: Eps | N31: 0.77696186 | O31: 0.03672612 | P31: Eps | Q31: 21.761417 | R31: 2.2036656 | S31: 9.8918325 | T31: 9.8918325 | U31: 9.8918325 | X31: =Notes!U30 -> Jute | Y31: a_jute | Z31: 0.03672612 | AA31: Eps | AB31: Eps | AC31: 0.77696186 | AD31: Eps | AE31: Eps | AF31: 0.13423423 | AG31: Eps | AH31: Eps | AI31: 0.1722585 | AJ31: Eps | AK31: Eps | AL31: 0.25549077 | AM31: Eps | AN31: Eps
A32: 23 | C32: =Notes!U31 -> Nuts | D32: a_nuts | E32: 0.10133306 | F32: 0.060723846 | G32: 0.022485198 | H32: 0.061379817 | I32: 0.10282034 | J32: 0.15859799 | K32: 0.10183401 | L32: Eps | M32: Eps | N32: Eps | O32: Eps | P32: 1.579488 | Q32: Eps | R32: Eps | S32: Eps | T32: Eps | U32: 14.539061 | X32: =Notes!U31 -> Nuts | Y32: a_nuts | Z32: Eps | AA32: Eps | AB32: Eps | AC32: Eps | AD32: Eps | AE32: Eps | AF32: 0.061379817 | AG32: Eps | AH32: Eps | AI32: 0.060723846 | AJ32: Eps | AK32: Eps | AL32: 0.10133306 | AM32: Eps | AN32: Eps
A33: 24 | C33: =Notes!U32 -> Bananas and plantains | D33: a_bana | E33: 0.044765728 | F33: 0.027203959 | G33: 0.010646074 | H33: 0.024807189 | I33: 0.080848223 | J33: 0.37277973 | K33: 0.075685917 | L33: Eps | M33: Eps | N33: Eps | O33: Eps | P33: 8.2870148 | Q33: Eps | R33: Eps | S33: Eps | T33: Eps | U33: 11.725809 | X33: =Notes!U32 -> Bananas and plantains | Y33: a_bana | Z33: Eps | AA33: Eps | AB33: Eps | AC33: Eps | AD33: Eps | AE33: Eps | AF33: 0.024807189 | AG33: Eps | AH33: Eps | AI33: 0.027203959 | AJ33: Eps | AK33: Eps | AL33: 0.044765728 | AM33: Eps | AN33: Eps
A34: 25 | C34: =Notes!U33 -> Other fruits | D34: a_frui | E34: 0.26395265 | F34: 0.15952221 | G34: 0.061102709 | H34: 0.29650429 | I34: 0.88840452 | J34: 3.77898 | K34: 0.83728967 | L34: Eps | M34: Eps | N34: Eps | O34: 1.4152583 | P34: 14.326212 | Q34: Eps | R34: 52.865249 | S34: Eps | T34: 14.168776 | U34: 14.168776 | X34: =Notes!U33 -> Other fruits | Y34: a_frui | Z34: 1.4152583 | AA34: 30.982355 | AB34: 12.017175 | AC34: Eps | AD34: Eps | AE34: Eps | AF34: 0.29650429 | AG34: Eps | AH34: Eps | AI34: 0.15952221 | AJ34: Eps | AK34: Eps | AL34: 0.26395265 | AM34: Eps | AN34: Eps
A35: 26 | C35: =Notes!U34 -> Leaf tea | D35: a_teal | E35: 0.027250198 | F35: 0.021425868 | G35: 0.031940231 | H35: 0.020194155 | I35: 0.00043158996 | J35: 0.024838262 | K35: Eps | L35: Eps | M35: Eps | N35: Eps | O35: Eps | P35: 0.7010689 | Q35: Eps | R35: Eps | S35: Eps | T35: Eps | U35: 7.5289707 | X35: =Notes!U34 -> Leaf tea | Y35: a_teal | Z35: Eps | AA35: Eps | AB35: Eps | AC35: Eps | AD35: Eps | AE35: Eps | AF35: 0.020194155 | AG35: Eps | AH35: Eps | AI35: 0.021425868 | AJ35: Eps | AK35: Eps | AL35: 0.027250198 | AM35: Eps | AN35: Eps
A36: 27 | C36: =Notes!U35 -> Coffee | D36: a_coff | E36: Eps | F36: Eps | G36: Eps | H36: Eps | I36: Eps | J36: Eps | K36: Eps | L36: Eps | M36: Eps | N36: Eps | O36: Eps | P36: Eps | Q36: Eps | R36: Eps | S36: Eps | T36: Eps | U36: Eps | X36: =Notes!U35 -> Coffee | Y36: a_coff | Z36: Eps | AA36: Eps | AB36: Eps | AC36: Eps | AD36: Eps | AE36: Eps | AF36: Eps | AG36: Eps | AH36: Eps | AI36: Eps | AJ36: Eps | AK36: Eps | AL36: Eps | AM36: Eps | AN36: Eps
A37: 28 | C37: =Notes!U36 -> Cocoa | D37: a_coco | E37: Eps | F37: Eps | G37: Eps | H37: Eps | I37: Eps | J37: Eps | K37: Eps | L37: Eps | M37: Eps | N37: Eps | O37: Eps | P37: Eps | Q37: Eps | R37: Eps | S37: Eps | T37: Eps | U37: Eps | X37: =Notes!U36 -> Cocoa | Y37: a_coco | Z37: Eps | AA37: Eps | AB37: Eps | AC37: Eps | AD37: Eps | AE37: Eps | AF37: Eps | AG37: Eps | AH37: Eps | AI37: Eps | AJ37: Eps | AK37: Eps | AL37: Eps | AM37: Eps | AN37: Eps
A38: 29 | C38: =Notes!U37 -> Cut flowers | D38: a_flwr | E38: Eps | F38: Eps | G38: Eps | H38: Eps | I38: Eps | J38: Eps | K38: Eps | L38: Eps | M38: Eps | N38: Eps | O38: Eps | P38: Eps | Q38: Eps | R38: Eps | S38: Eps | T38: Eps | U38: Eps | X38: =Notes!U37 -> Cut flowers | Y38: a_flwr | Z38: Eps | AA38: Eps | AB38: Eps | AC38: Eps | AD38: Eps | AE38: Eps | AF38: Eps | AG38: Eps | AH38: Eps | AI38: Eps | AJ38: Eps | AK38: Eps | AL38: Eps | AM38: Eps | AN38: Eps
A39: 30 | C39: =Notes!U38 -> Rubber | D39: a_rubb | E39: Eps | F39: Eps | G39: Eps | H39: Eps | I39: Eps | J39: Eps | K39: Eps | L39: Eps | M39: Eps | N39: Eps | O39: Eps | P39: Eps | Q39: Eps | R39: Eps | S39: Eps | T39: Eps | U39: Eps | X39: =Notes!U38 -> Rubber | Y39: a_rubb | Z39: Eps | AA39: Eps | AB39: Eps | AC39: Eps | AD39: Eps | AE39: Eps | AF39: Eps | AG39: Eps | AH39: Eps | AI39: Eps | AJ39: Eps | AK39: Eps | AL39: Eps | AM39: Eps | AN39: Eps
A40: 31 | C40: =Notes!U39 -> Other crops | D40: a_ocrp | E40: 0.35974115 | F40: 0.25513224 | G40: 0.39547924 | H40: 0.31065581 | I40: Eps | J40: Eps | K40: Eps | L40: Eps | M40: Eps | N40: Eps | O40: 0.62931444 | P40: Eps | Q40: Eps | R40: 19.416224 | S40: Eps | T40: 10.232283 | U40: 10.232283 | X40: =Notes!U39 -> Other crops | Y40: a_ocrp | Z40: 0.62931444 | AA40: 18.13133 | AB40: 3.1271565 | AC40: Eps | AD40: Eps | AE40: Eps | AF40: 0.31065581 | AG40: 0.35249526 | AH40: 0.089411056 | AI40: 0.25513224 | AJ40: Eps | AK40: Eps | AL40: 0.35974115 | AM40: Eps | AN40: Eps
A41: 32 | C41: =Notes!U40 -> Livestock | D41: aa_LIVE | E41: 1.7216311 | F41: 2.1205224 | G41: 1.6180891 | H41: 1.7115213 | I41: 3.5124525 | J41: 73.183561 | K41: 2.2804389 | L41: Eps | M41: Eps | N41: Eps | O41: 0.024905271 | P41: 20.871257 | Q41: Eps | R41: 0.13756077 | S41: Eps | T41: 9.5435376 | U41: 13.832993 | X41: =Notes!U40 -> Livestock | Y41: aa_LIVE | Z41: 0.024905271 | AA41: 17.822213 | AB41: 0.12164805 | AC41: Eps | AD41: Eps | AE41: Eps | AF41: 1.7115213 | AG41: Eps | AH41: Eps | AI41: 2.1205224 | AJ41: Eps | AK41: Eps | AL41: 1.7216311 | AM41: Eps | AN41: Eps
A42: 33 | C42: =Notes!U41 -> Cattle | D42: a_catt | E42: 0.41802316 | F42: 0.65258335 | G42: 0.39920543 | H42: 0.61620979 | I42: 0.11126271 | J42: 6.4032358 | K42: Eps | L42: Eps | M42: Eps | N42: Eps | O42: Eps | P42: 5.9339167 | Q42: Eps | R42: Eps | S42: Eps | T42: Eps | U42: 12.564295 | X42: =Notes!U41 -> Cattle | Y42: a_catt | Z42: Eps | AA42: Eps | AB42: Eps | AC42: Eps | AD42: Eps | AE42: Eps | AF42: 0.61620979 | AG42: Eps | AH42: Eps | AI42: 0.65258335 | AJ42: Eps | AK42: Eps | AL42: 0.41802316 | AM42: Eps | AN42: Eps
A43: 34 | C43: =Notes!U42 -> Raw milk | D43: a_milk | E43: 0.260751 | F43: 0.39983807 | G43: 0.24954649 | H43: 0.36242818 | I43: 1.1122408 | J43: 9.115758 | K43: 0.97071238 | L43: Eps | M43: Eps | N43: Eps | O43: Eps | P43: 13.787533 | Q43: Eps | R43: Eps | S43: Eps | T43: Eps | U43: 16.52035 | X43: =Notes!U42 -> Raw milk | Y43: a_milk | Z43: Eps | AA43: Eps | AB43: Eps | AC43: Eps | AD43: Eps | AE43: Eps | AF43: 0.36242818 | AG43: Eps | AH43: Eps | AI43: 0.39983807 | AJ43: Eps | AK43: Eps | AL43: 0.260751 | AM43: Eps | AN43: Eps
A44: 35 | C44: =Notes!U43 -> Poultry | D44: a_poul | E44: 0.14655953 | F44: 0.21005913 | G44: 0.12023308 | H44: 0.1594674 | I44: 0.13831227 | J44: 7.9599544 | K44: Eps | L44: Eps | M44: Eps | N44: Eps | O44: 0.024905271 | P44: 22.916429 | Q44: Eps | R44: 1.4764033 | S44: Eps | T44: 9.5435376 | U44: 9.5435376 | X44: =Notes!U43 -> Poultry | Y44: a_poul | Z44: 0.024905271 | AA44: 17.822213 | AB44: 0.12164805 | AC44: Eps | AD44: Eps | AE44: Eps | AF44: 0.1594674 | AG44: Eps | AH44: Eps | AI44: 0.21005913 | AJ44: Eps | AK44: Eps | AL44: 0.14655953 | AM44: Eps | AN44: Eps
A45: 36 | C45: =Notes!U44 -> Eggs | D45: a_eggs | E45: 0.15149365 | F45: 0.2046448 | G45: 0.13066578 | H45: 0.16596227 | I45: 0.62943756 | J45: 4.9577373 | K45: 0.55289903 | L45: Eps | M45: Eps | N45: Eps | O45: Eps | P45: 14.65078 | Q45: Eps | R45: Eps | S45: Eps | T45: Eps | U45: 7.6282294 | X45: =Notes!U44 -> Eggs | Y45: a_eggs | Z45: Eps | AA45: Eps | AB45: Eps | AC45: Eps | AD45: Eps | AE45: Eps | AF45: 0.16596227 | AG45: Eps | AH45: Eps | AI45: 0.2046448 | AJ45: Eps | AK45: Eps | AL45: 0.15149365 | AM45: Eps | AN45: Eps
A46: 37 | C46: =Notes!U45 -> Small ruminants | D46: a_smlr | E46: 0.52739008 | F46: 0.4659492 | G46: 0.51274241 | H46: 0.22717495 | I46: 1.4873537 | J46: 42.799051 | K46: 0.7568275 | L46: Eps | M46: Eps | N46: Eps | O46: Eps | P46: 55.548649 | Q46: Eps | R46: Eps | S46: Eps | T46: Eps | U46: 19.977621 | X46: =Notes!U45 -> Small ruminants | Y46: a_smlr | Z46: Eps | AA46: Eps | AB46: Eps | AC46: Eps | AD46: Eps | AE46: Eps | AF46: 0.22717495 | AG46: Eps | AH46: Eps | AI46: 0.4659492 | AJ46: Eps | AK46: Eps | AL46: 0.52739008 | AM46: Eps | AN46: Eps
A47: 38 | C47: =Notes!U46 -> Other livestock | D47: a_oliv | E47: 0.21741368 | F47: 0.18744783 | G47: 0.20569593 | H47: 0.18027871 | I47: 0.033845431 | J47: 1.9478249 | K47: Eps | L47: Eps | M47: Eps | N47: Eps | O47: Eps | P47: 6.284163 | Q47: Eps | R47: Eps | S47: Eps | T47: Eps | U47: 14.474167 | X47: =Notes!U46 -> Other livestock | Y47: a_oliv | Z47: Eps | AA47: Eps | AB47: Eps | AC47: Eps | AD47: Eps | AE47: Eps | AF47: 0.18027871 | AG47: Eps | AH47: Eps | AI47: 0.18744783 | AJ47: Eps | AK47: Eps | AL47: 0.21741368 | AM47: Eps | AN47: Eps
A48: 39 | C48: =Notes!U47 -> Other agriculture | D48: aa_OAGR | E48: 4.030338 | F48: 4.1855586 | G48: 3.6389873 | H48: 4.5269757 | I48: 5.1166852 | J48: 14.950341 | K48: 4.9427939 | L48: Eps | M48: Eps | N48: 0.46717704 | O48: Eps | P48: 2.1601088 | Q48: 0.47383862 | R48: Eps | S48: 22.426324 | T48: Eps | U48: 20.978216 | X48: =Notes!U47 -> Other agriculture | Y48: aa_OAGR | Z48: Eps | AA48: Eps | AB48: Eps | AC48: 0.46717704 | AD48: Eps | AE48: Eps | AF48: 4.5269757 | AG48: Eps | AH48: Eps | AI48: 4.1855586 | AJ48: Eps | AK48: Eps | AL48: 4.030338 | AM48: Eps | AN48: Eps
A49: 40 | C49: =Notes!U48 -> Forestry | D49: a_fore | E49: 1.4548769 | F49: 1.5966247 | G49: 0.66566442 | H49: 2.0201609 | I49: 0.75247041 | J49: Eps | K49: 0.76577656 | L49: Eps | M49: Eps | N49: Eps | O49: Eps | P49: Eps | Q49: Eps | R49: Eps | S49: Eps | T49: Eps | U49: 30.63103 | X49: =Notes!U48 -> Forestry | Y49: a_fore | Z49: Eps | AA49: Eps | AB49: Eps | AC49: Eps | AD49: Eps | AE49: Eps | AF49: 2.0201609 | AG49: Eps | AH49: Eps | AI49: 1.5966247 | AJ49: Eps | AK49: Eps | AL49: 1.4548769 | AM49: Eps | AN49: Eps
A50: 41 | C50: =Notes!U49 -> Aquaculture | D50: a_aqua | E50: 1.4625278 | F50: 1.807923 | G50: 1.5914007 | H50: 1.6985209 | I50: 2.7741857 | J50: 7.1427651 | K50: 2.6969349 | L50: Eps | M50: Eps | N50: Eps | O50: Eps | P50: 2.3892653 | Q50: Eps | R50: Eps | S50: Eps | T50: Eps | U50: 8.8083715 | X50: =Notes!U49 -> Aquaculture | Y50: a_aqua | Z50: Eps | AA50: Eps | AB50: Eps | AC50: Eps | AD50: Eps | AE50: Eps | AF50: 1.6985209 | AG50: Eps | AH50: Eps | AI50: 1.807923 | AJ50: Eps | AK50: Eps | AL50: 1.4625278 | AM50: Eps | AN50: Eps
A51: 42 | C51: =Notes!U50 -> Capture fisheries | D51: a_fish | E51: 1.1129333 | F51: 0.78101086 | G51: 1.3819221 | H51: 0.80829392 | I51: 1.5900291 | J51: 7.8075763 | K51: 1.4800825 | L51: Eps | M51: Eps | N51: 0.46717704 | O51: Eps | P51: 6.0455679 | Q51: 2.6443899 | R51: Eps | S51: 22.426324 | T51: Eps | U51: 22.426324 | X51: =Notes!U50 -> Capture fisheries | Y51: a_fish | Z51: Eps | AA51: Eps | AB51: Eps | AC51: 0.46717704 | AD51: Eps | AE51: Eps | AF51: 0.80829392 | AG51: Eps | AH51: Eps | AI51: 0.78101086 | AJ51: Eps | AK51: Eps | AL51: 1.1129333 | AM51: Eps | AN51: Eps
A52: 43 | C52: =Notes!U51 -> Industry | D52: aa_INDU | E52: 35.260304 | F52: 52.41503 | G52: 51.221609 | H52: 55.047731 | I52: 58.001578 | J52: Eps | K52: 59.027236 | L52: Eps | M52: 100 | N52: 88.433346 | O52: 69.80239 | P52: Eps | Q52: 7.9388294 | R52: 11.535118 | S52: 12.119446 | T52: 14.819872 | U52: 11.052639 | X52: =Notes!U51 -> Industry | Y52: aa_INDU | Z52: 69.80239 | AA52: 4.3923551 | AB52: 84.027222 | AC52: 88.433346 | AD52: 0.00011882156 | AE52: 100 | AF52: 55.047731 | AG52: 2.2228678 | AH52: 99.910586 | AI52: 52.41503 | AJ52: Eps | AK52: Eps | AL52: 35.260304 | AM52: Eps | AN52: Eps
A53: 44 | C53: =Notes!U52 -> Mining | D53: aa_MINE | E53: 1.5260924 | F53: 1.5416612 | G53: 0.91013849 | H53: 1.9491739 | I53: 0.013124345 | J53: Eps | K53: 0.013356427 | L53: Eps | M53: Eps | N53: Eps | O53: 6.4842518 | P53: Eps | Q53: Eps | R53: 26.575175 | S53: Eps | T53: 4.7101008 | U53: 5.4455198 | X53: =Notes!U52 -> Mining | Y53: aa_MINE | Z53: 6.4842518 | AA53: 4.8762932 | AB53: 8.665666 | AC53: Eps | AD53: Eps | AE53: Eps | AF53: 1.9491739 | AG53: 0.0088241175 | AH53: 0.014043661 | AI53: 1.5416612 | AJ53: Eps | AK53: Eps | AL53: 1.5260924 | AM53: Eps | AN53: Eps
A54: 45 | C54: =Notes!U53 -> Coal and lignite | D54: a_coal | E54: 0.25682764 | F54: 0.2901481 | G54: 0.17228704 | H54: 0.44545793 | I54: 0.013124345 | J54: Eps | K54: 0.013356427 | L54: Eps | M54: Eps | N54: Eps | O54: 2.3561124 | P54: Eps | Q54: Eps | R54: 40.172388 | S54: Eps | T54: 4.4436117 | U54: 4.4436117 | X54: =Notes!U53 -> Coal and lignite | Y54: a_coal | Z54: 2.3561124 | AA54: Eps | AB54: Eps | AC54: Eps | AD54: Eps | AE54: Eps | AF54: 0.44545793 | AG54: Eps | AH54: Eps | AI54: 0.2901481 | AJ54: Eps | AK54: Eps | AL54: 0.25682764 | AM54: Eps | AN54: Eps
A55: 46 | C55: =Notes!U54 -> Crude oil | D55: a_coil | E55: Eps | F55: Eps | G55: Eps | H55: 0.14305598 | I55: Eps | J55: Eps | K55: Eps | L55: Eps | M55: Eps | N55: Eps | O55: 1.8786272 | P55: Eps | Q55: Eps | R55: 100 | S55: Eps | T55: 4.5765442 | U55: Eps | X55: =Notes!U54 -> Crude oil | Y55: a_coil | Z55: 1.8786272 | AA55: Eps | AB55: Eps | AC55: Eps | AD55: Eps | AE55: Eps | AF55: 0.14305598 | AG55: 0.12023084 | AH55: 0.014043661 | AI55: Eps | AJ55: Eps | AK55: Eps | AL55: Eps | AM55: Eps | AN55: Eps
A56: 47 | C56: =Notes!U55 -> Natural gas | D56: a_ngas | E56: 0.27689266 | F56: 0.15042788 | G56: 0.091875123 | H56: 0.14671046 | I56: Eps | J56: Eps | K56: Eps | L56: Eps | M56: Eps | N56: Eps | O56: Eps | P56: Eps | Q56: Eps | R56: Eps | S56: Eps | T56: Eps | U56: 10.005571 | X56: =Notes!U55 -> Natural gas | Y56: a_ngas | Z56: Eps | AA56: Eps | AB56: Eps | AC56: Eps | AD56: Eps | AE56: Eps | AF56: 0.14671046 | AG56: Eps | AH56: Eps | AI56: 0.15042788 | AJ56: Eps | AK56: Eps | AL56: 0.27689266 | AM56: Eps | AN56: Eps
A57: 48 | C57: =Notes!U56 -> Other mining | D57: a_omin | E57: 0.99237211 | F57: 1.1010852 | G57: 0.64597633 | H57: 1.2139496 | I57: Eps | J57: Eps | K57: Eps | L57: Eps | M57: Eps | N57: Eps | O57: 2.2495122 | P57: Eps | Q57: Eps | R57: 16.155169 | S57: Eps | T57: 5.0505715 | U57: 5.0505715 | X57: =Notes!U56 -> Other mining | Y57: a_omin | Z57: 2.2495122 | AA57: 14.055986 | AB57: 8.665666 | AC57: Eps | AD57: Eps | AE57: Eps | AF57: 1.2139496 | AG57: Eps | AH57: Eps | AI57: 1.1010852 | AJ57: Eps | AK57: Eps | AL57: 0.99237211 | AM57: Eps | AN57: Eps
A58: 49 | C58: =Notes!U57 -> Manufacturing | D58: aa_MANU | E58: 22.639906 | F58: 35.207724 | G58: 26.835502 | H58: 39.216167 | I58: 56.078325 | J58: Eps | K58: 57.069974 | L58: Eps | M58: 20.716233 | N58: 88.433346 | O58: 61.491338 | P58: Eps | Q58: 11.818826 | R58: 14.629491 | S58: 12.119446 | T58: 16.115492 | U58: 15.985517 | X58: =Notes!U57 -> Manufacturing | Y58: aa_MANU | Z58: 61.491338 | AA58: 4.4718131 | AB58: 75.361556 | AC58: 88.433346 | AD58: 0.00011882156 | AE58: 100 | AF58: 39.216167 | AG58: 3.1198008 | AH58: 99.896543 | AI58: 35.207724 | AJ58: Eps | AK58: Eps | AL58: 22.639906 | AM58: Eps | AN58: Eps
A59: 50 | C59: =Notes!U58 -> Food processing | D59: aa_FOOD | E59: 3.0534493 | F59: 5.8596306 | G59: 5.1226324 | H59: 6.7018493 | I59: 17.4226 | J59: Eps | K59: 17.730689 | L59: Eps | M59: Eps | N59: 0.29433304 | O59: 7.8145729 | P59: Eps | Q59: 0.25086436 | R59: 10.024508 | S59: 6.7247937 | T59: 6.6891796 | U59: 9.4592777 | X59: =Notes!U58 -> Food processing | Y59: aa_FOOD | Z59: 7.8145729 | AA59: 3.8607187 | AB59: 8.2684799 | AC59: 0.29433304 | AD59: Eps | AE59: Eps | AF59: 6.7018493 | AG59: 6.0352637 | AH59: 33.025497 | AI59: 5.8596306 | AJ59: Eps | AK59: Eps | AL59: 3.0534493 | AM59: Eps | AN59: Eps
A60: 51 | C60: =Notes!U59 -> Meat processing | D60: a_meat | E60: 0.62866702 | F60: 0.70691068 | G60: 1.4991464 | H60: 0.69755231 | I60: 1.4514389 | J60: Eps | K60: 1.4771051 | L60: Eps | M60: Eps | N60: Eps | O60: 0.099566892 | P60: Eps | Q60: Eps | R60: 1.1512543 | S60: Eps | T60: 10.016069 | U60: 10.016069 | X60: =Notes!U59 -> Meat processing | Y60: a_meat | Z60: 0.099566892 | AA60: Eps | AB60: Eps | AC60: Eps | AD60: Eps | AE60: Eps | AF60: 0.69755231 | AG60: Eps | AH60: Eps | AI60: 0.70691068 | AJ60: Eps | AK60: Eps | AL60: 0.62866702 | AM60: Eps | AN60: Eps
A61: 52 | C61: =Notes!U60 -> Fish and seafood processing | D61: a_fsea | E61: 0.26916542 | F61: 0.31055158 | G61: 0.36162367 | H61: 0.29021938 | I61: 0.64941486 | J61: Eps | K61: 0.66089865 | L61: Eps | M61: Eps | N61: 0.096800017 | O61: 0.073775733 | P61: Eps | Q61: 1.583652 | R61: 2.5888127 | S61: 5.1113885 | T61: 5.1113885 | U61: 5.1113885 | X61: =Notes!U60 -> Fish and seafood processing | Y61: a_fsea | Z61: 0.073775733 | AA61: 33.146433 | AB61: 0.67019719 | AC61: 0.096800017 | AD61: Eps | AE61: Eps | AF61: 0.29021938 | AG61: Eps | AH61: Eps | AI61: 0.31055158 | AJ61: Eps | AK61: Eps | AL61: 0.26916542 | AM61: Eps | AN61: Eps
A62: 53 | C62: =Notes!U61 -> Dairy | D62: a_dair | E62: 0.093111444 | F62: 0.12760947 | G62: 0.069648109 | H62: 0.20657419 | I62: 0.60199608 | J62: Eps | K62: 0.61264134 | L62: Eps | M62: Eps | N62: Eps | O62: 0.49489297 | P62: Eps | Q62: Eps | R62: 24.281694 | S62: Eps | T62: 7.0912546 | U62: 7.0912546 | X62: =Notes!U61 -> Dairy | Y62: a_dair | Z62: 0.49489297 | AA62: Eps | AB62: Eps | AC62: Eps | AD62: Eps | AE62: Eps | AF62: 0.20657419 | AG62: 22.927806 | AH62: 3.8672033 | AI62: 0.12760947 | AJ62: Eps | AK62: Eps | AL62: 0.093111444 | AM62: Eps | AN62: Eps
A63: 54 | C63: =Notes!U62 -> Fruit and vegetable processing | D63: a_fveg | E63: 0.06208285 | F63: 0.093836071 | G63: 0.14518883 | H63: 0.10812968 | I63: 0.280978 | J63: Eps | K63: 0.28594661 | L63: Eps | M63: Eps | N63: Eps | O63: 0.28742832 | P63: Eps | Q63: Eps | R63: 20.209688 | S63: Eps | T63: 4.5396342 | U63: 4.5396342 | X63: =Notes!U62 -> Fruit and vegetable processing | Y63: a_fveg | Z63: 0.28742832 | AA63: Eps | AB63: Eps | AC63: Eps | AD63: Eps | AE63: Eps | AF63: 0.10812968 | AG63: Eps | AH63: Eps | AI63: 0.093836071 | AJ63: Eps | AK63: Eps | AL63: 0.06208285 | AM63: Eps | AN63: Eps
A64: 55 | C64: =Notes!U63 -> Fats and oils | D64: a_foil | E64: 0.048781573 | F64: 0.056115384 | G64: 0.057593376 | H64: 0.31634386 | I64: 0.46477617 | J64: Eps | K64: 0.47299493 | L64: Eps | M64: Eps | N64: Eps | O64: 1.5910611 | P64: Eps | Q64: Eps | R64: 72.302619 | S64: Eps | T64: 5.7127234 | U64: 5.7127234 | X64: =Notes!U63 -> Fats and oils | Y64: a_foil | Z64: 1.5910611 | AA64: 11.34243 | AB64: 4.9458988 | AC64: Eps | AD64: Eps | AE64: Eps | AF64: 0.31634386 | AG64: 40.381769 | AH64: 10.430454 | AI64: 0.056115384 | AJ64: Eps | AK64: Eps | AL64: 0.048781573 | AM64: Eps | AN64: Eps
A65: 56 | C65: =Notes!U64 -> Maize milling | D65: a_mmll | E65: 0.02423157 | F65: 0.044722674 | G65: 0.035723633 | H65: 0.044650412 | I65: 0.086015356 | J65: Eps | K65: 0.087536389 | L65: Eps | M65: Eps | N65: Eps | O65: 0.0082596364 | P65: Eps | Q65: Eps | R65: 1.504183 | S65: Eps | T65: 10.744937 | U65: 10.744937 | X65: =Notes!U64 -> Maize milling | Y65: a_mmll | Z65: 0.0082596364 | AA65: Eps | AB65: Eps | AC65: Eps | AD65: Eps | AE65: Eps | AF65: 0.044650412 | AG65: Eps | AH65: Eps | AI65: 0.044722674 | AJ65: Eps | AK65: Eps | AL65: 0.02423157 | AM65: Eps | AN65: Eps
A66: 57 | C66: =Notes!U65 -> Sorghum and millet milling | D66: a_smll | E66: Eps | F66: Eps | G66: Eps | H66: Eps | I66: Eps | J66: Eps | K66: Eps | L66: Eps | M66: Eps | N66: Eps | O66: Eps | P66: Eps | Q66: Eps | R66: Eps | S66: Eps | T66: Eps | U66: Eps | X66: =Notes!U65 -> Sorghum and millet milling | Y66: a_smll | Z66: Eps | AA66: Eps | AB66: Eps | AC66: Eps | AD66: Eps | AE66: Eps | AF66: Eps | AG66: Eps | AH66: Eps | AI66: Eps | AJ66: Eps | AK66: Eps | AL66: Eps | AM66: Eps | AN66: Eps
A67: 58 | C67: =Notes!U66 -> Rice milling | D67: a_rmll | E67: Eps | F67: Eps | G67: Eps | H67: Eps | I67: Eps | J67: Eps | K67: Eps | L67: Eps | M67: Eps | N67: Eps | O67: Eps | P67: Eps | Q67: Eps | R67: Eps | S67: Eps | T67: Eps | U67: Eps | X67: =Notes!U66 -> Rice milling | Y67: a_rmll | Z67: Eps | AA67: Eps | AB67: Eps | AC67: Eps | AD67: Eps | AE67: Eps | AF67: Eps | AG67: Eps | AH67: Eps | AI67: Eps | AJ67: Eps | AK67: Eps | AL67: Eps | AM67: Eps | AN67: Eps
A68: 59 | C68: =Notes!U67 -> Rice milling - coarse | D68: a_rmlc | E68: 0.21543312 | F68: 1.0631823 | G68: 0.29357987 | H68: 1.0316097 | I68: 3.3837172 | J68: Eps | K68: 3.4435524 | L68: Eps | M68: Eps | N68: Eps | O68: Eps | P68: Eps | Q68: Eps | R68: Eps | S68: Eps | T68: Eps | U68: 9.5433097 | X68: =Notes!U67 -> Rice milling - coarse | Y68: a_rmlc | Z68: Eps | AA68: Eps | AB68: Eps | AC68: Eps | AD68: Eps | AE68: Eps | AF68: 1.0316097 | AG68: Eps | AH68: Eps | AI68: 1.0631823 | AJ68: Eps | AK68: Eps | AL68: 0.21543312 | AM68: Eps | AN68: Eps
A69: 60 | C69: =Notes!U68 -> Rice milling - other | D69: a_rmlo | E69: 0.44943005 | F69: 1.6774556 | G69: 0.6123214 | H69: 1.679453 | I69: 5.4881764 | J69: Eps | K69: 5.5852253 | L69: Eps | M69: Eps | N69: Eps | O69: Eps | P69: Eps | Q69: Eps | R69: Eps | S69: Eps | T69: Eps | U69: 12.333932 | X69: =Notes!U68 -> Rice milling - other | Y69: a_rmlo | Z69: Eps | AA69: Eps | AB69: Eps | AC69: Eps | AD69: Eps | AE69: Eps | AF69: 1.679453 | AG69: Eps | AH69: Eps | AI69: 1.6774556 | AJ69: Eps | AK69: Eps | AL69: 0.44943005 | AM69: Eps | AN69: Eps
A70: 61 | C70: =Notes!U69 -> Wheat and barley milling | D70: a_wmll | E70: 0.035891905 | F70: 0.20519104 | G70: 0.052898345 | H70: 0.20423178 | I70: 0.66857041 | J70: Eps | K70: 0.68039293 | L70: Eps | M70: Eps | N70: Eps | O70: Eps | P70: Eps | Q70: Eps | R70: Eps | S70: Eps | T70: Eps | U70: 11.817292 | X70: =Notes!U69 -> Wheat and barley milling | Y70: a_wmll | Z70: Eps | AA70: Eps | AB70: Eps | AC70: Eps | AD70: Eps | AE70: Eps | AF70: 0.20423178 | AG70: Eps | AH70: Eps | AI70: 0.20519104 | AJ70: Eps | AK70: Eps | AL70: 0.035891905 | AM70: Eps | AN70: Eps
A71: 62 | C71: =Notes!U70 -> Other grain milling | D71: a_gmll | E71: 0.016337219 | F71: 0.090725755 | G71: 0.024074391 | H71: 0.089390612 | I71: 0.098126477 | J71: Eps | K71: 0.099861674 | L71: Eps | M71: Eps | N71: Eps | O71: Eps | P71: Eps | Q71: Eps | R71: Eps | S71: Eps | T71: Eps | U71: 10.918598 | X71: =Notes!U70 -> Other grain milling | Y71: a_gmll | Z71: Eps | AA71: Eps | AB71: Eps | AC71: Eps | AD71: Eps | AE71: Eps | AF71: 0.089390612 | AG71: Eps | AH71: Eps | AI71: 0.090725755 | AJ71: Eps | AK71: Eps | AL71: 0.016337219 | AM71: Eps | AN71: Eps
A72: 63 | C72: =Notes!U71 -> Sugar refining | D72: a_sref | E72: 0.10713988 | F72: 0.16003964 | G72: 0.24807955 | H72: 0.6388042 | I72: 1.5367258 | J72: Eps | K72: 1.5639002 | L72: Eps | M72: Eps | N72: Eps | O72: 3.8387756 | P72: Eps | Q72: Eps | R72: 66.990363 | S72: Eps | T72: 7.5342357 | U72: 7.5342357 | X72: =Notes!U71 -> Sugar refining | Y72: a_sref | Z72: 3.8387756 | AA72: 2.3191009 | AB72: 2.4398584 | AC72: Eps | AD72: Eps | AE72: Eps | AF72: 0.6388042 | AG72: 27.957885 | AH72: 14.582451 | AI72: 0.16003964 | AJ72: Eps | AK72: Eps | AL72: 0.10713988 | AM72: Eps | AN72: Eps
A73: 64 | C73: =Notes!U72 -> Coffee processing | D73: a_pcof | E73: Eps | F73: Eps | G73: Eps | H73: Eps | I73: Eps | J73: Eps | K73: Eps | L73: Eps | M73: Eps | N73: Eps | O73: Eps | P73: Eps | Q73: Eps | R73: Eps | S73: Eps | T73: Eps | U73: Eps | X73: =Notes!U72 -> Coffee processing | Y73: a_pcof | Z73: Eps | AA73: Eps | AB73: Eps | AC73: Eps | AD73: Eps | AE73: Eps | AF73: Eps | AG73: Eps | AH73: Eps | AI73: Eps | AJ73: Eps | AK73: Eps | AL73: Eps | AM73: Eps | AN73: Eps
A74: 65 | C74: =Notes!U73 -> Tea processing | D74: a_ptea | E74: Eps | F74: Eps | G74: Eps | H74: Eps | I74: Eps | J74: Eps | K74: Eps | L74: Eps | M74: Eps | N74: Eps | O74: Eps | P74: Eps | Q74: Eps | R74: Eps | S74: Eps | T74: Eps | U74: Eps | X74: =Notes!U73 -> Tea processing | Y74: a_ptea | Z74: Eps | AA74: Eps | AB74: Eps | AC74: Eps | AD74: Eps | AE74: Eps | AF74: Eps | AG74: Eps | AH74: Eps | AI74: Eps | AJ74: Eps | AK74: Eps | AL74: Eps | AM74: Eps | AN74: Eps
A75: 66 | C75: =Notes!U74 -> Other foods | D75: a_food | E75: 0.73680164 | F75: 0.87074636 | G75: 0.86639863 | H75: 0.90301943 | I75: 2.7126642 | J75: Eps | K75: 2.760633 | L75: Eps | M75: Eps | N75: 0.19753302 | O75: 0.44041271 | P75: Eps | Q75: 1.123366 | R75: 4.1266937 | S75: 7.5154344 | T75: 7.5154344 | U75: 7.5154344 | X75: =Notes!U74 -> Other foods | Y75: a_food | Z75: 0.44041271 | AA75: 1.760755 | AB75: 0.21252549 | AC75: 0.19753302 | AD75: Eps | AE75: Eps | AF75: 0.90301943 | AG75: 5.622245 | AH75: 4.1453892 | AI75: 0.87074636 | AJ75: Eps | AK75: Eps | AL75: 0.73680164 | AM75: Eps | AN75: Eps
A76: 67 | C76: =Notes!U75 -> Animal feed | D76: a_feed | E76: 0.3663756 | F76: 0.45254405 | G76: 0.85635615 | H76: 0.49187072 | I76: Eps | J76: Eps | K76: Eps | L76: Eps | M76: Eps | N76: Eps | O76: 0.98039994 | P76: Eps | Q76: Eps | R76: 15.192415 | S76: Eps | T76: 4.7810135 | U76: 4.7810135 | X76: =Notes!U75 -> Animal feed | Y76: a_feed | Z76: 0.98039994 | AA76: Eps | AB76: Eps | AC76: Eps | AD76: Eps | AE76: Eps | AF76: 0.49187072 | AG76: Eps | AH76: Eps | AI76: 0.45254405 | AJ76: Eps | AK76: Eps | AL76: 0.3663756 | AM76: Eps | AN76: Eps
A77: 68 | C77: =Notes!U76 -> Beverages and tobacco | D77: aa_BEVE | E77: 0.46022999 | F77: 1.061821 | G77: 0.35806847 | H77: 1.1460517 | I77: 3.3972409 | J77: Eps | K77: 3.4573153 | L77: Eps | M77: Eps | N77: 0.29742042 | O77: 0.10189903 | P77: Eps | Q77: 1.3902932 | R77: 0.69611494 | S77: 7.2993096 | T77: 7.2993096 | U77: 19.248814 | X77: =Notes!U76 -> Beverages and tobacco | Y77: aa_BEVE | Z77: 0.10189903 | AA77: Eps | AB77: Eps | AC77: 0.29742042 | AD77: Eps | AE77: Eps | AF77: 1.1460517 | AG77: Eps | AH77: Eps | AI77: 1.061821 | AJ77: Eps | AK77: Eps | AL77: 0.46022999 | AM77: Eps | AN77: Eps
A78: 69 | C78: =Notes!U77 -> Beverages | D78: a_beve | E78: 0.34709197 | F78: 0.43987343 | G78: 0.27898422 | H78: 0.41047956 | I78: 1.2171241 | J78: Eps | K78: 1.2386468 | L78: Eps | M78: Eps | N78: 0.29742042 | O78: 0.10189903 | P78: Eps | Q78: 3.3560621 | R78: 1.9435406 | S78: 7.2993096 | T78: 7.2993096 | U78: 7.2993096 | X78: =Notes!U77 -> Beverages | Y78: a_beve | Z78: 0.10189903 | AA78: Eps | AB78: Eps | AC78: 0.29742042 | AD78: Eps | AE78: Eps | AF78: 0.41047956 | AG78: Eps | AH78: Eps | AI78: 0.43987343 | AJ78: Eps | AK78: Eps | AL78: 0.34709197 | AM78: Eps | AN78: Eps
A79: 70 | C79: =Notes!U78 -> Tobacco processing | D79: a_ptob | E79: 0.11313802 | F79: 0.62194758 | G79: 0.079084246 | H79: 0.73557211 | I79: 2.1801169 | J79: Eps | K79: 2.2186685 | L79: Eps | M79: Eps | N79: Eps | O79: Eps | P79: Eps | Q79: Eps | R79: Eps | S79: Eps | T79: Eps | U79: 25.787529 | X79: =Notes!U78 -> Tobacco processing | Y79: a_ptob | Z79: Eps | AA79: Eps | AB79: Eps | AC79: Eps | AD79: Eps | AE79: Eps | AF79: 0.73557211 | AG79: Eps | AH79: Eps | AI79: 0.62194758 | AJ79: Eps | AK79: Eps | AL79: 0.11313802 | AM79: Eps | AN79: Eps
A80: 71 | C80: =Notes!U79 -> Textiles, clothing and leather | D80: aa_TEXT | E80: 8.3175035 | F80: 10.021369 | G80: 14.079552 | H80: 7.798457 | I80: 11.631567 | J80: Eps | K80: 11.837252 | L80: Eps | M80: Eps | N80: 71.024907 | O80: 16.491268 | P80: Eps | Q80: 34.584425 | R80: 17.301245 | S80: 8.8632353 | T80: 10.064766 | U80: 10.198708 | X80: =Notes!U79 -> Textiles, clothing and leather | Y80: aa_TEXT | Z80: 16.491268 | AA80: 0.72333817 | AB80: 3.2692467 | AC80: 71.024907 | AD80: 0.00014794512 | AE80: 100 | AF80: 7.798457 | AG80: 0.65035048 | AH80: 4.1410894 | AI80: 10.021369 | AJ80: Eps | AK80: Eps | AL80: 8.3175035 | AM80: Eps | AN80: Eps
A81: 72 | C81: =Notes!U80 -> Jute baling | D81: a_bale | E81: 0.074761094 | F81: 0.084279372 | G81: 0.11082036 | H81: 0.0036546495 | I81: Eps | J81: Eps | K81: Eps | L81: Eps | M81: Eps | N81: 1.5593012 | O81: Eps | P81: Eps | Q81: 95.249638 | R81: Eps | S81: 3.8497035 | T81: Eps | U81: 3.8497035 | X81: =Notes!U80 -> Jute baling | Y81: a_bale | Z81: Eps | AA81: Eps | AB81: Eps | AC81: 1.5593012 | AD81: Eps | AE81: Eps | AF81: 0.0036546495 | AG81: Eps | AH81: Eps | AI81: 0.084279372 | AJ81: Eps | AK81: Eps | AL81: 0.074761094 | AM81: Eps | AN81: Eps
A82: 73 | C82: =Notes!U81 -> Jute fabrication | D82: a_pjut | E82: 0.049706312 | F82: 0.08133419 | G82: 0.12302626 | H82: 0.074173903 | I82: 0.24120266 | J82: Eps | K82: 0.24546791 | L82: Eps | M82: Eps | N82: Eps | O82: Eps | P82: Eps | Q82: Eps | R82: Eps | S82: Eps | T82: Eps | U82: 3.7567284 | X82: =Notes!U81 -> Jute fabrication | Y82: a_pjut | Z82: Eps | AA82: Eps | AB82: Eps | AC82: Eps | AD82: Eps | AE82: Eps | AF82: 0.074173903 | AG82: Eps | AH82: Eps | AI82: 0.08133419 | AJ82: Eps | AK82: Eps | AL82: 0.049706312 | AM82: Eps | AN82: Eps
A83: 74 | C83: =Notes!U82 -> Cotton yarn | D83: a_yarn | E83: 0.12218708 | F83: 0.14817036 | G83: 0.23712582 | H83: 0.57461888 | I83: 0.0097854548 | J83: Eps | K83: 0.0099584937 | L83: Eps | M83: Eps | N83: Eps | O83: 5.1185766 | P83: Eps | Q83: Eps | R83: 74.235597 | S83: Eps | T83: 12.156482 | U83: 12.156482 | X83: =Notes!U82 -> Cotton yarn | Y83: a_yarn | Z83: 5.1185766 | AA83: 0.86826162 | AB83: 1.2180134 | AC83: Eps | AD83: Eps | AE83: Eps | AF83: 0.57461888 | AG83: Eps | AH83: Eps | AI83: 0.14817036 | AJ83: Eps | AK83: Eps | AL83: 0.12218708 | AM83: Eps | AN83: Eps
A84: 75 | C84: =Notes!U83 -> Textiles | D84: a_text | E84: 1.0233707 | F84: 1.2484265 | G84: 1.8163099 | H84: 2.0710488 | I84: 2.9995357 | J84: Eps | K84: 3.0525773 | L84: Eps | M84: Eps | N84: 1.730149 | O84: 11.372691 | P84: Eps | Q84: 6.7459594 | R84: 44.845112 | S84: 9.08842 | T84: 9.08842 | U84: 9.08842 | X84: =Notes!U83 -> Textiles | Y84: a_text | Z84: 11.372691 | AA84: 0.65811158 | AB84: 2.0512333 | AC84: 1.730149 | AD84: Eps | AE84: Eps | AF84: 2.0710488 | AG84: 1.6021868 | AH84: 2.7093303 | AI84: 1.2484265 | AJ84: Eps | AK84: Eps | AL84: 1.0233707 | AM84: Eps | AN84: Eps
A85: 76 | C85: =Notes!U84 -> Clothing | D85: a_clth | E85: 6.1543027 | F85: 6.9899388 | G85: 10.547959 | H85: 3.68775 | I85: 7.7368339 | J85: Eps | K85: 7.8736465 | L85: Eps | M85: Eps | N85: 64.888063 | O85: Eps | P85: Eps | Q85: 45.380695 | R85: Eps | S85: 8.698812 | T85: Eps | U85: 8.698812 | X85: =Notes!U84 -> Clothing | Y85: a_clth | Z85: Eps | AA85: Eps | AB85: Eps | AC85: 64.888063 | AD85: 0.00016193716 | AE85: 100 | AF85: 3.68775 | AG85: 0.47549946 | AH85: 1.4317591 | AI85: 6.9899388 | AJ85: Eps | AK85: Eps | AL85: 6.1543027 | AM85: Eps | AN85: Eps
A86: 77 | C86: =Notes!U85 -> Leather and footwear | D86: a_leat | E86: 0.89317564 | F86: 1.4692198 | G86: 1.2443108 | H86: 1.3872108 | I86: 0.64420962 | J86: Eps | K86: 0.65560136 | L86: Eps | M86: Eps | N86: 2.8473931 | O86: Eps | P86: Eps | Q86: 8.7975882 | R86: Eps | S86: 15.218906 | T86: Eps | U86: 15.218906 | X86: =Notes!U85 -> Leather and footwear | Y86: a_leat | Z86: Eps | AA86: Eps | AB86: Eps | AC86: 2.8473931 | AD86: Eps | AE86: Eps | AF86: 1.3872108 | AG86: Eps | AH86: Eps | AI86: 1.4692198 | AJ86: Eps | AK86: Eps | AL86: 0.89317564 | AM86: Eps | AN86: Eps
A87: 78 | C87: =Notes!U86 -> Wood and paper products | D87: aa_WOOD | E87: 0.64116577 | F87: 1.4123104 | G87: 0.76339971 | H87: 1.58511 | I87: 0.74675796 | J87: Eps | K87: 0.75996308 | L87: Eps | M87: Eps | N87: Eps | O87: 1.2619011 | P87: Eps | Q87: Eps | R87: 9.3997494 | S87: Eps | T87: 32.525962 | U87: 13.176449 | X87: =Notes!U86 -> Wood and paper products | Y87: aa_WOOD | Z87: 1.2619011 | AA87: 9.1292479 | AB87: 3.1572763 | AC87: Eps | AD87: Eps | AE87: Eps | AF87: 1.58511 | AG87: 0.58493998 | AH87: 0.75705801 | AI87: 1.4123104 | AJ87: Eps | AK87: Eps | AL87: 0.64116577 | AM87: Eps | AN87: Eps
A88: 79 | C88: =Notes!U87 -> Wood products | D88: a_wood | E88: 0.42748719 | F88: 1.1561183 | G88: 0.45911436 | H88: 1.0944577 | I88: 0.24137113 | J88: Eps | K88: 0.24563937 | L88: Eps | M88: Eps | N88: Eps | O88: Eps | P88: Eps | Q88: Eps | R88: Eps | S88: Eps | T88: Eps | U88: 7.2846427 | X88: =Notes!U87 -> Wood products | Y88: a_wood | Z88: Eps | AA88: Eps | AB88: Eps | AC88: Eps | AD88: Eps | AE88: Eps | AF88: 1.0944577 | AG88: Eps | AH88: Eps | AI88: 1.1561183 | AJ88: Eps | AK88: Eps | AL88: 0.42748719 | AM88: Eps | AN88: Eps
A89: 80 | C89: =Notes!U88 -> Paper products and publishing | D89: a_papr | E89: 0.21367859 | F89: 0.25619208 | G89: 0.30428535 | H89: 0.49065229 | I89: 0.50538682 | J89: Eps | K89: 0.51432372 | L89: Eps | M89: Eps | N89: Eps | O89: 1.2619011 | P89: Eps | Q89: Eps | R89: 30.77085 | S89: Eps | T89: 32.525962 | U89: 32.525962 | X89: =Notes!U88 -> Paper products and publishing | Y89: a_papr | Z89: 1.2619011 | AA89: 9.1292479 | AB89: 3.1572763 | AC89: Eps | AD89: Eps | AE89: Eps | AF89: 0.49065229 | AG89: 1.8897174 | AH89: 0.75705801 | AI89: 0.25619208 | AJ89: Eps | AK89: Eps | AL89: 0.21367859 | AM89: Eps | AN89: Eps
A90: 81 | C90: =Notes!U89 -> Chemical products | D90: aa_CHEM | E90: 0.71318134 | F90: 1.5881019 | G90: 0.41690779 | H90: 4.4331036 | I90: 3.0264647 | J90: Eps | K90: 3.0799825 | L90: Eps | M90: Eps | N90: Eps | O90: 16.932777 | P90: Eps | Q90: Eps | R90: 45.774206 | S90: Eps | T90: 21.665682 | U90: 30.036791 | X90: =Notes!U89 -> Chemical products | Y90: aa_CHEM | Z90: 16.932777 | AA90: 7.2007195 | AB90: 33.416146 | AC90: Eps | AD90: Eps | AE90: Eps | AF90: 4.4331036 | AG90: 17.12125 | AH90: 61.972898 | AI90: 1.5881019 | AJ90: Eps | AK90: Eps | AL90: 0.71318134 | AM90: Eps | AN90: Eps
A91: 82 | C91: =Notes!U90 -> Petroleum products | D91: a_petr | E91: 0.07971033 | F91: 0.16955023 | G91: 0.020052833 | H91: 1.5470675 | I91: 1.7380985 | J91: Eps | K91: 1.7688338 | L91: Eps | M91: Eps | N91: Eps | O91: 7.5921581 | P91: Eps | Q91: Eps | R91: 79.761292 | S91: Eps | T91: 6.6956153 | U91: 6.6956153 | X91: =Notes!U90 -> Petroleum products | Y91: a_petr | Z91: 7.5921581 | AA91: 6.437054 | AB91: 13.393826 | AC91: Eps | AD91: Eps | AE91: Eps | AF91: 1.5470675 | AG91: 49.060738 | AH91: 61.972898 | AI91: 0.16955023 | AJ91: Eps | AK91: Eps | AL91: 0.07971033 | AM91: Eps | AN91: Eps
A92: 83 | C92: =Notes!U91 -> Fertilizers and herbicides | D92: a_fert | E92: 0.13922578 | F92: 0.1090868 | G92: 0.079533325 | H92: 0.30603848 | I92: Eps | J92: Eps | K92: Eps | L92: Eps | M92: Eps | N92: Eps | O92: 2.061786 | P92: Eps | Q92: Eps | R92: 60.981147 | S92: Eps | T92: 19.819267 | U92: 19.819267 | X92: =Notes!U91 -> Fertilizers and herbicides | Y92: a_fert | Z92: 2.061786 | AA92: Eps | AB92: Eps | AC92: Eps | AD92: Eps | AE92: Eps | AF92: 0.30603848 | AG92: Eps | AH92: Eps | AI92: 0.1090868 | AJ92: Eps | AK92: Eps | AL92: 0.13922578 | AM92: Eps | AN92: Eps
A93: 84 | C93: =Notes!U92 -> Other chemicals | D93: a_chem | E93: 0.49424523 | F93: 1.3094648 | G93: 0.31732163 | H93: 2.5799976 | I93: 1.2883662 | J93: Eps | K93: 1.3111487 | L93: Eps | M93: Eps | N93: Eps | O93: 7.2788333 | P93: Eps | Q93: Eps | R93: 33.588949 | S93: Eps | T93: 32.921624 | U93: 32.921624 | X93: =Notes!U92 -> Other chemicals | Y93: a_chem | Z93: 7.2788333 | AA93: 10.036917 | AB93: 20.022319 | AC93: Eps | AD93: Eps | AE93: Eps | AF93: 2.5799976 | AG93: Eps | AH93: Eps | AI93: 1.3094648 | AJ93: Eps | AK93: Eps | AL93: 0.49424523 | AM93: Eps | AN93: Eps
A94: 85 | C94: =Notes!U93 -> Non-metal minerals | D94: a_nmet | E94: 2.9460631 | F94: 4.8319184 | G94: 1.4761712 | H94: 5.3824024 | I94: 9.0997657 | J94: Eps | K94: 9.2606794 | L94: Eps | M94: Eps | N94: 12.370367 | O94: Eps | P94: Eps | Q94: 9.7480016 | R94: Eps | S94: 28.887063 | T94: Eps | U94: 28.887063 | X94: =Notes!U93 -> Non-metal minerals | Y94: a_nmet | Z94: Eps | AA94: Eps | AB94: Eps | AC94: 12.370367 | AD94: Eps | AE94: Eps | AF94: 5.3824024 | AG94: Eps | AH94: Eps | AI94: 4.8319184 | AJ94: Eps | AK94: Eps | AL94: 2.9460631 | AM94: Eps | AN94: Eps
A95: 86 | C95: =Notes!U94 -> Metals and metal products | D95: a_metl | E95: 1.6338633 | F95: 4.2705131 | G95: 2.8405277 | H95: 4.4874375 | I95: 1.4199162 | J95: Eps | K95: 1.4450249 | L95: Eps | M95: Eps | N95: 3.6918046 | O95: Eps | P95: Eps | Q95: 3.7223575 | R95: Eps | S95: 19.581596 | T95: Eps | U95: 19.581596 | X95: =Notes!U94 -> Metals and metal products | Y95: a_metl | Z95: Eps | AA95: Eps | AB95: Eps | AC95: 3.6918046 | AD95: Eps | AE95: Eps | AF95: 4.4874375 | AG95: Eps | AH95: Eps | AI95: 4.2705131 | AJ95: Eps | AK95: Eps | AL95: 1.6338633 | AM95: Eps | AN95: Eps
A96: 87 | C96: =Notes!U95 -> Machinery and equipment | D96: aa_MACH | E96: 2.2978281 | F96: 3.1265538 | G96: 0.73892573 | H96: 4.5873523 | I96: 1.9966626 | J96: Eps | K96: 2.0319701 | L96: Eps | M96: 20.716233 | N96: Eps | O96: 17.409899 | P96: Eps | Q96: Eps | R96: 35.307937 | S96: Eps | T96: 17.965838 | U96: 7.5299341 | X96: =Notes!U95 -> Machinery and equipment | Y96: aa_MACH | Z96: 17.409899 | AA96: 5.1561945 | AB96: 24.602419 | AC96: Eps | AD96: Eps | AE96: Eps | AF96: 4.5873523 | AG96: Eps | AH96: Eps | AI96: 3.1265538 | AJ96: Eps | AK96: Eps | AL96: 2.2978281 | AM96: Eps | AN96: Eps
A97: 88 | C97: =Notes!U96 -> Machinery and other equipment | D97: a_mach | E97: 0.052246768 | F97: 0.12253503 | G97: 0.015514601 | H97: 1.0606516 | I97: 0.013599048 | J97: Eps | K97: 0.013839524 | L97: Eps | M97: 3.0709145 | N97: Eps | O97: 9.2688173 | P97: Eps | Q97: Eps | R97: 86.854134 | S97: Eps | T97: 22.865852 | U97: 22.865852 | X97: =Notes!U96 -> Machinery and other equipment | Y97: a_mach | Z97: 9.2688173 | AA97: 5.6300632 | AB97: 14.301772 | AC97: Eps | AD97: Eps | AE97: Eps | AF97: 1.0606516 | AG97: Eps | AH97: Eps | AI97: 0.12253503 | AJ97: Eps | AK97: Eps | AL97: 0.052246768 | AM97: Eps | AN97: Eps
A98: 89 | C98: =Notes!U97 -> Electrical equipment | D98: a_equi | E98: 0.11009567 | F98: 0.19367734 | G98: 0.046914713 | H98: 0.66064468 | I98: 0.78308376 | J98: Eps | K98: 0.79693125 | L98: Eps | M98: Eps | N98: Eps | O98: 5.4677448 | P98: Eps | Q98: Eps | R98: 70.009783 | S98: Eps | T98: 14.201512 | U98: 14.201512 | X98: =Notes!U97 -> Electrical equipment | Y98: a_equi | Z98: 5.4677448 | AA98: Eps | AB98: Eps | AC98: Eps | AD98: Eps | AE98: Eps | AF98: 0.66064468 | AG98: Eps | AH98: Eps | AI98: 0.19367734 | AJ98: Eps | AK98: Eps | AL98: 0.11009567 | AM98: Eps | AN98: Eps
A99: 90 | C99: =Notes!U98 -> Vehicles and transport equipment | D99: a_vehi | E99: 2.1354857 | F99: 2.8103414 | G99: 0.67649642 | H99: 2.866056 | I99: 1.1999798 | J99: Eps | K99: 1.2211993 | L99: Eps | M99: 17.645319 | N99: Eps | O99: 2.6733367 | P99: Eps | Q99: Eps | R99: 8.2330483 | S99: Eps | T99: 6.2143351 | U99: 6.2143351 | X99: =Notes!U98 -> Vehicles and transport equipment | Y99: a_vehi | Z99: 2.6733367 | AA99: 14.059134 | AB99: 10.300647 | AC99: Eps | AD99: Eps | AE99: Eps | AF99: 2.866056 | AG99: Eps | AH99: Eps | AI99: 2.8103414 | AJ99: Eps | AK99: Eps | AL99: 2.1354857 | AM99: Eps | AN99: Eps
A100: 91 | C100: =Notes!U99 -> Other manufacturing | D100: a_oman | E100: 2.5766217 | F100: 3.0355062 | G100: 1.0393169 | H100: 3.0944029 | I100: 7.3373501 | J100: Eps | K100: 7.4670985 | L100: Eps | M100: Eps | N100: 0.75451456 | O100: 1.4790209 | P100: Eps | Q100: 1.1815348 | R100: 4.1626724 | S100: 11.221861 | T100: 11.221861 | U100: 11.221861 | X100: =Notes!U99 -> Other manufacturing | Y100: a_oman | Z100: 1.4790209 | AA100: 6.5326519 | AB100: 2.6479886 | AC100: 0.75451456 | AD100: Eps | AE100: Eps | AF100: 3.0944029 | AG100: Eps | AH100: Eps | AI100: 3.0355062 | AJ100: Eps | AK100: Eps | AL100: 2.5766217 | AM100: Eps | AN100: Eps
A101: 92 | C101: =Notes!U100 -> Utilities | D101: aa_UTIL | E101: 1.3307618 | F101: 2.739482 | G101: 0.50721563 | H101: 2.5370393 | I101: 1.9101283 | J101: Eps | K101: 1.9439057 | L101: Eps | M101: Eps | N101: Eps | O101: 1.8268 | P101: Eps | Q101: Eps | R101: 5.2259096 | S101: Eps | T101: Eps | U101: Eps | X101: =Notes!U100 -> Utilities | Y101: aa_UTIL | Z101: 1.8268 | AA101: Eps | AB101: Eps | AC101: Eps | AD101: Eps | AE101: Eps | AF101: 2.5370393 | AG101: Eps | AH101: Eps | AI101: 2.739482 | AJ101: Eps | AK101: Eps | AL101: 1.3307618 | AM101: Eps | AN101: Eps
A102: 93 | C102: =Notes!U101 -> Electricity, gas and steam | D102: a_elec | E102: 1.2408248 | F102: 2.5780328 | G102: 0.46184924 | H102: 2.3953345 | I102: 1.6306883 | J102: Eps | K102: 1.6595242 | L102: Eps | M102: Eps | N102: Eps | O102: 1.8268 | P102: Eps | Q102: Eps | R102: 5.5350673 | S102: Eps | T102: Eps | U102: Eps | X102: =Notes!U101 -> Electricity, gas and steam | Y102: a_elec | Z102: 1.8268 | AA102: Eps | AB102: Eps | AC102: Eps | AD102: Eps | AE102: Eps | AF102: 2.3953345 | AG102: Eps | AH102: Eps | AI102: 2.5780328 | AJ102: Eps | AK102: Eps | AL102: 1.2408248 | AM102: Eps | AN102: Eps
...

Sheet Macro
A1: Macroeconomic Results | N1: Tables: | O1: =C5 -> Quantities, price indices, and GDP shares
C5: Quantities, price indices, and GDP shares
C6: Init = Base year value or share of total GDP | Base = Average annual growth rate (%) | Sims = Deviation in average annual growth rate from baseline (%-point)
F7: init | G7: base | H7: sim1 | I7: sim2 | J7: sim3 | K7: sim4 | L7: sim5 | M7: sim6 | N7: sim7 | O7: sim8 | P7: sim9 | Q7: sim10 | R7: sim11 | S7: sim12 | T7: sim13 | U7: sim14 | V7: sim15
A8: 1 | C8: Quantities | D8: Absorption | E8: QABSTOT | F8: 52862.932 | G8: 3.0684079 | H8: Eps | I8: Eps | J8: Eps | K8: Eps | L8: Eps | M8: Eps | N8: Eps | O8: Eps | P8: Eps | Q8: Eps | R8: Eps | S8: Eps | T8: Eps | U8: Eps | V8: Eps
A9: 2 | D9: Private consumption | E9: QHTOT | F9: 33987.205 | G9: 3.0405704 | H9: Eps | I9: Eps | J9: Eps | K9: Eps | L9: Eps | M9: Eps | N9: Eps | O9: Eps | P9: Eps | Q9: Eps | R9: Eps | S9: Eps | T9: Eps | U9: Eps | V9: Eps
A10: 3 | D10: Government consumption | E10: QGTOT | F10: 3146.0385 | G10: 3.5 | H10: Eps | I10: Eps | J10: Eps | K10: Eps | L10: Eps | M10: Eps | N10: Eps | O10: Eps | P10: Eps | Q10: Eps | R10: Eps | S10: Eps | T10: Eps | U10: Eps | V10: Eps
A11: 4 | D11: Gross capital formation | E11: QINVTOT | F11: 15729.688 | G11: 3.0410731 | H11: Eps | I11: Eps | J11: Eps | K11: Eps | L11: Eps | M11: Eps | N11: Eps | O11: Eps | P11: Eps | Q11: Eps | R11: Eps | S11: Eps | T11: Eps | U11: Eps | V11: Eps
A12: 5 | D12: Exports | E12: QETOT | F12: 5228.6748 | G12: 2.9317433 | H12: Eps | I12: Eps | J12: Eps | K12: Eps | L12: Eps | M12: Eps | N12: Eps | O12: Eps | P12: Eps | Q12: Eps | R12: Eps | S12: Eps | T12: Eps | U12: Eps | V12: Eps
A13: 6 | D13: Imports | E13: QMTOT | F13: 8074.9039 | G13: 3.0511199 | H13: Eps | I13: Eps | J13: Eps | K13: Eps | L13: Eps | M13: Eps | N13: Eps | O13: Eps | P13: Eps | Q13: Eps | R13: Eps | S13: Eps | T13: Eps | U13: Eps | V13: Eps
A14: 7 | C14: Price indices | D14: Real exchange rate | E14: REXR | F14: 100 | G14: -0.01801394 | H14: Eps | I14: Eps | J14: Eps | K14: Eps | L14: Eps | M14: Eps | N14: Eps | O14: Eps | P14: Eps | Q14: Eps | R14: Eps | S14: Eps | T14: Eps | U14: Eps | V14: Eps
A15: 8 | D15: Nominal exchange rate | E15: NEXR | F15: 100 | G15: -0.018013939 | H15: Eps | I15: Eps | J15: Eps | K15: Eps | L15: Eps | M15: Eps | N15: Eps | O15: Eps | P15: Eps | Q15: Eps | R15: Eps | S15: Eps | T15: Eps | U15: Eps | V15: Eps
A16: 9 | D16: World export price index | E16: PWEIND | F16: 100 | G16: Eps | H16: Eps | I16: Eps | J16: Eps | K16: Eps | L16: Eps | M16: Eps | N16: Eps | O16: Eps | P16: Eps | Q16: Eps | R16: Eps | S16: Eps | T16: Eps | U16: Eps | V16: Eps
A17: 10 | D17: World import price index | E17: PWMIND | F17: 100 | G17: Eps | H17: Eps | I17: Eps | J17: Eps | K17: Eps | L17: Eps | M17: Eps | N17: Eps | O17: Eps | P17: Eps | Q17: Eps | R17: Eps | S17: Eps | T17: Eps | U17: Eps | V17: Eps
A18: 11 | D18: World price index | E18: PWIND | F18: 100 | G18: Eps | H18: Eps | I18: Eps | J18: Eps | K18: Eps | L18: Eps | M18: Eps | N18: Eps | O18: Eps | P18: Eps | Q18: Eps | R18: Eps | S18: Eps | T18: Eps | U18: Eps | V18: Eps
A19: 12 | D19: Domestic price index | E19: PDIND | F19: 100 | G19: 7.9924956e-10 | H19: Eps | I19: Eps | J19: Eps | K19: Eps | L19: Eps | M19: Eps | N19: Eps | O19: Eps | P19: Eps | Q19: Eps | R19: Eps | S19: Eps | T19: Eps | U19: Eps | V19: Eps
A20: 13 | D20: Consumer price index | E20: CPI | F20: 100 | G20: -0.00016062873 | H20: Eps | I20: Eps | J20: Eps | K20: Eps | L20: Eps | M20: Eps | N20: Eps | O20: Eps | P20: Eps | Q20: Eps | R20: Eps | S20: Eps | T20: Eps | U20: Eps | V20: Eps
A21: 14 | D21: Terms-of-trade | E21: TOFT | F21: 100 | G21: Eps | H21: Eps | I21: Eps | J21: Eps | K21: Eps | L21: Eps | M21: Eps | N21: Eps | O21: Eps | P21: Eps | Q21: Eps | R21: Eps | S21: Eps | T21: Eps | U21: Eps | V21: Eps
A22: 15 | C22: GDP shares | D22: Investment / GDP | E22: INVGDP | F22: 31.44887 | G22: -0.044809076 | H22: Eps | I22: Eps | J22: Eps | K22: Eps | L22: Eps | M22: Eps | N22: Eps | O22: Eps | P22: Eps | Q22: Eps | R22: Eps | S22: Eps | T22: Eps | U22: Eps | V22: Eps
D23: Savings / GDP | E23: TSAVGDP | F23: 31.44887 | G23: -0.04480908 | H23: Eps | I23: Eps | J23: Eps | K23: Eps | L23: Eps | M23: Eps | N23: Eps | O23: Eps | P23: Eps | Q23: Eps | R23: Eps | S23: Eps | T23: Eps | U23: Eps | V23: Eps
A24: 16 | D24: Private savings / GDP | E24: PRVSAVGDP | F24: 32.111755 | G24: -0.1461332 | H24: Eps | I24: Eps | J24: Eps | K24: Eps | L24: Eps | M24: Eps | N24: Eps | O24: Eps | P24: Eps | Q24: Eps | R24: Eps | S24: Eps | T24: Eps | U24: Eps | V24: Eps
A25: 17 | D25: Government savings / GDP | E25: GOVSAVGDP | F25: -2.5917392 | G25: 0.11248925 | H25: Eps | I25: Eps | J25: Eps | K25: Eps | L25: Eps | M25: Eps | N25: Eps | O25: Eps | P25: Eps | Q25: Eps | R25: Eps | S25: Eps | T25: Eps | U25: Eps | V25: Eps
A26: 18 | D26: Foreign savings / GDP | E26: FORSAVGDP | F26: 1.9288538 | G26: -0.011165135 | H26: Eps | I26: Eps | J26: Eps | K26: Eps | L26: Eps | M26: Eps | N26: Eps | O26: Eps | P26: Eps | Q26: Eps | R26: Eps | S26: Eps | T26: Eps | U26: Eps | V26: Eps
A27: 19 | D27: Trade deficit / GDP | E27: TRDDEFGDP | F27: 9.7200714 | G27: 0.057433811 | H27: Eps | I27: Eps | J27: Eps | K27: Eps | L27: Eps | M27: Eps | N27: Eps | O27: Eps | P27: Eps | Q27: Eps | R27: Eps | S27: Eps | T27: Eps | U27: Eps | V27: Eps
A28: 20 | D28: Tax revenue / GDP | E28: TOTTXGDP | F28: 5.1475267 | G28: -0.01848243 | H28: Eps | I28: Eps | J28: Eps | K28: Eps | L28: Eps | M28: Eps | N28: Eps | O28: Eps | P28: Eps | Q28: Eps | R28: Eps | S28: Eps | T28: Eps | U28: Eps | V28: Eps
A29: 21 | D29: Indirect tax revenue / GDP | E29: INDTXGDP | F29: 3.3134533 | G29: -0.0066687152 | H29: Eps | I29: Eps | J29: Eps | K29: Eps | L29: Eps | M29: Eps | N29: Eps | O29: Eps | P29: Eps | Q29: Eps | R29: Eps | S29: Eps | T29: Eps | U29: Eps | V29: Eps
A30: 22 | D30: Activity taxes / GDP | E30: ACTTXGDP | F30: Eps | G30: Eps | H30: Eps | I30: Eps | J30: Eps | K30: Eps | L30: Eps | M30: Eps | N30: Eps | O30: Eps | P30: Eps | Q30: Eps | R30: Eps | S30: Eps | T30: Eps | U30: Eps | V30: Eps
A31: 23 | D31: Value-added taxes / GDP | E31: VADTXGDP | F31: Eps | G31: Eps | H31: Eps | I31: Eps | J31: Eps | K31: Eps | L31: Eps | M31: Eps | N31: Eps | O31: Eps | P31: Eps | Q31: Eps | R31: Eps | S31: Eps | T31: Eps | U31: Eps | V31: Eps
A32: 24 | D32: Sales taxes / GDP | E32: COMTXGDP | F32: 2.7243681 | G32: -0.0057883392 | H32: Eps | I32: Eps | J32: Eps | K32: Eps | L32: Eps | M32: Eps | N32: Eps | O32: Eps | P32: Eps | Q32: Eps | R32: Eps | S32: Eps | T32: Eps | U32: Eps | V32: Eps
A33: 25 | D33: Export taxes / GDP | E33: EXPTXGDP | F33: 1.0984692e-05 | G33: -1.4555339e-07 | H33: Eps | I33: Eps | J33: Eps | K33: Eps | L33: Eps | M33: Eps | N33: Eps | O33: Eps | P33: Eps | Q33: Eps | R33: Eps | S33: Eps | T33: Eps | U33: Eps | V33: Eps
A34: 26 | D34: Import tariffs / GDP | E34: IMPTXGDP | F34: 0.58907425 | G34: -0.00088023043 | H34: Eps | I34: Eps | J34: Eps | K34: Eps | L34: Eps | M34: Eps | N34: Eps | O34: Eps | P34: Eps | Q34: Eps | R34: Eps | S34: Eps | T34: Eps | U34: Eps | V34: Eps
A35: 27 | D35: Direct tax revenue / GDP | E35: DIRTXGDP | F35: 1.8340734 | G35: -0.011813715 | H35: Eps | I35: Eps | J35: Eps | K35: Eps | L35: Eps | M35: Eps | N35: Eps | O35: Eps | P35: Eps | Q35: Eps | R35: Eps | S35: Eps | T35: Eps | U35: Eps | V35: Eps
A36: 28 | D36: Factor taxes / GDP | E36: FACTXGDP | F36: 0.01833389 | G36: -2.9622284e-05 | H36: Eps | I36: Eps | J36: Eps | K36: Eps | L36: Eps | M36: Eps | N36: Eps | O36: Eps | P36: Eps | Q36: Eps | R36: Eps | S36: Eps | T36: Eps | U36: Eps | V36: Eps
A37: 29 | D37: Institution taxes / GDP | E37: INSTXGDP | F37: 1.8157395 | G37: -0.011784093 | H37: Eps | I37: Eps | J37: Eps | K37: Eps | L37: Eps | M37: Eps | N37: Eps | O37: Eps | P37: Eps | Q37: Eps | R37: Eps | S37: Eps | T37: Eps | U37: Eps | V37: Eps
A38: 30
A39: 31

Sheet GDP
A1: Gross Domestic Product (GDP) | O1: Tables: | P1: =C5 -> GDP by expenditure component
P2: =Z5 -> Share of total GDP at market prices
C5: GDP by expenditure component | Z5: Share of total GDP at market prices
C6: Init = Base year share of GDP at market prices | Base = Average annual growth rate (%) | Sims = Deviation in average annual growth rate from baseline (%-point) | Z6: Init = Base year share of GDP at market prices | Base = Final deviation in share from base year (%-point) | Sims = Deviation in final share from baseline final share (%-point)
G7: init | H7: base | I7: sim1 | J7: sim2 | K7: sim3 | L7: sim4 | M7: sim5 | N7: sim6 | O7: sim7 | P7: sim8 | Q7: sim9 | R7: sim10 | S7: sim11 | T7: sim12 | U7: sim13 | V7: sim14 | W7: sim15 | AD7: init | AE7: base | AF7: sim1 | AG7: sim2 | AH7: sim3 | AI7: sim4 | AJ7: sim5 | AK7: sim6 | AL7: sim7 | AM7: sim8 | AN7: sim9 | AO7: sim10 | AP7: sim11 | AQ7: sim12 | AR7: sim13 | AS7: sim14 | AT7: sim15
A8: 1 | C8: Nominal | D8: GDP at factor cost | E8: NOMINAL | F8: r_GDPFC | G8: 96.686547 | H8: 3.067902 | I8: Eps | J8: Eps | K8: Eps | L8: Eps | M8: Eps | N8: Eps | O8: Eps | P8: Eps | Q8: Eps | R8: Eps | S8: Eps | T8: Eps | U8: Eps | V8: Eps | W8: Eps | Z8: Nominal | AA8: GDP at factor cost | AB8: NOMINAL | AC8: r_GDPFC | AD8: 96.686547 | AE8: 0.006668712 | AF8: Eps | AG8: Eps | AH8: Eps | AI8: Eps | AJ8: Eps | AK8: Eps | AL8: Eps | AM8: Eps | AN8: Eps | AO8: Eps | AP8: Eps | AQ8: Eps | AR8: Eps | AS8: Eps | AT8: Eps
A9: 2 | D9: Net indirect taxes | E9: NOMINAL | F9: r_NETITAX | G9: 3.3134533 | H9: 3.0372275 | I9: Eps | J9: Eps | K9: Eps | L9: Eps | M9: Eps | N9: Eps | O9: Eps | P9: Eps | Q9: Eps | R9: Eps | S9: Eps | T9: Eps | U9: Eps | V9: Eps | W9: Eps | AA9: Net indirect taxes | AB9: NOMINAL | AC9: r_NETITAX | AD9: 3.3134533 | AE9: -0.006668712 | AF9: Eps | AG9: Eps | AH9: Eps | AI9: Eps | AJ9: Eps | AK9: Eps | AL9: Eps | AM9: Eps | AN9: Eps | AO9: Eps | AP9: Eps | AQ9: Eps | AR9: Eps | AS9: Eps | AT9: Eps
A10: 3 | D10: GDP at market prices | E10: NOMINAL | F10: r_GDPMP | G10: 100 | H10: 3.0668865 | I10: Eps | J10: Eps | K10: Eps | L10: Eps | M10: Eps | N10: Eps | O10: Eps | P10: Eps | Q10: Eps | R10: Eps | S10: Eps | T10: Eps | U10: Eps | V10: Eps | W10: Eps | AA10: GDP at market prices | AB10: NOMINAL | AC10: r_GDPMP | AD10: 100 | AE10: Eps | AF10: Eps | AG10: Eps | AH10: Eps | AI10: Eps | AJ10: Eps | AK10: Eps | AL10: Eps | AM10: Eps | AN10: Eps | AO10: Eps | AP10: Eps | AQ10: Eps | AR10: Eps | AS10: Eps | AT10: Eps
A11: 4 | D11: Absorption | E11: NOMINAL | F11: r_ABSORP | G11: 105.69056 | H11: 3.0767781 | I11: Eps | J11: Eps | K11: Eps | L11: Eps | M11: Eps | N11: Eps | O11: Eps | P11: Eps | Q11: Eps | R11: Eps | S11: Eps | T11: Eps | U11: Eps | V11: Eps | W11: Eps | AA11: Absorption | AB11: NOMINAL | AC11: r_ABSORP | AD11: 105.69056 | AE11: 0.071024075 | AF11: Eps | AG11: Eps | AH11: Eps | AI11: Eps | AJ11: Eps | AK11: Eps | AL11: Eps | AM11: Eps | AN11: Eps | AO11: Eps | AP11: Eps | AQ11: Eps | AR11: Eps | AS11: Eps | AT11: Eps
A12: 5 | D12: Private consumption | E12: NOMINAL | F12: r_PRVCON | G12: 67.951711 | H12: 3.0411835 | I12: Eps | J12: Eps | K12: Eps | L12: Eps | M12: Eps | N12: Eps | O12: Eps | P12: Eps | Q12: Eps | R12: Eps | S12: Eps | T12: Eps | U12: Eps | V12: Eps | W12: Eps | AA12: Private consumption | AB12: NOMINAL | AC12: r_PRVCON | AD12: 67.951711 | AE12: -0.11853269 | AF12: Eps | AG12: Eps | AH12: Eps | AI12: Eps | AJ12: Eps | AK12: Eps | AL12: Eps | AM12: Eps | AN12: Eps | AO12: Eps | AP12: Eps | AQ12: Eps | AR12: Eps | AS12: Eps | AT12: Eps
A13: 6 | D13: Government consumption | E13: NOMINAL | F13: r_GOVCON | G13: 6.2899758 | H13: 3.6069362 | I13: Eps | J13: Eps | K13: Eps | L13: Eps | M13: Eps | N13: Eps | O13: Eps | P13: Eps | Q13: Eps | R13: Eps | S13: Eps | T13: Eps | U13: Eps | V13: Eps | W13: Eps | AA13: Government consumption | AB13: NOMINAL | AC13: r_GOVCON | AD13: 6.2899758 | AE13: 0.23436585 | AF13: Eps | AG13: Eps | AH13: Eps | AI13: Eps | AJ13: Eps | AK13: Eps | AL13: Eps | AM13: Eps | AN13: Eps | AO13: Eps | AP13: Eps | AQ13: Eps | AR13: Eps | AS13: Eps | AT13: Eps
A14: 7 | D14: Gross capital formation | E14: NOMINAL | F14: r_GCF | G14: 31.44887 | H14: 3.0458948 | I14: Eps | J14: Eps | K14: Eps | L14: Eps | M14: Eps | N14: Eps | O14: Eps | P14: Eps | Q14: Eps | R14: Eps | S14: Eps | T14: Eps | U14: Eps | V14: Eps | W14: Eps | AA14: Gross capital formation | AB14: NOMINAL | AC14: r_GCF | AD14: 31.44887 | AE14: -0.044809076 | AF14: Eps | AG14: Eps | AH14: Eps | AI14: Eps | AJ14: Eps | AK14: Eps | AL14: Eps | AM14: Eps | AN14: Eps | AO14: Eps | AP14: Eps | AQ14: Eps | AR14: Eps | AS14: Eps | AT14: Eps
A15: 8 | D15: Fixed capital formation | E15: NOMINAL | F15: r_GFCF | G15: 31.498388 | H15: 3.0415334 | I15: Eps | J15: Eps | K15: Eps | L15: Eps | M15: Eps | N15: Eps | O15: Eps | P15: Eps | Q15: Eps | R15: Eps | S15: Eps | T15: Eps | U15: Eps | V15: Eps | W15: Eps | AA15: Fixed capital formation | AB15: NOMINAL | AC15: r_GFCF | AD15: 31.498388 | AE15: -0.054197325 | AF15: Eps | AG15: Eps | AH15: Eps | AI15: Eps | AJ15: Eps | AK15: Eps | AL15: Eps | AM15: Eps | AN15: Eps | AO15: Eps | AP15: Eps | AQ15: Eps | AR15: Eps | AS15: Eps | AT15: Eps
A16: 9 | D16: Change in stocks | E16: NOMINAL | F16: r_STK | G16: -0.049517693 | H16: 0.017660504 | I16: Eps | J16: Eps | K16: Eps | L16: Eps | M16: Eps | N16: Eps | O16: Eps | P16: Eps | Q16: Eps | R16: Eps | S16: Eps | T16: Eps | U16: Eps | V16: Eps | W16: Eps | AA16: Change in stocks | AB16: NOMINAL | AC16: r_STK | AD16: -0.049517693 | AE16: 0.0093882485 | AF16: Eps | AG16: Eps | AH16: Eps | AI16: Eps | AJ16: Eps | AK16: Eps | AL16: Eps | AM16: Eps | AN16: Eps | AO16: Eps | AP16: Eps | AQ16: Eps | AR16: Eps | AS16: Eps | AT16: Eps
A17: 10 | D17: Net trade balance | E17: NOMINAL | F17: r_TRDBAL | G17: -5.6905573 | H17: 3.2496799 | I17: Eps | J17: Eps | K17: Eps | L17: Eps | M17: Eps | N17: Eps | O17: Eps | P17: Eps | Q17: Eps | R17: Eps | S17: Eps | T17: Eps | U17: Eps | V17: Eps | W17: Eps | AA17: Net trade balance | AB17: NOMINAL | AC17: r_TRDBAL | AD17: -5.6905573 | AE17: -0.071024075 | AF17: Eps | AG17: Eps | AH17: Eps | AI17: Eps | AJ17: Eps | AK17: Eps | AL17: Eps | AM17: Eps | AN17: Eps | AO17: Eps | AP17: Eps | AQ17: Eps | AR17: Eps | AS17: Eps | AT17: Eps
A18: 11 | D18: Exports | E18: NOMINAL | F18: r_EXP | G18: 10.453857 | H18: 2.9132012 | I18: Eps | J18: Eps | K18: Eps | L18: Eps | M18: Eps | N18: Eps | O18: Eps | P18: Eps | Q18: Eps | R18: Eps | S18: Eps | T18: Eps | U18: Eps | V18: Eps | W18: Eps | AA18: Exports | AB18: NOMINAL | AC18: r_EXP | AD18: 10.453857 | AE18: -0.10862894 | AF18: Eps | AG18: Eps | AH18: Eps | AI18: Eps | AJ18: Eps | AK18: Eps | AL18: Eps | AM18: Eps | AN18: Eps | AO18: Eps | AP18: Eps | AQ18: Eps | AR18: Eps | AS18: Eps | AT18: Eps
A19: 12 | D19: Imports | E19: NOMINAL | F19: r_IMP | G19: 16.144415 | H19: 3.0325563 | I19: Eps | J19: Eps | K19: Eps | L19: Eps | M19: Eps | N19: Eps | O19: Eps | P19: Eps | Q19: Eps | R19: Eps | S19: Eps | T19: Eps | U19: Eps | V19: Eps | W19: Eps | AA19: Imports | AB19: NOMINAL | AC19: r_IMP | AD19: 16.144415 | AE19: -0.037604863 | AF19: Eps | AG19: Eps | AH19: Eps | AI19: Eps | AJ19: Eps | AK19: Eps | AL19: Eps | AM19: Eps | AN19: Eps | AO19: Eps | AP19: Eps | AQ19: Eps | AR19: Eps | AS19: Eps | AT19: Eps
A20: 13 | C20: Real | D20: GDP at factor cost | E20: REAL | F20: r_GDPFC | G20: 96.686547 | H20: 3.0571208 | I20: Eps | J20: Eps | K20: Eps | L20: Eps | M20: Eps | N20: Eps | O20: Eps | P20: Eps | Q20: Eps | R20: Eps | S20: Eps | T20: Eps | U20: Eps | V20: Eps | W20: Eps | Z20: Real | AA20: GDP at factor cost | AB20: REAL | AC20: r_GDPFC | AD20: 96.686547 | AE20: 0.0010312575 | AF20: Eps | AG20: Eps | AH20: Eps | AI20: Eps | AJ20: Eps | AK20: Eps | AL20: Eps | AM20: Eps | AN20: Eps | AO20: Eps | AP20: Eps | AQ20: Eps | AR20: Eps | AS20: Eps | AT20: Eps
A21: 14 | D21: Net indirect taxes | E21: REAL | F21: r_NETITAX | G21: 3.3134533 | H21: 3.052381 | I21: Eps | J21: Eps | K21: Eps | L21: Eps | M21: Eps | N21: Eps | O21: Eps | P21: Eps | Q21: Eps | R21: Eps | S21: Eps | T21: Eps | U21: Eps | V21: Eps | W21: Eps | AA21: Net indirect taxes | AB21: REAL | AC21: r_NETITAX | AD21: 3.3134533 | AE21: -0.0010312575 | AF21: Eps | AG21: Eps | AH21: Eps | AI21: Eps | AJ21: Eps | AK21: Eps | AL21: Eps | AM21: Eps | AN21: Eps | AO21: Eps | AP21: Eps | AQ21: Eps | AR21: Eps | AS21: Eps | AT21: Eps
A22: 15 | D22: GDP at market prices | E22: REAL | F22: r_GDPMP | G22: 100 | H22: 3.0569638 | I22: Eps | J22: Eps | K22: Eps | L22: Eps | M22: Eps | N22: Eps | O22: Eps | P22: Eps | Q22: Eps | R22: Eps | S22: Eps | T22: Eps | U22: Eps | V22: Eps | W22: Eps | AA22: GDP at market prices | AB22: REAL | AC22: r_GDPMP | AD22: 100 | AE22: Eps | AF22: Eps | AG22: Eps | AH22: Eps | AI22: Eps | AJ22: Eps | AK22: Eps | AL22: Eps | AM22: Eps | AN22: Eps | AO22: Eps | AP22: Eps | AQ22: Eps | AR22: Eps | AS22: Eps | AT22: Eps
A23: 16 | D23: Absorption | E23: REAL | F23: r_ABSORP | G23: 105.69056 | H23: 3.0684079 | I23: Eps | J23: Eps | K23: Eps | L23: Eps | M23: Eps | N23: Eps | O23: Eps | P23: Eps | Q23: Eps | R23: Eps | S23: Eps | T23: Eps | U23: Eps | V23: Eps | W23: Eps | AA23: Absorption | AB23: REAL | AC23: r_ABSORP | AD23: 105.69056 | AE23: 0.082183802 | AF23: Eps | AG23: Eps | AH23: Eps | AI23: Eps | AJ23: Eps | AK23: Eps | AL23: Eps | AM23: Eps | AN23: Eps | AO23: Eps | AP23: Eps | AQ23: Eps | AR23: Eps | AS23: Eps | AT23: Eps
A24: 17 | D24: Private consumption | E24: REAL | F24: r_PRVCON | G24: 67.951711 | H24: 3.0405704 | I24: Eps | J24: Eps | K24: Eps | L24: Eps | M24: Eps | N24: Eps | O24: Eps | P24: Eps | Q24: Eps | R24: Eps | S24: Eps | T24: Eps | U24: Eps | V24: Eps | W24: Eps | AA24: Private consumption | AB24: REAL | AC24: r_PRVCON | AD24: 67.951711 | AE24: -0.075627994 | AF24: Eps | AG24: Eps | AH24: Eps | AI24: Eps | AJ24: Eps | AK24: Eps | AL24: Eps | AM24: Eps | AN24: Eps | AO24: Eps | AP24: Eps | AQ24: Eps | AR24: Eps | AS24: Eps | AT24: Eps
A25: 18 | D25: Government consumption | E25: REAL | F25: r_GOVCON | G25: 6.2899758 | H25: 3.5 | I25: Eps | J25: Eps | K25: Eps | L25: Eps | M25: Eps | N25: Eps | O25: Eps | P25: Eps | Q25: Eps | R25: Eps | S25: Eps | T25: Eps | U25: Eps | V25: Eps | W25: Eps | AA25: Government consumption | AB25: REAL | AC25: r_GOVCON | AD25: 6.2899758 | AE25: 0.19174054 | AF25: Eps | AG25: Eps | AH25: Eps | AI25: Eps | AJ25: Eps | AK25: Eps | AL25: Eps | AM25: Eps | AN25: Eps | AO25: Eps | AP25: Eps | AQ25: Eps | AR25: Eps | AS25: Eps | AT25: Eps
A26: 19 | D26: Gross capital formation | E26: REAL | F26: r_GCF | G26: 31.44887 | H26: 3.0410731 | I26: Eps | J26: Eps | K26: Eps | L26: Eps | M26: Eps | N26: Eps | O26: Eps | P26: Eps | Q26: Eps | R26: Eps | S26: Eps | T26: Eps | U26: Eps | V26: Eps | W26: Eps | AA26: Gross capital formation | AB26: REAL | AC26: r_GCF | AD26: 31.44887 | AE26: -0.03392874 | AF26: Eps | AG26: Eps | AH26: Eps | AI26: Eps | AJ26: Eps | AK26: Eps | AL26: Eps | AM26: Eps | AN26: Eps | AO26: Eps | AP26: Eps | AQ26: Eps | AR26: Eps | AS26: Eps | AT26: Eps
A27: 20 | D27: Fixed capital formation | E27: REAL | F27: r_GFCF | G27: 31.498388 | H27: 3.0366948 | I27: Eps | J27: Eps | K27: Eps | L27: Eps | M27: Eps | N27: Eps | O27: Eps | P27: Eps | Q27: Eps | R27: Eps | S27: Eps | T27: Eps | U27: Eps | V27: Eps | W27: Eps | AA27: Fixed capital formation | AB27: REAL | AC27: r_GFCF | AD27: 31.498388 | AE27: -0.043339542 | AF27: Eps | AG27: Eps | AH27: Eps | AI27: Eps | AJ27: Eps | AK27: Eps | AL27: Eps | AM27: Eps | AN27: Eps | AO27: Eps | AP27: Eps | AQ27: Eps | AR27: Eps | AS27: Eps | AT27: Eps
A28: 21 | D28: Change in stocks | E28: REAL | F28: r_STK | G28: -0.049517693 | H28: Eps | I28: Eps | J28: Eps | K28: Eps | L28: Eps | M28: Eps | N28: Eps | O28: Eps | P28: Eps | Q28: Eps | R28: Eps | S28: Eps | T28: Eps | U28: Eps | V28: Eps | W28: Eps | AA28: Change in stocks | AB28: REAL | AC28: r_STK | AD28: -0.049517693 | AE28: 0.0094108017 | AF28: Eps | AG28: Eps | AH28: Eps | AI28: Eps | AJ28: Eps | AK28: Eps | AL28: Eps | AM28: Eps | AN28: Eps | AO28: Eps | AP28: Eps | AQ28: Eps | AR28: Eps | AS28: Eps | AT28: Eps
A29: 22 | D29: Net trade balance | E29: REAL | F29: r_TRDBAL | G29: -5.6905573 | H29: 3.2682826 | I29: Eps | J29: Eps | K29: Eps | L29: Eps | M29: Eps | N29: Eps | O29: Eps | P29: Eps | Q29: Eps | R29: Eps | S29: Eps | T29: Eps | U29: Eps | V29: Eps | W29: Eps | AA29: Net trade balance | AB29: REAL | AC29: r_TRDBAL | AD29: -5.6905573 | AE29: -0.082183802 | AF29: Eps | AG29: Eps | AH29: Eps | AI29: Eps | AJ29: Eps | AK29: Eps | AL29: Eps | AM29: Eps | AN29: Eps | AO29: Eps | AP29: Eps | AQ29: Eps | AR29: Eps | AS29: Eps | AT29: Eps
A30: 23 | D30: Exports | E30: REAL | F30: r_EXP | G30: 10.453857 | H30: 2.9317433 | I30: Eps | J30: Eps | K30: Eps | L30: Eps | M30: Eps | N30: Eps | O30: Eps | P30: Eps | Q30: Eps | R30: Eps | S30: Eps | T30: Eps | U30: Eps | V30: Eps | W30: Eps | AA30: Exports | AB30: REAL | AC30: r_EXP | AD30: 10.453857 | AE30: -0.088591051 | AF30: Eps | AG30: Eps | AH30: Eps | AI30: Eps | AJ30: Eps | AK30: Eps | AL30: Eps | AM30: Eps | AN30: Eps | AO30: Eps | AP30: Eps | AQ30: Eps | AR30: Eps | AS30: Eps | AT30: Eps
A31: 24 | D31: Imports | E31: REAL | F31: r_IMP | G31: 16.144415 | H31: 3.0511199 | I31: Eps | J31: Eps | K31: Eps | L31: Eps | M31: Eps | N31: Eps | O31: Eps | P31: Eps | Q31: Eps | R31: Eps | S31: Eps | T31: Eps | U31: Eps | V31: Eps | W31: Eps | AA31: Imports | AB31: REAL | AC31: r_IMP | AD31: 16.144415 | AE31: -0.0064072486 | AF31: Eps | AG31: Eps | AH31: Eps | AI31: Eps | AJ31: Eps | AK31: Eps | AL31: Eps | AM31: Eps | AN31: Eps | AO31: Eps | AP31: Eps | AQ31: Eps | AR31: Eps | AS31: Eps | AT31: Eps
A32: 150

Sheet Sector
A1: Sectoral Gross Domestic Product (GDP) | M1: Tables: | N1: =C5 -> GDP at factor cost (PVA×QVA)
N2: =X5 -> Share of total GDP at factor cost (PVA×QVA)
C5: GDP at factor cost (PVA×QVA) | X5: Share of total GDP at factor cost (PVA×QVA)
C6: Init = Base year share of total GDP | Base = Average annual growth rate (%) | Sims = Deviation in average annual growth rate from baseline (%-point) | X6: Init = Base year share of total GDP | Base = Final deviation in share from base year (%-point) | Sims = Deviation in final share from baseline final share (%-point)
E7: init | F7: base | G7: sim1 | H7: sim2 | I7: sim3 | J7: sim4 | K7: sim5 | L7: sim6 | M7: sim7 | N7: sim8 | O7: sim9 | P7: sim10 | Q7: sim11 | R7: sim12 | S7: sim13 | T7: sim14 | U7: sim15 | Z7: init | AA7: base | AB7: sim1 | AC7: sim2 | AD7: sim3 | AE7: sim4 | AF7: sim5 | AG7: sim6 | AH7: sim7 | AI7: sim8 | AJ7: sim9 | AK7: sim10 | AL7: sim11 | AM7: sim12 | AN7: sim13 | AO7: sim14 | AP7: sim15
A8: 1 | C8: =Notes!T9 -> All sectors | D8: aa_GDP | E8: 100 | F8: 3.0571208 | G8: Eps | H8: Eps | I8: Eps | J8: Eps | K8: Eps | L8: Eps | M8: Eps | N8: Eps | O8: Eps | P8: Eps | Q8: Eps | R8: Eps | S8: Eps | T8: Eps | U8: Eps | X8: =Notes!T9 -> All sectors | Y8: aa_GDP | Z8: 100 | AA8: Eps | AB8: Eps | AC8: Eps | AD8: Eps | AE8: Eps | AF8: Eps | AG8: Eps | AH8: Eps | AI8: Eps | AJ8: Eps | AK8: Eps | AL8: Eps | AM8: Eps | AN8: Eps | AO8: Eps | AP8: Eps
A9: 2 | C9: =Notes!T10 -> Agriculture | D9: aa_AGRI | E9: 11.553747 | F9: 3.0398052 | G9: Eps | H9: Eps | I9: Eps | J9: Eps | K9: Eps | L9: Eps | M9: Eps | N9: Eps | O9: Eps | P9: Eps | Q9: Eps | R9: Eps | S9: Eps | T9: Eps | U9: Eps | X9: =Notes!T10 -> Agriculture | Y9: aa_AGRI | Z9: 11.553747 | AA9: -0.013581916 | AB9: Eps | AC9: Eps | AD9: Eps | AE9: Eps | AF9: Eps | AG9: Eps | AH9: Eps | AI9: Eps | AJ9: Eps | AK9: Eps | AL9: Eps | AM9: Eps | AN9: Eps | AO9: Eps | AP9: Eps
A10: 3 | C10: =Notes!T11 -> Crops | D10: aa_CROP | E10: 5.8017781 | F10: 3.0211436 | G10: Eps | H10: Eps | I10: Eps | J10: Eps | K10: Eps | L10: Eps | M10: Eps | N10: Eps | O10: Eps | P10: Eps | Q10: Eps | R10: Eps | S10: Eps | T10: Eps | U10: Eps | X10: =Notes!T11 -> Crops | Y10: aa_CROP | Z10: 5.8017781 | AA10: -0.014162952 | AB10: Eps | AC10: Eps | AD10: Eps | AE10: Eps | AF10: Eps | AG10: Eps | AH10: Eps | AI10: Eps | AJ10: Eps | AK10: Eps | AL10: Eps | AM10: Eps | AN10: Eps | AO10: Eps | AP10: Eps
A11: 4 | C11: =Notes!T12 -> Maize | D11: a_maiz | E11: 0.057176284 | F11: 2.9900765 | G11: Eps | H11: Eps | I11: Eps | J11: Eps | K11: Eps | L11: Eps | M11: Eps | N11: Eps | O11: Eps | P11: Eps | Q11: Eps | R11: Eps | S11: Eps | T11: Eps | U11: Eps | X11: =Notes!T12 -> Maize | Y11: a_maiz | Z11: 0.057176284 | AA11: -0.0002598665 | AB11: Eps | AC11: Eps | AD11: Eps | AE11: Eps | AF11: Eps | AG11: Eps | AH11: Eps | AI11: Eps | AJ11: Eps | AK11: Eps | AL11: Eps | AM11: Eps | AN11: Eps | AO11: Eps | AP11: Eps
A12: 5 | C12: =Notes!T13 -> Sorghum and millet | D12: a_sorg | E12: Eps | F12: Eps | G12: Eps | H12: Eps | I12: Eps | J12: Eps | K12: Eps | L12: Eps | M12: Eps | N12: Eps | O12: Eps | P12: Eps | Q12: Eps | R12: Eps | S12: Eps | T12: Eps | U12: Eps | X12: =Notes!T13 -> Sorghum and millet | Y12: a_sorg | Z12: Eps | AA12: Eps | AB12: Eps | AC12: Eps | AD12: Eps | AE12: Eps | AF12: Eps | AG12: Eps | AH12: Eps | AI12: Eps | AJ12: Eps | AK12: Eps | AL12: Eps | AM12: Eps | AN12: Eps | AO12: Eps | AP12: Eps
A13: 6 | C13: =Notes!T14 -> Rice paddy (Aman) | D13: a_aman | E13: 1.7790835 | F13: 3.0279636 | G13: Eps | H13: Eps | I13: Eps | J13: Eps | K13: Eps | L13: Eps | M13: Eps | N13: Eps | O13: Eps | P13: Eps | Q13: Eps | R13: Eps | S13: Eps | T13: Eps | U13: Eps | X13: =Notes!T14 -> Rice paddy (Aman) | Y13: a_aman | Z13: 1.7790835 | AA13: -0.0035204153 | AB13: Eps | AC13: Eps | AD13: Eps | AE13: Eps | AF13: Eps | AG13: Eps | AH13: Eps | AI13: Eps | AJ13: Eps | AK13: Eps | AL13: Eps | AM13: Eps | AN13: Eps | AO13: Eps | AP13: Eps
A14: 7 | C14: =Notes!T15 -> Rice paddy (Boro) | D14: a_boro | E14: 1.7183562 | F14: 3.0279813 | G14: Eps | H14: Eps | I14: Eps | J14: Eps | K14: Eps | L14: Eps | M14: Eps | N14: Eps | O14: Eps | P14: Eps | Q14: Eps | R14: Eps | S14: Eps | T14: Eps | U14: Eps | X14: =Notes!T15 -> Rice paddy (Boro) | Y14: a_boro | Z14: 1.7183562 | AA14: -0.0033981863 | AB14: Eps | AC14: Eps | AD14: Eps | AE14: Eps | AF14: Eps | AG14: Eps | AH14: Eps | AI14: Eps | AJ14: Eps | AK14: Eps | AL14: Eps | AM14: Eps | AN14: Eps | AO14: Eps | AP14: Eps
A15: 8 | C15: =Notes!T16 -> Wheat and barley | D15: a_whea | E15: 0.019864455 | F15: 2.9442668 | G15: Eps | H15: Eps | I15: Eps | J15: Eps | K15: Eps | L15: Eps | M15: Eps | N15: Eps | O15: Eps | P15: Eps | Q15: Eps | R15: Eps | S15: Eps | T15: Eps | U15: Eps | X15: =Notes!T16 -> Wheat and barley | Y15: a_whea | Z15: 0.019864455 | AA15: -0.00015177044 | AB15: Eps | AC15: Eps | AD15: Eps | AE15: Eps | AF15: Eps | AG15: Eps | AH15: Eps | AI15: Eps | AJ15: Eps | AK15: Eps | AL15: Eps | AM15: Eps | AN15: Eps | AO15: Eps | AP15: Eps
A16: 9 | C16: =Notes!T17 -> Other cereals | D16: a_ocer | E16: Eps | F16: Eps | G16: Eps | H16: Eps | I16: Eps | J16: Eps | K16: Eps | L16: Eps | M16: Eps | N16: Eps | O16: Eps | P16: Eps | Q16: Eps | R16: Eps | S16: Eps | T16: Eps | U16: Eps | X16: =Notes!T17 -> Other cereals | Y16: a_ocer | Z16: Eps | AA16: Eps | AB16: Eps | AC16: Eps | AD16: Eps | AE16: Eps | AF16: Eps | AG16: Eps | AH16: Eps | AI16: Eps | AJ16: Eps | AK16: Eps | AL16: Eps | AM16: Eps | AN16: Eps | AO16: Eps | AP16: Eps
A17: 10 | C17: =Notes!T18 -> Pulses | D17: a_puls | E17: 0.097083773 | F17: 2.9854809 | G17: Eps | H17: Eps | I17: Eps | J17: Eps | K17: Eps | L17: Eps | M17: Eps | N17: Eps | O17: Eps | P17: Eps | Q17: Eps | R17: Eps | S17: Eps | T17: Eps | U17: Eps | X17: =Notes!T18 -> Pulses | Y17: a_puls | Z17: 0.097083773 | AA17: -0.00047142881 | AB17: Eps | AC17: Eps | AD17: Eps | AE17: Eps | AF17: Eps | AG17: Eps | AH17: Eps | AI17: Eps | AJ17: Eps | AK17: Eps | AL17: Eps | AM17: Eps | AN17: Eps | AO17: Eps | AP17: Eps
A18: 11 | C18: =Notes!T19 -> Groundnuts | D18: a_gnut | E18: Eps | F18: Eps | G18: Eps | H18: Eps | I18: Eps | J18: Eps | K18: Eps | L18: Eps | M18: Eps | N18: Eps | O18: Eps | P18: Eps | Q18: Eps | R18: Eps | S18: Eps | T18: Eps | U18: Eps | X18: =Notes!T19 -> Groundnuts | Y18: a_gnut | Z18: Eps | AA18: Eps | AB18: Eps | AC18: Eps | AD18: Eps | AE18: Eps | AF18: Eps | AG18: Eps | AH18: Eps | AI18: Eps | AJ18: Eps | AK18: Eps | AL18: Eps | AM18: Eps | AN18: Eps | AO18: Eps | AP18: Eps
A19: 12 | C19: =Notes!T20 -> Other oilseeds | D19: a_oils | E19: 0.17907292 | F19: 2.964204 | G19: Eps | H19: Eps | I19: Eps | J19: Eps | K19: Eps | L19: Eps | M19: Eps | N19: Eps | O19: Eps | P19: Eps | Q19: Eps | R19: Eps | S19: Eps | T19: Eps | U19: Eps | X19: =Notes!T20 -> Other oilseeds | Y19: a_oils | Z19: 0.17907292 | AA19: -0.001127119 | AB19: Eps | AC19: Eps | AD19: Eps | AE19: Eps | AF19: Eps | AG19: Eps | AH19: Eps | AI19: Eps | AJ19: Eps | AK19: Eps | AL19: Eps | AM19: Eps | AN19: Eps | AO19: Eps | AP19: Eps
A20: 13 | C20: =Notes!T21 -> Cassava | D20: a_cass | E20: Eps | F20: Eps | G20: Eps | H20: Eps | I20: Eps | J20: Eps | K20: Eps | L20: Eps | M20: Eps | N20: Eps | O20: Eps | P20: Eps | Q20: Eps | R20: Eps | S20: Eps | T20: Eps | U20: Eps | X20: =Notes!T21 -> Cassava | Y20: a_cass | Z20: Eps | AA20: Eps | AB20: Eps | AC20: Eps | AD20: Eps | AE20: Eps | AF20: Eps | AG20: Eps | AH20: Eps | AI20: Eps | AJ20: Eps | AK20: Eps | AL20: Eps | AM20: Eps | AN20: Eps | AO20: Eps | AP20: Eps
A21: 14 | C21: =Notes!T22 -> Irish potatoes | D21: a_ipot | E21: 0.15284804 | F21: 3.0353308 | G21: Eps | H21: Eps | I21: Eps | J21: Eps | K21: Eps | L21: Eps | M21: Eps | N21: Eps | O21: Eps | P21: Eps | Q21: Eps | R21: Eps | S21: Eps | T21: Eps | U21: Eps | X21: =Notes!T22 -> Irish potatoes | Y21: a_ipot | Z21: 0.15284804 | AA21: -0.00022607942 | AB21: Eps | AC21: Eps | AD21: Eps | AE21: Eps | AF21: Eps | AG21: Eps | AH21: Eps | AI21: Eps | AJ21: Eps | AK21: Eps | AL21: Eps | AM21: Eps | AN21: Eps | AO21: Eps | AP21: Eps
A22: 15 | C22: =Notes!T23 -> Sweet potatoes | D22: a_spot | E22: Eps | F22: Eps | G22: Eps | H22: Eps | I22: Eps | J22: Eps | K22: Eps | L22: Eps | M22: Eps | N22: Eps | O22: Eps | P22: Eps | Q22: Eps | R22: Eps | S22: Eps | T22: Eps | U22: Eps | X22: =Notes!T23 -> Sweet potatoes | Y22: a_spot | Z22: Eps | AA22: Eps | AB22: Eps | AC22: Eps | AD22: Eps | AE22: Eps | AF22: Eps | AG22: Eps | AH22: Eps | AI22: Eps | AJ22: Eps | AK22: Eps | AL22: Eps | AM22: Eps | AN22: Eps | AO22: Eps | AP22: Eps
A23: 16 | C23: =Notes!T24 -> Other roots | D23: a_root | E23: Eps | F23: Eps | G23: Eps | H23: Eps | I23: Eps | J23: Eps | K23: Eps | L23: Eps | M23: Eps | N23: Eps | O23: Eps | P23: Eps | Q23: Eps | R23: Eps | S23: Eps | T23: Eps | U23: Eps | X23: =Notes!T24 -> Other roots | Y23: a_root | Z23: Eps | AA23: Eps | AB23: Eps | AC23: Eps | AD23: Eps | AE23: Eps | AF23: Eps | AG23: Eps | AH23: Eps | AI23: Eps | AJ23: Eps | AK23: Eps | AL23: Eps | AM23: Eps | AN23: Eps | AO23: Eps | AP23: Eps
A24: 17 | C24: =Notes!T25 -> Leafy vegetables | D24: a_leaf | E24: 0.13963036 | F24: 3.0180475 | G24: Eps | H24: Eps | I24: Eps | J24: Eps | K24: Eps | L24: Eps | M24: Eps | N24: Eps | O24: Eps | P24: Eps | Q24: Eps | R24: Eps | S24: Eps | T24: Eps | U24: Eps | X24: =Notes!T25 -> Leafy vegetables | Y24: a_leaf | Z24: 0.13963036 | AA24: -0.00037015722 | AB24: Eps | AC24: Eps | AD24: Eps | AE24: Eps | AF24: Eps | AG24: Eps | AH24: Eps | AI24: Eps | AJ24: Eps | AK24: Eps | AL24: Eps | AM24: Eps | AN24: Eps | AO24: Eps | AP24: Eps
A25: 18 | C25: =Notes!T26 -> Other vegetables | D25: a_vege | E25: 0.3074146 | F25: 3.0127606 | G25: Eps | H25: Eps | I25: Eps | J25: Eps | K25: Eps | L25: Eps | M25: Eps | N25: Eps | O25: Eps | P25: Eps | Q25: Eps | R25: Eps | S25: Eps | T25: Eps | U25: Eps | X25: =Notes!T26 -> Other vegetables | Y25: a_vege | Z25: 0.3074146 | AA25: -0.00092507471 | AB25: Eps | AC25: Eps | AD25: Eps | AE25: Eps | AF25: Eps | AG25: Eps | AH25: Eps | AI25: Eps | AJ25: Eps | AK25: Eps | AL25: Eps | AM25: Eps | AN25: Eps | AO25: Eps | AP25: Eps
A26: 19 | C26: =Notes!T27 -> Sugarcane | D26: a_sugr | E26: 0.082417407 | F26: 2.9996094 | G26: Eps | H26: Eps | I26: Eps | J26: Eps | K26: Eps | L26: Eps | M26: Eps | N26: Eps | O26: Eps | P26: Eps | Q26: Eps | R26: Eps | S26: Eps | T26: Eps | U26: Eps | X26: =Notes!T27 -> Sugarcane | Y26: a_sugr | Z26: 0.082417407 | AA26: -0.00032141446 | AB26: Eps | AC26: Eps | AD26: Eps | AE26: Eps | AF26: Eps | AG26: Eps | AH26: Eps | AI26: Eps | AJ26: Eps | AK26: Eps | AL26: Eps | AM26: Eps | AN26: Eps | AO26: Eps | AP26: Eps
A27: 20 | C27: =Notes!T28 -> Tobacco | D27: a_toba | E27: 0.21507085 | F27: 3.041946 | G27: Eps | H27: Eps | I27: Eps | J27: Eps | K27: Eps | L27: Eps | M27: Eps | N27: Eps | O27: Eps | P27: Eps | Q27: Eps | R27: Eps | S27: Eps | T27: Eps | U27: Eps | X27: =Notes!T28 -> Tobacco | Y27: a_toba | Z27: 0.21507085 | AA27: -0.00022158118 | AB27: Eps | AC27: Eps | AD27: Eps | AE27: Eps | AF27: Eps | AG27: Eps | AH27: Eps | AI27: Eps | AJ27: Eps | AK27: Eps | AL27: Eps | AM27: Eps | AN27: Eps | AO27: Eps | AP27: Eps
A28: 21 | C28: =Notes!T29 -> Cotton and fibres | D28: a_cott | E28: 0.0012261848 | F28: 3.0120056 | G28: Eps | H28: Eps | I28: Eps | J28: Eps | K28: Eps | L28: Eps | M28: Eps | N28: Eps | O28: Eps | P28: Eps | Q28: Eps | R28: Eps | S28: Eps | T28: Eps | U28: Eps | X28: =Notes!T29 -> Cotton and fibres | Y28: a_cott | Z28: 0.0012261848 | AA28: -3.752567e-06 | AB28: Eps | AC28: Eps | AD28: Eps | AE28: Eps | AF28: Eps | AG28: Eps | AH28: Eps | AI28: Eps | AJ28: Eps | AK28: Eps | AL28: Eps | AM28: Eps | AN28: Eps | AO28: Eps | AP28: Eps
A29: 22 | C29: =Notes!T30 -> Jute | D29: a_jute | E29: 0.25549077 | F29: 2.9894656 | G29: Eps | H29: Eps | I29: Eps | J29: Eps | K29: Eps | L29: Eps | M29: Eps | N29: Eps | O29: Eps | P29: Eps | Q29: Eps | R29: Eps | S29: Eps | T29: Eps | U29: Eps | X29: =Notes!T30 -> Jute | Y29: a_jute | Z29: 0.25549077 | AA29: -0.0011717667 | AB29: Eps | AC29: Eps | AD29: Eps | AE29: Eps | AF29: Eps | AG29: Eps | AH29: Eps | AI29: Eps | AJ29: Eps | AK29: Eps | AL29: Eps | AM29: Eps | AN29: Eps | AO29: Eps | AP29: Eps
A30: 23 | C30: =Notes!T31 -> Nuts | D30: a_nuts | E30: 0.10133306 | F30: 3.0207416 | G30: Eps | H30: Eps | I30: Eps | J30: Eps | K30: Eps | L30: Eps | M30: Eps | N30: Eps | O30: Eps | P30: Eps | Q30: Eps | R30: Eps | S30: Eps | T30: Eps | U30: Eps | X30: =Notes!T31 -> Nuts | Y30: a_nuts | Z30: 0.10133306 | AA30: -0.00025012888 | AB30: Eps | AC30: Eps | AD30: Eps | AE30: Eps | AF30: Eps | AG30: Eps | AH30: Eps | AI30: Eps | AJ30: Eps | AK30: Eps | AL30: Eps | AM30: Eps | AN30: Eps | AO30: Eps | AP30: Eps
A31: 24 | C31: =Notes!T32 -> Bananas and plantains | D31: a_bana | E31: 0.044765728 | F31: 3.0214266 | G31: Eps | H31: Eps | I31: Eps | J31: Eps | K31: Eps | L31: Eps | M31: Eps | N31: Eps | O31: Eps | P31: Eps | Q31: Eps | R31: Eps | S31: Eps | T31: Eps | U31: Eps | X31: =Notes!T32 -> Bananas and plantains | Y31: a_bana | Z31: 0.044765728 | AA31: -0.00010842047 | AB31: Eps | AC31: Eps | AD31: Eps | AE31: Eps | AF31: Eps | AG31: Eps | AH31: Eps | AI31: Eps | AJ31: Eps | AK31: Eps | AL31: Eps | AM31: Eps | AN31: Eps | AO31: Eps | AP31: Eps
A32: 25 | C32: =Notes!T33 -> Other fruits | D32: a_frui | E32: 0.26395265 | F32: 3.0209752 | G32: Eps | H32: Eps | I32: Eps | J32: Eps | K32: Eps | L32: Eps | M32: Eps | N32: Eps | O32: Eps | P32: Eps | Q32: Eps | R32: Eps | S32: Eps | T32: Eps | U32: Eps | X32: =Notes!T33 -> Other fruits | Y32: a_frui | Z32: 0.26395265 | AA32: -0.00064735803 | AB32: Eps | AC32: Eps | AD32: Eps | AE32: Eps | AF32: Eps | AG32: Eps | AH32: Eps | AI32: Eps | AJ32: Eps | AK32: Eps | AL32: Eps | AM32: Eps | AN32: Eps | AO32: Eps | AP32: Eps
A33: 26 | C33: =Notes!T34 -> Leaf tea | D33: a_teal | E33: 0.027250198 | F33: 3.0451908 | G33: Eps | H33: Eps | I33: Eps | J33: Eps | K33: Eps | L33: Eps | M33: Eps | N33: Eps | O33: Eps | P33: Eps | Q33: Eps | R33: Eps | S33: Eps | T33: Eps | U33: Eps | X33: =Notes!T34 -> Leaf tea | Y33: a_teal | Z33: 0.027250198 | AA33: -2.2073926e-05 | AB33: Eps | AC33: Eps | AD33: Eps | AE33: Eps | AF33: Eps | AG33: Eps | AH33: Eps | AI33: Eps | AJ33: Eps | AK33: Eps | AL33: Eps | AM33: Eps | AN33: Eps | AO33: Eps | AP33: Eps
A34: 27 | C34: =Notes!T35 -> Coffee | D34: a_coff | E34: Eps | F34: Eps | G34: Eps | H34: Eps | I34: Eps | J34: Eps | K34: Eps | L34: Eps | M34: Eps | N34: Eps | O34: Eps | P34: Eps | Q34: Eps | R34: Eps | S34: Eps | T34: Eps | U34: Eps | X34: =Notes!T35 -> Coffee | Y34: a_coff | Z34: Eps | AA34: Eps | AB34: Eps | AC34: Eps | AD34: Eps | AE34: Eps | AF34: Eps | AG34: Eps | AH34: Eps | AI34: Eps | AJ34: Eps | AK34: Eps | AL34: Eps | AM34: Eps | AN34: Eps | AO34: Eps | AP34: Eps
A35: 28 | C35: =Notes!T36 -> Cocoa | D35: a_coco | E35: Eps | F35: Eps | G35: Eps | H35: Eps | I35: Eps | J35: Eps | K35: Eps | L35: Eps | M35: Eps | N35: Eps | O35: Eps | P35: Eps | Q35: Eps | R35: Eps | S35: Eps | T35: Eps | U35: Eps | X35: =Notes!T36 -> Cocoa | Y35: a_coco | Z35: Eps | AA35: Eps | AB35: Eps | AC35: Eps | AD35: Eps | AE35: Eps | AF35: Eps | AG35: Eps | AH35: Eps | AI35: Eps | AJ35: Eps | AK35: Eps | AL35: Eps | AM35: Eps | AN35: Eps | AO35: Eps | AP35: Eps
A36: 29 | C36: =Notes!T37 -> Cut flowers | D36: a_flwr | E36: Eps | F36: Eps | G36: Eps | H36: Eps | I36: Eps | J36: Eps | K36: Eps | L36: Eps | M36: Eps | N36: Eps | O36: Eps | P36: Eps | Q36: Eps | R36: Eps | S36: Eps | T36: Eps | U36: Eps | X36: =Notes!T37 -> Cut flowers | Y36: a_flwr | Z36: Eps | AA36: Eps | AB36: Eps | AC36: Eps | AD36: Eps | AE36: Eps | AF36: Eps | AG36: Eps | AH36: Eps | AI36: Eps | AJ36: Eps | AK36: Eps | AL36: Eps | AM36: Eps | AN36: Eps | AO36: Eps | AP36: Eps
A37: 30 | C37: =Notes!T38 -> Rubber | D37: a_rubb | E37: Eps | F37: Eps | G37: Eps | H37: Eps | I37: Eps | J37: Eps | K37: Eps | L37: Eps | M37: Eps | N37: Eps | O37: Eps | P37: Eps | Q37: Eps | R37: Eps | S37: Eps | T37: Eps | U37: Eps | X37: =Notes!T38 -> Rubber | Y37: a_rubb | Z37: Eps | AA37: Eps | AB37: Eps | AC37: Eps | AD37: Eps | AE37: Eps | AF37: Eps | AG37: Eps | AH37: Eps | AI37: Eps | AJ37: Eps | AK37: Eps | AL37: Eps | AM37: Eps | AN37: Eps | AO37: Eps | AP37: Eps
A38: 31 | C38: =Notes!T39 -> Other crops | D38: a_ocrp | E38: 0.35974115 | F38: 3.0175269 | G38: Eps | H38: Eps | I38: Eps | J38: Eps | K38: Eps | L38: Eps | M38: Eps | N38: Eps | O38: Eps | P38: Eps | Q38: Eps | R38: Eps | S38: Eps | T38: Eps | U38: Eps | X38: =Notes!T39 -> Other crops | Y38: a_ocrp | Z38: 0.35974115 | AA38: -0.00096635797 | AB38: Eps | AC38: Eps | AD38: Eps | AE38: Eps | AF38: Eps | AG38: Eps | AH38: Eps | AI38: Eps | AJ38: Eps | AK38: Eps | AL38: Eps | AM38: Eps | AN38: Eps | AO38: Eps | AP38: Eps
A39: 32 | C39: =Notes!T40 -> Livestock | D39: aa_LIVE | E39: 1.7216311 | F39: 3.0498576 | G39: Eps | H39: Eps | I39: Eps | J39: Eps | K39: Eps | L39: Eps | M39: Eps | N39: Eps | O39: Eps | P39: Eps | Q39: Eps | R39: Eps | S39: Eps | T39: Eps | U39: Eps | X39: =Notes!T40 -> Livestock | Y39: aa_LIVE | Z39: 1.7216311 | AA39: -0.00084916733 | AB39: Eps | AC39: Eps | AD39: Eps | AE39: Eps | AF39: Eps | AG39: Eps | AH39: Eps | AI39: Eps | AJ39: Eps | AK39: Eps | AL39: Eps | AM39: Eps | AN39: Eps | AO39: Eps | AP39: Eps
A40: 33 | C40: =Notes!T41 -> Cattle | D40: a_catt | E40: 0.41802316 | F40: 3.0440343 | G40: Eps | H40: Eps | I40: Eps | J40: Eps | K40: Eps | L40: Eps | M40: Eps | N40: Eps | O40: Eps | P40: Eps | Q40: Eps | R40: Eps | S40: Eps | T40: Eps | U40: Eps | X40: =Notes!T41 -> Cattle | Y40: a_catt | Z40: 0.41802316 | AA40: -0.00037142931 | AB40: Eps | AC40: Eps | AD40: Eps | AE40: Eps | AF40: Eps | AG40: Eps | AH40: Eps | AI40: Eps | AJ40: Eps | AK40: Eps | AL40: Eps | AM40: Eps | AN40: Eps | AO40: Eps | AP40: Eps
A41: 34 | C41: =Notes!T42 -> Raw milk | D41: a_milk | E41: 0.260751 | F41: 3.0486321 | G41: Eps | H41: Eps | I41: Eps | J41: Eps | K41: Eps | L41: Eps | M41: Eps | N41: Eps | O41: Eps | P41: Eps | Q41: Eps | R41: Eps | S41: Eps | T41: Eps | U41: Eps | X41: =Notes!T42 -> Raw milk | Y41: a_milk | Z41: 0.260751 | AA41: -0.0001503068 | AB41: Eps | AC41: Eps | AD41: Eps | AE41: Eps | AF41: Eps | AG41: Eps | AH41: Eps | AI41: Eps | AJ41: Eps | AK41: Eps | AL41: Eps | AM41: Eps | AN41: Eps | AO41: Eps | AP41: Eps
A42: 35 | C42: =Notes!T43 -> Poultry | D42: a_poul | E42: 0.14655953 | F42: 3.0565558 | G42: Eps | H42: Eps | I42: Eps | J42: Eps | K42: Eps | L42: Eps | M42: Eps | N42: Eps | O42: Eps | P42: Eps | Q42: Eps | R42: Eps | S42: Eps | T42: Eps | U42: Eps | X42: =Notes!T43 -> Poultry | Y42: a_poul | Z42: 0.14655953 | AA42: -5.6243063e-06 | AB42: Eps | AC42: Eps | AD42: Eps | AE42: Eps | AF42: Eps | AG42: Eps | AH42: Eps | AI42: Eps | AJ42: Eps | AK42: Eps | AL42: Eps | AM42: Eps | AN42: Eps | AO42: Eps | AP42: Eps
A43: 36 | C43: =Notes!T44 -> Eggs | D43: a_eggs | E43: 0.15149365 | F43: 3.0619317 | G43: Eps | H43: Eps | I43: Eps | J43: Eps | K43: Eps | L43: Eps | M43: Eps | N43: Eps | O43: Eps | P43: Eps | Q43: Eps | R43: Eps | S43: Eps | T43: Eps | U43: Eps | X43: =Notes!T44 -> Eggs | Y43: a_eggs | Z43: 0.15149365 | AA43: 4.9510917e-05 | AB43: Eps | AC43: Eps | AD43: Eps | AE43: Eps | AF43: Eps | AG43: Eps | AH43: Eps | AI43: Eps | AJ43: Eps | AK43: Eps | AL43: Eps | AM43: Eps | AN43: Eps | AO43: Eps | AP43: Eps
A44: 37 | C44: =Notes!T45 -> Small ruminants | D44: a_smlr | E44: 0.52739008 | F44: 3.0543017 | G44: Eps | H44: Eps | I44: Eps | J44: Eps | K44: Eps | L44: Eps | M44: Eps | N44: Eps | O44: Eps | P44: Eps | Q44: Eps | R44: Eps | S44: Eps | T44: Eps | U44: Eps | X44: =Notes!T45 -> Small ruminants | Y44: a_smlr | Z44: 0.52739008 | AA44: -0.00010097894 | AB44: Eps | AC44: Eps | AD44: Eps | AE44: Eps | AF44: Eps | AG44: Eps | AH44: Eps | AI44: Eps | AJ44: Eps | AK44: Eps | AL44: Eps | AM44: Eps | AN44: Eps | AO44: Eps | AP44: Eps
A45: 38 | C45: =Notes!T46 -> Other livestock | D45: a_oliv | E45: 0.21741368 | F45: 3.0388047 | G45: Eps | H45: Eps | I45: Eps | J45: Eps | K45: Eps | L45: Eps | M45: Eps | N45: Eps | O45: Eps | P45: Eps | Q45: Eps | R45: Eps | S45: Eps | T45: Eps | U45: Eps | X45: =Notes!T46 -> Other livestock | Y45: a_oliv | Z45: 0.21741368 | AA45: -0.00027033889 | AB45: Eps | AC45: Eps | AD45: Eps | AE45: Eps | AF45: Eps | AG45: Eps | AH45: Eps | AI45: Eps | AJ45: Eps | AK45: Eps | AL45: Eps | AM45: Eps | AN45: Eps | AO45: Eps | AP45: Eps
A46: 39 | C46: =Notes!T47 -> Other agriculture | D46: aa_OAGR | E46: 4.030338 | F46: 3.0623444 | G46: Eps | H46: Eps | I46: Eps | J46: Eps | K46: Eps | L46: Eps | M46: Eps | N46: Eps | O46: Eps | P46: Eps | Q46: Eps | R46: Eps | S46: Eps | T46: Eps | U46: Eps | X46: =Notes!T47 -> Other agriculture | Y46: aa_OAGR | Z46: 4.030338 | AA46: 0.0014302033 | AB46: Eps | AC46: Eps | AD46: Eps | AE46: Eps | AF46: Eps | AG46: Eps | AH46: Eps | AI46: Eps | AJ46: Eps | AK46: Eps | AL46: Eps | AM46: Eps | AN46: Eps | AO46: Eps | AP46: Eps
A47: 40 | C47: =Notes!T48 -> Forestry | D47: a_fore | E47: 1.4548769 | F47: 3.0565301 | G47: Eps | H47: Eps | I47: Eps | J47: Eps | K47: Eps | L47: Eps | M47: Eps | N47: Eps | O47: Eps | P47: Eps | Q47: Eps | R47: Eps | S47: Eps | T47: Eps | U47: Eps | X47: =Notes!T48 -> Forestry | Y47: a_fore | Z47: 1.4548769 | AA47: -5.8371272e-05 | AB47: Eps | AC47: Eps | AD47: Eps | AE47: Eps | AF47: Eps | AG47: Eps | AH47: Eps | AI47: Eps | AJ47: Eps | AK47: Eps | AL47: Eps | AM47: Eps | AN47: Eps | AO47: Eps | AP47: Eps
A48: 41 | C48: =Notes!T49 -> Aquaculture | D48: a_aqua | E48: 1.4625278 | F48: 3.06281 | G48: Eps | H48: Eps | I48: Eps | J48: Eps | K48: Eps | L48: Eps | M48: Eps | N48: Eps | O48: Eps | P48: Eps | Q48: Eps | R48: Eps | S48: Eps | T48: Eps | U48: Eps | X48: =Notes!T49 -> Aquaculture | Y48: a_aqua | Z48: 1.4625278 | AA48: 0.00056525958 | AB48: Eps | AC48: Eps | AD48: Eps | AE48: Eps | AF48: Eps | AG48: Eps | AH48: Eps | AI48: Eps | AJ48: Eps | AK48: Eps | AL48: Eps | AM48: Eps | AN48: Eps | AO48: Eps | AP48: Eps
A49: 42 | C49: =Notes!T50 -> Capture fisheries | D49: a_fish | E49: 1.1129333 | F49: 3.0693305 | G49: Eps | H49: Eps | I49: Eps | J49: Eps | K49: Eps | L49: Eps | M49: Eps | N49: Eps | O49: Eps | P49: Eps | Q49: Eps | R49: Eps | S49: Eps | T49: Eps | U49: Eps | X49: =Notes!T50 -> Capture fisheries | Y49: a_fish | Z49: 1.1129333 | AA49: 0.000923315 | AB49: Eps | AC49: Eps | AD49: Eps | AE49: Eps | AF49: Eps | AG49: Eps | AH49: Eps | AI49: Eps | AJ49: Eps | AK49: Eps | AL49: Eps | AM49: Eps | AN49: Eps | AO49: Eps | AP49: Eps
... A52: 45 | C52: =Notes!T53 -> Coal and lignite | D52: a_coal | E52: 0.25682764 | F52: 3.0530382 | G52: Eps | H52: Eps | I52: Eps | J52: Eps | K52: Eps | L52: Eps | M52: Eps | N52: Eps | O52: Eps | P52: Eps | Q52: Eps | R52: Eps | S52: Eps | T52: Eps | U52: Eps | X52: =Notes!T53 -> Coal and lignite | Y52: a_coal | Z52: 0.25682764 | AA52: -7.121083e-05 | AB52: Eps | AC52: Eps | AD52: Eps | AE52: Eps | AF52: Eps | AG52: Eps | AH52: Eps | AI52: Eps | AJ52: Eps | AK52: Eps | AL52: Eps | AM52: Eps | AN52: Eps | AO52: Eps | AP52: Eps
A53: 46 | C53: =Notes!T54 -> Crude oil | D53: a_coil | E53: Eps | F53: Eps | G53: Eps | H53: Eps | I53: Eps | J53: Eps | K53: Eps | L53: Eps | M53: Eps | N53: Eps | O53: Eps | P53: Eps | Q53: Eps | R53: Eps | S53: Eps | T53: Eps | U53: Eps | X53: =Notes!T54 -> Crude oil | Y53: a_coil | Z53: Eps | AA53: Eps | AB53: Eps | AC53: Eps | AD53: Eps | AE53: Eps | AF53: Eps | AG53: Eps | AH53: Eps | AI53: Eps | AJ53: Eps | AK53: Eps | AL53: Eps | AM53: Eps | AN53: Eps | AO53: Eps | AP53: Eps
A54: 47 | C54: =Notes!T55 -> Natural gas | D54: a_ngas | E54: 0.27689266 | F54: 3.0457786 | G54: Eps | H54: Eps | I54: Eps | J54: Eps | K54: Eps | L54: Eps | M54: Eps | N54: Eps | O54: Eps | P54: Eps | Q54: Eps | R54: Eps | S54: Eps | T54: Eps | U54: Eps | X54: =Notes!T55 -> Natural gas | Y54: a_ngas | Z54: 0.27689266 | AA54: -0.00021324749 | AB54: Eps | AC54: Eps | AD54: Eps | AE54: Eps | AF54: Eps | AG54: Eps | AH54: Eps | AI54: Eps | AJ54: Eps | AK54: Eps | AL54: Eps | AM54: Eps | AN54: Eps | AO54: Eps | AP54: Eps
A55: 48 | C55: =Notes!T56 -> Other mining | D55: a_omin | E55: 0.99237211 | F55: 3.0479075 | G55: Eps | H55: Eps | I55: Eps | J55: Eps | K55: Eps | L55: Eps | M55: Eps | N55: Eps | O55: Eps | P55: Eps | Q55: Eps | R55: Eps | S55: Eps | T55: Eps | U55: Eps | X55: =Notes!T56 -> Other mining | Y55: a_omin | Z55: 0.99237211 | AA55: -0.00062086108 | AB55: Eps | AC55: Eps | AD55: Eps | AE55: Eps | AF55: Eps | AG55: Eps | AH55: Eps | AI55: Eps | AJ55: Eps | AK55: Eps | AL55: Eps | AM55: Eps | AN55: Eps | AO55: Eps | AP55: Eps
A56: 49 | C56: =Notes!T57 -> Manufacturing | D56: aa_MANU | E56: 22.639906 | F56: 3.0156675 | G56: Eps | H56: Eps | I56: Eps | J56: Eps | K56: Eps | L56: Eps | M56: Eps | N56: Eps | O56: Eps | P56: Eps | Q56: Eps | R56: Eps | S56: Eps | T56: Eps | U56: Eps | X56: =Notes!T57 -> Manufacturing | Y56: aa_MANU | Z56: 22.639906 | AA56: -0.063669284 | AB56: Eps | AC56: Eps | AD56: Eps | AE56: Eps | AF56: Eps | AG56: Eps | AH56: Eps | AI56: Eps | AJ56: Eps | AK56: Eps | AL56: Eps | AM56: Eps | AN56: Eps | AO56: Eps | AP56: Eps
A57: 50 | C57: =Notes!T58 -> Food processing | D57: aa_FOOD | E57: 3.0534493 | F57: 3.0280002 | G57: Eps | H57: Eps | I57: Eps | J57: Eps | K57: Eps | L57: Eps | M57: Eps | N57: Eps | O57: Eps | P57: Eps | Q57: Eps | R57: Eps | S57: Eps | T57: Eps | U57: Eps | X57: =Notes!T58 -> Food processing | Y57: aa_FOOD | Z57: 3.0534493 | AA57: -0.0060345159 | AB57: Eps | AC57: Eps | AD57: Eps | AE57: Eps | AF57: Eps | AG57: Eps | AH57: Eps | AI57: Eps | AJ57: Eps | AK57: Eps | AL57: Eps | AM57: Eps | AN57: Eps | AO57: Eps | AP57: Eps
A58: 51 | C58: =Notes!T59 -> Meat processing | D58: a_meat | E58: 0.62866702 | F58: 3.0288561 | G58: Eps | H58: Eps | I58: Eps | J58: Eps | K58: Eps | L58: Eps | M58: Eps | N58: Eps | O58: Eps | P58: Eps | Q58: Eps | R58: Eps | S58: Eps | T58: Eps | U58: Eps | X58: =Notes!T59 -> Meat processing | Y58: a_meat | Z58: 0.62866702 | AA58: -0.0012059441 | AB58: Eps | AC58: Eps | AD58: Eps | AE58: Eps | AF58: Eps | AG58: Eps | AH58: Eps | AI58: Eps | AJ58: Eps | AK58: Eps | AL58: Eps | AM58: Eps | AN58: Eps | AO58: Eps | AP58: Eps
A59: 52 | C59: =Notes!T60 -> Fish and seafood processing | D59: a_fsea | E59: 0.26916542 | F59: 3.022049 | G59: Eps | H59: Eps | I59: Eps | J59: Eps | K59: Eps | L59: Eps | M59: Eps | N59: Eps | O59: Eps | P59: Eps | Q59: Eps | R59: Eps | S59: Eps | T59: Eps | U59: Eps | X59: =Notes!T60 -> Fish and seafood processing | Y59: a_fsea | Z59: 0.26916542 | AA59: -0.00064055064 | AB59: Eps | AC59: Eps | AD59: Eps | AE59: Eps | AF59: Eps | AG59: Eps | AH59: Eps | AI59: Eps | AJ59: Eps | AK59: Eps | AL59: Eps | AM59: Eps | AN59: Eps | AO59: Eps | AP59: Eps
A60: 53 | C60: =Notes!T61 -> Dairy | D60: a_dair | E60: 0.093111444 | F60: 3.037773 | G60: Eps | H60: Eps | I60: Eps | J60: Eps | K60: Eps | L60: Eps | M60: Eps | N60: Eps | O60: Eps | P60: Eps | Q60: Eps | R60: Eps | S60: Eps | T60: Eps | U60: Eps | X60: =Notes!T61 -> Dairy | Y60: a_dair | Z60: 0.093111444 | AA60: -0.00012229548 | AB60: Eps | AC60: Eps | AD60: Eps | AE60: Eps | AF60: Eps | AG60: Eps | AH60: Eps | AI60: Eps | AJ60: Eps | AK60: Eps | AL60: Eps | AM60: Eps | AN60: Eps | AO60: Eps | AP60: Eps
A61: 54 | C61: =Notes!T62 -> Fruit and vegetable processing | D61: a_fveg | E61: 0.06208285 | F61: 2.9986176 | G61: Eps | H61: Eps | I61: Eps | J61: Eps | K61: Eps | L61: Eps | M61: Eps | N61: Eps | O61: Eps | P61: Eps | Q61: Eps | R61: Eps | S61: Eps | T61: Eps | U61: Eps | X61: =Notes!T62 -> Fruit and vegetable processing | Y61: a_fveg | Z61: 0.06208285 | AA61: -0.00024628134 | AB61: Eps | AC61: Eps | AD61: Eps | AE61: Eps | AF61: Eps | AG61: Eps | AH61: Eps | AI61: Eps | AJ61: Eps | AK61: Eps | AL61: Eps | AM61: Eps | AN61: Eps | AO61: Eps | AP61: Eps
A62: 55 | C62: =Notes!T63 -> Fats and oils | D62: a_foil | E62: 0.048781573 | F62: 3.0070271 | G62: Eps | H62: Eps | I62: Eps | J62: Eps | K62: Eps | L62: Eps | M62: Eps | N62: Eps | O62: Eps | P62: Eps | Q62: Eps | R62: Eps | S62: Eps | T62: Eps | U62: Eps | X62: =Notes!T63 -> Fats and oils | Y62: a_foil | Z62: 0.048781573 | AA62: -0.00016573939 | AB62: Eps | AC62: Eps | AD62: Eps | AE62: Eps | AF62: Eps | AG62: Eps | AH62: Eps | AI62: Eps | AJ62: Eps | AK62: Eps | AL62: Eps | AM62: Eps | AN62: Eps | AO62: Eps | AP62: Eps
A63: 56 | C63: =Notes!T64 -> Maize milling | D63: a_mmll | E63: 0.02423157 | F63: 3.037108 | G63: Eps | H63: Eps | I63: Eps | J63: Eps | K63: Eps | L63: Eps | M63: Eps | N63: Eps | O63: Eps | P63: Eps | Q63: Eps | R63: Eps | S63: Eps | T63: Eps | U63: Eps | X63: =Notes!T64 -> Maize milling | Y63: a_mmll | Z63: 0.02423157 | AA63: -3.2919786e-05 | AB63: Eps | AC63: Eps | AD63: Eps | AE63: Eps | AF63: Eps | AG63: Eps | AH63: Eps | AI63: Eps | AJ63: Eps | AK63: Eps | AL63: Eps | AM63: Eps | AN63: Eps | AO63: Eps | AP63: Eps
A64: 57 | C64: =Notes!T65 -> Sorghum and millet milling | D64: a_smll | E64: Eps | F64: Eps | G64: Eps | H64: Eps | I64: Eps | J64: Eps | K64: Eps | L64: Eps | M64: Eps | N64: Eps | O64: Eps | P64: Eps | Q64: Eps | R64: Eps | S64: Eps | T64: Eps | U64: Eps | X64: =Notes!T65 -> Sorghum and millet milling | Y64: a_smll | Z64: Eps | AA64: Eps | AB64: Eps | AC64: Eps | AD64: Eps | AE64: Eps | AF64: Eps | AG64: Eps | AH64: Eps | AI64: Eps | AJ64: Eps | AK64: Eps | AL64: Eps | AM64: Eps | AN64: Eps | AO64: Eps | AP64: Eps
A65: 58 | C65: =Notes!T66 -> Rice milling | D65: a_rmll | E65: Eps | F65: Eps | G65: Eps | H65: Eps | I65: Eps | J65: Eps | K65: Eps | L65: Eps | M65: Eps | N65: Eps | O65: Eps | P65: Eps | Q65: Eps | R65: Eps | S65: Eps | T65: Eps | U65: Eps | X65: =Notes!T66 -> Rice milling | Y65: a_rmll | Z65: Eps | AA65: Eps | AB65: Eps | AC65: Eps | AD65: Eps | AE65: Eps | AF65: Eps | AG65: Eps | AH65: Eps | AI65: Eps | AJ65: Eps | AK65: Eps | AL65: Eps | AM65: Eps | AN65: Eps | AO65: Eps | AP65: Eps
A66: 59 | C66: =Notes!T67 -> Rice milling - coarse | D66: a_rmlc | E66: 0.21543312 | F66: 3.0290844 | G66: Eps | H66: Eps | I66: Eps | J66: Eps | K66: Eps | L66: Eps | M66: Eps | N66: Eps | O66: Eps | P66: Eps | Q66: Eps | R66: Eps | S66: Eps | T66: Eps | U66: Eps | X66: =Notes!T67 -> Rice milling - coarse | Y66: a_rmlc | Z66: 0.21543312 | AA66: -0.00040992043 | AB66: Eps | AC66: Eps | AD66: Eps | AE66: Eps | AF66: Eps | AG66: Eps | AH66: Eps | AI66: Eps | AJ66: Eps | AK66: Eps | AL66: Eps | AM66: Eps | AN66: Eps | AO66: Eps | AP66: Eps
A67: 60 | C67: =Notes!T68 -> Rice milling - other | D67: a_rmlo | E67: 0.44943005 | F67: 3.0242183 | G67: Eps | H67: Eps | I67: Eps | J67: Eps | K67: Eps | L67: Eps | M67: Eps | N67: Eps | O67: Eps | P67: Eps | Q67: Eps | R67: Eps | S67: Eps | T67: Eps | U67: Eps | X67: =Notes!T68 -> Rice milling - other | Y67: a_rmlo | Z67: 0.44943005 | AA67: -0.0010034473 | AB67: Eps | AC67: Eps | AD67: Eps | AE67: Eps | AF67: Eps | AG67: Eps | AH67: Eps | AI67: Eps | AJ67: Eps | AK67: Eps | AL67: Eps | AM67: Eps | AN67: Eps | AO67: Eps | AP67: Eps
A68: 61 | C68: =Notes!T69 -> Wheat and barley milling | D68: a_wmll | E68: 0.035891905 | F68: 3.0525259 | G68: Eps | H68: Eps | I68: Eps | J68: Eps | K68: Eps | L68: Eps | M68: Eps | N68: Eps | O68: Eps | P68: Eps | Q68: Eps | R68: Eps | S68: Eps | T68: Eps | U68: Eps | X68: =Notes!T69 -> Wheat and barley milling | Y68: a_wmll | Z68: 0.035891905 | AA68: -1.1200338e-05 | AB68: Eps | AC68: Eps | AD68: Eps | AE68: Eps | AF68: Eps | AG68: Eps | AH68: Eps | AI68: Eps | AJ68: Eps | AK68: Eps | AL68: Eps | AM68: Eps | AN68: Eps | AO68: Eps | AP68: Eps
A69: 62 | C69: =Notes!T70 -> Other grain milling | D69: a_gmll | E69: 0.016337219 | F69: 3.0391387 | G69: Eps | H69: Eps | I69: Eps | J69: Eps | K69: Eps | L69: Eps | M69: Eps | N69: Eps | O69: Eps | P69: Eps | Q69: Eps | R69: Eps | S69: Eps | T69: Eps | U69: Eps | X69: =Notes!T70 -> Other grain milling | Y69: a_gmll | Z69: 0.016337219 | AA69: -1.9943958e-05 | AB69: Eps | AC69: Eps | AD69: Eps | AE69: Eps | AF69: Eps | AG69: Eps | AH69: Eps | AI69: Eps | AJ69: Eps | AK69: Eps | AL69: Eps | AM69: Eps | AN69: Eps | AO69: Eps | AP69: Eps
A70: 63 | C70: =Notes!T71 -> Sugar refining | D70: a_sref | E70: 0.10713988 | F70: 2.9969939 | G70: Eps | H70: Eps | I70: Eps | J70: Eps | K70: Eps | L70: Eps | M70: Eps | N70: Eps | O70: Eps | P70: Eps | Q70: Eps | R70: Eps | S70: Eps | T70: Eps | U70: Eps | X70: =Notes!T71 -> Sugar refining | Y70: a_sref | Z70: 0.10713988 | AA70: -0.00043679712 | AB70: Eps | AC70: Eps | AD70: Eps | AE70: Eps | AF70: Eps | AG70: Eps | AH70: Eps | AI70: Eps | AJ70: Eps | AK70: Eps | AL70: Eps | AM70: Eps | AN70: Eps | AO70: Eps | AP70: Eps
A71: 64 | C71: =Notes!T72 -> Coffee processing | D71: a_pcof | E71: Eps | F71: Eps | G71: Eps | H71: Eps | I71: Eps | J71: Eps | K71: Eps | L71: Eps | M71: Eps | N71: Eps | O71: Eps | P71: Eps | Q71: Eps | R71: Eps | S71: Eps | T71: Eps | U71: Eps | X71: =Notes!T72 -> Coffee processing | Y71: a_pcof | Z71: Eps | AA71: Eps | AB71: Eps | AC71: Eps | AD71: Eps | AE71: Eps | AF71: Eps | AG71: Eps | AH71: Eps | AI71: Eps | AJ71: Eps | AK71: Eps | AL71: Eps | AM71: Eps | AN71: Eps | AO71: Eps | AP71: Eps
A72: 65 | C72: =Notes!T73 -> Tea processing | D72: a_ptea | E72: Eps | F72: Eps | G72: Eps | H72: Eps | I72: Eps | J72: Eps | K72: Eps | L72: Eps | M72: Eps | N72: Eps | O72: Eps | P72: Eps | Q72: Eps | R72: Eps | S72: Eps | T72: Eps | U72: Eps | X72: =Notes!T73 -> Tea processing | Y72: a_ptea | Z72: Eps | AA72: Eps | AB72: Eps | AC72: Eps | AD72: Eps | AE72: Eps | AF72: Eps | AG72: Eps | AH72: Eps | AI72: Eps | AJ72: Eps | AK72: Eps | AL72: Eps | AM72: Eps | AN72: Eps | AO72: Eps | AP72: Eps
A73: 66 | C73: =Notes!T74 -> Other foods | D73: a_food | E73: 0.73680164 | F73: 3.0340948 | G73: Eps | H73: Eps | I73: Eps | J73: Eps | K73: Eps | L73: Eps | M73: Eps | N73: Eps | O73: Eps | P73: Eps | Q73: Eps | R73: Eps | S73: Eps | T73: Eps | U73: Eps | X73: =Notes!T74 -> Other foods | Y73: a_food | Z73: 0.73680164 | AA73: -0.0011515902 | AB73: Eps | AC73: Eps | AD73: Eps | AE73: Eps | AF73: Eps | AG73: Eps | AH73: Eps | AI73: Eps | AJ73: Eps | AK73: Eps | AL73: Eps | AM73: Eps | AN73: Eps | AO73: Eps | AP73: Eps
A74: 67 | C74: =Notes!T75 -> Animal feed | D74: a_feed | E74: 0.3663756 | F74: 3.0334809 | G74: Eps | H74: Eps | I74: Eps | J74: Eps | K74: Eps | L74: Eps | M74: Eps | N74: Eps | O74: Eps | P74: Eps | Q74: Eps | R74: Eps | S74: Eps | T74: Eps | U74: Eps | X74: =Notes!T75 -> Animal feed | Y74: a_feed | Z74: 0.3663756 | AA74: -0.0005878858 | AB74: Eps | AC74: Eps | AD74: Eps | AE74: Eps | AF74: Eps | AG74: Eps | AH74: Eps | AI74: Eps | AJ74: Eps | AK74: Eps | AL74: Eps | AM74: Eps | AN74: Eps | AO74: Eps | AP74: Eps
A75: 68 | C75: =Notes!T76 -> Beverages and tobacco | D75: aa_BEVE | E75: 0.46022999 | F75: 3.0457162 | G75: Eps | H75: Eps | I75: Eps | J75: Eps | K75: Eps | L75: Eps | M75: Eps | N75: Eps | O75: Eps | P75: Eps | Q75: Eps | R75: Eps | S75: Eps | T75: Eps | U75: Eps | X75: =Notes!T76 -> Beverages and tobacco | Y75: aa_BEVE | Z75: 0.46022999 | AA75: -0.00035639435 | AB75: Eps | AC75: Eps | AD75: Eps | AE75: Eps | AF75: Eps | AG75: Eps | AH75: Eps | AI75: Eps | AJ75: Eps | AK75: Eps | AL75: Eps | AM75: Eps | AN75: Eps | AO75: Eps | AP75: Eps
A76: 69 | C76: =Notes!T77 -> Beverages | D76: a_beve | E76: 0.34709197 | F76: 3.046913 | G76: Eps | H76: Eps | I76: Eps | J76: Eps | K76: Eps | L76: Eps | M76: Eps | N76: Eps | O76: Eps | P76: Eps | Q76: Eps | R76: Eps | S76: Eps | T76: Eps | U76: Eps | X76: =Notes!T77 -> Beverages | Y76: a_beve | Z76: 0.34709197 | AA76: -0.00024058371 | AB76: Eps | AC76: Eps | AD76: Eps | AE76: Eps | AF76: Eps | AG76: Eps | AH76: Eps | AI76: Eps | AJ76: Eps | AK76: Eps | AL76: Eps | AM76: Eps | AN76: Eps | AO76: Eps | AP76: Eps
A77: 70 | C77: =Notes!T78 -> Tobacco processing | D77: a_ptob | E77: 0.11313802 | F77: 3.0420439 | G77: Eps | H77: Eps | I77: Eps | J77: Eps | K77: Eps | L77: Eps | M77: Eps | N77: Eps | O77: Eps | P77: Eps | Q77: Eps | R77: Eps | S77: Eps | T77: Eps | U77: Eps | X77: =Notes!T78 -> Tobacco processing | Y77: a_ptob | Z77: 0.11313802 | AA77: -0.00011581063 | AB77: Eps | AC77: Eps | AD77: Eps | AE77: Eps | AF77: Eps | AG77: Eps | AH77: Eps | AI77: Eps | AJ77: Eps | AK77: Eps | AL77: Eps | AM77: Eps | AN77: Eps | AO77: Eps | AP77: Eps
A78: 71 | C78: =Notes!T79 -> Textiles, clothing and leather | D78: aa_TEXT | E78: 8.3175035 | F78: 2.9661727 | G78: Eps | H78: Eps | I78: Eps | J78: Eps | K78: Eps | L78: Eps | M78: Eps | N78: Eps | O78: Eps | P78: Eps | Q78: Eps | R78: Eps | S78: Eps | T78: Eps | U78: Eps | X78: =Notes!T79 -> Textiles, clothing and leather | Y78: aa_TEXT | Z78: 8.3175035 | AA78: -0.051245659 | AB78: Eps | AC78: Eps | AD78: Eps | AE78: Eps | AF78: Eps | AG78: Eps | AH78: Eps | AI78: Eps | AJ78: Eps | AK78: Eps | AL78: Eps | AM78: Eps | AN78: Eps | AO78: Eps | AP78: Eps
A79: 72 | C79: =Notes!T80 -> Jute baling | D79: a_bale | E79: 0.074761094 | F79: 2.9364396 | G79: Eps | H79: Eps | I79: Eps | J79: Eps | K79: Eps | L79: Eps | M79: Eps | N79: Eps | O79: Eps | P79: Eps | Q79: Eps | R79: Eps | S79: Eps | T79: Eps | U79: Eps | X79: =Notes!T80 -> Jute baling | Y79: a_bale | Z79: 0.074761094 | AA79: -0.00061067434 | AB79: Eps | AC79: Eps | AD79: Eps | AE79: Eps | AF79: Eps | AG79: Eps | AH79: Eps | AI79: Eps | AJ79: Eps | AK79: Eps | AL79: Eps | AM79: Eps | AN79: Eps | AO79: Eps | AP79: Eps
A80: 73 | C80: =Notes!T81 -> Jute fabrication | D80: a_pjut | E80: 0.049706312 | F80: 3.0340087 | G80: Eps | H80: Eps | I80: Eps | J80: Eps | K80: Eps | L80: Eps | M80: Eps | N80: Eps | O80: Eps | P80: Eps | Q80: Eps | R80: Eps | S80: Eps | T80: Eps | U80: Eps | X80: =Notes!T81 -> Jute fabrication | Y80: a_pjut | Z80: 0.049706312 | AA80: -7.7979067e-05 | AB80: Eps | AC80: Eps | AD80: Eps | AE80: Eps | AF80: Eps | AG80: Eps | AH80: Eps | AI80: Eps | AJ80: Eps | AK80: Eps | AL80: Eps | AM80: Eps | AN80: Eps | AO80: Eps | AP80: Eps
A81: 74 | C81: =Notes!T82 -> Cotton yarn | D81: a_yarn | E81: 0.12218708 | F81: 2.9471933 | G81: Eps | H81: Eps | I81: Eps | J81: Eps | K81: Eps | L81: Eps | M81: Eps | N81: Eps | O81: Eps | P81: Eps | Q81: Eps | R81: Eps | S81: Eps | T81: Eps | U81: Eps | X81: =Notes!T82 -> Cotton yarn | Y81: a_yarn | Z81: 0.12218708 | AA81: -0.0009094148 | AB81: Eps | AC81: Eps | AD81: Eps | AE81: Eps | AF81: Eps | AG81: Eps | AH81: Eps | AI81: Eps | AJ81: Eps | AK81: Eps | AL81: Eps | AM81: Eps | AN81: Eps | AO81: Eps | AP81: Eps
A82: 75 | C82: =Notes!T83 -> Textiles | D82: a_text | E82: 1.0233707 | F82: 2.9741302 | G82: Eps | H82: Eps | I82: Eps | J82: Eps | K82: Eps | L82: Eps | M82: Eps | N82: Eps | O82: Eps | P82: Eps | Q82: Eps | R82: Eps | S82: Eps | T82: Eps | U82: Eps | X82: =Notes!T83 -> Textiles | Y82: a_text | Z82: 1.0233707 | AA82: -0.0057548299 | AB82: Eps | AC82: Eps | AD82: Eps | AE82: Eps | AF82: Eps | AG82: Eps | AH82: Eps | AI82: Eps | AJ82: Eps | AK82: Eps | AL82: Eps | AM82: Eps | AN82: Eps | AO82: Eps | AP82: Eps
A83: 76 | C83: =Notes!T84 -> Clothing | D83: a_clth | E83: 6.1543027 | F83: 2.9556292 | G83: Eps | H83: Eps | I83: Eps | J83: Eps | K83: Eps | L83: Eps | M83: Eps | N83: Eps | O83: Eps | P83: Eps | Q83: Eps | R83: Eps | S83: Eps | T83: Eps | U83: Eps | X83: =Notes!T84 -> Clothing | Y83: a_clth | Z83: 6.1543027 | AA83: -0.042300551 | AB83: Eps | AC83: Eps | AD83: Eps | AE83: Eps | AF83: Eps | AG83: Eps | AH83: Eps | AI83: Eps | AJ83: Eps | AK83: Eps | AL83: Eps | AM83: Eps | AN83: Eps | AO83: Eps | AP83: Eps
A84: 77 | C84: =Notes!T85 -> Leather and footwear | D84: a_leat | E84: 0.89317564 | F84: 3.0308559 | G84: Eps | H84: Eps | I84: Eps | J84: Eps | K84: Eps | L84: Eps | M84: Eps | N84: Eps | O84: Eps | P84: Eps | Q84: Eps | R84: Eps | S84: Eps | T84: Eps | U84: Eps | X84: =Notes!T85 -> Leather and footwear | Y84: a_leat | Z84: 0.89317564 | AA84: -0.0015922099 | AB84: Eps | AC84: Eps | AD84: Eps | AE84: Eps | AF84: Eps | AG84: Eps | AH84: Eps | AI84: Eps | AJ84: Eps | AK84: Eps | AL84: Eps | AM84: Eps | AN84: Eps | AO84: Eps | AP84: Eps
... A119: 112 | C119: =Notes!T120 -> Other services | D119: a_osrv | E119: 5.2393999 | F119: 3.0539945 | G119: Eps | H119: Eps | I119: Eps | J119: Eps | K119: Eps | L119: Eps | M119: Eps | N119: Eps | O119: Eps | P119: Eps | Q119: Eps | R119: Eps | S119: Eps | T119: Eps | U119: Eps | X119: =Notes!T120 -> Other services | Y119: a_osrv | Z119: 5.2393999 | AA119: -0.0011124654 | AB119: Eps | AC119: Eps | AD119: Eps | AE119: Eps | AF119: Eps | AG119: Eps | AH119: Eps | AI119: Eps | AJ119: Eps | AK119: Eps | AL119: Eps | AM119: Eps | AN119: Eps | AO119: Eps | AP119: Eps
A120: 113 | C120: =Notes!T121 | D120: a_padm | X120: =Notes!T121 | Y120: a_padm
A121: 114 | C121: =Notes!T122 | D121: a_educ | X121: =Notes!T122 | Y121: a_educ
A122: 115 | C122: =Notes!T123 | D122: a_heal | X122: =Notes!T123 | Y122: a_heal
A123: 116 | C123: =Notes!T124 | D123: a_osrv | X123: =Notes!T124 | Y123: a_osrv
A124: 117 | C124: =Notes!T125 | X124: =Notes!T125
A125: 118 | C125: =Notes!T126 | X125: =Notes!T126
A126: 119 | C126: =Notes!T127 | X126: =Notes!T127
A127: 120 | C127: =Notes!T128 | X127: =Notes!T128
A128: 121 | C128: =Notes!T129 | X128: =Notes!T129
A129: 122 | C129: =Notes!T130 | X129: =Notes!T130
A130: 123 | C130: =Notes!T131 | X130: =Notes!T131
A131: 124 | C131: =Notes!T132 | X131: =Notes!T132
A132: 125 | C132: =Notes!T133 | X132: =Notes!T133
A133: 126 | C133: =Notes!T134 | X133: =Notes!T134
A134: 127 | C134: =Notes!T135 | X134: =Notes!T135
A135: 128 | C135: =Notes!T136 | X135: =Notes!T136
... A157: 150 | C157: =Notes!T158 | X157: =Notes!T158

Sheet Trade
A1: International Trade | M1: Tables: | N1: =C5 -> Export value (PE×QE)
N2: =X5 -> Import value (PM×QM)
C5: Export value (PE×QE) | X5: Import value (PM×QM)
C6: Init = Base year share of total exports | Base = Average annual growth rate (%) | Sims = Deviation in average annual growth rate from baseline (%-point) | X6: Init = Base year share of total imports | Base = Average annual growth rate (%) | Sims = Deviation in average annual growth rate from baseline (%-point)
E7: init | F7: base | G7: sim1 | H7: sim2 | I7: sim3 | J7: sim4 | K7: sim5 | L7: sim6 | M7: sim7 | N7: sim8 | O7: sim9 | P7: sim10 | Q7: sim11 | R7: sim12 | S7: sim13 | T7: sim14 | U7: sim15 | Z7: init | AA7: base | AB7: sim1 | AC7: sim2 | AD7: sim3 | AE7: sim4 | AF7: sim5 | AG7: sim6 | AH7: sim7 | AI7: sim8 | AJ7: sim9 | AK7: sim10 | AL7: sim11 | AM7: sim12 | AN7: sim13 | AO7: sim14 | AP7: sim15
A8: 1 | C8: =Notes!U9 -> All products | D8: aa_GDP | E8: 100 | F8: 2.9317433 | G8: Eps | H8: Eps | I8: Eps | J8: Eps | K8: Eps | L8: Eps | M8: Eps | N8: Eps | O8: Eps | P8: Eps | Q8: Eps | R8: Eps | S8: Eps | T8: Eps | U8: Eps | X8: =Notes!U9 -> All products | Y8: aa_GDP | Z8: 100 | AA8: 3.0511199 | AB8: Eps | AC8: Eps | AD8: Eps | AE8: Eps | AF8: Eps | AG8: Eps | AH8: Eps | AI8: Eps | AJ8: Eps | AK8: Eps | AL8: Eps | AM8: Eps | AN8: Eps | AO8: Eps | AP8: Eps
A9: 2 | C9: =Notes!U10 -> Agriculture | D9: aa_AGRI | E9: 1.2441389 | F9: 3.0120562 | G9: Eps | H9: Eps | I9: Eps | J9: Eps | K9: Eps | L9: Eps | M9: Eps | N9: Eps | O9: Eps | P9: Eps | Q9: Eps | R9: Eps | S9: Eps | T9: Eps | U9: Eps | X9: =Notes!U10 -> Agriculture | Y9: aa_AGRI | Z9: 12.301297 | AA9: 3.0614162 | AB9: Eps | AC9: Eps | AD9: Eps | AE9: Eps | AF9: Eps | AG9: Eps | AH9: Eps | AI9: Eps | AJ9: Eps | AK9: Eps | AL9: Eps | AM9: Eps | AN9: Eps | AO9: Eps | AP9: Eps
A10: 3 | C10: =Notes!U11 -> Crops | D10: aa_CROP | E10: 0.77696186 | F10: 2.9896993 | G10: Eps | H10: Eps | I10: Eps | J10: Eps | K10: Eps | L10: Eps | M10: Eps | N10: Eps | O10: Eps | P10: Eps | Q10: Eps | R10: Eps | S10: Eps | T10: Eps | U10: Eps | X10: =Notes!U11 -> Crops | Y10: aa_CROP | Z10: 12.276392 | AA10: 3.0614587 | AB10: Eps | AC10: Eps | AD10: Eps | AE10: Eps | AF10: Eps | AG10: Eps | AH10: Eps | AI10: Eps | AJ10: Eps | AK10: Eps | AL10: Eps | AM10: Eps | AN10: Eps | AO10: Eps | AP10: Eps
A11: 4 | C11: =Notes!U12 -> Maize | D11: a_maiz | E11: Eps | F11: Eps | G11: Eps | H11: Eps | I11: Eps | J11: Eps | K11: Eps | L11: Eps | M11: Eps | N11: Eps | O11: Eps | P11: Eps | Q11: Eps | R11: Eps | S11: Eps | T11: Eps | U11: Eps | X11: =Notes!U12 -> Maize | Y11: a_maiz | Z11: 0.91911364 | AA11: 3.0593879 | AB11: Eps | AC11: Eps | AD11: Eps | AE11: Eps | AF11: Eps | AG11: Eps | AH11: Eps | AI11: Eps | AJ11: Eps | AK11: Eps | AL11: Eps | AM11: Eps | AN11: Eps | AO11: Eps | AP11: Eps
A12: 5 | C12: =Notes!U13 -> Sorghum and millet | D12: a_sorg | E12: Eps | F12: Eps | G12: Eps | H12: Eps | I12: Eps | J12: Eps | K12: Eps | L12: Eps | M12: Eps | N12: Eps | O12: Eps | P12: Eps | Q12: Eps | R12: Eps | S12: Eps | T12: Eps | U12: Eps | X12: =Notes!U13 -> Sorghum and millet | Y12: a_sorg | Z12: Eps | AA12: Eps | AB12: Eps | AC12: Eps | AD12: Eps | AE12: Eps | AF12: Eps | AG12: Eps | AH12: Eps | AI12: Eps | AJ12: Eps | AK12: Eps | AL12: Eps | AM12: Eps | AN12: Eps | AO12: Eps | AP12: Eps
A13: 6 | C13: =Notes!U14 -> Rice paddy (Aman) | D13: a_aman | E13: Eps | F13: Eps | G13: Eps | H13: Eps | I13: Eps | J13: Eps | K13: Eps | L13: Eps | M13: Eps | N13: Eps | O13: Eps | P13: Eps | Q13: Eps | R13: Eps | S13: Eps | T13: Eps | U13: Eps | X13: =Notes!U14 -> Rice paddy (Aman) | Y13: a_aman | Z13: Eps | AA13: Eps | AB13: Eps | AC13: Eps | AD13: Eps | AE13: Eps | AF13: Eps | AG13: Eps | AH13: Eps | AI13: Eps | AJ13: Eps | AK13: Eps | AL13: Eps | AM13: Eps | AN13: Eps | AO13: Eps | AP13: Eps
A14: 7 | C14: =Notes!U15 -> Rice paddy (Boro) | D14: a_boro | E14: Eps | F14: Eps | G14: Eps | H14: Eps | I14: Eps | J14: Eps | K14: Eps | L14: Eps | M14: Eps | N14: Eps | O14: Eps | P14: Eps | Q14: Eps | R14: Eps | S14: Eps | T14: Eps | U14: Eps | X14: =Notes!U15 -> Rice paddy (Boro) | Y14: a_boro | Z14: Eps | AA14: Eps | AB14: Eps | AC14: Eps | AD14: Eps | AE14: Eps | AF14: Eps | AG14: Eps | AH14: Eps | AI14: Eps | AJ14: Eps | AK14: Eps | AL14: Eps | AM14: Eps | AN14: Eps | AO14: Eps | AP14: Eps
A15: 8 | C15: =Notes!U16 -> Wheat and barley | D15: a_whea | E15: Eps | F15: Eps | G15: Eps | H15: Eps | I15: Eps | J15: Eps | K15: Eps | L15: Eps | M15: Eps | N15: Eps | O15: Eps | P15: Eps | Q15: Eps | R15: Eps | S15: Eps | T15: Eps | U15: Eps | X15: =Notes!U16 -> Wheat and barley | Y15: a_whea | Z15: 4.078035 | AA15: 3.0469567 | AB15: Eps | AC15: Eps | AD15: Eps | AE15: Eps | AF15: Eps | AG15: Eps | AH15: Eps | AI15: Eps | AJ15: Eps | AK15: Eps | AL15: Eps | AM15: Eps | AN15: Eps | AO15: Eps | AP15: Eps
A16: 9 | C16: =Notes!U17 -> Other cereals | D16: a_ocer | E16: Eps | F16: Eps | G16: Eps | H16: Eps | I16: Eps | J16: Eps | K16: Eps | L16: Eps | M16: Eps | N16: Eps | O16: Eps | P16: Eps | Q16: Eps | R16: Eps | S16: Eps | T16: Eps | U16: Eps | X16: =Notes!U17 -> Other cereals | Y16: a_ocer | Z16: Eps | AA16: Eps | AB16: Eps | AC16: Eps | AD16: Eps | AE16: Eps | AF16: Eps | AG16: Eps | AH16: Eps | AI16: Eps | AJ16: Eps | AK16: Eps | AL16: Eps | AM16: Eps | AN16: Eps | AO16: Eps | AP16: Eps
A17: 10 | C17: =Notes!U18 -> Pulses | D17: a_puls | E17: Eps | F17: Eps | G17: Eps | H17: Eps | I17: Eps | J17: Eps | K17: Eps | L17: Eps | M17: Eps | N17: Eps | O17: Eps | P17: Eps | Q17: Eps | R17: Eps | S17: Eps | T17: Eps | U17: Eps | X17: =Notes!U18 -> Pulses | Y17: a_puls | Z17: 1.4135578 | AA17: 3.0719167 | AB17: Eps | AC17: Eps | AD17: Eps | AE17: Eps | AF17: Eps | AG17: Eps | AH17: Eps | AI17: Eps | AJ17: Eps | AK17: Eps | AL17: Eps | AM17: Eps | AN17: Eps | AO17: Eps | AP17: Eps
A18: 11 | C18: =Notes!U19 -> Groundnuts | D18: a_gnut | E18: Eps | F18: Eps | G18: Eps | H18: Eps | I18: Eps | J18: Eps | K18: Eps | L18: Eps | M18: Eps | N18: Eps | O18: Eps | P18: Eps | Q18: Eps | R18: Eps | S18: Eps | T18: Eps | U18: Eps | X18: =Notes!U19 -> Groundnuts | Y18: a_gnut | Z18: Eps | AA18: Eps | AB18: Eps | AC18: Eps | AD18: Eps | AE18: Eps | AF18: Eps | AG18: Eps | AH18: Eps | AI18: Eps | AJ18: Eps | AK18: Eps | AL18: Eps | AM18: Eps | AN18: Eps | AO18: Eps | AP18: Eps
A19: 12 | C19: =Notes!U20 -> Other oilseeds | D19: a_oils | E19: Eps | F19: Eps | G19: Eps | H19: Eps | I19: Eps | J19: Eps | K19: Eps | L19: Eps | M19: Eps | N19: Eps | O19: Eps | P19: Eps | Q19: Eps | R19: Eps | S19: Eps | T19: Eps | U19: Eps | X19: =Notes!U20 -> Other oilseeds | Y19: a_oils | Z19: 1.6621684 | AA19: 3.0938396 | AB19: Eps | AC19: Eps | AD19: Eps | AE19: Eps | AF19: Eps | AG19: Eps | AH19: Eps | AI19: Eps | AJ19: Eps | AK19: Eps | AL19: Eps | AM19: Eps | AN19: Eps | AO19: Eps | AP19: Eps
A20: 13 | C20: =Notes!U21 -> Cassava | D20: a_cass | E20: Eps | F20: Eps | G20: Eps | H20: Eps | I20: Eps | J20: Eps | K20: Eps | L20: Eps | M20: Eps | N20: Eps | O20: Eps | P20: Eps | Q20: Eps | R20: Eps | S20: Eps | T20: Eps | U20: Eps | X20: =Notes!U21 -> Cassava | Y20: a_cass | Z20: Eps | AA20: Eps | AB20: Eps | AC20: Eps | AD20: Eps | AE20: Eps | AF20: Eps | AG20: Eps | AH20: Eps | AI20: Eps | AJ20: Eps | AK20: Eps | AL20: Eps | AM20: Eps | AN20: Eps | AO20: Eps | AP20: Eps
A21: 14 | C21: =Notes!U22 -> Irish potatoes | D21: a_ipot | E21: Eps | F21: Eps | G21: Eps | H21: Eps | I21: Eps | J21: Eps | K21: Eps | L21: Eps | M21: Eps | N21: Eps | O21: Eps | P21: Eps | Q21: Eps | R21: Eps | S21: Eps | T21: Eps | U21: Eps | X21: =Notes!U22 -> Irish potatoes | Y21: a_ipot | Z21: Eps | AA21: Eps | AB21: Eps | AC21: Eps | AD21: Eps | AE21: Eps | AF21: Eps | AG21: Eps | AH21: Eps | AI21: Eps | AJ21: Eps | AK21: Eps | AL21: Eps | AM21: Eps | AN21: Eps | AO21: Eps | AP21: Eps
A22: 15 | C22: =Notes!U23 -> Sweet potatoes | D22: a_spot | E22: Eps | F22: Eps | G22: Eps | H22: Eps | I22: Eps | J22: Eps | K22: Eps | L22: Eps | M22: Eps | N22: Eps | O22: Eps | P22: Eps | Q22: Eps | R22: Eps | S22: Eps | T22: Eps | U22: Eps | X22: =Notes!U23 -> Sweet potatoes | Y22: a_spot | Z22: Eps | AA22: Eps | AB22: Eps | AC22: Eps | AD22: Eps | AE22: Eps | AF22: Eps | AG22: Eps | AH22: Eps | AI22: Eps | AJ22: Eps | AK22: Eps | AL22: Eps | AM22: Eps | AN22: Eps | AO22: Eps | AP22: Eps
A23: 16 | C23: =Notes!U24 -> Other roots | D23: a_root | E23: Eps | F23: Eps | G23: Eps | H23: Eps | I23: Eps | J23: Eps | K23: Eps | L23: Eps | M23: Eps | N23: Eps | O23: Eps | P23: Eps | Q23: Eps | R23: Eps | S23: Eps | T23: Eps | U23: Eps | X23: =Notes!U24 -> Other roots | Y23: a_root | Z23: Eps | AA23: Eps | AB23: Eps | AC23: Eps | AD23: Eps | AE23: Eps | AF23: Eps | AG23: Eps | AH23: Eps | AI23: Eps | AJ23: Eps | AK23: Eps | AL23: Eps | AM23: Eps | AN23: Eps | AO23: Eps | AP23: Eps
A24: 17 | C24: =Notes!U25 -> Leafy vegetables | D24: a_leaf | E24: Eps | F24: Eps | G24: Eps | H24: Eps | I24: Eps | J24: Eps | K24: Eps | L24: Eps | M24: Eps | N24: Eps | O24: Eps | P24: Eps | Q24: Eps | R24: Eps | S24: Eps | T24: Eps | U24: Eps | X24: =Notes!U25 -> Leafy vegetables | Y24: a_leaf | Z24: Eps | AA24: Eps | AB24: Eps | AC24: Eps | AD24: Eps | AE24: Eps | AF24: Eps | AG24: Eps | AH24: Eps | AI24: Eps | AJ24: Eps | AK24: Eps | AL24: Eps | AM24: Eps | AN24: Eps | AO24: Eps | AP24: Eps
A25: 18 | C25: =Notes!U26 -> Other vegetables | D25: a_vege | E25: Eps | F25: Eps | G25: Eps | H25: Eps | I25: Eps | J25: Eps | K25: Eps | L25: Eps | M25: Eps | N25: Eps | O25: Eps | P25: Eps | Q25: Eps | R25: Eps | S25: Eps | T25: Eps | U25: Eps | X25: =Notes!U26 -> Other vegetables | Y25: a_vege | Z25: 0.5461967 | AA25: 3.0892736 | AB25: Eps | AC25: Eps | AD25: Eps | AE25: Eps | AF25: Eps | AG25: Eps | AH25: Eps | AI25: Eps | AJ25: Eps | AK25: Eps | AL25: Eps | AM25: Eps | AN25: Eps | AO25: Eps | AP25: Eps
A26: 19 | C26: =Notes!U27 -> Sugarcane | D26: a_sugr | E26: Eps | F26: Eps | G26: Eps | H26: Eps | I26: Eps | J26: Eps | K26: Eps | L26: Eps | M26: Eps | N26: Eps | O26: Eps | P26: Eps | Q26: Eps | R26: Eps | S26: Eps | T26: Eps | U26: Eps | X26: =Notes!U27 -> Sugarcane | Y26: a_sugr | Z26: Eps | AA26: Eps | AB26: Eps | AC26: Eps | AD26: Eps | AE26: Eps | AF26: Eps | AG26: Eps | AH26: Eps | AI26: Eps | AJ26: Eps | AK26: Eps | AL26: Eps | AM26: Eps | AN26: Eps | AO26: Eps | AP26: Eps
A27: 20 | C27: =Notes!U28 -> Tobacco | D27: a_toba | E27: Eps | F27: Eps | G27: Eps | H27: Eps | I27: Eps | J27: Eps | K27: Eps | L27: Eps | M27: Eps | N27: Eps | O27: Eps | P27: Eps | Q27: Eps | R27: Eps | S27: Eps | T27: Eps | U27: Eps | X27: =Notes!U28 -> Tobacco | Y27: a_toba | Z27: Eps | AA27: Eps | AB27: Eps | AC27: Eps | AD27: Eps | AE27: Eps | AF27: Eps | AG27: Eps | AH27: Eps | AI27: Eps | AJ27: Eps | AK27: Eps | AL27: Eps | AM27: Eps | AN27: Eps | AO27: Eps | AP27: Eps
A28: 21 | C28: =Notes!U29 -> Cotton and fibres | D28: a_cott | E28: Eps | F28: Eps | G28: Eps | H28: Eps | I28: Eps | J28: Eps | K28: Eps | L28: Eps | M28: Eps | N28: Eps | O28: Eps | P28: Eps | Q28: Eps | R28: Eps | S28: Eps | T28: Eps | U28: Eps | X28: =Notes!U29 -> Cotton and fibres | Y28: a_cott | Z28: 1.5760217 | AA28: 3.0063607 | AB28: Eps | AC28: Eps | AD28: Eps | AE28: Eps | AF28: Eps | AG28: Eps | AH28: Eps | AI28: Eps | AJ28: Eps | AK28: Eps | AL28: Eps | AM28: Eps | AN28: Eps | AO28: Eps | AP28: Eps
A29: 22 | C29: =Notes!U30 -> Jute | D29: a_jute | E29: 0.77696186 | F29: 2.9896993 | G29: Eps | H29: Eps | I29: Eps | J29: Eps | K29: Eps | L29: Eps | M29: Eps | N29: Eps | O29: Eps | P29: Eps | Q29: Eps | R29: Eps | S29: Eps | T29: Eps | U29: Eps | X29: =Notes!U30 -> Jute | Y29: a_jute | Z29: 0.03672612 | AA29: 2.9880557 | AB29: Eps | AC29: Eps | AD29: Eps | AE29: Eps | AF29: Eps | AG29: Eps | AH29: Eps | AI29: Eps | AJ29: Eps | AK29: Eps | AL29: Eps | AM29: Eps | AN29: Eps | AO29: Eps | AP29: Eps
A30: 23 | C30: =Notes!U31 -> Nuts | D30: a_nuts | E30: Eps | F30: Eps | G30: Eps | H30: Eps | I30: Eps | J30: Eps | K30: Eps | L30: Eps | M30: Eps | N30: Eps | O30: Eps | P30: Eps | Q30: Eps | R30: Eps | S30: Eps | T30: Eps | U30: Eps | X30: =Notes!U31 -> Nuts | Y30: a_nuts | Z30: Eps | AA30: Eps | AB30: Eps | AC30: Eps | AD30: Eps | AE30: Eps | AF30: Eps | AG30: Eps | AH30: Eps | AI30: Eps | AJ30: Eps | AK30: Eps | AL30: Eps | AM30: Eps | AN30: Eps | AO30: Eps | AP30: Eps
A31: 24 | C31: =Notes!U32 -> Bananas and plantains | D31: a_bana | E31: Eps | F31: Eps | G31: Eps | H31: Eps | I31: Eps | J31: Eps | K31: Eps | L31: Eps | M31: Eps | N31: Eps | O31: Eps | P31: Eps | Q31: Eps | R31: Eps | S31: Eps | T31: Eps | U31: Eps | X31: =Notes!U32 -> Bananas and plantains | Y31: a_bana | Z31: Eps | AA31: Eps | AB31: Eps | AC31: Eps | AD31: Eps | AE31: Eps | AF31: Eps | AG31: Eps | AH31: Eps | AI31: Eps | AJ31: Eps | AK31: Eps | AL31: Eps | AM31: Eps | AN31: Eps | AO31: Eps | AP31: Eps
A32: 25 | C32: =Notes!U33 -> Other fruits | D32: a_frui | E32: Eps | F32: Eps | G32: Eps | H32: Eps | I32: Eps | J32: Eps | K32: Eps | L32: Eps | M32: Eps | N32: Eps | O32: Eps | P32: Eps | Q32: Eps | R32: Eps | S32: Eps | T32: Eps | U32: Eps | X32: =Notes!U33 -> Other fruits | Y32: a_frui | Z32: 1.4152583 | AA32: 3.0643325 | AB32: Eps | AC32: Eps | AD32: Eps | AE32: Eps | AF32: Eps | AG32: Eps | AH32: Eps | AI32: Eps | AJ32: Eps | AK32: Eps | AL32: Eps | AM32: Eps | AN32: Eps | AO32: Eps | AP32: Eps
A33: 26 | C33: =Notes!U34 -> Leaf tea | D33: a_teal | E33: Eps | F33: Eps | G33: Eps | H33: Eps | I33: Eps | J33: Eps | K33: Eps | L33: Eps | M33: Eps | N33: Eps | O33: Eps | P33: Eps | Q33: Eps | R33: Eps | S33: Eps | T33: Eps | U33: Eps | X33: =Notes!U34 -> Leaf tea | Y33: a_teal | Z33: Eps | AA33: Eps | AB33: Eps | AC33: Eps | AD33: Eps | AE33: Eps | AF33: Eps | AG33: Eps | AH33: Eps | AI33: Eps | AJ33: Eps | AK33: Eps | AL33: Eps | AM33: Eps | AN33: Eps | AO33: Eps | AP33: Eps
A34: 27 | C34: =Notes!U35 -> Coffee | D34: a_coff | E34: Eps | F34: Eps | G34: Eps | H34: Eps | I34: Eps | J34: Eps | K34: Eps | L34: Eps | M34: Eps | N34: Eps | O34: Eps | P34: Eps | Q34: Eps | R34: Eps | S34: Eps | T34: Eps | U34: Eps | X34: =Notes!U35 -> Coffee | Y34: a_coff | Z34: Eps | AA34: Eps | AB34: Eps | AC34: Eps | AD34: Eps | AE34: Eps | AF34: Eps | AG34: Eps | AH34: Eps | AI34: Eps | AJ34: Eps | AK34: Eps | AL34: Eps | AM34: Eps | AN34: Eps | AO34: Eps | AP34: Eps
A35: 28 | C35: =Notes!U36 -> Cocoa | D35: a_coco | E35: Eps | F35: Eps | G35: Eps | H35: Eps | I35: Eps | J35: Eps | K35: Eps | L35: Eps | M35: Eps | N35: Eps | O35: Eps | P35: Eps | Q35: Eps | R35: Eps | S35: Eps | T35: Eps | U35: Eps | X35: =Notes!U36 -> Cocoa | Y35: a_coco | Z35: Eps | AA35: Eps | AB35: Eps | AC35: Eps | AD35: Eps | AE35: Eps | AF35: Eps | AG35: Eps | AH35: Eps | AI35: Eps | AJ35: Eps | AK35: Eps | AL35: Eps | AM35: Eps | AN35: Eps | AO35: Eps | AP35: Eps
A36: 29 | C36: =Notes!U37 -> Cut flowers | D36: a_flwr | E36: Eps | F36: Eps | G36: Eps | H36: Eps | I36: Eps | J36: Eps | K36: Eps | L36: Eps | M36: Eps | N36: Eps | O36: Eps | P36: Eps | Q36: Eps | R36: Eps | S36: Eps | T36: Eps | U36: Eps | X36: =Notes!U37 -> Cut flowers | Y36: a_flwr | Z36: Eps | AA36: Eps | AB36: Eps | AC36: Eps | AD36: Eps | AE36: Eps | AF36: Eps | AG36: Eps | AH36: Eps | AI36: Eps | AJ36: Eps | AK36: Eps | AL36: Eps | AM36: Eps | AN36: Eps | AO36: Eps | AP36: Eps
A37: 30 | C37: =Notes!U38 -> Rubber | D37: a_rubb | E37: Eps | F37: Eps | G37: Eps | H37: Eps | I37: Eps | J37: Eps | K37: Eps | L37: Eps | M37: Eps | N37: Eps | O37: Eps | P37: Eps | Q37: Eps | R37: Eps | S37: Eps | T37: Eps | U37: Eps | X37: =Notes!U38 -> Rubber | Y37: a_rubb | Z37: Eps | AA37: Eps | AB37: Eps | AC37: Eps | AD37: Eps | AE37: Eps | AF37: Eps | AG37: Eps | AH37: Eps | AI37: Eps | AJ37: Eps | AK37: Eps | AL37: Eps | AM37: Eps | AN37: Eps | AO37: Eps | AP37: Eps
A38: 31 | C38: =Notes!U39 -> Other crops | D38: a_ocrp | E38: Eps | F38: Eps | G38: Eps | H38: Eps | I38: Eps | J38: Eps | K38: Eps | L38: Eps | M38: Eps | N38: Eps | O38: Eps | P38: Eps | Q38: Eps | R38: Eps | S38: Eps | T38: Eps | U38: Eps | X38: =Notes!U39 -> Other crops | Y38: a_ocrp | Z38: 0.62931444 | AA38: 3.1604421 | AB38: Eps | AC38: Eps | AD38: Eps | AE38: Eps | AF38: Eps | AG38: Eps | AH38: Eps | AI38: Eps | AJ38: Eps | AK38: Eps | AL38: Eps | AM38: Eps | AN38: Eps | AO38: Eps | AP38: Eps
A39: 32 | C39: =Notes!U40 -> Livestock | D39: aa_LIVE | E39: Eps | F39: Eps | G39: Eps | H39: Eps | I39: Eps | J39: Eps | K39: Eps | L39: Eps | M39: Eps | N39: Eps | O39: Eps | P39: Eps | Q39: Eps | R39: Eps | S39: Eps | T39: Eps | U39: Eps | X39: =Notes!U40 -> Livestock | Y39: aa_LIVE | Z39: 0.024905271 | AA39: 3.0404686 | AB39: Eps | AC39: Eps | AD39: Eps | AE39: Eps | AF39: Eps | AG39: Eps | AH39: Eps | AI39: Eps | AJ39: Eps | AK39: Eps | AL39: Eps | AM39: Eps | AN39: Eps | AO39: Eps | AP39: Eps
A40: 33 | C40: =Notes!U41 -> Cattle | D40: a_catt | E40: Eps | F40: Eps | G40: Eps | H40: Eps | I40: Eps | J40: Eps | K40: Eps | L40: Eps | M40: Eps | N40: Eps | O40: Eps | P40: Eps | Q40: Eps | R40: Eps | S40: Eps | T40: Eps | U40: Eps | X40: =Notes!U41 -> Cattle | Y40: a_catt | Z40: Eps | AA40: Eps | AB40: Eps | AC40: Eps | AD40: Eps | AE40: Eps | AF40: Eps | AG40: Eps | AH40: Eps | AI40: Eps | AJ40: Eps | AK40: Eps | AL40: Eps | AM40: Eps | AN40: Eps | AO40: Eps | AP40: Eps
A41: 34 | C41: =Notes!U42 -> Raw milk | D41: a_milk | E41: Eps | F41: Eps | G41: Eps | H41: Eps | I41: Eps | J41: Eps | K41: Eps | L41: Eps | M41: Eps | N41: Eps | O41: Eps | P41: Eps | Q41: Eps | R41: Eps | S41: Eps | T41: Eps | U41: Eps | X41: =Notes!U42 -> Raw milk | Y41: a_milk | Z41: Eps | AA41: Eps | AB41: Eps | AC41: Eps | AD41: Eps | AE41: Eps | AF41: Eps | AG41: Eps | AH41: Eps | AI41: Eps | AJ41: Eps | AK41: Eps | AL41: Eps | AM41: Eps | AN41: Eps | AO41: Eps | AP41: Eps
A42: 35 | C42: =Notes!U43 -> Poultry | D42: a_poul | E42: Eps | F42: Eps | G42: Eps | H42: Eps | I42: Eps | J42: Eps | K42: Eps | L42: Eps | M42: Eps | N42: Eps | O42: Eps | P42: Eps | Q42: Eps | R42: Eps | S42: Eps | T42: Eps | U42: Eps | X42: =Notes!U43 -> Poultry | Y42: a_poul | Z42: 0.024905271 | AA42: 3.0404686 | AB42: Eps | AC42: Eps | AD42: Eps | AE42: Eps | AF42: Eps | AG42: Eps | AH42: Eps | AI42: Eps | AJ42: Eps | AK42: Eps | AL42: Eps | AM42: Eps | AN42: Eps | AO42: Eps | AP42: Eps
A43: 36 | C43: =Notes!U44 -> Eggs | D43: a_eggs | E43: Eps | F43: Eps | G43: Eps | H43: Eps | I43: Eps | J43: Eps | K43: Eps | L43: Eps | M43: Eps | N43: Eps | O43: Eps | P43: Eps | Q43: Eps | R43: Eps | S43: Eps | T43: Eps | U43: Eps | X43: =Notes!U44 -> Eggs | Y43: a_eggs | Z43: Eps | AA43: Eps | AB43: Eps | AC43: Eps | AD43: Eps | AE43: Eps | AF43: Eps | AG43: Eps | AH43: Eps | AI43: Eps | AJ43: Eps | AK43: Eps | AL43: Eps | AM43: Eps | AN43: Eps | AO43: Eps | AP43: Eps
A44: 37 | C44: =Notes!U45 -> Small ruminants | D44: a_smlr | E44: Eps | F44: Eps | G44: Eps | H44: Eps | I44: Eps | J44: Eps | K44: Eps | L44: Eps | M44: Eps | N44: Eps | O44: Eps | P44: Eps | Q44: Eps | R44: Eps | S44: Eps | T44: Eps | U44: Eps | X44: =Notes!U45 -> Small ruminants | Y44: a_smlr | Z44: Eps | AA44: Eps | AB44: Eps | AC44: Eps | AD44: Eps | AE44: Eps | AF44: Eps | AG44: Eps | AH44: Eps | AI44: Eps | AJ44: Eps | AK44: Eps | AL44: Eps | AM44: Eps | AN44: Eps | AO44: Eps | AP44: Eps
A45: 38 | C45: =Notes!U46 -> Other livestock | D45: a_oliv | E45: Eps | F45: Eps | G45: Eps | H45: Eps | I45: Eps | J45: Eps | K45: Eps | L45: Eps | M45: Eps | N45: Eps | O45: Eps | P45: Eps | Q45: Eps | R45: Eps | S45: Eps | T45: Eps | U45: Eps | X45: =Notes!U46 -> Other livestock | Y45: a_oliv | Z45: Eps | AA45: Eps | AB45: Eps | AC45: Eps | AD45: Eps | AE45: Eps | AF45: Eps | AG45: Eps | AH45: Eps | AI45: Eps | AJ45: Eps | AK45: Eps | AL45: Eps | AM45: Eps | AN45: Eps | AO45: Eps | AP45: Eps
A46: 39 | C46: =Notes!U47 -> Other agriculture | D46: aa_OAGR | E46: 0.46717704 | F46: 3.0491736 | G46: Eps | H46: Eps | I46: Eps | J46: Eps | K46: Eps | L46: Eps | M46: Eps | N46: Eps | O46: Eps | P46: Eps | Q46: Eps | R46: Eps | S46: Eps | T46: Eps | U46: Eps | X46: =Notes!U47 -> Other agriculture | Y46: aa_OAGR | Z46: Eps | AA46: Eps | AB46: Eps | AC46: Eps | AD46: Eps | AE46: Eps | AF46: Eps | AG46: Eps | AH46: Eps | AI46: Eps | AJ46: Eps | AK46: Eps | AL46: Eps | AM46: Eps | AN46: Eps | AO46: Eps | AP46: Eps
A47: 40 | C47: =Notes!U48 -> Forestry | D47: a_fore | E47: Eps | F47: Eps | G47: Eps | H47: Eps | I47: Eps | J47: Eps | K47: Eps | L47: Eps | M47: Eps | N47: Eps | O47: Eps | P47: Eps | Q47: Eps | R47: Eps | S47: Eps | T47: Eps | U47: Eps | X47: =Notes!U48 -> Forestry | Y47: a_fore | Z47: Eps | AA47: Eps | AB47: Eps | AC47: Eps | AD47: Eps | AE47: Eps | AF47: Eps | AG47: Eps | AH47: Eps | AI47: Eps | AJ47: Eps | AK47: Eps | AL47: Eps | AM47: Eps | AN47: Eps | AO47: Eps | AP47: Eps
A48: 41 | C48: =Notes!U49 -> Aquaculture | D48: a_aqua | E48: Eps | F48: Eps | G48: Eps | H48: Eps | I48: Eps | J48: Eps | K48: Eps | L48: Eps | M48: Eps | N48: Eps | O48: Eps | P48: Eps | Q48: Eps | R48: Eps | S48: Eps | T48: Eps | U48: Eps | X48: =Notes!U49 -> Aquaculture | Y48: a_aqua | Z48: Eps | AA48: Eps | AB48: Eps | AC48: Eps | AD48: Eps | AE48: Eps | AF48: Eps | AG48: Eps | AH48: Eps | AI48: Eps | AJ48: Eps | AK48: Eps | AL48: Eps | AM48: Eps | AN48: Eps | AO48: Eps | AP48: Eps
A49: 42 | C49: =Notes!U50 -> Capture fisheries | D49: a_fish | E49: 0.46717704 | F49: 3.0491736 | G49: Eps | H49: Eps | I49: Eps | J49: Eps | K49: Eps | L49: Eps | M49: Eps | N49: Eps | O49: Eps | P49: Eps | Q49: Eps | R49: Eps | S49: Eps | T49: Eps | U49: Eps | X49: =Notes!U50 -> Capture fisheries | Y49: a_fish | Z49: Eps | AA49: Eps | AB49: Eps | AC49: Eps | AD49: Eps | AE49: Eps | AF49: Eps | AG49: Eps | AH49: Eps | AI49: Eps | AJ49: Eps | AK49: Eps | AL49: Eps | AM49: Eps | AN49: Eps | AO49: Eps | AP49: Eps
A50: 43 | C50: =Notes!U51 -> Industry | D50: aa_INDU | E50: 88.433346 | F50: 2.9188537 | G50: Eps | H50: Eps | I50: Eps | J50: Eps | K50: Eps | L50: Eps | M50: Eps | N50: Eps | O50: Eps | P50: Eps | Q50: Eps | R50: Eps | S50: Eps | T50: Eps | U50: Eps | X50: =Notes!U51 -> Industry | Y50: aa_INDU | Z50: 69.80239 | AA50: 3.0520537 | AB50: Eps | AC50: Eps | AD50: Eps | AE50: Eps | AF50: Eps | AG50: Eps | AH50: Eps | AI50: Eps | AJ50: Eps | AK50: Eps | AL50: Eps | AM50: Eps | AN50: Eps | AO50: Eps | AP50: Eps
A51: 44 | C51: =Notes!U52 -> Mining | D51: aa_MINE | E51: Eps | F51: Eps | G51: Eps | H51: Eps | I51: Eps | J51: Eps | K51: Eps | L51: Eps | M51: Eps | N51: Eps | O51: Eps | P51: Eps | Q51: Eps | R51: Eps | S51: Eps | T51: Eps | U51: Eps | X51: =Notes!U52 -> Mining | Y51: aa_MINE | Z51: 6.4842518 | AA51: 3.0402884 | AB51: Eps | AC51: Eps | AD51: Eps | AE51: Eps | AF51: Eps | AG51: Eps | AH51: Eps | AI51: Eps | AJ51: Eps | AK51: Eps | AL51: Eps | AM51: Eps | AN51: Eps | AO51: Eps | AP51: Eps
A52: 45 | C52: =Notes!U53 -> Coal and lignite | D52: a_coal | E52: Eps | F52: Eps | G52: Eps | H52: Eps | I52: Eps | J52: Eps | K52: Eps | L52: Eps | M52: Eps | N52: Eps | O52: Eps | P52: Eps | Q52: Eps | R52: Eps | S52: Eps | T52: Eps | U52: Eps | X52: =Notes!U53 -> Coal and lignite | Y52: a_coal | Z52: 2.3561124 | AA52: 3.0388091 | AB52: Eps | AC52: Eps | AD52: Eps | AE52: Eps | AF52: Eps | AG52: Eps | AH52: Eps | AI52: Eps | AJ52: Eps | AK52: Eps | AL52: Eps | AM52: Eps | AN52: Eps | AO52: Eps | AP52: Eps
A53: 46 | C53: =Notes!U54 -> Crude oil | D53: a_coil | E53: Eps | F53: Eps | G53: Eps | H53: Eps | I53: Eps | J53: Eps | K53: Eps | L53: Eps | M53: Eps | N53: Eps | O53: Eps | P53: Eps | Q53: Eps | R53: Eps | S53: Eps | T53: Eps | U53: Eps | X53: =Notes!U54 -> Crude oil | Y53: a_coil | Z53: 1.8786272 | AA53: 3.0564792 | AB53: Eps | AC53: Eps | AD53: Eps | AE53: Eps | AF53: Eps | AG53: Eps | AH53: Eps | AI53: Eps | AJ53: Eps | AK53: Eps | AL53: Eps | AM53: Eps | AN53: Eps | AO53: Eps | AP53: Eps
A54: 47 | C54: =Notes!U55 -> Natural gas | D54: a_ngas | E54: Eps | F54: Eps | G54: Eps | H54: Eps | I54: Eps | J54: Eps | K54: Eps | L54: Eps | M54: Eps | N54: Eps | O54: Eps | P54: Eps | Q54: Eps | R54: Eps | S54: Eps | T54: Eps | U54: Eps | X54: =Notes!U55 -> Natural gas | Y54: a_ngas | Z54: Eps | AA54: Eps | AB54: Eps | AC54: Eps | AD54: Eps | AE54: Eps | AF54: Eps | AG54: Eps | AH54: Eps | AI54: Eps | AJ54: Eps | AK54: Eps | AL54: Eps | AM54: Eps | AN54: Eps | AO54: Eps | AP54: Eps
A55: 48 | C55: =Notes!U56 -> Other mining | D55: a_omin | E55: Eps | F55: Eps | G55: Eps | H55: Eps | I55: Eps | J55: Eps | K55: Eps | L55: Eps | M55: Eps | N55: Eps | O55: Eps | P55: Eps | Q55: Eps | R55: Eps | S55: Eps | T55: Eps | U55: Eps | X55: =Notes!U56 -> Other mining | Y55: a_omin | Z55: 2.2495122 | AA55: 3.0283058 | AB55: Eps | AC55: Eps | AD55: Eps | AE55: Eps | AF55: Eps | AG55: Eps | AH55: Eps | AI55: Eps | AJ55: Eps | AK55: Eps | AL55: Eps | AM55: Eps | AN55: Eps | AO55: Eps | AP55: Eps
A56: 49 | C56: =Notes!U57 -> Manufacturing | D56: aa_MANU | E56: 88.433346 | F56: 2.9188537 | G56: Eps | H56: Eps | I56: Eps | J56: Eps | K56: Eps | L56: Eps | M56: Eps | N56: Eps | O56: Eps | P56: Eps | Q56: Eps | R56: Eps | S56: Eps | T56: Eps | U56: Eps | X56: =Notes!U57 -> Manufacturing | Y56: aa_MANU | Z56: 61.491338 | AA56: 3.0554449 | AB56: Eps | AC56: Eps | AD56: Eps | AE56: Eps | AF56: Eps | AG56: Eps | AH56: Eps | AI56: Eps | AJ56: Eps | AK56: Eps | AL56: Eps | AM56: Eps | AN56: Eps | AO56: Eps | AP56: Eps
A57: 50 | C57: =Notes!U58 -> Food processing | D57: aa_FOOD | E57: 0.29433304 | F57: 2.9496354 | G57: Eps | H57: Eps | I57: Eps | J57: Eps | K57: Eps | L57: Eps | M57: Eps | N57: Eps | O57: Eps | P57: Eps | Q57: Eps | R57: Eps | S57: Eps | T57: Eps | U57: Eps | X57: =Notes!U58 -> Food processing | Y57: aa_FOOD | Z57: 7.8145729 | AA57: 3.0872782 | AB57: Eps | AC57: Eps | AD57: Eps | AE57: Eps | AF57: Eps | AG57: Eps | AH57: Eps | AI57: Eps | AJ57: Eps | AK57: Eps | AL57: Eps | AM57: Eps | AN57: Eps | AO57: Eps | AP57: Eps
A58: 51 | C58: =Notes!U59 -> Meat processing | D58: a_meat | E58: Eps | F58: Eps | G58: Eps | H58: Eps | I58: Eps | J58: Eps | K58: Eps | L58: Eps | M58: Eps | N58: Eps | O58: Eps | P58: Eps | Q58: Eps | R58: Eps | S58: Eps | T58: Eps | U58: Eps | X58: =Notes!U59 -> Meat processing | Y58: a_meat | Z58: 0.099566892 | AA58: 3.1783459 | AB58: Eps | AC58: Eps | AD58: Eps | AE58: Eps | AF58: Eps | AG58: Eps | AH58: Eps | AI58: Eps | AJ58: Eps | AK58: Eps | AL58: Eps | AM58: Eps | AN58: Eps | AO58: Eps | AP58: Eps
A59: 52 | C59: =Notes!U60 -> Fish and seafood processing | D59: a_fsea | E59: 0.096800017 | F59: 2.8939932 | G59: Eps | H59: Eps | I59: Eps | J59: Eps | K59: Eps | L59: Eps | M59: Eps | N59: Eps | O59: Eps | P59: Eps | Q59: Eps | R59: Eps | S59: Eps | T59: Eps | U59: Eps | X59: =Notes!U60 -> Fish and seafood processing | Y59: a_fsea | Z59: 0.073775733 | AA59: 3.1468556 | AB59: Eps | AC59: Eps | AD59: Eps | AE59: Eps | AF59: Eps | AG59: Eps | AH59: Eps | AI59: Eps | AJ59: Eps | AK59: Eps | AL59: Eps | AM59: Eps | AN59: Eps | AO59: Eps | AP59: Eps
A60: 53 | C60: =Notes!U61 -> Dairy | D60: a_dair | E60: Eps | F60: Eps | G60: Eps | H60: Eps | I60: Eps | J60: Eps | K60: Eps | L60: Eps | M60: Eps | N60: Eps | O60: Eps | P60: Eps | Q60: Eps | R60: Eps | S60: Eps | T60: Eps | U60: Eps | X60: =Notes!U61 -> Dairy | Y60: a_dair | Z60: 0.49489297 | AA60: 3.078322 | AB60: Eps | AC60: Eps | AD60: Eps | AE60: Eps | AF60: Eps | AG60: Eps | AH60: Eps | AI60: Eps | AJ60: Eps | AK60: Eps | AL60: Eps | AM60: Eps | AN60: Eps | AO60: Eps | AP60: Eps
A61: 54 | C61: =Notes!U62 -> Fruit and vegetable processing | D61: a_fveg | E61: Eps | F61: Eps | G61: Eps | H61: Eps | I61: Eps | J61: Eps | K61: Eps | L61: Eps | M61: Eps | N61: Eps | O61: Eps | P61: Eps | Q61: Eps | R61: Eps | S61: Eps | T61: Eps | U61: Eps | X61: =Notes!U62 -> Fruit and vegetable processing | Y61: a_fveg | Z61: 0.28742832 | AA61: 3.1418979 | AB61: Eps | AC61: Eps | AD61: Eps | AE61: Eps | AF61: Eps | AG61: Eps | AH61: Eps | AI61: Eps | AJ61: Eps | AK61: Eps | AL61: Eps | AM61: Eps | AN61: Eps | AO61: Eps | AP61: Eps
A62: 55 | C62: =Notes!U63 -> Fats and oils | D62: a_foil | E62: Eps | F62: Eps | G62: Eps | H62: Eps | I62: Eps | J62: Eps | K62: Eps | L62: Eps | M62: Eps | N62: Eps | O62: Eps | P62: Eps | Q62: Eps | R62: Eps | S62: Eps | T62: Eps | U62: Eps | X62: =Notes!U63 -> Fats and oils | Y62: a_foil | Z62: 1.5910611 | AA62: 3.0697362 | AB62: Eps | AC62: Eps | AD62: Eps | AE62: Eps | AF62: Eps | AG62: Eps | AH62: Eps | AI62: Eps | AJ62: Eps | AK62: Eps | AL62: Eps | AM62: Eps | AN62: Eps | AO62: Eps | AP62: Eps
A63: 56 | C63: =Notes!U64 -> Maize milling | D63: a_mmll | E63: Eps | F63: Eps | G63: Eps | H63: Eps | I63: Eps | J63: Eps | K63: Eps | L63: Eps | M63: Eps | N63: Eps | O63: Eps | P63: Eps | Q63: Eps | R63: Eps | S63: Eps | T63: Eps | U63: Eps | X63: =Notes!U64 -> Maize milling | Y63: a_mmll | Z63: 0.0082596364 | AA63: 3.1131012 | AB63: Eps | AC63: Eps | AD63: Eps | AE63: Eps | AF63: Eps | AG63: Eps | AH63: Eps | AI63: Eps | AJ63: Eps | AK63: Eps | AL63: Eps | AM63: Eps | AN63: Eps | AO63: Eps | AP63: Eps
A64: 57 | C64: =Notes!U65 -> Sorghum and millet milling | D64: a_smll | E64: Eps | F64: Eps | G64: Eps | H64: Eps | I64: Eps | J64: Eps | K64: Eps | L64: Eps | M64: Eps | N64: Eps | O64: Eps | P64: Eps | Q64: Eps | R64: Eps | S64: Eps | T64: Eps | U64: Eps | X64: =Notes!U65 -> Sorghum and millet milling | Y64: a_smll | Z64: Eps | AA64: Eps | AB64: Eps | AC64: Eps | AD64: Eps | AE64: Eps | AF64: Eps | AG64: Eps | AH64: Eps | AI64: Eps | AJ64: Eps | AK64: Eps | AL64: Eps | AM64: Eps | AN64: Eps | AO64: Eps | AP64: Eps
A65: 58 | C65: =Notes!U66 -> Rice milling | D65: a_rmll | E65: Eps | F65: Eps | G65: Eps | H65: Eps | I65: Eps | J65: Eps | K65: Eps | L65: Eps | M65: Eps | N65: Eps | O65: Eps | P65: Eps | Q65: Eps | R65: Eps | S65: Eps | T65: Eps | U65: Eps | X65: =Notes!U66 -> Rice milling | Y65: a_rmll | Z65: Eps | AA65: Eps | AB65: Eps | AC65: Eps | AD65: Eps | AE65: Eps | AF65: Eps | AG65: Eps | AH65: Eps | AI65: Eps | AJ65: Eps | AK65: Eps | AL65: Eps | AM65: Eps | AN65: Eps | AO65: Eps | AP65: Eps
A66: 59 | C66: =Notes!U67 -> Rice milling - coarse | D66: a_rmlc | E66: Eps | F66: Eps | G66: Eps | H66: Eps | I66: Eps | J66: Eps | K66: Eps | L66: Eps | M66: Eps | N66: Eps | O66: Eps | P66: Eps | Q66: Eps | R66: Eps | S66: Eps | T66: Eps | U66: Eps | X66: =Notes!U67 -> Rice milling - coarse | Y66: a_rmlc | Z66: Eps | AA66: Eps | AB66: Eps | AC66: Eps | AD66: Eps | AE66: Eps | AF66: Eps | AG66: Eps | AH66: Eps | AI66: Eps | AJ66: Eps | AK66: Eps | AL66: Eps | AM66: Eps | AN66: Eps | AO66: Eps | AP66: Eps
A67: 60 | C67: =Notes!U68 -> Rice milling - other | D67: a_rmlo | E67: Eps | F67: Eps | G67: Eps | H67: Eps | I67: Eps | J67: Eps | K67: Eps | L67: Eps | M67: Eps | N67: Eps | O67: Eps | P67: Eps | Q67: Eps | R67: Eps | S67: Eps | T67: Eps | U67: Eps | X67: =Notes!U68 -> Rice milling - other | Y67: a_rmlo | Z67: Eps | AA67: Eps | AB67: Eps | AC67: Eps | AD67: Eps | AE67: Eps | AF67: Eps | AG67: Eps | AH67: Eps | AI67: Eps | AJ67: Eps | AK67: Eps | AL67: Eps | AM67: Eps | AN67: Eps | AO67: Eps | AP67: Eps
A68: 61 | C68: =Notes!U69 -> Wheat and barley milling | D68: a_wmll | E68: Eps | F68: Eps | G68: Eps | H68: Eps | I68: Eps | J68: Eps | K68: Eps | L68: Eps | M68: Eps | N68: Eps | O68: Eps | P68: Eps | Q68: Eps | R68: Eps | S68: Eps | T68: Eps | U68: Eps | X68: =Notes!U69 -> Wheat and barley milling | Y68: a_wmll | Z68: Eps | AA68: Eps | AB68: Eps | AC68: Eps | AD68: Eps | AE68: Eps | AF68: Eps | AG68: Eps | AH68: Eps | AI68: Eps | AJ68: Eps | AK68: Eps | AL68: Eps | AM68: Eps | AN68: Eps | AO68: Eps | AP68: Eps
A69: 62 | C69: =Notes!U70 -> Other grain milling | D69: a_gmll | E69: Eps | F69: Eps | G69: Eps | H69: Eps | I69: Eps | J69: Eps | K69: Eps | L69: Eps | M69: Eps | N69: Eps | O69: Eps | P69: Eps | Q69: Eps | R69: Eps | S69: Eps | T69: Eps | U69: Eps | X69: =Notes!U70 -> Other grain milling | Y69: a_gmll | Z69: Eps | AA69: Eps | AB69: Eps | AC69: Eps | AD69: Eps | AE69: Eps | AF69: Eps | AG69: Eps | AH69: Eps | AI69: Eps | AJ69: Eps | AK69: Eps | AL69: Eps | AM69: Eps | AN69: Eps | AO69: Eps | AP69: Eps
A70: 63 | C70: =Notes!U71 -> Sugar refining | D70: a_sref | E70: Eps | F70: Eps | G70: Eps | H70: Eps | I70: Eps | J70: Eps | K70: Eps | L70: Eps | M70: Eps | N70: Eps | O70: Eps | P70: Eps | Q70: Eps | R70: Eps | S70: Eps | T70: Eps | U70: Eps | X70: =Notes!U71 -> Sugar refining | Y70: a_sref | Z70: 3.8387756 | AA70: 3.0752503 | AB70: Eps | AC70: Eps | AD70: Eps | AE70: Eps | AF70: Eps | AG70: Eps | AH70: Eps | AI70: Eps | AJ70: Eps | AK70: Eps | AL70: Eps | AM70: Eps | AN70: Eps | AO70: Eps | AP70: Eps
A71: 64 | C71: =Notes!U72 -> Coffee processing | D71: a_pcof | E71: Eps | F71: Eps | G71: Eps | H71: Eps | I71: Eps | J71: Eps | K71: Eps | L71: Eps | M71: Eps | N71: Eps | O71: Eps | P71: Eps | Q71: Eps | R71: Eps | S71: Eps | T71: Eps | U71: Eps | X71: =Notes!U72 -> Coffee processing | Y71: a_pcof | Z71: Eps | AA71: Eps | AB71: Eps | AC71: Eps | AD71: Eps | AE71: Eps | AF71: Eps | AG71: Eps | AH71: Eps | AI71: Eps | AJ71: Eps | AK71: Eps | AL71: Eps | AM71: Eps | AN71: Eps | AO71: Eps | AP71: Eps
A72: 65 | C72: =Notes!U73 -> Tea processing | D72: a_ptea | E72: Eps | F72: Eps | G72: Eps | H72: Eps | I72: Eps | J72: Eps | K72: Eps | L72: Eps | M72: Eps | N72: Eps | O72: Eps | P72: Eps | Q72: Eps | R72: Eps | S72: Eps | T72: Eps | U72: Eps | X72: =Notes!U73 -> Tea processing | Y72: a_ptea | Z72: Eps | AA72: Eps | AB72: Eps | AC72: Eps | AD72: Eps | AE72: Eps | AF72: Eps | AG72: Eps | AH72: Eps | AI72: Eps | AJ72: Eps | AK72: Eps | AL72: Eps | AM72: Eps | AN72: Eps | AO72: Eps | AP72: Eps
A73: 66 | C73: =Notes!U74 -> Other foods | D73: a_food | E73: 0.19753302 | F73: 2.9768369 | G73: Eps | H73: Eps | I73: Eps | J73: Eps | K73: Eps | L73: Eps | M73: Eps | N73: Eps | O73: Eps | P73: Eps | Q73: Eps | R73: Eps | S73: Eps | T73: Eps | U73: Eps | X73: =Notes!U74 -> Other foods | Y73: a_food | Z73: 0.44041271 | AA73: 3.0876755 | AB73: Eps | AC73: Eps | AD73: Eps | AE73: Eps | AF73: Eps | AG73: Eps | AH73: Eps | AI73: Eps | AJ73: Eps | AK73: Eps | AL73: Eps | AM73: Eps | AN73: Eps | AO73: Eps | AP73: Eps
A74: 67 | C74: =Notes!U75 -> Animal feed | D74: a_feed | E74: Eps | F74: Eps | G74: Eps | H74: Eps | I74: Eps | J74: Eps | K74: Eps | L74: Eps | M74: Eps | N74: Eps | O74: Eps | P74: Eps | Q74: Eps | R74: Eps | S74: Eps | T74: Eps | U74: Eps | X74: =Notes!U75 -> Animal feed | Y74: a_feed | Z74: 0.98039994 | AA74: 3.1370598 | AB74: Eps | AC74: Eps | AD74: Eps | AE74: Eps | AF74: Eps | AG74: Eps | AH74: Eps | AI74: Eps | AJ74: Eps | AK74: Eps | AL74: Eps | AM74: Eps | AN74: Eps | AO74: Eps | AP74: Eps
A75: 68 | C75: =Notes!U76 -> Beverages and tobacco | D75: aa_BEVE | E75: 0.29742042 | F75: 3.0330047 | G75: Eps | H75: Eps | I75: Eps | J75: Eps | K75: Eps | L75: Eps | M75: Eps | N75: Eps | O75: Eps | P75: Eps | Q75: Eps | R75: Eps | S75: Eps | T75: Eps | U75: Eps | X75: =Notes!U76 -> Beverages and tobacco | Y75: aa_BEVE | Z75: 0.10189903 | AA75: 3.0603725 | AB75: Eps | AC75: Eps | AD75: Eps | AE75: Eps | AF75: Eps | AG75: Eps | AH75: Eps | AI75: Eps | AJ75: Eps | AK75: Eps | AL75: Eps | AM75: Eps | AN75: Eps | AO75: Eps | AP75: Eps
A76: 69 | C76: =Notes!U77 -> Beverages | D76: a_beve | E76: 0.29742042 | F76: 3.0330047 | G76: Eps | H76: Eps | I76: Eps | J76: Eps | K76: Eps | L76: Eps | M76: Eps | N76: Eps | O76: Eps | P76: Eps | Q76: Eps | R76: Eps | S76: Eps | T76: Eps | U76: Eps | X76: =Notes!U77 -> Beverages | Y76: a_beve | Z76: 0.10189903 | AA76: 3.0603725 | AB76: Eps | AC76: Eps | AD76: Eps | AE76: Eps | AF76: Eps | AG76: Eps | AH76: Eps | AI76: Eps | AJ76: Eps | AK76: Eps | AL76: Eps | AM76: Eps | AN76: Eps | AO76: Eps | AP76: Eps
A77: 70 | C77: =Notes!U78 -> Tobacco processing | D77: a_ptob | E77: Eps | F77: Eps | G77: Eps | H77: Eps | I77: Eps | J77: Eps | K77: Eps | L77: Eps | M77: Eps | N77: Eps | O77: Eps | P77: Eps | Q77: Eps | R77: Eps | S77: Eps | T77: Eps | U77: Eps | X77: =Notes!U78 -> Tobacco processing | Y77: a_ptob | Z77: Eps | AA77: Eps | AB77: Eps | AC77: Eps | AD77: Eps | AE77: Eps | AF77: Eps | AG77: Eps | AH77: Eps | AI77: Eps | AJ77: Eps | AK77: Eps | AL77: Eps | AM77: Eps | AN77: Eps | AO77: Eps | AP77: Eps
A78: 71 | C78: =Notes!U79 -> Textiles, clothing and leather | D78: aa_TEXT | E78: 71.024907 | F78: 2.8916765 | G78: Eps | H78: Eps | I78: Eps | J78: Eps | K78: Eps | L78: Eps | M78: Eps | N78: Eps | O78: Eps | P78: Eps | Q78: Eps | R78: Eps | S78: Eps | T78: Eps | U78: Eps | X78: =Notes!U79 -> Textiles, clothing and leather | Y78: aa_TEXT | Z78: 16.491268 | AA78: 3.0346113 | AB78: Eps | AC78: Eps | AD78: Eps | AE78: Eps | AF78: Eps | AG78: Eps | AH78: Eps | AI78: Eps | AJ78: Eps | AK78: Eps | AL78: Eps | AM78: Eps | AN78: Eps | AO78: Eps | AP78: Eps
A79: 72 | C79: =Notes!U80 -> Jute baling | D79: a_bale | E79: 1.5593012 | F79: 2.9353761 | G79: Eps | H79: Eps | I79: Eps | J79: Eps | K79: Eps | L79: Eps | M79: Eps | N79: Eps | O79: Eps | P79: Eps | Q79: Eps | R79: Eps | S79: Eps | T79: Eps | U79: Eps | X79: =Notes!U80 -> Jute baling | Y79: a_bale | Z79: Eps | AA79: Eps | AB79: Eps | AC79: Eps | AD79: Eps | AE79: Eps | AF79: Eps | AG79: Eps | AH79: Eps | AI79: Eps | AJ79: Eps | AK79: Eps | AL79: Eps | AM79: Eps | AN79: Eps | AO79: Eps | AP79: Eps
A80: 73 | C80: =Notes!U81 -> Jute fabrication | D80: a_pjut | E80: Eps | F80: Eps | G80: Eps | H80: Eps | I80: Eps | J80: Eps | K80: Eps | L80: Eps | M80: Eps | N80: Eps | O80: Eps | P80: Eps | Q80: Eps | R80: Eps | S80: Eps | T80: Eps | U80: Eps | X80: =Notes!U81 -> Jute fabrication | Y80: a_pjut | Z80: Eps | AA80: Eps | AB80: Eps | AC80: Eps | AD80: Eps | AE80: Eps | AF80: Eps | AG80: Eps | AH80: Eps | AI80: Eps | AJ80: Eps | AK80: Eps | AL80: Eps | AM80: Eps | AN80: Eps | AO80: Eps | AP80: Eps
A81: 74 | C81: =Notes!U82 -> Cotton yarn | D81: a_yarn | E81: Eps | F81: Eps | G81: Eps | H81: Eps | I81: Eps | J81: Eps | K81: Eps | L81: Eps | M81: Eps | N81: Eps | O81: Eps | P81: Eps | Q81: Eps | R81: Eps | S81: Eps | T81: Eps | U81: Eps | X81: =Notes!U82 -> Cotton yarn | Y81: a_yarn | Z81: 5.1185766 | AA81: 3.0158108 | AB81: Eps | AC81: Eps | AD81: Eps | AE81: Eps | AF81: Eps | AG81: Eps | AH81: Eps | AI81: Eps | AJ81: Eps | AK81: Eps | AL81: Eps | AM81: Eps | AN81: Eps | AO81: Eps | AP81: Eps
A82: 75 | C82: =Notes!U83 -> Textiles | D82: a_text | E82: 1.730149 | F82: 2.9069055 | G82: Eps | H82: Eps | I82: Eps | J82: Eps | K82: Eps | L82: Eps | M82: Eps | N82: Eps | O82: Eps | P82: Eps | Q82: Eps | R82: Eps | S82: Eps | T82: Eps | U82: Eps | X82: =Notes!U83 -> Textiles | Y82: a_text | Z82: 11.372691 | AA82: 3.0430663 | AB82: Eps | AC82: Eps | AD82: Eps | AE82: Eps | AF82: Eps | AG82: Eps | AH82: Eps | AI82: Eps | AJ82: Eps | AK82: Eps | AL82: Eps | AM82: Eps | AN82: Eps | AO82: Eps | AP82: Eps
A83: 76 | C83: =Notes!U84 -> Clothing | D83: a_clth | E83: 64.888063 | F83: 2.8892046 | G83: Eps | H83: Eps | I83: Eps | J83: Eps | K83: Eps | L83: Eps | M83: Eps | N83: Eps | O83: Eps | P83: Eps | Q83: Eps | R83: Eps | S83: Eps | T83: Eps | U83: Eps | X83: =Notes!U84 -> Clothing | Y83: a_clth | Z83: Eps | AA83: Eps | AB83: Eps | AC83: Eps | AD83: Eps | AE83: Eps | AF83: Eps | AG83: Eps | AH83: Eps | AI83: Eps | AJ83: Eps | AK83: Eps | AL83: Eps | AM83: Eps | AN83: Eps | AO83: Eps | AP83: Eps
A84: 77 | C84: =Notes!U85 -> Leather and footwear | D84: a_leat | E84: 2.8473931 | F84: 2.9147689 | G84: Eps | H84: Eps | I84: Eps | J84: Eps | K84: Eps | L84: Eps | M84: Eps | N84: Eps | O84: Eps | P84: Eps | Q84: Eps | R84: Eps | S84: Eps | T84: Eps | U84: Eps | X84: =Notes!U85 -> Leather and footwear | Y84: a_leat | Z84: Eps | AA84: Eps | AB84: Eps | AC84: Eps | AD84: Eps | AE84: Eps | AF84: Eps | AG84: Eps | AH84: Eps | AI84: Eps | AJ84: Eps | AK84: Eps | AL84: Eps | AM84: Eps | AN84: Eps | AO84: Eps | AP84: Eps
A85: 78 | C85: =Notes!U86 -> Wood and paper products | D85: aa_WOOD | E85: Eps | F85: Eps | G85: Eps | H85: Eps | I85: Eps | J85: Eps | K85: Eps | L85: Eps | M85: Eps | N85: Eps | O85: Eps | P85: Eps | Q85: Eps | R85: Eps | S85: Eps | T85: Eps | U85: Eps | X85: =Notes!U86 -> Wood and paper products | Y85: aa_WOOD | Z85: 1.2619011 | AA85: 3.07271 | AB85: Eps | AC85: Eps | AD85: Eps | AE85: Eps | AF85: Eps | AG85: Eps | AH85: Eps | AI85: Eps | AJ85: Eps | AK85: Eps | AL85: Eps | AM85: Eps | AN85: Eps | AO85: Eps | AP85: Eps
A86: 79 | C86: =Notes!U87 -> Wood products | D86: a_wood | E86: Eps | F86: Eps | G86: Eps | H86: Eps | I86: Eps | J86: Eps | K86: Eps | L86: Eps | M86: Eps | N86: Eps | O86: Eps | P86: Eps | Q86: Eps | R86: Eps | S86: Eps | T86: Eps | U86: Eps | X86: =Notes!U87 -> Wood products | Y86: a_wood | Z86: Eps | AA86: Eps | AB86: Eps | AC86: Eps | AD86: Eps | AE86: Eps | AF86: Eps | AG86: Eps | AH86: Eps | AI86: Eps | AJ86: Eps | AK86: Eps | AL86: Eps | AM86: Eps | AN86: Eps | AO86: Eps | AP86: Eps
A87: 80 | C87: =Notes!U88 -> Paper products and publishing | D87: a_papr | E87: Eps | F87: Eps | G87: Eps | H87: Eps | I87: Eps | J87: Eps | K87: Eps | L87: Eps | M87: Eps | N87: Eps | O87: Eps | P87: Eps | Q87: Eps | R87: Eps | S87: Eps | T87: Eps | U87: Eps | X87: =Notes!U88 -> Paper products and publishing | Y87: a_papr | Z87: 1.2619011 | AA87: 3.07271 | AB87: Eps | AC87: Eps | AD87: Eps | AE87: Eps | AF87: Eps | AG87: Eps | AH87: Eps | AI87: Eps | AJ87: Eps | AK87: Eps | AL87: Eps | AM87: Eps | AN87: Eps | AO87: Eps | AP87: Eps
A88: 81 | C88: =Notes!U89 -> Chemical products | D88: aa_CHEM | E88: Eps | F88: Eps | G88: Eps | H88: Eps | I88: Eps | J88: Eps | K88: Eps | L88: Eps | M88: Eps | N88: Eps | O88: Eps | P88: Eps | Q88: Eps | R88: Eps | S88: Eps | T88: Eps | U88: Eps | X88: =Notes!U89 -> Chemical products | Y88: aa_CHEM | Z88: 16.932777 | AA88: 3.0684264 | AB88: Eps | AC88: Eps | AD88: Eps | AE88: Eps | AF88: Eps | AG88: Eps | AH88: Eps | AI88: Eps | AJ88: Eps | AK88: Eps | AL88: Eps | AM88: Eps | AN88: Eps | AO88: Eps | AP88: Eps
A89: 82 | C89: =Notes!U90 -> Petroleum products | D89: a_petr | E89: Eps | F89: Eps | G89: Eps | H89: Eps | I89: Eps | J89: Eps | K89: Eps | L89: Eps | M89: Eps | N89: Eps | O89: Eps | P89: Eps | Q89: Eps | R89: Eps | S89: Eps | T89: Eps | U89: Eps | X89: =Notes!U90 -> Petroleum products | Y89: a_petr | Z89: 7.5921581 | AA89: 3.0521572 | AB89: Eps | AC89: Eps | AD89: Eps | AE89: Eps | AF89: Eps | AG89: Eps | AH89: Eps | AI89: Eps | AJ89: Eps | AK89: Eps | AL89: Eps | AM89: Eps | AN89: Eps | AO89: Eps | AP89: Eps
A90: 83 | C90: =Notes!U91 -> Fertilizers and herbicides | D90: a_fert | E90: Eps | F90: Eps | G90: Eps | H90: Eps | I90: Eps | J90: Eps | K90: Eps | L90: Eps | M90: Eps | N90: Eps | O90: Eps | P90: Eps | Q90: Eps | R90: Eps | S90: Eps | T90: Eps | U90: Eps | X90: =Notes!U91 -> Fertilizers and herbicides | Y90: a_fert | Z90: 2.061786 | AA90: 3.0205932 | AB90: Eps | AC90: Eps | AD90: Eps | AE90: Eps | AF90: Eps | AG90: Eps | AH90: Eps | AI90: Eps | AJ90: Eps | AK90: Eps | AL90: Eps | AM90: Eps | AN90: Eps | AO90: Eps | AP90: Eps
A91: 84 | C91: =Notes!U92 -> Other chemicals | D91: a_chem | E91: Eps | F91: Eps | G91: Eps | H91: Eps | I91: Eps | J91: Eps | K91: Eps | L91: Eps | M91: Eps | N91: Eps | O91: Eps | P91: Eps | Q91: Eps | R91: Eps | S91: Eps | T91: Eps | U91: Eps | X91: =Notes!U92 -> Other chemicals | Y91: a_chem | Z91: 7.2788333 | AA91: 3.0988912 | AB91: Eps | AC91: Eps | AD91: Eps | AE91: Eps | AF91: Eps | AG91: Eps | AH91: Eps | AI91: Eps | AJ91: Eps | AK91: Eps | AL91: Eps | AM91: Eps | AN91: Eps | AO91: Eps | AP91: Eps
A92: 85 | C92: =Notes!U93 -> Non-metal minerals | D92: a_nmet | E92: 12.370367 | F92: 3.041125 | G92: Eps | H92: Eps | I92: Eps | J92: Eps | K92: Eps | L92: Eps | M92: Eps | N92: Eps | O92: Eps | P92: Eps | Q92: Eps | R92: Eps | S92: Eps | T92: Eps | U92: Eps | X92: =Notes!U93 -> Non-metal minerals | Y92: a_nmet | Z92: Eps | AA92: Eps | AB92: Eps | AC92: Eps | AD92: Eps | AE92: Eps | AF92: Eps | AG92: Eps | AH92: Eps | AI92: Eps | AJ92: Eps | AK92: Eps | AL92: Eps | AM92: Eps | AN92: Eps | AO92: Eps | AP92: Eps
A93: 86 | C93: =Notes!U94 -> Metals and metal products | D93: a_metl | E93: 3.6918046 | F93: 2.9942971 | G93: Eps | H93: Eps | I93: Eps | J93: Eps | K93: Eps | L93: Eps | M93: Eps | N93: Eps | O93: Eps | P93: Eps | Q93: Eps | R93: Eps | S93: Eps | T93: Eps | U93: Eps | X93: =Notes!U94 -> Metals and metal products | Y93: a_metl | Z93: Eps | AA93: Eps | AB93: Eps | AC93: Eps | AD93: Eps | AE93: Eps | AF93: Eps | AG93: Eps | AH93: Eps | AI93: Eps | AJ93: Eps | AK93: Eps | AL93: Eps | AM93: Eps | AN93: Eps | AO93: Eps | AP93: Eps
A94: 87 | C94: =Notes!U95 -> Machinery and equipment | D94: aa_MACH | E94: Eps | F94: Eps | G94: Eps | H94: Eps | I94: Eps | J94: Eps | K94: Eps | L94: Eps | M94: Eps | N94: Eps | O94: Eps | P94: Eps | Q94: Eps | R94: Eps | S94: Eps | T94: Eps | U94: Eps | X94: =Notes!U95 -> Machinery and equipment | Y94: aa_MACH | Z94: 17.409899 | AA94: 3.0455042 | AB94: Eps | AC94: Eps | AD94: Eps | AE94: Eps | AF94: Eps | AG94: Eps | AH94: Eps | AI94: Eps | AJ94: Eps | AK94: Eps | AL94: Eps | AM94: Eps | AN94: Eps | AO94: Eps | AP94: Eps
A95: 88 | C95: =Notes!U96 -> Machinery and other equipment | D95: a_mach | E95: Eps | F95: Eps | G95: Eps | H95: Eps | I95: Eps | J95: Eps | K95: Eps | L95: Eps | M95: Eps | N95: Eps | O95: Eps | P95: Eps | Q95: Eps | R95: Eps | S95: Eps | T95: Eps | U95: Eps | X95: =Notes!U96 -> Machinery and other equipment | Y95: a_mach | Z95: 9.2688173 | AA95: 3.0402116 | AB95: Eps | AC95: Eps | AD95: Eps | AE95: Eps | AF95: Eps | AG95: Eps | AH95: Eps | AI95: Eps | AJ95: Eps | AK95: Eps | AL95: Eps | AM95: Eps | AN95: Eps | AO95: Eps | AP95: Eps
A96: 89 | C96: =Notes!U97 -> Electrical equipment | D96: a_equi | E96: Eps | F96: Eps | G96: Eps | H96: Eps | I96: Eps | J96: Eps | K96: Eps | L96: Eps | M96: Eps | N96: Eps | O96: Eps | P96: Eps | Q96: Eps | R96: Eps | S96: Eps | T96: Eps | U96: Eps | X96: =Notes!U97 -> Electrical equipment | Y96: a_equi | Z96: 5.4677448 | AA96: 3.0614443 | AB96: Eps | AC96: Eps | AD96: Eps | AE96: Eps | AF96: Eps | AG96: Eps | AH96: Eps | AI96: Eps | AJ96: Eps | AK96: Eps | AL96: Eps | AM96: Eps | AN96: Eps | AO96: Eps | AP96: Eps
A97: 90 | C97: =Notes!U98 -> Vehicles and transport equipment | D97: a_vehi | E97: Eps | F97: Eps | G97: Eps | H97: Eps | I97: Eps | J97: Eps | K97: Eps | L97: Eps | M97: Eps | N97: Eps | O97: Eps | P97: Eps | Q97: Eps | R97: Eps | S97: Eps | T97: Eps | U97: Eps | X97: =Notes!U98 -> Vehicles and transport equipment | Y97: a_vehi | Z97: 2.6733367 | AA97: 3.0312285 | AB97: Eps | AC97: Eps | AD97: Eps | AE97: Eps | AF97: Eps | AG97: Eps | AH97: Eps | AI97: Eps | AJ97: Eps | AK97: Eps | AL97: Eps | AM97: Eps | AN97: Eps | AO97: Eps | AP97: Eps
A98: 91 | C98: =Notes!U99 -> Other manufacturing | D98: a_oman | E98: 0.75451456 | F98: 3.0357732 | G98: Eps | H98: Eps | I98: Eps | J98: Eps | K98: Eps | L98: Eps | M98: Eps | N98: Eps | O98: Eps | P98: Eps | Q98: Eps | R98: Eps | S98: Eps | T98: Eps | U98: Eps | X98: =Notes!U99 -> Other manufacturing | Y98: a_oman | Z98: 1.4790209 | AA98: 3.0724688 | AB98: Eps | AC98: Eps | AD98: Eps | AE98: Eps | AF98: Eps | AG98: Eps | AH98: Eps | AI98: Eps | AJ98: Eps | AK98: Eps | AL98: Eps | AM98: Eps | AN98: Eps | AO98: Eps | AP98: Eps
A99: 92 | C99: =Notes!U100 -> Utilities | D99: aa_UTIL | E99: Eps | F99: Eps | G99: Eps | H99: Eps | I99: Eps | J99: Eps | K99: Eps | L99: Eps | M99: Eps | N99: Eps | O99: Eps | P99: Eps | Q99: Eps | R99: Eps | S99: Eps | T99: Eps | U99: Eps | X99: =Notes!U100 -> Utilities | Y99: aa_UTIL | Z99: 1.8268 | AA99: 2.9794844 | AB99: Eps | AC99: Eps | AD99: Eps | AE99: Eps | AF99: Eps | AG99: Eps | AH99: Eps | AI99: Eps | AJ99: Eps | AK99: Eps | AL99: Eps | AM99: Eps | AN99: Eps | AO99: Eps | AP99: Eps
A100: 93 | C100: =Notes!U101 -> Electricity, gas and steam | D100: a_elec | E100: Eps | F100: Eps | G100: Eps | H100: Eps | I100: Eps | J100: Eps | K100: Eps | L100: Eps | M100: Eps | N100: Eps | O100: Eps | P100: Eps | Q100: Eps | R100: Eps | S100: Eps | T100: Eps | U100: Eps | X100: =Notes!U101 -> Electricity, gas and steam | Y100: a_elec | Z100: 1.8268 | AA100: 2.9794844 | AB100: Eps | AC100: Eps | AD100: Eps | AE100: Eps | AF100: Eps | AG100: Eps | AH100: Eps | AI100: Eps | AJ100: Eps | AK100: Eps | AL100: Eps | AM100: Eps | AN100: Eps | AO100: Eps | AP100: Eps
A101: 94 | C101: =Notes!U102 -> Water supply and sewage | D101: a_watr | E101: Eps | F101: Eps | G101: Eps | H101: Eps | I101: Eps | J101: Eps | K101: Eps | L101: Eps | M101: Eps | N101: Eps | O101: Eps | P101: Eps | Q101: Eps | R101: Eps | S101: Eps | T101: Eps | U101: Eps | X101: =Notes!U102 -> Water supply and sewage | Y101: a_watr | Z101: Eps | AA101: Eps | AB101: Eps | AC101: Eps | AD101: Eps | AE101: Eps | AF101: Eps | AG101: Eps | AH101: Eps | AI101: Eps | AJ101: Eps | AK101: Eps | AL101: Eps | AM101: Eps | AN101: Eps | AO101: Eps | AP101: Eps
A102: 95 | C102: =Notes!U103 -> Construction | D102: a_cons | E102: Eps | F102: Eps | G102: Eps | H102: Eps | I102: Eps | J102: Eps | K102: Eps | L102: Eps | M102: Eps | N102: Eps | O102: Eps | P102: Eps | Q102: Eps | R102: Eps | S102: Eps | T102: Eps | U102: Eps | X102: =Notes!U103 -> Construction | Y102: a_cons | Z102: Eps | AA102: Eps | AB102: Eps | AC102: Eps | AD102: Eps | AE102: Eps | AF102: Eps | AG102: Eps | AH102: Eps | AI102: Eps | AJ102: Eps | AK102: Eps | AL102: Eps | AM102: Eps | AN102: Eps | AO102: Eps | AP102: Eps
...

Sheet Prices
A1: Price Indices | M1: Tables: | N1: =C5 -> Average output price (PX) | R1: =BN5 -> Import price incl. transaction costs (PM)
N2: =X5 -> Composite commodity price (PQ) | R2: =CI5 -> World export price excl. transaction costs (pwe)
N3: =AS5 -> Export price incl. transaction costs (PE) | R3: =DD5 -> World import price excl. transaction costs (pwm)
C5: Average output price (PX) | X5: Composite commodity price (PQ) | AS5: Export price incl. transaction costs (PE) | BN5: Import price incl. transaction costs (PM) | CI5: World export price excl. transaction costs (pwe) | DD5: World import price excl. transaction costs (pwm)
C6: Init = Base year price index weight | Base = Average annual growth rate (%) | Sims = Deviation in average annual growth rate from baseline (%-point) | X6: Init = Base year price index weight | Base = Average annual growth rate (%) | Sims = Deviation in average annual growth rate from baseline (%-point) | AS6: Init = Base year price index weight | Base = Average annual growth rate (%) | Sims = Deviation in average annual growth rate from baseline (%-point) | BN6: Init = Base year price index weight | Base = Average annual growth rate (%) | Sims = Deviation in average annual growth rate from baseline (%-point) | CI6: Init = Base year price index weight | Base = Average annual growth rate (%) | Sims = Deviation in average annual growth rate from baseline (%-point) | DD6: Init = Base year price index weight | Base = Average annual growth rate (%) | Sims = Deviation in average annual growth rate from baseline (%-point)
E7: init | F7: base | G7: sim1 | H7: sim2 | I7: sim3 | J7: sim4 | K7: sim5 | L7: sim6 | M7: sim7 | N7: sim8 | O7: sim9 | P7: sim10 | Q7: sim11 | R7: sim12 | S7: sim13 | T7: sim14 | U7: sim15 | Z7: init | AA7: base | AB7: sim1 | AC7: sim2 | AD7: sim3 | AE7: sim4 | AF7: sim5 | AG7: sim6 | AH7: sim7 | AI7: sim8 | AJ7: sim9 | AK7: sim10 | AL7: sim11 | AM7: sim12 | AN7: sim13 | AO7: sim14 | AP7: sim15 | AU7: init | AV7: base | AW7: sim1 | AX7: sim2 | AY7: sim3 | AZ7: sim4 | BA7: sim5 | BB7: sim6 | BC7: sim7 | BD7: sim8 | BE7: sim9 | BF7: sim10 | BG7: sim11 | BH7: sim12 | BI7: sim13 | BJ7: sim14 | BK7: sim15 | BP7: init | BQ7: base | BR7: sim1 | BS7: sim2 | BT7: sim3 | BU7: sim4 | BV7: sim5 | BW7: sim6 | BX7: sim7 | BY7: sim8 | BZ7: sim9 | CA7: sim10 | CB7: sim11 | CC7: sim12 | CD7: sim13 | CE7: sim14 | CF7: sim15 | CK7: init | CL7: base | CM7: sim1 | CN7: sim2 | CO7: sim3 | CP7: sim4 | CQ7: sim5 | CR7: sim6 | CS7: sim7 | CT7: sim8 | CU7: sim9 | CV7: sim10 | CW7: sim11 | CX7: sim12 | CY7: sim13 | CZ7: sim14 | DA7: sim15 | DF7: init | DG7: base | DH7: sim1 | DI7: sim2 | DJ7: sim3 | DK7: sim4 | DL7: sim5 | DM7: sim6 | DN7: sim7 | DO7: sim8 | DP7: sim9 | DQ7: sim10 | DR7: sim11 | DS7: sim12 | DT7: sim13 | DU7: sim14 | DV7: sim15
A8: 1 | C8: =Notes!U9 -> All products | D8: aa_GDP | E8: 1 | F8: -0.00088620053 | G8: Eps | H8: Eps | I8: Eps | J8: Eps | K8: Eps | L8: Eps | M8: Eps | N8: Eps | O8: Eps | P8: Eps | Q8: Eps | R8: Eps | S8: Eps | T8: Eps | U8: Eps | X8: =Notes!U9 -> All products | Y8: aa_GDP | Z8: 1.12887 | AA8: -0.0036308185 | AB8: Eps | AC8: Eps | AD8: Eps | AE8: Eps | AF8: Eps | AG8: Eps | AH8: Eps | AI8: Eps | AJ8: Eps | AK8: Eps | AL8: Eps | AM8: Eps | AN8: Eps | AO8: Eps | AP8: Eps | AS8: =Notes!U9 -> All products | AT8: aa_GDP | AU8: 1 | AV8: -0.018530529 | AW8: Eps | AX8: Eps | AY8: Eps | AZ8: Eps | BA8: Eps | BB8: Eps | BC8: Eps | BD8: Eps | BE8: Eps | BF8: Eps | BG8: Eps | BH8: Eps | BI8: Eps | BJ8: Eps | BK8: Eps | BN8: =Notes!U9 -> All products | BO8: aa_GDP | BP8: 1.1538765 | BQ8: -0.017447985 | BR8: Eps | BS8: Eps | BT8: Eps | BU8: Eps | BV8: Eps | BW8: Eps | BX8: Eps | BY8: Eps | BZ8: Eps | CA8: Eps | CB8: Eps | CC8: Eps | CD8: Eps | CE8: Eps | CF8: Eps | CI8: =Notes!U9 -> All products | CJ8: aa_GDP | CK8: 1.1321328 | CL8: Eps | CM8: Eps | CN8: Eps | CO8: Eps | CP8: Eps | CQ8: Eps | CR8: Eps | CS8: Eps | CT8: Eps | CU8: Eps | CV8: Eps | CW8: Eps | CX8: Eps | CY8: Eps | CZ8: Eps | DA8: Eps | DD8: =Notes!U9 -> All products | DE8: aa_GDP | DF8: 0.96639836 | DG8: Eps | DH8: Eps | DI8: Eps | DJ8: Eps | DK8: Eps | DL8: Eps | DM8: Eps | DN8: Eps | DO8: Eps | DP8: Eps | DQ8: Eps | DR8: Eps | DS8: Eps | DT8: Eps | DU8: Eps | DV8: Eps
A9: 2 | C9: =Notes!U10 -> Agriculture | D9: aa_AGRI | E9: 1 | F9: -0.0049904683 | G9: Eps | H9: Eps | I9: Eps | J9: Eps | K9: Eps | L9: Eps | M9: Eps | N9: Eps | O9: Eps | P9: Eps | Q9: Eps | R9: Eps | S9: Eps | T9: Eps | U9: Eps | X9: =Notes!U10 -> Agriculture | Y9: aa_AGRI | Z9: 1.2278891 | AA9: -0.0089674228 | AB9: Eps | AC9: Eps | AD9: Eps | AE9: Eps | AF9: Eps | AG9: Eps | AH9: Eps | AI9: Eps | AJ9: Eps | AK9: Eps | AL9: Eps | AM9: Eps | AN9: Eps | AO9: Eps | AP9: Eps | AS9: =Notes!U10 -> Agriculture | AT9: aa_AGRI | AU9: 1 | AV9: -0.01873584 | AW9: Eps | AX9: Eps | AY9: Eps | AZ9: Eps | BA9: Eps | BB9: Eps | BC9: Eps | BD9: Eps | BE9: Eps | BF9: Eps | BG9: Eps | BH9: Eps | BI9: Eps | BJ9: Eps | BK9: Eps | BN9: =Notes!U10 -> Agriculture | BO9: aa_AGRI | BP9: 1.1258354 | BQ9: -0.017541935 | BR9: Eps | BS9: Eps | BT9: Eps | BU9: Eps | BV9: Eps | BW9: Eps | BX9: Eps | BY9: Eps | BZ9: Eps | CA9: Eps | CB9: Eps | CC9: Eps | CD9: Eps | CE9: Eps | CF9: Eps | CI9: =Notes!U10 -> Agriculture | CJ9: aa_AGRI | CK9: 1.1771123 | CL9: Eps | CM9: Eps | CN9: Eps | CO9: Eps | CP9: Eps | CQ9: Eps | CR9: Eps | CS9: Eps | CT9: Eps | CU9: Eps | CV9: Eps | CW9: Eps | CX9: Eps | CY9: Eps | CZ9: Eps | DA9: Eps | DD9: =Notes!U10 -> Agriculture | DE9: aa_AGRI | DF9: 0.96255848 | DG9: Eps | DH9: Eps | DI9: Eps | DJ9: Eps | DK9: Eps | DL9: Eps | DM9: Eps | DN9: Eps | DO9: Eps | DP9: Eps | DQ9: Eps | DR9: Eps | DS9: Eps | DT9: Eps | DU9: Eps | DV9: Eps
A10: 3 | C10: =Notes!U11 -> Crops | D10: aa_CROP | E10: 1 | F10: 0.040933064 | G10: Eps | H10: Eps | I10: Eps | J10: Eps | K10: Eps | L10: Eps | M10: Eps | N10: Eps | O10: Eps | P10: Eps | Q10: Eps | R10: Eps | S10: Eps | T10: Eps | U10: Eps | X10: =Notes!U11 -> Crops | Y10: aa_CROP | Z10: 1.1993565 | AA10: 0.022365929 | AB10: Eps | AC10: Eps | AD10: Eps | AE10: Eps | AF10: Eps | AG10: Eps | AH10: Eps | AI10: Eps | AJ10: Eps | AK10: Eps | AL10: Eps | AM10: Eps | AN10: Eps | AO10: Eps | AP10: Eps | AS10: =Notes!U11 -> Crops | AT10: aa_CROP | AU10: 1 | AV10: -0.018477537 | AW10: Eps | AX10: Eps | AY10: Eps | AZ10: Eps | BA10: Eps | BB10: Eps | BC10: Eps | BD10: Eps | BE10: Eps | BF10: Eps | BG10: Eps | BH10: Eps | BI10: Eps | BJ10: Eps | BK10: Eps | BN10: =Notes!U11 -> Crops | BO10: aa_CROP | BP10: 1.1258811 | BQ10: -0.017541783 | BR10: Eps | BS10: Eps | BT10: Eps | BU10: Eps | BV10: Eps | BW10: Eps | BX10: Eps | BY10: Eps | BZ10: Eps | CA10: Eps | CB10: Eps | CC10: Eps | CD10: Eps | CE10: Eps | CF10: Eps | CI10: =Notes!U11 -> Crops | CJ10: aa_CROP | CK10: 1.1097773 | CL10: Eps | CM10: Eps | CN10: Eps | CO10: Eps | CP10: Eps | CQ10: Eps | CR10: Eps | CS10: Eps | CT10: Eps | CU10: Eps | CV10: Eps | CW10: Eps | CX10: Eps | CY10: Eps | CZ10: Eps | DA10: Eps | DD10: =Notes!U11 -> Crops | DE10: aa_CROP | DF10: 0.96278939 | DG10: Eps | DH10: Eps | DI10: Eps | DJ10: Eps | DK10: Eps | DL10: Eps | DM10: Eps | DN10: Eps | DO10: Eps | DP10: Eps | DQ10: Eps | DR10: Eps | DS10: Eps | DT10: Eps | DU10: Eps | DV10: Eps
A11: 4 | C11: =Notes!U12 -> Maize | D11: a_maiz | E11: 1 | F11: 0.041077937 | G11: Eps | H11: Eps | I11: Eps | J11: Eps | K11: Eps | L11: Eps | M11: Eps | N11: Eps | O11: Eps | P11: Eps | Q11: Eps | R11: Eps | S11: Eps | T11: Eps | U11: Eps | X11: =Notes!U12 -> Maize | Y11: a_maiz | Z11: 1.1391282 | AA11: -0.0011192883 | AB11: Eps | AC11: Eps | AD11: Eps | AE11: Eps | AF11: Eps | AG11: Eps | AH11: Eps | AI11: Eps | AJ11: Eps | AK11: Eps | AL11: Eps | AM11: Eps | AN11: Eps | AO11: Eps | AP11: Eps | AS11: =Notes!U12 -> Maize | AT11: a_maiz | AU11: Eps | AV11: Eps | AW11: Eps | AX11: Eps | AY11: Eps | AZ11: Eps | BA11: Eps | BB11: Eps | BC11: Eps | BD11: Eps | BE11: Eps | BF11: Eps | BG11: Eps | BH11: Eps | BI11: Eps | BJ11: Eps | BK11: Eps | BN11: =Notes!U12 -> Maize | BO11: a_maiz | BP11: 1.1391282 | BQ11: -0.017498165 | BR11: Eps | BS11: Eps | BT11: Eps | BU11: Eps | BV11: Eps | BW11: Eps | BX11: Eps | BY11: Eps | BZ11: Eps | CA11: Eps | CB11: Eps | CC11: Eps | CD11: Eps | CE11: Eps | CF11: Eps | CI11: =Notes!U12 -> Maize | CJ11: a_maiz | CK11: Eps | CL11: Eps | CM11: Eps | CN11: Eps | CO11: Eps | CP11: Eps | CQ11: Eps | CR11: Eps | CS11: Eps | CT11: Eps | CU11: Eps | CV11: Eps | CW11: Eps | CX11: Eps | CY11: Eps | CZ11: Eps | DA11: Eps | DD11: =Notes!U12 -> Maize | DE11: a_maiz | DF11: 1 | DG11: Eps | DH11: Eps | DI11: Eps | DJ11: Eps | DK11: Eps | DL11: Eps | DM11: Eps | DN11: Eps | DO11: Eps | DP11: Eps | DQ11: Eps | DR11: Eps | DS11: Eps | DT11: Eps | DU11: Eps | DV11: Eps
