Workbook

Sheet Notes
A1: =CONCATENATE(B4," ",B3," Standard Excel Interface Model") -> 2017 Rwanda Standard Excel Interface Model
A3: Country | B3: Rwanda
A4: Year | B4: 2017
A5: Units | B5: Billions of Rwanda Francs
A7: Activities and commodities | E7: Factors | H7: Households | K7: Other accounts
A8: asorg | B8: csorg | C8: Sorghum (A111) | E8: flab-rn | F8: Labor - rural uneducated | H8: hhd-f1 | I8: Rural - farm q1 | K8: trc | L8: Transaction costs
A9: amaiz | B9: cmaiz | C9: Maize (A112) | E9: flab-rp | F9: Labor - rural primary | H9: hhd-f2 | I9: Rural - farm q2 | K9: flab | L9: Labor
A10: awhea | B10: cwhea | C10: Wheat (A113) | E10: flab-rs | F10: Labor - rural secondary | H10: hhd-f3 | I10: Rural - farm q3 | K10: flnd | L10: Land
A11: arice | B11: crice | C11: Paddy & husked rice (A116) | E11: flab-rt | F11: Labor - rural tertiary | H11: hhd-f4 | I11: Rural - farm q4 | K11: fcap | L11: Capital
A12: aocer | B12: cocer | C12: Other cereals (A119) | E12: flab-un | F12: Labor - urban uneducated | H12: hhd-f5 | I12: Rural - farm q5 | K12: ent | L12: Enterprises
A13: aipot | B13: cipot | C13: Irish potatoes (A121) | E13: flab-up | F13: Labor - urban primary | H13: hhd-n1 | I13: Rural - nonfarm q1 | K13: hhd | L13: Households
A14: aspot | B14: cspot | C14: Sweet potatoes (A122) | E14: flab-us | F14: Labor - urban secondary | H14: hhd-n2 | I14: Rural - nonfarm q2 | K14: gov | L14: Government
A15: acass | B15: ccass | C15: Cassava (A123) | E15: flab-ut | F15: Labor - urban tertiary | H15: hhd-n3 | I15: Rural - nonfarm q3 | K15: atax | L15: Taxes - activity (production)
A16: aroot | B16: croot | C16: Other roots & tubers (A129) | E16: flab-kn | F16: Labor - Kigali uneducated | H16: hhd-n4 | I16: Rural - nonfarm q4 | K16: ctax | L16: Taxes - customs duties (imports)
A17: abean | B17: cbean | C17: Dried beans (A131) | E17: flab-kp | F17: Labor - Kigali primary | H17: hhd-n5 | I17: Rural - nonfarm q5 | K17: dtax | L17: Taxes - direct (corporate, private)
A18: apeas | B18: cpeas | C18: Peas & other legumes (A132) | E18: flab-ks | F18: Labor - Kigali secondary | H18: hhd-u1 | I18: Urban - q1 | K18: etax | L18: Taxes - exports
A19: avege | B19: cvege | C19: Other vegetables (A139) | E19: flab-kt | F19: Labor - Kigali tertiary | H19: hhd-u2 | I19: Urban - q2 | K19: ftax | L19: Taxes - factors (royalities)
... A24: agnut | B24: cgnut | C24: Ground nuts (A151) | E24: fcap-n | F24: Capital - non-primary | H24: hhd-k2 | I24: Kigali - q2 | K24: s-i | L24: Savings-investment
A25: asoya | B25: csoya | C25: Soya (A152) | H25: hhd-k3 | I25: Kigali - q3 | K25: dstk | L25: Change in stocks
A26: aoils | B26: coils | C26: Other oil seeds (A159) | H26: hhd-k4 | I26: Kigali - q4 | K26: row | L26: Rest of world
A27: acoff | B27: ccoff | C27: Coffee, not roasted, not decaffeinated (A210) | H27: hhd-k5 | I27: Kigali - q5 | K27: total | L27: Total
A28: ateal | B28: cteal | C28: Tea (unprocessed green leaf) (A220)
A29: atoba | B29: ctoba | C29: Tobacco, raw (A291)
A30: asugr | B30: csugr | C30: Sugar cane (A292)
A31: apyre | B31: cpyre | C31: Pyrethrum (A293)
A32: aocrp | B32: cocrp | C32: Agricultural products n.e.c. (A299)
A33: acatt | B33: ccatt | C33: Bovine cattle, live (A311)
A34: asmlr | B34: csmlr | C34: Sheep, goats, pigs,live (A312)
A35: apoul | B35: cpoul | C35: Poultry, live (A313)
A36: aoliv | B36: coliv | C36: Other live animals (A319)
A37: amilk | B37: cmilk | C37: Raw milk (A321)
A38: aeggs | B38: ceggs | C38: Eggs (A322)
A39: ahony | B39: chony | C39: Natural honey (A323)
... A111: atrdc | B111: ctrdc | C111: Travel debits & credits (V00)

Sheet Main
A1: Activate Simulations and Select Closures
A3: Activate simulations | F3: Macroeconomic closures
A4: Active? (0=no; 1=yes) | G4: {=TRANSPOSE(A6:A14)} -> Chem_wp_shk | H4: Food_shk | I4: Fuel&gas_shk | J4: HH shk | K4: sim5 | L4: sim6 | M4: sim7 | N4: sim8 | O4: sim9
A5: base | B5: 1 | C5: Base scenario | F5: Numeraire | G5: 2 | H5: 2 | I5: 2 | J5: 2 | K5: 2 | L5: 2 | M5: 2 | N5: 2 | O5: 2
A6: Chem_wp_shk | B6: 0 | C6: 50%_incr_cchem | F6: Savings-investment | G6: 3 | H6: 3 | I6: 3 | J6: 3 | K6: 3 | L6: 3 | M6: 3 | N6: 3 | O6: 3
A7: Food_shk | B7: 0 | C7: 50 % Incr_pwm_cereal&ed.oil | F7: Government account | G7: 1 | H7: 1 | I7: 1 | J7: 1 | K7: 1 | L7: 1 | M7: 1 | N7: 1 | O7: 1
A8: Fuel&gas_shk | B8: 0 | C8: Incr_pmw_oil | F8: Current account | G8: 1 | H8: 1 | I8: 1 | J8: 1 | K8: 1 | L8: 1 | M8: 1 | N8: 1 | O8: 1
A9: HH shk
A10: sim5 | F10: Factor market closures
A11: sim6 | G11: {=TRANSPOSE(A6:A14)} -> Chem_wp_shk | H11: Food_shk | I11: Fuel&gas_shk | J11: HH shk | K11: sim5 | L11: sim6 | M11: sim7 | N11: sim8 | O11: sim9
A12: sim7 | F12: Labor - rural uneducated | G12: 1 | H12: 3 | I12: 3 | J12: 1 | K12: 1 | L12: 1 | M12: 1 | N12: 1 | O12: 1
A13: sim8 | F13: Labor - rural primary | G13: 1 | H13: 3 | I13: 3 | J13: 1 | K13: 1 | L13: 1 | M13: 1 | N13: 1 | O13: 1
A14: sim9 | F14: Labor - rural secondary | G14: 1 | H14: 1 | I14: 1 | J14: 3 | K14: 1 | L14: 1 | M14: 1 | N14: 1 | O14: 1
F15: Labor - rural tertiary | G15: 1 | H15: 1 | I15: 1 | J15: 3 | K15: 1 | L15: 1 | M15: 1 | N15: 1 | O15: 1
F16: Labor - urban uneducated | G16: 1 | H16: 3 | I16: 3 | J16: 1 | K16: 3 | L16: 1 | M16: 1 | N16: 1 | O16: 1
F17: Labor - urban primary | G17: 1 | H17: 3 | I17: 3 | J17: 1 | K17: 3 | L17: 1 | M17: 1 | N17: 1 | O17: 1
F18: Labor - urban secondary | G18: 1 | H18: 1 | I18: 1 | J18: 3 | K18: 1 | L18: 1 | M18: 1 | N18: 1 | O18: 1
F19: Labor - urban tertiary | G19: 1 | H19: 1 | I19: 1 | J19: 3 | K19: 1 | L19: 1 | M19: 1 | N19: 1 | O19: 1
F20: Labor - Kigali uneducated | G20: 1 | H20: 3 | I20: 3 | J20: 1 | K20: 1 | L20: 1 | M20: 1 | N20: 1 | O20: 1
F21: Labor - Kigali primary | G21: 1 | H21: 3 | I21: 3 | J21: 1 | K21: 3 | L21: 1 | M21: 1 | N21: 1 | O21: 1
F22: Labor - Kigali secondary | G22: 1 | H22: 1 | I22: 1 | J22: 3 | K22: 3 | L22: 1 | M22: 1 | N22: 1 | O22: 1
F23: Labor - Kigali tertiary | G23: 1 | H23: 1 | I23: 1 | J23: 3 | K23: 1 | L23: 1 | M23: 1 | N23: 1 | O23: 1
F24: Crop land | G24: 1 | H24: 1 | I24: 1 | J24: 1 | K24: 1 | L24: 1 | M24: 1 | N24: 1 | O24: 1
F25: Capital - crops | G25: 2 | H25: 2 | I25: 2 | J25: 2 | K25: 2 | L25: 2 | M25: 2 | N25: 2 | O25: 2
F26: Capital - livestock | G26: 2 | H26: 2 | I26: 2 | J26: 2 | K26: 2 | L26: 2 | M26: 2 | N26: 2 | O26: 2
... F28: Capital - non-primary | G28: 2 | H28: 2 | I28: 2 | J28: 2 | K28: 2 | L28: 2 | M28: 2 | N28: 2 | O28: 2
A32: Numeraire
A33: 1 | B33: CPI is numeraire (and fixed) -- DPI is flexible
A34: 2 | B34: DPI is numeraire (and fixed) -- CPI is flexible
A36: Factor closure options
A37: 1 | B37: fully employed and mobile
A38: 2 | B38: fully employed and activity-specific
A39: 3 | B39: unemployed and mobile
A41: Savings-investment closure options
A42: 1 | B42: investment-driven savings -- uniform mps rate point change for selected institutions
A43: 2 | B43: investment-driven savings -- scaled mps for for selected institutions
A44: 3 | B44: investment is savings-driven
A45: 4 | B45: investment is fixed absolute share - uniform mps rate point change - balanced closure
A46: 5 | B46: investment is fixed abs share - scaled mps - balanced closure
A48: Current account closure options
A49: 1 | B49: exchange rate is flexible, foreign savings are fixed
A50: 2 | B50: exchange rate is fixed, foreign savings are flexible
A52: Government account closure options
A53: 1 | B53: government savings are flexible, direct tax rate is fixed
A54: 2 | B54: government savings are fixed, uniform direct tax rate point change for selected ins
A55: 3 | B55: government savings are fixed, scaled direct tax rate for selected institutions

Sheet S1
A1: ="Simulation "&Y1&IF(X1<>""," : "&X1,"") -> Simulation Chem_wp_shk : 50%_incr_cchem | X1: =IF(Main!C6<>"",Main!C6,"") -> 50%_incr_cchem | Y1: =Main!A6 -> Chem_wp_shk
A3: Commodity shocks | N3: Activity shocks | V3: Factor shocks
B4: World prices | D4: Commodity taxes | G4: Transaction costs | J4: Import | O4: Fix cap? | P4: TFP | Q4: Activity taxes | W4: Factor | X4: Wage | Y4: Factor
B5: Exports | C5: Imports | D5: Exports | E5: Imports | F5: Sales | G5: Exports | H5: Imports | I5: Domestic | J5: subsidy | O5: (1=yes) | Q5: Activity | R5: ValAd. | W5: taxes | X5: rate | Y5: supply
B6: pwe | C6: pwm | D6: te | E6: tm | F6: tq | G6: ice | H6: icm | I6: icd | J6: tms | O6: fixcap | P6: alphava | Q6: ta | R6: tva | W6: tf | X6: wf | Y6: qfs
A7: csorg | B7: eps | C7: eps | D7: eps | E7: eps | F7: eps | G7: eps | H7: eps | I7: eps | J7: eps | N7: asorg | O7: 0 | P7: eps | Q7: eps | R7: eps | V7: flab-rn | W7: eps | X7: eps | Y7: eps
A8: cmaiz | B8: eps | C8: eps | D8: eps | E8: eps | F8: eps | G8: eps | H8: eps | I8: eps | J8: eps | N8: amaiz | O8: 0 | P8: eps | Q8: eps | R8: eps | V8: flab-rp | W8: eps | X8: eps | Y8: eps
A9: cwhea | B9: eps | C9: eps | D9: eps | E9: eps | F9: eps | G9: eps | H9: eps | I9: eps | J9: eps | N9: awhea | O9: 0 | P9: eps | Q9: eps | R9: eps | V9: flab-rs | W9: eps | X9: eps | Y9: eps
A10: crice | B10: eps | C10: eps | D10: eps | E10: eps | F10: eps | G10: eps | H10: eps | I10: eps | J10: eps | N10: arice | O10: 0 | P10: eps | Q10: eps | R10: eps | V10: flab-rt | W10: eps | X10: eps | Y10: eps
A11: cocer | B11: eps | C11: eps | D11: eps | E11: eps | F11: eps | G11: eps | H11: eps | I11: eps | J11: eps | N11: aocer | O11: 0 | P11: eps | Q11: eps | R11: eps | V11: flab-un | W11: eps | X11: eps | Y11: eps
A12: cipot | B12: eps | C12: eps | D12: eps | E12: eps | F12: eps | G12: eps | H12: eps | I12: eps | J12: eps | N12: aipot | O12: 0 | P12: eps | Q12: eps | R12: eps | V12: flab-up | W12: eps | X12: eps | Y12: eps
A13: cspot | B13: eps | C13: eps | D13: eps | E13: eps | F13: eps | G13: eps | H13: eps | I13: eps | J13: eps | N13: aspot | O13: 0 | P13: eps | Q13: eps | R13: eps | V13: flab-us | W13: eps | X13: eps | Y13: eps
A14: ccass | B14: eps | C14: eps | D14: eps | E14: eps | F14: eps | G14: eps | H14: eps | I14: eps | J14: eps | N14: acass | O14: 0 | P14: eps | Q14: eps | R14: eps | V14: flab-ut | W14: eps | X14: eps | Y14: eps
A15: croot | B15: eps | C15: eps | D15: eps | E15: eps | F15: eps | G15: eps | H15: eps | I15: eps | J15: eps | N15: aroot | O15: 0 | P15: eps | Q15: eps | R15: eps | V15: flab-kn | W15: eps | X15: eps | Y15: eps
A16: cbean | B16: eps | C16: eps | D16: eps | E16: eps | F16: eps | G16: eps | H16: eps | I16: eps | J16: eps | N16: abean | O16: 0 | P16: eps | Q16: eps | R16: eps | V16: flab-kp | W16: eps | X16: eps | Y16: eps
A17: cpeas | B17: eps | C17: eps | D17: eps | E17: eps | F17: eps | G17: eps | H17: eps | I17: eps | J17: eps | N17: apeas | O17: 0 | P17: eps | Q17: eps | R17: eps | V17: flab-ks | W17: eps | X17: eps | Y17: eps
A18: cvege | B18: eps | C18: eps | D18: eps | E18: eps | F18: eps | G18: eps | H18: eps | I18: eps | J18: eps | N18: avege | O18: 0 | P18: eps | Q18: eps | R18: eps | V18: flab-kt | W18: eps | X18: eps | Y18: eps
... A23: cgnut | B23: eps | C23: eps | D23: eps | E23: eps | F23: eps | G23: eps | H23: eps | I23: eps | J23: eps | N23: agnut | O23: 0 | P23: eps | Q23: eps | R23: eps | V23: fcap-n | W23: eps | X23: eps | Y23: eps
A24: csoya | B24: eps | C24: eps | D24: eps | E24: eps | F24: eps | G24: eps | H24: eps | I24: eps | J24: eps | N24: asoya | O24: 0 | P24: eps | Q24: eps | R24: eps
A25: coils | B25: eps | C25: eps | D25: eps | E25: eps | F25: eps | G25: eps | H25: eps | I25: eps | J25: eps | N25: aoils | O25: 0 | P25: eps | Q25: eps | R25: eps | V25: Household income shocks
A26: ccoff | B26: eps | C26: eps | D26: eps | E26: eps | F26: eps | G26: eps | H26: eps | I26: eps | J26: eps | N26: acoff | O26: 0 | P26: eps | Q26: eps | R26: eps | X26: Gov. | Y26: World
A27: cteal | B27: eps | C27: eps | D27: eps | E27: eps | F27: eps | G27: eps | H27: eps | I27: eps | J27: eps | N27: ateal | O27: 0 | P27: eps | Q27: eps | R27: eps | X27: trn | Y27: rem
A28: ctoba | B28: eps | C28: eps | D28: eps | E28: eps | F28: eps | G28: eps | H28: eps | I28: eps | J28: eps | N28: atoba | O28: 0 | P28: eps | Q28: eps | R28: eps | V28: Farm | W28: hhd-r1 | X28: eps | Y28: eps
A29: csugr | B29: eps | C29: eps | D29: eps | E29: eps | F29: eps | G29: eps | H29: eps | I29: eps | J29: eps | N29: asugr | O29: 0 | P29: eps | Q29: eps | R29: eps | W29: hhd-r2 | X29: eps | Y29: eps
A30: cpyre | B30: eps | C30: eps | D30: eps | E30: eps | F30: eps | G30: eps | H30: eps | I30: eps | J30: eps | N30: apyre | O30: 0 | P30: eps | Q30: eps | R30: eps | W30: hhd-r3 | X30: eps | Y30: eps
A31: cocrp | B31: eps | C31: eps | D31: eps | E31: eps | F31: eps | G31: eps | H31: eps | I31: eps | J31: eps | N31: aocrp | O31: 0 | P31: eps | Q31: eps | R31: eps | W31: hhd-r4 | X31: eps | Y31: eps
A32: ccatt | B32: eps | C32: eps | D32: eps | E32: eps | F32: eps | G32: eps | H32: eps | I32: eps | J32: eps | N32: acatt | O32: 0 | P32: eps | Q32: eps | R32: eps | W32: hhd-r5 | X32: eps | Y32: eps
A33: csmlr | B33: eps | C33: eps | D33: eps | E33: eps | F33: eps | G33: eps | H33: eps | I33: eps | J33: eps | N33: asmlr | O33: 0 | P33: eps | Q33: eps | R33: eps | V33: Nonfarm | W33: hhd-u1 | X33: eps | Y33: eps
A34: cpoul | B34: eps | C34: eps | D34: eps | E34: eps | F34: eps | G34: eps | H34: eps | I34: eps | J34: eps | N34: apoul | O34: 0 | P34: eps | Q34: eps | R34: eps | W34: hhd-u2 | X34: eps | Y34: eps
A35: coliv | B35: eps | C35: eps | D35: eps | E35: eps | F35: eps | G35: eps | H35: eps | I35: eps | J35: eps | N35: aoliv | O35: 0 | P35: eps | Q35: eps | R35: eps | W35: hhd-u3 | X35: eps | Y35: eps
A36: cmilk | B36: eps | C36: eps | D36: eps | E36: eps | F36: eps | G36: eps | H36: eps | I36: eps | J36: eps | N36: amilk | O36: 0 | P36: eps | Q36: eps | R36: eps | W36: hhd-u4 | X36: eps | Y36: eps
A37: ceggs | B37: eps | C37: eps | D37: eps | E37: eps | F37: eps | G37: eps | H37: eps | I37: eps | J37: eps | N37: aeggs | O37: 0 | P37: eps | Q37: eps | R37: eps | W37: hhd-u5 | X37: eps | Y37: eps
A38: chony | B38: eps | C38: eps | D38: eps | E38: eps | F38: eps | G38: eps | H38: eps | I38: eps | J38: eps | N38: ahony | O38: 0 | P38: eps | Q38: eps | R38: eps | V38: Urban | W38: hhd-k1 | X38: eps | Y38: eps
A39: chunt | B39: eps | C39: eps | D39: eps | E39: eps | F39: eps | G39: eps | H39: eps | I39: eps | J39: eps | N39: ahunt | O39: 0 | P39: eps | Q39: eps | R39: eps | W39: hhd-k2 | X39: eps | Y39: eps
A40: cfuel | B40: eps | C40: eps | D40: eps | E40: eps | F40: eps | G40: eps | H40: eps | I40: eps | J40: eps | N40: afuel | O40: 0 | P40: eps | Q40: eps | R40: eps | W40: hhd-k3 | X40: eps | Y40: eps
A41: cchar | B41: eps | C41: eps | D41: eps | E41: eps | F41: eps | G41: eps | H41: eps | I41: eps | J41: eps | N41: achar | O41: 0 | P41: eps | Q41: eps | R41: eps | W41: hhd-k4 | X41: eps | Y41: eps
A42: cfore | B42: eps | C42: eps | D42: eps | E42: eps | F42: eps | G42: eps | H42: eps | I42: eps | J42: eps | N42: afore | O42: 0 | P42: eps | Q42: eps | R42: eps | W42: hhd-k5 | X42: eps | Y42: eps
A43: cfish | B43: eps | C43: eps | D43: eps | E43: eps | F43: eps | G43: eps | H43: eps | I43: eps | J43: eps | N43: afish | O43: 0 | P43: eps | Q43: eps | R43: eps
A44: cngas | B44: eps | C44: eps | D44: eps | E44: eps | F44: eps | G44: eps | H44: eps | I44: eps | J44: eps | N44: angas | O44: 0 | P44: eps | Q44: eps | R44: eps | V44: Scalar shocks
A45: cmore | B45: eps | C45: eps | D45: eps | E45: eps | F45: eps | G45: eps | H45: eps | I45: eps | J45: eps | N45: amore | O45: 0 | P45: eps | Q45: eps | R45: eps
A46: comin | B46: eps | C46: eps | D46: eps | E46: eps | F46: eps | G46: eps | H46: eps | I46: eps | J46: eps | N46: aomin | O46: 0 | P46: eps | Q46: eps | R46: eps | V46: Exchange rate | X46: exr | Y46: eps
A47: cmeat | B47: eps | C47: eps | D47: eps | E47: eps | F47: eps | G47: eps | H47: eps | I47: eps | J47: eps | N47: ameat | O47: 0 | P47: eps | Q47: eps | R47: eps | V47: Investment | X47: iadj | Y47: eps
A48: cfsea | B48: eps | C48: eps | D48: eps | E48: eps | F48: eps | G48: eps | H48: eps | I48: eps | J48: eps | N48: afsea | O48: 0 | P48: eps | Q48: eps | R48: eps | V48: Foreign savings | X48: fsav | Y48: -10
A49: cfveg | B49: eps | C49: eps | D49: eps | E49: eps | F49: eps | G49: eps | H49: eps | I49: eps | J49: eps | N49: afveg | O49: 0 | P49: eps | Q49: eps | R49: eps | V49: Gov. savings | X49: gsav | Y49: eps
A50: cfoil | B50: eps | C50: eps | D50: eps | E50: eps | F50: eps | G50: eps | H50: eps | I50: eps | J50: eps | N50: afoil | O50: 0 | P50: eps | Q50: eps | R50: eps | V50: Gov. spending | X50: gadj | Y50: eps
A51: cdair | B51: eps | C51: eps | D51: eps | E51: eps | F51: eps | G51: eps | H51: eps | I51: eps | J51: eps | N51: adair | O51: 0 | P51: eps | Q51: eps | R51: eps | V51: Savings rates | X51: mpsadj | Y51: eps
A52: cgmll | B52: eps | C52: eps | D52: eps | E52: eps | F52: eps | G52: eps | H52: eps | I52: eps | J52: eps | N52: agmll | O52: 0 | P52: eps | Q52: eps | R52: eps | X52: dmps | Y52: eps
A53: cbake | B53: eps | C53: eps | D53: eps | E53: eps | F53: eps | G53: eps | H53: eps | I53: eps | J53: eps | N53: abake | O53: 0 | P53: eps | Q53: eps | R53: eps | V53: Direct tax rates | X53: tinsadj | Y53: eps
A54: cfeed | B54: eps | C54: eps | D54: eps | E54: eps | F54: eps | G54: eps | H54: eps | I54: eps | J54: eps | N54: afeed | O54: 0 | P54: eps | Q54: eps | R54: eps | X54: dtins | Y54: eps
A55: cfood | B55: eps | C55: eps | D55: eps | E55: eps | F55: eps | G55: eps | H55: eps | I55: eps | J55: eps | N55: afood | O55: 0 | P55: eps | Q55: eps | R55: eps
A56: calco | B56: eps | C56: eps | D56: eps | E56: eps | F56: eps | G56: eps | H56: eps | I56: eps | J56: eps | N56: aalco | O56: 0 | P56: eps | Q56: eps | R56: eps | V56: Institutional closures
A57: cbeve | B57: eps | C57: eps | D57: eps | E57: eps | F57: eps | G57: eps | H57: eps | I57: eps | J57: eps | N57: abeve | O57: 0 | P57: eps | Q57: eps | R57: eps | X57: Savings | Y57: Taxes
A58: cptob | B58: eps | C58: eps | D58: eps | E58: eps | F58: eps | G58: eps | H58: eps | I58: eps | J58: eps | N58: aptob | O58: 0 | P58: eps | Q58: eps | R58: eps | X58: mps | Y58: tins
A59: ctext | B59: eps | C59: eps | D59: eps | E59: eps | F59: eps | G59: eps | H59: eps | I59: eps | J59: eps | N59: atext | O59: 0 | P59: eps | Q59: eps | R59: eps | V59: Enter. | W59: ent | X59: 1 | Y59: 1
A60: cwood | B60: eps | C60: eps | D60: eps | E60: eps | F60: eps | G60: eps | H60: eps | I60: eps | J60: eps | N60: awood | O60: 0 | P60: eps | Q60: eps | R60: eps | V60: House. | W60: hhd-r1 | X60: 1 | Y60: 1
A61: cprnt | B61: eps | C61: eps | D61: eps | E61: eps | F61: eps | G61: eps | H61: eps | I61: eps | J61: eps | N61: aprnt | O61: 0 | P61: eps | Q61: eps | R61: eps | W61: hhd-r2 | X61: 1 | Y61: 1
A62: cpetr | B62: eps | C62: eps | D62: eps | E62: eps | F62: eps | G62: eps | H62: eps | I62: eps | J62: eps | N62: apetr | O62: 0 | P62: eps | Q62: eps | R62: eps | W62: hhd-r3 | X62: 1 | Y62: 1
A63: cchem | B63: eps | C63: 50 | D63: eps | E63: eps | F63: eps | G63: eps | H63: eps | I63: eps | J63: eps | N63: achem | O63: 0 | P63: eps | Q63: eps | R63: eps | W63: hhd-r4 | X63: 1 | Y63: 1
A64: cphar | B64: eps | C64: eps | D64: eps | E64: eps | F64: eps | G64: eps | H64: eps | I64: eps | J64: eps | N64: aphar | O64: 0 | P64: eps | Q64: eps | R64: eps | W64: hhd-r5 | X64: 1 | Y64: 1
A65: cprub | B65: eps | C65: eps | D65: eps | E65: eps | F65: eps | G65: eps | H65: eps | I65: eps | J65: eps | N65: aprub | O65: 0 | P65: eps | Q65: eps | R65: eps | W65: hhd-u1 | X65: 1 | Y65: 1
A66: cnmet | B66: eps | C66: eps | D66: eps | E66: eps | F66: eps | G66: eps | H66: eps | I66: eps | J66: eps | N66: anmet | O66: 0 | P66: eps | Q66: eps | R66: eps | W66: hhd-u2 | X66: 1 | Y66: 1
A67: cceme | B67: eps | C67: eps | D67: eps | E67: eps | F67: eps | G67: eps | H67: eps | I67: eps | J67: eps | N67: aceme | O67: 0 | P67: eps | Q67: eps | R67: eps | W67: hhd-u3 | X67: 1 | Y67: 1
A68: cclay | B68: eps | C68: eps | D68: eps | E68: eps | F68: eps | G68: eps | H68: eps | I68: eps | J68: eps | N68: aclay | O68: 0 | P68: eps | Q68: eps | R68: eps | W68: hhd-u4 | X68: 1 | Y68: 1
A69: cmetl | B69: eps | C69: eps | D69: eps | E69: eps | F69: eps | G69: eps | H69: eps | I69: eps | J69: eps | N69: ametl | O69: 0 | P69: eps | Q69: eps | R69: eps | W69: hhd-u5 | X69: 1 | Y69: 1
A70: cmach | B70: eps | C70: eps | D70: eps | E70: eps | F70: eps | G70: eps | H70: eps | I70: eps | J70: eps | N70: amach | O70: 0 | P70: eps | Q70: eps | R70: eps | W70: hhd-k1 | X70: 1 | Y70: 1
A71: cvehi | B71: eps | C71: eps | D71: eps | E71: eps | F71: eps | G71: eps | H71: eps | I71: eps | J71: eps | N71: avehi | O71: 0 | P71: eps | Q71: eps | R71: eps | W71: hhd-k2 | X71: 1 | Y71: 1
A72: cfurn | B72: eps | C72: eps | D72: eps | E72: eps | F72: eps | G72: eps | H72: eps | I72: eps | J72: eps | N72: afurn | O72: 0 | P72: eps | Q72: eps | R72: eps | W72: hhd-k3 | X72: 1 | Y72: 1
A73: coman | B73: eps | C73: eps | D73: eps | E73: eps | F73: eps | G73: eps | H73: eps | I73: eps | J73: eps | N73: aoman | O73: 0 | P73: eps | Q73: eps | R73: eps | W73: hhd-k4 | X73: 1 | Y73: 1
A74: crepr | B74: eps | C74: eps | D74: eps | E74: eps | F74: eps | G74: eps | H74: eps | I74: eps | J74: eps | N74: arepr | O74: 0 | P74: eps | Q74: eps | R74: eps | W74: hhd-k5 | X74: 1 | Y74: 1
A75: celec | B75: eps | C75: eps | D75: eps | E75: eps | F75: eps | G75: eps | H75: eps | I75: eps | J75: eps | N75: aelec | O75: 0 | P75: eps | Q75: eps | R75: eps
A76: cwatr | B76: eps | C76: eps | D76: eps | E76: eps | F76: eps | G76: eps | H76: eps | I76: eps | J76: eps | N76: awatr | O76: 0 | P76: eps | Q76: eps | R76: eps | V76: Macroeconomic closures
A77: cwast | B77: eps | C77: eps | D77: eps | E77: eps | F77: eps | G77: eps | H77: eps | I77: eps | J77: eps | N77: awast | O77: 0 | P77: eps | Q77: eps | R77: eps | V77: Num. | W77: dum | X77: =SUMIF(Main!G4:O4,Y1,Main!G5:O5) -> 2
A78: ccons | B78: eps | C78: eps | D78: eps | E78: eps | F78: eps | G78: eps | H78: eps | I78: eps | J78: eps | N78: acons | O78: 0 | P78: eps | Q78: eps | R78: eps | V78: Sav-Inv. | W78: s-i | X78: =SUMIF(Main!G4:O4,Y1,Main!G6:O6) -> 3
A79: ccont | B79: eps | C79: eps | D79: eps | E79: eps | F79: eps | G79: eps | H79: eps | I79: eps | J79: eps | N79: acont | O79: 0 | P79: eps | Q79: eps | R79: eps | V79: Gov. | W79: gov | X79: =SUMIF(Main!G4:O4,Y1,Main!G7:O7) -> 1
A80: cvehr | B80: eps | C80: eps | D80: eps | E80: eps | F80: eps | G80: eps | H80: eps | I80: eps | J80: eps | N80: avehr | O80: 0 | P80: eps | Q80: eps | R80: eps | V80: Cur. a/c | W80: row | X80: =SUMIF(Main!G4:O4,Y1,Main!G8:O8) -> 1
A81: cveht | B81: eps | C81: eps | D81: eps | E81: eps | F81: eps | G81: eps | H81: eps | I81: eps | J81: eps | N81: aveht | O81: 0 | P81: eps | Q81: eps | R81: eps
A82: ctrdw | B82: eps | C82: eps | D82: eps | E82: eps | F82: eps | G82: eps | H82: eps | I82: eps | J82: eps | N82: atrdw | O82: 0 | P82: eps | Q82: eps | R82: eps | V82: Factor market closures
A83: ctrdr | B83: eps | C83: eps | D83: eps | E83: eps | F83: eps | G83: eps | H83: eps | I83: eps | J83: eps | N83: atrdr | O83: 0 | P83: eps | Q83: eps | R83: eps | V83: Labor | W83: flab-rn | X83: =SUMIF(Main!G11:O11,'S1'!Y1,Main!G12:O12) -> 1
A84: ctrnl | B84: eps | C84: eps | D84: eps | E84: eps | F84: eps | G84: eps | H84: eps | I84: eps | J84: eps | N84: atrnl | O84: 0 | P84: eps | Q84: eps | R84: eps | W84: flab-rp | X84: =SUMIF(Main!G11:O11,'S1'!Y1,Main!G13:O13) -> 1
A85: ctrna | B85: eps | C85: eps | D85: eps | E85: eps | F85: eps | G85: eps | H85: eps | I85: eps | J85: eps | N85: atrna | O85: 0 | P85: eps | Q85: eps | R85: eps | W85: flab-rs | X85: =SUMIF(Main!G11:O11,'S1'!Y1,Main!G14:O14) -> 1
A86: ctrns | B86: eps | C86: eps | D86: eps | E86: eps | F86: eps | G86: eps | H86: eps | I86: eps | J86: eps | N86: atrns | O86: 0 | P86: eps | Q86: eps | R86: eps | W86: flab-rt | X86: =SUMIF(Main!G11:O11,'S1'!Y1,Main!G15:O15) -> 1
A87: cpost | B87: eps | C87: eps | D87: eps | E87: eps | F87: eps | G87: eps | H87: eps | I87: eps | J87: eps | N87: apost | O87: 0 | P87: eps | Q87: eps | R87: eps | W87: flab-un | X87: =SUMIF(Main!G11:O11,'S1'!Y1,Main!G16:O16) -> 1
A88: chotl | B88: eps | C88: eps | D88: eps | E88: eps | F88: eps | G88: eps | H88: eps | I88: eps | J88: eps | N88: ahotl | O88: 0 | P88: eps | Q88: eps | R88: eps | W88: flab-up | X88: =SUMIF(Main!G11:O11,'S1'!Y1,Main!G17:O17) -> 1
A89: cpubl | B89: eps | C89: eps | D89: eps | E89: eps | F89: eps | G89: eps | H89: eps | I89: eps | J89: eps | N89: apubl | O89: 0 | P89: eps | Q89: eps | R89: eps | W89: flab-us | X89: =SUMIF(Main!G11:O11,'S1'!Y1,Main!G18:O18) -> 1
A90: ccomm | B90: eps | C90: eps | D90: eps | E90: eps | F90: eps | G90: eps | H90: eps | I90: eps | J90: eps | N90: acomm | O90: 0 | P90: eps | Q90: eps | R90: eps | W90: flab-ut | X90: =SUMIF(Main!G11:O11,'S1'!Y1,Main!G19:O19) -> 1
A91: cinfo | B91: eps | C91: eps | D91: eps | E91: eps | F91: eps | G91: eps | H91: eps | I91: eps | J91: eps | N91: ainfo | O91: 0 | P91: eps | Q91: eps | R91: eps | W91: flab-kn | X91: =SUMIF(Main!G11:O11,'S1'!Y1,Main!G20:O20) -> 1
A92: cbank | B92: eps | C92: eps | D92: eps | E92: eps | F92: eps | G92: eps | H92: eps | I92: eps | J92: eps | N92: abank | O92: 0 | P92: eps | Q92: eps | R92: eps | W92: flab-kp | X92: =SUMIF(Main!G11:O11,'S1'!Y1,Main!G21:O21) -> 1
A93: cinsu | B93: eps | C93: eps | D93: eps | E93: eps | F93: eps | G93: eps | H93: eps | I93: eps | J93: eps | N93: ainsu | O93: 0 | P93: eps | Q93: eps | R93: eps | W93: flab-ks | X93: =SUMIF(Main!G11:O11,'S1'!Y1,Main!G22:O22) -> 1
A94: cofsv | B94: eps | C94: eps | D94: eps | E94: eps | F94: eps | G94: eps | H94: eps | I94: eps | J94: eps | N94: aofsv | O94: 0 | P94: eps | Q94: eps | R94: eps | W94: flab-kt | X94: =SUMIF(Main!G11:O11,'S1'!Y1,Main!G23:O23) -> 1
A95: crent | B95: eps | C95: eps | D95: eps | E95: eps | F95: eps | G95: eps | H95: eps | I95: eps | J95: eps | N95: arent | O95: 0 | P95: eps | Q95: eps | R95: eps | V95: Land | W95: flnd | X95: =SUMIF(Main!G11:O11,'S1'!Y1,Main!G24:O24) -> 1
A96: creal | B96: eps | C96: eps | D96: eps | E96: eps | F96: eps | G96: eps | H96: eps | I96: eps | J96: eps | N96: areal | O96: 0 | P96: eps | Q96: eps | R96: eps | V96: Capital | W96: fcap-c | X96: =SUMIF(Main!G11:O11,'S1'!Y1,Main!G25:O25) -> 2
A97: clegl | B97: eps | C97: eps | D97: eps | E97: eps | F97: eps | G97: eps | H97: eps | I97: eps | J97: eps | N97: alegl | O97: 0 | P97: eps | Q97: eps | R97: eps | W97: fcap-l | X97: =SUMIF(Main!G11:O11,'S1'!Y1,Main!G26:O26) -> 2
A98: cenga | B98: eps | C98: eps | D98: eps | E98: eps | F98: eps | G98: eps | H98: eps | I98: eps | J98: eps | N98: aenga | O98: 0 | P98: eps | Q98: eps | R98: eps | W98: fcap-m | X98: =SUMIF(Main!G11:O11,'S1'!Y1,Main!G27:O27) -> 2
A99: cprod | B99: eps | C99: eps | D99: eps | E99: eps | F99: eps | G99: eps | H99: eps | I99: eps | J99: eps | N99: aprod | O99: 0 | P99: eps | Q99: eps | R99: eps | W99: fcap-n | X99: =SUMIF(Main!G11:O11,'S1'!Y1,Main!G28:O28) -> 2
A100: ctrvl | B100: eps | C100: eps | D100: eps | E100: eps | F100: eps | G100: eps | H100: eps | I100: eps | J100: eps | N100: atrvl | O100: 0 | P100: eps | Q100: eps | R100: eps
A101: cobsv | B101: eps | C101: eps | D101: eps | E101: eps | F101: eps | G101: eps | H101: eps | I101: eps | J101: eps | N101: aobsv | O101: 0 | P101: eps | Q101: eps | R101: eps
A102: cpadm | B102: eps | C102: eps | D102: eps | E102: eps | F102: eps | G102: eps | H102: eps | I102: eps | J102: eps | N102: apadm | O102: 0 | P102: eps | Q102: eps | R102: eps
A103: ceduc | B103: eps | C103: eps | D103: eps | E103: eps | F103: eps | G103: eps | H103: eps | I103: eps | J103: eps | N103: aeduc | O103: 0 | P103: eps | Q103: eps | R103: eps
A104: cheal | B104: eps | C104: eps | D104: eps | E104: eps | F104: eps | G104: eps | H104: eps | I104: eps | J104: eps | N104: aheal | O104: 0 | P104: eps | Q104: eps | R104: eps
A105: csocw | B105: eps | C105: eps | D105: eps | E105: eps | F105: eps | G105: eps | H105: eps | I105: eps | J105: eps | N105: asocw | O105: 0 | P105: eps | Q105: eps | R105: eps
...

Sheet S2
A1: ="Simulation "&Y1&IF(X1<>""," : "&X1,"") -> Simulation Food_shk : 50%_incr_cchem | X1: =IF(Main!C6<>"",Main!C6,"") -> 50%_incr_cchem | Y1: =Main!A7 -> Food_shk
A3: Commodity shocks | N3: Activity shocks | V3: Factor shocks
B4: World prices | D4: Commodity taxes | G4: Transaction costs | J4: Import | O4: Fix cap? | P4: TFP | Q4: Activity taxes | W4: Factor | X4: Wage | Y4: Factor
B5: Exports | C5: Imports | D5: Exports | E5: Imports | F5: Sales | G5: Exports | H5: Imports | I5: Domestic | J5: subsidy | O5: (1=yes) | Q5: Activity | R5: ValAd. | W5: taxes | X5: rate | Y5: supply
B6: pwe | C6: pwm | D6: te | E6: tm | F6: tq | G6: ice | H6: icm | I6: icd | J6: tms | O6: fixcap | P6: alphava | Q6: ta | R6: tva | W6: tf | X6: wf | Y6: qfs
A7: csorg | B7: eps | C7: eps | D7: eps | E7: eps | F7: eps | G7: eps | H7: eps | I7: eps | J7: eps | N7: asorg | O7: 0 | P7: eps | Q7: eps | R7: eps | V7: flab-rn | W7: eps | X7: eps | Y7: eps
A8: cmaiz | B8: eps | C8: 10 | D8: eps | E8: eps | F8: eps | G8: eps | H8: eps | I8: eps | J8: eps | N8: amaiz | O8: 0 | P8: eps | Q8: eps | R8: eps | V8: flab-rp | W8: eps | X8: eps | Y8: eps
A9: cwhea | B9: eps | C9: 100 | D9: eps | E9: eps | F9: eps | G9: eps | H9: eps | I9: eps | J9: eps | N9: awhea | O9: 0 | P9: eps | Q9: eps | R9: eps | V9: flab-rs | W9: eps | X9: eps | Y9: eps
A10: crice | B10: eps | C10: -13 | D10: eps | E10: eps | F10: eps | G10: eps | H10: eps | I10: eps | J10: eps | N10: arice | O10: 0 | P10: eps | Q10: eps | R10: eps | V10: flab-rt | W10: eps | X10: eps | Y10: eps
A11: cocer | B11: eps | C11: eps | D11: eps | E11: eps | F11: eps | G11: eps | H11: eps | I11: eps | J11: eps | N11: aocer | O11: 0 | P11: eps | Q11: eps | R11: eps | V11: flab-un | W11: eps | X11: eps | Y11: eps
A12: cipot | B12: eps | C12: eps | D12: eps | E12: eps | F12: eps | G12: eps | H12: eps | I12: eps | J12: eps | N12: aipot | O12: 0 | P12: eps | Q12: eps | R12: eps | V12: flab-up | W12: eps | X12: eps | Y12: eps
A13: cspot | B13: eps | C13: eps | D13: eps | E13: eps | F13: eps | G13: eps | H13: eps | I13: eps | J13: eps | N13: aspot | O13: 0 | P13: eps | Q13: eps | R13: eps | V13: flab-us | W13: eps | X13: eps | Y13: eps
A14: ccass | B14: eps | C14: eps | D14: eps | E14: eps | F14: eps | G14: eps | H14: eps | I14: eps | J14: eps | N14: acass | O14: 0 | P14: eps | Q14: eps | R14: eps | V14: flab-ut | W14: eps | X14: eps | Y14: eps
A15: croot | B15: eps | C15: eps | D15: eps | E15: eps | F15: eps | G15: eps | H15: eps | I15: eps | J15: eps | N15: aroot | O15: 0 | P15: eps | Q15: eps | R15: eps | V15: flab-kn | W15: eps | X15: eps | Y15: eps
A16: cbean | B16: eps | C16: eps | D16: eps | E16: eps | F16: eps | G16: eps | H16: eps | I16: eps | J16: eps | N16: abean | O16: 0 | P16: eps | Q16: eps | R16: eps | V16: flab-kp | W16: eps | X16: eps | Y16: eps
A17: cpeas | B17: eps | C17: eps | D17: eps | E17: eps | F17: eps | G17: eps | H17: eps | I17: eps | J17: eps | N17: apeas | O17: 0 | P17: eps | Q17: eps | R17: eps | V17: flab-ks | W17: eps | X17: eps | Y17: eps
A18: cvege | B18: eps | C18: eps | D18: eps | E18: eps | F18: eps | G18: eps | H18: eps | I18: eps | J18: eps | N18: avege | O18: 0 | P18: eps | Q18: eps | R18: eps | V18: flab-kt | W18: eps | X18: eps | Y18: eps
A19: cbanb | B19: eps | C19: eps | D19: eps | E19: eps | F19: eps | G19: eps | H19: eps | I19: eps | J19: eps | N19: abanb | O19: 0 | P19: eps | Q19: eps | R19: eps | V19: flnd | W19: eps | X19: eps | Y19: eps
A20: cbanc | B20: eps | C20: eps | D20: eps | E20: eps | F20: eps | G20: eps | H20: eps | I20: eps | J20: eps | N20: abanc | O20: 0 | P20: eps | Q20: eps | R20: eps | V20: fcap-c | W20: eps | X20: eps | Y20: eps
A21: cbans | B21: eps | C21: eps | D21: eps | E21: eps | F21: eps | G21: eps | H21: eps | I21: eps | J21: eps | N21: abans | O21: 0 | P21: eps | Q21: eps | R21: eps | V21: fcap-l | W21: eps | X21: eps | Y21: eps
A22: cfrui | B22: eps | C22: eps | D22: eps | E22: eps | F22: eps | G22: eps | H22: eps | I22: eps | J22: eps | N22: afrui | O22: 0 | P22: eps | Q22: eps | R22: eps | V22: fcap-m | W22: eps | X22: eps | Y22: eps
A23: cgnut | B23: eps | C23: eps | D23: eps | E23: eps | F23: eps | G23: eps | H23: eps | I23: eps | J23: eps | N23: agnut | O23: 0 | P23: eps | Q23: eps | R23: eps | V23: fcap-n | W23: eps | X23: eps | Y23: eps
A24: csoya | B24: eps | C24: eps | D24: eps | E24: eps | F24: eps | G24: eps | H24: eps | I24: eps | J24: eps | N24: asoya | O24: 0 | P24: eps | Q24: eps | R24: eps
A25: coils | B25: eps | C25: eps | D25: eps | E25: eps | F25: eps | G25: eps | H25: eps | I25: eps | J25: eps | N25: aoils | O25: 0 | P25: eps | Q25: eps | R25: eps | V25: Household income shocks
A26: ccoff | B26: eps | C26: eps | D26: eps | E26: eps | F26: eps | G26: eps | H26: eps | I26: eps | J26: eps | N26: acoff | O26: 0 | P26: eps | Q26: eps | R26: eps | X26: Gov. | Y26: World
A27: cteal | B27: eps | C27: eps | D27: eps | E27: eps | F27: eps | G27: eps | H27: eps | I27: eps | J27: eps | N27: ateal | O27: 0 | P27: eps | Q27: eps | R27: eps | X27: trn | Y27: rem
A28: ctoba | B28: eps | C28: eps | D28: eps | E28: eps | F28: eps | G28: eps | H28: eps | I28: eps | J28: eps | N28: atoba | O28: 0 | P28: eps | Q28: eps | R28: eps | V28: Farm | W28: hhd-r1 | X28: eps | Y28: eps
A29: csugr | B29: eps | C29: eps | D29: eps | E29: eps | F29: eps | G29: eps | H29: eps | I29: eps | J29: eps | N29: asugr | O29: 0 | P29: eps | Q29: eps | R29: eps | W29: hhd-r2 | X29: eps | Y29: eps
A30: cpyre | B30: eps | C30: eps | D30: eps | E30: eps | F30: eps | G30: eps | H30: eps | I30: eps | J30: eps | N30: apyre | O30: 0 | P30: eps | Q30: eps | R30: eps | W30: hhd-r3 | X30: eps | Y30: eps
A31: cocrp | B31: eps | C31: eps | D31: eps | E31: eps | F31: eps | G31: eps | H31: eps | I31: eps | J31: eps | N31: aocrp | O31: 0 | P31: eps | Q31: eps | R31: eps | W31: hhd-r4 | X31: eps | Y31: eps
A32: ccatt | B32: eps | C32: eps | D32: eps | E32: eps | F32: eps | G32: eps | H32: eps | I32: eps | J32: eps | N32: acatt | O32: 0 | P32: eps | Q32: eps | R32: eps | W32: hhd-r5 | X32: eps | Y32: eps
A33: csmlr | B33: eps | C33: eps | D33: eps | E33: eps | F33: eps | G33: eps | H33: eps | I33: eps | J33: eps | N33: asmlr | O33: 0 | P33: eps | Q33: eps | R33: eps | V33: Nonfarm | W33: hhd-u1 | X33: eps | Y33: eps
A34: cpoul | B34: eps | C34: eps | D34: eps | E34: eps | F34: eps | G34: eps | H34: eps | I34: eps | J34: eps | N34: apoul | O34: 0 | P34: eps | Q34: eps | R34: eps | W34: hhd-u2 | X34: eps | Y34: eps
A35: coliv | B35: eps | C35: eps | D35: eps | E35: eps | F35: eps | G35: eps | H35: eps | I35: eps | J35: eps | N35: aoliv | O35: 0 | P35: eps | Q35: eps | R35: eps | W35: hhd-u3 | X35: eps | Y35: eps
A36: cmilk | B36: eps | C36: eps | D36: eps | E36: eps | F36: eps | G36: eps | H36: eps | I36: eps | J36: eps | N36: amilk | O36: 0 | P36: eps | Q36: eps | R36: eps | W36: hhd-u4 | X36: eps | Y36: eps
A37: ceggs | B37: eps | C37: eps | D37: eps | E37: eps | F37: eps | G37: eps | H37: eps | I37: eps | J37: eps | N37: aeggs | O37: 0 | P37: eps | Q37: eps | R37: eps | W37: hhd-u5 | X37: eps | Y37: eps
A38: chony | B38: eps | C38: eps | D38: eps | E38: eps | F38: eps | G38: eps | H38: eps | I38: eps | J38: eps | N38: ahony | O38: 0 | P38: eps | Q38: eps | R38: eps | V38: Urban | W38: hhd-k1 | X38: eps | Y38: eps
A39: chunt | B39: eps | C39: eps | D39: eps | E39: eps | F39: eps | G39: eps | H39: eps | I39: eps | J39: eps | N39: ahunt | O39: 0 | P39: eps | Q39: eps | R39: eps | W39: hhd-k2 | X39: eps | Y39: eps
A40: cfuel | B40: eps | C40: eps | D40: eps | E40: eps | F40: eps | G40: eps | H40: eps | I40: eps | J40: eps | N40: afuel | O40: 0 | P40: eps | Q40: eps | R40: eps | W40: hhd-k3 | X40: eps | Y40: eps
A41: cchar | B41: eps | C41: eps | D41: eps | E41: eps | F41: eps | G41: eps | H41: eps | I41: eps | J41: eps | N41: achar | O41: 0 | P41: eps | Q41: eps | R41: eps | W41: hhd-k4 | X41: eps | Y41: eps
A42: cfore | B42: eps | C42: eps | D42: eps | E42: eps | F42: eps | G42: eps | H42: eps | I42: eps | J42: eps | N42: afore | O42: 0 | P42: eps | Q42: eps | R42: eps | W42: hhd-k5 | X42: eps | Y42: eps
A43: cfish | B43: eps | C43: eps | D43: eps | E43: eps | F43: eps | G43: eps | H43: eps | I43: eps | J43: eps | N43: afish | O43: 0 | P43: eps | Q43: eps | R43: eps
A44: cngas | B44: eps | C44: eps | D44: eps | E44: eps | F44: eps | G44: eps | H44: eps | I44: eps | J44: eps | N44: angas | O44: 0 | P44: eps | Q44: eps | R44: eps | V44: Scalar shocks
A45: cmore | B45: eps | C45: eps | D45: eps | E45: eps | F45: eps | G45: eps | H45: eps | I45: eps | J45: eps | N45: amore | O45: 0 | P45: eps | Q45: eps | R45: eps
A46: comin | B46: eps | C46: eps | D46: eps | E46: eps | F46: eps | G46: eps | H46: eps | I46: eps | J46: eps | N46: aomin | O46: 0 | P46: eps | Q46: eps | R46: eps | V46: Exchange rate | X46: exr | Y46: eps
A47: cmeat | B47: eps | C47: eps | D47: eps | E47: eps | F47: eps | G47: eps | H47: eps | I47: eps | J47: eps | N47: ameat | O47: 0 | P47: eps | Q47: eps | R47: eps | V47: Investment | X47: iadj | Y47: eps
A48: cfsea | B48: eps | C48: eps | D48: eps | E48: eps | F48: eps | G48: eps | H48: eps | I48: eps | J48: eps | N48: afsea | O48: 0 | P48: eps | Q48: eps | R48: eps | V48: Foreign savings | X48: fsav | Y48: eps
A49: cfveg | B49: eps | C49: eps | D49: eps | E49: eps | F49: eps | G49: eps | H49: eps | I49: eps | J49: eps | N49: afveg | O49: 0 | P49: eps | Q49: eps | R49: eps | V49: Gov. savings | X49: gsav | Y49: eps
A50: cfoil | B50: eps | C50: 56 | D50: eps | E50: eps | F50: eps | G50: eps | H50: eps | I50: eps | J50: eps | N50: afoil | O50: 0 | P50: eps | Q50: eps | R50: eps | V50: Gov. spending | X50: gadj | Y50: eps
A51: cdair | B51: eps | C51: eps | D51: eps | E51: eps | F51: eps | G51: eps | H51: eps | I51: eps | J51: eps | N51: adair | O51: 0 | P51: eps | Q51: eps | R51: eps | V51: Savings rates | X51: mpsadj | Y51: eps
A52: cgmll | B52: eps | C52: eps | D52: eps | E52: eps | F52: eps | G52: eps | H52: eps | I52: eps | J52: eps | N52: agmll | O52: 0 | P52: eps | Q52: eps | R52: eps | X52: dmps | Y52: eps
A53: cbake | B53: eps | C53: eps | D53: eps | E53: eps | F53: eps | G53: eps | H53: eps | I53: eps | J53: eps | N53: abake | O53: 0 | P53: eps | Q53: eps | R53: eps | V53: Direct tax rates | X53: tinsadj | Y53: eps
A54: cfeed | B54: eps | C54: eps | D54: eps | E54: eps | F54: eps | G54: eps | H54: eps | I54: eps | J54: eps | N54: afeed | O54: 0 | P54: eps | Q54: eps | R54: eps | X54: dtins | Y54: eps
A55: cfood | B55: eps | C55: eps | D55: eps | E55: eps | F55: eps | G55: eps | H55: eps | I55: eps | J55: eps | N55: afood | O55: 0 | P55: eps | Q55: eps | R55: eps
A56: calco | B56: eps | C56: eps | D56: eps | E56: eps | F56: eps | G56: eps | H56: eps | I56: eps | J56: eps | N56: aalco | O56: 0 | P56: eps | Q56: eps | R56: eps | V56: Institutional closures
A57: cbeve | B57: eps | C57: eps | D57: eps | E57: eps | F57: eps | G57: eps | H57: eps | I57: eps | J57: eps | N57: abeve | O57: 0 | P57: eps | Q57: eps | R57: eps | X57: Savings | Y57: Taxes
A58: cptob | B58: eps | C58: eps | D58: eps | E58: eps | F58: eps | G58: eps | H58: eps | I58: eps | J58: eps | N58: aptob | O58: 0 | P58: eps | Q58: eps | R58: eps | X58: mps | Y58: tins
A59: ctext | B59: eps | C59: eps | D59: eps | E59: eps | F59: eps | G59: eps | H59: eps | I59: eps | J59: eps | N59: atext | O59: 0 | P59: eps | Q59: eps | R59: eps | V59: Enter. | W59: ent | X59: 1 | Y59: 1
A60: cwood | B60: eps | C60: eps | D60: eps | E60: eps | F60: eps | G60: eps | H60: eps | I60: eps | J60: eps | N60: awood | O60: 0 | P60: eps | Q60: eps | R60: eps | V60: House. | W60: hhd-r1 | X60: 1 | Y60: 1
A61: cprnt | B61: eps | C61: eps | D61: eps | E61: eps | F61: eps | G61: eps | H61: eps | I61: eps | J61: eps | N61: aprnt | O61: 0 | P61: eps | Q61: eps | R61: eps | W61: hhd-r2 | X61: 1 | Y61: 1
A62: cpetr | B62: eps | C62: eps | D62: eps | E62: eps | F62: eps | G62: eps | H62: eps | I62: eps | J62: eps | N62: apetr | O62: 0 | P62: eps | Q62: eps | R62: eps | W62: hhd-r3 | X62: 1 | Y62: 1
A63: cchem | B63: eps | C63: eps | D63: eps | E63: eps | F63: eps | G63: eps | H63: eps | I63: eps | J63: eps | N63: achem | O63: 0 | P63: eps | Q63: eps | R63: eps | W63: hhd-r4 | X63: 1 | Y63: 1
A64: cphar | B64: eps | C64: eps | D64: eps | E64: eps | F64: eps | G64: eps | H64: eps | I64: eps | J64: eps | N64: aphar | O64: 0 | P64: eps | Q64: eps | R64: eps | W64: hhd-r5 | X64: 1 | Y64: 1
A65: cprub | B65: eps | C65: eps | D65: eps | E65: eps | F65: eps | G65: eps | H65: eps | I65: eps | J65: eps | N65: aprub | O65: 0 | P65: eps | Q65: eps | R65: eps | W65: hhd-u1 | X65: 1 | Y65: 1
A66: cnmet | B66: eps | C66: eps | D66: eps | E66: eps | F66: eps | G66: eps | H66: eps | I66: eps | J66: eps | N66: anmet | O66: 0 | P66: eps | Q66: eps | R66: eps | W66: hhd-u2 | X66: 1 | Y66: 1
A67: cceme | B67: eps | C67: eps | D67: eps | E67: eps | F67: eps | G67: eps | H67: eps | I67: eps | J67: eps | N67: aceme | O67: 0 | P67: eps | Q67: eps | R67: eps | W67: hhd-u3 | X67: 1 | Y67: 1
A68: cclay | B68: eps | C68: eps | D68: eps | E68: eps | F68: eps | G68: eps | H68: eps | I68: eps | J68: eps | N68: aclay | O68: 0 | P68: eps | Q68: eps | R68: eps | W68: hhd-u4 | X68: 1 | Y68: 1
A69: cmetl | B69: eps | C69: eps | D69: eps | E69: eps | F69: eps | G69: eps | H69: eps | I69: eps | J69: eps | N69: ametl | O69: 0 | P69: eps | Q69: eps | R69: eps | W69: hhd-u5 | X69: 1 | Y69: 1
A70: cmach | B70: eps | C70: eps | D70: eps | E70: eps | F70: eps | G70: eps | H70: eps | I70: eps | J70: eps | N70: amach | O70: 0 | P70: eps | Q70: eps | R70: eps | W70: hhd-k1 | X70: 1 | Y70: 1
A71: cvehi | B71: eps | C71: eps | D71: eps | E71: eps | F71: eps | G71: eps | H71: eps | I71: eps | J71: eps | N71: avehi | O71: 0 | P71: eps | Q71: eps | R71: eps | W71: hhd-k2 | X71: 1 | Y71: 1
A72: cfurn | B72: eps | C72: eps | D72: eps | E72: eps | F72: eps | G72: eps | H72: eps | I72: eps | J72: eps | N72: afurn | O72: 0 | P72: eps | Q72: eps | R72: eps | W72: hhd-k3 | X72: 1 | Y72: 1
... A74: crepr | B74: eps | C74: eps | D74: eps | E74: eps | F74: eps | G74: eps | H74: eps | I74: eps | J74: eps | N74: arepr | O74: 0 | P74: eps | Q74: eps | R74: eps | W74: hhd-k5 | X74: 1 | Y74: 1
A75: celec | B75: eps | C75: eps | D75: eps | E75: eps | F75: eps | G75: eps | H75: eps | I75: eps | J75: eps | N75: aelec | O75: 0 | P75: eps | Q75: eps | R75: eps
A76: cwatr | B76: eps | C76: eps | D76: eps | E76: eps | F76: eps | G76: eps | H76: eps | I76: eps | J76: eps | N76: awatr | O76: 0 | P76: eps | Q76: eps | R76: eps | V76: Macroeconomic closures
A77: cwast | B77: eps | C77: eps | D77: eps | E77: eps | F77: eps | G77: eps | H77: eps | I77: eps | J77: eps | N77: awast | O77: 0 | P77: eps | Q77: eps | R77: eps | V77: Num. | W77: dum | X77: =SUMIF(Main!G4:O4,Y1,Main!G5:O5) -> 2
A78: ccons | B78: eps | C78: eps | D78: eps | E78: eps | F78: eps | G78: eps | H78: eps | I78: eps | J78: eps | N78: acons | O78: 0 | P78: eps | Q78: eps | R78: eps | V78: Sav-Inv. | W78: s-i | X78: =SUMIF(Main!G4:O4,Y1,Main!G6:O6) -> 3
A79: ccont | B79: eps | C79: eps | D79: eps | E79: eps | F79: eps | G79: eps | H79: eps | I79: eps | J79: eps | N79: acont | O79: 0 | P79: eps | Q79: eps | R79: eps | V79: Gov. | W79: gov | X79: =SUMIF(Main!G4:O4,Y1,Main!G7:O7) -> 1
A80: cvehr | B80: eps | C80: eps | D80: eps | E80: eps | F80: eps | G80: eps | H80: eps | I80: eps | J80: eps | N80: avehr | O80: 0 | P80: eps | Q80: eps | R80: eps | V80: Cur. a/c | W80: row | X80: =SUMIF(Main!G4:O4,Y1,Main!G8:O8) -> 1
A81: cveht | B81: eps | C81: eps | D81: eps | E81: eps | F81: eps | G81: eps | H81: eps | I81: eps | J81: eps | N81: aveht | O81: 0 | P81: eps | Q81: eps | R81: eps
A82: ctrdw | B82: eps | C82: eps | D82: eps | E82: eps | F82: eps | G82: eps | H82: eps | I82: eps | J82: eps | N82: atrdw | O82: 0 | P82: eps | Q82: eps | R82: eps | V82: Factor market closures
A83: ctrdr | B83: eps | C83: eps | D83: eps | E83: eps | F83: eps | G83: eps | H83: eps | I83: eps | J83: eps | N83: atrdr | O83: 0 | P83: eps | Q83: eps | R83: eps | V83: Labor | W83: flab-rn | X83: =SUMIF(Main!G11:O11,'S2'!Y1,Main!G12:O12) -> 3
A84: ctrnl | B84: eps | C84: eps | D84: eps | E84: eps | F84: eps | G84: eps | H84: eps | I84: eps | J84: eps | N84: atrnl | O84: 0 | P84: eps | Q84: eps | R84: eps | W84: flab-rp | X84: =SUMIF(Main!G11:O11,'S2'!Y1,Main!G13:O13) -> 3
A85: ctrna | B85: eps | C85: eps | D85: eps | E85: eps | F85: eps | G85: eps | H85: eps | I85: eps | J85: eps | N85: atrna | O85: 0 | P85: eps | Q85: eps | R85: eps | W85: flab-rs | X85: =SUMIF(Main!G11:O11,'S2'!Y1,Main!G14:O14) -> 1
A86: ctrns | B86: eps | C86: eps | D86: eps | E86: eps | F86: eps | G86: eps | H86: eps | I86: eps | J86: eps | N86: atrns | O86: 0 | P86: eps | Q86: eps | R86: eps | W86: flab-rt | X86: =SUMIF(Main!G11:O11,'S2'!Y1,Main!G15:O15) -> 1
A87: cpost | B87: eps | C87: eps | D87: eps | E87: eps | F87: eps | G87: eps | H87: eps | I87: eps | J87: eps | N87: apost | O87: 0 | P87: eps | Q87: eps | R87: eps | W87: flab-un | X87: =SUMIF(Main!G11:O11,'S2'!Y1,Main!G16:O16) -> 3
A88: chotl | B88: eps | C88: eps | D88: eps | E88: eps | F88: eps | G88: eps | H88: eps | I88: eps | J88: eps | N88: ahotl | O88: 0 | P88: eps | Q88: eps | R88: eps | W88: flab-up | X88: =SUMIF(Main!G11:O11,'S2'!Y1,Main!G17:O17) -> 3
A89: cpubl | B89: eps | C89: eps | D89: eps | E89: eps | F89: eps | G89: eps | H89: eps | I89: eps | J89: eps | N89: apubl | O89: 0 | P89: eps | Q89: eps | R89: eps | W89: flab-us | X89: =SUMIF(Main!G11:O11,'S2'!Y1,Main!G18:O18) -> 1
A90: ccomm | B90: eps | C90: eps | D90: eps | E90: eps | F90: eps | G90: eps | H90: eps | I90: eps | J90: eps | N90: acomm | O90: 0 | P90: eps | Q90: eps | R90: eps | W90: flab-ut | X90: =SUMIF(Main!G11:O11,'S2'!Y1,Main!G19:O19) -> 1
A91: cinfo | B91: eps | C91: eps | D91: eps | E91: eps | F91: eps | G91: eps | H91: eps | I91: eps | J91: eps | N91: ainfo | O91: 0 | P91: eps | Q91: eps | R91: eps | W91: flab-kn | X91: =SUMIF(Main!G11:O11,'S2'!Y1,Main!G20:O20) -> 3
A92: cbank | B92: eps | C92: eps | D92: eps | E92: eps | F92: eps | G92: eps | H92: eps | I92: eps | J92: eps | N92: abank | O92: 0 | P92: eps | Q92: eps | R92: eps | W92: flab-kp | X92: =SUMIF(Main!G11:O11,'S2'!Y1,Main!G21:O21) -> 3
A93: cinsu | B93: eps | C93: eps | D93: eps | E93: eps | F93: eps | G93: eps | H93: eps | I93: eps | J93: eps | N93: ainsu | O93: 0 | P93: eps | Q93: eps | R93: eps | W93: flab-ks | X93: =SUMIF(Main!G11:O11,'S2'!Y1,Main!G22:O22) -> 1
A94: cofsv | B94: eps | C94: eps | D94: eps | E94: eps | F94: eps | G94: eps | H94: eps | I94: eps | J94: eps | N94: aofsv | O94: 0 | P94: eps | Q94: eps | R94: eps | W94: flab-kt | X94: =SUMIF(Main!G11:O11,'S2'!Y1,Main!G23:O23) -> 1
A95: crent | B95: eps | C95: eps | D95: eps | E95: eps | F95: eps | G95: eps | H95: eps | I95: eps | J95: eps | N95: arent | O95: 0 | P95: eps | Q95: eps | R95: eps | V95: Land | W95: flnd | X95: =SUMIF(Main!G11:O11,'S2'!Y1,Main!G24:O24) -> 1
A96: creal | B96: eps | C96: eps | D96: eps | E96: eps | F96: eps | G96: eps | H96: eps | I96: eps | J96: eps | N96: areal | O96: 0 | P96: eps | Q96: eps | R96: eps | V96: Capital | W96: fcap-c | X96: =SUMIF(Main!G11:O11,'S2'!Y1,Main!G25:O25) -> 2
A97: clegl | B97: eps | C97: eps | D97: eps | E97: eps | F97: eps | G97: eps | H97: eps | I97: eps | J97: eps | N97: alegl | O97: 0 | P97: eps | Q97: eps | R97: eps | W97: fcap-l | X97: =SUMIF(Main!G11:O11,'S2'!Y1,Main!G26:O26) -> 2
A98: cenga | B98: eps | C98: eps | D98: eps | E98: eps | F98: eps | G98: eps | H98: eps | I98: eps | J98: eps | N98: aenga | O98: 0 | P98: eps | Q98: eps | R98: eps | W98: fcap-m | X98: =SUMIF(Main!G11:O11,'S2'!Y1,Main!G27:O27) -> 2
A99: cprod | B99: eps | C99: eps | D99: eps | E99: eps | F99: eps | G99: eps | H99: eps | I99: eps | J99: eps | N99: aprod | O99: 0 | P99: eps | Q99: eps | R99: eps | W99: fcap-n | X99: =SUMIF(Main!G11:O11,'S2'!Y1,Main!G28:O28) -> 2
A100: ctrvl | B100: eps | C100: eps | D100: eps | E100: eps | F100: eps | G100: eps | H100: eps | I100: eps | J100: eps | N100: atrvl | O100: 0 | P100: eps | Q100: eps | R100: eps
A101: cobsv | B101: eps | C101: eps | D101: eps | E101: eps | F101: eps | G101: eps | H101: eps | I101: eps | J101: eps | N101: aobsv | O101: 0 | P101: eps | Q101: eps | R101: eps
A102: cpadm | B102: eps | C102: eps | D102: eps | E102: eps | F102: eps | G102: eps | H102: eps | I102: eps | J102: eps | N102: apadm | O102: 0 | P102: eps | Q102: eps | R102: eps
...

Sheet S3
A1: ="Simulation "&Y1&IF(X1<>""," : "&X1,"") -> Simulation Fuel&gas_shk : 50%_incr_cchem | X1: =IF(Main!C6<>"",Main!C6,"") -> 50%_incr_cchem | Y1: =Main!A8 -> Fuel&gas_shk
A3: Commodity shocks | N3: Activity shocks | V3: Factor shocks
B4: World prices | D4: Commodity taxes | G4: Transaction costs | J4: Import | O4: Fix cap? | P4: TFP | Q4: Activity taxes | W4: Factor | X4: Wage | Y4: Factor
B5: Exports | C5: Imports | D5: Exports | E5: Imports | F5: Sales | G5: Exports | H5: Imports | I5: Domestic | J5: subsidy | O5: (1=yes) | Q5: Activity | R5: ValAd. | W5: taxes | X5: rate | Y5: supply
B6: pwe | C6: pwm | D6: te | E6: tm | F6: tq | G6: ice | H6: icm | I6: icd | J6: tms | O6: fixcap | P6: alphava | Q6: ta | R6: tva | W6: tf | X6: wf | Y6: qfs
A7: csorg | B7: eps | C7: eps | D7: eps | E7: eps | F7: eps | G7: eps | H7: eps | I7: eps | J7: eps | N7: asorg | O7: 0 | P7: eps | Q7: eps | R7: eps | V7: flab-rn | W7: eps | X7: eps | Y7: eps
A8: cmaiz | B8: eps | C8: eps | D8: eps | E8: eps | F8: eps | G8: eps | H8: eps | I8: eps | J8: eps | N8: amaiz | O8: 0 | P8: eps | Q8: eps | R8: eps | V8: flab-rp | W8: eps | X8: eps | Y8: eps
A9: cwhea | B9: eps | C9: eps | D9: eps | E9: eps | F9: eps | G9: eps | H9: eps | I9: eps | J9: eps | N9: awhea | O9: 0 | P9: eps | Q9: eps | R9: eps | V9: flab-rs | W9: eps | X9: eps | Y9: eps
A10: crice | B10: eps | C10: eps | D10: eps | E10: eps | F10: eps | G10: eps | H10: eps | I10: eps | J10: eps | N10: arice | O10: 0 | P10: eps | Q10: eps | R10: eps | V10: flab-rt | W10: eps | X10: eps | Y10: eps
A11: cocer | B11: eps | C11: eps | D11: eps | E11: eps | F11: eps | G11: eps | H11: eps | I11: eps | J11: eps | N11: aocer | O11: 0 | P11: eps | Q11: eps | R11: eps | V11: flab-un | W11: eps | X11: eps | Y11: eps
A12: cipot | B12: eps | C12: eps | D12: eps | E12: eps | F12: eps | G12: eps | H12: eps | I12: eps | J12: eps | N12: aipot | O12: 0 | P12: eps | Q12: eps | R12: eps | V12: flab-up | W12: eps | X12: eps | Y12: eps
A13: cspot | B13: eps | C13: eps | D13: eps | E13: eps | F13: eps | G13: eps | H13: eps | I13: eps | J13: eps | N13: aspot | O13: 0 | P13: eps | Q13: eps | R13: eps | V13: flab-us | W13: eps | X13: eps | Y13: eps
A14: ccass | B14: eps | C14: eps | D14: eps | E14: eps | F14: eps | G14: eps | H14: eps | I14: eps | J14: eps | N14: acass | O14: 0 | P14: eps | Q14: eps | R14: eps | V14: flab-ut | W14: eps | X14: eps | Y14: eps
A15: croot | B15: eps | C15: eps | D15: eps | E15: eps | F15: eps | G15: eps | H15: eps | I15: eps | J15: eps | N15: aroot | O15: 0 | P15: eps | Q15: eps | R15: eps | V15: flab-kn | W15: eps | X15: eps | Y15: eps
A16: cbean | B16: eps | C16: eps | D16: eps | E16: eps | F16: eps | G16: eps | H16: eps | I16: eps | J16: eps | N16: abean | O16: 0 | P16: eps | Q16: eps | R16: eps | V16: flab-kp | W16: eps | X16: eps | Y16: eps
A17: cpeas | B17: eps | C17: eps | D17: eps | E17: eps | F17: eps | G17: eps | H17: eps | I17: eps | J17: eps | N17: apeas | O17: 0 | P17: eps | Q17: eps | R17: eps | V17: flab-ks | W17: eps | X17: eps | Y17: eps
A18: cvege | B18: eps | C18: eps | D18: eps | E18: eps | F18: eps | G18: eps | H18: eps | I18: eps | J18: eps | N18: avege | O18: 0 | P18: eps | Q18: eps | R18: eps | V18: flab-kt | W18: eps | X18: eps | Y18: eps
... A23: cgnut | B23: eps | C23: eps | D23: eps | E23: eps | F23: eps | G23: eps | H23: eps | I23: eps | J23: eps | N23: agnut | O23: 0 | P23: eps | Q23: eps | R23: eps | V23: fcap-n | W23: eps | X23: eps | Y23: eps
A24: csoya | B24: eps | C24: eps | D24: eps | E24: eps | F24: eps | G24: eps | H24: eps | I24: eps | J24: eps | N24: asoya | O24: 0 | P24: eps | Q24: eps | R24: eps
A25: coils | B25: eps | C25: eps | D25: eps | E25: eps | F25: eps | G25: eps | H25: eps | I25: eps | J25: eps | N25: aoils | O25: 0 | P25: eps | Q25: eps | R25: eps | V25: Household income shocks
A26: ccoff | B26: eps | C26: eps | D26: eps | E26: eps | F26: eps | G26: eps | H26: eps | I26: eps | J26: eps | N26: acoff | O26: 0 | P26: eps | Q26: eps | R26: eps | X26: Gov. | Y26: World
A27: cteal | B27: eps | C27: eps | D27: eps | E27: eps | F27: eps | G27: eps | H27: eps | I27: eps | J27: eps | N27: ateal | O27: 0 | P27: eps | Q27: eps | R27: eps | X27: trn | Y27: rem
A28: ctoba | B28: eps | C28: eps | D28: eps | E28: eps | F28: eps | G28: eps | H28: eps | I28: eps | J28: eps | N28: atoba | O28: 0 | P28: eps | Q28: eps | R28: eps | V28: Farm | W28: hhd-r1 | X28: eps | Y28: eps
A29: csugr | B29: eps | C29: eps | D29: eps | E29: eps | F29: eps | G29: eps | H29: eps | I29: eps | J29: eps | N29: asugr | O29: 0 | P29: eps | Q29: eps | R29: eps | W29: hhd-r2 | X29: eps | Y29: eps
A30: cpyre | B30: eps | C30: eps | D30: eps | E30: eps | F30: eps | G30: eps | H30: eps | I30: eps | J30: eps | N30: apyre | O30: 0 | P30: eps | Q30: eps | R30: eps | W30: hhd-r3 | X30: eps | Y30: eps
A31: cocrp | B31: eps | C31: eps | D31: eps | E31: eps | F31: eps | G31: eps | H31: eps | I31: eps | J31: eps | N31: aocrp | O31: 0 | P31: eps | Q31: eps | R31: eps | W31: hhd-r4 | X31: eps | Y31: eps
A32: ccatt | B32: eps | C32: eps | D32: eps | E32: eps | F32: eps | G32: eps | H32: eps | I32: eps | J32: eps | N32: acatt | O32: 0 | P32: eps | Q32: eps | R32: eps | W32: hhd-r5 | X32: eps | Y32: eps
A33: csmlr | B33: eps | C33: eps | D33: eps | E33: eps | F33: eps | G33: eps | H33: eps | I33: eps | J33: eps | N33: asmlr | O33: 0 | P33: eps | Q33: eps | R33: eps | V33: Nonfarm | W33: hhd-u1 | X33: eps | Y33: eps
A34: cpoul | B34: eps | C34: eps | D34: eps | E34: eps | F34: eps | G34: eps | H34: eps | I34: eps | J34: eps | N34: apoul | O34: 0 | P34: eps | Q34: eps | R34: eps | W34: hhd-u2 | X34: eps | Y34: eps
A35: coliv | B35: eps | C35: eps | D35: eps | E35: eps | F35: eps | G35: eps | H35: eps | I35: eps | J35: eps | N35: aoliv | O35: 0 | P35: eps | Q35: eps | R35: eps | W35: hhd-u3 | X35: eps | Y35: eps
A36: cmilk | B36: eps | C36: eps | D36: eps | E36: eps | F36: eps | G36: eps | H36: eps | I36: eps | J36: eps | N36: amilk | O36: 0 | P36: eps | Q36: eps | R36: eps | W36: hhd-u4 | X36: eps | Y36: eps
A37: ceggs | B37: eps | C37: eps | D37: eps | E37: eps | F37: eps | G37: eps | H37: eps | I37: eps | J37: eps | N37: aeggs | O37: 0 | P37: eps | Q37: eps | R37: eps | W37: hhd-u5 | X37: eps | Y37: eps
A38: chony | B38: eps | C38: eps | D38: eps | E38: eps | F38: eps | G38: eps | H38: eps | I38: eps | J38: eps | N38: ahony | O38: 0 | P38: eps | Q38: eps | R38: eps | V38: Urban | W38: hhd-k1 | X38: eps | Y38: eps
A39: chunt | B39: eps | C39: eps | D39: eps | E39: eps | F39: eps | G39: eps | H39: eps | I39: eps | J39: eps | N39: ahunt | O39: 0 | P39: eps | Q39: eps | R39: eps | W39: hhd-k2 | X39: eps | Y39: eps
A40: cfuel | B40: eps | C40: eps | D40: eps | E40: eps | F40: eps | G40: eps | H40: eps | I40: eps | J40: eps | N40: afuel | O40: 0 | P40: eps | Q40: eps | R40: eps | W40: hhd-k3 | X40: eps | Y40: eps
A41: cchar | B41: eps | C41: eps | D41: eps | E41: eps | F41: eps | G41: eps | H41: eps | I41: eps | J41: eps | N41: achar | O41: 0 | P41: eps | Q41: eps | R41: eps | W41: hhd-k4 | X41: eps | Y41: eps
A42: cfore | B42: eps | C42: eps | D42: eps | E42: eps | F42: eps | G42: eps | H42: eps | I42: eps | J42: eps | N42: afore | O42: 0 | P42: eps | Q42: eps | R42: eps | W42: hhd-k5 | X42: eps | Y42: eps
A43: cfish | B43: eps | C43: eps | D43: eps | E43: eps | F43: eps | G43: eps | H43: eps | I43: eps | J43: eps | N43: afish | O43: 0 | P43: eps | Q43: eps | R43: eps
A44: cngas | B44: eps | C44: 34 | D44: eps | E44: eps | F44: eps | G44: eps | H44: eps | I44: eps | J44: eps | N44: angas | O44: 0 | P44: eps | Q44: eps | R44: eps | V44: Scalar shocks
A45: cmore | B45: eps | C45: eps | D45: eps | E45: eps | F45: eps | G45: eps | H45: eps | I45: eps | J45: eps | N45: amore | O45: 0 | P45: eps | Q45: eps | R45: eps
A46: comin | B46: eps | C46: eps | D46: eps | E46: eps | F46: eps | G46: eps | H46: eps | I46: eps | J46: eps | N46: aomin | O46: 0 | P46: eps | Q46: eps | R46: eps | V46: Exchange rate | X46: exr | Y46: eps
A47: cmeat | B47: eps | C47: eps | D47: eps | E47: eps | F47: eps | G47: eps | H47: eps | I47: eps | J47: eps | N47: ameat | O47: 0 | P47: eps | Q47: eps | R47: eps | V47: Investment | X47: iadj | Y47: eps
A48: cfsea | B48: eps | C48: eps | D48: eps | E48: eps | F48: eps | G48: eps | H48: eps | I48: eps | J48: eps | N48: afsea | O48: 0 | P48: eps | Q48: eps | R48: eps | V48: Foreign savings | X48: fsav | Y48: eps
A49: cfveg | B49: eps | C49: eps | D49: eps | E49: eps | F49: eps | G49: eps | H49: eps | I49: eps | J49: eps | N49: afveg | O49: 0 | P49: eps | Q49: eps | R49: eps | V49: Gov. savings | X49: gsav | Y49: eps
A50: cfoil | B50: eps | C50: eps | D50: eps | E50: eps | F50: eps | G50: eps | H50: eps | I50: eps | J50: eps | N50: afoil | O50: 0 | P50: eps | Q50: eps | R50: eps | V50: Gov. spending | X50: gadj | Y50: eps
A51: cdair | B51: eps | C51: eps | D51: eps | E51: eps | F51: eps | G51: eps | H51: eps | I51: eps | J51: eps | N51: adair | O51: 0 | P51: eps | Q51: eps | R51: eps | V51: Savings rates | X51: mpsadj | Y51: eps
A52: cgmll | B52: eps | C52: eps | D52: eps | E52: eps | F52: eps | G52: eps | H52: eps | I52: eps | J52: eps | N52: agmll | O52: 0 | P52: eps | Q52: eps | R52: eps | X52: dmps | Y52: eps
A53: cbake | B53: eps | C53: eps | D53: eps | E53: eps | F53: eps | G53: eps | H53: eps | I53: eps | J53: eps | N53: abake | O53: 0 | P53: eps | Q53: eps | R53: eps | V53: Direct tax rates | X53: tinsadj | Y53: eps
A54: cfeed | B54: eps | C54: eps | D54: eps | E54: eps | F54: eps | G54: eps | H54: eps | I54: eps | J54: eps | N54: afeed | O54: 0 | P54: eps | Q54: eps | R54: eps | X54: dtins | Y54: eps
A55: cfood | B55: eps | C55: eps | D55: eps | E55: eps | F55: eps | G55: eps | H55: eps | I55: eps | J55: eps | N55: afood | O55: 0 | P55: eps | Q55: eps | R55: eps
A56: calco | B56: eps | C56: eps | D56: eps | E56: eps | F56: eps | G56: eps | H56: eps | I56: eps | J56: eps | N56: aalco | O56: 0 | P56: eps | Q56: eps | R56: eps | V56: Institutional closures
A57: cbeve | B57: eps | C57: eps | D57: eps | E57: eps | F57: eps | G57: eps | H57: eps | I57: eps | J57: eps | N57: abeve | O57: 0 | P57: eps | Q57: eps | R57: eps | X57: Savings | Y57: Taxes
A58: cptob | B58: eps | C58: eps | D58: eps | E58: eps | F58: eps | G58: eps | H58: eps | I58: eps | J58: eps | N58: aptob | O58: 0 | P58: eps | Q58: eps | R58: eps | X58: mps | Y58: tins
A59: ctext | B59: eps | C59: eps | D59: eps | E59: eps | F59: eps | G59: eps | H59: eps | I59: eps | J59: eps | N59: atext | O59: 0 | P59: eps | Q59: eps | R59: eps | V59: Enter. | W59: ent | X59: 1 | Y59: 1
A60: cwood | B60: eps | C60: eps | D60: eps | E60: eps | F60: eps | G60: eps | H60: eps | I60: eps | J60: eps | N60: awood | O60: 0 | P60: eps | Q60: eps | R60: eps | V60: House. | W60: hhd-r1 | X60: 1 | Y60: 1
A61: cprnt | B61: eps | C61: eps | D61: eps | E61: eps | F61: eps | G61: eps | H61: eps | I61: eps | J61: eps | N61: aprnt | O61: 0 | P61: eps | Q61: eps | R61: eps | W61: hhd-r2 | X61: 1 | Y61: 1
A62: cpetr | B62: eps | C62: 88 | D62: eps | E62: eps | F62: eps | G62: eps | H62: eps | I62: eps | J62: eps | N62: apetr | O62: 0 | P62: eps | Q62: eps | R62: eps | W62: hhd-r3 | X62: 1 | Y62: 1
A63: cchem | B63: eps | C63: eps | D63: eps | E63: eps | F63: eps | G63: eps | H63: eps | I63: eps | J63: eps | N63: achem | O63: 0 | P63: eps | Q63: eps | R63: eps | W63: hhd-r4 | X63: 1 | Y63: 1
A64: cphar | B64: eps | C64: eps | D64: eps | E64: eps | F64: eps | G64: eps | H64: eps | I64: eps | J64: eps | N64: aphar | O64: 0 | P64: eps | Q64: eps | R64: eps | W64: hhd-r5 | X64: 1 | Y64: 1
A65: cprub | B65: eps | C65: eps | D65: eps | E65: eps | F65: eps | G65: eps | H65: eps | I65: eps | J65: eps | N65: aprub | O65: 0 | P65: eps | Q65: eps | R65: eps | W65: hhd-u1 | X65: 1 | Y65: 1
A66: cnmet | B66: eps | C66: eps | D66: eps | E66: eps | F66: eps | G66: eps | H66: eps | I66: eps | J66: eps | N66: anmet | O66: 0 | P66: eps | Q66: eps | R66: eps | W66: hhd-u2 | X66: 1 | Y66: 1
A67: cceme | B67: eps | C67: eps | D67: eps | E67: eps | F67: eps | G67: eps | H67: eps | I67: eps | J67: eps | N67: aceme | O67: 0 | P67: eps | Q67: eps | R67: eps | W67: hhd-u3 | X67: 1 | Y67: 1
A68: cclay | B68: eps | C68: eps | D68: eps | E68: eps | F68: eps | G68: eps | H68: eps | I68: eps | J68: eps | N68: aclay | O68: 0 | P68: eps | Q68: eps | R68: eps | W68: hhd-u4 | X68: 1 | Y68: 1
A69: cmetl | B69: eps | C69: eps | D69: eps | E69: eps | F69: eps | G69: eps | H69: eps | I69: eps | J69: eps | N69: ametl | O69: 0 | P69: eps | Q69: eps | R69: eps | W69: hhd-u5 | X69: 1 | Y69: 1
A70: cmach | B70: eps | C70: eps | D70: eps | E70: eps | F70: eps | G70: eps | H70: eps | I70: eps | J70: eps | N70: amach | O70: 0 | P70: eps | Q70: eps | R70: eps | W70: hhd-k1 | X70: 1 | Y70: 1
A71: cvehi | B71: eps | C71: eps | D71: eps | E71: eps | F71: eps | G71: eps | H71: eps | I71: eps | J71: eps | N71: avehi | O71: 0 | P71: eps | Q71: eps | R71: eps | W71: hhd-k2 | X71: 1 | Y71: 1
A72: cfurn | B72: eps | C72: eps | D72: eps | E72: eps | F72: eps | G72: eps | H72: eps | I72: eps | J72: eps | N72: afurn | O72: 0 | P72: eps | Q72: eps | R72: eps | W72: hhd-k3 | X72: 1 | Y72: 1
A73: coman | B73: eps | C73: eps | D73: eps | E73: eps | F73: eps | G73: eps | H73: eps | I73: eps | J73: eps | N73: aoman | O73: 0 | P73: eps | Q73: eps | R73: eps | W73: hhd-k4 | X73: 1 | Y73: 1
A74: crepr | B74: eps | C74: eps | D74: eps | E74: eps | F74: eps | G74: eps | H74: eps | I74: eps | J74: eps | N74: arepr | O74: 0 | P74: eps | Q74: eps | R74: eps | W74: hhd-k5 | X74: 1 | Y74: 1
A75: celec | B75: eps | C75: eps | D75: eps | E75: eps | F75: eps | G75: eps | H75: eps | I75: eps | J75: eps | N75: aelec | O75: 0 | P75: eps | Q75: eps | R75: eps
A76: cwatr | B76: eps | C76: eps | D76: eps | E76: eps | F76: eps | G76: eps | H76: eps | I76: eps | J76: eps | N76: awatr | O76: 0 | P76: eps | Q76: eps | R76: eps | V76: Macroeconomic closures
A77: cwast | B77: eps | C77: eps | D77: eps | E77: eps | F77: eps | G77: eps | H77: eps | I77: eps | J77: eps | N77: awast | O77: 0 | P77: eps | Q77: eps | R77: eps | V77: Num. | W77: dum | X77: =SUMIF(Main!G4:O4,Y1,Main!G5:O5) -> 2
A78: ccons | B78: eps | C78: eps | D78: eps | E78: eps | F78: eps | G78: eps | H78: eps | I78: eps | J78: eps | N78: acons | O78: 0 | P78: eps | Q78: eps | R78: eps | V78: Sav-Inv. | W78: s-i | X78: =SUMIF(Main!G4:O4,Y1,Main!G6:O6) -> 3
A79: ccont | B79: eps | C79: eps | D79: eps | E79: eps | F79: eps | G79: eps | H79: eps | I79: eps | J79: eps | N79: acont | O79: 0 | P79: eps | Q79: eps | R79: eps | V79: Gov. | W79: gov | X79: =SUMIF(Main!G4:O4,Y1,Main!G7:O7) -> 1
A80: cvehr | B80: eps | C80: eps | D80: eps | E80: eps | F80: eps | G80: eps | H80: eps | I80: eps | J80: eps | N80: avehr | O80: 0 | P80: eps | Q80: eps | R80: eps | V80: Cur. a/c | W80: row | X80: =SUMIF(Main!G4:O4,Y1,Main!G8:O8) -> 1
A81: cveht | B81: eps | C81: eps | D81: eps | E81: eps | F81: eps | G81: eps | H81: eps | I81: eps | J81: eps | N81: aveht | O81: 0 | P81: eps | Q81: eps | R81: eps
A82: ctrdw | B82: eps | C82: eps | D82: eps | E82: eps | F82: eps | G82: eps | H82: eps | I82: eps | J82: eps | N82: atrdw | O82: 0 | P82: eps | Q82: eps | R82: eps | V82: Factor market closures
A83: ctrdr | B83: eps | C83: eps | D83: eps | E83: eps | F83: eps | G83: eps | H83: eps | I83: eps | J83: eps | N83: atrdr | O83: 0 | P83: eps | Q83: eps | R83: eps | V83: Labor | W83: flab-rn | X83: =SUMIF(Main!G11:O11,'S3'!Y1,Main!G12:O12) -> 3
A84: ctrnl | B84: eps | C84: eps | D84: eps | E84: eps | F84: eps | G84: eps | H84: eps | I84: eps | J84: eps | N84: atrnl | O84: 0 | P84: eps | Q84: eps | R84: eps | W84: flab-rp | X84: =SUMIF(Main!G11:O11,'S3'!Y1,Main!G13:O13) -> 3
A85: ctrna | B85: eps | C85: eps | D85: eps | E85: eps | F85: eps | G85: eps | H85: eps | I85: eps | J85: eps | N85: atrna | O85: 0 | P85: eps | Q85: eps | R85: eps | W85: flab-rs | X85: =SUMIF(Main!G11:O11,'S3'!Y1,Main!G14:O14) -> 1
A86: ctrns | B86: eps | C86: eps | D86: eps | E86: eps | F86: eps | G86: eps | H86: eps | I86: eps | J86: eps | N86: atrns | O86: 0 | P86: eps | Q86: eps | R86: eps | W86: flab-rt | X86: =SUMIF(Main!G11:O11,'S3'!Y1,Main!G15:O15) -> 1
A87: cpost | B87: eps | C87: eps | D87: eps | E87: eps | F87: eps | G87: eps | H87: eps | I87: eps | J87: eps | N87: apost | O87: 0 | P87: eps | Q87: eps | R87: eps | W87: flab-un | X87: =SUMIF(Main!G11:O11,'S3'!Y1,Main!G16:O16) -> 3
A88: chotl | B88: eps | C88: eps | D88: eps | E88: eps | F88: eps | G88: eps | H88: eps | I88: eps | J88: eps | N88: ahotl | O88: 0 | P88: eps | Q88: eps | R88: eps | W88: flab-up | X88: =SUMIF(Main!G11:O11,'S3'!Y1,Main!G17:O17) -> 3
A89: cpubl | B89: eps | C89: eps | D89: eps | E89: eps | F89: eps | G89: eps | H89: eps | I89: eps | J89: eps | N89: apubl | O89: 0 | P89: eps | Q89: eps | R89: eps | W89: flab-us | X89: =SUMIF(Main!G11:O11,'S3'!Y1,Main!G18:O18) -> 1
A90: ccomm | B90: eps | C90: eps | D90: eps | E90: eps | F90: eps | G90: eps | H90: eps | I90: eps | J90: eps | N90: acomm | O90: 0 | P90: eps | Q90: eps | R90: eps | W90: flab-ut | X90: =SUMIF(Main!G11:O11,'S3'!Y1,Main!G19:O19) -> 1
A91: cinfo | B91: eps | C91: eps | D91: eps | E91: eps | F91: eps | G91: eps | H91: eps | I91: eps | J91: eps | N91: ainfo | O91: 0 | P91: eps | Q91: eps | R91: eps | W91: flab-kn | X91: =SUMIF(Main!G11:O11,'S3'!Y1,Main!G20:O20) -> 3
A92: cbank | B92: eps | C92: eps | D92: eps | E92: eps | F92: eps | G92: eps | H92: eps | I92: eps | J92: eps | N92: abank | O92: 0 | P92: eps | Q92: eps | R92: eps | W92: flab-kp | X92: =SUMIF(Main!G11:O11,'S3'!Y1,Main!G21:O21) -> 3
A93: cinsu | B93: eps | C93: eps | D93: eps | E93: eps | F93: eps | G93: eps | H93: eps | I93: eps | J93: eps | N93: ainsu | O93: 0 | P93: eps | Q93: eps | R93: eps | W93: flab-ks | X93: =SUMIF(Main!G11:O11,'S3'!Y1,Main!G22:O22) -> 1
A94: cofsv | B94: eps | C94: eps | D94: eps | E94: eps | F94: eps | G94: eps | H94: eps | I94: eps | J94: eps | N94: aofsv | O94: 0 | P94: eps | Q94: eps | R94: eps | W94: flab-kt | X94: =SUMIF(Main!G11:O11,'S3'!Y1,Main!G23:O23) -> 1
A95: crent | B95: eps | C95: eps | D95: eps | E95: eps | F95: eps | G95: eps | H95: eps | I95: eps | J95: eps | N95: arent | O95: 0 | P95: eps | Q95: eps | R95: eps | V95: Land | W95: flnd | X95: =SUMIF(Main!G11:O11,'S3'!Y1,Main!G24:O24) -> 1
A96: creal | B96: eps | C96: eps | D96: eps | E96: eps | F96: eps | G96: eps | H96: eps | I96: eps | J96: eps | N96: areal | O96: 0 | P96: eps | Q96: eps | R96: eps | V96: Capital | W96: fcap-c | X96: =SUMIF(Main!G11:O11,'S3'!Y1,Main!G25:O25) -> 2
A97: clegl | B97: eps | C97: eps | D97: eps | E97: eps | F97: eps | G97: eps | H97: eps | I97: eps | J97: eps | N97: alegl | O97: 0 | P97: eps | Q97: eps | R97: eps | W97: fcap-l | X97: =SUMIF(Main!G11:O11,'S3'!Y1,Main!G26:O26) -> 2
A98: cenga | B98: eps | C98: eps | D98: eps | E98: eps | F98: eps | G98: eps | H98: eps | I98: eps | J98: eps | N98: aenga | O98: 0 | P98: eps | Q98: eps | R98: eps | W98: fcap-m | X98: =SUMIF(Main!G11:O11,'S3'!Y1,Main!G27:O27) -> 2
A99: cprod | B99: eps | C99: eps | D99: eps | E99: eps | F99: eps | G99: eps | H99: eps | I99: eps | J99: eps | N99: aprod | O99: 0 | P99: eps | Q99: eps | R99: eps | W99: fcap-n | X99: =SUMIF(Main!G11:O11,'S3'!Y1,Main!G28:O28) -> 2
A100: ctrvl | B100: eps | C100: eps | D100: eps | E100: eps | F100: eps | G100: eps | H100: eps | I100: eps | J100: eps | N100: atrvl | O100: 0 | P100: eps | Q100: eps | R100: eps
A101: cobsv | B101: eps | C101: eps | D101: eps | E101: eps | F101: eps | G101: eps | H101: eps | I101: eps | J101: eps | N101: aobsv | O101: 0 | P101: eps | Q101: eps | R101: eps
A102: cpadm | B102: eps | C102: eps | D102: eps | E102: eps | F102: eps | G102: eps | H102: eps | I102: eps | J102: eps | N102: apadm | O102: 0 | P102: eps | Q102: eps | R102: eps
A103: ceduc | B103: eps | C103: eps | D103: eps | E103: eps | F103: eps | G103: eps | H103: eps | I103: eps | J103: eps | N103: aeduc | O103: 0 | P103: eps | Q103: eps | R103: eps
A104: cheal | B104: eps | C104: eps | D104: eps | E104: eps | F104: eps | G104: eps | H104: eps | I104: eps | J104: eps | N104: aheal | O104: 0 | P104: eps | Q104: eps | R104: eps
A105: csocw | B105: eps | C105: eps | D105: eps | E105: eps | F105: eps | G105: eps | H105: eps | I105: eps | J105: eps | N105: asocw | O105: 0 | P105: eps | Q105: eps | R105: eps
...

Sheet S4
A1: ="Simulation "&Y1&IF(X1<>""," : "&X1,"") -> Simulation HH shk : 50%_incr_cchem | X1: =IF(Main!C6<>"",Main!C6,"") -> 50%_incr_cchem | Y1: =Main!A9 -> HH shk
A3: Commodity shocks | N3: Activity shocks | V3: Factor shocks
B4: World prices | D4: Commodity taxes | G4: Transaction costs | J4: Import | O4: Fix cap? | P4: TFP | Q4: Activity taxes | W4: Factor | X4: Wage | Y4: Factor
B5: Exports | C5: Imports | D5: Exports | E5: Imports | F5: Sales | G5: Exports | H5: Imports | I5: Domestic | J5: subsidy | O5: (1=yes) | Q5: Activity | R5: ValAd. | W5: taxes | X5: rate | Y5: supply
B6: pwe | C6: pwm | D6: te | E6: tm | F6: tq | G6: ice | H6: icm | I6: icd | J6: tms | O6: fixcap | P6: alphava | Q6: ta | R6: tva | W6: tf | X6: wf | Y6: qfs
A7: csorg | B7: eps | C7: eps | D7: eps | E7: eps | F7: eps | G7: eps | H7: eps | I7: eps | J7: eps | N7: asorg | O7: 0 | P7: eps | Q7: eps | R7: eps | V7: flab-rn | W7: eps | X7: eps | Y7: eps
A8: cmaiz | B8: eps | C8: 11 | D8: eps | E8: eps | F8: eps | G8: eps | H8: eps | I8: eps | J8: eps | N8: amaiz | O8: 0 | P8: eps | Q8: eps | R8: eps | V8: flab-rp | W8: eps | X8: eps | Y8: eps
A9: cwhea | B9: eps | C9: 100 | D9: eps | E9: eps | F9: eps | G9: eps | H9: eps | I9: eps | J9: eps | N9: awhea | O9: 0 | P9: eps | Q9: eps | R9: eps | V9: flab-rs | W9: eps | X9: eps | Y9: eps
A10: crice | B10: eps | C10: -13 | D10: eps | E10: eps | F10: eps | G10: eps | H10: eps | I10: eps | J10: eps | N10: arice | O10: 0 | P10: eps | Q10: eps | R10: eps | V10: flab-rt | W10: eps | X10: eps | Y10: eps
A11: cocer | B11: eps | C11: eps | D11: eps | E11: eps | F11: eps | G11: eps | H11: eps | I11: eps | J11: eps | N11: aocer | O11: 0 | P11: eps | Q11: eps | R11: eps | V11: flab-un | W11: eps | X11: eps | Y11: eps
A12: cipot | B12: eps | C12: eps | D12: eps | E12: eps | F12: eps | G12: eps | H12: eps | I12: eps | J12: eps | N12: aipot | O12: 0 | P12: eps | Q12: eps | R12: eps | V12: flab-up | W12: eps | X12: eps | Y12: eps
A13: cspot | B13: eps | C13: eps | D13: eps | E13: eps | F13: eps | G13: eps | H13: eps | I13: eps | J13: eps | N13: aspot | O13: 0 | P13: eps | Q13: eps | R13: eps | V13: flab-us | W13: eps | X13: eps | Y13: eps
A14: ccass | B14: eps | C14: eps | D14: eps | E14: eps | F14: eps | G14: eps | H14: eps | I14: eps | J14: eps | N14: acass | O14: 0 | P14: eps | Q14: eps | R14: eps | V14: flab-ut | W14: eps | X14: eps | Y14: eps
A15: croot | B15: eps | C15: eps | D15: eps | E15: eps | F15: eps | G15: eps | H15: eps | I15: eps | J15: eps | N15: aroot | O15: 0 | P15: eps | Q15: eps | R15: eps | V15: flab-kn | W15: eps | X15: eps | Y15: eps
A16: cbean | B16: eps | C16: eps | D16: eps | E16: eps | F16: eps | G16: eps | H16: eps | I16: eps | J16: eps | N16: abean | O16: 0 | P16: eps | Q16: eps | R16: eps | V16: flab-kp | W16: eps | X16: eps | Y16: eps
A17: cpeas | B17: eps | C17: eps | D17: eps | E17: eps | F17: eps | G17: eps | H17: eps | I17: eps | J17: eps | N17: apeas | O17: 0 | P17: eps | Q17: eps | R17: eps | V17: flab-ks | W17: eps | X17: eps | Y17: eps
A18: cvege | B18: eps | C18: eps | D18: eps | E18: eps | F18: eps | G18: eps | H18: eps | I18: eps | J18: eps | N18: avege | O18: 0 | P18: eps | Q18: eps | R18: eps | V18: flab-kt | W18: eps | X18: eps | Y18: eps
A19: cbanb | B19: eps | C19: eps | D19: eps | E19: eps | F19: eps | G19: eps | H19: eps | I19: eps | J19: eps | N19: abanb | O19: 0 | P19: eps | Q19: eps | R19: eps | V19: flnd | W19: eps | X19: eps | Y19: eps
A20: cbanc | B20: eps | C20: eps | D20: eps | E20: eps | F20: eps | G20: eps | H20: eps | I20: eps | J20: eps | N20: abanc | O20: 0 | P20: eps | Q20: eps | R20: eps | V20: fcap-c | W20: eps | X20: eps | Y20: eps
A21: cbans | B21: eps | C21: eps | D21: eps | E21: eps | F21: eps | G21: eps | H21: eps | I21: eps | J21: eps | N21: abans | O21: 0 | P21: eps | Q21: eps | R21: eps | V21: fcap-l | W21: eps | X21: eps | Y21: eps
A22: cfrui | B22: eps | C22: eps | D22: eps | E22: eps | F22: eps | G22: eps | H22: eps | I22: eps | J22: eps | N22: afrui | O22: 0 | P22: eps | Q22: eps | R22: eps | V22: fcap-m | W22: eps | X22: eps | Y22: eps
A23: cgnut | B23: eps | C23: eps | D23: eps | E23: eps | F23: eps | G23: eps | H23: eps | I23: eps | J23: eps | N23: agnut | O23: 0 | P23: eps | Q23: eps | R23: eps | V23: fcap-n | W23: eps | X23: eps | Y23: eps
A24: csoya | B24: eps | C24: eps | D24: eps | E24: eps | F24: eps | G24: eps | H24: eps | I24: eps | J24: eps | N24: asoya | O24: 0 | P24: eps | Q24: eps | R24: eps
A25: coils | B25: eps | C25: eps | D25: eps | E25: eps | F25: eps | G25: eps | H25: eps | I25: eps | J25: eps | N25: aoils | O25: 0 | P25: eps | Q25: eps | R25: eps | V25: Household income shocks
A26: ccoff | B26: eps | C26: eps | D26: eps | E26: eps | F26: eps | G26: eps | H26: eps | I26: eps | J26: eps | N26: acoff | O26: 0 | P26: eps | Q26: eps | R26: eps | X26: Gov. | Y26: World
A27: cteal | B27: eps | C27: eps | D27: eps | E27: eps | F27: eps | G27: eps | H27: eps | I27: eps | J27: eps | N27: ateal | O27: 0 | P27: eps | Q27: eps | R27: eps | X27: trn | Y27: rem
A28: ctoba | B28: eps | C28: eps | D28: eps | E28: eps | F28: eps | G28: eps | H28: eps | I28: eps | J28: eps | N28: atoba | O28: 0 | P28: eps | Q28: eps | R28: eps | V28: Farm | W28: hhd-r1 | X28: eps | Y28: eps
A29: csugr | B29: eps | C29: eps | D29: eps | E29: eps | F29: eps | G29: eps | H29: eps | I29: eps | J29: eps | N29: asugr | O29: 0 | P29: eps | Q29: eps | R29: eps | W29: hhd-r2 | X29: eps | Y29: eps
A30: cpyre | B30: eps | C30: eps | D30: eps | E30: eps | F30: eps | G30: eps | H30: eps | I30: eps | J30: eps | N30: apyre | O30: 0 | P30: eps | Q30: eps | R30: eps | W30: hhd-r3 | X30: eps | Y30: eps
A31: cocrp | B31: eps | C31: eps | D31: eps | E31: eps | F31: eps | G31: eps | H31: eps | I31: eps | J31: eps | N31: aocrp | O31: 0 | P31: eps | Q31: eps | R31: eps | W31: hhd-r4 | X31: eps | Y31: eps
A32: ccatt | B32: eps | C32: eps | D32: eps | E32: eps | F32: eps | G32: eps | H32: eps | I32: eps | J32: eps | N32: acatt | O32: 0 | P32: eps | Q32: eps | R32: eps | W32: hhd-r5 | X32: eps | Y32: eps
A33: csmlr | B33: eps | C33: eps | D33: eps | E33: eps | F33: eps | G33: eps | H33: eps | I33: eps | J33: eps | N33: asmlr | O33: 0 | P33: eps | Q33: eps | R33: eps | V33: Nonfarm | W33: hhd-u1 | X33: eps | Y33: eps
A34: cpoul | B34: eps | C34: eps | D34: eps | E34: eps | F34: eps | G34: eps | H34: eps | I34: eps | J34: eps | N34: apoul | O34: 0 | P34: eps | Q34: eps | R34: eps | W34: hhd-u2 | X34: eps | Y34: eps
A35: coliv | B35: eps | C35: eps | D35: eps | E35: eps | F35: eps | G35: eps | H35: eps | I35: eps | J35: eps | N35: aoliv | O35: 0 | P35: eps | Q35: eps | R35: eps | W35: hhd-u3 | X35: eps | Y35: eps
A36: cmilk | B36: eps | C36: eps | D36: eps | E36: eps | F36: eps | G36: eps | H36: eps | I36: eps | J36: eps | N36: amilk | O36: 0 | P36: eps | Q36: eps | R36: eps | W36: hhd-u4 | X36: eps | Y36: eps
A37: ceggs | B37: eps | C37: eps | D37: eps | E37: eps | F37: eps | G37: eps | H37: eps | I37: eps | J37: eps | N37: aeggs | O37: 0 | P37: eps | Q37: eps | R37: eps | W37: hhd-u5 | X37: eps | Y37: eps
A38: chony | B38: eps | C38: eps | D38: eps | E38: eps | F38: eps | G38: eps | H38: eps | I38: eps | J38: eps | N38: ahony | O38: 0 | P38: eps | Q38: eps | R38: eps | V38: Urban | W38: hhd-k1 | X38: eps | Y38: eps
A39: chunt | B39: eps | C39: eps | D39: eps | E39: eps | F39: eps | G39: eps | H39: eps | I39: eps | J39: eps | N39: ahunt | O39: 0 | P39: eps | Q39: eps | R39: eps | W39: hhd-k2 | X39: eps | Y39: eps
A40: cfuel | B40: eps | C40: eps | D40: eps | E40: eps | F40: eps | G40: eps | H40: eps | I40: eps | J40: eps | N40: afuel | O40: 0 | P40: eps | Q40: eps | R40: eps | W40: hhd-k3 | X40: eps | Y40: eps
A41: cchar | B41: eps | C41: eps | D41: eps | E41: eps | F41: eps | G41: eps | H41: eps | I41: eps | J41: eps | N41: achar | O41: 0 | P41: eps | Q41: eps | R41: eps | W41: hhd-k4 | X41: eps | Y41: eps
A42: cfore | B42: eps | C42: eps | D42: eps | E42: eps | F42: eps | G42: eps | H42: eps | I42: eps | J42: eps | N42: afore | O42: 0 | P42: eps | Q42: eps | R42: eps | W42: hhd-k5 | X42: eps | Y42: eps
A43: cfish | B43: eps | C43: eps | D43: eps | E43: eps | F43: eps | G43: eps | H43: eps | I43: eps | J43: eps | N43: afish | O43: 0 | P43: eps | Q43: eps | R43: eps
A44: cngas | B44: eps | C44: eps | D44: eps | E44: eps | F44: eps | G44: eps | H44: eps | I44: eps | J44: eps | N44: angas | O44: 0 | P44: eps | Q44: eps | R44: eps | V44: Scalar shocks
A45: cmore | B45: eps | C45: eps | D45: eps | E45: eps | F45: eps | G45: eps | H45: eps | I45: eps | J45: eps | N45: amore | O45: 0 | P45: eps | Q45: eps | R45: eps
A46: comin | B46: eps | C46: eps | D46: eps | E46: eps | F46: eps | G46: eps | H46: eps | I46: eps | J46: eps | N46: aomin | O46: 0 | P46: eps | Q46: eps | R46: eps | V46: Exchange rate | X46: exr | Y46: eps
A47: cmeat | B47: eps | C47: eps | D47: eps | E47: eps | F47: eps | G47: eps | H47: eps | I47: eps | J47: eps | N47: ameat | O47: 0 | P47: eps | Q47: eps | R47: eps | V47: Investment | X47: iadj | Y47: eps
A48: cfsea | B48: eps | C48: eps | D48: eps | E48: eps | F48: eps | G48: eps | H48: eps | I48: eps | J48: eps | N48: afsea | O48: 0 | P48: eps | Q48: eps | R48: eps | V48: Foreign savings | X48: fsav | Y48: eps
A49: cfveg | B49: eps | C49: eps | D49: eps | E49: eps | F49: eps | G49: eps | H49: eps | I49: eps | J49: eps | N49: afveg | O49: 0 | P49: eps | Q49: eps | R49: eps | V49: Gov. savings | X49: gsav | Y49: eps
A50: cfoil | B50: eps | C50: eps | D50: eps | E50: eps | F50: eps | G50: eps | H50: eps | I50: eps | J50: eps | N50: afoil | O50: 0 | P50: eps | Q50: eps | R50: eps | V50: Gov. spending | X50: gadj | Y50: eps
A51: cdair | B51: eps | C51: eps | D51: eps | E51: eps | F51: eps | G51: eps | H51: eps | I51: eps | J51: eps | N51: adair | O51: 0 | P51: eps | Q51: eps | R51: eps | V51: Savings rates | X51: mpsadj | Y51: eps
A52: cgmll | B52: eps | C52: eps | D52: eps | E52: eps | F52: eps | G52: eps | H52: eps | I52: eps | J52: eps | N52: agmll | O52: 0 | P52: eps | Q52: eps | R52: eps | X52: dmps | Y52: eps
A53: cbake | B53: eps | C53: eps | D53: eps | E53: eps | F53: eps | G53: eps | H53: eps | I53: eps | J53: eps | N53: abake | O53: 0 | P53: eps | Q53: eps | R53: eps | V53: Direct tax rates | X53: tinsadj | Y53: eps
A54: cfeed | B54: eps | C54: eps | D54: eps | E54: eps | F54: eps | G54: eps | H54: eps | I54: eps | J54: eps | N54: afeed | O54: 0 | P54: eps | Q54: eps | R54: eps | X54: dtins | Y54: eps
A55: cfood | B55: eps | C55: eps | D55: eps | E55: eps | F55: eps | G55: eps | H55: eps | I55: eps | J55: eps | N55: afood | O55: 0 | P55: eps | Q55: eps | R55: eps
A56: calco | B56: eps | C56: eps | D56: eps | E56: eps | F56: eps | G56: eps | H56: eps | I56: eps | J56: eps | N56: aalco | O56: 0 | P56: eps | Q56: eps | R56: eps | V56: Institutional closures
A57: cbeve | B57: eps | C57: eps | D57: eps | E57: eps | F57: eps | G57: eps | H57: eps | I57: eps | J57: eps | N57: abeve | O57: 0 | P57: eps | Q57: eps | R57: eps | X57: Savings | Y57: Taxes
A58: cptob | B58: eps | C58: eps | D58: eps | E58: eps | F58: eps | G58: eps | H58: eps | I58: eps | J58: eps | N58: aptob | O58: 0 | P58: eps | Q58: eps | R58: eps | X58: mps | Y58: tins
A59: ctext | B59: eps | C59: eps | D59: eps | E59: eps | F59: eps | G59: eps | H59: eps | I59: eps | J59: eps | N59: atext | O59: 0 | P59: eps | Q59: eps | R59: eps | V59: Enter. | W59: ent | X59: 1 | Y59: 1
A60: cwood | B60: eps | C60: eps | D60: eps | E60: eps | F60: eps | G60: eps | H60: eps | I60: eps | J60: eps | N60: awood | O60: 0 | P60: eps | Q60: eps | R60: eps | V60: House. | W60: hhd-r1 | X60: 1 | Y60: 1
A61: cprnt | B61: eps | C61: eps | D61: eps | E61: eps | F61: eps | G61: eps | H61: eps | I61: eps | J61: eps | N61: aprnt | O61: 0 | P61: eps | Q61: eps | R61: eps | W61: hhd-r2 | X61: 1 | Y61: 1
A62: cpetr | B62: eps | C62: eps | D62: eps | E62: eps | F62: eps | G62: eps | H62: eps | I62: eps | J62: eps | N62: apetr | O62: 0 | P62: eps | Q62: eps | R62: eps | W62: hhd-r3 | X62: 1 | Y62: 1
A63: cchem | B63: eps | C63: eps | D63: eps | E63: eps | F63: eps | G63: eps | H63: eps | I63: eps | J63: eps | N63: achem | O63: 0 | P63: eps | Q63: eps | R63: eps | W63: hhd-r4 | X63: 1 | Y63: 1
A64: cphar | B64: eps | C64: eps | D64: eps | E64: eps | F64: eps | G64: eps | H64: eps | I64: eps | J64: eps | N64: aphar | O64: 0 | P64: eps | Q64: eps | R64: eps | W64: hhd-r5 | X64: 1 | Y64: 1
A65: cprub | B65: eps | C65: eps | D65: eps | E65: eps | F65: eps | G65: eps | H65: eps | I65: eps | J65: eps | N65: aprub | O65: 0 | P65: eps | Q65: eps | R65: eps | W65: hhd-u1 | X65: 1 | Y65: 1
A66: cnmet | B66: eps | C66: eps | D66: eps | E66: eps | F66: eps | G66: eps | H66: eps | I66: eps | J66: eps | N66: anmet | O66: 0 | P66: eps | Q66: eps | R66: eps | W66: hhd-u2 | X66: 1 | Y66: 1
A67: cceme | B67: eps | C67: eps | D67: eps | E67: eps | F67: eps | G67: eps | H67: eps | I67: eps | J67: eps | N67: aceme | O67: 0 | P67: eps | Q67: eps | R67: eps | W67: hhd-u3 | X67: 1 | Y67: 1
A68: cclay | B68: eps | C68: eps | D68: eps | E68: eps | F68: eps | G68: eps | H68: eps | I68: eps | J68: eps | N68: aclay | O68: 0 | P68: eps | Q68: eps | R68: eps | W68: hhd-u4 | X68: 1 | Y68: 1
A69: cmetl | B69: eps | C69: eps | D69: eps | E69: eps | F69: eps | G69: eps | H69: eps | I69: eps | J69: eps | N69: ametl | O69: 0 | P69: eps | Q69: eps | R69: eps | W69: hhd-u5 | X69: 1 | Y69: 1
A70: cmach | B70: eps | C70: eps | D70: eps | E70: eps | F70: eps | G70: eps | H70: eps | I70: eps | J70: eps | N70: amach | O70: 0 | P70: eps | Q70: eps | R70: eps | W70: hhd-k1 | X70: 1 | Y70: 1
A71: cvehi | B71: eps | C71: eps | D71: eps | E71: eps | F71: eps | G71: eps | H71: eps | I71: eps | J71: eps | N71: avehi | O71: 0 | P71: eps | Q71: eps | R71: eps | W71: hhd-k2 | X71: 1 | Y71: 1
A72: cfurn | B72: eps | C72: eps | D72: eps | E72: eps | F72: eps | G72: eps | H72: eps | I72: eps | J72: eps | N72: afurn | O72: 0 | P72: eps | Q72: eps | R72: eps | W72: hhd-k3 | X72: 1 | Y72: 1
... A74: crepr | B74: eps | C74: eps | D74: eps | E74: eps | F74: eps | G74: eps | H74: eps | I74: eps | J74: eps | N74: arepr | O74: 0 | P74: eps | Q74: eps | R74: eps | W74: hhd-k5 | X74: 1 | Y74: 1
A75: celec | B75: eps | C75: eps | D75: eps | E75: eps | F75: eps | G75: eps | H75: eps | I75: eps | J75: eps | N75: aelec | O75: 0 | P75: eps | Q75: eps | R75: eps
A76: cwatr | B76: eps | C76: eps | D76: eps | E76: eps | F76: eps | G76: eps | H76: eps | I76: eps | J76: eps | N76: awatr | O76: 0 | P76: eps | Q76: eps | R76: eps | V76: Macroeconomic closures
A77: cwast | B77: eps | C77: eps | D77: eps | E77: eps | F77: eps | G77: eps | H77: eps | I77: eps | J77: eps | N77: awast | O77: 0 | P77: eps | Q77: eps | R77: eps | V77: Num. | W77: dum | X77: =SUMIF(Main!G4:O4,Y1,Main!G5:O5) -> 2
A78: ccons | B78: eps | C78: eps | D78: eps | E78: eps | F78: eps | G78: eps | H78: eps | I78: eps | J78: eps | N78: acons | O78: 0 | P78: eps | Q78: eps | R78: eps | V78: Sav-Inv. | W78: s-i | X78: =SUMIF(Main!G4:O4,Y1,Main!G6:O6) -> 3
A79: ccont | B79: eps | C79: eps | D79: eps | E79: eps | F79: eps | G79: eps | H79: eps | I79: eps | J79: eps | N79: acont | O79: 0 | P79: eps | Q79: eps | R79: eps | V79: Gov. | W79: gov | X79: =SUMIF(Main!G4:O4,Y1,Main!G7:O7) -> 1
A80: cvehr | B80: eps | C80: eps | D80: eps | E80: eps | F80: eps | G80: eps | H80: eps | I80: eps | J80: eps | N80: avehr | O80: 0 | P80: eps | Q80: eps | R80: eps | V80: Cur. a/c | W80: row | X80: =SUMIF(Main!G4:O4,Y1,Main!G8:O8) -> 1
A81: cveht | B81: eps | C81: eps | D81: eps | E81: eps | F81: eps | G81: eps | H81: eps | I81: eps | J81: eps | N81: aveht | O81: 0 | P81: eps | Q81: eps | R81: eps
A82: ctrdw | B82: eps | C82: eps | D82: eps | E82: eps | F82: eps | G82: eps | H82: eps | I82: eps | J82: eps | N82: atrdw | O82: 0 | P82: eps | Q82: eps | R82: eps | V82: Factor market closures
A83: ctrdr | B83: eps | C83: eps | D83: eps | E83: eps | F83: eps | G83: eps | H83: eps | I83: eps | J83: eps | N83: atrdr | O83: 0 | P83: eps | Q83: eps | R83: eps | V83: Labor | W83: flab-rn | X83: =SUMIF(Main!G11:O11,'S4'!Y1,Main!G12:O12) -> 1
A84: ctrnl | B84: eps | C84: eps | D84: eps | E84: eps | F84: eps | G84: eps | H84: eps | I84: eps | J84: eps | N84: atrnl | O84: 0 | P84: eps | Q84: eps | R84: eps | W84: flab-rp | X84: =SUMIF(Main!G11:O11,'S4'!Y1,Main!G13:O13) -> 1
A85: ctrna | B85: eps | C85: eps | D85: eps | E85: eps | F85: eps | G85: eps | H85: eps | I85: eps | J85: eps | N85: atrna | O85: 0 | P85: eps | Q85: eps | R85: eps | W85: flab-rs | X85: =SUMIF(Main!G11:O11,'S4'!Y1,Main!G14:O14) -> 3
A86: ctrns | B86: eps | C86: eps | D86: eps | E86: eps | F86: eps | G86: eps | H86: eps | I86: eps | J86: eps | N86: atrns | O86: 0 | P86: eps | Q86: eps | R86: eps | W86: flab-rt | X86: =SUMIF(Main!G11:O11,'S4'!Y1,Main!G15:O15) -> 3
A87: cpost | B87: eps | C87: eps | D87: eps | E87: eps | F87: eps | G87: eps | H87: eps | I87: eps | J87: eps | N87: apost | O87: 0 | P87: eps | Q87: eps | R87: eps | W87: flab-un | X87: =SUMIF(Main!G11:O11,'S4'!Y1,Main!G16:O16) -> 1
A88: chotl | B88: eps | C88: eps | D88: eps | E88: eps | F88: eps | G88: eps | H88: eps | I88: eps | J88: eps | N88: ahotl | O88: 0 | P88: eps | Q88: eps | R88: eps | W88: flab-up | X88: =SUMIF(Main!G11:O11,'S4'!Y1,Main!G17:O17) -> 1
A89: cpubl | B89: eps | C89: eps | D89: eps | E89: eps | F89: eps | G89: eps | H89: eps | I89: eps | J89: eps | N89: apubl | O89: 0 | P89: eps | Q89: eps | R89: eps | W89: flab-us | X89: =SUMIF(Main!G11:O11,'S4'!Y1,Main!G18:O18) -> 3
A90: ccomm | B90: eps | C90: eps | D90: eps | E90: eps | F90: eps | G90: eps | H90: eps | I90: eps | J90: eps | N90: acomm | O90: 0 | P90: eps | Q90: eps | R90: eps | W90: flab-ut | X90: =SUMIF(Main!G11:O11,'S4'!Y1,Main!G19:O19) -> 3
A91: cinfo | B91: eps | C91: eps | D91: eps | E91: eps | F91: eps | G91: eps | H91: eps | I91: eps | J91: eps | N91: ainfo | O91: 0 | P91: eps | Q91: eps | R91: eps | W91: flab-kn | X91: =SUMIF(Main!G11:O11,'S4'!Y1,Main!G20:O20) -> 1
A92: cbank | B92: eps | C92: eps | D92: eps | E92: eps | F92: eps | G92: eps | H92: eps | I92: eps | J92: eps | N92: abank | O92: 0 | P92: eps | Q92: eps | R92: eps | W92: flab-kp | X92: =SUMIF(Main!G11:O11,'S4'!Y1,Main!G21:O21) -> 1
A93: cinsu | B93: eps | C93: eps | D93: eps | E93: eps | F93: eps | G93: eps | H93: eps | I93: eps | J93: eps | N93: ainsu | O93: 0 | P93: eps | Q93: eps | R93: eps | W93: flab-ks | X93: =SUMIF(Main!G11:O11,'S4'!Y1,Main!G22:O22) -> 3
A94: cofsv | B94: eps | C94: eps | D94: eps | E94: eps | F94: eps | G94: eps | H94: eps | I94: eps | J94: eps | N94: aofsv | O94: 0 | P94: eps | Q94: eps | R94: eps | W94: flab-kt | X94: =SUMIF(Main!G11:O11,'S4'!Y1,Main!G23:O23) -> 3
A95: crent | B95: eps | C95: eps | D95: eps | E95: eps | F95: eps | G95: eps | H95: eps | I95: eps | J95: eps | N95: arent | O95: 0 | P95: eps | Q95: eps | R95: eps | V95: Land | W95: flnd | X95: =SUMIF(Main!G11:O11,'S4'!Y1,Main!G24:O24) -> 1
A96: creal | B96: eps | C96: eps | D96: eps | E96: eps | F96: eps | G96: eps | H96: eps | I96: eps | J96: eps | N96: areal | O96: 0 | P96: eps | Q96: eps | R96: eps | V96: Capital | W96: fcap-c | X96: =SUMIF(Main!G11:O11,'S4'!Y1,Main!G25:O25) -> 2
A97: clegl | B97: eps | C97: eps | D97: eps | E97: eps | F97: eps | G97: eps | H97: eps | I97: eps | J97: eps | N97: alegl | O97: 0 | P97: eps | Q97: eps | R97: eps | W97: fcap-l | X97: =SUMIF(Main!G11:O11,'S4'!Y1,Main!G26:O26) -> 2
A98: cenga | B98: eps | C98: eps | D98: eps | E98: eps | F98: eps | G98: eps | H98: eps | I98: eps | J98: eps | N98: aenga | O98: 0 | P98: eps | Q98: eps | R98: eps | W98: fcap-m | X98: =SUMIF(Main!G11:O11,'S4'!Y1,Main!G27:O27) -> 2
A99: cprod | B99: eps | C99: eps | D99: eps | E99: eps | F99: eps | G99: eps | H99: eps | I99: eps | J99: eps | N99: aprod | O99: 0 | P99: eps | Q99: eps | R99: eps | W99: fcap-n | X99: =SUMIF(Main!G11:O11,'S4'!Y1,Main!G28:O28) -> 2
A100: ctrvl | B100: eps | C100: eps | D100: eps | E100: eps | F100: eps | G100: eps | H100: eps | I100: eps | J100: eps | N100: atrvl | O100: 0 | P100: eps | Q100: eps | R100: eps
A101: cobsv | B101: eps | C101: eps | D101: eps | E101: eps | F101: eps | G101: eps | H101: eps | I101: eps | J101: eps | N101: aobsv | O101: 0 | P101: eps | Q101: eps | R101: eps
A102: cpadm | B102: eps | C102: eps | D102: eps | E102: eps | F102: eps | G102: eps | H102: eps | I102: eps | J102: eps | N102: apadm | O102: 0 | P102: eps | Q102: eps | R102: eps
...

Sheet S5
A1: ="Simulation "&Y1&IF(X1<>""," : "&X1,"") -> Simulation sim5 : 50%_incr_cchem | X1: =IF(Main!C6<>"",Main!C6,"") -> 50%_incr_cchem | Y1: =Main!A10 -> sim5
A3: Commodity shocks | N3: Activity shocks | V3: Factor shocks
B4: World prices | D4: Commodity taxes | G4: Transaction costs | J4: Import | O4: Fix cap? | P4: TFP | Q4: Activity taxes | W4: Factor | X4: Wage | Y4: Factor
B5: Exports | C5: Imports | D5: Exports | E5: Imports | F5: Sales | G5: Exports | H5: Imports | I5: Domestic | J5: subsidy | O5: (1=yes) | Q5: Activity | R5: ValAd. | W5: taxes | X5: rate | Y5: supply
B6: pwe | C6: pwm | D6: te | E6: tm | F6: tq | G6: ice | H6: icm | I6: icd | J6: tms | O6: fixcap | P6: alphava | Q6: ta | R6: tva | W6: tf | X6: wf | Y6: qfs
A7: csorg | B7: eps | C7: eps | D7: eps | E7: eps | F7: eps | G7: eps | H7: eps | I7: eps | J7: eps | N7: asorg | O7: 0 | P7: eps | Q7: eps | R7: eps | V7: flab-rn | W7: eps | X7: eps | Y7: eps
A8: cmaiz | B8: eps | C8: eps | D8: eps | E8: eps | F8: eps | G8: eps | H8: eps | I8: eps | J8: eps | N8: amaiz | O8: 0 | P8: eps | Q8: eps | R8: eps | V8: flab-rp | W8: eps | X8: eps | Y8: eps
A9: cwhea | B9: eps | C9: eps | D9: eps | E9: eps | F9: eps | G9: eps | H9: eps | I9: eps | J9: eps | N9: awhea | O9: 0 | P9: eps | Q9: eps | R9: eps | V9: flab-rs | W9: eps | X9: eps | Y9: eps
A10: crice | B10: eps | C10: eps | D10: eps | E10: eps | F10: eps | G10: eps | H10: eps | I10: eps | J10: eps | N10: arice | O10: 0 | P10: eps | Q10: eps | R10: eps | V10: flab-rt | W10: eps | X10: eps | Y10: eps
A11: cocer | B11: eps | C11: eps | D11: eps | E11: eps | F11: eps | G11: eps | H11: eps | I11: eps | J11: eps | N11: aocer | O11: 0 | P11: eps | Q11: eps | R11: eps | V11: flab-un | W11: eps | X11: eps | Y11: eps
A12: cipot | B12: eps | C12: eps | D12: eps | E12: eps | F12: eps | G12: eps | H12: eps | I12: eps | J12: eps | N12: aipot | O12: 0 | P12: eps | Q12: eps | R12: eps | V12: flab-up | W12: eps | X12: eps | Y12: eps
A13: cspot | B13: eps | C13: eps | D13: eps | E13: eps | F13: eps | G13: eps | H13: eps | I13: eps | J13: eps | N13: aspot | O13: 0 | P13: eps | Q13: eps | R13: eps | V13: flab-us | W13: eps | X13: eps | Y13: eps
A14: ccass | B14: eps | C14: eps | D14: eps | E14: eps | F14: eps | G14: eps | H14: eps | I14: eps | J14: eps | N14: acass | O14: 0 | P14: eps | Q14: eps | R14: eps | V14: flab-ut | W14: eps | X14: eps | Y14: eps
A15: croot | B15: eps | C15: eps | D15: eps | E15: eps | F15: eps | G15: eps | H15: eps | I15: eps | J15: eps | N15: aroot | O15: 0 | P15: eps | Q15: eps | R15: eps | V15: flab-kn | W15: eps | X15: eps | Y15: eps
A16: cbean | B16: eps | C16: eps | D16: eps | E16: eps | F16: eps | G16: eps | H16: eps | I16: eps | J16: eps | N16: abean | O16: 0 | P16: eps | Q16: eps | R16: eps | V16: flab-kp | W16: eps | X16: eps | Y16: eps
A17: cpeas | B17: eps | C17: eps | D17: eps | E17: eps | F17: eps | G17: eps | H17: eps | I17: eps | J17: eps | N17: apeas | O17: 0 | P17: eps | Q17: eps | R17: eps | V17: flab-ks | W17: eps | X17: eps | Y17: eps
A18: cvege | B18: eps | C18: eps | D18: eps | E18: eps | F18: eps | G18: eps | H18: eps | I18: eps | J18: eps | N18: avege | O18: 0 | P18: eps | Q18: eps | R18: eps | V18: flab-kt | W18: eps | X18: eps | Y18: eps
... A23: cgnut | B23: eps | C23: eps | D23: eps | E23: eps | F23: eps | G23: eps | H23: eps | I23: eps | J23: eps | N23: agnut | O23: 0 | P23: eps | Q23: eps | R23: eps | V23: fcap-n | W23: eps | X23: eps | Y23: eps
A24: csoya | B24: eps | C24: eps | D24: eps | E24: eps | F24: eps | G24: eps | H24: eps | I24: eps | J24: eps | N24: asoya | O24: 0 | P24: eps | Q24: eps | R24: eps
A25: coils | B25: eps | C25: eps | D25: eps | E25: eps | F25: eps | G25: eps | H25: eps | I25: eps | J25: eps | N25: aoils | O25: 0 | P25: eps | Q25: eps | R25: eps | V25: Household income shocks
A26: ccoff | B26: eps | C26: eps | D26: eps | E26: eps | F26: eps | G26: eps | H26: eps | I26: eps | J26: eps | N26: acoff | O26: 0 | P26: eps | Q26: eps | R26: eps | X26: Gov. | Y26: World
A27: cteal | B27: eps | C27: eps | D27: eps | E27: eps | F27: eps | G27: eps | H27: eps | I27: eps | J27: eps | N27: ateal | O27: 0 | P27: eps | Q27: eps | R27: eps | X27: trn | Y27: rem
A28: ctoba | B28: eps | C28: eps | D28: eps | E28: eps | F28: eps | G28: eps | H28: eps | I28: eps | J28: eps | N28: atoba | O28: 0 | P28: eps | Q28: eps | R28: eps | V28: Farm | W28: hhd-r1 | X28: eps | Y28: eps
A29: csugr | B29: eps | C29: eps | D29: eps | E29: eps | F29: eps | G29: eps | H29: eps | I29: eps | J29: eps | N29: asugr | O29: 0 | P29: eps | Q29: eps | R29: eps | W29: hhd-r2 | X29: eps | Y29: eps
A30: cpyre | B30: eps | C30: eps | D30: eps | E30: eps | F30: eps | G30: eps | H30: eps | I30: eps | J30: eps | N30: apyre | O30: 0 | P30: eps | Q30: eps | R30: eps | W30: hhd-r3 | X30: eps | Y30: eps
A31: cocrp | B31: eps | C31: eps | D31: eps | E31: eps | F31: eps | G31: eps | H31: eps | I31: eps | J31: eps | N31: aocrp | O31: 0 | P31: eps | Q31: eps | R31: eps | W31: hhd-r4 | X31: eps | Y31: eps
A32: ccatt | B32: eps | C32: eps | D32: eps | E32: eps | F32: eps | G32: eps | H32: eps | I32: eps | J32: eps | N32: acatt | O32: 0 | P32: eps | Q32: eps | R32: eps | W32: hhd-r5 | X32: eps | Y32: eps
A33: csmlr | B33: eps | C33: eps | D33: eps | E33: eps | F33: eps | G33: eps | H33: eps | I33: eps | J33: eps | N33: asmlr | O33: 0 | P33: eps | Q33: eps | R33: eps | V33: Nonfarm | W33: hhd-u1 | X33: eps | Y33: eps
A34: cpoul | B34: eps | C34: eps | D34: eps | E34: eps | F34: eps | G34: eps | H34: eps | I34: eps | J34: eps | N34: apoul | O34: 0 | P34: eps | Q34: eps | R34: eps | W34: hhd-u2 | X34: eps | Y34: eps
A35: coliv | B35: eps | C35: eps | D35: eps | E35: eps | F35: eps | G35: eps | H35: eps | I35: eps | J35: eps | N35: aoliv | O35: 0 | P35: eps | Q35: eps | R35: eps | W35: hhd-u3 | X35: eps | Y35: eps
A36: cmilk | B36: eps | C36: eps | D36: eps | E36: eps | F36: eps | G36: eps | H36: eps | I36: eps | J36: eps | N36: amilk | O36: 0 | P36: eps | Q36: eps | R36: eps | W36: hhd-u4 | X36: eps | Y36: eps
A37: ceggs | B37: eps | C37: eps | D37: eps | E37: eps | F37: eps | G37: eps | H37: eps | I37: eps | J37: eps | N37: aeggs | O37: 0 | P37: eps | Q37: eps | R37: eps | W37: hhd-u5 | X37: eps | Y37: eps
A38: chony | B38: eps | C38: eps | D38: eps | E38: eps | F38: eps | G38: eps | H38: eps | I38: eps | J38: eps | N38: ahony | O38: 0 | P38: eps | Q38: eps | R38: eps | V38: Urban | W38: hhd-k1 | X38: eps | Y38: eps
A39: chunt | B39: eps | C39: eps | D39: eps | E39: eps | F39: eps | G39: eps | H39: eps | I39: eps | J39: eps | N39: ahunt | O39: 0 | P39: eps | Q39: eps | R39: eps | W39: hhd-k2 | X39: eps | Y39: eps
A40: cfuel | B40: eps | C40: eps | D40: eps | E40: eps | F40: eps | G40: eps | H40: eps | I40: eps | J40: eps | N40: afuel | O40: 0 | P40: eps | Q40: eps | R40: eps | W40: hhd-k3 | X40: eps | Y40: eps
A41: cchar | B41: eps | C41: eps | D41: eps | E41: eps | F41: eps | G41: eps | H41: eps | I41: eps | J41: eps | N41: achar | O41: 0 | P41: eps | Q41: eps | R41: eps | W41: hhd-k4 | X41: eps | Y41: eps
A42: cfore | B42: eps | C42: eps | D42: eps | E42: eps | F42: eps | G42: eps | H42: eps | I42: eps | J42: eps | N42: afore | O42: 0 | P42: eps | Q42: eps | R42: eps | W42: hhd-k5 | X42: eps | Y42: eps
A43: cfish | B43: eps | C43: eps | D43: eps | E43: eps | F43: eps | G43: eps | H43: eps | I43: eps | J43: eps | N43: afish | O43: 0 | P43: eps | Q43: eps | R43: eps
A44: cngas | B44: eps | C44: eps | D44: eps | E44: eps | F44: eps | G44: eps | H44: eps | I44: eps | J44: eps | N44: angas | O44: 0 | P44: eps | Q44: eps | R44: eps | V44: Scalar shocks
A45: cmore | B45: eps | C45: eps | D45: eps | E45: eps | F45: eps | G45: eps | H45: eps | I45: eps | J45: eps | N45: amore | O45: 0 | P45: eps | Q45: eps | R45: eps
A46: comin | B46: eps | C46: eps | D46: eps | E46: eps | F46: eps | G46: eps | H46: eps | I46: eps | J46: eps | N46: aomin | O46: 0 | P46: eps | Q46: eps | R46: eps | V46: Exchange rate | X46: exr | Y46: eps
A47: cmeat | B47: eps | C47: eps | D47: eps | E47: eps | F47: eps | G47: eps | H47: eps | I47: eps | J47: eps | N47: ameat | O47: 0 | P47: eps | Q47: eps | R47: eps | V47: Investment | X47: iadj | Y47: eps
A48: cfsea | B48: eps | C48: eps | D48: eps | E48: eps | F48: eps | G48: eps | H48: eps | I48: eps | J48: eps | N48: afsea | O48: 0 | P48: eps | Q48: eps | R48: eps | V48: Foreign savings | X48: fsav | Y48: eps
A49: cfveg | B49: eps | C49: eps | D49: eps | E49: eps | F49: eps | G49: eps | H49: eps | I49: eps | J49: eps | N49: afveg | O49: 0 | P49: eps | Q49: eps | R49: eps | V49: Gov. savings | X49: gsav | Y49: eps
A50: cfoil | B50: eps | C50: eps | D50: eps | E50: eps | F50: eps | G50: eps | H50: eps | I50: eps | J50: eps | N50: afoil | O50: 0 | P50: eps | Q50: eps | R50: eps | V50: Gov. spending | X50: gadj | Y50: eps
A51: cdair | B51: eps | C51: eps | D51: eps | E51: eps | F51: eps | G51: eps | H51: eps | I51: eps | J51: eps | N51: adair | O51: 0 | P51: eps | Q51: eps | R51: eps | V51: Savings rates | X51: mpsadj | Y51: eps
A52: cgmll | B52: eps | C52: eps | D52: eps | E52: eps | F52: eps | G52: eps | H52: eps | I52: eps | J52: eps | N52: agmll | O52: 0 | P52: eps | Q52: eps | R52: eps | X52: dmps | Y52: eps
A53: cbake | B53: eps | C53: eps | D53: eps | E53: eps | F53: eps | G53: eps | H53: eps | I53: eps | J53: eps | N53: abake | O53: 0 | P53: eps | Q53: eps | R53: eps | V53: Direct tax rates | X53: tinsadj | Y53: eps
A54: cfeed | B54: eps | C54: eps | D54: eps | E54: eps | F54: eps | G54: eps | H54: eps | I54: eps | J54: eps | N54: afeed | O54: 0 | P54: eps | Q54: eps | R54: eps | X54: dtins | Y54: eps
A55: cfood | B55: eps | C55: eps | D55: eps | E55: eps | F55: eps | G55: eps | H55: eps | I55: eps | J55: eps | N55: afood | O55: 0 | P55: eps | Q55: eps | R55: eps
A56: calco | B56: eps | C56: eps | D56: eps | E56: eps | F56: eps | G56: eps | H56: eps | I56: eps | J56: eps | N56: aalco | O56: 0 | P56: eps | Q56: eps | R56: eps | V56: Institutional closures
A57: cbeve | B57: eps | C57: eps | D57: eps | E57: eps | F57: eps | G57: eps | H57: eps | I57: eps | J57: eps | N57: abeve | O57: 0 | P57: eps | Q57: eps | R57: eps | X57: Savings | Y57: Taxes
A58: cptob | B58: eps | C58: eps | D58: eps | E58: eps | F58: eps | G58: eps | H58: eps | I58: eps | J58: eps | N58: aptob | O58: 0 | P58: eps | Q58: eps | R58: eps | X58: mps | Y58: tins
A59: ctext | B59: eps | C59: eps | D59: eps | E59: eps | F59: eps | G59: eps | H59: eps | I59: eps | J59: eps | N59: atext | O59: 0 | P59: eps | Q59: eps | R59: eps | V59: Enter. | W59: ent | X59: 1 | Y59: 1
A60: cwood | B60: eps | C60: eps | D60: eps | E60: eps | F60: eps | G60: eps | H60: eps | I60: eps | J60: eps | N60: awood | O60: 0 | P60: eps | Q60: eps | R60: eps | V60: House. | W60: hhd-r1 | X60: 1 | Y60: 1
A61: cprnt | B61: eps | C61: eps | D61: eps | E61: eps | F61: eps | G61: eps | H61: eps | I61: eps | J61: eps | N61: aprnt | O61: 0 | P61: eps | Q61: eps | R61: eps | W61: hhd-r2 | X61: 1 | Y61: 1
A62: cpetr | B62: eps | C62: eps | D62: eps | E62: eps | F62: eps | G62: eps | H62: eps | I62: eps | J62: eps | N62: apetr | O62: 0 | P62: eps | Q62: eps | R62: eps | W62: hhd-r3 | X62: 1 | Y62: 1
A63: cchem | B63: eps | C63: eps | D63: eps | E63: eps | F63: eps | G63: eps | H63: eps | I63: eps | J63: eps | N63: achem | O63: 0 | P63: eps | Q63: eps | R63: eps | W63: hhd-r4 | X63: 1 | Y63: 1
A64: cphar | B64: eps | C64: eps | D64: eps | E64: eps | F64: eps | G64: eps | H64: eps | I64: eps | J64: eps | N64: aphar | O64: 0 | P64: eps | Q64: eps | R64: eps | W64: hhd-r5 | X64: 1 | Y64: 1
A65: cprub | B65: eps | C65: eps | D65: eps | E65: eps | F65: eps | G65: eps | H65: eps | I65: eps | J65: eps | N65: aprub | O65: 0 | P65: eps | Q65: eps | R65: eps | W65: hhd-u1 | X65: 1 | Y65: 1
A66: cnmet | B66: eps | C66: eps | D66: eps | E66: eps | F66: eps | G66: eps | H66: eps | I66: eps | J66: eps | N66: anmet | O66: 0 | P66: eps | Q66: eps | R66: eps | W66: hhd-u2 | X66: 1 | Y66: 1
A67: cceme | B67: eps | C67: eps | D67: eps | E67: eps | F67: eps | G67: eps | H67: eps | I67: eps | J67: eps | N67: aceme | O67: 0 | P67: eps | Q67: eps | R67: eps | W67: hhd-u3 | X67: 1 | Y67: 1
A68: cclay | B68: eps | C68: eps | D68: eps | E68: eps | F68: eps | G68: eps | H68: eps | I68: eps | J68: eps | N68: aclay | O68: 0 | P68: eps | Q68: eps | R68: eps | W68: hhd-u4 | X68: 1 | Y68: 1
A69: cmetl | B69: eps | C69: eps | D69: eps | E69: eps | F69: eps | G69: eps | H69: eps | I69: eps | J69: eps | N69: ametl | O69: 0 | P69: eps | Q69: eps | R69: eps | W69: hhd-u5 | X69: 1 | Y69: 1
A70: cmach | B70: eps | C70: eps | D70: eps | E70: eps | F70: eps | G70: eps | H70: eps | I70: eps | J70: eps | N70: amach | O70: 0 | P70: eps | Q70: eps | R70: eps | W70: hhd-k1 | X70: 1 | Y70: 1
A71: cvehi | B71: eps | C71: eps | D71: eps | E71: eps | F71: eps | G71: eps | H71: eps | I71: eps | J71: eps | N71: avehi | O71: 0 | P71: eps | Q71: eps | R71: eps | W71: hhd-k2 | X71: 1 | Y71: 1
A72: cfurn | B72: eps | C72: eps | D72: eps | E72: eps | F72: eps | G72: eps | H72: eps | I72: eps | J72: eps | N72: afurn | O72: 0 | P72: eps | Q72: eps | R72: eps | W72: hhd-k3 | X72: 1 | Y72: 1
... A74: crepr | B74: eps | C74: eps | D74: eps | E74: eps | F74: eps | G74: eps | H74: eps | I74: eps | J74: eps | N74: arepr | O74: 0 | P74: eps | Q74: eps | R74: eps | W74: hhd-k5 | X74: 1 | Y74: 1
A75: celec | B75: eps | C75: eps | D75: eps | E75: eps | F75: eps | G75: eps | H75: eps | I75: eps | J75: eps | N75: aelec | O75: 0 | P75: eps | Q75: eps | R75: eps
A76: cwatr | B76: eps | C76: eps | D76: eps | E76: eps | F76: eps | G76: eps | H76: eps | I76: eps | J76: eps | N76: awatr | O76: 0 | P76: eps | Q76: eps | R76: eps | V76: Macroeconomic closures
A77: cwast | B77: eps | C77: eps | D77: eps | E77: eps | F77: eps | G77: eps | H77: eps | I77: eps | J77: eps | N77: awast | O77: 0 | P77: eps | Q77: eps | R77: eps | V77: Num. | W77: dum | X77: =SUMIF(Main!G4:O4,Y1,Main!G5:O5) -> 2
A78: ccons | B78: eps | C78: eps | D78: eps | E78: eps | F78: eps | G78: eps | H78: eps | I78: eps | J78: eps | N78: acons | O78: 0 | P78: eps | Q78: eps | R78: eps | V78: Sav-Inv. | W78: s-i | X78: =SUMIF(Main!G4:O4,Y1,Main!G6:O6) -> 3
A79: ccont | B79: eps | C79: eps | D79: eps | E79: eps | F79: eps | G79: eps | H79: eps | I79: eps | J79: eps | N79: acont | O79: 0 | P79: eps | Q79: eps | R79: eps | V79: Gov. | W79: gov | X79: =SUMIF(Main!G4:O4,Y1,Main!G7:O7) -> 1
A80: cvehr | B80: eps | C80: eps | D80: eps | E80: eps | F80: eps | G80: eps | H80: eps | I80: eps | J80: eps | N80: avehr | O80: 0 | P80: eps | Q80: eps | R80: eps | V80: Cur. a/c | W80: row | X80: =SUMIF(Main!G4:O4,Y1,Main!G8:O8) -> 1
A81: cveht | B81: eps | C81: eps | D81: eps | E81: eps | F81: eps | G81: eps | H81: eps | I81: eps | J81: eps | N81: aveht | O81: 0 | P81: eps | Q81: eps | R81: eps
A82: ctrdw | B82: eps | C82: eps | D82: eps | E82: eps | F82: eps | G82: eps | H82: eps | I82: eps | J82: eps | N82: atrdw | O82: 0 | P82: eps | Q82: eps | R82: eps | V82: Factor market closures
A83: ctrdr | B83: eps | C83: eps | D83: eps | E83: eps | F83: eps | G83: eps | H83: eps | I83: eps | J83: eps | N83: atrdr | O83: 0 | P83: eps | Q83: eps | R83: eps | V83: Labor | W83: flab-rn | X83: =SUMIF(Main!G11:O11,'S5'!Y1,Main!G12:O12) -> 1
A84: ctrnl | B84: eps | C84: eps | D84: eps | E84: eps | F84: eps | G84: eps | H84: eps | I84: eps | J84: eps | N84: atrnl | O84: 0 | P84: eps | Q84: eps | R84: eps | W84: flab-rp | X84: =SUMIF(Main!G11:O11,'S5'!Y1,Main!G13:O13) -> 1
A85: ctrna | B85: eps | C85: eps | D85: eps | E85: eps | F85: eps | G85: eps | H85: eps | I85: eps | J85: eps | N85: atrna | O85: 0 | P85: eps | Q85: eps | R85: eps | W85: flab-rs | X85: =SUMIF(Main!G11:O11,'S5'!Y1,Main!G14:O14) -> 1
A86: ctrns | B86: eps | C86: eps | D86: eps | E86: eps | F86: eps | G86: eps | H86: eps | I86: eps | J86: eps | N86: atrns | O86: 0 | P86: eps | Q86: eps | R86: eps | W86: flab-rt | X86: =SUMIF(Main!G11:O11,'S5'!Y1,Main!G15:O15) -> 1
A87: cpost | B87: eps | C87: eps | D87: eps | E87: eps | F87: eps | G87: eps | H87: eps | I87: eps | J87: eps | N87: apost | O87: 0 | P87: eps | Q87: eps | R87: eps | W87: flab-un | X87: =SUMIF(Main!G11:O11,'S5'!Y1,Main!G16:O16) -> 3
A88: chotl | B88: eps | C88: eps | D88: eps | E88: eps | F88: eps | G88: eps | H88: eps | I88: eps | J88: eps | N88: ahotl | O88: 0 | P88: eps | Q88: eps | R88: eps | W88: flab-up | X88: =SUMIF(Main!G11:O11,'S5'!Y1,Main!G17:O17) -> 3
A89: cpubl | B89: eps | C89: eps | D89: eps | E89: eps | F89: eps | G89: eps | H89: eps | I89: eps | J89: eps | N89: apubl | O89: 0 | P89: eps | Q89: eps | R89: eps | W89: flab-us | X89: =SUMIF(Main!G11:O11,'S5'!Y1,Main!G18:O18) -> 1
A90: ccomm | B90: eps | C90: eps | D90: eps | E90: eps | F90: eps | G90: eps | H90: eps | I90: eps | J90: eps | N90: acomm | O90: 0 | P90: eps | Q90: eps | R90: eps | W90: flab-ut | X90: =SUMIF(Main!G11:O11,'S5'!Y1,Main!G19:O19) -> 1
A91: cinfo | B91: eps | C91: eps | D91: eps | E91: eps | F91: eps | G91: eps | H91: eps | I91: eps | J91: eps | N91: ainfo | O91: 0 | P91: eps | Q91: eps | R91: eps | W91: flab-kn | X91: =SUMIF(Main!G11:O11,'S5'!Y1,Main!G20:O20) -> 1
A92: cbank | B92: eps | C92: eps | D92: eps | E92: eps | F92: eps | G92: eps | H92: eps | I92: eps | J92: eps | N92: abank | O92: 0 | P92: eps | Q92: eps | R92: eps | W92: flab-kp | X92: =SUMIF(Main!G11:O11,'S5'!Y1,Main!G21:O21) -> 3
A93: cinsu | B93: eps | C93: eps | D93: eps | E93: eps | F93: eps | G93: eps | H93: eps | I93: eps | J93: eps | N93: ainsu | O93: 0 | P93: eps | Q93: eps | R93: eps | W93: flab-ks | X93: =SUMIF(Main!G11:O11,'S5'!Y1,Main!G22:O22) -> 3
A94: cofsv | B94: eps | C94: eps | D94: eps | E94: eps | F94: eps | G94: eps | H94: eps | I94: eps | J94: eps | N94: aofsv | O94: 0 | P94: eps | Q94: eps | R94: eps | W94: flab-kt | X94: =SUMIF(Main!G11:O11,'S5'!Y1,Main!G23:O23) -> 1
A95: crent | B95: eps | C95: eps | D95: eps | E95: eps | F95: eps | G95: eps | H95: eps | I95: eps | J95: eps | N95: arent | O95: 0 | P95: eps | Q95: eps | R95: eps | V95: Land | W95: flnd | X95: =SUMIF(Main!G11:O11,'S5'!Y1,Main!G24:O24) -> 1
A96: creal | B96: eps | C96: eps | D96: eps | E96: eps | F96: eps | G96: eps | H96: eps | I96: eps | J96: eps | N96: areal | O96: 0 | P96: eps | Q96: eps | R96: eps | V96: Capital | W96: fcap-c | X96: =SUMIF(Main!G11:O11,'S5'!Y1,Main!G25:O25) -> 2
A97: clegl | B97: eps | C97: eps | D97: eps | E97: eps | F97: eps | G97: eps | H97: eps | I97: eps | J97: eps | N97: alegl | O97: 0 | P97: eps | Q97: eps | R97: eps | W97: fcap-l | X97: =SUMIF(Main!G11:O11,'S5'!Y1,Main!G26:O26) -> 2
A98: cenga | B98: eps | C98: eps | D98: eps | E98: eps | F98: eps | G98: eps | H98: eps | I98: eps | J98: eps | N98: aenga | O98: 0 | P98: eps | Q98: eps | R98: eps | W98: fcap-m | X98: =SUMIF(Main!G11:O11,'S5'!Y1,Main!G27:O27) -> 2
A99: cprod | B99: eps | C99: eps | D99: eps | E99: eps | F99: eps | G99: eps | H99: eps | I99: eps | J99: eps | N99: aprod | O99: 0 | P99: eps | Q99: eps | R99: eps | W99: fcap-n | X99: =SUMIF(Main!G11:O11,'S5'!Y1,Main!G28:O28) -> 2
A100: ctrvl | B100: eps | C100: eps | D100: eps | E100: eps | F100: eps | G100: eps | H100: eps | I100: eps | J100: eps | N100: atrvl | O100: 0 | P100: eps | Q100: eps | R100: eps
A101: cobsv | B101: eps | C101: eps | D101: eps | E101: eps | F101: eps | G101: eps | H101: eps | I101: eps | J101: eps | N101: aobsv | O101: 0 | P101: eps | Q101: eps | R101: eps
A102: cpadm | B102: eps | C102: eps | D102: eps | E102: eps | F102: eps | G102: eps | H102: eps | I102: eps | J102: eps | N102: apadm | O102: 0 | P102: eps | Q102: eps | R102: eps
A103: ceduc | B103: eps | C103: eps | D103: eps | E103: eps | F103: eps | G103: eps | H103: eps | I103: eps | J103: eps | N103: aeduc | O103: 0 | P103: eps | Q103: eps | R103: eps
A104: cheal | B104: eps | C104: eps | D104: eps | E104: eps | F104: eps | G104: eps | H104: eps | I104: eps | J104: eps | N104: aheal | O104: 0 | P104: eps | Q104: eps | R104: eps
A105: csocw | B105: eps | C105: eps | D105: eps | E105: eps | F105: eps | G105: eps | H105: eps | I105: eps | J105: eps | N105: asocw | O105: 0 | P105: eps | Q105: eps | R105: eps
A106: ccult | B106: eps | C106: eps | D106: eps | E106: eps | F106: eps | G106: eps | H106: eps | I106: eps | J106: eps | N106: acult | O106: 0 | P106: eps | Q106: eps | R106: eps
...

Sheet S6
A1: ="Simulation "&Y1&IF(X1<>""," : "&X1,"") -> Simulation sim6 : 50%_incr_cchem | X1: =IF(Main!C6<>"",Main!C6,"") -> 50%_incr_cchem | Y1: =Main!A11 -> sim6
A3: Commodity shocks | N3: Activity shocks | V3: Factor shocks
B4: World prices | D4: Commodity taxes | G4: Transaction costs | J4: Import | O4: Fix cap? | P4: TFP | Q4: Activity taxes | W4: Factor | X4: Wage | Y4: Factor
B5: Exports | C5: Imports | D5: Exports | E5: Imports | F5: Sales | G5: Exports | H5: Imports | I5: Domestic | J5: subsidy | O5: (1=yes) | Q5: Activity | R5: ValAd. | W5: taxes | X5: rate | Y5: supply
B6: pwe | C6: pwm | D6: te | E6: tm | F6: tq | G6: ice | H6: icm | I6: icd | J6: tms | O6: fixcap | P6: alphava | Q6: ta | R6: tva | W6: tf | X6: wf | Y6: qfs
A7: csorg | B7: eps | C7: eps | D7: eps | E7: eps | F7: eps | G7: eps | H7: eps | I7: eps | J7: eps | N7: asorg | O7: 0 | P7: eps | Q7: eps | R7: eps | V7: flab-rn | W7: eps | X7: eps | Y7: eps
A8: cmaiz | B8: eps | C8: eps | D8: eps | E8: eps | F8: eps | G8: eps | H8: eps | I8: eps | J8: eps | N8: amaiz | O8: 0 | P8: eps | Q8: eps | R8: eps | V8: flab-rp | W8: eps | X8: eps | Y8: eps
A9: cwhea | B9: eps | C9: eps | D9: eps | E9: eps | F9: eps | G9: eps | H9: eps | I9: eps | J9: eps | N9: awhea | O9: 0 | P9: eps | Q9: eps | R9: eps | V9: flab-rs | W9: eps | X9: eps | Y9: eps
A10: crice | B10: eps | C10: eps | D10: eps | E10: eps | F10: eps | G10: eps | H10: eps | I10: eps | J10: eps | N10: arice | O10: 0 | P10: eps | Q10: eps | R10: eps | V10: flab-rt | W10: eps | X10: eps | Y10: eps
A11: cocer | B11: eps | C11: eps | D11: eps | E11: eps | F11: eps | G11: eps | H11: eps | I11: eps | J11: eps | N11: aocer | O11: 0 | P11: eps | Q11: eps | R11: eps | V11: flab-un | W11: eps | X11: eps | Y11: eps
A12: cipot | B12: eps | C12: eps | D12: eps | E12: eps | F12: eps | G12: eps | H12: eps | I12: eps | J12: eps | N12: aipot | O12: 0 | P12: eps | Q12: eps | R12: eps | V12: flab-up | W12: eps | X12: eps | Y12: eps
A13: cspot | B13: eps | C13: eps | D13: eps | E13: eps | F13: eps | G13: eps | H13: eps | I13: eps | J13: eps | N13: aspot | O13: 0 | P13: eps | Q13: eps | R13: eps | V13: flab-us | W13: eps | X13: eps | Y13: eps
A14: ccass | B14: eps | C14: eps | D14: eps | E14: eps | F14: eps | G14: eps | H14: eps | I14: eps | J14: eps | N14: acass | O14: 0 | P14: eps | Q14: eps | R14: eps | V14: flab-ut | W14: eps | X14: eps | Y14: eps
A15: croot | B15: eps | C15: eps | D15: eps | E15: eps | F15: eps | G15: eps | H15: eps | I15: eps | J15: eps | N15: aroot | O15: 0 | P15: eps | Q15: eps | R15: eps | V15: flab-kn | W15: eps | X15: eps | Y15: eps
A16: cbean | B16: eps | C16: eps | D16: eps | E16: eps | F16: eps | G16: eps | H16: eps | I16: eps | J16: eps | N16: abean | O16: 0 | P16: eps | Q16: eps | R16: eps | V16: flab-kp | W16: eps | X16: eps | Y16: eps
A17: cpeas | B17: eps | C17: eps | D17: eps | E17: eps | F17: eps | G17: eps | H17: eps | I17: eps | J17: eps | N17: apeas | O17: 0 | P17: eps | Q17: eps | R17: eps | V17: flab-ks | W17: eps | X17: eps | Y17: eps
A18: cvege | B18: eps | C18: eps | D18: eps | E18: eps | F18: eps | G18: eps | H18: eps | I18: eps | J18: eps | N18: avege | O18: 0 | P18: eps | Q18: eps | R18: eps | V18: flab-kt | W18: eps | X18: eps | Y18: eps
... A23: cgnut | B23: eps | C23: eps | D23: eps | E23: eps | F23: eps | G23: eps | H23: eps | I23: eps | J23: eps | N23: agnut | O23: 0 | P23: eps | Q23: eps | R23: eps | V23: fcap-n | W23: eps | X23: eps | Y23: eps
A24: csoya | B24: eps | C24: eps | D24: eps | E24: eps | F24: eps | G24: eps | H24: eps | I24: eps | J24: eps | N24: asoya | O24: 0 | P24: eps | Q24: eps | R24: eps
A25: coils | B25: eps | C25: eps | D25: eps | E25: eps | F25: eps | G25: eps | H25: eps | I25: eps | J25: eps | N25: aoils | O25: 0 | P25: eps | Q25: eps | R25: eps | V25: Household income shocks
A26: ccoff | B26: eps | C26: eps | D26: eps | E26: eps | F26: eps | G26: eps | H26: eps | I26: eps | J26: eps | N26: acoff | O26: 0 | P26: eps | Q26: eps | R26: eps | X26: Gov. | Y26: World
A27: cteal | B27: eps | C27: eps | D27: eps | E27: eps | F27: eps | G27: eps | H27: eps | I27: eps | J27: eps | N27: ateal | O27: 0 | P27: eps | Q27: eps | R27: eps | X27: trn | Y27: rem
A28: ctoba | B28: eps | C28: eps | D28: eps | E28: eps | F28: eps | G28: eps | H28: eps | I28: eps | J28: eps | N28: atoba | O28: 0 | P28: eps | Q28: eps | R28: eps | V28: Farm | W28: hhd-r1 | X28: eps | Y28: eps
A29: csugr | B29: eps | C29: eps | D29: eps | E29: eps | F29: eps | G29: eps | H29: eps | I29: eps | J29: eps | N29: asugr | O29: 0 | P29: eps | Q29: eps | R29: eps | W29: hhd-r2 | X29: eps | Y29: eps
A30: cpyre | B30: eps | C30: eps | D30: eps | E30: eps | F30: eps | G30: eps | H30: eps | I30: eps | J30: eps | N30: apyre | O30: 0 | P30: eps | Q30: eps | R30: eps | W30: hhd-r3 | X30: eps | Y30: eps
A31: cocrp | B31: eps | C31: eps | D31: eps | E31: eps | F31: eps | G31: eps | H31: eps | I31: eps | J31: eps | N31: aocrp | O31: 0 | P31: eps | Q31: eps | R31: eps | W31: hhd-r4 | X31: eps | Y31: eps
A32: ccatt | B32: eps | C32: eps | D32: eps | E32: eps | F32: eps | G32: eps | H32: eps | I32: eps | J32: eps | N32: acatt | O32: 0 | P32: eps | Q32: eps | R32: eps | W32: hhd-r5 | X32: eps | Y32: eps
A33: csmlr | B33: eps | C33: eps | D33: eps | E33: eps | F33: eps | G33: eps | H33: eps | I33: eps | J33: eps | N33: asmlr | O33: 0 | P33: eps | Q33: eps | R33: eps | V33: Nonfarm | W33: hhd-u1 | X33: eps | Y33: eps
A34: cpoul | B34: eps | C34: eps | D34: eps | E34: eps | F34: eps | G34: eps | H34: eps | I34: eps | J34: eps | N34: apoul | O34: 0 | P34: eps | Q34: eps | R34: eps | W34: hhd-u2 | X34: eps | Y34: eps
A35: coliv | B35: eps | C35: eps | D35: eps | E35: eps | F35: eps | G35: eps | H35: eps | I35: eps | J35: eps | N35: aoliv | O35: 0 | P35: eps | Q35: eps | R35: eps | W35: hhd-u3 | X35: eps | Y35: eps
A36: cmilk | B36: eps | C36: eps | D36: eps | E36: eps | F36: eps | G36: eps | H36: eps | I36: eps | J36: eps | N36: amilk | O36: 0 | P36: eps | Q36: eps | R36: eps | W36: hhd-u4 | X36: eps | Y36: eps
A37: ceggs | B37: eps | C37: eps | D37: eps | E37: eps | F37: eps | G37: eps | H37: eps | I37: eps | J37: eps | N37: aeggs | O37: 0 | P37: eps | Q37: eps | R37: eps | W37: hhd-u5 | X37: eps | Y37: eps
A38: chony | B38: eps | C38: eps | D38: eps | E38: eps | F38: eps | G38: eps | H38: eps | I38: eps | J38: eps | N38: ahony | O38: 0 | P38: eps | Q38: eps | R38: eps | V38: Urban | W38: hhd-k1 | X38: eps | Y38: eps
A39: chunt | B39: eps | C39: eps | D39: eps | E39: eps | F39: eps | G39: eps | H39: eps | I39: eps | J39: eps | N39: ahunt | O39: 0 | P39: eps | Q39: eps | R39: eps | W39: hhd-k2 | X39: eps | Y39: eps
A40: cfuel | B40: eps | C40: eps | D40: eps | E40: eps | F40: eps | G40: eps | H40: eps | I40: eps | J40: eps | N40: afuel | O40: 0 | P40: eps | Q40: eps | R40: eps | W40: hhd-k3 | X40: eps | Y40: eps
A41: cchar | B41: eps | C41: eps | D41: eps | E41: eps | F41: eps | G41: eps | H41: eps | I41: eps | J41: eps | N41: achar | O41: 0 | P41: eps | Q41: eps | R41: eps | W41: hhd-k4 | X41: eps | Y41: eps
A42: cfore | B42: eps | C42: eps | D42: eps | E42: eps | F42: eps | G42: eps | H42: eps | I42: eps | J42: eps | N42: afore | O42: 0 | P42: eps | Q42: eps | R42: eps | W42: hhd-k5 | X42: eps | Y42: eps
A43: cfish | B43: eps | C43: eps | D43: eps | E43: eps | F43: eps | G43: eps | H43: eps | I43: eps | J43: eps | N43: afish | O43: 0 | P43: eps | Q43: eps | R43: eps
A44: cngas | B44: eps | C44: eps | D44: eps | E44: eps | F44: eps | G44: eps | H44: eps | I44: eps | J44: eps | N44: angas | O44: 0 | P44: eps | Q44: eps | R44: eps | V44: Scalar shocks
A45: cmore | B45: eps | C45: eps | D45: eps | E45: eps | F45: eps | G45: eps | H45: eps | I45: eps | J45: eps | N45: amore | O45: 0 | P45: eps | Q45: eps | R45: eps
A46: comin | B46: eps | C46: eps | D46: eps | E46: eps | F46: eps | G46: eps | H46: eps | I46: eps | J46: eps | N46: aomin | O46: 0 | P46: eps | Q46: eps | R46: eps | V46: Exchange rate | X46: exr | Y46: eps
A47: cmeat | B47: eps | C47: eps | D47: eps | E47: eps | F47: eps | G47: eps | H47: eps | I47: eps | J47: eps | N47: ameat | O47: 0 | P47: eps | Q47: eps | R47: eps | V47: Investment | X47: iadj | Y47: eps
A48: cfsea | B48: eps | C48: eps | D48: eps | E48: eps | F48: eps | G48: eps | H48: eps | I48: eps | J48: eps | N48: afsea | O48: 0 | P48: eps | Q48: eps | R48: eps | V48: Foreign savings | X48: fsav | Y48: eps
A49: cfveg | B49: eps | C49: eps | D49: eps | E49: eps | F49: eps | G49: eps | H49: eps | I49: eps | J49: eps | N49: afveg | O49: 0 | P49: eps | Q49: eps | R49: eps | V49: Gov. savings | X49: gsav | Y49: eps
A50: cfoil | B50: eps | C50: eps | D50: eps | E50: eps | F50: eps | G50: eps | H50: eps | I50: eps | J50: eps | N50: afoil | O50: 0 | P50: eps | Q50: eps | R50: eps | V50: Gov. spending | X50: gadj | Y50: eps
A51: cdair | B51: eps | C51: eps | D51: eps | E51: eps | F51: eps | G51: eps | H51: eps | I51: eps | J51: eps | N51: adair | O51: 0 | P51: eps | Q51: eps | R51: eps | V51: Savings rates | X51: mpsadj | Y51: eps
A52: cgmll | B52: eps | C52: eps | D52: eps | E52: eps | F52: eps | G52: eps | H52: eps | I52: eps | J52: eps | N52: agmll | O52: 0 | P52: eps | Q52: eps | R52: eps | X52: dmps | Y52: eps
A53: cbake | B53: eps | C53: eps | D53: eps | E53: eps | F53: eps | G53: eps | H53: eps | I53: eps | J53: eps | N53: abake | O53: 0 | P53: eps | Q53: eps | R53: eps | V53: Direct tax rates | X53: tinsadj | Y53: eps
A54: cfeed | B54: eps | C54: eps | D54: eps | E54: eps | F54: eps | G54: eps | H54: eps | I54: eps | J54: eps | N54: afeed | O54: 0 | P54: eps | Q54: eps | R54: eps | X54: dtins | Y54: eps
A55: cfood | B55: eps | C55: eps | D55: eps | E55: eps | F55: eps | G55: eps | H55: eps | I55: eps | J55: eps | N55: afood | O55: 0 | P55: eps | Q55: eps | R55: eps
A56: calco | B56: eps | C56: eps | D56: eps | E56: eps | F56: eps | G56: eps | H56: eps | I56: eps | J56: eps | N56: aalco | O56: 0 | P56: eps | Q56: eps | R56: eps | V56: Institutional closures
A57: cbeve | B57: eps | C57: eps | D57: eps | E57: eps | F57: eps | G57: eps | H57: eps | I57: eps | J57: eps | N57: abeve | O57: 0 | P57: eps | Q57: eps | R57: eps | X57: Savings | Y57: Taxes
A58: cptob | B58: eps | C58: eps | D58: eps | E58: eps | F58: eps | G58: eps | H58: eps | I58: eps | J58: eps | N58: aptob | O58: 0 | P58: eps | Q58: eps | R58: eps | X58: mps | Y58: tins
A59: ctext | B59: eps | C59: eps | D59: eps | E59: eps | F59: eps | G59: eps | H59: eps | I59: eps | J59: eps | N59: atext | O59: 0 | P59: eps | Q59: eps | R59: eps | V59: Enter. | W59: ent | X59: 1 | Y59: 1
A60: cwood | B60: eps | C60: eps | D60: eps | E60: eps | F60: eps | G60: eps | H60: eps | I60: eps | J60: eps | N60: awood | O60: 0 | P60: eps | Q60: eps | R60: eps | V60: House. | W60: hhd-r1 | X60: 1 | Y60: 1
A61: cprnt | B61: eps | C61: eps | D61: eps | E61: eps | F61: eps | G61: eps | H61: eps | I61: eps | J61: eps | N61: aprnt | O61: 0 | P61: eps | Q61: eps | R61: eps | W61: hhd-r2 | X61: 1 | Y61: 1
A62: cpetr | B62: eps | C62: eps | D62: eps | E62: eps | F62: eps | G62: eps | H62: eps | I62: eps | J62: eps | N62: apetr | O62: 0 | P62: eps | Q62: eps | R62: eps | W62: hhd-r3 | X62: 1 | Y62: 1
A63: cchem | B63: eps | C63: eps | D63: eps | E63: eps | F63: eps | G63: eps | H63: eps | I63: eps | J63: eps | N63: achem | O63: 0 | P63: eps | Q63: eps | R63: eps | W63: hhd-r4 | X63: 1 | Y63: 1
A64: cphar | B64: eps | C64: eps | D64: eps | E64: eps | F64: eps | G64: eps | H64: eps | I64: eps | J64: eps | N64: aphar | O64: 0 | P64: eps | Q64: eps | R64: eps | W64: hhd-r5 | X64: 1 | Y64: 1
A65: cprub | B65: eps | C65: eps | D65: eps | E65: eps | F65: eps | G65: eps | H65: eps | I65: eps | J65: eps | N65: aprub | O65: 0 | P65: eps | Q65: eps | R65: eps | W65: hhd-u1 | X65: 1 | Y65: 1
A66: cnmet | B66: eps | C66: eps | D66: eps | E66: eps | F66: eps | G66: eps | H66: eps | I66: eps | J66: eps | N66: anmet | O66: 0 | P66: eps | Q66: eps | R66: eps | W66: hhd-u2 | X66: 1 | Y66: 1
A67: cceme | B67: eps | C67: eps | D67: eps | E67: eps | F67: eps | G67: eps | H67: eps | I67: eps | J67: eps | N67: aceme | O67: 0 | P67: eps | Q67: eps | R67: eps | W67: hhd-u3 | X67: 1 | Y67: 1
A68: cclay | B68: eps | C68: eps | D68: eps | E68: eps | F68: eps | G68: eps | H68: eps | I68: eps | J68: eps | N68: aclay | O68: 0 | P68: eps | Q68: eps | R68: eps | W68: hhd-u4 | X68: 1 | Y68: 1
A69: cmetl | B69: eps | C69: eps | D69: eps | E69: eps | F69: eps | G69: eps | H69: eps | I69: eps | J69: eps | N69: ametl | O69: 0 | P69: eps | Q69: eps | R69: eps | W69: hhd-u5 | X69: 1 | Y69: 1
A70: cmach | B70: eps | C70: eps | D70: eps | E70: eps | F70: eps | G70: eps | H70: eps | I70: eps | J70: eps | N70: amach | O70: 0 | P70: eps | Q70: eps | R70: eps | W70: hhd-k1 | X70: 1 | Y70: 1
A71: cvehi | B71: eps | C71: eps | D71: eps | E71: eps | F71: eps | G71: eps | H71: eps | I71: eps | J71: eps | N71: avehi | O71: 0 | P71: eps | Q71: eps | R71: eps | W71: hhd-k2 | X71: 1 | Y71: 1
A72: cfurn | B72: eps | C72: eps | D72: eps | E72: eps | F72: eps | G72: eps | H72: eps | I72: eps | J72: eps | N72: afurn | O72: 0 | P72: eps | Q72: eps | R72: eps | W72: hhd-k3 | X72: 1 | Y72: 1
... A74: crepr | B74: eps | C74: eps | D74: eps | E74: eps | F74: eps | G74: eps | H74: eps | I74: eps | J74: eps | N74: arepr | O74: 0 | P74: eps | Q74: eps | R74: eps | W74: hhd-k5 | X74: 1 | Y74: 1
A75: celec | B75: eps | C75: eps | D75: eps | E75: eps | F75: eps | G75: eps | H75: eps | I75: eps | J75: eps | N75: aelec | O75: 0 | P75: eps | Q75: eps | R75: eps
A76: cwatr | B76: eps | C76: eps | D76: eps | E76: eps | F76: eps | G76: eps | H76: eps | I76: eps | J76: eps | N76: awatr | O76: 0 | P76: eps | Q76: eps | R76: eps | V76: Macroeconomic closures
A77: cwast | B77: eps | C77: eps | D77: eps | E77: eps | F77: eps | G77: eps | H77: eps | I77: eps | J77: eps | N77: awast | O77: 0 | P77: eps | Q77: eps | R77: eps | V77: Num. | W77: dum | X77: =SUMIF(Main!G4:O4,Y1,Main!G5:O5) -> 2
A78: ccons | B78: eps | C78: eps | D78: eps | E78: eps | F78: eps | G78: eps | H78: eps | I78: eps | J78: eps | N78: acons | O78: 0 | P78: eps | Q78: eps | R78: eps | V78: Sav-Inv. | W78: s-i | X78: =SUMIF(Main!G4:O4,Y1,Main!G6:O6) -> 3
A79: ccont | B79: eps | C79: eps | D79: eps | E79: eps | F79: eps | G79: eps | H79: eps | I79: eps | J79: eps | N79: acont | O79: 0 | P79: eps | Q79: eps | R79: eps | V79: Gov. | W79: gov | X79: =SUMIF(Main!G4:O4,Y1,Main!G7:O7) -> 1
A80: cvehr | B80: eps | C80: eps | D80: eps | E80: eps | F80: eps | G80: eps | H80: eps | I80: eps | J80: eps | N80: avehr | O80: 0 | P80: eps | Q80: eps | R80: eps | V80: Cur. a/c | W80: row | X80: =SUMIF(Main!G4:O4,Y1,Main!G8:O8) -> 1
A81: cveht | B81: eps | C81: eps | D81: eps | E81: eps | F81: eps | G81: eps | H81: eps | I81: eps | J81: eps | N81: aveht | O81: 0 | P81: eps | Q81: eps | R81: eps
A82: ctrdw | B82: eps | C82: eps | D82: eps | E82: eps | F82: eps | G82: eps | H82: eps | I82: eps | J82: eps | N82: atrdw | O82: 0 | P82: eps | Q82: eps | R82: eps | V82: Factor market closures
A83: ctrdr | B83: eps | C83: eps | D83: eps | E83: eps | F83: eps | G83: eps | H83: eps | I83: eps | J83: eps | N83: atrdr | O83: 0 | P83: eps | Q83: eps | R83: eps | V83: Labor | W83: flab-rn | X83: =SUMIF(Main!G11:O11,'S6'!Y1,Main!G12:O12) -> 1
A84: ctrnl | B84: eps | C84: eps | D84: eps | E84: eps | F84: eps | G84: eps | H84: eps | I84: eps | J84: eps | N84: atrnl | O84: 0 | P84: eps | Q84: eps | R84: eps | W84: flab-rp | X84: =SUMIF(Main!G11:O11,'S6'!Y1,Main!G13:O13) -> 1
A85: ctrna | B85: eps | C85: eps | D85: eps | E85: eps | F85: eps | G85: eps | H85: eps | I85: eps | J85: eps | N85: atrna | O85: 0 | P85: eps | Q85: eps | R85: eps | W85: flab-rs | X85: =SUMIF(Main!G11:O11,'S6'!Y1,Main!G14:O14) -> 1
A86: ctrns | B86: eps | C86: eps | D86: eps | E86: eps | F86: eps | G86: eps | H86: eps | I86: eps | J86: eps | N86: atrns | O86: 0 | P86: eps | Q86: eps | R86: eps | W86: flab-rt | X86: =SUMIF(Main!G11:O11,'S6'!Y1,Main!G15:O15) -> 1
A87: cpost | B87: eps | C87: eps | D87: eps | E87: eps | F87: eps | G87: eps | H87: eps | I87: eps | J87: eps | N87: apost | O87: 0 | P87: eps | Q87: eps | R87: eps | W87: flab-un | X87: =SUMIF(Main!G11:O11,'S6'!Y1,Main!G16:O16) -> 1
A88: chotl | B88: eps | C88: eps | D88: eps | E88: eps | F88: eps | G88: eps | H88: eps | I88: eps | J88: eps | N88: ahotl | O88: 0 | P88: eps | Q88: eps | R88: eps | W88: flab-up | X88: =SUMIF(Main!G11:O11,'S6'!Y1,Main!G17:O17) -> 1
A89: cpubl | B89: eps | C89: eps | D89: eps | E89: eps | F89: eps | G89: eps | H89: eps | I89: eps | J89: eps | N89: apubl | O89: 0 | P89: eps | Q89: eps | R89: eps | W89: flab-us | X89: =SUMIF(Main!G11:O11,'S6'!Y1,Main!G18:O18) -> 1
A90: ccomm | B90: eps | C90: eps | D90: eps | E90: eps | F90: eps | G90: eps | H90: eps | I90: eps | J90: eps | N90: acomm | O90: 0 | P90: eps | Q90: eps | R90: eps | W90: flab-ut | X90: =SUMIF(Main!G11:O11,'S6'!Y1,Main!G19:O19) -> 1
A91: cinfo | B91: eps | C91: eps | D91: eps | E91: eps | F91: eps | G91: eps | H91: eps | I91: eps | J91: eps | N91: ainfo | O91: 0 | P91: eps | Q91: eps | R91: eps | W91: flab-kn | X91: =SUMIF(Main!G11:O11,'S6'!Y1,Main!G20:O20) -> 1
A92: cbank | B92: eps | C92: eps | D92: eps | E92: eps | F92: eps | G92: eps | H92: eps | I92: eps | J92: eps | N92: abank | O92: 0 | P92: eps | Q92: eps | R92: eps | W92: flab-kp | X92: =SUMIF(Main!G11:O11,'S6'!Y1,Main!G21:O21) -> 1
A93: cinsu | B93: eps | C93: eps | D93: eps | E93: eps | F93: eps | G93: eps | H93: eps | I93: eps | J93: eps | N93: ainsu | O93: 0 | P93: eps | Q93: eps | R93: eps | W93: flab-ks | X93: =SUMIF(Main!G11:O11,'S6'!Y1,Main!G22:O22) -> 1
A94: cofsv | B94: eps | C94: eps | D94: eps | E94: eps | F94: eps | G94: eps | H94: eps | I94: eps | J94: eps | N94: aofsv | O94: 0 | P94: eps | Q94: eps | R94: eps | W94: flab-kt | X94: =SUMIF(Main!G11:O11,'S6'!Y1,Main!G23:O23) -> 1
A95: crent | B95: eps | C95: eps | D95: eps | E95: eps | F95: eps | G95: eps | H95: eps | I95: eps | J95: eps | N95: arent | O95: 0 | P95: eps | Q95: eps | R95: eps | V95: Land | W95: flnd | X95: =SUMIF(Main!G11:O11,'S6'!Y1,Main!G24:O24) -> 1
A96: creal | B96: eps | C96: eps | D96: eps | E96: eps | F96: eps | G96: eps | H96: eps | I96: eps | J96: eps | N96: areal | O96: 0 | P96: eps | Q96: eps | R96: eps | V96: Capital | W96: fcap-c | X96: =SUMIF(Main!G11:O11,'S6'!Y1,Main!G25:O25) -> 2
A97: clegl | B97: eps | C97: eps | D97: eps | E97: eps | F97: eps | G97: eps | H97: eps | I97: eps | J97: eps | N97: alegl | O97: 0 | P97: eps | Q97: eps | R97: eps | W97: fcap-l | X97: =SUMIF(Main!G11:O11,'S6'!Y1,Main!G26:O26) -> 2
A98: cenga | B98: eps | C98: eps | D98: eps | E98: eps | F98: eps | G98: eps | H98: eps | I98: eps | J98: eps | N98: aenga | O98: 0 | P98: eps | Q98: eps | R98: eps | W98: fcap-m | X98: =SUMIF(Main!G11:O11,'S6'!Y1,Main!G27:O27) -> 2
A99: cprod | B99: eps | C99: eps | D99: eps | E99: eps | F99: eps | G99: eps | H99: eps | I99: eps | J99: eps | N99: aprod | O99: 0 | P99: eps | Q99: eps | R99: eps | W99: fcap-n | X99: =SUMIF(Main!G11:O11,'S6'!Y1,Main!G28:O28) -> 2
A100: ctrvl | B100: eps | C100: eps | D100: eps | E100: eps | F100: eps | G100: eps | H100: eps | I100: eps | J100: eps | N100: atrvl | O100: 0 | P100: eps | Q100: eps | R100: eps
A101: cobsv | B101: eps | C101: eps | D101: eps | E101: eps | F101: eps | G101: eps | H101: eps | I101: eps | J101: eps | N101: aobsv | O101: 0 | P101: eps | Q101: eps | R101: eps
A102: cpadm | B102: eps | C102: eps | D102: eps | E102: eps | F102: eps | G102: eps | H102: eps | I102: eps | J102: eps | N102: apadm | O102: 0 | P102: eps | Q102: eps | R102: eps
A103: ceduc | B103: eps | C103: eps | D103: eps | E103: eps | F103: eps | G103: eps | H103: eps | I103: eps | J103: eps | N103: aeduc | O103: 0 | P103: eps | Q103: eps | R103: eps
A104: cheal | B104: eps | C104: eps | D104: eps | E104: eps | F104: eps | G104: eps | H104: eps | I104: eps | J104: eps | N104: aheal | O104: 0 | P104: eps | Q104: eps | R104: eps
A105: csocw | B105: eps | C105: eps | D105: eps | E105: eps | F105: eps | G105: eps | H105: eps | I105: eps | J105: eps | N105: asocw | O105: 0 | P105: eps | Q105: eps | R105: eps
A106: ccult | B106: eps | C106: eps | D106: eps | E106: eps | F106: eps | G106: eps | H106: eps | I106: eps | J106: eps | N106: acult | O106: 0 | P106: eps | Q106: eps | R106: eps
...

Sheet S7
A1: ="Simulation "&Y1&IF(X1<>""," : "&X1,"") -> Simulation sim7 : 50%_incr_cchem | X1: =IF(Main!C6<>"",Main!C6,"") -> 50%_incr_cchem | Y1: =Main!A12 -> sim7
A3: Commodity shocks | N3: Activity shocks | V3: Factor shocks
B4: World prices | D4: Commodity taxes | G4: Transaction costs | J4: Import | O4: Fix cap? | P4: TFP | Q4: Activity taxes | W4: Factor | X4: Wage | Y4: Factor
B5: Exports | C5: Imports | D5: Exports | E5: Imports | F5: Sales | G5: Exports | H5: Imports | I5: Domestic | J5: subsidy | O5: (1=yes) | Q5: Activity | R5: ValAd. | W5: taxes | X5: rate | Y5: supply
B6: pwe | C6: pwm | D6: te | E6: tm | F6: tq | G6: ice | H6: icm | I6: icd | J6: tms | O6: fixcap | P6: alphava | Q6: ta | R6: tva | W6: tf | X6: wf | Y6: qfs
A7: csorg | B7: eps | C7: eps | D7: eps | E7: eps | F7: eps | G7: eps | H7: eps | I7: eps | J7: eps | N7: asorg | O7: 0 | P7: eps | Q7: eps | R7: eps | V7: flab-rn | W7: eps | X7: eps | Y7: eps
A8: cmaiz | B8: eps | C8: eps | D8: eps | E8: eps | F8: eps | G8: eps | H8: eps | I8: eps | J8: eps | N8: amaiz | O8: 0 | P8: eps | Q8: eps | R8: eps | V8: flab-rp | W8: eps | X8: eps | Y8: eps
A9: cwhea | B9: eps | C9: eps | D9: eps | E9: eps | F9: eps | G9: eps | H9: eps | I9: eps | J9: eps | N9: awhea | O9: 0 | P9: eps | Q9: eps | R9: eps | V9: flab-rs | W9: eps | X9: eps | Y9: eps
A10: crice | B10: eps | C10: eps | D10: eps | E10: eps | F10: eps | G10: eps | H10: eps | I10: eps | J10: eps | N10: arice | O10: 0 | P10: eps | Q10: eps | R10: eps | V10: flab-rt | W10: eps | X10: eps | Y10: eps
A11: cocer | B11: eps | C11: eps | D11: eps | E11: eps | F11: eps | G11: eps | H11: eps | I11: eps | J11: eps | N11: aocer | O11: 0 | P11: eps | Q11: eps | R11: eps | V11: flab-un | W11: eps | X11: eps | Y11: eps
A12: cipot | B12: eps | C12: eps | D12: eps | E12: eps | F12: eps | G12: eps | H12: eps | I12: eps | J12: eps | N12: aipot | O12: 0 | P12: eps | Q12: eps | R12: eps | V12: flab-up | W12: eps | X12: eps | Y12: eps
A13: cspot | B13: eps | C13: eps | D13: eps | E13: eps | F13: eps | G13: eps | H13: eps | I13: eps | J13: eps | N13: aspot | O13: 0 | P13: eps | Q13: eps | R13: eps | V13: flab-us | W13: eps | X13: eps | Y13: eps
A14: ccass | B14: eps | C14: eps | D14: eps | E14: eps | F14: eps | G14: eps | H14: eps | I14: eps | J14: eps | N14: acass | O14: 0 | P14: eps | Q14: eps | R14: eps | V14: flab-ut | W14: eps | X14: eps | Y14: eps
A15: croot | B15: eps | C15: eps | D15: eps | E15: eps | F15: eps | G15: eps | H15: eps | I15: eps | J15: eps | N15: aroot | O15: 0 | P15: eps | Q15: eps | R15: eps | V15: flab-kn | W15: eps | X15: eps | Y15: eps
A16: cbean | B16: eps | C16: eps | D16: eps | E16: eps | F16: eps | G16: eps | H16: eps | I16: eps | J16: eps | N16: abean | O16: 0 | P16: eps | Q16: eps | R16: eps | V16: flab-kp | W16: eps | X16: eps | Y16: eps
A17: cpeas | B17: eps | C17: eps | D17: eps | E17: eps | F17: eps | G17: eps | H17: eps | I17: eps | J17: eps | N17: apeas | O17: 0 | P17: eps | Q17: eps | R17: eps | V17: flab-ks | W17: eps | X17: eps | Y17: eps
A18: cvege | B18: eps | C18: eps | D18: eps | E18: eps | F18: eps | G18: eps | H18: eps | I18: eps | J18: eps | N18: avege | O18: 0 | P18: eps | Q18: eps | R18: eps | V18: flab-kt | W18: eps | X18: eps | Y18: eps
... A23: cgnut | B23: eps | C23: eps | D23: eps | E23: eps | F23: eps | G23: eps | H23: eps | I23: eps | J23: eps | N23: agnut | O23: 0 | P23: eps | Q23: eps | R23: eps | V23: fcap-n | W23: eps | X23: eps | Y23: eps
A24: csoya | B24: eps | C24: eps | D24: eps | E24: eps | F24: eps | G24: eps | H24: eps | I24: eps | J24: eps | N24: asoya | O24: 0 | P24: eps | Q24: eps | R24: eps
A25: coils | B25: eps | C25: eps | D25: eps | E25: eps | F25: eps | G25: eps | H25: eps | I25: eps | J25: eps | N25: aoils | O25: 0 | P25: eps | Q25: eps | R25: eps | V25: Household income shocks
A26: ccoff | B26: eps | C26: eps | D26: eps | E26: eps | F26: eps | G26: eps | H26: eps | I26: eps | J26: eps | N26: acoff | O26: 0 | P26: eps | Q26: eps | R26: eps | X26: Gov. | Y26: World
A27: cteal | B27: eps | C27: eps | D27: eps | E27: eps | F27: eps | G27: eps | H27: eps | I27: eps | J27: eps | N27: ateal | O27: 0 | P27: eps | Q27: eps | R27: eps | X27: trn | Y27: rem
A28: ctoba | B28: eps | C28: eps | D28: eps | E28: eps | F28: eps | G28: eps | H28: eps | I28: eps | J28: eps | N28: atoba | O28: 0 | P28: eps | Q28: eps | R28: eps | V28: Farm | W28: hhd-r1 | X28: eps | Y28: eps
A29: csugr | B29: eps | C29: eps | D29: eps | E29: eps | F29: eps | G29: eps | H29: eps | I29: eps | J29: eps | N29: asugr | O29: 0 | P29: eps | Q29: eps | R29: eps | W29: hhd-r2 | X29: eps | Y29: eps
A30: cpyre | B30: eps | C30: eps | D30: eps | E30: eps | F30: eps | G30: eps | H30: eps | I30: eps | J30: eps | N30: apyre | O30: 0 | P30: eps | Q30: eps | R30: eps | W30: hhd-r3 | X30: eps | Y30: eps
A31: cocrp | B31: eps | C31: eps | D31: eps | E31: eps | F31: eps | G31: eps | H31: eps | I31: eps | J31: eps | N31: aocrp | O31: 0 | P31: eps | Q31: eps | R31: eps | W31: hhd-r4 | X31: eps | Y31: eps
A32: ccatt | B32: eps | C32: eps | D32: eps | E32: eps | F32: eps | G32: eps | H32: eps | I32: eps | J32: eps | N32: acatt | O32: 0 | P32: eps | Q32: eps | R32: eps | W32: hhd-r5 | X32: eps | Y32: eps
A33: csmlr | B33: eps | C33: eps | D33: eps | E33: eps | F33: eps | G33: eps | H33: eps | I33: eps | J33: eps | N33: asmlr | O33: 0 | P33: eps | Q33: eps | R33: eps | V33: Nonfarm | W33: hhd-u1 | X33: eps | Y33: eps
A34: cpoul | B34: eps | C34: eps | D34: eps | E34: eps | F34: eps | G34: eps | H34: eps | I34: eps | J34: eps | N34: apoul | O34: 0 | P34: eps | Q34: eps | R34: eps | W34: hhd-u2 | X34: eps | Y34: eps
A35: coliv | B35: eps | C35: eps | D35: eps | E35: eps | F35: eps | G35: eps | H35: eps | I35: eps | J35: eps | N35: aoliv | O35: 0 | P35: eps | Q35: eps | R35: eps | W35: hhd-u3 | X35: eps | Y35: eps
A36: cmilk | B36: eps | C36: eps | D36: eps | E36: eps | F36: eps | G36: eps | H36: eps | I36: eps | J36: eps | N36: amilk | O36: 0 | P36: eps | Q36: eps | R36: eps | W36: hhd-u4 | X36: eps | Y36: eps
A37: ceggs | B37: eps | C37: eps | D37: eps | E37: eps | F37: eps | G37: eps | H37: eps | I37: eps | J37: eps | N37: aeggs | O37: 0 | P37: eps | Q37: eps | R37: eps | W37: hhd-u5 | X37: eps | Y37: eps
A38: chony | B38: eps | C38: eps | D38: eps | E38: eps | F38: eps | G38: eps | H38: eps | I38: eps | J38: eps | N38: ahony | O38: 0 | P38: eps | Q38: eps | R38: eps | V38: Urban | W38: hhd-k1 | X38: eps | Y38: eps
A39: chunt | B39: eps | C39: eps | D39: eps | E39: eps | F39: eps | G39: eps | H39: eps | I39: eps | J39: eps | N39: ahunt | O39: 0 | P39: eps | Q39: eps | R39: eps | W39: hhd-k2 | X39: eps | Y39: eps
A40: cfuel | B40: eps | C40: eps | D40: eps | E40: eps | F40: eps | G40: eps | H40: eps | I40: eps | J40: eps | N40: afuel | O40: 0 | P40: eps | Q40: eps | R40: eps | W40: hhd-k3 | X40: eps | Y40: eps
A41: cchar | B41: eps | C41: eps | D41: eps | E41: eps | F41: eps | G41: eps | H41: eps | I41: eps | J41: eps | N41: achar | O41: 0 | P41: eps | Q41: eps | R41: eps | W41: hhd-k4 | X41: eps | Y41: eps
A42: cfore | B42: eps | C42: eps | D42: eps | E42: eps | F42: eps | G42: eps | H42: eps | I42: eps | J42: eps | N42: afore | O42: 0 | P42: eps | Q42: eps | R42: eps | W42: hhd-k5 | X42: eps | Y42: eps
A43: cfish | B43: eps | C43: eps | D43: eps | E43: eps | F43: eps | G43: eps | H43: eps | I43: eps | J43: eps | N43: afish | O43: 0 | P43: eps | Q43: eps | R43: eps
A44: cngas | B44: eps | C44: eps | D44: eps | E44: eps | F44: eps | G44: eps | H44: eps | I44: eps | J44: eps | N44: angas | O44: 0 | P44: eps | Q44: eps | R44: eps | V44: Scalar shocks
A45: cmore | B45: eps | C45: eps | D45: eps | E45: eps | F45: eps | G45: eps | H45: eps | I45: eps | J45: eps | N45: amore | O45: 0 | P45: eps | Q45: eps | R45: eps
A46: comin | B46: eps | C46: eps | D46: eps | E46: eps | F46: eps | G46: eps | H46: eps | I46: eps | J46: eps | N46: aomin | O46: 0 | P46: eps | Q46: eps | R46: eps | V46: Exchange rate | X46: exr | Y46: eps
A47: cmeat | B47: eps | C47: eps | D47: eps | E47: eps | F47: eps | G47: eps | H47: eps | I47: eps | J47: eps | N47: ameat | O47: 0 | P47: eps | Q47: eps | R47: eps | V47: Investment | X47: iadj | Y47: eps
A48: cfsea | B48: eps | C48: eps | D48: eps | E48: eps | F48: eps | G48: eps | H48: eps | I48: eps | J48: eps | N48: afsea | O48: 0 | P48: eps | Q48: eps | R48: eps | V48: Foreign savings | X48: fsav | Y48: eps
A49: cfveg | B49: eps | C49: eps | D49: eps | E49: eps | F49: eps | G49: eps | H49: eps | I49: eps | J49: eps | N49: afveg | O49: 0 | P49: eps | Q49: eps | R49: eps | V49: Gov. savings | X49: gsav | Y49: eps
A50: cfoil | B50: eps | C50: eps | D50: eps | E50: eps | F50: eps | G50: eps | H50: eps | I50: eps | J50: eps | N50: afoil | O50: 0 | P50: eps | Q50: eps | R50: eps | V50: Gov. spending | X50: gadj | Y50: eps
A51: cdair | B51: eps | C51: eps | D51: eps | E51: eps | F51: eps | G51: eps | H51: eps | I51: eps | J51: eps | N51: adair | O51: 0 | P51: eps | Q51: eps | R51: eps | V51: Savings rates | X51: mpsadj | Y51: eps
A52: cgmll | B52: eps | C52: eps | D52: eps | E52: eps | F52: eps | G52: eps | H52: eps | I52: eps | J52: eps | N52: agmll | O52: 0 | P52: eps | Q52: eps | R52: eps | X52: dmps | Y52: eps
A53: cbake | B53: eps | C53: eps | D53: eps | E53: eps | F53: eps | G53: eps | H53: eps | I53: eps | J53: eps | N53: abake | O53: 0 | P53: eps | Q53: eps | R53: eps | V53: Direct tax rates | X53: tinsadj | Y53: eps
A54: cfeed | B54: eps | C54: eps | D54: eps | E54: eps | F54: eps | G54: eps | H54: eps | I54: eps | J54: eps | N54: afeed | O54: 0 | P54: eps | Q54: eps | R54: eps | X54: dtins | Y54: eps
A55: cfood | B55: eps | C55: eps | D55: eps | E55: eps | F55: eps | G55: eps | H55: eps | I55: eps | J55: eps | N55: afood | O55: 0 | P55: eps | Q55: eps | R55: eps
A56: calco | B56: eps | C56: eps | D56: eps | E56: eps | F56: eps | G56: eps | H56: eps | I56: eps | J56: eps | N56: aalco | O56: 0 | P56: eps | Q56: eps | R56: eps | V56: Institutional closures
A57: cbeve | B57: eps | C57: eps | D57: eps | E57: eps | F57: eps | G57: eps | H57: eps | I57: eps | J57: eps | N57: abeve | O57: 0 | P57: eps | Q57: eps | R57: eps | X57: Savings | Y57: Taxes
A58: cptob | B58: eps | C58: eps | D58: eps | E58: eps | F58: eps | G58: eps | H58: eps | I58: eps | J58: eps | N58: aptob | O58: 0 | P58: eps | Q58: eps | R58: eps | X58: mps | Y58: tins
A59: ctext | B59: eps | C59: eps | D59: eps | E59: eps | F59: eps | G59: eps | H59: eps | I59: eps | J59: eps | N59: atext | O59: 0 | P59: eps | Q59: eps | R59: eps | V59: Enter. | W59: ent | X59: 1 | Y59: 1
A60: cwood | B60: eps | C60: eps | D60: eps | E60: eps | F60: eps | G60: eps | H60: eps | I60: eps | J60: eps | N60: awood | O60: 0 | P60: eps | Q60: eps | R60: eps | V60: House. | W60: hhd-r1 | X60: 1 | Y60: 1
A61: cprnt | B61: eps | C61: eps | D61: eps | E61: eps | F61: eps | G61: eps | H61: eps | I61: eps | J61: eps | N61: aprnt | O61: 0 | P61: eps | Q61: eps | R61: eps | W61: hhd-r2 | X61: 1 | Y61: 1
A62: cpetr | B62: eps | C62: eps | D62: eps | E62: eps | F62: eps | G62: eps | H62: eps | I62: eps | J62: eps | N62: apetr | O62: 0 | P62: eps | Q62: eps | R62: eps | W62: hhd-r3 | X62: 1 | Y62: 1
A63: cchem | B63: eps | C63: eps | D63: eps | E63: eps | F63: eps | G63: eps | H63: eps | I63: eps | J63: eps | N63: achem | O63: 0 | P63: eps | Q63: eps | R63: eps | W63: hhd-r4 | X63: 1 | Y63: 1
A64: cphar | B64: eps | C64: eps | D64: eps | E64: eps | F64: eps | G64: eps | H64: eps | I64: eps | J64: eps | N64: aphar | O64: 0 | P64: eps | Q64: eps | R64: eps | W64: hhd-r5 | X64: 1 | Y64: 1
A65: cprub | B65: eps | C65: eps | D65: eps | E65: eps | F65: eps | G65: eps | H65: eps | I65: eps | J65: eps | N65: aprub | O65: 0 | P65: eps | Q65: eps | R65: eps | W65: hhd-u1 | X65: 1 | Y65: 1
A66: cnmet | B66: eps | C66: eps | D66: eps | E66: eps | F66: eps | G66: eps | H66: eps | I66: eps | J66: eps | N66: anmet | O66: 0 | P66: eps | Q66: eps | R66: eps | W66: hhd-u2 | X66: 1 | Y66: 1
A67: cceme | B67: eps | C67: eps | D67: eps | E67: eps | F67: eps | G67: eps | H67: eps | I67: eps | J67: eps | N67: aceme | O67: 0 | P67: eps | Q67: eps | R67: eps | W67: hhd-u3 | X67: 1 | Y67: 1
A68: cclay | B68: eps | C68: eps | D68: eps | E68: eps | F68: eps | G68: eps | H68: eps | I68: eps | J68: eps | N68: aclay | O68: 0 | P68: eps | Q68: eps | R68: eps | W68: hhd-u4 | X68: 1 | Y68: 1
A69: cmetl | B69: eps | C69: eps | D69: eps | E69: eps | F69: eps | G69: eps | H69: eps | I69: eps | J69: eps | N69: ametl | O69: 0 | P69: eps | Q69: eps | R69: eps | W69: hhd-u5 | X69: 1 | Y69: 1
A70: cmach | B70: eps | C70: eps | D70: eps | E70: eps | F70: eps | G70: eps | H70: eps | I70: eps | J70: eps | N70: amach | O70: 0 | P70: eps | Q70: eps | R70: eps | W70: hhd-k1 | X70: 1 | Y70: 1
A71: cvehi | B71: eps | C71: eps | D71: eps | E71: eps | F71: eps | G71: eps | H71: eps | I71: eps | J71: eps | N71: avehi | O71: 0 | P71: eps | Q71: eps | R71: eps | W71: hhd-k2 | X71: 1 | Y71: 1
A72: cfurn | B72: eps | C72: eps | D72: eps | E72: eps | F72: eps | G72: eps | H72: eps | I72: eps | J72: eps | N72: afurn | O72: 0 | P72: eps | Q72: eps | R72: eps | W72: hhd-k3 | X72: 1 | Y72: 1
... A74: crepr | B74: eps | C74: eps | D74: eps | E74: eps | F74: eps | G74: eps | H74: eps | I74: eps | J74: eps | N74: arepr | O74: 0 | P74: eps | Q74: eps | R74: eps | W74: hhd-k5 | X74: 1 | Y74: 1
A75: celec | B75: eps | C75: eps | D75: eps | E75: eps | F75: eps | G75: eps | H75: eps | I75: eps | J75: eps | N75: aelec | O75: 0 | P75: eps | Q75: eps | R75: eps
A76: cwatr | B76: eps | C76: eps | D76: eps | E76: eps | F76: eps | G76: eps | H76: eps | I76: eps | J76: eps | N76: awatr | O76: 0 | P76: eps | Q76: eps | R76: eps | V76: Macroeconomic closures
A77: cwast | B77: eps | C77: eps | D77: eps | E77: eps | F77: eps | G77: eps | H77: eps | I77: eps | J77: eps | N77: awast | O77: 0 | P77: eps | Q77: eps | R77: eps | V77: Num. | W77: dum | X77: =SUMIF(Main!G4:O4,Y1,Main!G5:O5) -> 2
A78: ccons | B78: eps | C78: eps | D78: eps | E78: eps | F78: eps | G78: eps | H78: eps | I78: eps | J78: eps | N78: acons | O78: 0 | P78: eps | Q78: eps | R78: eps | V78: Sav-Inv. | W78: s-i | X78: =SUMIF(Main!G4:O4,Y1,Main!G6:O6) -> 3
A79: ccont | B79: eps | C79: eps | D79: eps | E79: eps | F79: eps | G79: eps | H79: eps | I79: eps | J79: eps | N79: acont | O79: 0 | P79: eps | Q79: eps | R79: eps | V79: Gov. | W79: gov | X79: =SUMIF(Main!G4:O4,Y1,Main!G7:O7) -> 1
A80: cvehr | B80: eps | C80: eps | D80: eps | E80: eps | F80: eps | G80: eps | H80: eps | I80: eps | J80: eps | N80: avehr | O80: 0 | P80: eps | Q80: eps | R80: eps | V80: Cur. a/c | W80: row | X80: =SUMIF(Main!G4:O4,Y1,Main!G8:O8) -> 1
A81: cveht | B81: eps | C81: eps | D81: eps | E81: eps | F81: eps | G81: eps | H81: eps | I81: eps | J81: eps | N81: aveht | O81: 0 | P81: eps | Q81: eps | R81: eps
A82: ctrdw | B82: eps | C82: eps | D82: eps | E82: eps | F82: eps | G82: eps | H82: eps | I82: eps | J82: eps | N82: atrdw | O82: 0 | P82: eps | Q82: eps | R82: eps | V82: Factor market closures
A83: ctrdr | B83: eps | C83: eps | D83: eps | E83: eps | F83: eps | G83: eps | H83: eps | I83: eps | J83: eps | N83: atrdr | O83: 0 | P83: eps | Q83: eps | R83: eps | V83: Labor | W83: flab-rn | X83: =SUMIF(Main!G11:O11,'S7'!Y1,Main!G12:O12) -> 1
A84: ctrnl | B84: eps | C84: eps | D84: eps | E84: eps | F84: eps | G84: eps | H84: eps | I84: eps | J84: eps | N84: atrnl | O84: 0 | P84: eps | Q84: eps | R84: eps | W84: flab-rp | X84: =SUMIF(Main!G11:O11,'S7'!Y1,Main!G13:O13) -> 1
A85: ctrna | B85: eps | C85: eps | D85: eps | E85: eps | F85: eps | G85: eps | H85: eps | I85: eps | J85: eps | N85: atrna | O85: 0 | P85: eps | Q85: eps | R85: eps | W85: flab-rs | X85: =SUMIF(Main!G11:O11,'S7'!Y1,Main!G14:O14) -> 1
A86: ctrns | B86: eps | C86: eps | D86: eps | E86: eps | F86: eps | G86: eps | H86: eps | I86: eps | J86: eps | N86: atrns | O86: 0 | P86: eps | Q86: eps | R86: eps | W86: flab-rt | X86: =SUMIF(Main!G11:O11,'S7'!Y1,Main!G15:O15) -> 1
A87: cpost | B87: eps | C87: eps | D87: eps | E87: eps | F87: eps | G87: eps | H87: eps | I87: eps | J87: eps | N87: apost | O87: 0 | P87: eps | Q87: eps | R87: eps | W87: flab-un | X87: =SUMIF(Main!G11:O11,'S7'!Y1,Main!G16:O16) -> 1
A88: chotl | B88: eps | C88: eps | D88: eps | E88: eps | F88: eps | G88: eps | H88: eps | I88: eps | J88: eps | N88: ahotl | O88: 0 | P88: eps | Q88: eps | R88: eps | W88: flab-up | X88: =SUMIF(Main!G11:O11,'S7'!Y1,Main!G17:O17) -> 1
A89: cpubl | B89: eps | C89: eps | D89: eps | E89: eps | F89: eps | G89: eps | H89: eps | I89: eps | J89: eps | N89: apubl | O89: 0 | P89: eps | Q89: eps | R89: eps | W89: flab-us | X89: =SUMIF(Main!G11:O11,'S7'!Y1,Main!G18:O18) -> 1
A90: ccomm | B90: eps | C90: eps | D90: eps | E90: eps | F90: eps | G90: eps | H90: eps | I90: eps | J90: eps | N90: acomm | O90: 0 | P90: eps | Q90: eps | R90: eps | W90: flab-ut | X90: =SUMIF(Main!G11:O11,'S7'!Y1,Main!G19:O19) -> 1
A91: cinfo | B91: eps | C91: eps | D91: eps | E91: eps | F91: eps | G91: eps | H91: eps | I91: eps | J91: eps | N91: ainfo | O91: 0 | P91: eps | Q91: eps | R91: eps | W91: flab-kn | X91: =SUMIF(Main!G11:O11,'S7'!Y1,Main!G20:O20) -> 1
A92: cbank | B92: eps | C92: eps | D92: eps | E92: eps | F92: eps | G92: eps | H92: eps | I92: eps | J92: eps | N92: abank | O92: 0 | P92: eps | Q92: eps | R92: eps | W92: flab-kp | X92: =SUMIF(Main!G11:O11,'S7'!Y1,Main!G21:O21) -> 1
A93: cinsu | B93: eps | C93: eps | D93: eps | E93: eps | F93: eps | G93: eps | H93: eps | I93: eps | J93: eps | N93: ainsu | O93: 0 | P93: eps | Q93: eps | R93: eps | W93: flab-ks | X93: =SUMIF(Main!G11:O11,'S7'!Y1,Main!G22:O22) -> 1
A94: cofsv | B94: eps | C94: eps | D94: eps | E94: eps | F94: eps | G94: eps | H94: eps | I94: eps | J94: eps | N94: aofsv | O94: 0 | P94: eps | Q94: eps | R94: eps | W94: flab-kt | X94: =SUMIF(Main!G11:O11,'S7'!Y1,Main!G23:O23) -> 1
A95: crent | B95: eps | C95: eps | D95: eps | E95: eps | F95: eps | G95: eps | H95: eps | I95: eps | J95: eps | N95: arent | O95: 0 | P95: eps | Q95: eps | R95: eps | V95: Land | W95: flnd | X95: =SUMIF(Main!G11:O11,'S7'!Y1,Main!G24:O24) -> 1
A96: creal | B96: eps | C96: eps | D96: eps | E96: eps | F96: eps | G96: eps | H96: eps | I96: eps | J96: eps | N96: areal | O96: 0 | P96: eps | Q96: eps | R96: eps | V96: Capital | W96: fcap-c | X96: =SUMIF(Main!G11:O11,'S7'!Y1,Main!G25:O25) -> 2
A97: clegl | B97: eps | C97: eps | D97: eps | E97: eps | F97: eps | G97: eps | H97: eps | I97: eps | J97: eps | N97: alegl | O97: 0 | P97: eps | Q97: eps | R97: eps | W97: fcap-l | X97: =SUMIF(Main!G11:O11,'S7'!Y1,Main!G26:O26) -> 2
A98: cenga | B98: eps | C98: eps | D98: eps | E98: eps | F98: eps | G98: eps | H98: eps | I98: eps | J98: eps | N98: aenga | O98: 0 | P98: eps | Q98: eps | R98: eps | W98: fcap-m | X98: =SUMIF(Main!G11:O11,'S7'!Y1,Main!G27:O27) -> 2
A99: cprod | B99: eps | C99: eps | D99: eps | E99: eps | F99: eps | G99: eps | H99: eps | I99: eps | J99: eps | N99: aprod | O99: 0 | P99: eps | Q99: eps | R99: eps | W99: fcap-n | X99: =SUMIF(Main!G11:O11,'S7'!Y1,Main!G28:O28) -> 2
A100: ctrvl | B100: eps | C100: eps | D100: eps | E100: eps | F100: eps | G100: eps | H100: eps | I100: eps | J100: eps | N100: atrvl | O100: 0 | P100: eps | Q100: eps | R100: eps
A101: cobsv | B101: eps | C101: eps | D101: eps | E101: eps | F101: eps | G101: eps | H101: eps | I101: eps | J101: eps | N101: aobsv | O101: 0 | P101: eps | Q101: eps | R101: eps
A102: cpadm | B102: eps | C102: eps | D102: eps | E102: eps | F102: eps | G102: eps | H102: eps | I102: eps | J102: eps | N102: apadm | O102: 0 | P102: eps | Q102: eps | R102: eps
A103: ceduc | B103: eps | C103: eps | D103: eps | E103: eps | F103: eps | G103: eps | H103: eps | I103: eps | J103: eps | N103: aeduc | O103: 0 | P103: eps | Q103: eps | R103: eps
A104: cheal | B104: eps | C104: eps | D104: eps | E104: eps | F104: eps | G104: eps | H104: eps | I104: eps | J104: eps | N104: aheal | O104: 0 | P104: eps | Q104: eps | R104: eps
A105: csocw | B105: eps | C105: eps | D105: eps | E105: eps | F105: eps | G105: eps | H105: eps | I105: eps | J105: eps | N105: asocw | O105: 0 | P105: eps | Q105: eps | R105: eps
A106: ccult | B106: eps | C106: eps | D106: eps | E106: eps | F106: eps | G106: eps | H106: eps | I106: eps | J106: eps | N106: acult | O106: 0 | P106: eps | Q106: eps | R106: eps
...

Sheet S8
A1: ="Simulation "&Y1&IF(X1<>""," : "&X1,"") -> Simulation sim8 : 50%_incr_cchem | X1: =IF(Main!C6<>"",Main!C6,"") -> 50%_incr_cchem | Y1: =Main!A13 -> sim8
A3: Commodity shocks | N3: Activity shocks | V3: Factor shocks
B4: World prices | D4: Commodity taxes | G4: Transaction costs | J4: Import | O4: Fix cap? | P4: TFP | Q4: Activity taxes | W4: Factor | X4: Wage | Y4: Factor
B5: Exports | C5: Imports | D5: Exports | E5: Imports | F5: Sales | G5: Exports | H5: Imports | I5: Domestic | J5: subsidy | O5: (1=yes) | Q5: Activity | R5: ValAd. | W5: taxes | X5: rate | Y5: supply
B6: pwe | C6: pwm | D6: te | E6: tm | F6: tq | G6: ice | H6: icm | I6: icd | J6: tms | O6: fixcap | P6: alphava | Q6: ta | R6: tva | W6: tf | X6: wf | Y6: qfs
A7: csorg | B7: eps | C7: eps | D7: eps | E7: eps | F7: eps | G7: eps | H7: eps | I7: eps | J7: eps | N7: asorg | O7: 0 | P7: eps | Q7: eps | R7: eps | V7: flab-rn | W7: eps | X7: eps | Y7: eps
A8: cmaiz | B8: eps | C8: eps | D8: eps | E8: eps | F8: eps | G8: eps | H8: eps | I8: eps | J8: eps | N8: amaiz | O8: 0 | P8: eps | Q8: eps | R8: eps | V8: flab-rp | W8: eps | X8: eps | Y8: eps
A9: cwhea | B9: eps | C9: eps | D9: eps | E9: eps | F9: eps | G9: eps | H9: eps | I9: eps | J9: eps | N9: awhea | O9: 0 | P9: eps | Q9: eps | R9: eps | V9: flab-rs | W9: eps | X9: eps | Y9: eps
A10: crice | B10: eps | C10: eps | D10: eps | E10: eps | F10: eps | G10: eps | H10: eps | I10: eps | J10: eps | N10: arice | O10: 0 | P10: eps | Q10: eps | R10: eps | V10: flab-rt | W10: eps | X10: eps | Y10: eps
A11: cocer | B11: eps | C11: eps | D11: eps | E11: eps | F11: eps | G11: eps | H11: eps | I11: eps | J11: eps | N11: aocer | O11: 0 | P11: eps | Q11: eps | R11: eps | V11: flab-un | W11: eps | X11: eps | Y11: eps
A12: cipot | B12: eps | C12: eps | D12: eps | E12: eps | F12: eps | G12: eps | H12: eps | I12: eps | J12: eps | N12: aipot | O12: 0 | P12: eps | Q12: eps | R12: eps | V12: flab-up | W12: eps | X12: eps | Y12: eps
A13: cspot | B13: eps | C13: eps | D13: eps | E13: eps | F13: eps | G13: eps | H13: eps | I13: eps | J13: eps | N13: aspot | O13: 0 | P13: eps | Q13: eps | R13: eps | V13: flab-us | W13: eps | X13: eps | Y13: eps
A14: ccass | B14: eps | C14: eps | D14: eps | E14: eps | F14: eps | G14: eps | H14: eps | I14: eps | J14: eps | N14: acass | O14: 0 | P14: eps | Q14: eps | R14: eps | V14: flab-ut | W14: eps | X14: eps | Y14: eps
A15: croot | B15: eps | C15: eps | D15: eps | E15: eps | F15: eps | G15: eps | H15: eps | I15: eps | J15: eps | N15: aroot | O15: 0 | P15: eps | Q15: eps | R15: eps | V15: flab-kn | W15: eps | X15: eps | Y15: eps
A16: cbean | B16: eps | C16: eps | D16: eps | E16: eps | F16: eps | G16: eps | H16: eps | I16: eps | J16: eps | N16: abean | O16: 0 | P16: eps | Q16: eps | R16: eps | V16: flab-kp | W16: eps | X16: eps | Y16: eps
A17: cpeas | B17: eps | C17: eps | D17: eps | E17: eps | F17: eps | G17: eps | H17: eps | I17: eps | J17: eps | N17: apeas | O17: 0 | P17: eps | Q17: eps | R17: eps | V17: flab-ks | W17: eps | X17: eps | Y17: eps
A18: cvege | B18: eps | C18: eps | D18: eps | E18: eps | F18: eps | G18: eps | H18: eps | I18: eps | J18: eps | N18: avege | O18: 0 | P18: eps | Q18: eps | R18: eps | V18: flab-kt | W18: eps | X18: eps | Y18: eps
... A23: cgnut | B23: eps | C23: eps | D23: eps | E23: eps | F23: eps | G23: eps | H23: eps | I23: eps | J23: eps | N23: agnut | O23: 0 | P23: eps | Q23: eps | R23: eps | V23: fcap-n | W23: eps | X23: eps | Y23: eps
A24: csoya | B24: eps | C24: eps | D24: eps | E24: eps | F24: eps | G24: eps | H24: eps | I24: eps | J24: eps | N24: asoya | O24: 0 | P24: eps | Q24: eps | R24: eps
A25: coils | B25: eps | C25: eps | D25: eps | E25: eps | F25: eps | G25: eps | H25: eps | I25: eps | J25: eps | N25: aoils | O25: 0 | P25: eps | Q25: eps | R25: eps | V25: Household income shocks
A26: ccoff | B26: eps | C26: eps | D26: eps | E26: eps | F26: eps | G26: eps | H26: eps | I26: eps | J26: eps | N26: acoff | O26: 0 | P26: eps | Q26: eps | R26: eps | X26: Gov. | Y26: World
A27: cteal | B27: eps | C27: eps | D27: eps | E27: eps | F27: eps | G27: eps | H27: eps | I27: eps | J27: eps | N27: ateal | O27: 0 | P27: eps | Q27: eps | R27: eps | X27: trn | Y27: rem
A28: ctoba | B28: eps | C28: eps | D28: eps | E28: eps | F28: eps | G28: eps | H28: eps | I28: eps | J28: eps | N28: atoba | O28: 0 | P28: eps | Q28: eps | R28: eps | V28: Farm | W28: hhd-r1 | X28: eps | Y28: eps
A29: csugr | B29: eps | C29: eps | D29: eps | E29: eps | F29: eps | G29: eps | H29: eps | I29: eps | J29: eps | N29: asugr | O29: 0 | P29: eps | Q29: eps | R29: eps | W29: hhd-r2 | X29: eps | Y29: eps
A30: cpyre | B30: eps | C30: eps | D30: eps | E30: eps | F30: eps | G30: eps | H30: eps | I30: eps | J30: eps | N30: apyre | O30: 0 | P30: eps | Q30: eps | R30: eps | W30: hhd-r3 | X30: eps | Y30: eps
A31: cocrp | B31: eps | C31: eps | D31: eps | E31: eps | F31: eps | G31: eps | H31: eps | I31: eps | J31: eps | N31: aocrp | O31: 0 | P31: eps | Q31: eps | R31: eps | W31: hhd-r4 | X31: eps | Y31: eps
A32: ccatt | B32: eps | C32: eps | D32: eps | E32: eps | F32: eps | G32: eps | H32: eps | I32: eps | J32: eps | N32: acatt | O32: 0 | P32: eps | Q32: eps | R32: eps | W32: hhd-r5 | X32: eps | Y32: eps
A33: csmlr | B33: eps | C33: eps | D33: eps | E33: eps | F33: eps | G33: eps | H33: eps | I33: eps | J33: eps | N33: asmlr | O33: 0 | P33: eps | Q33: eps | R33: eps | V33: Nonfarm | W33: hhd-u1 | X33: eps | Y33: eps
A34: cpoul | B34: eps | C34: eps | D34: eps | E34: eps | F34: eps | G34: eps | H34: eps | I34: eps | J34: eps | N34: apoul | O34: 0 | P34: eps | Q34: eps | R34: eps | W34: hhd-u2 | X34: eps | Y34: eps
A35: coliv | B35: eps | C35: eps | D35: eps | E35: eps | F35: eps | G35: eps | H35: eps | I35: eps | J35: eps | N35: aoliv | O35: 0 | P35: eps | Q35: eps | R35: eps | W35: hhd-u3 | X35: eps | Y35: eps
A36: cmilk | B36: eps | C36: eps | D36: eps | E36: eps | F36: eps | G36: eps | H36: eps | I36: eps | J36: eps | N36: amilk | O36: 0 | P36: eps | Q36: eps | R36: eps | W36: hhd-u4 | X36: eps | Y36: eps
A37: ceggs | B37: eps | C37: eps | D37: eps | E37: eps | F37: eps | G37: eps | H37: eps | I37: eps | J37: eps | N37: aeggs | O37: 0 | P37: eps | Q37: eps | R37: eps | W37: hhd-u5 | X37: eps | Y37: eps
A38: chony | B38: eps | C38: eps | D38: eps | E38: eps | F38: eps | G38: eps | H38: eps | I38: eps | J38: eps | N38: ahony | O38: 0 | P38: eps | Q38: eps | R38: eps | V38: Urban | W38: hhd-k1 | X38: eps | Y38: eps
A39: chunt | B39: eps | C39: eps | D39: eps | E39: eps | F39: eps | G39: eps | H39: eps | I39: eps | J39: eps | N39: ahunt | O39: 0 | P39: eps | Q39: eps | R39: eps | W39: hhd-k2 | X39: eps | Y39: eps
A40: cfuel | B40: eps | C40: eps | D40: eps | E40: eps | F40: eps | G40: eps | H40: eps | I40: eps | J40: eps | N40: afuel | O40: 0 | P40: eps | Q40: eps | R40: eps | W40: hhd-k3 | X40: eps | Y40: eps
A41: cchar | B41: eps | C41: eps | D41: eps | E41: eps | F41: eps | G41: eps | H41: eps | I41: eps | J41: eps | N41: achar | O41: 0 | P41: eps | Q41: eps | R41: eps | W41: hhd-k4 | X41: eps | Y41: eps
A42: cfore | B42: eps | C42: eps | D42: eps | E42: eps | F42: eps | G42: eps | H42: eps | I42: eps | J42: eps | N42: afore | O42: 0 | P42: eps | Q42: eps | R42: eps | W42: hhd-k5 | X42: eps | Y42: eps
A43: cfish | B43: eps | C43: eps | D43: eps | E43: eps | F43: eps | G43: eps | H43: eps | I43: eps | J43: eps | N43: afish | O43: 0 | P43: eps | Q43: eps | R43: eps
A44: cngas | B44: eps | C44: eps | D44: eps | E44: eps | F44: eps | G44: eps | H44: eps | I44: eps | J44: eps | N44: angas | O44: 0 | P44: eps | Q44: eps | R44: eps | V44: Scalar shocks
A45: cmore | B45: eps | C45: eps | D45: eps | E45: eps | F45: eps | G45: eps | H45: eps | I45: eps | J45: eps | N45: amore | O45: 0 | P45: eps | Q45: eps | R45: eps
A46: comin | B46: eps | C46: eps | D46: eps | E46: eps | F46: eps | G46: eps | H46: eps | I46: eps | J46: eps | N46: aomin | O46: 0 | P46: eps | Q46: eps | R46: eps | V46: Exchange rate | X46: exr | Y46: eps
A47: cmeat | B47: eps | C47: eps | D47: eps | E47: eps | F47: eps | G47: eps | H47: eps | I47: eps | J47: eps | N47: ameat | O47: 0 | P47: eps | Q47: eps | R47: eps | V47: Investment | X47: iadj | Y47: eps
A48: cfsea | B48: eps | C48: eps | D48: eps | E48: eps | F48: eps | G48: eps | H48: eps | I48: eps | J48: eps | N48: afsea | O48: 0 | P48: eps | Q48: eps | R48: eps | V48: Foreign savings | X48: fsav | Y48: eps
A49: cfveg | B49: eps | C49: eps | D49: eps | E49: eps | F49: eps | G49: eps | H49: eps | I49: eps | J49: eps | N49: afveg | O49: 0 | P49: eps | Q49: eps | R49: eps | V49: Gov. savings | X49: gsav | Y49: eps
A50: cfoil | B50: eps | C50: eps | D50: eps | E50: eps | F50: eps | G50: eps | H50: eps | I50: eps | J50: eps | N50: afoil | O50: 0 | P50: eps | Q50: eps | R50: eps | V50: Gov. spending | X50: gadj | Y50: eps
A51: cdair | B51: eps | C51: eps | D51: eps | E51: eps | F51: eps | G51: eps | H51: eps | I51: eps | J51: eps | N51: adair | O51: 0 | P51: eps | Q51: eps | R51: eps | V51: Savings rates | X51: mpsadj | Y51: eps
A52: cgmll | B52: eps | C52: eps | D52: eps | E52: eps | F52: eps | G52: eps | H52: eps | I52: eps | J52: eps | N52: agmll | O52: 0 | P52: eps | Q52: eps | R52: eps | X52: dmps | Y52: eps
A53: cbake | B53: eps | C53: eps | D53: eps | E53: eps | F53: eps | G53: eps | H53: eps | I53: eps | J53: eps | N53: abake | O53: 0 | P53: eps | Q53: eps | R53: eps | V53: Direct tax rates | X53: tinsadj | Y53: eps
A54: cfeed | B54: eps | C54: eps | D54: eps | E54: eps | F54: eps | G54: eps | H54: eps | I54: eps | J54: eps | N54: afeed | O54: 0 | P54: eps | Q54: eps | R54: eps | X54: dtins | Y54: eps
A55: cfood | B55: eps | C55: eps | D55: eps | E55: eps | F55: eps | G55: eps | H55: eps | I55: eps | J55: eps | N55: afood | O55: 0 | P55: eps | Q55: eps | R55: eps
A56: calco | B56: eps | C56: eps | D56: eps | E56: eps | F56: eps | G56: eps | H56: eps | I56: eps | J56: eps | N56: aalco | O56: 0 | P56: eps | Q56: eps | R56: eps | V56: Institutional closures
A57: cbeve | B57: eps | C57: eps | D57: eps | E57: eps | F57: eps | G57: eps | H57: eps | I57: eps | J57: eps | N57: abeve | O57: 0 | P57: eps | Q57: eps | R57: eps | X57: Savings | Y57: Taxes
A58: cptob | B58: eps | C58: eps | D58: eps | E58: eps | F58: eps | G58: eps | H58: eps | I58: eps | J58: eps | N58: aptob | O58: 0 | P58: eps | Q58: eps | R58: eps | X58: mps | Y58: tins
A59: ctext | B59: eps | C59: eps | D59: eps | E59: eps | F59: eps | G59: eps | H59: eps | I59: eps | J59: eps | N59: atext | O59: 0 | P59: eps | Q59: eps | R59: eps | V59: Enter. | W59: ent | X59: 1 | Y59: 1
A60: cwood | B60: eps | C60: eps | D60: eps | E60: eps | F60: eps | G60: eps | H60: eps | I60: eps | J60: eps | N60: awood | O60: 0 | P60: eps | Q60: eps | R60: eps | V60: House. | W60: hhd-r1 | X60: 1 | Y60: 1
A61: cprnt | B61: eps | C61: eps | D61: eps | E61: eps | F61: eps | G61: eps | H61: eps | I61: eps | J61: eps | N61: aprnt | O61: 0 | P61: eps | Q61: eps | R61: eps | W61: hhd-r2 | X61: 1 | Y61: 1
A62: cpetr | B62: eps | C62: eps | D62: eps | E62: eps | F62: eps | G62: eps | H62: eps | I62: eps | J62: eps | N62: apetr | O62: 0 | P62: eps | Q62: eps | R62: eps | W62: hhd-r3 | X62: 1 | Y62: 1
A63: cchem | B63: eps | C63: eps | D63: eps | E63: eps | F63: eps | G63: eps | H63: eps | I63: eps | J63: eps | N63: achem | O63: 0 | P63: eps | Q63: eps | R63: eps | W63: hhd-r4 | X63: 1 | Y63: 1
A64: cphar | B64: eps | C64: eps | D64: eps | E64: eps | F64: eps | G64: eps | H64: eps | I64: eps | J64: eps | N64: aphar | O64: 0 | P64: eps | Q64: eps | R64: eps | W64: hhd-r5 | X64: 1 | Y64: 1
A65: cprub | B65: eps | C65: eps | D65: eps | E65: eps | F65: eps | G65: eps | H65: eps | I65: eps | J65: eps | N65: aprub | O65: 0 | P65: eps | Q65: eps | R65: eps | W65: hhd-u1 | X65: 1 | Y65: 1
A66: cnmet | B66: eps | C66: eps | D66: eps | E66: eps | F66: eps | G66: eps | H66: eps | I66: eps | J66: eps | N66: anmet | O66: 0 | P66: eps | Q66: eps | R66: eps | W66: hhd-u2 | X66: 1 | Y66: 1
A67: cceme | B67: eps | C67: eps | D67: eps | E67: eps | F67: eps | G67: eps | H67: eps | I67: eps | J67: eps | N67: aceme | O67: 0 | P67: eps | Q67: eps | R67: eps | W67: hhd-u3 | X67: 1 | Y67: 1
A68: cclay | B68: eps | C68: eps | D68: eps | E68: eps | F68: eps | G68: eps | H68: eps | I68: eps | J68: eps | N68: aclay | O68: 0 | P68: eps | Q68: eps | R68: eps | W68: hhd-u4 | X68: 1 | Y68: 1
A69: cmetl | B69: eps | C69: eps | D69: eps | E69: eps | F69: eps | G69: eps | H69: eps | I69: eps | J69: eps | N69: ametl | O69: 0 | P69: eps | Q69: eps | R69: eps | W69: hhd-u5 | X69: 1 | Y69: 1
A70: cmach | B70: eps | C70: eps | D70: eps | E70: eps | F70: eps | G70: eps | H70: eps | I70: eps | J70: eps | N70: amach | O70: 0 | P70: eps | Q70: eps | R70: eps | W70: hhd-k1 | X70: 1 | Y70: 1
A71: cvehi | B71: eps | C71: eps | D71: eps | E71: eps | F71: eps | G71: eps | H71: eps | I71: eps | J71: eps | N71: avehi | O71: 0 | P71: eps | Q71: eps | R71: eps | W71: hhd-k2 | X71: 1 | Y71: 1
A72: cfurn | B72: eps | C72: eps | D72: eps | E72: eps | F72: eps | G72: eps | H72: eps | I72: eps | J72: eps | N72: afurn | O72: 0 | P72: eps | Q72: eps | R72: eps | W72: hhd-k3 | X72: 1 | Y72: 1
... A74: crepr | B74: eps | C74: eps | D74: eps | E74: eps | F74: eps | G74: eps | H74: eps | I74: eps | J74: eps | N74: arepr | O74: 0 | P74: eps | Q74: eps | R74: eps | W74: hhd-k5 | X74: 1 | Y74: 1
A75: celec | B75: eps | C75: eps | D75: eps | E75: eps | F75: eps | G75: eps | H75: eps | I75: eps | J75: eps | N75: aelec | O75: 0 | P75: eps | Q75: eps | R75: eps
A76: cwatr | B76: eps | C76: eps | D76: eps | E76: eps | F76: eps | G76: eps | H76: eps | I76: eps | J76: eps | N76: awatr | O76: 0 | P76: eps | Q76: eps | R76: eps | V76: Macroeconomic closures
A77: cwast | B77: eps | C77: eps | D77: eps | E77: eps | F77: eps | G77: eps | H77: eps | I77: eps | J77: eps | N77: awast | O77: 0 | P77: eps | Q77: eps | R77: eps | V77: Num. | W77: dum | X77: =SUMIF(Main!G4:O4,Y1,Main!G5:O5) -> 2
A78: ccons | B78: eps | C78: eps | D78: eps | E78: eps | F78: eps | G78: eps | H78: eps | I78: eps | J78: eps | N78: acons | O78: 0 | P78: eps | Q78: eps | R78: eps | V78: Sav-Inv. | W78: s-i | X78: =SUMIF(Main!G4:O4,Y1,Main!G6:O6) -> 3
A79: ccont | B79: eps | C79: eps | D79: eps | E79: eps | F79: eps | G79: eps | H79: eps | I79: eps | J79: eps | N79: acont | O79: 0 | P79: eps | Q79: eps | R79: eps | V79: Gov. | W79: gov | X79: =SUMIF(Main!G4:O4,Y1,Main!G7:O7) -> 1
A80: cvehr | B80: eps | C80: eps | D80: eps | E80: eps | F80: eps | G80: eps | H80: eps | I80: eps | J80: eps | N80: avehr | O80: 0 | P80: eps | Q80: eps | R80: eps | V80: Cur. a/c | W80: row | X80: =SUMIF(Main!G4:O4,Y1,Main!G8:O8) -> 1
A81: cveht | B81: eps | C81: eps | D81: eps | E81: eps | F81: eps | G81: eps | H81: eps | I81: eps | J81: eps | N81: aveht | O81: 0 | P81: eps | Q81: eps | R81: eps
A82: ctrdw | B82: eps | C82: eps | D82: eps | E82: eps | F82: eps | G82: eps | H82: eps | I82: eps | J82: eps | N82: atrdw | O82: 0 | P82: eps | Q82: eps | R82: eps | V82: Factor market closures
A83: ctrdr | B83: eps | C83: eps | D83: eps | E83: eps | F83: eps | G83: eps | H83: eps | I83: eps | J83: eps | N83: atrdr | O83: 0 | P83: eps | Q83: eps | R83: eps | V83: Labor | W83: flab-rn | X83: =SUMIF(Main!G11:O11,'S8'!Y1,Main!G12:O12) -> 1
A84: ctrnl | B84: eps | C84: eps | D84: eps | E84: eps | F84: eps | G84: eps | H84: eps | I84: eps | J84: eps | N84: atrnl | O84: 0 | P84: eps | Q84: eps | R84: eps | W84: flab-rp | X84: =SUMIF(Main!G11:O11,'S8'!Y1,Main!G13:O13) -> 1
A85: ctrna | B85: eps | C85: eps | D85: eps | E85: eps | F85: eps | G85: eps | H85: eps | I85: eps | J85: eps | N85: atrna | O85: 0 | P85: eps | Q85: eps | R85: eps | W85: flab-rs | X85: =SUMIF(Main!G11:O11,'S8'!Y1,Main!G14:O14) -> 1
A86: ctrns | B86: eps | C86: eps | D86: eps | E86: eps | F86: eps | G86: eps | H86: eps | I86: eps | J86: eps | N86: atrns | O86: 0 | P86: eps | Q86: eps | R86: eps | W86: flab-rt | X86: =SUMIF(Main!G11:O11,'S8'!Y1,Main!G15:O15) -> 1
A87: cpost | B87: eps | C87: eps | D87: eps | E87: eps | F87: eps | G87: eps | H87: eps | I87: eps | J87: eps | N87: apost | O87: 0 | P87: eps | Q87: eps | R87: eps | W87: flab-un | X87: =SUMIF(Main!G11:O11,'S8'!Y1,Main!G16:O16) -> 1
A88: chotl | B88: eps | C88: eps | D88: eps | E88: eps | F88: eps | G88: eps | H88: eps | I88: eps | J88: eps | N88: ahotl | O88: 0 | P88: eps | Q88: eps | R88: eps | W88: flab-up | X88: =SUMIF(Main!G11:O11,'S8'!Y1,Main!G17:O17) -> 1
A89: cpubl | B89: eps | C89: eps | D89: eps | E89: eps | F89: eps | G89: eps | H89: eps | I89: eps | J89: eps | N89: apubl | O89: 0 | P89: eps | Q89: eps | R89: eps | W89: flab-us | X89: =SUMIF(Main!G11:O11,'S8'!Y1,Main!G18:O18) -> 1
A90: ccomm | B90: eps | C90: eps | D90: eps | E90: eps | F90: eps | G90: eps | H90: eps | I90: eps | J90: eps | N90: acomm | O90: 0 | P90: eps | Q90: eps | R90: eps | W90: flab-ut | X90: =SUMIF(Main!G11:O11,'S8'!Y1,Main!G19:O19) -> 1
A91: cinfo | B91: eps | C91: eps | D91: eps | E91: eps | F91: eps | G91: eps | H91: eps | I91: eps | J91: eps | N91: ainfo | O91: 0 | P91: eps | Q91: eps | R91: eps | W91: flab-kn | X91: =SUMIF(Main!G11:O11,'S8'!Y1,Main!G20:O20) -> 1
A92: cbank | B92: eps | C92: eps | D92: eps | E92: eps | F92: eps | G92: eps | H92: eps | I92: eps | J92: eps | N92: abank | O92: 0 | P92: eps | Q92: eps | R92: eps | W92: flab-kp | X92: =SUMIF(Main!G11:O11,'S8'!Y1,Main!G21:O21) -> 1
A93: cinsu | B93: eps | C93: eps | D93: eps | E93: eps | F93: eps | G93: eps | H93: eps | I93: eps | J93: eps | N93: ainsu | O93: 0 | P93: eps | Q93: eps | R93: eps | W93: flab-ks | X93: =SUMIF(Main!G11:O11,'S8'!Y1,Main!G22:O22) -> 1
A94: cofsv | B94: eps | C94: eps | D94: eps | E94: eps | F94: eps | G94: eps | H94: eps | I94: eps | J94: eps | N94: aofsv | O94: 0 | P94: eps | Q94: eps | R94: eps | W94: flab-kt | X94: =SUMIF(Main!G11:O11,'S8'!Y1,Main!G23:O23) -> 1
A95: crent | B95: eps | C95: eps | D95: eps | E95: eps | F95: eps | G95: eps | H95: eps | I95: eps | J95: eps | N95: arent | O95: 0 | P95: eps | Q95: eps | R95: eps | V95: Land | W95: flnd | X95: =SUMIF(Main!G11:O11,'S8'!Y1,Main!G24:O24) -> 1
A96: creal | B96: eps | C96: eps | D96: eps | E96: eps | F96: eps | G96: eps | H96: eps | I96: eps | J96: eps | N96: areal | O96: 0 | P96: eps | Q96: eps | R96: eps | V96: Capital | W96: fcap-c | X96: =SUMIF(Main!G11:O11,'S8'!Y1,Main!G25:O25) -> 2
A97: clegl | B97: eps | C97: eps | D97: eps | E97: eps | F97: eps | G97: eps | H97: eps | I97: eps | J97: eps | N97: alegl | O97: 0 | P97: eps | Q97: eps | R97: eps | W97: fcap-l | X97: =SUMIF(Main!G11:O11,'S8'!Y1,Main!G26:O26) -> 2
A98: cenga | B98: eps | C98: eps | D98: eps | E98: eps | F98: eps | G98: eps | H98: eps | I98: eps | J98: eps | N98: aenga | O98: 0 | P98: eps | Q98: eps | R98: eps | W98: fcap-m | X98: =SUMIF(Main!G11:O11,'S8'!Y1,Main!G27:O27) -> 2
A99: cprod | B99: eps | C99: eps | D99: eps | E99: eps | F99: eps | G99: eps | H99: eps | I99: eps | J99: eps | N99: aprod | O99: 0 | P99: eps | Q99: eps | R99: eps | W99: fcap-n | X99: =SUMIF(Main!G11:O11,'S8'!Y1,Main!G28:O28) -> 2
A100: ctrvl | B100: eps | C100: eps | D100: eps | E100: eps | F100: eps | G100: eps | H100: eps | I100: eps | J100: eps | N100: atrvl | O100: 0 | P100: eps | Q100: eps | R100: eps
A101: cobsv | B101: eps | C101: eps | D101: eps | E101: eps | F101: eps | G101: eps | H101: eps | I101: eps | J101: eps | N101: aobsv | O101: 0 | P101: eps | Q101: eps | R101: eps
A102: cpadm | B102: eps | C102: eps | D102: eps | E102: eps | F102: eps | G102: eps | H102: eps | I102: eps | J102: eps | N102: apadm | O102: 0 | P102: eps | Q102: eps | R102: eps
A103: ceduc | B103: eps | C103: eps | D103: eps | E103: eps | F103: eps | G103: eps | H103: eps | I103: eps | J103: eps | N103: aeduc | O103: 0 | P103: eps | Q103: eps | R103: eps
A104: cheal | B104: eps | C104: eps | D104: eps | E104: eps | F104: eps | G104: eps | H104: eps | I104: eps | J104: eps | N104: aheal | O104: 0 | P104: eps | Q104: eps | R104: eps
A105: csocw | B105: eps | C105: eps | D105: eps | E105: eps | F105: eps | G105: eps | H105: eps | I105: eps | J105: eps | N105: asocw | O105: 0 | P105: eps | Q105: eps | R105: eps
A106: ccult | B106: eps | C106: eps | D106: eps | E106: eps | F106: eps | G106: eps | H106: eps | I106: eps | J106: eps | N106: acult | O106: 0 | P106: eps | Q106: eps | R106: eps
...

Sheet S9
A1: ="Simulation "&Y1&IF(X1<>""," : "&X1,"") -> Simulation sim9 : 50%_incr_cchem | X1: =IF(Main!C6<>"",Main!C6,"") -> 50%_incr_cchem | Y1: =Main!A14 -> sim9
A3: Commodity shocks | N3: Activity shocks | V3: Factor shocks
B4: World prices | D4: Commodity taxes | G4: Transaction costs | J4: Import | O4: Fix cap? | P4: TFP | Q4: Activity taxes | W4: Factor | X4: Wage | Y4: Factor
B5: Exports | C5: Imports | D5: Exports | E5: Imports | F5: Sales | G5: Exports | H5: Imports | I5: Domestic | J5: subsidy | O5: (1=yes) | Q5: Activity | R5: ValAd. | W5: taxes | X5: rate | Y5: supply
B6: pwe | C6: pwm | D6: te | E6: tm | F6: tq | G6: ice | H6: icm | I6: icd | J6: tms | O6: fixcap | P6: alphava | Q6: ta | R6: tva | W6: tf | X6: wf | Y6: qfs
A7: csorg | B7: eps | C7: eps | D7: eps | E7: eps | F7: eps | G7: eps | H7: eps | I7: eps | J7: eps | N7: asorg | O7: 0 | P7: eps | Q7: eps | R7: eps | V7: flab-rn | W7: eps | X7: eps | Y7: eps
A8: cmaiz | B8: eps | C8: eps | D8: eps | E8: eps | F8: eps | G8: eps | H8: eps | I8: eps | J8: eps | N8: amaiz | O8: 0 | P8: eps | Q8: eps | R8: eps | V8: flab-rp | W8: eps | X8: eps | Y8: eps
A9: cwhea | B9: eps | C9: eps | D9: eps | E9: eps | F9: eps | G9: eps | H9: eps | I9: eps | J9: eps | N9: awhea | O9: 0 | P9: eps | Q9: eps | R9: eps | V9: flab-rs | W9: eps | X9: eps | Y9: eps
A10: crice | B10: eps | C10: eps | D10: eps | E10: eps | F10: eps | G10: eps | H10: eps | I10: eps | J10: eps | N10: arice | O10: 0 | P10: eps | Q10: eps | R10: eps | V10: flab-rt | W10: eps | X10: eps | Y10: eps
A11: cocer | B11: eps | C11: eps | D11: eps | E11: eps | F11: eps | G11: eps | H11: eps | I11: eps | J11: eps | N11: aocer | O11: 0 | P11: eps | Q11: eps | R11: eps | V11: flab-un | W11: eps | X11: eps | Y11: eps
A12: cipot | B12: eps | C12: eps | D12: eps | E12: eps | F12: eps | G12: eps | H12: eps | I12: eps | J12: eps | N12: aipot | O12: 0 | P12: eps | Q12: eps | R12: eps | V12: flab-up | W12: eps | X12: eps | Y12: eps
A13: cspot | B13: eps | C13: eps | D13: eps | E13: eps | F13: eps | G13: eps | H13: eps | I13: eps | J13: eps | N13: aspot | O13: 0 | P13: eps | Q13: eps | R13: eps | V13: flab-us | W13: eps | X13: eps | Y13: eps
A14: ccass | B14: eps | C14: eps | D14: eps | E14: eps | F14: eps | G14: eps | H14: eps | I14: eps | J14: eps | N14: acass | O14: 0 | P14: eps | Q14: eps | R14: eps | V14: flab-ut | W14: eps | X14: eps | Y14: eps
A15: croot | B15: eps | C15: eps | D15: eps | E15: eps | F15: eps | G15: eps | H15: eps | I15: eps | J15: eps | N15: aroot | O15: 0 | P15: eps | Q15: eps | R15: eps | V15: flab-kn | W15: eps | X15: eps | Y15: eps
A16: cbean | B16: eps | C16: eps | D16: eps | E16: eps | F16: eps | G16: eps | H16: eps | I16: eps | J16: eps | N16: abean | O16: 0 | P16: eps | Q16: eps | R16: eps | V16: flab-kp | W16: eps | X16: eps | Y16: eps
A17: cpeas | B17: eps | C17: eps | D17: eps | E17: eps | F17: eps | G17: eps | H17: eps | I17: eps | J17: eps | N17: apeas | O17: 0 | P17: eps | Q17: eps | R17: eps | V17: flab-ks | W17: eps | X17: eps | Y17: eps
A18: cvege | B18: eps | C18: eps | D18: eps | E18: eps | F18: eps | G18: eps | H18: eps | I18: eps | J18: eps | N18: avege | O18: 0 | P18: eps | Q18: eps | R18: eps | V18: flab-kt | W18: eps | X18: eps | Y18: eps
... A23: cgnut | B23: eps | C23: eps | D23: eps | E23: eps | F23: eps | G23: eps | H23: eps | I23: eps | J23: eps | N23: agnut | O23: 0 | P23: eps | Q23: eps | R23: eps | V23: fcap-n | W23: eps | X23: eps | Y23: eps
A24: csoya | B24: eps | C24: eps | D24: eps | E24: eps | F24: eps | G24: eps | H24: eps | I24: eps | J24: eps | N24: asoya | O24: 0 | P24: eps | Q24: eps | R24: eps
A25: coils | B25: eps | C25: eps | D25: eps | E25: eps | F25: eps | G25: eps | H25: eps | I25: eps | J25: eps | N25: aoils | O25: 0 | P25: eps | Q25: eps | R25: eps | V25: Household income shocks
A26: ccoff | B26: eps | C26: eps | D26: eps | E26: eps | F26: eps | G26: eps | H26: eps | I26: eps | J26: eps | N26: acoff | O26: 0 | P26: eps | Q26: eps | R26: eps | X26: Gov. | Y26: World
A27: cteal | B27: eps | C27: eps | D27: eps | E27: eps | F27: eps | G27: eps | H27: eps | I27: eps | J27: eps | N27: ateal | O27: 0 | P27: eps | Q27: eps | R27: eps | X27: trn | Y27: rem
A28: ctoba | B28: eps | C28: eps | D28: eps | E28: eps | F28: eps | G28: eps | H28: eps | I28: eps | J28: eps | N28: atoba | O28: 0 | P28: eps | Q28: eps | R28: eps | V28: Farm | W28: hhd-r1 | X28: eps | Y28: eps
A29: csugr | B29: eps | C29: eps | D29: eps | E29: eps | F29: eps | G29: eps | H29: eps | I29: eps | J29: eps | N29: asugr | O29: 0 | P29: eps | Q29: eps | R29: eps | W29: hhd-r2 | X29: eps | Y29: eps
A30: cpyre | B30: eps | C30: eps | D30: eps | E30: eps | F30: eps | G30: eps | H30: eps | I30: eps | J30: eps | N30: apyre | O30: 0 | P30: eps | Q30: eps | R30: eps | W30: hhd-r3 | X30: eps | Y30: eps
A31: cocrp | B31: eps | C31: eps | D31: eps | E31: eps | F31: eps | G31: eps | H31: eps | I31: eps | J31: eps | N31: aocrp | O31: 0 | P31: eps | Q31: eps | R31: eps | W31: hhd-r4 | X31: eps | Y31: eps
A32: ccatt | B32: eps | C32: eps | D32: eps | E32: eps | F32: eps | G32: eps | H32: eps | I32: eps | J32: eps | N32: acatt | O32: 0 | P32: eps | Q32: eps | R32: eps | W32: hhd-r5 | X32: eps | Y32: eps
A33: csmlr | B33: eps | C33: eps | D33: eps | E33: eps | F33: eps | G33: eps | H33: eps | I33: eps | J33: eps | N33: asmlr | O33: 0 | P33: eps | Q33: eps | R33: eps | V33: Nonfarm | W33: hhd-u1 | X33: eps | Y33: eps
A34: cpoul | B34: eps | C34: eps | D34: eps | E34: eps | F34: eps | G34: eps | H34: eps | I34: eps | J34: eps | N34: apoul | O34: 0 | P34: eps | Q34: eps | R34: eps | W34: hhd-u2 | X34: eps | Y34: eps
A35: coliv | B35: eps | C35: eps | D35: eps | E35: eps | F35: eps | G35: eps | H35: eps | I35: eps | J35: eps | N35: aoliv | O35: 0 | P35: eps | Q35: eps | R35: eps | W35: hhd-u3 | X35: eps | Y35: eps
A36: cmilk | B36: eps | C36: eps | D36: eps | E36: eps | F36: eps | G36: eps | H36: eps | I36: eps | J36: eps | N36: amilk | O36: 0 | P36: eps | Q36: eps | R36: eps | W36: hhd-u4 | X36: eps | Y36: eps
A37: ceggs | B37: eps | C37: eps | D37: eps | E37: eps | F37: eps | G37: eps | H37: eps | I37: eps | J37: eps | N37: aeggs | O37: 0 | P37: eps | Q37: eps | R37: eps | W37: hhd-u5 | X37: eps | Y37: eps
A38: chony | B38: eps | C38: eps | D38: eps | E38: eps | F38: eps | G38: eps | H38: eps | I38: eps | J38: eps | N38: ahony | O38: 0 | P38: eps | Q38: eps | R38: eps | V38: Urban | W38: hhd-k1 | X38: eps | Y38: eps
A39: chunt | B39: eps | C39: eps | D39: eps | E39: eps | F39: eps | G39: eps | H39: eps | I39: eps | J39: eps | N39: ahunt | O39: 0 | P39: eps | Q39: eps | R39: eps | W39: hhd-k2 | X39: eps | Y39: eps
A40: cfuel | B40: eps | C40: eps | D40: eps | E40: eps | F40: eps | G40: eps | H40: eps | I40: eps | J40: eps | N40: afuel | O40: 0 | P40: eps | Q40: eps | R40: eps | W40: hhd-k3 | X40: eps | Y40: eps
A41: cchar | B41: eps | C41: eps | D41: eps | E41: eps | F41: eps | G41: eps | H41: eps | I41: eps | J41: eps | N41: achar | O41: 0 | P41: eps | Q41: eps | R41: eps | W41: hhd-k4 | X41: eps | Y41: eps
A42: cfore | B42: eps | C42: eps | D42: eps | E42: eps | F42: eps | G42: eps | H42: eps | I42: eps | J42: eps | N42: afore | O42: 0 | P42: eps | Q42: eps | R42: eps | W42: hhd-k5 | X42: eps | Y42: eps
A43: cfish | B43: eps | C43: eps | D43: eps | E43: eps | F43: eps | G43: eps | H43: eps | I43: eps | J43: eps | N43: afish | O43: 0 | P43: eps | Q43: eps | R43: eps
A44: cngas | B44: eps | C44: eps | D44: eps | E44: eps | F44: eps | G44: eps | H44: eps | I44: eps | J44: eps | N44: angas | O44: 0 | P44: eps | Q44: eps | R44: eps | V44: Scalar shocks
A45: cmore | B45: eps | C45: eps | D45: eps | E45: eps | F45: eps | G45: eps | H45: eps | I45: eps | J45: eps | N45: amore | O45: 0 | P45: eps | Q45: eps | R45: eps
A46: comin | B46: eps | C46: eps | D46: eps | E46: eps | F46: eps | G46: eps | H46: eps | I46: eps | J46: eps | N46: aomin | O46: 0 | P46: eps | Q46: eps | R46: eps | V46: Exchange rate | X46: exr | Y46: eps
A47: cmeat | B47: eps | C47: eps | D47: eps | E47: eps | F47: eps | G47: eps | H47: eps | I47: eps | J47: eps | N47: ameat | O47: 0 | P47: eps | Q47: eps | R47: eps | V47: Investment | X47: iadj | Y47: eps
A48: cfsea | B48: eps | C48: eps | D48: eps | E48: eps | F48: eps | G48: eps | H48: eps | I48: eps | J48: eps | N48: afsea | O48: 0 | P48: eps | Q48: eps | R48: eps | V48: Foreign savings | X48: fsav | Y48: eps
A49: cfveg | B49: eps | C49: eps | D49: eps | E49: eps | F49: eps | G49: eps | H49: eps | I49: eps | J49: eps | N49: afveg | O49: 0 | P49: eps | Q49: eps | R49: eps | V49: Gov. savings | X49: gsav | Y49: eps
A50: cfoil | B50: eps | C50: eps | D50: eps | E50: eps | F50: eps | G50: eps | H50: eps | I50: eps | J50: eps | N50: afoil | O50: 0 | P50: eps | Q50: eps | R50: eps | V50: Gov. spending | X50: gadj | Y50: eps
A51: cdair | B51: eps | C51: eps | D51: eps | E51: eps | F51: eps | G51: eps | H51: eps | I51: eps | J51: eps | N51: adair | O51: 0 | P51: eps | Q51: eps | R51: eps | V51: Savings rates | X51: mpsadj | Y51: eps
A52: cgmll | B52: eps | C52: eps | D52: eps | E52: eps | F52: eps | G52: eps | H52: eps | I52: eps | J52: eps | N52: agmll | O52: 0 | P52: eps | Q52: eps | R52: eps | X52: dmps | Y52: eps
A53: cbake | B53: eps | C53: eps | D53: eps | E53: eps | F53: eps | G53: eps | H53: eps | I53: eps | J53: eps | N53: abake | O53: 0 | P53: eps | Q53: eps | R53: eps | V53: Direct tax rates | X53: tinsadj | Y53: eps
A54: cfeed | B54: eps | C54: eps | D54: eps | E54: eps | F54: eps | G54: eps | H54: eps | I54: eps | J54: eps | N54: afeed | O54: 0 | P54: eps | Q54: eps | R54: eps | X54: dtins | Y54: eps
A55: cfood | B55: eps | C55: eps | D55: eps | E55: eps | F55: eps | G55: eps | H55: eps | I55: eps | J55: eps | N55: afood | O55: 0 | P55: eps | Q55: eps | R55: eps
A56: calco | B56: eps | C56: eps | D56: eps | E56: eps | F56: eps | G56: eps | H56: eps | I56: eps | J56: eps | N56: aalco | O56: 0 | P56: eps | Q56: eps | R56: eps | V56: Institutional closures
A57: cbeve | B57: eps | C57: eps | D57: eps | E57: eps | F57: eps | G57: eps | H57: eps | I57: eps | J57: eps | N57: abeve | O57: 0 | P57: eps | Q57: eps | R57: eps | X57: Savings | Y57: Taxes
A58: cptob | B58: eps | C58: eps | D58: eps | E58: eps | F58: eps | G58: eps | H58: eps | I58: eps | J58: eps | N58: aptob | O58: 0 | P58: eps | Q58: eps | R58: eps | X58: mps | Y58: tins
A59: ctext | B59: eps | C59: eps | D59: eps | E59: eps | F59: eps | G59: eps | H59: eps | I59: eps | J59: eps | N59: atext | O59: 0 | P59: eps | Q59: eps | R59: eps | V59: Enter. | W59: ent | X59: 1 | Y59: 1
A60: cwood | B60: eps | C60: eps | D60: eps | E60: eps | F60: eps | G60: eps | H60: eps | I60: eps | J60: eps | N60: awood | O60: 0 | P60: eps | Q60: eps | R60: eps | V60: House. | W60: hhd-r1 | X60: 1 | Y60: 1
A61: cprnt | B61: eps | C61: eps | D61: eps | E61: eps | F61: eps | G61: eps | H61: eps | I61: eps | J61: eps | N61: aprnt | O61: 0 | P61: eps | Q61: eps | R61: eps | W61: hhd-r2 | X61: 1 | Y61: 1
A62: cpetr | B62: eps | C62: eps | D62: eps | E62: eps | F62: eps | G62: eps | H62: eps | I62: eps | J62: eps | N62: apetr | O62: 0 | P62: eps | Q62: eps | R62: eps | W62: hhd-r3 | X62: 1 | Y62: 1
A63: cchem | B63: eps | C63: eps | D63: eps | E63: eps | F63: eps | G63: eps | H63: eps | I63: eps | J63: eps | N63: achem | O63: 0 | P63: eps | Q63: eps | R63: eps | W63: hhd-r4 | X63: 1 | Y63: 1
A64: cphar | B64: eps | C64: eps | D64: eps | E64: eps | F64: eps | G64: eps | H64: eps | I64: eps | J64: eps | N64: aphar | O64: 0 | P64: eps | Q64: eps | R64: eps | W64: hhd-r5 | X64: 1 | Y64: 1
A65: cprub | B65: eps | C65: eps | D65: eps | E65: eps | F65: eps | G65: eps | H65: eps | I65: eps | J65: eps | N65: aprub | O65: 0 | P65: eps | Q65: eps | R65: eps | W65: hhd-u1 | X65: 1 | Y65: 1
A66: cnmet | B66: eps | C66: eps | D66: eps | E66: eps | F66: eps | G66: eps | H66: eps | I66: eps | J66: eps | N66: anmet | O66: 0 | P66: eps | Q66: eps | R66: eps | W66: hhd-u2 | X66: 1 | Y66: 1
A67: cceme | B67: eps | C67: eps | D67: eps | E67: eps | F67: eps | G67: eps | H67: eps | I67: eps | J67: eps | N67: aceme | O67: 0 | P67: eps | Q67: eps | R67: eps | W67: hhd-u3 | X67: 1 | Y67: 1
A68: cclay | B68: eps | C68: eps | D68: eps | E68: eps | F68: eps | G68: eps | H68: eps | I68: eps | J68: eps | N68: aclay | O68: 0 | P68: eps | Q68: eps | R68: eps | W68: hhd-u4 | X68: 1 | Y68: 1
A69: cmetl | B69: eps | C69: eps | D69: eps | E69: eps | F69: eps | G69: eps | H69: eps | I69: eps | J69: eps | N69: ametl | O69: 0 | P69: eps | Q69: eps | R69: eps | W69: hhd-u5 | X69: 1 | Y69: 1
A70: cmach | B70: eps | C70: eps | D70: eps | E70: eps | F70: eps | G70: eps | H70: eps | I70: eps | J70: eps | N70: amach | O70: 0 | P70: eps | Q70: eps | R70: eps | W70: hhd-k1 | X70: 1 | Y70: 1
A71: cvehi | B71: eps | C71: eps | D71: eps | E71: eps | F71: eps | G71: eps | H71: eps | I71: eps | J71: eps | N71: avehi | O71: 0 | P71: eps | Q71: eps | R71: eps | W71: hhd-k2 | X71: 1 | Y71: 1
A72: cfurn | B72: eps | C72: eps | D72: eps | E72: eps | F72: eps | G72: eps | H72: eps | I72: eps | J72: eps | N72: afurn | O72: 0 | P72: eps | Q72: eps | R72: eps | W72: hhd-k3 | X72: 1 | Y72: 1
... A74: crepr | B74: eps | C74: eps | D74: eps | E74: eps | F74: eps | G74: eps | H74: eps | I74: eps | J74: eps | N74: arepr | O74: 0 | P74: eps | Q74: eps | R74: eps | W74: hhd-k5 | X74: 1 | Y74: 1
A75: celec | B75: eps | C75: eps | D75: eps | E75: eps | F75: eps | G75: eps | H75: eps | I75: eps | J75: eps | N75: aelec | O75: 0 | P75: eps | Q75: eps | R75: eps
A76: cwatr | B76: eps | C76: eps | D76: eps | E76: eps | F76: eps | G76: eps | H76: eps | I76: eps | J76: eps | N76: awatr | O76: 0 | P76: eps | Q76: eps | R76: eps | V76: Macroeconomic closures
A77: cwast | B77: eps | C77: eps | D77: eps | E77: eps | F77: eps | G77: eps | H77: eps | I77: eps | J77: eps | N77: awast | O77: 0 | P77: eps | Q77: eps | R77: eps | V77: Num. | W77: dum | X77: =SUMIF(Main!G4:O4,Y1,Main!G5:O5) -> 2
A78: ccons | B78: eps | C78: eps | D78: eps | E78: eps | F78: eps | G78: eps | H78: eps | I78: eps | J78: eps | N78: acons | O78: 0 | P78: eps | Q78: eps | R78: eps | V78: Sav-Inv. | W78: s-i | X78: =SUMIF(Main!G4:O4,Y1,Main!G6:O6) -> 3
A79: ccont | B79: eps | C79: eps | D79: eps | E79: eps | F79: eps | G79: eps | H79: eps | I79: eps | J79: eps | N79: acont | O79: 0 | P79: eps | Q79: eps | R79: eps | V79: Gov. | W79: gov | X79: =SUMIF(Main!G4:O4,Y1,Main!G7:O7) -> 1
A80: cvehr | B80: eps | C80: eps | D80: eps | E80: eps | F80: eps | G80: eps | H80: eps | I80: eps | J80: eps | N80: avehr | O80: 0 | P80: eps | Q80: eps | R80: eps | V80: Cur. a/c | W80: row | X80: =SUMIF(Main!G4:O4,Y1,Main!G8:O8) -> 1
A81: cveht | B81: eps | C81: eps | D81: eps | E81: eps | F81: eps | G81: eps | H81: eps | I81: eps | J81: eps | N81: aveht | O81: 0 | P81: eps | Q81: eps | R81: eps
A82: ctrdw | B82: eps | C82: eps | D82: eps | E82: eps | F82: eps | G82: eps | H82: eps | I82: eps | J82: eps | N82: atrdw | O82: 0 | P82: eps | Q82: eps | R82: eps | V82: Factor market closures
A83: ctrdr | B83: eps | C83: eps | D83: eps | E83: eps | F83: eps | G83: eps | H83: eps | I83: eps | J83: eps | N83: atrdr | O83: 0 | P83: eps | Q83: eps | R83: eps | V83: Labor | W83: flab-rn | X83: =SUMIF(Main!G11:O11,'S9'!Y1,Main!G12:O12) -> 1
A84: ctrnl | B84: eps | C84: eps | D84: eps | E84: eps | F84: eps | G84: eps | H84: eps | I84: eps | J84: eps | N84: atrnl | O84: 0 | P84: eps | Q84: eps | R84: eps | W84: flab-rp | X84: =SUMIF(Main!G11:O11,'S9'!Y1,Main!G13:O13) -> 1
A85: ctrna | B85: eps | C85: eps | D85: eps | E85: eps | F85: eps | G85: eps | H85: eps | I85: eps | J85: eps | N85: atrna | O85: 0 | P85: eps | Q85: eps | R85: eps | W85: flab-rs | X85: =SUMIF(Main!G11:O11,'S9'!Y1,Main!G14:O14) -> 1
A86: ctrns | B86: eps | C86: eps | D86: eps | E86: eps | F86: eps | G86: eps | H86: eps | I86: eps | J86: eps | N86: atrns | O86: 0 | P86: eps | Q86: eps | R86: eps | W86: flab-rt | X86: =SUMIF(Main!G11:O11,'S9'!Y1,Main!G15:O15) -> 1
A87: cpost | B87: eps | C87: eps | D87: eps | E87: eps | F87: eps | G87: eps | H87: eps | I87: eps | J87: eps | N87: apost | O87: 0 | P87: eps | Q87: eps | R87: eps | W87: flab-un | X87: =SUMIF(Main!G11:O11,'S9'!Y1,Main!G16:O16) -> 1
A88: chotl | B88: eps | C88: eps | D88: eps | E88: eps | F88: eps | G88: eps | H88: eps | I88: eps | J88: eps | N88: ahotl | O88: 0 | P88: eps | Q88: eps | R88: eps | W88: flab-up | X88: =SUMIF(Main!G11:O11,'S9'!Y1,Main!G17:O17) -> 1
A89: cpubl | B89: eps | C89: eps | D89: eps | E89: eps | F89: eps | G89: eps | H89: eps | I89: eps | J89: eps | N89: apubl | O89: 0 | P89: eps | Q89: eps | R89: eps | W89: flab-us | X89: =SUMIF(Main!G11:O11,'S9'!Y1,Main!G18:O18) -> 1
A90: ccomm | B90: eps | C90: eps | D90: eps | E90: eps | F90: eps | G90: eps | H90: eps | I90: eps | J90: eps | N90: acomm | O90: 0 | P90: eps | Q90: eps | R90: eps | W90: flab-ut | X90: =SUMIF(Main!G11:O11,'S9'!Y1,Main!G19:O19) -> 1
A91: cinfo | B91: eps | C91: eps | D91: eps | E91: eps | F91: eps | G91: eps | H91: eps | I91: eps | J91: eps | N91: ainfo | O91: 0 | P91: eps | Q91: eps | R91: eps | W91: flab-kn | X91: =SUMIF(Main!G11:O11,'S9'!Y1,Main!G20:O20) -> 1
A92: cbank | B92: eps | C92: eps | D92: eps | E92: eps | F92: eps | G92: eps | H92: eps | I92: eps | J92: eps | N92: abank | O92: 0 | P92: eps | Q92: eps | R92: eps | W92: flab-kp | X92: =SUMIF(Main!G11:O11,'S9'!Y1,Main!G21:O21) -> 1
A93: cinsu | B93: eps | C93: eps | D93: eps | E93: eps | F93: eps | G93: eps | H93: eps | I93: eps | J93: eps | N93: ainsu | O93: 0 | P93: eps | Q93: eps | R93: eps | W93: flab-ks | X93: =SUMIF(Main!G11:O11,'S9'!Y1,Main!G22:O22) -> 1
A94: cofsv | B94: eps | C94: eps | D94: eps | E94: eps | F94: eps | G94: eps | H94: eps | I94: eps | J94: eps | N94: aofsv | O94: 0 | P94: eps | Q94: eps | R94: eps | W94: flab-kt | X94: =SUMIF(Main!G11:O11,'S9'!Y1,Main!G23:O23) -> 1
A95: crent | B95: eps | C95: eps | D95: eps | E95: eps | F95: eps | G95: eps | H95: eps | I95: eps | J95: eps | N95: arent | O95: 0 | P95: eps | Q95: eps | R95: eps | V95: Land | W95: flnd | X95: =SUMIF(Main!G11:O11,'S9'!Y1,Main!G24:O24) -> 1
A96: creal | B96: eps | C96: eps | D96: eps | E96: eps | F96: eps | G96: eps | H96: eps | I96: eps | J96: eps | N96: areal | O96: 0 | P96: eps | Q96: eps | R96: eps | V96: Capital | W96: fcap-c | X96: =SUMIF(Main!G11:O11,'S9'!Y1,Main!G25:O25) -> 2
A97: clegl | B97: eps | C97: eps | D97: eps | E97: eps | F97: eps | G97: eps | H97: eps | I97: eps | J97: eps | N97: alegl | O97: 0 | P97: eps | Q97: eps | R97: eps | W97: fcap-l | X97: =SUMIF(Main!G11:O11,'S9'!Y1,Main!G26:O26) -> 2
A98: cenga | B98: eps | C98: eps | D98: eps | E98: eps | F98: eps | G98: eps | H98: eps | I98: eps | J98: eps | N98: aenga | O98: 0 | P98: eps | Q98: eps | R98: eps | W98: fcap-m | X98: =SUMIF(Main!G11:O11,'S9'!Y1,Main!G27:O27) -> 2
A99: cprod | B99: eps | C99: eps | D99: eps | E99: eps | F99: eps | G99: eps | H99: eps | I99: eps | J99: eps | N99: aprod | O99: 0 | P99: eps | Q99: eps | R99: eps | W99: fcap-n | X99: =SUMIF(Main!G11:O11,'S9'!Y1,Main!G28:O28) -> 2
A100: ctrvl | B100: eps | C100: eps | D100: eps | E100: eps | F100: eps | G100: eps | H100: eps | I100: eps | J100: eps | N100: atrvl | O100: 0 | P100: eps | Q100: eps | R100: eps
A101: cobsv | B101: eps | C101: eps | D101: eps | E101: eps | F101: eps | G101: eps | H101: eps | I101: eps | J101: eps | N101: aobsv | O101: 0 | P101: eps | Q101: eps | R101: eps
A102: cpadm | B102: eps | C102: eps | D102: eps | E102: eps | F102: eps | G102: eps | H102: eps | I102: eps | J102: eps | N102: apadm | O102: 0 | P102: eps | Q102: eps | R102: eps
A103: ceduc | B103: eps | C103: eps | D103: eps | E103: eps | F103: eps | G103: eps | H103: eps | I103: eps | J103: eps | N103: aeduc | O103: 0 | P103: eps | Q103: eps | R103: eps
A104: cheal | B104: eps | C104: eps | D104: eps | E104: eps | F104: eps | G104: eps | H104: eps | I104: eps | J104: eps | N104: aheal | O104: 0 | P104: eps | Q104: eps | R104: eps
A105: csocw | B105: eps | C105: eps | D105: eps | E105: eps | F105: eps | G105: eps | H105: eps | I105: eps | J105: eps | N105: asocw | O105: 0 | P105: eps | Q105: eps | R105: eps
A106: ccult | B106: eps | C106: eps | D106: eps | E106: eps | F106: eps | G106: eps | H106: eps | I106: eps | J106: eps | N106: acult | O106: 0 | P106: eps | Q106: eps | R106: eps
...

Sheet Index
A1: GDX index
H6: rdim | I6: cdim
E7: dset | F7: sim | G7: main!a5 | H7: 1
E8: par | F8: active | G8: main!a5 | H8: 1
A9: sim1 | B9: c | C9: a | D9: 6 | E9: par | F9: =A9&B9 -> sim1c | G9: ="s"&MID(A9,4,2)&"!"&C9&D9 -> s1!a6 | H9: 1 | I9: 1
A10: =A9 -> sim1 | B10: a | C10: n | D10: 6 | E10: par | F10: =A10&B10 -> sim1a | G10: ="s"&MID(A10,4,2)&"!"&C10&D10 -> s1!n6 | H10: 1 | I10: 1
A11: =A10 -> sim1 | B11: f | C11: v | D11: 6 | E11: par | F11: =A11&B11 -> sim1f | G11: ="s"&MID(A11,4,2)&"!"&C11&D11 -> s1!v6 | H11: 1 | I11: 1
A12: =A11 -> sim1 | B12: s | C12: x | D12: 46 | E12: par | F12: =A12&B12 -> sim1s | G12: ="s"&MID(A12,4,2)&"!"&C12&D12 -> s1!x46 | H12: 1
A13: =A12 -> sim1 | B13: h | C13: w | D13: 27 | E13: par | F13: =A13&B13 -> sim1h | G13: ="s"&MID(A13,4,2)&"!"&C13&D13 -> s1!w27 | H13: 1 | I13: 1
A14: =A12 -> sim1 | B14: mc | C14: w | D14: 77 | E14: par | F14: =A14&B14 -> sim1mc | G14: ="s"&MID(A14,4,2)&"!"&C14&D14 -> s1!w77 | H14: 1
A15: =A14 -> sim1 | B15: fc | C15: w | D15: 83 | E15: par | F15: =A15&B15 -> sim1fc | G15: ="s"&MID(A15,4,2)&"!"&C15&D15 -> s1!w83 | H15: 1
A16: =A15 -> sim1 | B16: hc | C16: w | D16: 58 | E16: par | F16: =A16&B16 -> sim1hc | G16: ="s"&MID(A16,4,2)&"!"&C16&D16 -> s1!w58 | H16: 1 | I16: 1
A17: ="sim"&RIGHT(A9,1)+1 -> sim2 | B17: =B9 -> c | C17: =C9 -> a | D17: =D9 -> 6 | E17: par | F17: =A17&B17 -> sim2c | G17: ="s"&MID(A17,4,2)&"!"&C17&D17 -> s2!a6 | H17: 1 | I17: 1
A18: =A17 -> sim2 | B18: =B10 -> a | C18: =C10 -> n | D18: =D10 -> 6 | E18: par | F18: =A18&B18 -> sim2a | G18: ="s"&MID(A18,4,2)&"!"&C18&D18 -> s2!n6 | H18: 1 | I18: 1
A19: =A18 -> sim2 | B19: =B11 -> f | C19: =C11 -> v | D19: =D11 -> 6 | E19: par | F19: =A19&B19 -> sim2f | G19: ="s"&MID(A19,4,2)&"!"&C19&D19 -> s2!v6 | H19: 1 | I19: 1
A20: =A19 -> sim2 | B20: =B12 -> s | C20: =C12 -> x | D20: =D12 -> 46 | E20: par | F20: =A20&B20 -> sim2s | G20: ="s"&MID(A20,4,2)&"!"&C20&D20 -> s2!x46 | H20: 1
A21: =A20 -> sim2 | B21: =B13 -> h | C21: =C13 -> w | D21: =D13 -> 27 | E21: par | F21: =A21&B21 -> sim2h | G21: ="s"&MID(A21,4,2)&"!"&C21&D21 -> s2!w27 | H21: 1 | I21: 1
A22: =A20 -> sim2 | B22: =B14 -> mc | C22: =C14 -> w | D22: =D14 -> 77 | E22: par | F22: =A22&B22 -> sim2mc | G22: ="s"&MID(A22,4,2)&"!"&C22&D22 -> s2!w77 | H22: 1
A23: =A22 -> sim2 | B23: =B15 -> fc | C23: =C15 -> w | D23: =D15 -> 83 | E23: par | F23: =A23&B23 -> sim2fc | G23: ="s"&MID(A23,4,2)&"!"&C23&D23 -> s2!w83 | H23: 1
A24: =A23 -> sim2 | B24: =B16 -> hc | C24: =C16 -> w | D24: =D16 -> 58 | E24: par | F24: =A24&B24 -> sim2hc | G24: ="s"&MID(A24,4,2)&"!"&C24&D24 -> s2!w58 | H24: 1 | I24: 1
A25: ="sim"&RIGHT(A17,1)+1 -> sim3 | B25: =B17 -> c | C25: =C17 -> a | D25: =D17 -> 6 | E25: par | F25: =A25&B25 -> sim3c | G25: ="s"&MID(A25,4,2)&"!"&C25&D25 -> s3!a6 | H25: 1 | I25: 1
A26: =A25 -> sim3 | B26: =B18 -> a | C26: =C18 -> n | D26: =D18 -> 6 | E26: par | F26: =A26&B26 -> sim3a | G26: ="s"&MID(A26,4,2)&"!"&C26&D26 -> s3!n6 | H26: 1 | I26: 1
A27: =A26 -> sim3 | B27: =B19 -> f | C27: =C19 -> v | D27: =D19 -> 6 | E27: par | F27: =A27&B27 -> sim3f | G27: ="s"&MID(A27,4,2)&"!"&C27&D27 -> s3!v6 | H27: 1 | I27: 1
A28: =A27 -> sim3 | B28: =B20 -> s | C28: =C20 -> x | D28: =D20 -> 46 | E28: par | F28: =A28&B28 -> sim3s | G28: ="s"&MID(A28,4,2)&"!"&C28&D28 -> s3!x46 | H28: 1
A29: =A28 -> sim3 | B29: =B21 -> h | C29: =C21 -> w | D29: =D21 -> 27 | E29: par | F29: =A29&B29 -> sim3h | G29: ="s"&MID(A29,4,2)&"!"&C29&D29 -> s3!w27 | H29: 1 | I29: 1
A30: =A28 -> sim3 | B30: =B22 -> mc | C30: =C22 -> w | D30: =D22 -> 77 | E30: par | F30: =A30&B30 -> sim3mc | G30: ="s"&MID(A30,4,2)&"!"&C30&D30 -> s3!w77 | H30: 1
A31: =A30 -> sim3 | B31: =B23 -> fc | C31: =C23 -> w | D31: =D23 -> 83 | E31: par | F31: =A31&B31 -> sim3fc | G31: ="s"&MID(A31,4,2)&"!"&C31&D31 -> s3!w83 | H31: 1
A32: =A31 -> sim3 | B32: =B24 -> hc | C32: =C24 -> w | D32: =D24 -> 58 | E32: par | F32: =A32&B32 -> sim3hc | G32: ="s"&MID(A32,4,2)&"!"&C32&D32 -> s3!w58 | H32: 1 | I32: 1
A33: ="sim"&RIGHT(A25,1)+1 -> sim4 | B33: =B25 -> c | C33: =C25 -> a | D33: =D25 -> 6 | E33: par | F33: =A33&B33 -> sim4c | G33: ="s"&MID(A33,4,2)&"!"&C33&D33 -> s4!a6 | H33: 1 | I33: 1
A34: =A33 -> sim4 | B34: =B26 -> a | C34: =C26 -> n | D34: =D26 -> 6 | E34: par | F34: =A34&B34 -> sim4a | G34: ="s"&MID(A34,4,2)&"!"&C34&D34 -> s4!n6 | H34: 1 | I34: 1
A35: =A34 -> sim4 | B35: =B27 -> f | C35: =C27 -> v | D35: =D27 -> 6 | E35: par | F35: =A35&B35 -> sim4f | G35: ="s"&MID(A35,4,2)&"!"&C35&D35 -> s4!v6 | H35: 1 | I35: 1
A36: =A35 -> sim4 | B36: =B28 -> s | C36: =C28 -> x | D36: =D28 -> 46 | E36: par | F36: =A36&B36 -> sim4s | G36: ="s"&MID(A36,4,2)&"!"&C36&D36 -> s4!x46 | H36: 1
A37: =A36 -> sim4 | B37: =B29 -> h | C37: =C29 -> w | D37: =D29 -> 27 | E37: par | F37: =A37&B37 -> sim4h | G37: ="s"&MID(A37,4,2)&"!"&C37&D37 -> s4!w27 | H37: 1 | I37: 1
A38: =A36 -> sim4 | B38: =B30 -> mc | C38: =C30 -> w | D38: =D30 -> 77 | E38: par | F38: =A38&B38 -> sim4mc | G38: ="s"&MID(A38,4,2)&"!"&C38&D38 -> s4!w77 | H38: 1
A39: =A38 -> sim4 | B39: =B31 -> fc | C39: =C31 -> w | D39: =D31 -> 83 | E39: par | F39: =A39&B39 -> sim4fc | G39: ="s"&MID(A39,4,2)&"!"&C39&D39 -> s4!w83 | H39: 1
A40: =A39 -> sim4 | B40: =B32 -> hc | C40: =C32 -> w | D40: =D32 -> 58 | E40: par | F40: =A40&B40 -> sim4hc | G40: ="s"&MID(A40,4,2)&"!"&C40&D40 -> s4!w58 | H40: 1 | I40: 1
A41: ="sim"&RIGHT(A33,1)+1 -> sim5 | B41: =B33 -> c | C41: =C33 -> a | D41: =D33 -> 6 | E41: par | F41: =A41&B41 -> sim5c | G41: ="s"&MID(A41,4,2)&"!"&C41&D41 -> s5!a6 | H41: 1 | I41: 1
A42: =A41 -> sim5 | B42: =B34 -> a | C42: =C34 -> n | D42: =D34 -> 6 | E42: par | F42: =A42&B42 -> sim5a | G42: ="s"&MID(A42,4,2)&"!"&C42&D42 -> s5!n6 | H42: 1 | I42: 1
A43: =A42 -> sim5 | B43: =B35 -> f | C43: =C35 -> v | D43: =D35 -> 6 | E43: par | F43: =A43&B43 -> sim5f | G43: ="s"&MID(A43,4,2)&"!"&C43&D43 -> s5!v6 | H43: 1 | I43: 1
A44: =A43 -> sim5 | B44: =B36 -> s | C44: =C36 -> x | D44: =D36 -> 46 | E44: par | F44: =A44&B44 -> sim5s | G44: ="s"&MID(A44,4,2)&"!"&C44&D44 -> s5!x46 | H44: 1
A45: =A44 -> sim5 | B45: =B37 -> h | C45: =C37 -> w | D45: =D37 -> 27 | E45: par | F45: =A45&B45 -> sim5h | G45: ="s"&MID(A45,4,2)&"!"&C45&D45 -> s5!w27 | H45: 1 | I45: 1
A46: =A44 -> sim5 | B46: =B38 -> mc | C46: =C38 -> w | D46: =D38 -> 77 | E46: par | F46: =A46&B46 -> sim5mc | G46: ="s"&MID(A46,4,2)&"!"&C46&D46 -> s5!w77 | H46: 1
A47: =A46 -> sim5 | B47: =B39 -> fc | C47: =C39 -> w | D47: =D39 -> 83 | E47: par | F47: =A47&B47 -> sim5fc | G47: ="s"&MID(A47,4,2)&"!"&C47&D47 -> s5!w83 | H47: 1
A48: =A47 -> sim5 | B48: =B40 -> hc | C48: =C40 -> w | D48: =D40 -> 58 | E48: par | F48: =A48&B48 -> sim5hc | G48: ="s"&MID(A48,4,2)&"!"&C48&D48 -> s5!w58 | H48: 1 | I48: 1
A49: ="sim"&RIGHT(A41,1)+1 -> sim6 | B49: =B41 -> c | C49: =C41 -> a | D49: =D41 -> 6 | E49: par | F49: =A49&B49 -> sim6c | G49: ="s"&MID(A49,4,2)&"!"&C49&D49 -> s6!a6 | H49: 1 | I49: 1
A50: =A49 -> sim6 | B50: =B42 -> a | C50: =C42 -> n | D50: =D42 -> 6 | E50: par | F50: =A50&B50 -> sim6a | G50: ="s"&MID(A50,4,2)&"!"&C50&D50 -> s6!n6 | H50: 1 | I50: 1
A51: =A50 -> sim6 | B51: =B43 -> f | C51: =C43 -> v | D51: =D43 -> 6 | E51: par | F51: =A51&B51 -> sim6f | G51: ="s"&MID(A51,4,2)&"!"&C51&D51 -> s6!v6 | H51: 1 | I51: 1
A52: =A51 -> sim6 | B52: =B44 -> s | C52: =C44 -> x | D52: =D44 -> 46 | E52: par | F52: =A52&B52 -> sim6s | G52: ="s"&MID(A52,4,2)&"!"&C52&D52 -> s6!x46 | H52: 1
A53: =A52 -> sim6 | B53: =B45 -> h | C53: =C45 -> w | D53: =D45 -> 27 | E53: par | F53: =A53&B53 -> sim6h | G53: ="s"&MID(A53,4,2)&"!"&C53&D53 -> s6!w27 | H53: 1 | I53: 1
A54: =A52 -> sim6 | B54: =B46 -> mc | C54: =C46 -> w | D54: =D46 -> 77 | E54: par | F54: =A54&B54 -> sim6mc | G54: ="s"&MID(A54,4,2)&"!"&C54&D54 -> s6!w77 | H54: 1
A55: =A54 -> sim6 | B55: =B47 -> fc | C55: =C47 -> w | D55: =D47 -> 83 | E55: par | F55: =A55&B55 -> sim6fc | G55: ="s"&MID(A55,4,2)&"!"&C55&D55 -> s6!w83 | H55: 1
A56: =A55 -> sim6 | B56: =B48 -> hc | C56: =C48 -> w | D56: =D48 -> 58 | E56: par | F56: =A56&B56 -> sim6hc | G56: ="s"&MID(A56,4,2)&"!"&C56&D56 -> s6!w58 | H56: 1 | I56: 1
A57: ="sim"&RIGHT(A49,1)+1 -> sim7 | B57: =B49 -> c | C57: =C49 -> a | D57: =D49 -> 6 | E57: par | F57: =A57&B57 -> sim7c | G57: ="s"&MID(A57,4,2)&"!"&C57&D57 -> s7!a6 | H57: 1 | I57: 1
A58: =A57 -> sim7 | B58: =B50 -> a | C58: =C50 -> n | D58: =D50 -> 6 | E58: par | F58: =A58&B58 -> sim7a | G58: ="s"&MID(A58,4,2)&"!"&C58&D58 -> s7!n6 | H58: 1 | I58: 1
A59: =A58 -> sim7 | B59: =B51 -> f | C59: =C51 -> v | D59: =D51 -> 6 | E59: par | F59: =A59&B59 -> sim7f | G59: ="s"&MID(A59,4,2)&"!"&C59&D59 -> s7!v6 | H59: 1 | I59: 1
A60: =A59 -> sim7 | B60: =B52 -> s | C60: =C52 -> x | D60: =D52 -> 46 | E60: par | F60: =A60&B60 -> sim7s | G60: ="s"&MID(A60,4,2)&"!"&C60&D60 -> s7!x46 | H60: 1
A61: =A60 -> sim7 | B61: =B53 -> h | C61: =C53 -> w | D61: =D53 -> 27 | E61: par | F61: =A61&B61 -> sim7h | G61: ="s"&MID(A61,4,2)&"!"&C61&D61 -> s7!w27 | H61: 1 | I61: 1
A62: =A60 -> sim7 | B62: =B54 -> mc | C62: =C54 -> w | D62: =D54 -> 77 | E62: par | F62: =A62&B62 -> sim7mc | G62: ="s"&MID(A62,4,2)&"!"&C62&D62 -> s7!w77 | H62: 1
A63: =A62 -> sim7 | B63: =B55 -> fc | C63: =C55 -> w | D63: =D55 -> 83 | E63: par | F63: =A63&B63 -> sim7fc | G63: ="s"&MID(A63,4,2)&"!"&C63&D63 -> s7!w83 | H63: 1
A64: =A63 -> sim7 | B64: =B56 -> hc | C64: =C56 -> w | D64: =D56 -> 58 | E64: par | F64: =A64&B64 -> sim7hc | G64: ="s"&MID(A64,4,2)&"!"&C64&D64 -> s7!w58 | H64: 1 | I64: 1
